{
  "type": "Feature",
  "properties": {
    "addr:full":"25086 Rezzato Rezzato Brescia 25086",
    "addr:postcode":"25086;25086",
    "iso:country":"IT",
    "sg:address":"25086 Rezzato",
    "sg:city":"Rezzato",
    "sg:orig_category":"Servizi Ausiliari Per Il Trasporto. Servizi Vari Di Interesse Pubblico",
    "sg:phone":"+39 030 259 4462",
    "sg:postcode":"25086",
    "sg:province":"Brescia",
    "sg:website":"http://www.lacattolica.net",
    "wof:name":"Onoranze Funebri La Cattolica Srl",
    "wof:placetype":"venue"
},
  "geometry": {"coordinates":[10.304779,45.52317],"type":"Point"}
}