{
  "type": "Feature",
  "properties": {
    "addr:full":"95045 Misterbianco Misterbianco Catania 95045",
    "addr:postcode":"95045;95045",
    "iso:country":"IT",
    "sg:address":"95045 Misterbianco",
    "sg:city":"Misterbianco",
    "sg:orig_category":"Tempo Libero - Articoli E Forniture. Regalistica Aziendale",
    "sg:phone":"+39 095 303599",
    "sg:postcode":"95045",
    "sg:province":"Catania",
    "wof:name":"D'arrigo Giocattoli Sas Di D'arrigo & C.",
    "wof:placetype":"venue"
},
  "geometry": {"coordinates":[15.086667,37.525677],"type":"Point"}
}