{
  "type": "Feature",
  "properties": {
    "iso:country":"IT",
    "sg:address":"12084 Mondovi'",
    "sg:orig_category":"Autofficine E Centri Assistenza",
    "sg:phone":"+39 0174 42988",
    "sg:postcode":"12084",
    "sg:province":"Cuneo",
    "wof:name":"Baravalle M. & C. Snc",
    "wof:placetype":"venue"
},
  "geometry": {"coordinates":[7.664921,44.39539],"type":"Point"}
}