{
  "type": "Feature",
  "properties": {
    "iso:country":"IT",
    "sg:address":"50053 Empoli",
    "sg:city":"Empoli",
    "sg:orig_category":"Sport - Articoli E Forniture",
    "sg:phone":"+39 0571 73189",
    "sg:postcode":"50053",
    "sg:province":"Firenze",
    "wof:name":"Mazzino Di Gracci Carla Sas",
    "wof:placetype":"venue"
},
  "geometry": {"coordinates":[10.942518,43.718613],"type":"Point"}
}