{
  "type": "Feature",
  "properties": {
    "iso:country":"IT",
    "sg:address":"06019 Umbertide",
    "sg:city":"Umbertide",
    "sg:orig_category":"Servizi E Lavori Per Agricoltura E Zootecnia. Servizi E Lavori Per Edilizia E Lavori Pubblici",
    "sg:phone":"+39 075 941 0354",
    "sg:postcode":"06019",
    "sg:province":"Perugia",
    "sg:website":"http://www.fantaverde.com",
    "wof:name":"Pazzaglia Gabriele",
    "wof:placetype":"venue"
},
  "geometry": {"coordinates":[12.277684,43.30069],"type":"Point"}
}