{
  "type": "Feature",
  "properties": {
    "iso:country":"IT",
    "sg:address":"Str. Statale 345 25060 Collio",
    "sg:city":"Collio",
    "sg:classifiers":[
        {
            "category":"Manufacturing",
            "subcategory":"Tools & Machinery",
            "type":"Manufacturing & Wholesale Goods"
        }
    ],
    "sg:phone":"+39 030 927226",
    "sg:postcode":"25060",
    "sg:province":"Brescia",
    "sg:tags":[
        "machine",
        "nc",
        "accessory"
    ],
    "sg:website":"www.omz.it",
    "wof:name":"O.m.z. Srl",
    "wof:placetype":"venue"
},
  "geometry": {"coordinates":[10.222958,45.539829],"type":"Point"}
}