{
  "type": "Feature",
  "properties": {
    "iso:country":"IT",
    "sg:address":"00153 Roma",
    "sg:city":"Roma",
    "sg:orig_category":"Minuterie Metalliche E Ferramenta",
    "sg:phone":"+39 06 588 6022",
    "sg:postcode":"00153",
    "sg:province":"Roma",
    "wof:name":"Fisiocentro S.r.l.",
    "wof:placetype":"venue"
},
  "geometry": {"coordinates":[12.4735002518,41.8884315491],"type":"Point"}
}