{
  "type": "Feature",
  "properties": {
    "iso:country":"IT",
    "sg:address":"21036 Gemonio",
    "sg:city":"Gemonio",
    "sg:orig_category":"Tranciatura Metalli",
    "sg:phone":"+39 0332 602654",
    "sg:postcode":"21036",
    "sg:province":"Varese",
    "wof:name":"Giacchin Vittorio",
    "wof:placetype":"venue"
},
  "geometry": {"coordinates":[8.680362,45.884125],"type":"Point"}
}