{
  "type": "Feature",
  "properties": {
    "iso:country":"IT",
    "sg:address":"70021 Acquaviva Delle Fonti",
    "sg:city":"Acquaviva delle Fonti",
    "sg:orig_category":"Fotografia Pubblicitaria",
    "sg:phone":"+39 080 305 0527",
    "sg:postcode":"70021",
    "sg:province":"Bari",
    "wof:name":"Filigrana Di Caivano Vincenzo",
    "wof:placetype":"venue"
},
  "geometry": {"coordinates":[16.8394145966,40.9026451111],"type":"Point"}
}