{
  "type": "Feature",
  "properties": {
    "addr:full":"00171 Roma Roma Roma 00171",
    "addr:postcode":"00171;00171",
    "iso:country":"IT",
    "sg:address":"00171 Roma",
    "sg:city":"Roma",
    "sg:orig_category":"Autoaccessori - Commercio",
    "sg:phone":"+39 06 259 2183",
    "sg:postcode":"00171",
    "sg:province":"Roma",
    "wof:name":"C.e.p. Srl",
    "wof:placetype":"venue"
},
  "geometry": {"coordinates":[12.55656,41.892914],"type":"Point"}
}