{
  "type": "Feature",
  "properties": {
    "iso:country":"IT",
    "sg:address":"73055 Racale",
    "sg:city":"Racale",
    "sg:orig_category":"Manufacturers: Prefabbricati. Arredi Ed Attrezzature Per Attivita' Commerciali Ed Artigianali",
    "sg:phone":"+39 0833 552997",
    "sg:postcode":"73055",
    "sg:province":"Lecce",
    "sg:website":"http://www.jonicascale.it",
    "wof:name":"Jonica Scale Di Luigi Marzano",
    "wof:placetype":"venue"
},
  "geometry": {"coordinates":[18.065794,39.964466],"type":"Point"}
}