{
  "type": "Feature",
  "properties": {
    "addr:full":"21, Via Volta 23877 Paderno D'adda Lecco 23877",
    "addr:postcode":"23877;23877",
    "addr:street":"Via Volta",
    "iso:country":"IT",
    "sg:address":"21, Via Volta 23877 Paderno D'adda",
    "sg:classifiers":[
        {
            "category":"Shopping",
            "subcategory":"Clothing, Apparel, & Fashions",
            "type":"Retail Goods"
        }
    ],
    "sg:phone":"+39 39039510037",
    "sg:postcode":"23877",
    "sg:province":"Lecco",
    "sg:tags":[
        "clothes"
    ],
    "wof:name":"Maglificio Regina Di Riva A. & C. Snc",
    "wof:placetype":"venue"
},
  "geometry": {"coordinates":[9.390071,45.852982],"type":"Point"}
}