{
  "type": "Feature",
  "properties": {
    "iso:country":"IT",
    "sg:address":"55064 Pescaglia",
    "sg:city":"Pescaglia",
    "sg:orig_category":"Articoli Regalo - Produzione E Ingrosso",
    "sg:phone":"+39 0583 38124",
    "sg:postcode":"55064",
    "sg:province":"Lucca",
    "wof:name":"Olivar Di Tomei Mario",
    "wof:placetype":"venue"
},
  "geometry": {"coordinates":[10.475305,43.891724],"type":"Point"}
}