{
  "type": "Feature",
  "properties": {
    "iso:country":"IT",
    "sg:address":"66, Via Trento 20059 Vimercate",
    "sg:city":"Vimercate",
    "sg:classifiers":[
        {
            "category":"Manufacturing",
            "subcategory":"Paper Products",
            "type":"Manufacturing & Wholesale Goods"
        }
    ],
    "sg:phone":"+39 039 608 2860",
    "sg:postcode":"20059",
    "sg:province":"Milano",
    "sg:tags":[
        "cardboard"
    ],
    "wof:name":"Simi S.r.l.",
    "wof:placetype":"venue"
},
  "geometry": {"coordinates":[9.3589086533,45.5910415649],"type":"Point"}
}