{
  "type": "Feature",
  "properties": {
    "addr:full":"27010 Siziano Siziano Pavia 27010",
    "addr:postcode":"27010;27010",
    "iso:country":"IT",
    "sg:address":"27010 Siziano",
    "sg:city":"Siziano",
    "sg:orig_category":"Arredamenti - Materiali",
    "sg:phone":"+39 0382 617884",
    "sg:postcode":"27010",
    "sg:province":"Pavia",
    "sg:website":"http://www.suardi.com",
    "wof:name":"Suardi Arredamenti Srl",
    "wof:placetype":"venue"
},
  "geometry": {"coordinates":[9.204222,45.315315],"type":"Point"}
}