{
  "type": "Feature",
  "properties": {
    "addr:full":"68, Via Sangro 66022 Fossacesia Fossacesia Chieti 66022",
    "addr:postcode":"66022;66022",
    "addr:street":"Via Sangro",
    "iso:country":"IT",
    "sg:address":"68, Via Sangro 66022 Fossacesia",
    "sg:city":"Fossacesia",
    "sg:classifiers":[
        {
            "category":"Building & Trades",
            "subcategory":"Construction",
            "type":"Services"
        }
    ],
    "sg:phone":"+39 0872 608243",
    "sg:postcode":"66022",
    "sg:province":"Chieti",
    "sg:tags":[
        "work",
        "public"
    ],
    "wof:name":"Bucciante Costruzioni (s.r.l.)",
    "wof:placetype":"venue"
},
  "geometry": {"coordinates":[14.397544,42.227013],"type":"Point"}
}