{
  "type": "Feature",
  "properties": {
    "iso:country":"IT",
    "sg:address":"22036 Erba",
    "sg:city":"Erba",
    "sg:orig_category":"Climatizzazione E Condizionamento, Apparecchiature E Servizi. Elettrodomestici",
    "sg:phone":"+39 031 643344",
    "sg:postcode":"22036",
    "sg:province":"Como",
    "wof:name":"Aria Acqua Snc",
    "wof:placetype":"venue"
},
  "geometry": {"coordinates":[9.217548,45.803574],"type":"Point"}
}