{
  "type": "Feature",
  "properties": {
    "iso:country":"IT",
    "sg:address":"33, Piazza 4 Novembre 54100 Massa",
    "sg:city":"Massa",
    "sg:classifiers":[
        {
            "category":"Professional",
            "subcategory":"Engineering",
            "type":"Services"
        }
    ],
    "sg:phone":"+39 0585 793231",
    "sg:postcode":"54100",
    "sg:province":"Massa-Carrara",
    "sg:tags":[
        "machine",
        "-",
        "mechanical"
    ],
    "wof:name":"Barsanti Macchine Spa",
    "wof:placetype":"venue"
},
  "geometry": {"coordinates":[10.135955,44.024452],"type":"Point"}
}