{
  "type": "Feature",
  "properties": {
    "iso:country":"IT",
    "sg:address":"39047 Santa Cristina Val Gardena",
    "sg:city":"Santa Cristina Val Gardena",
    "sg:orig_category":"Elettricisti",
    "sg:phone":"+39 0471 793066",
    "sg:postcode":"39047",
    "sg:province":"Bolzano/Bozen",
    "wof:name":"Rudi Runggaldier Elettricista",
    "wof:placetype":"venue"
},
  "geometry": {"coordinates":[11.735288,46.576248],"type":"Point"}
}