{
  "type": "Feature",
  "properties": {
    "iso:country":"IT",
    "sg:address":"21, Via Sile 31057 Silea",
    "sg:city":"Silea",
    "sg:classifiers":[
        {
            "category":"Shopping",
            "subcategory":"Clothing, Apparel, & Fashions",
            "type":"Retail Goods"
        }
    ],
    "sg:phone":"+39 0422 362323",
    "sg:postcode":"31057",
    "sg:province":"Treviso",
    "sg:tags":[
        "clothes"
    ],
    "wof:name":"Criver Trade Srl",
    "wof:placetype":"venue"
},
  "geometry": {"coordinates":[12.29732,45.650642],"type":"Point"}
}