{
  "type": "Feature",
  "properties": {
    "addr:full":"41012 Carpi Carpi Modena 41012",
    "addr:postcode":"41012;41012",
    "iso:country":"IT",
    "sg:address":"41012 Carpi",
    "sg:city":"Carpi",
    "sg:orig_category":"Fotografia - Servizi, Studi, Sviluppo E Stampa",
    "sg:phone":"+39 059 654624",
    "sg:postcode":"41012",
    "sg:province":"Modena",
    "wof:name":"G.l.l. Srl",
    "wof:placetype":"venue"
},
  "geometry": {"coordinates":[10.8979301453,44.820098877],"type":"Point"}
}