{
  "type": "Feature",
  "properties": {
    "iso:country":"IT",
    "sg:address":"35129 Padova",
    "sg:city":"Padova",
    "sg:orig_category":"Valvole E Apparecchiature Di Misura. Ricambi E Componenti Dei Mezzi Di Trasporto",
    "sg:phone":"+39 049 775464",
    "sg:postcode":"35129",
    "sg:province":"Padova",
    "wof:name":"Casa Del Contachilometri (s.n.c.)",
    "wof:placetype":"venue"
},
  "geometry": {"coordinates":[11.925999,45.426647],"type":"Point"}
}