{
  "type": "Feature",
  "properties": {
    "iso:country":"IT",
    "sg:address":"21100 Varese",
    "sg:city":"Varese",
    "sg:orig_category":"Fotografia Apparecchi E Materiali - Vendita Al Dettaglio",
    "sg:phone":"+39 0332 238519",
    "sg:postcode":"21100",
    "sg:province":"Varese",
    "wof:name":"Angelo Casati & C.",
    "wof:placetype":"venue"
},
  "geometry": {"coordinates":[8.8185167313,45.8208808899],"type":"Point"}
}