{
  "type": "Feature",
  "properties": {
    "iso:country":"IT",
    "sg:address":"48012 Bagnacavallo",
    "sg:city":"Bagnacavallo",
    "sg:orig_category":"Macchine, Impianti Ed Attrezzature Per Agricoltura E Zootecnia",
    "sg:phone":"+39 0545 61148",
    "sg:postcode":"48012",
    "sg:province":"Ravenna",
    "wof:name":"M.b.m. Di Bagnara Luciano & C. Snc",
    "wof:placetype":"venue"
},
  "geometry": {"coordinates":[12.017562,44.397507],"type":"Point"}
}