{
  "type": "Feature",
  "properties": {
    "addr:full":"33050 Pozzuolo Del Friuli Pozzuolo del Friuli Udine 33050",
    "addr:postcode":"33050;33050",
    "addr:street":"Del Friuli",
    "iso:country":"IT",
    "sg:address":"33050 Pozzuolo Del Friuli",
    "sg:city":"Pozzuolo del Friuli",
    "sg:orig_category":"Macchine Utensili E Impianti",
    "sg:phone":"+39 0432 525911",
    "sg:postcode":"33050",
    "sg:province":"Udine",
    "sg:website":"http://www.sidermontaggi.it",
    "wof:name":"Sidermontaggi Spa",
    "wof:placetype":"venue"
},
  "geometry": {"coordinates":[13.246384,46.007542],"type":"Point"}
}