{
  "type": "Feature",
  "properties": {
    "iso:country":"IT",
    "sg:address":"49, Via Borgo Roldi 26025 Pandino",
    "sg:city":"Pandino",
    "sg:classifiers":[
        {
            "category":"Utilities",
            "subcategory":"Electric",
            "type":"Services"
        }
    ],
    "sg:phone":"+39 0373 920659",
    "sg:postcode":"26025",
    "sg:province":"Cremona",
    "sg:tags":[
        "component",
        "electronic"
    ],
    "wof:name":"Rte Di Brambilla Massimo Giorgio & C. (s.n.c.)",
    "wof:placetype":"venue"
},
  "geometry": {"coordinates":[9.549499,45.411537],"type":"Point"}
}