{
  "type": "Feature",
  "properties": {
    "iso:country":"IT",
    "sg:address":"11100 Aosta",
    "sg:city":"Aosta",
    "sg:orig_category":"Manufacturers: Prefabbricati",
    "sg:phone":"+39 0165 262161",
    "sg:postcode":"11100",
    "sg:province":"Aosta",
    "wof:name":"Edilaosta Srl",
    "wof:placetype":"venue"
},
  "geometry": {"coordinates":[7.313853,45.733791],"type":"Point"}
}