{
  "type": "Feature",
  "properties": {
    "iso:country":"IT",
    "sg:address":"37135 Verona",
    "sg:city":"Verona",
    "sg:orig_category":"Fiorai - Accessori E Forniture",
    "sg:phone":"+39 045 820 1159",
    "sg:postcode":"37135",
    "sg:province":"Verona",
    "wof:name":"Bertolani Service Srl",
    "wof:placetype":"venue"
},
  "geometry": {"coordinates":[10.9917478561,45.4383659363],"type":"Point"}
}