{
  "type": "Feature",
  "properties": {
    "iso:country":"IT",
    "sg:address":"33085 Maniago",
    "sg:city":"Maniago",
    "sg:orig_category":"Articoli Medico-sanitari Ed Ortopedici. Impianti, Attrezzature E Forniture Sanitarie Ed Ospedaliere",
    "sg:phone":"+39 0427 71561",
    "sg:postcode":"33085",
    "sg:province":"Pordenone",
    "wof:name":"Den Tag Srl",
    "wof:placetype":"venue"
},
  "geometry": {"coordinates":[12.704222,46.169334],"type":"Point"}
}