{
  "type": "Feature",
  "properties": {
    "iso:country":"IT",
    "sg:address":"20022 Castano Primo",
    "sg:city":"Castano Primo",
    "sg:orig_category":"Macchine, Impianti Ed Attrezzature Per Industria Alimentare E Bevande",
    "sg:phone":"+39 0331 880964",
    "sg:postcode":"20022",
    "sg:province":"Milano",
    "wof:name":"Perotta Macchine Industria Dolciaria (s.a.s.)",
    "wof:placetype":"venue"
},
  "geometry": {"coordinates":[8.781878,45.547997],"type":"Point"}
}