{
  "type": "Feature",
  "properties": {
    "addr:full":"12025 Dronero Dronero Cuneo 12025",
    "addr:postcode":"12025;12025",
    "iso:country":"IT",
    "sg:address":"12025 Dronero",
    "sg:city":"Dronero",
    "sg:orig_category":"Trattamenti Termici E Superficiali Metalli, Galvanotecnica",
    "sg:phone":"+39 0171 918358",
    "sg:postcode":"12025",
    "sg:province":"Cuneo",
    "wof:name":"Cherasco Snc Di Cherasco Gianpiero & C.",
    "wof:placetype":"venue"
},
  "geometry": {"coordinates":[7.350286,44.46833],"type":"Point"}
}