{
  "type": "Feature",
  "properties": {
    "iso:country":"IT",
    "sg:address":"9, Via Gallarate 21040 Morazzone",
    "sg:city":"Morazzone",
    "sg:classifiers":[
        {
            "category":"Manufacturing",
            "subcategory":"Printing",
            "type":"Manufacturing & Wholesale Goods"
        }
    ],
    "sg:phone":"+39 0332 892257",
    "sg:postcode":"21040",
    "sg:province":"Varese",
    "sg:tags":[
        "publishing"
    ],
    "wof:name":"Binfare' Varese Srl",
    "wof:placetype":"venue"
},
  "geometry": {"coordinates":[8.8124399185,45.764377594],"type":"Point"}
}