{
  "type": "Feature",
  "properties": {
    "iso:country":"IT",
    "sg:address":"40012 Calderara Di Reno",
    "sg:city":"Calderara di Reno",
    "sg:orig_category":"Macchine Utensili E Impianti",
    "sg:phone":"+39 051 729028",
    "sg:postcode":"40012",
    "sg:province":"Bologna",
    "wof:name":"Officina Meccanica Ferioli Snc",
    "wof:placetype":"venue"
},
  "geometry": {"coordinates":[11.264005,44.53994],"type":"Point"}
}