{
  "type": "Feature",
  "properties": {
    "addr:full":"Bivio Spigno Vecchio 04020 Spigno Saturnia Spigno Saturnia Latina 04020",
    "addr:postcode":"04020;04020",
    "addr:street":"Saturnia",
    "iso:country":"IT",
    "sg:address":"Bivio Spigno Vecchio 04020 Spigno Saturnia",
    "sg:city":"Spigno Saturnia",
    "sg:classifiers":[
        {
            "category":"Shopping",
            "subcategory":"Crafts & Fabrics",
            "type":"Retail Goods"
        }
    ],
    "sg:phone":"+39 39077164030",
    "sg:postcode":"04020",
    "sg:province":"Latina",
    "sg:tags":[
        "ceramic"
    ],
    "wof:name":"Saltarelli Mario & Guido",
    "wof:placetype":"venue"
},
  "geometry": {"coordinates":[12.9037,41.467598],"type":"Point"}
}