{
  "type": "Feature",
  "properties": {
    "iso:country":"IT",
    "sg:address":"31010 Col San Martino",
    "sg:city":"Col San Martino",
    "sg:orig_category":"Bevande, Vini E Liquori. Shopping",
    "sg:phone":"+39 0438 898147",
    "sg:postcode":"31010",
    "sg:province":"Treviso",
    "sg:website":"http://www.aicasali.com",
    "wof:name":"Vigneto Ai Casali Di De Nardi Ferruccio",
    "wof:placetype":"venue"
},
  "geometry": {"coordinates":[12.087156,45.89563],"type":"Point"}
}