{
  "type": "Feature",
  "properties": {
    "addr:full":"16162 Genova Genova Genova 16162",
    "addr:postcode":"16162;16162",
    "iso:country":"IT",
    "sg:address":"16162 Genova",
    "sg:city":"Genova",
    "sg:orig_category":"Trasporti E Spedizioni Merci",
    "sg:phone":"+39 010 712236",
    "sg:postcode":"16162",
    "sg:province":"Genova",
    "wof:name":"Cavalieri Trasporti Spa",
    "wof:placetype":"venue"
},
  "geometry": {"coordinates":[8.895978,44.46991],"type":"Point"}
}