{
  "type": "Feature",
  "properties": {
    "iso:country":"IT",
    "sg:address":"Via Staranzano 23 34077 Ronchi Dei Legionari",
    "sg:city":"Ronchi dei Legionari",
    "sg:classifiers":[
        {
            "category":"Wholesale",
            "subcategory":"Machinery & Supplies",
            "type":"Manufacturing & Wholesale Goods"
        }
    ],
    "sg:phone":"+39 0481 60237",
    "sg:postcode":"34077",
    "sg:province":"Gorizia",
    "sg:tags":[
        "agricultural",
        "equipment"
    ],
    "wof:name":"La Buona Terra Societa' Cooperativa",
    "wof:placetype":"venue"
},
  "geometry": {"coordinates":[13.504458,45.814335],"type":"Point"}
}