{
  "type": "Feature",
  "properties": {
    "iso:country":"IT",
    "sg:address":"00148 Roma",
    "sg:city":"Roma",
    "sg:orig_category":"Materiali Semilavorati Metallici",
    "sg:phone":"+39 06 6567 0829",
    "sg:postcode":"00148",
    "sg:province":"Roma",
    "wof:name":"Al.pi Metalleria Laurentina Di Piarulli Alessandro",
    "wof:placetype":"venue"
},
  "geometry": {"coordinates":[12.398524,41.820183],"type":"Point"}
}