{
  "type": "Feature",
  "properties": {
    "addr:full":"30, Viale Martiri Della Liberta' 17031 Albenga Albenga Savona 17031",
    "addr:housenumber":"30",
    "addr:postcode":"17031;17031",
    "addr:street":"Viale Martiri Della Liberta '",
    "iso:country":"IT",
    "sg:address":"30, Viale Martiri Della Liberta' 17031 Albenga",
    "sg:city":"Albenga",
    "sg:classifiers":[
        {
            "category":"Professional",
            "subcategory":"Printing & Photocopies",
            "type":"Services"
        }
    ],
    "sg:phone":"+39 39018250412",
    "sg:postcode":"17031",
    "sg:province":"Savona",
    "wof:name":"Tipolitografia F.lli Stalla Di Stalla Rosanna Fu Bruno & C. Snc",
    "wof:placetype":"venue"
},
  "geometry": {"coordinates":[8.2163476944,44.0480041504],"type":"Point"}
}