{
  "type": "Feature",
  "properties": {
    "iso:country":"IT",
    "sg:address":"53014 Monteroni D'arbia",
    "sg:orig_category":"Macchine, Impianti Ed Attrezzature Industria Chimica",
    "sg:phone":"+39 0577 373229",
    "sg:postcode":"53014",
    "sg:province":"Siena",
    "wof:name":"Messere Enzo",
    "wof:placetype":"venue"
},
  "geometry": {"coordinates":[11.411751,43.226051],"type":"Point"}
}