{
  "type": "Feature",
  "properties": {
    "iso:country":"IT",
    "sg:address":"98122 Messina",
    "sg:city":"Messina",
    "sg:orig_category":"Forniture Alle Strutture Ricettive. Forniture Per Attivita' Commerciali Ed Artigianali",
    "sg:phone":"+39 090 711955",
    "sg:postcode":"98122",
    "sg:province":"Messina",
    "wof:name":"Bonaccorso Tessuti Di Bonaccorso Eugenio",
    "wof:placetype":"venue"
},
  "geometry": {"coordinates":[15.5570230484,38.1870803833],"type":"Point"}
}