{
  "type": "Feature",
  "properties": {
    "addr:full":"33, Via Della Liberazione 20098 San Giuliano Milanese San Giuliano Milanese Milano 20098",
    "addr:postcode":"20098;20098",
    "addr:street":"Via Della Liberazione",
    "iso:country":"IT",
    "sg:address":"33, Via Della Liberazione 20098 San Giuliano Milanese",
    "sg:city":"San Giuliano Milanese",
    "sg:classifiers":[
        {
            "category":"Professional",
            "subcategory":"Engineering",
            "type":"Services"
        }
    ],
    "sg:phone":"+39 02 9828 1035",
    "sg:postcode":"20098",
    "sg:province":"Milano",
    "sg:tags":[
        "machine",
        "-",
        "mechanical"
    ],
    "wof:name":"Tumac (s.p.a.)",
    "wof:placetype":"venue"
},
  "geometry": {"coordinates":[9.264246,45.401676],"type":"Point"}
}