{
  "type": "Feature",
  "properties": {
    "addr:full":"71, Via Pentelete 80044 Ottaviano Ottaviano Napoli 80044",
    "addr:postcode":"80044;80044",
    "addr:street":"Via Pentelete",
    "iso:country":"IT",
    "sg:address":"71, Via Pentelete 80044 Ottaviano",
    "sg:city":"Ottaviano",
    "sg:classifiers":[
        {
            "category":"Shopping",
            "subcategory":"Clothing, Apparel, & Fashions",
            "type":"Retail Goods"
        }
    ],
    "sg:phone":"+39 081 528 9686",
    "sg:postcode":"80044",
    "sg:province":"Napoli",
    "sg:tags":[
        "clothes"
    ],
    "wof:name":"Criggi S.r.l.",
    "wof:placetype":"venue"
},
  "geometry": {"coordinates":[14.475883,40.857712],"type":"Point"}
}