{
  "type": "Feature",
  "properties": {
    "iso:country":"IT",
    "sg:address":"20019 Settimo Milanese",
    "sg:city":"Settimo Milanese",
    "sg:orig_category":"Elettrotecnica Industriale, Prodotti E Apparecchiature",
    "sg:phone":"+39 02 3351 2217",
    "sg:postcode":"20019",
    "sg:province":"Milano",
    "wof:name":"Emmegi Di Maestrello G.",
    "wof:placetype":"venue"
},
  "geometry": {"coordinates":[9.04556,45.49334],"type":"Point"}
}