{
  "type": "Feature",
  "properties": {
    "addr:full":"31100 Treviso Treviso Treviso 31100",
    "addr:postcode":"31100;31100",
    "iso:country":"IT",
    "sg:address":"31100 Treviso",
    "sg:city":"Treviso",
    "sg:orig_category":"Articoli Da Regalo. Regalistica Aziendale",
    "sg:phone":"+39 0422 6721",
    "sg:postcode":"31100",
    "sg:province":"Treviso",
    "sg:website":"http://www.tognana-porcellane.com",
    "wof:name":"Tognana Porcellane Spa",
    "wof:placetype":"venue"
},
  "geometry": {"coordinates":[12.254918,45.660366],"type":"Point"}
}