{
  "type": "Feature",
  "properties": {
    "addr:full":"40137 Bologna Bologna Bologna 40137",
    "addr:postcode":"40137;40137",
    "iso:country":"IT",
    "sg:address":"40137 Bologna",
    "sg:city":"Bologna",
    "sg:classifiers":[
        {
            "category":"Health Services",
            "subcategory":"Health Practitioner",
            "type":"Services"
        }
    ],
    "sg:phone":"+39 051 342912",
    "sg:postcode":"40137",
    "sg:province":"Bologna",
    "sg:tags":[
        "medici"
    ],
    "wof:name":"Gottarelli Prof. Dott. Paolo",
    "wof:placetype":"venue"
},
  "geometry": {"coordinates":[11.358686,44.48304],"type":"Point"}
}