{
  "type": "Feature",
  "properties": {
    "iso:country":"IT",
    "sg:address":"65127 Pescara",
    "sg:city":"Pescara",
    "sg:orig_category":"Abbigliamento Esterno, Maglierie E Pelliccerie. Forniture Per Il Settore Dello Spettacolo",
    "sg:phone":"+39 085 63728",
    "sg:postcode":"65127",
    "sg:province":"Pescara",
    "wof:name":"Frammenti Di Ridolfi Giovanna",
    "wof:placetype":"venue"
},
  "geometry": {"coordinates":[14.212333,42.461266],"type":"Point"}
}