{
  "type": "Feature",
  "properties": {
    "iso:country":"IT",
    "sg:address":"20133 Milano",
    "sg:city":"Milano",
    "sg:orig_category":"Servizi E Lavori Per Abbigliamento E Pelletterie",
    "sg:phone":"+39 02 204 7195",
    "sg:postcode":"20133",
    "sg:province":"Milano",
    "wof:name":"Basilicata Sonia",
    "wof:placetype":"venue"
},
  "geometry": {"coordinates":[9.218929,45.477657],"type":"Point"}
}