{
  "type": "Feature",
  "properties": {
    "addr:full":"60123 Ancona Ancona Ancona 60123",
    "addr:postcode":"60123;60123",
    "iso:country":"IT",
    "sg:address":"60123 Ancona",
    "sg:city":"Ancona",
    "sg:classifiers":[
        {
            "category":"Health Services",
            "subcategory":"Health Practitioner",
            "type":"Services"
        }
    ],
    "sg:phone":"+39 071 358971",
    "sg:postcode":"60123",
    "sg:province":"Ancona",
    "sg:tags":[
        "medici"
    ],
    "wof:name":"Studio Associato Dott. S. De Paoli, Dott. R. S. Bottacchiari, Dott. C. De Paoli",
    "wof:placetype":"venue"
},
  "geometry": {"coordinates":[13.5277853012,43.6185531616],"type":"Point"}
}