{
  "type": "Feature",
  "properties": {
    "iso:country":"IT",
    "sg:address":"23020 Montagna Valtellina",
    "sg:orig_category":"Bagno - Accessori E Mobili",
    "sg:phone":"+39 0342 381022",
    "sg:postcode":"23020",
    "sg:province":"Sondrio",
    "wof:name":"Casastyle Snc Di Gandossini Geom. Stefano & Sonia",
    "wof:placetype":"venue"
},
  "geometry": {"coordinates":[9.900743,46.176495],"type":"Point"}
}