{
  "type": "Feature",
  "properties": {
    "iso:country":"IT",
    "sg:address":"60030 Castelbellino",
    "sg:city":"Castelbellino",
    "sg:orig_category":"Elettrotecnica Industriale, Prodotti E Apparecchiature",
    "sg:phone":"+39 0731 705062",
    "sg:postcode":"60030",
    "sg:province":"Ancona",
    "wof:name":"Cable System Di Marinelli Laura",
    "wof:placetype":"venue"
},
  "geometry": {"coordinates":[13.503948,43.595448],"type":"Point"}
}