{
  "type": "Feature",
  "properties": {
    "iso:country":"IT",
    "sg:address":"15100 Alessandria",
    "sg:city":"Alessandria",
    "sg:orig_category":"Macchine, Impianti E Forniture Per Industria Grafica, Cartaria E Cartotecnica. Forniture Per Uffici",
    "sg:phone":"+39 0131 223762",
    "sg:postcode":"15100",
    "sg:province":"Alessandria",
    "wof:name":"Errepi Di Renato Rosa & C. Snc",
    "wof:placetype":"venue"
},
  "geometry": {"coordinates":[8.617342,44.917503],"type":"Point"}
}