{
  "type": "Feature",
  "properties": {
    "iso:country":"IT",
    "sg:address":"Viale Veneto 35020 Saonara",
    "sg:city":"Saonara",
    "sg:classifiers":[
        {
            "category":"Manufacturing",
            "subcategory":"Food",
            "type":"Manufacturing & Wholesale Goods"
        }
    ],
    "sg:phone":"+39 39049640372",
    "sg:postcode":"35020",
    "sg:province":"Padova",
    "sg:tags":[
        "equipment",
        "processing",
        "-",
        "machinery"
    ],
    "wof:name":"B.c.m. (s.n.c.)",
    "wof:placetype":"venue"
},
  "geometry": {"coordinates":[11.958325386,45.3827095032],"type":"Point"}
}