{
  "type": "Feature",
  "properties": {
    "iso:country":"IT",
    "sg:address":"23030 Livigno",
    "sg:city":"Livigno",
    "sg:orig_category":"Servizi Per Lo Sport E Il Tempo Libero. Servizi Al Turismo",
    "sg:phone":"+39 0342 997173",
    "sg:postcode":"23030",
    "sg:province":"Sondrio",
    "wof:name":"Sciovia Doss Di Peri Agostino E C. Snc",
    "wof:placetype":"venue"
},
  "geometry": {"coordinates":[10.125843,46.521976],"type":"Point"}
}