{
  "type": "Feature",
  "properties": {
    "iso:country":"IT",
    "sg:address":"40026 Imola",
    "sg:city":"Imola",
    "sg:orig_category":"Forniture Per Edilizia E Lavori Pubblici. Forniture Industriali Per Prevenzione, Controllo E Sicurezza",
    "sg:phone":"+39 0542 42316",
    "sg:postcode":"40026",
    "sg:province":"Bologna",
    "wof:name":"Antincendio Imolese Srl",
    "wof:placetype":"venue"
},
  "geometry": {"coordinates":[11.6959810257,44.3586158752],"type":"Point"}
}