{
  "type": "Feature",
  "properties": {
    "iso:country":"IT",
    "sg:address":"197, Via Salce 32100 Belluno",
    "sg:city":"Belluno",
    "sg:classifiers":[
        {
            "category":"Wholesale",
            "subcategory":"Medical Equipment & Supplies",
            "type":"Manufacturing & Wholesale Goods"
        }
    ],
    "sg:phone":"+39 0437 296840",
    "sg:postcode":"32100",
    "sg:province":"Belluno",
    "sg:tags":[
        "-",
        "health",
        "instrument"
    ],
    "wof:name":"Studio Promozionali (s.n.c.) Di Baldi Esterina - Cafiero Guido & C.",
    "wof:placetype":"venue"
},
  "geometry": {"coordinates":[12.219366,46.136608],"type":"Point"}
}