{
  "type": "Feature",
  "properties": {
    "iso:country":"IT",
    "sg:address":"11100 Aosta",
    "sg:city":"Aosta",
    "sg:orig_category":"Musica",
    "sg:phone":"+39 0165 31504",
    "sg:postcode":"11100",
    "sg:province":"Aosta",
    "wof:name":"Il Disco Di Curioni Bruna & C. Snc",
    "wof:placetype":"venue"
},
  "geometry": {"coordinates":[7.3132338524,45.7350006104],"type":"Point"}
}