{
  "type": "Feature",
  "properties": {
    "addr:full":"54100 Massa Massa Massa-Carrara 54100",
    "addr:postcode":"54100;54100",
    "iso:country":"IT",
    "sg:address":"54100 Massa",
    "sg:city":"Massa",
    "sg:orig_category":"Impiantistica E Prodotti Tecnologici Per Edilizia. Telecomunicazioni E Telefonia, Impianti, Apparecchi E Servizi",
    "sg:phone":"+39 0585 810800",
    "sg:postcode":"54100",
    "sg:province":"Massa-Carrara",
    "sg:website":"http://www.zibaldone.com",
    "wof:name":"Type E Tape Srl",
    "wof:placetype":"venue"
},
  "geometry": {"coordinates":[10.102194,44.006973],"type":"Point"}
}