{
  "type": "Feature",
  "properties": {
    "addr:full":"36010 Velo D'astico Velo Vicenza 36010",
    "addr:postcode":"36010;36010",
    "iso:country":"IT",
    "sg:address":"36010 Velo D'astico",
    "sg:city":"Velo",
    "sg:orig_category":"Articoli Da Regalo. Hobbistica. Shopping",
    "sg:phone":"+39 0445 740118",
    "sg:postcode":"36010",
    "sg:province":"Vicenza",
    "wof:name":"Pedemonte Paolo",
    "wof:placetype":"venue"
},
  "geometry": {"coordinates":[11.366405,45.793522],"type":"Point"}
}