{
  "type": "Feature",
  "properties": {
    "iso:country":"IT",
    "sg:address":"Via Suganappa 10 22015 Gravedona",
    "sg:city":"Gravedona",
    "sg:classifiers":[
        {
            "category":"Sports & Exercise",
            "subcategory":"Ski Resort",
            "type":"Entertainment"
        }
    ],
    "sg:phone":"+39 0344 85224",
    "sg:postcode":"22015",
    "sg:province":"Como",
    "sg:tags":[
        "spectacles",
        "spectacle"
    ],
    "sg:website":"www.saliceocchiali.it",
    "wof:name":"Salice Occhiali Srl",
    "wof:placetype":"venue"
},
  "geometry": {"coordinates":[9.304498,46.144733],"type":"Point"}
}