{
  "type": "Feature",
  "properties": {
    "addr:full":"00152 Roma Roma Roma 00152",
    "addr:postcode":"00152;00152",
    "iso:country":"IT",
    "sg:address":"00152 Roma",
    "sg:city":"Roma",
    "sg:orig_category":"Manufacturers: Prefabbricati",
    "sg:phone":"+39 06 5327 6007",
    "sg:postcode":"00152",
    "sg:province":"Roma",
    "sg:website":"http://www.cpr_engineer.com",
    "wof:name":"C.p.r. Engineer Srl",
    "wof:placetype":"venue"
},
  "geometry": {"coordinates":[12.454273,41.875874],"type":"Point"}
}