{
  "type": "Feature",
  "properties": {
    "iso:country":"IT",
    "sg:address":"00141 Roma",
    "sg:city":"Roma",
    "sg:orig_category":"Elettronica Professionale E Di Consumo. Tempo Libero - Articoli E Forniture",
    "sg:phone":"+39 06 8832 7882",
    "sg:postcode":"00141",
    "sg:province":"Roma",
    "wof:name":"Gamepro Di Cera Antonio",
    "wof:placetype":"venue"
},
  "geometry": {"coordinates":[12.524493,41.941505],"type":"Point"}
}