{
  "type": "Feature",
  "properties": {
    "iso:country":"IT",
    "sg:address":"15, Contrada Majanesi 62010 Treia",
    "sg:city":"Treia",
    "sg:classifiers":[
        {
            "category":"Manufacturing",
            "subcategory":"Tools & Machinery",
            "type":"Manufacturing & Wholesale Goods"
        }
    ],
    "sg:phone":"+39 0733 541458",
    "sg:postcode":"62010",
    "sg:province":"Macerata",
    "sg:tags":[
        "environment",
        "equipment",
        "-"
    ],
    "wof:name":"Co.fer.metal (s.r.l.)",
    "wof:placetype":"venue"
},
  "geometry": {"coordinates":[13.321248,43.277111],"type":"Point"}
}