{
  "type": "Feature",
  "properties": {
    "addr:full":"42/a, Via Gramsci Antonio 00197 Roma Roma Roma 00197",
    "addr:housenumber":"42 / a",
    "addr:postcode":"00197;00197",
    "addr:street":"Via Gramsci Antonio",
    "iso:country":"IT",
    "sg:address":"42/a, Via Gramsci Antonio 00197 Roma",
    "sg:city":"Roma",
    "sg:classifiers":[
        {
            "category":"Professional",
            "subcategory":"Advertising",
            "type":"Services"
        }
    ],
    "sg:phone":"+39 39063222882",
    "sg:postcode":"00197",
    "sg:province":"Roma",
    "sg:tags":[
        "communication",
        "medium"
    ],
    "wof:name":"Compagnia Leone Cinematografica S.r.l.",
    "wof:placetype":"venue"
},
  "geometry": {"coordinates":[12.373774,42.112556],"type":"Point"}
}