{
  "type": "Feature",
  "properties": {
    "iso:country":"IT",
    "sg:address":"209, Via Massarenti Giuseppe 40138 Bologna",
    "sg:city":"Bologna",
    "sg:classifiers":[
        {
            "category":"Bars & Pubs",
            "subcategory":"Nightclub",
            "type":"Food & Drink"
        }
    ],
    "sg:phone":"+39 051 601 0970",
    "sg:postcode":"40138",
    "sg:province":"Bologna",
    "sg:tags":[
        "cake",
        "bread"
    ],
    "wof:name":"Nuova Panemilia S.r.l.",
    "wof:placetype":"venue"
},
  "geometry": {"coordinates":[11.346481,44.494221],"type":"Point"}
}