{
  "type": "Feature",
  "properties": {
    "iso:country":"IT",
    "sg:address":"Cascina Cortenuova 14 Via Case Par 28100 Novara",
    "sg:city":"Novara",
    "sg:classifiers":[
        {
            "category":"Structure",
            "subcategory":"Factory",
            "type":"Public Place"
        }
    ],
    "sg:phone":"+39 0321 455192",
    "sg:postcode":"28100",
    "sg:province":"Novara",
    "sg:tags":[
        "complete",
        "installations"
    ],
    "sg:website":"www.facchinettinovara.com",
    "wof:name":"Facchinetti Srl",
    "wof:placetype":"venue"
},
  "geometry": {"coordinates":[8.6186714172,45.4450836182],"type":"Point"}
}