{
  "type": "Feature",
  "properties": {
    "iso:country":"IT",
    "sg:address":"513, Via Sauro Nazario S. Concordio C. 55100 Lucca",
    "sg:city":"Lucca",
    "sg:classifiers":[
        {
            "category":"Manufacturing",
            "subcategory":"Rubber & Plastics",
            "type":"Manufacturing & Wholesale Goods"
        }
    ],
    "sg:phone":"+39 39058395881",
    "sg:postcode":"55100",
    "sg:province":"Lucca",
    "wof:name":"La.pa.sca. S.p.a.",
    "wof:placetype":"venue"
},
  "geometry": {"coordinates":[10.5079936981,43.8430137634],"type":"Point"}
}