{
  "type": "Feature",
  "properties": {
    "iso:country":"IT",
    "sg:address":"92, Via Archimede 47023 Cesena",
    "sg:city":"Cesena",
    "sg:classifiers":[
        {
            "category":"Manufacturing",
            "subcategory":"Rubber & Plastics",
            "type":"Manufacturing & Wholesale Goods"
        }
    ],
    "sg:phone":"+39 0547 301568",
    "sg:postcode":"47023",
    "sg:province":"Forl\u00ec-Cesena",
    "wof:name":"Illuminotecnica M. & M.di Giorgi E Magnani (s.n.c.)",
    "wof:placetype":"venue"
},
  "geometry": {"coordinates":[12.2943582535,44.1187973022],"type":"Point"}
}