{
  "type": "Feature",
  "properties": {
    "iso:country":"IT",
    "sg:address":"1/a, Via Palazzetto 36070 Castelgomberto",
    "sg:city":"Castelgomberto",
    "sg:classifiers":[
        {
            "category":"Manufacturing",
            "subcategory":"Tools & Machinery",
            "type":"Manufacturing & Wholesale Goods"
        }
    ],
    "sg:phone":"+39 0445 941400",
    "sg:postcode":"36070",
    "sg:province":"Vicenza",
    "sg:tags":[
        "environment",
        "equipment",
        "-"
    ],
    "wof:name":"Diquigiovanni (s.r.l.)",
    "wof:placetype":"venue"
},
  "geometry": {"coordinates":[11.474985,45.593483],"type":"Point"}
}