{
  "type": "Feature",
  "properties": {
    "addr:full":"20090 Pieve Emanuele Pieve Emanuele Milano 20090",
    "addr:postcode":"20090;20090",
    "iso:country":"IT",
    "sg:address":"20090 Pieve Emanuele",
    "sg:city":"Pieve Emanuele",
    "sg:orig_category":"Trattamenti Termici E Superficiali Metalli, Galvanotecnica",
    "sg:phone":"+39 02 9078 2446",
    "sg:postcode":"20090",
    "sg:province":"Milano",
    "wof:name":"Anastasi Snc Di Anastasi Alfonso & C.",
    "wof:placetype":"venue"
},
  "geometry": {"coordinates":[9.18511,45.372276],"type":"Point"}
}