{
  "type": "Feature",
  "properties": {
    "addr:full":"6, Via Manzoni Alessandro 20045 Besana In Brianza Besana in Brianza Milano 20045",
    "addr:postcode":"20045;20045",
    "addr:street":"Via Manzoni Alessandro",
    "iso:country":"IT",
    "sg:address":"6, Via Manzoni Alessandro 20045 Besana In Brianza",
    "sg:city":"Besana in Brianza",
    "sg:classifiers":[
        {
            "category":"Shopping",
            "subcategory":"Crafts & Fabrics",
            "type":"Retail Goods"
        }
    ],
    "sg:phone":"+39 036 299 6651",
    "sg:postcode":"20045",
    "sg:province":"Milano",
    "wof:name":"Manifattura Casati (s.a.s.)",
    "wof:placetype":"venue"
},
  "geometry": {"coordinates":[9.2124643326,45.4880142212],"type":"Point"}
}