{
  "type": "Feature",
  "properties": {
    "iso:country":"IT",
    "sg:address":"20, Via S. Antonio 15032 Borgo San Martino",
    "sg:city":"Borgo San Martino",
    "sg:classifiers":[
        {
            "category":"Food & Beverages",
            "subcategory":"Groceries & Convenience Stores",
            "type":"Retail Goods"
        }
    ],
    "sg:phone":"+39 0142 428002",
    "sg:postcode":"15032",
    "sg:province":"Alessandria",
    "sg:tags":[
        "product",
        "related"
    ],
    "wof:name":"Rota Fratelli S.r.l.",
    "wof:placetype":"venue"
},
  "geometry": {"coordinates":[8.6169509888,44.9132156372],"type":"Point"}
}