{
  "type": "Feature",
  "properties": {
    "iso:country":"IT",
    "sg:address":"Via Cavour 40/42, 20075 Lodi, Lo",
    "sg:classifiers":[
        {
            "category":"Banks & Credit Unions",
            "subcategory":"Bank",
            "type":"Services"
        }
    ],
    "sg:phone":"+39 0371 595230",
    "wof:name":"Padana Partecipazioni Spa",
    "wof:placetype":"venue"
},
  "geometry": {"coordinates":[9.505144,45.314445],"type":"Point"}
}