{
  "type": "Feature",
  "properties": {
    "iso:country":"IT",
    "sg:address":"6, Strada Vallero 10080 Salassa",
    "sg:city":"Salassa",
    "sg:classifiers":[
        {
            "category":"Professional",
            "subcategory":"Engineering",
            "type":"Services"
        }
    ],
    "sg:phone":"+39 39012436333",
    "sg:postcode":"10080",
    "sg:province":"Torino",
    "sg:tags":[
        "machine",
        "-",
        "mechanical"
    ],
    "wof:name":"Ecoplus S.r.l.",
    "wof:placetype":"venue"
},
  "geometry": {"coordinates":[7.680283,45.363659],"type":"Point"}
}