{
  "type": "Feature",
  "properties": {
    "iso:country":"IT",
    "sg:address":"24060 Viadanica",
    "sg:city":"Viadanica",
    "sg:orig_category":"Ristorazione E Locali Pubblici Affini. Ristoranti Ed Esercizi Affini. Servizi Ausiliari Di Ristorazione E Di Intrattenimento",
    "sg:phone":"+39 035 926188",
    "sg:postcode":"24060",
    "sg:province":"Bergamo",
    "wof:name":"Trattoria Braga",
    "wof:placetype":"venue"
},
  "geometry": {"coordinates":[9.974972,45.690117],"type":"Point"}
}