{
  "type": "Feature",
  "properties": {
    "iso:country":"IT",
    "sg:address":"55100 Lucca",
    "sg:city":"Lucca",
    "sg:orig_category":"Pubblicita', Marketing E Comunicazione",
    "sg:phone":"+39 0583 469292",
    "sg:postcode":"55100",
    "sg:province":"Lucca",
    "sg:website":"http://www.vipanimazione.it",
    "wof:name":"V.i.p. Di Fabbri & Falco Snc",
    "wof:placetype":"venue"
},
  "geometry": {"coordinates":[10.5192346573,43.8399543762],"type":"Point"}
}