{
  "type": "Feature",
  "properties": {
    "iso:country":"IT",
    "sg:address":"3, V. Bonini 21100 Varese",
    "sg:city":"Varese",
    "sg:classifiers":[
        {
            "category":"Professional",
            "subcategory":"Engineering",
            "type":"Services"
        }
    ],
    "sg:phone":"+39 0332 238014",
    "sg:postcode":"21100",
    "sg:province":"Varese",
    "sg:tags":[
        "machine",
        "-",
        "mechanical"
    ],
    "sg:website":"http://www.lemavarese.it:ws_end: :mark:ws:http://www.paginegialle.it/lemasrl",
    "wof:name":"Lema Srl",
    "wof:placetype":"venue"
},
  "geometry": {"coordinates":[8.831755,45.829205],"type":"Point"}
}