{
  "type": "Feature",
  "properties": {
    "iso:country":"IT",
    "sg:address":"05023 Baschi",
    "sg:city":"Baschi",
    "sg:orig_category":"Motori Ed Organi Di Trasmissione",
    "sg:phone":"+39 0744 956016",
    "sg:postcode":"05023",
    "sg:province":"Terni",
    "wof:name":"Telor Srl.",
    "wof:placetype":"venue"
},
  "geometry": {"coordinates":[12.2891311646,42.7152099609],"type":"Point"}
}