{
  "type": "Feature",
  "properties": {
    "addr:full":"36, Frazione Falcero 13825 Valle Mosso Valle Mosso Biella 13825",
    "addr:postcode":"13825;13825",
    "addr:street":"Frazione Falcero;Mosso",
    "iso:country":"IT",
    "sg:address":"36, Frazione Falcero 13825 Valle Mosso",
    "sg:city":"Valle Mosso",
    "sg:classifiers":[
        {
            "category":"Shopping",
            "subcategory":"Crafts & Fabrics",
            "type":"Retail Goods"
        }
    ],
    "sg:phone":"+39 015 704 8800",
    "sg:postcode":"13825",
    "sg:province":"Biella",
    "wof:name":"Garlanda Fratelli Lanificio S.p.a.",
    "wof:placetype":"venue"
},
  "geometry": {"coordinates":[8.1516637802,45.6259002686],"type":"Point"}
}