{
  "type": "Feature",
  "properties": {
    "iso:country":"IT",
    "sg:address":"Via Argine Destro 607 18100 Imperia",
    "sg:city":"Imperia",
    "sg:classifiers":[
        {
            "category":"Building & Trades",
            "subcategory":"Electrical",
            "type":"Services"
        }
    ],
    "sg:phone":"+39 0183 767115",
    "sg:postcode":"18100",
    "sg:province":"Imperia",
    "sg:tags":[
        "communication",
        "computers",
        "equipment",
        "terminals",
        "computer",
        "data"
    ],
    "sg:website":"www.goldmedia.it",
    "wof:name":"Gold Italia S.r.l.",
    "wof:placetype":"venue"
},
  "geometry": {"coordinates":[8.033062,43.892994],"type":"Point"}
}