{
  "type": "Feature",
  "properties": {
    "iso:country":"IT",
    "sg:address":"53045 Montepulciano",
    "sg:city":"Abbadia",
    "sg:orig_category":"Serramenti Ed Infissi",
    "sg:phone":"+39 0578 708096",
    "sg:postcode":"53045",
    "sg:province":"Siena",
    "wof:name":"So.l.a.t. Srl",
    "wof:placetype":"venue"
},
  "geometry": {"coordinates":[11.782389,43.092926],"type":"Point"}
}