{
  "type": "Feature",
  "properties": {
    "iso:country":"IT",
    "sg:address":"170, Via Aldo Moro 66020 San Giovanni Teatino",
    "sg:city":"San Giovanni Teatino",
    "sg:classifiers":[
        {
            "category":"Manufacturing",
            "subcategory":"Metals",
            "type":"Manufacturing & Wholesale Goods"
        }
    ],
    "sg:phone":"+39 085 446 1381",
    "sg:postcode":"66020",
    "sg:province":"Chieti",
    "sg:tags":[
        "metallurgy",
        "metalworking"
    ],
    "wof:name":"Tas - Tac Anchor System S.r.l.",
    "wof:placetype":"venue"
},
  "geometry": {"coordinates":[14.1803159714,42.4184417725],"type":"Point"}
}