{
  "type": "Feature",
  "properties": {
    "iso:country":"IT",
    "sg:address":"25038 Rovato",
    "sg:city":"Rovato",
    "sg:classifiers":[
        {
            "category":"Manufacturing",
            "subcategory":"Motor Vehicles & Parts",
            "type":"Manufacturing & Wholesale Goods"
        }
    ],
    "sg:phone":"+39 030 724 0105",
    "sg:postcode":"25038",
    "sg:province":"Brescia",
    "sg:tags":[
        "spare",
        "vehicles",
        "component"
    ],
    "wof:name":"Kwp Srl",
    "wof:placetype":"venue"
},
  "geometry": {"coordinates":[10.0171489716,45.5306396484],"type":"Point"}
}