{
  "type": "Feature",
  "properties": {
    "iso:country":"IT",
    "sg:address":"39011 Lana",
    "sg:city":"Lana",
    "sg:orig_category":"Bevande, Vini E Liquori",
    "sg:phone":"+39 0473 552900",
    "sg:postcode":"39011",
    "sg:province":"Bolzano/Bozen",
    "wof:name":"Iprona Spa",
    "wof:placetype":"venue"
},
  "geometry": {"coordinates":[11.342223,46.504448],"type":"Point"}
}