{
  "type": "Feature",
  "properties": {
    "addr:full":"24060 Telgate Telgate Bergamo 24060",
    "addr:postcode":"24060;24060",
    "addr:street":"Telgate Telgate",
    "iso:country":"IT",
    "sg:address":"24060 Telgate",
    "sg:city":"Telgate",
    "sg:orig_category":"Motocicli E Motocarri - Commercio E Riparazione",
    "sg:phone":"+39 035 831407",
    "sg:postcode":"24060",
    "sg:province":"Bergamo",
    "wof:name":"Leo Moto Snc",
    "wof:placetype":"venue"
},
  "geometry": {"coordinates":[9.8528337479,45.6298522949],"type":"Point"}
}