{
  "type": "Feature",
  "properties": {
    "addr:full":"44100 Ferrara Ferrara Ferrara 44100",
    "addr:postcode":"44100;44100",
    "iso:country":"IT",
    "sg:address":"44100 Ferrara",
    "sg:city":"Ferrara",
    "sg:orig_category":"Ricerca Scientifica - Laboratori",
    "sg:phone":"+39 0532 205877",
    "sg:postcode":"44100",
    "sg:province":"Ferrara",
    "wof:name":"Laboratorio Analisi Cliniche Estense Snc",
    "wof:placetype":"venue"
},
  "geometry": {"coordinates":[11.616814,44.837151],"type":"Point"}
}