{
  "type": "Feature",
  "properties": {
    "iso:country":"IT",
    "sg:address":"74100 Taranto",
    "sg:city":"Taranto",
    "sg:orig_category":"Materiali Edili",
    "sg:phone":"+39 099 470 4369",
    "sg:postcode":"74100",
    "sg:province":"Taranto",
    "wof:name":"Calce Segreto Cosimo",
    "wof:placetype":"venue"
},
  "geometry": {"coordinates":[17.313931,40.503941],"type":"Point"}
}