{
  "type": "Feature",
  "properties": {
    "iso:country":"IT",
    "sg:address":"70126 Bari",
    "sg:city":"Bari",
    "sg:orig_category":"Consulenza Di Direzione Ed Organizzazione Aziendale",
    "sg:phone":"+39 080 523 4414",
    "sg:postcode":"70126",
    "sg:province":"Bari",
    "wof:name":"Prog. E Co. Sas Di Giangregorio Francesco Maurizio & C.",
    "wof:placetype":"venue"
},
  "geometry": {"coordinates":[16.886787,41.041485],"type":"Point"}
}