{
  "type": "Feature",
  "properties": {
    "addr:full":"36010 Carr\u00e8 Vicenza 36010",
    "addr:postcode":"36010;36010",
    "iso:country":"IT",
    "sg:address":"36010 Carr\u00e8",
    "sg:classifiers":[
        {
            "category":"Manufacturing",
            "subcategory":"Metals",
            "type":"Manufacturing & Wholesale Goods"
        }
    ],
    "sg:phone":"+39 0445 390428",
    "sg:postcode":"36010",
    "sg:province":"Vicenza",
    "sg:tags":[
        "forming",
        "working",
        "welding"
    ],
    "wof:name":"Tomasi Torneria Meccanica",
    "wof:placetype":"venue"
},
  "geometry": {"coordinates":[11.464427948,45.7365722656],"type":"Point"}
}