{
  "type": "Feature",
  "properties": {
    "addr:full":"Via Oliveto 03049 Sant'elia Fiumerapido Frosinone 03049",
    "addr:postcode":"03049;03049",
    "addr:street":"Via Oliveto",
    "iso:country":"IT",
    "sg:address":"Via Oliveto 03049 Sant'elia Fiumerapido",
    "sg:classifiers":[
        {
            "category":"Real Estate",
            "subcategory":"Surveying",
            "type":"Services"
        }
    ],
    "sg:phone":"+39 0776 429666",
    "sg:postcode":"03049",
    "sg:province":"Frosinone",
    "sg:tags":[
        "equipment",
        "material",
        "good",
        "-",
        "handling"
    ],
    "wof:name":"Se.l.a. Legni (s.r.l.)",
    "wof:placetype":"venue"
},
  "geometry": {"coordinates":[13.864278,41.525822],"type":"Point"}
}