{
  "type": "Feature",
  "properties": {
    "iso:country":"IT",
    "sg:address":"Via Barchetto 46048 Roverbella",
    "sg:city":"Roverbella",
    "sg:classifiers":[
        {
            "category":"Manufacturing",
            "subcategory":"Food",
            "type":"Manufacturing & Wholesale Goods"
        }
    ],
    "sg:phone":"+39 0376 694138",
    "sg:postcode":"46048",
    "sg:province":"Mantova",
    "sg:tags":[
        "equipment",
        "processing",
        "-",
        "machinery"
    ],
    "wof:name":"Costruzioni Tecniche (s.r.l.)",
    "wof:placetype":"venue"
},
  "geometry": {"coordinates":[10.7744483948,45.2621269226],"type":"Point"}
}