{
  "type": "Feature",
  "properties": {
    "iso:country":"IT",
    "sg:address":"65121 Pescara",
    "sg:city":"Pescara",
    "sg:orig_category":"Arredo Camera Letto E Complementi",
    "sg:phone":"+39 085 378203",
    "sg:postcode":"65121",
    "sg:province":"Pescara",
    "wof:name":"Nido D'oro",
    "wof:placetype":"venue"
},
  "geometry": {"coordinates":[14.212867,42.463982],"type":"Point"}
}