{
  "type": "Feature",
  "properties": {
    "addr:full":"20121 Milano Milano Milano 20121",
    "addr:postcode":"20121;20121",
    "iso:country":"IT",
    "sg:address":"20121 Milano",
    "sg:city":"Milano",
    "sg:orig_category":"Banche E Servizi Finanziari",
    "sg:phone":"+39 02 865251",
    "sg:postcode":"20121",
    "sg:province":"Milano",
    "wof:name":"C.c.f. Chartehouse S.p.a.",
    "wof:placetype":"venue"
},
  "geometry": {"coordinates":[9.187298,45.467804],"type":"Point"}
}