{
  "type": "Feature",
  "properties": {
    "addr:full":"Via Guido Rossa 34 20066 Melzo Melzo Milano 20066",
    "addr:housenumber":"34",
    "addr:postcode":"20066;20066",
    "addr:street":"Via Guido Rossa",
    "iso:country":"IT",
    "sg:address":"Via Guido Rossa 34 20066 Melzo",
    "sg:city":"Melzo",
    "sg:classifiers":[
        {
            "category":"Manufacturing",
            "subcategory":"Electronics",
            "type":"Manufacturing & Wholesale Goods"
        }
    ],
    "sg:phone":"+39 02 9573 6202",
    "sg:postcode":"20066",
    "sg:province":"Milano",
    "sg:tags":[
        "industrial",
        "cable"
    ],
    "wof:name":"Moba Srl",
    "wof:placetype":"venue"
},
  "geometry": {"coordinates":[9.415351,45.490257],"type":"Point"}
}