{
  "type": "Feature",
  "properties": {
    "addr:full":"Via G. Verdi, 1/2 40067 Rastignano Rastignano Bologna 40067",
    "addr:housenumber":"1 / 2",
    "addr:postcode":"40067;rastignano bologna 40067",
    "addr:street":"Via G. Verdi",
    "iso:country":"IT",
    "sg:address":"Via G. Verdi, 1/2 40067 Rastignano",
    "sg:city":"Rastignano",
    "sg:classifiers":[
        {
            "category":"Wholesale",
            "subcategory":"Vending Machines",
            "type":"Manufacturing & Wholesale Goods"
        }
    ],
    "sg:phone":"+39 051 744100",
    "sg:postcode":"40067",
    "sg:province":"Bologna",
    "sg:tags":[
        "packing",
        "wrapping",
        "enveloping"
    ],
    "wof:name":"O.a.m. Spa",
    "wof:placetype":"venue"
},
  "geometry": {"coordinates":[11.34984,44.422493],"type":"Point"}
}