{
  "type": "Feature",
  "properties": {
    "iso:country":"IT",
    "sg:address":"20154 Milano",
    "sg:city":"Milano",
    "sg:orig_category":"Apparecchiature Ed Attrezzature Meccaniche. Ricambi E Componenti Dei Mezzi Di Trasporto",
    "sg:phone":"+39 02 3360 8274",
    "sg:postcode":"20154",
    "sg:province":"Milano",
    "wof:name":"Nuova Raim Di Ramaioli Luca",
    "wof:placetype":"venue"
},
  "geometry": {"coordinates":[9.17131,45.481037],"type":"Point"}
}