{
  "type": "Feature",
  "properties": {
    "iso:country":"IT",
    "sg:address":"55/a, Via Campigliano 50012 Bagno A Ripoli",
    "sg:city":"Bagno a Ripoli",
    "sg:classifiers":[
        {
            "category":"Shopping",
            "subcategory":"Clothing, Apparel, & Fashions",
            "type":"Retail Goods"
        }
    ],
    "sg:phone":"+39 39055640757",
    "sg:postcode":"50012",
    "sg:province":"Firenze",
    "sg:tags":[
        "clothes"
    ],
    "wof:name":"Masini",
    "wof:placetype":"venue"
},
  "geometry": {"coordinates":[11.292947,43.734119],"type":"Point"}
}