{
  "type": "Feature",
  "properties": {
    "iso:country":"IT",
    "sg:address":"16143 Genova",
    "sg:city":"Genova",
    "sg:orig_category":"Carni, Salumi E Pesci",
    "sg:phone":"+39 010 518353",
    "sg:postcode":"16143",
    "sg:province":"Genova",
    "wof:name":"Polleria M.d. Di Moretti E Dalzini",
    "wof:placetype":"venue"
},
  "geometry": {"coordinates":[8.658443,44.402184],"type":"Point"}
}