{
  "type": "Feature",
  "properties": {
    "iso:country":"IT",
    "sg:address":"27024 Cilavegna",
    "sg:city":"Cilavegna",
    "sg:orig_category":"Accessori Moda D'abbigliamento. Forniture Per Abbigliamento E Pelletterie",
    "sg:phone":"+39 0381 96255",
    "sg:postcode":"27024",
    "sg:province":"Pavia",
    "wof:name":"Fa.ci Di Falzoni Luigi & C. (s.n.c.)",
    "wof:placetype":"venue"
},
  "geometry": {"coordinates":[9.137515,45.160103],"type":"Point"}
}