{
  "type": "Feature",
  "properties": {
    "iso:country":"IT",
    "sg:address":"34/a, V. Rivolta 56029 S. Croce Sull'arno",
    "sg:classifiers":[
        {
            "category":"Manufacturing",
            "subcategory":"Textiles",
            "type":"Manufacturing & Wholesale Goods"
        }
    ],
    "sg:phone":"+39 39057132258",
    "sg:postcode":"56029",
    "sg:province":"Pisa",
    "sg:tags":[
        "leather",
        "raw",
        "material",
        "-"
    ],
    "sg:website":"http://www.soldani.it",
    "wof:name":"Officina Meccanica Soldani",
    "wof:placetype":"venue"
},
  "geometry": {"coordinates":[10.396585,43.716137],"type":"Point"}
}