{
  "type": "Feature",
  "properties": {
    "iso:country":"IT",
    "sg:address":"64021 Giulianova",
    "sg:city":"Giulianova",
    "sg:orig_category":"Macchine Ed Impianti Per Edilizia E Lavori Pubblici",
    "sg:phone":"+39 085 800 3118",
    "sg:postcode":"64021",
    "sg:province":"Teramo",
    "wof:name":"Sonda Cementi S.a.s.",
    "wof:placetype":"venue"
},
  "geometry": {"coordinates":[13.963192,42.758907],"type":"Point"}
}