{
  "type": "Feature",
  "properties": {
    "iso:country":"IT",
    "sg:address":"00192 Roma",
    "sg:city":"Roma",
    "sg:orig_category":"Servizi Vari Di Interesse Pubblico",
    "sg:phone":"+39 06 3972 3975",
    "sg:postcode":"00192",
    "sg:province":"Roma",
    "wof:name":"Il Maestro Ludovico",
    "wof:placetype":"venue"
},
  "geometry": {"coordinates":[12.453125,41.907364],"type":"Point"}
}