{
  "type": "Feature",
  "properties": {
    "iso:country":"IT",
    "sg:address":"Piazza Umberto I 31; Nogara; 37054",
    "sg:city":"Nogara",
    "sg:classifiers":[
        {
            "category":"Banks & Credit Unions",
            "subcategory":"Bank",
            "type":"Services"
        }
    ],
    "sg:phone":"+39 0442 88122",
    "sg:postcode":"37054",
    "sg:province":"Verona",
    "wof:name":"Cariverona Banca Spa",
    "wof:placetype":"venue"
},
  "geometry": {"coordinates":[11.060049,45.178482],"type":"Point"}
}