{
  "type": "Feature",
  "properties": {
    "iso:country":"IT",
    "sg:address":"Via Genova 12100 Cuneo",
    "sg:city":"Cuneo",
    "sg:classifiers":[
        {
            "category":"Professional",
            "subcategory":"Engineering",
            "type":"Services"
        }
    ],
    "sg:phone":"+39 0171 346293",
    "sg:postcode":"12100",
    "sg:province":"Cuneo",
    "sg:tags":[
        "machine",
        "-",
        "mechanical"
    ],
    "wof:name":"Ambrogio Luigi & Figli (s.n.c.)",
    "wof:placetype":"venue"
},
  "geometry": {"coordinates":[7.592999,44.382206],"type":"Point"}
}