{
  "type": "Feature",
  "properties": {
    "iso:country":"IT",
    "sg:address":"80122 Napoli",
    "sg:city":"Chiaia",
    "sg:orig_category":"Materiali E Componenti Elettrotecnici",
    "sg:phone":"+39 081 680596",
    "sg:postcode":"80122",
    "sg:province":"Napoli",
    "wof:name":"Elettrostore Srl",
    "wof:placetype":"venue"
},
  "geometry": {"coordinates":[14.227293,40.832787],"type":"Point"}
}