{
  "type": "Feature",
  "properties": {
    "addr:full":"22030 Proserpio Proserpio Como 22030",
    "addr:postcode":"22030;22030",
    "iso:country":"IT",
    "sg:address":"22030 Proserpio",
    "sg:city":"Proserpio",
    "sg:orig_category":"Elettrotecnica Industriale, Prodotti E Apparecchiature",
    "sg:phone":"+39 031 622191",
    "sg:postcode":"22030",
    "sg:province":"Como",
    "wof:name":"Officina Meccanica Franchi Emilio Snc",
    "wof:placetype":"venue"
},
  "geometry": {"coordinates":[9.2489366531,45.8277549744],"type":"Point"}
}