{
  "type": "Feature",
  "properties": {
    "addr:full":"Piazza Della Liberta 18; Appiano Gentile; 22070 Appiano Gentile Como 22070",
    "addr:housenumber":"18",
    "addr:postcode":"22070;22070",
    "addr:street":"Piazza Della Liberta;Gentile",
    "iso:country":"IT",
    "sg:address":"Piazza Della Liberta 18; Appiano Gentile; 22070",
    "sg:city":"Appiano Gentile",
    "sg:classifiers":[
        {
            "category":"Banks & Credit Unions",
            "subcategory":"Bank",
            "type":"Services"
        }
    ],
    "sg:phone":"+39 031 890521",
    "sg:postcode":"22070",
    "sg:province":"Como",
    "wof:name":"Credito Italiano Spa",
    "wof:placetype":"venue"
},
  "geometry": {"coordinates":[8.97927,45.734829],"type":"Point"}
}