{
  "type": "Feature",
  "properties": {
    "addr:full":"5, Via Decorati Al Valor Civile 41100 Modena Modena Modena 41100",
    "addr:postcode":"41100;41100",
    "addr:street":"Via Decorati Al Valor Civile",
    "iso:country":"IT",
    "sg:address":"5, Via Decorati Al Valor Civile 41100 Modena",
    "sg:city":"Modena",
    "sg:classifiers":[
        {
            "category":"Real Estate",
            "subcategory":"Surveying",
            "type":"Services"
        }
    ],
    "sg:phone":"+39 39059511686",
    "sg:postcode":"41100",
    "sg:province":"Modena",
    "sg:tags":[
        "equipment",
        "material",
        "good",
        "-",
        "handling"
    ],
    "wof:name":"Euromont (s.r.l.)",
    "wof:placetype":"venue"
},
  "geometry": {"coordinates":[10.86446,44.610073],"type":"Point"}
}