{
  "type": "Feature",
  "properties": {
    "iso:country":"IT",
    "sg:address":"20149 Milano",
    "sg:city":"Milano",
    "sg:orig_category":"Abbigliamento - Vendita Al Dettaglio",
    "sg:phone":"+39 02 4851 7744",
    "sg:postcode":"20149",
    "sg:province":"Milano",
    "sg:website":"http://www.paginegialle.it/revolutiongroup",
    "wof:name":"Revolution Group",
    "wof:placetype":"venue"
},
  "geometry": {"coordinates":[9.143885,45.474545],"type":"Point"}
}