{
  "type": "Feature",
  "properties": {
    "addr:full":"21014 Laveno Mombello Laveno Varese 21014",
    "addr:postcode":"21014;21014",
    "iso:country":"IT",
    "sg:address":"21014 Laveno Mombello",
    "sg:city":"Laveno",
    "sg:orig_category":"Apparecchiature E Sistemi Per Magazzinaggio E Movimentazione",
    "sg:phone":"+39 0332 667591",
    "sg:postcode":"21014",
    "sg:province":"Varese",
    "wof:name":"Magic Gru S.n.c. Di Colombo Carlo E Colombo Gianni",
    "wof:placetype":"venue"
},
  "geometry": {"coordinates":[8.617407,45.917728],"type":"Point"}
}