{
  "type": "Feature",
  "properties": {
    "iso:country":"IT",
    "sg:address":"20122 Milano",
    "sg:city":"Milano",
    "sg:orig_category":"Musica",
    "sg:phone":"+39 02 780362",
    "sg:postcode":"20122",
    "sg:province":"Milano",
    "wof:name":"Bosoni (s.r.l.)",
    "wof:placetype":"venue"
},
  "geometry": {"coordinates":[9.2047510147,45.4675979614],"type":"Point"}
}