{
  "type": "Feature",
  "properties": {
    "iso:country":"IT",
    "sg:address":"10073 Cirie'",
    "sg:orig_category":"Tessuti E Stoffe. Forniture Per Attivita' Industriali",
    "sg:phone":"+39 011 921 1673",
    "sg:postcode":"10073",
    "sg:province":"Torino",
    "wof:name":"Universal Insulating (s.r.l.)",
    "wof:placetype":"venue"
},
  "geometry": {"coordinates":[7.594856,45.225658],"type":"Point"}
}