{
  "type": "Feature",
  "properties": {
    "iso:country":"IT",
    "sg:address":"00187 Roma",
    "sg:city":"Roma",
    "sg:orig_category":"Serramenti Ed Infissi. Forniture Industriali Per Prevenzione, Controllo E Sicurezza",
    "sg:phone":"+39 06 483925",
    "sg:postcode":"00187",
    "sg:province":"Roma",
    "wof:name":"Pietrini F. Lli Snc",
    "wof:placetype":"venue"
},
  "geometry": {"coordinates":[12.488451,41.902596],"type":"Point"}
}