{
  "type": "Feature",
  "properties": {
    "iso:country":"IT",
    "sg:address":"52027 San Giovanni Valdarno",
    "sg:city":"San Giovanni Valdarno",
    "sg:orig_category":"Prodotti Alimentari. Agricoltura, Orticoltura E Floricoltura",
    "sg:phone":"+39 055 912 1249",
    "sg:postcode":"52027",
    "sg:province":"Arezzo",
    "wof:name":"Bartoli Claudio",
    "wof:placetype":"venue"
},
  "geometry": {"coordinates":[11.5236091614,43.5621566772],"type":"Point"}
}