{
  "type": "Feature",
  "properties": {
    "iso:country":"IT",
    "sg:address":"36, Via Chiari 25033 Cologne",
    "sg:city":"Cologne",
    "sg:classifiers":[
        {
            "category":"Professional",
            "subcategory":"Engineering",
            "type":"Services"
        }
    ],
    "sg:phone":"+39 030 705 8211",
    "sg:postcode":"25033",
    "sg:province":"Brescia",
    "sg:tags":[
        "machine",
        "-",
        "mechanical"
    ],
    "wof:name":"Coram S.p.a.",
    "wof:placetype":"venue"
},
  "geometry": {"coordinates":[9.984098,45.583237],"type":"Point"}
}