{
  "type": "Feature",
  "properties": {
    "iso:country":"IT",
    "sg:address":"Via Vecchia Madonna Dello Sterpeto1 70051 Barletta",
    "sg:city":"Barletta",
    "sg:orig_category":"Ladies' Shoes",
    "sg:phone":"+39 0883 333502",
    "sg:postcode":"70051",
    "sg:province":"Bari",
    "wof:name":"Calzaturificio Games Sport S.r.l.",
    "wof:placetype":"venue"
},
  "geometry": {"coordinates":[16.869291,41.126053],"type":"Point"}
}