{
  "type": "Feature",
  "properties": {
    "iso:country":"IT",
    "sg:address":"3/a, P. Masi 06081 Assisi",
    "sg:city":"Assisi",
    "sg:classifiers":[
        {
            "category":"Parking",
            "subcategory":"Lot",
            "type":"Transportation"
        }
    ],
    "sg:phone":"+39 075 803 0128",
    "sg:postcode":"06081",
    "sg:province":"Perugia",
    "sg:tags":[
        "transport",
        "road"
    ],
    "sg:website":"http://www.nuovanaof.it",
    "wof:name":"Nuova N.a.o.f. Srl",
    "wof:placetype":"venue"
},
  "geometry": {"coordinates":[12.535823,43.102924],"type":"Point"}
}