{
  "type": "Feature",
  "properties": {
    "iso:country":"IT",
    "sg:address":"20154 Milano",
    "sg:city":"Milano",
    "sg:orig_category":"Cinematografia E Radiotelevisione",
    "sg:phone":"+39 02 3310 6624",
    "sg:postcode":"20154",
    "sg:province":"Milano",
    "wof:name":"Mixal Snc",
    "wof:placetype":"venue"
},
  "geometry": {"coordinates":[9.179523,45.480507],"type":"Point"}
}