{
  "type": "Feature",
  "properties": {
    "iso:country":"IT",
    "sg:address":"21, Via Battistig Romeo 33100 Udine",
    "sg:city":"Udine",
    "sg:classifiers":[
        {
            "category":"Sports & Exercise",
            "subcategory":"Playing Field",
            "type":"Entertainment"
        }
    ],
    "sg:phone":"+39 0432 507101",
    "sg:postcode":"33100",
    "sg:province":"Udine",
    "sg:tags":[
        "game"
    ],
    "wof:name":"Di Bernardo Import S.r.l.",
    "wof:placetype":"venue"
},
  "geometry": {"coordinates":[13.230724,46.064941],"type":"Point"}
}