{
  "type": "Feature",
  "properties": {
    "iso:country":"IT",
    "sg:address":"Via Istria 3 36027 Rosa'",
    "sg:classifiers":[
        {
            "category":"Wholesale",
            "subcategory":"Vending Machines",
            "type":"Manufacturing & Wholesale Goods"
        }
    ],
    "sg:phone":"+39 0424 581572",
    "sg:postcode":"36027",
    "sg:province":"Vicenza",
    "sg:tags":[
        "carpentry"
    ],
    "wof:name":"Lorenzin Giuseppe",
    "wof:placetype":"venue"
},
  "geometry": {"coordinates":[11.734613,45.697834],"type":"Point"}
}