{
  "type": "Feature",
  "properties": {
    "iso:country":"IT",
    "sg:address":"20097 San Donato Milanese",
    "sg:city":"San Donato Milanese",
    "sg:orig_category":"Vetrerie Per Uso Chimico E Farmaceutico",
    "sg:phone":"+39 02 5560 1240",
    "sg:postcode":"20097",
    "sg:province":"Milano",
    "wof:name":"Sicas Snc",
    "wof:placetype":"venue"
},
  "geometry": {"coordinates":[9.256701,45.413094],"type":"Point"}
}