{
  "type": "Feature",
  "properties": {
    "addr:full":"12, Via Piubega 46040 Ceresara Ceresara Mantova 46040",
    "addr:postcode":"46040;46040",
    "addr:street":"Via Piubega",
    "iso:country":"IT",
    "sg:address":"12, Via Piubega 46040 Ceresara",
    "sg:city":"Ceresara",
    "sg:classifiers":[
        {
            "category":"Shopping",
            "subcategory":"Clothing, Apparel, & Fashions",
            "type":"Retail Goods"
        }
    ],
    "sg:phone":"+39 39037687028",
    "sg:postcode":"46040",
    "sg:province":"Mantova",
    "sg:tags":[
        "clothes"
    ],
    "wof:name":"Lotus Calze (s.n.c.)",
    "wof:placetype":"venue"
},
  "geometry": {"coordinates":[10.558399,45.255486],"type":"Point"}
}