{
  "type": "Feature",
  "properties": {
    "iso:country":"IT",
    "sg:address":"10154 Torino",
    "sg:city":"Torino",
    "sg:orig_category":"Forniture Per Attivita' Commerciali Ed Artigianali. Pubblicita', Marketing E Comunicazione",
    "sg:phone":"+39 011 242 4223",
    "sg:postcode":"10154",
    "sg:province":"Torino",
    "sg:website":"http://www.novaselar.com",
    "wof:name":"Nova Selar Srl",
    "wof:placetype":"venue"
},
  "geometry": {"coordinates":[7.6968603134,45.0951843262],"type":"Point"}
}