{
  "type": "Feature",
  "properties": {
    "iso:country":"IT",
    "sg:address":"165, Via Agusta 21017 Samarate",
    "sg:city":"Samarate",
    "sg:classifiers":[
        {
            "category":"Manufacturing",
            "subcategory":"Lumber",
            "type":"Manufacturing & Wholesale Goods"
        }
    ],
    "sg:phone":"+39 0331 220434",
    "sg:postcode":"21017",
    "sg:province":"Varese",
    "sg:tags":[
        "wood"
    ],
    "wof:name":"Sartori Sergio",
    "wof:placetype":"venue"
},
  "geometry": {"coordinates":[8.762604,45.630569],"type":"Point"}
}