{
  "type": "Feature",
  "properties": {
    "addr:full":"32/b, Via Fossano 12041 Bene Vagienna Bene Vagienna Cuneo 12041",
    "addr:housenumber":"32 / b",
    "addr:postcode":"12041;12041",
    "addr:street":"Via Fossano",
    "iso:country":"IT",
    "sg:address":"32/b, Via Fossano 12041 Bene Vagienna",
    "sg:city":"Bene Vagienna",
    "sg:classifiers":[
        {
            "category":"Manufacturing",
            "subcategory":"Food",
            "type":"Manufacturing & Wholesale Goods"
        }
    ],
    "sg:phone":"+39 0172 654755",
    "sg:postcode":"12041",
    "sg:province":"Cuneo",
    "sg:tags":[
        "equipment",
        "processing",
        "-",
        "machinery"
    ],
    "wof:name":"Anselmo S.r.l.",
    "wof:placetype":"venue"
},
  "geometry": {"coordinates":[7.7541589737,44.4695625305],"type":"Point"}
}