{
  "type": "Feature",
  "properties": {
    "iso:country":"IT",
    "sg:address":"20068 Peschiera Borromeo",
    "sg:city":"Peschiera Borromeo",
    "sg:orig_category":"Indirizzi Commerciali",
    "sg:phone":"+39 02 5530 1854",
    "sg:postcode":"20068",
    "sg:province":"Milano",
    "wof:name":"Gruppo Galli",
    "wof:placetype":"venue"
},
  "geometry": {"coordinates":[9.285807,45.429497],"type":"Point"}
}