{
  "type": "Feature",
  "properties": {
    "iso:country":"IT",
    "sg:address":"21052 Busto Arsizio",
    "sg:city":"Busto Arsizio",
    "sg:orig_category":"Forniture Per Abbigliamento E Pelletterie. Forniture Per Attivita' Commerciali Ed Artigianali",
    "sg:phone":"+39 0331 679481",
    "sg:postcode":"21052",
    "sg:province":"Varese",
    "wof:name":"Cucirini Industriali Luisa Snc Di Bardella Luisa & C.",
    "wof:placetype":"venue"
},
  "geometry": {"coordinates":[8.8385820389,45.6140556335],"type":"Point"}
}