{
  "type": "Feature",
  "properties": {
    "iso:country":"IT",
    "sg:address":"16030 Avegno",
    "sg:city":"Avegno",
    "sg:orig_category":"Valvole E Apparecchiature Di Misura. Apparecchiature E Sistemi Per Imballaggio E Confezionamento",
    "sg:phone":"+39 0185 79412",
    "sg:postcode":"16030",
    "sg:province":"Genova",
    "wof:name":"Tenco S.n.c. Di Giuseppe Tenco E C.",
    "wof:placetype":"venue"
},
  "geometry": {"coordinates":[9.104316,44.371201],"type":"Point"}
}