{
  "type": "Feature",
  "properties": {
    "iso:country":"IT",
    "sg:address":"160, Via Xxv Luglio 84013 Cava De' Tirreni",
    "sg:classifiers":[
        {
            "category":"Manufacturing",
            "subcategory":"Metals",
            "type":"Manufacturing & Wholesale Goods"
        }
    ],
    "sg:phone":"+39 39089344633",
    "sg:postcode":"84013",
    "sg:province":"Salerno",
    "sg:tags":[
        "processing"
    ],
    "wof:name":"Me.de.a. (s.p.a.)",
    "wof:placetype":"venue"
},
  "geometry": {"coordinates":[14.765912056,40.6779556274],"type":"Point"}
}