{
  "type": "Feature",
  "properties": {
    "iso:country":"IT",
    "sg:address":"20052 Monza",
    "sg:city":"Monza",
    "sg:orig_category":"Arredamenti - Vendita Al Dettaglio",
    "sg:phone":"+39 039 390 0804",
    "sg:postcode":"20052",
    "sg:province":"Milano",
    "sg:website":"http://www.camerettaonline.it",
    "wof:name":"Dr Design - Cameretta On Line",
    "wof:placetype":"venue"
},
  "geometry": {"coordinates":[9.2929,45.590889],"type":"Point"}
}