{
  "type": "Feature",
  "properties": {
    "addr:full":"00185 Roma Roma Roma 00185",
    "addr:postcode":"00185;00185",
    "iso:country":"IT",
    "sg:address":"00185 Roma",
    "sg:city":"Roma",
    "sg:orig_category":"Trasporti E Spedizioni Merci",
    "sg:phone":"+39 06 446 0240",
    "sg:postcode":"00185",
    "sg:province":"Roma",
    "wof:name":"G.t.s. General Transport System Srl",
    "wof:placetype":"venue"
},
  "geometry": {"coordinates":[12.513995,41.900055],"type":"Point"}
}