{
  "type": "Feature",
  "properties": {
    "iso:country":"IT",
    "sg:address":"33076 Pravisdomini",
    "sg:city":"Pravisdomini",
    "sg:orig_category":"Diamanti Industriali",
    "sg:phone":"+39 0434 644934",
    "sg:postcode":"33076",
    "sg:province":"Pordenone",
    "sg:website":"http://www.nordest-group.it",
    "wof:name":"Nord Est Snc Di Battiston & Visintin",
    "wof:placetype":"venue"
},
  "geometry": {"coordinates":[12.681712,45.809216],"type":"Point"}
}