{
  "type": "Feature",
  "properties": {
    "iso:country":"IT",
    "sg:address":"10032 Brandizzo",
    "sg:city":"Brandizzo",
    "sg:orig_category":"Servizi E Lavori Per Industria Alimentare E Bevande",
    "sg:phone":"+39 011 913 9123",
    "sg:postcode":"10032",
    "sg:province":"Torino",
    "wof:name":"Macinazione Di Brandizzo (s.p.a.)",
    "wof:placetype":"venue"
},
  "geometry": {"coordinates":[7.837663,45.174076],"type":"Point"}
}