{
  "type": "Feature",
  "properties": {
    "addr:full":"24040 Misano Di Gera D'adda Bergamo 24040",
    "addr:postcode":"24040;24040",
    "iso:country":"IT",
    "sg:address":"24040 Misano Di Gera D'adda",
    "sg:orig_category":"Materiali E Componenti Elettrotecnici",
    "sg:phone":"+39 036 384626",
    "sg:postcode":"24040",
    "sg:province":"Bergamo",
    "wof:name":"Isocom (s.r.l.)",
    "wof:placetype":"venue"
},
  "geometry": {"coordinates":[9.619514,45.468987],"type":"Point"}
}