{
  "type": "Feature",
  "properties": {
    "iso:country":"IT",
    "sg:address":"Via Colombo 130 21055 Gorla Minore",
    "sg:city":"Gorla Minore",
    "sg:classifiers":[
        {
            "category":"Manufacturing",
            "subcategory":"Tools & Machinery",
            "type":"Manufacturing & Wholesale Goods"
        }
    ],
    "sg:phone":"+39 0331 604417",
    "sg:postcode":"21055",
    "sg:province":"Varese",
    "sg:tags":[
        "machine",
        "hosiery",
        "knitting",
        "accessory"
    ],
    "sg:website":"www.ntsrl.it",
    "wof:name":"Nt New Technologies Srl",
    "wof:placetype":"venue"
},
  "geometry": {"coordinates":[8.826385,45.817604],"type":"Point"}
}