{
  "type": "Feature",
  "properties": {
    "addr:full":"18039 Ventimiglia Ventimiglia Imperia 18039",
    "addr:postcode":"18039;18039",
    "iso:country":"IT",
    "sg:address":"18039 Ventimiglia",
    "sg:city":"Ventimiglia",
    "sg:orig_category":"Motori Ed Organi Di Trasmissione. Ricambi E Componenti Dei Mezzi Di Trasporto",
    "sg:phone":"+39 0184 294378",
    "sg:postcode":"18039",
    "sg:province":"Imperia",
    "wof:name":"Dinielli Autoricambi Snc Di Costantino E Flavio Dinielli",
    "wof:placetype":"venue"
},
  "geometry": {"coordinates":[8.0395393372,43.8952293396],"type":"Point"}
}