{
  "type": "Feature",
  "properties": {
    "addr:full":"00145 Roma Roma Roma 00145",
    "addr:postcode":"00145;00145",
    "iso:country":"IT",
    "sg:address":"00145 Roma",
    "sg:city":"Roma",
    "sg:classifiers":[
        {
            "category":"Home & Garden",
            "subcategory":"Building Materials",
            "type":"Retail Goods"
        }
    ],
    "sg:phone":"+39 06 594 2461",
    "sg:postcode":"00145",
    "sg:province":"Roma",
    "sg:tags":[
        "window",
        "door",
        "frame"
    ],
    "wof:name":"Security House Snc",
    "wof:placetype":"venue"
},
  "geometry": {"coordinates":[12.484943,41.850658],"type":"Point"}
}