{
  "type": "Feature",
  "properties": {
    "iso:country":"IT",
    "sg:address":"Via Sernaglia 20 31010 Farra Di Soligo",
    "sg:city":"Farra di Soligo",
    "sg:classifiers":[
        {
            "category":"Government",
            "subcategory":"Court House",
            "type":"Public Place"
        }
    ],
    "sg:phone":"+39 0438 900123",
    "sg:postcode":"31010",
    "sg:province":"Treviso",
    "sg:tags":[
        "accommodation",
        "furniture"
    ],
    "sg:website":"www.morassutti-play.it",
    "wof:name":"Play Srl",
    "wof:placetype":"venue"
},
  "geometry": {"coordinates":[12.242072,45.666286],"type":"Point"}
}