{
  "type": "Feature",
  "properties": {
    "addr:full":"90, Via Mappano 10071 Borgaro Torinese Borgaro Torinese Torino 10071",
    "addr:postcode":"10071;10071",
    "addr:street":"Via Mappano",
    "iso:country":"IT",
    "sg:address":"90, Via Mappano 10071 Borgaro Torinese",
    "sg:city":"Borgaro Torinese",
    "sg:classifiers":[
        {
            "category":"Parking",
            "subcategory":"Lot",
            "type":"Transportation"
        }
    ],
    "sg:phone":"+39 011 262 4389",
    "sg:postcode":"10071",
    "sg:province":"Torino",
    "sg:tags":[
        "transport",
        "road"
    ],
    "wof:name":"S.t.m. Sollevamento Trasporto Macchinari (s.r.l.)",
    "wof:placetype":"venue"
},
  "geometry": {"coordinates":[7.694977,45.15023],"type":"Point"}
}