{
  "type": "Feature",
  "properties": {
    "iso:country":"IT",
    "sg:address":"13835 Trivero",
    "sg:city":"Trivero",
    "sg:orig_category":"Arredo Cucina Ed Elettrodomestici",
    "sg:phone":"+39 015 738 8472",
    "sg:postcode":"13835",
    "sg:province":"Biella",
    "sg:website":"http://www.intercom.it/alternativa",
    "wof:name":"Alternativa Sas",
    "wof:placetype":"venue"
},
  "geometry": {"coordinates":[8.076365,45.587189],"type":"Point"}
}