{
  "type": "Feature",
  "properties": {
    "addr:full":"14, Via Del Commercio 36065 Mussolente Mussolente Vicenza 36065",
    "addr:postcode":"36065;36065",
    "addr:street":"Via Del Commercio",
    "iso:country":"IT",
    "sg:address":"14, Via Del Commercio 36065 Mussolente",
    "sg:city":"Mussolente",
    "sg:classifiers":[
        {
            "category":"Manufacturing",
            "subcategory":"Metals",
            "type":"Manufacturing & Wholesale Goods"
        }
    ],
    "sg:phone":"+39 0424 578026",
    "sg:postcode":"36065",
    "sg:province":"Vicenza",
    "sg:tags":[
        "processing"
    ],
    "wof:name":"Silver Shine S.r.l.",
    "wof:placetype":"venue"
},
  "geometry": {"coordinates":[11.8085355759,45.7652015686],"type":"Point"}
}