{
  "type": "Feature",
  "properties": {
    "iso:country":"IT",
    "sg:address":"252, Corso Genova 27029 Vigevano",
    "sg:city":"Vigevano",
    "sg:classifiers":[
        {
            "category":"Professional",
            "subcategory":"Engineering",
            "type":"Services"
        }
    ],
    "sg:phone":"+39 0381 346616",
    "sg:postcode":"27029",
    "sg:province":"Pavia",
    "sg:tags":[
        "machine",
        "-",
        "mechanical"
    ],
    "wof:name":"F.i.m.a.s. (s.r.l.)",
    "wof:placetype":"venue"
},
  "geometry": {"coordinates":[8.854099,45.282627],"type":"Point"}
}