{
  "type": "Feature",
  "properties": {
    "iso:country":"IT",
    "sg:address":"00191 Roma",
    "sg:city":"Roma",
    "sg:orig_category":"Calzature, Pelletterie E Pelli. Servizi E Lavori Per Abbigliamento E Pelletterie",
    "sg:phone":"+39 06 333 0243",
    "sg:postcode":"00191",
    "sg:province":"Roma",
    "wof:name":"Bruno Vincenzo",
    "wof:placetype":"venue"
},
  "geometry": {"coordinates":[12.475497,41.947796],"type":"Point"}
}