{
  "type": "Feature",
  "properties": {
    "iso:country":"IT",
    "sg:address":"00182 Roma",
    "sg:city":"Roma",
    "sg:orig_category":"Automazione E Macchine Per Ufficio. Forniture Industriali Per Prevenzione, Controllo E Sicurezza",
    "sg:phone":"+39 06 702 0451",
    "sg:postcode":"00182",
    "sg:province":"Roma",
    "wof:name":"Essebi Snc",
    "wof:placetype":"venue"
},
  "geometry": {"coordinates":[12.517733,41.883858],"type":"Point"}
}