{
  "type": "Feature",
  "properties": {
    "addr:full":"7, Via Della Fonte 56020 Santa Maria A Monte Santa Maria a Monte Pisa 56020",
    "addr:postcode":"56020;56020",
    "addr:street":"Via Della Fonte;Maria A Monte Pisa",
    "iso:country":"IT",
    "sg:address":"7, Via Della Fonte 56020 Santa Maria A Monte",
    "sg:city":"Santa Maria a Monte",
    "sg:classifiers":[
        {
            "category":"Personal",
            "subcategory":"Shoe Repair & Shine",
            "type":"Services"
        }
    ],
    "sg:phone":"+39 0587 704004",
    "sg:postcode":"56020",
    "sg:province":"Pisa",
    "sg:tags":[
        "leather"
    ],
    "wof:name":"Solettificio Maffei Mila Snc",
    "wof:placetype":"venue"
},
  "geometry": {"coordinates":[10.68707,43.699875],"type":"Point"}
}