{
  "type": "Feature",
  "properties": {
    "addr:full":"95030 Nicolosi Nicolosi Catania 95030",
    "addr:postcode":"95030;95030",
    "iso:country":"IT",
    "sg:address":"95030 Nicolosi",
    "sg:city":"Nicolosi",
    "sg:orig_category":"Funivie, Sciovie E Impianti Di Risalita - Societa' Di Esercizio",
    "sg:phone":"+39 095 911158",
    "sg:postcode":"95030",
    "sg:province":"Catania",
    "wof:name":"Sitas Spa Funivia Dell'etna",
    "wof:placetype":"venue"
},
  "geometry": {"coordinates":[15.0697288513,37.57604599],"type":"Point"}
}