{
  "type": "Feature",
  "properties": {
    "addr:full":"22, Via Provinciale La Novedratese 22060 Novedrate Novedrate Como 22060",
    "addr:postcode":"22060;22060",
    "addr:street":"Via Provinciale La Novedratese",
    "iso:country":"IT",
    "sg:address":"22, Via Provinciale La Novedratese 22060 Novedrate",
    "sg:city":"Novedrate",
    "sg:classifiers":[
        {
            "category":"Manufacturing",
            "subcategory":"Metals",
            "type":"Manufacturing & Wholesale Goods"
        }
    ],
    "sg:phone":"+39 39031790853",
    "sg:postcode":"22060",
    "sg:province":"Como",
    "sg:tags":[
        "processing"
    ],
    "wof:name":"Tecnometal 90 Snc Di Tagliabue Dario & C.",
    "wof:placetype":"venue"
},
  "geometry": {"coordinates":[9.0854558945,45.8119659424],"type":"Point"}
}