{
  "type": "Feature",
  "properties": {
    "iso:country":"IT",
    "sg:address":"00153 Roma",
    "sg:city":"Roma",
    "sg:orig_category":"Servizi Culturali E Per Lo Spettacolo. Servizi Al Turismo. Acqua, Luce, Gas E Societa' Di Esercizio Pubblico",
    "sg:phone":"+39 06 581 4651",
    "sg:postcode":"00153",
    "sg:province":"Roma",
    "wof:name":"Centro Studi Emigrazione",
    "wof:placetype":"venue"
},
  "geometry": {"coordinates":[12.466862,41.883492],"type":"Point"}
}