{
  "type": "Feature",
  "properties": {
    "addr:full":"Corso Italia 49, 20122 Milan, Mi Milano 20122",
    "addr:housenumber":"49",
    "addr:postcode":"20122;20122",
    "addr:street":"Corso Italia",
    "iso:country":"IT",
    "sg:address":"Corso Italia 49, 20122 Milan, Mi",
    "sg:classifiers":[
        {
            "category":"Banks & Credit Unions",
            "subcategory":"Bank",
            "type":"Services"
        }
    ],
    "sg:postcode":"20122",
    "sg:province":"Milano",
    "wof:name":"Banca Profilo Spa",
    "wof:placetype":"venue"
},
  "geometry": {"coordinates":[9.186852,45.45269],"type":"Point"}
}