{
  "type": "Feature",
  "properties": {
    "iso:country":"IT",
    "sg:address":"Via Dell'industria 1 33086 Montereale Valcellina",
    "sg:city":"Montereale Valcellina",
    "sg:classifiers":[
        {
            "category":"Home & Garden",
            "subcategory":"Garden Supply",
            "type":"Retail Goods"
        }
    ],
    "sg:phone":"+39 0427 734411",
    "sg:postcode":"33086",
    "sg:province":"Pordenone",
    "sg:website":"www.uniflexutiltime.com",
    "wof:name":"Uniflex Utiltime Spa",
    "wof:placetype":"venue"
},
  "geometry": {"coordinates":[12.655044,45.96265],"type":"Point"}
}