{
  "type": "Feature",
  "properties": {
    "addr:full":"21055 Gorla Minore Gorla Minore Varese 21055",
    "addr:postcode":"21055;21055",
    "iso:country":"IT",
    "sg:address":"21055 Gorla Minore",
    "sg:city":"Gorla Minore",
    "sg:orig_category":"Fonderie Alluminio",
    "sg:phone":"+39 0331 601821",
    "sg:postcode":"21055",
    "sg:province":"Varese",
    "wof:name":"Foam Di Gatti Ettore",
    "wof:placetype":"venue"
},
  "geometry": {"coordinates":[8.9101724625,45.6388168335],"type":"Point"}
}