{
  "type": "Feature",
  "properties": {
    "iso:country":"IT",
    "sg:address":"10149 Torino",
    "sg:city":"Torino",
    "sg:orig_category":"Elettrotecnica Industriale, Prodotti E Apparecchiature. Forniture Per Attivita' Commerciali Ed Artigianali",
    "sg:postcode":"10149",
    "sg:province":"Torino",
    "wof:name":"Neon - Ferraro",
    "wof:placetype":"venue"
},
  "geometry": {"coordinates":[7.660723,45.100567],"type":"Point"}
}