{
  "type": "Feature",
  "properties": {
    "iso:country":"IT",
    "sg:address":"33048 S. Giovanni Natisone",
    "sg:orig_category":"Furnishings And Accessories, Bathroom. Household Appliances",
    "sg:phone":"+39 0432 756482",
    "sg:postcode":"33048",
    "sg:province":"Udine",
    "wof:name":"Ideal Termo Bagno Srl",
    "wof:placetype":"venue"
},
  "geometry": {"coordinates":[13.3886299133,45.9777679443],"type":"Point"}
}