{
  "type": "Feature",
  "properties": {
    "addr:full":"20019 Settimo Milanese Settimo Milanese Milano 20019",
    "addr:postcode":"20019;20019",
    "iso:country":"IT",
    "sg:address":"20019 Settimo Milanese",
    "sg:city":"Settimo Milanese",
    "sg:orig_category":"Forniture Per Abbigliamento E Pelletterie",
    "sg:phone":"+39 02 328 7677",
    "sg:postcode":"20019",
    "sg:province":"Milano",
    "wof:name":"D.w. Shop Snc Di Daniela E Wilma Bologna",
    "wof:placetype":"venue"
},
  "geometry": {"coordinates":[9.0552377701,45.4802284241],"type":"Point"}
}