{
  "type": "Feature",
  "properties": {
    "iso:country":"IT",
    "sg:address":"46, Localita' Crocioni 37012 Bussolengo",
    "sg:city":"Bussolengo",
    "sg:classifiers":[
        {
            "category":"Shopping",
            "subcategory":"Computers & Home Electronics",
            "type":"Retail Goods"
        }
    ],
    "sg:phone":"+39 045 676 0211",
    "sg:postcode":"37012",
    "sg:province":"Verona",
    "sg:tags":[
        "electronic",
        "electrical",
        "equipment"
    ],
    "wof:name":"Jenbacher S.r.l.",
    "wof:placetype":"venue"
},
  "geometry": {"coordinates":[10.846523,45.445652],"type":"Point"}
}