{
  "type": "Feature",
  "properties": {
    "addr:full":"83030 Torre Le Nocelle Torre le Nocelle Avellino 83030",
    "addr:postcode":"83030;83030",
    "addr:street":"Le Nocelle Avellino",
    "iso:country":"IT",
    "sg:address":"83030 Torre Le Nocelle",
    "sg:city":"Torre le Nocelle",
    "sg:orig_category":"Articoli Funerari",
    "sg:phone":"+39 0825 969052",
    "sg:postcode":"83030",
    "sg:province":"Avellino",
    "wof:name":"Onoranze Funebri De Cristofaro Michelina Snc",
    "wof:placetype":"venue"
},
  "geometry": {"coordinates":[14.912879,41.0196],"type":"Point"}
}