{
  "type": "Feature",
  "properties": {
    "iso:country":"IT",
    "sg:address":"13030 Caresanablot",
    "sg:city":"Caresanablot",
    "sg:orig_category":"Ospedali E Servizi Sanitari",
    "sg:phone":"+39 0161 234800",
    "sg:postcode":"13030",
    "sg:province":"Vercelli",
    "sg:website":"http://www.puntoservice.org",
    "wof:name":"Punto Service Soc.coop.r.l.",
    "wof:placetype":"venue"
},
  "geometry": {"coordinates":[8.388285,45.357548],"type":"Point"}
}