{
  "type": "Feature",
  "properties": {
    "addr:full":"00137 Roma Roma Roma 00137",
    "addr:postcode":"00137;00137",
    "iso:country":"IT",
    "sg:address":"00137 Roma",
    "sg:city":"Roma",
    "sg:classifiers":[
        {
            "category":"Home & Garden",
            "subcategory":"Building Materials",
            "type":"Retail Goods"
        }
    ],
    "sg:phone":"+39 06 8200 2101",
    "sg:postcode":"00137",
    "sg:province":"Roma",
    "sg:tags":[
        "window",
        "door",
        "frame"
    ],
    "wof:name":"Baltera Sas Di Claudio Baltera & C.",
    "wof:placetype":"venue"
},
  "geometry": {"coordinates":[12.570031,41.950829],"type":"Point"}
}