{
  "type": "Feature",
  "properties": {
    "iso:country":"IT",
    "sg:address":"16, Via Sardegna 40024 Castel San Pietro Terme",
    "sg:city":"Castel San Pietro Terme",
    "sg:classifiers":[
        {
            "category":"Professional",
            "subcategory":"Engineering",
            "type":"Services"
        }
    ],
    "sg:phone":"+39 39051946869",
    "sg:postcode":"40024",
    "sg:province":"Bologna",
    "sg:tags":[
        "machine",
        "-",
        "mechanical"
    ],
    "wof:name":"Inn.tec. (s.r.l.)",
    "wof:placetype":"venue"
},
  "geometry": {"coordinates":[11.522553,44.43454],"type":"Point"}
}