{
  "type": "Feature",
  "properties": {
    "iso:country":"IT",
    "sg:address":"Piazza Marconi 35; Bagnolo Cremasco; 35023",
    "sg:classifiers":[
        {
            "category":"Banks & Credit Unions",
            "subcategory":"Bank",
            "type":"Services"
        }
    ],
    "sg:phone":"+39 049 538 0034",
    "sg:postcode":"35023",
    "sg:province":"Padova",
    "wof:name":"Banca Popolare Veneta",
    "wof:placetype":"venue"
},
  "geometry": {"coordinates":[11.900247,45.1772],"type":"Point"}
}