{
  "type": "Feature",
  "properties": {
    "addr:full":"10078 Venaria Torino 10078",
    "addr:postcode":"10078;10078",
    "iso:country":"IT",
    "sg:address":"10078 Venaria",
    "sg:orig_category":"Utensili Meccanici E Materiali",
    "sg:phone":"+39 011 455 7986",
    "sg:postcode":"10078",
    "sg:province":"Torino",
    "wof:name":"Exp S.r.l.",
    "wof:placetype":"venue"
},
  "geometry": {"coordinates":[7.649751,45.113831],"type":"Point"}
}