{
  "type": "Feature",
  "properties": {
    "iso:country":"IT",
    "sg:address":"30122 Venezia",
    "sg:city":"Castello",
    "sg:orig_category":"Accessori Moda D'abbigliamento. Forniture Per Abbigliamento E Pelletterie",
    "sg:phone":"+39 041 523 5485",
    "sg:postcode":"30122",
    "sg:province":"Venezia",
    "wof:name":"Lace & Linen S.r.l.",
    "wof:placetype":"venue"
},
  "geometry": {"coordinates":[12.340962,45.435192],"type":"Point"}
}