{
  "type": "Feature",
  "properties": {
    "iso:country":"IT",
    "sg:address":"25040 Corte Franca",
    "sg:city":"Corte Franca",
    "sg:orig_category":"Carni, Salumi E Pesci",
    "sg:phone":"+39 030 982 8298",
    "sg:postcode":"25040",
    "sg:province":"Brescia",
    "sg:website":"http://www.salumificiodifranciacorta.it",
    "wof:name":"Salumificio Di Franciacorta Industria Alimentare Srl",
    "wof:placetype":"venue"
},
  "geometry": {"coordinates":[9.989232,45.631023],"type":"Point"}
}