{
  "type": "Feature",
  "properties": {
    "iso:country":"IT",
    "sg:address":"70031 Andria",
    "sg:city":"Andria",
    "sg:orig_category":"Servizi E Lavori Industria Della Gomma. Servizi E Lavori Industria Delle Materie Plastiche. Forniture Per Edilizia E Lavori Pubblici",
    "sg:phone":"+39 0883 595843",
    "sg:postcode":"70031",
    "sg:province":"Bari",
    "wof:name":"S.a.r.p.i.c. Dei Fratelli Coratella",
    "wof:placetype":"venue"
},
  "geometry": {"coordinates":[16.298706,41.230267],"type":"Point"}
}