{
  "type": "Feature",
  "properties": {
    "iso:country":"IT",
    "sg:address":"Via Roma 31; Nocera",
    "sg:classifiers":[
        {
            "category":"Banks & Credit Unions",
            "subcategory":"Bank",
            "type":"Services"
        }
    ],
    "sg:phone":"+39 081 517 6017",
    "wof:name":"Banca Di Roma",
    "wof:placetype":"venue"
},
  "geometry": {"coordinates":[14.638693,40.744663],"type":"Point"}
}