{
  "type": "Feature",
  "properties": {
    "iso:country":"IT",
    "sg:address":"59013 Montemurlo",
    "sg:city":"Montemurlo",
    "sg:orig_category":"Abbigliamento Esterno, Maglierie E Pelliccerie. Calzature, Pelletterie E Pelli",
    "sg:phone":"+39 0574 650692",
    "sg:postcode":"59013",
    "sg:province":"Prato",
    "wof:name":"Lady V. (s.a.s.)",
    "wof:placetype":"venue"
},
  "geometry": {"coordinates":[11.050394,43.9128],"type":"Point"}
}