{
  "type": "Feature",
  "properties": {
    "addr:full":"80013 Casalnuovo Di Napoli Casalnuovo di Napoli Napoli 80013",
    "addr:postcode":"80013;80013",
    "iso:country":"IT",
    "sg:address":"80013 Casalnuovo Di Napoli",
    "sg:city":"Casalnuovo di Napoli",
    "sg:orig_category":"Macchine, Impianti E Forniture Per Industria Grafica, Cartaria E Cartotecnica. Automazione E Macchine Per Ufficio",
    "sg:phone":"+39 081 842 7377",
    "sg:postcode":"80013",
    "sg:province":"Napoli",
    "wof:name":"Geomedia 3 Srl",
    "wof:placetype":"venue"
},
  "geometry": {"coordinates":[14.346478,40.901367],"type":"Point"}
}