{
  "type": "Feature",
  "properties": {
    "iso:country":"IT",
    "sg:address":"68, Viale Certosa 27100 Pavia",
    "sg:city":"Pavia",
    "sg:classifiers":[
        {
            "category":"Communications",
            "subcategory":"Newspaper",
            "type":"Services"
        }
    ],
    "sg:phone":"+39 0382 529461",
    "sg:postcode":"27100",
    "sg:province":"Pavia",
    "sg:tags":[
        "advertising"
    ],
    "wof:name":"Promo Service Marketing S.r.l.",
    "wof:placetype":"venue"
},
  "geometry": {"coordinates":[9.143092,45.219563],"type":"Point"}
}