{
  "type": "Feature",
  "properties": {
    "addr:full":"65012 Cepagatti Cepagatti Pescara 65012",
    "addr:postcode":"65012;65012",
    "iso:country":"IT",
    "sg:address":"65012 Cepagatti",
    "sg:city":"Cepagatti",
    "sg:orig_category":"Prodotti E Manufatti In Gomma",
    "sg:phone":"+39 085 974790",
    "sg:postcode":"65012",
    "sg:province":"Pescara",
    "wof:name":"Ecogomma S.r.l.",
    "wof:placetype":"venue"
},
  "geometry": {"coordinates":[14.1059408188,42.3631401062],"type":"Point"}
}