{
  "type": "Feature",
  "properties": {
    "iso:country":"IT",
    "sg:address":"123, Via Stazione 21020 Mornago",
    "sg:city":"Mornago",
    "sg:classifiers":[
        {
            "category":"Shopping",
            "subcategory":"Crafts & Fabrics",
            "type":"Retail Goods"
        }
    ],
    "sg:phone":"+39 0331 900111",
    "sg:postcode":"21020",
    "sg:province":"Varese",
    "sg:tags":[
        "linen"
    ],
    "wof:name":"Gabel Industria Tessile S.p.a.",
    "wof:placetype":"venue"
},
  "geometry": {"coordinates":[8.7293558121,45.7293243408],"type":"Point"}
}