{
  "type": "Feature",
  "properties": {
    "addr:full":"20156 Milano Milano Milano 20156",
    "addr:postcode":"20156;20156",
    "iso:country":"IT",
    "sg:address":"20156 Milano",
    "sg:city":"Milano",
    "sg:orig_category":"Motori Ed Organi Di Trasmissione. Ricambi E Componenti Dei Mezzi Di Trasporto",
    "sg:phone":"+39 02 3340 0600",
    "sg:postcode":"20156",
    "sg:province":"Milano",
    "wof:name":"Cbc Colombo Brugnoni & Co (s.p.a.)",
    "wof:placetype":"venue"
},
  "geometry": {"coordinates":[9.134976387,45.5027770996],"type":"Point"}
}