{
  "type": "Feature",
  "properties": {
    "iso:country":"IT",
    "sg:address":"18038 Sanremo",
    "sg:orig_category":"Serramenti Ed Infissi",
    "sg:phone":"+39 0184 531074",
    "sg:postcode":"18038",
    "sg:province":"Imperia",
    "wof:name":"Calabria Romualdo Tecnostil",
    "wof:placetype":"venue"
},
  "geometry": {"coordinates":[7.77427,43.841179],"type":"Point"}
}