{
  "type": "Feature",
  "properties": {
    "addr:full":"13, Via Sondrio 10144 Torino Torino Torino 10144",
    "addr:postcode":"10144;10144",
    "addr:street":"Via Sondrio",
    "iso:country":"IT",
    "sg:address":"13, Via Sondrio 10144 Torino",
    "sg:city":"Torino",
    "sg:classifiers":[
        {
            "category":"Professional",
            "subcategory":"Business Services",
            "type":"Services"
        }
    ],
    "sg:phone":"+39 011 437 0111",
    "sg:postcode":"10144",
    "sg:province":"Torino",
    "sg:tags":[
        "advice"
    ],
    "wof:name":"Linear System S.r.l.",
    "wof:placetype":"venue"
},
  "geometry": {"coordinates":[7.659828,45.08543],"type":"Point"}
}