{
  "type": "Feature",
  "properties": {
    "iso:country":"IT",
    "sg:address":"20145 Milano",
    "sg:city":"Milano",
    "sg:orig_category":"Prodotti E Manufatti In Gomma",
    "sg:phone":"+39 02 481 4042",
    "sg:postcode":"20145",
    "sg:province":"Milano",
    "sg:website":"http://www.belfiorenautica.it",
    "wof:name":"Belfiore Nautica Gomma Plast Di Chiodo Angelo",
    "wof:placetype":"venue"
},
  "geometry": {"coordinates":[9.1592569351,45.4673194885],"type":"Point"}
}