{
  "type": "Feature",
  "properties": {
    "iso:country":"IT",
    "sg:address":"20052 Monza",
    "sg:city":"Monza",
    "sg:classifiers":[
        {
            "category":"Communications",
            "subcategory":"Film & Video Production",
            "type":"Services"
        }
    ],
    "sg:phone":"+39 039 20441",
    "sg:postcode":"20052",
    "sg:province":"Milano",
    "sg:tags":[
        "semi-finished",
        "materials",
        "metal"
    ],
    "sg:website":"http://www.ims.it",
    "wof:name":"Ims Spa",
    "wof:placetype":"venue"
},
  "geometry": {"coordinates":[9.2319984436,45.5485725403],"type":"Point"}
}