{
  "type": "Feature",
  "properties": {
    "iso:country":"IT",
    "sg:address":"15, Via Piave 20045 Besana In Brianza",
    "sg:city":"Besana in Brianza",
    "sg:classifiers":[
        {
            "category":"Manufacturing",
            "subcategory":"Food",
            "type":"Manufacturing & Wholesale Goods"
        }
    ],
    "sg:phone":"+39 036 299 5110",
    "sg:postcode":"20045",
    "sg:province":"Milano",
    "sg:tags":[
        "equipment",
        "processing",
        "-",
        "machinery"
    ],
    "wof:name":"Moriondo Snc",
    "wof:placetype":"venue"
},
  "geometry": {"coordinates":[9.2304115295,45.6898994446],"type":"Point"}
}