{
  "type": "Feature",
  "properties": {
    "iso:country":"IT",
    "sg:address":"25064 Gussago",
    "sg:city":"Gussago",
    "sg:orig_category":"Gioielleria, Oreficeria E Argenteria. Articoli Da Regalo. Shopping",
    "sg:phone":"+39 030 321104",
    "sg:postcode":"25064",
    "sg:province":"Brescia",
    "wof:name":"Crescini Fratelli Snc",
    "wof:placetype":"venue"
},
  "geometry": {"coordinates":[10.155905,45.558277],"type":"Point"}
}