{
  "type": "Feature",
  "properties": {
    "addr:full":"Localita' Comero 25070 Casto Casto Brescia 25070",
    "addr:postcode":"25070;25070",
    "addr:street":"Localita ' Comero",
    "iso:country":"IT",
    "sg:address":"Localita' Comero 25070 Casto",
    "sg:city":"Casto",
    "sg:classifiers":[
        {
            "category":"Manufacturing",
            "subcategory":"Metals",
            "type":"Manufacturing & Wholesale Goods"
        }
    ],
    "sg:phone":"+39 39036588166",
    "sg:postcode":"25070",
    "sg:province":"Brescia",
    "sg:tags":[
        "processing"
    ],
    "wof:name":"Brecom Di Brescianini Pietro E C. (s.n.c.)",
    "wof:placetype":"venue"
},
  "geometry": {"coordinates":[10.2229576111,45.5398292542],"type":"Point"}
}