{
  "type": "Feature",
  "properties": {
    "iso:country":"IT",
    "sg:address":"Via Moretta 7 12030 Scarnafigi",
    "sg:city":"Scarnafigi",
    "sg:classifiers":[
        {
            "category":"Food & Beverages",
            "subcategory":"Cheese",
            "type":"Retail Goods"
        }
    ],
    "sg:phone":"+39 0175 274784",
    "sg:postcode":"12030",
    "sg:province":"Cuneo",
    "sg:tags":[
        "hard"
    ],
    "sg:website":"www.valgrana.com",
    "wof:name":"Valgrana Spa",
    "wof:placetype":"venue"
},
  "geometry": {"coordinates":[7.571042,44.72789],"type":"Point"}
}