{
  "type": "Feature",
  "properties": {
    "iso:country":"IT",
    "sg:address":"09131 Cagliari",
    "sg:city":"Cagliari",
    "sg:orig_category":"Centri Di Estetica E Cosmesi E Servizi",
    "sg:phone":"+39 070 520542",
    "sg:postcode":"09131",
    "sg:province":"Cagliari",
    "wof:name":"Idem For Lady Di Carta Anastasia",
    "wof:placetype":"venue"
},
  "geometry": {"coordinates":[9.127629,39.232998],"type":"Point"}
}