{
  "type": "Feature",
  "properties": {
    "iso:country":"IT",
    "sg:address":"Area Industriale Calaggio 83046 Lacedonia",
    "sg:city":"Lacedonia",
    "sg:classifiers":[
        {
            "category":"Autos & Motor Vehicles",
            "subcategory":"Auto Supplies",
            "type":"Retail Goods"
        }
    ],
    "sg:phone":"+39 0827 85667",
    "sg:postcode":"83046",
    "sg:province":"Avellino",
    "sg:tags":[
        "interior",
        "covering"
    ],
    "wof:name":"Liquid Packaging International L.p.i. Srl",
    "wof:placetype":"venue"
},
  "geometry": {"coordinates":[15.37108,41.079128],"type":"Point"}
}