{
  "type": "Feature",
  "properties": {
    "addr:full":"95013 Fiumefreddo Sicilia Catania 95013",
    "addr:postcode":"95013;95013",
    "addr:street":"Fiumefreddo Sicilia",
    "iso:country":"IT",
    "sg:address":"95013 Fiumefreddo Sicilia",
    "sg:orig_category":"Alimentare E Conserviera Industria - Macchine",
    "sg:phone":"+39 095 642026",
    "sg:postcode":"95013",
    "sg:province":"Catania",
    "wof:name":"Nicotra Francesco",
    "wof:placetype":"venue"
},
  "geometry": {"coordinates":[14.84159,37.291153],"type":"Point"}
}