{
  "type": "Feature",
  "properties": {
    "addr:full":"40128 Bologna Bologna Bologna 40128",
    "addr:postcode":"40128;40128",
    "iso:country":"IT",
    "sg:address":"40128 Bologna",
    "sg:city":"Bologna",
    "sg:orig_category":"Informatica - Consulenza E Servizi. Pubblicita', Marketing E Comunicazione",
    "sg:phone":"+39 051 638 8614",
    "sg:postcode":"40128",
    "sg:province":"Bologna",
    "sg:website":"http://www.powerstation.it",
    "wof:name":"Digibyte Srl",
    "wof:placetype":"venue"
},
  "geometry": {"coordinates":[11.351789,44.531921],"type":"Point"}
}