{
  "type": "Feature",
  "properties": {
    "addr:full":"34122 Trieste Trieste Trieste 34122",
    "addr:postcode":"34122;34122",
    "iso:country":"IT",
    "sg:address":"34122 Trieste",
    "sg:city":"Trieste",
    "sg:orig_category":"Amministrazioni Immobiliari",
    "sg:phone":"+39 040 631338",
    "sg:postcode":"34122",
    "sg:province":"Trieste",
    "wof:name":"Amministrazione Stabili Malabotti Di Bruna Malabotti",
    "wof:placetype":"venue"
},
  "geometry": {"coordinates":[13.774359,45.650349],"type":"Point"}
}