{
  "type": "Feature",
  "properties": {
    "addr:full":"10137 Torino Torino Torino 10137",
    "addr:postcode":"10137;10137",
    "iso:country":"IT",
    "sg:address":"10137 Torino",
    "sg:city":"Torino",
    "sg:orig_category":"Studi E Consulenze Tecniche E Industriali. Consulenze Tecniche, Amministrative E Perizie. Professionisti - Studi E Servizi Ed Associazioni Di Interesse Aziendale",
    "sg:phone":"+39 011 311 9219",
    "sg:postcode":"10137",
    "sg:province":"Torino",
    "wof:name":"Gentili Diego",
    "wof:placetype":"venue"
},
  "geometry": {"coordinates":[7.636516,45.035641],"type":"Point"}
}