{
  "type": "Feature",
  "properties": {
    "iso:country":"IT",
    "sg:address":"Via Fornari Pasquale 12/14 20146 Milano",
    "sg:city":"Milano",
    "sg:classifiers":[
        {
            "category":"Ferry Terminal",
            "type":"Transportation"
        }
    ],
    "sg:phone":"+39 02 403 9900",
    "sg:postcode":"20146",
    "sg:province":"Milano",
    "sg:tags":[
        "lens",
        "optical"
    ],
    "sg:website":"www.lobre.it",
    "wof:name":"Lobre S.r.l.",
    "wof:placetype":"venue"
},
  "geometry": {"coordinates":[9.143801,45.463463],"type":"Point"}
}