{
  "type": "Feature",
  "properties": {
    "iso:country":"IT",
    "sg:address":"04029 Sperlonga",
    "sg:city":"Sperlonga",
    "sg:orig_category":"Prodotti E Manufatti In Materie Plastiche",
    "sg:phone":"+39 0771 548137",
    "sg:postcode":"04029",
    "sg:province":"Latina",
    "wof:name":"Guviplastex",
    "wof:placetype":"venue"
},
  "geometry": {"coordinates":[13.4439105988,41.2574539185],"type":"Point"}
}