{
  "type": "Feature",
  "properties": {
    "iso:country":"IT",
    "sg:address":"50058 Signa",
    "sg:city":"Signa",
    "sg:orig_category":"Macchine, Impianti Ed Attrezzature Per Abbigliamento E Pelletterie",
    "sg:phone":"+39 055 873 5587",
    "sg:postcode":"50058",
    "sg:province":"Firenze",
    "wof:name":"Safi Macchine Maglieria S.r.l.",
    "wof:placetype":"venue"
},
  "geometry": {"coordinates":[11.128779,43.795982],"type":"Point"}
}