{
  "type": "Feature",
  "properties": {
    "addr:full":"16122 Genova Genova Genova 16122",
    "addr:postcode":"16122;16122",
    "iso:country":"IT",
    "sg:address":"16122 Genova",
    "sg:city":"Genova",
    "sg:orig_category":"Elaborazione Dati - Servizio Conto Terzi",
    "sg:phone":"+39 010 831 5722",
    "sg:postcode":"16122",
    "sg:province":"Genova",
    "wof:name":"Ferrara Rag. Stefano",
    "wof:placetype":"venue"
},
  "geometry": {"coordinates":[8.944764,44.413025],"type":"Point"}
}