{
  "type": "Feature",
  "properties": {
    "iso:country":"IT",
    "sg:address":"00189 Roma",
    "sg:city":"Roma",
    "sg:orig_category":"Impianti, Attrezzature E Forniture Sanitarie Ed Ospedaliere",
    "sg:phone":"+39 06 331 2057",
    "sg:postcode":"00189",
    "sg:province":"Roma",
    "wof:name":"Topphysio Srl",
    "wof:placetype":"venue"
},
  "geometry": {"coordinates":[12.38226,42.035652],"type":"Point"}
}