{
  "type": "Feature",
  "properties": {
    "iso:country":"IT",
    "sg:address":"28, V. Matteotti 21050 Cairate",
    "sg:city":"Cairate",
    "sg:classifiers":[
        {
            "category":"Real Estate",
            "subcategory":"Surveying",
            "type":"Services"
        }
    ],
    "sg:phone":"+39 0331 310770",
    "sg:postcode":"21050",
    "sg:province":"Varese",
    "sg:tags":[
        "equipment",
        "material",
        "good",
        "-",
        "handling"
    ],
    "sg:website":"http://www.grimasrl.it",
    "wof:name":"Grima Srl",
    "wof:placetype":"venue"
},
  "geometry": {"coordinates":[8.849866,45.693356],"type":"Point"}
}