{
  "type": "Feature",
  "properties": {
    "iso:country":"IT",
    "sg:address":"87, Corso Italia 12037 Saluzzo",
    "sg:city":"Saluzzo",
    "sg:classifiers":[
        {
            "category":"Professional",
            "subcategory":"Business Services",
            "type":"Services"
        }
    ],
    "sg:phone":"+39 39017544250",
    "sg:postcode":"12037",
    "sg:province":"Cuneo",
    "sg:tags":[
        "advice"
    ],
    "wof:name":"Fontana Centro Studi S.a.s.",
    "wof:placetype":"venue"
},
  "geometry": {"coordinates":[7.490136,44.645985],"type":"Point"}
}