{
  "type": "Feature",
  "properties": {
    "iso:country":"IT",
    "sg:address":"36021 Barbarano Vicentino",
    "sg:city":"Barbarano Vicentino",
    "sg:orig_category":"Macchine, Impianti Ed Attrezzature Per Industria Alimentare E Bevande",
    "sg:phone":"+39 0444 886111",
    "sg:postcode":"36021",
    "sg:province":"Vicenza",
    "wof:name":"Oleificio Berico Snc Di Menegatti Giuliano & C.",
    "wof:placetype":"venue"
},
  "geometry": {"coordinates":[11.550295,45.408123],"type":"Point"}
}