{
  "type": "Feature",
  "properties": {
    "iso:country":"IT",
    "sg:address":"35127 Camin",
    "sg:orig_category":"Servizi E Lavori Per Agricoltura E Zootecnia",
    "sg:phone":"+39 049 644486",
    "sg:postcode":"35127",
    "sg:province":"Padova",
    "wof:name":"Cognolato Francesco",
    "wof:placetype":"venue"
},
  "geometry": {"coordinates":[11.956699,45.384399],"type":"Point"}
}