{
  "type": "Feature",
  "properties": {
    "iso:country":"IT",
    "sg:address":"6, Via Calegreno 24012 Brembilla",
    "sg:city":"Brembilla",
    "sg:classifiers":[
        {
            "category":"Manufacturing",
            "subcategory":"Lumber",
            "type":"Manufacturing & Wholesale Goods"
        }
    ],
    "sg:phone":"+39 39034599387",
    "sg:postcode":"24012",
    "sg:province":"Bergamo",
    "sg:tags":[
        "wood"
    ],
    "wof:name":"Lodofin Spa",
    "wof:placetype":"venue"
},
  "geometry": {"coordinates":[9.601508,45.812424],"type":"Point"}
}