{
  "type": "Feature",
  "properties": {
    "iso:country":"IT",
    "sg:address":"95045 Misterbianco",
    "sg:city":"Misterbianco",
    "sg:orig_category":"Petroli, Gas E Combustibili",
    "sg:phone":"+39 095 471005",
    "sg:postcode":"95045",
    "sg:province":"Catania",
    "wof:name":"Caloroil (s.r.l.)",
    "wof:placetype":"venue"
},
  "geometry": {"coordinates":[15.028834343,37.5130653381],"type":"Point"}
}