{
  "type": "Feature",
  "properties": {
    "addr:full":"20123 Milano Milano Milano 20123",
    "addr:postcode":"20123;20123",
    "iso:country":"IT",
    "sg:address":"20123 Milano",
    "sg:city":"Milano",
    "sg:orig_category":"Pubblicita', Marketing E Comunicazione",
    "sg:phone":"+39 02 878784",
    "sg:postcode":"20123",
    "sg:province":"Milano",
    "wof:name":"Minghetti & Pieri Communication Srl",
    "wof:placetype":"venue"
},
  "geometry": {"coordinates":[9.182756424,45.4606513977],"type":"Point"}
}