{
  "type": "Feature",
  "properties": {
    "iso:country":"IT",
    "sg:address":"20, Strada Per Felizzano 15043 Fubine",
    "sg:city":"Fubine",
    "sg:classifiers":[
        {
            "category":"Professional",
            "subcategory":"Engineering",
            "type":"Services"
        }
    ],
    "sg:phone":"+39 0131 791683",
    "sg:postcode":"15043",
    "sg:province":"Alessandria",
    "sg:tags":[
        "machine",
        "-",
        "mechanical"
    ],
    "wof:name":"M.e.c.a.l. S.r.l.",
    "wof:placetype":"venue"
},
  "geometry": {"coordinates":[8.44128,44.949062],"type":"Point"}
}