{
  "type": "Feature",
  "properties": {
    "iso:country":"IT",
    "sg:address":"Via General Cantore 2; Chiusa San Michele; 10050",
    "sg:classifiers":[
        {
            "category":"Banks & Credit Unions",
            "subcategory":"Bank",
            "type":"Services"
        }
    ],
    "sg:phone":"+39 011 964 3332",
    "sg:postcode":"10050",
    "sg:province":"Torino",
    "wof:name":"Banca Sella Spa",
    "wof:placetype":"venue"
},
  "geometry": {"coordinates":[7.325917,45.103378],"type":"Point"}
}