{
  "type": "Feature",
  "properties": {
    "addr:full":"9, Via Tagliamento 59100 Prato Prato Prato 59100",
    "addr:postcode":"59100;59100",
    "addr:street":"Via Tagliamento",
    "iso:country":"IT",
    "sg:address":"9, Via Tagliamento 59100 Prato",
    "sg:city":"Prato",
    "sg:classifiers":[
        {
            "category":"Shopping",
            "subcategory":"Crafts & Fabrics",
            "type":"Retail Goods"
        }
    ],
    "sg:phone":"+39 0574 461710",
    "sg:postcode":"59100",
    "sg:province":"Prato",
    "wof:name":"C.m. Di Cassarini Fernando & C. (s.n.c.)",
    "wof:placetype":"venue"
},
  "geometry": {"coordinates":[11.0882034302,43.8982696533],"type":"Point"}
}