{
  "type": "Feature",
  "properties": {
    "addr:full":"73100 Lecce Lecce Lecce 73100",
    "addr:postcode":"73100;73100",
    "iso:country":"IT",
    "sg:address":"73100 Lecce",
    "sg:city":"Lecce",
    "sg:orig_category":"Agenzie Investigative",
    "sg:phone":"+39 0832 315094",
    "sg:postcode":"73100",
    "sg:province":"Lecce",
    "wof:name":"Aic Srl",
    "wof:placetype":"venue"
},
  "geometry": {"coordinates":[18.276882,40.316765],"type":"Point"}
}