{
  "type": "Feature",
  "properties": {
    "iso:country":"IT",
    "sg:address":"167, Circonvallazione Clodia 00195 Roma",
    "sg:city":"Roma",
    "sg:classifiers":[
        {
            "category":"Professional",
            "subcategory":"Advertising",
            "type":"Services"
        }
    ],
    "sg:phone":"+39 39063701818",
    "sg:postcode":"00195",
    "sg:province":"Roma",
    "sg:tags":[
        "communication",
        "medium"
    ],
    "wof:name":"A.a.a. Tony Ponzi Investigazioni S.r.l.",
    "wof:placetype":"venue"
},
  "geometry": {"coordinates":[12.457668,41.9212],"type":"Point"}
}