{
  "type": "Feature",
  "properties": {
    "iso:country":"IT",
    "sg:address":"31015 Conegliano",
    "sg:city":"Conegliano",
    "sg:orig_category":"Architetti - Studi",
    "sg:phone":"+39 0438 21577",
    "sg:postcode":"31015",
    "sg:province":"Treviso",
    "wof:name":"Del Missier Arch. Lorenzo",
    "wof:placetype":"venue"
},
  "geometry": {"coordinates":[12.301216,45.890625],"type":"Point"}
}