{
  "type": "Feature",
  "properties": {
    "iso:country":"IT",
    "sg:address":"25, Via Tinelli 54100 Massa",
    "sg:city":"Massa",
    "sg:classifiers":[
        {
            "category":"Professional",
            "subcategory":"Engineering",
            "type":"Services"
        }
    ],
    "sg:phone":"+39 39058542186",
    "sg:postcode":"54100",
    "sg:province":"Massa-Carrara",
    "sg:tags":[
        "machine",
        "-",
        "mechanical"
    ],
    "wof:name":"I.m.a.s. Stampi (s.a.s.)",
    "wof:placetype":"venue"
},
  "geometry": {"coordinates":[10.127439,44.038307],"type":"Point"}
}