{
  "type": "Feature",
  "properties": {
    "addr:full":"06012 Citta'dicastello Perugia 06012",
    "addr:postcode":"06012;06012",
    "iso:country":"IT",
    "sg:address":"06012 Citta'dicastello",
    "sg:orig_category":"Prodotti Chimici Secondari. Servizi E Lavori Per Ecologia E Smaltimento Rifiuti. Macchine E Forniture Per Ecologia E Smaltimento Rifiuti",
    "sg:phone":"+39 075 855 7956",
    "sg:postcode":"06012",
    "sg:province":"Perugia",
    "wof:name":"Depuratore So.ge.pu.- S.p.a.",
    "wof:placetype":"venue"
},
  "geometry": {"coordinates":[12.3188934326,43.0647125244],"type":"Point"}
}