{
  "type": "Feature",
  "properties": {
    "iso:country":"IT",
    "sg:address":"03042 Atina",
    "sg:city":"Atina",
    "sg:orig_category":"Vetrate Artistiche",
    "sg:phone":"+39 0776 691194",
    "sg:postcode":"03042",
    "sg:province":"Frosinone",
    "wof:name":"Antonio Simeone",
    "wof:placetype":"venue"
},
  "geometry": {"coordinates":[13.798648,41.620426],"type":"Point"}
}