{
  "type": "Feature",
  "properties": {
    "addr:full":"220, Via Zoe Fontana 00131 Roma Roma Roma 00131",
    "addr:housenumber":"220",
    "addr:postcode":"00131;00131",
    "addr:street":"Via Zoe Fontana",
    "iso:country":"IT",
    "sg:address":"220, Via Zoe Fontana 00131 Roma",
    "sg:city":"Roma",
    "sg:classifiers":[
        {
            "category":"Professional",
            "subcategory":"Computer Services",
            "type":"Services"
        }
    ],
    "sg:phone":"+39 06 4129 4922",
    "sg:postcode":"00131",
    "sg:province":"Roma",
    "sg:tags":[
        "information",
        "technology"
    ],
    "wof:name":"Itaco Srl",
    "wof:placetype":"venue"
},
  "geometry": {"coordinates":[12.609928,41.93214],"type":"Point"}
}