{
  "type": "Feature",
  "properties": {
    "iso:country":"IT",
    "sg:address":"Via Tonale E; Endine Gaiano; 24060",
    "sg:city":"Endine",
    "sg:classifiers":[
        {
            "category":"Banks & Credit Unions",
            "subcategory":"Bank",
            "type":"Services"
        }
    ],
    "sg:phone":"+39 035 826161",
    "sg:postcode":"24060",
    "sg:province":"Bergamo",
    "wof:name":"Istituto Bancario, San Paolo Di Torino Spa",
    "wof:placetype":"venue"
},
  "geometry": {"coordinates":[10.003973,45.7924],"type":"Point"}
}