{
  "type": "Feature",
  "properties": {
    "iso:country":"IT",
    "sg:address":"73047 Monteroni Di Lecce",
    "sg:city":"Monteroni di Lecce",
    "sg:classifiers":[
        {
            "category":"Manufacturing",
            "subcategory":"Leather Goods",
            "type":"Manufacturing & Wholesale Goods"
        }
    ],
    "sg:phone":"+39 0832 321996",
    "sg:postcode":"73047",
    "sg:province":"Lecce",
    "sg:tags":[
        "footwear",
        "skin"
    ],
    "wof:name":"Calzaturificio Fracap Srl",
    "wof:placetype":"venue"
},
  "geometry": {"coordinates":[18.0870075226,40.3216972351],"type":"Point"}
}