{
  "type": "Feature",
  "properties": {
    "iso:country":"IT",
    "sg:address":"Via Delle Molina 69 51017 Pescia",
    "sg:city":"Pescia",
    "sg:orig_category":"Pulp Works And Paper Mills, Turnkey",
    "sg:phone":"+39 0572 429053",
    "sg:postcode":"51017",
    "sg:province":"Pistoia",
    "sg:website":"www.meridianapro.it",
    "wof:name":"Massimiliano Corsini Srl",
    "wof:placetype":"venue"
},
  "geometry": {"coordinates":[10.6659946442,43.8829956055],"type":"Point"}
}