{
  "type": "Feature",
  "properties": {
    "iso:country":"IT",
    "sg:address":"50012 Grassina",
    "sg:orig_category":"Prodotti Di Base E Forniture Per Industria Alimentare E Bevande. Forniture Per Attivita' Commerciali Ed Artigianali",
    "sg:phone":"+39 055 640128",
    "sg:postcode":"50012",
    "sg:province":"Firenze",
    "wof:name":"Cono Firenze (s.n.c.)",
    "wof:placetype":"venue"
},
  "geometry": {"coordinates":[11.2959032059,43.7311286926],"type":"Point"}
}