{
  "type": "Feature",
  "properties": {
    "iso:country":"IT",
    "sg:address":"34, Via Solferino 20030 Seveso",
    "sg:city":"Seveso",
    "sg:classifiers":[
        {
            "category":"Professional",
            "subcategory":"Printing & Photocopies",
            "type":"Services"
        }
    ],
    "sg:phone":"+39 036 255 2186",
    "sg:postcode":"20030",
    "sg:province":"Milano",
    "wof:name":"New Press & C. (s.a.s.)",
    "wof:placetype":"venue"
},
  "geometry": {"coordinates":[9.1878452301,45.4772186279],"type":"Point"}
}