{
  "type": "Feature",
  "properties": {
    "iso:country":"IT",
    "sg:address":"84131 Salerno",
    "sg:city":"Salerno",
    "sg:orig_category":"Prodotti Vari In Metallo",
    "sg:phone":"+39 089 301230",
    "sg:postcode":"84131",
    "sg:province":"Salerno",
    "wof:name":"Metalrete",
    "wof:placetype":"venue"
},
  "geometry": {"coordinates":[14.8110122681,40.6624565125],"type":"Point"}
}