{
  "type": "Feature",
  "properties": {
    "addr:full":"Via Mantovana 104 45014 Porto Viro Porto Viro Rovigo 45014",
    "addr:housenumber":"104",
    "addr:postcode":"45014;45014",
    "addr:street":"Via Mantovana;Viro",
    "iso:country":"IT",
    "sg:address":"Via Mantovana 104 45014 Porto Viro",
    "sg:city":"Porto Viro",
    "sg:classifiers":[
        {
            "category":"Building & Trades",
            "subcategory":"Plumbing",
            "type":"Services"
        }
    ],
    "sg:phone":"+39 0426 321900",
    "sg:postcode":"45014",
    "sg:province":"Rovigo",
    "sg:tags":[
        "tank"
    ],
    "wof:name":"Vianello Inox S.p.a.",
    "wof:placetype":"venue"
},
  "geometry": {"coordinates":[12.217007,45.042992],"type":"Point"}
}