{
  "type": "Feature",
  "properties": {
    "addr:full":"Via Nazionale 20 33019 Tricesimo Tricesimo Udine 33019",
    "addr:housenumber":"20",
    "addr:postcode":"33019;33019",
    "addr:street":"Via Nazionale",
    "iso:country":"IT",
    "sg:address":"Via Nazionale 20 33019 Tricesimo",
    "sg:city":"Tricesimo",
    "sg:orig_category":"Furniture, General",
    "sg:phone":"+39 0432 851270",
    "sg:postcode":"33019",
    "sg:province":"Udine",
    "sg:website":"www.walcher.it",
    "wof:name":"Walcher Snc",
    "wof:placetype":"venue"
},
  "geometry": {"coordinates":[13.2245664597,46.1266479492],"type":"Point"}
}