{
  "type": "Feature",
  "properties": {
    "addr:full":"23033 Grosio Grosio Sondrio 23033",
    "addr:postcode":"23033;23033",
    "iso:country":"IT",
    "sg:address":"23033 Grosio",
    "sg:city":"Grosio",
    "sg:orig_category":"Forniture Per Edilizia E Lavori Pubblici",
    "sg:phone":"+39 0342 848201",
    "sg:postcode":"23033",
    "sg:province":"Sondrio",
    "wof:name":"Sassella Gian Paolo",
    "wof:placetype":"venue"
},
  "geometry": {"coordinates":[10.2801523209,46.3035354614],"type":"Point"}
}