{
  "type": "Feature",
  "properties": {
    "addr:full":"16121 Genova Genova Genova 16121",
    "addr:postcode":"16121;16121",
    "iso:country":"IT",
    "sg:address":"16121 Genova",
    "sg:city":"Genova",
    "sg:orig_category":"Forniture Per Attivita' Commerciali Ed Artigianali",
    "sg:phone":"+39 010 580631",
    "sg:postcode":"16121",
    "sg:province":"Genova",
    "wof:name":"Arte Della Medaglia Di Marco E Gabriella Benzo & C. Snc",
    "wof:placetype":"venue"
},
  "geometry": {"coordinates":[8.9397134781,44.4056282043],"type":"Point"}
}