{
  "type": "Feature",
  "properties": {
    "iso:country":"IT",
    "sg:address":"Via Vittime Di Piazza Fontana 38 10024 Moncalieri",
    "sg:city":"Moncalieri",
    "sg:classifiers":[
        {
            "category":"Arts & Performance",
            "subcategory":"Music",
            "type":"Entertainment"
        }
    ],
    "sg:phone":"+39 011 689 4611",
    "sg:postcode":"10024",
    "sg:province":"Torino",
    "sg:tags":[
        "pattern"
    ],
    "sg:website":"www.model-master.com",
    "wof:name":"Model Master Spa",
    "wof:placetype":"venue"
},
  "geometry": {"coordinates":[7.7259287834,44.9712295532],"type":"Point"}
}