{
  "type": "Feature",
  "properties": {
    "iso:country":"IT",
    "sg:address":"55040 Camaiore",
    "sg:orig_category":"Frigotecnica, Apparecchiature E Servizi",
    "sg:phone":"+39 0584 969601",
    "sg:postcode":"55040",
    "sg:province":"Lucca",
    "wof:name":"Fricom Srl",
    "wof:placetype":"venue"
},
  "geometry": {"coordinates":[10.2607927322,43.9018211365],"type":"Point"}
}