{
  "type": "Feature",
  "properties": {
    "addr:full":"81052 Pignataro Maggiore Pignataro Maggiore Caserta 81052",
    "addr:housenumber":"maggiore",
    "addr:postcode":"81052;81052",
    "addr:street":"Maggiore",
    "iso:country":"IT",
    "sg:address":"81052 Pignataro Maggiore",
    "sg:city":"Pignataro Maggiore",
    "sg:orig_category":"Stampaggio Metalli A Caldo",
    "sg:phone":"+39 0823 871666",
    "sg:postcode":"81052",
    "sg:province":"Caserta",
    "wof:name":"Tower Automotive Sud Srl",
    "wof:placetype":"venue"
},
  "geometry": {"coordinates":[14.158225,41.190727],"type":"Point"}
}