{
  "type": "Feature",
  "properties": {
    "addr:full":"31033 Castelfranco Veneto Castelfranco Veneto Treviso 31033",
    "addr:postcode":"31033;31033",
    "iso:country":"IT",
    "sg:address":"31033 Castelfranco Veneto",
    "sg:city":"Castelfranco Veneto",
    "sg:orig_category":"Articoli Medico-sanitari Ed Ortopedici. Impianti, Attrezzature E Forniture Sanitarie Ed Ospedaliere",
    "sg:phone":"+39 0423 492332",
    "sg:postcode":"31033",
    "sg:province":"Treviso",
    "wof:name":"G. & G. Di Gavriil Gerasimos E C. S.n.c.",
    "wof:placetype":"venue"
},
  "geometry": {"coordinates":[11.941913,45.672989],"type":"Point"}
}