{
  "type": "Feature",
  "properties": {
    "iso:country":"IT",
    "sg:address":"16121 Genova",
    "sg:city":"Genova",
    "sg:orig_category":"Servizi Di Magazzinaggio E Movimentazione",
    "sg:phone":"+39 010 57161",
    "sg:postcode":"16121",
    "sg:province":"Genova",
    "sg:website":"http://www.bossi-transiti.it",
    "wof:name":"Bossi & C. Transiti Spa",
    "wof:placetype":"venue"
},
  "geometry": {"coordinates":[8.941647,44.404625],"type":"Point"}
}