{
  "type": "Feature",
  "properties": {
    "addr:full":"87027 Paola Paola Cosenza 87027",
    "addr:postcode":"87027;87027",
    "iso:country":"IT",
    "sg:address":"87027 Paola",
    "sg:city":"Paola",
    "sg:orig_category":"Nautica. Automobili E Mezzi Di Trasporto",
    "sg:phone":"+39 338 813 7595",
    "sg:postcode":"87027",
    "sg:province":"Cosenza",
    "wof:name":"La Bubbazza Piccola Societ\u00c0",
    "wof:placetype":"venue"
},
  "geometry": {"coordinates":[16.052261,39.360771],"type":"Point"}
}