{
  "type": "Feature",
  "properties": {
    "iso:country":"IT",
    "sg:address":"24050 Orio Al Serio",
    "sg:city":"Orio al Serio",
    "sg:orig_category":"Servizi Al Turismo. Trasporto Pubblico E Privato",
    "sg:phone":"+39 035 330080",
    "sg:postcode":"24050",
    "sg:province":"Bergamo",
    "wof:name":"Flygroup (s.a.s)",
    "wof:placetype":"venue"
},
  "geometry": {"coordinates":[9.697451,45.665333],"type":"Point"}
}