{
  "type": "Feature",
  "properties": {
    "iso:country":"IT",
    "sg:address":"00144 Roma",
    "sg:city":"Roma",
    "sg:orig_category":"Finanziamenti E Mutui",
    "sg:phone":"+39 06 591 5844",
    "sg:postcode":"00144",
    "sg:province":"Roma",
    "wof:name":"Assifin Servizi Sas",
    "wof:placetype":"venue"
},
  "geometry": {"coordinates":[12.4574098587,41.8239364624],"type":"Point"}
}