{
  "type": "Feature",
  "properties": {
    "iso:country":"IT",
    "sg:address":"12084 Mondovi'",
    "sg:orig_category":"Banche E Servizi Finanziari",
    "sg:phone":"+39 0174 556305",
    "sg:postcode":"12084",
    "sg:province":"Cuneo",
    "wof:name":"Ge Capital Servizi Finanziari Srl",
    "wof:placetype":"venue"
},
  "geometry": {"coordinates":[7.816567,44.391541],"type":"Point"}
}