{
  "type": "Feature",
  "properties": {
    "iso:country":"IT",
    "sg:address":"22020 Cavallasca",
    "sg:city":"Cavallasca",
    "sg:orig_category":"Abbigliamento Intimo, Calze E Costumi Da Bagno. Accessori Moda D'abbigliamento",
    "sg:phone":"+39 031 211416",
    "sg:postcode":"22020",
    "sg:province":"Como",
    "wof:name":"Gemac S.n.c.",
    "wof:placetype":"venue"
},
  "geometry": {"coordinates":[9.036837,45.812416],"type":"Point"}
}