{
  "type": "Feature",
  "properties": {
    "iso:country":"IT",
    "sg:address":"17, Localita' Stein 39025 Naturno",
    "sg:city":"Naturno",
    "sg:classifiers":[
        {
            "category":"Food & Beverages",
            "subcategory":"Groceries & Convenience Stores",
            "type":"Retail Goods"
        }
    ],
    "sg:phone":"+39 0473 671011",
    "sg:postcode":"39025",
    "sg:province":"Bolzano/Bozen",
    "sg:tags":[
        "product",
        "related"
    ],
    "wof:name":"Moser S.r.l.",
    "wof:placetype":"venue"
},
  "geometry": {"coordinates":[11.35800457,46.4967155457],"type":"Point"}
}