{
  "type": "Feature",
  "properties": {
    "iso:country":"IT",
    "sg:address":"80022 Arzano",
    "sg:city":"Arzano",
    "sg:orig_category":"Arredi Ed Attrezzature Per Attivita' Commerciali Ed Artigianali",
    "sg:phone":"+39 081 731 3930",
    "sg:postcode":"80022",
    "sg:province":"Napoli",
    "wof:name":"Cuozzo Salvatore",
    "wof:placetype":"venue"
},
  "geometry": {"coordinates":[14.268666,40.914997],"type":"Point"}
}