{
  "type": "Feature",
  "properties": {
    "iso:country":"IT",
    "sg:address":"50018 Scandicci",
    "sg:city":"Scandicci",
    "sg:orig_category":"Macchine Utensili E Impianti. Elettrotecnica Industriale, Prodotti E Apparecchiature",
    "sg:phone":"+39 055 721667",
    "sg:postcode":"50018",
    "sg:province":"Firenze",
    "wof:name":"Catarzi Piero - Catrzi Elettrica",
    "wof:placetype":"venue"
},
  "geometry": {"coordinates":[11.151772,43.770195],"type":"Point"}
}