{
  "type": "Feature",
  "properties": {
    "iso:country":"IT",
    "sg:address":"22046 Merone",
    "sg:city":"Merone",
    "sg:orig_category":"Macchine E Forniture Per Arredamento E Industria Del Legno",
    "sg:phone":"+39 031 617997",
    "sg:postcode":"22046",
    "sg:province":"Como",
    "wof:name":"Canali Snc",
    "wof:placetype":"venue"
},
  "geometry": {"coordinates":[8.928926,45.788612],"type":"Point"}
}