{
  "type": "Feature",
  "properties": {
    "iso:country":"IT",
    "sg:address":"98123 Messina",
    "sg:city":"Messina",
    "sg:classifiers":[
        {
            "category":"Farming",
            "subcategory":"Livestock Farm",
            "type":"Manufacturing & Wholesale Goods"
        }
    ],
    "sg:phone":"+39 090 717967",
    "sg:postcode":"98123",
    "sg:province":"Messina",
    "sg:tags":[
        "equipment",
        "breeding",
        "agriculture",
        "machinery"
    ],
    "wof:name":"Antonio Amenta Snc Di Vincenzo & Alfredo Amenta",
    "wof:placetype":"venue"
},
  "geometry": {"coordinates":[15.551699,38.184437],"type":"Point"}
}