{
  "type": "Feature",
  "properties": {
    "iso:country":"IT",
    "sg:address":"90/f, Strada Statale Romana Sud 41012 Carpi",
    "sg:city":"Carpi",
    "sg:classifiers":[
        {
            "category":"Professional",
            "subcategory":"Engineering",
            "type":"Services"
        }
    ],
    "sg:phone":"+39 39059639411",
    "sg:postcode":"41012",
    "sg:province":"Modena",
    "sg:tags":[
        "machine",
        "-",
        "mechanical"
    ],
    "wof:name":"Angelo Po Grandi Cucine S.p.a.",
    "wof:placetype":"venue"
},
  "geometry": {"coordinates":[10.880321,44.74736],"type":"Point"}
}