{
  "type": "Feature",
  "properties": {
    "iso:country":"IT",
    "sg:address":"20031 Cesano Maderno",
    "sg:city":"Cesano Maderno",
    "sg:orig_category":"Materiali Edili",
    "sg:phone":"+39 036 255 3173",
    "sg:postcode":"20031",
    "sg:province":"Milano",
    "wof:name":"Elle-pi Di Lo Giudice Santo & C.",
    "wof:placetype":"venue"
},
  "geometry": {"coordinates":[9.186241,45.639065],"type":"Point"}
}