{
  "type": "Feature",
  "properties": {
    "addr:full":"21056 Induno Olona Induno Olona Varese 21056",
    "addr:postcode":"21056;21056",
    "iso:country":"IT",
    "sg:address":"21056 Induno Olona",
    "sg:city":"Induno Olona",
    "sg:orig_category":"Dolciumi E Gelati",
    "sg:phone":"+39 0332 209111",
    "sg:postcode":"21056",
    "sg:province":"Varese",
    "wof:name":"Lindt & Sprungli Spa",
    "wof:placetype":"venue"
},
  "geometry": {"coordinates":[8.824292,45.842758],"type":"Point"}
}