{
  "type": "Feature",
  "properties": {
    "addr:full":"28, Via Prampolini 43044 Collecchio Collecchio Parma 43044",
    "addr:postcode":"43044;43044",
    "addr:street":"Via Prampolini",
    "iso:country":"IT",
    "sg:address":"28, Via Prampolini 43044 Collecchio",
    "sg:city":"Collecchio",
    "sg:classifiers":[
        {
            "category":"Utilities",
            "subcategory":"Electric",
            "type":"Services"
        }
    ],
    "sg:phone":"+39 0521 804427",
    "sg:postcode":"43044",
    "sg:province":"Parma",
    "sg:tags":[
        "component",
        "electronic"
    ],
    "wof:name":"Alpha Elettronica S.r.l.",
    "wof:placetype":"venue"
},
  "geometry": {"coordinates":[10.260416,44.772263],"type":"Point"}
}