{
  "type": "Feature",
  "properties": {
    "addr:full":"Via Ciro Ferrari 16 37060 Caselle Di Sommacampagna Verona 37060",
    "addr:housenumber":"16",
    "addr:postcode":"37060;37060",
    "addr:street":"Via Ciro Ferrari",
    "iso:country":"IT",
    "sg:address":"Via Ciro Ferrari 16 37060 Caselle Di Sommacampagna",
    "sg:classifiers":[
        {
            "category":"Military Area",
            "subcategory":"Air Force Base",
            "type":"Public Place"
        }
    ],
    "sg:phone":"+39 045 829 5900",
    "sg:postcode":"37060",
    "sg:province":"Verona",
    "sg:tags":[
        "precast",
        "component",
        "concrete"
    ],
    "sg:website":"www.gecofin.it",
    "wof:name":"Gecofin Prefabricati Spa",
    "wof:placetype":"venue"
},
  "geometry": {"coordinates":[10.9032201767,45.4123916626],"type":"Point"}
}