{
  "type": "Feature",
  "properties": {
    "iso:country":"IT",
    "sg:address":"73044 Galatone",
    "sg:city":"Galatone",
    "sg:orig_category":"Accessori Dei Mezzi Di Trasporto. Riparazione Dei Mezzi Di Trasporto",
    "sg:phone":"+39 0833 832176",
    "sg:postcode":"73044",
    "sg:province":"Lecce",
    "sg:website":"http://www.softex-srl.it",
    "wof:name":"Softex Srl",
    "wof:placetype":"venue"
},
  "geometry": {"coordinates":[18.059866,40.13916],"type":"Point"}
}