{
  "type": "Feature",
  "properties": {
    "iso:country":"IT",
    "sg:address":"Via Degli Artigiani, 20/22 25029 Verolavecchia",
    "sg:city":"Verolavecchia",
    "sg:orig_category":"Ladies' Shoes",
    "sg:phone":"+39 030 992 0388",
    "sg:postcode":"25029",
    "sg:province":"Brescia",
    "sg:website":"www.absol.it/giquattro/",
    "wof:name":"G I Quattro S.r.l.",
    "wof:placetype":"venue"
},
  "geometry": {"coordinates":[10.062329,45.324509],"type":"Point"}
}