{
  "type": "Feature",
  "properties": {
    "addr:full":"20063 Cernusco Sul Naviglio Cernusco sul Naviglio Milano 20063",
    "addr:postcode":"20063;20063",
    "iso:country":"IT",
    "sg:address":"20063 Cernusco Sul Naviglio",
    "sg:city":"Cernusco sul Naviglio",
    "sg:orig_category":"Articoli Da Regalo. Regalistica Aziendale",
    "sg:phone":"+39 02 924 1552",
    "sg:postcode":"20063",
    "sg:province":"Milano",
    "wof:name":"Oriani Alice",
    "wof:placetype":"venue"
},
  "geometry": {"coordinates":[9.332033,45.525944],"type":"Point"}
}