{
  "type": "Feature",
  "properties": {
    "addr:full":"46046 Medole Medole Mantova 46046",
    "addr:postcode":"46046;46046",
    "iso:country":"IT",
    "sg:address":"46046 Medole",
    "sg:city":"Medole",
    "sg:orig_category":"Abbigliamento Intimo, Calze E Costumi Da Bagno",
    "sg:phone":"+39 0376 868588",
    "sg:postcode":"46046",
    "sg:province":"Mantova",
    "wof:name":"Bianchini Elsa Manifattura Elsa",
    "wof:placetype":"venue"
},
  "geometry": {"coordinates":[10.516273,45.333305],"type":"Point"}
}