{
  "type": "Feature",
  "properties": {
    "addr:full":"11, V. Iv Novembre 43030 San Polo Di Torrile Parma 43030",
    "addr:housenumber":"11",
    "addr:postcode":"43030;43030",
    "addr:street":"V. Iv Novembre",
    "iso:country":"IT",
    "sg:address":"11, V. Iv Novembre 43030 San Polo Di Torrile",
    "sg:classifiers":[
        {
            "category":"Personal",
            "subcategory":"Shoe Repair & Shine",
            "type":"Services"
        }
    ],
    "sg:phone":"+39 0521 819955",
    "sg:postcode":"43030",
    "sg:province":"Parma",
    "sg:tags":[
        "leather"
    ],
    "sg:website":"http://www.gegfootwear.it:ws_end: :mark:ws:http://www.paginegialle.it/gegfootwear",
    "wof:name":"G & G Footwear Srl",
    "wof:placetype":"venue"
},
  "geometry": {"coordinates":[10.3295478821,44.8078651428],"type":"Point"}
}