{
  "type": "Feature",
  "properties": {
    "addr:full":"20146 Milano Milano Milano 20146",
    "addr:postcode":"20146;20146",
    "iso:country":"IT",
    "sg:address":"20146 Milano",
    "sg:city":"Milano",
    "sg:orig_category":"Servizi Ausiliari Di Analisi, Controllo E Ricerca",
    "sg:phone":"+39 02 4895 0555",
    "sg:postcode":"20146",
    "sg:province":"Milano",
    "wof:name":"Ele.ap. Elettronica Applicata Di Nava B.",
    "wof:placetype":"venue"
},
  "geometry": {"coordinates":[9.151074,45.45134],"type":"Point"}
}