{
  "type": "Feature",
  "properties": {
    "addr:full":"00138 Roma Roma Roma 00138",
    "addr:postcode":"00138;00138",
    "iso:country":"IT",
    "sg:address":"00138 Roma",
    "sg:city":"Roma",
    "sg:orig_category":"Chiusure Lampo",
    "sg:phone":"+39 06 8852 1736",
    "sg:postcode":"00138",
    "sg:province":"Roma",
    "wof:name":"Gme Sas",
    "wof:placetype":"venue"
},
  "geometry": {"coordinates":[12.508547,41.988113],"type":"Point"}
}