{
  "type": "Feature",
  "properties": {
    "iso:country":"IT",
    "sg:address":"73010 Porto Cesareo",
    "sg:city":"Porto Cesareo",
    "sg:orig_category":"Campeggi, Ostelli E Villaggi Turistici",
    "sg:phone":"+39 0833 563062",
    "sg:postcode":"73010",
    "sg:province":"Lecce",
    "wof:name":"Ego Srl",
    "wof:placetype":"venue"
},
  "geometry": {"coordinates":[17.884863,40.267265],"type":"Point"}
}