{
  "type": "Feature",
  "properties": {
    "addr:full":"10042 Nichelino Nichelino Torino 10042",
    "addr:postcode":"10042;10042",
    "iso:country":"IT",
    "sg:address":"10042 Nichelino",
    "sg:city":"Nichelino",
    "sg:orig_category":"Lavanderie Industriali E Noleggio Biancheria",
    "sg:phone":"+39 011 627 2911",
    "sg:postcode":"10042",
    "sg:province":"Torino",
    "wof:name":"Lanza Daniela & Ornella Snc",
    "wof:placetype":"venue"
},
  "geometry": {"coordinates":[7.657003,45.006027],"type":"Point"}
}