{
  "type": "Feature",
  "properties": {
    "addr:full":"80122 Napoli Napoli Napoli 80122",
    "addr:housenumber":"80122",
    "addr:postcode":"80122",
    "iso:country":"IT",
    "sg:address":"80122 Napoli",
    "sg:city":"Napoli",
    "sg:orig_category":"Agenzie D'affari E Servizi Commerciali. Acqua, Luce, Gas E Societa' Di Esercizio Pubblico",
    "sg:phone":"+39 081 664755",
    "sg:postcode":"80122",
    "sg:province":"Napoli",
    "wof:name":"Assoincanti Napoli",
    "wof:placetype":"venue"
},
  "geometry": {"coordinates":[14.181726,40.898018],"type":"Point"}
}