{
  "type": "Feature",
  "properties": {
    "addr:full":"80026 Casoria Casoria Napoli 80026",
    "addr:postcode":"80026;80026",
    "iso:country":"IT",
    "sg:address":"80026 Casoria",
    "sg:city":"Casoria",
    "sg:orig_category":"Macchine, Impianti Ed Attrezzature Per Abbigliamento E Pelletterie",
    "sg:phone":"+39 081 584 4584",
    "sg:postcode":"80026",
    "sg:province":"Napoli",
    "wof:name":"Singer Italia S.p.a.",
    "wof:placetype":"venue"
},
  "geometry": {"coordinates":[14.313904,40.898529],"type":"Point"}
}