{
  "type": "Feature",
  "properties": {
    "iso:country":"IT",
    "sg:address":"26010 Campagnola Cremasca",
    "sg:city":"Campagnola Cremasca",
    "sg:orig_category":"Impiantistica E Prodotti Tecnologici Per Edilizia. Elettrotecnica Industriale, Prodotti E Apparecchiature. Elettrotecnica Professionale E Di Consumo",
    "sg:phone":"+39 0373 273135",
    "sg:postcode":"26010",
    "sg:province":"Cremona",
    "wof:name":"Rho Pasquale Elettricista",
    "wof:placetype":"venue"
},
  "geometry": {"coordinates":[9.670332,45.399689],"type":"Point"}
}