{
  "type": "Feature",
  "properties": {
    "iso:country":"IT",
    "sg:address":"Piazza Mameli 10; Bardineto; 17020",
    "sg:classifiers":[
        {
            "category":"Banks & Credit Unions",
            "subcategory":"Bank",
            "type":"Services"
        }
    ],
    "sg:phone":"+39 019 790098",
    "sg:postcode":"17020",
    "sg:province":"Savona",
    "wof:name":"Cassa Risparmio Di Savona",
    "wof:placetype":"venue"
},
  "geometry": {"coordinates":[8.130395,44.192265],"type":"Point"}
}