{
  "type": "Feature",
  "properties": {
    "addr:full":"41050 Samone MO",
    "addr:postcode":"41050",
    "iso:country":"IT",
    "sg:address":"41050 Samone",
    "sg:orig_category":"Scuole E Servizi Scolastici",
    "sg:phone":"+39 059 700292",
    "sg:province":"MO",
    "wof:name":"Istituto Angelo Marinelli",
    "wof:placetype":"venue"
},
  "geometry": {"coordinates":[10.96569,44.392265],"type":"Point"}
}