{
  "type": "Feature",
  "properties": {
    "iso:country":"IT",
    "sg:address":"20127 Milano",
    "sg:city":"Milano",
    "sg:orig_category":"Utensili Meccanici E Materiali",
    "sg:phone":"+39 02 2614 9205",
    "sg:postcode":"20127",
    "sg:province":"Milano",
    "wof:name":"Sibeldiam Di Pierro Guglielmo",
    "wof:placetype":"venue"
},
  "geometry": {"coordinates":[9.224513,45.501492],"type":"Point"}
}