{
  "type": "Feature",
  "properties": {
    "addr:full":"20143 Milano Milano Milano 20143",
    "addr:postcode":"20143;20143",
    "iso:country":"IT",
    "sg:address":"20143 Milano",
    "sg:city":"Milano",
    "sg:orig_category":"Frigotecnica, Apparecchiature E Servizi",
    "sg:phone":"+39 02 5811 1495",
    "sg:postcode":"20143",
    "sg:province":"Milano",
    "wof:name":"Novafrigor Srl",
    "wof:placetype":"venue"
},
  "geometry": {"coordinates":[9.1757917404,45.4435501099],"type":"Point"}
}