{
  "type": "Feature",
  "properties": {
    "addr:full":"20128 Milano Milano Milano 20128",
    "addr:postcode":"20128;20128",
    "iso:country":"IT",
    "sg:address":"20128 Milano",
    "sg:city":"Milano",
    "sg:orig_category":"Prodotti Di Base E Forniture Per Industria Alimentare E Bevande. Prodotti Chimici Di Base",
    "sg:phone":"+39 02 2700 0755",
    "sg:postcode":"20128",
    "sg:province":"Milano",
    "wof:name":"Fitoaromatico S.r.l.",
    "wof:placetype":"venue"
},
  "geometry": {"coordinates":[9.2265710831,45.5113067627],"type":"Point"}
}