{
  "type": "Feature",
  "properties": {
    "addr:full":"Via Duca Degli; S. Salvo; 66050 Chieti 66050",
    "addr:postcode":"66050;66050",
    "addr:street":"Via Duca Degli S. Salvo",
    "iso:country":"IT",
    "sg:address":"Via Duca Degli; S. Salvo; 66050",
    "sg:classifiers":[
        {
            "category":"Banks & Credit Unions",
            "subcategory":"Bank",
            "type":"Services"
        }
    ],
    "sg:phone":"+39 0873 343311",
    "sg:postcode":"66050",
    "sg:province":"Chieti",
    "wof:name":"Banca Toscana Spa",
    "wof:placetype":"venue"
},
  "geometry": {"coordinates":[14.727685,42.046459],"type":"Point"}
}