{
  "type": "Feature",
  "properties": {
    "iso:country":"IT",
    "sg:address":"40068 San Lazzaro Di Savena",
    "sg:city":"San Lazzaro",
    "sg:orig_category":"Sport - Articoli E Forniture",
    "sg:phone":"+39 051 625 9408",
    "sg:postcode":"40068",
    "sg:province":"Bologna",
    "wof:name":"Elio Gualandi & C.",
    "wof:placetype":"venue"
},
  "geometry": {"coordinates":[11.423903,44.464764],"type":"Point"}
}