{
  "type": "Feature",
  "properties": {
    "addr:full":"Via Arno 46 50019 Sesto Fiorentino Sesto Fiorentino Firenze 50019",
    "addr:housenumber":"46",
    "addr:postcode":"50019;50019",
    "addr:street":"Via Arno",
    "iso:country":"IT",
    "sg:address":"Via Arno 46 50019 Sesto Fiorentino",
    "sg:city":"Sesto Fiorentino",
    "sg:classifiers":[
        {
            "category":"Shopping",
            "subcategory":"Event Tickets",
            "type":"Retail Goods"
        }
    ],
    "sg:phone":"+39 055 300493",
    "sg:postcode":"50019",
    "sg:province":"Firenze",
    "sg:tags":[
        "billfold"
    ],
    "sg:website":"www.cp3fashion.com",
    "wof:name":"Cp3 Srl",
    "wof:placetype":"venue"
},
  "geometry": {"coordinates":[11.176677,43.811813],"type":"Point"}
}