{
  "type": "Feature",
  "properties": {
    "iso:country":"IT",
    "sg:address":"Via Madonna Pellegrina 166n 20010 Bareggio",
    "sg:city":"Bareggio",
    "sg:classifiers":[
        {
            "category":"Military Area",
            "subcategory":"Air Force Base",
            "type":"Public Place"
        }
    ],
    "sg:phone":"+39 02 9036 1523",
    "sg:postcode":"20010",
    "sg:province":"Milano",
    "sg:tags":[
        "installation",
        "kiln",
        "enamelling"
    ],
    "sg:website":"www.newfurnace.it",
    "wof:name":"New Furnace Italia Srl",
    "wof:placetype":"venue"
},
  "geometry": {"coordinates":[9.005776,45.482327],"type":"Point"}
}