{
  "type": "Feature",
  "properties": {
    "addr:full":"4, Via S. Luigi 10092 Beinasco Beinasco Torino 10092",
    "addr:postcode":"10092;10092",
    "addr:street":"Via S.",
    "iso:country":"IT",
    "sg:address":"4, Via S. Luigi 10092 Beinasco",
    "sg:city":"Beinasco",
    "sg:classifiers":[
        {
            "category":"Real Estate",
            "subcategory":"Surveying",
            "type":"Services"
        }
    ],
    "sg:phone":"+39 011 398 8411",
    "sg:postcode":"10092",
    "sg:province":"Torino",
    "sg:tags":[
        "equipment",
        "material",
        "good",
        "-",
        "handling"
    ],
    "wof:name":"C.p.m. S.p.a.",
    "wof:placetype":"venue"
},
  "geometry": {"coordinates":[7.558662,45.025181],"type":"Point"}
}