{
  "type": "Feature",
  "properties": {
    "iso:country":"IT",
    "sg:address":"54, Via Muratori Ludovico 41012 Carpi",
    "sg:city":"Carpi",
    "sg:classifiers":[
        {
            "category":"Shopping",
            "subcategory":"Clothing, Apparel, & Fashions",
            "type":"Retail Goods"
        }
    ],
    "sg:phone":"+39 39059644911",
    "sg:postcode":"41012",
    "sg:province":"Modena",
    "sg:tags":[
        "clothes"
    ],
    "wof:name":"Drea (s.r.l.)",
    "wof:placetype":"venue"
},
  "geometry": {"coordinates":[10.958344,44.842831],"type":"Point"}
}