{
  "type": "Feature",
  "properties": {
    "iso:country":"IT",
    "sg:address":"09039 Villacidro",
    "sg:city":"Villacidro",
    "sg:classifiers":[
        {
            "category":"Health Services",
            "subcategory":"Health Practitioner",
            "type":"Services"
        }
    ],
    "sg:phone":"+39 070 932 9454",
    "sg:postcode":"09039",
    "sg:province":"Medio Campidano",
    "sg:tags":[
        "medici"
    ],
    "wof:name":"Erbi Salvatore",
    "wof:placetype":"venue"
},
  "geometry": {"coordinates":[8.737748,39.459652],"type":"Point"}
}