{
  "type": "Feature",
  "properties": {
    "addr:full":"50012 Bagno A Ripoli Bagno a Ripoli Firenze 50012",
    "addr:postcode":"50012;50012",
    "addr:street":"A",
    "iso:country":"IT",
    "sg:address":"50012 Bagno A Ripoli",
    "sg:city":"Bagno a Ripoli",
    "sg:orig_category":"Materiali Edili",
    "sg:phone":"+39 055 682 0372",
    "sg:postcode":"50012",
    "sg:province":"Firenze",
    "wof:name":"Lwb Refractories S.r.l.",
    "wof:placetype":"venue"
},
  "geometry": {"coordinates":[11.309168,43.753052],"type":"Point"}
}