{
  "type": "Feature",
  "properties": {
    "addr:full":"23868 Valmadrera Valmadrera Lecco 23868",
    "addr:postcode":"23868;23868",
    "iso:country":"IT",
    "sg:address":"23868 Valmadrera",
    "sg:city":"Valmadrera",
    "sg:orig_category":"Macchine Utensili E Impianti",
    "sg:phone":"+39 0341 580632",
    "sg:postcode":"23868",
    "sg:province":"Lecco",
    "wof:name":"Officina Meccanica Pasquali Mauro & C. Snc",
    "wof:placetype":"venue"
},
  "geometry": {"coordinates":[9.367928,45.845387],"type":"Point"}
}