{
  "type": "Feature",
  "properties": {
    "addr:full":"86170 Isernia Isernia Isernia 86170",
    "addr:postcode":"86170;86170",
    "iso:country":"IT",
    "sg:address":"86170 Isernia",
    "sg:city":"Isernia",
    "sg:orig_category":"Motori Ed Organi Di Trasmissione. Ricambi E Componenti Dei Mezzi Di Trasporto",
    "sg:phone":"+39 0865 413661",
    "sg:postcode":"86170",
    "sg:province":"Isernia",
    "wof:name":"Tamburro Luigi",
    "wof:placetype":"venue"
},
  "geometry": {"coordinates":[14.227355957,41.5910758972],"type":"Point"}
}