{
  "type": "Feature",
  "properties": {
    "addr:full":"20054 Nova Milanese Nova Milanese Milano 20054",
    "addr:housenumber":"20054",
    "addr:postcode":"20054",
    "iso:country":"IT",
    "sg:address":"20054 Nova Milanese",
    "sg:city":"Nova Milanese",
    "sg:orig_category":"Forniture Per Abbigliamento E Pelletterie",
    "sg:phone":"+39 036 236 6813",
    "sg:postcode":"20054",
    "sg:province":"Milano",
    "wof:name":"Italchiusure S.r.l.",
    "wof:placetype":"venue"
},
  "geometry": {"coordinates":[9.1939220428,45.5860061646],"type":"Point"}
}