{
  "type": "Feature",
  "properties": {
    "addr:full":"20, V. Sant'agostino 22066 Mariano Comense Mariano Comense Como 22066",
    "addr:housenumber":"20",
    "addr:postcode":"22066;22066",
    "addr:street":"V. Sant'Agostino",
    "iso:country":"IT",
    "sg:address":"20, V. Sant'agostino 22066 Mariano Comense",
    "sg:city":"Mariano Comense",
    "sg:classifiers":[
        {
            "category":"Home & Garden",
            "subcategory":"Home Furnishings",
            "type":"Retail Goods"
        }
    ],
    "sg:phone":"+39 39031745186",
    "sg:postcode":"22066",
    "sg:province":"Como",
    "sg:tags":[
        "household"
    ],
    "sg:website":"http://www.crippasedie.it",
    "wof:name":"Crippa Fratelli Di Alberto Crippa & C Snc",
    "wof:placetype":"venue"
},
  "geometry": {"coordinates":[9.16989,45.694607],"type":"Point"}
}