{
  "type": "Feature",
  "properties": {
    "addr:full":"Via Cajkovskij 14 20092 Cinisello Balsamo Cinisello Balsamo Milano 20092",
    "addr:housenumber":"14",
    "addr:postcode":"20092;20092",
    "addr:street":"Via Cajkovskij",
    "iso:country":"IT",
    "sg:address":"Via Cajkovskij 14 20092 Cinisello Balsamo",
    "sg:city":"Cinisello Balsamo",
    "sg:classifiers":[
        {
            "category":"Building & Trades",
            "subcategory":"Cleaning & Sanitation",
            "type":"Services"
        }
    ],
    "sg:phone":"+39 02 6604 5052",
    "sg:postcode":"20092",
    "sg:province":"Milano",
    "sg:tags":[
        "brush"
    ],
    "sg:website":"www.kunzletasin.com",
    "wof:name":"Macrotec S.r.l.",
    "wof:placetype":"venue"
},
  "geometry": {"coordinates":[9.188141,45.463688],"type":"Point"}
}