{
  "type": "Feature",
  "properties": {
    "iso:country":"IT",
    "sg:address":"50038 Scarperia",
    "sg:city":"Scarperia",
    "sg:orig_category":"Non-classified Establishments",
    "sg:phone":"+39 055 846 8224",
    "sg:postcode":"50038",
    "sg:province":"Firenze",
    "wof:name":"Oasi Srl",
    "wof:placetype":"venue"
},
  "geometry": {"coordinates":[11.320416,44.04398],"type":"Point"}
}