{
  "type": "Feature",
  "properties": {
    "iso:country":"IT",
    "sg:address":"29010 Pontenure",
    "sg:city":"Pontenure",
    "sg:orig_category":"Macchine Ed Impianti Per Edilizia E Lavori Pubblici",
    "sg:phone":"+39 0523 517541",
    "sg:postcode":"29010",
    "sg:province":"Piacenza",
    "wof:name":"Well Equipments International Srl",
    "wof:placetype":"venue"
},
  "geometry": {"coordinates":[9.787306,45.000362],"type":"Point"}
}