{
  "type": "Feature",
  "properties": {
    "iso:country":"IT",
    "sg:address":"24030 Mozzo",
    "sg:city":"Mozzo",
    "sg:orig_category":"Telecomunicazioni E Telefonia, Impianti, Apparecchi E Servizi",
    "sg:phone":"+39 035 467011",
    "sg:postcode":"24030",
    "sg:province":"Bergamo",
    "sg:website":"http://www.audiotel.it",
    "wof:name":"Audiotel Engineering Spa",
    "wof:placetype":"venue"
},
  "geometry": {"coordinates":[9.603739,45.706596],"type":"Point"}
}