{
  "type": "Feature",
  "properties": {
    "iso:country":"IT",
    "sg:address":"43100 Parma",
    "sg:city":"Parma",
    "sg:orig_category":"Cosmetici, Prodotti Di Bellezza E Di Igiene",
    "sg:phone":"+39 0521 662111",
    "sg:postcode":"43100",
    "sg:province":"Parma",
    "wof:name":"Morris Profumi Divisione Della Henkel Spa",
    "wof:placetype":"venue"
},
  "geometry": {"coordinates":[10.277682,44.846001],"type":"Point"}
}