{
  "type": "Feature",
  "properties": {
    "iso:country":"IT",
    "sg:address":"20136 Milano",
    "sg:city":"Milano",
    "sg:orig_category":"Cine-foto-ottica. Articoli Medico-sanitari Ed Ortopedici",
    "sg:phone":"+39 02 8940 0324",
    "sg:postcode":"20136",
    "sg:province":"Milano",
    "wof:name":"Elios Di Sabbadini Federica",
    "wof:placetype":"venue"
},
  "geometry": {"coordinates":[9.183938,45.45203],"type":"Point"}
}