{
  "type": "Feature",
  "properties": {
    "iso:country":"IT",
    "sg:address":"33044 Manzano",
    "sg:city":"Manzano",
    "sg:orig_category":"Materiali Edili",
    "sg:phone":"+39 0432 74732",
    "sg:postcode":"33044",
    "sg:province":"Udine",
    "wof:name":"Fornaci Di Manzano Spa",
    "wof:placetype":"venue"
},
  "geometry": {"coordinates":[13.363714,45.991093],"type":"Point"}
}