{
  "type": "Feature",
  "properties": {
    "addr:full":"20144 Milano Milano Milano 20144",
    "addr:postcode":"20144;20144",
    "iso:country":"IT",
    "sg:address":"20144 Milano",
    "sg:city":"Milano",
    "sg:orig_category":"Abbigliamento Esterno, Maglierie E Pelliccerie. Servizi E Lavori Per Abbigliamento E Pelletterie",
    "sg:phone":"+39 02 498 3123",
    "sg:postcode":"20144",
    "sg:province":"Milano",
    "wof:name":"Fromm Srl",
    "wof:placetype":"venue"
},
  "geometry": {"coordinates":[9.155886,45.465862],"type":"Point"}
}