{
  "type": "Feature",
  "properties": {
    "addr:full":"66034 Lanciano Lanciano Chieti 66034",
    "addr:postcode":"66034;66034",
    "iso:country":"IT",
    "sg:address":"66034 Lanciano",
    "sg:city":"Lanciano",
    "sg:orig_category":"Forniture Per Abbigliamento E Pelletterie",
    "sg:phone":"+39 0872 719240",
    "sg:postcode":"66034",
    "sg:province":"Chieti",
    "wof:name":"Di Cecco Pasquale Umberto",
    "wof:placetype":"venue"
},
  "geometry": {"coordinates":[14.39083004,42.2160224915],"type":"Point"}
}