{
  "type": "Feature",
  "properties": {
    "addr:full":"24030 Paladina Paladina Bergamo 24030",
    "addr:postcode":"24030;24030",
    "iso:country":"IT",
    "sg:address":"24030 Paladina",
    "sg:city":"Paladina",
    "sg:orig_category":"Tempo Libero - Articoli E Forniture. Automobili E Mezzi Di Trasporto",
    "sg:phone":"+39 035 637553",
    "sg:postcode":"24030",
    "sg:province":"Bergamo",
    "wof:name":"Brember Valley S.r.l.",
    "wof:placetype":"venue"
},
  "geometry": {"coordinates":[9.606153,45.724873],"type":"Point"}
}