{
  "type": "Feature",
  "properties": {
    "iso:country":"IT",
    "sg:address":"70010 Valenzano",
    "sg:city":"Valenzano",
    "sg:orig_category":"Agenzie Investigative",
    "sg:phone":"+39 080 460 2138",
    "sg:postcode":"70010",
    "sg:province":"Bari",
    "wof:name":"Ocram Di Campanelli Vincenzo",
    "wof:placetype":"venue"
},
  "geometry": {"coordinates":[16.882723,41.057018],"type":"Point"}
}