{
  "type": "Feature",
  "properties": {
    "addr:full":"20136 Milano Milano Milano 20136",
    "addr:postcode":"20136;20136",
    "iso:country":"IT",
    "sg:address":"20136 Milano",
    "sg:city":"Milano",
    "sg:orig_category":"Tempo Libero - Articoli E Forniture. Forniture Per Congressi, Fiere E Manifestazioni. Regalistica Aziendale",
    "sg:phone":"+39 02 5830 1198",
    "sg:postcode":"20136",
    "sg:province":"Milano",
    "wof:name":"L.a.t.a.s.",
    "wof:placetype":"venue"
},
  "geometry": {"coordinates":[9.189752,45.451042],"type":"Point"}
}