{
  "type": "Feature",
  "properties": {
    "addr:full":"25065 Lumezzane Lumezzane Brescia 25065",
    "addr:postcode":"25065;25065",
    "iso:country":"IT",
    "sg:address":"25065 Lumezzane",
    "sg:city":"Lumezzane",
    "sg:orig_category":"Non-classified Establishments",
    "sg:phone":"+39 030 892 1720",
    "sg:postcode":"25065",
    "sg:province":"Brescia",
    "wof:name":"Ri. Vi.",
    "wof:placetype":"venue"
},
  "geometry": {"coordinates":[10.285565,45.650349],"type":"Point"}
}