{
  "type": "Feature",
  "properties": {
    "addr:full":"21100 Varese Varese Varese 21100",
    "addr:postcode":"21100;21100",
    "iso:country":"IT",
    "sg:address":"21100 Varese",
    "sg:city":"Varese",
    "sg:orig_category":"Prodotti E Manufatti In Materie Plastiche",
    "sg:phone":"+39 0332 333034",
    "sg:postcode":"21100",
    "sg:province":"Varese",
    "sg:website":"http://www.broggini.it",
    "wof:name":"Broggini Rag. Vittorio Srl",
    "wof:placetype":"venue"
},
  "geometry": {"coordinates":[8.8482217789,45.8148574829],"type":"Point"}
}