{
  "type": "Feature",
  "properties": {
    "iso:country":"IT",
    "sg:address":"Km. 1,200, Via Trani 70031 Andria",
    "sg:city":"Andria",
    "sg:classifiers":[
        {
            "category":"Manufacturing",
            "subcategory":"Metals",
            "type":"Manufacturing & Wholesale Goods"
        }
    ],
    "sg:phone":"+39 0883 557543",
    "sg:postcode":"70031",
    "sg:province":"Bari",
    "sg:tags":[
        "processing"
    ],
    "wof:name":"Pi.sa Di Lambo Giuseppe & C. (s.n.c.)",
    "wof:placetype":"venue"
},
  "geometry": {"coordinates":[16.8692913055,41.1260528564],"type":"Point"}
}