{
  "type": "Feature",
  "properties": {
    "iso:country":"IT",
    "sg:address":"Via Fratelli Cairoli 23 27035 Mede",
    "sg:city":"Mede",
    "sg:orig_category":"Ladies' Knitwear",
    "sg:phone":"+39 0384 820195",
    "sg:postcode":"27035",
    "sg:province":"Pavia",
    "wof:name":"La Giannetta Di Negri Gian Pasquale Sas",
    "wof:placetype":"venue"
},
  "geometry": {"coordinates":[8.738209,45.099247],"type":"Point"}
}