{
  "type": "Feature",
  "properties": {
    "iso:country":"IT",
    "sg:address":"58, V. Monte Summano 36010 Zan\u00e8",
    "sg:classifiers":[
        {
            "category":"Manufacturing",
            "subcategory":"Food",
            "type":"Manufacturing & Wholesale Goods"
        }
    ],
    "sg:phone":"+39 0445 314388",
    "sg:postcode":"36010",
    "sg:province":"Vicenza",
    "sg:tags":[
        "equipment",
        "processing",
        "-",
        "machinery"
    ],
    "sg:website":"http://www.sandore.com",
    "wof:name":"Sandor\u00c8 Snc",
    "wof:placetype":"venue"
},
  "geometry": {"coordinates":[11.4447851181,45.7322769165],"type":"Point"}
}