{
  "type": "Feature",
  "properties": {
    "iso:country":"IT",
    "sg:address":"51039 Quarrata",
    "sg:city":"Quarrata",
    "sg:orig_category":"Arredamenti - Produzione E Ingrosso",
    "sg:phone":"+39 0573 73098",
    "sg:postcode":"51039",
    "sg:province":"Pistoia",
    "wof:name":"Parentesi Quadra Di Baldassini Massimo",
    "wof:placetype":"venue"
},
  "geometry": {"coordinates":[10.99365,43.853844],"type":"Point"}
}