{
  "type": "Feature",
  "properties": {
    "iso:country":"IT",
    "sg:address":"20090 Buccinasco",
    "sg:city":"Buccinasco",
    "sg:orig_category":"Chiese Ed Associazioni Religiose",
    "sg:phone":"+39 02 4570 8526",
    "sg:postcode":"20090",
    "sg:province":"Milano",
    "wof:name":"Monastero Benedettino Ss. Pietro E Paolo",
    "wof:placetype":"venue"
},
  "geometry": {"coordinates":[8.886488,45.416534],"type":"Point"}
}