{
  "type": "Feature",
  "properties": {
    "iso:country":"IT",
    "sg:address":"24055 Cologno Al Serio",
    "sg:city":"Cologno al Serio",
    "sg:orig_category":"Servizi E Lavori Per Arredamento E Industria Del Legno. Servizi E Lavori Per Edilizia E Lavori Pubblici",
    "sg:phone":"+39 035 898920",
    "sg:postcode":"24055",
    "sg:province":"Bergamo",
    "wof:name":"F.lli Poliani Srl",
    "wof:placetype":"venue"
},
  "geometry": {"coordinates":[9.70972,45.590031],"type":"Point"}
}