{
  "type": "Feature",
  "properties": {
    "iso:country":"IT",
    "sg:address":"35127 Padova",
    "sg:city":"Padova",
    "sg:orig_category":"Impianti, Attrezzature E Forniture Sanitarie Ed Ospedaliere",
    "sg:phone":"+39 049 760026",
    "sg:postcode":"35127",
    "sg:province":"Padova",
    "wof:name":"C.e.m. Srl",
    "wof:placetype":"venue"
},
  "geometry": {"coordinates":[11.934061,45.387646],"type":"Point"}
}