{
  "type": "Feature",
  "properties": {
    "addr:full":"Via Manzoni 64; Carpi; 41012 Carpi Modena 41012",
    "addr:housenumber":"64",
    "addr:postcode":"41012;41012",
    "addr:street":"Via Manzoni",
    "iso:country":"IT",
    "sg:address":"Via Manzoni 64; Carpi; 41012",
    "sg:city":"Carpi",
    "sg:classifiers":[
        {
            "category":"Banks & Credit Unions",
            "subcategory":"Bank",
            "type":"Services"
        }
    ],
    "sg:phone":"+39 059 684080",
    "sg:postcode":"41012",
    "sg:province":"Modena",
    "wof:name":"Cassa Risparmio Carpi Spa",
    "wof:placetype":"venue"
},
  "geometry": {"coordinates":[10.884959,44.789661],"type":"Point"}
}