{
  "type": "Feature",
  "properties": {
    "addr:full":"31050 Morgano Morgano Treviso 31050",
    "addr:postcode":"31050;31050",
    "iso:country":"IT",
    "sg:address":"31050 Morgano",
    "sg:city":"Morgano",
    "sg:orig_category":"Manufacturers: Prefabbricati. Impianti E Attrezzature Per Lo Sport E Il Tempo Libero",
    "sg:phone":"+39 0422 832923",
    "sg:postcode":"31050",
    "sg:province":"Treviso",
    "wof:name":"Seven Play S.n.c. Di Santin Massimiliano & C.",
    "wof:placetype":"venue"
},
  "geometry": {"coordinates":[12.120335,45.652897],"type":"Point"}
}