{
  "type": "Feature",
  "properties": {
    "addr:full":"03100 Frosinone Frosinone Frosinone 03100",
    "addr:postcode":"03100;03100",
    "iso:country":"IT",
    "sg:address":"03100 Frosinone",
    "sg:city":"Frosinone",
    "sg:orig_category":"Articoli Da Regalo. Arte Ed Artigianato Artistico",
    "sg:phone":"+39 0775 821062",
    "sg:postcode":"03100",
    "sg:province":"Frosinone",
    "wof:name":"Crescenzi Tiziana",
    "wof:placetype":"venue"
},
  "geometry": {"coordinates":[13.329042,41.651459],"type":"Point"}
}