{
  "type": "Feature",
  "properties": {
    "addr:full":"00061 Anguillara Sabazia Anguillara Sabazia Roma 00061",
    "addr:postcode":"00061;00061",
    "addr:street":"Roma",
    "iso:country":"IT",
    "sg:address":"00061 Anguillara Sabazia",
    "sg:city":"Anguillara Sabazia",
    "sg:orig_category":"Supermercati, Grandi Magazzini E Centri Commerciali",
    "sg:phone":"+39 06 999 5109",
    "sg:postcode":"00061",
    "sg:province":"Roma",
    "wof:name":"Falconi Ivana",
    "wof:placetype":"venue"
},
  "geometry": {"coordinates":[12.266237,42.078068],"type":"Point"}
}