{
  "type": "Feature",
  "properties": {
    "addr:full":"1, Via Dogana 33080 Porcia Porcia Pordenone 33080",
    "addr:postcode":"33080;33080",
    "addr:street":"Via Dogana",
    "iso:country":"IT",
    "sg:address":"1, Via Dogana 33080 Porcia",
    "sg:city":"Porcia",
    "sg:classifiers":[
        {
            "category":"Professional",
            "subcategory":"Engineering",
            "type":"Services"
        }
    ],
    "sg:phone":"+39 0434 552830",
    "sg:postcode":"33080",
    "sg:province":"Pordenone",
    "sg:tags":[
        "machine",
        "-",
        "mechanical"
    ],
    "wof:name":"Porracin",
    "wof:placetype":"venue"
},
  "geometry": {"coordinates":[12.658198,45.94883],"type":"Point"}
}