{
  "type": "Feature",
  "properties": {
    "addr:full":"Via Schieppe 61038 Orciano Di Pesaro Orciano di Pesaro Pesaro E Urbino 61038",
    "addr:postcode":"61038;61038",
    "addr:street":"Via Schieppe;Di Pesaro;Di Pesaro;E Urbino",
    "iso:country":"IT",
    "sg:address":"Via Schieppe 61038 Orciano Di Pesaro",
    "sg:city":"Orciano di Pesaro",
    "sg:classifiers":[
        {
            "category":"Retail",
            "subcategory":"Animal Services",
            "type":"Services"
        }
    ],
    "sg:phone":"+39 0721 981988",
    "sg:postcode":"61038",
    "sg:province":"Pesaro E Urbino",
    "sg:tags":[
        "breeding"
    ],
    "wof:name":"Wafer Zoo Srl",
    "wof:placetype":"venue"
},
  "geometry": {"coordinates":[12.89699,43.711624],"type":"Point"}
}