{
  "type": "Feature",
  "properties": {
    "addr:full":"12, Strada Statale 231 12066 Monticello D'alba Cuneo 12066",
    "addr:housenumber":"231",
    "addr:postcode":"12066;12066",
    "addr:street":"Strada Statale",
    "iso:country":"IT",
    "sg:address":"12, Strada Statale 231 12066 Monticello D'alba",
    "sg:classifiers":[
        {
            "category":"Autos & Motor Vehicles",
            "subcategory":"Automobile Sales",
            "type":"Retail Goods"
        }
    ],
    "sg:phone":"+39 0173 441008",
    "sg:postcode":"12066",
    "sg:province":"Cuneo",
    "sg:tags":[
        "motor-cars"
    ],
    "wof:name":"Camauto (s.r.l.)",
    "wof:placetype":"venue"
},
  "geometry": {"coordinates":[7.9711022377,44.701133728],"type":"Point"}
}