{
  "type": "Feature",
  "properties": {
    "addr:full":"Via Zona Industriale 64020 Bellante Bellante Teramo 64020",
    "addr:postcode":"64020;64020",
    "addr:street":"Via Zona Industriale",
    "iso:country":"IT",
    "sg:address":"Via Zona Industriale 64020 Bellante",
    "sg:city":"Bellante",
    "sg:classifiers":[
        {
            "category":"Shopping",
            "type":"Retail Goods"
        }
    ],
    "sg:phone":"+39 0861 610327",
    "sg:postcode":"64020",
    "sg:province":"Teramo",
    "sg:tags":[
        "finished",
        "-",
        "metallic"
    ],
    "wof:name":"Di Giuseppe Francesco & Vitelli Vincenzo S.n.c.",
    "wof:placetype":"venue"
},
  "geometry": {"coordinates":[13.8473567963,42.7026786804],"type":"Point"}
}