{
  "type": "Feature",
  "properties": {
    "iso:country":"IT",
    "sg:address":"13011 Borgosesia",
    "sg:city":"Borgosesia",
    "sg:orig_category":"Filati E Materie Prime Tessili",
    "sg:phone":"+39 0163 200012",
    "sg:postcode":"13011",
    "sg:province":"Vercelli",
    "sg:website":"http://www.quarona.com",
    "wof:name":"Lanificio Di Quarona Srl",
    "wof:placetype":"venue"
},
  "geometry": {"coordinates":[8.2819652557,45.7208824158],"type":"Point"}
}