{
  "type": "Feature",
  "properties": {
    "addr:full":"20020 Vanzaghello Vanzaghello Milano 20020",
    "addr:postcode":"20020;20020",
    "iso:country":"IT",
    "sg:address":"20020 Vanzaghello",
    "sg:city":"Vanzaghello",
    "sg:orig_category":"Engineering Societa'",
    "sg:phone":"+39 0331 657632",
    "sg:postcode":"20020",
    "sg:province":"Milano",
    "wof:name":"Gallucci Cristiano - Disegni Per Produrre",
    "wof:placetype":"venue"
},
  "geometry": {"coordinates":[8.779769,45.580017],"type":"Point"}
}