{
  "type": "Feature",
  "properties": {
    "iso:country":"IT",
    "sg:address":"Via Ferraris 7 42040 Calerno",
    "sg:classifiers":[
        {
            "category":"Food & Beverages",
            "subcategory":"Bakery",
            "type":"Retail Goods"
        }
    ],
    "sg:phone":"+39 0522 679797",
    "sg:postcode":"42040",
    "sg:province":"Reggio Nell'Emilia",
    "sg:tags":[
        "biscuit"
    ],
    "sg:website":"www.cabrioni.it",
    "wof:name":"Cabrioni Srl",
    "wof:placetype":"venue"
},
  "geometry": {"coordinates":[10.484265,44.751904],"type":"Point"}
}