{
  "type": "Feature",
  "properties": {
    "iso:country":"IT",
    "sg:address":"70043 Monopoli",
    "sg:city":"Monopoli",
    "sg:orig_category":"Servizi E Lavori Per Edilizia E Lavori Pubblici. Servizi E Lavori Per Ecologia E Smaltimento Rifiuti. Macchine E Forniture Per Ecologia E Smaltimento Rifiuti. Acqua, Luce, Gas E Societa' Di Esercizio ",
    "sg:phone":"+39 080 937 2560",
    "sg:postcode":"70043",
    "sg:province":"Bari",
    "wof:name":"Amplifon Spa",
    "wof:placetype":"venue"
},
  "geometry": {"coordinates":[17.296135,40.954132],"type":"Point"}
}