{
  "type": "Feature",
  "properties": {
    "iso:country":"IT",
    "sg:address":"21050 Bisuschio",
    "sg:city":"Bisuschio",
    "sg:orig_category":"Restauratori D'arte",
    "sg:phone":"+39 0332 471134",
    "sg:postcode":"21050",
    "sg:province":"Varese",
    "wof:name":"Amministrazione Villa Cicogna Mozzoni Sas",
    "wof:placetype":"venue"
},
  "geometry": {"coordinates":[8.870437,45.875816],"type":"Point"}
}