{
  "type": "Feature",
  "properties": {
    "addr:full":"14, Via Bernini Gian Lorenzo 20020 Solaro Solaro Milano 20020",
    "addr:postcode":"20020;20020",
    "addr:street":"Via Bernini Gian Lorenzo",
    "iso:country":"IT",
    "sg:address":"14, Via Bernini Gian Lorenzo 20020 Solaro",
    "sg:city":"Solaro",
    "sg:classifiers":[
        {
            "category":"Manufacturing",
            "subcategory":"Motor Vehicles & Parts",
            "type":"Manufacturing & Wholesale Goods"
        }
    ],
    "sg:phone":"+39 390 296 9801",
    "sg:postcode":"20020",
    "sg:province":"Milano",
    "sg:tags":[
        "engine"
    ],
    "wof:name":"Sew Eurodrive Sas",
    "wof:placetype":"venue"
},
  "geometry": {"coordinates":[9.188141,45.463688],"type":"Point"}
}