{
  "type": "Feature",
  "properties": {
    "iso:country":"IT",
    "sg:address":"47, Via De Amicis Edmondo 20123 Milano",
    "sg:city":"Milano",
    "sg:classifiers":[
        {
            "category":"Manufacturing",
            "subcategory":"Printing",
            "type":"Manufacturing & Wholesale Goods"
        }
    ],
    "sg:phone":"+39 02 8940 0800",
    "sg:postcode":"20123",
    "sg:province":"Milano",
    "sg:tags":[
        "publishing"
    ],
    "wof:name":"Marri (s.r.l.)",
    "wof:placetype":"venue"
},
  "geometry": {"coordinates":[9.1753282547,45.4602546692],"type":"Point"}
}