{
  "type": "Feature",
  "properties": {
    "iso:country":"IT",
    "sg:address":"34/b, Via Chiabrera G. 47900 Rimini",
    "sg:city":"Rimini",
    "sg:classifiers":[
        {
            "category":"Utilities",
            "subcategory":"Electric",
            "type":"Services"
        }
    ],
    "sg:phone":"+39 0541 380089",
    "sg:postcode":"47900",
    "sg:province":"Rimini",
    "sg:tags":[
        "energy"
    ],
    "wof:name":"Gruppo Societa' Gas Rimini",
    "wof:placetype":"venue"
},
  "geometry": {"coordinates":[12.566257,44.06078],"type":"Point"}
}