{
  "type": "Feature",
  "properties": {
    "iso:country":"IT",
    "sg:address":"Via Del Vallo 1 61100 Pesaro",
    "sg:city":"Pesaro",
    "sg:classifiers":[
        {
            "category":"Shopping",
            "subcategory":"Stationery & Office Supplies",
            "type":"Retail Goods"
        }
    ],
    "sg:phone":"+39 0721 20400",
    "sg:postcode":"61100",
    "sg:province":"Pesaro E Urbino",
    "sg:tags":[
        "furniture"
    ],
    "sg:website":"www.dellarovere.it",
    "wof:name":"Della Rovere Spa",
    "wof:placetype":"venue"
},
  "geometry": {"coordinates":[12.830703,43.885586],"type":"Point"}
}