{
  "type": "Feature",
  "properties": {
    "iso:country":"IT",
    "sg:address":"40050 Monte San Pietro",
    "sg:city":"Monte San Pietro",
    "sg:orig_category":"Cartotecnica E Servizi. Forniture Per Attivita' Commerciali Ed Artigianali",
    "sg:phone":"+39 051 676 1041",
    "sg:postcode":"40050",
    "sg:province":"Bologna",
    "wof:name":"Sfera Carta Modulistica Sas Di Gambarini Claudio E C.",
    "wof:placetype":"venue"
},
  "geometry": {"coordinates":[11.195059,44.462837],"type":"Point"}
}