{
  "type": "Feature",
  "properties": {
    "iso:country":"IT",
    "sg:address":"30023 Concordia Sagittaria",
    "sg:city":"Concordia Sagittaria",
    "sg:orig_category":"Macchine Utensili E Impianti",
    "sg:phone":"+39 0421 275932",
    "sg:postcode":"30023",
    "sg:province":"Venezia",
    "wof:name":"Oleotecnica S.a.s. Di Giordano Dall'occo",
    "wof:placetype":"venue"
},
  "geometry": {"coordinates":[12.811964,45.755383],"type":"Point"}
}