{
  "type": "Feature",
  "properties": {
    "addr:full":"17, Via Giacomo Leopardi 63020 Montappone Montappone Ascoli Piceno 63020",
    "addr:postcode":"63020;63020",
    "addr:street":"Via Giacomo Leopardi",
    "iso:country":"IT",
    "sg:address":"17, Via Giacomo Leopardi 63020 Montappone",
    "sg:city":"Montappone",
    "sg:classifiers":[
        {
            "category":"Personal",
            "subcategory":"Shoe Repair & Shine",
            "type":"Services"
        }
    ],
    "sg:phone":"+39 0734 760396",
    "sg:postcode":"63020",
    "sg:province":"Ascoli Piceno",
    "sg:tags":[
        "leather"
    ],
    "wof:name":"Frontoni Gabriele Industriale S.r.l.",
    "wof:placetype":"venue"
},
  "geometry": {"coordinates":[13.468762,43.138073],"type":"Point"}
}