{
  "type": "Feature",
  "properties": {
    "iso:country":"IT",
    "sg:address":"1, Via Delle Guardie 25050 Paderno Franciacorta",
    "sg:city":"Paderno Franciacorta",
    "sg:classifiers":[
        {
            "category":"Professional",
            "subcategory":"Engineering",
            "type":"Services"
        }
    ],
    "sg:phone":"+39 030 685 3211",
    "sg:postcode":"25050",
    "sg:province":"Brescia",
    "sg:tags":[
        "machine",
        "-",
        "mechanical"
    ],
    "wof:name":"Fab Spa",
    "wof:placetype":"venue"
},
  "geometry": {"coordinates":[10.083828,45.580173],"type":"Point"}
}