{
  "type": "Feature",
  "properties": {
    "iso:country":"IT",
    "sg:address":"Via Del Castello 2 24030 Mapello",
    "sg:city":"Mapello",
    "sg:classifiers":[
        {
            "category":"Manufacturing",
            "subcategory":"Motor Vehicles & Parts",
            "type":"Manufacturing & Wholesale Goods"
        }
    ],
    "sg:phone":"+39 035 909166",
    "sg:postcode":"24030",
    "sg:province":"Bergamo",
    "sg:tags":[
        "industry",
        "metallurgical",
        "spare"
    ],
    "wof:name":"Sotec S.p.a.",
    "wof:placetype":"venue"
},
  "geometry": {"coordinates":[9.559928,45.716675],"type":"Point"}
}