{
  "type": "Feature",
  "properties": {
    "iso:country":"IT",
    "sg:address":"20121 Milano",
    "sg:city":"Milano",
    "sg:orig_category":"Studi E Consulenze Legali E Notarili. Avvocati, Notai E Servizi Legali. Professionisti - Studi E Servizi Ed Associazioni Di Interesse Aziendale",
    "sg:phone":"+39 02 877351",
    "sg:postcode":"20121",
    "sg:province":"Milano",
    "wof:name":"Cambri-dalmasso Notai S.s.",
    "wof:placetype":"venue"
},
  "geometry": {"coordinates":[9.189117,45.468384],"type":"Point"}
}