{
  "type": "Feature",
  "properties": {
    "addr:full":"41/e, Via Scodoncello 43044 Collecchio Collecchio Parma 43044",
    "addr:housenumber":"41 / e",
    "addr:postcode":"43044;43044",
    "addr:street":"Via Scodoncello",
    "iso:country":"IT",
    "sg:address":"41/e, Via Scodoncello 43044 Collecchio",
    "sg:city":"Collecchio",
    "sg:classifiers":[
        {
            "category":"Professional",
            "subcategory":"Engineering",
            "type":"Services"
        }
    ],
    "sg:phone":"+39 0521 541011",
    "sg:postcode":"43044",
    "sg:province":"Parma",
    "sg:tags":[
        "machine",
        "-",
        "mechanical"
    ],
    "wof:name":"Lanfranchi Srl",
    "wof:placetype":"venue"
},
  "geometry": {"coordinates":[10.203838,44.75412],"type":"Point"}
}