{
  "type": "Feature",
  "properties": {
    "addr:full":"411, Via Tunisi 91025 Marsala Marsala Trapani 91025",
    "addr:housenumber":"411",
    "addr:postcode":"91025;91025",
    "addr:street":"Via Tunisi",
    "iso:country":"IT",
    "sg:address":"411, Via Tunisi 91025 Marsala",
    "sg:city":"Marsala",
    "sg:classifiers":[
        {
            "category":"Manufacturing",
            "subcategory":"Rubber & Plastics",
            "type":"Manufacturing & Wholesale Goods"
        }
    ],
    "sg:phone":"+39 0923 999462",
    "sg:postcode":"91025",
    "sg:province":"Trapani",
    "sg:tags":[
        "packaging",
        "material",
        "-"
    ],
    "wof:name":"Meridional Plast Srl",
    "wof:placetype":"venue"
},
  "geometry": {"coordinates":[12.4533166885,37.7899284363],"type":"Point"}
}