{
  "type": "Feature",
  "properties": {
    "iso:country":"IT",
    "sg:address":"63020 Massa Fermana",
    "sg:city":"Massa Fermana",
    "sg:orig_category":"Calzaturifici E Calzolai - Forniture",
    "sg:phone":"+39 0734 761103",
    "sg:postcode":"63020",
    "sg:province":"Ascoli Piceno",
    "wof:name":"Ciccioli Sergio Ciccioli Macchine",
    "wof:placetype":"venue"
},
  "geometry": {"coordinates":[13.516686,42.882851],"type":"Point"}
}