{
  "type": "Feature",
  "properties": {
    "iso:country":"IT",
    "sg:address":"10146 Torino",
    "sg:city":"Torino",
    "sg:orig_category":"Scuole E Servizi Scolastici. Servizi Per Lo Sport E Il Tempo Libero",
    "sg:phone":"+39 011 771 1820",
    "sg:postcode":"10146",
    "sg:province":"Torino",
    "wof:name":"Associazione Nouvelle Maison De La Danse",
    "wof:placetype":"venue"
},
  "geometry": {"coordinates":[7.634157,45.077957],"type":"Point"}
}