{
  "type": "Feature",
  "properties": {
    "iso:country":"IT",
    "sg:address":"20133 Milano",
    "sg:city":"Milano",
    "sg:orig_category":"Trasporti E Spedizioni Merci",
    "sg:phone":"+39 02 7010 8984",
    "sg:postcode":"20133",
    "sg:province":"Milano",
    "wof:name":"C.s. Lines Srl",
    "wof:placetype":"venue"
},
  "geometry": {"coordinates":[9.229692,45.471371],"type":"Point"}
}