{
  "type": "Feature",
  "properties": {
    "addr:full":"104, Via Di Soffiano 50143 Firenze Firenze Firenze 50143",
    "addr:housenumber":"104",
    "addr:postcode":"50143;50143",
    "addr:street":"Via Di Soffiano",
    "iso:country":"IT",
    "sg:address":"104, Via Di Soffiano 50143 Firenze",
    "sg:city":"Firenze",
    "sg:classifiers":[
        {
            "category":"Personal",
            "subcategory":"Shoe Repair & Shine",
            "type":"Services"
        }
    ],
    "sg:phone":"+39 39055701676",
    "sg:postcode":"50143",
    "sg:province":"Firenze",
    "sg:tags":[
        "leather"
    ],
    "wof:name":"Linea 86 Pelletteria",
    "wof:placetype":"venue"
},
  "geometry": {"coordinates":[11.221153,43.767139],"type":"Point"}
}