{
  "type": "Feature",
  "properties": {
    "iso:country":"IT",
    "sg:address":"Via Nazionale - Montepaone Lido 39/41, 88060 Montepaone",
    "sg:city":"Montepaone",
    "sg:classifiers":[
        {
            "category":"Banks & Credit Unions",
            "subcategory":"Financial Services",
            "type":"Services"
        }
    ],
    "sg:phone":"+39 0967 576942",
    "sg:postcode":"88060",
    "sg:province":"Catanzaro",
    "sg:tags":[
        "banking",
        "finance",
        "insurance"
    ],
    "wof:name":"Banca Di Credito Cooperativo Di Montepaone",
    "wof:placetype":"venue"
},
  "geometry": {"coordinates":[16.5876789093,38.9105987549],"type":"Point"}
}