{
  "type": "Feature",
  "properties": {
    "iso:country":"IT",
    "sg:address":"20145 Milano",
    "sg:city":"Milano",
    "sg:orig_category":"Servizi Di Magazzinaggio E Movimentazione",
    "sg:phone":"+39 02 4801 2180",
    "sg:postcode":"20145",
    "sg:province":"Milano",
    "wof:name":"Magazzini Generali Della Brianza S.p.a.",
    "wof:placetype":"venue"
},
  "geometry": {"coordinates":[9.165237,45.470078],"type":"Point"}
}