{
  "type": "Feature",
  "properties": {
    "iso:country":"IT",
    "sg:address":"31040 Segusino",
    "sg:city":"Segusino",
    "sg:orig_category":"Autofficine E Centri Assistenza",
    "sg:phone":"+39 0423 979864",
    "sg:postcode":"31040",
    "sg:province":"Treviso",
    "wof:name":"Ceri Di Coppe Ermanno",
    "wof:placetype":"venue"
},
  "geometry": {"coordinates":[12.221045,45.677658],"type":"Point"}
}