{
  "type": "Feature",
  "properties": {
    "iso:country":"IT",
    "sg:address":"25036 Palazzolo Sull'oglio",
    "sg:classifiers":[
        {
            "category":"Manufacturing",
            "subcategory":"Leather Goods",
            "type":"Manufacturing & Wholesale Goods"
        }
    ],
    "sg:phone":"+39 030 740 2470",
    "sg:postcode":"25036",
    "sg:province":"Brescia",
    "sg:tags":[
        "footwear",
        "skin"
    ],
    "sg:website":"http://www.raccagni.it",
    "wof:name":"Raccagni Snc Di Raccagni Italo Snc",
    "wof:placetype":"venue"
},
  "geometry": {"coordinates":[9.8911876678,45.5941009521],"type":"Point"}
}