{
  "type": "Feature",
  "properties": {
    "iso:country":"IT",
    "sg:address":"21, Via Novi 15060 Silvano D'orba",
    "sg:classifiers":[
        {
            "category":"Autos & Motor Vehicles",
            "subcategory":"Automobile Sales",
            "type":"Retail Goods"
        }
    ],
    "sg:phone":"+39 0143 841992",
    "sg:postcode":"15060",
    "sg:province":"Alessandria",
    "sg:tags":[
        "industrial"
    ],
    "wof:name":"Matrix Sas",
    "wof:placetype":"venue"
},
  "geometry": {"coordinates":[8.68076,44.692513],"type":"Point"}
}