{
  "type": "Feature",
  "properties": {
    "iso:country":"IT",
    "sg:address":"43010 Parma",
    "sg:orig_category":"Forniture Per Agricoltura E Zootecnia. Prodotti Chimici Secondari",
    "sg:phone":"+39 0521 995026",
    "sg:postcode":"43010",
    "sg:province":"Parma",
    "wof:name":"Carretta Uldarico",
    "wof:placetype":"venue"
},
  "geometry": {"coordinates":[10.3092880249,44.8576049805],"type":"Point"}
}