{
  "type": "Feature",
  "properties": {
    "addr:full":"2, Via Cesarotti Melchiorre 35123 Padova Padova Padova 35123",
    "addr:postcode":"35123;35123",
    "addr:street":"Via Cesarotti Melchiorre",
    "iso:country":"IT",
    "sg:address":"2, Via Cesarotti Melchiorre 35123 Padova",
    "sg:city":"Padova",
    "sg:classifiers":[
        {
            "category":"Manufacturing",
            "subcategory":"Printing",
            "type":"Manufacturing & Wholesale Goods"
        }
    ],
    "sg:phone":"+39 049 875 7063",
    "sg:postcode":"35123",
    "sg:province":"Padova",
    "sg:tags":[
        "publishing"
    ],
    "wof:name":"Provincia Padovana Fmc",
    "wof:placetype":"venue"
},
  "geometry": {"coordinates":[11.8807067871,45.401927948],"type":"Point"}
}