{
  "type": "Feature",
  "properties": {
    "iso:country":"IT",
    "sg:address":"16126 Genova",
    "sg:city":"Genova",
    "sg:orig_category":"Servizi Al Turismo. Trasporto Pubblico E Privato",
    "sg:phone":"+39 010 251 8398",
    "sg:postcode":"16126",
    "sg:province":"Genova",
    "wof:name":"Tirrenia Navigazione S.p.a.",
    "wof:placetype":"venue"
},
  "geometry": {"coordinates":[8.909358,44.40567],"type":"Point"}
}