{
  "type": "Feature",
  "properties": {
    "addr:full":"10040 Caselette Caselette Torino 10040",
    "addr:postcode":"10040;10040",
    "iso:country":"IT",
    "sg:address":"10040 Caselette",
    "sg:city":"Caselette",
    "sg:orig_category":"Acciaierie E Fonderie",
    "sg:postcode":"10040",
    "sg:province":"Torino",
    "wof:name":"Fonderia L.e.a. S.r.l.",
    "wof:placetype":"venue"
},
  "geometry": {"coordinates":[7.637922,44.987766],"type":"Point"}
}