{
  "type": "Feature",
  "properties": {
    "iso:country":"IT",
    "sg:address":"56125 Pisa",
    "sg:city":"Pisa",
    "sg:orig_category":"Articoli Regalo - Vendita Al Dettaglio",
    "sg:phone":"+39 050 27078",
    "sg:postcode":"56125",
    "sg:province":"Pisa",
    "sg:website":"http://www.pasquinucci.com",
    "wof:name":"Pasquinuccio Pasquinucci Sas",
    "wof:placetype":"venue"
},
  "geometry": {"coordinates":[10.401732,43.71069],"type":"Point"}
}