{
  "type": "Feature",
  "properties": {
    "addr:full":"5/g, Via Nuova Valassina 22046 Merone Merone Como 22046",
    "addr:housenumber":"5 / g",
    "addr:postcode":"22046;22046",
    "addr:street":"Via Nuova Valassina",
    "iso:country":"IT",
    "sg:address":"5/g, Via Nuova Valassina 22046 Merone",
    "sg:city":"Merone",
    "sg:classifiers":[
        {
            "category":"Shopping",
            "subcategory":"Crafts & Fabrics",
            "type":"Retail Goods"
        }
    ],
    "sg:phone":"+39 39031642318",
    "sg:postcode":"22046",
    "sg:province":"Como",
    "wof:name":"Rusconi Tende Sas Di Rusconi Stefano & C.",
    "wof:placetype":"venue"
},
  "geometry": {"coordinates":[9.0854558945,45.8119659424],"type":"Point"}
}