{
  "type": "Feature",
  "properties": {
    "iso:country":"IT",
    "sg:address":"10042 Nichelino",
    "sg:city":"Nichelino",
    "sg:orig_category":"Minuterie Metalliche E Ferramenta",
    "sg:phone":"+39 011 627 5106",
    "sg:postcode":"10042",
    "sg:province":"Torino",
    "wof:name":"Auno Security Srl",
    "wof:placetype":"venue"
},
  "geometry": {"coordinates":[7.6421604156,44.9754524231],"type":"Point"}
}