{
  "type": "Feature",
  "properties": {
    "iso:country":"IT",
    "sg:address":"48015 Montaletto",
    "sg:orig_category":"Imprese Di Costruzioni Civili Ed Industriali",
    "sg:phone":"+39 0544 966000",
    "sg:postcode":"48015",
    "sg:province":"Ravenna",
    "wof:name":"Tecno Legno Di Giunchi Geom. Ezio E C. Snc",
    "wof:placetype":"venue"
},
  "geometry": {"coordinates":[12.334611,44.222973],"type":"Point"}
}