{
  "type": "Feature",
  "properties": {
    "iso:country":"IT",
    "sg:address":"47023 Cesena",
    "sg:city":"Cesena",
    "sg:orig_category":"Motori Ed Organi Di Trasmissione",
    "sg:phone":"+39 0547 383294",
    "sg:postcode":"47023",
    "sg:province":"Forl\u00ec-Cesena",
    "wof:name":"C.r.c. Compressori Di Casadei Salvatore & C. Snc",
    "wof:placetype":"venue"
},
  "geometry": {"coordinates":[11.9804611206,43.9947662354],"type":"Point"}
}