{
  "type": "Feature",
  "properties": {
    "iso:country":"IT",
    "sg:address":"70122 Bari",
    "sg:city":"Bari",
    "sg:orig_category":"Antiquariato",
    "sg:phone":"+39 339 261 6204",
    "sg:postcode":"70122",
    "sg:province":"Bari",
    "wof:name":"Un Tuffo Nel Passato Di Antonio Alberga",
    "wof:placetype":"venue"
},
  "geometry": {"coordinates":[16.872547,41.075459],"type":"Point"}
}