{
  "type": "Feature",
  "properties": {
    "iso:country":"IT",
    "sg:address":"20090 Segrate",
    "sg:city":"Segrate",
    "sg:orig_category":"Chiese Ed Associazioni Religiose",
    "sg:phone":"+39 02 213 4337",
    "sg:postcode":"20090",
    "sg:province":"Milano",
    "wof:name":"Parrocchia Santo Stefano",
    "wof:placetype":"venue"
},
  "geometry": {"coordinates":[9.295156,45.489834],"type":"Point"}
}