{
  "type": "Feature",
  "properties": {
    "iso:country":"IT",
    "sg:address":"20121 Milano",
    "sg:city":"Milano",
    "sg:orig_category":"Pubblicita', Marketing E Comunicazione",
    "sg:phone":"+39 02 2900 5061",
    "sg:postcode":"20121",
    "sg:province":"Milano",
    "sg:website":"http://www.nomen.it",
    "wof:name":"Nomen Italia Srl",
    "wof:placetype":"venue"
},
  "geometry": {"coordinates":[9.1938323975,45.4776535034],"type":"Point"}
}