{
  "type": "Feature",
  "properties": {
    "iso:country":"IT",
    "sg:address":"74100 Taranto",
    "sg:city":"Taranto",
    "sg:orig_category":"Scuole E Servizi Scolastici. Centri Di Estetica E Cosmesi E Servizi. Ricerca, Selezione E Formazione Del Personale",
    "sg:phone":"+39 099 335814",
    "sg:postcode":"74100",
    "sg:province":"Taranto",
    "wof:name":"Scuola Estetica Elsa Tacconi Carelli Di Fornaro Valeria",
    "wof:placetype":"venue"
},
  "geometry": {"coordinates":[17.268282,40.462154],"type":"Point"}
}