{
  "type": "Feature",
  "properties": {
    "iso:country":"IT",
    "sg:address":"80078 Pozzuoli",
    "sg:city":"Pozzuoli",
    "sg:orig_category":"Cucine Per Comunita'",
    "sg:phone":"+39 081 303 1034",
    "sg:postcode":"80078",
    "sg:province":"Napoli",
    "wof:name":"Mgi Di Gennaro De Maria",
    "wof:placetype":"venue"
},
  "geometry": {"coordinates":[14.131048,40.824844],"type":"Point"}
}