{
  "type": "Feature",
  "properties": {
    "iso:country":"IT",
    "sg:address":"Via Foro Boario 20 31049 Valdobbiadene",
    "sg:city":"Valdobbiadene",
    "sg:classifiers":[
        {
            "category":"Food & Beverages",
            "subcategory":"Liquor & Beverages",
            "type":"Retail Goods"
        }
    ],
    "sg:phone":"+39 0423 972402",
    "sg:postcode":"31049",
    "sg:province":"Treviso",
    "sg:tags":[
        "wine",
        "italian"
    ],
    "sg:website":"www.valdo.com",
    "wof:name":"Spumanti Valdo S.r.l.",
    "wof:placetype":"venue"
},
  "geometry": {"coordinates":[12.242072,45.666286],"type":"Point"}
}