{
  "type": "Feature",
  "properties": {
    "iso:country":"IT",
    "sg:address":"57121 Livorno",
    "sg:city":"Livorno",
    "sg:orig_category":"Elettronica Professionale E Di Consumo. Musica. Forniture Per Congressi, Fiere E Manifestazioni",
    "sg:phone":"+39 0586 426406",
    "sg:postcode":"57121",
    "sg:province":"Livorno",
    "wof:name":"Music Empire Studios",
    "wof:placetype":"venue"
},
  "geometry": {"coordinates":[10.364166,43.568642],"type":"Point"}
}