{
  "type": "Feature",
  "properties": {
    "iso:country":"IT",
    "sg:address":"92019 Sciacca",
    "sg:city":"Sciacca",
    "sg:orig_category":"Prodotti Di Base E Forniture Per Industria Alimentare E Bevande. Macchine, Impianti Ed Attrezzature Per Industria Alimentare E Bevande. Frigotecnica, Apparecchiature E Servizi. Macchine E Impianti Per",
    "sg:phone":"+39 0925 22481",
    "sg:postcode":"92019",
    "sg:province":"Agrigento",
    "wof:name":"Curreri Vincenzo",
    "wof:placetype":"venue"
},
  "geometry": {"coordinates":[13.0587396622,37.5676307678],"type":"Point"}
}