{
  "type": "Feature",
  "properties": {
    "addr:full":"57022 Castagneto Carducci Castagneto Carducci Livorno 57022",
    "addr:housenumber":"carducci",
    "addr:postcode":"57022;57022",
    "iso:country":"IT",
    "sg:address":"57022 Castagneto Carducci",
    "sg:city":"Castagneto Carducci",
    "sg:orig_category":"Ceramiche Artistiche",
    "sg:phone":"+39 0565 776092",
    "sg:postcode":"57022",
    "sg:province":"Livorno",
    "wof:name":"Esterni Terracotte Ceramiche Di Iacoponi Luca",
    "wof:placetype":"venue"
},
  "geometry": {"coordinates":[10.560956,43.15662],"type":"Point"}
}