{
  "type": "Feature",
  "properties": {
    "addr:full":"Via S. Vito 37040 Zimella Zimella Verona 37040",
    "addr:postcode":"37040;37040",
    "addr:street":"Via S. Vito",
    "iso:country":"IT",
    "sg:address":"Via S. Vito 37040 Zimella",
    "sg:city":"Zimella",
    "sg:classifiers":[
        {
            "category":"Shopping",
            "subcategory":"Crafts & Fabrics",
            "type":"Retail Goods"
        }
    ],
    "sg:phone":"+39 0442 411360",
    "sg:postcode":"37040",
    "sg:province":"Verona",
    "wof:name":"Resinatura Veneta (s.r.l.)",
    "wof:placetype":"venue"
},
  "geometry": {"coordinates":[10.9917478561,45.4383659363],"type":"Point"}
}