{
  "type": "Feature",
  "properties": {
    "addr:full":"Contrada Tesino 63035 Offida Offida Ascoli Piceno 63035",
    "addr:postcode":"63035;63035",
    "addr:street":"Contrada Tesino",
    "iso:country":"IT",
    "sg:address":"Contrada Tesino 63035 Offida",
    "sg:city":"Offida",
    "sg:classifiers":[
        {
            "category":"Personal",
            "subcategory":"Shoe Repair & Shine",
            "type":"Services"
        }
    ],
    "sg:phone":"+39 0736 889977",
    "sg:postcode":"63035",
    "sg:province":"Ascoli Piceno",
    "sg:tags":[
        "leather"
    ],
    "wof:name":"Vog S.r.l.",
    "wof:placetype":"venue"
},
  "geometry": {"coordinates":[13.574977,42.8554],"type":"Point"}
}