{
  "type": "Feature",
  "properties": {
    "addr:full":"61, Via Salgari Emilio 41100 Modena Modena Modena 41100",
    "addr:postcode":"41100;41100",
    "addr:street":"Via Salgari Emilio",
    "iso:country":"IT",
    "sg:address":"61, Via Salgari Emilio 41100 Modena",
    "sg:city":"Modena",
    "sg:classifiers":[
        {
            "category":"Professional",
            "subcategory":"Printing & Photocopies",
            "type":"Services"
        }
    ],
    "sg:phone":"+39 39059330540",
    "sg:postcode":"41100",
    "sg:province":"Modena",
    "wof:name":"Vaccari Zincografica (s.r.l.)",
    "wof:placetype":"venue"
},
  "geometry": {"coordinates":[10.9252195358,44.6470794678],"type":"Point"}
}