{
  "type": "Feature",
  "properties": {
    "addr:full":"12010 San Rocco Cuneo 12010",
    "addr:housenumber":"12010",
    "addr:postcode":"12010",
    "addr:street":"San",
    "iso:country":"IT",
    "sg:address":"12010 San Rocco",
    "sg:orig_category":"Macchine Ed Impianti Per Edilizia E Lavori Pubblici",
    "sg:phone":"+39 0171 687061",
    "sg:postcode":"12010",
    "sg:province":"Cuneo",
    "wof:name":"Fissologru (s.r.l.)",
    "wof:placetype":"venue"
},
  "geometry": {"coordinates":[7.472802,44.397007],"type":"Point"}
}