{
  "type": "Feature",
  "properties": {
    "iso:country":"IT",
    "sg:address":"50018 Scandicci",
    "sg:city":"Scandicci",
    "sg:orig_category":"Non-classified Establishments",
    "sg:phone":"+39 055 252401",
    "sg:postcode":"50018",
    "sg:province":"Firenze",
    "wof:name":"Mobil Giunco Di Sampoli Anna",
    "wof:placetype":"venue"
},
  "geometry": {"coordinates":[11.200947,43.758305],"type":"Point"}
}