{
  "type": "Feature",
  "properties": {
    "iso:country":"IT",
    "sg:address":"27046 Santa Giuletta",
    "sg:city":"Santa Giuletta",
    "sg:orig_category":"Abbigliamento Esterno, Maglierie E Pelliccerie. Calzature, Pelletterie E Pelli. Sport - Articoli E Forniture",
    "sg:phone":"+39 0383 899814",
    "sg:postcode":"27046",
    "sg:province":"Pavia",
    "wof:name":"Faldetta Adriana",
    "wof:placetype":"venue"
},
  "geometry": {"coordinates":[9.179051,45.03825],"type":"Point"}
}