{
  "type": "Feature",
  "properties": {
    "iso:country":"IT",
    "sg:address":"20154 Milano",
    "sg:city":"Milano",
    "sg:orig_category":"Materie Plastiche - Produzione E Lavorazione",
    "sg:phone":"+39 02 349 4205",
    "sg:postcode":"20154",
    "sg:province":"Milano",
    "wof:name":"Antonio Noberini Srl",
    "wof:placetype":"venue"
},
  "geometry": {"coordinates":[9.171903,45.488056],"type":"Point"}
}