{
  "type": "Feature",
  "properties": {
    "iso:country":"IT",
    "sg:address":"30172 Mestre",
    "sg:orig_category":"Ricerca, Selezione E Formazione Del Personale",
    "sg:phone":"+39 041 951373",
    "sg:postcode":"30172",
    "sg:province":"Venezia",
    "wof:name":"Agenzia Angela",
    "wof:placetype":"venue"
},
  "geometry": {"coordinates":[12.244619,45.490898],"type":"Point"}
}