{
  "type": "Feature",
  "properties": {
    "addr:full":"16/a, Via Per Ronco 21023 Besozzo Besozzo Varese 21023",
    "addr:housenumber":"16 / a",
    "addr:postcode":"21023;21023",
    "addr:street":"Via Per Ronco",
    "iso:country":"IT",
    "sg:address":"16/a, Via Per Ronco 21023 Besozzo",
    "sg:city":"Besozzo",
    "sg:classifiers":[
        {
            "category":"Manufacturing",
            "subcategory":"Glass & Minerals",
            "type":"Manufacturing & Wholesale Goods"
        }
    ],
    "sg:phone":"+39 0332 771125",
    "sg:postcode":"21023",
    "sg:province":"Varese",
    "wof:name":"Gadk Di Bordiga Giuseppe",
    "wof:placetype":"venue"
},
  "geometry": {"coordinates":[8.826385,45.817604],"type":"Point"}
}