{
  "type": "Feature",
  "properties": {
    "iso:country":"IT",
    "sg:address":"Via Xxix Aprile 43 15048 Valenza",
    "sg:city":"Valenza",
    "sg:classifiers":[
        {
            "category":"Manufacturing",
            "subcategory":"Tools & Machinery",
            "type":"Manufacturing & Wholesale Goods"
        }
    ],
    "sg:phone":"+39 0131 924264",
    "sg:postcode":"15048",
    "sg:province":"Alessandria",
    "sg:tags":[
        "machine",
        "gem",
        "dressing"
    ],
    "wof:name":"Garbarino & Titonel S.n.c.",
    "wof:placetype":"venue"
},
  "geometry": {"coordinates":[8.616951,44.913216],"type":"Point"}
}