{
  "type": "Feature",
  "properties": {
    "iso:country":"IT",
    "sg:address":"20026 Novate Milanese",
    "sg:city":"Novate Milanese",
    "sg:orig_category":"Servizi E Lavori Per Abbigliamento E Pelletterie",
    "sg:phone":"+39 02 354 3048",
    "sg:postcode":"20026",
    "sg:province":"Milano",
    "wof:name":"Fusari Carla",
    "wof:placetype":"venue"
},
  "geometry": {"coordinates":[9.137203,45.539124],"type":"Point"}
}