{
  "type": "Feature",
  "properties": {
    "addr:full":"98123 Messina Messina Messina 98123",
    "addr:postcode":"98123;98123",
    "iso:country":"IT",
    "sg:address":"98123 Messina",
    "sg:city":"Messina",
    "sg:orig_category":"Ospedali E Servizi Sanitari. Servizi Sociali. Associazioni Ed Organismi Di Interesse Pubblico",
    "sg:phone":"+39 090 716720",
    "sg:postcode":"98123",
    "sg:province":"Messina",
    "wof:name":"A.v.i.s. Associazione Volontari Italiani Sangue",
    "wof:placetype":"venue"
},
  "geometry": {"coordinates":[15.553501,38.184292],"type":"Point"}
}