{
  "type": "Feature",
  "properties": {
    "iso:country":"IT",
    "sg:address":"44100 Ferrara",
    "sg:city":"Ferrara",
    "sg:orig_category":"Arredo Cucina Ed Elettrodomestici. Elettrodomestici. Apparecchi, Attrezzature E Forniture Per Centri Estetici",
    "sg:phone":"+39 0532 209778",
    "sg:postcode":"44100",
    "sg:province":"Ferrara",
    "wof:name":"Clinica Dei Rasoi",
    "wof:placetype":"venue"
},
  "geometry": {"coordinates":[11.641193,44.816753],"type":"Point"}
}