{
  "type": "Feature",
  "properties": {
    "iso:country":"IT",
    "sg:address":"73, Via Marconi 73040 Specchia",
    "sg:city":"Specchia",
    "sg:classifiers":[
        {
            "category":"Real Estate",
            "subcategory":"Architect",
            "type":"Services"
        }
    ],
    "sg:phone":"+39 0833 536050",
    "sg:postcode":"73040",
    "sg:province":"Lecce",
    "sg:tags":[
        "textile",
        "clothing"
    ],
    "wof:name":"Punto Exe Srl",
    "wof:placetype":"venue"
},
  "geometry": {"coordinates":[18.411543,40.087254],"type":"Point"}
}