{
  "type": "Feature",
  "properties": {
    "iso:country":"IT",
    "sg:address":"47034 Forlimpopoli",
    "sg:city":"Forlimpopoli",
    "sg:orig_category":"Dolciumi E Gelati. Condimenti, Spezie, Infusi E Caffe'",
    "sg:phone":"+39 0543 748911",
    "sg:postcode":"47034",
    "sg:province":"Forl\u00ec-Cesena",
    "wof:name":"Societa' Fondiaria Industriale Romagnola (s.p.a.)",
    "wof:placetype":"venue"
},
  "geometry": {"coordinates":[12.185463,44.200558],"type":"Point"}
}