{
  "type": "Feature",
  "properties": {
    "addr:full":"Viale Trieste 27; Tivoli; 00019 Tivoli Roma 00019",
    "addr:housenumber":"27",
    "addr:postcode":"00019;roma 00019",
    "addr:street":"Viale Trieste",
    "iso:country":"IT",
    "sg:address":"Viale Trieste 27; Tivoli; 00019",
    "sg:city":"Tivoli",
    "sg:classifiers":[
        {
            "category":"Banks & Credit Unions",
            "subcategory":"Bank",
            "type":"Services"
        }
    ],
    "sg:phone":"+39 0774 318156",
    "sg:postcode":"00019",
    "sg:province":"Roma",
    "wof:name":"Istituto Bancario, San Paolo Di Torino Spa",
    "wof:placetype":"venue"
},
  "geometry": {"coordinates":[12.798667,41.959724],"type":"Point"}
}