{
  "type": "Feature",
  "properties": {
    "iso:country":"IT",
    "sg:address":"33058 San Giorgio Di Nogaro",
    "sg:city":"San Giorgio di Nogaro",
    "sg:orig_category":"Marmo, Pietre Ed Affini",
    "sg:phone":"+39 0431 620440",
    "sg:postcode":"33058",
    "sg:province":"Udine",
    "wof:name":"Ca' D'oro Spa",
    "wof:placetype":"venue"
},
  "geometry": {"coordinates":[13.221848,45.809917],"type":"Point"}
}