{
  "type": "Feature",
  "properties": {
    "addr:full":"81/a, Via Vico Gallinaro 03040 Gallinaro Gallinaro Frosinone 03040",
    "addr:housenumber":"81 / a",
    "addr:postcode":"03040;03040",
    "addr:street":"Via Vico Gallinaro",
    "iso:country":"IT",
    "sg:address":"81/a, Via Vico Gallinaro 03040 Gallinaro",
    "sg:city":"Gallinaro",
    "sg:classifiers":[
        {
            "category":"Travel",
            "subcategory":"Travel Agent",
            "type":"Entertainment"
        }
    ],
    "sg:phone":"+39 0776 695150",
    "sg:postcode":"03040",
    "sg:province":"Frosinone",
    "sg:tags":[
        "business"
    ],
    "wof:name":"Hotel Tramp's",
    "wof:placetype":"venue"
},
  "geometry": {"coordinates":[13.351902,41.640137],"type":"Point"}
}