{
  "type": "Feature",
  "properties": {
    "iso:country":"IT",
    "sg:address":"62100 Macerata",
    "sg:city":"Macerata",
    "sg:orig_category":"Impiantistica E Prodotti Tecnologici Per Edilizia",
    "sg:phone":"+39 0733 262288",
    "sg:postcode":"62100",
    "sg:province":"Macerata",
    "wof:name":"Fratini Antonio & C. Snc",
    "wof:placetype":"venue"
},
  "geometry": {"coordinates":[13.427276,43.298161],"type":"Point"}
}