{
  "type": "Feature",
  "properties": {
    "iso:country":"IT",
    "sg:address":"Viale Italia 48; Ladispoli; 00055",
    "sg:city":"Ladispoli",
    "sg:classifiers":[
        {
            "category":"Banks & Credit Unions",
            "subcategory":"Bank",
            "type":"Services"
        }
    ],
    "sg:phone":"+39 06 994 7945",
    "sg:postcode":"00055",
    "sg:province":"Roma",
    "wof:name":"Credito Italiano Spa",
    "wof:placetype":"venue"
},
  "geometry": {"coordinates":[12.079396,41.950455],"type":"Point"}
}