{
  "type": "Feature",
  "properties": {
    "addr:full":"80059 Torre Del Greco Torre del Greco Napoli 80059",
    "addr:postcode":"80059;80059",
    "iso:country":"IT",
    "sg:address":"80059 Torre Del Greco",
    "sg:city":"Torre del Greco",
    "sg:orig_category":"Lavorazioni Meccaniche E Servizi. Riparazione Dei Mezzi Di Trasporto",
    "sg:phone":"+39 081 881 9127",
    "sg:postcode":"80059",
    "sg:province":"Napoli",
    "wof:name":"Gaudino Giovanni",
    "wof:placetype":"venue"
},
  "geometry": {"coordinates":[14.368029,40.78722],"type":"Point"}
}