{
  "type": "Feature",
  "properties": {
    "iso:country":"IT",
    "sg:address":"75015 Pisticci",
    "sg:city":"Pisticci",
    "sg:classifiers":[
        {
            "category":"Health Services",
            "subcategory":"Health Practitioner",
            "type":"Services"
        }
    ],
    "sg:phone":"+39 0835 582606",
    "sg:postcode":"75015",
    "sg:province":"Matera",
    "sg:tags":[
        "medici"
    ],
    "wof:name":"Silletti Franco",
    "wof:placetype":"venue"
},
  "geometry": {"coordinates":[16.6055526733,40.3729286194],"type":"Point"}
}