{
  "type": "Feature",
  "properties": {
    "iso:country":"IT",
    "sg:address":"50126 Firenze",
    "sg:city":"Firenze",
    "sg:orig_category":"Chiese Ed Associazioni Religiose",
    "sg:phone":"+39 055 681 0681",
    "sg:postcode":"50126",
    "sg:province":"Firenze",
    "wof:name":"Chiesa Di Altri Culti Evangelica Riformata",
    "wof:placetype":"venue"
},
  "geometry": {"coordinates":[11.274224,43.76297],"type":"Point"}
}