{
  "type": "Feature",
  "properties": {
    "addr:full":"Via Galileo Galilei 16 20054 Nova Milanese Nova Milanese Milano 20054",
    "addr:housenumber":"16",
    "addr:postcode":"20054;20054",
    "addr:street":"Via Galileo Galilei",
    "iso:country":"IT",
    "sg:address":"Via Galileo Galilei 16 20054 Nova Milanese",
    "sg:city":"Nova Milanese",
    "sg:orig_category":"Microwave Components",
    "sg:phone":"+39 036 245 0421",
    "sg:postcode":"20054",
    "sg:province":"Milano",
    "sg:website":"www.labem-microwave.it",
    "wof:name":"Labem S.r.l.",
    "wof:placetype":"venue"
},
  "geometry": {"coordinates":[9.155632019,45.5609512329],"type":"Point"}
}