{
  "type": "Feature",
  "properties": {
    "iso:country":"IT",
    "sg:address":"18038 Sanremo",
    "sg:orig_category":"Autoscuole",
    "sg:phone":"+39 0184 42224",
    "sg:postcode":"18038",
    "sg:province":"Imperia",
    "wof:name":"Autoscuole Riunite Sanremesi E Armesi Snc",
    "wof:placetype":"venue"
},
  "geometry": {"coordinates":[8.03093,43.902428],"type":"Point"}
}