{
  "type": "Feature",
  "properties": {
    "iso:country":"IT",
    "sg:address":"00174 Roma",
    "sg:city":"Roma",
    "sg:orig_category":"Calzature, Pelletterie E Pelli. Shopping",
    "sg:phone":"+39 06 7154 3008",
    "sg:postcode":"00174",
    "sg:province":"Roma",
    "wof:name":"Montesi Fabio",
    "wof:placetype":"venue"
},
  "geometry": {"coordinates":[12.561424,41.857136],"type":"Point"}
}