{
  "type": "Feature",
  "properties": {
    "iso:country":"IT",
    "sg:address":"40123 Bologna",
    "sg:city":"Bologna",
    "sg:orig_category":"Ceramiche: Prodotti E Lavorazioni",
    "sg:phone":"+39 051 644 6732",
    "sg:postcode":"40123",
    "sg:province":"Bologna",
    "wof:name":"Chelli Alfredo & C. Sas",
    "wof:placetype":"venue"
},
  "geometry": {"coordinates":[11.337277,44.490314],"type":"Point"}
}