{
  "type": "Feature",
  "properties": {
    "addr:full":"09045 Quartu Sant'elena Cagliari 09045",
    "addr:postcode":"09045;09045",
    "iso:country":"IT",
    "sg:address":"09045 Quartu Sant'elena",
    "sg:orig_category":"Nautica. Automobili E Mezzi Di Trasporto",
    "sg:phone":"+39 070 805183",
    "sg:postcode":"09045",
    "sg:province":"Cagliari",
    "wof:name":"Nauticar S.r.l.",
    "wof:placetype":"venue"
},
  "geometry": {"coordinates":[9.304144,39.208817],"type":"Point"}
}