{
  "type": "Feature",
  "properties": {
    "addr:full":"00165 Roma Roma Roma 00165",
    "addr:postcode":"00165;00165",
    "iso:country":"IT",
    "sg:address":"00165 Roma",
    "sg:city":"Roma",
    "sg:orig_category":"Carni, Salumi E Pesci",
    "sg:phone":"+39 06 662 5185",
    "sg:postcode":"00165",
    "sg:province":"Roma",
    "wof:name":"Pezzatini Remo",
    "wof:placetype":"venue"
},
  "geometry": {"coordinates":[12.420355,41.896675],"type":"Point"}
}