{
  "type": "Feature",
  "properties": {
    "iso:country":"IT",
    "sg:address":"17, Via Francesco Baracca 20047 Brugherio",
    "sg:city":"Brugherio",
    "sg:classifiers":[
        {
            "category":"Professional",
            "subcategory":"Engineering",
            "type":"Services"
        }
    ],
    "sg:phone":"+39 039 287 3705",
    "sg:postcode":"20047",
    "sg:province":"Milano",
    "sg:tags":[
        "machine",
        "-",
        "mechanical"
    ],
    "wof:name":"Melli Automazione Sas Di Melli Costanza E C.",
    "wof:placetype":"venue"
},
  "geometry": {"coordinates":[9.269773,45.52692],"type":"Point"}
}