{
  "type": "Feature",
  "properties": {
    "addr:full":"04100 Latina Latina Latina 04100",
    "addr:postcode":"04100;04100",
    "iso:country":"IT",
    "sg:address":"04100 Latina",
    "sg:city":"Latina",
    "sg:orig_category":"Aspirapolvere E Lucidatrici Uso Domestico",
    "sg:phone":"+39 0773 602548",
    "sg:postcode":"04100",
    "sg:province":"Latina",
    "wof:name":"Start-point Sas",
    "wof:placetype":"venue"
},
  "geometry": {"coordinates":[12.877412,41.443981],"type":"Point"}
}