{
  "type": "Feature",
  "properties": {
    "addr:full":"1, Via Manzoni Luigi 31015 Conegliano Conegliano Treviso 31015",
    "addr:postcode":"31015;31015",
    "addr:street":"Via Manzoni Luigi",
    "iso:country":"IT",
    "sg:address":"1, Via Manzoni Luigi 31015 Conegliano",
    "sg:city":"Conegliano",
    "sg:classifiers":[
        {
            "category":"Manufacturing",
            "subcategory":"Rubber & Plastics",
            "type":"Manufacturing & Wholesale Goods"
        }
    ],
    "sg:phone":"+39 39043861336",
    "sg:postcode":"31015",
    "sg:province":"Treviso",
    "wof:name":"Unica Di Damian Francesco Luca & C. S.n.c.",
    "wof:placetype":"venue"
},
  "geometry": {"coordinates":[12.2420721054,45.6662864685],"type":"Point"}
}