{
  "type": "Feature",
  "properties": {
    "iso:country":"IT",
    "sg:address":"31033 Castelfranco Veneto",
    "sg:city":"Castelfranco Veneto",
    "sg:orig_category":"Servizi E Lavori Per Abbigliamento E Pelletterie",
    "sg:phone":"+39 0423 491836",
    "sg:postcode":"31033",
    "sg:province":"Treviso",
    "wof:name":"Rebellato Graziano Pellicceria Sas",
    "wof:placetype":"venue"
},
  "geometry": {"coordinates":[11.936238,45.669506],"type":"Point"}
}