{
  "type": "Feature",
  "properties": {
    "iso:country":"IT",
    "sg:address":"46100 Mantova",
    "sg:city":"Mantova",
    "sg:orig_category":"Manufacturers: Prefabbricati. Servizi E Lavori Per Ecologia E Smaltimento Rifiuti",
    "sg:phone":"+39 0376 399294",
    "sg:postcode":"46100",
    "sg:province":"Mantova",
    "wof:name":"Eurospurghi Di Martinelli Gian Pietro",
    "wof:placetype":"venue"
},
  "geometry": {"coordinates":[10.791869,45.182652],"type":"Point"}
}