{
  "type": "Feature",
  "properties": {
    "iso:country":"IT",
    "sg:address":"Via Cesare Battisti 97 31028 Vazzola",
    "sg:city":"Vazzola",
    "sg:classifiers":[
        {
            "category":"Shopping",
            "subcategory":"Stationery & Office Supplies",
            "type":"Retail Goods"
        }
    ],
    "sg:phone":"+39 0438 441368",
    "sg:postcode":"31028",
    "sg:province":"Treviso",
    "sg:tags":[
        "component",
        "furniture"
    ],
    "wof:name":"Castagner S.n.c.",
    "wof:placetype":"venue"
},
  "geometry": {"coordinates":[12.385571,45.845886],"type":"Point"}
}