{
  "type": "Feature",
  "properties": {
    "iso:country":"IT",
    "sg:address":"37019 Peschiera Del Garda",
    "sg:city":"Peschiera del Garda",
    "sg:orig_category":"Medicinali E Prodotti Parafarmaceutici. Prodotti Cosmetici E Da Toeletta",
    "sg:phone":"+39 045 755 0190",
    "sg:postcode":"37019",
    "sg:province":"Verona",
    "wof:name":"Erboristeria Zenatti Giovanni",
    "wof:placetype":"venue"
},
  "geometry": {"coordinates":[10.7001085281,45.4426078796],"type":"Point"}
}