{
  "type": "Feature",
  "properties": {
    "iso:country":"IT",
    "sg:address":"50019 Sesto Fiorentino",
    "sg:city":"Sesto Fiorentino",
    "sg:orig_category":"Apparecchiature Ed Attrezzature Meccaniche",
    "sg:phone":"+39 055 374691",
    "sg:postcode":"50019",
    "sg:province":"Firenze",
    "wof:name":"Oleodinamica Giannini S.r.l.",
    "wof:placetype":"venue"
},
  "geometry": {"coordinates":[11.175246,43.812374],"type":"Point"}
}