{
  "type": "Feature",
  "properties": {
    "iso:country":"IT",
    "sg:address":"42016 Guastalla",
    "sg:orig_category":"Avicoltura",
    "sg:phone":"+39 0522 831247",
    "sg:postcode":"42016",
    "sg:province":"Reggio Nell'Emilia",
    "wof:name":"Tabec Srl",
    "wof:placetype":"venue"
},
  "geometry": {"coordinates":[10.627794,44.696228],"type":"Point"}
}