{
  "type": "Feature",
  "properties": {
    "iso:country":"IT",
    "sg:address":"Via Starza 84013 Cava De' Tirreni",
    "sg:classifiers":[
        {
            "category":"Home & Garden",
            "subcategory":"Carpets & Floor Coverings",
            "type":"Retail Goods"
        }
    ],
    "sg:phone":"+39 089 466364",
    "sg:postcode":"84013",
    "sg:province":"Salerno",
    "sg:tags":[
        "glazed",
        "tiles",
        "hand-painted"
    ],
    "sg:website":"www.cottovietri.com",
    "wof:name":"Cotto Vietri Snc",
    "wof:placetype":"venue"
},
  "geometry": {"coordinates":[14.70853,40.720589],"type":"Point"}
}