{
  "type": "Feature",
  "properties": {
    "iso:country":"IT",
    "sg:address":"00169 Roma",
    "sg:city":"Roma",
    "sg:orig_category":"Prodotti Alimentari",
    "sg:phone":"+39 06 266957",
    "sg:postcode":"00169",
    "sg:province":"Roma",
    "wof:name":"Secondi Polzonetti",
    "wof:placetype":"venue"
},
  "geometry": {"coordinates":[12.5927305222,41.8671226501],"type":"Point"}
}