{
  "type": "Feature",
  "properties": {
    "iso:country":"IT",
    "sg:address":"81041 Vitulazio",
    "sg:city":"Vitulazio",
    "sg:orig_category":"Macchine, Impianti Ed Attrezzature Per Industria Alimentare E Bevande. Apparecchiature E Sistemi Per Imballaggio E Confezionamento",
    "sg:phone":"+39 0823 990035",
    "sg:postcode":"81041",
    "sg:province":"Caserta",
    "wof:name":"Zippo Gas S.n.c. Di Zippo Orsola E Mauro Maria Rosa",
    "wof:placetype":"venue"
},
  "geometry": {"coordinates":[14.216643,41.163921],"type":"Point"}
}