{
  "type": "Feature",
  "properties": {
    "iso:country":"IT",
    "sg:address":"00031 Artena",
    "sg:city":"Artena",
    "sg:orig_category":"Zootecnia E Pesca, Allevamento Piccoli Animali",
    "sg:phone":"+39 06 951 7785",
    "sg:postcode":"00031",
    "sg:province":"Roma",
    "wof:name":"Masella Rosaria",
    "wof:placetype":"venue"
},
  "geometry": {"coordinates":[12.915335,41.738762],"type":"Point"}
}