{
  "type": "Feature",
  "properties": {
    "iso:country":"IT",
    "sg:address":"00012 Guidonia Montecelio",
    "sg:city":"Guidonia",
    "sg:orig_category":"Scuole Di Ballo E Danza Classica E Moderna",
    "sg:phone":"+39 0774 365202",
    "sg:postcode":"00012",
    "sg:province":"Roma",
    "wof:name":"Dance Accademy",
    "wof:placetype":"venue"
},
  "geometry": {"coordinates":[12.625509,41.937199],"type":"Point"}
}