{
  "type": "Feature",
  "properties": {
    "iso:country":"IT",
    "sg:address":"21013 Gallarate",
    "sg:city":"Gallarate",
    "sg:classifiers":[
        {
            "category":"Retail",
            "subcategory":"Storage",
            "type":"Services"
        }
    ],
    "sg:phone":"+39 0331 785300",
    "sg:postcode":"21013",
    "sg:province":"Varese",
    "sg:tags":[
        "equipment",
        "handling",
        "system"
    ],
    "wof:name":"A.t.c.",
    "wof:placetype":"venue"
},
  "geometry": {"coordinates":[8.799751,45.680588],"type":"Point"}
}