{
  "type": "Feature",
  "properties": {
    "addr:full":"Via Struppa 300 16165 Genova Genova Genova 16165",
    "addr:housenumber":"300",
    "addr:postcode":"16165;16165",
    "addr:street":"Via Struppa",
    "iso:country":"IT",
    "sg:address":"Via Struppa 300 16165 Genova",
    "sg:city":"Genova",
    "sg:orig_category":"Philatelic Accessories",
    "sg:phone":"+39 010 802186",
    "sg:postcode":"16165",
    "sg:province":"Genova",
    "sg:website":"www.albummarini.com",
    "wof:name":"Ernesto Marini S.r.l.",
    "wof:placetype":"venue"
},
  "geometry": {"coordinates":[9.0207309723,44.4495429993],"type":"Point"}
}