{
  "type": "Feature",
  "properties": {
    "iso:country":"IT",
    "sg:address":"Via Fambrini 142 55029 Ponte A Moriano",
    "sg:classifiers":[
        {
            "category":"Personal",
            "subcategory":"Shoe Repair & Shine",
            "type":"Services"
        }
    ],
    "sg:phone":"+39 0583 406043",
    "sg:province":"LU",
    "sg:tags":[
        "sandal"
    ],
    "wof:name":"Lottini Srl",
    "wof:placetype":"venue"
},
  "geometry": {"coordinates":[10.531562,43.916965],"type":"Point"}
}