{
  "type": "Feature",
  "properties": {
    "iso:country":"IT",
    "sg:address":"Via Michelino 77 40127 Bologna",
    "sg:city":"Bologna",
    "sg:classifiers":[
        {
            "category":"Utilities",
            "subcategory":"Natural Gas",
            "type":"Services"
        }
    ],
    "sg:phone":"+39 051 511216",
    "sg:postcode":"40127",
    "sg:province":"Bologna",
    "sg:tags":[
        "burner",
        "central",
        "system",
        "heating"
    ],
    "sg:website":"www.bernini-impianti.it",
    "wof:name":"Bernini Impianti Srl",
    "wof:placetype":"venue"
},
  "geometry": {"coordinates":[11.374051,44.514774],"type":"Point"}
}