{
  "type": "Feature",
  "properties": {
    "iso:country":"IT",
    "sg:address":"36075 Montecchio Maggiore",
    "sg:city":"Montecchio Maggiore",
    "sg:orig_category":"Cine-foto-ottica",
    "sg:phone":"+39 0444 696533",
    "sg:postcode":"36075",
    "sg:province":"Vicenza",
    "wof:name":"Centro Ottico Carta Di Scarpa Srl Di Scarpa Stefania & C.",
    "wof:placetype":"venue"
},
  "geometry": {"coordinates":[11.448092,45.526699],"type":"Point"}
}