{
  "type": "Feature",
  "properties": {
    "iso:country":"IT",
    "sg:address":"47900 Rimini",
    "sg:city":"Rimini",
    "sg:classifiers":[
        {
            "category":"Professional",
            "subcategory":"Business Services",
            "type":"Services"
        }
    ],
    "sg:phone":"+39 0541 56000",
    "sg:postcode":"47900",
    "sg:province":"Rimini",
    "sg:tags":[
        "support",
        "companies",
        "events",
        "trade"
    ],
    "wof:name":"Grand Hotel Di Rimini",
    "wof:placetype":"venue"
},
  "geometry": {"coordinates":[12.552751,44.026459],"type":"Point"}
}