{
  "type": "Feature",
  "properties": {
    "iso:country":"IT",
    "sg:address":"Via Gualverio Michelangeli 3/b 05018 Orvieto",
    "sg:city":"Orvieto",
    "sg:classifiers":[
        {
            "category":"Social Services",
            "subcategory":"Child Care",
            "type":"Services"
        }
    ],
    "sg:phone":"+39 0763 342660",
    "sg:postcode":"05018",
    "sg:province":"Terni",
    "sg:tags":[
        "apparel",
        "children's"
    ],
    "sg:website":"www.michelangeli.it",
    "wof:name":"Michelangeli Bottega Snc",
    "wof:placetype":"venue"
},
  "geometry": {"coordinates":[12.069637,42.739304],"type":"Point"}
}