{
  "type": "Feature",
  "properties": {
    "addr:full":"73, Corso Europa 12051 Alba Alba Cuneo 12051",
    "addr:postcode":"12051;12051",
    "addr:street":"Corso Europa",
    "iso:country":"IT",
    "sg:address":"73, Corso Europa 12051 Alba",
    "sg:city":"Alba",
    "sg:classifiers":[
        {
            "category":"Professional",
            "subcategory":"Engineering",
            "type":"Services"
        }
    ],
    "sg:phone":"+39 0173 283703",
    "sg:postcode":"12051",
    "sg:province":"Cuneo",
    "sg:tags":[
        "machine",
        "-",
        "mechanical"
    ],
    "wof:name":"Progecta Srl",
    "wof:placetype":"venue"
},
  "geometry": {"coordinates":[8.074887,44.745422],"type":"Point"}
}