{
  "type": "Feature",
  "properties": {
    "iso:country":"IT",
    "sg:address":"00012 Villalba",
    "sg:city":"Villalba",
    "sg:orig_category":"Scuole E Servizi Scolastici",
    "sg:phone":"+39 0774 373206",
    "sg:postcode":"00012",
    "sg:province":"Roma",
    "wof:name":"Scuola Materna Sacro Cuore",
    "wof:placetype":"venue"
},
  "geometry": {"coordinates":[12.734568,41.955177],"type":"Point"}
}