{
  "type": "Feature",
  "properties": {
    "iso:country":"IT",
    "sg:address":"22100 Como",
    "sg:city":"Como",
    "sg:orig_category":"Prodotti E Manufatti In Materie Plastiche. Articoli Per Imballaggio E Confezionamento",
    "sg:phone":"+39 031 271180",
    "sg:postcode":"22100",
    "sg:province":"Como",
    "sg:website":"http://www.plastec.it",
    "wof:name":"Plast'ec Di Valli Fabrizio",
    "wof:placetype":"venue"
},
  "geometry": {"coordinates":[9.0854110718,45.8101196289],"type":"Point"}
}