{
  "type": "Feature",
  "properties": {
    "iso:country":"IT",
    "sg:address":"16138 Genova",
    "sg:city":"Genova",
    "sg:orig_category":"Radiatori Riscaldamento",
    "sg:phone":"+39 010 836 6448",
    "sg:postcode":"16138",
    "sg:province":"Genova",
    "wof:name":"Fp Snc Di Parodi Elio & C.",
    "wof:placetype":"venue"
},
  "geometry": {"coordinates":[8.974224,44.46497],"type":"Point"}
}