{
  "type": "Feature",
  "properties": {
    "addr:full":"138, Via Trieste 10080 Bosconero Bosconero Torino 10080",
    "addr:housenumber":"138",
    "addr:postcode":"10080;10080",
    "addr:street":"Via Trieste",
    "iso:country":"IT",
    "sg:address":"138, Via Trieste 10080 Bosconero",
    "sg:city":"Bosconero",
    "sg:classifiers":[
        {
            "category":"Real Estate",
            "subcategory":"Architect",
            "type":"Services"
        }
    ],
    "sg:phone":"+39 011 988 9797",
    "sg:postcode":"10080",
    "sg:province":"Torino",
    "sg:tags":[
        "textile",
        "clothing"
    ],
    "wof:name":"Gruppo Abbigliamento Piemontese Srl",
    "wof:placetype":"venue"
},
  "geometry": {"coordinates":[7.766674,45.262074],"type":"Point"}
}