{
  "type": "Feature",
  "properties": {
    "iso:country":"IT",
    "sg:address":"34135 Trieste",
    "sg:city":"Trieste",
    "sg:orig_category":"Elettronica Professionale E Di Consumo. Musica",
    "sg:phone":"+39 040 418706",
    "sg:postcode":"34135",
    "sg:province":"Trieste",
    "sg:website":"http://www.radioroselli.it",
    "wof:name":"Radio Roselli Sas Di C. Roselli & C.",
    "wof:placetype":"venue"
},
  "geometry": {"coordinates":[13.771684,45.661545],"type":"Point"}
}