{
  "type": "Feature",
  "properties": {
    "addr:full":"292, Via Fiume Vecchio 40062 Molinella Molinella Bologna 40062",
    "addr:housenumber":"292",
    "addr:postcode":"40062;40062",
    "addr:street":"Via Fiume Vecchio",
    "iso:country":"IT",
    "sg:address":"292, Via Fiume Vecchio 40062 Molinella",
    "sg:city":"Molinella",
    "sg:classifiers":[
        {
            "category":"Food & Beverages",
            "subcategory":"Groceries & Convenience Stores",
            "type":"Retail Goods"
        }
    ],
    "sg:phone":"+39 39051884020",
    "sg:postcode":"40062",
    "sg:province":"Bologna",
    "sg:tags":[
        "product",
        "related"
    ],
    "wof:name":"Agriilpa",
    "wof:placetype":"venue"
},
  "geometry": {"coordinates":[11.7322101593,44.6146621704],"type":"Point"}
}