{
  "type": "Feature",
  "properties": {
    "addr:full":"50, Via Delle Industrie 30020 Marcon Marcon Venezia 30020",
    "addr:postcode":"30020;30020",
    "addr:street":"Via Delle Industrie",
    "iso:country":"IT",
    "sg:address":"50, Via Delle Industrie 30020 Marcon",
    "sg:city":"Marcon",
    "sg:classifiers":[
        {
            "category":"Food & Beverages",
            "subcategory":"Groceries & Convenience Stores",
            "type":"Retail Goods"
        }
    ],
    "sg:phone":"+39 041 456 9377",
    "sg:postcode":"30020",
    "sg:province":"Venezia",
    "sg:tags":[
        "product",
        "related"
    ],
    "wof:name":"Giordani (s.p.a.)",
    "wof:placetype":"venue"
},
  "geometry": {"coordinates":[12.2921991348,45.5442008972],"type":"Point"}
}