{
  "type": "Feature",
  "properties": {
    "iso:country":"IT",
    "sg:address":"37129 Verona",
    "sg:city":"Verona",
    "sg:orig_category":"Medici Specialisti - Radiologia E Radioterapia",
    "sg:phone":"+39 045 594747",
    "sg:postcode":"37129",
    "sg:province":"Verona",
    "wof:name":"Squassabia Prof. Antonio",
    "wof:placetype":"venue"
},
  "geometry": {"coordinates":[11.004202,45.442753],"type":"Point"}
}