{
  "type": "Feature",
  "properties": {
    "iso:country":"IT",
    "sg:address":"153/2, Viale Marx Carlo 00137 Roma",
    "sg:city":"Roma",
    "sg:classifiers":[
        {
            "category":"Utilities",
            "subcategory":"Electric",
            "type":"Services"
        }
    ],
    "sg:phone":"+39 06 8689 5015",
    "sg:postcode":"00137",
    "sg:province":"Roma",
    "sg:tags":[
        "component",
        "electronic"
    ],
    "wof:name":"Sematron Italia Srl",
    "wof:placetype":"venue"
},
  "geometry": {"coordinates":[12.482325,41.895466],"type":"Point"}
}