{
  "type": "Feature",
  "properties": {
    "iso:country":"IT",
    "sg:address":"Via Sernaglia 74 31053 Pieve Di Soligo",
    "sg:city":"Pieve di Soligo",
    "sg:classifiers":[
        {
            "category":"Autos & Motor Vehicles",
            "subcategory":"Recreational Vehicle Sales",
            "type":"Retail Goods"
        }
    ],
    "sg:phone":"+39 0438 82354",
    "sg:postcode":"31053",
    "sg:province":"Treviso",
    "sg:tags":[
        "stretch-blow",
        "machine",
        "moulding"
    ],
    "sg:website":"www.gmp.it",
    "wof:name":"Gmp Commerciale Srl",
    "wof:placetype":"venue"
},
  "geometry": {"coordinates":[12.158564,45.890564],"type":"Point"}
}