{
  "type": "Feature",
  "properties": {
    "addr:full":"50, Via Madonna Della Catena 70010 Locorotondo Locorotondo Bari 70010",
    "addr:postcode":"70010;70010",
    "addr:street":"Via Madonna Della Catena",
    "iso:country":"IT",
    "sg:address":"50, Via Madonna Della Catena 70010 Locorotondo",
    "sg:city":"Locorotondo",
    "sg:classifiers":[
        {
            "category":"Real Estate",
            "subcategory":"Architect",
            "type":"Services"
        }
    ],
    "sg:phone":"+39 080 431 1799",
    "sg:postcode":"70010",
    "sg:province":"Bari",
    "sg:tags":[
        "textile",
        "clothing"
    ],
    "wof:name":"Confezioni Rapporto S.r.l.",
    "wof:placetype":"venue"
},
  "geometry": {"coordinates":[17.319239,40.755592],"type":"Point"}
}