{
  "type": "Feature",
  "properties": {
    "iso:country":"IT",
    "sg:address":"21014 Laveno Mombello",
    "sg:city":"Laveno",
    "sg:orig_category":"Servizi Al Turismo. Trasporto Pubblico E Privato",
    "sg:phone":"+39 0332 667128",
    "sg:postcode":"21014",
    "sg:province":"Varese",
    "wof:name":"Navigazione Lago Maggiore",
    "wof:placetype":"venue"
},
  "geometry": {"coordinates":[8.632118,45.903709],"type":"Point"}
}