{
  "type": "Feature",
  "properties": {
    "iso:country":"IT",
    "sg:address":"Via Val Di Cossu 07029 Tempio Pausania",
    "sg:city":"Tempio Pausania",
    "sg:classifiers":[
        {
            "category":"Food & Beverages",
            "subcategory":"Groceries & Convenience Stores",
            "type":"Retail Goods"
        }
    ],
    "sg:phone":"+39 39079671257",
    "sg:postcode":"07029",
    "sg:province":"Olbia-Tempio",
    "sg:tags":[
        "drink"
    ],
    "wof:name":"Cantina Sociale Gallura",
    "wof:placetype":"venue"
},
  "geometry": {"coordinates":[9.117414,40.903645],"type":"Point"}
}