{
  "type": "Feature",
  "properties": {
    "iso:country":"IT",
    "sg:address":"20096 Pioltello",
    "sg:city":"Pioltello",
    "sg:orig_category":"Agricoltura, Orticoltura E Floricoltura",
    "sg:phone":"+39 02 926 6517",
    "sg:postcode":"20096",
    "sg:province":"Milano",
    "wof:name":"Perfoods S.r.l.",
    "wof:placetype":"venue"
},
  "geometry": {"coordinates":[9.322072,45.49762],"type":"Point"}
}