{
  "type": "Feature",
  "properties": {
    "addr:full":"46047 Porto Mantovano Porto Mantovano Mantova 46047",
    "addr:postcode":"46047;46047",
    "iso:country":"IT",
    "sg:address":"46047 Porto Mantovano",
    "sg:city":"Porto Mantovano",
    "sg:orig_category":"Macchine Ed Impianti Per Edilizia E Lavori Pubblici",
    "sg:phone":"+39 0376 389611",
    "sg:postcode":"46047",
    "sg:province":"Mantova",
    "wof:name":"Gru Benedini Spa",
    "wof:placetype":"venue"
},
  "geometry": {"coordinates":[10.801211,45.17775],"type":"Point"}
}