{
  "type": "Feature",
  "properties": {
    "iso:country":"IT",
    "sg:address":"38068 Rovereto",
    "sg:city":"Rovereto",
    "sg:orig_category":"Accessori Dei Mezzi Di Trasporto",
    "sg:phone":"+39 0464 434218",
    "sg:postcode":"38068",
    "sg:province":"Trento",
    "wof:name":"Damiata Claudio",
    "wof:placetype":"venue"
},
  "geometry": {"coordinates":[11.04355,45.894974],"type":"Point"}
}