{
  "type": "Feature",
  "properties": {
    "iso:country":"IT",
    "sg:address":"Via Don Minzoni 6 20020 Lainate",
    "sg:city":"Lainate",
    "sg:orig_category":"Hand Lift Trucks",
    "sg:phone":"+39 02 9379 9212",
    "sg:postcode":"20020",
    "sg:province":"Milano",
    "sg:website":"www.valente.it",
    "wof:name":"Valente Spa",
    "wof:placetype":"venue"
},
  "geometry": {"coordinates":[9.049516,45.528084],"type":"Point"}
}