{
  "type": "Feature",
  "properties": {
    "addr:full":"1, Via Sapegno Natalino 91022 Castelvetrano Castelvetrano Trapani 91022",
    "addr:postcode":"91022;91022",
    "addr:street":"Via Sapegno Natalino",
    "iso:country":"IT",
    "sg:address":"1, Via Sapegno Natalino 91022 Castelvetrano",
    "sg:city":"Castelvetrano",
    "sg:classifiers":[
        {
            "category":"Food & Beverages",
            "subcategory":"Groceries & Convenience Stores",
            "type":"Retail Goods"
        }
    ],
    "sg:phone":"+39 0924 932152",
    "sg:postcode":"91022",
    "sg:province":"Trapani",
    "sg:tags":[
        "product",
        "related"
    ],
    "wof:name":"Demetra Srl",
    "wof:placetype":"venue"
},
  "geometry": {"coordinates":[12.5146341324,38.0185890198],"type":"Point"}
}