{
  "type": "Feature",
  "properties": {
    "iso:country":"IT",
    "sg:address":"25050 Passirano",
    "sg:city":"Passirano",
    "sg:classifiers":[
        {
            "category":"Manufacturing",
            "subcategory":"Metals",
            "type":"Manufacturing & Wholesale Goods"
        }
    ],
    "sg:phone":"+39 030 657 7115",
    "sg:postcode":"25050",
    "sg:province":"Brescia",
    "sg:tags":[
        "forming",
        "working",
        "welding"
    ],
    "sg:website":"http://www.isa-srl.com",
    "wof:name":"I.s.a. Srl",
    "wof:placetype":"venue"
},
  "geometry": {"coordinates":[10.0678329468,45.5997047424],"type":"Point"}
}