{
  "type": "Feature",
  "properties": {
    "iso:country":"IT",
    "sg:address":"Town Branch; Cesenatico; 47042",
    "sg:city":"Cesenatico",
    "sg:classifiers":[
        {
            "category":"Banks & Credit Unions",
            "subcategory":"Bank",
            "type":"Services"
        }
    ],
    "sg:phone":"+39 0547 83178",
    "sg:postcode":"47042",
    "sg:province":"Forl\u00ec-Cesena",
    "wof:name":"Banca Popolare Di Cesenatico",
    "wof:placetype":"venue"
},
  "geometry": {"coordinates":[12.349441,44.165012],"type":"Point"}
}