{
  "type": "Feature",
  "properties": {
    "iso:country":"IT",
    "sg:address":"22037 Ponte Lambro",
    "sg:city":"Ponte Lambro",
    "sg:orig_category":"Manufacturers: Prefabbricati",
    "sg:phone":"+39 031 623153",
    "sg:postcode":"22037",
    "sg:province":"Como",
    "wof:name":"Lattoneria Iodice",
    "wof:placetype":"venue"
},
  "geometry": {"coordinates":[9.225528,45.829159],"type":"Point"}
}