{
  "type": "Feature",
  "properties": {
    "iso:country":"IT",
    "sg:address":"5, Via Cavalcanti Guido 20127 Milano",
    "sg:city":"Milano",
    "sg:classifiers":[
        {
            "category":"Professional",
            "subcategory":"Computer Services",
            "type":"Services"
        }
    ],
    "sg:phone":"+39 39022831121",
    "sg:postcode":"20127",
    "sg:province":"Milano",
    "sg:tags":[
        "information",
        "technology"
    ],
    "wof:name":"Finson S.p.a.",
    "wof:placetype":"venue"
},
  "geometry": {"coordinates":[9.212998,45.49226],"type":"Point"}
}