{
  "type": "Feature",
  "properties": {
    "iso:country":"IT",
    "sg:address":"70121 Bari",
    "sg:city":"Bari",
    "sg:orig_category":"Prodotti Finiti Stampati. Forniture Per Uffici",
    "sg:phone":"+39 080 523 2211",
    "sg:postcode":"70121",
    "sg:province":"Bari",
    "wof:name":"Passiatore Ugo",
    "wof:placetype":"venue"
},
  "geometry": {"coordinates":[16.8719825745,41.0550880432],"type":"Point"}
}