{
  "type": "Feature",
  "properties": {
    "iso:country":"IT",
    "sg:address":"50144 Firenze",
    "sg:city":"Firenze",
    "sg:orig_category":"Abbigliamento - Vendita Al Dettaglio",
    "sg:phone":"+39 055 324 5074",
    "sg:postcode":"50144",
    "sg:province":"Firenze",
    "wof:name":"Climb Di Andrea Astorri",
    "wof:placetype":"venue"
},
  "geometry": {"coordinates":[11.229721,43.788986],"type":"Point"}
}