{
  "type": "Feature",
  "properties": {
    "iso:country":"IT",
    "sg:address":"Via Unione 22; Mezzago; 20050",
    "sg:city":"Mezzago",
    "sg:classifiers":[
        {
            "category":"Banks & Credit Unions",
            "subcategory":"Bank",
            "type":"Services"
        }
    ],
    "sg:phone":"+39 039 602 0670",
    "sg:postcode":"20050",
    "sg:province":"Milano",
    "wof:name":"Istituto Bancario, San Paolo Di Torino Spa",
    "wof:placetype":"venue"
},
  "geometry": {"coordinates":[9.443248,45.628696],"type":"Point"}
}