{
  "type": "Feature",
  "properties": {
    "iso:country":"IT",
    "sg:address":"41100 Modena",
    "sg:city":"Modena",
    "sg:orig_category":"Carta E Cartone - Produzione E Commercio",
    "sg:phone":"+39 059 251427",
    "sg:postcode":"41100",
    "sg:province":"Modena",
    "sg:website":"http://www.coopcartai.it",
    "wof:name":"C.c.m. Coop. Cartai Modenese Soc.coop.r.l.",
    "wof:placetype":"venue"
},
  "geometry": {"coordinates":[10.957465,44.652996],"type":"Point"}
}