{
  "type": "Feature",
  "properties": {
    "addr:full":"50019 Sesto Fiorentino Sesto Fiorentino Firenze 50019",
    "addr:postcode":"50019;50019",
    "iso:country":"IT",
    "sg:address":"50019 Sesto Fiorentino",
    "sg:city":"Sesto Fiorentino",
    "sg:orig_category":"Campeggio. Accessori Dei Mezzi Di Trasporto",
    "sg:phone":"+39 055 421 8726",
    "sg:postcode":"50019",
    "sg:province":"Firenze",
    "wof:name":"Teloneria Fiorentina Di Zani Gabriele E C.",
    "wof:placetype":"venue"
},
  "geometry": {"coordinates":[11.184494,43.829975],"type":"Point"}
}