{
  "type": "Feature",
  "properties": {
    "addr:full":"26, Viale Battisti Cesare 13900 Biella Biella Biella 13900",
    "addr:housenumber":"26",
    "addr:postcode":"13900;13900",
    "addr:street":"Viale Battisti Cesare",
    "iso:country":"IT",
    "sg:address":"26, Viale Battisti Cesare 13900 Biella",
    "sg:city":"Biella",
    "sg:orig_category":"Miscellaneous Products",
    "sg:phone":"+39 390 153 4141",
    "sg:postcode":"13900",
    "sg:province":"Biella",
    "wof:name":"Fila Sport (s.p.a.)",
    "wof:placetype":"venue"
},
  "geometry": {"coordinates":[8.0582695007,45.5628356934],"type":"Point"}
}