{
  "type": "Feature",
  "properties": {
    "addr:full":"10042 Nichelino Nichelino Torino 10042",
    "addr:postcode":"10042;10042",
    "iso:country":"IT",
    "sg:address":"10042 Nichelino",
    "sg:city":"Nichelino",
    "sg:orig_category":"Macchine E Forniture Per Arredamento E Industria Del Legno. Prodotti E Manufatti In Gomma",
    "sg:phone":"+39 011 627 4868",
    "sg:postcode":"10042",
    "sg:province":"Torino",
    "wof:name":"T.p.e. Di Rosas A.& C. S.a.s.",
    "wof:placetype":"venue"
},
  "geometry": {"coordinates":[7.643659,44.997768],"type":"Point"}
}