{
  "type": "Feature",
  "properties": {
    "addr:full":"50136 Firenze Firenze Firenze 50136",
    "addr:postcode":"50136;50136",
    "iso:country":"IT",
    "sg:address":"50136 Firenze",
    "sg:city":"Firenze",
    "sg:orig_category":"Servizi E Lavori Per Agricoltura E Zootecnia. Animali Domestici",
    "sg:phone":"+39 055 247 7859",
    "sg:postcode":"50136",
    "sg:province":"Firenze",
    "wof:name":"Toilette Per Cani Di Batazzi Corrado",
    "wof:placetype":"venue"
},
  "geometry": {"coordinates":[11.272955,43.772511],"type":"Point"}
}