{
  "type": "Feature",
  "properties": {
    "iso:country":"IT",
    "sg:address":"20090 Trezzano Sul Naviglio",
    "sg:city":"Trezzano sul Naviglio",
    "sg:orig_category":"Prodotti Chimici Secondari. Materiali Edili",
    "sg:phone":"+39 02 484 2041",
    "sg:postcode":"20090",
    "sg:province":"Milano",
    "wof:name":"M.p.m. Materiali Protettivi Milano S.p.a.",
    "wof:placetype":"venue"
},
  "geometry": {"coordinates":[9.0543861389,45.4166069031],"type":"Point"}
}