{
  "type": "Feature",
  "properties": {
    "iso:country":"IT",
    "sg:address":"37034 Verona",
    "sg:orig_category":"Servizi E Lavori Per Industria Alimentare E Bevande",
    "sg:phone":"+39 045 870 0193",
    "sg:province":"VR",
    "wof:name":"Mercatino Ortofrutta Stallavena",
    "wof:placetype":"venue"
},
  "geometry": {"coordinates":[-86.681252,35.629597],"type":"Point"}
}