{
  "type": "Feature",
  "properties": {
    "iso:country":"IT",
    "sg:address":"00189 Roma",
    "sg:city":"Roma",
    "sg:orig_category":"Servizi E Lavori Per Edilizia E Lavori Pubblici. Acqua, Luce, Gas E Societa' Di Esercizio Pubblico",
    "sg:phone":"+39 06 331 2748",
    "sg:postcode":"00189",
    "sg:province":"Roma",
    "wof:name":"Enel Societa' Per Azioni",
    "wof:placetype":"venue"
},
  "geometry": {"coordinates":[12.461404,41.961601],"type":"Point"}
}