{
  "type": "Feature",
  "properties": {
    "iso:country":"IT",
    "sg:address":"97019 Vittoria",
    "sg:city":"Vittoria",
    "sg:orig_category":"Macchine, Impianti Ed Attrezzature Per Agricoltura E Zootecnia. Forniture Per Agricoltura E Zootecnia",
    "sg:phone":"+39 0932 997211",
    "sg:postcode":"97019",
    "sg:province":"Ragusa",
    "sg:website":"http://www.agriplast.com",
    "wof:name":"Agriplast Srl",
    "wof:placetype":"venue"
},
  "geometry": {"coordinates":[14.495624,36.935825],"type":"Point"}
}