{
  "type": "Feature",
  "properties": {
    "iso:country":"IT",
    "sg:address":"80133 Napoli",
    "sg:city":"Napoli",
    "sg:orig_category":"Tessuti E Stoffe",
    "sg:phone":"+39 081 551 6729",
    "sg:postcode":"80133",
    "sg:province":"Napoli",
    "wof:name":"Fermo Valli Spa",
    "wof:placetype":"venue"
},
  "geometry": {"coordinates":[14.249557,40.8414],"type":"Point"}
}