{
  "type": "Feature",
  "properties": {
    "iso:country":"IT",
    "sg:address":"20121 Milano",
    "sg:city":"Milano",
    "sg:orig_category":"Servizi Editoriali. Shopping",
    "sg:phone":"+39 02 2901 0444",
    "sg:postcode":"20121",
    "sg:province":"Milano",
    "wof:name":"Libreria Antiquaria L'archivolto (s.a.s.)",
    "wof:placetype":"venue"
},
  "geometry": {"coordinates":[9.187426,45.478603],"type":"Point"}
}