{
  "type": "Feature",
  "properties": {
    "iso:country":"IT",
    "sg:address":"28883 Gravellona Toce",
    "sg:city":"Gravellona Toce",
    "sg:orig_category":"Manufacturers: Prefabbricati. Forniture Per Edilizia E Lavori Pubblici",
    "sg:phone":"+39 0323 840224",
    "sg:postcode":"28883",
    "sg:province":"Verbano-Cusio-Ossola",
    "sg:website":"http://www.inox-design.it",
    "wof:name":"Inox Design Srl",
    "wof:placetype":"venue"
},
  "geometry": {"coordinates":[8.432466,45.927917],"type":"Point"}
}