{
  "type": "Feature",
  "properties": {
    "iso:country":"IT",
    "sg:address":"00184 Roma",
    "sg:city":"Roma",
    "sg:orig_category":"Macchine E Forniture Per Industria Orafa E Per Orologeria",
    "sg:phone":"+39 06 474 7934",
    "sg:postcode":"00184",
    "sg:province":"Roma",
    "wof:name":"Marwel Watch Srl",
    "wof:placetype":"venue"
},
  "geometry": {"coordinates":[12.490626,41.895134],"type":"Point"}
}