{
  "type": "Feature",
  "properties": {
    "addr:full":"30135 Venezia Venezia Venezia 30135",
    "addr:postcode":"30135;30135",
    "iso:country":"IT",
    "sg:address":"30135 Venezia",
    "sg:city":"Venezia",
    "sg:orig_category":"Sport And Leisure, Services. Tourism, Services. Motor Vehicles, Auxiliary Services. Transport, Auxiliary Services",
    "sg:phone":"+39 041 522 3000",
    "sg:postcode":"30135",
    "sg:province":"Venezia",
    "wof:name":"Expressway Srl",
    "wof:placetype":"venue"
},
  "geometry": {"coordinates":[12.317584,45.438885],"type":"Point"}
}