{
  "type": "Feature",
  "properties": {
    "addr:full":"60027 Osimo Osimo Ancona 60027",
    "addr:postcode":"60027;60027",
    "iso:country":"IT",
    "sg:address":"60027 Osimo",
    "sg:city":"Osimo",
    "sg:orig_category":"Abbigliamento Esterno, Maglierie E Pelliccerie",
    "sg:phone":"+39 071 723 2004",
    "sg:postcode":"60027",
    "sg:province":"Ancona",
    "wof:name":"Prosperi Fabio",
    "wof:placetype":"venue"
},
  "geometry": {"coordinates":[13.475478,43.485538],"type":"Point"}
}