{
  "type": "Feature",
  "properties": {
    "iso:country":"IT",
    "sg:address":"35020 Due Carrare",
    "sg:city":"Due Carrare",
    "sg:orig_category":"Zootecnia E Pesca, Allevamento Piccoli Animali. Animali Domestici",
    "sg:phone":"+39 049 911 5009",
    "sg:postcode":"35020",
    "sg:province":"Padova",
    "wof:name":"Allevamento Pensione Smeraldo",
    "wof:placetype":"venue"
},
  "geometry": {"coordinates":[11.828417,45.283878],"type":"Point"}
}