{
  "type": "Feature",
  "properties": {
    "iso:country":"IT",
    "sg:address":"10128 Torino",
    "sg:city":"Torino",
    "sg:orig_category":"Non-classified Establishments",
    "sg:phone":"+39 011 541857",
    "sg:postcode":"10128",
    "sg:province":"Torino",
    "wof:name":"Kay Morrison Di Vianzone Luisella & C. S.a.s.",
    "wof:placetype":"venue"
},
  "geometry": {"coordinates":[7.668423,45.061428],"type":"Point"}
}