{
  "type": "Feature",
  "properties": {
    "iso:country":"IT",
    "sg:address":"20155 Milano",
    "sg:city":"Milano",
    "sg:orig_category":"Ricambi E Componenti Dei Mezzi Di Trasporto",
    "sg:phone":"+39 02 3921 1025",
    "sg:postcode":"20155",
    "sg:province":"Milano",
    "wof:name":"Cavauto Di Ligama Cinzia",
    "wof:placetype":"venue"
},
  "geometry": {"coordinates":[9.14943,45.492706],"type":"Point"}
}