{
  "type": "Feature",
  "properties": {
    "iso:country":"IT",
    "sg:address":"14, Strada Per Cavriana 46040 Guidizzolo",
    "sg:city":"Cavriana",
    "sg:classifiers":[
        {
            "category":"Shopping",
            "subcategory":"Clothing, Apparel, & Fashions",
            "type":"Retail Goods"
        }
    ],
    "sg:phone":"+39 0376 818740",
    "sg:postcode":"46040",
    "sg:province":"Mantova",
    "sg:tags":[
        "clothes"
    ],
    "wof:name":"Gafitex S.r.l.",
    "wof:placetype":"venue"
},
  "geometry": {"coordinates":[10.592373,45.320198],"type":"Point"}
}