{
  "type": "Feature",
  "properties": {
    "iso:country":"IT",
    "sg:address":"2, Via Battisti 21045 Gazzada Schianno",
    "sg:city":"Gazzada",
    "sg:classifiers":[
        {
            "category":"Manufacturing",
            "subcategory":"Rubber & Plastics",
            "type":"Manufacturing & Wholesale Goods"
        }
    ],
    "sg:phone":"+39 0332 462254",
    "sg:postcode":"21045",
    "sg:province":"Varese",
    "sg:tags":[
        "packaging",
        "material",
        "-"
    ],
    "wof:name":"Plastilux S.r.l.",
    "wof:placetype":"venue"
},
  "geometry": {"coordinates":[8.816781044,45.7697944641],"type":"Point"}
}