{
  "type": "Feature",
  "properties": {
    "iso:country":"IT",
    "sg:address":"Via Respighi 105 41100 Modena",
    "sg:city":"Modena",
    "sg:classifiers":[
        {
            "category":"Military Area",
            "subcategory":"Air Force Base",
            "type":"Public Place"
        }
    ],
    "sg:phone":"+39 059 364055",
    "sg:postcode":"41100",
    "sg:province":"Modena",
    "sg:tags":[
        "component",
        "elevator"
    ],
    "sg:website":"www.pfb.it",
    "wof:name":"P.f.b. Srl",
    "wof:placetype":"venue"
},
  "geometry": {"coordinates":[10.956989,44.63641],"type":"Point"}
}