{
  "type": "Feature",
  "properties": {
    "iso:country":"IT",
    "sg:address":"Forlimpopoli, Fo",
    "sg:classifiers":[
        {
            "category":"Banks & Credit Unions",
            "subcategory":"Bank",
            "type":"Services"
        }
    ],
    "wof:name":"Banca Romagna Centro-credito Cooperativo Scrl",
    "wof:placetype":"venue"
},
  "geometry": {"coordinates":[12.126752,44.18877],"type":"Point"}
}