{
  "type": "Feature",
  "properties": {
    "iso:country":"IT",
    "sg:address":"Via Oberdan 4 40055 Villanova",
    "sg:city":"Villanova",
    "sg:classifiers":[
        {
            "category":"Professional",
            "subcategory":"Art Services",
            "type":"Services"
        }
    ],
    "sg:phone":"+39 051 605 3194",
    "sg:postcode":"40055",
    "sg:province":"Bologna",
    "sg:tags":[
        "print"
    ],
    "sg:website":"www.webitaliasrl.it",
    "wof:name":"Web Italia Srl",
    "wof:placetype":"venue"
},
  "geometry": {"coordinates":[11.422606,44.497742],"type":"Point"}
}