{
  "type": "Feature",
  "properties": {
    "iso:country":"IT",
    "sg:address":"Via Casale 42035 Castelnovo Ne' Monti",
    "sg:classifiers":[
        {
            "category":"Food & Beverages",
            "subcategory":"Dairy",
            "type":"Retail Goods"
        }
    ],
    "sg:phone":"+39 0522 812069",
    "sg:postcode":"42035",
    "sg:province":"Reggio Nell'Emilia",
    "sg:tags":[
        "product"
    ],
    "wof:name":"Latteria Sociale Casale Di Bismantova",
    "wof:placetype":"venue"
},
  "geometry": {"coordinates":[10.428454,44.418591],"type":"Point"}
}