{
  "type": "Feature",
  "properties": {
    "iso:country":"IT",
    "sg:address":"Via Cavera 21 20034 Giussano",
    "sg:city":"Giussano",
    "sg:classifiers":[
        {
            "category":"Manufacturing",
            "subcategory":"Electronics",
            "type":"Manufacturing & Wholesale Goods"
        }
    ],
    "sg:phone":"+39 036 285 2055",
    "sg:postcode":"20034",
    "sg:province":"Milano",
    "sg:tags":[
        "large",
        "machine",
        "industrial",
        "electrical",
        "equipment"
    ],
    "sg:website":"www.montele.it",
    "wof:name":"Mont - Ele Srl",
    "wof:placetype":"venue"
},
  "geometry": {"coordinates":[9.206588,45.699753],"type":"Point"}
}