{
  "type": "Feature",
  "properties": {
    "iso:country":"IT",
    "sg:address":"Viale Europa 9 24048 Treviolo",
    "sg:city":"Treviolo",
    "sg:classifiers":[
        {
            "category":"Banks & Credit Unions",
            "subcategory":"Investment Brokerage",
            "type":"Services"
        }
    ],
    "sg:phone":"+39 035 691220",
    "sg:postcode":"24048",
    "sg:province":"Bergamo",
    "sg:tags":[
        "slat",
        "bed"
    ],
    "sg:website":"www.veraflex.it",
    "wof:name":"Veraflex",
    "wof:placetype":"venue"
},
  "geometry": {"coordinates":[9.632571,45.67654],"type":"Point"}
}