{
  "type": "Feature",
  "properties": {
    "iso:country":"IT",
    "sg:address":"Via Girardini E Tonello 8 31046 Oderzo",
    "sg:city":"Oderzo",
    "sg:classifiers":[
        {
            "category":"Banks & Credit Unions",
            "subcategory":"Bureau De Change",
            "type":"Services"
        }
    ],
    "sg:phone":"+39 0422 712519",
    "sg:postcode":"31046",
    "sg:province":"Treviso",
    "sg:tags":[
        "solid",
        "rubber",
        "tyre"
    ],
    "wof:name":"Bruno Momesso Emporio Gomme",
    "wof:placetype":"venue"
},
  "geometry": {"coordinates":[12.510504,45.794868],"type":"Point"}
}