{
  "type": "Feature",
  "properties": {
    "iso:country":"IT",
    "sg:address":"24066 Pedrengo",
    "sg:city":"Pedrengo",
    "sg:orig_category":"Arredamenti - Produzione E Ingrosso",
    "sg:phone":"+39 035 665858",
    "sg:postcode":"24066",
    "sg:province":"Bergamo",
    "sg:website":"http://www.benignimobili.com",
    "wof:name":"Benigni Mobili Snc",
    "wof:placetype":"venue"
},
  "geometry": {"coordinates":[9.74449,45.696342],"type":"Point"}
}