{
  "type": "Feature",
  "properties": {
    "iso:country":"IT",
    "sg:address":"1, Via Traversagna 56019 Vecchiano",
    "sg:city":"Vecchiano",
    "sg:classifiers":[
        {
            "category":"Shopping",
            "subcategory":"Clothing, Apparel, & Fashions",
            "type":"Retail Goods"
        }
    ],
    "sg:phone":"+39 39050804494",
    "sg:postcode":"56019",
    "sg:province":"Pisa",
    "sg:tags":[
        "clothes"
    ],
    "wof:name":"Dominique & Jacqueline (s.r.l.)",
    "wof:placetype":"venue"
},
  "geometry": {"coordinates":[10.357233,43.803593],"type":"Point"}
}