{
  "type": "Feature",
  "properties": {
    "iso:country":"IT",
    "sg:address":"24060 Brusaporto",
    "sg:city":"Brusaporto",
    "sg:orig_category":"Detergenti Industriali",
    "sg:phone":"+39 035 682488",
    "sg:postcode":"24060",
    "sg:province":"Bergamo",
    "wof:name":"Deterchimica Snc Di Cutroni Antonio & Figlo",
    "wof:placetype":"venue"
},
  "geometry": {"coordinates":[9.745475,45.667049],"type":"Point"}
}