{
  "type": "Feature",
  "properties": {
    "iso:country":"IT",
    "sg:address":"183, V. Del Lavoro 81055 Santa Maria Capua Vetere",
    "sg:city":"Santa Maria Capua Vetere",
    "sg:classifiers":[
        {
            "category":"Food & Beverages",
            "subcategory":"Dairy",
            "type":"Retail Goods"
        }
    ],
    "sg:phone":"+39 0823 798111",
    "sg:postcode":"81055",
    "sg:province":"Caserta",
    "sg:tags":[
        "product"
    ],
    "sg:website":"http://www.paginegialle.it/labuonacremeria",
    "wof:name":"Caseificio La Buona Cremeria",
    "wof:placetype":"venue"
},
  "geometry": {"coordinates":[14.241207,41.088371],"type":"Point"}
}