{
  "type": "Feature",
  "properties": {
    "addr:full":"5, Via Girardina 36066 Sandrigo Sandrigo Vicenza 36066",
    "addr:postcode":"36066;36066",
    "addr:street":"Via Girardina",
    "iso:country":"IT",
    "sg:address":"5, Via Girardina 36066 Sandrigo",
    "sg:city":"Sandrigo",
    "sg:classifiers":[
        {
            "category":"Shopping",
            "subcategory":"Jewelry",
            "type":"Retail Goods"
        }
    ],
    "sg:phone":"+39 0444 658013",
    "sg:postcode":"36066",
    "sg:province":"Vicenza",
    "sg:tags":[
        "jewellery"
    ],
    "wof:name":"Vilor (s.r.l.)",
    "wof:placetype":"venue"
},
  "geometry": {"coordinates":[11.60085,45.658436],"type":"Point"}
}