{
  "type": "Feature",
  "properties": {
    "addr:full":"16149 Genova Genova Genova 16149",
    "addr:postcode":"16149;16149",
    "iso:country":"IT",
    "sg:address":"16149 Genova",
    "sg:city":"Genova",
    "sg:orig_category":"Ospedali E Servizi Sanitari",
    "sg:phone":"+39 010 469 5808",
    "sg:postcode":"16149",
    "sg:province":"Genova",
    "wof:name":"Reale Dr. Hc Nunzio",
    "wof:placetype":"venue"
},
  "geometry": {"coordinates":[8.889291,44.412804],"type":"Point"}
}