{
  "type": "Feature",
  "properties": {
    "iso:country":"IT",
    "sg:address":"24060 San Paolo D'argon",
    "sg:orig_category":"Macchine Ed Impianti Per Edilizia E Lavori Pubblici",
    "sg:phone":"+39 035 959405",
    "sg:postcode":"24060",
    "sg:province":"Bergamo",
    "wof:name":"Tecnovema Srl",
    "wof:placetype":"venue"
},
  "geometry": {"coordinates":[9.794329,45.679577],"type":"Point"}
}