{
  "type": "Feature",
  "properties": {
    "iso:country":"IT",
    "sg:address":"Via Vecchia 170 43019 Soragna",
    "sg:city":"Soragna",
    "sg:classifiers":[
        {
            "category":"Wholesale",
            "subcategory":"Construction Materials",
            "type":"Manufacturing & Wholesale Goods"
        }
    ],
    "sg:phone":"+39 0524 597072",
    "sg:postcode":"43019",
    "sg:province":"Parma",
    "sg:tags":[
        "mould",
        "injection"
    ],
    "sg:website":"www.odag.it",
    "wof:name":"Odag Snc",
    "wof:placetype":"venue"
},
  "geometry": {"coordinates":[10.329548,44.807865],"type":"Point"}
}