{
  "type": "Feature",
  "properties": {
    "addr:full":"Via Paterno 00010 Villa Adriana Villa Adriana Roma 00010",
    "addr:postcode":"00010;00010",
    "addr:street":"Via Paterno;Adriana Villa;Roma",
    "iso:country":"IT",
    "sg:address":"Via Paterno 00010 Villa Adriana",
    "sg:city":"Villa Adriana",
    "sg:classifiers":[
        {
            "category":"Manufacturing",
            "subcategory":"Tools & Machinery",
            "type":"Manufacturing & Wholesale Goods"
        }
    ],
    "sg:phone":"+39 0774 381558",
    "sg:postcode":"00010",
    "sg:province":"Roma",
    "sg:tags":[
        "diamond"
    ],
    "wof:name":"Uds Utensili Diamantati Srl",
    "wof:placetype":"venue"
},
  "geometry": {"coordinates":[12.777671,41.960602],"type":"Point"}
}