{
  "type": "Feature",
  "properties": {
    "iso:country":"IT",
    "sg:address":"20025 Legnano",
    "sg:city":"Legnano",
    "sg:orig_category":"Agenzie D'affari E Servizi Commerciali",
    "sg:phone":"+39 0331 520218",
    "sg:postcode":"20025",
    "sg:province":"Milano",
    "sg:website":"http://www.erif.it",
    "wof:name":"Edil Rhodense Srl",
    "wof:placetype":"venue"
},
  "geometry": {"coordinates":[8.903826,45.590061],"type":"Point"}
}