{
  "type": "Feature",
  "properties": {
    "iso:country":"IT",
    "sg:address":"18, Via Nazionale 24060 Vigano San Martino",
    "sg:city":"Vigano San Martino",
    "sg:classifiers":[
        {
            "category":"Manufacturing",
            "subcategory":"Rubber & Plastics",
            "type":"Manufacturing & Wholesale Goods"
        }
    ],
    "sg:phone":"+39 39035822323",
    "sg:postcode":"24060",
    "sg:province":"Bergamo",
    "wof:name":"Euroart (srl)",
    "wof:placetype":"venue"
},
  "geometry": {"coordinates":[9.8917961121,45.7201004028],"type":"Point"}
}