{
  "type": "Feature",
  "properties": {
    "iso:country":"IT",
    "sg:address":"50139 Firenze",
    "sg:city":"Firenze",
    "sg:orig_category":"Imprese Di Costruzioni Civili Ed Industriali",
    "sg:phone":"+39 055 488990",
    "sg:postcode":"50139",
    "sg:province":"Firenze",
    "wof:name":"Monducci Paolo",
    "wof:placetype":"venue"
},
  "geometry": {"coordinates":[11.247929,43.794861],"type":"Point"}
}