{
  "type": "Feature",
  "properties": {
    "addr:full":"23100 Sondrio Sondrio Sondrio 23100",
    "addr:postcode":"23100;23100",
    "iso:country":"IT",
    "sg:address":"23100 Sondrio",
    "sg:city":"Sondrio",
    "sg:orig_category":"Agenzie D'affari E Servizi Commerciali",
    "sg:phone":"+39 800 117 766",
    "sg:postcode":"23100",
    "sg:province":"Sondrio",
    "wof:name":"Pec - Pronto Emergenza Casa Srl",
    "wof:placetype":"venue"
},
  "geometry": {"coordinates":[9.875048,46.169716],"type":"Point"}
}