{
  "type": "Feature",
  "properties": {
    "iso:country":"IT",
    "sg:address":"00132 Roma",
    "sg:city":"Roma",
    "sg:orig_category":"Macchine E Forniture Per Ecologia E Smaltimento Rifiuti",
    "sg:phone":"+39 06 207 3033",
    "sg:postcode":"00132",
    "sg:province":"Roma",
    "wof:name":"Italservizi 2000 Srl",
    "wof:placetype":"venue"
},
  "geometry": {"coordinates":[12.6947,41.863499],"type":"Point"}
}