{
  "type": "Feature",
  "properties": {
    "iso:country":"IT",
    "sg:address":"11, Via Volta Alessandro 39100 Bolzano",
    "sg:city":"Bolzano",
    "sg:classifiers":[
        {
            "category":"Manufacturing",
            "subcategory":"Metals",
            "type":"Manufacturing & Wholesale Goods"
        }
    ],
    "sg:phone":"+39 0471 203481",
    "sg:postcode":"39100",
    "sg:province":"Bolzano/Bozen",
    "sg:tags":[
        "metallurgy",
        "metalworking"
    ],
    "wof:name":"Alcoa Italia Spa",
    "wof:placetype":"venue"
},
  "geometry": {"coordinates":[11.3282394409,46.461643219],"type":"Point"}
}