{
  "type": "Feature",
  "properties": {
    "iso:country":"IT",
    "sg:address":"90147 Palermo",
    "sg:city":"Palermo",
    "sg:orig_category":"Materassi - Vendita Al Dettaglio",
    "sg:phone":"+39 091 679 1766",
    "sg:postcode":"90147",
    "sg:province":"Palermo",
    "sg:website":"http://www.rimark.it",
    "wof:name":"Rimark Srl",
    "wof:placetype":"venue"
},
  "geometry": {"coordinates":[13.313894,38.162819],"type":"Point"}
}