{
  "type": "Feature",
  "properties": {
    "iso:country":"IT",
    "sg:address":"25011 Calcinato",
    "sg:city":"Calcinato",
    "sg:orig_category":"Metalli E Leghe",
    "sg:postcode":"25011",
    "sg:province":"Brescia",
    "wof:name":"Cori Engineering (s.p.a.)",
    "wof:placetype":"venue"
},
  "geometry": {"coordinates":[10.2230758667,45.5343208313],"type":"Point"}
}