{
  "type": "Feature",
  "properties": {
    "iso:country":"IT",
    "sg:address":"41012 Carpi",
    "sg:city":"Carpi",
    "sg:orig_category":"Forniture Per Abbigliamento E Pelletterie. Forniture Per Attivita' Commerciali Ed Artigianali",
    "sg:phone":"+39 059 689032",
    "sg:postcode":"41012",
    "sg:province":"Modena",
    "wof:name":"Carpitex Srl",
    "wof:placetype":"venue"
},
  "geometry": {"coordinates":[10.8936758041,44.796836853],"type":"Point"}
}