{
  "type": "Feature",
  "properties": {
    "iso:country":"IT",
    "sg:address":"20159 Milano",
    "sg:city":"Milano",
    "sg:orig_category":"Abbigliamento Esterno, Maglierie E Pelliccerie",
    "sg:phone":"+39 02 6078 1035",
    "sg:postcode":"20159",
    "sg:province":"Milano",
    "sg:website":"http://www.ilmondodelbebe.com",
    "wof:name":"Il Mondo Del Beb\u00c8",
    "wof:placetype":"venue"
},
  "geometry": {"coordinates":[9.191761,45.498196],"type":"Point"}
}