{
  "type": "Feature",
  "properties": {
    "addr:full":"50145 Firenze Firenze Firenze 50145",
    "addr:postcode":"50145;50145",
    "iso:country":"IT",
    "sg:address":"50145 Firenze",
    "sg:city":"Firenze",
    "sg:classifiers":[
        {
            "category":"Home & Garden",
            "subcategory":"Carpets & Floor Coverings",
            "type":"Retail Goods"
        }
    ],
    "sg:phone":"+39 055 310522",
    "sg:postcode":"50145",
    "sg:province":"Firenze",
    "sg:tags":[
        "curtain",
        "material",
        "fabric",
        "fabrics",
        "furnishing"
    ],
    "wof:name":"Stock Style 2000 Srl",
    "wof:placetype":"venue"
},
  "geometry": {"coordinates":[11.1821937561,43.7967224121],"type":"Point"}
}