{
  "type": "Feature",
  "properties": {
    "iso:country":"IT",
    "sg:address":"92/94, V. Milano 59013 Montemurlo",
    "sg:city":"Montemurlo",
    "sg:classifiers":[
        {
            "category":"Professional",
            "subcategory":"Engineering",
            "type":"Services"
        }
    ],
    "sg:phone":"+39 0574 798256",
    "sg:postcode":"59013",
    "sg:province":"Prato",
    "sg:tags":[
        "machine",
        "-",
        "mechanical"
    ],
    "sg:website":"http://www.vanniniofficina.it",
    "wof:name":"Officina Meccanica Vannini Snc",
    "wof:placetype":"venue"
},
  "geometry": {"coordinates":[11.031035,43.91114],"type":"Point"}
}