{
  "type": "Feature",
  "properties": {
    "iso:country":"IT",
    "sg:address":"33044 Manzano",
    "sg:city":"Manzano",
    "sg:orig_category":"Arredamenti - Produzione E Ingrosso",
    "sg:phone":"+39 0432 755115",
    "sg:postcode":"33044",
    "sg:province":"Udine",
    "wof:name":"Don Claudio & C. Snc",
    "wof:placetype":"venue"
},
  "geometry": {"coordinates":[13.362626,45.98328],"type":"Point"}
}