{
  "type": "Feature",
  "properties": {
    "iso:country":"IT",
    "sg:address":"Via Nazionale 138; S. Giacomo Di Teglio",
    "sg:classifiers":[
        {
            "category":"Banks & Credit Unions",
            "subcategory":"Bank",
            "type":"Services"
        }
    ],
    "sg:phone":"+39 0342 786077",
    "wof:name":"Credito Valtellinese Scarl",
    "wof:placetype":"venue"
},
  "geometry": {"coordinates":[10.000202,46.164715],"type":"Point"}
}