{
  "type": "Feature",
  "properties": {
    "addr:full":"Via Dell' Artigianato 60019 Senigallia Senigallia Ancona 60019",
    "addr:postcode":"60019;60019",
    "addr:street":"Via Dell ' Artigianato",
    "iso:country":"IT",
    "sg:address":"Via Dell' Artigianato 60019 Senigallia",
    "sg:city":"Senigallia",
    "sg:classifiers":[
        {
            "category":"Building & Trades",
            "subcategory":"Construction",
            "type":"Services"
        }
    ],
    "sg:phone":"+39 071 792 2934",
    "sg:postcode":"60019",
    "sg:province":"Ancona",
    "sg:tags":[
        "work",
        "public"
    ],
    "wof:name":"Elisport Costruzioni S.r.l.",
    "wof:placetype":"venue"
},
  "geometry": {"coordinates":[13.201488,43.693195],"type":"Point"}
}