{
  "type": "Feature",
  "properties": {
    "iso:country":"IT",
    "sg:address":"14042 Calamandrana",
    "sg:city":"Calamandrana",
    "sg:orig_category":"Bevande, Vini E Liquori. Shopping",
    "sg:phone":"+39 0141 769025",
    "sg:postcode":"14042",
    "sg:province":"Asti",
    "wof:name":"Lovisolo Vincenzo So.vi.pi. Di Lovisolo Massimo & C. Sas",
    "wof:placetype":"venue"
},
  "geometry": {"coordinates":[8.339851,44.738129],"type":"Point"}
}