{
  "type": "Feature",
  "properties": {
    "iso:country":"IT",
    "sg:address":"95039 Trecastagni",
    "sg:city":"Trecastagni",
    "sg:orig_category":"Studi E Consulenze Tecniche E Industriali. Servizi E Lavori Per Edilizia E Lavori Pubblici. Professionisti - Studi E Servizi Ed Associazioni Di Interesse Aziendale",
    "sg:phone":"+39 095 780 6307",
    "sg:postcode":"95039",
    "sg:province":"Catania",
    "wof:name":"Studio Tecnico Associato Nicolosi",
    "wof:placetype":"venue"
},
  "geometry": {"coordinates":[15.091653,37.607742],"type":"Point"}
}