{
  "type": "Feature",
  "properties": {
    "addr:full":"31037 Loria Loria Treviso 31037",
    "addr:postcode":"31037;31037",
    "iso:country":"IT",
    "sg:address":"31037 Loria",
    "sg:city":"Loria",
    "sg:orig_category":"Materassi - Produzione E Ingrosso",
    "sg:phone":"+39 0423 470621",
    "sg:postcode":"31037",
    "sg:province":"Treviso",
    "sg:website":"http://www.linearete.com",
    "wof:name":"Linea Rete Snc",
    "wof:placetype":"venue"
},
  "geometry": {"coordinates":[11.822401,45.718483],"type":"Point"}
}