{
  "type": "Feature",
  "properties": {
    "addr:full":"20154 Milano Milano Milano 20154",
    "addr:postcode":"20154;20154",
    "iso:country":"IT",
    "sg:address":"20154 Milano",
    "sg:city":"Milano",
    "sg:orig_category":"Servizi E Lavori Per Abbigliamento E Pelletterie",
    "sg:phone":"+39 02 317776",
    "sg:postcode":"20154",
    "sg:province":"Milano",
    "wof:name":"Vulpio Irene",
    "wof:placetype":"venue"
},
  "geometry": {"coordinates":[9.173913,45.479134],"type":"Point"}
}