{
  "type": "Feature",
  "properties": {
    "addr:full":"Corso Italia; Gesualdo; 83040 Gesualdo Avellino 83040",
    "addr:postcode":"83040;83040",
    "addr:street":"Corso Italia",
    "iso:country":"IT",
    "sg:address":"Corso Italia; Gesualdo; 83040",
    "sg:city":"Gesualdo",
    "sg:classifiers":[
        {
            "category":"Banks & Credit Unions",
            "subcategory":"Bank",
            "type":"Services"
        }
    ],
    "sg:phone":"+39 0825 401421",
    "sg:postcode":"83040",
    "sg:province":"Avellino",
    "wof:name":"Banca Popolare Dell'irpinia Scarl",
    "wof:placetype":"venue"
},
  "geometry": {"coordinates":[15.073034,41.006466],"type":"Point"}
}