{
  "type": "Feature",
  "properties": {
    "addr:full":"Via Verro Bernardino 31 20141 Milano Milano Milano 20141",
    "addr:housenumber":"31",
    "addr:postcode":"20141;20141",
    "addr:street":"Via Verro Bernardino",
    "iso:country":"IT",
    "sg:address":"Via Verro Bernardino 31 20141 Milano",
    "sg:city":"Milano",
    "sg:orig_category":"Foundry Tools",
    "sg:phone":"+39 02 843 7380",
    "sg:postcode":"20141",
    "sg:province":"Milano",
    "wof:name":"L.t.i. Srl",
    "wof:placetype":"venue"
},
  "geometry": {"coordinates":[9.1900234222,45.4400444031],"type":"Point"}
}