{
  "type": "Feature",
  "properties": {
    "addr:full":"21042 Caronno Pertusella Caronno Pertusella Varese 21042",
    "addr:postcode":"21042;pertusella;21042",
    "addr:street":"Pertusella",
    "iso:country":"IT",
    "sg:address":"21042 Caronno Pertusella",
    "sg:city":"Caronno Pertusella",
    "sg:orig_category":"Prodotti E Manufatti In Materie Plastiche",
    "sg:phone":"+39 02 963 9921",
    "sg:postcode":"21042",
    "sg:province":"Varese",
    "wof:name":"Benasedo S.p.a.",
    "wof:placetype":"venue"
},
  "geometry": {"coordinates":[9.0344696045,45.5993309021],"type":"Point"}
}