{
  "type": "Feature",
  "properties": {
    "iso:country":"IT",
    "sg:address":"16149 Genova",
    "sg:city":"Genova",
    "sg:orig_category":"Asciugamani Elettrici Ad Aria, Automatici Di Tela E Carta",
    "sg:phone":"+39 010 645 8799",
    "sg:postcode":"16149",
    "sg:province":"Genova",
    "sg:website":"http://www.paredes.fr",
    "wof:name":"Paredes Italia Srl",
    "wof:placetype":"venue"
},
  "geometry": {"coordinates":[8.890163,44.411766],"type":"Point"}
}