{
  "type": "Feature",
  "properties": {
    "addr:full":"80044 Ottaviano Ottaviano Napoli 80044",
    "addr:postcode":"80044;80044",
    "iso:country":"IT",
    "sg:address":"80044 Ottaviano",
    "sg:city":"Ottaviano",
    "sg:classifiers":[
        {
            "category":"Home & Garden",
            "subcategory":"Carpets & Floor Coverings",
            "type":"Retail Goods"
        }
    ],
    "sg:phone":"+39 081 827 0489",
    "sg:postcode":"80044",
    "sg:province":"Napoli",
    "sg:tags":[
        "building",
        "supply",
        "civil",
        "industry",
        "furnishing",
        "curtain",
        "works",
        "fabrics",
        "carpets"
    ],
    "wof:name":"Faepflex Srl",
    "wof:placetype":"venue"
},
  "geometry": {"coordinates":[14.4781532288,40.8388938904],"type":"Point"}
}