{
  "type": "Feature",
  "properties": {
    "iso:country":"IT",
    "sg:address":"88046 Lamezia Terme",
    "sg:city":"Lamezia Terme",
    "sg:orig_category":"Macchine, Impianti Ed Attrezzature Per Agricoltura E Zootecnia",
    "sg:phone":"+39 0968 462572",
    "sg:postcode":"88046",
    "sg:province":"Catanzaro",
    "wof:name":"Agrinova Sas",
    "wof:placetype":"venue"
},
  "geometry": {"coordinates":[16.275751,38.93362],"type":"Point"}
}