{
  "type": "Feature",
  "properties": {
    "iso:country":"IT",
    "sg:address":"10040 Volvera",
    "sg:city":"Volvera",
    "sg:orig_category":"Attrezzature E Forniture Per Officine Riparazione E Servizi Ausiliari",
    "sg:phone":"+39 011 990 6139",
    "sg:postcode":"10040",
    "sg:province":"Torino",
    "wof:name":"Sistem Snc",
    "wof:placetype":"venue"
},
  "geometry": {"coordinates":[7.527368,44.985992],"type":"Point"}
}