{
  "type": "Feature",
  "properties": {
    "addr:full":"19 Via Tesoro, 88841 Isola Di Capo Rizzuto Isola di Capo Rizzuto Crotone 88841",
    "addr:postcode":"88841;88841",
    "addr:street":"Via Tesoro",
    "iso:country":"IT",
    "sg:address":"19 Via Tesoro, 88841 Isola Di Capo Rizzuto",
    "sg:city":"Isola di Capo Rizzuto",
    "sg:classifiers":[
        {
            "category":"Banks & Credit Unions",
            "subcategory":"Financial Services",
            "type":"Services"
        }
    ],
    "sg:phone":"+39 0962 791062",
    "sg:postcode":"88841",
    "sg:province":"Crotone",
    "sg:tags":[
        "banking",
        "finance",
        "insurance"
    ],
    "wof:name":"Banca Di Credito Cooperativo Di Isola Capo Rizzuto Srl",
    "wof:placetype":"venue"
},
  "geometry": {"coordinates":[17.0794353485,38.9953765869],"type":"Point"}
}