{
  "type": "Feature",
  "properties": {
    "iso:country":"IT",
    "sg:address":"Piazza S. Gregorio 8/10; Basiano; 20060",
    "sg:city":"Basiano",
    "sg:classifiers":[
        {
            "category":"Banks & Credit Unions",
            "subcategory":"Bank",
            "type":"Services"
        }
    ],
    "sg:phone":"+39 02 9576 1759",
    "sg:postcode":"20060",
    "sg:province":"Milano",
    "wof:name":"Istituto Bancario, San Paolo Di Torino Spa",
    "wof:placetype":"venue"
},
  "geometry": {"coordinates":[9.467254,45.573845],"type":"Point"}
}