{
  "type": "Feature",
  "properties": {
    "iso:country":"IT",
    "sg:address":"20133 Milano",
    "sg:city":"Milano",
    "sg:orig_category":"Servizi Ausiliari Di Analisi, Controllo E Ricerca",
    "sg:phone":"+39 02 738 1615",
    "sg:postcode":"20133",
    "sg:province":"Milano",
    "wof:name":"C.s.e. Centro Per Gli Studi Economici (s.r.l.)",
    "wof:placetype":"venue"
},
  "geometry": {"coordinates":[9.226591,45.475552],"type":"Point"}
}