{
  "type": "Feature",
  "properties": {
    "addr:full":"16, Via Della Resistenza 48013 Brisighella Brisighella Ravenna 48013",
    "addr:postcode":"48013;48013",
    "addr:street":"Via Della Resistenza",
    "iso:country":"IT",
    "sg:address":"16, Via Della Resistenza 48013 Brisighella",
    "sg:city":"Brisighella",
    "sg:classifiers":[
        {
            "category":"Real Estate",
            "subcategory":"Architect",
            "type":"Services"
        }
    ],
    "sg:phone":"+39 39054683161",
    "sg:postcode":"48013",
    "sg:province":"Ravenna",
    "sg:tags":[
        "textile",
        "clothing"
    ],
    "wof:name":"Confezione Flo Di Palli Floriana",
    "wof:placetype":"venue"
},
  "geometry": {"coordinates":[11.751009,44.209129],"type":"Point"}
}