{
  "type": "Feature",
  "properties": {
    "addr:full":"116, Via Roma 40012 Calderara Di Reno Calderara di Reno Bologna 40012",
    "addr:housenumber":"116",
    "addr:postcode":"40012;40012",
    "addr:street":"Via Roma",
    "iso:country":"IT",
    "sg:address":"116, Via Roma 40012 Calderara Di Reno",
    "sg:city":"Calderara di Reno",
    "sg:classifiers":[
        {
            "category":"Manufacturing",
            "subcategory":"Rubber & Plastics",
            "type":"Manufacturing & Wholesale Goods"
        }
    ],
    "sg:phone":"+39 39051727597",
    "sg:postcode":"40012",
    "sg:province":"Bologna",
    "wof:name":"D'alimonte Srl",
    "wof:placetype":"venue"
},
  "geometry": {"coordinates":[11.2642040253,44.5492172241],"type":"Point"}
}