{
  "type": "Feature",
  "properties": {
    "addr:full":"Via Pigafetta Antonio 10 34147 Trieste Trieste Trieste 34147",
    "addr:housenumber":"10",
    "addr:postcode":"34147;34147",
    "addr:street":"Via Pigafetta Antonio",
    "iso:country":"IT",
    "sg:address":"Via Pigafetta Antonio 10 34147 Trieste",
    "sg:city":"Trieste",
    "sg:orig_category":"Generators And Motors For Air Conditioning Systems For Ships",
    "sg:phone":"+39 040 820377",
    "sg:postcode":"34147",
    "sg:province":"Trieste",
    "wof:name":"F. Gurian Snc",
    "wof:placetype":"venue"
},
  "geometry": {"coordinates":[13.778407,45.653629],"type":"Point"}
}