{
  "type": "Feature",
  "properties": {
    "iso:country":"IT",
    "sg:address":"20010 Inveruno",
    "sg:city":"Inveruno",
    "sg:orig_category":"Filati E Materie Prime Tessili",
    "sg:phone":"+39 02 9029 6738",
    "sg:postcode":"20010",
    "sg:province":"Milano",
    "wof:name":"Filelmo Srl",
    "wof:placetype":"venue"
},
  "geometry": {"coordinates":[8.8859539032,45.5133018494],"type":"Point"}
}