{
  "type": "Feature",
  "properties": {
    "iso:country":"IT",
    "sg:address":"18, Via Stazione 15010 Terzo",
    "sg:city":"Terzo",
    "sg:classifiers":[
        {
            "category":"Manufacturing",
            "subcategory":"Lumber",
            "type":"Manufacturing & Wholesale Goods"
        }
    ],
    "sg:phone":"+39 0144 594444",
    "sg:postcode":"15010",
    "sg:province":"Alessandria",
    "sg:tags":[
        "wood"
    ],
    "wof:name":"Grillo Legno Spa",
    "wof:placetype":"venue"
},
  "geometry": {"coordinates":[8.429202,44.671116],"type":"Point"}
}