{
  "type": "Feature",
  "properties": {
    "addr:full":"Via Vittorio Emanuele 105 12048 Sommariva Bosco Cuneo 12048",
    "addr:housenumber":"105",
    "addr:postcode":"12048;12048",
    "addr:street":"Via Vittorio Emanuele",
    "iso:country":"IT",
    "sg:address":"Via Vittorio Emanuele 105 12048 Sommariva Bosco",
    "sg:classifiers":[
        {
            "category":"Wholesale",
            "subcategory":"Chemicals & Plastics",
            "type":"Manufacturing & Wholesale Goods"
        }
    ],
    "sg:phone":"+39 0172 54015",
    "sg:postcode":"12048",
    "sg:province":"Cuneo",
    "sg:tags":[
        "industrial",
        "engineering",
        "parts",
        "vehicle",
        "injection",
        "moulded"
    ],
    "sg:website":"www.ims.sh",
    "wof:name":"I.m.s. Sas",
    "wof:placetype":"venue"
},
  "geometry": {"coordinates":[7.547111,44.388798],"type":"Point"}
}