{
  "type": "Feature",
  "properties": {
    "addr:full":"Via Isolella 91100 Trapani Trapani Trapani 91100",
    "addr:postcode":"91100;91100",
    "addr:street":"Via Isolella",
    "iso:country":"IT",
    "sg:address":"Via Isolella 91100 Trapani",
    "sg:city":"Trapani",
    "sg:classifiers":[
        {
            "category":"Autos & Motor Vehicles",
            "subcategory":"Boat Sales",
            "type":"Retail Goods"
        }
    ],
    "sg:phone":"+39 39092327866",
    "sg:postcode":"91100",
    "sg:province":"Trapani",
    "wof:name":"Cantiere Navale Di Trapani S.p.a.",
    "wof:placetype":"venue"
},
  "geometry": {"coordinates":[12.514634,38.018589],"type":"Point"}
}