{
  "type": "Feature",
  "properties": {
    "addr:full":"20029 Turbigo Turbigo Milano 20029",
    "addr:postcode":"20029;20029",
    "iso:country":"IT",
    "sg:address":"20029 Turbigo",
    "sg:city":"Turbigo",
    "sg:orig_category":"Materiali Edili",
    "sg:phone":"+39 0331 899296",
    "sg:postcode":"20029",
    "sg:province":"Milano",
    "wof:name":"Cantiere Solai Villa Di Villa Elia & C.",
    "wof:placetype":"venue"
},
  "geometry": {"coordinates":[8.748124,45.533863],"type":"Point"}
}