{
  "type": "Feature",
  "properties": {
    "addr:full":"33010 Magnano In Riviera Magnano in Riviera Udine 33010",
    "addr:postcode":"33010;33010",
    "addr:street":"Riviera",
    "iso:country":"IT",
    "sg:address":"33010 Magnano In Riviera",
    "sg:city":"Magnano in Riviera",
    "sg:orig_category":"Medicinali E Prodotti Parafarmaceutici",
    "sg:phone":"+39 0432 793339",
    "sg:postcode":"33010",
    "sg:province":"Udine",
    "wof:name":"Pavan Luisa",
    "wof:placetype":"venue"
},
  "geometry": {"coordinates":[13.1602993011,46.235118866],"type":"Point"}
}