{
  "type": "Feature",
  "properties": {
    "iso:country":"IT",
    "sg:address":"20143 Milano",
    "sg:city":"Milano",
    "sg:orig_category":"Servizi Ausiliari Dei Mezzi Di Trasporto",
    "sg:phone":"+39 02 817484",
    "sg:postcode":"20143",
    "sg:province":"Milano",
    "wof:name":"Perone Tommaso",
    "wof:placetype":"venue"
},
  "geometry": {"coordinates":[9.148488,45.442276],"type":"Point"}
}