{
  "type": "Feature",
  "properties": {
    "addr:full":"31051 Follina Follina Treviso 31051",
    "addr:postcode":"31051;31051",
    "iso:country":"IT",
    "sg:address":"31051 Follina",
    "sg:city":"Follina",
    "sg:orig_category":"Filati E Materie Prime Tessili",
    "sg:phone":"+39 0438 970895",
    "sg:postcode":"31051",
    "sg:province":"Treviso",
    "wof:name":"Effeti S.r.l.",
    "wof:placetype":"venue"
},
  "geometry": {"coordinates":[12.1194915771,45.9514732361],"type":"Point"}
}