{
  "type": "Feature",
  "properties": {
    "iso:country":"IT",
    "sg:address":"00187 Roma",
    "sg:city":"Roma",
    "sg:classifiers":[
        {
            "category":"Personal",
            "subcategory":"Beauty Salon",
            "type":"Services"
        }
    ],
    "sg:phone":"+39 06 679 6228",
    "sg:postcode":"00187",
    "sg:province":"Roma",
    "sg:tags":[
        "cosmetic"
    ],
    "wof:name":"Giancarlo A Fontana Di Trevi",
    "wof:placetype":"venue"
},
  "geometry": {"coordinates":[12.483619,41.902367],"type":"Point"}
}