{
  "type": "Feature",
  "properties": {
    "iso:country":"IT",
    "sg:address":"95127 Catania",
    "sg:city":"Catania",
    "sg:orig_category":"Prodotti Alimentari. Bevande, Vini E Liquori. Medicinali E Prodotti Parafarmaceutici",
    "sg:phone":"+39 095 444850",
    "sg:postcode":"95127",
    "sg:province":"Catania",
    "wof:name":"Integra",
    "wof:placetype":"venue"
},
  "geometry": {"coordinates":[15.0930299759,37.5180702209],"type":"Point"}
}