{
  "type": "Feature",
  "properties": {
    "addr:full":"20013 Magenta Magenta Milano 20013",
    "addr:postcode":"20013;20013",
    "iso:country":"IT",
    "sg:address":"20013 Magenta",
    "sg:city":"Magenta",
    "sg:orig_category":"Termotecnica E Riscaldamento, Apparecchiature E Servizi",
    "sg:phone":"+39 02 979 3732",
    "sg:postcode":"20013",
    "sg:province":"Milano",
    "wof:name":"Carenzi Carlo",
    "wof:placetype":"venue"
},
  "geometry": {"coordinates":[9.14397,45.494709],"type":"Point"}
}