{
  "type": "Feature",
  "properties": {
    "addr:full":"20123 Milano Milano Milano 20123",
    "addr:postcode":"20123;20123",
    "iso:country":"IT",
    "sg:address":"20123 Milano",
    "sg:city":"Milano",
    "sg:classifiers":[
        {
            "category":"Retail",
            "subcategory":"Storage",
            "type":"Services"
        }
    ],
    "sg:phone":"+39 02 8940 6816",
    "sg:postcode":"20123",
    "sg:province":"Milano",
    "sg:tags":[
        "equipment",
        "handling",
        "systems"
    ],
    "sg:website":"http://www.milanoservice.com",
    "wof:name":"Milanoservice Srl",
    "wof:placetype":"venue"
},
  "geometry": {"coordinates":[9.175213,45.457001],"type":"Point"}
}