{
  "type": "Feature",
  "properties": {
    "iso:country":"IT",
    "sg:address":"20124 Milano",
    "sg:city":"Milano",
    "sg:orig_category":"Forniture Per Uffici. Servizi Vari Di Interesse Pubblico",
    "sg:phone":"+39 02 204 9295",
    "sg:postcode":"20124",
    "sg:province":"Milano",
    "wof:name":"Tabaccheria Petitti Di Petitti N.",
    "wof:placetype":"venue"
},
  "geometry": {"coordinates":[9.2066984177,45.4823951721],"type":"Point"}
}