{
  "type": "Feature",
  "properties": {
    "addr:full":"10022 Carmagnola Carmagnola Torino 10022",
    "addr:postcode":"10022;10022",
    "iso:country":"IT",
    "sg:address":"10022 Carmagnola",
    "sg:city":"Carmagnola",
    "sg:orig_category":"Servizi Ausiliari Dei Mezzi Di Trasporto. Servizi Ausiliari Per Il Trasporto. Acqua, Luce, Gas E Societa' Di Esercizio Pubblico",
    "sg:phone":"+39 011 972 0587",
    "sg:postcode":"10022",
    "sg:province":"Torino",
    "wof:name":"Autostrada Torino - Savona (s.p.a.)",
    "wof:placetype":"venue"
},
  "geometry": {"coordinates":[7.719197,44.845486],"type":"Point"}
}