{
  "type": "Feature",
  "properties": {
    "addr:full":"18/a, Via Volterra 00182 Roma Roma Roma 00182",
    "addr:housenumber":"18 / a",
    "addr:postcode":"00182;00182",
    "addr:street":"Via Volterra",
    "iso:country":"IT",
    "sg:address":"18/a, Via Volterra 00182 Roma",
    "sg:city":"Roma",
    "sg:classifiers":[
        {
            "category":"Sports & Exercise",
            "subcategory":"Playing Field",
            "type":"Entertainment"
        }
    ],
    "sg:phone":"+39 39067013423",
    "sg:postcode":"00182",
    "sg:province":"Roma",
    "sg:tags":[
        "game"
    ],
    "wof:name":"F.lli Masala Srl",
    "wof:placetype":"venue"
},
  "geometry": {"coordinates":[12.470715,41.854294],"type":"Point"}
}