{
  "type": "Feature",
  "properties": {
    "addr:full":"47900 Rimini Rimini Rimini 47900",
    "addr:postcode":"47900;47900",
    "iso:country":"IT",
    "sg:address":"47900 Rimini",
    "sg:city":"Rimini",
    "sg:orig_category":"Macchine, Impianti Ed Attrezzature Per Agricoltura E Zootecnia. Prodotti Vari In Metallo. Apparecchiature E Sistemi Per Magazzinaggio E Movimentazione",
    "sg:phone":"+39 0541 728008",
    "sg:postcode":"47900",
    "sg:province":"Rimini",
    "wof:name":"Vetroresine Ecologica Snc Di Muccioli Luciano & Raniero",
    "wof:placetype":"venue"
},
  "geometry": {"coordinates":[12.552751,44.026459],"type":"Point"}
}