{
  "type": "Feature",
  "properties": {
    "iso:country":"IT",
    "sg:address":"25046 Cazzago San Martino",
    "sg:city":"Cazzago San Martino",
    "sg:orig_category":"Zootecnia E Pesca, Allevamento Piccoli Animali",
    "sg:phone":"+39 030 725266",
    "sg:postcode":"25046",
    "sg:province":"Brescia",
    "wof:name":"Quaresmini Luigi",
    "wof:placetype":"venue"
},
  "geometry": {"coordinates":[10.108301,45.552891],"type":"Point"}
}