{
  "type": "Feature",
  "properties": {
    "addr:full":"20021 Bollate Bollate Milano 20021",
    "addr:postcode":"20021;20021",
    "iso:country":"IT",
    "sg:address":"20021 Bollate",
    "sg:city":"Bollate",
    "sg:orig_category":"Prodotti Alimentari",
    "sg:phone":"+39 02 351 1520",
    "sg:postcode":"20021",
    "sg:province":"Milano",
    "wof:name":"Bertorelli Erminia",
    "wof:placetype":"venue"
},
  "geometry": {"coordinates":[9.1455488205,45.5484619141],"type":"Point"}
}