{
  "type": "Feature",
  "properties": {
    "addr:full":"11, Via Umberto I 84068 Pollica Pollica Salerno 84068",
    "addr:postcode":"84068;84068",
    "addr:street":"Via Umberto I",
    "iso:country":"IT",
    "sg:address":"11, Via Umberto I 84068 Pollica",
    "sg:city":"Pollica",
    "sg:classifiers":[
        {
            "category":"Building & Trades",
            "subcategory":"Construction",
            "type":"Services"
        }
    ],
    "sg:phone":"+39 0974 901488",
    "sg:postcode":"84068",
    "sg:province":"Salerno",
    "sg:tags":[
        "work",
        "public"
    ],
    "wof:name":"Il Tetto Del Cilento S.c.r.l.",
    "wof:placetype":"venue"
},
  "geometry": {"coordinates":[15.055762,40.19043],"type":"Point"}
}