{
  "type": "Feature",
  "properties": {
    "iso:country":"IT",
    "sg:address":"1, Localita' Cerratina 66034 Lanciano",
    "sg:city":"Lanciano",
    "sg:classifiers":[
        {
            "category":"Autos & Motor Vehicles",
            "subcategory":"Automobile Sales",
            "type":"Retail Goods"
        }
    ],
    "sg:phone":"+39 390 872 5001",
    "sg:postcode":"66034",
    "sg:province":"Chieti",
    "sg:tags":[
        "motor-cars"
    ],
    "wof:name":"Pierburg S.p.a.",
    "wof:placetype":"venue"
},
  "geometry": {"coordinates":[14.1412115097,42.3578186035],"type":"Point"}
}