{
  "type": "Feature",
  "properties": {
    "iso:country":"IT",
    "sg:address":"18, V. Del Commercio 35036 Montegrotto Terme",
    "sg:city":"Montegrotto Terme",
    "sg:classifiers":[
        {
            "category":"Shopping",
            "subcategory":"Stationery & Office Supplies",
            "type":"Retail Goods"
        }
    ],
    "sg:phone":"+39 049 891 2868",
    "sg:postcode":"35036",
    "sg:province":"Padova",
    "sg:tags":[
        "professional"
    ],
    "sg:website":"http://www.paginegialle.it/masterallestimenti",
    "wof:name":"Master Comuniicazione & Immagine",
    "wof:placetype":"venue"
},
  "geometry": {"coordinates":[11.7636137009,45.3360443115],"type":"Point"}
}