{
  "type": "Feature",
  "properties": {
    "iso:country":"IT",
    "sg:address":"40010 Bentivoglio",
    "sg:city":"Bentivoglio",
    "sg:orig_category":"Studi E Consulenze Tecniche E Industriali. Servizi E Lavori Per Edilizia E Lavori Pubblici. Professionisti - Studi E Servizi Ed Associazioni Di Interesse Aziendale",
    "sg:phone":"+39 051 891308",
    "sg:postcode":"40010",
    "sg:province":"Bologna",
    "sg:website":"http://www.progetto-m.com",
    "wof:name":"Progetto M International Srl",
    "wof:placetype":"venue"
},
  "geometry": {"coordinates":[11.419074,44.635647],"type":"Point"}
}