{
  "type": "Feature",
  "properties": {
    "addr:full":"15068 Pozzolo Formigaro Pozzolo Formigaro Alessandria 15068",
    "addr:postcode":"15068;15068",
    "iso:country":"IT",
    "sg:address":"15068 Pozzolo Formigaro",
    "sg:city":"Pozzolo Formigaro",
    "sg:orig_category":"Macchine Ed Impianti Per Edilizia E Lavori Pubblici",
    "sg:phone":"+39 0143 417524",
    "sg:postcode":"15068",
    "sg:province":"Alessandria",
    "wof:name":"L'edilcasa Di Tassone Sas",
    "wof:placetype":"venue"
},
  "geometry": {"coordinates":[8.779819,44.795761],"type":"Point"}
}