{
  "type": "Feature",
  "properties": {
    "iso:country":"IT",
    "sg:address":"Piazza Assunzione; Morgex; 11017",
    "sg:city":"Morgex",
    "sg:classifiers":[
        {
            "category":"Banks & Credit Unions",
            "subcategory":"Bank",
            "type":"Services"
        }
    ],
    "sg:phone":"+39 0165 809706",
    "sg:postcode":"11017",
    "sg:province":"Aosta",
    "wof:name":"Cassa Di Risparmio Di Torino",
    "wof:placetype":"venue"
},
  "geometry": {"coordinates":[7.012968,45.755527],"type":"Point"}
}