{
  "type": "Feature",
  "properties": {
    "iso:country":"IT",
    "sg:address":"Via Monviso 7 10060 None",
    "sg:city":"None",
    "sg:classifiers":[
        {
            "category":"Restaurant",
            "type":"Food & Drink"
        }
    ],
    "sg:phone":"+39 011 990 4310",
    "sg:postcode":"10060",
    "sg:province":"Torino",
    "sg:tags":[
        "pasta"
    ],
    "sg:website":"www.anticopastificio.net",
    "wof:name":"Antico Pastificio Srl",
    "wof:placetype":"venue"
},
  "geometry": {"coordinates":[7.5151171684,44.9871063232],"type":"Point"}
}