{
  "type": "Feature",
  "properties": {
    "iso:country":"IT",
    "sg:address":"20148 Milano",
    "sg:city":"Milano",
    "sg:orig_category":"Materiali E Componenti Elettronici",
    "sg:phone":"+39 02 4871 2520",
    "sg:postcode":"20148",
    "sg:province":"Milano",
    "wof:name":"Xilinx Development Corporation",
    "wof:placetype":"venue"
},
  "geometry": {"coordinates":[9.13337,45.475147],"type":"Point"}
}