{
  "type": "Feature",
  "properties": {
    "iso:country":"IT",
    "sg:address":"70014 Conversano",
    "sg:city":"Conversano",
    "sg:orig_category":"Macchine, Impianti Ed Attrezzature Per Agricoltura E Zootecnia",
    "sg:phone":"+39 080 495 7049",
    "sg:postcode":"70014",
    "sg:province":"Bari",
    "wof:name":"Buonasora G.",
    "wof:placetype":"venue"
},
  "geometry": {"coordinates":[17.105272,40.972542],"type":"Point"}
}