{
  "type": "Feature",
  "properties": {
    "addr:full":"22, V. S. M. Rocca Maggiore 37129 Verona Verona Verona 37129",
    "addr:housenumber":"22",
    "addr:postcode":"37129;37129",
    "addr:street":"V. S. M. Rocca Maggiore",
    "iso:country":"IT",
    "sg:address":"22, V. S. M. Rocca Maggiore 37129 Verona",
    "sg:city":"Verona",
    "sg:classifiers":[
        {
            "category":"Shopping",
            "subcategory":"Jewelry",
            "type":"Retail Goods"
        }
    ],
    "sg:phone":"+39 045 801 4036",
    "sg:postcode":"37129",
    "sg:province":"Verona",
    "sg:tags":[
        "jewellery"
    ],
    "sg:website":"http://www.lineafidia.it",
    "wof:name":"Linea Fidia Di Finotti Zeno",
    "wof:placetype":"venue"
},
  "geometry": {"coordinates":[11.00281,45.444111],"type":"Point"}
}