{
  "type": "Feature",
  "properties": {
    "iso:country":"IT",
    "sg:address":"1/b, Via Pia 31021 Mogliano Veneto",
    "sg:city":"Mogliano Veneto",
    "sg:classifiers":[
        {
            "category":"Utilities",
            "subcategory":"Electric",
            "type":"Services"
        }
    ],
    "sg:phone":"+39 041 590 1516",
    "sg:postcode":"31021",
    "sg:province":"Treviso",
    "sg:tags":[
        "energy"
    ],
    "wof:name":"Spim Servizi Pubblici Integrati Mogliano (s.p.a.)",
    "wof:placetype":"venue"
},
  "geometry": {"coordinates":[12.2420721054,45.6662864685],"type":"Point"}
}