{
  "type": "Feature",
  "properties": {
    "iso:country":"IT",
    "sg:address":"Via Masiano 6/a, Masiano, 51030 Pistoia, Pt",
    "sg:classifiers":[
        {
            "category":"Banks & Credit Unions",
            "subcategory":"Bank",
            "type":"Services"
        }
    ],
    "sg:postcode":"51030",
    "sg:province":"Pistoia",
    "wof:name":"Banca Di Credito Cooperativo Di Masiano (pistoia)",
    "wof:placetype":"venue"
},
  "geometry": {"coordinates":[10.918524,43.932156],"type":"Point"}
}