{
  "type": "Feature",
  "properties": {
    "iso:country":"IT",
    "sg:address":"36051 Olmo",
    "sg:city":"Olmo",
    "sg:orig_category":"Macchine E Forniture Per Industria Orafa E Per Orologeria",
    "sg:phone":"+39 0444 340467",
    "sg:postcode":"36051",
    "sg:province":"Vicenza",
    "wof:name":"Pilatone Federico",
    "wof:placetype":"venue"
},
  "geometry": {"coordinates":[11.491244,45.532387],"type":"Point"}
}