{
  "type": "Feature",
  "properties": {
    "addr:full":"Via Emilia Ponente 130 40133 Bologna Bologna Bologna 40133",
    "addr:housenumber":"130",
    "addr:postcode":"40133;40133",
    "addr:street":"Via Emilia Ponente",
    "iso:country":"IT",
    "sg:address":"Via Emilia Ponente 130 40133 Bologna",
    "sg:city":"Bologna",
    "sg:classifiers":[
        {
            "category":"Shopping",
            "subcategory":"Clothing, Apparel, & Fashions",
            "type":"Retail Goods"
        }
    ],
    "sg:phone":"+39 051 314 5311",
    "sg:postcode":"40133",
    "sg:province":"Bologna",
    "sg:tags":[
        "leather",
        "clothing"
    ],
    "wof:name":"Hettabretz Spa",
    "wof:placetype":"venue"
},
  "geometry": {"coordinates":[11.299738,44.508327],"type":"Point"}
}