{
  "type": "Feature",
  "properties": {
    "iso:country":"IT",
    "sg:address":"33070 Brugnera",
    "sg:city":"Brugnera",
    "sg:orig_category":"Studi E Consulenze Amministrative, Commerciali E Aziendali. Consulenze Tecniche, Amministrative E Perizie. Professionisti - Studi E Servizi Ed Associazioni Di Interesse Aziendale",
    "sg:phone":"+39 0434 606407",
    "sg:postcode":"33070",
    "sg:province":"Pordenone",
    "wof:name":"Vardanega Giovanna",
    "wof:placetype":"venue"
},
  "geometry": {"coordinates":[12.581918,45.922485],"type":"Point"}
}