{
  "type": "Feature",
  "properties": {
    "addr:full":"40/7, Viale Della Navigazione Interna 35129 Padova Padova Padova 35129",
    "addr:housenumber":"40 / 7",
    "addr:postcode":"35129;35129",
    "addr:street":"Viale Della Navigazione Interna",
    "iso:country":"IT",
    "sg:address":"40/7, Viale Della Navigazione Interna 35129 Padova",
    "sg:city":"Padova",
    "sg:orig_category":"Miscellaneous Products",
    "sg:phone":"+39 39049774388",
    "sg:postcode":"35129",
    "sg:province":"Padova",
    "wof:name":"Gottardo (s.r.l.)",
    "wof:placetype":"venue"
},
  "geometry": {"coordinates":[11.9195728302,45.4096832275],"type":"Point"}
}