{
  "type": "Feature",
  "properties": {
    "iso:country":"IT",
    "sg:address":"25064 Gussago",
    "sg:city":"Gussago",
    "sg:orig_category":"Arredamento Negozi E Supermercati",
    "sg:phone":"+39 030 252 9382",
    "sg:postcode":"25064",
    "sg:province":"Brescia",
    "sg:website":"http://www.stampofer.it",
    "wof:name":"Stampo-fer Di Lombardi & Della Fiore Snc",
    "wof:placetype":"venue"
},
  "geometry": {"coordinates":[10.155672,45.560043],"type":"Point"}
}