{
  "type": "Feature",
  "properties": {
    "iso:country":"IT",
    "sg:address":"14, Via Mentana 10042 Nichelino",
    "sg:city":"Nichelino",
    "sg:classifiers":[
        {
            "category":"Utilities",
            "subcategory":"Telephone",
            "type":"Services"
        }
    ],
    "sg:phone":"+39 011 627 5603",
    "sg:postcode":"10042",
    "sg:province":"Torino",
    "sg:tags":[
        "telecommunication"
    ],
    "wof:name":"Co.ge.tel S.r.l.",
    "wof:placetype":"venue"
},
  "geometry": {"coordinates":[7.640455,44.975773],"type":"Point"}
}