{
  "type": "Feature",
  "properties": {
    "iso:country":"IT",
    "sg:address":"95030 Nicolosi",
    "sg:city":"Nicolosi",
    "sg:orig_category":"Servizi Ausiliari Di Analisi, Controllo E Ricerca. Acqua, Luce, Gas E Societa' Di Esercizio Pubblico",
    "sg:phone":"+39 095 916184",
    "sg:postcode":"95030",
    "sg:province":"Catania",
    "wof:name":"Osservatorio Astrofisico Di Catania",
    "wof:placetype":"venue"
},
  "geometry": {"coordinates":[15.026502,37.614254],"type":"Point"}
}