{
  "type": "Feature",
  "properties": {
    "addr:full":"205, Via Maestra 33084 Cordenons Cordenons Pordenone 33084",
    "addr:housenumber":"205",
    "addr:postcode":"33084;33084",
    "addr:street":"Via Maestra",
    "iso:country":"IT",
    "sg:address":"205, Via Maestra 33084 Cordenons",
    "sg:city":"Cordenons",
    "sg:classifiers":[
        {
            "category":"Professional",
            "subcategory":"Engineering",
            "type":"Services"
        }
    ],
    "sg:phone":"+39 39043440585",
    "sg:postcode":"33084",
    "sg:province":"Pordenone",
    "sg:tags":[
        "machine",
        "-",
        "mechanical"
    ],
    "wof:name":"Brillfond (s.a.s.)",
    "wof:placetype":"venue"
},
  "geometry": {"coordinates":[12.692943,45.988853],"type":"Point"}
}