{
  "type": "Feature",
  "properties": {
    "addr:full":"Via Balbi 53; Ospedaletto Lodigiano; 20080 Milano 20080",
    "addr:housenumber":"53",
    "addr:postcode":"20080;20080",
    "addr:street":"Via Balbi;Lodigiano",
    "iso:country":"IT",
    "sg:address":"Via Balbi 53; Ospedaletto Lodigiano; 20080",
    "sg:classifiers":[
        {
            "category":"Banks & Credit Unions",
            "subcategory":"Bank",
            "type":"Services"
        }
    ],
    "sg:phone":"+39 0377 86034",
    "sg:postcode":"20080",
    "sg:province":"Milano",
    "wof:name":"Istituto Bancario, San Paolo Di Torino Spa",
    "wof:placetype":"venue"
},
  "geometry": {"coordinates":[9.115146,45.359673],"type":"Point"}
}