{
  "type": "Feature",
  "properties": {
    "iso:country":"IT",
    "sg:address":"20017 Mazzo",
    "sg:orig_category":"Automazione E Macchine Per Ufficio. Servizi Ausiliari Di Certificati, Riproduzioni, Disegni E Foto",
    "sg:phone":"+39 02 9390 9021",
    "sg:postcode":"20017",
    "sg:province":"Milano",
    "wof:name":"Italarchivi S.r.l.",
    "wof:placetype":"venue"
},
  "geometry": {"coordinates":[9.084982,45.525616],"type":"Point"}
}