{
  "type": "Feature",
  "properties": {
    "addr:full":"Via Xx Settembre 41 27020 Gravellona Lomellina Gravellona Lomellina Pavia 27020",
    "addr:housenumber":"41",
    "addr:postcode":"27020;27020",
    "addr:street":"Via Xx Settembre;Lomellina",
    "iso:country":"IT",
    "sg:address":"Via Xx Settembre 41 27020 Gravellona Lomellina",
    "sg:city":"Gravellona Lomellina",
    "sg:orig_category":"Hosiery, Nightwear, Daywear",
    "sg:phone":"+39 0381 650112",
    "sg:postcode":"27020",
    "sg:province":"Pavia",
    "sg:website":"www.fancysrl.com",
    "wof:name":"Fancy Srl",
    "wof:placetype":"venue"
},
  "geometry": {"coordinates":[9.156563,45.185886],"type":"Point"}
}