{
  "type": "Feature",
  "properties": {
    "iso:country":"IT",
    "sg:address":"34, Via Balbo Cesare 20136 Milano",
    "sg:city":"Milano",
    "sg:classifiers":[
        {
            "category":"Shopping",
            "subcategory":"Jewelry",
            "type":"Retail Goods"
        }
    ],
    "sg:phone":"+39 02 5831 4152",
    "sg:postcode":"20136",
    "sg:province":"Milano",
    "sg:tags":[
        "jewellery"
    ],
    "wof:name":"Micheletto S.r.l.",
    "wof:placetype":"venue"
},
  "geometry": {"coordinates":[9.196041,45.446793],"type":"Point"}
}