{
  "type": "Feature",
  "properties": {
    "iso:country":"IT",
    "sg:address":"55054 Massarosa",
    "sg:city":"Bozzano",
    "sg:orig_category":"Lavorazioni Metalli, Stampaggio E Saldatura",
    "sg:phone":"+39 0584 975424",
    "sg:postcode":"55054",
    "sg:province":"Lucca",
    "wof:name":"Bianucci & Busatti",
    "wof:placetype":"venue"
},
  "geometry": {"coordinates":[10.340796,43.868778],"type":"Point"}
}