{
  "type": "Feature",
  "properties": {
    "addr:full":"80129 Napoli Napoli Napoli 80129",
    "addr:housenumber":"80129",
    "addr:postcode":"80129",
    "iso:country":"IT",
    "sg:address":"80129 Napoli",
    "sg:city":"Napoli",
    "sg:orig_category":"Antifurto",
    "sg:phone":"+39 081 578 4993",
    "sg:postcode":"80129",
    "sg:province":"Napoli",
    "wof:name":"Tecnotre Di Ricciardi Raffaele",
    "wof:placetype":"venue"
},
  "geometry": {"coordinates":[14.241447,40.935978],"type":"Point"}
}