{
  "type": "Feature",
  "properties": {
    "iso:country":"IT",
    "sg:address":"12030 Marene",
    "sg:city":"Marene",
    "sg:orig_category":"Macchine Agricole - Commercio E Riparazione",
    "sg:phone":"+39 0172 742344",
    "sg:postcode":"12030",
    "sg:province":"Cuneo",
    "wof:name":"Racca Gabriele & C. Snc",
    "wof:placetype":"venue"
},
  "geometry": {"coordinates":[7.5513,44.392933],"type":"Point"}
}