{
  "type": "Feature",
  "properties": {
    "iso:country":"IT",
    "sg:address":"20090 Vimodrone",
    "sg:city":"Vimodrone",
    "sg:orig_category":"Servizi E Lavori Per Arredamento E Industria Del Legno. Servizi E Lavori Per Edilizia E Lavori Pubblici",
    "sg:phone":"+39 02 250 0922",
    "sg:postcode":"20090",
    "sg:province":"Milano",
    "wof:name":"Conti Diego",
    "wof:placetype":"venue"
},
  "geometry": {"coordinates":[9.28824,45.522091],"type":"Point"}
}