{
  "type": "Feature",
  "properties": {
    "iso:country":"IT",
    "sg:address":"24, Via Nazionale 30039 Stra",
    "sg:city":"Stra",
    "sg:classifiers":[
        {
            "category":"Personal",
            "subcategory":"Shoe Repair & Shine",
            "type":"Services"
        }
    ],
    "sg:phone":"+39 39049502182",
    "sg:postcode":"30039",
    "sg:province":"Venezia",
    "sg:tags":[
        "leather"
    ],
    "wof:name":"Ballin",
    "wof:placetype":"venue"
},
  "geometry": {"coordinates":[12.133402,45.438129],"type":"Point"}
}