{
  "type": "Feature",
  "properties": {
    "addr:full":"Via Lepori 4 57017 Stagno Stagno Livorno 57017",
    "addr:housenumber":"4",
    "addr:postcode":"57017;57017",
    "addr:street":"Via Lepori",
    "iso:country":"IT",
    "sg:address":"Via Lepori 4 57017 Stagno",
    "sg:city":"Stagno",
    "sg:classifiers":[
        {
            "category":"Food & Beverages",
            "subcategory":"Meat & Fish",
            "type":"Retail Goods"
        }
    ],
    "sg:phone":"+39 0586 940056",
    "sg:postcode":"57017",
    "sg:province":"Livorno",
    "sg:tags":[
        "fresh"
    ],
    "wof:name":"Star Fish S.r.l.",
    "wof:placetype":"venue"
},
  "geometry": {"coordinates":[10.3461303711,43.5840072632],"type":"Point"}
}