{
  "type": "Feature",
  "properties": {
    "addr:full":"20152 Milano Milano Milano 20152",
    "addr:postcode":"20152;20152",
    "iso:country":"IT",
    "sg:address":"20152 Milano",
    "sg:city":"Milano",
    "sg:orig_category":"Scuole E Servizi Scolastici. Ricerca, Selezione E Formazione Del Personale. Pubblica Amministrazione",
    "sg:phone":"+39 02 405176",
    "sg:postcode":"20152",
    "sg:province":"Milano",
    "wof:name":"Scuole Pubbliche/scuole Elementari",
    "wof:placetype":"venue"
},
  "geometry": {"coordinates":[9.066766,45.444138],"type":"Point"}
}