{
  "type": "Feature",
  "properties": {
    "iso:country":"IT",
    "sg:address":"1, Via Presciano 52020 Pergine Valdarno",
    "sg:city":"Pergine Valdarno",
    "sg:classifiers":[
        {
            "category":"Professional",
            "subcategory":"Engineering",
            "type":"Services"
        }
    ],
    "sg:phone":"+39 0575 897234",
    "sg:postcode":"52020",
    "sg:province":"Arezzo",
    "sg:tags":[
        "machine",
        "-",
        "mechanical"
    ],
    "wof:name":"Costruzioni Aretine Ruote Srl",
    "wof:placetype":"venue"
},
  "geometry": {"coordinates":[11.670018,43.460518],"type":"Point"}
}