{
  "type": "Feature",
  "properties": {
    "iso:country":"IT",
    "sg:address":"10073 Cirie'",
    "sg:orig_category":"Termotecnica E Riscaldamento, Apparecchiature E Servizi",
    "sg:phone":"+39 011 921 0239",
    "sg:postcode":"10073",
    "sg:province":"Torino",
    "wof:name":"Garbero Piero",
    "wof:placetype":"venue"
},
  "geometry": {"coordinates":[7.594856,45.225658],"type":"Point"}
}