{
  "type": "Feature",
  "properties": {
    "iso:country":"IT",
    "sg:address":"Localit\u00e0 Piane Di Carniglia 46 43041 Bedonia",
    "sg:city":"Bedonia",
    "sg:classifiers":[
        {
            "category":"Landmark",
            "subcategory":"City Walls",
            "type":"Public Place"
        }
    ],
    "sg:phone":"+39 0525 824505",
    "sg:postcode":"43041",
    "sg:province":"Parma",
    "sg:tags":[
        "stone",
        "working"
    ],
    "sg:website":"www.cff-filiberti.com",
    "wof:name":"Cff Filiberti Srl",
    "wof:placetype":"venue"
},
  "geometry": {"coordinates":[10.329548,44.807865],"type":"Point"}
}