{
  "type": "Feature",
  "properties": {
    "iso:country":"IT",
    "sg:address":"15028 Quattordio",
    "sg:city":"Quattordio",
    "sg:orig_category":"Materiali Semilavorati Metallici",
    "sg:phone":"+39 0131 7941",
    "sg:postcode":"15028",
    "sg:province":"Alessandria",
    "wof:name":"Pirelli Cavi E Sistemi Spa",
    "wof:placetype":"venue"
},
  "geometry": {"coordinates":[8.381578,44.907364],"type":"Point"}
}