{
  "type": "Feature",
  "properties": {
    "addr:full":"25126 Brescia Brescia Brescia 25126",
    "addr:postcode":"25126;25126",
    "iso:country":"IT",
    "sg:address":"25126 Brescia",
    "sg:city":"Brescia",
    "sg:classifiers":[
        {
            "category":"Health Services",
            "subcategory":"Health Practitioner",
            "type":"Services"
        }
    ],
    "sg:phone":"+39 030 294 2000",
    "sg:postcode":"25126",
    "sg:province":"Brescia",
    "sg:tags":[
        "medici"
    ],
    "wof:name":"Albanese Dr.aldo",
    "wof:placetype":"venue"
},
  "geometry": {"coordinates":[10.196121,45.54089],"type":"Point"}
}