{
  "type": "Feature",
  "properties": {
    "iso:country":"IT",
    "sg:address":"84091 Battipaglia",
    "sg:city":"Battipaglia",
    "sg:orig_category":"Valvole E Apparecchiature Di Misura",
    "sg:phone":"+39 0828 304433",
    "sg:postcode":"84091",
    "sg:province":"Salerno",
    "wof:name":"Fluid Service Srl",
    "wof:placetype":"venue"
},
  "geometry": {"coordinates":[14.950567,40.593929],"type":"Point"}
}