{
  "type": "Feature",
  "properties": {
    "iso:country":"IT",
    "sg:address":"7, Viale Della Vittoria 20058 Villasanta",
    "sg:city":"Villasanta",
    "sg:classifiers":[
        {
            "category":"Shopping",
            "subcategory":"Crafts & Fabrics",
            "type":"Retail Goods"
        }
    ],
    "sg:phone":"+39 39039303755",
    "sg:postcode":"20058",
    "sg:province":"Milano",
    "wof:name":"Rossi Lorenzo & Figli Snc Di Rossi Luigi & C.",
    "wof:placetype":"venue"
},
  "geometry": {"coordinates":[9.302895546,45.6143913269],"type":"Point"}
}