{
  "type": "Feature",
  "properties": {
    "addr:full":"00040 Pomezia Pomezia Roma 00040",
    "addr:postcode":"00040;roma 00040",
    "iso:country":"IT",
    "sg:address":"00040 Pomezia",
    "sg:city":"Pomezia",
    "sg:orig_category":"Forniture Per Uffici. Arredi Ed Attrezzature Per Uffici. Automazione E Macchine Per Ufficio",
    "sg:phone":"+39 06 9162 0024",
    "sg:postcode":"00040",
    "sg:province":"Roma",
    "wof:name":"Gruppo Buffetti S.p.a.",
    "wof:placetype":"venue"
},
  "geometry": {"coordinates":[12.4897670746,41.6823005676],"type":"Point"}
}