{
  "type": "Feature",
  "properties": {
    "iso:country":"IT",
    "sg:address":"10093 Collegno",
    "sg:city":"Collegno",
    "sg:orig_category":"Articoli Da Regalo. Arte Ed Artigianato Artistico. Shopping",
    "sg:phone":"+39 011 789091",
    "sg:postcode":"10093",
    "sg:province":"Torino",
    "wof:name":"Meraviglie Del Mondo",
    "wof:placetype":"venue"
},
  "geometry": {"coordinates":[7.580332,45.072517],"type":"Point"}
}