{
  "type": "Feature",
  "properties": {
    "iso:country":"IT",
    "sg:address":"42100 Reggio Emilia",
    "sg:orig_category":"Avvocati, Notai E Servizi Legali. Consulenze Tecniche, Amministrative E Perizie",
    "sg:phone":"+39 0522 366623",
    "sg:postcode":"42100",
    "sg:province":"Reggio Nell'Emilia",
    "wof:name":"Unicon Italia Srl",
    "wof:placetype":"venue"
},
  "geometry": {"coordinates":[10.618393,44.713398],"type":"Point"}
}