{
  "type": "Feature",
  "properties": {
    "iso:country":"IT",
    "sg:address":"2/26, Via Reiss Romoli 20019 Settimo Milanese",
    "sg:city":"Settimo Milanese",
    "sg:classifiers":[
        {
            "category":"Manufacturing",
            "subcategory":"Motor Vehicles & Parts",
            "type":"Manufacturing & Wholesale Goods"
        }
    ],
    "sg:phone":"+39 39023287650",
    "sg:postcode":"20019",
    "sg:province":"Milano",
    "sg:tags":[
        "engine"
    ],
    "wof:name":"Mi.ra Milano Raccordi S.r.l.",
    "wof:placetype":"venue"
},
  "geometry": {"coordinates":[9.06542,45.480972],"type":"Point"}
}