{
  "type": "Feature",
  "properties": {
    "iso:country":"IT",
    "sg:address":"00055 Ladispoli",
    "sg:city":"Ladispoli",
    "sg:orig_category":"Sport - Articoli E Forniture",
    "sg:phone":"+39 06 9922 1834",
    "sg:postcode":"00055",
    "sg:province":"Roma",
    "wof:name":"La Venia Cristiana",
    "wof:placetype":"venue"
},
  "geometry": {"coordinates":[12.492622,41.900158],"type":"Point"}
}