{
  "type": "Feature",
  "properties": {
    "iso:country":"IT",
    "sg:address":"59100 Prato",
    "sg:city":"Prato",
    "sg:classifiers":[
        {
            "category":"Utilities",
            "subcategory":"Refuse",
            "type":"Services"
        }
    ],
    "sg:phone":"+39 0574 462391",
    "sg:postcode":"59100",
    "sg:province":"Prato",
    "sg:tags":[
        "houseware",
        "utensil",
        "linen",
        "blankets",
        "drapery",
        "kitchen"
    ],
    "sg:website":"http://www.dormisano.it",
    "wof:name":"Dormosano Srl",
    "wof:placetype":"venue"
},
  "geometry": {"coordinates":[11.111831,43.902767],"type":"Point"}
}