{
  "type": "Feature",
  "properties": {
    "iso:country":"IT",
    "sg:address":"Corso Moncenisio 51 10057 Sant'ambrogio Di Torino",
    "sg:classifiers":[
        {
            "category":"Shopping",
            "subcategory":"Crafts & Fabrics",
            "type":"Retail Goods"
        }
    ],
    "sg:phone":"+39 011 932 4111",
    "sg:postcode":"10057",
    "sg:province":"Torino",
    "sg:tags":[
        "cloth",
        "felt"
    ],
    "sg:website":"www.fir-feltrifici.com",
    "wof:name":"Fir Spa",
    "wof:placetype":"venue"
},
  "geometry": {"coordinates":[7.3670148849,45.0968742371],"type":"Point"}
}