{
  "type": "Feature",
  "properties": {
    "iso:country":"IT",
    "sg:address":"10080 Rivara",
    "sg:city":"Rivara",
    "sg:classifiers":[
        {
            "category":"Manufacturing",
            "subcategory":"Tools & Machinery",
            "type":"Manufacturing & Wholesale Goods"
        }
    ],
    "sg:phone":"+39 0124 48827",
    "sg:postcode":"10080",
    "sg:province":"Torino",
    "sg:tags":[
        "machine",
        "system"
    ],
    "wof:name":"Trafco Srl",
    "wof:placetype":"venue"
},
  "geometry": {"coordinates":[7.686619,45.07056],"type":"Point"}
}