{
  "type": "Feature",
  "properties": {
    "iso:country":"IT",
    "sg:address":"24060 Brusaporto",
    "sg:city":"Brusaporto",
    "sg:classifiers":[
        {
            "category":"Government",
            "subcategory":"Office",
            "type":"Public Place"
        }
    ],
    "sg:phone":"+39 035 683370",
    "sg:postcode":"24060",
    "sg:province":"Bergamo",
    "sg:tags":[
        "sector",
        "fair",
        "entertainment",
        "supply",
        "non-professional",
        "engineering",
        "congresses",
        "supplies",
        "professional",
        "automation",
        "electronic",
        "events",
        "machines"
    ],
    "wof:name":"Sangalli Snc Di Sangalli & Terzi",
    "wof:placetype":"venue"
},
  "geometry": {"coordinates":[9.7446460724,45.6656570435],"type":"Point"}
}