{
  "type": "Feature",
  "properties": {
    "addr:full":"22, Via Canturino 22070 Vertemate Con Minoprio Minoprio Como 22070",
    "addr:postcode":"22070;22070",
    "addr:street":"Via Canturino;Con Minoprio Minoprio",
    "iso:country":"IT",
    "sg:address":"22, Via Canturino 22070 Vertemate Con Minoprio",
    "sg:city":"Minoprio",
    "sg:classifiers":[
        {
            "category":"Manufacturing",
            "subcategory":"Rubber & Plastics",
            "type":"Manufacturing & Wholesale Goods"
        }
    ],
    "sg:phone":"+39 39031900751",
    "sg:postcode":"22070",
    "sg:province":"Como",
    "wof:name":"Effe Emme (s.a.s.)",
    "wof:placetype":"venue"
},
  "geometry": {"coordinates":[9.1135635376,45.7616004944],"type":"Point"}
}