{
  "type": "Feature",
  "properties": {
    "addr:full":"39012 Merano Merano Bolzano/Bozen 39012",
    "addr:postcode":"39012;39012",
    "iso:country":"IT",
    "sg:address":"39012 Merano",
    "sg:city":"Merano",
    "sg:orig_category":"Prodotti Di Base E Forniture Per Industria Alimentare E Bevande. Forniture Per Attivita' Commerciali Ed Artigianali",
    "sg:phone":"+39 0473 230560",
    "sg:postcode":"39012",
    "sg:province":"Bolzano/Bozen",
    "wof:name":"Pfitscher I. & H. (s.n.c.)",
    "wof:placetype":"venue"
},
  "geometry": {"coordinates":[11.3409986496,46.493221283],"type":"Point"}
}