{
  "type": "Feature",
  "properties": {
    "iso:country":"IT",
    "sg:address":"92019 Sciacca",
    "sg:city":"Sciacca",
    "sg:orig_category":"Macchine, Impianti Ed Attrezzature Industria Chimica. Impiantistica E Prodotti Tecnologici Per Edilizia. Impianti, Attrezzature E Forniture Sanitarie Ed Ospedaliere",
    "sg:phone":"+39 0925 22746",
    "sg:postcode":"92019",
    "sg:province":"Agrigento",
    "wof:name":"Ce.as.",
    "wof:placetype":"venue"
},
  "geometry": {"coordinates":[13.05874,37.567631],"type":"Point"}
}