{
  "type": "Feature",
  "properties": {
    "iso:country":"IT",
    "sg:address":"84036 Sala Consilina",
    "sg:city":"Sala Consilina",
    "sg:orig_category":"Servizi E Lavori Per Arredamento E Industria Del Legno. Servizi Di Magazzinaggio E Movimentazione",
    "sg:phone":"+39 0975 520018",
    "sg:postcode":"84036",
    "sg:province":"Salerno",
    "wof:name":"Traslochi Marmo Achille",
    "wof:placetype":"venue"
},
  "geometry": {"coordinates":[15.617794,40.394474],"type":"Point"}
}