{
  "type": "Feature",
  "properties": {
    "iso:country":"IT",
    "sg:address":"25050 Provaglio D'iseo",
    "sg:orig_category":"Escavatori E Draghe",
    "sg:phone":"+39 030 982 3555",
    "sg:postcode":"25050",
    "sg:province":"Brescia",
    "wof:name":"L.m. Srl",
    "wof:placetype":"venue"
},
  "geometry": {"coordinates":[10.045796,45.636425],"type":"Point"}
}