{
  "type": "Feature",
  "properties": {
    "addr:full":"21016 Luino Luino Varese 21016",
    "addr:postcode":"21016;21016",
    "iso:country":"IT",
    "sg:address":"21016 Luino",
    "sg:city":"Luino",
    "sg:orig_category":"Torrefazione Di Caffe' Ed Affini - Lavorazione E Ingrosso",
    "sg:phone":"+39 0332 511057",
    "sg:postcode":"21016",
    "sg:province":"Varese",
    "wof:name":"Torrefazione Caffe' El Miguel Srl",
    "wof:placetype":"venue"
},
  "geometry": {"coordinates":[8.741787,45.995235],"type":"Point"}
}