{
  "type": "Feature",
  "properties": {
    "addr:full":"37036 San Martino Buon Albergo San Martino Buon Albergo Verona 37036",
    "addr:housenumber":"37036",
    "addr:postcode":"buon albergo;37036",
    "iso:country":"IT",
    "sg:address":"37036 San Martino Buon Albergo",
    "sg:city":"San Martino Buon Albergo",
    "sg:orig_category":"Impiantistica E Prodotti Tecnologici Per Edilizia. Climatizzazione E Condizionamento, Apparecchiature E Servizi",
    "sg:phone":"+39 045 878 0532",
    "sg:postcode":"37036",
    "sg:province":"Verona",
    "sg:website":"http://www.unitre.com",
    "wof:name":"Unitre Srl",
    "wof:placetype":"venue"
},
  "geometry": {"coordinates":[11.111832,45.419884],"type":"Point"}
}