{
  "type": "Feature",
  "properties": {
    "addr:full":"15016 Cassine Cassine Alessandria 15016",
    "addr:postcode":"15016;15016",
    "iso:country":"IT",
    "sg:address":"15016 Cassine",
    "sg:city":"Cassine",
    "sg:orig_category":"Forniture E Materiali Per Imballaggio E Confezionamento",
    "sg:phone":"+39 0144 715006",
    "sg:postcode":"15016",
    "sg:province":"Alessandria",
    "wof:name":"F.i.c. Fabbrica Italiana Capsule S.r.l.",
    "wof:placetype":"venue"
},
  "geometry": {"coordinates":[8.5744915009,44.8456878662],"type":"Point"}
}