{
  "type": "Feature",
  "properties": {
    "iso:country":"IT",
    "sg:address":"19124 La Spezia",
    "sg:classifiers":[
        {
            "category":"Education",
            "subcategory":"School",
            "type":"Public Place"
        }
    ],
    "sg:phone":"+39 0187 732774",
    "sg:province":"SP",
    "sg:tags":[
        "scuole",
        "informatica",
        "di"
    ],
    "wof:name":"Istituto Politecnico Informatico",
    "wof:placetype":"venue"
},
  "geometry": {"coordinates":[9.833347,44.11013],"type":"Point"}
}