{
  "type": "Feature",
  "properties": {
    "iso:country":"IT",
    "sg:address":"41100 Modena",
    "sg:city":"Modena",
    "sg:orig_category":"Chiese Ed Associazioni Religiose",
    "sg:phone":"+39 059 225950",
    "sg:postcode":"41100",
    "sg:province":"Modena",
    "wof:name":"Centro Evangelico Modenese",
    "wof:placetype":"venue"
},
  "geometry": {"coordinates":[10.914429,44.663944],"type":"Point"}
}