{
  "type": "Feature",
  "properties": {
    "iso:country":"IT",
    "sg:address":"00172 Roma",
    "sg:city":"Roma",
    "sg:orig_category":"Scuole E Servizi Scolastici. Alberghi E Strutture Extra Alberghiere",
    "sg:phone":"+39 06 251011",
    "sg:postcode":"00172",
    "sg:province":"Roma",
    "wof:name":"Collegium Lateranense",
    "wof:placetype":"venue"
},
  "geometry": {"coordinates":[12.576663,41.886898],"type":"Point"}
}