{
  "type": "Feature",
  "properties": {
    "iso:country":"IT",
    "sg:address":"17017 Millesimo",
    "sg:city":"Millesimo",
    "sg:orig_category":"Zootecnia E Pesca, Allevamento Piccoli Animali",
    "sg:phone":"+39 019 564256",
    "sg:postcode":"17017",
    "sg:province":"Savona",
    "wof:name":"Caretto Franco",
    "wof:placetype":"venue"
},
  "geometry": {"coordinates":[8.20594,44.364128],"type":"Point"}
}