{
  "type": "Feature",
  "properties": {
    "iso:country":"IT",
    "sg:address":"19126 La Spezia",
    "sg:orig_category":"Servizi E Lavori Per Ecologia E Smaltimento Rifiuti. Servizi Ausiliari Di Sorveglianza, Manutenzione E Pulizia",
    "sg:phone":"+39 0187 506391",
    "sg:province":"SP",
    "sg:website":"http://www.ipoter.com",
    "wof:name":"Ipoter Srl",
    "wof:placetype":"venue"
},
  "geometry": {"coordinates":[9.85375,44.111294],"type":"Point"}
}