{
  "type": "Feature",
  "properties": {
    "iso:country":"IT",
    "sg:address":"19, Via Di Vittorio 20060 Vignate",
    "sg:city":"Vignate",
    "sg:classifiers":[
        {
            "category":"Real Estate",
            "subcategory":"Surveying",
            "type":"Services"
        }
    ],
    "sg:phone":"+39 39029566411",
    "sg:postcode":"20060",
    "sg:province":"Milano",
    "sg:tags":[
        "equipment",
        "material",
        "good",
        "-",
        "handling"
    ],
    "wof:name":"2 Mc S.r.l.",
    "wof:placetype":"venue"
},
  "geometry": {"coordinates":[9.332701,45.503017],"type":"Point"}
}