{
  "type": "Feature",
  "properties": {
    "iso:country":"IT",
    "sg:address":"19124 La Spezia",
    "sg:orig_category":"Tourism, Services. Transport, Auxiliary Services",
    "sg:phone":"+39 0187 734403",
    "sg:province":"SP",
    "wof:name":"Aiazzi Group Di Aiazzi F. & C.",
    "wof:placetype":"venue"
},
  "geometry": {"coordinates":[9.827123,44.107327],"type":"Point"}
}