{
  "type": "Feature",
  "properties": {
    "addr:full":"20040 Usmate Velate Usmate Velate Milano 20040",
    "addr:postcode":"20040;20040",
    "iso:country":"IT",
    "sg:address":"20040 Usmate Velate",
    "sg:city":"Usmate Velate",
    "sg:orig_category":"Materassi - Vendita Al Dettaglio",
    "sg:phone":"+39 039 675041",
    "sg:postcode":"20040",
    "sg:province":"Milano",
    "wof:name":"L.a.i.c.a. Snc",
    "wof:placetype":"venue"
},
  "geometry": {"coordinates":[9.313617,45.659851],"type":"Point"}
}