{
  "type": "Feature",
  "properties": {
    "iso:country":"IT",
    "sg:address":"74100 Taranto",
    "sg:city":"Taranto",
    "sg:orig_category":"Servizi Ausiliari Di Certificati, Riproduzioni, Disegni E Foto",
    "sg:phone":"+39 099 779 5926",
    "sg:postcode":"74100",
    "sg:province":"Taranto",
    "wof:name":"Fotocolor Liuzzi Di Liuzzi Angelo",
    "wof:placetype":"venue"
},
  "geometry": {"coordinates":[17.313931,40.503941],"type":"Point"}
}