{
  "type": "Feature",
  "properties": {
    "addr:full":"30035 Mirano Mirano Venezia 30035",
    "addr:postcode":"30035;30035",
    "iso:country":"IT",
    "sg:address":"30035 Mirano",
    "sg:city":"Mirano",
    "sg:orig_category":"Motori Ed Organi Di Trasmissione",
    "sg:phone":"+39 041 570 1388",
    "sg:postcode":"30035",
    "sg:province":"Venezia",
    "wof:name":"Megadyne S.e.d. Veneto S.r.l.",
    "wof:placetype":"venue"
},
  "geometry": {"coordinates":[12.1333742142,45.4952735901],"type":"Point"}
}