{
  "type": "Feature",
  "properties": {
    "iso:country":"IT",
    "sg:address":"00151 Roma",
    "sg:city":"Roma",
    "sg:orig_category":"Abiti Da Lavoro Ed Indumenti Protettivi",
    "sg:phone":"+39 06 5823 3865",
    "sg:postcode":"00151",
    "sg:province":"Roma",
    "wof:name":"Montesi Pietro & C. Sas",
    "wof:placetype":"venue"
},
  "geometry": {"coordinates":[12.445785,41.87236],"type":"Point"}
}