{
  "type": "Feature",
  "properties": {
    "iso:country":"IT",
    "sg:address":"10123 Torino",
    "sg:city":"Torino",
    "sg:orig_category":"Forniture Per Edilizia E Lavori Pubblici. Forniture Per Attivita' Industriali",
    "sg:phone":"+39 011 812 4765",
    "sg:postcode":"10123",
    "sg:province":"Torino",
    "wof:name":"Lco",
    "wof:placetype":"venue"
},
  "geometry": {"coordinates":[7.1200766563,45.1260185242],"type":"Point"}
}