{
  "type": "Feature",
  "properties": {
    "iso:country":"IT",
    "sg:address":"Via Grassa 6; Rivara; 10080",
    "sg:city":"Rivara",
    "sg:classifiers":[
        {
            "category":"Banks & Credit Unions",
            "subcategory":"Bank",
            "type":"Services"
        }
    ],
    "sg:phone":"+39 0124 31296",
    "sg:postcode":"10080",
    "sg:province":"Torino",
    "wof:name":"Istituto Bancario, San Paolo Di Torino Spa",
    "wof:placetype":"venue"
},
  "geometry": {"coordinates":[7.624614,45.334743],"type":"Point"}
}