{
  "type": "Feature",
  "properties": {
    "iso:country":"IT",
    "sg:address":"11, Via Popoli Uniti 20127 Milano",
    "sg:city":"Milano",
    "sg:classifiers":[
        {
            "category":"Bars & Pubs",
            "subcategory":"Nightclub",
            "type":"Food & Drink"
        }
    ],
    "sg:phone":"+39 39022846442",
    "sg:postcode":"20127",
    "sg:province":"Milano",
    "sg:tags":[
        "cake",
        "bread"
    ],
    "wof:name":"Cova G. & C.",
    "wof:placetype":"venue"
},
  "geometry": {"coordinates":[9.21835,45.496006],"type":"Point"}
}