{
  "type": "Feature",
  "properties": {
    "addr:full":"37067 Valeggio Sul Mincio Valeggio sul Mincio Verona 37067",
    "addr:postcode":"37067;37067",
    "iso:country":"IT",
    "sg:address":"37067 Valeggio Sul Mincio",
    "sg:city":"Valeggio sul Mincio",
    "sg:orig_category":"Servizi E Lavori Per Agricoltura E Zootecnia. Servizi E Lavori Per Ecologia E Smaltimento Rifiuti",
    "sg:phone":"+39 045 795 0019",
    "sg:postcode":"37067",
    "sg:province":"Verona",
    "wof:name":"Consorzio Di Bonifica Adige Garda",
    "wof:placetype":"venue"
},
  "geometry": {"coordinates":[10.737686,45.350521],"type":"Point"}
}