{
  "type": "Feature",
  "properties": {
    "iso:country":"IT",
    "sg:address":"20036 Meda",
    "sg:city":"Meda",
    "sg:orig_category":"Legno E Semilavorati",
    "sg:phone":"+39 036 271278",
    "sg:postcode":"20036",
    "sg:province":"Milano",
    "sg:website":"http://www.caronnisnc.com",
    "wof:name":"Caronni Snc Di A. Caronni & C.",
    "wof:placetype":"venue"
},
  "geometry": {"coordinates":[9.213362,45.467617],"type":"Point"}
}