{
  "type": "Feature",
  "properties": {
    "iso:country":"IT",
    "sg:address":"15, Contrada Collevecchio 65019 Pianella",
    "sg:city":"Pianella",
    "sg:classifiers":[
        {
            "category":"Parking",
            "subcategory":"Lot",
            "type":"Transportation"
        }
    ],
    "sg:phone":"+39 39085972634",
    "sg:postcode":"65019",
    "sg:province":"Pescara",
    "sg:tags":[
        "transport",
        "road"
    ],
    "wof:name":"Autotrasporti Cutilli & C. Snc",
    "wof:placetype":"venue"
},
  "geometry": {"coordinates":[14.03161,42.382698],"type":"Point"}
}