{
  "type": "Feature",
  "properties": {
    "iso:country":"IT",
    "sg:address":"20154 Milano",
    "sg:city":"Milano",
    "sg:orig_category":"Servizi Vari Di Interesse Pubblico",
    "sg:phone":"+39 02 331 3635",
    "sg:postcode":"20154",
    "sg:province":"Milano",
    "wof:name":"Ogliari Antonio",
    "wof:placetype":"venue"
},
  "geometry": {"coordinates":[9.171083,45.480442],"type":"Point"}
}