{
  "type": "Feature",
  "properties": {
    "iso:country":"IT",
    "sg:address":"10154 Torino",
    "sg:city":"Torino",
    "sg:orig_category":"Servizi E Lavori Per Agricoltura E Zootecnia. Servizi Ausiliari Di Analisi, Controllo E Ricerca",
    "sg:phone":"+39 011 247 2025",
    "sg:postcode":"10154",
    "sg:province":"Torino",
    "wof:name":"Istit. Zooprofil. Sperimentale",
    "wof:placetype":"venue"
},
  "geometry": {"coordinates":[7.703932,45.086227],"type":"Point"}
}