{
  "type": "Feature",
  "properties": {
    "addr:full":"105, V. Bra 12062 Cherasco Cherasco Cuneo 12062",
    "addr:housenumber":"105",
    "addr:postcode":"12062;12062",
    "addr:street":"V. Bra",
    "iso:country":"IT",
    "sg:address":"105, V. Bra 12062 Cherasco",
    "sg:city":"Cherasco",
    "sg:classifiers":[
        {
            "category":"Parking",
            "subcategory":"Lot",
            "type":"Transportation"
        }
    ],
    "sg:phone":"+39 0172 495164",
    "sg:postcode":"12062",
    "sg:province":"Cuneo",
    "sg:tags":[
        "transport",
        "road"
    ],
    "sg:website":"http://www.paginegialle.it/veglioluigi",
    "wof:name":"Veglio Luigi Sas",
    "wof:placetype":"venue"
},
  "geometry": {"coordinates":[7.850744,44.685532],"type":"Point"}
}