{
  "type": "Feature",
  "properties": {
    "iso:country":"IT",
    "sg:address":"96100 Siracusa",
    "sg:city":"Siracusa",
    "sg:classifiers":[
        {
            "category":"Travel",
            "subcategory":"Travel Agent",
            "type":"Entertainment"
        }
    ],
    "sg:phone":"+39 0931 463866",
    "sg:postcode":"96100",
    "sg:province":"Siracusa",
    "sg:tags":[
        "operator",
        "tour",
        "tourist"
    ],
    "wof:name":"Maritime Services Giovanni Boccadifuoco Figli Srl",
    "wof:placetype":"venue"
},
  "geometry": {"coordinates":[15.290663,37.062881],"type":"Point"}
}