{
  "type": "Feature",
  "properties": {
    "iso:country":"IT",
    "sg:address":"37068 Vigasio",
    "sg:city":"Vigasio",
    "sg:orig_category":"Vetro: Prodotti E Lavorazioni",
    "sg:phone":"+39 045 669 9100",
    "sg:postcode":"37068",
    "sg:province":"Verona",
    "wof:name":"Rossi Oscar Isor Alluminio",
    "wof:placetype":"venue"
},
  "geometry": {"coordinates":[10.933436,45.324314],"type":"Point"}
}