{
  "type": "Feature",
  "properties": {
    "iso:country":"IT",
    "sg:address":"20127 Milano",
    "sg:city":"Milano",
    "sg:orig_category":"Guarnizioni Industriali",
    "sg:phone":"+39 02 257 8308",
    "sg:postcode":"20127",
    "sg:province":"Milano",
    "wof:name":"James Walker Italiana Srl",
    "wof:placetype":"venue"
},
  "geometry": {"coordinates":[9.224364,45.504704],"type":"Point"}
}