{
  "type": "Feature",
  "properties": {
    "iso:country":"IT",
    "sg:address":"00155 Roma",
    "sg:city":"Roma",
    "sg:orig_category":"Macchine Utensili E Impianti",
    "sg:phone":"+39 06 228 5487",
    "sg:postcode":"00155",
    "sg:province":"Roma",
    "wof:name":"A.r.p.e.n. (s.r.l.)",
    "wof:placetype":"venue"
},
  "geometry": {"coordinates":[12.611196,41.886631],"type":"Point"}
}