{
  "type": "Feature",
  "properties": {
    "iso:country":"IT",
    "sg:address":"50060 Ferrano",
    "sg:orig_category":"Alberghi E Strutture Extra Alberghiere. Ospedali E Servizi Sanitari",
    "sg:phone":"+39 055 832 6739",
    "sg:postcode":"50060",
    "sg:province":"Firenze",
    "wof:name":"Campeggio Il Mastio",
    "wof:placetype":"venue"
},
  "geometry": {"coordinates":[11.54054,43.779099],"type":"Point"}
}