{
  "type": "Feature",
  "properties": {
    "iso:country":"IT",
    "sg:address":"88100 Catanzaro",
    "sg:city":"Catanzaro",
    "sg:classifiers":[
        {
            "category":"Retail",
            "subcategory":"Auto Repair",
            "type":"Services"
        }
    ],
    "sg:phone":"+39 0961 719030",
    "sg:postcode":"88100",
    "sg:province":"Catanzaro",
    "sg:tags":[
        "repairs",
        "vehicles",
        "auxiliary",
        "motor"
    ],
    "wof:name":"Anania Giovanni",
    "wof:placetype":"venue"
},
  "geometry": {"coordinates":[16.6055526733,38.8860588074],"type":"Point"}
}