{
  "type": "Feature",
  "properties": {
    "iso:country":"IT",
    "sg:address":"50055 Lastra A Signa",
    "sg:city":"Lastra a Signa",
    "sg:orig_category":"Agenzie D'affari E Servizi Commerciali",
    "sg:phone":"+39 055 872 0026",
    "sg:postcode":"50055",
    "sg:province":"Firenze",
    "wof:name":"Consorzio Firenze Export",
    "wof:placetype":"venue"
},
  "geometry": {"coordinates":[11.082491,43.73737],"type":"Point"}
}