{
  "type": "Feature",
  "properties": {
    "iso:country":"IT",
    "sg:address":"Piazza Amisani 5/6; Mede; 27035",
    "sg:city":"Mede",
    "sg:classifiers":[
        {
            "category":"Banks & Credit Unions",
            "subcategory":"Bank",
            "type":"Services"
        }
    ],
    "sg:phone":"+39 0384 805252",
    "sg:postcode":"27035",
    "sg:province":"Pavia",
    "wof:name":"Cassa Di Risparmio Di Alessandria Spa",
    "wof:placetype":"venue"
},
  "geometry": {"coordinates":[8.7361,45.096867],"type":"Point"}
}