{
  "type": "Feature",
  "properties": {
    "iso:country":"IT",
    "sg:address":"Viale Trieste 163; Vicenza",
    "sg:classifiers":[
        {
            "category":"Banks & Credit Unions",
            "subcategory":"Bank",
            "type":"Services"
        }
    ],
    "sg:phone":"+39 0444 500255",
    "wof:name":"Banca Di Roma",
    "wof:placetype":"venue"
},
  "geometry": {"coordinates":[11.559588,45.558678],"type":"Point"}
}