{
  "type": "Feature",
  "properties": {
    "iso:country":"IT",
    "sg:address":"46010 Curtatone",
    "sg:city":"Curtatone",
    "sg:orig_category":"Petroli, Gas E Combustibili. Termotecnica E Riscaldamento, Apparecchiature E Servizi",
    "sg:phone":"+39 0376 291768",
    "sg:postcode":"46010",
    "sg:province":"Mantova",
    "wof:name":"Nardi Natale Sas Di Nardi Natale & C.",
    "wof:placetype":"venue"
},
  "geometry": {"coordinates":[10.735918045,45.0840682983],"type":"Point"}
}