{
  "type": "Feature",
  "properties": {
    "iso:country":"IT",
    "sg:address":"Via Gaudenzio Ferrari 21 21047 Saronno",
    "sg:city":"Saronno",
    "sg:classifiers":[
        {
            "category":"Structure",
            "subcategory":"Factory",
            "type":"Public Place"
        }
    ],
    "sg:phone":"+39 02 9670 1418",
    "sg:postcode":"21047",
    "sg:province":"Varese",
    "sg:tags":[
        "complete",
        "installations"
    ],
    "sg:website":"www.cimipi.it",
    "wof:name":"Cimipi S.r.l",
    "wof:placetype":"venue"
},
  "geometry": {"coordinates":[9.0284862518,45.6242446899],"type":"Point"}
}