{
  "type": "Feature",
  "properties": {
    "iso:country":"IT",
    "sg:address":"00161 Roma",
    "sg:city":"Roma",
    "sg:classifiers":[
        {
            "category":"Health Services",
            "subcategory":"Health Practitioner",
            "type":"Services"
        }
    ],
    "sg:phone":"+39 800 993 300",
    "sg:postcode":"00161",
    "sg:province":"Roma",
    "sg:tags":[
        "medici"
    ],
    "wof:name":"Assomedico",
    "wof:placetype":"venue"
},
  "geometry": {"coordinates":[12.479751,41.807034],"type":"Point"}
}