{
  "type": "Feature",
  "properties": {
    "iso:country":"IT",
    "sg:address":"20145 Milano",
    "sg:city":"Milano",
    "sg:orig_category":"Servizi Ausiliari Dei Mezzi Di Trasporto",
    "sg:phone":"+39 02 481 7481",
    "sg:postcode":"20145",
    "sg:province":"Milano",
    "wof:name":"Garage Piercapponi",
    "wof:placetype":"venue"
},
  "geometry": {"coordinates":[9.158108,45.469044],"type":"Point"}
}