{
  "type": "Feature",
  "properties": {
    "addr:full":"95045 Misterbianco Misterbianco Catania 95045",
    "addr:postcode":"95045;95045",
    "iso:country":"IT",
    "sg:address":"95045 Misterbianco",
    "sg:city":"Misterbianco",
    "sg:orig_category":"Servizi Editoriali",
    "sg:phone":"+39 095 714 4199",
    "sg:postcode":"95045",
    "sg:province":"Catania",
    "wof:name":"Guglielmo Ubaldo",
    "wof:placetype":"venue"
},
  "geometry": {"coordinates":[15.050841,37.533756],"type":"Point"}
}