{
  "type": "Feature",
  "properties": {
    "iso:country":"IT",
    "sg:address":"25049 Iseo",
    "sg:city":"Iseo",
    "sg:classifiers":[
        {
            "category":"Government",
            "subcategory":"Office",
            "type":"Public Place"
        }
    ],
    "sg:phone":"+39 030 9822 2231",
    "sg:postcode":"25049",
    "sg:province":"Brescia",
    "sg:tags":[
        "e",
        "lo",
        "tempo",
        "libero",
        "per",
        "spettacolo",
        "servizi",
        "culturali",
        "sport",
        "il"
    ],
    "wof:name":"Consoli Pier Luigi",
    "wof:placetype":"venue"
},
  "geometry": {"coordinates":[10.064176,45.628212],"type":"Point"}
}