{
  "type": "Feature",
  "properties": {
    "iso:country":"IT",
    "sg:address":"Via Altovergante 33 28045 Invorio",
    "sg:city":"Invorio",
    "sg:orig_category":"Fittings, Valves",
    "sg:phone":"+39 0322 255391",
    "sg:postcode":"28045",
    "sg:province":"Novara",
    "sg:website":"www.latorresrl.com",
    "wof:name":"La Torre Srl",
    "wof:placetype":"venue"
},
  "geometry": {"coordinates":[8.4908981323,45.7295646667],"type":"Point"}
}