{
  "type": "Feature",
  "properties": {
    "iso:country":"IT",
    "sg:address":"S. Angelo; 65013",
    "sg:classifiers":[
        {
            "category":"Banks & Credit Unions",
            "subcategory":"Bank",
            "type":"Services"
        }
    ],
    "sg:phone":"+39 085 95123",
    "sg:postcode":"65013",
    "sg:province":"Pescara",
    "wof:name":"Banca Popolare Dell'adriatico",
    "wof:placetype":"venue"
},
  "geometry": {"coordinates":[14.065289,42.507992],"type":"Point"}
}