{
  "type": "Feature",
  "properties": {
    "iso:country":"IT",
    "sg:address":"90133 Palermo",
    "sg:city":"Palermo",
    "sg:orig_category":"Materiali Edili",
    "sg:phone":"+39 091 585422",
    "sg:postcode":"90133",
    "sg:province":"Palermo",
    "wof:name":"Cillari Gioacchino",
    "wof:placetype":"venue"
},
  "geometry": {"coordinates":[13.35984,38.121334],"type":"Point"}
}