{
  "type": "Feature",
  "properties": {
    "addr:full":"25020 Seniga Seniga Brescia 25020",
    "addr:postcode":"25020;25020",
    "iso:country":"IT",
    "sg:address":"25020 Seniga",
    "sg:city":"Seniga",
    "sg:classifiers":[
        {
            "category":"Home & Garden",
            "subcategory":"Home Furnishings",
            "type":"Retail Goods"
        }
    ],
    "sg:phone":"+39 030 995 5329",
    "sg:postcode":"25020",
    "sg:province":"Brescia",
    "sg:tags":[
        "bathroom",
        "accessories"
    ],
    "wof:name":"Pantografature Diem Sas Di Mazza Diego",
    "wof:placetype":"venue"
},
  "geometry": {"coordinates":[10.1988382339,45.539226532],"type":"Point"}
}