{
  "type": "Feature",
  "properties": {
    "iso:country":"IT",
    "sg:address":"Piazza Mercato 42 35010 Villanova Di Camposanpiero",
    "sg:city":"Villanova",
    "sg:classifiers":[
        {
            "category":"Wholesale",
            "subcategory":"Office Equipment",
            "type":"Manufacturing & Wholesale Goods"
        }
    ],
    "sg:phone":"+39 049 929 9299",
    "sg:postcode":"35010",
    "sg:province":"Padova",
    "sg:tags":[
        "chairs",
        "swivel",
        "chair"
    ],
    "wof:name":"Diwar Spa",
    "wof:placetype":"venue"
},
  "geometry": {"coordinates":[11.972558,45.491035],"type":"Point"}
}