{
  "type": "Feature",
  "properties": {
    "iso:country":"IT",
    "sg:address":"Via Xxiv Maggio 1 24055 Cologno Al Serio",
    "sg:city":"Cologno al Serio",
    "sg:classifiers":[
        {
            "category":"Structure",
            "subcategory":"Tunnel",
            "type":"Public Place"
        }
    ],
    "sg:phone":"+39 035 487 1487",
    "sg:postcode":"24055",
    "sg:province":"Bergamo",
    "sg:tags":[
        "packing",
        "system"
    ],
    "wof:name":"Grifal Spa",
    "wof:placetype":"venue"
},
  "geometry": {"coordinates":[9.6699523926,45.6949043274],"type":"Point"}
}