{
  "type": "Feature",
  "properties": {
    "iso:country":"IT",
    "sg:address":"20098 San Giuliano Milanese",
    "sg:city":"San Giuliano Milanese",
    "sg:orig_category":"Macchine, Impianti E Forniture Per Industria Grafica, Cartaria E Cartotecnica. Prodotti Chimici Secondari",
    "sg:phone":"+39 02 9828 4060",
    "sg:postcode":"20098",
    "sg:province":"Milano",
    "wof:name":"Kfg Italiana S.r.l.",
    "wof:placetype":"venue"
},
  "geometry": {"coordinates":[9.264843,45.39563],"type":"Point"}
}