{
  "type": "Feature",
  "properties": {
    "iso:country":"IT",
    "sg:address":"Via Lignano Sabbiadoro 28/c 33050 Pertegada",
    "sg:city":"Pertegada",
    "sg:classifiers":[
        {
            "category":"Real Estate",
            "subcategory":"Real Estate Agent",
            "type":"Services"
        }
    ],
    "sg:phone":"+39 0431 55068",
    "sg:postcode":"33050",
    "sg:province":"Udine",
    "sg:tags":[
        "lacquer"
    ],
    "sg:website":"www.netanday.it",
    "wof:name":"Foce Srl",
    "wof:placetype":"venue"
},
  "geometry": {"coordinates":[13.043347,45.732124],"type":"Point"}
}