{
  "type": "Feature",
  "properties": {
    "iso:country":"IT",
    "sg:address":"31050 Onigo",
    "sg:orig_category":"Apparecchiature Ed Attrezzature Meccaniche",
    "sg:phone":"+39 0423 64122",
    "sg:postcode":"31050",
    "sg:province":"Treviso",
    "wof:name":"Novatec S.r.l.",
    "wof:placetype":"venue"
},
  "geometry": {"coordinates":[11.988906,45.857559],"type":"Point"}
}