{
  "type": "Feature",
  "properties": {
    "addr:full":"Via Farnace 35010 San Pietro In Gu San Pietro in Gu Padova 35010",
    "addr:postcode":"35010;pietro;35010",
    "addr:street":"Via Farnace;Gu San;Gu Padova",
    "iso:country":"IT",
    "sg:address":"Via Farnace 35010 San Pietro In Gu",
    "sg:city":"San Pietro in Gu",
    "sg:orig_category":"Photo Finishing",
    "sg:phone":"+39 049 945 5277",
    "sg:postcode":"35010",
    "sg:province":"Padova",
    "sg:website":"www.afilab.com",
    "wof:name":"A.f.i. Srl",
    "wof:placetype":"venue"
},
  "geometry": {"coordinates":[11.8765888214,45.4095687866],"type":"Point"}
}