{
  "type": "Feature",
  "properties": {
    "iso:country":"IT",
    "sg:address":"20127 Milano",
    "sg:city":"Milano",
    "sg:orig_category":"Materiali E Componenti Elettronici",
    "sg:phone":"+39 02 2720 9005",
    "sg:postcode":"20127",
    "sg:province":"Milano",
    "wof:name":"Stagnatura Paruta Snc",
    "wof:placetype":"venue"
},
  "geometry": {"coordinates":[9.238507,45.503777],"type":"Point"}
}