{
  "type": "Feature",
  "properties": {
    "iso:country":"IT",
    "sg:address":"46040 Guidizzolo",
    "sg:city":"Guidizzolo",
    "sg:orig_category":"Servizi E Lavori Per Arredamento E Industria Del Legno. Servizi E Lavori Per Edilizia E Lavori Pubblici",
    "sg:phone":"+39 0376 840362",
    "sg:postcode":"46040",
    "sg:province":"Mantova",
    "wof:name":"Goitese Legnami Di Bordiga Cristina & C. Snc",
    "wof:placetype":"venue"
},
  "geometry": {"coordinates":[10.581574,45.321739],"type":"Point"}
}