{
  "type": "Feature",
  "properties": {
    "addr:full":"Via Roma 26; Venosa; 85029 Venosa Potenza 85029",
    "addr:housenumber":"26",
    "addr:postcode":"85029;85029",
    "addr:street":"Via Roma;Venosa",
    "iso:country":"IT",
    "sg:address":"Via Roma 26; Venosa; 85029",
    "sg:city":"Venosa",
    "sg:classifiers":[
        {
            "category":"Banks & Credit Unions",
            "subcategory":"Bank",
            "type":"Services"
        }
    ],
    "sg:phone":"+39 0972 31004",
    "sg:postcode":"85029",
    "sg:province":"Potenza",
    "wof:name":"Banco Di Napoli Spa",
    "wof:placetype":"venue"
},
  "geometry": {"coordinates":[15.816896,40.961926],"type":"Point"}
}