{
  "type": "Feature",
  "properties": {
    "iso:country":"IT",
    "sg:address":"59, Via Pertini Sandro 50019 Sesto Fiorentino",
    "sg:city":"Sesto Fiorentino",
    "sg:classifiers":[
        {
            "category":"Personal",
            "subcategory":"Shoe Repair & Shine",
            "type":"Services"
        }
    ],
    "sg:phone":"+39 055 421 1232",
    "sg:postcode":"50019",
    "sg:province":"Firenze",
    "sg:tags":[
        "leather"
    ],
    "wof:name":"Arte Della Pelle S.r.l.",
    "wof:placetype":"venue"
},
  "geometry": {"coordinates":[11.228927,43.793552],"type":"Point"}
}