{
  "type": "Feature",
  "properties": {
    "iso:country":"IT",
    "sg:address":"40055 Castenaso",
    "sg:city":"Castenaso",
    "sg:orig_category":"Apparecchiature Ed Attrezzature Meccaniche",
    "sg:phone":"+39 051 780051",
    "sg:postcode":"40055",
    "sg:province":"Bologna",
    "wof:name":"Aertubi S.r.l.",
    "wof:placetype":"venue"
},
  "geometry": {"coordinates":[11.434513,44.502823],"type":"Point"}
}