{
  "type": "Feature",
  "properties": {
    "iso:country":"IT",
    "sg:address":"119, Via Astalonga 80047 San Giuseppe Vesuviano",
    "sg:city":"San Giuseppe Vesuviano",
    "sg:classifiers":[
        {
            "category":"Shopping",
            "subcategory":"Crafts & Fabrics",
            "type":"Retail Goods"
        }
    ],
    "sg:phone":"+39 081 529 5771",
    "sg:postcode":"80047",
    "sg:province":"Napoli",
    "wof:name":"Centro Tessile Annunziata S.r.l.",
    "wof:placetype":"venue"
},
  "geometry": {"coordinates":[14.4938774109,40.8385124207],"type":"Point"}
}