{
  "type": "Feature",
  "properties": {
    "iso:country":"IT",
    "sg:address":"51031 Agliana",
    "sg:city":"Agliana",
    "sg:orig_category":"Forniture Per Abbigliamento E Pelletterie",
    "sg:phone":"+39 0574 718220",
    "sg:postcode":"51031",
    "sg:province":"Pistoia",
    "wof:name":"Sfilacciatura Torracchi (s.n.c.)",
    "wof:placetype":"venue"
},
  "geometry": {"coordinates":[11.0048427582,43.9072952271],"type":"Point"}
}