{
  "type": "Feature",
  "properties": {
    "iso:country":"IT",
    "sg:address":"00128 Roma",
    "sg:city":"Roma",
    "sg:orig_category":"Macchine Utensili E Impianti",
    "sg:phone":"+39 06 507 1910",
    "sg:postcode":"00128",
    "sg:province":"Roma",
    "wof:name":"Tecnoviti Di Maccari Antonio",
    "wof:placetype":"venue"
},
  "geometry": {"coordinates":[12.451842,41.793617],"type":"Point"}
}