{
  "type": "Feature",
  "properties": {
    "iso:country":"IT",
    "sg:address":"25085 Gavardo",
    "sg:city":"Gavardo",
    "sg:orig_category":"Lavorazioni Metalli, Stampaggio E Saldatura",
    "sg:phone":"+39 036 537 4547",
    "sg:postcode":"25085",
    "sg:province":"Brescia",
    "wof:name":"Tecnojet Snc Di Frapporti & C.",
    "wof:placetype":"venue"
},
  "geometry": {"coordinates":[10.419898,45.589684],"type":"Point"}
}