{
  "type": "Feature",
  "properties": {
    "iso:country":"IT",
    "sg:address":"56021 Cascina",
    "sg:city":"Cascina",
    "sg:orig_category":"Calzature, Pelletterie E Pelli",
    "sg:phone":"+39 050 703062",
    "sg:postcode":"56021",
    "sg:province":"Pisa",
    "wof:name":"Salvadori Paola",
    "wof:placetype":"venue"
},
  "geometry": {"coordinates":[10.549444,43.673817],"type":"Point"}
}