{
  "type": "Feature",
  "properties": {
    "iso:country":"IT",
    "sg:address":"20129 Milano",
    "sg:city":"Milano",
    "sg:orig_category":"Apparecchi, Attrezzature E Forniture Per Centri Estetici",
    "sg:phone":"+39 02 2048 0811",
    "sg:postcode":"20129",
    "sg:province":"Milano",
    "wof:name":"Beauty Business Srl",
    "wof:placetype":"venue"
},
  "geometry": {"coordinates":[9.205524,45.473705],"type":"Point"}
}