{
  "type": "Feature",
  "properties": {
    "iso:country":"IT",
    "sg:address":"3/r, V. Fracastoro 50134 Firenze",
    "sg:city":"Firenze",
    "sg:classifiers":[
        {
            "category":"Manufacturing",
            "subcategory":"Glass & Minerals",
            "type":"Manufacturing & Wholesale Goods"
        }
    ],
    "sg:phone":"+39 055 436 0795",
    "sg:postcode":"50134",
    "sg:province":"Firenze",
    "sg:website":"http://www.paginegialle.it/firenzevetri",
    "wof:name":"Firenze Vetri Srl",
    "wof:placetype":"venue"
},
  "geometry": {"coordinates":[11.242117,43.798725],"type":"Point"}
}