{
  "type": "Feature",
  "properties": {
    "addr:full":"13048 Santhia' Vercelli 13048",
    "addr:postcode":"13048;13048",
    "iso:country":"IT",
    "sg:address":"13048 Santhia'",
    "sg:orig_category":"Accessori Moda D'abbigliamento. Shopping",
    "sg:phone":"+39 0161 923135",
    "sg:postcode":"13048",
    "sg:province":"Vercelli",
    "wof:name":"Fracasso Spartaco",
    "wof:placetype":"venue"
},
  "geometry": {"coordinates":[8.179369,45.366398],"type":"Point"}
}