{
  "type": "Feature",
  "properties": {
    "iso:country":"IT",
    "sg:address":"42041 Brescello",
    "sg:orig_category":"Arredo Cucina Ed Elettrodomestici. Frigotecnica, Apparecchiature E Servizi. Elettrodomestici",
    "sg:phone":"+39 0522 687295",
    "sg:postcode":"42041",
    "sg:province":"Reggio Nell'Emilia",
    "wof:name":"Safo (s.n.c.)",
    "wof:placetype":"venue"
},
  "geometry": {"coordinates":[10.644668,44.695835],"type":"Point"}
}