{
  "type": "Feature",
  "properties": {
    "iso:country":"IT",
    "sg:address":"46010 Curtatone",
    "sg:city":"Curtatone",
    "sg:orig_category":"Servizi E Lavori Per Edilizia E Lavori Pubblici. Professionisti - Studi E Servizi Ed Associazioni Di Interesse Aziendale",
    "sg:phone":"+39 0376 31174",
    "sg:postcode":"46010",
    "sg:province":"Mantova",
    "wof:name":"Silla Daniele",
    "wof:placetype":"venue"
},
  "geometry": {"coordinates":[10.436913,45.278812],"type":"Point"}
}