{
  "type": "Feature",
  "properties": {
    "iso:country":"IT",
    "sg:address":"95129 Catania",
    "sg:city":"Catania",
    "sg:orig_category":"Ceramiche: Prodotti E Lavorazioni. Forniture Per Attivita' Industriali",
    "sg:phone":"+39 095 321275",
    "sg:postcode":"95129",
    "sg:province":"Catania",
    "wof:name":"L'artistica Srl",
    "wof:placetype":"venue"
},
  "geometry": {"coordinates":[15.093471,37.515564],"type":"Point"}
}