{
  "type": "Feature",
  "properties": {
    "iso:country":"IT",
    "sg:address":"47, Via Marchefave 45026 Lendinara",
    "sg:city":"Lendinara",
    "sg:classifiers":[
        {
            "category":"Shopping",
            "subcategory":"Clothing, Apparel, & Fashions",
            "type":"Retail Goods"
        }
    ],
    "sg:phone":"+39 0425 601366",
    "sg:postcode":"45026",
    "sg:province":"Rovigo",
    "sg:tags":[
        "clothes"
    ],
    "wof:name":"Confezioni Amsterdam",
    "wof:placetype":"venue"
},
  "geometry": {"coordinates":[11.627128,45.077362],"type":"Point"}
}