{
  "type": "Feature",
  "properties": {
    "iso:country":"IT",
    "sg:address":"00171 Roma",
    "sg:city":"Roma",
    "sg:classifiers":[
        {
            "category":"Health Services",
            "subcategory":"Health Practitioner",
            "type":"Services"
        }
    ],
    "sg:phone":"+39 06 215 4032",
    "sg:postcode":"00171",
    "sg:province":"Roma",
    "sg:tags":[
        "medici"
    ],
    "wof:name":"Michael Michael",
    "wof:placetype":"venue"
},
  "geometry": {"coordinates":[12.561316,41.891674],"type":"Point"}
}