{
  "type": "Feature",
  "properties": {
    "iso:country":"IT",
    "sg:address":"126, Viale Testi Fulvio 20092 Cinisello Balsamo",
    "sg:city":"Cinisello Balsamo",
    "sg:classifiers":[
        {
            "category":"Utilities",
            "subcategory":"Electric",
            "type":"Services"
        }
    ],
    "sg:phone":"+39 39022491121",
    "sg:postcode":"20092",
    "sg:province":"Milano",
    "sg:tags":[
        "component",
        "electronic"
    ],
    "wof:name":"Intersil S.r.l.",
    "wof:placetype":"venue"
},
  "geometry": {"coordinates":[9.215252,45.531631],"type":"Point"}
}