{
  "type": "Feature",
  "properties": {
    "iso:country":"IT",
    "sg:address":"45, Via Nappi G. 83100 Avellino",
    "sg:city":"Avellino",
    "sg:classifiers":[
        {
            "category":"Communications",
            "subcategory":"Television Station",
            "type":"Services"
        }
    ],
    "sg:phone":"+39 39082574582",
    "sg:postcode":"83100",
    "sg:province":"Avellino",
    "sg:tags":[
        "equipment",
        "optical",
        "instrument"
    ],
    "wof:name":"Ascon S.r.l.",
    "wof:placetype":"venue"
},
  "geometry": {"coordinates":[14.820302,40.921459],"type":"Point"}
}