{
  "type": "Feature",
  "properties": {
    "iso:country":"IT",
    "sg:address":"19126 La Spezia",
    "sg:classifiers":[
        {
            "category":"Home & Garden",
            "subcategory":"Home Furnishings",
            "type":"Retail Goods"
        }
    ],
    "sg:phone":"+39 0187 280355",
    "sg:province":"SP",
    "sg:tags":[
        "art",
        "furniture",
        "shopping",
        "artistic",
        "crafts"
    ],
    "wof:name":"Nautilus Di Valli Catia",
    "wof:placetype":"venue"
},
  "geometry": {"coordinates":[9.8599328995,44.1075286865],"type":"Point"}
}