{
  "type": "Feature",
  "properties": {
    "iso:country":"IT",
    "sg:address":"Via Pedrada, 16 - Vigonovo 33074 Fontanafredda",
    "sg:city":"Fontanafredda",
    "sg:classifiers":[
        {
            "category":"Utilities",
            "subcategory":"Sewage",
            "type":"Services"
        }
    ],
    "sg:phone":"+39 0434 999606",
    "sg:postcode":"33074",
    "sg:province":"Pordenone",
    "sg:tags":[
        "plant",
        "industrial",
        "stp",
        "treatment"
    ],
    "wof:name":"Friulana Costruzioni Srl",
    "wof:placetype":"venue"
},
  "geometry": {"coordinates":[12.522274,45.975376],"type":"Point"}
}