{
  "type": "Feature",
  "properties": {
    "addr:full":"25125 Brescia Brescia Brescia 25125",
    "addr:postcode":"25125;25125",
    "iso:country":"IT",
    "sg:address":"25125 Brescia",
    "sg:city":"Brescia",
    "sg:orig_category":"Banche E Servizi Finanziari. Acqua, Luce, Gas E Societa' Di Esercizio Pubblico. Pubblica Amministrazione",
    "sg:phone":"+39 030 347758",
    "sg:postcode":"25125",
    "sg:province":"Brescia",
    "wof:name":"Agenzia Delle Entrate",
    "wof:placetype":"venue"
},
  "geometry": {"coordinates":[10.186083,45.530098],"type":"Point"}
}