{
  "type": "Feature",
  "properties": {
    "iso:country":"IT",
    "sg:address":"56017 San Giuliano Terme",
    "sg:city":"San Giuliano Terme",
    "sg:orig_category":"Elettronica Professionale E Di Consumo. Forniture Per Il Settore Dello Spettacolo. Automazione E Macchine Per Ufficio. Forniture Per Congressi, Fiere E Manifestazioni",
    "sg:phone":"+39 050 859945",
    "sg:postcode":"56017",
    "sg:province":"Pisa",
    "sg:website":"http://www.northstar.it",
    "wof:name":"North Star Design Srl",
    "wof:placetype":"venue"
},
  "geometry": {"coordinates":[10.411765,43.76535],"type":"Point"}
}