{
  "type": "Feature",
  "properties": {
    "addr:full":"24042 Capriate San Gervasio Capriate San Gervasio Bergamo 24042",
    "addr:housenumber":"24042",
    "addr:postcode":"24042",
    "addr:street":"Capriate",
    "iso:country":"IT",
    "sg:address":"24042 Capriate San Gervasio",
    "sg:city":"Capriate San Gervasio",
    "sg:orig_category":"Hobbistica",
    "sg:phone":"+39 02 909 1536",
    "sg:postcode":"24042",
    "sg:province":"Bergamo",
    "wof:name":"Negri Giordano",
    "wof:placetype":"venue"
},
  "geometry": {"coordinates":[9.5284776688,45.6132087708],"type":"Point"}
}