{
  "type": "Feature",
  "properties": {
    "iso:country":"IT",
    "sg:address":"17100 Savona",
    "sg:city":"Savona",
    "sg:orig_category":"Arredamenti E Mobili Professionali. Apparecchi, Attrezzature E Forniture Per Centri Estetici. Arredi Ed Attrezzature Per Attivita' Commerciali Ed Artigianali",
    "sg:phone":"+39 019 811388",
    "sg:postcode":"17100",
    "sg:province":"Savona",
    "wof:name":"D'amico Aldo",
    "wof:placetype":"venue"
},
  "geometry": {"coordinates":[8.472462,44.310101],"type":"Point"}
}