{
  "type": "Feature",
  "properties": {
    "iso:country":"IT",
    "sg:address":"14100 Asti",
    "sg:city":"Asti",
    "sg:orig_category":"Climatizzazione E Condizionamento, Apparecchiature E Servizi",
    "sg:phone":"+39 0141 210422",
    "sg:postcode":"14100",
    "sg:province":"Asti",
    "wof:name":"Agenzia Punto Service Mg",
    "wof:placetype":"venue"
},
  "geometry": {"coordinates":[7.952234,45.022579],"type":"Point"}
}