{
  "type": "Feature",
  "properties": {
    "iso:country":"IT",
    "sg:address":"22, Via Achille Grandi 23847 Molteno",
    "sg:city":"Molteno",
    "sg:classifiers":[
        {
            "category":"Professional",
            "subcategory":"Engineering",
            "type":"Services"
        }
    ],
    "sg:phone":"+39 39031851036",
    "sg:postcode":"23847",
    "sg:province":"Lecco",
    "sg:tags":[
        "machine",
        "-",
        "mechanical"
    ],
    "wof:name":"O.m.e.c. (s.r.l.)",
    "wof:placetype":"venue"
},
  "geometry": {"coordinates":[9.309472,45.774906],"type":"Point"}
}