{
  "type": "Feature",
  "properties": {
    "addr:full":"2, Via Kennedy 22040 Alzate Brianza Alzate Brianza Como 22040",
    "addr:postcode":"22040;22040",
    "addr:street":"Via Kennedy",
    "iso:country":"IT",
    "sg:address":"2, Via Kennedy 22040 Alzate Brianza",
    "sg:city":"Alzate Brianza",
    "sg:classifiers":[
        {
            "category":"Home & Garden",
            "subcategory":"Home Furnishings",
            "type":"Retail Goods"
        }
    ],
    "sg:phone":"+39 39031630287",
    "sg:postcode":"22040",
    "sg:province":"Como",
    "sg:tags":[
        "household"
    ],
    "wof:name":"Cattaneo Luigi Luigi",
    "wof:placetype":"venue"
},
  "geometry": {"coordinates":[9.123761,45.74173],"type":"Point"}
}