{
  "type": "Feature",
  "properties": {
    "iso:country":"IT",
    "sg:address":"27, Viale Guglielmo Marconi 26020 Spinadesco",
    "sg:city":"Spinadesco",
    "sg:classifiers":[
        {
            "category":"Sports & Exercise",
            "subcategory":"Playing Field",
            "type":"Entertainment"
        }
    ],
    "sg:phone":"+39 0372 491591",
    "sg:postcode":"26020",
    "sg:province":"Cremona",
    "sg:tags":[
        "game"
    ],
    "wof:name":"Italtrade Srl",
    "wof:placetype":"venue"
},
  "geometry": {"coordinates":[9.988399,45.107311],"type":"Point"}
}