{
  "type": "Feature",
  "properties": {
    "iso:country":"IT",
    "sg:address":"10026 Santena",
    "sg:city":"Santena",
    "sg:orig_category":"Servizi Per Imballaggio E Confezionamento",
    "sg:phone":"+39 011 949 2168",
    "sg:postcode":"10026",
    "sg:province":"Torino",
    "wof:name":"Coasco Piccola Soc.coop.r.l.",
    "wof:placetype":"venue"
},
  "geometry": {"coordinates":[7.775879,44.956524],"type":"Point"}
}