{
  "type": "Feature",
  "properties": {
    "addr:full":"20161 Milano Milano Milano 20161",
    "addr:postcode":"20161;20161",
    "iso:country":"IT",
    "sg:address":"20161 Milano",
    "sg:city":"Milano",
    "sg:orig_category":"Motocicli E Motocarri - Commercio E Riparazione",
    "sg:phone":"+39 02 648 0475",
    "sg:postcode":"20161",
    "sg:province":"Milano",
    "sg:website":"http://www.superbikesp.it",
    "wof:name":"Superbike Snc",
    "wof:placetype":"venue"
},
  "geometry": {"coordinates":[9.1708402634,45.523651123],"type":"Point"}
}