{
  "type": "Feature",
  "properties": {
    "iso:country":"IT",
    "sg:address":"Corso Matteotti, 24; S. Terenzo; 19032",
    "sg:classifiers":[
        {
            "category":"Banks & Credit Unions",
            "subcategory":"Bank",
            "type":"Services"
        }
    ],
    "sg:phone":"+39 0187 971001",
    "sg:postcode":"19032",
    "sg:province":"La Spezia",
    "wof:name":"Cassa Di Risparmio Della Spezia",
    "wof:placetype":"venue"
},
  "geometry": {"coordinates":[9.898309,44.08353],"type":"Point"}
}