{
  "type": "Feature",
  "properties": {
    "iso:country":"IT",
    "sg:address":"Strada Della Rezza 20 10020 Andezeno",
    "sg:city":"Andezeno",
    "sg:classifiers":[
        {
            "category":"Manufacturing",
            "subcategory":"Paper Products",
            "type":"Manufacturing & Wholesale Goods"
        }
    ],
    "sg:phone":"+39 011 943 4264",
    "sg:postcode":"10020",
    "sg:province":"Torino",
    "sg:tags":[
        "cardboard",
        "package"
    ],
    "wof:name":"Tubificio S. Anna Srl",
    "wof:placetype":"venue"
},
  "geometry": {"coordinates":[7.852681,45.032291],"type":"Point"}
}