{
  "type": "Feature",
  "properties": {
    "iso:country":"IT",
    "sg:address":"5, Via Commercio 30175 Venezia",
    "sg:city":"Venezia",
    "sg:classifiers":[
        {
            "category":"Manufacturing",
            "subcategory":"Metals",
            "type":"Manufacturing & Wholesale Goods"
        }
    ],
    "sg:phone":"+39 041 258 3711",
    "sg:postcode":"30175",
    "sg:province":"Venezia",
    "sg:tags":[
        "metallurgy",
        "metalworking"
    ],
    "wof:name":"Afv Acciaierie Beltrame S.p.a.",
    "wof:placetype":"venue"
},
  "geometry": {"coordinates":[12.3388051987,45.4362411499],"type":"Point"}
}