{
  "type": "Feature",
  "properties": {
    "iso:country":"IT",
    "sg:address":"Via Cellini 27 59013 Montemurlo",
    "sg:city":"Montemurlo",
    "sg:classifiers":[
        {
            "category":"Shopping",
            "subcategory":"Clothing, Apparel, & Fashions",
            "type":"Retail Goods"
        }
    ],
    "sg:phone":"+39 0574 652727",
    "sg:postcode":"59013",
    "sg:province":"Prato",
    "sg:tags":[
        "clothing",
        "fabric"
    ],
    "wof:name":"Lanificio Montecarlo Srl",
    "wof:placetype":"venue"
},
  "geometry": {"coordinates":[11.059583,43.912415],"type":"Point"}
}