{
  "type": "Feature",
  "properties": {
    "addr:full":"84016 Pagani Pagani Salerno 84016",
    "addr:postcode":"84016;84016",
    "iso:country":"IT",
    "sg:address":"84016 Pagani",
    "sg:city":"Pagani",
    "sg:orig_category":"Prodotti Chimici Secondari. Tempo Libero - Articoli E Forniture. Servizi Per Lo Sport E Il Tempo Libero. Servizi Per Aziende, Manifestazioni E Supporto Agli Scambi Commerciali",
    "sg:phone":"+39 081 917015",
    "sg:postcode":"84016",
    "sg:province":"Salerno",
    "wof:name":"Caso Sabato",
    "wof:placetype":"venue"
},
  "geometry": {"coordinates":[14.6160097122,40.7445869446],"type":"Point"}
}