{
  "type": "Feature",
  "properties": {
    "iso:country":"IT",
    "sg:address":"12100 Cuneo",
    "sg:city":"Cuneo",
    "sg:orig_category":"Legno E Semilavorati",
    "sg:phone":"+39 0171 412721",
    "sg:postcode":"12100",
    "sg:province":"Cuneo",
    "wof:name":"Market Compensati Spa",
    "wof:placetype":"venue"
},
  "geometry": {"coordinates":[7.560297,44.423393],"type":"Point"}
}