{
  "type": "Feature",
  "properties": {
    "iso:country":"IT",
    "sg:address":"53, Via Sottorive 33048 San Giovanni Al Natisone",
    "sg:city":"San Giovanni al Natisone",
    "sg:classifiers":[
        {
            "category":"Home & Garden",
            "subcategory":"Home Furnishings",
            "type":"Retail Goods"
        }
    ],
    "sg:phone":"+39 0432 757466",
    "sg:postcode":"33048",
    "sg:province":"Udine",
    "sg:tags":[
        "household"
    ],
    "wof:name":"Eltor S.r.l.",
    "wof:placetype":"venue"
},
  "geometry": {"coordinates":[13.230724,46.064941],"type":"Point"}
}