{
  "type": "Feature",
  "properties": {
    "addr:full":"6, Via Piave 16145 Genova Genova Genova 16145",
    "addr:postcode":"16145;16145",
    "addr:street":"Via Piave",
    "iso:country":"IT",
    "sg:address":"6, Via Piave 16145 Genova",
    "sg:city":"Genova",
    "sg:classifiers":[
        {
            "category":"Personal",
            "subcategory":"Shoe Repair & Shine",
            "type":"Services"
        }
    ],
    "sg:phone":"+39 39010318520",
    "sg:postcode":"16145",
    "sg:province":"Genova",
    "sg:tags":[
        "leather"
    ],
    "wof:name":"Carrea Alfredo & Figli (s.r.l.)",
    "wof:placetype":"venue"
},
  "geometry": {"coordinates":[8.953898,44.393421],"type":"Point"}
}