{
  "type": "Feature",
  "properties": {
    "addr:full":"37012 Bussolengo Bussolengo Verona 37012",
    "addr:postcode":"37012;37012",
    "iso:country":"IT",
    "sg:address":"37012 Bussolengo",
    "sg:city":"Bussolengo",
    "sg:orig_category":"Macchine, Impianti Ed Attrezzature Per Abbigliamento E Pelletterie",
    "sg:phone":"+39 045 676 6285",
    "sg:postcode":"37012",
    "sg:province":"Verona",
    "wof:name":"Gibimac S.a.s. Di Brazioli Enzo & Giaretta Roberto & C.",
    "wof:placetype":"venue"
},
  "geometry": {"coordinates":[10.854765,45.446205],"type":"Point"}
}