{
  "type": "Feature",
  "properties": {
    "iso:country":"IT",
    "sg:address":"29100 Piacenza",
    "sg:city":"Piacenza",
    "sg:orig_category":"Macchine, Impianti Ed Attrezzature Per Abbigliamento E Pelletterie",
    "sg:phone":"+39 0523 497083",
    "sg:postcode":"29100",
    "sg:province":"Piacenza",
    "wof:name":"Dia Srl Development In Automation",
    "wof:placetype":"venue"
},
  "geometry": {"coordinates":[8.705935,44.923347],"type":"Point"}
}