{
  "type": "Feature",
  "properties": {
    "iso:country":"IT",
    "sg:address":"91025 Marsala",
    "sg:city":"Marsala",
    "sg:orig_category":"Articoli Da Regalo. Forniture Per Attivita' Commerciali Ed Artigianali",
    "sg:phone":"+39 0923 981210",
    "sg:postcode":"91025",
    "sg:province":"Trapani",
    "wof:name":"Commerciale Canale",
    "wof:placetype":"venue"
},
  "geometry": {"coordinates":[12.552751,37.832535],"type":"Point"}
}