{
  "type": "Feature",
  "properties": {
    "iso:country":"IT",
    "sg:address":"120, Via Flavia 34147 Trieste",
    "sg:city":"Trieste",
    "sg:classifiers":[
        {
            "category":"Autos & Motor Vehicles",
            "subcategory":"Automobile Sales",
            "type":"Retail Goods"
        }
    ],
    "sg:phone":"+39 39040281166",
    "sg:postcode":"34147",
    "sg:province":"Trieste",
    "sg:tags":[
        "motor-cars"
    ],
    "wof:name":"Grandi Antonio S.r.l.",
    "wof:placetype":"venue"
},
  "geometry": {"coordinates":[13.8188657761,45.611415863],"type":"Point"}
}