{
  "type": "Feature",
  "properties": {
    "addr:full":"20, Viale Caduti Sul Lavoro 41100 Modena Modena Modena 41100",
    "addr:housenumber":"20",
    "addr:postcode":"41100;41100",
    "addr:street":"Viale Caduti Sul Lavoro",
    "iso:country":"IT",
    "sg:address":"20, Viale Caduti Sul Lavoro 41100 Modena",
    "sg:city":"Modena",
    "sg:classifiers":[
        {
            "category":"Professional",
            "subcategory":"Engineering",
            "type":"Services"
        }
    ],
    "sg:phone":"+39 39059373222",
    "sg:postcode":"41100",
    "sg:province":"Modena",
    "sg:tags":[
        "machine",
        "-",
        "mechanical"
    ],
    "wof:name":"Dec S.r.l.",
    "wof:placetype":"venue"
},
  "geometry": {"coordinates":[10.970031,44.629047],"type":"Point"}
}