{
  "type": "Feature",
  "properties": {
    "addr:full":"4, Viale Dei Mareschi 10051 Avigliana Avigliana Torino 10051",
    "addr:postcode":"10051;10051",
    "addr:street":"Viale Dei Mareschi",
    "iso:country":"IT",
    "sg:address":"4, Viale Dei Mareschi 10051 Avigliana",
    "sg:city":"Avigliana",
    "sg:classifiers":[
        {
            "category":"Manufacturing",
            "subcategory":"Aerospace",
            "type":"Manufacturing & Wholesale Goods"
        }
    ],
    "sg:phone":"+39 011 934 8738",
    "sg:postcode":"10051",
    "sg:province":"Torino",
    "sg:tags":[
        "aeronautic"
    ],
    "wof:name":"Oms Di Saladino Paolo & C. Snc",
    "wof:placetype":"venue"
},
  "geometry": {"coordinates":[7.377176,45.078239],"type":"Point"}
}