{
  "type": "Feature",
  "properties": {
    "addr:full":"19, Via Pontecerretano 50050 Cerreto Guidi Cerreto Guidi Firenze 50050",
    "addr:postcode":"50050;50050",
    "addr:street":"Via Pontecerretano",
    "iso:country":"IT",
    "sg:address":"19, Via Pontecerretano 50050 Cerreto Guidi",
    "sg:city":"Cerreto Guidi",
    "sg:classifiers":[
        {
            "category":"Manufacturing",
            "subcategory":"Rubber & Plastics",
            "type":"Manufacturing & Wholesale Goods"
        }
    ],
    "sg:phone":"+39 0571 508256",
    "sg:postcode":"50050",
    "sg:province":"Firenze",
    "wof:name":"Faraoni Casalinghi (s.n.c.)",
    "wof:placetype":"venue"
},
  "geometry": {"coordinates":[11.256901741,43.7687339783],"type":"Point"}
}