{
  "type": "Feature",
  "properties": {
    "iso:country":"IT",
    "sg:address":"20144 Milano",
    "sg:city":"Milano",
    "sg:orig_category":"Agenzie D'affari E Servizi Commerciali",
    "sg:phone":"+39 02 461834",
    "sg:postcode":"20144",
    "sg:province":"Milano",
    "wof:name":"Marelli Dr. Luigi",
    "wof:placetype":"venue"
},
  "geometry": {"coordinates":[9.162931,45.465042],"type":"Point"}
}