{
  "type": "Feature",
  "properties": {
    "iso:country":"IT",
    "sg:address":"00186 Roma",
    "sg:city":"Roma",
    "sg:classifiers":[
        {
            "category":"Professional",
            "subcategory":"Computer Services",
            "type":"Services"
        }
    ],
    "sg:phone":"+39 06 686 5809",
    "sg:postcode":"00186",
    "sg:province":"Roma",
    "sg:tags":[
        "decorative",
        "furniture",
        "object",
        "furnishings",
        "furnishing"
    ],
    "wof:name":"Arredamento Liturgico Srl",
    "wof:placetype":"venue"
},
  "geometry": {"coordinates":[12.4773492813,41.8968544006],"type":"Point"}
}