{
  "type": "Feature",
  "properties": {
    "iso:country":"IT",
    "sg:address":"20093 Cologno Monzese",
    "sg:city":"Cologno Monzese",
    "sg:orig_category":"Mosaici Artistici",
    "sg:phone":"+39 02 253 2564",
    "sg:postcode":"20093",
    "sg:province":"Milano",
    "wof:name":"Mosaici Bonazza & C.",
    "wof:placetype":"venue"
},
  "geometry": {"coordinates":[9.2781057358,45.5394363403],"type":"Point"}
}