{
  "type": "Feature",
  "properties": {
    "iso:country":"IT",
    "sg:address":"22066 Mariano Comense",
    "sg:city":"Mariano Comense",
    "sg:orig_category":"Servizi E Lavori Per Ecologia E Smaltimento Rifiuti. Forniture Industriali Per Prevenzione, Controllo E Sicurezza",
    "sg:phone":"+39 031 749101",
    "sg:postcode":"22066",
    "sg:province":"Como",
    "wof:name":"Insonorizzazioni Industriali Baldo Altemio & C.",
    "wof:placetype":"venue"
},
  "geometry": {"coordinates":[9.183165,45.681152],"type":"Point"}
}