{
  "type": "Feature",
  "properties": {
    "addr:full":"60122 Ancona Ancona Ancona 60122",
    "addr:postcode":"60122;60122",
    "iso:country":"IT",
    "sg:address":"60122 Ancona",
    "sg:city":"Ancona",
    "sg:orig_category":"Servizi Per Aziende, Manifestazioni E Supporto Agli Scambi Commerciali",
    "sg:phone":"+39 071 204067",
    "sg:postcode":"60122",
    "sg:province":"Ancona",
    "wof:name":"Paduano Donatella",
    "wof:placetype":"venue"
},
  "geometry": {"coordinates":[13.508214,43.616135],"type":"Point"}
}