{
  "type": "Feature",
  "properties": {
    "iso:country":"IT",
    "sg:address":"98121 Messina",
    "sg:city":"Messina",
    "sg:orig_category":"Impiantistica E Prodotti Tecnologici Per Edilizia. Telecomunicazioni E Telefonia, Impianti, Apparecchi E Servizi",
    "sg:phone":"+39 090 344044",
    "sg:postcode":"98121",
    "sg:province":"Messina",
    "sg:website":"http://www.larredaufficio.it",
    "wof:name":"L'arredaufficio Srl",
    "wof:placetype":"venue"
},
  "geometry": {"coordinates":[15.553056,38.205303],"type":"Point"}
}