{
  "type": "Feature",
  "properties": {
    "iso:country":"IT",
    "sg:address":"20011 Corbetta",
    "sg:city":"Corbetta",
    "sg:orig_category":"Filati E Materie Prime Tessili",
    "sg:phone":"+39 02 977 1970",
    "sg:postcode":"20011",
    "sg:province":"Milano",
    "wof:name":"Lo Scampolo Di De Vecchi Eleonora",
    "wof:placetype":"venue"
},
  "geometry": {"coordinates":[9.0050010681,45.4852828979],"type":"Point"}
}