{
  "type": "Feature",
  "properties": {
    "iso:country":"IT",
    "sg:address":"35023 Bagnoli Di Sopra",
    "sg:city":"Bagnoli di Sopra",
    "sg:orig_category":"Macchine, Impianti Ed Attrezzature Industria Chimica. Vetro: Prodotti E Lavorazioni",
    "sg:phone":"+39 049 953 5066",
    "sg:postcode":"35023",
    "sg:province":"Padova",
    "wof:name":"Avidue Vetro S.r.l.",
    "wof:placetype":"venue"
},
  "geometry": {"coordinates":[11.889931,45.201099],"type":"Point"}
}