{
  "type": "Feature",
  "properties": {
    "iso:country":"IT",
    "sg:address":"71016 San Severo",
    "sg:city":"San Severo",
    "sg:classifiers":[
        {
            "category":"Building & Trades",
            "subcategory":"Locksmith",
            "type":"Services"
        }
    ],
    "sg:phone":"+39 338 817 8140",
    "sg:postcode":"71016",
    "sg:province":"Foggia",
    "sg:tags":[
        "livestock",
        "civil",
        "industry",
        "work",
        "breeding",
        "works",
        "agriculture"
    ],
    "wof:name":"Vivai Piante Padre Pio",
    "wof:placetype":"venue"
},
  "geometry": {"coordinates":[15.430239,41.641582],"type":"Point"}
}