{
  "type": "Feature",
  "properties": {
    "iso:country":"IT",
    "sg:address":"53035 Monteriggioni",
    "sg:city":"Monteriggioni",
    "sg:orig_category":"Servizi E Lavori Per Agricoltura E Zootecnia. Servizi E Lavori Industria Chimica. Servizi Ausiliari Di Analisi, Controllo E Ricerca",
    "sg:phone":"+39 0577 588539",
    "sg:postcode":"53035",
    "sg:province":"Siena",
    "wof:name":"Philogen Srl",
    "wof:placetype":"venue"
},
  "geometry": {"coordinates":[11.218378,43.363014],"type":"Point"}
}