{
  "type": "Feature",
  "properties": {
    "iso:country":"IT",
    "sg:address":"20121 Milano",
    "sg:city":"Milano",
    "sg:orig_category":"Servizi Per Lo Sport E Il Tempo Libero. Servizi Al Turismo",
    "sg:phone":"+39 02 8646 2927",
    "sg:postcode":"20121",
    "sg:province":"Milano",
    "wof:name":"Palestra Armonia",
    "wof:placetype":"venue"
},
  "geometry": {"coordinates":[9.184939,45.468773],"type":"Point"}
}