{
  "type": "Feature",
  "properties": {
    "iso:country":"IT",
    "sg:address":"20024 Garbagnate Milanese",
    "sg:city":"Garbagnate Milanese",
    "sg:orig_category":"Pubblica Amministrazione",
    "sg:phone":"+39 02 9906 9683",
    "sg:postcode":"20024",
    "sg:province":"Milano",
    "wof:name":"Comando Stazione Forestale",
    "wof:placetype":"venue"
},
  "geometry": {"coordinates":[9.0783748627,45.5862541199],"type":"Point"}
}