{
  "type": "Feature",
  "properties": {
    "iso:country":"IT",
    "sg:address":"Zona Industriale 73020 Castrignano De' Greci",
    "sg:classifiers":[
        {
            "category":"Shopping",
            "subcategory":"Crafts & Fabrics",
            "type":"Retail Goods"
        }
    ],
    "sg:phone":"+39 0836 589414",
    "sg:postcode":"73020",
    "sg:province":"Lecce",
    "sg:tags":[
        "decorative"
    ],
    "wof:name":"Eurotex S.r.l.",
    "wof:placetype":"venue"
},
  "geometry": {"coordinates":[18.174015,40.353291],"type":"Point"}
}