{
  "type": "Feature",
  "properties": {
    "iso:country":"IT",
    "sg:address":"81100 Caserta",
    "sg:city":"Caserta",
    "sg:classifiers":[
        {
            "category":"Wholesale",
            "subcategory":"Home Furnishings",
            "type":"Manufacturing & Wholesale Goods"
        }
    ],
    "sg:phone":"+39 0823 371726",
    "sg:postcode":"81100",
    "sg:province":"Caserta",
    "sg:tags":[
        "decorative",
        "objects",
        "furnishings",
        "gift"
    ],
    "wof:name":"Farina Nicola",
    "wof:placetype":"venue"
},
  "geometry": {"coordinates":[14.3663892746,41.0966682434],"type":"Point"}
}