{
  "type": "Feature",
  "properties": {
    "addr:full":"63100 Ascoli Piceno Ascoli Piceno Ascoli Piceno 63100",
    "addr:postcode":"63100;63100",
    "iso:country":"IT",
    "sg:address":"63100 Ascoli Piceno",
    "sg:city":"Ascoli Piceno",
    "sg:orig_category":"Arredamento Uffici",
    "sg:phone":"+39 0736 344820",
    "sg:postcode":"63100",
    "sg:province":"Ascoli Piceno",
    "wof:name":"Cesari Srl",
    "wof:placetype":"venue"
},
  "geometry": {"coordinates":[13.715178,42.828609],"type":"Point"}
}