{
  "type": "Feature",
  "properties": {
    "addr:full":"56017 San Giuliano Terme San Giuliano Terme Pisa 56017",
    "addr:postcode":"56017;56017",
    "iso:country":"IT",
    "sg:address":"56017 San Giuliano Terme",
    "sg:city":"San Giuliano Terme",
    "sg:orig_category":"Apparecchiature E Sistemi Per Magazzinaggio E Movimentazione",
    "sg:phone":"+39 050 811371",
    "sg:postcode":"56017",
    "sg:province":"Pisa",
    "wof:name":"Effebi Snc Di Ferrati",
    "wof:placetype":"venue"
},
  "geometry": {"coordinates":[10.372716,43.756798],"type":"Point"}
}