{
  "type": "Feature",
  "properties": {
    "addr:full":"50041 Calenzano Calenzano Firenze 50041",
    "addr:postcode":"50041;50041",
    "iso:country":"IT",
    "sg:address":"50041 Calenzano",
    "sg:city":"Calenzano",
    "sg:orig_category":"Informatica - Consulenza E Software",
    "sg:phone":"+39 055 883 9891",
    "sg:postcode":"50041",
    "sg:province":"Firenze",
    "sg:website":"http://www.isgtoscana.it",
    "wof:name":"I.s.g. Toscana",
    "wof:placetype":"venue"
},
  "geometry": {"coordinates":[11.175839,43.846958],"type":"Point"}
}