{
  "type": "Feature",
  "properties": {
    "addr:full":"41, Via Fermi Enrico 37136 Verona Verona Verona 37136",
    "addr:postcode":"37136;37136",
    "addr:street":"Via Fermi Enrico",
    "iso:country":"IT",
    "sg:address":"41, Via Fermi Enrico 37136 Verona",
    "sg:city":"Verona",
    "sg:classifiers":[
        {
            "category":"Autos & Motor Vehicles",
            "subcategory":"Automobile Sales",
            "type":"Retail Goods"
        }
    ],
    "sg:phone":"+39 045 862 0500",
    "sg:postcode":"37136",
    "sg:province":"Verona",
    "sg:tags":[
        "motor-cars"
    ],
    "wof:name":"Rodegher Motors (s.r.l.)",
    "wof:placetype":"venue"
},
  "geometry": {"coordinates":[10.9590511322,45.4072341919],"type":"Point"}
}