{
  "type": "Feature",
  "properties": {
    "iso:country":"IT",
    "sg:address":"Via Nazionale 73; Novara Di Sicilia; 98058",
    "sg:city":"Novara di Sicilia",
    "sg:classifiers":[
        {
            "category":"Banks & Credit Unions",
            "subcategory":"Bank",
            "type":"Services"
        }
    ],
    "sg:phone":"+39 0941 650021",
    "sg:postcode":"98058",
    "sg:province":"Messina",
    "wof:name":"Banco Di Sicilia Spa",
    "wof:placetype":"venue"
},
  "geometry": {"coordinates":[15.134131,38.015205],"type":"Point"}
}