{
  "type": "Feature",
  "properties": {
    "addr:full":"Via Pontebbana 28 33080 Fiume Veneto Fiume Veneto Pordenone 33080",
    "addr:housenumber":"28",
    "addr:postcode":"33080;33080",
    "addr:street":"Via Pontebbana",
    "iso:country":"IT",
    "sg:address":"Via Pontebbana 28 33080 Fiume Veneto",
    "sg:city":"Fiume Veneto",
    "sg:orig_category":"Development Machines And Systems For Printing Plates",
    "sg:phone":"+39 0434 950111",
    "sg:postcode":"33080",
    "sg:province":"Pordenone",
    "wof:name":"San Marco Imaging Srl",
    "wof:placetype":"venue"
},
  "geometry": {"coordinates":[12.714156,45.933537],"type":"Point"}
}