{
  "type": "Feature",
  "properties": {
    "iso:country":"IT",
    "sg:address":"22012 Cernobbio",
    "sg:city":"Cernobbio",
    "sg:orig_category":"Scuole E Servizi Scolastici. Servizi Ausiliari Dei Mezzi Di Trasporto. Ricerca, Selezione E Formazione Del Personale",
    "sg:phone":"+39 031 511170",
    "sg:postcode":"22012",
    "sg:province":"Como",
    "wof:name":"Autoscuola D'este",
    "wof:placetype":"venue"
},
  "geometry": {"coordinates":[9.070904,45.838799],"type":"Point"}
}