{
  "type": "Feature",
  "properties": {
    "addr:full":"50126 Firenze Firenze Firenze 50126",
    "addr:postcode":"50126;50126",
    "iso:country":"IT",
    "sg:address":"50126 Firenze",
    "sg:city":"Firenze",
    "sg:classifiers":[
        {
            "category":"Manufacturing",
            "subcategory":"Tools & Machinery",
            "type":"Manufacturing & Wholesale Goods"
        }
    ],
    "sg:phone":"+39 055 680753",
    "sg:postcode":"50126",
    "sg:province":"Firenze",
    "sg:tags":[
        "machining",
        "mechanical"
    ],
    "wof:name":"O.c.e.m. Srl",
    "wof:placetype":"venue"
},
  "geometry": {"coordinates":[11.29434,43.759705],"type":"Point"}
}