{
  "type": "Feature",
  "properties": {
    "addr:full":"51016 Montecatini Terme Pistoia 51016",
    "addr:postcode":"51016;51016",
    "iso:country":"IT",
    "sg:address":"51016 Montecatini Terme",
    "sg:orig_category":"Servizi E Lavori Per Arredamento E Industria Del Legno. Servizi E Lavori Per Edilizia E Lavori Pubblici. Arte Ed Artigianato Artistico",
    "sg:phone":"+39 0572 773428",
    "sg:postcode":"51016",
    "sg:province":"Pistoia",
    "sg:website":"http://www.rindoriedipinti.it",
    "wof:name":"Rindori & Dipinti",
    "wof:placetype":"venue"
},
  "geometry": {"coordinates":[10.767292,43.885811],"type":"Point"}
}