{
  "type": "Feature",
  "properties": {
    "iso:country":"IT",
    "sg:address":"20144 Milano",
    "sg:city":"Milano",
    "sg:classifiers":[
        {
            "category":"Health Services",
            "subcategory":"Health Practitioner",
            "type":"Services"
        }
    ],
    "sg:phone":"+39 02 4800 6128",
    "sg:postcode":"20144",
    "sg:province":"Milano",
    "sg:tags":[
        "medici"
    ],
    "wof:name":"Borella Elena",
    "wof:placetype":"venue"
},
  "geometry": {"coordinates":[9.160213,45.46072],"type":"Point"}
}