{
  "type": "Feature",
  "properties": {
    "iso:country":"IT",
    "sg:address":"51039 Quarrata",
    "sg:city":"Quarrata",
    "sg:orig_category":"Rifiuti Industriali E Speciali Smaltimento E Trattamento - Servizio",
    "sg:phone":"+39 0573 545136",
    "sg:postcode":"51039",
    "sg:province":"Pistoia",
    "wof:name":"M.i.r. Srl",
    "wof:placetype":"venue"
},
  "geometry": {"coordinates":[11.000167,43.884556],"type":"Point"}
}