{
  "type": "Feature",
  "properties": {
    "iso:country":"IT",
    "sg:address":"00146 Roma",
    "sg:city":"Roma",
    "sg:orig_category":"Prodotti Alimentari",
    "sg:phone":"+39 06 556 5760",
    "sg:postcode":"00146",
    "sg:province":"Roma",
    "wof:name":"Terracina Noemi",
    "wof:placetype":"venue"
},
  "geometry": {"coordinates":[12.4710197449,41.8631134033],"type":"Point"}
}