{
  "type": "Feature",
  "properties": {
    "iso:country":"IT",
    "sg:address":"51100 Pistoia",
    "sg:city":"Pistoia",
    "sg:orig_category":"Servizi Al Turismo. Trasporto Pubblico E Privato. Acqua, Luce, Gas E Societa' Di Esercizio Pubblico",
    "sg:phone":"+39 0573 3630",
    "sg:postcode":"51100",
    "sg:province":"Pistoia",
    "wof:name":"Copit Spa",
    "wof:placetype":"venue"
},
  "geometry": {"coordinates":[10.91356,43.940193],"type":"Point"}
}