{
  "type": "Feature",
  "properties": {
    "addr:full":"Piazzale Europa; Tolentino; 62029 Tolentino Macerata 62029",
    "addr:postcode":"62029;62029",
    "addr:street":"Piazzale Europa Tolentino",
    "iso:country":"IT",
    "sg:address":"Piazzale Europa; Tolentino; 62029",
    "sg:city":"Tolentino",
    "sg:classifiers":[
        {
            "category":"Banks & Credit Unions",
            "subcategory":"Bank",
            "type":"Services"
        }
    ],
    "sg:phone":"+39 0733 971741",
    "sg:postcode":"62029",
    "sg:province":"Macerata",
    "wof:name":"Banca Delle Marche Spa",
    "wof:placetype":"venue"
},
  "geometry": {"coordinates":[13.285743,43.212238],"type":"Point"}
}