{
  "type": "Feature",
  "properties": {
    "addr:full":"16157 Savignone Genova 16157",
    "addr:postcode":"16157;16157",
    "iso:country":"IT",
    "sg:address":"16157 Savignone",
    "sg:orig_category":"Arredo Bagno Ed Idrosanitari. Idrosanitari E Accessori",
    "sg:phone":"+39 010 936 0195",
    "sg:postcode":"16157",
    "sg:province":"Genova",
    "wof:name":"Fabbricazioni Idrauliche Spa",
    "wof:placetype":"venue"
},
  "geometry": {"coordinates":[8.927384,44.538792],"type":"Point"}
}