{
  "type": "Feature",
  "properties": {
    "addr:full":"25036 Palazzolo Sull'oglio Brescia 25036",
    "addr:postcode":"25036;25036",
    "iso:country":"IT",
    "sg:address":"25036 Palazzolo Sull'oglio",
    "sg:orig_category":"Apparecchiature E Sistemi Per Imballaggio E Confezionamento",
    "sg:phone":"+39 030 730 0611",
    "sg:postcode":"25036",
    "sg:province":"Brescia",
    "wof:name":"Ca.ve.co. Srl",
    "wof:placetype":"venue"
},
  "geometry": {"coordinates":[9.88133,45.58688],"type":"Point"}
}