{
  "type": "Feature",
  "properties": {
    "addr:full":"05100 Terni Terni Terni 05100",
    "addr:postcode":"05100;05100",
    "iso:country":"IT",
    "sg:address":"05100 Terni",
    "sg:city":"Terni",
    "sg:orig_category":"Macchine Utensili E Impianti",
    "sg:phone":"+39 0744 400658",
    "sg:postcode":"05100",
    "sg:province":"Terni",
    "wof:name":"Alfa Rappresentanze Snc",
    "wof:placetype":"venue"
},
  "geometry": {"coordinates":[12.650428,42.561016],"type":"Point"}
}