{
  "type": "Feature",
  "properties": {
    "addr:full":"270, Corso Regina Margherita 10144 Torino Torino Torino 10144",
    "addr:postcode":"10144;10144",
    "addr:street":"Corso Regina Margherita",
    "iso:country":"IT",
    "sg:address":"270, Corso Regina Margherita 10144 Torino",
    "sg:city":"Torino",
    "sg:classifiers":[
        {
            "category":"Autos & Motor Vehicles",
            "subcategory":"Automobile Sales",
            "type":"Retail Goods"
        }
    ],
    "sg:phone":"+39 011 437 5151",
    "sg:postcode":"10144",
    "sg:province":"Torino",
    "sg:tags":[
        "motor-cars"
    ],
    "wof:name":"Lancar (s.p.a.)",
    "wof:placetype":"venue"
},
  "geometry": {"coordinates":[7.6592788696,45.0849761963],"type":"Point"}
}