{
  "type": "Feature",
  "properties": {
    "iso:country":"IT",
    "sg:address":"50129 Firenze",
    "sg:city":"Firenze",
    "sg:orig_category":"Salotti, Poltrone, Sedie E Tavoli",
    "sg:phone":"+39 055 576652",
    "sg:postcode":"50129",
    "sg:province":"Firenze",
    "sg:website":"http://www.salotti2elle.it",
    "wof:name":"Salotti 2 Elle Di Labiri Leo",
    "wof:placetype":"venue"
},
  "geometry": {"coordinates":[11.265633,43.785248],"type":"Point"}
}