{
  "type": "Feature",
  "properties": {
    "iso:country":"IT",
    "sg:address":"59100 Prato",
    "sg:city":"Prato",
    "sg:orig_category":"Filati E Materie Prime Tessili",
    "sg:phone":"+39 0574 634621",
    "sg:postcode":"59100",
    "sg:province":"Prato",
    "wof:name":"Thessa Spa",
    "wof:placetype":"venue"
},
  "geometry": {"coordinates":[11.0938081741,43.8780326843],"type":"Point"}
}