{
  "type": "Feature",
  "properties": {
    "addr:full":"40050 Argelato Argelato Bologna 40050",
    "addr:postcode":"40050;40050",
    "iso:country":"IT",
    "sg:address":"40050 Argelato",
    "sg:city":"Argelato",
    "sg:orig_category":"Materiali Semilavorati Metallici",
    "sg:phone":"+39 051 664 6460",
    "sg:postcode":"40050",
    "sg:province":"Bologna",
    "wof:name":"Tubitalia Srl",
    "wof:placetype":"venue"
},
  "geometry": {"coordinates":[11.367518,44.594555],"type":"Point"}
}