{
  "type": "Feature",
  "properties": {
    "iso:country":"IT",
    "sg:address":"22, Via Filippo Degli Ugoni 50126 Firenze",
    "sg:city":"Firenze",
    "sg:classifiers":[
        {
            "category":"Shopping",
            "subcategory":"Gifts & Souvenirs",
            "type":"Retail Goods"
        }
    ],
    "sg:phone":"+39 39055688231",
    "sg:postcode":"50126",
    "sg:province":"Firenze",
    "wof:name":"Ditta Chiarugi & C. Srl",
    "wof:placetype":"venue"
},
  "geometry": {"coordinates":[11.289068,43.760864],"type":"Point"}
}