{
  "type": "Feature",
  "properties": {
    "addr:full":"Via Chioda 123a 37136 Verona Verona Verona 37136",
    "addr:housenumber":"123a",
    "addr:postcode":"37136;37136",
    "addr:street":"Via Chioda",
    "iso:country":"IT",
    "sg:address":"Via Chioda 123a 37136 Verona",
    "sg:city":"Verona",
    "sg:classifiers":[
        {
            "category":"Professional",
            "subcategory":"Advertising",
            "type":"Services"
        }
    ],
    "sg:phone":"+39 045 862 1132",
    "sg:postcode":"37136",
    "sg:province":"Verona",
    "sg:tags":[
        "lettering",
        "medium"
    ],
    "wof:name":"Europlanning Srl",
    "wof:placetype":"venue"
},
  "geometry": {"coordinates":[10.954526,45.407818],"type":"Point"}
}