{
  "type": "Feature",
  "properties": {
    "addr:full":"99, Via Como 20036 Meda Meda Milano 20036",
    "addr:postcode":"20036;20036",
    "addr:street":"Via Como",
    "iso:country":"IT",
    "sg:address":"99, Via Como 20036 Meda",
    "sg:city":"Meda",
    "sg:classifiers":[
        {
            "category":"Home & Garden",
            "subcategory":"Home Furnishings",
            "type":"Retail Goods"
        }
    ],
    "sg:phone":"+39 39036271701",
    "sg:postcode":"20036",
    "sg:province":"Milano",
    "sg:tags":[
        "household"
    ],
    "wof:name":"Pigoli Salotti Srl",
    "wof:placetype":"venue"
},
  "geometry": {"coordinates":[9.163579,45.672691],"type":"Point"}
}