{
  "type": "Feature",
  "properties": {
    "addr:full":"52026 Pian Di Sco Pian di Sco Arezzo 52026",
    "addr:postcode":"52026;52026",
    "iso:country":"IT",
    "sg:address":"52026 Pian Di Sco",
    "sg:city":"Pian di Sco",
    "sg:orig_category":"Metalli E Leghe. Gioielleria, Oreficeria E Argenteria",
    "sg:phone":"+39 055 959552",
    "sg:postcode":"52026",
    "sg:province":"Arezzo",
    "wof:name":"Effedue Di Lazzerini Luigi Lavorazione Preziosi",
    "wof:placetype":"venue"
},
  "geometry": {"coordinates":[11.5532255173,43.6571731567],"type":"Point"}
}