{
  "type": "Feature",
  "properties": {
    "addr:full":"42046 Reggiolo Reggio Nell'Emilia 42046",
    "addr:postcode":"42046;42046",
    "iso:country":"IT",
    "sg:address":"42046 Reggiolo",
    "sg:orig_category":"Forniture Alle Strutture Ricettive. Macchine E Impianti Per Attivita' Commerciali Ed Artigianali",
    "sg:phone":"+39 0522 973002",
    "sg:postcode":"42046",
    "sg:province":"Reggio Nell'Emilia",
    "wof:name":"Camurri Brevetti (s.r.l.)",
    "wof:placetype":"venue"
},
  "geometry": {"coordinates":[10.617061615,44.6849060059],"type":"Point"}
}