{
  "type": "Feature",
  "properties": {
    "iso:country":"IT",
    "sg:address":"80026 Casoria",
    "sg:city":"Casoria",
    "sg:orig_category":"Lampadari - Vendita Al Dettaglio",
    "sg:phone":"+39 081 758 7624",
    "sg:postcode":"80026",
    "sg:province":"Napoli",
    "sg:website":"http://www.idn.it/aziende/ciccariello",
    "wof:name":"A. Ciccariello & C. Sas Di A. Kuhn",
    "wof:placetype":"venue"
},
  "geometry": {"coordinates":[14.284781,40.907173],"type":"Point"}
}