{
  "type": "Feature",
  "properties": {
    "iso:country":"IT",
    "sg:address":"Sda Provinciale 87 70027 Palo Del Colle",
    "sg:city":"Palo del Colle",
    "sg:classifiers":[
        {
            "category":"Manufacturing",
            "subcategory":"Glass & Minerals",
            "type":"Manufacturing & Wholesale Goods"
        }
    ],
    "sg:phone":"+39 080 626729",
    "sg:postcode":"70027",
    "sg:province":"Bari",
    "sg:tags":[
        "finishing"
    ],
    "wof:name":"Vetreria Cristalflorio Di Florio Ni",
    "wof:placetype":"venue"
},
  "geometry": {"coordinates":[16.869291,41.126053],"type":"Point"}
}