{
  "type": "Feature",
  "properties": {
    "iso:country":"IT",
    "sg:address":"81025 Marcianise",
    "sg:city":"Marcianise",
    "sg:orig_category":"Servizi E Lavori Per Edilizia E Lavori Pubblici",
    "sg:phone":"+39 0823 832552",
    "sg:postcode":"81025",
    "sg:province":"Caserta",
    "wof:name":"Liotto Giuseppe",
    "wof:placetype":"venue"
},
  "geometry": {"coordinates":[14.290171,41.038284],"type":"Point"}
}