{
  "type": "Feature",
  "properties": {
    "iso:country":"IT",
    "sg:address":"00040 Ardea",
    "sg:city":"Ardea",
    "sg:orig_category":"Cartotecnica E Servizi. Prodotti E Manufatti In Materie Plastiche. Articoli Per Imballaggio E Confezionamento",
    "sg:phone":"+39 06 914 5795",
    "sg:postcode":"00040",
    "sg:province":"Roma",
    "wof:name":"Silcep (s.r.l.)",
    "wof:placetype":"venue"
},
  "geometry": {"coordinates":[12.538832,41.669987],"type":"Point"}
}