{
  "type": "Feature",
  "properties": {
    "addr:full":"33017 Tarcento Tarcento Udine 33017",
    "addr:postcode":"33017;33017",
    "iso:country":"IT",
    "sg:address":"33017 Tarcento",
    "sg:city":"Tarcento",
    "sg:orig_category":"Legna Da Ardere",
    "sg:phone":"+39 0432 784282",
    "sg:postcode":"33017",
    "sg:province":"Udine",
    "wof:name":"Allwood Srl",
    "wof:placetype":"venue"
},
  "geometry": {"coordinates":[13.21294,46.212269],"type":"Point"}
}