{
  "type": "Feature",
  "properties": {
    "iso:country":"IT",
    "sg:address":"39, Via Manzoni Alessandro 20020 Lainate",
    "sg:city":"Lainate",
    "sg:classifiers":[
        {
            "category":"Manufacturing",
            "subcategory":"Metals",
            "type":"Manufacturing & Wholesale Goods"
        }
    ],
    "sg:phone":"+39 39029374231",
    "sg:postcode":"20020",
    "sg:province":"Milano",
    "sg:tags":[
        "metallurgy",
        "metalworking"
    ],
    "wof:name":"Trafilerie Di Lainate (s.p.a.)",
    "wof:placetype":"venue"
},
  "geometry": {"coordinates":[9.0749368668,45.5505027771],"type":"Point"}
}