{
  "type": "Feature",
  "properties": {
    "addr:full":"28041 Arona Arona Novara 28041",
    "addr:postcode":"28041;28041",
    "iso:country":"IT",
    "sg:address":"28041 Arona",
    "sg:city":"Arona",
    "sg:orig_category":"Servizi Al Turismo. Trasporto Pubblico E Privato",
    "sg:phone":"+39 0322 242352",
    "sg:postcode":"28041",
    "sg:province":"Novara",
    "wof:name":"Navigazione Lago Maggiore",
    "wof:placetype":"venue"
},
  "geometry": {"coordinates":[8.560925,45.758987],"type":"Point"}
}