{
  "type": "Feature",
  "properties": {
    "iso:country":"IT",
    "sg:address":"20, Via Artigianale 25010 Montirone",
    "sg:city":"Montirone",
    "sg:classifiers":[
        {
            "category":"Professional",
            "subcategory":"Engineering",
            "type":"Services"
        }
    ],
    "sg:phone":"+39 39030267213",
    "sg:postcode":"25010",
    "sg:province":"Brescia",
    "sg:tags":[
        "machine",
        "-",
        "mechanical"
    ],
    "wof:name":"Nuova Marc Tex (s.p.a.)",
    "wof:placetype":"venue"
},
  "geometry": {"coordinates":[10.215894,45.450497],"type":"Point"}
}