{
  "type": "Feature",
  "properties": {
    "iso:country":"IT",
    "sg:address":"40133 Bologna",
    "sg:city":"Bologna",
    "sg:orig_category":"Serramenti Ed Infissi",
    "sg:phone":"+39 051 381870",
    "sg:postcode":"40133",
    "sg:province":"Bologna",
    "wof:name":"Artigian Service Di Tomaselli G.",
    "wof:placetype":"venue"
},
  "geometry": {"coordinates":[11.31211,44.521149],"type":"Point"}
}