{
  "type": "Feature",
  "properties": {
    "iso:country":"IT",
    "sg:address":"Via S. Francesco D'assisi 12; Romano Di Lombardia; 24058",
    "sg:city":"Romano di Lombardia",
    "sg:classifiers":[
        {
            "category":"Banks & Credit Unions",
            "subcategory":"Bank",
            "type":"Services"
        }
    ],
    "sg:phone":"+39 036 390 3318",
    "sg:postcode":"24058",
    "sg:province":"Bergamo",
    "wof:name":"Istituto Bancario, San Paolo Di Torino Spa",
    "wof:placetype":"venue"
},
  "geometry": {"coordinates":[9.751833,45.519283],"type":"Point"}
}