{
  "type": "Feature",
  "properties": {
    "addr:full":"41100 Modena Modena Modena 41100",
    "addr:postcode":"41100;41100",
    "iso:country":"IT",
    "sg:address":"41100 Modena",
    "sg:city":"Modena",
    "sg:orig_category":"Motori Ed Organi Di Trasmissione. Ricambi E Componenti Dei Mezzi Di Trasporto",
    "sg:phone":"+39 059 361318",
    "sg:postcode":"41100",
    "sg:province":"Modena",
    "wof:name":"Midas",
    "wof:placetype":"venue"
},
  "geometry": {"coordinates":[10.9394702911,44.6324577332],"type":"Point"}
}