{
  "type": "Feature",
  "properties": {
    "iso:country":"IT",
    "sg:address":"56021 Cascina",
    "sg:city":"Cascina",
    "sg:orig_category":"Arredamenti E Mobili Professionali. Arredi Ed Attrezzature Per Attivita' Commerciali Ed Artigianali",
    "sg:phone":"+39 050 702104",
    "sg:postcode":"56021",
    "sg:province":"Pisa",
    "sg:website":"http://www.pentarredo.it",
    "wof:name":"Pentarredo Di Ceccotti G. Francesco & C.",
    "wof:placetype":"venue"
},
  "geometry": {"coordinates":[10.476599,43.70998],"type":"Point"}
}