{
  "type": "Feature",
  "properties": {
    "iso:country":"IT",
    "sg:address":"5, Via Monte Tomba 36060 Romano D'ezzelino",
    "sg:classifiers":[
        {
            "category":"Food & Beverages",
            "subcategory":"Groceries & Convenience Stores",
            "type":"Retail Goods"
        }
    ],
    "sg:phone":"+39 390 424 8188",
    "sg:postcode":"36060",
    "sg:province":"Vicenza",
    "sg:tags":[
        "product",
        "related"
    ],
    "wof:name":"Marchi S P A",
    "wof:placetype":"venue"
},
  "geometry": {"coordinates":[11.7782697678,45.7605247498],"type":"Point"}
}