{
  "type": "Feature",
  "properties": {
    "iso:country":"IT",
    "sg:address":"16047 Moconesi",
    "sg:city":"Moconesi",
    "sg:orig_category":"Campeggio. Automobili E Mezzi Di Trasporto",
    "sg:phone":"+39 339 432 4300",
    "sg:postcode":"16047",
    "sg:province":"Genova",
    "wof:name":"Qss International Di A. Casagrande",
    "wof:placetype":"venue"
},
  "geometry": {"coordinates":[9.223139,44.430996],"type":"Point"}
}