{
  "type": "Feature",
  "properties": {
    "addr:full":"Via Toscana 13 21013 Gallarate Gallarate Varese 21013",
    "addr:housenumber":"13",
    "addr:postcode":"21013;21013",
    "addr:street":"Via Toscana",
    "iso:country":"IT",
    "sg:address":"Via Toscana 13 21013 Gallarate",
    "sg:city":"Gallarate",
    "sg:classifiers":[
        {
            "category":"Autos & Motor Vehicles",
            "subcategory":"Recreational Vehicle Sales",
            "type":"Retail Goods"
        }
    ],
    "sg:phone":"+39 0331 714511",
    "sg:postcode":"21013",
    "sg:province":"Varese",
    "sg:tags":[
        "machine",
        "tool",
        "accessory"
    ],
    "sg:website":"www.luigibianchi.it",
    "wof:name":"Bianchi Luigi Spa",
    "wof:placetype":"venue"
},
  "geometry": {"coordinates":[8.79388,45.643284],"type":"Point"}
}