{
  "type": "Feature",
  "properties": {
    "addr:full":"Via G. Amendola 16/a 48017 Conselice Conselice Ravenna 48017",
    "addr:housenumber":"16 / a",
    "addr:postcode":"48017;48017",
    "addr:street":"Via G. Amendola",
    "iso:country":"IT",
    "sg:address":"Via G. Amendola 16/a 48017 Conselice",
    "sg:city":"Conselice",
    "sg:classifiers":[
        {
            "category":"Science Facility",
            "type":"Public Place"
        }
    ],
    "sg:phone":"+39 0545 85231",
    "sg:postcode":"48017",
    "sg:province":"Ravenna",
    "sg:tags":[
        "installation",
        "milling",
        "installations",
        "grinding"
    ],
    "wof:name":"Rimplast Srl",
    "wof:placetype":"venue"
},
  "geometry": {"coordinates":[11.835121,44.509926],"type":"Point"}
}