{
  "type": "Feature",
  "properties": {
    "addr:full":"31, Largo Adua 70121 Bari Bari Bari 70121",
    "addr:housenumber":"31",
    "addr:postcode":"70121;70121",
    "addr:street":"Largo Adua",
    "iso:country":"IT",
    "sg:address":"31, Largo Adua 70121 Bari",
    "sg:city":"Bari",
    "sg:classifiers":[
        {
            "category":"Communications",
            "subcategory":"Newspaper",
            "type":"Services"
        }
    ],
    "sg:phone":"+39 080 554 1335",
    "sg:postcode":"70121",
    "sg:province":"Bari",
    "sg:tags":[
        "advertising"
    ],
    "wof:name":"Studio 9 Italia Agenzia Di Marketing & Pubblicita' (s.r.l.)",
    "wof:placetype":"venue"
},
  "geometry": {"coordinates":[16.802197,41.000023],"type":"Point"}
}