{
  "type": "Feature",
  "properties": {
    "addr:full":"31037 Loria Loria Treviso 31037",
    "addr:postcode":"31037;31037",
    "iso:country":"IT",
    "sg:address":"31037 Loria",
    "sg:city":"Loria",
    "sg:orig_category":"Acciaierie E Fonderie",
    "sg:phone":"+39 0423 456075",
    "sg:postcode":"31037",
    "sg:province":"Treviso",
    "wof:name":"Nicolini Adelisio",
    "wof:placetype":"venue"
},
  "geometry": {"coordinates":[11.857018,45.716228],"type":"Point"}
}