{
  "type": "Feature",
  "properties": {
    "addr:full":"18038 Sanremo Imperia 18038",
    "addr:postcode":"18038;18038",
    "iso:country":"IT",
    "sg:address":"18038 Sanremo",
    "sg:orig_category":"Elettrodomestici - Riparazione E Vendita Al Dettaglio Di Accessori",
    "sg:phone":"+39 0184 577250",
    "sg:postcode":"18038",
    "sg:province":"Imperia",
    "wof:name":"Riviera Service Center",
    "wof:placetype":"venue"
},
  "geometry": {"coordinates":[7.794724,43.820648],"type":"Point"}
}