{
  "type": "Feature",
  "properties": {
    "iso:country":"IT",
    "sg:address":"22100 Como",
    "sg:city":"Como",
    "sg:orig_category":"Materiali E Componenti Elettrotecnici",
    "sg:phone":"+39 031 240515",
    "sg:postcode":"22100",
    "sg:province":"Como",
    "wof:name":"Bigatti Renato",
    "wof:placetype":"venue"
},
  "geometry": {"coordinates":[9.090487,45.801289],"type":"Point"}
}