{
  "type": "Feature",
  "properties": {
    "addr:full":"1/l, Via Virgilio 00193 Roma Roma Roma 00193",
    "addr:housenumber":"1 / l",
    "addr:postcode":"00193;00193",
    "addr:street":"Via Virgilio",
    "iso:country":"IT",
    "sg:address":"1/l, Via Virgilio 00193 Roma",
    "sg:city":"Roma",
    "sg:classifiers":[
        {
            "category":"Shopping",
            "subcategory":"Gifts & Souvenirs",
            "type":"Retail Goods"
        }
    ],
    "sg:phone":"+39 39063729427",
    "sg:postcode":"00193",
    "sg:province":"Roma",
    "wof:name":"Italtabacchi (s.r.l.)",
    "wof:placetype":"venue"
},
  "geometry": {"coordinates":[12.487512,41.840214],"type":"Point"}
}