{
  "type": "Feature",
  "properties": {
    "addr:full":"10147 Torino Torino Torino 10147",
    "addr:postcode":"10147;10147",
    "iso:country":"IT",
    "sg:address":"10147 Torino",
    "sg:city":"Torino",
    "sg:orig_category":"Automazione E Macchine Per Ufficio",
    "sg:phone":"+39 011 229 6033",
    "sg:postcode":"10147",
    "sg:province":"Torino",
    "wof:name":"Gi.al (s.n.c.)",
    "wof:placetype":"venue"
},
  "geometry": {"coordinates":[7.681945,45.097145],"type":"Point"}
}