{
  "type": "Feature",
  "properties": {
    "iso:country":"IT",
    "sg:address":"01027 Montefiascone",
    "sg:city":"Montefiascone",
    "sg:orig_category":"Manufacturers: Prefabbricati. Forniture Per Edilizia E Lavori Pubblici",
    "sg:phone":"+39 0761 827192",
    "sg:postcode":"01027",
    "sg:province":"Viterbo",
    "wof:name":"Compar Srl",
    "wof:placetype":"venue"
},
  "geometry": {"coordinates":[12.037557,42.529873],"type":"Point"}
}