{
  "type": "Feature",
  "properties": {
    "iso:country":"IT",
    "sg:address":"10137 Torino",
    "sg:city":"Torino",
    "sg:orig_category":"Forniture Per Edilizia E Lavori Pubblici",
    "sg:phone":"+39 011 354440",
    "sg:postcode":"10137",
    "sg:province":"Torino",
    "wof:name":"Ri.el.ca. Torino",
    "wof:placetype":"venue"
},
  "geometry": {"coordinates":[7.3559718132,44.8895759583],"type":"Point"}
}