{
  "type": "Feature",
  "properties": {
    "iso:country":"IT",
    "sg:address":"47039 Savignano Sul Rubicone",
    "sg:city":"Savignano sul Rubicone",
    "sg:orig_category":"Minuterie Metalliche E Ferramenta",
    "sg:phone":"+39 0541 946720",
    "sg:postcode":"47039",
    "sg:province":"Forl\u00ec-Cesena",
    "wof:name":"Gregori Tiziano",
    "wof:placetype":"venue"
},
  "geometry": {"coordinates":[12.3979434967,44.095123291],"type":"Point"}
}