{
  "type": "Feature",
  "properties": {
    "addr:full":"7, Via Varese 22076 Mozzate Mozzate Como 22076",
    "addr:postcode":"22076;22076",
    "addr:street":"Via Varese",
    "iso:country":"IT",
    "sg:address":"7, Via Varese 22076 Mozzate",
    "sg:city":"Mozzate",
    "sg:classifiers":[
        {
            "category":"Professional",
            "subcategory":"Engineering",
            "type":"Services"
        }
    ],
    "sg:phone":"+39 0331 821093",
    "sg:postcode":"22076",
    "sg:province":"Como",
    "sg:tags":[
        "machine",
        "-",
        "mechanical"
    ],
    "wof:name":"Serri Enrico",
    "wof:placetype":"venue"
},
  "geometry": {"coordinates":[8.94749,45.677753],"type":"Point"}
}