{
  "type": "Feature",
  "properties": {
    "iso:country":"IT",
    "sg:address":"21014 Laveno Mombello",
    "sg:city":"Laveno",
    "sg:orig_category":"Non-classified Establishments",
    "sg:phone":"+39 0332 668153",
    "sg:postcode":"21014",
    "sg:province":"Varese",
    "sg:website":"http://www.fogolacasalinghi.it",
    "wof:name":"Fogola Snc Di Fogola Ersilia & C.",
    "wof:placetype":"venue"
},
  "geometry": {"coordinates":[8.618952,45.90567],"type":"Point"}
}