{
  "type": "Feature",
  "properties": {
    "addr:full":"12, Via Carlotti 55016 Porcari Porcari Lucca 55016",
    "addr:postcode":"55016;55016",
    "addr:street":"Via Carlotti",
    "iso:country":"IT",
    "sg:address":"12, Via Carlotti 55016 Porcari",
    "sg:city":"Porcari",
    "sg:classifiers":[
        {
            "category":"Shopping",
            "type":"Retail Goods"
        }
    ],
    "sg:phone":"+39 0583 298218",
    "sg:postcode":"55016",
    "sg:province":"Lucca",
    "sg:tags":[
        "finished",
        "-",
        "metallic"
    ],
    "wof:name":"Carp - Inox",
    "wof:placetype":"venue"
},
  "geometry": {"coordinates":[10.6195554733,43.8224182129],"type":"Point"}
}