{
  "type": "Feature",
  "properties": {
    "iso:country":"IT",
    "sg:address":"21/b, Corso Europa 97012 Chiaramonte Gulfi",
    "sg:city":"Chiaramonte Gulfi",
    "sg:classifiers":[
        {
            "category":"Personal",
            "subcategory":"Shoe Repair & Shine",
            "type":"Services"
        }
    ],
    "sg:phone":"+39 0932 922180",
    "sg:postcode":"97012",
    "sg:province":"Ragusa",
    "sg:tags":[
        "leather"
    ],
    "wof:name":"Calzaturificio Chiaramonte Di Catania Iacono & C.s.n.c.",
    "wof:placetype":"venue"
},
  "geometry": {"coordinates":[14.700401,37.0322],"type":"Point"}
}