{
  "type": "Feature",
  "properties": {
    "addr:full":"13026 Carcoforo Carcoforo Vercelli 13026",
    "addr:housenumber":"13026",
    "addr:postcode":"13026",
    "addr:street":"Carcoforo Carcoforo",
    "iso:country":"IT",
    "sg:address":"13026 Carcoforo",
    "sg:city":"Carcoforo",
    "sg:orig_category":"Servizi Per Lo Sport E Il Tempo Libero. Alberghi E Strutture Extra Alberghiere",
    "sg:phone":"+39 0163 95645",
    "sg:postcode":"13026",
    "sg:province":"Vercelli",
    "wof:name":"Rifugio Boffalora Alpe Piovale",
    "wof:placetype":"venue"
},
  "geometry": {"coordinates":[8.426394,45.32106],"type":"Point"}
}