{
  "type": "Feature",
  "properties": {
    "addr:full":"50050 Cerreto Guidi Cerreto Guidi Firenze 50050",
    "addr:postcode":"50050;50050",
    "iso:country":"IT",
    "sg:address":"50050 Cerreto Guidi",
    "sg:city":"Cerreto Guidi",
    "sg:orig_category":"Tessuti E Stoffe",
    "sg:phone":"+39 0571 956127",
    "sg:postcode":"50050",
    "sg:province":"Firenze",
    "wof:name":"Toscana Non Tessuti S.r.l.",
    "wof:placetype":"venue"
},
  "geometry": {"coordinates":[10.932546,43.720093],"type":"Point"}
}