{
  "type": "Feature",
  "properties": {
    "iso:country":"IT",
    "sg:address":"00155 Roma",
    "sg:city":"Roma",
    "sg:orig_category":"Acciai Inossidabili - Lavorazione",
    "sg:phone":"+39 06 228 3341",
    "sg:postcode":"00155",
    "sg:province":"Roma",
    "wof:name":"Pontecorvo & C. Spa",
    "wof:placetype":"venue"
},
  "geometry": {"coordinates":[12.591759,41.907986],"type":"Point"}
}