{
  "type": "Feature",
  "properties": {
    "iso:country":"IT",
    "sg:address":"65, Via Torino 30172 Venezia",
    "sg:city":"Venezia",
    "sg:classifiers":[
        {
            "category":"Utilities",
            "subcategory":"Telephone",
            "type":"Services"
        }
    ],
    "sg:phone":"+39 041 531 7876",
    "sg:postcode":"30172",
    "sg:province":"Venezia",
    "sg:tags":[
        "telecommunication"
    ],
    "wof:name":"Intelme (s.r.l.)",
    "wof:placetype":"venue"
},
  "geometry": {"coordinates":[12.776561,45.823318],"type":"Point"}
}