{
  "type": "Feature",
  "properties": {
    "iso:country":"IT",
    "sg:address":"3, Piazza Guglielmo Marconi 25072 Bagolino",
    "sg:city":"Bagolino",
    "sg:classifiers":[
        {
            "category":"Farming",
            "subcategory":"Livestock Farm",
            "type":"Manufacturing & Wholesale Goods"
        }
    ],
    "sg:phone":"+39 036 590 3027",
    "sg:postcode":"25072",
    "sg:province":"Brescia",
    "sg:tags":[
        "agriculture"
    ],
    "wof:name":"Foglio Angelo",
    "wof:placetype":"venue"
},
  "geometry": {"coordinates":[10.46232,45.823872],"type":"Point"}
}