{
  "type": "Feature",
  "properties": {
    "iso:country":"IT",
    "sg:address":"Via Ponte Nuovo 51 20128 Milano",
    "sg:city":"Milano",
    "sg:classifiers":[
        {
            "category":"Shopping",
            "subcategory":"Department Store",
            "type":"Retail Goods"
        }
    ],
    "sg:phone":"+39 02 2720 0522",
    "sg:postcode":"20128",
    "sg:province":"Milano",
    "sg:tags":[
        "anode"
    ],
    "sg:website":"www.omodeo.it",
    "wof:name":"Omodeo A.&s. Metalleghe Spa",
    "wof:placetype":"venue"
},
  "geometry": {"coordinates":[9.23619,45.508633],"type":"Point"}
}