{
  "type": "Feature",
  "properties": {
    "iso:country":"IT",
    "sg:address":"70010 Valenzano",
    "sg:city":"Valenzano",
    "sg:orig_category":"Impiantistica E Prodotti Tecnologici Per Edilizia. Climatizzazione E Condizionamento, Apparecchiature E Servizi",
    "sg:phone":"+39 080 467 4971",
    "sg:postcode":"70010",
    "sg:province":"Bari",
    "wof:name":"S.m.i.ter Srl",
    "wof:placetype":"venue"
},
  "geometry": {"coordinates":[16.88236,41.051762],"type":"Point"}
}