{
  "type": "Feature",
  "properties": {
    "iso:country":"IT",
    "sg:address":"20131 Milano",
    "sg:city":"Milano",
    "sg:orig_category":"Servizi E Lavori Per Abbigliamento E Pelletterie",
    "sg:phone":"+39 02 261 3545",
    "sg:postcode":"20131",
    "sg:province":"Milano",
    "wof:name":"Galesi Luigia",
    "wof:placetype":"venue"
},
  "geometry": {"coordinates":[9.231722,45.489269],"type":"Point"}
}