{
  "type": "Feature",
  "properties": {
    "addr:full":"21/b, Via Leopardi Giacomo 60015 Falconara Marittima Falconara Marittima Ancona 60015",
    "addr:housenumber":"21 / b",
    "addr:postcode":"60015;60015",
    "addr:street":"Via Leopardi Giacomo",
    "iso:country":"IT",
    "sg:address":"21/b, Via Leopardi Giacomo 60015 Falconara Marittima",
    "sg:city":"Falconara Marittima",
    "sg:classifiers":[
        {
            "category":"Shopping",
            "subcategory":"Computers & Home Electronics",
            "type":"Retail Goods"
        }
    ],
    "sg:phone":"+39 071 917 4802",
    "sg:postcode":"60015",
    "sg:province":"Ancona",
    "sg:tags":[
        "electronic",
        "electrical",
        "equipment"
    ],
    "wof:name":"El.tec. S.r.l.",
    "wof:placetype":"venue"
},
  "geometry": {"coordinates":[13.399973,43.627544],"type":"Point"}
}