{
  "type": "Feature",
  "properties": {
    "iso:country":"IT",
    "sg:address":"53100 Siena",
    "sg:city":"Siena",
    "sg:orig_category":"Etichette",
    "sg:phone":"+39 0577 49283",
    "sg:postcode":"53100",
    "sg:province":"Siena",
    "wof:name":"Etichettificio Senese Srl",
    "wof:placetype":"venue"
},
  "geometry": {"coordinates":[11.308245,43.313927],"type":"Point"}
}