{
  "type": "Feature",
  "properties": {
    "addr:full":"41100 Modena Modena Modena 41100",
    "addr:postcode":"41100;41100",
    "iso:country":"IT",
    "sg:address":"41100 Modena",
    "sg:city":"Modena",
    "sg:orig_category":"Motocicli E Motocarri Accessori E Parti - Vendita Al Dettaglio",
    "sg:phone":"+39 059 285192",
    "sg:postcode":"41100",
    "sg:province":"Modena",
    "sg:website":"http://www.neropaco.it",
    "wof:name":"Neropaco Srl",
    "wof:placetype":"venue"
},
  "geometry": {"coordinates":[10.9735078812,44.6355667114],"type":"Point"}
}