{
  "type": "Feature",
  "properties": {
    "addr:full":"14055 Costigliole D'asti Asti 14055",
    "addr:postcode":"14055;14055",
    "iso:country":"IT",
    "sg:address":"14055 Costigliole D'asti",
    "sg:orig_category":"Macchine, Impianti Ed Attrezzature Per Abbigliamento E Pelletterie",
    "sg:phone":"+39 0141 966310",
    "sg:postcode":"14055",
    "sg:province":"Asti",
    "wof:name":"Altex S.a.s.",
    "wof:placetype":"venue"
},
  "geometry": {"coordinates":[8.172073,44.793213],"type":"Point"}
}