{
  "type": "Feature",
  "properties": {
    "addr:full":"3, Via Dell' Artigianato 31041 Cornuda Cornuda Treviso 31041",
    "addr:postcode":"31041;31041",
    "addr:street":"Via Dell ' Artigianato",
    "iso:country":"IT",
    "sg:address":"3, Via Dell' Artigianato 31041 Cornuda",
    "sg:city":"Cornuda",
    "sg:classifiers":[
        {
            "category":"Professional",
            "subcategory":"Printing & Photocopies",
            "type":"Services"
        }
    ],
    "sg:phone":"+39 39042383294",
    "sg:postcode":"31041",
    "sg:province":"Treviso",
    "wof:name":"S 4 Serigrafia (s.r.l.)",
    "wof:placetype":"venue"
},
  "geometry": {"coordinates":[12.0085678101,45.8145256042],"type":"Point"}
}