{
  "type": "Feature",
  "properties": {
    "addr:full":"37055 Ronco All'adige Verona 37055",
    "addr:postcode":"37055;37055",
    "iso:country":"IT",
    "sg:address":"37055 Ronco All'adige",
    "sg:orig_category":"Pubblica Amministrazione",
    "sg:phone":"+39 045 661 6093",
    "sg:postcode":"37055",
    "sg:province":"Verona",
    "wof:name":"Carabinieri",
    "wof:placetype":"venue"
},
  "geometry": {"coordinates":[11.231467247,45.3216094971],"type":"Point"}
}