{
  "type": "Feature",
  "properties": {
    "iso:country":"IT",
    "sg:address":"42011 Bagnolo In Piano",
    "sg:orig_category":"Macchine, Impianti Ed Attrezzature Per Agricoltura E Zootecnia. Macchine E Forniture Per Arredamento E Industria Del Legno",
    "sg:phone":"+39 0522 959011",
    "sg:postcode":"42011",
    "sg:province":"Reggio Nell'Emilia",
    "wof:name":"Tecomec Spa",
    "wof:placetype":"venue"
},
  "geometry": {"coordinates":[10.669834,44.757042],"type":"Point"}
}