{
  "type": "Feature",
  "properties": {
    "addr:full":"22036 Erba Erba Como 22036",
    "addr:postcode":"22036;22036",
    "iso:country":"IT",
    "sg:address":"22036 Erba",
    "sg:city":"Erba",
    "sg:orig_category":"Fissaggio Articoli",
    "sg:phone":"+39 031 641590",
    "sg:postcode":"22036",
    "sg:province":"Como",
    "wof:name":"Alpefix",
    "wof:placetype":"venue"
},
  "geometry": {"coordinates":[9.2332286835,45.8137512207],"type":"Point"}
}