{
  "type": "Feature",
  "properties": {
    "iso:country":"IT",
    "sg:address":"06132 Perugia",
    "sg:city":"Perugia",
    "sg:orig_category":"Climatizzazione E Condizionamento, Apparecchiature E Servizi",
    "sg:phone":"+39 075 528 0393",
    "sg:postcode":"06132",
    "sg:province":"Perugia",
    "wof:name":"Clima Service Di Mencarelli & C. Snc",
    "wof:placetype":"venue"
},
  "geometry": {"coordinates":[12.357842,43.034187],"type":"Point"}
}