{
  "type": "Feature",
  "properties": {
    "addr:full":"Via Del Pratignone 20/22 50041 Calenzano Calenzano Firenze 50041",
    "addr:housenumber":"20 / 22",
    "addr:postcode":"50041;50041",
    "addr:street":"Via Del Pratignone",
    "iso:country":"IT",
    "sg:address":"Via Del Pratignone 20/22 50041 Calenzano",
    "sg:city":"Calenzano",
    "sg:classifiers":[
        {
            "category":"Shopping",
            "subcategory":"Discount & Variety Stores",
            "type":"Retail Goods"
        }
    ],
    "sg:phone":"+39 055 887 9465",
    "sg:postcode":"50041",
    "sg:province":"Firenze",
    "sg:tags":[
        "shop",
        "fitting"
    ],
    "sg:website":"www.arpaarreda.com",
    "wof:name":"Arpa Arreda Srl",
    "wof:placetype":"venue"
},
  "geometry": {"coordinates":[11.1627082825,43.8492889404],"type":"Point"}
}