{
  "type": "Feature",
  "properties": {
    "addr:full":"20123 Milano Milano Milano 20123",
    "addr:postcode":"20123;20123",
    "iso:country":"IT",
    "sg:address":"20123 Milano",
    "sg:city":"Milano",
    "sg:orig_category":"Forniture Per Uffici. Servizi Vari Di Interesse Pubblico",
    "sg:phone":"+39 02 804767",
    "sg:postcode":"20123",
    "sg:province":"Milano",
    "wof:name":"Miliardo Di Andrea Molteni & C. S.n.c.",
    "wof:placetype":"venue"
},
  "geometry": {"coordinates":[9.1869382858,45.4627532959],"type":"Point"}
}