{
  "type": "Feature",
  "properties": {
    "iso:country":"IT",
    "sg:address":"42048 Rubiera",
    "sg:orig_category":"Impiantistica E Prodotti Tecnologici Per Edilizia. Elettrotecnica Industriale, Prodotti E Apparecchiature. Elettrotecnica Professionale E Di Consumo",
    "sg:phone":"+39 0522 626156",
    "sg:postcode":"42048",
    "sg:province":"Reggio Nell'Emilia",
    "wof:name":"Elettrofile Srl",
    "wof:placetype":"venue"
},
  "geometry": {"coordinates":[10.779716,44.648479],"type":"Point"}
}