{
  "type": "Feature",
  "properties": {
    "iso:country":"IT",
    "sg:address":"80053 Castellammare Di Stabia",
    "sg:city":"Castellammare di Stabia",
    "sg:orig_category":"Ambulanze Private - Servizio",
    "sg:phone":"+39 081 871 2717",
    "sg:postcode":"80053",
    "sg:province":"Napoli",
    "wof:name":"Eurosan Sas",
    "wof:placetype":"venue"
},
  "geometry": {"coordinates":[14.480992,40.717377],"type":"Point"}
}