{
  "type": "Feature",
  "properties": {
    "iso:country":"IT",
    "sg:address":"20080 San Pietro Cusico",
    "sg:city":"San Pietro Cusico",
    "sg:orig_category":"Climatizzazione E Condizionamento, Apparecchiature E Servizi. Elettrotecnica Professionale E Di Consumo",
    "sg:phone":"+39 02 9000 2491",
    "sg:postcode":"20080",
    "sg:province":"Milano",
    "wof:name":"Textil Elettrochimica",
    "wof:placetype":"venue"
},
  "geometry": {"coordinates":[9.097369,45.381298],"type":"Point"}
}