{
  "type": "Feature",
  "properties": {
    "addr:full":"31020 San Fior Castello roganzuolo Treviso 31020",
    "addr:housenumber":"31020",
    "addr:postcode":"31020",
    "addr:street":"San;Treviso",
    "iso:country":"IT",
    "sg:address":"31020 San Fior",
    "sg:city":"Castello roganzuolo",
    "sg:orig_category":"Serramenti Ed Infissi",
    "sg:phone":"+39 0438 260100",
    "sg:postcode":"31020",
    "sg:province":"Treviso",
    "sg:website":"http://www.rosada.com",
    "wof:name":"Rosada Spa",
    "wof:placetype":"venue"
},
  "geometry": {"coordinates":[12.342189,45.909683],"type":"Point"}
}