{
  "type": "Feature",
  "properties": {
    "iso:country":"IT",
    "sg:address":"48018 Faenza",
    "sg:city":"Faenza",
    "sg:classifiers":[
        {
            "category":"Bars & Pubs",
            "subcategory":"Biergarten",
            "type":"Food & Drink"
        }
    ],
    "sg:phone":"+39 0546 682565",
    "sg:postcode":"48018",
    "sg:province":"Ravenna",
    "sg:tags":[
        "birrerie",
        "e"
    ],
    "wof:name":"Chalet Dello Sport",
    "wof:placetype":"venue"
},
  "geometry": {"coordinates":[12.030304,44.372849],"type":"Point"}
}