{
  "type": "Feature",
  "properties": {
    "addr:full":"10142 Torino Torino Torino 10142",
    "addr:postcode":"10142;10142",
    "iso:country":"IT",
    "sg:address":"10142 Torino",
    "sg:city":"Torino",
    "sg:orig_category":"Macchine Ed Impianti Per Edilizia E Lavori Pubblici. Elettronica Industriale, Prodotti E Apparecchiature",
    "sg:phone":"+39 011 707 2610",
    "sg:postcode":"10142",
    "sg:province":"Torino",
    "wof:name":"Mazzaferro Cosimo",
    "wof:placetype":"venue"
},
  "geometry": {"coordinates":[7.612369,45.071617],"type":"Point"}
}