{
  "type": "Feature",
  "properties": {
    "iso:country":"IT",
    "sg:address":"86010 Castropignano",
    "sg:city":"Castropignano",
    "sg:classifiers":[
        {
            "category":"Restaurant",
            "type":"Food & Drink"
        }
    ],
    "sg:phone":"+39 0874 503164",
    "sg:postcode":"86010",
    "sg:province":"Campobasso",
    "sg:tags":[
        "auxiliary",
        "entertainment",
        "premises",
        "related",
        "catering",
        "similar",
        "public",
        "restaurants"
    ],
    "wof:name":"Tavaniello Michele",
    "wof:placetype":"venue"
},
  "geometry": {"coordinates":[14.573209,41.641624],"type":"Point"}
}