{
  "type": "Feature",
  "properties": {
    "iso:country":"IT",
    "sg:address":"62012 Civitanova Marche",
    "sg:city":"Civitanova Marche",
    "sg:orig_category":"Utensili Meccanici E Materiali",
    "sg:phone":"+39 0733 829602",
    "sg:postcode":"62012",
    "sg:province":"Macerata",
    "wof:name":"Modelleria Alma Di Lori S. & Romanelli P. Snc",
    "wof:placetype":"venue"
},
  "geometry": {"coordinates":[13.705384,43.294106],"type":"Point"}
}