{
  "type": "Feature",
  "properties": {
    "iso:country":"IT",
    "sg:address":"Via Persicetana 24b 40012 Calderara Di Reno",
    "sg:city":"Calderara di Reno",
    "sg:classifiers":[
        {
            "category":"Government",
            "subcategory":"Department Of Motor Vehicles",
            "type":"Public Place"
        }
    ],
    "sg:phone":"+39 051 729916",
    "sg:postcode":"40012",
    "sg:province":"Bologna",
    "sg:tags":[
        "gearing",
        "speed",
        "transmissions",
        "manual",
        "change"
    ],
    "sg:website":"www.paginegialle.it/cobra-02",
    "wof:name":"Cobra Srl",
    "wof:placetype":"venue"
},
  "geometry": {"coordinates":[11.255376,44.556087],"type":"Point"}
}