{
  "type": "Feature",
  "properties": {
    "addr:full":"V.v. Emanuele; Acerenza; 85011 Acerenza Potenza 85011",
    "addr:postcode":"85011;85011",
    "addr:street":"Acerenza",
    "iso:country":"IT",
    "sg:address":"V.v. Emanuele; Acerenza; 85011",
    "sg:city":"Acerenza",
    "sg:classifiers":[
        {
            "category":"Banks & Credit Unions",
            "subcategory":"Bank",
            "type":"Services"
        }
    ],
    "sg:phone":"+39 0971 941007",
    "sg:postcode":"85011",
    "sg:province":"Potenza",
    "wof:name":"Banca Di Lucania",
    "wof:placetype":"venue"
},
  "geometry": {"coordinates":[15.938783,40.793671],"type":"Point"}
}