{
  "type": "Feature",
  "properties": {
    "iso:country":"IT",
    "sg:address":"6, Via Maestri Del Lavoro 30026 Portogruaro",
    "sg:city":"Portogruaro",
    "sg:classifiers":[
        {
            "category":"Wholesale",
            "subcategory":"Drugs",
            "type":"Manufacturing & Wholesale Goods"
        }
    ],
    "sg:phone":"+39 0421 275018",
    "sg:postcode":"30026",
    "sg:province":"Venezia",
    "sg:tags":[
        "chemical",
        "pharmaceutical"
    ],
    "wof:name":"Euromec 2 S.r.l.",
    "wof:placetype":"venue"
},
  "geometry": {"coordinates":[12.874956,45.781475],"type":"Point"}
}