{
  "type": "Feature",
  "properties": {
    "iso:country":"IT",
    "sg:address":"2, Via Tavernola 83020 Domicella",
    "sg:city":"Domicella",
    "sg:classifiers":[
        {
            "category":"Manufacturing",
            "subcategory":"Lumber",
            "type":"Manufacturing & Wholesale Goods"
        }
    ],
    "sg:phone":"+39 081 825 4289",
    "sg:postcode":"83020",
    "sg:province":"Avellino",
    "sg:tags":[
        "wood"
    ],
    "wof:name":"Sorrentino Industria Legnami Srl",
    "wof:placetype":"venue"
},
  "geometry": {"coordinates":[14.57699,40.881905],"type":"Point"}
}