{
  "type": "Feature",
  "properties": {
    "iso:country":"IT",
    "sg:address":"17100 Montemoro",
    "sg:orig_category":"Forniture Per Agricoltura E Zootecnia. Prodotti Chimici Secondari",
    "sg:phone":"+39 019 875101",
    "sg:postcode":"17100",
    "sg:province":"Savona",
    "wof:name":"Valli Tomaso",
    "wof:placetype":"venue"
},
  "geometry": {"coordinates":[8.4160823822,44.3254547119],"type":"Point"}
}