{
  "type": "Feature",
  "properties": {
    "addr:full":"40, Corso Sempione 20154 Milano Milano Milano 20154",
    "addr:postcode":"20154;20154",
    "addr:street":"Corso Sempione",
    "iso:country":"IT",
    "sg:address":"40, Corso Sempione 20154 Milano",
    "sg:city":"Milano",
    "sg:classifiers":[
        {
            "category":"Manufacturing",
            "subcategory":"Printing",
            "type":"Manufacturing & Wholesale Goods"
        }
    ],
    "sg:phone":"+39 02 3310 5635",
    "sg:postcode":"20154",
    "sg:province":"Milano",
    "sg:tags":[
        "publishing"
    ],
    "wof:name":"Peperoncino Studio (s.r.l.)",
    "wof:placetype":"venue"
},
  "geometry": {"coordinates":[9.1653938293,45.4815292358],"type":"Point"}
}