{
  "type": "Feature",
  "properties": {
    "iso:country":"IT",
    "sg:address":"20035 Lissone",
    "sg:city":"Lissone",
    "sg:orig_category":"Tempo Libero - Articoli E Forniture. Regalistica Aziendale",
    "sg:phone":"+39 039 463624",
    "sg:postcode":"20035",
    "sg:province":"Milano",
    "sg:website":"http://www.osm.it",
    "wof:name":"O.s.m. Srl",
    "wof:placetype":"venue"
},
  "geometry": {"coordinates":[9.173513,45.481186],"type":"Point"}
}