{
  "type": "Feature",
  "properties": {
    "addr:full":"10, Via Giacomo Leopardi 23890 Barzago Barzago Lecco 23890",
    "addr:postcode":"23890;23890",
    "addr:street":"Via Giacomo Leopardi",
    "iso:country":"IT",
    "sg:address":"10, Via Giacomo Leopardi 23890 Barzago",
    "sg:city":"Barzago",
    "sg:classifiers":[
        {
            "category":"Shopping",
            "subcategory":"Crafts & Fabrics",
            "type":"Retail Goods"
        }
    ],
    "sg:phone":"+39 39031874372",
    "sg:postcode":"23890",
    "sg:province":"Lecco",
    "wof:name":"Pozzi (s.p.a.)",
    "wof:placetype":"venue"
},
  "geometry": {"coordinates":[9.3144006729,45.7517471313],"type":"Point"}
}