{
  "type": "Feature",
  "properties": {
    "addr:full":"31, Via Palermo 20090 Buccinasco Buccinasco Milano 20090",
    "addr:postcode":"20090;20090",
    "addr:street":"Via Palermo",
    "iso:country":"IT",
    "sg:address":"31, Via Palermo 20090 Buccinasco",
    "sg:city":"Buccinasco",
    "sg:classifiers":[
        {
            "category":"Professional",
            "subcategory":"Engineering",
            "type":"Services"
        }
    ],
    "sg:phone":"+39 02 4570 3500",
    "sg:postcode":"20090",
    "sg:province":"Milano",
    "sg:tags":[
        "machine",
        "-",
        "mechanical"
    ],
    "wof:name":"Somova Srl",
    "wof:placetype":"venue"
},
  "geometry": {"coordinates":[9.114241,45.425423],"type":"Point"}
}