{
  "type": "Feature",
  "properties": {
    "iso:country":"IT",
    "sg:address":"Via Balzani Ugo 12 00162 Roma",
    "sg:city":"Roma",
    "sg:classifiers":[
        {
            "category":"Professional",
            "subcategory":"Detective & Security Services",
            "type":"Services"
        }
    ],
    "sg:phone":"+39 06 8620 5258",
    "sg:postcode":"00162",
    "sg:province":"Roma",
    "sg:tags":[
        "agency"
    ],
    "wof:name":"Edal Srl",
    "wof:placetype":"venue"
},
  "geometry": {"coordinates":[12.482325,41.895466],"type":"Point"}
}