{
  "type": "Feature",
  "properties": {
    "addr:full":"40064 Ozzano Dell'emilia Bologna 40064",
    "addr:postcode":"40064;40064",
    "iso:country":"IT",
    "sg:address":"40064 Ozzano Dell'emilia",
    "sg:orig_category":"Prodotti Vari In Metallo. Articoli Per Imballaggio E Confezionamento",
    "sg:phone":"+39 051 797495",
    "sg:postcode":"40064",
    "sg:province":"Bologna",
    "wof:name":"Italserbatoi Snc Di Corrente Pasquale & C",
    "wof:placetype":"venue"
},
  "geometry": {"coordinates":[11.5031747818,44.4647407532],"type":"Point"}
}