{
  "type": "Feature",
  "properties": {
    "iso:country":"IT",
    "sg:address":"16149 Genova",
    "sg:city":"Genova",
    "sg:orig_category":"Trasporti E Spedizioni Merci",
    "sg:phone":"+39 010 417532",
    "sg:postcode":"16149",
    "sg:province":"Genova",
    "wof:name":"Macor Cav. Placido & C. Srl",
    "wof:placetype":"venue"
},
  "geometry": {"coordinates":[8.890105,44.411594],"type":"Point"}
}