{
  "type": "Feature",
  "properties": {
    "addr:full":"20124 Milano Milano Milano 20124",
    "addr:postcode":"20124;20124",
    "iso:country":"IT",
    "sg:address":"20124 Milano",
    "sg:city":"Milano",
    "sg:classifiers":[
        {
            "category":"Banks & Credit Unions",
            "subcategory":"Investment Brokerage",
            "type":"Services"
        }
    ],
    "sg:phone":"+39 02 688 3934",
    "sg:postcode":"20124",
    "sg:province":"Milano",
    "sg:tags":[
        "building",
        "livestock",
        "civil",
        "industry",
        "equipment",
        "machinery",
        "breeding",
        "works",
        "agriculture"
    ],
    "sg:website":"http://www.paginegialle/scrim",
    "wof:name":"S.c.r.i.m. Srl",
    "wof:placetype":"venue"
},
  "geometry": {"coordinates":[9.196469,45.492901],"type":"Point"}
}