{
  "type": "Feature",
  "properties": {
    "iso:country":"IT",
    "sg:address":"41100 Modena",
    "sg:city":"Modena",
    "sg:orig_category":"Pubblicita', Marketing E Comunicazione",
    "sg:phone":"+39 059 366626",
    "sg:postcode":"41100",
    "sg:province":"Modena",
    "sg:website":"http://www.mainstreet.it",
    "wof:name":"Main Street Grafica",
    "wof:placetype":"venue"
},
  "geometry": {"coordinates":[10.9410963058,44.6425132751],"type":"Point"}
}