{
  "type": "Feature",
  "properties": {
    "iso:country":"IT",
    "sg:address":"Via Xxv Luglio 11 41037 Mirandola",
    "sg:city":"Mirandola",
    "sg:classifiers":[
        {
            "category":"Science Facility",
            "type":"Public Place"
        }
    ],
    "sg:phone":"+39 0535 616711",
    "sg:postcode":"41037",
    "sg:province":"Modena",
    "sg:tags":[
        "appliance",
        "biomedical"
    ],
    "sg:website":"www.bbraun.com",
    "wof:name":"B. Braun Carex Spa",
    "wof:placetype":"venue"
},
  "geometry": {"coordinates":[10.92522,44.647079],"type":"Point"}
}