{
  "type": "Feature",
  "properties": {
    "iso:country":"IT",
    "sg:address":"Prima Strada 2 Interporto Sito 10043 Orbassano",
    "sg:city":"Orbassano",
    "sg:classifiers":[
        {
            "category":"Shopping",
            "subcategory":"Pets & Pet Supplies",
            "type":"Retail Goods"
        }
    ],
    "sg:phone":"+39 011 397 5759",
    "sg:postcode":"10043",
    "sg:province":"Torino",
    "sg:tags":[
        "container"
    ],
    "sg:website":"www.allibert.it",
    "wof:name":"Allibert Contenitori S.p.a.",
    "wof:placetype":"venue"
},
  "geometry": {"coordinates":[7.6866188049,45.0705604553],"type":"Point"}
}