{
  "type": "Feature",
  "properties": {
    "iso:country":"IT",
    "sg:address":"00048 Nettuno",
    "sg:city":"Nettuno",
    "sg:orig_category":"Banche E Servizi Finanziari",
    "sg:phone":"+39 06 980 3330",
    "sg:postcode":"00048",
    "sg:province":"Roma",
    "wof:name":"Studio Cavallaro Cipriani",
    "wof:placetype":"venue"
},
  "geometry": {"coordinates":[12.46104,41.919617],"type":"Point"}
}