{
  "type": "Feature",
  "properties": {
    "iso:country":"IT",
    "sg:address":"Via Bovio, 45; Cattolica; 47033",
    "sg:classifiers":[
        {
            "category":"Banks & Credit Unions",
            "subcategory":"Bank",
            "type":"Services"
        }
    ],
    "sg:phone":"+39 0541 953719",
    "wof:name":"Cassa Di Risparmio Di Rimini",
    "wof:placetype":"venue"
},
  "geometry": {"coordinates":[12.741321,43.965599],"type":"Point"}
}