{
  "type": "Feature",
  "properties": {
    "addr:full":"Via Gualco 36 16165 Genova Genova Genova 16165",
    "addr:housenumber":"36",
    "addr:postcode":"16165;16165",
    "addr:street":"Via Gualco",
    "iso:country":"IT",
    "sg:address":"Via Gualco 36 16165 Genova",
    "sg:city":"Genova",
    "sg:classifiers":[
        {
            "category":"Manufacturing",
            "subcategory":"Rubber & Plastics",
            "type":"Manufacturing & Wholesale Goods"
        }
    ],
    "sg:phone":"+39 010 809971",
    "sg:postcode":"16165",
    "sg:province":"Genova",
    "sg:tags":[
        "tube",
        "component",
        "shaped"
    ],
    "wof:name":"Fiver Srl",
    "wof:placetype":"venue"
},
  "geometry": {"coordinates":[9.001981,44.446239],"type":"Point"}
}