{
  "type": "Feature",
  "properties": {
    "addr:full":"31040 Volpago Del Montello Volpago del Montello Treviso 31040",
    "addr:housenumber":"del montello",
    "addr:postcode":"31040;31040",
    "addr:street":"Del Montello",
    "iso:country":"IT",
    "sg:address":"31040 Volpago Del Montello",
    "sg:city":"Volpago del Montello",
    "sg:orig_category":"Calzature - Produzione E Ingrosso",
    "sg:phone":"+39 0423 870020",
    "sg:postcode":"31040",
    "sg:province":"Treviso",
    "wof:name":"Calzaturificio Mepres Srl",
    "wof:placetype":"venue"
},
  "geometry": {"coordinates":[12.102073,45.77824],"type":"Point"}
}