{
  "type": "Feature",
  "properties": {
    "iso:country":"IT",
    "sg:address":"00167 Roma",
    "sg:city":"Roma",
    "sg:orig_category":"Servizi E Lavori Industria Chimica",
    "sg:phone":"+39 06 3973 2066",
    "sg:postcode":"00167",
    "sg:province":"Roma",
    "wof:name":"Venturini Moto",
    "wof:placetype":"venue"
},
  "geometry": {"coordinates":[12.434708,41.909145],"type":"Point"}
}