{
  "type": "Feature",
  "properties": {
    "iso:country":"IT",
    "sg:address":"20030 Senago",
    "sg:city":"Senago",
    "sg:orig_category":"Prodotti Alimentari",
    "sg:phone":"+39 02 998 6224",
    "sg:postcode":"20030",
    "sg:province":"Milano",
    "wof:name":"Delgrossi Spa",
    "wof:placetype":"venue"
},
  "geometry": {"coordinates":[9.1566896439,45.5710372925],"type":"Point"}
}