{
  "type": "Feature",
  "properties": {
    "iso:country":"IT",
    "sg:address":"20127 Milano",
    "sg:city":"Milano",
    "sg:classifiers":[
        {
            "category":"Shopping",
            "subcategory":"Crafts & Fabrics",
            "type":"Retail Goods"
        }
    ],
    "sg:phone":"+39 02 284 7286",
    "sg:postcode":"20127",
    "sg:province":"Milano",
    "sg:tags":[
        "steelworks",
        "art",
        "artistic",
        "foundries"
    ],
    "wof:name":"Fonderia D'arte M.a.f. Snc",
    "wof:placetype":"venue"
},
  "geometry": {"coordinates":[9.21195,45.490257],"type":"Point"}
}