{
  "type": "Feature",
  "properties": {
    "iso:country":"IT",
    "sg:address":"20016 Pero",
    "sg:city":"Pero",
    "sg:orig_category":"Ricambi E Componenti Dei Mezzi Di Trasporto",
    "sg:phone":"+39 02 3810 0432",
    "sg:postcode":"20016",
    "sg:province":"Milano",
    "wof:name":"Franchetti Antonio",
    "wof:placetype":"venue"
},
  "geometry": {"coordinates":[9.082224,45.514225],"type":"Point"}
}