{
  "type": "Feature",
  "properties": {
    "iso:country":"IT",
    "sg:address":"23873 Missaglia",
    "sg:city":"Missaglia",
    "sg:orig_category":"Carrelli Elevatori E Trasportatori - Commercio E Noleggio",
    "sg:phone":"+39 039 924 1613",
    "sg:postcode":"23873",
    "sg:province":"Lecco",
    "sg:website":"http://www.co-car.it",
    "wof:name":"Co-car Srl",
    "wof:placetype":"venue"
},
  "geometry": {"coordinates":[9.347558,45.697399],"type":"Point"}
}