{
  "type": "Feature",
  "properties": {
    "iso:country":"IT",
    "sg:address":"00122 Lido Di Ostia",
    "sg:orig_category":"Servizi Per Lo Sport E Il Tempo Libero. Alberghi E Strutture Extra Alberghiere",
    "sg:phone":"+39 06 5647 0326",
    "sg:postcode":"00122",
    "sg:province":"Roma",
    "wof:name":"Europa Srl",
    "wof:placetype":"venue"
},
  "geometry": {"coordinates":[12.319139,41.713493],"type":"Point"}
}