{
  "type": "Feature",
  "properties": {
    "iso:country":"IT",
    "sg:address":"Via Delle Industrie 4 26020 Spinadesco",
    "sg:city":"Spinadesco",
    "sg:classifiers":[
        {
            "category":"Food & Beverages",
            "subcategory":"Specialty",
            "type":"Retail Goods"
        }
    ],
    "sg:phone":"+39 0372 446177",
    "sg:postcode":"26020",
    "sg:province":"Cremona",
    "sg:tags":[
        "solvent"
    ],
    "wof:name":"Vernisol Italiana Srl",
    "wof:placetype":"venue"
},
  "geometry": {"coordinates":[9.938555,45.149834],"type":"Point"}
}