{
  "type": "Feature",
  "properties": {
    "iso:country":"IT",
    "sg:address":"00198 Roma",
    "sg:city":"Roma",
    "sg:orig_category":"Servizi Per Aziende, Manifestazioni E Supporto Agli Scambi Commerciali",
    "sg:phone":"+39 06 854 2141",
    "sg:postcode":"00198",
    "sg:province":"Roma",
    "sg:website":"http://www.hotelbeverly.com",
    "wof:name":"Hotel Beverly Hills",
    "wof:placetype":"venue"
},
  "geometry": {"coordinates":[12.503992,41.917881],"type":"Point"}
}