{
  "type": "Feature",
  "properties": {
    "iso:country":"IT",
    "sg:address":"Via Verona 7 20063 Cernusco Sul Naviglio",
    "sg:city":"Cernusco sul Naviglio",
    "sg:classifiers":[
        {
            "category":"Utilities",
            "subcategory":"Water",
            "type":"Services"
        }
    ],
    "sg:phone":"+39 02 924 4341",
    "sg:postcode":"20063",
    "sg:province":"Milano",
    "sg:tags":[
        "aluminium",
        "collapsible",
        "tube"
    ],
    "sg:website":"www.favia.it",
    "wof:name":"Tubettificio Favia Srl",
    "wof:placetype":"venue"
},
  "geometry": {"coordinates":[9.294989,45.529625],"type":"Point"}
}