{
  "type": "Feature",
  "properties": {
    "iso:country":"IT",
    "sg:address":"24126 Bergamo",
    "sg:city":"Bergamo",
    "sg:orig_category":"Trattamenti Termici E Superficiali Metalli, Galvanotecnica",
    "sg:phone":"+39 035 320062",
    "sg:postcode":"24126",
    "sg:province":"Bergamo",
    "wof:name":"Vicentini Olivo & C. S.d.f.",
    "wof:placetype":"venue"
},
  "geometry": {"coordinates":[9.653214,45.675579],"type":"Point"}
}