{
  "type": "Feature",
  "properties": {
    "iso:country":"IT",
    "sg:address":"20127 Milano",
    "sg:city":"Milano",
    "sg:orig_category":"Ospedali E Servizi Sanitari",
    "sg:phone":"+39 02 261 5692",
    "sg:postcode":"20127",
    "sg:province":"Milano",
    "wof:name":"Costa Mirella",
    "wof:placetype":"venue"
},
  "geometry": {"coordinates":[9.229825,45.496296],"type":"Point"}
}