{
  "type": "Feature",
  "properties": {
    "addr:full":"55010 Lunata Lucca 55010",
    "addr:postcode":"55010;55010",
    "iso:country":"IT",
    "sg:address":"55010 Lunata",
    "sg:orig_category":"Carta, Cartone E Prodotti Primari. Forniture Per Uffici",
    "sg:phone":"+39 0583 93011",
    "sg:postcode":"55010",
    "sg:province":"Lucca",
    "wof:name":"Linder Spa",
    "wof:placetype":"venue"
},
  "geometry": {"coordinates":[10.507994,43.843014],"type":"Point"}
}