{
  "type": "Feature",
  "properties": {
    "iso:country":"IT",
    "sg:address":"98048 Spadafora",
    "sg:city":"Spadafora",
    "sg:orig_category":"Materiali Edili",
    "sg:phone":"+39 090 994 1856",
    "sg:postcode":"98048",
    "sg:province":"Messina",
    "wof:name":"Ragno Santi",
    "wof:placetype":"venue"
},
  "geometry": {"coordinates":[15.389237,38.211403],"type":"Point"}
}