{
  "type": "Feature",
  "properties": {
    "addr:full":"50018 Scandicci Scandicci Firenze 50018",
    "addr:postcode":"50018;50018",
    "iso:country":"IT",
    "sg:address":"50018 Scandicci",
    "sg:city":"Scandicci",
    "sg:classifiers":[
        {
            "category":"Home & Garden",
            "subcategory":"Furniture",
            "type":"Retail Goods"
        }
    ],
    "sg:phone":"+39 055 756031",
    "sg:postcode":"50018",
    "sg:province":"Firenze",
    "sg:tags":[
        "furnishing"
    ],
    "wof:name":"Chelini Spa",
    "wof:placetype":"venue"
},
  "geometry": {"coordinates":[11.1730356216,43.7585067749],"type":"Point"}
}