{
  "type": "Feature",
  "properties": {
    "addr:full":"50064 Incisa In Val D'arno Firenze 50064",
    "addr:postcode":"50064;50064",
    "addr:street":"Incisa In Val D'Arno",
    "iso:country":"IT",
    "sg:address":"50064 Incisa In Val D'arno",
    "sg:orig_category":"Accessori Dei Mezzi Di Trasporto",
    "sg:phone":"+39 055 833 5051",
    "sg:postcode":"50064",
    "sg:province":"Firenze",
    "wof:name":"Bianchi Moto Snc Di Bianchi Cesarino E Stefano",
    "wof:placetype":"venue"
},
  "geometry": {"coordinates":[11.448588,43.660606],"type":"Point"}
}