{
  "type": "Feature",
  "properties": {
    "iso:country":"IT",
    "sg:address":"Lungotevere Aventino, 5; Roma; 00153",
    "sg:city":"Roma",
    "sg:classifiers":[
        {
            "category":"Travel",
            "subcategory":"Travel Agent",
            "type":"Entertainment"
        }
    ],
    "sg:phone":"+39 390 657 1111",
    "sg:postcode":"00153",
    "sg:province":"Roma",
    "sg:website":"amthotels.com",
    "wof:name":"Amt Hotels",
    "wof:placetype":"venue"
},
  "geometry": {"coordinates":[12.479427,41.885635],"type":"Point"}
}