{
  "type": "Feature",
  "properties": {
    "addr:full":"1, Via Galvani 35030 Rubano Rubano Padova 35030",
    "addr:postcode":"35030;35030",
    "addr:street":"Via Galvani",
    "iso:country":"IT",
    "sg:address":"1, Via Galvani 35030 Rubano",
    "sg:city":"Rubano",
    "sg:classifiers":[
        {
            "category":"Home & Garden",
            "subcategory":"Home Furnishings",
            "type":"Retail Goods"
        }
    ],
    "sg:phone":"+39 049 897 6322",
    "sg:postcode":"35030",
    "sg:province":"Padova",
    "sg:tags":[
        "household"
    ],
    "wof:name":"Lb Industries S.r.l.",
    "wof:placetype":"venue"
},
  "geometry": {"coordinates":[11.8116922379,45.4094543457],"type":"Point"}
}