{
  "type": "Feature",
  "properties": {
    "iso:country":"IT",
    "sg:address":"35015 Galliera Veneta",
    "sg:city":"Galliera Veneta",
    "sg:orig_category":"Scaffalature Metalliche E Componibili",
    "sg:phone":"+39 049 941 6111",
    "sg:postcode":"35015",
    "sg:province":"Padova",
    "sg:website":"http://www.gsscaffalature.it",
    "wof:name":"G.s. Scaffalature Engineering Spa",
    "wof:placetype":"venue"
},
  "geometry": {"coordinates":[11.818079,45.667545],"type":"Point"}
}