{
  "type": "Feature",
  "properties": {
    "addr:full":"10072 Caselle Torinese Caselle Torinese Torino 10072",
    "addr:postcode":"10072;10072",
    "iso:country":"IT",
    "sg:address":"10072 Caselle Torinese",
    "sg:city":"Caselle Torinese",
    "sg:orig_category":"Prodotti E Manufatti In Materie Plastiche. Servizi E Lavori Industria Delle Materie Plastiche",
    "sg:phone":"+39 011 996 8136",
    "sg:postcode":"10072",
    "sg:province":"Torino",
    "sg:website":"http://www.castelli-isolanti.it",
    "wof:name":"Castelli Di Castelli Alessandro & C. Sas",
    "wof:placetype":"venue"
},
  "geometry": {"coordinates":[7.6509232521,45.1842308044],"type":"Point"}
}