{
  "type": "Feature",
  "properties": {
    "iso:country":"IT",
    "sg:address":"Largo Orbassano, 66; Torino; 10129",
    "sg:city":"Torino",
    "sg:classifiers":[
        {
            "category":"Banks & Credit Unions",
            "subcategory":"Bank",
            "type":"Services"
        }
    ],
    "sg:phone":"+39 011 318 6664",
    "sg:postcode":"10129",
    "sg:province":"Torino",
    "wof:name":"Cassa Di Risparmio Di Fossano Spa",
    "wof:placetype":"venue"
},
  "geometry": {"coordinates":[7.654895,45.053001],"type":"Point"}
}