{
  "type": "Feature",
  "properties": {
    "addr:full":"26/b, V. Bassa Dei Sassi 40138 Bologna Bologna Bologna 40138",
    "addr:housenumber":"26 / b v.",
    "addr:postcode":"40138;40138",
    "addr:street":"Bassa Dei Sassi",
    "iso:country":"IT",
    "sg:address":"26/b, V. Bassa Dei Sassi 40138 Bologna",
    "sg:city":"Bologna",
    "sg:classifiers":[
        {
            "category":"Wholesale",
            "subcategory":"Machinery & Supplies",
            "type":"Manufacturing & Wholesale Goods"
        }
    ],
    "sg:phone":"+39 051 601 3501",
    "sg:postcode":"40138",
    "sg:province":"Bologna",
    "sg:tags":[
        "equipment",
        "precision"
    ],
    "sg:website":"http://www.paginegialle.it/drl",
    "wof:name":"D.r.l. Snc",
    "wof:placetype":"venue"
},
  "geometry": {"coordinates":[11.4030256271,44.4972381592],"type":"Point"}
}