{
  "type": "Feature",
  "properties": {
    "addr:full":"3, Piazza Liberta' 39045 Fortezza Fortezza Bolzano/Bozen 39045",
    "addr:postcode":"39045;39045",
    "addr:street":"Piazza Liberta '",
    "iso:country":"IT",
    "sg:address":"3, Piazza Liberta' 39045 Fortezza",
    "sg:city":"Fortezza",
    "sg:classifiers":[
        {
            "category":"Manufacturing",
            "subcategory":"Paper Products",
            "type":"Manufacturing & Wholesale Goods"
        }
    ],
    "sg:phone":"+39 0472 458624",
    "sg:postcode":"39045",
    "sg:province":"Bolzano/Bozen",
    "sg:tags":[
        "cardboard"
    ],
    "wof:name":"Pretz J. Commercio Carta & Cartoni (s.a.s.) & C.",
    "wof:placetype":"venue"
},
  "geometry": {"coordinates":[11.35800457,46.4967155457],"type":"Point"}
}