{
  "type": "Feature",
  "properties": {
    "iso:country":"IT",
    "sg:address":"20010 Bareggio",
    "sg:city":"Bareggio",
    "sg:orig_category":"Servizi Di Magazzinaggio E Movimentazione",
    "sg:phone":"+39 02 9036 1441",
    "sg:postcode":"20010",
    "sg:province":"Milano",
    "wof:name":"Chemidocks (s.r.l.)",
    "wof:placetype":"venue"
},
  "geometry": {"coordinates":[9.156636,45.460545],"type":"Point"}
}