{
  "type": "Feature",
  "properties": {
    "addr:full":"60, Localita' Lamar 38100 Trento Trento Trento 38100",
    "addr:postcode":"38100;38100",
    "addr:street":"Localita ' Lamar",
    "iso:country":"IT",
    "sg:address":"60, Localita' Lamar 38100 Trento",
    "sg:city":"Trento",
    "sg:classifiers":[
        {
            "category":"Shopping",
            "type":"Retail Goods"
        }
    ],
    "sg:phone":"+39 0461 990347",
    "sg:postcode":"38100",
    "sg:province":"Trento",
    "sg:tags":[
        "finished",
        "-",
        "metallic"
    ],
    "wof:name":"Mcm (s.r.l.)",
    "wof:placetype":"venue"
},
  "geometry": {"coordinates":[11.1092357635,46.1271705627],"type":"Point"}
}