{
  "type": "Feature",
  "properties": {
    "iso:country":"IT",
    "sg:address":"Via Caprile Centro 6 44021 Codigoro",
    "sg:city":"Codigoro",
    "sg:classifiers":[
        {
            "category":"Professional",
            "type":"Services"
        }
    ],
    "sg:phone":"+39 0533 98850",
    "sg:postcode":"44021",
    "sg:province":"Ferrara",
    "sg:tags":[
        "transport"
    ],
    "wof:name":"F.lli Benazzi Srl Autotrasporti E Spedizioni",
    "wof:placetype":"venue"
},
  "geometry": {"coordinates":[11.62044,44.837894],"type":"Point"}
}