{
  "type": "Feature",
  "properties": {
    "addr:full":"10010 Torre Canavese Torre Canavese Torino 10010",
    "addr:postcode":"10010;10010",
    "iso:country":"IT",
    "sg:address":"10010 Torre Canavese",
    "sg:city":"Torre Canavese",
    "sg:orig_category":"Materiali Semilavorati Metallici",
    "sg:phone":"+39 0124 513882",
    "sg:postcode":"10010",
    "sg:province":"Torino",
    "wof:name":"Bono Roch Elvo & C.",
    "wof:placetype":"venue"
},
  "geometry": {"coordinates":[7.760944,45.393147],"type":"Point"}
}