{
  "type": "Feature",
  "properties": {
    "addr:full":"20123 Milano Milano Milano 20123",
    "addr:postcode":"20123;20123",
    "iso:country":"IT",
    "sg:address":"20123 Milano",
    "sg:city":"Milano",
    "sg:orig_category":"Calzature, Pelletterie E Pelli. Shopping",
    "sg:phone":"+39 02 8940 0234",
    "sg:postcode":"20123",
    "sg:province":"Milano",
    "wof:name":"Annalisa Pizzi Borse",
    "wof:placetype":"venue"
},
  "geometry": {"coordinates":[9.179014,45.45937],"type":"Point"}
}