{
  "type": "Feature",
  "properties": {
    "addr:full":"94010 Nissoria Nissoria Enna 94010",
    "addr:postcode":"94010;94010",
    "addr:street":"Nissoria Enna",
    "iso:country":"IT",
    "sg:address":"94010 Nissoria",
    "sg:city":"Nissoria",
    "sg:orig_category":"Bestiame - Allevamento E Commercio",
    "sg:phone":"+39 0935 660142",
    "sg:postcode":"94010",
    "sg:province":"Enna",
    "wof:name":"Planet 2000",
    "wof:placetype":"venue"
},
  "geometry": {"coordinates":[14.448416,37.656212],"type":"Point"}
}