{
  "type": "Feature",
  "properties": {
    "iso:country":"IT",
    "sg:address":"23880 Casatenovo",
    "sg:city":"Casatenovo",
    "sg:orig_category":"Arredo Bagno Ed Idrosanitari. Complementi Di Arredamento. Vetro: Prodotti E Lavorazioni",
    "sg:phone":"+39 039 920 4636",
    "sg:postcode":"23880",
    "sg:province":"Lecco",
    "wof:name":"Voleno Felice S.r.l.",
    "wof:placetype":"venue"
},
  "geometry": {"coordinates":[9.367341,45.769318],"type":"Point"}
}