{
  "type": "Feature",
  "properties": {
    "addr:full":"20146 Milano Milano Milano 20146",
    "addr:postcode":"20146;20146",
    "iso:country":"IT",
    "sg:address":"20146 Milano",
    "sg:city":"Milano",
    "sg:orig_category":"Cinematografia E Radiotelevisione",
    "sg:phone":"+39 02 428924",
    "sg:postcode":"20146",
    "sg:province":"Milano",
    "wof:name":"Veem Pictures Di Valenti Enzo E C. Sas",
    "wof:placetype":"venue"
},
  "geometry": {"coordinates":[9.153024,45.456844],"type":"Point"}
}