{
  "type": "Feature",
  "properties": {
    "iso:country":"IT",
    "sg:address":"00186 Roma",
    "sg:city":"Roma",
    "sg:orig_category":"Restauratori D'arte",
    "sg:phone":"+39 06 687 8861",
    "sg:postcode":"00186",
    "sg:province":"Roma",
    "wof:name":"A.r.p.a. Di Squadrone Dario",
    "wof:placetype":"venue"
},
  "geometry": {"coordinates":[12.476774,41.902679],"type":"Point"}
}