{
  "type": "Feature",
  "properties": {
    "addr:full":"20144 Milano Milano Milano 20144",
    "addr:postcode":"20144;20144",
    "iso:country":"IT",
    "sg:address":"20144 Milano",
    "sg:city":"Milano",
    "sg:orig_category":"Petroli, Gas E Combustibili",
    "sg:phone":"+39 02 462541",
    "sg:postcode":"20144",
    "sg:province":"Milano",
    "wof:name":"Grandi Reti Societa' Consortile S.r.l.",
    "wof:placetype":"venue"
},
  "geometry": {"coordinates":[9.1572666168,45.4657592773],"type":"Point"}
}