{
  "type": "Feature",
  "properties": {
    "iso:country":"IT",
    "sg:address":"10135 Torino",
    "sg:city":"Torino",
    "sg:orig_category":"Materiali E Componenti Elettrotecnici",
    "sg:phone":"+39 011 341241",
    "sg:postcode":"10135",
    "sg:province":"Torino",
    "wof:name":"A.e.c. S.r.l.",
    "wof:placetype":"venue"
},
  "geometry": {"coordinates":[7.624039,45.021557],"type":"Point"}
}