{
  "type": "Feature",
  "properties": {
    "addr:full":"95037 San Giovanni La Punta San Giovanni la Punta Catania 95037",
    "addr:housenumber":"95037",
    "addr:postcode":"95037",
    "iso:country":"IT",
    "sg:address":"95037 San Giovanni La Punta",
    "sg:city":"San Giovanni la Punta",
    "sg:orig_category":"Agenzie D'affari E Servizi Commerciali. Servizi Per Aziende, Manifestazioni E Supporto Agli Scambi Commerciali",
    "sg:phone":"+39 095 741 0476",
    "sg:postcode":"95037",
    "sg:province":"Catania",
    "wof:name":"Puglisi Rag. Marcello",
    "wof:placetype":"venue"
},
  "geometry": {"coordinates":[15.094178,37.579422],"type":"Point"}
}