{
  "type": "Feature",
  "properties": {
    "iso:country":"IT",
    "sg:address":"16030 Avegno",
    "sg:city":"Avegno",
    "sg:orig_category":"Carni, Salumi E Pesci",
    "sg:phone":"+39 0185 79043",
    "sg:postcode":"16030",
    "sg:province":"Genova",
    "sg:website":"http://www.lariunione.it",
    "wof:name":"Riunione Industrie Alimentari Srl",
    "wof:placetype":"venue"
},
  "geometry": {"coordinates":[9.1637,44.388237],"type":"Point"}
}