{
  "type": "Feature",
  "properties": {
    "iso:country":"IT",
    "sg:address":"20098 San Giuliano Milanese",
    "sg:city":"San Giuliano Milanese",
    "sg:orig_category":"Abbigliamento Industria - Macchine Ed Attrezzature",
    "sg:phone":"+39 02 9824 1757",
    "sg:postcode":"20098",
    "sg:province":"Milano",
    "sg:website":"http://www.atecon-it.com",
    "wof:name":"Atecon Srl",
    "wof:placetype":"venue"
},
  "geometry": {"coordinates":[9.299162,45.391972],"type":"Point"}
}