{
  "type": "Feature",
  "properties": {
    "addr:full":"46040 Monzambano Monzambano Mantova 46040",
    "addr:postcode":"46040;46040",
    "iso:country":"IT",
    "sg:address":"46040 Monzambano",
    "sg:city":"Monzambano",
    "sg:orig_category":"Bevande, Vini E Liquori. Servizi E Lavori Per Industria Alimentare E Bevande",
    "sg:phone":"+39 0376 800020",
    "sg:postcode":"46040",
    "sg:province":"Mantova",
    "wof:name":"Distilleria Gobetti A.",
    "wof:placetype":"venue"
},
  "geometry": {"coordinates":[10.692822,45.385788],"type":"Point"}
}