{
  "type": "Feature",
  "properties": {
    "iso:country":"IT",
    "sg:address":"70022 Altamura",
    "sg:city":"Altamura",
    "sg:orig_category":"Prodotti Chimici Secondari",
    "sg:phone":"+39 080 311 1842",
    "sg:postcode":"70022",
    "sg:province":"Bari",
    "wof:name":"C.e.a. (s.n.c.)",
    "wof:placetype":"venue"
},
  "geometry": {"coordinates":[16.5552635193,40.8214950562],"type":"Point"}
}