{
  "type": "Feature",
  "properties": {
    "addr:full":"Via Marconi 90/94; Calusco D'adda; 24033 Bergamo 24033",
    "addr:housenumber":"90 / 94",
    "addr:postcode":"24033;24033",
    "addr:street":"Via Marconi",
    "iso:country":"IT",
    "sg:address":"Via Marconi 90/94; Calusco D'adda; 24033",
    "sg:classifiers":[
        {
            "category":"Banks & Credit Unions",
            "subcategory":"Bank",
            "type":"Services"
        }
    ],
    "sg:phone":"+39 035 797210",
    "sg:postcode":"24033",
    "sg:province":"Bergamo",
    "wof:name":"Credito Bergamasco Spa",
    "wof:placetype":"venue"
},
  "geometry": {"coordinates":[9.475865,45.690697],"type":"Point"}
}