{
  "type": "Feature",
  "properties": {
    "addr:full":"1, Zona Industriale 66054 Vasto Vasto Chieti 66054",
    "addr:housenumber":"1",
    "addr:postcode":"66054;66054",
    "addr:street":"Zona Industriale",
    "iso:country":"IT",
    "sg:address":"1, Zona Industriale 66054 Vasto",
    "sg:city":"Vasto",
    "sg:classifiers":[
        {
            "category":"Shopping",
            "type":"Retail Goods"
        }
    ],
    "sg:phone":"+39 0873 310497",
    "sg:postcode":"66054",
    "sg:province":"Chieti",
    "sg:tags":[
        "finished",
        "-",
        "metallic"
    ],
    "wof:name":"Tecnometal S.r.l.",
    "wof:placetype":"venue"
},
  "geometry": {"coordinates":[14.1671514511,42.3517913818],"type":"Point"}
}