{
  "type": "Feature",
  "properties": {
    "iso:country":"IT",
    "sg:address":"Via Nocolo Girardengo 26; Novi Ligure; 15067",
    "sg:city":"Novi Ligure",
    "sg:classifiers":[
        {
            "category":"Banks & Credit Unions",
            "subcategory":"Bank",
            "type":"Services"
        }
    ],
    "sg:phone":"+39 0143 334411",
    "sg:postcode":"15067",
    "sg:province":"Alessandria",
    "wof:name":"Credito Italiano Spa",
    "wof:placetype":"venue"
},
  "geometry": {"coordinates":[8.798325,44.75425],"type":"Point"}
}