{
  "type": "Feature",
  "properties": {
    "iso:country":"IT",
    "sg:address":"Via San Rocco 10 46040 Casalromano",
    "sg:city":"Casalromano",
    "sg:classifiers":[
        {
            "category":"Home & Garden",
            "subcategory":"Hardware",
            "type":"Retail Goods"
        }
    ],
    "sg:phone":"+39 0376 76009",
    "sg:postcode":"46040",
    "sg:province":"Mantova",
    "sg:tags":[
        "lawn",
        "pumps",
        "irrigation",
        "pump"
    ],
    "sg:website":"www.volpioriginale.it",
    "wof:name":"Davide E Luigi Volpi Spa",
    "wof:placetype":"venue"
},
  "geometry": {"coordinates":[10.370083,45.199627],"type":"Point"}
}