{
  "type": "Feature",
  "properties": {
    "addr:full":"95, Via Umberto I 35020 Arzergrande Arzergrande Padova 35020",
    "addr:postcode":"35020;35020",
    "addr:street":"Via Umberto I",
    "iso:country":"IT",
    "sg:address":"95, Via Umberto I 35020 Arzergrande",
    "sg:city":"Arzergrande",
    "sg:classifiers":[
        {
            "category":"Manufacturing",
            "subcategory":"Paper Products",
            "type":"Manufacturing & Wholesale Goods"
        }
    ],
    "sg:phone":"+39 049 580 0133",
    "sg:postcode":"35020",
    "sg:province":"Padova",
    "sg:tags":[
        "cardboard"
    ],
    "wof:name":"Scatolificio Bozzato (s.r.l.)",
    "wof:placetype":"venue"
},
  "geometry": {"coordinates":[11.8765888214,45.4095687866],"type":"Point"}
}