{
  "type": "Feature",
  "properties": {
    "iso:country":"IT",
    "sg:address":"41100 Modena",
    "sg:city":"Modena",
    "sg:orig_category":"Abbigliamento Esterno, Maglierie E Pelliccerie. Forniture Per Il Settore Dello Spettacolo",
    "sg:phone":"+39 059 243599",
    "sg:postcode":"41100",
    "sg:province":"Modena",
    "wof:name":"Incerti Medici Mara",
    "wof:placetype":"venue"
},
  "geometry": {"coordinates":[10.922409,44.646904],"type":"Point"}
}