{
  "type": "Feature",
  "properties": {
    "addr:full":"Via Rossi I Trav 34; Volla",
    "addr:housenumber":"34",
    "addr:street":"Via Rossi I Trav",
    "iso:country":"IT",
    "sg:address":"Via Rossi I Trav 34; Volla",
    "sg:classifiers":[
        {
            "category":"Banks & Credit Unions",
            "subcategory":"Bank",
            "type":"Services"
        }
    ],
    "sg:phone":"+39 081 773 4988",
    "wof:name":"Banca Della Provincia, Di Napoli",
    "wof:placetype":"venue"
},
  "geometry": {"coordinates":[14.343925,40.879555],"type":"Point"}
}