{
  "type": "Feature",
  "properties": {
    "addr:full":"Via Delle Fontane, 4/6 10080 Baldissero Canavese Baldissero Canavese Torino 10080",
    "addr:housenumber":"4 / 6",
    "addr:postcode":"10080;10080",
    "addr:street":"Via Delle Fontane;Canavese",
    "iso:country":"IT",
    "sg:address":"Via Delle Fontane, 4/6 10080 Baldissero Canavese",
    "sg:city":"Baldissero Canavese",
    "sg:classifiers":[
        {
            "category":"Shopping",
            "subcategory":"Clothing, Apparel, & Fashions",
            "type":"Retail Goods"
        }
    ],
    "sg:phone":"+39 0124 510007",
    "sg:postcode":"10080",
    "sg:province":"Torino",
    "sg:tags":[
        "children's",
        "clothing"
    ],
    "sg:website":"www.bombboogie.com",
    "wof:name":"Space 2000 Spa",
    "wof:placetype":"venue"
},
  "geometry": {"coordinates":[7.686619,45.07056],"type":"Point"}
}