{
  "type": "Feature",
  "properties": {
    "addr:full":"81011 Alife Alife Caserta 81011",
    "addr:postcode":"81011;81011",
    "iso:country":"IT",
    "sg:address":"81011 Alife",
    "sg:city":"Alife",
    "sg:orig_category":"Prodotti Cosmetici E Da Toeletta. Forniture Per Attivita' Industriali",
    "sg:phone":"+39 0823 783474",
    "sg:postcode":"81011",
    "sg:province":"Caserta",
    "wof:name":"Nucci Addolorata",
    "wof:placetype":"venue"
},
  "geometry": {"coordinates":[14.3369569778,41.3305244446],"type":"Point"}
}