{
  "type": "Feature",
  "properties": {
    "iso:country":"IT",
    "sg:address":"36072 Chiampo",
    "sg:city":"Chiampo",
    "sg:orig_category":"Abbigliamento Esterno, Maglierie E Pelliccerie. Calzature, Pelletterie E Pelli",
    "sg:phone":"+39 0444 420800",
    "sg:postcode":"36072",
    "sg:province":"Vicenza",
    "sg:website":"http://www.conceriatolio.com",
    "wof:name":"Conceria Tolio Spa",
    "wof:placetype":"venue"
},
  "geometry": {"coordinates":[11.344989,45.517727],"type":"Point"}
}