{
  "type": "Feature",
  "properties": {
    "iso:country":"IT",
    "sg:address":"21040 Origgio",
    "sg:city":"Origgio",
    "sg:orig_category":"Trattamenti Termici E Superficiali Metalli, Galvanotecnica",
    "sg:phone":"+39 02 9673 4029",
    "sg:postcode":"21040",
    "sg:province":"Varese",
    "wof:name":"Lagef (s.a.s.)",
    "wof:placetype":"venue"
},
  "geometry": {"coordinates":[9.025958,45.595158],"type":"Point"}
}