{
  "type": "Feature",
  "properties": {
    "addr:full":"71, V. Roma 26010 Ripalta Cremasca Ripalta Cremasca Cremona 26010",
    "addr:housenumber":"71",
    "addr:postcode":"26010;cremasca;26010",
    "addr:street":"V. Roma",
    "iso:country":"IT",
    "sg:address":"71, V. Roma 26010 Ripalta Cremasca",
    "sg:city":"Ripalta Cremasca",
    "sg:classifiers":[
        {
            "category":"Wholesale",
            "subcategory":"Drugs",
            "type":"Manufacturing & Wholesale Goods"
        }
    ],
    "sg:phone":"+39 39037368112",
    "sg:postcode":"26010",
    "sg:province":"Cremona",
    "sg:tags":[
        "chemical",
        "pharmaceutical"
    ],
    "wof:name":"Dumax Srl",
    "wof:placetype":"venue"
},
  "geometry": {"coordinates":[9.699594,45.321785],"type":"Point"}
}