{
  "type": "Feature",
  "properties": {
    "iso:country":"IT",
    "sg:address":"3, Via Tavazzano 26855 Lodi Vecchio",
    "sg:city":"Lodi Vecchio",
    "sg:classifiers":[
        {
            "category":"Manufacturing",
            "subcategory":"Food",
            "type":"Manufacturing & Wholesale Goods"
        }
    ],
    "sg:phone":"+39 0371 752563",
    "sg:postcode":"26855",
    "sg:province":"Lodi",
    "sg:tags":[
        "equipment",
        "processing",
        "-",
        "machinery"
    ],
    "wof:name":"Curti Srl",
    "wof:placetype":"venue"
},
  "geometry": {"coordinates":[9.4011335373,45.3325767517],"type":"Point"}
}