{
  "type": "Feature",
  "properties": {
    "iso:country":"IT",
    "sg:address":"06034 Foligno",
    "sg:city":"Fiamenga",
    "sg:classifiers":[
        {
            "category":"Manufacturing",
            "subcategory":"Motor Vehicles & Parts",
            "type":"Manufacturing & Wholesale Goods"
        }
    ],
    "sg:phone":"+39 0742 320651",
    "sg:postcode":"06034",
    "sg:province":"Perugia",
    "sg:tags":[
        "vehicles",
        "accessory"
    ],
    "wof:name":"Martelli Auto Di Martelli Giorgio & C. Snc",
    "wof:placetype":"venue"
},
  "geometry": {"coordinates":[12.6635541916,42.9539070129],"type":"Point"}
}