{
  "type": "Feature",
  "properties": {
    "iso:country":"IT",
    "sg:address":"Via Stefanardo Da Vimercate 23 20128 Milano",
    "sg:city":"Milano",
    "sg:classifiers":[
        {
            "category":"Manufacturing",
            "subcategory":"Metals",
            "type":"Manufacturing & Wholesale Goods"
        }
    ],
    "sg:phone":"+39 02 257 5375",
    "sg:postcode":"20128",
    "sg:province":"Milano",
    "sg:tags":[
        "used",
        "sheet",
        "working",
        "machines"
    ],
    "wof:name":"Comal Srl",
    "wof:placetype":"venue"
},
  "geometry": {"coordinates":[9.228142,45.506729],"type":"Point"}
}