{
  "type": "Feature",
  "properties": {
    "addr:full":"20145 Milano Milano Milano 20145",
    "addr:postcode":"20145;20145",
    "iso:country":"IT",
    "sg:address":"20145 Milano",
    "sg:city":"Milano",
    "sg:orig_category":"Professionisti - Studi E Servizi Ed Associazioni Di Interesse Aziendale. Associazioni Ed Organismi Di Interesse Pubblico",
    "sg:phone":"+39 02 498 9361",
    "sg:postcode":"20145",
    "sg:province":"Milano",
    "wof:name":"Centre Europeen D'arbitrage",
    "wof:placetype":"venue"
},
  "geometry": {"coordinates":[9.1594676971,45.4743118286],"type":"Point"}
}