{
  "type": "Feature",
  "properties": {
    "iso:country":"IT",
    "sg:address":"23, Via Locatelli Antonio 24022 Alzano Lombardo",
    "sg:city":"Alzano Lombardo",
    "sg:classifiers":[
        {
            "category":"Shopping",
            "subcategory":"Clothing, Apparel, & Fashions",
            "type":"Retail Goods"
        }
    ],
    "sg:phone":"+39 39035515401",
    "sg:postcode":"24022",
    "sg:province":"Bergamo",
    "sg:tags":[
        "clothes"
    ],
    "wof:name":"Pesenti Gloria",
    "wof:placetype":"venue"
},
  "geometry": {"coordinates":[9.728395,45.732979],"type":"Point"}
}