{
  "type": "Feature",
  "properties": {
    "iso:country":"IT",
    "sg:address":"00184 Roma",
    "sg:city":"Roma",
    "sg:orig_category":"Banche E Servizi Finanziari",
    "sg:phone":"+39 06 482 5356",
    "sg:postcode":"00184",
    "sg:province":"Roma",
    "wof:name":"Incafin Italiana Srl Monte Di Pieta'",
    "wof:placetype":"venue"
},
  "geometry": {"coordinates":[12.498258,41.889187],"type":"Point"}
}