{
  "type": "Feature",
  "properties": {
    "iso:country":"IT",
    "sg:address":"Via Catullo Valerio 18 37121 Verona",
    "sg:city":"Verona",
    "sg:classifiers":[
        {
            "category":"Food & Beverages",
            "subcategory":"Meat & Fish",
            "type":"Retail Goods"
        }
    ],
    "sg:phone":"+39 045 800 0411",
    "sg:postcode":"37121",
    "sg:province":"Verona",
    "sg:tags":[
        "sausage"
    ],
    "sg:website":"www.adamiexport.com",
    "wof:name":"Adami Export Management Srl",
    "wof:placetype":"venue"
},
  "geometry": {"coordinates":[10.991748,45.438366],"type":"Point"}
}