{
  "type": "Feature",
  "properties": {
    "iso:country":"IT",
    "sg:address":"24068 Seriate",
    "sg:city":"Seriate",
    "sg:orig_category":"Impianti, Attrezzature E Forniture Sanitarie Ed Ospedaliere",
    "sg:phone":"+39 035 269459",
    "sg:postcode":"24068",
    "sg:province":"Bergamo",
    "sg:website":"http://www.orobicadivari.it",
    "wof:name":"Orobica Di Vari Srl",
    "wof:placetype":"venue"
},
  "geometry": {"coordinates":[9.744165,45.669025],"type":"Point"}
}