{
  "type": "Feature",
  "properties": {
    "iso:country":"IT",
    "sg:address":"44, Zona Artigianale 39040 Varna",
    "sg:city":"Varna",
    "sg:classifiers":[
        {
            "category":"Professional",
            "subcategory":"Engineering",
            "type":"Services"
        }
    ],
    "sg:phone":"+39 0472 835190",
    "sg:postcode":"39040",
    "sg:province":"Bolzano/Bozen",
    "sg:tags":[
        "machine",
        "-",
        "mechanical"
    ],
    "wof:name":"Grass R.w. (s.r.l.)",
    "wof:placetype":"venue"
},
  "geometry": {"coordinates":[11.652039,46.732529],"type":"Point"}
}