{
  "type": "Feature",
  "properties": {
    "iso:country":"IT",
    "sg:address":"36071 Arzignano",
    "sg:city":"Arzignano",
    "sg:orig_category":"Servizi E Lavori Per Ecologia E Smaltimento Rifiuti. Ospedali E Servizi Sanitari. Servizi Ausiliari Di Analisi, Controllo E Ricerca",
    "sg:phone":"+39 0444 452022",
    "sg:postcode":"36071",
    "sg:province":"Vicenza",
    "wof:name":"Analytical Sas",
    "wof:placetype":"venue"
},
  "geometry": {"coordinates":[11.514715,45.5308],"type":"Point"}
}