{
  "type": "Feature",
  "properties": {
    "iso:country":"IT",
    "sg:address":"35, Via Filottrano 60027 Osimo",
    "sg:city":"Osimo",
    "sg:classifiers":[
        {
            "category":"Shopping",
            "subcategory":"Jewelry",
            "type":"Retail Goods"
        }
    ],
    "sg:phone":"+39 071 723 1349",
    "sg:postcode":"60027",
    "sg:province":"Ancona",
    "sg:tags":[
        "jewellery"
    ],
    "wof:name":"T.s.g.srl",
    "wof:placetype":"venue"
},
  "geometry": {"coordinates":[13.435404,43.461887],"type":"Point"}
}