{
  "type": "Feature",
  "properties": {
    "addr:full":"19, Via Andorra 35127 Padova Padova Padova 35127",
    "addr:postcode":"35127;35127",
    "addr:street":"Via Andorra",
    "iso:country":"IT",
    "sg:address":"19, Via Andorra 35127 Padova",
    "sg:city":"Padova",
    "sg:classifiers":[
        {
            "category":"Manufacturing",
            "subcategory":"Rubber & Plastics",
            "type":"Manufacturing & Wholesale Goods"
        }
    ],
    "sg:phone":"+39 049 870 2088",
    "sg:postcode":"35127",
    "sg:province":"Padova",
    "wof:name":"P.m.s. & D. - Plano Manufacturing Sales And Distribution (s.r.l.)",
    "wof:placetype":"venue"
},
  "geometry": {"coordinates":[11.8441667557,45.3974990845],"type":"Point"}
}