{
  "type": "Feature",
  "properties": {
    "iso:country":"IT",
    "sg:address":"23873 Missaglia",
    "sg:city":"Missaglia",
    "sg:orig_category":"Termotecnica E Riscaldamento, Apparecchiature E Servizi",
    "sg:phone":"+39 039 927 9312",
    "sg:postcode":"23873",
    "sg:province":"Lecco",
    "wof:name":"Si.co.tec. Di Gallo Vincenzo",
    "wof:placetype":"venue"
},
  "geometry": {"coordinates":[9.347558,45.697399],"type":"Point"}
}