{
  "type": "Feature",
  "properties": {
    "iso:country":"IT",
    "sg:address":"70, Strada St. Laghi Di Avigliana 12022 Busca",
    "sg:city":"Busca",
    "sg:classifiers":[
        {
            "category":"Wholesale",
            "subcategory":"Machinery & Supplies",
            "type":"Manufacturing & Wholesale Goods"
        }
    ],
    "sg:phone":"+39 0171 946736",
    "sg:postcode":"12022",
    "sg:province":"Cuneo",
    "sg:tags":[
        "-",
        "agriculture",
        "equipment"
    ],
    "wof:name":"Cta Agri S.r.l.",
    "wof:placetype":"venue"
},
  "geometry": {"coordinates":[7.547111,44.388798],"type":"Point"}
}