{
  "type": "Feature",
  "properties": {
    "addr:full":"21/23, Via Longo Luigi 50019 Sesto Fiorentino Sesto Fiorentino Firenze 50019",
    "addr:housenumber":"21 / 23",
    "addr:postcode":"50019;50019",
    "addr:street":"Via Longo Luigi",
    "iso:country":"IT",
    "sg:address":"21/23, Via Longo Luigi 50019 Sesto Fiorentino",
    "sg:city":"Sesto Fiorentino",
    "sg:classifiers":[
        {
            "category":"Professional",
            "subcategory":"Engineering",
            "type":"Services"
        }
    ],
    "sg:phone":"+39 055 420 7372",
    "sg:postcode":"50019",
    "sg:province":"Firenze",
    "sg:tags":[
        "machine",
        "-",
        "mechanical"
    ],
    "wof:name":"Ecotechnics Spa",
    "wof:placetype":"venue"
},
  "geometry": {"coordinates":[11.17521,43.841473],"type":"Point"}
}