{
  "type": "Feature",
  "properties": {
    "iso:country":"IT",
    "sg:address":"56125 Pisa",
    "sg:city":"Pisa",
    "sg:orig_category":"Pubblicita', Marketing E Comunicazione",
    "sg:phone":"+39 050 220 5000",
    "sg:postcode":"56125",
    "sg:province":"Pisa",
    "wof:name":"Nuova Versilia Blu",
    "wof:placetype":"venue"
},
  "geometry": {"coordinates":[10.4022045135,43.7087669373],"type":"Point"}
}