{
  "type": "Feature",
  "properties": {
    "iso:country":"IT",
    "sg:address":"20121 Milano",
    "sg:city":"Milano",
    "sg:orig_category":"Servizi Editoriali. Shopping",
    "sg:phone":"+39 02 864871",
    "sg:postcode":"20121",
    "sg:province":"Milano",
    "sg:website":"http://www.hoepli.it",
    "wof:name":"Hoepli Ulrico Spa",
    "wof:placetype":"venue"
},
  "geometry": {"coordinates":[9.192515,45.466446],"type":"Point"}
}