{
  "type": "Feature",
  "properties": {
    "iso:country":"IT",
    "sg:address":"2, Via Roma 38038 Tesero",
    "sg:city":"Tesero",
    "sg:classifiers":[
        {
            "category":"Sports & Exercise",
            "subcategory":"Playing Field",
            "type":"Entertainment"
        }
    ],
    "sg:phone":"+39 0462 813051",
    "sg:postcode":"38038",
    "sg:province":"Trento",
    "sg:tags":[
        "game"
    ],
    "wof:name":"Frade S.r.l.",
    "wof:placetype":"venue"
},
  "geometry": {"coordinates":[11.503604,46.289162],"type":"Point"}
}