{
  "type": "Feature",
  "properties": {
    "iso:country":"IT",
    "sg:address":"36015 Schio",
    "sg:city":"Schio",
    "sg:classifiers":[
        {
            "category":"Manufacturing",
            "subcategory":"Tools & Machinery",
            "type":"Manufacturing & Wholesale Goods"
        }
    ],
    "sg:phone":"+39 0445 575180",
    "sg:postcode":"36015",
    "sg:province":"Vicenza",
    "sg:tags":[
        "leather",
        "equipment",
        "goods",
        "clothing"
    ],
    "wof:name":"Triveneta Grandi Impianti Srl",
    "wof:placetype":"venue"
},
  "geometry": {"coordinates":[11.3917837143,45.7219276428],"type":"Point"}
}