{
  "type": "Feature",
  "properties": {
    "iso:country":"IT",
    "sg:address":"Via Basilicata 5 63018 Porto Sant'elpidio",
    "sg:orig_category":"Ladies' Shoes",
    "sg:phone":"+39 0734 993256",
    "sg:postcode":"63018",
    "sg:province":"Ascoli Piceno",
    "wof:name":"Calzaturificio Giorgio Pacini Snc",
    "wof:placetype":"venue"
},
  "geometry": {"coordinates":[13.754355,43.26458],"type":"Point"}
}