{
  "type": "Feature",
  "properties": {
    "iso:country":"IT",
    "sg:address":"48100 Ravenna",
    "sg:city":"Fornace zarattini",
    "sg:orig_category":"Apparecchiature Ed Attrezzature Meccaniche",
    "sg:phone":"+39 0544 465616",
    "sg:postcode":"48100",
    "sg:province":"Ravenna",
    "wof:name":"Menotti Poverini Srl",
    "wof:placetype":"venue"
},
  "geometry": {"coordinates":[12.152362,44.418575],"type":"Point"}
}