{
  "type": "Feature",
  "properties": {
    "addr:full":"60127 Ancona Ancona Ancona 60127",
    "addr:postcode":"60127;60127",
    "iso:country":"IT",
    "sg:address":"60127 Ancona",
    "sg:city":"Ancona",
    "sg:orig_category":"Forniture Per Abbigliamento E Pelletterie",
    "sg:phone":"+39 071 280 1222",
    "sg:postcode":"60127",
    "sg:province":"Ancona",
    "sg:website":"http://www.giolito.it",
    "wof:name":"Giolito Francesco Sas Di Giolito Angelo & C.",
    "wof:placetype":"venue"
},
  "geometry": {"coordinates":[13.0656299591,43.4422035217],"type":"Point"}
}