{
  "type": "Feature",
  "properties": {
    "iso:country":"IT",
    "sg:address":"17/c, Via Stelloni 40010 Sala Bolognese",
    "sg:city":"Sala Bolognese",
    "sg:classifiers":[
        {
            "category":"Manufacturing",
            "subcategory":"Rubber & Plastics",
            "type":"Manufacturing & Wholesale Goods"
        }
    ],
    "sg:phone":"+39 051 681 4614",
    "sg:postcode":"40010",
    "sg:province":"Bologna",
    "wof:name":"Vettaflex (s.r.l.)",
    "wof:placetype":"venue"
},
  "geometry": {"coordinates":[11.2682304382,44.5751495361],"type":"Point"}
}