{
  "type": "Feature",
  "properties": {
    "iso:country":"IT",
    "sg:address":"4, Via Clivio 21036 Gemonio",
    "sg:city":"Gemonio",
    "sg:classifiers":[
        {
            "category":"Home & Garden",
            "subcategory":"Home Furnishings",
            "type":"Retail Goods"
        }
    ],
    "sg:phone":"+39 0332 602590",
    "sg:postcode":"21036",
    "sg:province":"Varese",
    "sg:tags":[
        "household"
    ],
    "wof:name":"Mattioni S.r.l.",
    "wof:placetype":"venue"
},
  "geometry": {"coordinates":[8.673415,45.872677],"type":"Point"}
}