{
  "type": "Feature",
  "properties": {
    "addr:full":"09033 Decimomannu Decimomannu Cagliari 09033",
    "addr:postcode":"09033;09033",
    "iso:country":"IT",
    "sg:address":"09033 Decimomannu",
    "sg:city":"Decimomannu",
    "sg:orig_category":"Apparecchiature E Sistemi Per Magazzinaggio E Movimentazione",
    "sg:phone":"+39 070 966 3065",
    "sg:postcode":"09033",
    "sg:province":"Cagliari",
    "wof:name":"C.f. Service S.r.l.",
    "wof:placetype":"venue"
},
  "geometry": {"coordinates":[8.999045,39.294796],"type":"Point"}
}