{
  "type": "Feature",
  "properties": {
    "iso:country":"IT",
    "sg:address":"2, Viale Ferdinando Di Savoia 20124 Milano",
    "sg:city":"Milano",
    "sg:classifiers":[
        {
            "category":"Wholesale",
            "subcategory":"Drugs",
            "type":"Manufacturing & Wholesale Goods"
        }
    ],
    "sg:phone":"+39 02 6671 0156",
    "sg:postcode":"20124",
    "sg:province":"Milano",
    "sg:tags":[
        "chemical",
        "pharmaceutical"
    ],
    "wof:name":"Gicar Spa",
    "wof:placetype":"venue"
},
  "geometry": {"coordinates":[9.198113,45.480686],"type":"Point"}
}