{
  "type": "Feature",
  "properties": {
    "addr:full":"70031 Andria Andria Bari 70031",
    "addr:housenumber":"70031",
    "addr:postcode":"70031",
    "iso:country":"IT",
    "sg:address":"70031 Andria",
    "sg:city":"Andria",
    "sg:orig_category":"Forniture Per Abbigliamento E Pelletterie",
    "sg:phone":"+39 0883 552270",
    "sg:postcode":"70031",
    "sg:province":"Bari",
    "wof:name":"Il Bottonificio Meridionale Di Fortunato Mosca & C. Snc",
    "wof:placetype":"venue"
},
  "geometry": {"coordinates":[16.2972545624,41.2314376831],"type":"Point"}
}