{
  "type": "Feature",
  "properties": {
    "iso:country":"IT",
    "sg:address":"20127 Milano",
    "sg:city":"Milano",
    "sg:orig_category":"Metalli E Leghe",
    "sg:phone":"+39 02 259 0889",
    "sg:postcode":"20127",
    "sg:province":"Milano",
    "wof:name":"Costanzo Nino",
    "wof:placetype":"venue"
},
  "geometry": {"coordinates":[9.2422628403,45.5068893433],"type":"Point"}
}