{
  "type": "Feature",
  "properties": {
    "addr:full":"16147 Genova Genova Genova 16147",
    "addr:postcode":"16147;16147",
    "iso:country":"IT",
    "sg:address":"16147 Genova",
    "sg:city":"Genova",
    "sg:orig_category":"Musica. Shopping",
    "sg:phone":"+39 010 391226",
    "sg:postcode":"16147",
    "sg:province":"Genova",
    "sg:website":"http://www.utenti.tripod.it/spacemusic",
    "wof:name":"Space Music",
    "wof:placetype":"venue"
},
  "geometry": {"coordinates":[8.9894132614,44.3946800232],"type":"Point"}
}