{
  "type": "Feature",
  "properties": {
    "iso:country":"IT",
    "sg:address":"7, Via Canneto 25134 Brescia",
    "sg:city":"Brescia",
    "sg:classifiers":[
        {
            "category":"Manufacturing",
            "subcategory":"Metals",
            "type":"Manufacturing & Wholesale Goods"
        }
    ],
    "sg:phone":"+39 030 230 0496",
    "sg:postcode":"25134",
    "sg:province":"Brescia",
    "sg:tags":[
        "metallurgy",
        "metalworking"
    ],
    "wof:name":"Officina Del Molino (s.r.l.)",
    "wof:placetype":"venue"
},
  "geometry": {"coordinates":[10.2727441788,45.4956703186],"type":"Point"}
}