{
  "type": "Feature",
  "properties": {
    "addr:full":"6, Via Portogallo 47900 Rimini Rimini Rimini 47900",
    "addr:postcode":"47900;47900",
    "addr:street":"Via Portogallo",
    "iso:country":"IT",
    "sg:address":"6, Via Portogallo 47900 Rimini",
    "sg:city":"Rimini",
    "sg:classifiers":[
        {
            "category":"Shopping",
            "subcategory":"Clothing, Apparel, & Fashions",
            "type":"Retail Goods"
        }
    ],
    "sg:phone":"+39 0541 740192",
    "sg:postcode":"47900",
    "sg:province":"Rimini",
    "sg:tags":[
        "clothes"
    ],
    "wof:name":"Mei Confezioni (s.n.c.)",
    "wof:placetype":"venue"
},
  "geometry": {"coordinates":[12.532481,44.063599],"type":"Point"}
}