{
  "type": "Feature",
  "properties": {
    "iso:country":"IT",
    "sg:address":"00137 Roma",
    "sg:city":"Roma",
    "sg:orig_category":"Ristorazione E Locali Pubblici Affini. Ristoranti Ed Esercizi Affini. Servizi Ausiliari Di Ristorazione E Di Intrattenimento",
    "sg:phone":"+39 06 827 2672",
    "sg:postcode":"00137",
    "sg:province":"Roma",
    "wof:name":"Cosmos Tennis Club",
    "wof:placetype":"venue"
},
  "geometry": {"coordinates":[12.523556,41.932568],"type":"Point"}
}