{
  "type": "Feature",
  "properties": {
    "iso:country":"IT",
    "sg:address":"Via Tripoli 24 20035 Lissone",
    "sg:city":"Lissone",
    "sg:classifiers":[
        {
            "category":"Government",
            "subcategory":"Court House",
            "type":"Public Place"
        }
    ],
    "sg:phone":"+39 039 461213",
    "sg:postcode":"20035",
    "sg:province":"Milano",
    "sg:tags":[
        "accommodation",
        "furniture"
    ],
    "sg:website":"www.anacletomariani.it",
    "wof:name":"Anacleto Mariani Srl",
    "wof:placetype":"venue"
},
  "geometry": {"coordinates":[9.232413,45.612659],"type":"Point"}
}