{
  "type": "Feature",
  "properties": {
    "iso:country":"IT",
    "sg:address":"57038 Rio Marina",
    "sg:city":"Cavo",
    "sg:orig_category":"Ospedali E Servizi Sanitari",
    "sg:phone":"+39 0565 949994",
    "sg:postcode":"57038",
    "sg:province":"Livorno",
    "wof:name":"Misericordia Servizio Ambulanze",
    "wof:placetype":"venue"
},
  "geometry": {"coordinates":[10.418503,42.859009],"type":"Point"}
}