{
  "type": "Feature",
  "properties": {
    "iso:country":"IT",
    "sg:address":"Via Tavernanova 80036 Palma Campania",
    "sg:city":"Palma Campania",
    "sg:classifiers":[
        {
            "category":"Wholesale",
            "subcategory":"Drugs",
            "type":"Manufacturing & Wholesale Goods"
        }
    ],
    "sg:phone":"+39 081 510 1009",
    "sg:postcode":"80036",
    "sg:province":"Napoli",
    "sg:tags":[
        "chemical",
        "pharmaceutical"
    ],
    "wof:name":"Lincar - Gas (s.r.l.)",
    "wof:placetype":"venue"
},
  "geometry": {"coordinates":[14.550379,40.827415],"type":"Point"}
}