{
  "type": "Feature",
  "properties": {
    "addr:full":"38, Via Acquicella Porto 95121 Catania Catania Catania 95121",
    "addr:postcode":"95121;95121",
    "addr:street":"Via Acquicella Porto",
    "iso:country":"IT",
    "sg:address":"38, Via Acquicella Porto 95121 Catania",
    "sg:city":"Catania",
    "sg:classifiers":[
        {
            "category":"Parking",
            "subcategory":"Lot",
            "type":"Transportation"
        }
    ],
    "sg:phone":"+39 39095346511",
    "sg:postcode":"95121",
    "sg:province":"Catania",
    "sg:tags":[
        "transport",
        "road"
    ],
    "wof:name":"Crisafulli Express Srl",
    "wof:placetype":"venue"
},
  "geometry": {"coordinates":[15.075818,37.490402],"type":"Point"}
}