{
  "type": "Feature",
  "properties": {
    "iso:country":"IT",
    "sg:address":"06087 Ponte San Giovanni",
    "sg:orig_category":"Prodotti E Manufatti In Gomma. Servizi E Lavori Industria Della Gomma. Ricambi E Componenti Dei Mezzi Di Trasporto",
    "sg:phone":"+39 075 393665",
    "sg:province":"PG",
    "wof:name":"Pneuservice 90 Spa",
    "wof:placetype":"venue"
},
  "geometry": {"coordinates":[-72.8869018555,41.757598877],"type":"Point"}
}