{
  "type": "Feature",
  "properties": {
    "addr:full":"2, Lungo Mare Matteotti 04019 Terracina Terracina Latina 04019",
    "addr:housenumber":"2",
    "addr:postcode":"04019;04019",
    "addr:street":"Lungo Mare Matteotti",
    "iso:country":"IT",
    "sg:address":"2, Lungo Mare Matteotti 04019 Terracina",
    "sg:city":"Terracina",
    "sg:classifiers":[
        {
            "category":"Travel",
            "subcategory":"Travel Agent",
            "type":"Entertainment"
        }
    ],
    "sg:phone":"+39 0773 709523",
    "sg:postcode":"04019",
    "sg:province":"Latina",
    "sg:tags":[
        "business"
    ],
    "wof:name":"Grand Hotel Palace",
    "wof:placetype":"venue"
},
  "geometry": {"coordinates":[12.9037,41.467598],"type":"Point"}
}