{
  "type": "Feature",
  "properties": {
    "iso:country":"IT",
    "sg:address":"00010 Gallicano Nel Lazio",
    "sg:city":"Gallicano nel Lazio",
    "sg:orig_category":"Articoli Da Regalo. Regalistica Aziendale",
    "sg:phone":"+39 06 9546 0061",
    "sg:postcode":"00010",
    "sg:province":"Roma",
    "wof:name":"De Angelis Fabrizio",
    "wof:placetype":"venue"
},
  "geometry": {"coordinates":[12.818844,41.872112],"type":"Point"}
}