{
  "type": "Feature",
  "properties": {
    "addr:full":"31038 Paese Paese Treviso 31038",
    "addr:postcode":"31038;31038",
    "addr:street":"Paese Paese",
    "iso:country":"IT",
    "sg:address":"31038 Paese",
    "sg:city":"Paese",
    "sg:orig_category":"Sport - Articoli E Forniture. Automobili E Mezzi Di Trasporto",
    "sg:phone":"+39 0422 452252",
    "sg:postcode":"31038",
    "sg:province":"Treviso",
    "wof:name":"Tuttokart 2 Di Gabriele Antonio",
    "wof:placetype":"venue"
},
  "geometry": {"coordinates":[12.160611,45.677795],"type":"Point"}
}