{
  "type": "Feature",
  "properties": {
    "iso:country":"IT",
    "sg:address":"41015 Nonantola",
    "sg:city":"Bagazzano",
    "sg:orig_category":"Ricevimenti E Banchetti - Sale E Servizi",
    "sg:phone":"+39 059 546166",
    "sg:postcode":"41015",
    "sg:province":"Modena",
    "sg:website":"http://wwww.villacasinoriva.it",
    "wof:name":"Casino Riva Srl",
    "wof:placetype":"venue"
},
  "geometry": {"coordinates":[11.047807,44.67453],"type":"Point"}
}