{
  "type": "Feature",
  "properties": {
    "iso:country":"IT",
    "sg:address":"70024 Gravina In Puglia",
    "sg:city":"Gravina in Puglia",
    "sg:orig_category":"Tempo Libero - Articoli E Forniture. Regalistica Aziendale",
    "sg:phone":"+39 080 322 3316",
    "sg:postcode":"70024",
    "sg:province":"Bari",
    "wof:name":"Cip Cip Store Di Barbara Pasquale Walter",
    "wof:placetype":"venue"
},
  "geometry": {"coordinates":[16.369926,40.842537],"type":"Point"}
}