{
  "type": "Feature",
  "properties": {
    "addr:full":"Via Siffredi Angelo 58 16153 Genova Genova Genova 16153",
    "addr:housenumber":"58",
    "addr:postcode":"16153;16153",
    "addr:street":"Via Siffredi Angelo",
    "iso:country":"IT",
    "sg:address":"Via Siffredi Angelo 58 16153 Genova",
    "sg:city":"Genova",
    "sg:classifiers":[
        {
            "category":"Health Services",
            "subcategory":"Nursing And Care Facility",
            "type":"Services"
        }
    ],
    "sg:phone":"+39 010 65471",
    "sg:postcode":"16153",
    "sg:province":"Genova",
    "sg:tags":[
        "electro-medical",
        "apparatus"
    ],
    "sg:website":"www.esaote.com",
    "wof:name":"Esaote Spa",
    "wof:placetype":"venue"
},
  "geometry": {"coordinates":[8.933989,44.407063],"type":"Point"}
}