{
  "type": "Feature",
  "properties": {
    "addr:full":"20010 Santo Stefano Ticino Santo Stefano Ticino Milano 20010",
    "addr:postcode":"20010;20010",
    "iso:country":"IT",
    "sg:address":"20010 Santo Stefano Ticino",
    "sg:city":"Santo Stefano Ticino",
    "sg:orig_category":"Macchine, Impianti E Forniture Per Industria Grafica, Cartaria E Cartotecnica",
    "sg:phone":"+39 02 9727 3088",
    "sg:postcode":"20010",
    "sg:province":"Milano",
    "wof:name":"Rocchini Forn.graf.snc Di G. Rocchini & C.",
    "wof:placetype":"venue"
},
  "geometry": {"coordinates":[9.184439,45.458836],"type":"Point"}
}