{
  "type": "Feature",
  "properties": {
    "addr:full":"18, Via Nosari 24024 Gandino Gandino Bergamo 24024",
    "addr:postcode":"24024;24024",
    "addr:street":"Via Nosari",
    "iso:country":"IT",
    "sg:address":"18, Via Nosari 24024 Gandino",
    "sg:city":"Gandino",
    "sg:classifiers":[
        {
            "category":"Professional",
            "subcategory":"Engineering",
            "type":"Services"
        }
    ],
    "sg:phone":"+39 39035745124",
    "sg:postcode":"24024",
    "sg:province":"Bergamo",
    "sg:tags":[
        "machine",
        "-",
        "mechanical"
    ],
    "wof:name":"Martel S.r.l.",
    "wof:placetype":"venue"
},
  "geometry": {"coordinates":[9.894176,45.810726],"type":"Point"}
}