{
  "type": "Feature",
  "properties": {
    "iso:country":"IT",
    "sg:address":"86100 Campobasso",
    "sg:city":"Campobasso",
    "sg:orig_category":"Ospedali E Servizi Sanitari. Servizi Sociali. Associazioni Ed Organismi Di Interesse Pubblico",
    "sg:phone":"+39 0874 699090",
    "sg:postcode":"86100",
    "sg:province":"Campobasso",
    "wof:name":"Associazione Molise Emergenza",
    "wof:placetype":"venue"
},
  "geometry": {"coordinates":[14.686942,41.564789],"type":"Point"}
}