{
  "type": "Feature",
  "properties": {
    "iso:country":"IT",
    "sg:address":"Via Principale 12; Verderio; 22050",
    "sg:classifiers":[
        {
            "category":"Banks & Credit Unions",
            "subcategory":"Bank",
            "type":"Services"
        }
    ],
    "sg:phone":"+39 039 951 5299",
    "wof:name":"Istituto Bancario, San Paolo Di Torino Spa",
    "wof:placetype":"venue"
},
  "geometry": {"coordinates":[9.440435,45.668121],"type":"Point"}
}