{
  "type": "Feature",
  "properties": {
    "iso:country":"IT",
    "sg:address":"66021 Casalbordino",
    "sg:city":"Casalbordino",
    "sg:orig_category":"Prodotti Chimici Secondari",
    "sg:phone":"+39 0873 918151",
    "sg:postcode":"66021",
    "sg:province":"Chieti",
    "wof:name":"Esplodenti Sabino Srl",
    "wof:placetype":"venue"
},
  "geometry": {"coordinates":[14.6004915237,42.1697044373],"type":"Point"}
}