{
  "type": "Feature",
  "properties": {
    "iso:country":"IT",
    "sg:address":"42013 Veggia",
    "sg:orig_category":"Servizi Ausiliari Di Analisi, Controllo E Ricerca",
    "sg:phone":"+39 0536 824693",
    "sg:postcode":"42013",
    "sg:province":"Reggio Nell'Emilia",
    "wof:name":"Zanni Giuseppe S.n.c.",
    "wof:placetype":"venue"
},
  "geometry": {"coordinates":[10.627794,44.696228],"type":"Point"}
}