{
  "type": "Feature",
  "properties": {
    "iso:country":"IT",
    "sg:address":"62015 Monte San Giusto",
    "sg:city":"Monte San Giusto",
    "sg:orig_category":"Automazione E Macchine Per Ufficio",
    "sg:phone":"+39 0733 837109",
    "sg:postcode":"62015",
    "sg:province":"Macerata",
    "wof:name":"Sw Office Automation Srl",
    "wof:placetype":"venue"
},
  "geometry": {"coordinates":[13.591853,43.259941],"type":"Point"}
}