{
  "type": "Feature",
  "properties": {
    "addr:full":"26100 Cremona Cremona Cremona 26100",
    "addr:postcode":"26100;26100",
    "iso:country":"IT",
    "sg:address":"26100 Cremona",
    "sg:city":"Cremona",
    "sg:orig_category":"Apparecchiature Ed Attrezzature Meccaniche",
    "sg:phone":"+39 0372 25465",
    "sg:postcode":"26100",
    "sg:province":"Cremona",
    "wof:name":"Officina Meccanica Tosi Di Tosi Geom. Giuseppe",
    "wof:placetype":"venue"
},
  "geometry": {"coordinates":[9.999443,45.132507],"type":"Point"}
}