{
  "type": "Feature",
  "properties": {
    "iso:country":"IT",
    "sg:address":"1, Via Salita Motto 13836 Cossato",
    "sg:city":"Cossato",
    "sg:classifiers":[
        {
            "category":"Manufacturing",
            "subcategory":"Lumber",
            "type":"Manufacturing & Wholesale Goods"
        }
    ],
    "sg:phone":"+39 390 159 3782",
    "sg:postcode":"13836",
    "sg:province":"Biella",
    "sg:tags":[
        "wood"
    ],
    "wof:name":"Segheria - Carpenteria Di Cossato Di Mioni E Crestani (s.n.c.)",
    "wof:placetype":"venue"
},
  "geometry": {"coordinates":[8.05827,45.562836],"type":"Point"}
}