{
  "type": "Feature",
  "properties": {
    "addr:full":"24/d, Via Principe Di Napoli 80147 Napoli Napoli Napoli 80147",
    "addr:housenumber":"24 / d",
    "addr:postcode":"80147;80147",
    "addr:street":"Via Principe Di Napoli",
    "iso:country":"IT",
    "sg:address":"24/d, Via Principe Di Napoli 80147 Napoli",
    "sg:city":"Napoli",
    "sg:classifiers":[
        {
            "category":"Food & Beverages",
            "subcategory":"Groceries & Convenience Stores",
            "type":"Retail Goods"
        }
    ],
    "sg:phone":"+39 081 561 5314",
    "sg:postcode":"80147",
    "sg:province":"Napoli",
    "sg:tags":[
        "product",
        "related"
    ],
    "wof:name":"S.a.c.i. (s.r.l.)",
    "wof:placetype":"venue"
},
  "geometry": {"coordinates":[14.2856435776,40.8913040161],"type":"Point"}
}