{
  "type": "Feature",
  "properties": {
    "iso:country":"IT",
    "sg:address":"00012 Guidonia Montecelio",
    "sg:city":"Guidonia",
    "sg:orig_category":"Serrande Avvolgibili",
    "sg:phone":"+39 0774 527764",
    "sg:postcode":"00012",
    "sg:province":"Roma",
    "sg:website":"http://www.paginegialle.it/semetsas",
    "wof:name":"Marazza Marcello",
    "wof:placetype":"venue"
},
  "geometry": {"coordinates":[12.733952,41.982262],"type":"Point"}
}