{
  "type": "Feature",
  "properties": {
    "iso:country":"IT",
    "sg:address":"Via Giusti 45 63018 Porto Sant'elpidio",
    "sg:orig_category":"Ladies' Shoes",
    "sg:phone":"+39 0734 991112",
    "sg:postcode":"63018",
    "sg:province":"Ascoli Piceno",
    "sg:website":"www.giovannigiusti.it",
    "wof:name":"Calzaturificio Giusti Srl",
    "wof:placetype":"venue"
},
  "geometry": {"coordinates":[13.759933,43.252224],"type":"Point"}
}