{
  "type": "Feature",
  "properties": {
    "iso:country":"IT",
    "sg:address":"40026 Imola",
    "sg:city":"Imola",
    "sg:orig_category":"Macchine, Impianti Ed Attrezzature Per Industria Alimentare E Bevande",
    "sg:phone":"+39 0542 22435",
    "sg:postcode":"40026",
    "sg:province":"Bologna",
    "wof:name":"O.g. Impianti Srl",
    "wof:placetype":"venue"
},
  "geometry": {"coordinates":[11.725174,44.349644],"type":"Point"}
}