{
  "type": "Feature",
  "properties": {
    "iso:country":"IT",
    "sg:address":"Strada 4 Palazzo A2 20090 Assago",
    "sg:city":"Assago",
    "sg:classifiers":[
        {
            "category":"Retail",
            "subcategory":"Car Wash",
            "type":"Services"
        }
    ],
    "sg:phone":"+39 02 5751 2291",
    "sg:postcode":"20090",
    "sg:province":"Milano",
    "sg:tags":[
        "chemical",
        "product",
        "machine",
        "filling",
        "bottle",
        "sealing"
    ],
    "sg:website":"www.simeng.it",
    "wof:name":"Simi Engineering Srl",
    "wof:placetype":"venue"
},
  "geometry": {"coordinates":[9.131515,45.404312],"type":"Point"}
}