{
  "type": "Feature",
  "properties": {
    "iso:country":"IT",
    "sg:address":"56, Via Irpinia 35020 Saonara",
    "sg:city":"Saonara",
    "sg:classifiers":[
        {
            "category":"Shopping",
            "subcategory":"Stationery & Office Supplies",
            "type":"Retail Goods"
        }
    ],
    "sg:phone":"+39 049 879 1870",
    "sg:postcode":"35020",
    "sg:province":"Padova",
    "sg:tags":[
        "professional"
    ],
    "wof:name":"Centro Ambiente Ufficio S.p.a.",
    "wof:placetype":"venue"
},
  "geometry": {"coordinates":[11.9662475586,45.3802490234],"type":"Point"}
}