{
  "type": "Feature",
  "properties": {
    "iso:country":"IT",
    "sg:address":"80142 Napoli",
    "sg:city":"Napoli",
    "sg:orig_category":"Accessori Moda D'abbigliamento",
    "sg:phone":"+39 081 286984",
    "sg:postcode":"80142",
    "sg:province":"Napoli",
    "wof:name":"Ingegno Bruno",
    "wof:placetype":"venue"
},
  "geometry": {"coordinates":[14.23216,40.922462],"type":"Point"}
}