{
  "type": "Feature",
  "properties": {
    "iso:country":"IT",
    "sg:address":"18033 Camporosso",
    "sg:city":"Camporosso",
    "sg:orig_category":"Banche Ed Istituti Di Credito E Risparmio",
    "sg:phone":"+39 0184 287000",
    "sg:postcode":"18033",
    "sg:province":"Imperia",
    "wof:name":"Banca Di Caraglio E Della Riviera Dei Fiori - Credito Cooperativo",
    "wof:placetype":"venue"
},
  "geometry": {"coordinates":[7.628826,43.813072],"type":"Point"}
}