{
  "type": "Feature",
  "properties": {
    "addr:full":"Via Delle Magnolie 11 70123 Bari Bari Bari 70123",
    "addr:housenumber":"11",
    "addr:postcode":"70123;70123",
    "addr:street":"Via Delle Magnolie",
    "iso:country":"IT",
    "sg:address":"Via Delle Magnolie 11 70123 Bari",
    "sg:city":"Bari",
    "sg:classifiers":[
        {
            "category":"Shopping",
            "subcategory":"Computers & Home Electronics",
            "type":"Retail Goods"
        }
    ],
    "sg:phone":"+39 080 537 5560",
    "sg:postcode":"70123",
    "sg:province":"Bari",
    "sg:tags":[
        "tube",
        "manipulation"
    ],
    "wof:name":"Acciaierie E Tubificio Meridionali Spa",
    "wof:placetype":"venue"
},
  "geometry": {"coordinates":[16.868982,41.062969],"type":"Point"}
}