{
  "type": "Feature",
  "properties": {
    "iso:country":"IT",
    "sg:address":"20123 Milano",
    "sg:city":"Milano",
    "sg:orig_category":"Macchine E Forniture Per Industria Orafa E Per Orologeria",
    "sg:phone":"+39 02 805 7044",
    "sg:postcode":"20123",
    "sg:province":"Milano",
    "wof:name":"Forniture Orologerie S. Maurilio Snc",
    "wof:placetype":"venue"
},
  "geometry": {"coordinates":[9.184436,45.461926],"type":"Point"}
}