{
  "type": "Feature",
  "properties": {
    "iso:country":"IT",
    "sg:address":"42, Via Brenta 38052 Caldonazzo",
    "sg:city":"Caldonazzo",
    "sg:classifiers":[
        {
            "category":"Farming",
            "subcategory":"Livestock Farm",
            "type":"Manufacturing & Wholesale Goods"
        }
    ],
    "sg:phone":"+39 0461 723442",
    "sg:postcode":"38052",
    "sg:province":"Trento",
    "sg:tags":[
        "agriculture"
    ],
    "wof:name":"Consorzio Frutticoltori Alta Valsugana Co.f.a.v.",
    "wof:placetype":"venue"
},
  "geometry": {"coordinates":[11.267797,45.998627],"type":"Point"}
}