{
  "type": "Feature",
  "properties": {
    "iso:country":"IT",
    "sg:address":"16122 Genova",
    "sg:city":"Genova",
    "sg:orig_category":"Dolciumi E Gelati",
    "sg:phone":"+39 010 819051",
    "sg:postcode":"16122",
    "sg:province":"Genova",
    "sg:website":"http://www.romanengo.com",
    "wof:name":"Romanengo Pietro Fu Stefano Srl",
    "wof:placetype":"venue"
},
  "geometry": {"coordinates":[8.943854,44.413506],"type":"Point"}
}