{
  "type": "Feature",
  "properties": {
    "iso:country":"IT",
    "sg:address":"79/81, Viale Agricoltura 27029 Vigevano",
    "sg:city":"Vigevano",
    "sg:classifiers":[
        {
            "category":"Shopping",
            "subcategory":"Computers & Home Electronics",
            "type":"Retail Goods"
        }
    ],
    "sg:phone":"+39 0381 344185",
    "sg:postcode":"27029",
    "sg:province":"Pavia",
    "sg:tags":[
        "electronic",
        "electrical",
        "equipment"
    ],
    "wof:name":"Carena Cavi Di Dott.ing.ettore Carena & C. (s.r.l.)",
    "wof:placetype":"venue"
},
  "geometry": {"coordinates":[8.845349,45.297749],"type":"Point"}
}