{
  "type": "Feature",
  "properties": {
    "iso:country":"IT",
    "sg:address":"21100 Varese",
    "sg:city":"Varese",
    "sg:orig_category":"Prodotti Alimentari",
    "sg:phone":"+39 0332 274710",
    "sg:postcode":"21100",
    "sg:province":"Varese",
    "wof:name":"Pistoletti Enrico",
    "wof:placetype":"venue"
},
  "geometry": {"coordinates":[8.8629703522,45.7887802124],"type":"Point"}
}