{
  "type": "Feature",
  "properties": {
    "addr:full":"03043 Cassino Cassino Frosinone 03043",
    "addr:postcode":"03043;03043",
    "iso:country":"IT",
    "sg:address":"03043 Cassino",
    "sg:city":"Cassino",
    "sg:orig_category":"Prodotti E Manufatti In Materie Plastiche",
    "sg:phone":"+39 0776 329093",
    "sg:postcode":"03043",
    "sg:province":"Frosinone",
    "wof:name":"Fasani Di Fasani E. E P. Sas",
    "wof:placetype":"venue"
},
  "geometry": {"coordinates":[13.8332195282,41.4866943359],"type":"Point"}
}