{
  "type": "Feature",
  "properties": {
    "iso:country":"IT",
    "sg:address":"20050 Sovico",
    "sg:city":"Sovico",
    "sg:orig_category":"Arredo Camera Letto E Complementi",
    "sg:phone":"+39 039 201 0834",
    "sg:postcode":"20050",
    "sg:province":"Milano",
    "wof:name":"Retex Snc Di Recalcati Roberto & C.",
    "wof:placetype":"venue"
},
  "geometry": {"coordinates":[9.260791,45.644905],"type":"Point"}
}