{
  "type": "Feature",
  "properties": {
    "iso:country":"IT",
    "sg:address":"32, Via Della Resistenza 35027 Noventa Padovana",
    "sg:city":"Noventa Padovana",
    "sg:classifiers":[
        {
            "category":"Food & Beverages",
            "subcategory":"Groceries & Convenience Stores",
            "type":"Retail Goods"
        }
    ],
    "sg:phone":"+39 39049625155",
    "sg:postcode":"35027",
    "sg:province":"Padova",
    "sg:tags":[
        "product",
        "related"
    ],
    "wof:name":"Brugnolo Giancarlo (s.p.a.)",
    "wof:placetype":"venue"
},
  "geometry": {"coordinates":[11.9477319717,45.4212532043],"type":"Point"}
}