{
  "type": "Feature",
  "properties": {
    "iso:country":"IT",
    "sg:address":"93012 Gela",
    "sg:city":"Gela",
    "sg:orig_category":"Antiquariato",
    "sg:phone":"+39 0933 939948",
    "sg:postcode":"93012",
    "sg:province":"Caltanissetta",
    "wof:name":"\u20acurostyle",
    "wof:placetype":"venue"
},
  "geometry": {"coordinates":[14.210865,37.08115],"type":"Point"}
}