{
  "type": "Feature",
  "properties": {
    "iso:country":"IT",
    "sg:address":"41012 Carpi",
    "sg:city":"Carpi",
    "sg:orig_category":"Servizi E Lavori Per Abbigliamento E Pelletterie",
    "sg:phone":"+39 059 685566",
    "sg:postcode":"41012",
    "sg:province":"Modena",
    "wof:name":"Plisse' Sas",
    "wof:placetype":"venue"
},
  "geometry": {"coordinates":[10.898591,44.794537],"type":"Point"}
}