{
  "type": "Feature",
  "properties": {
    "iso:country":"IT",
    "sg:address":"12, Via Grecia 46042 Castel Goffredo",
    "sg:city":"Castel Goffredo",
    "sg:classifiers":[
        {
            "category":"Shopping",
            "subcategory":"Crafts & Fabrics",
            "type":"Retail Goods"
        }
    ],
    "sg:phone":"+39 0376 779101",
    "sg:postcode":"46042",
    "sg:province":"Mantova",
    "wof:name":"Fyl Bel",
    "wof:placetype":"venue"
},
  "geometry": {"coordinates":[10.4686374664,45.2863998413],"type":"Point"}
}