{
  "type": "Feature",
  "properties": {
    "addr:full":"Via Marengo 32 59100 Prato Prato Prato 59100",
    "addr:housenumber":"32",
    "addr:postcode":"59100;59100",
    "addr:street":"Via Marengo",
    "iso:country":"IT",
    "sg:address":"Via Marengo 32 59100 Prato",
    "sg:city":"Prato",
    "sg:orig_category":"Ladies' Trousers Suits, Suits, Jackets, Skirts, And Trousers",
    "sg:phone":"+39 0574 36388",
    "sg:postcode":"59100",
    "sg:province":"Prato",
    "wof:name":"Blu Mania S.r.l.",
    "wof:placetype":"venue"
},
  "geometry": {"coordinates":[11.087978,43.871918],"type":"Point"}
}