{
  "type": "Feature",
  "properties": {
    "addr:full":"58, V. Cavour 33030 Flaibano Flaibano Udine 33030",
    "addr:housenumber":"58",
    "addr:postcode":"33030;33030",
    "addr:street":"V. Cavour",
    "iso:country":"IT",
    "sg:address":"58, V. Cavour 33030 Flaibano",
    "sg:city":"Flaibano",
    "sg:classifiers":[
        {
            "category":"Food & Beverages",
            "subcategory":"Dairy",
            "type":"Retail Goods"
        }
    ],
    "sg:phone":"+39 0432 869355",
    "sg:postcode":"33030",
    "sg:province":"Udine",
    "sg:tags":[
        "product"
    ],
    "sg:website":"http://www.cepparo.it",
    "wof:name":"Cepparo Srl",
    "wof:placetype":"venue"
},
  "geometry": {"coordinates":[13.230724,46.064941],"type":"Point"}
}