{
  "type": "Feature",
  "properties": {
    "iso:country":"IT",
    "sg:address":"7, Via Donatello 95025 Aci Sant'antonio",
    "sg:classifiers":[
        {
            "category":"Manufacturing",
            "subcategory":"Paper Products",
            "type":"Manufacturing & Wholesale Goods"
        }
    ],
    "sg:phone":"+39 095 790 1313",
    "sg:postcode":"95025",
    "sg:province":"Catania",
    "sg:tags":[
        "cardboard"
    ],
    "wof:name":"S.c.i.a. Sas Di Losito Giovanni",
    "wof:placetype":"venue"
},
  "geometry": {"coordinates":[15.1162996292,37.6040039062],"type":"Point"}
}