{
  "type": "Feature",
  "properties": {
    "addr:full":"20121 Milano Milano Milano 20121",
    "addr:postcode":"20121;20121",
    "iso:country":"IT",
    "sg:address":"20121 Milano",
    "sg:city":"Milano",
    "sg:orig_category":"Servizi E Lavori Per Edilizia E Lavori Pubblici. Banche E Servizi Finanziari",
    "sg:phone":"+39 02 860644",
    "sg:postcode":"20121",
    "sg:province":"Milano",
    "wof:name":"Marbon Sas",
    "wof:placetype":"venue"
},
  "geometry": {"coordinates":[9.182781,45.474339],"type":"Point"}
}