{
  "type": "Feature",
  "properties": {
    "addr:full":"10153 Torino Torino Torino 10153",
    "addr:postcode":"10153;10153",
    "iso:country":"IT",
    "sg:address":"10153 Torino",
    "sg:city":"Torino",
    "sg:orig_category":"Ascensori - Installazione E Manutenzione",
    "sg:phone":"+39 011 226 4913",
    "sg:postcode":"10153",
    "sg:province":"Torino",
    "wof:name":"Gruppo Simet Snc",
    "wof:placetype":"venue"
},
  "geometry": {"coordinates":[7.713487,45.074207],"type":"Point"}
}