{
  "type": "Feature",
  "properties": {
    "iso:country":"IT",
    "sg:address":"20017 Rho",
    "sg:city":"Rho",
    "sg:orig_category":"Acciaierie E Fonderie",
    "sg:phone":"+39 02 930 1473",
    "sg:postcode":"20017",
    "sg:province":"Milano",
    "wof:name":"Pressofusione Di Landella Mauro & C. (s.n.c.)",
    "wof:placetype":"venue"
},
  "geometry": {"coordinates":[9.249382,45.398399],"type":"Point"}
}