{
  "type": "Feature",
  "properties": {
    "addr:full":"34074 Monfalcone Monfalcone Gorizia 34074",
    "addr:postcode":"34074;34074",
    "iso:country":"IT",
    "sg:address":"34074 Monfalcone",
    "sg:city":"Monfalcone",
    "sg:orig_category":"Trasporti E Spedizioni Merci",
    "sg:phone":"+39 0481 412200",
    "sg:postcode":"34074",
    "sg:province":"Gorizia",
    "sg:website":"http://paginegialle.it/bbsspedizioni",
    "wof:name":"Bbs Spedizioni Di Bruno Bonetti",
    "wof:placetype":"venue"
},
  "geometry": {"coordinates":[13.53372,45.805492],"type":"Point"}
}