{
  "type": "Feature",
  "properties": {
    "iso:country":"IT",
    "sg:address":"00142 Roma",
    "sg:city":"Roma",
    "sg:classifiers":[
        {
            "category":"Communications",
            "subcategory":"Newspaper",
            "type":"Services"
        }
    ],
    "sg:phone":"+39 06 540 6873",
    "sg:postcode":"00142",
    "sg:province":"Roma",
    "sg:tags":[
        "graphic",
        "publishing",
        "industry",
        "automation",
        "machine",
        "equipment",
        "paper",
        "machinery",
        "supplies"
    ],
    "sg:website":"http://www.diario-srl.it",
    "wof:name":"Diario Srl",
    "wof:placetype":"venue"
},
  "geometry": {"coordinates":[12.489655,41.833878],"type":"Point"}
}