{
  "type": "Feature",
  "properties": {
    "iso:country":"IT",
    "sg:address":"6, Via Bissolati Leonida 30172 Venezia",
    "sg:city":"Venezia",
    "sg:orig_category":"Miscellaneous Products",
    "sg:phone":"+39 39041940689",
    "sg:postcode":"30172",
    "sg:province":"Venezia",
    "wof:name":"Cagive S.r.l.",
    "wof:placetype":"venue"
},
  "geometry": {"coordinates":[12.3266267776,45.4408950806],"type":"Point"}
}