{
  "type": "Feature",
  "properties": {
    "iso:country":"IT",
    "sg:address":"71019 Vieste",
    "sg:city":"Vieste",
    "sg:classifiers":[
        {
            "category":"Travel",
            "subcategory":"Hotels & Motels",
            "type":"Entertainment"
        }
    ],
    "sg:phone":"+39 0884 706078",
    "sg:postcode":"71019",
    "sg:province":"Foggia",
    "sg:tags":[
        "hotels",
        "facility"
    ],
    "wof:name":"Residence Costamartino",
    "wof:placetype":"venue"
},
  "geometry": {"coordinates":[16.153584,41.876572],"type":"Point"}
}