{
  "type": "Feature",
  "properties": {
    "iso:country":"IT",
    "sg:address":"61100 Pesaro",
    "sg:city":"Pesaro",
    "sg:orig_category":"Lotto, Ricevitorie Concorsi E Giocate",
    "sg:phone":"+39 0721 34163",
    "sg:postcode":"61100",
    "sg:province":"Pesaro E Urbino",
    "wof:name":"Tomassoli Roberto",
    "wof:placetype":"venue"
},
  "geometry": {"coordinates":[12.91633,43.907757],"type":"Point"}
}