{
  "type": "Feature",
  "properties": {
    "addr:full":"21020 Bodio Lomnago Bodio Varese 21020",
    "addr:postcode":"21020;21020",
    "iso:country":"IT",
    "sg:address":"21020 Bodio Lomnago",
    "sg:city":"Bodio",
    "sg:orig_category":"Articoli Per Imballaggio E Confezionamento",
    "sg:phone":"+39 0332 949 1609",
    "sg:postcode":"21020",
    "sg:province":"Varese",
    "wof:name":"Galimberti Giorgio",
    "wof:placetype":"venue"
},
  "geometry": {"coordinates":[8.743683,45.793114],"type":"Point"}
}