{
  "type": "Feature",
  "properties": {
    "iso:country":"IT",
    "sg:address":"19, Via Del Mare 10040 Piobesi Torinese",
    "sg:city":"Piobesi Torinese",
    "sg:classifiers":[
        {
            "category":"Professional",
            "subcategory":"Engineering",
            "type":"Services"
        }
    ],
    "sg:phone":"+39 011 965 0308",
    "sg:postcode":"10040",
    "sg:province":"Torino",
    "sg:tags":[
        "machine",
        "-",
        "mechanical"
    ],
    "wof:name":"Co.st.at. Srl",
    "wof:placetype":"venue"
},
  "geometry": {"coordinates":[7.625688,44.927387],"type":"Point"}
}