{
  "type": "Feature",
  "properties": {
    "iso:country":"IT",
    "sg:address":"59013 Montemurlo",
    "sg:city":"Montemurlo",
    "sg:orig_category":"Filati E Materie Prime Tessili",
    "sg:phone":"+39 0574 798795",
    "sg:postcode":"59013",
    "sg:province":"Prato",
    "wof:name":"Azzurra 2 Srl",
    "wof:placetype":"venue"
},
  "geometry": {"coordinates":[11.0245285034,43.9062919617],"type":"Point"}
}