{
  "type": "Feature",
  "properties": {
    "addr:full":"60, Via De Marini 16149 Genova Genova Genova 16149",
    "addr:postcode":"16149;16149",
    "addr:street":"Via De Marini",
    "iso:country":"IT",
    "sg:address":"60, Via De Marini 16149 Genova",
    "sg:city":"Genova",
    "sg:classifiers":[
        {
            "category":"Marine",
            "type":"Transportation"
        }
    ],
    "sg:phone":"+39 39010267681",
    "sg:postcode":"16149",
    "sg:province":"Genova",
    "sg:tags":[
        "transport",
        "sea"
    ],
    "wof:name":"Veroggio Eugenio & Figli",
    "wof:placetype":"venue"
},
  "geometry": {"coordinates":[8.901684,44.407822],"type":"Point"}
}