{
  "type": "Feature",
  "properties": {
    "addr:full":"10, Via Dante Alighieri 24059 Urgnano Urgnano Bergamo 24059",
    "addr:postcode":"24059;24059",
    "addr:street":"Via Dante Alighieri",
    "iso:country":"IT",
    "sg:address":"10, Via Dante Alighieri 24059 Urgnano",
    "sg:city":"Urgnano",
    "sg:classifiers":[
        {
            "category":"Professional",
            "subcategory":"Engineering",
            "type":"Services"
        }
    ],
    "sg:phone":"+39 39035894301",
    "sg:postcode":"24059",
    "sg:province":"Bergamo",
    "sg:tags":[
        "machine",
        "-",
        "mechanical"
    ],
    "wof:name":"Automazione 2001 (s.r.l.)",
    "wof:placetype":"venue"
},
  "geometry": {"coordinates":[9.647109,45.640442],"type":"Point"}
}