{
  "type": "Feature",
  "properties": {
    "addr:full":"50018 Scandicci Scandicci Firenze 50018",
    "addr:postcode":"50018;50018",
    "iso:country":"IT",
    "sg:address":"50018 Scandicci",
    "sg:city":"Scandicci",
    "sg:orig_category":"Materiali E Componenti Elettronici",
    "sg:phone":"+39 055 720312",
    "sg:postcode":"50018",
    "sg:province":"Firenze",
    "wof:name":"Essedue Rappresentanze Srl",
    "wof:placetype":"venue"
},
  "geometry": {"coordinates":[11.157576,43.76112],"type":"Point"}
}