{
  "type": "Feature",
  "properties": {
    "iso:country":"IT",
    "sg:address":"24060 San Paolo D'argon",
    "sg:classifiers":[
        {
            "category":"Manufacturing",
            "subcategory":"Leather Goods",
            "type":"Manufacturing & Wholesale Goods"
        }
    ],
    "sg:phone":"+39 035 951008",
    "sg:postcode":"24060",
    "sg:province":"Bergamo",
    "sg:tags":[
        "goods",
        "clothing",
        "supply"
    ],
    "sg:website":"http://www.corozite.com",
    "wof:name":"Corozite Spa",
    "wof:placetype":"venue"
},
  "geometry": {"coordinates":[9.809579,45.673393],"type":"Point"}
}