{
  "type": "Feature",
  "properties": {
    "iso:country":"IT",
    "sg:address":"20068 Peschiera Borromeo",
    "sg:city":"Peschiera Borromeo",
    "sg:orig_category":"Macchine, Impianti E Forniture Per Industria Grafica, Cartaria E Cartotecnica. Prodotti Chimici Secondari",
    "sg:phone":"+39 02 553 7811",
    "sg:postcode":"20068",
    "sg:province":"Milano",
    "wof:name":"Sun Chemical S.p.a.",
    "wof:placetype":"venue"
},
  "geometry": {"coordinates":[9.303743,45.439217],"type":"Point"}
}