{
  "type": "Feature",
  "properties": {
    "iso:country":"IT",
    "sg:address":"10, Piazza Giovanni Nep. Croce Pressano 38015 Lavis",
    "sg:city":"Lavis",
    "sg:classifiers":[
        {
            "category":"Banks & Credit Unions",
            "subcategory":"Bank",
            "type":"Services"
        }
    ],
    "sg:phone":"+39 0461 246351",
    "sg:postcode":"38015",
    "sg:province":"Trento",
    "sg:tags":[
        "banking",
        "institution"
    ],
    "wof:name":"Cassa Rurale Lavis Valle Di Cembra",
    "wof:placetype":"venue"
},
  "geometry": {"coordinates":[11.119053,46.066738],"type":"Point"}
}