{
  "type": "Feature",
  "properties": {
    "iso:country":"IT",
    "sg:address":"Via Italia 6 24040 Levate",
    "sg:city":"Levate",
    "sg:classifiers":[
        {
            "category":"Train Station",
            "subcategory":"Light Rail",
            "type":"Transportation"
        }
    ],
    "sg:phone":"+39 035 594455",
    "sg:postcode":"24040",
    "sg:province":"Bergamo",
    "sg:tags":[
        "lighting"
    ],
    "wof:name":"Otm Srl",
    "wof:placetype":"venue"
},
  "geometry": {"coordinates":[9.62192,45.639595],"type":"Point"}
}