{
  "type": "Feature",
  "properties": {
    "iso:country":"IT",
    "sg:address":"Via Trinitapoli Zona Torretta 71044 Margherita Di Savoia",
    "sg:city":"Margherita di Savoia",
    "sg:classifiers":[
        {
            "category":"Food & Beverages",
            "subcategory":"Groceries & Convenience Stores",
            "type":"Retail Goods"
        }
    ],
    "sg:phone":"+39 0883 654942",
    "sg:postcode":"71044",
    "sg:province":"Foggia",
    "sg:tags":[
        "product",
        "related"
    ],
    "wof:name":"Sai Sali Alimentari E Industriali S.r.l.",
    "wof:placetype":"venue"
},
  "geometry": {"coordinates":[15.5446996689,41.4623336792],"type":"Point"}
}