{
  "type": "Feature",
  "properties": {
    "addr:full":"00133 Roma Roma Roma 00133",
    "addr:postcode":"00133;00133",
    "iso:country":"IT",
    "sg:address":"00133 Roma",
    "sg:city":"Roma",
    "sg:orig_category":"Arredi Ed Attrezzature Per Uffici",
    "sg:phone":"+39 06 2042 7640",
    "sg:postcode":"00133",
    "sg:province":"Roma",
    "sg:website":"http://www.eurodispenser.it",
    "wof:name":"Eurodispenser Srl",
    "wof:placetype":"venue"
},
  "geometry": {"coordinates":[12.611909,41.847965],"type":"Point"}
}