{
  "type": "Feature",
  "properties": {
    "addr:full":"9, Via Buccia 35010 Limena Limena Padova 35010",
    "addr:postcode":"35010;35010",
    "addr:street":"Via Buccia",
    "iso:country":"IT",
    "sg:address":"9, Via Buccia 35010 Limena",
    "sg:city":"Limena",
    "sg:classifiers":[
        {
            "category":"Sports & Exercise",
            "subcategory":"Playing Field",
            "type":"Entertainment"
        }
    ],
    "sg:phone":"+39 049 884 0677",
    "sg:postcode":"35010",
    "sg:province":"Padova",
    "sg:tags":[
        "game"
    ],
    "wof:name":"Elbi S.p.a.",
    "wof:placetype":"venue"
},
  "geometry": {"coordinates":[11.841495,45.472019],"type":"Point"}
}