{
  "type": "Feature",
  "properties": {
    "addr:full":"16, Via Delle Azalee 80029 Sant'antimo Napoli 80029",
    "addr:postcode":"80029;80029",
    "addr:street":"Via Delle Azalee",
    "iso:country":"IT",
    "sg:address":"16, Via Delle Azalee 80029 Sant'antimo",
    "sg:classifiers":[
        {
            "category":"Personal",
            "subcategory":"Shoe Repair & Shine",
            "type":"Services"
        }
    ],
    "sg:phone":"+39 081 395 2132",
    "sg:postcode":"80029",
    "sg:province":"Napoli",
    "sg:tags":[
        "leather"
    ],
    "wof:name":"Calzaturificio Aesse Club S.r.l.",
    "wof:placetype":"venue"
},
  "geometry": {"coordinates":[14.220962,40.942497],"type":"Point"}
}