{
  "type": "Feature",
  "properties": {
    "iso:country":"IT",
    "sg:address":"81031 Aversa",
    "sg:city":"Aversa",
    "sg:orig_category":"Studi E Consulenze Legali E Notarili. Avvocati, Notai E Servizi Legali. Professionisti - Studi E Servizi Ed Associazioni Di Interesse Aziendale",
    "sg:phone":"+39 081 811 3132",
    "sg:postcode":"81031",
    "sg:province":"Caserta",
    "wof:name":"Liscio Giuseppe",
    "wof:placetype":"venue"
},
  "geometry": {"coordinates":[14.206888,40.965054],"type":"Point"}
}