{
  "type": "Feature",
  "properties": {
    "iso:country":"IT",
    "sg:address":"43100 Parma",
    "sg:city":"Parma",
    "sg:orig_category":"Assicurazioni E Servizi Assicurativi",
    "sg:phone":"+39 0521 235560",
    "sg:postcode":"43100",
    "sg:province":"Parma",
    "wof:name":"Aon Nikols Srl",
    "wof:placetype":"venue"
},
  "geometry": {"coordinates":[10.328499,44.801086],"type":"Point"}
}