{
  "type": "Feature",
  "properties": {
    "addr:full":"Via Ai Campi 4 23849 Rogeno Rogeno Lecco 23849",
    "addr:housenumber":"4",
    "addr:postcode":"23849;23849",
    "addr:street":"Via Ai Campi",
    "iso:country":"IT",
    "sg:address":"Via Ai Campi 4 23849 Rogeno",
    "sg:city":"Rogeno",
    "sg:orig_category":"Dead-mould Castings",
    "sg:phone":"+39 031 876565",
    "sg:postcode":"23849",
    "sg:province":"Lecco",
    "wof:name":"Faser Spa",
    "wof:placetype":"venue"
},
  "geometry": {"coordinates":[9.280169,45.773521],"type":"Point"}
}