{
  "type": "Feature",
  "properties": {
    "addr:full":"84037 Sant'arsenio Salerno 84037",
    "addr:postcode":"84037;84037",
    "iso:country":"IT",
    "sg:address":"84037 Sant'arsenio",
    "sg:orig_category":"Materiali Edili",
    "sg:phone":"+39 0975 390975",
    "sg:postcode":"84037",
    "sg:province":"Salerno",
    "wof:name":"Service Impianti",
    "wof:placetype":"venue"
},
  "geometry": {"coordinates":[15.484839,40.467724],"type":"Point"}
}