{
  "type": "Feature",
  "properties": {
    "addr:full":"5, Via Martiri Di Montesole 40129 Bologna Bologna Bologna 40129",
    "addr:postcode":"40129;40129",
    "addr:street":"Via Martiri Di Montesole",
    "iso:country":"IT",
    "sg:address":"5, Via Martiri Di Montesole 40129 Bologna",
    "sg:city":"Bologna",
    "sg:classifiers":[
        {
            "category":"Shopping",
            "subcategory":"Computers & Home Electronics",
            "type":"Retail Goods"
        }
    ],
    "sg:phone":"+39 39051356065",
    "sg:postcode":"40129",
    "sg:province":"Bologna",
    "sg:tags":[
        "electronic",
        "electrical",
        "equipment"
    ],
    "wof:name":"C.e.m.a. Srl",
    "wof:placetype":"venue"
},
  "geometry": {"coordinates":[11.346481,44.494221],"type":"Point"}
}