{
  "type": "Feature",
  "properties": {
    "iso:country":"IT",
    "sg:address":"Via Nuova Cliternia 70 86042 Campomarino",
    "sg:city":"Campomarino",
    "sg:classifiers":[
        {
            "category":"Food & Beverages",
            "subcategory":"Liquor & Beverages",
            "type":"Retail Goods"
        }
    ],
    "sg:phone":"+39 0875 57106",
    "sg:postcode":"86042",
    "sg:province":"Campobasso",
    "sg:tags":[
        "wine",
        "italian"
    ],
    "sg:website":"www.cliternia.it",
    "wof:name":"Cantina Cliternia S.c.a.r.l.",
    "wof:placetype":"venue"
},
  "geometry": {"coordinates":[15.076275,41.89716],"type":"Point"}
}