{
  "type": "Feature",
  "properties": {
    "iso:country":"IT",
    "sg:address":"56, Via Palazzetto 33080 Prata Di Pordenone",
    "sg:city":"Prata di Pordenone",
    "sg:classifiers":[
        {
            "category":"Manufacturing",
            "subcategory":"Wood Products",
            "type":"Manufacturing & Wholesale Goods"
        }
    ],
    "sg:phone":"+39 0434 626740",
    "sg:postcode":"33080",
    "sg:province":"Pordenone",
    "sg:tags":[
        "furniture"
    ],
    "wof:name":"Ar-due S.p.a.",
    "wof:placetype":"venue"
},
  "geometry": {"coordinates":[12.559342,45.848175],"type":"Point"}
}