{
  "type": "Feature",
  "properties": {
    "iso:country":"IT",
    "sg:address":"00191 Roma",
    "sg:city":"Roma",
    "sg:orig_category":"Riparazione Dei Mezzi Di Trasporto",
    "sg:phone":"+39 06 333 3309",
    "sg:postcode":"00191",
    "sg:province":"Roma",
    "wof:name":"Autocarrozzeria F.lli De Clementi",
    "wof:placetype":"venue"
},
  "geometry": {"coordinates":[12.586015,42.107132],"type":"Point"}
}