{
  "type": "Feature",
  "properties": {
    "iso:country":"IT",
    "sg:address":"95122 Catania",
    "sg:city":"Catania",
    "sg:orig_category":"Servizi E Lavori Per Arredamento E Industria Del Legno",
    "sg:phone":"+39 095 472129",
    "sg:postcode":"95122",
    "sg:province":"Catania",
    "wof:name":"Arch Studio 1 Di Cosimo Tudisco",
    "wof:placetype":"venue"
},
  "geometry": {"coordinates":[15.039861,37.565239],"type":"Point"}
}