{
  "type": "Feature",
  "properties": {
    "iso:country":"IT",
    "sg:address":"70126 Bari",
    "sg:city":"Bari",
    "sg:orig_category":"Autogru - Noleggio",
    "sg:phone":"+39 080 546 1942",
    "sg:postcode":"70126",
    "sg:province":"Bari",
    "sg:website":"http://www.globser.it",
    "wof:name":"Global Service One Srl",
    "wof:placetype":"venue"
},
  "geometry": {"coordinates":[16.90365,41.08189],"type":"Point"}
}