{
  "type": "Feature",
  "properties": {
    "iso:country":"IT",
    "sg:address":"10036 Settimo Torinese",
    "sg:city":"Settimo Torinese",
    "sg:orig_category":"Manufacturers: Prefabbricati",
    "sg:phone":"+39 011 800 5258",
    "sg:postcode":"10036",
    "sg:province":"Torino",
    "wof:name":"C.m. S.a.s.industrial Plants Di Cernusco Lino & C.",
    "wof:placetype":"venue"
},
  "geometry": {"coordinates":[7.769189,45.138271],"type":"Point"}
}