{
  "type": "Feature",
  "properties": {
    "iso:country":"IT",
    "sg:address":"65124 Pescara",
    "sg:city":"Pescara",
    "sg:orig_category":"Banche E Servizi Finanziari",
    "sg:phone":"+39 085 422 2404",
    "sg:postcode":"65124",
    "sg:province":"Pescara",
    "wof:name":"Inter Services Leasing",
    "wof:placetype":"venue"
},
  "geometry": {"coordinates":[14.196591,42.476597],"type":"Point"}
}