{
  "type": "Feature",
  "properties": {
    "iso:country":"IT",
    "sg:address":"20124 Milano",
    "sg:city":"Milano",
    "sg:orig_category":"Scuole E Servizi Scolastici. Ricerca, Selezione E Formazione Del Personale",
    "sg:phone":"+39 02 669 1338",
    "sg:postcode":"20124",
    "sg:province":"Milano",
    "sg:website":"http://cti-communication.it",
    "wof:name":"C.t.i. Communication Trend Italia Di Brighenti Hugony",
    "wof:placetype":"venue"
},
  "geometry": {"coordinates":[9.2109,45.486671],"type":"Point"}
}