{
  "type": "Feature",
  "properties": {
    "iso:country":"IT",
    "sg:address":"50028 Tavarnelle Val Di Pesa",
    "sg:city":"Tavarnelle Val di Pesa",
    "sg:orig_category":"Galvanotecnica",
    "sg:phone":"+39 055 807 0047",
    "sg:postcode":"50028",
    "sg:province":"Firenze",
    "wof:name":"Zi.el. Di Mannini",
    "wof:placetype":"venue"
},
  "geometry": {"coordinates":[11.200813,43.589329],"type":"Point"}
}