{
  "type": "Feature",
  "properties": {
    "iso:country":"IT",
    "sg:address":"7, Via Tonale 24061 Albano Sant'alessandro",
    "sg:classifiers":[
        {
            "category":"Professional",
            "subcategory":"Engineering",
            "type":"Services"
        }
    ],
    "sg:phone":"+39 39035583158",
    "sg:postcode":"24061",
    "sg:province":"Bergamo",
    "sg:tags":[
        "machine",
        "-",
        "mechanical"
    ],
    "wof:name":"Cattaneo Presse Spa",
    "wof:placetype":"venue"
},
  "geometry": {"coordinates":[9.75059,45.687134],"type":"Point"}
}