{
  "type": "Feature",
  "properties": {
    "iso:country":"IT",
    "sg:address":"05100 Terni",
    "sg:city":"Terni",
    "sg:orig_category":"Arredamenti - Vendita Al Dettaglio",
    "sg:phone":"+39 0744 285621",
    "sg:postcode":"05100",
    "sg:province":"Terni",
    "wof:name":"Locci Lampadari",
    "wof:placetype":"venue"
},
  "geometry": {"coordinates":[12.637478,42.552937],"type":"Point"}
}