{
  "type": "Feature",
  "properties": {
    "iso:country":"IT",
    "sg:address":"12040 Vezza D'alba",
    "sg:city":"Montaldo Roero",
    "sg:orig_category":"Cancelli, Porte E Portoni Automatici E Telecomandati",
    "sg:phone":"+39 0173 65675",
    "sg:postcode":"12040",
    "sg:province":"Cuneo",
    "wof:name":"Careglio Luigi",
    "wof:placetype":"venue"
},
  "geometry": {"coordinates":[7.978616,44.757309],"type":"Point"}
}