{
  "type": "Feature",
  "properties": {
    "iso:country":"IT",
    "sg:address":"Via Gambellara 6 40026 Imola",
    "sg:city":"Imola",
    "sg:classifiers":[
        {
            "category":"Community Center",
            "type":"Public Place"
        }
    ],
    "sg:phone":"+39 0542 641450",
    "sg:postcode":"40026",
    "sg:province":"Bologna",
    "sg:tags":[
        "part",
        "spare",
        "excavator"
    ],
    "sg:website":"www.benati.it",
    "wof:name":"Imola Parts Srl",
    "wof:placetype":"venue"
},
  "geometry": {"coordinates":[11.749942,44.40868],"type":"Point"}
}