{
  "type": "Feature",
  "properties": {
    "iso:country":"IT",
    "sg:address":"Via Cabriolo 61 43036 Fidenza",
    "sg:city":"Fidenza",
    "sg:classifiers":[
        {
            "category":"Food & Beverages",
            "subcategory":"Fruits & Vegetables",
            "type":"Retail Goods"
        }
    ],
    "sg:phone":"+39 0524 528439",
    "sg:postcode":"43036",
    "sg:province":"Parma",
    "sg:tags":[
        "seed",
        "forage"
    ],
    "sg:website":"www.isisementi.com",
    "wof:name":"Isi Sementi S.p.a.",
    "wof:placetype":"venue"
},
  "geometry": {"coordinates":[10.0372009277,44.8451156616],"type":"Point"}
}