{
  "type": "Feature",
  "properties": {
    "iso:country":"IT",
    "sg:address":"43036 Fidenza",
    "sg:city":"Fidenza",
    "sg:classifiers":[
        {
            "category":"Manufacturing",
            "subcategory":"Metals",
            "type":"Manufacturing & Wholesale Goods"
        }
    ],
    "sg:phone":"+39 0524 520210",
    "sg:postcode":"43036",
    "sg:province":"Parma",
    "sg:tags":[
        "forming",
        "working",
        "welding"
    ],
    "wof:name":"E.t. System Srl",
    "wof:placetype":"venue"
},
  "geometry": {"coordinates":[10.0633993149,44.86460495],"type":"Point"}
}