{
  "type": "Feature",
  "properties": {
    "iso:country":"IT",
    "sg:address":"81022 Casagiove",
    "sg:city":"Casagiove",
    "sg:orig_category":"Forniture Per Attivita' Industriali",
    "sg:phone":"+39 0823 464073",
    "sg:postcode":"81022",
    "sg:province":"Caserta",
    "wof:name":"Centro Cuscinetti Srl",
    "wof:placetype":"venue"
},
  "geometry": {"coordinates":[14.3188209534,41.0760498047],"type":"Point"}
}