{
  "type": "Feature",
  "properties": {
    "iso:country":"IT",
    "sg:address":"Via Xx Settembre 196; Avezzano; 67051",
    "sg:classifiers":[
        {
            "category":"Banks & Credit Unions",
            "subcategory":"Bank",
            "type":"Services"
        }
    ],
    "sg:phone":"+39 0863 410715",
    "sg:postcode":"67051",
    "sg:province":"L'Aquila",
    "wof:name":"Banca Toscana Spa",
    "wof:placetype":"venue"
},
  "geometry": {"coordinates":[13.474299,42.04789],"type":"Point"}
}