{
  "type": "Feature",
  "properties": {
    "iso:country":"IT",
    "sg:address":"85/19, C. Pavia 27029 Vigevano",
    "sg:city":"Vigevano",
    "sg:classifiers":[
        {
            "category":"Shopping",
            "type":"Retail Goods"
        }
    ],
    "sg:phone":"+39 0381 344323",
    "sg:postcode":"27029",
    "sg:province":"Pavia",
    "sg:tags":[
        "finished",
        "-",
        "metallic"
    ],
    "sg:website":"http://www.paginegialle.it/matti",
    "wof:name":"Matti Srl",
    "wof:placetype":"venue"
},
  "geometry": {"coordinates":[9.1582317352,45.199848175],"type":"Point"}
}