{
  "type": "Feature",
  "properties": {
    "iso:country":"IT",
    "sg:address":"52045 Foiano Della Chiana",
    "sg:city":"Foiano della Chiana",
    "sg:orig_category":"Forniture Per Agricoltura E Zootecnia",
    "sg:phone":"+39 0575 642060",
    "sg:postcode":"52045",
    "sg:province":"Arezzo",
    "sg:website":"http://www.omeonauts.com",
    "wof:name":"Omeonatus Srl",
    "wof:placetype":"venue"
},
  "geometry": {"coordinates":[11.8093585968,43.2647781372],"type":"Point"}
}