{
  "type": "Feature",
  "properties": {
    "addr:full":"09018 Sarroch Sarroch Cagliari 09018",
    "addr:postcode":"09018;09018",
    "iso:country":"IT",
    "sg:address":"09018 Sarroch",
    "sg:city":"Sarroch",
    "sg:orig_category":"Petroli, Gas E Combustibili. Servizi E Lavori Industria Chimica",
    "sg:phone":"+39 070 906061",
    "sg:postcode":"09018",
    "sg:province":"Cagliari",
    "wof:name":"Sarlux Srl",
    "wof:placetype":"venue"
},
  "geometry": {"coordinates":[8.9907941818,39.0772590637],"type":"Point"}
}