{
  "type": "Feature",
  "properties": {
    "addr:full":"10, Viale Delle Industrie 33085 Maniago Maniago Pordenone 33085",
    "addr:housenumber":"10",
    "addr:postcode":"33085;33085",
    "addr:street":"Viale Delle Industrie",
    "iso:country":"IT",
    "sg:address":"10, Viale Delle Industrie 33085 Maniago",
    "sg:city":"Maniago",
    "sg:classifiers":[
        {
            "category":"Manufacturing",
            "subcategory":"Metals",
            "type":"Manufacturing & Wholesale Goods"
        }
    ],
    "sg:phone":"+39 0427 708111",
    "sg:postcode":"33085",
    "sg:province":"Pordenone",
    "sg:tags":[
        "metallurgy",
        "metalworking"
    ],
    "wof:name":"Zml Industries S.p.a.",
    "wof:placetype":"venue"
},
  "geometry": {"coordinates":[12.655043602,45.9626502991],"type":"Point"}
}