{
  "type": "Feature",
  "properties": {
    "iso:country":"IT",
    "sg:address":"40139 Bologna",
    "sg:city":"Bologna",
    "sg:orig_category":"Telecomunicazioni E Telefonia, Impianti, Apparecchi E Servizi",
    "sg:phone":"+39 051 454715",
    "sg:postcode":"40139",
    "sg:province":"Bologna",
    "wof:name":"Studio A.b. Di Antonio Benassi & C. Snc",
    "wof:placetype":"venue"
},
  "geometry": {"coordinates":[11.656878,44.977913],"type":"Point"}
}