{
  "type": "Feature",
  "properties": {
    "iso:country":"IT",
    "sg:address":"26013 Crema",
    "sg:city":"Crema",
    "sg:orig_category":"Servizi Vari Di Interesse Pubblico",
    "sg:phone":"+39 0373 81069",
    "sg:postcode":"26013",
    "sg:province":"Cremona",
    "wof:name":"Bio Energy",
    "wof:placetype":"venue"
},
  "geometry": {"coordinates":[9.685962,45.363461],"type":"Point"}
}