{
  "type": "Feature",
  "properties": {
    "addr:full":"Via Milano 1; Villaverla; 36030 Villaverla Vicenza 36030",
    "addr:housenumber":"1",
    "addr:postcode":"36030;36030",
    "addr:street":"Via Milano",
    "iso:country":"IT",
    "sg:address":"Via Milano 1; Villaverla; 36030",
    "sg:city":"Villaverla",
    "sg:classifiers":[
        {
            "category":"Banks & Credit Unions",
            "subcategory":"Bank",
            "type":"Services"
        }
    ],
    "sg:phone":"+39 0445 855622",
    "sg:postcode":"36030",
    "sg:province":"Vicenza",
    "wof:name":"Banca Popolare Vicentina Scparl",
    "wof:placetype":"venue"
},
  "geometry": {"coordinates":[11.494264,45.649097],"type":"Point"}
}