{
  "type": "Feature",
  "properties": {
    "iso:country":"IT",
    "sg:address":"02034 Montopoli Di Sabina",
    "sg:city":"Montopoli di Sabina",
    "sg:orig_category":"Insegne Luminose",
    "sg:phone":"+39 0765 444120",
    "sg:postcode":"02034",
    "sg:province":"Rieti",
    "wof:name":"Nero Luce Pubblicita' Snc",
    "wof:placetype":"venue"
},
  "geometry": {"coordinates":[12.692212,42.256763],"type":"Point"}
}