{
  "type": "Feature",
  "properties": {
    "iso:country":"IT",
    "sg:address":"20154 Milano",
    "sg:city":"Milano",
    "sg:orig_category":"Banche E Servizi Finanziari",
    "sg:phone":"+39 02 3360 0175",
    "sg:postcode":"20154",
    "sg:province":"Milano",
    "wof:name":"Signoroni Livio",
    "wof:placetype":"venue"
},
  "geometry": {"coordinates":[9.171506,45.483704],"type":"Point"}
}