{
  "type": "Feature",
  "properties": {
    "addr:full":"Via Vittorio Continelli 53, 72017 Ostuni, Br Ostuni Brindisi 72017",
    "addr:housenumber":"53",
    "addr:postcode":"72017;br;72017",
    "addr:street":"Via Vittorio Continelli",
    "iso:country":"IT",
    "sg:address":"Via Vittorio Continelli 53, 72017 Ostuni, Br",
    "sg:city":"Ostuni",
    "sg:classifiers":[
        {
            "category":"Banks & Credit Unions",
            "subcategory":"Bank",
            "type":"Services"
        }
    ],
    "sg:postcode":"72017",
    "sg:province":"Brindisi",
    "wof:name":"Cassa Rurale E Artigiana Di Ostuni (brindisi) Credito Cooperativo",
    "wof:placetype":"venue"
},
  "geometry": {"coordinates":[17.576349,40.727428],"type":"Point"}
}