{
  "type": "Feature",
  "properties": {
    "iso:country":"IT",
    "sg:address":"31048 S. Biagio Di Callalta",
    "sg:orig_category":"Bevande, Vini E Liquori. Shopping",
    "sg:phone":"+39 0422 895222",
    "sg:postcode":"31048",
    "sg:province":"Treviso",
    "wof:name":"Cantina Borgoverde Srl",
    "wof:placetype":"venue"
},
  "geometry": {"coordinates":[12.315576,45.667877],"type":"Point"}
}