{
  "type": "Feature",
  "properties": {
    "addr:full":"25030 Torbole Casaglia Torbole Casaglia Brescia 25030",
    "addr:postcode":"25030;25030",
    "iso:country":"IT",
    "sg:address":"25030 Torbole Casaglia",
    "sg:city":"Torbole Casaglia",
    "sg:orig_category":"Macchine E Forniture Per Arredamento E Industria Del Legno",
    "sg:phone":"+39 030 265 0866",
    "sg:postcode":"25030",
    "sg:province":"Brescia",
    "wof:name":"Ecomec S.r.l.",
    "wof:placetype":"venue"
},
  "geometry": {"coordinates":[10.125112,45.518379],"type":"Point"}
}