{
  "type": "Feature",
  "properties": {
    "iso:country":"IT",
    "sg:address":"63020 Falerone",
    "sg:city":"Falerone",
    "sg:classifiers":[
        {
            "category":"Bars & Pubs",
            "subcategory":"Wine Bar",
            "type":"Food & Drink"
        }
    ],
    "sg:phone":"+39 0734 750072",
    "sg:postcode":"63020",
    "sg:province":"Ascoli Piceno",
    "sg:tags":[
        "liqueur",
        "drinks"
    ],
    "wof:name":"Fermani Cannucce Di Tarulli & C. Snc",
    "wof:placetype":"venue"
},
  "geometry": {"coordinates":[13.719063,42.862637],"type":"Point"}
}