{
  "type": "Feature",
  "properties": {
    "addr:full":"53041 Asciano Arbia Siena 53041",
    "addr:postcode":"53041;53041",
    "iso:country":"IT",
    "sg:address":"53041 Asciano",
    "sg:city":"Arbia",
    "sg:orig_category":"Frigotecnica, Apparecchiature E Servizi",
    "sg:phone":"+39 0577 364605",
    "sg:postcode":"53041",
    "sg:province":"Siena",
    "wof:name":"Frigo Service Snc",
    "wof:placetype":"venue"
},
  "geometry": {"coordinates":[11.4073810577,43.2919006348],"type":"Point"}
}