{
  "type": "Feature",
  "properties": {
    "iso:country":"IT",
    "sg:address":"20060 Ornago",
    "sg:city":"Ornago",
    "sg:classifiers":[
        {
            "category":"Shopping",
            "type":"Retail Goods"
        }
    ],
    "sg:phone":"+39 039 601 0614",
    "sg:postcode":"20060",
    "sg:province":"Milano",
    "sg:tags":[
        "letti"
    ],
    "sg:website":"http://www.zandarin.it",
    "wof:name":"Zandarin Alfieri Egidio & C. Snc",
    "wof:placetype":"venue"
},
  "geometry": {"coordinates":[9.415168,45.617176],"type":"Point"}
}