{
  "type": "Feature",
  "properties": {
    "iso:country":"IT",
    "sg:address":"65, Via Rodi 25124 Brescia",
    "sg:city":"Brescia",
    "sg:classifiers":[
        {
            "category":"Sports & Exercise",
            "subcategory":"Playing Field",
            "type":"Entertainment"
        }
    ],
    "sg:phone":"+39 030 242 5410",
    "sg:postcode":"25124",
    "sg:province":"Brescia",
    "sg:tags":[
        "game"
    ],
    "wof:name":"Polis Planet",
    "wof:placetype":"venue"
},
  "geometry": {"coordinates":[10.207637,45.523193],"type":"Point"}
}