{
  "type": "Feature",
  "properties": {
    "addr:full":"60022 Castelfidardo Castelfidardo Ancona 60022",
    "addr:postcode":"60022;60022",
    "iso:country":"IT",
    "sg:address":"60022 Castelfidardo",
    "sg:city":"Castelfidardo",
    "sg:orig_category":"Utensili Meccanici E Materiali",
    "sg:phone":"+39 071 782 0410",
    "sg:postcode":"60022",
    "sg:province":"Ancona",
    "sg:website":"http://www.somipress.com",
    "wof:name":"So.m.i. Press Srl",
    "wof:placetype":"venue"
},
  "geometry": {"coordinates":[13.554281,43.524475],"type":"Point"}
}