{
  "type": "Feature",
  "properties": {
    "addr:full":"Via F. Guerrazzi, 7; Rimini; 47037",
    "addr:housenumber":"7",
    "addr:postcode":"47037",
    "addr:street":"Via F. Guerrazzi",
    "iso:country":"IT",
    "sg:address":"Via F. Guerrazzi, 7; Rimini; 47037",
    "sg:classifiers":[
        {
            "category":"Banks & Credit Unions",
            "subcategory":"Bank",
            "type":"Services"
        }
    ],
    "sg:phone":"+39 0541 51383",
    "wof:name":"Cassa Di Risparmio In Bologna",
    "wof:placetype":"venue"
},
  "geometry": {"coordinates":[12.570701,44.059193],"type":"Point"}
}