{
  "type": "Feature",
  "properties": {
    "iso:country":"IT",
    "sg:address":"66026 Ortona",
    "sg:city":"Ortona",
    "sg:classifiers":[
        {
            "category":"Health Services",
            "subcategory":"Health Practitioner",
            "type":"Services"
        }
    ],
    "sg:phone":"+39 085 906 6011",
    "sg:postcode":"66026",
    "sg:province":"Chieti",
    "sg:tags":[
        "medici"
    ],
    "wof:name":"De Grandis Dr. Enrico",
    "wof:placetype":"venue"
},
  "geometry": {"coordinates":[14.367553,42.334919],"type":"Point"}
}