{
  "type": "Feature",
  "properties": {
    "iso:country":"IT",
    "sg:address":"22070 Beregazzo Con Figliaro",
    "sg:city":"Beregazzo",
    "sg:orig_category":"Forniture Per Attivita' Industriali",
    "sg:phone":"+39 031 988643",
    "sg:postcode":"22070",
    "sg:province":"Como",
    "wof:name":"Abrasivi Corvi - S.n.c. Di Tullio E Giovanni Corvi",
    "wof:placetype":"venue"
},
  "geometry": {"coordinates":[8.9628314972,45.7686691284],"type":"Point"}
}