{
  "type": "Feature",
  "properties": {
    "iso:country":"IT",
    "sg:address":"33015 Moggio Udinese",
    "sg:city":"Moggio Udinese",
    "sg:orig_category":"Manutenzioni Tecnologiche Industriali",
    "sg:phone":"+39 0432 548890",
    "sg:postcode":"33015",
    "sg:province":"Udine",
    "wof:name":"Maintech Engineering Srl",
    "wof:placetype":"venue"
},
  "geometry": {"coordinates":[13.191398,46.469311],"type":"Point"}
}