{
  "type": "Feature",
  "properties": {
    "iso:country":"IT",
    "sg:address":"50122 Firenze",
    "sg:city":"Firenze",
    "sg:orig_category":"Arte Ed Artigianato Artistico. Scuole E Servizi Scolastici. Servizi Ausiliari Di Analisi, Controllo E Ricerca",
    "sg:phone":"+39 055 215449",
    "sg:postcode":"50122",
    "sg:province":"Firenze",
    "wof:name":"Accademia Di Belle Arti",
    "wof:placetype":"venue"
},
  "geometry": {"coordinates":[11.257667,43.775661],"type":"Point"}
}