{
  "type": "Feature",
  "properties": {
    "iso:country":"IT",
    "sg:address":"30172 Venezia",
    "sg:city":"Venezia",
    "sg:orig_category":"Ospedali E Servizi Sanitari",
    "sg:phone":"+39 041 976556",
    "sg:postcode":"30172",
    "sg:province":"Venezia",
    "wof:name":"Antismoking Center",
    "wof:placetype":"venue"
},
  "geometry": {"coordinates":[12.244048,45.485725],"type":"Point"}
}