{
  "type": "Feature",
  "properties": {
    "addr:full":"Via A. Righi 34 52100 Arezzo Arezzo Arezzo 52100",
    "addr:housenumber":"34",
    "addr:postcode":"52100;52100",
    "addr:street":"Via A. Righi",
    "iso:country":"IT",
    "sg:address":"Via A. Righi 34 52100 Arezzo",
    "sg:city":"Arezzo",
    "sg:orig_category":"Stone Jewellery, Genuine",
    "sg:phone":"+39 0575 383041",
    "sg:postcode":"52100",
    "sg:province":"Arezzo",
    "sg:website":"www.italpreziosi.it",
    "wof:name":"Italpreziosi Spa",
    "wof:placetype":"venue"
},
  "geometry": {"coordinates":[11.863062,43.471203],"type":"Point"}
}