{
  "type": "Feature",
  "properties": {
    "iso:country":"IT",
    "sg:address":"2, Via Doccio 13011 Borgosesia",
    "sg:city":"Borgosesia",
    "sg:classifiers":[
        {
            "category":"Shopping",
            "type":"Retail Goods"
        }
    ],
    "sg:phone":"+39 39016321514",
    "sg:postcode":"13011",
    "sg:province":"Vercelli",
    "sg:tags":[
        "finished",
        "-",
        "metallic"
    ],
    "wof:name":"Galloppini S.r.l.",
    "wof:placetype":"venue"
},
  "geometry": {"coordinates":[8.2597303391,45.7405281067],"type":"Point"}
}