{
  "type": "Feature",
  "properties": {
    "iso:country":"IT",
    "sg:address":"74015 Martina Franca",
    "sg:city":"Martina Franca",
    "sg:orig_category":"Ospedali E Servizi Sanitari",
    "sg:phone":"+39 080 483 8891",
    "sg:postcode":"74015",
    "sg:province":"Taranto",
    "wof:name":"Centro Di Fisioterapia Santa Rita",
    "wof:placetype":"venue"
},
  "geometry": {"coordinates":[17.338175,40.698101],"type":"Point"}
}