{
  "type": "Feature",
  "properties": {
    "addr:full":"Strada Tirabrasse 8 10060 Bricherasio Bricherasio Torino 10060",
    "addr:housenumber":"8",
    "addr:postcode":"10060;10060",
    "addr:street":"Strada Tirabrasse",
    "iso:country":"IT",
    "sg:address":"Strada Tirabrasse 8 10060 Bricherasio",
    "sg:city":"Bricherasio",
    "sg:classifiers":[
        {
            "category":"Building & Trades",
            "subcategory":"Construction",
            "type":"Services"
        }
    ],
    "sg:phone":"+39 0121 59638",
    "sg:postcode":"10060",
    "sg:province":"Torino",
    "sg:tags":[
        "carpenter's",
        "work",
        "supraregional"
    ],
    "sg:website":"www.cmi-srl.com",
    "wof:name":"C.m.i. Srl",
    "wof:placetype":"venue"
},
  "geometry": {"coordinates":[7.305986,44.833004],"type":"Point"}
}