{
  "type": "Feature",
  "properties": {
    "iso:country":"IT",
    "sg:address":"364, Via Cervese 47023 Cesena",
    "sg:city":"Cesena",
    "sg:classifiers":[
        {
            "category":"Food & Beverages",
            "subcategory":"Groceries & Convenience Stores",
            "type":"Retail Goods"
        }
    ],
    "sg:phone":"+39 0547 631150",
    "sg:postcode":"47023",
    "sg:province":"Forl\u00ec-Cesena",
    "sg:tags":[
        "product",
        "related"
    ],
    "wof:name":"La Cesenate (s.p.a.)",
    "wof:placetype":"venue"
},
  "geometry": {"coordinates":[12.2547893524,44.1467475891],"type":"Point"}
}