{
  "type": "Feature",
  "properties": {
    "iso:country":"IT",
    "sg:address":"13, Via Della Torretta 51016 Montecatini Terme",
    "sg:classifiers":[
        {
            "category":"Travel",
            "subcategory":"Travel Agent",
            "type":"Entertainment"
        }
    ],
    "sg:phone":"+39 0572 910860",
    "sg:postcode":"51016",
    "sg:province":"Pistoia",
    "sg:tags":[
        "business"
    ],
    "wof:name":"Albergo Metropole",
    "wof:placetype":"venue"
},
  "geometry": {"coordinates":[10.772028,43.886192],"type":"Point"}
}