{
  "type": "Feature",
  "properties": {
    "iso:country":"IT",
    "sg:address":"50127 Firenze",
    "sg:city":"Firenze",
    "sg:orig_category":"Macchine E Forniture Per Ecologia E Smaltimento Rifiuti. Ricambi E Componenti Dei Mezzi Di Trasporto",
    "sg:phone":"+39 055 436 0689",
    "sg:postcode":"50127",
    "sg:province":"Firenze",
    "wof:name":"Scarpa Francesco Supercar",
    "wof:placetype":"venue"
},
  "geometry": {"coordinates":[11.219728,43.791237],"type":"Point"}
}