{
  "type": "Feature",
  "properties": {
    "addr:full":"20089 Rozzano Rozzano Milano 20089",
    "addr:postcode":"20089;20089",
    "iso:country":"IT",
    "sg:address":"20089 Rozzano",
    "sg:city":"Rozzano",
    "sg:orig_category":"Abrasivi",
    "sg:phone":"+39 02 824 2915",
    "sg:postcode":"20089",
    "sg:province":"Milano",
    "wof:name":"Swedital Sas",
    "wof:placetype":"venue"
},
  "geometry": {"coordinates":[9.166514,45.400166],"type":"Point"}
}