{
  "type": "Feature",
  "properties": {
    "iso:country":"IT",
    "sg:address":"40055 Villanova",
    "sg:city":"Villanova",
    "sg:orig_category":"Macchine Utensili E Impianti. Elettrotecnica Industriale, Prodotti E Apparecchiature",
    "sg:phone":"+39 051 781727",
    "sg:postcode":"40055",
    "sg:province":"Bologna",
    "wof:name":"Iceb Saldatrici (s.r.l.)",
    "wof:placetype":"venue"
},
  "geometry": {"coordinates":[11.439301,44.504726],"type":"Point"}
}