{
  "type": "Feature",
  "properties": {
    "iso:country":"IT",
    "sg:address":"54100 Massa",
    "sg:city":"Marina di Massa",
    "sg:orig_category":"Legno E Semilavorati. Apparecchiature E Sistemi Per Magazzinaggio E Movimentazione",
    "sg:phone":"+39 0585 780052",
    "sg:postcode":"54100",
    "sg:province":"Massa-Carrara",
    "wof:name":"Marinari E Figli & C. Snc",
    "wof:placetype":"venue"
},
  "geometry": {"coordinates":[10.072093,44.03376],"type":"Point"}
}