{
  "type": "Feature",
  "properties": {
    "iso:country":"IT",
    "sg:address":"Via Leonardo Da Vinci 35 20094 Corsico",
    "sg:city":"Corsico",
    "sg:classifiers":[
        {
            "category":"Shopping",
            "subcategory":"Stationery & Office Supplies",
            "type":"Retail Goods"
        }
    ],
    "sg:phone":"+39 02 450 2946",
    "sg:postcode":"20094",
    "sg:province":"Milano",
    "sg:website":"www.zeuss.it",
    "wof:name":"Zeuss Srl",
    "wof:placetype":"venue"
},
  "geometry": {"coordinates":[9.108855,45.445999],"type":"Point"}
}