{
  "type": "Feature",
  "properties": {
    "iso:country":"IT",
    "sg:address":"Contrada Serramonda 88044 Marcellinara",
    "sg:city":"Marcellinara",
    "sg:classifiers":[
        {
            "category":"Parking",
            "subcategory":"Lot",
            "type":"Transportation"
        }
    ],
    "sg:phone":"+39 0961 996746",
    "sg:postcode":"88044",
    "sg:province":"Catanzaro",
    "sg:tags":[
        "transport",
        "road"
    ],
    "wof:name":"Trasporti Consegne Merci Srl",
    "wof:placetype":"venue"
},
  "geometry": {"coordinates":[16.587679,38.910599],"type":"Point"}
}