{
  "type": "Feature",
  "properties": {
    "addr:full":"10121 Torino Torino Torino 10121",
    "addr:postcode":"10121;10121",
    "iso:country":"IT",
    "sg:address":"10121 Torino",
    "sg:city":"Torino",
    "sg:orig_category":"Librerie",
    "sg:phone":"+39 011 546941",
    "sg:postcode":"10121",
    "sg:province":"Torino",
    "sg:website":"http://www.hellas.it",
    "wof:name":"Libreria Internazionale Hellas Di Amedeo Goria",
    "wof:placetype":"venue"
},
  "geometry": {"coordinates":[7.682478,45.069687],"type":"Point"}
}