{
  "type": "Feature",
  "properties": {
    "addr:full":"61100 Pesaro Pesaro Pesaro E Urbino 61100",
    "addr:postcode":"61100;61100",
    "iso:country":"IT",
    "sg:address":"61100 Pesaro",
    "sg:city":"Pesaro",
    "sg:orig_category":"Macchine E Forniture Per Arredamento E Industria Del Legno",
    "sg:phone":"+39 0721 281524",
    "sg:postcode":"61100",
    "sg:province":"Pesaro E Urbino",
    "wof:name":"Fam Costruzione Meccaniche Srl",
    "wof:placetype":"venue"
},
  "geometry": {"coordinates":[12.858275,43.876774],"type":"Point"}
}