{
  "type": "Feature",
  "properties": {
    "addr:full":"Via Sardegna 64/d-bienate 20020 Magnago Bienate Milano 20020",
    "addr:housenumber":"64 / d-bienate",
    "addr:postcode":"20020;20020",
    "addr:street":"Via Sardegna",
    "iso:country":"IT",
    "sg:address":"Via Sardegna 64/d-bienate 20020 Magnago",
    "sg:city":"Bienate",
    "sg:orig_category":"Slitter Rewinders",
    "sg:phone":"+39 0331 306482",
    "sg:postcode":"20020",
    "sg:province":"Milano",
    "sg:website":"www.slitters-rewinders.com",
    "wof:name":"Officina Meccanica F.e.b.a. Di Ferraresi Enzo & C. S.n.c.",
    "wof:placetype":"venue"
},
  "geometry": {"coordinates":[9.188141,45.463688],"type":"Point"}
}