{
  "type": "Feature",
  "properties": {
    "iso:country":"IT",
    "sg:address":"20127 Milano",
    "sg:city":"Milano",
    "sg:orig_category":"Abbigliamento Esterno, Maglierie E Pelliccerie. Servizi E Lavori Per Abbigliamento E Pelletterie",
    "sg:phone":"+39 02 282 2013",
    "sg:postcode":"20127",
    "sg:province":"Milano",
    "wof:name":"Pellegrino Olindo",
    "wof:placetype":"venue"
},
  "geometry": {"coordinates":[9.231127,45.49757],"type":"Point"}
}