{
  "type": "Feature",
  "properties": {
    "iso:country":"IT",
    "sg:address":"23826 Mandello Del Lario",
    "sg:city":"Mandello del Lario",
    "sg:classifiers":[
        {
            "category":"Utilities",
            "subcategory":"Natural Gas",
            "type":"Services"
        }
    ],
    "sg:phone":"+39 0341 738211",
    "sg:postcode":"23826",
    "sg:province":"Lecco",
    "sg:tags":[
        "alloy",
        "metal"
    ],
    "wof:name":"Antonio Carcano Spa",
    "wof:placetype":"venue"
},
  "geometry": {"coordinates":[9.3227157593,45.9254798889],"type":"Point"}
}