{
  "type": "Feature",
  "properties": {
    "iso:country":"IT",
    "sg:address":"20095 Cusano Milanino",
    "sg:city":"Cusano Milanino",
    "sg:orig_category":"Impianti, Attrezzature E Forniture Sanitarie Ed Ospedaliere",
    "sg:phone":"+39 02 6640 1060",
    "sg:postcode":"20095",
    "sg:province":"Milano",
    "wof:name":"Alfa Hospital Snc",
    "wof:placetype":"venue"
},
  "geometry": {"coordinates":[9.176785,45.550339],"type":"Point"}
}