{
  "type": "Feature",
  "properties": {
    "iso:country":"IT",
    "sg:address":"20127 Milano",
    "sg:city":"Milano",
    "sg:orig_category":"Metalli E Leghe. Gioielleria, Oreficeria E Argenteria",
    "sg:phone":"+39 02 289 2956",
    "sg:postcode":"20127",
    "sg:province":"Milano",
    "wof:name":"Ta.va. (s.a.s.)",
    "wof:placetype":"venue"
},
  "geometry": {"coordinates":[9.2202444077,45.5030822754],"type":"Point"}
}