{
  "type": "Feature",
  "properties": {
    "iso:country":"IT",
    "sg:address":"20017 Rho",
    "sg:city":"Rho",
    "sg:orig_category":"Apparecchiature E Sistemi Per Imballaggio E Confezionamento",
    "sg:phone":"+39 02 9350 6686",
    "sg:postcode":"20017",
    "sg:province":"Milano",
    "wof:name":"Rhopack (s.n.c.)",
    "wof:placetype":"venue"
},
  "geometry": {"coordinates":[9.204217,45.464489],"type":"Point"}
}