{
  "type": "Feature",
  "properties": {
    "iso:country":"IT",
    "sg:address":"56121 Pisa",
    "sg:city":"Pisa",
    "sg:orig_category":"Manufacturers: Prefabbricati",
    "sg:phone":"+39 050 974111",
    "sg:postcode":"56121",
    "sg:province":"Pisa",
    "wof:name":"Cocchini Paola",
    "wof:placetype":"venue"
},
  "geometry": {"coordinates":[10.43845,43.683533],"type":"Point"}
}