{
  "type": "Feature",
  "properties": {
    "iso:country":"IT",
    "sg:address":"Palazzo Centi, Pizza S. Giusta, 67100 L'aquila, Aq",
    "sg:classifiers":[
        {
            "category":"Banks & Credit Unions",
            "subcategory":"Bank",
            "type":"Services"
        }
    ],
    "sg:postcode":"67100",
    "sg:province":"L'Aquila",
    "wof:name":"Abruzzo Capital Spa",
    "wof:placetype":"venue"
},
  "geometry": {"coordinates":[13.396531,42.351955],"type":"Point"}
}