{
  "type": "Feature",
  "properties": {
    "iso:country":"IT",
    "sg:address":"46010 Curtatone",
    "sg:city":"Buscoldo",
    "sg:orig_category":"Fognature",
    "sg:phone":"+39 0376 48024",
    "sg:postcode":"46010",
    "sg:province":"Mantova",
    "wof:name":"Capiluppi Olindo Di Capiluppi Enzo & C. Snc",
    "wof:placetype":"venue"
},
  "geometry": {"coordinates":[10.700917244,45.0948410034],"type":"Point"}
}