{
  "type": "Feature",
  "properties": {
    "addr:full":"32030 Quero Quero Belluno 32030",
    "addr:postcode":"32030;32030",
    "iso:country":"IT",
    "sg:address":"32030 Quero",
    "sg:city":"Quero",
    "sg:orig_category":"Lampadari - Produzione E Ingrosso",
    "sg:phone":"+39 0439 787029",
    "sg:postcode":"32030",
    "sg:province":"Belluno",
    "wof:name":"Favero Fratelli Snc",
    "wof:placetype":"venue"
},
  "geometry": {"coordinates":[11.93276,45.916439],"type":"Point"}
}