{
  "type": "Feature",
  "properties": {
    "addr:full":"24060 Villongo Villongo Bergamo 24060",
    "addr:postcode":"24060;24060",
    "iso:country":"IT",
    "sg:address":"24060 Villongo",
    "sg:city":"Villongo",
    "sg:orig_category":"Non-classified Establishments",
    "sg:phone":"+39 035 928107",
    "sg:postcode":"24060",
    "sg:province":"Bergamo",
    "wof:name":"Oldrati Giulio S.r.l.",
    "wof:placetype":"venue"
},
  "geometry": {"coordinates":[9.743482,45.738827],"type":"Point"}
}