{
  "type": "Feature",
  "properties": {
    "iso:country":"IT",
    "sg:address":"35020 Casalserugo",
    "sg:city":"Casalserugo",
    "sg:orig_category":"Impermeabilizzazioni Edili - Lavori",
    "sg:phone":"+39 049 950 1429",
    "sg:postcode":"35020",
    "sg:province":"Padova",
    "wof:name":"Italian Service Di Cesare Cecchinato",
    "wof:placetype":"venue"
},
  "geometry": {"coordinates":[11.910492,45.324577],"type":"Point"}
}