{
  "type": "Feature",
  "properties": {
    "addr:full":"21, V. Dell'artigianato 60027 Osimo Osimo Ancona 60027",
    "addr:housenumber":"21",
    "addr:postcode":"60027;60027",
    "addr:street":"V. Dell'Artigianato",
    "iso:country":"IT",
    "sg:address":"21, V. Dell'artigianato 60027 Osimo",
    "sg:city":"Osimo",
    "sg:classifiers":[
        {
            "category":"Real Estate",
            "subcategory":"Surveying",
            "type":"Services"
        }
    ],
    "sg:phone":"+39 071 723 0776",
    "sg:postcode":"60027",
    "sg:province":"Ancona",
    "sg:tags":[
        "equipment",
        "material",
        "good",
        "-",
        "handling"
    ],
    "sg:website":"http://www.paginegialle.it/adrservice-01",
    "wof:name":"Adriatica Service",
    "wof:placetype":"venue"
},
  "geometry": {"coordinates":[13.518757,43.615856],"type":"Point"}
}