{
  "type": "Feature",
  "properties": {
    "addr:full":"Via Sotto Sengia 8 37010 Sant Ambrogio Di Valpolicella Verona 37010",
    "addr:housenumber":"8",
    "addr:postcode":"37010;37010",
    "addr:street":"Via Sotto Sengia",
    "iso:country":"IT",
    "sg:address":"Via Sotto Sengia 8 37010 Sant Ambrogio Di Valpolicella",
    "sg:classifiers":[
        {
            "category":"Home & Garden",
            "subcategory":"Building Materials",
            "type":"Retail Goods"
        }
    ],
    "sg:phone":"+39 045 688 8569",
    "sg:postcode":"37010",
    "sg:province":"Verona",
    "sg:tags":[
        "tile",
        "marble"
    ],
    "sg:website":"www.rivamarmi.it",
    "wof:name":"Ri.va Marmi Di Righetti G. E C. S.n.c.",
    "wof:placetype":"venue"
},
  "geometry": {"coordinates":[10.991748,45.438366],"type":"Point"}
}