{
  "type": "Feature",
  "properties": {
    "addr:full":"63013 Grottammare Grottammare Ascoli Piceno 63013",
    "addr:postcode":"63013;63013",
    "iso:country":"IT",
    "sg:address":"63013 Grottammare",
    "sg:city":"Grottammare",
    "sg:orig_category":"Elettronica Industriale, Prodotti E Apparecchiature",
    "sg:phone":"+39 0735 735033",
    "sg:postcode":"63013",
    "sg:province":"Ascoli Piceno",
    "sg:website":"http://www.cs2.it",
    "wof:name":"Control Systems 2 Srl",
    "wof:placetype":"venue"
},
  "geometry": {"coordinates":[13.869921,42.975586],"type":"Point"}
}