{
  "type": "Feature",
  "properties": {
    "iso:country":"IT",
    "sg:address":"1, Via A. Capitini 43038 Sala Baganza",
    "sg:city":"Sala Baganza",
    "sg:classifiers":[
        {
            "category":"Manufacturing",
            "subcategory":"Motor Vehicles & Parts",
            "type":"Manufacturing & Wholesale Goods"
        }
    ],
    "sg:phone":"+39 0521 836159",
    "sg:postcode":"43038",
    "sg:province":"Parma",
    "sg:tags":[
        "engine"
    ],
    "wof:name":"S.a.r.m.e. (s.r.l.)",
    "wof:placetype":"venue"
},
  "geometry": {"coordinates":[10.23455,44.719299],"type":"Point"}
}