{
  "type": "Feature",
  "properties": {
    "addr:full":"Via Mure , 75 - Caselle Di Altivole 31030 Altivole Altivole Treviso 31030",
    "addr:housenumber":"75",
    "addr:postcode":"31030;31030",
    "addr:street":"Via Mure",
    "iso:country":"IT",
    "sg:address":"Via Mure , 75 - Caselle Di Altivole 31030 Altivole",
    "sg:city":"Altivole",
    "sg:classifiers":[
        {
            "category":"Sports & Exercise",
            "subcategory":"Bicycle Rental",
            "type":"Entertainment"
        }
    ],
    "sg:phone":"+39 0423 566268",
    "sg:postcode":"31030",
    "sg:province":"Treviso",
    "sg:tags":[
        "boot",
        "shoes",
        "leisure"
    ],
    "sg:website":"www.askew.it",
    "wof:name":"Askew S.r.l.",
    "wof:placetype":"venue"
},
  "geometry": {"coordinates":[12.242072,45.666286],"type":"Point"}
}