{
  "type": "Feature",
  "properties": {
    "iso:country":"IT",
    "sg:address":"60019 Senigallia",
    "sg:city":"Senigallia",
    "sg:orig_category":"Acquari Ornamentali Ed Accessori",
    "sg:phone":"+39 071 967045",
    "sg:postcode":"60019",
    "sg:province":"Ancona",
    "wof:name":"Casagrande Cinzia",
    "wof:placetype":"venue"
},
  "geometry": {"coordinates":[13.197106,43.68961],"type":"Point"}
}