{
  "type": "Feature",
  "properties": {
    "iso:country":"IT",
    "sg:address":"35132 Padova",
    "sg:city":"Padova",
    "sg:orig_category":"Articoli Pulizia",
    "sg:phone":"+39 049 604347",
    "sg:postcode":"35132",
    "sg:province":"Padova",
    "wof:name":"Giacometti Elisabetta",
    "wof:placetype":"venue"
},
  "geometry": {"coordinates":[11.795707,45.366764],"type":"Point"}
}