{
  "type": "Feature",
  "properties": {
    "iso:country":"IT",
    "sg:address":"20017 Rho",
    "sg:city":"Rho",
    "sg:orig_category":"Macchine, Strumenti Ed Apparecchi Per Attivita' Industriali",
    "sg:phone":"+39 02 9350 7111",
    "sg:postcode":"20017",
    "sg:province":"Milano",
    "wof:name":"Gamma Ind. Srl",
    "wof:placetype":"venue"
},
  "geometry": {"coordinates":[9.041696,45.535141],"type":"Point"}
}