{
  "type": "Feature",
  "properties": {
    "addr:full":"70121 Bari Bari Bari 70121",
    "addr:postcode":"70121;70121",
    "iso:country":"IT",
    "sg:address":"70121 Bari",
    "sg:city":"Bari",
    "sg:orig_category":"Banche E Servizi Finanziari",
    "sg:phone":"+39 080 523 5654",
    "sg:postcode":"70121",
    "sg:province":"Bari",
    "wof:name":"International Factors Italia (s.p.a.)",
    "wof:placetype":"venue"
},
  "geometry": {"coordinates":[16.872547,41.075459],"type":"Point"}
}