{
  "type": "Feature",
  "properties": {
    "iso:country":"IT",
    "sg:address":"98100 Messina",
    "sg:orig_category":"Bevande, Vini E Liquori",
    "sg:phone":"+39 090 621339",
    "sg:province":"ME",
    "wof:name":"Inagrus (s.a.s.)",
    "wof:placetype":"venue"
},
  "geometry": {"coordinates":[15.535219,38.157558],"type":"Point"}
}