{
  "type": "Feature",
  "properties": {
    "addr:full":"123, Via Marx Carlo 60022 Castelfidardo Castelfidardo Ancona 60022",
    "addr:housenumber":"123",
    "addr:postcode":"60022;60022",
    "addr:street":"Via Marx Carlo",
    "iso:country":"IT",
    "sg:address":"123, Via Marx Carlo 60022 Castelfidardo",
    "sg:city":"Castelfidardo",
    "sg:classifiers":[
        {
            "category":"Food & Beverages",
            "subcategory":"Groceries & Convenience Stores",
            "type":"Retail Goods"
        }
    ],
    "sg:phone":"+39 071 782 0163",
    "sg:postcode":"60022",
    "sg:province":"Ancona",
    "sg:tags":[
        "drink"
    ],
    "wof:name":"Garofoli Gioacchino Casa Vinicola Spa",
    "wof:placetype":"venue"
},
  "geometry": {"coordinates":[13.518757,43.615856],"type":"Point"}
}