{
  "type": "Feature",
  "properties": {
    "iso:country":"IT",
    "sg:address":"25131 Brescia",
    "sg:city":"Brescia",
    "sg:classifiers":[
        {
            "category":"Building & Trades",
            "subcategory":"Construction",
            "type":"Services"
        }
    ],
    "sg:phone":"+39 030 358 3999",
    "sg:postcode":"25131",
    "sg:province":"Brescia",
    "sg:tags":[
        "civil",
        "industry",
        "work",
        "wood",
        "furnishing",
        "works"
    ],
    "sg:website":"http://www.podavini.it",
    "wof:name":"Podavini Giuseppe - Legnami",
    "wof:placetype":"venue"
},
  "geometry": {"coordinates":[10.1595878601,45.5018806458],"type":"Point"}
}