{
  "type": "Feature",
  "properties": {
    "iso:country":"IT",
    "sg:address":"13030 Caresanablot",
    "sg:city":"Caresanablot",
    "sg:orig_category":"Agricoltura - Attrezzi, Prodotti E Forniture",
    "sg:phone":"+39 0161 33381",
    "sg:postcode":"13030",
    "sg:province":"Vercelli",
    "wof:name":"Valerio Snc",
    "wof:placetype":"venue"
},
  "geometry": {"coordinates":[8.395016,45.353222],"type":"Point"}
}