{
  "type": "Feature",
  "properties": {
    "addr:full":"27036 Mortara Mortara Pavia 27036",
    "addr:postcode":"27036;27036",
    "iso:country":"IT",
    "sg:address":"27036 Mortara",
    "sg:city":"Mortara",
    "sg:orig_category":"Certificazione Qualita', Sicurezza Ed Ambiente",
    "sg:phone":"+39 0384 296851",
    "sg:postcode":"27036",
    "sg:province":"Pavia",
    "sg:website":"http://www.paginegialle.it/rfmquality",
    "wof:name":"Rfm Quality Srl",
    "wof:placetype":"venue"
},
  "geometry": {"coordinates":[8.740982,45.242462],"type":"Point"}
}