{
  "type": "Feature",
  "properties": {
    "iso:country":"IT",
    "sg:address":"Strada Garella 34 13900 Biella",
    "sg:city":"Biella",
    "sg:classifiers":[
        {
            "category":"Professional",
            "subcategory":"Business Services",
            "type":"Services"
        }
    ],
    "sg:phone":"+39 015 21995",
    "sg:postcode":"13900",
    "sg:province":"Biella",
    "sg:tags":[
        "high-precision",
        "mechanic"
    ],
    "wof:name":"Officina Mecc. Azeglio Meini Srl",
    "wof:placetype":"venue"
},
  "geometry": {"coordinates":[8.041296,45.57378],"type":"Point"}
}