{
  "type": "Feature",
  "properties": {
    "iso:country":"IT",
    "sg:address":"00164 Roma",
    "sg:city":"Roma",
    "sg:orig_category":"Amplificazione Sonora",
    "sg:phone":"+39 06 6615 0858",
    "sg:postcode":"00164",
    "sg:province":"Roma",
    "sg:website":"http://www.orangesrl.it",
    "wof:name":"Orange Srl",
    "wof:placetype":"venue"
},
  "geometry": {"coordinates":[12.418977,41.871704],"type":"Point"}
}