{
  "type": "Feature",
  "properties": {
    "iso:country":"IT",
    "sg:address":"76, Via Napoli 80013 Casalnuovo Di Napoli",
    "sg:city":"Casalnuovo di Napoli",
    "sg:classifiers":[
        {
            "category":"Personal",
            "subcategory":"Shoe Repair & Shine",
            "type":"Services"
        }
    ],
    "sg:phone":"+39 081 522 4579",
    "sg:postcode":"80013",
    "sg:province":"Napoli",
    "sg:tags":[
        "leather"
    ],
    "wof:name":"Web's S.r.l.",
    "wof:placetype":"venue"
},
  "geometry": {"coordinates":[14.337605,40.907459],"type":"Point"}
}