{
  "type": "Feature",
  "properties": {
    "iso:country":"IT",
    "sg:address":"Via S. Carlo 13 20010 Bareggio",
    "sg:city":"Bareggio",
    "sg:classifiers":[
        {
            "category":"Transit Center",
            "subcategory":"Passenger",
            "type":"Transportation"
        }
    ],
    "sg:phone":"+39 02 903681",
    "sg:postcode":"20010",
    "sg:province":"Milano",
    "sg:tags":[
        "lift",
        "elevator"
    ],
    "sg:website":"www.semag.com",
    "wof:name":"Semag Spa",
    "wof:placetype":"venue"
},
  "geometry": {"coordinates":[9.0273704529,45.503818512],"type":"Point"}
}