{
  "type": "Feature",
  "properties": {
    "iso:country":"IT",
    "sg:address":"28100 Novara",
    "sg:city":"Novara",
    "sg:orig_category":"Scuole E Servizi Scolastici. Ricerca, Selezione E Formazione Del Personale",
    "sg:phone":"+39 0321 611070",
    "sg:postcode":"28100",
    "sg:province":"Novara",
    "wof:name":"Istituto Tecnico Galileo Galilei",
    "wof:placetype":"venue"
},
  "geometry": {"coordinates":[8.621308,45.450062],"type":"Point"}
}