{
  "type": "Feature",
  "properties": {
    "iso:country":"IT",
    "sg:address":"Km. 36.200, Via Nazionale Puglie 80013 Casalnuovo Di Napoli",
    "sg:city":"Casalnuovo di Napoli",
    "sg:orig_category":"Miscellaneous Products",
    "sg:phone":"+39 081 522 4885",
    "sg:postcode":"80013",
    "sg:province":"Napoli",
    "wof:name":"Boni Srl",
    "wof:placetype":"venue"
},
  "geometry": {"coordinates":[14.2516355515,40.84009552],"type":"Point"}
}