{
  "type": "Feature",
  "properties": {
    "iso:country":"IT",
    "sg:address":"1, Via Bessanese 10073 Cirie'",
    "sg:classifiers":[
        {
            "category":"Home & Garden",
            "subcategory":"Home Furnishings",
            "type":"Retail Goods"
        }
    ],
    "sg:phone":"+39 011 921 0326",
    "sg:postcode":"10073",
    "sg:province":"Torino",
    "sg:tags":[
        "household"
    ],
    "wof:name":"Arme (s.r.l.)",
    "wof:placetype":"venue"
},
  "geometry": {"coordinates":[7.594744,45.230419],"type":"Point"}
}