{
  "type": "Feature",
  "properties": {
    "iso:country":"IT",
    "sg:address":"20124 Milano",
    "sg:city":"Milano",
    "sg:orig_category":"Ospedali E Servizi Sanitari",
    "sg:phone":"+39 02 6680 6753",
    "sg:postcode":"20124",
    "sg:province":"Milano",
    "wof:name":"A.i.a.s.a. Societa' Cooperativa Sociale Arl",
    "wof:placetype":"venue"
},
  "geometry": {"coordinates":[9.194081,45.493736],"type":"Point"}
}