{
  "type": "Feature",
  "properties": {
    "iso:country":"IT",
    "sg:address":"22070 Cirimido",
    "sg:city":"Cirimido",
    "sg:orig_category":"Prodotti Chimici Di Base. Prodotti Cosmetici E Da Toeletta",
    "sg:phone":"+39 031 895290",
    "sg:postcode":"22070",
    "sg:province":"Como",
    "wof:name":"Sirdoc (s.r.l.)",
    "wof:placetype":"venue"
},
  "geometry": {"coordinates":[9.015912056,45.7018165588],"type":"Point"}
}