{
  "type": "Feature",
  "properties": {
    "addr:full":"23, Via Mart. Liberta' 31016 Cordignano Cordignano Treviso 31016",
    "addr:postcode":"31016;31016",
    "addr:street":"Via Mart. Liberta '",
    "iso:country":"IT",
    "sg:address":"23, Via Mart. Liberta' 31016 Cordignano",
    "sg:city":"Cordignano",
    "sg:classifiers":[
        {
            "category":"Shopping",
            "subcategory":"Stationery & Office Supplies",
            "type":"Retail Goods"
        }
    ],
    "sg:phone":"+39 0438 995450",
    "sg:postcode":"31016",
    "sg:province":"Treviso",
    "sg:tags":[
        "professional"
    ],
    "wof:name":"Toffoli Francesco (s.p.a.)",
    "wof:placetype":"venue"
},
  "geometry": {"coordinates":[12.2420721054,45.6662864685],"type":"Point"}
}