{
  "type": "Feature",
  "properties": {
    "iso:country":"IT",
    "sg:address":"50, Viale Odorico Da Pordenone 95126 Catania",
    "sg:city":"Catania",
    "sg:classifiers":[
        {
            "category":"Manufacturing",
            "subcategory":"Printing",
            "type":"Manufacturing & Wholesale Goods"
        }
    ],
    "sg:phone":"+39 39095222343",
    "sg:postcode":"95126",
    "sg:province":"Catania",
    "sg:tags":[
        "publishing"
    ],
    "wof:name":"Societa' Editoriale Meridionale S.r.l.",
    "wof:placetype":"venue"
},
  "geometry": {"coordinates":[15.0852365494,37.5278358459],"type":"Point"}
}