{
  "type": "Feature",
  "properties": {
    "addr:full":"00198 Roma Roma Roma 00198",
    "addr:postcode":"00198;00198",
    "iso:country":"IT",
    "sg:address":"00198 Roma",
    "sg:city":"Roma",
    "sg:classifiers":[
        {
            "category":"Utilities",
            "subcategory":"Mobile Phone",
            "type":"Services"
        }
    ],
    "sg:phone":"+39 06 841 3273",
    "sg:postcode":"00198",
    "sg:province":"Roma",
    "sg:tags":[
        "equipment",
        "telecommunication",
        "systems",
        "telephony"
    ],
    "sg:website":"http://www.easyline.it",
    "wof:name":"Easy Line By Gruppo Ricci Srl",
    "wof:placetype":"venue"
},
  "geometry": {"coordinates":[12.504273,41.920948],"type":"Point"}
}