{
  "type": "Feature",
  "properties": {
    "iso:country":"IT",
    "sg:address":"20019 Settimo Milanese",
    "sg:city":"Settimo Milanese",
    "sg:orig_category":"Lavorazioni Metalli, Stampaggio E Saldatura",
    "sg:phone":"+39 02 4892 9147",
    "sg:postcode":"20019",
    "sg:province":"Milano",
    "wof:name":"M.c.s. Meccanica Casanova Settimo Srl",
    "wof:placetype":"venue"
},
  "geometry": {"coordinates":[9.069446,45.466522],"type":"Point"}
}