{
  "type": "Feature",
  "properties": {
    "iso:country":"IT",
    "sg:address":"36040 Brendola",
    "sg:city":"Brendola",
    "sg:orig_category":"Ricambi E Componenti Dei Mezzi Di Trasporto",
    "sg:phone":"+39 0444 401001",
    "sg:postcode":"36040",
    "sg:province":"Vicenza",
    "wof:name":"Autoelettric Srl",
    "wof:placetype":"venue"
},
  "geometry": {"coordinates":[11.539657,45.553268],"type":"Point"}
}