{
  "type": "Feature",
  "properties": {
    "iso:country":"IT",
    "sg:address":"56022 Castelfranco Di Sotto",
    "sg:city":"Castelfranco di Sotto",
    "sg:orig_category":"Calzature - Produzione E Ingrosso",
    "sg:phone":"+39 0571 47407",
    "sg:postcode":"56022",
    "sg:province":"Pisa",
    "sg:website":"http://www.martiniosvaldo.it",
    "wof:name":"Martini Osvaldo Spa",
    "wof:placetype":"venue"
},
  "geometry": {"coordinates":[10.692881,43.770073],"type":"Point"}
}