{
  "type": "Feature",
  "properties": {
    "iso:country":"IT",
    "sg:address":"Ss S. Marino 50 47900 Rimini",
    "sg:city":"Rimini",
    "sg:classifiers":[
        {
            "category":"Government",
            "subcategory":"Court House",
            "type":"Public Place"
        }
    ],
    "sg:phone":"+39 0541 751162",
    "sg:postcode":"47900",
    "sg:province":"Rimini",
    "sg:tags":[
        "accommodation",
        "furniture"
    ],
    "wof:name":"Fecit Dei Fratelli Cupioli Snc",
    "wof:placetype":"venue"
},
  "geometry": {"coordinates":[12.566257,44.06078],"type":"Point"}
}