{
  "type": "Feature",
  "properties": {
    "iso:country":"IT",
    "sg:address":"00172 Roma",
    "sg:city":"Roma",
    "sg:orig_category":"Scuole E Servizi Scolastici. Centri Di Estetica E Cosmesi E Servizi. Ricerca, Selezione E Formazione Del Personale",
    "sg:phone":"+39 06 231 0589",
    "sg:postcode":"00172",
    "sg:province":"Roma",
    "wof:name":"Pazienza Oliviero",
    "wof:placetype":"venue"
},
  "geometry": {"coordinates":[12.566829,41.878117],"type":"Point"}
}