{
  "type": "Feature",
  "properties": {
    "addr:full":"Via Cristoforo Colombo 25013 Carpenedolo Carpenedolo Brescia 25013",
    "addr:postcode":"25013;25013",
    "addr:street":"Via Cristoforo Colombo",
    "iso:country":"IT",
    "sg:address":"Via Cristoforo Colombo 25013 Carpenedolo",
    "sg:city":"Carpenedolo",
    "sg:classifiers":[
        {
            "category":"Shopping",
            "type":"Retail Goods"
        }
    ],
    "sg:phone":"+39 030 996 6412",
    "sg:postcode":"25013",
    "sg:province":"Brescia",
    "sg:tags":[
        "finished",
        "-",
        "metallic"
    ],
    "wof:name":"Mak (s.r.l.)",
    "wof:placetype":"venue"
},
  "geometry": {"coordinates":[10.435962677,45.3500099182],"type":"Point"}
}