{
  "type": "Feature",
  "properties": {
    "addr:full":"20, Via Trento 09025 Sanluri Sanluri Medio Campidano 09025",
    "addr:postcode":"09025;09025",
    "addr:street":"Via Trento",
    "iso:country":"IT",
    "sg:address":"20, Via Trento 09025 Sanluri",
    "sg:city":"Sanluri",
    "sg:classifiers":[
        {
            "category":"Food & Beverages",
            "subcategory":"Groceries & Convenience Stores",
            "type":"Retail Goods"
        }
    ],
    "sg:phone":"+39 070 930 7777",
    "sg:postcode":"09025",
    "sg:province":"Medio Campidano",
    "sg:tags":[
        "product",
        "related"
    ],
    "wof:name":"Surgelfood S.r.l.",
    "wof:placetype":"venue"
},
  "geometry": {"coordinates":[8.9081878662,39.4807815552],"type":"Point"}
}