{
  "type": "Feature",
  "properties": {
    "addr:full":"15, Via Monte Bisbino 20021 Bollate Bollate Milano 20021",
    "addr:postcode":"20021;20021",
    "addr:street":"Via Monte Bisbino",
    "iso:country":"IT",
    "sg:address":"15, Via Monte Bisbino 20021 Bollate",
    "sg:city":"Bollate",
    "sg:classifiers":[
        {
            "category":"Manufacturing",
            "subcategory":"Printing",
            "type":"Manufacturing & Wholesale Goods"
        }
    ],
    "sg:phone":"+39 39023561868",
    "sg:postcode":"20021",
    "sg:province":"Milano",
    "sg:tags":[
        "publishing"
    ],
    "wof:name":"Micart (s.r.l.)",
    "wof:placetype":"venue"
},
  "geometry": {"coordinates":[9.1056537628,45.5253791809],"type":"Point"}
}