{
  "type": "Feature",
  "properties": {
    "iso:country":"IT",
    "sg:address":"17, Via Leonardo Da Vinci 20029 Turbigo",
    "sg:city":"Turbigo",
    "sg:classifiers":[
        {
            "category":"Wholesale",
            "subcategory":"Drugs",
            "type":"Manufacturing & Wholesale Goods"
        }
    ],
    "sg:phone":"+39 0331 871152",
    "sg:postcode":"20029",
    "sg:province":"Milano",
    "sg:tags":[
        "chemical",
        "pharmaceutical"
    ],
    "wof:name":"Tichem (s.r.l.)",
    "wof:placetype":"venue"
},
  "geometry": {"coordinates":[8.733671,45.532543],"type":"Point"}
}