{
  "type": "Feature",
  "properties": {
    "addr:full":"V. Flaminia 06023 Gualdo Tadino Gualdo Tadino Perugia 06023",
    "addr:postcode":"06023;06023",
    "addr:street":"V. Flaminia",
    "iso:country":"IT",
    "sg:address":"V. Flaminia 06023 Gualdo Tadino",
    "sg:city":"Gualdo Tadino",
    "sg:classifiers":[
        {
            "category":"Home & Garden",
            "subcategory":"Home Furnishings",
            "type":"Retail Goods"
        }
    ],
    "sg:phone":"+39 075 914 1306",
    "sg:postcode":"06023",
    "sg:province":"Perugia",
    "sg:tags":[
        "household"
    ],
    "sg:website":"http://www.pimpinelli.it",
    "wof:name":"Pimpinelli Vittorio",
    "wof:placetype":"venue"
},
  "geometry": {"coordinates":[12.779157,43.230736],"type":"Point"}
}