{
  "type": "Feature",
  "properties": {
    "iso:country":"IT",
    "sg:address":"240, Via Padana 30030 Venezia",
    "sg:classifiers":[
        {
            "category":"Shopping",
            "subcategory":"Jewelry",
            "type":"Retail Goods"
        }
    ],
    "sg:phone":"+39 39041920299",
    "sg:postcode":"30030",
    "sg:province":"Venezia",
    "sg:tags":[
        "jewellery"
    ],
    "wof:name":"Valter (s.r.l.)",
    "wof:placetype":"venue"
},
  "geometry": {"coordinates":[13.137466,45.6875],"type":"Point"}
}