{
  "type": "Feature",
  "properties": {
    "addr:full":"98, Via Pescarito 10099 San Mauro Torinese San Mauro Torinese Torino 10099",
    "addr:postcode":"10099;10099",
    "addr:street":"Via Pescarito",
    "iso:country":"IT",
    "sg:address":"98, Via Pescarito 10099 San Mauro Torinese",
    "sg:city":"San Mauro Torinese",
    "sg:classifiers":[
        {
            "category":"Shopping",
            "subcategory":"Clothing, Apparel, & Fashions",
            "type":"Retail Goods"
        }
    ],
    "sg:phone":"+39 011 223 7042",
    "sg:postcode":"10099",
    "sg:province":"Torino",
    "sg:tags":[
        "clothing",
        "accessory"
    ],
    "wof:name":"Nex Italia (s.r.l.)",
    "wof:placetype":"venue"
},
  "geometry": {"coordinates":[7.748302,45.11224],"type":"Point"}
}