{
  "type": "Feature",
  "properties": {
    "addr:full":"25028 Verolanuova Verolanuova Brescia 25028",
    "addr:postcode":"25028;25028",
    "iso:country":"IT",
    "sg:address":"25028 Verolanuova",
    "sg:city":"Verolanuova",
    "sg:orig_category":"Macchine, Impianti Ed Attrezzature Per Abbigliamento E Pelletterie",
    "sg:phone":"+39 030 936 1780",
    "sg:postcode":"25028",
    "sg:province":"Brescia",
    "wof:name":"Eurocomat S.r.l.",
    "wof:placetype":"venue"
},
  "geometry": {"coordinates":[9.97334,45.424408],"type":"Point"}
}