{
  "type": "Feature",
  "properties": {
    "iso:country":"IT",
    "sg:address":"10052 Bardonecchia",
    "sg:city":"Bardonecchia",
    "sg:orig_category":"Servizi Per Lo Sport E Il Tempo Libero. Servizi Al Turismo",
    "sg:phone":"+39 0122 99672",
    "sg:postcode":"10052",
    "sg:province":"Torino",
    "wof:name":"Colomion (s.p.a.)",
    "wof:placetype":"venue"
},
  "geometry": {"coordinates":[6.707226,45.083881],"type":"Point"}
}