{
  "type": "Feature",
  "properties": {
    "iso:country":"IT",
    "sg:address":"75100 Matera",
    "sg:city":"Matera",
    "sg:orig_category":"Prodotti E Manufatti In Materie Plastiche. Materiali Edili",
    "sg:phone":"+39 0835 381748",
    "sg:postcode":"75100",
    "sg:province":"Matera",
    "wof:name":"Poliuret Fibre Di F.p. Matera & C.snc",
    "wof:placetype":"venue"
},
  "geometry": {"coordinates":[16.5727176666,40.6738548279],"type":"Point"}
}