{
  "type": "Feature",
  "properties": {
    "addr:full":"Via Terni 3 01033 Civita Castellana Civita Castellana Viterbo 01033",
    "addr:housenumber":"3",
    "addr:postcode":"01033;01033",
    "addr:street":"Via Terni",
    "iso:country":"IT",
    "sg:address":"Via Terni 3 01033 Civita Castellana",
    "sg:city":"Civita Castellana",
    "sg:classifiers":[
        {
            "category":"Home & Garden",
            "subcategory":"Carpets & Floor Coverings",
            "type":"Retail Goods"
        }
    ],
    "sg:phone":"+39 0761 513698",
    "sg:postcode":"01033",
    "sg:province":"Viterbo",
    "sg:tags":[
        "decoration",
        "dish",
        "presentation",
        "plate"
    ],
    "sg:website":"www.sanmarciano.it",
    "wof:name":"San Marciano Sas",
    "wof:placetype":"venue"
},
  "geometry": {"coordinates":[12.414103,42.295662],"type":"Point"}
}