{
  "type": "Feature",
  "properties": {
    "iso:country":"IT",
    "sg:address":"27058 Voghera",
    "sg:city":"Voghera",
    "sg:orig_category":"Abbigliamento Esterno, Maglierie E Pelliccerie. Shopping",
    "sg:phone":"+39 0383 40101",
    "sg:postcode":"27058",
    "sg:province":"Pavia",
    "wof:name":"Universal Market Srl",
    "wof:placetype":"venue"
},
  "geometry": {"coordinates":[8.973295,44.997543],"type":"Point"}
}