{
  "type": "Feature",
  "properties": {
    "iso:country":"IT",
    "sg:address":"40069 Zola Predosa",
    "sg:city":"Zola",
    "sg:orig_category":"Servizi E Lavori Per Agricoltura E Zootecnia. Servizi E Lavori Per Edilizia E Lavori Pubblici",
    "sg:phone":"+39 051 752356",
    "sg:postcode":"40069",
    "sg:province":"Bologna",
    "sg:website":"http://www.greenpoolgiardinaggio.it",
    "wof:name":"Azienda Agricola Greenpool Sas Di U. Sogni & C.",
    "wof:placetype":"venue"
},
  "geometry": {"coordinates":[11.222052,44.506866],"type":"Point"}
}