{
  "type": "Feature",
  "properties": {
    "iso:country":"IT",
    "sg:address":"Via Del Borro 74; Arezzo; 52100",
    "sg:city":"Arezzo",
    "sg:classifiers":[
        {
            "category":"Banks & Credit Unions",
            "subcategory":"Bank",
            "type":"Services"
        }
    ],
    "sg:phone":"+39 0575 23529",
    "sg:postcode":"52100",
    "sg:province":"Arezzo",
    "wof:name":"Banca Toscana Spa",
    "wof:placetype":"venue"
},
  "geometry": {"coordinates":[11.861873,43.464161],"type":"Point"}
}