{
  "type": "Feature",
  "properties": {
    "iso:country":"IT",
    "sg:address":"22063 Cant\u00f9",
    "sg:orig_category":"Automobili E Mezzi Di Trasporto",
    "sg:phone":"+39 031 714010",
    "sg:postcode":"22063",
    "sg:province":"Como",
    "wof:name":"King Srl - Concessionaria Renault",
    "wof:placetype":"venue"
},
  "geometry": {"coordinates":[9.116138,45.744495],"type":"Point"}
}