{
  "type": "Feature",
  "properties": {
    "addr:full":"20131 Milano Milano Milano 20131",
    "addr:postcode":"20131;20131",
    "iso:country":"IT",
    "sg:address":"20131 Milano",
    "sg:city":"Milano",
    "sg:orig_category":"Prodotti Alimentari",
    "sg:phone":"+39 02 7063 2151",
    "sg:postcode":"20131",
    "sg:province":"Milano",
    "wof:name":"Il Cerchio S.a.s. Di Torelli Claudia E C.",
    "wof:placetype":"venue"
},
  "geometry": {"coordinates":[9.2353372574,45.4827232361],"type":"Point"}
}