{
  "type": "Feature",
  "properties": {
    "iso:country":"IT",
    "sg:address":"40138 Bologna",
    "sg:city":"Bologna",
    "sg:orig_category":"Bilance, Bilici E Bascule",
    "sg:phone":"+39 051 535550",
    "sg:postcode":"40138",
    "sg:province":"Bologna",
    "sg:website":"http://www.elcatronic.it",
    "wof:name":"Elcatronic Service Sas",
    "wof:placetype":"venue"
},
  "geometry": {"coordinates":[11.398565,44.499325],"type":"Point"}
}