{
  "type": "Feature",
  "properties": {
    "addr:full":"25065 Lumezzane Lumezzane Brescia 25065",
    "addr:postcode":"25065;25065",
    "iso:country":"IT",
    "sg:address":"25065 Lumezzane",
    "sg:city":"Lumezzane",
    "sg:orig_category":"Metalli E Leghe",
    "sg:phone":"+39 030 892 2255",
    "sg:postcode":"25065",
    "sg:province":"Brescia",
    "wof:name":"Italchimici Spa",
    "wof:placetype":"venue"
},
  "geometry": {"coordinates":[10.2712230682,45.6414413452],"type":"Point"}
}