{
  "type": "Feature",
  "properties": {
    "addr:full":"06012 Citt\u00e0 Di Castello Perugia 06012",
    "addr:postcode":"06012;06012",
    "iso:country":"IT",
    "sg:address":"06012 Citt\u00e0 Di Castello",
    "sg:orig_category":"Arti Grafiche",
    "sg:phone":"+39 075 855 7466",
    "sg:postcode":"06012",
    "sg:province":"Perugia",
    "wof:name":"Trastulla Marcello G. Service",
    "wof:placetype":"venue"
},
  "geometry": {"coordinates":[12.235945,43.470051],"type":"Point"}
}