{
  "type": "Feature",
  "properties": {
    "addr:full":"26034 Piadena Piadena Cremona 26034",
    "addr:postcode":"26034;26034",
    "iso:country":"IT",
    "sg:address":"26034 Piadena",
    "sg:city":"Piadena",
    "sg:orig_category":"Distillazione - Impianti E Attrezzature",
    "sg:phone":"+39 0375 98601",
    "sg:postcode":"26034",
    "sg:province":"Cremona",
    "wof:name":"Grifo Marchetti Giordano",
    "wof:placetype":"venue"
},
  "geometry": {"coordinates":[10.464189,45.111671],"type":"Point"}
}