{
  "type": "Feature",
  "properties": {
    "addr:full":"22074 Lomazzo Lomazzo Como 22074",
    "addr:postcode":"22074;22074",
    "iso:country":"IT",
    "sg:address":"22074 Lomazzo",
    "sg:city":"Lomazzo",
    "sg:orig_category":"Studi E Consulenze Legali E Notarili. Avvocati, Notai E Servizi Legali. Professionisti - Studi E Servizi Ed Associazioni Di Interesse Aziendale",
    "sg:phone":"+39 02 9637 0639",
    "sg:postcode":"22074",
    "sg:province":"Como",
    "sg:website":"http://www.studiomarzetti.it",
    "wof:name":"Studio Tecnico Associato - Giancarlo Marzetti E Alberto Marzetti",
    "wof:placetype":"venue"
},
  "geometry": {"coordinates":[9.030706,45.698647],"type":"Point"}
}