{
  "type": "Feature",
  "properties": {
    "addr:full":"06121 Perugia Perugia Perugia 06121",
    "addr:postcode":"06121;06121",
    "iso:country":"IT",
    "sg:address":"06121 Perugia",
    "sg:city":"Perugia",
    "sg:orig_category":"Videocassette - Vendita E Noleggio",
    "sg:phone":"+39 075 32036",
    "sg:postcode":"06121",
    "sg:province":"Perugia",
    "wof:name":"Planet Video",
    "wof:placetype":"venue"
},
  "geometry": {"coordinates":[12.391492,43.100075],"type":"Point"}
}