{
  "type": "Feature",
  "properties": {
    "addr:full":"09033 Decimomannu Decimomannu Cagliari 09033",
    "addr:postcode":"09033;09033",
    "iso:country":"IT",
    "sg:address":"09033 Decimomannu",
    "sg:city":"Decimomannu",
    "sg:classifiers":[
        {
            "category":"Banks & Credit Unions",
            "subcategory":"Investment Brokerage",
            "type":"Services"
        }
    ],
    "sg:phone":"+39 070 962925",
    "sg:postcode":"09033",
    "sg:province":"Cagliari",
    "sg:tags":[
        "activities",
        "industrial",
        "auxiliary",
        "surveillance",
        "cleaning",
        "maintenance",
        "supplies"
    ],
    "wof:name":"Dusit Srl",
    "wof:placetype":"venue"
},
  "geometry": {"coordinates":[8.957657,39.317078],"type":"Point"}
}