{
  "type": "Feature",
  "properties": {
    "iso:country":"IT",
    "sg:address":"Via Camporosolo 11/a; S. Bonifacio",
    "sg:classifiers":[
        {
            "category":"Banks & Credit Unions",
            "subcategory":"Bank",
            "type":"Services"
        }
    ],
    "sg:phone":"+39 045 610 1930",
    "wof:name":"Banca Di Roma",
    "wof:placetype":"venue"
},
  "geometry": {"coordinates":[11.270885,45.394741],"type":"Point"}
}