{
  "type": "Feature",
  "properties": {
    "iso:country":"IT",
    "sg:address":"Via Cagnona 1853 47039 Savignano Sul Rubicone",
    "sg:city":"Savignano sul Rubicone",
    "sg:classifiers":[
        {
            "category":"Home & Garden",
            "subcategory":"Carpets & Floor Coverings",
            "type":"Retail Goods"
        }
    ],
    "sg:phone":"+39 0541 938100",
    "sg:postcode":"47039",
    "sg:province":"Forl\u00ec-Cesena",
    "sg:tags":[
        "decoration",
        "article",
        "plush"
    ],
    "wof:name":"Lupi Rosauro",
    "wof:placetype":"venue"
},
  "geometry": {"coordinates":[12.427601,44.150902],"type":"Point"}
}