{
  "type": "Feature",
  "properties": {
    "iso:country":"IT",
    "sg:address":"25131 Brescia",
    "sg:city":"Brescia",
    "sg:classifiers":[
        {
            "category":"Train Station",
            "subcategory":"Light Rail",
            "type":"Transportation"
        }
    ],
    "sg:phone":"+39 030 268 1128",
    "sg:postcode":"25131",
    "sg:province":"Brescia",
    "sg:tags":[
        "plating",
        "treatments",
        "metals",
        "heat",
        "electroforming",
        "surface"
    ],
    "wof:name":"V.b.c. Srl",
    "wof:placetype":"venue"
},
  "geometry": {"coordinates":[10.1763973236,45.4895591736],"type":"Point"}
}