{
  "type": "Feature",
  "properties": {
    "addr:full":"65121 Pescara Pescara Pescara 65121",
    "addr:postcode":"65121;65121",
    "iso:country":"IT",
    "sg:address":"65121 Pescara",
    "sg:city":"Pescara",
    "sg:orig_category":"Abbigliamento Esterno, Maglierie E Pelliccerie. Shopping",
    "sg:phone":"+39 085 422 4984",
    "sg:postcode":"65121",
    "sg:province":"Pescara",
    "wof:name":"Due Bi Snc",
    "wof:placetype":"venue"
},
  "geometry": {"coordinates":[14.212854,42.465847],"type":"Point"}
}