{
  "type": "Feature",
  "properties": {
    "iso:country":"IT",
    "sg:address":"70125 Bari",
    "sg:city":"Bari",
    "sg:orig_category":"Macchine, Impianti Ed Attrezzature Industria Chimica. Prodotti Vari In Metallo. Articoli Per Imballaggio E Confezionamento",
    "sg:phone":"+39 080 556 6795",
    "sg:postcode":"70125",
    "sg:province":"Bari",
    "wof:name":"Cardinale Stefano",
    "wof:placetype":"venue"
},
  "geometry": {"coordinates":[16.880182,41.104633],"type":"Point"}
}