{
  "type": "Feature",
  "properties": {
    "iso:country":"IT",
    "sg:address":"70026 Modugno",
    "sg:city":"Modugno",
    "sg:orig_category":"Agenzie D'affari E Servizi Commerciali. Servizi Per Aziende, Manifestazioni E Supporto Agli Scambi Commerciali",
    "sg:phone":"+39 080 532 7257",
    "sg:postcode":"70026",
    "sg:province":"Bari",
    "wof:name":"Rana Dott. Giuseppe",
    "wof:placetype":"venue"
},
  "geometry": {"coordinates":[16.782473,41.08176],"type":"Point"}
}