{
  "type": "Feature",
  "properties": {
    "iso:country":"IT",
    "sg:address":"20134 Milano",
    "sg:city":"Milano",
    "sg:orig_category":"Abbigliamento Intimo, Calze E Costumi Da Bagno. Articoli Medico-sanitari Ed Ortopedici",
    "sg:phone":"+39 02 215 0481",
    "sg:postcode":"20134",
    "sg:province":"Milano",
    "wof:name":"Dongiovanni Leonardo",
    "wof:placetype":"venue"
},
  "geometry": {"coordinates":[9.242843,45.481312],"type":"Point"}
}