{
  "type": "Feature",
  "properties": {
    "iso:country":"IT",
    "sg:address":"47039 Savignano Sul Rubicone",
    "sg:city":"Savignano sul Rubicone",
    "sg:orig_category":"Servizi Vari Di Interesse Pubblico",
    "sg:phone":"+39 0541 801018",
    "sg:postcode":"47039",
    "sg:province":"Forl\u00ec-Cesena",
    "wof:name":"Service Web Cooperativa Sociale Arl",
    "wof:placetype":"venue"
},
  "geometry": {"coordinates":[12.397943,44.095123],"type":"Point"}
}