{
  "type": "Feature",
  "properties": {
    "iso:country":"IT",
    "sg:address":"Zona Industriale - Scerne 64025 Pineto",
    "sg:city":"Pineto",
    "sg:classifiers":[
        {
            "category":"Manufacturing",
            "subcategory":"Paper Products",
            "type":"Manufacturing & Wholesale Goods"
        }
    ],
    "sg:phone":"+39 085 946 2420",
    "sg:postcode":"64025",
    "sg:province":"Teramo",
    "sg:tags":[
        "cardboard"
    ],
    "sg:website":"http://www.trimalcartotecnica.it",
    "wof:name":"Trimal Cartotecnica",
    "wof:placetype":"venue"
},
  "geometry": {"coordinates":[13.6985311508,42.6612701416],"type":"Point"}
}