{
  "type": "Feature",
  "properties": {
    "iso:country":"IT",
    "sg:address":"09122 Cagliari",
    "sg:city":"Cagliari",
    "sg:orig_category":"Autofficine E Centri Assistenza",
    "sg:phone":"+39 070 287866",
    "sg:postcode":"09122",
    "sg:province":"Cagliari",
    "wof:name":"Officine Meccaniche Fanni Piccola Soc.coop.r.l.",
    "wof:placetype":"venue"
},
  "geometry": {"coordinates":[9.094282,39.241581],"type":"Point"}
}