{
  "type": "Feature",
  "properties": {
    "iso:country":"IT",
    "sg:address":"3, Via Legatore 40138 Bologna",
    "sg:city":"Bologna",
    "sg:classifiers":[
        {
            "category":"Professional",
            "subcategory":"Printing & Photocopies",
            "type":"Services"
        }
    ],
    "sg:phone":"+39 39051533311",
    "sg:postcode":"40138",
    "sg:province":"Bologna",
    "wof:name":"Tecnoprint",
    "wof:placetype":"venue"
},
  "geometry": {"coordinates":[11.4124155045,44.5066604614],"type":"Point"}
}