{
  "type": "Feature",
  "properties": {
    "iso:country":"IT",
    "sg:address":"Piazza Xx Settembre 4; Tolmezzo; 33028",
    "sg:city":"Tolmezzo",
    "sg:classifiers":[
        {
            "category":"Banks & Credit Unions",
            "subcategory":"Bank",
            "type":"Services"
        }
    ],
    "sg:phone":"+39 0433 2002",
    "sg:postcode":"33028",
    "sg:province":"Udine",
    "wof:name":"Rolo Banca 1473 Spa",
    "wof:placetype":"venue"
},
  "geometry": {"coordinates":[13.026283,46.42009],"type":"Point"}
}