{
  "type": "Feature",
  "properties": {
    "iso:country":"IT",
    "sg:address":"95025 Aci Sant'antonio",
    "sg:orig_category":"Arti Grafiche - Accessori E Forniture",
    "sg:phone":"+39 095 702 2103",
    "sg:postcode":"95025",
    "sg:province":"Catania",
    "wof:name":"T.s.t. Tecnologia Sistemi Transfer",
    "wof:placetype":"venue"
},
  "geometry": {"coordinates":[15.120049,37.625515],"type":"Point"}
}