{
  "type": "Feature",
  "properties": {
    "addr:full":"23032 Bormio Bormio Sondrio 23032",
    "addr:postcode":"23032;23032",
    "iso:country":"IT",
    "sg:address":"23032 Bormio",
    "sg:city":"Bormio",
    "sg:orig_category":"Impiantistica E Prodotti Tecnologici Per Edilizia",
    "sg:phone":"+39 0342 910722",
    "sg:postcode":"23032",
    "sg:province":"Sondrio",
    "wof:name":"Parking Contea Bormio",
    "wof:placetype":"venue"
},
  "geometry": {"coordinates":[10.371956,46.466232],"type":"Point"}
}