{
  "type": "Feature",
  "properties": {
    "iso:country":"IT",
    "sg:address":"03100 Frosinone",
    "sg:city":"Frosinone",
    "sg:orig_category":"Forniture Alle Strutture Ricettive. Macchine E Impianti Per Attivita' Commerciali Ed Artigianali",
    "sg:phone":"+39 0775 291649",
    "sg:postcode":"03100",
    "sg:province":"Frosinone",
    "wof:name":"Organizzazioni Salvitti A. & C. Sas",
    "wof:placetype":"venue"
},
  "geometry": {"coordinates":[13.3318157196,41.6286506653],"type":"Point"}
}