{
  "type": "Feature",
  "properties": {
    "iso:country":"IT",
    "sg:address":"43039 Salsomaggiore Terme",
    "sg:city":"Salsomaggiore Terme",
    "sg:orig_category":"Servizi Editoriali. Shopping",
    "sg:phone":"+39 0524 571920",
    "sg:postcode":"43039",
    "sg:province":"Parma",
    "wof:name":"Cosmic Comics",
    "wof:placetype":"venue"
},
  "geometry": {"coordinates":[9.964434,44.813995],"type":"Point"}
}