{
  "type": "Feature",
  "properties": {
    "addr:full":"6, V. Pacinotti 70017 Putignano Putignano Bari 70017",
    "addr:housenumber":"6",
    "addr:postcode":"70017;70017",
    "addr:street":"V. Pacinotti",
    "iso:country":"IT",
    "sg:address":"6, V. Pacinotti 70017 Putignano",
    "sg:city":"Putignano",
    "sg:classifiers":[
        {
            "category":"Shopping",
            "subcategory":"Clothing, Apparel, & Fashions",
            "type":"Retail Goods"
        }
    ],
    "sg:phone":"+39 080 491 1024",
    "sg:postcode":"70017",
    "sg:province":"Bari",
    "sg:tags":[
        "clothing",
        "accessory"
    ],
    "sg:website":"http://www.dalena.it:ws_end: :mark:ws:http://www.paginegialle.it/dalenaberrettificio",
    "wof:name":"Dalena Berrettificio Srl",
    "wof:placetype":"venue"
},
  "geometry": {"coordinates":[17.121117,40.855362],"type":"Point"}
}