{
  "type": "Feature",
  "properties": {
    "iso:country":"IT",
    "sg:address":"20090 Segrate",
    "sg:city":"Segrate",
    "sg:orig_category":"Materiali Edili",
    "sg:phone":"+39 02 213 2150",
    "sg:postcode":"20090",
    "sg:province":"Milano",
    "wof:name":"Barbieri Di Douglas Barbieri",
    "wof:placetype":"venue"
},
  "geometry": {"coordinates":[9.291694,45.501144],"type":"Point"}
}