{
  "type": "Feature",
  "properties": {
    "iso:country":"IT",
    "sg:address":"Via Degli Esportatori 43 96016 Lentini",
    "sg:city":"Lentini",
    "sg:classifiers":[
        {
            "category":"Food & Beverages",
            "subcategory":"Fruits & Vegetables",
            "type":"Retail Goods"
        }
    ],
    "sg:phone":"+39 095 901118",
    "sg:postcode":"96016",
    "sg:province":"Siracusa",
    "wof:name":"G. Russo & C Snc",
    "wof:placetype":"venue"
},
  "geometry": {"coordinates":[14.9994039536,37.299861908],"type":"Point"}
}