{
  "type": "Feature",
  "properties": {
    "addr:full":"35011 Campodarsego Campodarsego Padova 35011",
    "addr:postcode":"35011;35011",
    "iso:country":"IT",
    "sg:address":"35011 Campodarsego",
    "sg:city":"Campodarsego",
    "sg:orig_category":"Materiali Edili",
    "sg:phone":"+39 049 920 2136",
    "sg:postcode":"35011",
    "sg:province":"Padova",
    "wof:name":"Morocolor S.r.l.",
    "wof:placetype":"venue"
},
  "geometry": {"coordinates":[11.897046,45.459827],"type":"Point"}
}