{
  "type": "Feature",
  "properties": {
    "addr:full":"8, Via Alessandro Marcello 31050 Morgano Morgano Treviso 31050",
    "addr:postcode":"31050;31050",
    "addr:street":"Via Alessandro Marcello",
    "iso:country":"IT",
    "sg:address":"8, Via Alessandro Marcello 31050 Morgano",
    "sg:city":"Morgano",
    "sg:classifiers":[
        {
            "category":"Parking",
            "subcategory":"Lot",
            "type":"Transportation"
        }
    ],
    "sg:phone":"+39 0422 739175",
    "sg:postcode":"31050",
    "sg:province":"Treviso",
    "sg:tags":[
        "transport",
        "road"
    ],
    "wof:name":"Cavallin L. & C. Snc",
    "wof:placetype":"venue"
},
  "geometry": {"coordinates":[12.082229,45.634125],"type":"Point"}
}