{
  "type": "Feature",
  "properties": {
    "iso:country":"IT",
    "sg:address":"Via Della Nave A Rovezzano, 66/3 50012 Bagno A Ripoli",
    "sg:city":"Bagno a Ripoli",
    "sg:orig_category":"Lustres, Chandeliers",
    "sg:phone":"+39 055 632422",
    "sg:postcode":"50012",
    "sg:province":"Firenze",
    "wof:name":"Nuovasala Srl",
    "wof:placetype":"venue"
},
  "geometry": {"coordinates":[11.316768,43.755291],"type":"Point"}
}