{
  "type": "Feature",
  "properties": {
    "iso:country":"IT",
    "sg:address":"37011 Bardolino",
    "sg:city":"Bardolino",
    "sg:orig_category":"Aziende Agricole",
    "sg:phone":"+39 045 621 0856",
    "sg:postcode":"37011",
    "sg:province":"Verona",
    "sg:website":"http://www.cadellora.com",
    "wof:name":"Azienda Agricola Ca' Dell'ora Di Jugert Frank",
    "wof:placetype":"venue"
},
  "geometry": {"coordinates":[10.69142,45.545307],"type":"Point"}
}