{
  "type": "Feature",
  "properties": {
    "iso:country":"IT",
    "sg:address":"50, Via Delle Fornaci 00165 Roma",
    "sg:city":"Roma",
    "sg:classifiers":[
        {
            "category":"Manufacturing",
            "subcategory":"Printing",
            "type":"Manufacturing & Wholesale Goods"
        }
    ],
    "sg:phone":"+39 06 3937 6728",
    "sg:postcode":"00165",
    "sg:province":"Roma",
    "sg:tags":[
        "publishing"
    ],
    "wof:name":"Edizioni Borla Srl",
    "wof:placetype":"venue"
},
  "geometry": {"coordinates":[12.4568519592,41.8972320557],"type":"Point"}
}