{
  "type": "Feature",
  "properties": {
    "addr:full":"2, Via Dell' Artigianato 37020 Marano Di Valpolicella Marano di Valpolicella Verona 37020",
    "addr:postcode":"37020;37020",
    "addr:street":"Via Dell ' Artigianato",
    "iso:country":"IT",
    "sg:address":"2, Via Dell' Artigianato 37020 Marano Di Valpolicella",
    "sg:city":"Marano di Valpolicella",
    "sg:classifiers":[
        {
            "category":"Personal",
            "subcategory":"Shoe Repair & Shine",
            "type":"Services"
        }
    ],
    "sg:phone":"+39 045 680 1625",
    "sg:postcode":"37020",
    "sg:province":"Verona",
    "sg:tags":[
        "leather"
    ],
    "wof:name":"My Way.net Srl",
    "wof:placetype":"venue"
},
  "geometry": {"coordinates":[10.939188,45.525009],"type":"Point"}
}