{
  "type": "Feature",
  "properties": {
    "iso:country":"IT",
    "sg:address":"33100 Udine",
    "sg:city":"Udine",
    "sg:orig_category":"Impiantistica E Prodotti Tecnologici Per Edilizia. Elettronica Professionale E Di Consumo",
    "sg:phone":"+39 0432 602469",
    "sg:postcode":"33100",
    "sg:province":"Udine",
    "wof:name":"Italcontrol Telematica P.s.c.",
    "wof:placetype":"venue"
},
  "geometry": {"coordinates":[13.259665,46.026012],"type":"Point"}
}