{
  "type": "Feature",
  "properties": {
    "iso:country":"IT",
    "sg:address":"29, Via Copernico 41043 Formigine",
    "sg:city":"Formigine",
    "sg:classifiers":[
        {
            "category":"Professional",
            "subcategory":"Engineering",
            "type":"Services"
        }
    ],
    "sg:phone":"+39 39059550049",
    "sg:postcode":"41043",
    "sg:province":"Modena",
    "sg:tags":[
        "machine",
        "-",
        "mechanical"
    ],
    "wof:name":"Pragma S.r.l.",
    "wof:placetype":"venue"
},
  "geometry": {"coordinates":[10.849154,44.58844],"type":"Point"}
}