{
  "type": "Feature",
  "properties": {
    "addr:full":"20060 Pessano Con Bornago Ornago Milano 20060",
    "addr:postcode":"20060;20060",
    "iso:country":"IT",
    "sg:address":"20060 Pessano Con Bornago",
    "sg:city":"Ornago",
    "sg:orig_category":"Termotecnica E Riscaldamento, Apparecchiature E Servizi. Valvole E Apparecchiature Di Misura. Macchine, Strumenti Ed Apparecchi Per Attivita' Industriali",
    "sg:phone":"+39 02 9574 2784",
    "sg:postcode":"20060",
    "sg:province":"Milano",
    "wof:name":"Mater (s.r.l.)",
    "wof:placetype":"venue"
},
  "geometry": {"coordinates":[9.387856,45.552689],"type":"Point"}
}