{
  "type": "Feature",
  "properties": {
    "iso:country":"IT",
    "sg:address":"Via Meucci 13 61033 Fermignano",
    "sg:city":"Fermignano",
    "sg:classifiers":[
        {
            "category":"Wholesale",
            "subcategory":"Plants",
            "type":"Manufacturing & Wholesale Goods"
        }
    ],
    "sg:phone":"+39 0722 330888",
    "sg:postcode":"61033",
    "sg:province":"Pesaro E Urbino",
    "sg:tags":[
        "machine",
        "industrial",
        "automation"
    ],
    "wof:name":"Compac Srl",
    "wof:placetype":"venue"
},
  "geometry": {"coordinates":[12.529803,43.633556],"type":"Point"}
}