{
  "type": "Feature",
  "properties": {
    "iso:country":"IT",
    "sg:address":"55027 Gallicano",
    "sg:city":"Gallicano",
    "sg:orig_category":"Ceramiche Artistiche",
    "sg:phone":"+39 0583 730177",
    "sg:postcode":"55027",
    "sg:province":"Lucca",
    "wof:name":"Pacini 5 Srl",
    "wof:placetype":"venue"
},
  "geometry": {"coordinates":[10.447055,44.055164],"type":"Point"}
}