{
  "type": "Feature",
  "properties": {
    "addr:full":"4, Strada Lanzo 10070 Robassomero Robassomero Torino 10070",
    "addr:postcode":"10070;10070",
    "addr:street":"Strada Lanzo",
    "iso:country":"IT",
    "sg:address":"4, Strada Lanzo 10070 Robassomero",
    "sg:city":"Robassomero",
    "sg:classifiers":[
        {
            "category":"Home & Garden",
            "subcategory":"Home Furnishings",
            "type":"Retail Goods"
        }
    ],
    "sg:phone":"+39 011 923 5426",
    "sg:postcode":"10070",
    "sg:province":"Torino",
    "sg:tags":[
        "household"
    ],
    "wof:name":"Tecnical 2 (s.r.l.)",
    "wof:placetype":"venue"
},
  "geometry": {"coordinates":[7.568942,45.187664],"type":"Point"}
}