{
  "type": "Feature",
  "properties": {
    "iso:country":"IT",
    "sg:address":"39057 Appiano Strada Del Vino",
    "sg:orig_category":"Ceramiche: Prodotti E Lavorazioni",
    "sg:phone":"+39 0471 662718",
    "sg:postcode":"39057",
    "sg:province":"Bolzano/Bozen",
    "wof:name":"Dona' Florian",
    "wof:placetype":"venue"
},
  "geometry": {"coordinates":[11.253691,46.470665],"type":"Point"}
}