{
  "type": "Feature",
  "properties": {
    "addr:full":"30030 Martellago Martellago Venezia 30030",
    "addr:postcode":"30030;30030",
    "iso:country":"IT",
    "sg:address":"30030 Martellago",
    "sg:city":"Martellago",
    "sg:orig_category":"Motori Ed Organi Di Trasmissione. Ricambi E Componenti Dei Mezzi Di Trasporto",
    "sg:phone":"+39 041 540 3026",
    "sg:postcode":"30030",
    "sg:province":"Venezia",
    "wof:name":"Rima Spa",
    "wof:placetype":"venue"
},
  "geometry": {"coordinates":[12.1572694778,45.5441207886],"type":"Point"}
}