{
  "type": "Feature",
  "properties": {
    "iso:country":"IT",
    "sg:address":"18012 Bordighera",
    "sg:city":"Bordighera",
    "sg:orig_category":"Imprese Di Costruzioni Civili Ed Industriali",
    "sg:phone":"+39 0184 252566",
    "sg:postcode":"18012",
    "sg:province":"Imperia",
    "wof:name":"Edil M.ar Srl Di Artioli Geom. Marino",
    "wof:placetype":"venue"
},
  "geometry": {"coordinates":[8.101918,43.921459],"type":"Point"}
}