{
  "type": "Feature",
  "properties": {
    "addr:full":"34, Via Enrico Mattei 27038 Robbio Robbio Pavia 27038",
    "addr:postcode":"27038;27038",
    "addr:street":"Via Enrico Mattei",
    "iso:country":"IT",
    "sg:address":"34, Via Enrico Mattei 27038 Robbio",
    "sg:city":"Robbio",
    "sg:classifiers":[
        {
            "category":"Professional",
            "subcategory":"Engineering",
            "type":"Services"
        }
    ],
    "sg:phone":"+39 0384 671278",
    "sg:postcode":"27038",
    "sg:province":"Pavia",
    "sg:tags":[
        "machine",
        "-",
        "mechanical"
    ],
    "wof:name":"C.m.r. (s.r.l.)",
    "wof:placetype":"venue"
},
  "geometry": {"coordinates":[9.156563,45.185886],"type":"Point"}
}