{
  "type": "Feature",
  "properties": {
    "iso:country":"IT",
    "sg:address":"Via De Gasper Belvedere 30; Siracusa; 96100",
    "sg:city":"Belvedere",
    "sg:classifiers":[
        {
            "category":"Banks & Credit Unions",
            "subcategory":"Bank",
            "type":"Services"
        }
    ],
    "sg:phone":"+39 0937 11119",
    "sg:postcode":"96100",
    "sg:province":"Siracusa",
    "wof:name":"Banca Di Credito Popolare Di Siracu",
    "wof:placetype":"venue"
},
  "geometry": {"coordinates":[15.207517,37.092987],"type":"Point"}
}