{
  "type": "Feature",
  "properties": {
    "addr:full":"48100 Ravenna Ravenna Ravenna 48100",
    "addr:housenumber":"48100",
    "addr:postcode":"48100",
    "iso:country":"IT",
    "sg:address":"48100 Ravenna",
    "sg:city":"Ravenna",
    "sg:orig_category":"Arredo Camera Letto E Complementi",
    "sg:phone":"+39 0544 405550",
    "sg:postcode":"48100",
    "sg:province":"Ravenna",
    "sg:website":"http://www.illetto.it",
    "wof:name":"Il Letto Snc Di Poltronieri S. & C.",
    "wof:placetype":"venue"
},
  "geometry": {"coordinates":[12.224458,44.380314],"type":"Point"}
}