{
  "type": "Feature",
  "properties": {
    "addr:full":"48, Via Fermi 20019 Settimo Milanese Settimo Milanese Milano 20019",
    "addr:postcode":"20019;20019",
    "addr:street":"Via Fermi",
    "iso:country":"IT",
    "sg:address":"48, Via Fermi 20019 Settimo Milanese",
    "sg:city":"Settimo Milanese",
    "sg:classifiers":[
        {
            "category":"Manufacturing",
            "subcategory":"Motor Vehicles & Parts",
            "type":"Manufacturing & Wholesale Goods"
        }
    ],
    "sg:phone":"+39 39023285830",
    "sg:postcode":"20019",
    "sg:province":"Milano",
    "sg:tags":[
        "engine"
    ],
    "wof:name":"Servopresse (s.r.l.)",
    "wof:placetype":"venue"
},
  "geometry": {"coordinates":[9.067799,45.480034],"type":"Point"}
}