{
  "type": "Feature",
  "properties": {
    "addr:full":"60025 Loreto Loreto Ancona 60025",
    "addr:postcode":"60025;60025",
    "iso:country":"IT",
    "sg:address":"60025 Loreto",
    "sg:city":"Loreto",
    "sg:orig_category":"Prodotti E Manufatti In Materie Plastiche. Forniture Per Edilizia E Lavori Pubblici. Forniture E Materiali Per Imballaggio E Confezionamento",
    "sg:phone":"+39 071 970331",
    "sg:postcode":"60025",
    "sg:province":"Ancona",
    "wof:name":"Euroespans (s.n.c.)",
    "wof:placetype":"venue"
},
  "geometry": {"coordinates":[13.6189079285,43.4363098145],"type":"Point"}
}