{
  "type": "Feature",
  "properties": {
    "iso:country":"IT",
    "sg:address":"80138 Napoli",
    "sg:city":"Napoli",
    "sg:orig_category":"Centri Di Estetica E Cosmesi E Servizi. Prodotti Cosmetici E Da Toeletta",
    "sg:phone":"+39 081 205449",
    "sg:postcode":"80138",
    "sg:province":"Napoli",
    "wof:name":"Istituto L.t Di Vanorio Enrico",
    "wof:placetype":"venue"
},
  "geometry": {"coordinates":[14.180674,40.860336],"type":"Point"}
}