{
  "type": "Feature",
  "properties": {
    "iso:country":"IT",
    "sg:address":"Via San Lorenzo 8 36010 Carre'",
    "sg:classifiers":[
        {
            "category":"Landmark",
            "subcategory":"Monument",
            "type":"Public Place"
        }
    ],
    "sg:phone":"+39 0445 891744",
    "sg:postcode":"36010",
    "sg:province":"Vicenza",
    "sg:tags":[
        "sepulchral"
    ],
    "sg:website":"www.pilla.com",
    "wof:name":"Pilla Srl",
    "wof:placetype":"venue"
},
  "geometry": {"coordinates":[11.464428,45.736572],"type":"Point"}
}