{
  "type": "Feature",
  "properties": {
    "iso:country":"IT",
    "sg:address":"50013 Campi Bisenzio",
    "sg:city":"Campi Bisenzio",
    "sg:orig_category":"Elettrotecnica Professionale E Di Consumo",
    "sg:phone":"+39 055 898 5523",
    "sg:postcode":"50013",
    "sg:province":"Firenze",
    "wof:name":"Dura Lamp",
    "wof:placetype":"venue"
},
  "geometry": {"coordinates":[11.146754,43.844402],"type":"Point"}
}