{
  "type": "Feature",
  "properties": {
    "addr:full":"Piazza Caduti; Moncalieri; 10024 Moncalieri Torino 10024",
    "addr:postcode":"10024;10024",
    "addr:street":"Piazza Caduti Moncalieri",
    "iso:country":"IT",
    "sg:address":"Piazza Caduti; Moncalieri; 10024",
    "sg:city":"Moncalieri",
    "sg:classifiers":[
        {
            "category":"Banks & Credit Unions",
            "subcategory":"Bank",
            "type":"Services"
        }
    ],
    "sg:phone":"+39 011 640 6892",
    "sg:postcode":"10024",
    "sg:province":"Torino",
    "wof:name":"Banca Sella Spa",
    "wof:placetype":"venue"
},
  "geometry": {"coordinates":[7.680036,44.999538],"type":"Point"}
}