{
  "type": "Feature",
  "properties": {
    "iso:country":"IT",
    "sg:address":"24, V. Cesare Battisti 03039 Sora",
    "sg:city":"Sora",
    "sg:classifiers":[
        {
            "category":"Shopping",
            "subcategory":"Computers & Home Electronics",
            "type":"Retail Goods"
        }
    ],
    "sg:phone":"+39 0776 831510",
    "sg:postcode":"03039",
    "sg:province":"Frosinone",
    "sg:tags":[
        "electronic",
        "electrical",
        "equipment"
    ],
    "sg:website":"http://www.difazio.com",
    "wof:name":"Di Fazio Lampade Elettriche",
    "wof:placetype":"venue"
},
  "geometry": {"coordinates":[13.351902,41.640137],"type":"Point"}
}