{
  "type": "Feature",
  "properties": {
    "iso:country":"IT",
    "sg:address":"Via Garibaldi 63, 26812 Borghetto Lodigiano, Lo",
    "sg:city":"Borghetto Lodigiano",
    "sg:classifiers":[
        {
            "category":"Banks & Credit Unions",
            "subcategory":"Bank",
            "type":"Services"
        }
    ],
    "sg:postcode":"26812",
    "sg:province":"Lodi",
    "wof:name":"Banca Di Credito Cooperativo Di Borghetto Lodigiano",
    "wof:placetype":"venue"
},
  "geometry": {"coordinates":[9.496655,45.212105],"type":"Point"}
}