{
  "type": "Feature",
  "properties": {
    "addr:full":"Via Crocefissozi 21, 20100 Milan, Mi",
    "addr:housenumber":"21",
    "addr:postcode":"20100",
    "addr:street":"Via Crocefissozi",
    "iso:country":"IT",
    "sg:address":"Via Crocefissozi 21, 20100 Milan, Mi",
    "sg:classifiers":[
        {
            "category":"Banks & Credit Unions",
            "subcategory":"Bank",
            "type":"Services"
        }
    ],
    "wof:name":"Baldini & Custoldi Spa",
    "wof:placetype":"venue"
},
  "geometry": {"coordinates":[9.184901,45.456989],"type":"Point"}
}