{
  "type": "Feature",
  "properties": {
    "addr:full":"72, Viale Della Navigazione Interna 35129 Padova Padova Padova 35129",
    "addr:housenumber":"72",
    "addr:postcode":"35129;35129",
    "addr:street":"Viale Della Navigazione Interna",
    "iso:country":"IT",
    "sg:address":"72, Viale Della Navigazione Interna 35129 Padova",
    "sg:city":"Padova",
    "sg:classifiers":[
        {
            "category":"Manufacturing",
            "subcategory":"Metals",
            "type":"Manufacturing & Wholesale Goods"
        }
    ],
    "sg:phone":"+39 049 806 0111",
    "sg:postcode":"35129",
    "sg:province":"Padova",
    "sg:tags":[
        "metallurgy",
        "metalworking"
    ],
    "wof:name":"Industrial Technical Tools Spa",
    "wof:placetype":"venue"
},
  "geometry": {"coordinates":[11.8441667557,45.3974990845],"type":"Point"}
}