{
  "type": "Feature",
  "properties": {
    "iso:country":"IT",
    "sg:address":"33020 Amaro",
    "sg:city":"Amaro",
    "sg:orig_category":"Macchine Ed Impianti Per Edilizia E Lavori Pubblici. Macchine, Strumenti Ed Apparecchi Per Attivita' Industriali",
    "sg:phone":"+39 0433 94271",
    "sg:postcode":"33020",
    "sg:province":"Udine",
    "wof:name":"Vetri Artistici",
    "wof:placetype":"venue"
},
  "geometry": {"coordinates":[13.096574,46.375168],"type":"Point"}
}