{
  "type": "Feature",
  "properties": {
    "iso:country":"IT",
    "sg:address":"70056 Molfetta",
    "sg:city":"Molfetta",
    "sg:orig_category":"Ferramenta - Vendita Al Dettaglio",
    "sg:phone":"+39 080 397 1212",
    "sg:postcode":"70056",
    "sg:province":"Bari",
    "sg:website":"http://www.hettich.com",
    "wof:name":"La Notte Antonella",
    "wof:placetype":"venue"
},
  "geometry": {"coordinates":[16.9947299957,41.0876579285],"type":"Point"}
}