{
  "type": "Feature",
  "properties": {
    "addr:full":"70010 Sammichele Di Bari Sammichele di Bari Bari 70010",
    "addr:postcode":"70010;70010",
    "iso:country":"IT",
    "sg:address":"70010 Sammichele Di Bari",
    "sg:city":"Sammichele di Bari",
    "sg:orig_category":"Forniture Per Agricoltura E Zootecnia. Prodotti Chimici Secondari. Macchine E Forniture Per Ecologia E Smaltimento Rifiuti",
    "sg:phone":"+39 080 891 0745",
    "sg:postcode":"70010",
    "sg:province":"Bari",
    "wof:name":"Farmagricola Di Labalestra Lorenzo",
    "wof:placetype":"venue"
},
  "geometry": {"coordinates":[16.9458465576,40.8825416565],"type":"Point"}
}