{
  "type": "Feature",
  "properties": {
    "iso:country":"IT",
    "sg:address":"102, Via S. Maria 20093 Cologno Monzese",
    "sg:city":"Cologno Monzese",
    "sg:classifiers":[
        {
            "category":"Real Estate",
            "subcategory":"Surveying",
            "type":"Services"
        }
    ],
    "sg:phone":"+39 39022538242",
    "sg:postcode":"20093",
    "sg:province":"Milano",
    "sg:tags":[
        "equipment",
        "material",
        "good",
        "-",
        "handling"
    ],
    "wof:name":"Rotocar (s.r.l)",
    "wof:placetype":"venue"
},
  "geometry": {"coordinates":[9.270423,45.538074],"type":"Point"}
}