{
  "type": "Feature",
  "properties": {
    "addr:full":"84043 Agropoli Agropoli Salerno 84043",
    "addr:postcode":"84043;84043",
    "iso:country":"IT",
    "sg:address":"84043 Agropoli",
    "sg:city":"Agropoli",
    "sg:orig_category":"Arredo Camera Letto E Complementi",
    "sg:phone":"+39 0974 843056",
    "sg:postcode":"84043",
    "sg:province":"Salerno",
    "wof:name":"Eurosan Di Botticchio Giuseppina",
    "wof:placetype":"venue"
},
  "geometry": {"coordinates":[15.009274,40.339668],"type":"Point"}
}