{
  "type": "Feature",
  "properties": {
    "addr:full":"17, Via Galli D. 20090 Buccinasco Buccinasco Milano 20090",
    "addr:postcode":"20090;20090",
    "addr:street":"Via Galli D.",
    "iso:country":"IT",
    "sg:address":"17, Via Galli D. 20090 Buccinasco",
    "sg:city":"Buccinasco",
    "sg:classifiers":[
        {
            "category":"Professional",
            "subcategory":"Engineering",
            "type":"Services"
        }
    ],
    "sg:phone":"+39 02 4570 0556",
    "sg:postcode":"20090",
    "sg:province":"Milano",
    "sg:tags":[
        "machine",
        "-",
        "mechanical"
    ],
    "wof:name":"Arcopac S.r.l.",
    "wof:placetype":"venue"
},
  "geometry": {"coordinates":[9.119678,45.419537],"type":"Point"}
}