{
  "type": "Feature",
  "properties": {
    "iso:country":"IT",
    "sg:address":"5, Via I. Newton 67051 Avezzano",
    "sg:classifiers":[
        {
            "category":"Manufacturing",
            "subcategory":"Metals",
            "type":"Manufacturing & Wholesale Goods"
        }
    ],
    "sg:phone":"+39 0863 509329",
    "sg:postcode":"67051",
    "sg:province":"L'Aquila",
    "sg:tags":[
        "processing"
    ],
    "wof:name":"Z.c.m. Srl",
    "wof:placetype":"venue"
},
  "geometry": {"coordinates":[13.4313716888,42.0391159058],"type":"Point"}
}