{
  "type": "Feature",
  "properties": {
    "iso:country":"IT",
    "sg:address":"26, Via Trebbia 20135 Milano",
    "sg:city":"Milano",
    "sg:orig_category":"Miscellaneous Products",
    "sg:phone":"+39 02 5519 1579",
    "sg:postcode":"20135",
    "sg:province":"Milano",
    "wof:name":"Santara (s.r.l.)",
    "wof:placetype":"venue"
},
  "geometry": {"coordinates":[9.2010307312,45.4478416443],"type":"Point"}
}