{
  "type": "Feature",
  "properties": {
    "iso:country":"IT",
    "sg:address":"9, Loc. Alberetti 13875 Ponderano",
    "sg:city":"Ponderano",
    "sg:classifiers":[
        {
            "category":"Professional",
            "subcategory":"Engineering",
            "type":"Services"
        }
    ],
    "sg:phone":"+39 39015541258",
    "sg:postcode":"13875",
    "sg:province":"Biella",
    "sg:tags":[
        "machine",
        "-",
        "mechanical"
    ],
    "sg:website":"http://www.paginegialle.it/ramellasnc",
    "wof:name":"Officina Meccanica Ramella",
    "wof:placetype":"venue"
},
  "geometry": {"coordinates":[8.05827,45.562836],"type":"Point"}
}