{
  "type": "Feature",
  "properties": {
    "iso:country":"IT",
    "sg:address":"20125 Milano",
    "sg:city":"Milano",
    "sg:orig_category":"Macchine, Impianti Ed Attrezzature Per Abbigliamento E Pelletterie",
    "sg:phone":"+39 02 688 4241",
    "sg:postcode":"20125",
    "sg:province":"Milano",
    "wof:name":"Erbagan Melek",
    "wof:placetype":"venue"
},
  "geometry": {"coordinates":[9.196333,45.495358],"type":"Point"}
}