{
  "type": "Feature",
  "properties": {
    "iso:country":"IT",
    "sg:address":"74015 Martina Franca",
    "sg:city":"Martina Franca",
    "sg:orig_category":"Accessori Moda D'abbigliamento. Forniture Per Abbigliamento E Pelletterie",
    "sg:phone":"+39 080 480 0018",
    "sg:postcode":"74015",
    "sg:province":"Taranto",
    "wof:name":"Pizzi E Merletti Di Nella Acquaviva",
    "wof:placetype":"venue"
},
  "geometry": {"coordinates":[17.339006,40.704788],"type":"Point"}
}