{
  "type": "Feature",
  "properties": {
    "iso:country":"IT",
    "sg:address":"34, Via Della Cooperazione 40129 Bologna",
    "sg:city":"Bologna",
    "sg:classifiers":[
        {
            "category":"Autos & Motor Vehicles",
            "subcategory":"Automobile Sales",
            "type":"Retail Goods"
        }
    ],
    "sg:phone":"+39 39051323424",
    "sg:postcode":"40129",
    "sg:province":"Bologna",
    "sg:tags":[
        "equipment",
        "transport"
    ],
    "wof:name":"Costruzioni Linee Ferroviarie (s.p.a.)",
    "wof:placetype":"venue"
},
  "geometry": {"coordinates":[11.34755,44.535858],"type":"Point"}
}