{
  "type": "Feature",
  "properties": {
    "addr:full":"12, Via Padre Albisetti 24030 Terno D'isola Bergamo 24030",
    "addr:postcode":"24030;24030",
    "addr:street":"Via Padre Albisetti",
    "iso:country":"IT",
    "sg:address":"12, Via Padre Albisetti 24030 Terno D'isola",
    "sg:classifiers":[
        {
            "category":"Professional",
            "subcategory":"Business Services",
            "type":"Services"
        }
    ],
    "sg:phone":"+39 035 494 0868",
    "sg:postcode":"24030",
    "sg:province":"Bergamo",
    "sg:tags":[
        "advice"
    ],
    "wof:name":"La Sfinge (s.r.l.)",
    "wof:placetype":"venue"
},
  "geometry": {"coordinates":[9.526249,45.689514],"type":"Point"}
}