{
  "type": "Feature",
  "properties": {
    "addr:full":"28040 Borgo Ticino Borgo Ticino Novara 28040",
    "addr:postcode":"28040;28040",
    "iso:country":"IT",
    "sg:address":"28040 Borgo Ticino",
    "sg:city":"Borgo Ticino",
    "sg:orig_category":"Motori Ed Organi Di Trasmissione",
    "sg:phone":"+39 0321 90445",
    "sg:postcode":"28040",
    "sg:province":"Novara",
    "wof:name":"New Turbostart (s.p.a.)",
    "wof:placetype":"venue"
},
  "geometry": {"coordinates":[8.6023893356,45.6934089661],"type":"Point"}
}