{
  "type": "Feature",
  "properties": {
    "addr:full":"2/a, Via Valier Max 39012 Merano Merano Bolzano/Bozen 39012",
    "addr:housenumber":"2 / a",
    "addr:postcode":"39012;39012",
    "addr:street":"Via Valier Max",
    "iso:country":"IT",
    "sg:address":"2/a, Via Valier Max 39012 Merano",
    "sg:city":"Merano",
    "sg:classifiers":[
        {
            "category":"Food & Beverages",
            "subcategory":"Groceries & Convenience Stores",
            "type":"Retail Goods"
        }
    ],
    "sg:phone":"+39 0473 212512",
    "sg:postcode":"39012",
    "sg:province":"Bolzano/Bozen",
    "sg:tags":[
        "product",
        "related"
    ],
    "wof:name":"Siebenf\u00d6rcher G. & Co. (s.n.c.)",
    "wof:placetype":"venue"
},
  "geometry": {"coordinates":[11.35800457,46.4967155457],"type":"Point"}
}