{
  "type": "Feature",
  "properties": {
    "iso:country":"IT",
    "sg:address":"Corso Cavour 5; Corato; 70033",
    "sg:city":"Corato",
    "sg:classifiers":[
        {
            "category":"Banks & Credit Unions",
            "subcategory":"Bank",
            "type":"Services"
        }
    ],
    "sg:phone":"+39 080 872 4100",
    "sg:postcode":"70033",
    "sg:province":"Bari",
    "wof:name":"Banco Di Napoli Spa",
    "wof:placetype":"venue"
},
  "geometry": {"coordinates":[16.412243,41.154041],"type":"Point"}
}