{
  "type": "Feature",
  "properties": {
    "addr:full":"15/b, Via Cividina 33100 Udine Udine Udine 33100",
    "addr:housenumber":"15 / b",
    "addr:postcode":"33100;33100",
    "addr:street":"Via Cividina",
    "iso:country":"IT",
    "sg:address":"15/b, Via Cividina 33100 Udine",
    "sg:city":"Udine",
    "sg:classifiers":[
        {
            "category":"Shopping",
            "type":"Retail Goods"
        }
    ],
    "sg:phone":"+39 0432 481194",
    "sg:postcode":"33100",
    "sg:province":"Udine",
    "sg:tags":[
        "finished",
        "-",
        "metallic"
    ],
    "wof:name":"Il Cuscinetto S.r.l.",
    "wof:placetype":"venue"
},
  "geometry": {"coordinates":[13.2307243347,46.0649414062],"type":"Point"}
}