{
  "type": "Feature",
  "properties": {
    "iso:country":"IT",
    "sg:address":"9, Via Novara 20020 Magnago",
    "sg:city":"Magnago",
    "sg:classifiers":[
        {
            "category":"Shopping",
            "type":"Retail Goods"
        }
    ],
    "sg:phone":"+39 0331 657430",
    "sg:postcode":"20020",
    "sg:province":"Milano",
    "sg:tags":[
        "finished",
        "-",
        "metallic"
    ],
    "wof:name":"Ghi.ar Di Ferrari B. E C. S.a.s.",
    "wof:placetype":"venue"
},
  "geometry": {"coordinates":[8.782538414,45.5786628723],"type":"Point"}
}