{
  "type": "Feature",
  "properties": {
    "iso:country":"IT",
    "sg:address":"58100 Grosseto",
    "sg:city":"Grosseto",
    "sg:orig_category":"Centri Di Estetica E Cosmesi E Servizi",
    "sg:phone":"+39 0564 22531",
    "sg:postcode":"58100",
    "sg:province":"Grosseto",
    "wof:name":"Labriola Group Di Miserocchi Francesca",
    "wof:placetype":"venue"
},
  "geometry": {"coordinates":[11.11235,42.759632],"type":"Point"}
}