{
  "type": "Feature",
  "properties": {
    "iso:country":"IT",
    "sg:address":"00171 Roma",
    "sg:city":"Roma",
    "sg:orig_category":"Pompe",
    "sg:phone":"+39 06 258 8694",
    "sg:postcode":"00171",
    "sg:province":"Roma",
    "wof:name":"Commel Srl",
    "wof:placetype":"venue"
},
  "geometry": {"coordinates":[12.5619630814,41.8911819458],"type":"Point"}
}