{
  "type": "Feature",
  "properties": {
    "iso:country":"IT",
    "sg:address":"20093 Cologno Monzese",
    "sg:city":"Cologno Monzese",
    "sg:orig_category":"Shopping. Prodotti Cosmetici E Da Toeletta",
    "sg:phone":"+39 02 254 3216",
    "sg:postcode":"20093",
    "sg:province":"Milano",
    "wof:name":"Profumeria Evelyn",
    "wof:placetype":"venue"
},
  "geometry": {"coordinates":[9.271582,45.528049],"type":"Point"}
}