{
  "type": "Feature",
  "properties": {
    "iso:country":"IT",
    "sg:address":"60122 Ancona",
    "sg:city":"Ancona",
    "sg:orig_category":"Servizi Ausiliari Dei Mezzi Di Trasporto",
    "sg:phone":"+39 071 200585",
    "sg:postcode":"60122",
    "sg:province":"Ancona",
    "wof:name":"Autoscuola Cantiani Del Centro",
    "wof:placetype":"venue"
},
  "geometry": {"coordinates":[13.513769,43.616932],"type":"Point"}
}