{
  "type": "Feature",
  "properties": {
    "addr:full":"53, Via Como 23883 Brivio Brivio Lecco 23883",
    "addr:postcode":"23883;23883",
    "addr:street":"Via Como",
    "iso:country":"IT",
    "sg:address":"53, Via Como 23883 Brivio",
    "sg:city":"Brivio",
    "sg:classifiers":[
        {
            "category":"Parking",
            "subcategory":"Lot",
            "type":"Transportation"
        }
    ],
    "sg:phone":"+39 039 532 1318",
    "sg:postcode":"23883",
    "sg:province":"Lecco",
    "sg:tags":[
        "transport",
        "road"
    ],
    "wof:name":"F.t.i. Di Fumagalli Valter & C. S.a.s.",
    "wof:placetype":"venue"
},
  "geometry": {"coordinates":[9.431131,45.734985],"type":"Point"}
}