{
  "type": "Feature",
  "properties": {
    "iso:country":"IT",
    "sg:address":"34147 Trieste",
    "sg:city":"Trieste",
    "sg:orig_category":"Piscine Ed Accessori - Costruzione E Manutenzione",
    "sg:phone":"+39 040 381429",
    "sg:postcode":"34147",
    "sg:province":"Trieste",
    "wof:name":"Genercos Srl",
    "wof:placetype":"venue"
},
  "geometry": {"coordinates":[13.8092727661,45.6152534485],"type":"Point"}
}