{
  "type": "Feature",
  "properties": {
    "iso:country":"IT",
    "sg:address":"6, V. Anicio Paolino 00178 Roma",
    "sg:city":"Roma",
    "sg:classifiers":[
        {
            "category":"Shopping",
            "type":"Retail Goods"
        }
    ],
    "sg:phone":"+39 39067809997",
    "sg:postcode":"00178",
    "sg:province":"Roma",
    "sg:tags":[
        "finished",
        "-",
        "metallic"
    ],
    "sg:website":"http://www.tfpiping.com",
    "wof:name":"Tf Piping Srl Iso 902 Sgs",
    "wof:placetype":"venue"
},
  "geometry": {"coordinates":[12.537156105,41.8594779968],"type":"Point"}
}