{
  "type": "Feature",
  "properties": {
    "iso:country":"IT",
    "sg:address":"47039 Savignano Sul Rubicone",
    "sg:city":"Savignano sul Rubicone",
    "sg:orig_category":"Forniture Per Abbigliamento E Pelletterie",
    "sg:phone":"+39 0541 932886",
    "sg:postcode":"47039",
    "sg:province":"Forl\u00ec-Cesena",
    "wof:name":"Tacchificio E.z. Srl",
    "wof:placetype":"venue"
},
  "geometry": {"coordinates":[12.4018383026,44.1032371521],"type":"Point"}
}