{
  "type": "Feature",
  "properties": {
    "iso:country":"IT",
    "sg:address":"11/13, Via Luda 10022 Carmagnola",
    "sg:city":"Carmagnola",
    "sg:classifiers":[
        {
            "category":"Shopping",
            "subcategory":"Clothing, Apparel, & Fashions",
            "type":"Retail Goods"
        }
    ],
    "sg:phone":"+39 011 972 1336",
    "sg:postcode":"10022",
    "sg:province":"Torino",
    "sg:tags":[
        "clothes"
    ],
    "wof:name":"Offer S.r.l.",
    "wof:placetype":"venue"
},
  "geometry": {"coordinates":[7.711622,44.83749],"type":"Point"}
}