{
  "type": "Feature",
  "properties": {
    "addr:full":"67039 Sulmona L'Aquila 67039",
    "addr:postcode":"67039;67039",
    "iso:country":"IT",
    "sg:address":"67039 Sulmona",
    "sg:orig_category":"Non-classified Establishments",
    "sg:phone":"+39 0864 251787",
    "sg:postcode":"67039",
    "sg:province":"L'Aquila",
    "wof:name":"Savino Fiorenzo Srl",
    "wof:placetype":"venue"
},
  "geometry": {"coordinates":[13.406265,42.349148],"type":"Point"}
}