{
  "type": "Feature",
  "properties": {
    "iso:country":"IT",
    "sg:address":"25, Via Airuno 23883 Brivio",
    "sg:city":"Brivio",
    "sg:classifiers":[
        {
            "category":"Wholesale",
            "subcategory":"Machinery & Supplies",
            "type":"Manufacturing & Wholesale Goods"
        }
    ],
    "sg:phone":"+39 39039932951",
    "sg:postcode":"23883",
    "sg:province":"Lecco",
    "sg:tags":[
        "equipment",
        "precision"
    ],
    "wof:name":"Ravasi Robotics Srl",
    "wof:placetype":"venue"
},
  "geometry": {"coordinates":[9.4265937805,45.7831306458],"type":"Point"}
}