{
  "type": "Feature",
  "properties": {
    "addr:full":"Via Verona, 17 - Crocetta 40019 Sant'agata Bolognese Bologna 40019",
    "addr:housenumber":"17",
    "addr:postcode":"40019;40019",
    "addr:street":"Via Verona;Crocetta",
    "iso:country":"IT",
    "sg:address":"Via Verona, 17 - Crocetta 40019 Sant'agata Bolognese",
    "sg:classifiers":[
        {
            "category":"Manufacturing",
            "subcategory":"Metals",
            "type":"Manufacturing & Wholesale Goods"
        }
    ],
    "sg:phone":"+39 051 983084",
    "sg:postcode":"40019",
    "sg:province":"Bologna",
    "sg:tags":[
        "alloy",
        "construction",
        "lightweight"
    ],
    "sg:website":"www.metaco.it",
    "wof:name":"Metaco Snc",
    "wof:placetype":"venue"
},
  "geometry": {"coordinates":[11.159040451,44.6962394714],"type":"Point"}
}