{
  "type": "Feature",
  "properties": {
    "iso:country":"IT",
    "sg:address":"16, Via Saideno 23851 Galbiate",
    "sg:city":"Galbiate",
    "sg:classifiers":[
        {
            "category":"Shopping",
            "subcategory":"Clothing, Apparel, & Fashions",
            "type":"Retail Goods"
        }
    ],
    "sg:phone":"+39 0341 540136",
    "sg:postcode":"23851",
    "sg:province":"Lecco",
    "sg:tags":[
        "clothes"
    ],
    "wof:name":"Said (s.p.a.)",
    "wof:placetype":"venue"
},
  "geometry": {"coordinates":[9.363521,45.817364],"type":"Point"}
}