{
  "type": "Feature",
  "properties": {
    "iso:country":"IT",
    "sg:address":"25018 Montichiari",
    "sg:city":"Montichiari",
    "sg:orig_category":"Centri Di Estetica E Cosmesi E Servizi",
    "sg:phone":"+39 030 965 7181",
    "sg:postcode":"25018",
    "sg:province":"Brescia",
    "wof:name":"Pingo Milena New Line Estetica",
    "wof:placetype":"venue"
},
  "geometry": {"coordinates":[10.367213,45.413536],"type":"Point"}
}