{
  "type": "Feature",
  "properties": {
    "addr:full":"45130 Rovigo RO",
    "addr:postcode":"45130",
    "iso:country":"IT",
    "sg:address":"45130 Rovigo",
    "sg:orig_category":"Carta E Cartone - Produzione E Commercio",
    "sg:phone":"+39 0425 471038",
    "sg:province":"RO",
    "wof:name":"Unicarton Srl",
    "wof:placetype":"venue"
},
  "geometry": {"coordinates":[11.825771,44.997959],"type":"Point"}
}