{
  "type": "Feature",
  "properties": {
    "addr:full":"24050 Grassobbio Grassobbio Bergamo 24050",
    "addr:postcode":"24050;24050",
    "iso:country":"IT",
    "sg:address":"24050 Grassobbio",
    "sg:city":"Grassobbio",
    "sg:orig_category":"Dolciumi E Gelati",
    "sg:phone":"+39 035 525908",
    "sg:postcode":"24050",
    "sg:province":"Bergamo",
    "wof:name":"Patelli Pierantonio",
    "wof:placetype":"venue"
},
  "geometry": {"coordinates":[9.7206,45.662579],"type":"Point"}
}