{
  "type": "Feature",
  "properties": {
    "iso:country":"IT",
    "sg:address":"20090 Trezzano Naviglio",
    "sg:orig_category":"Circuiti Stampati",
    "sg:phone":"+39 02 445 0181",
    "sg:postcode":"20090",
    "sg:province":"Milano",
    "sg:website":"http://agm-pcb.it",
    "wof:name":"A.g.m. Srl",
    "wof:placetype":"venue"
},
  "geometry": {"coordinates":[9.059034,45.426376],"type":"Point"}
}