{
  "type": "Feature",
  "properties": {
    "iso:country":"IT",
    "sg:address":"20122 Milano",
    "sg:city":"Milano",
    "sg:orig_category":"Servizi Ausiliari Di Certificati, Riproduzioni, Disegni E Foto",
    "sg:phone":"+39 02 5518 9040",
    "sg:postcode":"20122",
    "sg:province":"Milano",
    "wof:name":"Silvia Bottino Photographer & C. Snc",
    "wof:placetype":"venue"
},
  "geometry": {"coordinates":[9.199568,45.455116],"type":"Point"}
}