{
  "type": "Feature",
  "properties": {
    "iso:country":"IT",
    "sg:address":"Via Per Castelletto Km. 1.200 28040 Borgo Ticino",
    "sg:city":"Borgo Ticino",
    "sg:classifiers":[
        {
            "category":"Professional",
            "subcategory":"Engineering",
            "type":"Services"
        }
    ],
    "sg:phone":"+39 39032190175",
    "sg:postcode":"28040",
    "sg:province":"Novara",
    "sg:tags":[
        "machine",
        "-",
        "mechanical"
    ],
    "wof:name":"Saronni (s.p.a.)",
    "wof:placetype":"venue"
},
  "geometry": {"coordinates":[8.618671,45.445084],"type":"Point"}
}