{
  "type": "Feature",
  "properties": {
    "addr:full":"20040 Usmate Velate Usmate Velate Milano 20040",
    "addr:postcode":"20040;20040",
    "iso:country":"IT",
    "sg:address":"20040 Usmate Velate",
    "sg:city":"Usmate Velate",
    "sg:orig_category":"Servizi Editoriali. Servizi Per Aziende, Manifestazioni E Supporto Agli Scambi Commerciali",
    "sg:phone":"+39 039 673669",
    "sg:postcode":"20040",
    "sg:province":"Milano",
    "wof:name":"Atena Sas Di Giulia Galimberti",
    "wof:placetype":"venue"
},
  "geometry": {"coordinates":[9.358834,45.650505],"type":"Point"}
}