{
  "type": "Feature",
  "properties": {
    "addr:full":"Vle Umbria 16 35043 Monselice Monselice Padova 35043",
    "addr:housenumber":"16",
    "addr:postcode":"35043;35043",
    "addr:street":"Vle Umbria",
    "iso:country":"IT",
    "sg:address":"Vle Umbria 16 35043 Monselice",
    "sg:city":"Monselice",
    "sg:classifiers":[
        {
            "category":"Food & Beverages",
            "subcategory":"Fruits & Vegetables",
            "type":"Retail Goods"
        }
    ],
    "sg:phone":"+39 0429 72161",
    "sg:postcode":"35043",
    "sg:province":"Padova",
    "sg:tags":[
        "canned"
    ],
    "sg:website":"www.collieuganei.it",
    "wof:name":"Saiace Societa' Azionaria Industrie Alimentari Colli Euganei Spa",
    "wof:placetype":"venue"
},
  "geometry": {"coordinates":[11.876589,45.409569],"type":"Point"}
}