{
  "type": "Feature",
  "properties": {
    "iso:country":"IT",
    "sg:address":"20020 Arese",
    "sg:city":"Arese",
    "sg:orig_category":"Accessori Dei Mezzi Di Trasporto",
    "sg:phone":"+39 02 9358 9523",
    "sg:postcode":"20020",
    "sg:province":"Milano",
    "wof:name":"Eleri Di Apostolo Mauro",
    "wof:placetype":"venue"
},
  "geometry": {"coordinates":[9.07752,45.552658],"type":"Point"}
}