{
  "type": "Feature",
  "properties": {
    "iso:country":"IT",
    "sg:address":"20090 Opera",
    "sg:city":"Opera",
    "sg:orig_category":"Ricambi E Componenti Dei Mezzi Di Trasporto",
    "sg:phone":"+39 02 5760 0741",
    "sg:postcode":"20090",
    "sg:province":"Milano",
    "wof:name":"Benzoni Angelo & C. Srl",
    "wof:placetype":"venue"
},
  "geometry": {"coordinates":[9.196614,45.36871],"type":"Point"}
}