{
  "type": "Feature",
  "properties": {
    "iso:country":"IT",
    "sg:address":"30039 Stra",
    "sg:city":"Stra",
    "sg:orig_category":"Abbigliamento Esterno, Maglierie E Pelliccerie. Calzature, Pelletterie E Pelli",
    "sg:phone":"+39 049 980 1188",
    "sg:postcode":"30039",
    "sg:province":"Venezia",
    "wof:name":"Emmebi Due Snc",
    "wof:placetype":"venue"
},
  "geometry": {"coordinates":[12.071679,45.384506],"type":"Point"}
}