{
  "type": "Feature",
  "properties": {
    "addr:full":"20037 Paderno Dugnano Paderno Dugnano Milano 20037",
    "addr:postcode":"20037;20037",
    "iso:country":"IT",
    "sg:address":"20037 Paderno Dugnano",
    "sg:city":"Paderno Dugnano",
    "sg:orig_category":"Lavorazioni Metalli, Stampaggio E Saldatura",
    "sg:phone":"+39 02 918 2769",
    "sg:postcode":"20037",
    "sg:province":"Milano",
    "wof:name":"Bottan Egidio",
    "wof:placetype":"venue"
},
  "geometry": {"coordinates":[9.137139,45.573738],"type":"Point"}
}