{
  "type": "Feature",
  "properties": {
    "iso:country":"IT",
    "sg:address":"20094 Corsico",
    "sg:city":"Corsico",
    "sg:orig_category":"Trattamenti Termici E Superficiali Metalli, Galvanotecnica",
    "sg:phone":"+39 02 440 1098",
    "sg:postcode":"20094",
    "sg:province":"Milano",
    "wof:name":"Nova Color 93 S.r.l.",
    "wof:placetype":"venue"
},
  "geometry": {"coordinates":[9.081969,45.425674],"type":"Point"}
}