{
  "type": "Feature",
  "properties": {
    "addr:full":"51011 Buggiano Buggiano Pistoia 51011",
    "addr:postcode":"51011;51011",
    "iso:country":"IT",
    "sg:address":"51011 Buggiano",
    "sg:city":"Buggiano",
    "sg:orig_category":"Forniture Per Abbigliamento E Pelletterie",
    "sg:phone":"+39 0572 31700",
    "sg:postcode":"51011",
    "sg:province":"Pistoia",
    "wof:name":"Lavorazione Piume S.p.a. Salpi",
    "wof:placetype":"venue"
},
  "geometry": {"coordinates":[10.9170360565,43.933052063],"type":"Point"}
}