{
  "type": "Feature",
  "properties": {
    "iso:country":"IT",
    "sg:address":"70121 Bari",
    "sg:city":"Bari",
    "sg:orig_category":"Tessuti Arredamento, Tende E Tappeti. Forniture Per Edilizia E Lavori Pubblici",
    "sg:phone":"+39 080 553 1193",
    "sg:postcode":"70121",
    "sg:province":"Bari",
    "wof:name":"Barsan Sas",
    "wof:placetype":"venue"
},
  "geometry": {"coordinates":[16.879181,41.121422],"type":"Point"}
}