{
  "type": "Feature",
  "properties": {
    "iso:country":"IT",
    "sg:address":"11, V. Stradone 47042 Sala Di Cesenatico",
    "sg:city":"Cesenatico",
    "sg:classifiers":[
        {
            "category":"Autos & Motor Vehicles",
            "subcategory":"Automobile Sales",
            "type":"Retail Goods"
        }
    ],
    "sg:phone":"+39 39054788112",
    "sg:postcode":"47042",
    "sg:province":"Forl\u00ec-Cesena",
    "sg:tags":[
        "industrial"
    ],
    "wof:name":"Eredi Parini Primo Di Parini Vinicio & C. Sas",
    "wof:placetype":"venue"
},
  "geometry": {"coordinates":[12.378229,44.155373],"type":"Point"}
}