{
  "type": "Feature",
  "properties": {
    "iso:country":"IT",
    "sg:address":"46010 Gazzuolo",
    "sg:city":"Belforte",
    "sg:orig_category":"Geometri - Studi",
    "sg:phone":"+39 0376 956067",
    "sg:postcode":"46010",
    "sg:province":"Mantova",
    "wof:name":"Studio Tecnico Parazzi",
    "wof:placetype":"venue"
},
  "geometry": {"coordinates":[10.56167,45.082401],"type":"Point"}
}