{
  "type": "Feature",
  "properties": {
    "iso:country":"IT",
    "sg:address":"92024 Canicatti'",
    "sg:orig_category":"Salotti, Poltrone, Sedie E Tavoli",
    "sg:phone":"+39 0922 832810",
    "sg:postcode":"92024",
    "sg:province":"Agrigento",
    "wof:name":"Di Mauro Salotti Sas",
    "wof:placetype":"venue"
},
  "geometry": {"coordinates":[13.592132,37.306145],"type":"Point"}
}