{
  "type": "Feature",
  "properties": {
    "iso:country":"IT",
    "sg:address":"7, Via Garzonera 21029 Vergiate",
    "sg:city":"Vergiate",
    "sg:classifiers":[
        {
            "category":"Shopping",
            "subcategory":"Crafts & Fabrics",
            "type":"Retail Goods"
        }
    ],
    "sg:phone":"+39 0331 946065",
    "sg:postcode":"21029",
    "sg:province":"Varese",
    "wof:name":"Novilsintetic S.r.l.",
    "wof:placetype":"venue"
},
  "geometry": {"coordinates":[8.6858386993,45.7129173279],"type":"Point"}
}