{
  "type": "Feature",
  "properties": {
    "addr:full":"28/30, Viale Dell' Industria 36070 Trissino Trissino Vicenza 36070",
    "addr:housenumber":"28 / 30",
    "addr:postcode":"36070;36070",
    "addr:street":"Viale Dell ' Industria",
    "iso:country":"IT",
    "sg:address":"28/30, Viale Dell' Industria 36070 Trissino",
    "sg:city":"Trissino",
    "sg:classifiers":[
        {
            "category":"Shopping",
            "subcategory":"Jewelry",
            "type":"Retail Goods"
        }
    ],
    "sg:phone":"+39 0445 962133",
    "sg:postcode":"36070",
    "sg:province":"Vicenza",
    "sg:tags":[
        "jewellery"
    ],
    "wof:name":"Laurentia Gioielli Srl",
    "wof:placetype":"venue"
},
  "geometry": {"coordinates":[11.368587,45.589348],"type":"Point"}
}