{
  "type": "Feature",
  "properties": {
    "iso:country":"IT",
    "sg:address":"70043 Monopoli",
    "sg:city":"Monopoli",
    "sg:classifiers":[
        {
            "category":"Health Services",
            "subcategory":"Health Practitioner",
            "type":"Services"
        }
    ],
    "sg:phone":"+39 080 937 1449",
    "sg:postcode":"70043",
    "sg:province":"Bari",
    "sg:tags":[
        "medici"
    ],
    "wof:name":"Specchia Alfredo",
    "wof:placetype":"venue"
},
  "geometry": {"coordinates":[16.8742980957,41.1148796082],"type":"Point"}
}