{
  "type": "Feature",
  "properties": {
    "addr:full":"171, Via Stra' 37030 Colognola Ai Colli Colognola ai Colli Verona 37030",
    "addr:housenumber":"171",
    "addr:postcode":"37030;37030",
    "addr:street":"Via Stra '",
    "iso:country":"IT",
    "sg:address":"171, Via Stra' 37030 Colognola Ai Colli",
    "sg:city":"Colognola ai Colli",
    "sg:classifiers":[
        {
            "category":"Manufacturing",
            "subcategory":"Rubber & Plastics",
            "type":"Manufacturing & Wholesale Goods"
        }
    ],
    "sg:phone":"+39 045 615 2044",
    "sg:postcode":"37030",
    "sg:province":"Verona",
    "wof:name":"Besafilm Srl",
    "wof:placetype":"venue"
},
  "geometry": {"coordinates":[11.1766996384,45.4166526794],"type":"Point"}
}