{
  "type": "Feature",
  "properties": {
    "iso:country":"IT",
    "sg:address":"20155 Milano",
    "sg:city":"Milano",
    "sg:orig_category":"Abbigliamento - Vendita Al Dettaglio",
    "sg:phone":"+39 02 3300 2793",
    "sg:postcode":"20155",
    "sg:province":"Milano",
    "wof:name":"Eredi Verzoni Bruna Snc",
    "wof:placetype":"venue"
},
  "geometry": {"coordinates":[9.152702,45.49485],"type":"Point"}
}