{
  "type": "Feature",
  "properties": {
    "addr:full":"00146 Roma Roma Roma 00146",
    "addr:postcode":"00146;00146",
    "iso:country":"IT",
    "sg:address":"00146 Roma",
    "sg:city":"Roma",
    "sg:orig_category":"Automobili E Mezzi Di Trasporto",
    "sg:phone":"+39 06 559 4504",
    "sg:postcode":"00146",
    "sg:province":"Roma",
    "sg:website":"http://www.bossiauto.com",
    "wof:name":"Bossi Auto",
    "wof:placetype":"venue"
},
  "geometry": {"coordinates":[12.469587,41.858105],"type":"Point"}
}