{
  "type": "Feature",
  "properties": {
    "iso:country":"IT",
    "sg:address":"36071 Arzignano",
    "sg:city":"Arzignano",
    "sg:orig_category":"Carrelli Elevatori E Trasportatori - Commercio E Noleggio",
    "sg:phone":"+39 0444 671280",
    "sg:postcode":"36071",
    "sg:province":"Vicenza",
    "sg:website":"http://www.degrocar.it",
    "wof:name":"Degrocar Srl",
    "wof:placetype":"venue"
},
  "geometry": {"coordinates":[11.385962,45.615944],"type":"Point"}
}