{
  "type": "Feature",
  "properties": {
    "addr:full":"10098 Rivoli Rivoli Torino 10098",
    "addr:postcode":"10098;10098",
    "iso:country":"IT",
    "sg:address":"10098 Rivoli",
    "sg:city":"Rivoli",
    "sg:orig_category":"Impianti Elettrici Industriali E Civili - Installazione E Manutenzione",
    "sg:phone":"+39 011 956 1596",
    "sg:postcode":"10098",
    "sg:province":"Torino",
    "wof:name":"I.t.e.l. Impianti Sas",
    "wof:placetype":"venue"
},
  "geometry": {"coordinates":[7.521297,45.0667],"type":"Point"}
}