{
  "type": "Feature",
  "properties": {
    "addr:full":"87032 Amantea Amantea Cosenza 87032",
    "addr:postcode":"87032;87032",
    "iso:country":"IT",
    "sg:address":"87032 Amantea",
    "sg:city":"Amantea",
    "sg:orig_category":"Prodotti Alimentari",
    "sg:phone":"+39 0982 424940",
    "sg:postcode":"87032",
    "sg:province":"Cosenza",
    "wof:name":"Rocco Morelli & Figli Snc",
    "wof:placetype":"venue"
},
  "geometry": {"coordinates":[16.0700397491,39.1344184875],"type":"Point"}
}