{
  "type": "Feature",
  "properties": {
    "iso:country":"IT",
    "sg:address":"Localita' Zona Industriale Tronco C 07046 Porto Torres",
    "sg:city":"Porto Torres",
    "sg:classifiers":[
        {
            "category":"Manufacturing",
            "subcategory":"Rubber & Plastics",
            "type":"Manufacturing & Wholesale Goods"
        }
    ],
    "sg:phone":"+39 39079513634",
    "sg:postcode":"07046",
    "sg:province":"Sassari",
    "wof:name":"Complast S.r.l.",
    "wof:placetype":"venue"
},
  "geometry": {"coordinates":[8.5584688187,40.7271652222],"type":"Point"}
}