{
  "type": "Feature",
  "properties": {
    "addr:full":"15047 Spinetta Marengo AL",
    "addr:postcode":"15047",
    "iso:country":"IT",
    "sg:address":"15047 Spinetta Marengo",
    "sg:orig_category":"Forniture Per Edilizia E Lavori Pubblici",
    "sg:phone":"+39 0131 610043",
    "sg:province":"AL",
    "wof:name":"Mendola Giuseppe",
    "wof:placetype":"venue"
},
  "geometry": {"coordinates":[8.6853723526,44.8805503845],"type":"Point"}
}