{
  "type": "Feature",
  "properties": {
    "addr:full":"00192 Roma Roma Roma 00192",
    "addr:postcode":"00192;00192",
    "iso:country":"IT",
    "sg:address":"00192 Roma",
    "sg:city":"Roma",
    "sg:orig_category":"Professionisti - Studi E Servizi Ed Associazioni Di Interesse Aziendale. Associazioni Ed Organismi Di Interesse Pubblico",
    "sg:phone":"+39 06 361 0992",
    "sg:postcode":"00192",
    "sg:province":"Roma",
    "wof:name":"U.c.l.a.i.",
    "wof:placetype":"venue"
},
  "geometry": {"coordinates":[12.4633617401,41.9090995789],"type":"Point"}
}