{
  "type": "Feature",
  "properties": {
    "addr:full":"00040 Morena Roma 00040",
    "addr:housenumber":"00040",
    "addr:postcode":"00040",
    "addr:street":"Morena Roma",
    "iso:country":"IT",
    "sg:address":"00040 Morena",
    "sg:orig_category":"Telecomunicazioni E Telefonia, Impianti, Apparecchi E Servizi",
    "sg:phone":"+39 06 790421",
    "sg:postcode":"00040",
    "sg:province":"Roma",
    "wof:name":"Lan Net Srl",
    "wof:placetype":"venue"
},
  "geometry": {"coordinates":[12.6082410812,41.8184318542],"type":"Point"}
}