{
  "type": "Feature",
  "properties": {
    "addr:full":"2, Contrada Fontanoli 65019 Pianella Pianella Pescara 65019",
    "addr:postcode":"65019;65019",
    "addr:street":"Contrada Fontanoli",
    "iso:country":"IT",
    "sg:address":"2, Contrada Fontanoli 65019 Pianella",
    "sg:city":"Pianella",
    "sg:classifiers":[
        {
            "category":"Shopping",
            "subcategory":"Clothing, Apparel, & Fashions",
            "type":"Retail Goods"
        }
    ],
    "sg:phone":"+39 39085973341",
    "sg:postcode":"65019",
    "sg:province":"Pescara",
    "sg:tags":[
        "clothes"
    ],
    "wof:name":"Eurostyle S.r.l.",
    "wof:placetype":"venue"
},
  "geometry": {"coordinates":[14.041872,42.403339],"type":"Point"}
}