{
  "type": "Feature",
  "properties": {
    "addr:full":"33, Str. St. Z.i. Predda Niedda Nord 07100 Sassari Sassari Sassari 07100",
    "addr:postcode":"07100;07100",
    "addr:street":"Str. St.;Predda Niedda Nord",
    "iso:country":"IT",
    "sg:address":"33, Str. St. Z.i. Predda Niedda Nord 07100 Sassari",
    "sg:city":"Sassari",
    "sg:classifiers":[
        {
            "category":"Shopping",
            "type":"Retail Goods"
        }
    ],
    "sg:phone":"+39 079 267 3128",
    "sg:postcode":"07100",
    "sg:province":"Sassari",
    "sg:tags":[
        "finished",
        "-",
        "metallic"
    ],
    "sg:website":"http://www.paginegialle.it/flairtec",
    "wof:name":"F.l. Air Tecnica Srl",
    "wof:placetype":"venue"
},
  "geometry": {"coordinates":[8.3745718002,40.7555809021],"type":"Point"}
}