{
  "type": "Feature",
  "properties": {
    "iso:country":"IT",
    "sg:address":"20121 Milano",
    "sg:city":"Milano",
    "sg:orig_category":"Dottori Commercialisti - Studi",
    "sg:phone":"+39 02 2900 5808",
    "sg:postcode":"20121",
    "sg:province":"Milano",
    "sg:website":"http://www.cedaz.it",
    "wof:name":"Cedaz Srl",
    "wof:placetype":"venue"
},
  "geometry": {"coordinates":[9.19269,45.472549],"type":"Point"}
}