{
  "type": "Feature",
  "properties": {
    "iso:country":"IT",
    "sg:address":"1938, Via Emilia 47822 Santarcangelo Di Romagna",
    "sg:city":"Santarcangelo di Romagna",
    "sg:classifiers":[
        {
            "category":"Professional",
            "subcategory":"Engineering",
            "type":"Services"
        }
    ],
    "sg:phone":"+39 0541 350511",
    "sg:postcode":"47822",
    "sg:province":"Rimini",
    "sg:tags":[
        "machine",
        "-",
        "mechanical"
    ],
    "wof:name":"Paglierani Costruzioni Meccaniche Di Antolini Primo & C. S.a.",
    "wof:placetype":"venue"
},
  "geometry": {"coordinates":[12.457531,44.063526],"type":"Point"}
}