{
  "type": "Feature",
  "properties": {
    "addr:full":"37045 Legnago Legnago Verona 37045",
    "addr:postcode":"37045;37045",
    "iso:country":"IT",
    "sg:address":"37045 Legnago",
    "sg:city":"Legnago",
    "sg:orig_category":"Elettrotecnica Industriale, Prodotti E Apparecchiature",
    "sg:phone":"+39 0442 635811",
    "sg:postcode":"37045",
    "sg:province":"Verona",
    "sg:website":"http://www.paginegialle.it/rielloelettronica",
    "wof:name":"Riello Elettronica Spa",
    "wof:placetype":"venue"
},
  "geometry": {"coordinates":[10.912846,45.395737],"type":"Point"}
}