{
  "type": "Feature",
  "properties": {
    "iso:country":"IT",
    "sg:address":"10036 Settimo Torinese",
    "sg:city":"Settimo Torinese",
    "sg:orig_category":"Acciai Comuni",
    "sg:phone":"+39 011 897 7904",
    "sg:postcode":"10036",
    "sg:province":"Torino",
    "wof:name":"O.m.a.s. Srl",
    "wof:placetype":"venue"
},
  "geometry": {"coordinates":[7.741707,45.142063],"type":"Point"}
}