{
  "type": "Feature",
  "properties": {
    "addr:full":"20138 Milano Milano Milano 20138",
    "addr:postcode":"20138;20138",
    "iso:country":"IT",
    "sg:address":"20138 Milano",
    "sg:city":"Milano",
    "sg:orig_category":"Professionisti - Studi E Servizi Ed Associazioni Di Interesse Aziendale. Associazioni Ed Organismi Di Interesse Pubblico",
    "sg:phone":"+39 02 501196",
    "sg:postcode":"20138",
    "sg:province":"Milano",
    "wof:name":"Cisq Federaz. Certificaz. Italiana Sistemi Qualita Aziendali",
    "wof:placetype":"venue"
},
  "geometry": {"coordinates":[9.2541475296,45.4480133057],"type":"Point"}
}