{
  "type": "Feature",
  "properties": {
    "iso:country":"IT",
    "sg:address":"20091 Bresso",
    "sg:city":"Bresso",
    "sg:orig_category":"Pompe - Produzione",
    "sg:phone":"+39 02 6640 1099",
    "sg:postcode":"20091",
    "sg:province":"Milano",
    "sg:website":"http://www.mencarellipompesrl.it",
    "wof:name":"Mencarelli Pompe E Valvole Srl",
    "wof:placetype":"venue"
},
  "geometry": {"coordinates":[9.1871566772,45.5454025269],"type":"Point"}
}