{
  "type": "Feature",
  "properties": {
    "addr:full":"91016 Erice Casa Santa Trapani 91016",
    "addr:postcode":"91016;91016",
    "iso:country":"IT",
    "sg:address":"91016 Erice",
    "sg:city":"Casa Santa",
    "sg:orig_category":"Apparecchi Acustici Per Sordita'",
    "sg:phone":"+39 0923 551441",
    "sg:postcode":"91016",
    "sg:province":"Trapani",
    "wof:name":"Ingrassia Claudio",
    "wof:placetype":"venue"
},
  "geometry": {"coordinates":[12.551412,38.024979],"type":"Point"}
}