{
  "type": "Feature",
  "properties": {
    "iso:country":"IT",
    "sg:address":"51031 Agliana",
    "sg:city":"Agliana",
    "sg:orig_category":"Cravatte, Sciarpe E Foulards",
    "sg:phone":"+39 0574 751388",
    "sg:postcode":"51031",
    "sg:province":"Pistoia",
    "sg:website":"http://www.ilguantificio.com",
    "wof:name":"Il Guantificio Srl",
    "wof:placetype":"venue"
},
  "geometry": {"coordinates":[10.994479,43.899651],"type":"Point"}
}