{
  "type": "Feature",
  "properties": {
    "addr:full":"20017 Passirana Passirana Milano 20017",
    "addr:postcode":"20017;20017",
    "addr:street":"Passirana",
    "iso:country":"IT",
    "sg:address":"20017 Passirana",
    "sg:city":"Passirana",
    "sg:orig_category":"Apparecchiature Ed Attrezzature Meccaniche",
    "sg:phone":"+39 02 930 7468",
    "sg:postcode":"20017",
    "sg:province":"Milano",
    "wof:name":"F.lli Lauria Di Lauria Salvatore E C.",
    "wof:placetype":"venue"
},
  "geometry": {"coordinates":[9.213289,45.470776],"type":"Point"}
}