{
  "type": "Feature",
  "properties": {
    "addr:full":"Via Dante Alighieri 7 21019 Somma Lombardo Somma Lombardo Varese 21019",
    "addr:housenumber":"7",
    "addr:postcode":"21019;21019",
    "addr:street":"Via Dante Alighieri",
    "iso:country":"IT",
    "sg:address":"Via Dante Alighieri 7 21019 Somma Lombardo",
    "sg:city":"Somma Lombardo",
    "sg:classifiers":[
        {
            "category":"Utilities",
            "subcategory":"Natural Gas",
            "type":"Services"
        }
    ],
    "sg:phone":"+39 0331 256304",
    "sg:postcode":"21019",
    "sg:province":"Varese",
    "sg:tags":[
        "cylinder",
        "pneumatic"
    ],
    "wof:name":"Silmer Srl",
    "wof:placetype":"venue"
},
  "geometry": {"coordinates":[8.7358427048,45.6881523132],"type":"Point"}
}