{
  "type": "Feature",
  "properties": {
    "addr:full":"50018 Scandicci Scandicci Firenze 50018",
    "addr:postcode":"50018;50018",
    "iso:country":"IT",
    "sg:address":"50018 Scandicci",
    "sg:city":"Scandicci",
    "sg:orig_category":"Servizi E Lavori Per Abbigliamento E Pelletterie. Arte Ed Artigianato Artistico. Shopping",
    "sg:phone":"+39 055 735 1037",
    "sg:postcode":"50018",
    "sg:province":"Firenze",
    "wof:name":"Massimetti Fabio",
    "wof:placetype":"venue"
},
  "geometry": {"coordinates":[11.165927,43.761204],"type":"Point"}
}