{
  "type": "Feature",
  "properties": {
    "iso:country":"IT",
    "sg:address":"73010 Surbo",
    "sg:city":"Surbo",
    "sg:orig_category":"Legno E Semilavorati. Macchine E Forniture Per Arredamento E Industria Del Legno. Hobbistica",
    "sg:phone":"+39 338 338 2211",
    "sg:postcode":"73010",
    "sg:province":"Lecce",
    "wof:name":"Ferramenta Danilo Srl",
    "wof:placetype":"venue"
},
  "geometry": {"coordinates":[18.134554,40.389034],"type":"Point"}
}