{
  "type": "Feature",
  "properties": {
    "addr:full":"30124 Venezia Venezia Venezia 30124",
    "addr:postcode":"30124;30124",
    "iso:country":"IT",
    "sg:address":"30124 Venezia",
    "sg:city":"Venezia",
    "sg:classifiers":[
        {
            "category":"Health Services",
            "subcategory":"Health Practitioner",
            "type":"Services"
        }
    ],
    "sg:phone":"+39 041 523 9966",
    "sg:postcode":"30124",
    "sg:province":"Venezia",
    "sg:tags":[
        "medici"
    ],
    "wof:name":"Medicenter",
    "wof:placetype":"venue"
},
  "geometry": {"coordinates":[12.335855,45.434925],"type":"Point"}
}