{
  "type": "Feature",
  "properties": {
    "iso:country":"IT",
    "sg:address":"13/bis, Via Madama Fileppa 80049 Somma Vesuviana",
    "sg:city":"Somma Vesuviana",
    "sg:classifiers":[
        {
            "category":"Home & Garden",
            "subcategory":"Home Furnishings",
            "type":"Retail Goods"
        }
    ],
    "sg:phone":"+39 081 899 7328",
    "sg:postcode":"80049",
    "sg:province":"Napoli",
    "sg:tags":[
        "household"
    ],
    "wof:name":"Lait S.r.l.",
    "wof:placetype":"venue"
},
  "geometry": {"coordinates":[14.251636,40.840096],"type":"Point"}
}