{
  "type": "Feature",
  "properties": {
    "iso:country":"IT",
    "sg:address":"20095 Cusano Milanino",
    "sg:city":"Cusano Milanino",
    "sg:orig_category":"Servizi Ausiliari Dei Mezzi Di Trasporto",
    "sg:phone":"+39 02 613 2171",
    "sg:postcode":"20095",
    "sg:province":"Milano",
    "wof:name":"Facciolo Domenico",
    "wof:placetype":"venue"
},
  "geometry": {"coordinates":[9.192339,45.552616],"type":"Point"}
}