{
  "type": "Feature",
  "properties": {
    "iso:country":"IT",
    "sg:address":"20147 Milano",
    "sg:city":"Milano",
    "sg:orig_category":"Elettrotecnica Industriale, Prodotti E Apparecchiature. Elettronica Industriale, Prodotti E Apparecchiature",
    "sg:phone":"+39 02 412 1455",
    "sg:postcode":"20147",
    "sg:province":"Milano",
    "wof:name":"Sesamo Distribuzione Lombardia Srl",
    "wof:placetype":"venue"
},
  "geometry": {"coordinates":[9.134661,45.451672],"type":"Point"}
}