{
  "type": "Feature",
  "properties": {
    "iso:country":"IT",
    "sg:address":"36061 Bassano Del Grappa",
    "sg:city":"Bassano del Grappa",
    "sg:orig_category":"Architetti - Studi",
    "sg:phone":"+39 0424 522296",
    "sg:postcode":"36061",
    "sg:province":"Vicenza",
    "wof:name":"Fracca Arch. Alberto",
    "wof:placetype":"venue"
},
  "geometry": {"coordinates":[11.573643,45.542103],"type":"Point"}
}