{
  "type": "Feature",
  "properties": {
    "iso:country":"IT",
    "sg:address":"71037 Monte Sant'angelo",
    "sg:orig_category":"Motori Ed Organi Di Trasmissione",
    "sg:phone":"+39 0884 588638",
    "sg:postcode":"71037",
    "sg:province":"Foggia",
    "wof:name":"T.m.i. Sud S.r.l.",
    "wof:placetype":"venue"
},
  "geometry": {"coordinates":[15.9464874268,41.7252311707],"type":"Point"}
}