{
  "type": "Feature",
  "properties": {
    "iso:country":"IT",
    "sg:address":"20090 Fizzonasco Di Pieve Emanuele",
    "sg:city":"Fizzonasco",
    "sg:orig_category":"Arredo Cucina Ed Elettrodomestici. Elettrodomestici",
    "sg:phone":"+39 02 9042 9287",
    "sg:postcode":"20090",
    "sg:province":"Milano",
    "wof:name":"Aspiria Di Favat\u00c0 Giuseppe",
    "wof:placetype":"venue"
},
  "geometry": {"coordinates":[9.168893,45.373943],"type":"Point"}
}