{
  "type": "Feature",
  "properties": {
    "iso:country":"IT",
    "sg:address":"13900 Biella",
    "sg:city":"Biella",
    "sg:orig_category":"Macchine, Impianti Ed Attrezzature Per Abbigliamento E Pelletterie",
    "sg:phone":"+39 015 849 1726",
    "sg:postcode":"13900",
    "sg:province":"Biella",
    "wof:name":"Bandini Utensilmeccanica Sas",
    "wof:placetype":"venue"
},
  "geometry": {"coordinates":[8.061755,45.552181],"type":"Point"}
}