{
  "type": "Feature",
  "properties": {
    "iso:country":"IT",
    "sg:address":"24035 Curno",
    "sg:city":"Curno",
    "sg:orig_category":"Materiali Edili",
    "sg:phone":"+39 035 460876",
    "sg:postcode":"24035",
    "sg:province":"Bergamo",
    "wof:name":"Fort Fibre Ottiche",
    "wof:placetype":"venue"
},
  "geometry": {"coordinates":[9.622319,45.685204],"type":"Point"}
}