{
  "type": "Feature",
  "properties": {
    "addr:full":"58033 Castel Del Piano Castel del Piano Grosseto 58033",
    "addr:housenumber":"del",
    "addr:postcode":"58033;58033",
    "iso:country":"IT",
    "sg:address":"58033 Castel Del Piano",
    "sg:city":"Castel del Piano",
    "sg:classifiers":[
        {
            "category":"Home & Garden",
            "subcategory":"Home Furnishings",
            "type":"Retail Goods"
        }
    ],
    "sg:phone":"+39 0564 955011",
    "sg:postcode":"58033",
    "sg:province":"Grosseto",
    "sg:tags":[
        "art",
        "furniture",
        "shopping",
        "artistic",
        "crafts"
    ],
    "wof:name":"Old England",
    "wof:placetype":"venue"
},
  "geometry": {"coordinates":[11.4907121658,42.9337158203],"type":"Point"}
}