{
  "type": "Feature",
  "properties": {
    "iso:country":"IT",
    "sg:address":"20037 Paderno Dugnano",
    "sg:city":"Paderno Dugnano",
    "sg:orig_category":"Utensili Meccanici E Materiali",
    "sg:phone":"+39 02 9904 4989",
    "sg:postcode":"20037",
    "sg:province":"Milano",
    "wof:name":"Elga Saldatura Srl",
    "wof:placetype":"venue"
},
  "geometry": {"coordinates":[9.176769,45.591236],"type":"Point"}
}