{
  "type": "Feature",
  "properties": {
    "addr:full":"40068 S.lazzaro Di Savena Bologna 40068",
    "addr:postcode":"40068;savena bologna 40068",
    "iso:country":"IT",
    "sg:address":"40068 S.lazzaro Di Savena",
    "sg:orig_category":"Acciaierie E Fonderie",
    "sg:phone":"+39 051 625 7876",
    "sg:postcode":"40068",
    "sg:province":"Bologna",
    "wof:name":"Da Corte Fonderia Snc",
    "wof:placetype":"venue"
},
  "geometry": {"coordinates":[11.425969,44.452267],"type":"Point"}
}