{
  "type": "Feature",
  "properties": {
    "addr:full":"32, Via Della Cooperazione 40129 Bologna Bologna Bologna 40129",
    "addr:postcode":"40129;40129",
    "addr:street":"Via Della Cooperazione",
    "iso:country":"IT",
    "sg:address":"32, Via Della Cooperazione 40129 Bologna",
    "sg:city":"Bologna",
    "sg:classifiers":[
        {
            "category":"Autos & Motor Vehicles",
            "subcategory":"Automobile Sales",
            "type":"Retail Goods"
        }
    ],
    "sg:phone":"+39 39051321571",
    "sg:postcode":"40129",
    "sg:province":"Bologna",
    "sg:tags":[
        "motor-cars"
    ],
    "wof:name":"Comel (s.p.a.)",
    "wof:placetype":"venue"
},
  "geometry": {"coordinates":[11.3462123871,44.5358810425],"type":"Point"}
}