{
  "type": "Feature",
  "properties": {
    "addr:full":"50, Via San Martino 03030 Broccostella Broccostella Frosinone 03030",
    "addr:postcode":"03030;03030",
    "addr:street":"Via San Martino",
    "iso:country":"IT",
    "sg:address":"50, Via San Martino 03030 Broccostella",
    "sg:city":"Broccostella",
    "sg:classifiers":[
        {
            "category":"Manufacturing",
            "subcategory":"Printing",
            "type":"Manufacturing & Wholesale Goods"
        }
    ],
    "sg:phone":"+39 0776 891242",
    "sg:postcode":"03030",
    "sg:province":"Frosinone",
    "sg:tags":[
        "publishing"
    ],
    "wof:name":"Cartiera San Martino S.r.l.",
    "wof:placetype":"venue"
},
  "geometry": {"coordinates":[13.6338157654,41.6975708008],"type":"Point"}
}