{
  "type": "Feature",
  "properties": {
    "iso:country":"IT",
    "sg:address":"25023 Gottolengo",
    "sg:city":"Gottolengo",
    "sg:orig_category":"Macchine, Impianti Ed Attrezzature Per Industria Alimentare E Bevande",
    "sg:phone":"+39 030 995 1050",
    "sg:postcode":"25023",
    "sg:province":"Brescia",
    "wof:name":"Tradizioni Padane Di Salvini Leonardo & Biloni Giuseppe S.n.c.",
    "wof:placetype":"venue"
},
  "geometry": {"coordinates":[10.181282,45.493019],"type":"Point"}
}