{
  "type": "Feature",
  "properties": {
    "addr:full":"20123 Milano Milano Milano 20123",
    "addr:postcode":"20123;20123",
    "iso:country":"IT",
    "sg:address":"20123 Milano",
    "sg:city":"Milano",
    "sg:orig_category":"Penne Stilografiche Ed Articoli Scrittura",
    "sg:phone":"+39 02 8645 1821",
    "sg:postcode":"20123",
    "sg:province":"Milano",
    "wof:name":"Brunori Giuseppe",
    "wof:placetype":"venue"
},
  "geometry": {"coordinates":[9.1817960739,45.4604988098],"type":"Point"}
}