{
  "type": "Feature",
  "properties": {
    "addr:full":"00139 Roma Roma Roma 00139",
    "addr:postcode":"00139;00139",
    "iso:country":"IT",
    "sg:address":"00139 Roma",
    "sg:city":"Roma",
    "sg:classifiers":[
        {
            "category":"Health Services",
            "subcategory":"Health Practitioner",
            "type":"Services"
        }
    ],
    "sg:phone":"+39 06 810 4840",
    "sg:postcode":"00139",
    "sg:province":"Roma",
    "sg:tags":[
        "medici"
    ],
    "wof:name":"Ponzi Silvia",
    "wof:placetype":"venue"
},
  "geometry": {"coordinates":[12.5642261505,41.9869155884],"type":"Point"}
}