{
  "type": "Feature",
  "properties": {
    "addr:full":"Via Bagni 25 34074 Monfalcone Monfalcone Gorizia 34074",
    "addr:housenumber":"25",
    "addr:postcode":"34074;34074",
    "addr:street":"Via Bagni",
    "iso:country":"IT",
    "sg:address":"Via Bagni 25 34074 Monfalcone",
    "sg:city":"Monfalcone",
    "sg:classifiers":[
        {
            "category":"Landmark",
            "subcategory":"Marketplace",
            "type":"Public Place"
        }
    ],
    "sg:phone":"+39 0481 484455",
    "sg:postcode":"34074",
    "sg:province":"Gorizia",
    "sg:tags":[
        "industry",
        "part",
        "bought-in",
        "furniture"
    ],
    "wof:name":"Italeuro Srl",
    "wof:placetype":"venue"
},
  "geometry": {"coordinates":[13.529799,45.78598],"type":"Point"}
}