{
  "type": "Feature",
  "properties": {
    "iso:country":"IT",
    "sg:address":"50019 Firenze",
    "sg:orig_category":"Macchine E Forniture Per Ecologia E Smaltimento Rifiuti",
    "sg:phone":"+39 055 300588",
    "sg:postcode":"50019",
    "sg:province":"Firenze",
    "wof:name":"Masan Srl",
    "wof:placetype":"venue"
},
  "geometry": {"coordinates":[11.256902,43.768734],"type":"Point"}
}