{
  "type": "Feature",
  "properties": {
    "addr:full":"Piazza Xx Settembre 5; Corato; 70033 Corato Bari 70033",
    "addr:housenumber":"5",
    "addr:postcode":"70033;70033",
    "addr:street":"Piazza Xx Settembre",
    "iso:country":"IT",
    "sg:address":"Piazza Xx Settembre 5; Corato; 70033",
    "sg:city":"Corato",
    "sg:classifiers":[
        {
            "category":"Banks & Credit Unions",
            "subcategory":"Bank",
            "type":"Services"
        }
    ],
    "sg:phone":"+39 080 824580",
    "sg:postcode":"70033",
    "sg:province":"Bari",
    "wof:name":"Banca Di Bisceglie",
    "wof:placetype":"venue"
},
  "geometry": {"coordinates":[16.369926,41.078545],"type":"Point"}
}