{
  "type": "Feature",
  "properties": {
    "iso:country":"IT",
    "sg:address":"29, Via Arluno 20010 Casorezzo",
    "sg:city":"Arluno",
    "sg:classifiers":[
        {
            "category":"Manufacturing",
            "subcategory":"Rubber & Plastics",
            "type":"Manufacturing & Wholesale Goods"
        }
    ],
    "sg:phone":"+39 39029010751",
    "sg:postcode":"20010",
    "sg:province":"Milano",
    "wof:name":"Technical Plast S.r.l.",
    "wof:placetype":"venue"
},
  "geometry": {"coordinates":[8.9201078415,45.4986991882],"type":"Point"}
}