{
  "type": "Feature",
  "properties": {
    "addr:full":"00121 Roma Roma Roma 00121",
    "addr:postcode":"00121;00121",
    "iso:country":"IT",
    "sg:address":"00121 Roma",
    "sg:city":"Roma",
    "sg:orig_category":"Campeggio. Automobili E Mezzi Di Trasporto",
    "sg:phone":"+39 06 564 4400",
    "sg:postcode":"00121",
    "sg:province":"Roma",
    "wof:name":"Ellis Srl",
    "wof:placetype":"venue"
},
  "geometry": {"coordinates":[12.281106,41.736481],"type":"Point"}
}