{
  "type": "Feature",
  "properties": {
    "iso:country":"IT",
    "sg:address":"40, Via Dell' Artigianato 59013 Montemurlo",
    "sg:city":"Montemurlo",
    "sg:classifiers":[
        {
            "category":"Sports & Exercise",
            "subcategory":"Playing Field",
            "type":"Entertainment"
        }
    ],
    "sg:phone":"+39 0574 720268",
    "sg:postcode":"59013",
    "sg:province":"Prato",
    "sg:tags":[
        "game"
    ],
    "wof:name":"Filatura Titanus (s.n.c.)",
    "wof:placetype":"venue"
},
  "geometry": {"coordinates":[11.050468,43.911728],"type":"Point"}
}