{
  "type": "Feature",
  "properties": {
    "iso:country":"IT",
    "sg:address":"40069 Zola Predosa",
    "sg:city":"Zola",
    "sg:orig_category":"Serramenti Ed Infissi",
    "sg:phone":"+39 051 751893",
    "sg:postcode":"40069",
    "sg:province":"Bologna",
    "wof:name":"Masetti Sergio",
    "wof:placetype":"venue"
},
  "geometry": {"coordinates":[11.208054,44.494389],"type":"Point"}
}