{
  "type": "Feature",
  "properties": {
    "iso:country":"IT",
    "sg:address":"10, Via Stoppani Antonio 21047 Saronno",
    "sg:city":"Saronno",
    "sg:classifiers":[
        {
            "category":"Shopping",
            "type":"Retail Goods"
        }
    ],
    "sg:phone":"+39 39029602783",
    "sg:postcode":"21047",
    "sg:province":"Varese",
    "sg:tags":[
        "finished",
        "-",
        "metallic"
    ],
    "wof:name":"Fermeccanica (s.r.l.)",
    "wof:placetype":"venue"
},
  "geometry": {"coordinates":[8.8263845444,45.8176040649],"type":"Point"}
}