{
  "type": "Feature",
  "properties": {
    "addr:full":"10156 Torino Torino Torino 10156",
    "addr:postcode":"10156;10156",
    "iso:country":"IT",
    "sg:address":"10156 Torino",
    "sg:city":"Torino",
    "sg:orig_category":"Minuterie Metalliche E Ferramenta. Forniture Per Attivita' Industriali",
    "sg:phone":"+39 011 273 3228",
    "sg:postcode":"10156",
    "sg:province":"Torino",
    "wof:name":"Mollificio Zagato",
    "wof:placetype":"venue"
},
  "geometry": {"coordinates":[7.7368927002,45.1359558105],"type":"Point"}
}