{
  "type": "Feature",
  "properties": {
    "iso:country":"IT",
    "sg:address":"00122 Lido Di Ostia",
    "sg:orig_category":"Banche E Servizi Finanziari",
    "sg:phone":"+39 06 5630 4860",
    "sg:postcode":"00122",
    "sg:province":"Roma",
    "wof:name":"Re Mida Srl",
    "wof:placetype":"venue"
},
  "geometry": {"coordinates":[12.282017,41.732258],"type":"Point"}
}