{
  "type": "Feature",
  "properties": {
    "iso:country":"IT",
    "sg:address":"80143 Napoli",
    "sg:city":"Napoli",
    "sg:orig_category":"Trasporti E Spedizioni Merci",
    "sg:phone":"+39 081 584 1465",
    "sg:postcode":"80143",
    "sg:province":"Napoli",
    "wof:name":"Zecchini Srl",
    "wof:placetype":"venue"
},
  "geometry": {"coordinates":[14.297167,40.871132],"type":"Point"}
}