{
  "type": "Feature",
  "properties": {
    "iso:country":"IT",
    "sg:address":"Via Emilia Ovest 1014 41100 Modena",
    "sg:city":"Modena",
    "sg:orig_category":"Lithos",
    "sg:phone":"+39 059 896811",
    "sg:postcode":"41100",
    "sg:province":"Modena",
    "sg:website":"www.arbegrafiche.it",
    "wof:name":"Arbe Industrie Grafiche Spa",
    "wof:placetype":"venue"
},
  "geometry": {"coordinates":[10.872847,44.652992],"type":"Point"}
}