{
  "type": "Feature",
  "properties": {
    "iso:country":"IT",
    "sg:address":"25124 Brescia",
    "sg:city":"Brescia",
    "sg:orig_category":"Animali Domestici - Toeletta",
    "sg:phone":"+39 030 222327",
    "sg:postcode":"25124",
    "sg:province":"Brescia",
    "wof:name":"Wind's Animals Di Palvarini Roberto",
    "wof:placetype":"venue"
},
  "geometry": {"coordinates":[10.220359,45.517273],"type":"Point"}
}