{
  "type": "Feature",
  "properties": {
    "addr:full":"28012 Cressa Cressa Novara 28012",
    "addr:postcode":"28012;28012",
    "iso:country":"IT",
    "sg:address":"28012 Cressa",
    "sg:city":"Cressa",
    "sg:orig_category":"Trasporti E Spedizioni Merci",
    "sg:phone":"+39 0322 863175",
    "sg:postcode":"28012",
    "sg:province":"Novara",
    "wof:name":"Autotrasporti Molli & Erbetta",
    "wof:placetype":"venue"
},
  "geometry": {"coordinates":[8.496863,45.652748],"type":"Point"}
}