{
  "type": "Feature",
  "properties": {
    "addr:full":"12, Via Sandro Pertini 27010 Miradolo Terme Miradolo Terme Pavia 27010",
    "addr:postcode":"27010;27010",
    "addr:street":"Via Sandro Pertini;Terme;Terme",
    "iso:country":"IT",
    "sg:address":"12, Via Sandro Pertini 27010 Miradolo Terme",
    "sg:city":"Miradolo Terme",
    "sg:classifiers":[
        {
            "category":"Shopping",
            "type":"Retail Goods"
        }
    ],
    "sg:phone":"+39 0382 722474",
    "sg:postcode":"27010",
    "sg:province":"Pavia",
    "sg:tags":[
        "finished",
        "-",
        "metallic"
    ],
    "wof:name":"Vi-ma Di Vitaloni Mario Angelo S.n.c.",
    "wof:placetype":"venue"
},
  "geometry": {"coordinates":[9.4490118027,45.1660423279],"type":"Point"}
}