{
  "type": "Feature",
  "properties": {
    "addr:full":"150, Via S.lucano 32027 Taibon Agordino Taibon Agordino Belluno 32027",
    "addr:housenumber":"150",
    "addr:postcode":"32027;32027",
    "addr:street":"Via S.Lucano;Agordino;Agordino",
    "iso:country":"IT",
    "sg:address":"150, Via S.lucano 32027 Taibon Agordino",
    "sg:city":"Taibon Agordino",
    "sg:classifiers":[
        {
            "category":"Wholesale",
            "subcategory":"Medical Equipment & Supplies",
            "type":"Manufacturing & Wholesale Goods"
        }
    ],
    "sg:phone":"+39 0437 660238",
    "sg:postcode":"32027",
    "sg:province":"Belluno",
    "sg:tags":[
        "-",
        "health",
        "instrument"
    ],
    "wof:name":"Dpa S.r.l.",
    "wof:placetype":"venue"
},
  "geometry": {"coordinates":[12.21759,46.139965],"type":"Point"}
}