{
  "type": "Feature",
  "properties": {
    "iso:country":"IT",
    "sg:address":"64, Via Alfieri 20089 Rozzano",
    "sg:city":"Rozzano",
    "sg:classifiers":[
        {
            "category":"Utilities",
            "subcategory":"Telephone",
            "type":"Services"
        }
    ],
    "sg:phone":"+39 39028252829",
    "sg:postcode":"20089",
    "sg:province":"Milano",
    "sg:tags":[
        "telecommunication"
    ],
    "wof:name":"Clod Srl",
    "wof:placetype":"venue"
},
  "geometry": {"coordinates":[9.176515,45.377655],"type":"Point"}
}