{
  "type": "Feature",
  "properties": {
    "addr:full":"Via Dell'olmo 10 47822 Santarcangelo Di Romagna Santarcangelo di Romagna Rimini 47822",
    "addr:housenumber":"10",
    "addr:postcode":"47822;47822",
    "addr:street":"Via Dell'Olmo",
    "iso:country":"IT",
    "sg:address":"Via Dell'olmo 10 47822 Santarcangelo Di Romagna",
    "sg:city":"Santarcangelo di Romagna",
    "sg:classifiers":[
        {
            "category":"Manufacturing",
            "subcategory":"Motor Vehicles & Parts",
            "type":"Manufacturing & Wholesale Goods"
        }
    ],
    "sg:phone":"+39 0541 625157",
    "sg:postcode":"47822",
    "sg:province":"Rimini",
    "sg:tags":[
        "industry",
        "metallurgical",
        "vendor"
    ],
    "sg:website":"www.italpack.net",
    "wof:name":"Italpack Di Righetti & Pirini Snc",
    "wof:placetype":"venue"
},
  "geometry": {"coordinates":[12.470245,44.070213],"type":"Point"}
}