{
  "type": "Feature",
  "properties": {
    "addr:full":"25050 Provaglio D'iseo Brescia 25050",
    "addr:postcode":"25050;25050",
    "iso:country":"IT",
    "sg:address":"25050 Provaglio D'iseo",
    "sg:orig_category":"Legno E Semilavorati",
    "sg:phone":"+39 030 983118",
    "sg:postcode":"25050",
    "sg:province":"Brescia",
    "wof:name":"Venturini Angelo",
    "wof:placetype":"venue"
},
  "geometry": {"coordinates":[10.043188,45.635231],"type":"Point"}
}