{
  "type": "Feature",
  "properties": {
    "iso:country":"IT",
    "sg:address":"34, Via Coroi 37053 Cerea",
    "sg:city":"Cerea",
    "sg:classifiers":[
        {
            "category":"Home & Garden",
            "subcategory":"Home Furnishings",
            "type":"Retail Goods"
        }
    ],
    "sg:phone":"+39 39044280166",
    "sg:postcode":"37053",
    "sg:province":"Verona",
    "sg:tags":[
        "household"
    ],
    "wof:name":"La Verdiana Di Vedovello Gigliola",
    "wof:placetype":"venue"
},
  "geometry": {"coordinates":[11.1874704361,45.2002372742],"type":"Point"}
}