{
  "type": "Feature",
  "properties": {
    "addr:full":"80026 Casoria Casoria Napoli 80026",
    "addr:postcode":"80026;80026",
    "iso:country":"IT",
    "sg:address":"80026 Casoria",
    "sg:city":"Casoria",
    "sg:orig_category":"Imprese Di Costruzioni Civili Ed Industriali",
    "sg:phone":"+39 081 584 3150",
    "sg:postcode":"80026",
    "sg:province":"Napoli",
    "wof:name":"Co-metal Sas",
    "wof:placetype":"venue"
},
  "geometry": {"coordinates":[14.31998,40.90205],"type":"Point"}
}