{
  "type": "Feature",
  "properties": {
    "addr:full":"63018 Porto Sant'elpidio Ascoli Piceno 63018",
    "addr:housenumber":"63018",
    "addr:postcode":"63018",
    "iso:country":"IT",
    "sg:address":"63018 Porto Sant'elpidio",
    "sg:orig_category":"Servizi E Lavori Per Abbigliamento E Pelletterie. Cartotecnica E Servizi. Servizi E Lavori Industria Delle Materie Plastiche",
    "sg:phone":"+39 0734 903691",
    "sg:postcode":"63018",
    "sg:province":"Ascoli Piceno",
    "wof:name":"Euro Accoppiatura Di Malavolta Renato",
    "wof:placetype":"venue"
},
  "geometry": {"coordinates":[13.7462949753,43.2501716614],"type":"Point"}
}