{
  "type": "Feature",
  "properties": {
    "iso:country":"IT",
    "sg:address":"40050 Monte San Pietro",
    "sg:city":"Monte San Pietro",
    "sg:orig_category":"Prodotti Vari In Metallo",
    "sg:phone":"+39 051 969295",
    "sg:postcode":"40050",
    "sg:province":"Bologna",
    "wof:name":"Cavor S.n.c Di Cavara Gaetano & C",
    "wof:placetype":"venue"
},
  "geometry": {"coordinates":[11.1315069199,44.4379768372],"type":"Point"}
}