{
  "type": "Feature",
  "properties": {
    "iso:country":"IT",
    "sg:address":"44022 Comacchio",
    "sg:city":"Comacchio",
    "sg:orig_category":"Climatizzazione E Condizionamento, Apparecchiature E Servizi. Accessori Dei Mezzi Di Trasporto",
    "sg:phone":"+39 0533 380150",
    "sg:postcode":"44022",
    "sg:province":"Ferrara",
    "wof:name":"Ferroni Car Sas",
    "wof:placetype":"venue"
},
  "geometry": {"coordinates":[12.179547,44.665981],"type":"Point"}
}