{
  "type": "Feature",
  "properties": {
    "iso:country":"IT",
    "sg:address":"52100 Arezzo",
    "sg:city":"Arezzo",
    "sg:orig_category":"Macchine E Forniture Per Industria Orafa E Per Orologeria",
    "sg:phone":"+39 0575 355024",
    "sg:postcode":"52100",
    "sg:province":"Arezzo",
    "wof:name":"Self Fioa Srl",
    "wof:placetype":"venue"
},
  "geometry": {"coordinates":[11.871274,43.470314],"type":"Point"}
}