{
  "type": "Feature",
  "properties": {
    "addr:full":"37015 Domegliara Domegliara Verona 37015",
    "addr:postcode":"37015;37015",
    "addr:street":"Domegliara",
    "iso:country":"IT",
    "sg:address":"37015 Domegliara",
    "sg:city":"Domegliara",
    "sg:orig_category":"Tessuti E Stoffe. Forniture Per Attivita' Industriali",
    "sg:phone":"+39 045 688 7231",
    "sg:postcode":"37015",
    "sg:province":"Verona",
    "wof:name":"Max Filter S.r.l.",
    "wof:placetype":"venue"
},
  "geometry": {"coordinates":[11.034027,45.373238],"type":"Point"}
}