{
  "type": "Feature",
  "properties": {
    "iso:country":"IT",
    "sg:address":"62010 Treia",
    "sg:city":"Treia",
    "sg:orig_category":"Motori Ed Organi Di Trasmissione",
    "sg:phone":"+39 0733 561147",
    "sg:postcode":"62010",
    "sg:province":"Macerata",
    "wof:name":"Micozzi Ivano & C. Snc",
    "wof:placetype":"venue"
},
  "geometry": {"coordinates":[13.3125181198,43.3115730286],"type":"Point"}
}