{
  "type": "Feature",
  "properties": {
    "iso:country":"IT",
    "sg:address":"47/49, Via La Valle 22066 Mariano Comense",
    "sg:city":"Mariano Comense",
    "sg:classifiers":[
        {
            "category":"Professional",
            "subcategory":"Engineering",
            "type":"Services"
        }
    ],
    "sg:phone":"+39 39031744752",
    "sg:postcode":"22066",
    "sg:province":"Como",
    "sg:tags":[
        "machine",
        "-",
        "mechanical"
    ],
    "wof:name":"Marval Srl",
    "wof:placetype":"venue"
},
  "geometry": {"coordinates":[9.164865,45.715385],"type":"Point"}
}