{
  "type": "Feature",
  "properties": {
    "iso:country":"IT",
    "sg:address":"20089 Quinto De'stampi",
    "sg:orig_category":"Forniture Per Abbigliamento E Pelletterie. Complementi Di Arredamento",
    "sg:phone":"+39 02 8920 1882",
    "sg:postcode":"20089",
    "sg:province":"Milano",
    "wof:name":"Passamaneria Di Venegoni E Figlio (s.n.c.)",
    "wof:placetype":"venue"
},
  "geometry": {"coordinates":[9.1643733978,45.3928184509],"type":"Point"}
}