{
  "type": "Feature",
  "properties": {
    "iso:country":"IT",
    "sg:address":"21020 Inarzo",
    "sg:city":"Inarzo",
    "sg:orig_category":"Fiori E Piante - Vendita Al Dettaglio",
    "sg:phone":"+39 0332 964250",
    "sg:postcode":"21020",
    "sg:province":"Varese",
    "wof:name":"Vanetti Pietro Eredi Di Vanetti Tommaso Sas",
    "wof:placetype":"venue"
},
  "geometry": {"coordinates":[8.7365312576,45.7850074768],"type":"Point"}
}