{
  "type": "Feature",
  "properties": {
    "iso:country":"IT",
    "sg:address":"4, Via Avigliana 10057 Sant'ambrogio Di Torino",
    "sg:classifiers":[
        {
            "category":"Wholesale",
            "subcategory":"Machinery & Supplies",
            "type":"Manufacturing & Wholesale Goods"
        }
    ],
    "sg:phone":"+39 011 932 4211",
    "sg:postcode":"10057",
    "sg:province":"Torino",
    "sg:tags":[
        "equipment",
        "-",
        "instrument",
        "measurement"
    ],
    "wof:name":"Portedi S.r.l.",
    "wof:placetype":"venue"
},
  "geometry": {"coordinates":[7.370414,45.103703],"type":"Point"}
}