{
  "type": "Feature",
  "properties": {
    "addr:full":"27, Via Dell' Industria 40043 Marzabotto Marzabotto Bologna 40043",
    "addr:postcode":"40043;40043",
    "addr:street":"Via Dell ' Industria",
    "iso:country":"IT",
    "sg:address":"27, Via Dell' Industria 40043 Marzabotto",
    "sg:city":"Marzabotto",
    "sg:classifiers":[
        {
            "category":"Manufacturing",
            "subcategory":"Rubber & Plastics",
            "type":"Manufacturing & Wholesale Goods"
        }
    ],
    "sg:phone":"+39 39051932323",
    "sg:postcode":"40043",
    "sg:province":"Bologna",
    "wof:name":"P M C Di Castilletti Mario",
    "wof:placetype":"venue"
},
  "geometry": {"coordinates":[11.2066726685,44.3490142822],"type":"Point"}
}