{
  "type": "Feature",
  "properties": {
    "addr:full":"43100 San Pancrazio Parma 43100",
    "addr:housenumber":"43100",
    "addr:postcode":"43100",
    "addr:street":"San",
    "iso:country":"IT",
    "sg:address":"43100 San Pancrazio",
    "sg:orig_category":"Elettrotecnica Professionale E Di Consumo. Forniture Alle Strutture Ricettive. Arredi Ed Attrezzature Per Attivita' Commerciali Ed Artigianali",
    "sg:phone":"+39 0521 671226",
    "sg:postcode":"43100",
    "sg:province":"Parma",
    "wof:name":"G.s.g. (s.n.c.)",
    "wof:placetype":"venue"
},
  "geometry": {"coordinates":[10.271933,44.815125],"type":"Point"}
}