{
  "type": "Feature",
  "properties": {
    "addr:full":"Via Giovanni Xxiii 2 40057 Quarto Inferiore Quarto Inferiore Bologna 40057",
    "addr:housenumber":"2",
    "addr:postcode":"40057;40057",
    "addr:street":"Via Giovanni Xxiii;Inferiore;Inferiore",
    "iso:country":"IT",
    "sg:address":"Via Giovanni Xxiii 2 40057 Quarto Inferiore",
    "sg:city":"Quarto Inferiore",
    "sg:orig_category":"Blind Rivets, Air And Water-tight",
    "sg:phone":"+39 051 767131",
    "sg:postcode":"40057",
    "sg:province":"Bologna",
    "sg:website":"www.far.bo.it",
    "wof:name":"Far Srl",
    "wof:placetype":"venue"
},
  "geometry": {"coordinates":[11.410947,44.533253],"type":"Point"}
}