{
  "type": "Feature",
  "properties": {
    "iso:country":"IT",
    "sg:address":"6, Via Marcheselli 29100 Piacenza",
    "sg:city":"Piacenza",
    "sg:classifiers":[
        {
            "category":"Shopping",
            "type":"Retail Goods"
        }
    ],
    "sg:phone":"+39 0523 593056",
    "sg:postcode":"29100",
    "sg:province":"Piacenza",
    "sg:tags":[
        "finished",
        "-",
        "metallic"
    ],
    "wof:name":"Cima Spa",
    "wof:placetype":"venue"
},
  "geometry": {"coordinates":[9.7282104492,45.0454940796],"type":"Point"}
}