{
  "type": "Feature",
  "properties": {
    "iso:country":"IT",
    "sg:address":"90039 Villabate",
    "sg:city":"Villabate",
    "sg:orig_category":"Macchine, Impianti Ed Attrezzature Industria Chimica. Macchine E Impianti Per Attivita' Commerciali Ed Artigianali",
    "sg:phone":"+39 091 491332",
    "sg:postcode":"90039",
    "sg:province":"Palermo",
    "wof:name":"Car Service Di Pelicane Antonio & Sas",
    "wof:placetype":"venue"
},
  "geometry": {"coordinates":[13.469506,38.088684],"type":"Point"}
}