{
  "type": "Feature",
  "properties": {
    "iso:country":"IT",
    "sg:address":"47037 Rimini",
    "sg:orig_category":"Arredo Cucina Ed Elettrodomestici. Elettrodomestici",
    "sg:phone":"+39 0541 783201",
    "sg:province":"RN",
    "wof:name":"Termoidraulica T & T Di Tonini Snc",
    "wof:placetype":"venue"
},
  "geometry": {"coordinates":[-85.334297,39.165173],"type":"Point"}
}