{
  "type": "Feature",
  "properties": {
    "iso:country":"IT",
    "sg:address":"41015 Nonantola",
    "sg:city":"Nonantola",
    "sg:orig_category":"Carpenterie Meccaniche",
    "sg:phone":"+39 059 545146",
    "sg:postcode":"41015",
    "sg:province":"Modena",
    "wof:name":"Erre-pi Di Piccinini & C. Sas",
    "wof:placetype":"venue"
},
  "geometry": {"coordinates":[11.015257,44.67717],"type":"Point"}
}