{
  "type": "Feature",
  "properties": {
    "iso:country":"IT",
    "sg:address":"95125 Catania",
    "sg:city":"Catania",
    "sg:orig_category":"Agricoltura, Orticoltura E Floricoltura. Articoli Da Regalo",
    "sg:phone":"+39 095 503158",
    "sg:postcode":"95125",
    "sg:province":"Catania",
    "wof:name":"Piccione Daniele",
    "wof:placetype":"venue"
},
  "geometry": {"coordinates":[15.08134,37.522202],"type":"Point"}
}