{
  "type": "Feature",
  "properties": {
    "addr:full":"06023 Gualdo Tadino Gualdo Tadino Perugia 06023",
    "addr:postcode":"06023;06023",
    "iso:country":"IT",
    "sg:address":"06023 Gualdo Tadino",
    "sg:city":"Gualdo Tadino",
    "sg:orig_category":"Imballaggi In Plastica",
    "sg:phone":"+39 075 915170",
    "sg:postcode":"06023",
    "sg:province":"Perugia",
    "wof:name":"Duniapack Di Gramaccia Massimo",
    "wof:placetype":"venue"
},
  "geometry": {"coordinates":[12.787458,43.229408],"type":"Point"}
}