{
  "type": "Feature",
  "properties": {
    "iso:country":"IT",
    "sg:address":"00144 Roma",
    "sg:city":"Roma",
    "sg:orig_category":"Macchine, Impianti E Forniture Per Industria Grafica, Cartaria E Cartotecnica. Forniture Per Uffici",
    "sg:phone":"+39 06 520 1753",
    "sg:postcode":"00144",
    "sg:province":"Roma",
    "wof:name":"Cam Grafic Srl",
    "wof:placetype":"venue"
},
  "geometry": {"coordinates":[12.443913,41.820667],"type":"Point"}
}