{
  "type": "Feature",
  "properties": {
    "iso:country":"IT",
    "sg:address":"30, Viale S. Maria 25013 Carpenedolo",
    "sg:city":"Carpenedolo",
    "sg:classifiers":[
        {
            "category":"Autos & Motor Vehicles",
            "subcategory":"Automobile Sales",
            "type":"Retail Goods"
        }
    ],
    "sg:phone":"+39 39030969110",
    "sg:postcode":"25013",
    "sg:province":"Brescia",
    "sg:tags":[
        "industrial"
    ],
    "wof:name":"Baroni Ribaltabili (s.n.c.)",
    "wof:placetype":"venue"
},
  "geometry": {"coordinates":[10.222958,45.539829],"type":"Point"}
}