{
  "type": "Feature",
  "properties": {
    "iso:country":"IT",
    "sg:address":"25032 Chiari",
    "sg:city":"Chiari",
    "sg:orig_category":"Apparecchiature E Sistemi Per Magazzinaggio E Movimentazione",
    "sg:phone":"+39 030 712534",
    "sg:postcode":"25032",
    "sg:province":"Brescia",
    "wof:name":"Officina Meccanica Di Loda Giovanni",
    "wof:placetype":"venue"
},
  "geometry": {"coordinates":[9.925162,45.538723],"type":"Point"}
}