{
  "type": "Feature",
  "properties": {
    "iso:country":"IT",
    "sg:address":"90141 Palermo",
    "sg:city":"Palermo",
    "sg:orig_category":"Riparazione Dei Mezzi Di Trasporto. Servizi Ausiliari Dei Mezzi Di Trasporto",
    "sg:phone":"+39 091 334032",
    "sg:postcode":"90141",
    "sg:province":"Palermo",
    "wof:name":"Battistiol Antonio E Mario - Pa.ga.",
    "wof:placetype":"venue"
},
  "geometry": {"coordinates":[13.348621,38.127865],"type":"Point"}
}