{
  "type": "Feature",
  "properties": {
    "iso:country":"IT",
    "sg:address":"42013 Casalgrande",
    "sg:orig_category":"Lavorazioni Metalli, Stampaggio E Saldatura",
    "sg:phone":"+39 0522 999125",
    "sg:postcode":"42013",
    "sg:province":"Reggio Nell'Emilia",
    "wof:name":"Cober (s.n.c.)",
    "wof:placetype":"venue"
},
  "geometry": {"coordinates":[10.627794,44.696228],"type":"Point"}
}