{
  "type": "Feature",
  "properties": {
    "addr:full":"24, V. Repubblica Di S. Marino 41100 Modena Modena Modena 41100",
    "addr:housenumber":"24",
    "addr:postcode":"41100;41100",
    "addr:street":"V. Repubblica Di S. Marino",
    "iso:country":"IT",
    "sg:address":"24, V. Repubblica Di S. Marino 41100 Modena",
    "sg:city":"Modena",
    "sg:classifiers":[
        {
            "category":"Wholesale",
            "subcategory":"Machinery & Supplies",
            "type":"Manufacturing & Wholesale Goods"
        }
    ],
    "sg:phone":"+39 39059315852",
    "sg:postcode":"41100",
    "sg:province":"Modena",
    "sg:tags":[
        "-",
        "agriculture",
        "equipment"
    ],
    "sg:website":"http://www.paginegialle.it/malavoltac",
    "wof:name":"Malavolta Carlo",
    "wof:placetype":"venue"
},
  "geometry": {"coordinates":[10.936644,44.677032],"type":"Point"}
}