{
  "type": "Feature",
  "properties": {
    "addr:full":"Via Appia Km 55,900 04012 Cisterna Di Latina Cisterna di Latina Latina 04012",
    "addr:housenumber":"55,900",
    "addr:postcode":"04012;04012",
    "addr:street":"Via Appia Km",
    "iso:country":"IT",
    "sg:address":"Via Appia Km 55,900 04012 Cisterna Di Latina",
    "sg:city":"Cisterna di Latina",
    "sg:classifiers":[
        {
            "category":"Wholesale",
            "subcategory":"Plants",
            "type":"Manufacturing & Wholesale Goods"
        }
    ],
    "sg:phone":"+39 06 969 4369",
    "sg:postcode":"04012",
    "sg:province":"Latina",
    "sg:tags":[
        "calculation",
        "planning",
        "industrial"
    ],
    "sg:website":"www.cemispa.it",
    "wof:name":"C.e.m.i. Costruzioni E Montaggi Industriali Spa",
    "wof:placetype":"venue"
},
  "geometry": {"coordinates":[12.909444809,41.543056488],"type":"Point"}
}