{
  "type": "Feature",
  "properties": {
    "iso:country":"IT",
    "sg:address":"59100 Prato",
    "sg:city":"Prato",
    "sg:orig_category":"Servizi E Lavori Per Abbigliamento E Pelletterie",
    "sg:phone":"+39 0574 650347",
    "sg:postcode":"59100",
    "sg:province":"Prato",
    "wof:name":"Magni Rosalba",
    "wof:placetype":"venue"
},
  "geometry": {"coordinates":[11.0821,43.903366],"type":"Point"}
}