{
  "type": "Feature",
  "properties": {
    "iso:country":"IT",
    "sg:address":"8/1, V. Nievo 40069 Zola Predosa",
    "sg:city":"Zola",
    "sg:classifiers":[
        {
            "category":"Real Estate",
            "subcategory":"Surveying",
            "type":"Services"
        }
    ],
    "sg:phone":"+39 39051755406",
    "sg:postcode":"40069",
    "sg:province":"Bologna",
    "sg:tags":[
        "equipment",
        "material",
        "good",
        "-",
        "handling"
    ],
    "sg:website":"http://www.paginegialle.it/dugomrulli",
    "wof:name":"Dugomrulli Srl",
    "wof:placetype":"venue"
},
  "geometry": {"coordinates":[11.237821,44.486069],"type":"Point"}
}