{
  "type": "Feature",
  "properties": {
    "iso:country":"IT",
    "sg:address":"Via Milano 94 21019 Somma Lombardo",
    "sg:city":"Somma Lombardo",
    "sg:classifiers":[
        {
            "category":"Professional",
            "subcategory":"Printing & Photocopies",
            "type":"Services"
        }
    ],
    "sg:phone":"+39 0331 251610",
    "sg:postcode":"21019",
    "sg:province":"Varese",
    "sg:tags":[
        "embroidery"
    ],
    "wof:name":"Ricamificio M6 Srl",
    "wof:placetype":"venue"
},
  "geometry": {"coordinates":[8.713779,45.681919],"type":"Point"}
}