{
  "type": "Feature",
  "properties": {
    "addr:full":"61034 Fossombrone Fossombrone Pesaro E Urbino 61034",
    "addr:postcode":"61034;61034",
    "iso:country":"IT",
    "sg:address":"61034 Fossombrone",
    "sg:city":"Fossombrone",
    "sg:orig_category":"Macchine Utensili E Impianti. Elettrotecnica Industriale, Prodotti E Apparecchiature",
    "sg:phone":"+39 0721 714071",
    "sg:postcode":"61034",
    "sg:province":"Pesaro E Urbino",
    "wof:name":"Storoni Tecnologie Di Storoni Gian Paolo",
    "wof:placetype":"venue"
},
  "geometry": {"coordinates":[12.821878,43.694283],"type":"Point"}
}