{
  "type": "Feature",
  "properties": {
    "iso:country":"IT",
    "sg:address":"Via Edison 6, 60027 Osimo, An",
    "sg:city":"Osimo",
    "sg:classifiers":[
        {
            "category":"Banks & Credit Unions",
            "subcategory":"Bank",
            "type":"Services"
        }
    ],
    "sg:postcode":"60027",
    "sg:province":"Ancona",
    "wof:name":"Marche Capital Spa",
    "wof:placetype":"venue"
},
  "geometry": {"coordinates":[13.513835,43.530384],"type":"Point"}
}