{
  "type": "Feature",
  "properties": {
    "iso:country":"IT",
    "sg:address":"Fondamenta Dei Vetrai 138 30141 Venezia",
    "sg:city":"Venezia",
    "sg:classifiers":[
        {
            "category":"Manufacturing",
            "subcategory":"Glass & Minerals",
            "type":"Manufacturing & Wholesale Goods"
        }
    ],
    "sg:phone":"+39 041 739285",
    "sg:postcode":"30141",
    "sg:province":"Venezia",
    "sg:tags":[
        "decorative",
        "artistic"
    ],
    "sg:website":"www.formiaglass.it",
    "wof:name":"Formia Srl",
    "wof:placetype":"venue"
},
  "geometry": {"coordinates":[12.35133,45.453133],"type":"Point"}
}