{
  "type": "Feature",
  "properties": {
    "iso:country":"IT",
    "sg:address":"31044 Montebelluna",
    "sg:city":"Montebelluna",
    "sg:orig_category":"Servizi Ausiliari Di Analisi, Controllo E Ricerca",
    "sg:phone":"+39 0423 288311",
    "sg:postcode":"31044",
    "sg:province":"Treviso",
    "wof:name":"Enel Distribuzione",
    "wof:placetype":"venue"
},
  "geometry": {"coordinates":[12.048293,45.757065],"type":"Point"}
}