{
  "type": "Feature",
  "properties": {
    "iso:country":"IT",
    "sg:address":"07026 Olbia",
    "sg:city":"Olbia",
    "sg:orig_category":"Carta Da Parati - Vendita Al Dettaglio",
    "sg:phone":"+39 0789 21116",
    "sg:postcode":"07026",
    "sg:province":"Olbia-Tempio",
    "wof:name":"Colmegna Enrico",
    "wof:placetype":"venue"
},
  "geometry": {"coordinates":[9.278559,40.826839],"type":"Point"}
}