{
  "type": "Feature",
  "properties": {
    "iso:country":"IT",
    "sg:address":"00161 Roma",
    "sg:city":"Roma",
    "sg:orig_category":"Articoli Da Regalo. Regalistica Aziendale",
    "sg:phone":"+39 06 445 6392",
    "sg:postcode":"00161",
    "sg:province":"Roma",
    "wof:name":"Marchetti Tullio",
    "wof:placetype":"venue"
},
  "geometry": {"coordinates":[12.516398,41.907978],"type":"Point"}
}