{
  "type": "Feature",
  "properties": {
    "iso:country":"IT",
    "sg:address":"70010 Valenzano",
    "sg:city":"Valenzano",
    "sg:orig_category":"Distributors: Automatici - Commercio E Gestione",
    "sg:phone":"+39 080 467 3007",
    "sg:postcode":"70010",
    "sg:province":"Bari",
    "wof:name":"D & D Srl",
    "wof:placetype":"venue"
},
  "geometry": {"coordinates":[16.882763,41.047237],"type":"Point"}
}