{
  "type": "Feature",
  "properties": {
    "addr:full":"Via Roma Sinistra 74 30016 Jesolo Venezia 30016",
    "addr:housenumber":"74",
    "addr:postcode":"30016;30016",
    "addr:street":"Via Roma Sinistra",
    "iso:country":"IT",
    "sg:address":"Via Roma Sinistra 74 30016 Jesolo",
    "sg:classifiers":[
        {
            "category":"Ice Cream",
            "type":"Food & Drink"
        }
    ],
    "sg:phone":"+39 0421 951048",
    "sg:postcode":"30016",
    "sg:province":"Venezia",
    "sg:tags":[
        "ice-cream"
    ],
    "sg:website":"www.adriagel.it",
    "wof:name":"Adriagel S.r.l.",
    "wof:placetype":"venue"
},
  "geometry": {"coordinates":[12.654204,45.547581],"type":"Point"}
}