{
  "type": "Feature",
  "properties": {
    "iso:country":"IT",
    "sg:address":"20154 Milano",
    "sg:city":"Milano",
    "sg:orig_category":"Lavorazioni Metalli, Stampaggio E Saldatura",
    "sg:phone":"+39 02 657 0218",
    "sg:postcode":"20154",
    "sg:province":"Milano",
    "wof:name":"Tartaglia Antonio",
    "wof:placetype":"venue"
},
  "geometry": {"coordinates":[9.183212,45.483074],"type":"Point"}
}