{
  "type": "Feature",
  "properties": {
    "addr:full":"40133 Bologna Bologna Bologna 40133",
    "addr:postcode":"40133;40133",
    "iso:country":"IT",
    "sg:address":"40133 Bologna",
    "sg:city":"Bologna",
    "sg:orig_category":"Ristoranti",
    "sg:phone":"+39 051 614 6874",
    "sg:postcode":"40133",
    "sg:province":"Bologna",
    "sg:website":"http://www.paginegialle.it/alghisello",
    "wof:name":"Al Ghisello Insieme Sas",
    "wof:placetype":"venue"
},
  "geometry": {"coordinates":[11.299614,44.491825],"type":"Point"}
}