{
  "type": "Feature",
  "properties": {
    "iso:country":"IT",
    "sg:address":"20091 Bresso",
    "sg:city":"Bresso",
    "sg:orig_category":"Macchine, Impianti Ed Attrezzature Industria Chimica",
    "sg:phone":"+39 02 610 0842",
    "sg:postcode":"20091",
    "sg:province":"Milano",
    "wof:name":"Viani S.n.c. Di Viani Emilio Antonio Mario & C.",
    "wof:placetype":"venue"
},
  "geometry": {"coordinates":[9.192549,45.543888],"type":"Point"}
}