{
  "type": "Feature",
  "properties": {
    "addr:full":"1, Via Dosa 30030 Martellago Martellago Venezia 30030",
    "addr:postcode":"30030;30030",
    "addr:street":"Via Dosa",
    "iso:country":"IT",
    "sg:address":"1, Via Dosa 30030 Martellago",
    "sg:city":"Martellago",
    "sg:classifiers":[
        {
            "category":"Communications",
            "subcategory":"Television Station",
            "type":"Services"
        }
    ],
    "sg:phone":"+39 39041909114",
    "sg:postcode":"30030",
    "sg:province":"Venezia",
    "sg:tags":[
        "equipment",
        "optical",
        "instrument"
    ],
    "wof:name":"Systel International (s.p.a.)",
    "wof:placetype":"venue"
},
  "geometry": {"coordinates":[12.192823,45.51606],"type":"Point"}
}