{
  "type": "Feature",
  "properties": {
    "iso:country":"IT",
    "sg:address":"Via Pavese 1 10060 San Pietro Val Lemina",
    "sg:city":"San Pietro Val Lemina",
    "sg:orig_category":"Ladies' Knitwear",
    "sg:phone":"+39 0121 543112",
    "sg:postcode":"10060",
    "sg:province":"Torino",
    "wof:name":"Magic Di Bergamaschi & C. Snc",
    "wof:placetype":"venue"
},
  "geometry": {"coordinates":[7.312568,44.906376],"type":"Point"}
}