{
  "type": "Feature",
  "properties": {
    "iso:country":"IT",
    "sg:address":"33048 San Giovanni Al Natisone",
    "sg:city":"Dolegnano",
    "sg:classifiers":[
        {
            "category":"Manufacturing",
            "subcategory":"Building Materials",
            "type":"Manufacturing & Wholesale Goods"
        }
    ],
    "sg:phone":"+39 0432 756454",
    "sg:postcode":"33048",
    "sg:province":"Udine",
    "sg:tags":[
        "semi-finished",
        "wood",
        "products"
    ],
    "wof:name":"Bucovaz Aldo & C. Snc",
    "wof:placetype":"venue"
},
  "geometry": {"coordinates":[13.400945,45.974854],"type":"Point"}
}