{
  "type": "Feature",
  "properties": {
    "iso:country":"IT",
    "sg:address":"00147 Roma",
    "sg:city":"Roma",
    "sg:orig_category":"Agricoltura, Orticoltura E Floricoltura",
    "sg:phone":"+39 06 510 7021",
    "sg:postcode":"00147",
    "sg:province":"Roma",
    "wof:name":"Ente Tabacchi Italiani",
    "wof:placetype":"venue"
},
  "geometry": {"coordinates":[12.496289,41.86565],"type":"Point"}
}