{
  "type": "Feature",
  "properties": {
    "iso:country":"IT",
    "sg:address":"34170 Gorizia",
    "sg:city":"Gorizia",
    "sg:orig_category":"Materiali E Componenti Elettrotecnici",
    "sg:phone":"+39 0481 522012",
    "sg:postcode":"34170",
    "sg:province":"Gorizia",
    "wof:name":"Coveme S.p.a.",
    "wof:placetype":"venue"
},
  "geometry": {"coordinates":[13.596686,45.916744],"type":"Point"}
}