{
  "type": "Feature",
  "properties": {
    "addr:full":"84021 Buccino Buccino Salerno 84021",
    "addr:postcode":"84021;84021",
    "iso:country":"IT",
    "sg:address":"84021 Buccino",
    "sg:city":"Buccino",
    "sg:orig_category":"Petroli, Gas E Combustibili",
    "sg:phone":"+39 0828 958005",
    "sg:postcode":"84021",
    "sg:province":"Salerno",
    "wof:name":"S.i.pr.i.o. Spa",
    "wof:placetype":"venue"
},
  "geometry": {"coordinates":[15.3716688156,40.6368408203],"type":"Point"}
}