{
  "type": "Feature",
  "properties": {
    "iso:country":"IT",
    "sg:address":"16128 Genova",
    "sg:city":"Genova",
    "sg:orig_category":"Adesivi",
    "sg:phone":"+39 010 275 8027",
    "sg:postcode":"16128",
    "sg:province":"Genova",
    "sg:website":"http://www.letterfix.com",
    "wof:name":"International Letterfix Srl",
    "wof:placetype":"venue"
},
  "geometry": {"coordinates":[8.929332,44.400768],"type":"Point"}
}