{
  "type": "Feature",
  "properties": {
    "iso:country":"IT",
    "sg:address":"84132 Salerno",
    "sg:city":"Salerno",
    "sg:orig_category":"Motori Ed Organi Di Trasmissione",
    "sg:phone":"+39 089 522 3260",
    "sg:postcode":"84132",
    "sg:province":"Salerno",
    "wof:name":"Ditta Elettronic Cisa Snc",
    "wof:placetype":"venue"
},
  "geometry": {"coordinates":[14.8026647568,40.6644210815],"type":"Point"}
}