{
  "type": "Feature",
  "properties": {
    "iso:country":"IT",
    "sg:address":"50050 Cerreto Guidi",
    "sg:city":"Cerreto Guidi",
    "sg:orig_category":"Attrezzature E Forniture Per Officine Riparazione E Servizi Ausiliari",
    "sg:phone":"+39 0571 509256",
    "sg:postcode":"50050",
    "sg:province":"Firenze",
    "wof:name":"Autocarrozzeria Dps",
    "wof:placetype":"venue"
},
  "geometry": {"coordinates":[10.880166,43.759827],"type":"Point"}
}