{
  "type": "Feature",
  "properties": {
    "iso:country":"IT",
    "sg:address":"50056 Capraia E Limite",
    "sg:orig_category":"Barche, Canotti Pneumatici E Motoscafi - Vendita Al Dettaglio",
    "sg:phone":"+39 0571 57122",
    "sg:postcode":"50056",
    "sg:province":"Firenze",
    "wof:name":"Vetus Italia Srl",
    "wof:placetype":"venue"
},
  "geometry": {"coordinates":[11.256902,43.768734],"type":"Point"}
}