{
  "type": "Feature",
  "properties": {
    "addr:full":"Via Lanzone 6 20123 Milano Milano Milano 20123",
    "addr:housenumber":"6",
    "addr:postcode":"20123;20123",
    "addr:street":"Via Lanzone",
    "iso:country":"IT",
    "sg:address":"Via Lanzone 6 20123 Milano",
    "sg:city":"Milano",
    "sg:classifiers":[
        {
            "category":"Shopping",
            "subcategory":"Beauty & Cosmetics",
            "type":"Retail Goods"
        }
    ],
    "sg:phone":"+39 02 8901 0064",
    "sg:postcode":"20123",
    "sg:province":"Milano",
    "sg:tags":[
        "natural"
    ],
    "wof:name":"Laboratori Fitocosmesi E Farmaceutici Srl",
    "wof:placetype":"venue"
},
  "geometry": {"coordinates":[9.178128,45.460472],"type":"Point"}
}