{
  "type": "Feature",
  "properties": {
    "addr:full":"Via C. Battisti 15 23845 Costa Masnaga Costa Masnaga Lecco 23845",
    "addr:housenumber":"15",
    "addr:postcode":"23845;masnaga;23845",
    "addr:street":"Via C. Battisti",
    "iso:country":"IT",
    "sg:address":"Via C. Battisti 15 23845 Costa Masnaga",
    "sg:city":"Costa Masnaga",
    "sg:classifiers":[
        {
            "category":"Shopping",
            "subcategory":"Clothing, Apparel, & Fashions",
            "type":"Retail Goods"
        }
    ],
    "sg:phone":"+39 031 857111",
    "sg:postcode":"23845",
    "sg:province":"Lecco",
    "sg:tags":[
        "clothing",
        "fabric"
    ],
    "sg:website":"www.limonta.com",
    "wof:name":"Limonta Spa",
    "wof:placetype":"venue"
},
  "geometry": {"coordinates":[9.390071,45.852982],"type":"Point"}
}