{
  "type": "Feature",
  "properties": {
    "addr:full":"Km. 122.600, Via Appia Lato Itri 04022 Fondi Fondi Latina 04022",
    "addr:postcode":"04022;04022",
    "addr:street":"Km. 122.600 Via Appia Lato",
    "iso:country":"IT",
    "sg:address":"Km. 122.600, Via Appia Lato Itri 04022 Fondi",
    "sg:city":"Fondi",
    "sg:classifiers":[
        {
            "category":"Shopping",
            "subcategory":"Stationery & Office Supplies",
            "type":"Retail Goods"
        }
    ],
    "sg:phone":"+39 0771 510254",
    "sg:postcode":"04022",
    "sg:province":"Latina",
    "sg:tags":[
        "professional"
    ],
    "wof:name":"I.p.a. Srl",
    "wof:placetype":"venue"
},
  "geometry": {"coordinates":[12.9036998749,41.4675979614],"type":"Point"}
}