{
  "type": "Feature",
  "properties": {
    "addr:full":"6, V. E. Mattei Castelfidardo Ancona 60022",
    "addr:housenumber":"6",
    "addr:postcode":"60022",
    "addr:street":"V. E. Mattei Castelfidardo",
    "iso:country":"IT",
    "sg:address":"6, V. E. Mattei",
    "sg:city":"Castelfidardo",
    "sg:classifiers":[
        {
            "category":"Manufacturing",
            "subcategory":"Metals",
            "type":"Manufacturing & Wholesale Goods"
        }
    ],
    "sg:phone":"+39 071 782 2364",
    "sg:postcode":"60022",
    "sg:province":"Ancona",
    "sg:tags":[
        "processing"
    ],
    "sg:website":"http://www.sifersrl.com:ws_end: :mark:ws:http://www.paginegialle.it/sifersrl",
    "wof:name":"Sifer Srl",
    "wof:placetype":"venue"
},
  "geometry": {"coordinates":[13.5187568665,43.6158561707],"type":"Point"}
}