{
  "type": "Feature",
  "properties": {
    "addr:full":"Via Jussi 1; S. Lazzaro",
    "addr:housenumber":"1",
    "addr:street":"Via Jussi",
    "iso:country":"IT",
    "sg:address":"Via Jussi 1; S. Lazzaro",
    "sg:classifiers":[
        {
            "category":"Banks & Credit Unions",
            "subcategory":"Bank",
            "type":"Services"
        }
    ],
    "sg:phone":"+39 051 627 9211",
    "wof:name":"Cassa Di Risparmio In Bologna Spa",
    "wof:placetype":"venue"
},
  "geometry": {"coordinates":[11.41155,44.4688],"type":"Point"}
}