{
  "type": "Feature",
  "properties": {
    "addr:full":"Via Toscana, 107/109 61100 Pesaro Pesaro Pesaro E Urbino 61100",
    "addr:housenumber":"107 / 109",
    "addr:postcode":"61100;61100",
    "addr:street":"Via Toscana",
    "iso:country":"IT",
    "sg:address":"Via Toscana, 107/109 61100 Pesaro",
    "sg:city":"Pesaro",
    "sg:classifiers":[
        {
            "category":"Organizations",
            "subcategory":"Labor Organization",
            "type":"Services"
        }
    ],
    "sg:phone":"+39 0721 41881",
    "sg:postcode":"61100",
    "sg:province":"Pesaro E Urbino",
    "sg:tags":[
        "varnishing",
        "painting",
        "system"
    ],
    "sg:website":"www.monaldi.com",
    "wof:name":"Monaldi Spa",
    "wof:placetype":"venue"
},
  "geometry": {"coordinates":[12.8801259995,43.9043922424],"type":"Point"}
}