{
  "type": "Feature",
  "properties": {
    "addr:full":"Via Crispi 77 21100 Varese Varese Varese 21100",
    "addr:housenumber":"77",
    "addr:postcode":"21100;21100",
    "addr:street":"Via Crispi",
    "iso:country":"IT",
    "sg:address":"Via Crispi 77 21100 Varese",
    "sg:city":"Varese",
    "sg:classifiers":[
        {
            "category":"Shopping",
            "subcategory":"Books",
            "type":"Retail Goods"
        }
    ],
    "sg:phone":"+39 0332 224690",
    "sg:postcode":"21100",
    "sg:province":"Varese",
    "sg:tags":[
        "young",
        "people's"
    ],
    "sg:website":"www.coccinella.com",
    "wof:name":"La Coccinella Srl",
    "wof:placetype":"venue"
},
  "geometry": {"coordinates":[8.826385,45.817604],"type":"Point"}
}