{
  "type": "Feature",
  "properties": {
    "iso:country":"IT",
    "sg:address":"71/a, 00187 Rome, Rm",
    "sg:classifiers":[
        {
            "category":"Banks & Credit Unions",
            "subcategory":"Bank",
            "type":"Services"
        }
    ],
    "sg:postcode":"00187",
    "sg:province":"Roma",
    "wof:name":"Immocri Spa",
    "wof:placetype":"venue"
},
  "geometry": {"coordinates":[12.514937,41.881882],"type":"Point"}
}