{
  "type": "Feature",
  "properties": {
    "iso:country":"IT",
    "sg:address":"83100 Avellino",
    "sg:city":"Avellino",
    "sg:orig_category":"Servizi E Lavori Per Agricoltura E Zootecnia. Servizi Ausiliari Di Analisi, Controllo E Ricerca",
    "sg:phone":"+39 0825 786419",
    "sg:postcode":"83100",
    "sg:province":"Avellino",
    "wof:name":"C.n.r. Ist. Di Scienze Alimentari",
    "wof:placetype":"venue"
},
  "geometry": {"coordinates":[14.777557,40.911297],"type":"Point"}
}