{
  "type": "Feature",
  "properties": {
    "addr:full":"00045 Genzano Di Roma Genzano di Roma Roma 00045",
    "addr:postcode":"00045;00045",
    "iso:country":"IT",
    "sg:address":"00045 Genzano Di Roma",
    "sg:city":"Genzano di Roma",
    "sg:orig_category":"Abbigliamento Intimo, Calze E Costumi Da Bagno. Sport - Articoli E Forniture. Shopping",
    "sg:phone":"+39 06 936 4390",
    "sg:postcode":"00045",
    "sg:province":"Roma",
    "wof:name":"Calze Intimo Mare - Pantys",
    "wof:placetype":"venue"
},
  "geometry": {"coordinates":[12.650665,41.749958],"type":"Point"}
}