{
  "type": "Feature",
  "properties": {
    "addr:full":"Via Scisciana 21052 Busto Arsizio Busto Arsizio Varese 21052",
    "addr:postcode":"21052;21052",
    "addr:street":"Via Scisciana",
    "iso:country":"IT",
    "sg:address":"Via Scisciana 21052 Busto Arsizio",
    "sg:city":"Busto Arsizio",
    "sg:classifiers":[
        {
            "category":"Shopping",
            "subcategory":"Clothing, Apparel, & Fashions",
            "type":"Retail Goods"
        }
    ],
    "sg:phone":"+39 0331 639441",
    "sg:postcode":"21052",
    "sg:province":"Varese",
    "sg:tags":[
        "clothes"
    ],
    "wof:name":"C.r.e. Calzifici Riuniti Elli (s.r.l.)",
    "wof:placetype":"venue"
},
  "geometry": {"coordinates":[8.859253,45.621613],"type":"Point"}
}