{
  "type": "Feature",
  "properties": {
    "iso:country":"IT",
    "sg:address":"Via Europa 17 25050 Passirano",
    "sg:city":"Passirano",
    "sg:classifiers":[
        {
            "category":"Manufacturing",
            "subcategory":"Metals",
            "type":"Manufacturing & Wholesale Goods"
        }
    ],
    "sg:phone":"+39 030 685 6500",
    "sg:postcode":"25050",
    "sg:province":"Brescia",
    "sg:tags":[
        "die",
        "aluminium",
        "casting"
    ],
    "sg:website":"www.donatigruppo.it",
    "wof:name":"Metalpres Donati Spa",
    "wof:placetype":"venue"
},
  "geometry": {"coordinates":[10.047607,45.569458],"type":"Point"}
}