{
  "type": "Feature",
  "properties": {
    "iso:country":"IT",
    "sg:address":"20090 Buccinasco",
    "sg:city":"Buccinasco",
    "sg:orig_category":"Macchine, Impianti Ed Attrezzature Industria Delle Materie Plastiche E Gomma",
    "sg:phone":"+39 02 440 0063",
    "sg:postcode":"20090",
    "sg:province":"Milano",
    "wof:name":"Blow Up Plastic Snc",
    "wof:placetype":"venue"
},
  "geometry": {"coordinates":[9.121167,45.435696],"type":"Point"}
}