{
  "type": "Feature",
  "properties": {
    "addr:full":"00151 Roma Roma Roma 00151",
    "addr:postcode":"00151;00151",
    "iso:country":"IT",
    "sg:address":"00151 Roma",
    "sg:city":"Roma",
    "sg:orig_category":"Macchine E Forniture Per Ecologia E Smaltimento Rifiuti",
    "sg:phone":"+39 06 582 7106",
    "sg:postcode":"00151",
    "sg:province":"Roma",
    "wof:name":"Ecotecna Srl",
    "wof:placetype":"venue"
},
  "geometry": {"coordinates":[12.445756,41.869682],"type":"Point"}
}