{
  "type": "Feature",
  "properties": {
    "iso:country":"IT",
    "sg:address":"00195 Roma",
    "sg:city":"Roma",
    "sg:orig_category":"Prodotti Alimentari",
    "sg:phone":"+39 06 372 9243",
    "sg:postcode":"00195",
    "sg:province":"Roma",
    "wof:name":"Piga Sas",
    "wof:placetype":"venue"
},
  "geometry": {"coordinates":[12.4583368301,41.9161567688],"type":"Point"}
}