{
  "type": "Feature",
  "properties": {
    "addr:full":"20050 Sovico Sovico Milano 20050",
    "addr:postcode":"20050;20050",
    "iso:country":"IT",
    "sg:address":"20050 Sovico",
    "sg:city":"Sovico",
    "sg:orig_category":"Tessuti E Stoffe. Filati E Materie Prime Tessili",
    "sg:phone":"+39 039 201 0177",
    "sg:postcode":"20050",
    "sg:province":"Milano",
    "wof:name":"Rocca Giovanni E Luigia (s.d.f.)",
    "wof:placetype":"venue"
},
  "geometry": {"coordinates":[9.260791,45.644905],"type":"Point"}
}