{
  "type": "Feature",
  "properties": {
    "iso:country":"IT",
    "sg:address":"63039 San Benedetto Del Tronto",
    "sg:city":"San Benedetto del Tronto",
    "sg:orig_category":"Macchine E Forniture Per Ecologia E Smaltimento Rifiuti. Termotecnica E Riscaldamento, Apparecchiature E Servizi",
    "sg:phone":"+39 0735 751248",
    "sg:postcode":"63039",
    "sg:province":"Ascoli Piceno",
    "sg:website":"http://www.western.it",
    "wof:name":"Western Co. Snc",
    "wof:placetype":"venue"
},
  "geometry": {"coordinates":[13.89347,42.905582],"type":"Point"}
}