{
  "type": "Feature",
  "properties": {
    "addr:full":"37010 Rivoli Veronese Rivoli Veronese Verona 37010",
    "addr:postcode":"37010;37010",
    "iso:country":"IT",
    "sg:address":"37010 Rivoli Veronese",
    "sg:city":"Rivoli Veronese",
    "sg:orig_category":"Servizi E Lavori Per Arredamento E Industria Del Legno. Forniture Per Congressi, Fiere E Manifestazioni. Servizi Per Aziende, Manifestazioni E Supporto Agli Scambi Commerciali",
    "sg:phone":"+39 045 728 1355",
    "sg:postcode":"37010",
    "sg:province":"Verona",
    "wof:name":"Hervit (s.r.l.)",
    "wof:placetype":"venue"
},
  "geometry": {"coordinates":[10.811929,45.57156],"type":"Point"}
}