{
  "type": "Feature",
  "properties": {
    "iso:country":"IT",
    "sg:address":"114, V. Roma 24064 Grumello Del Monte",
    "sg:city":"Grumello del Monte",
    "sg:classifiers":[
        {
            "category":"Shopping",
            "subcategory":"Clothing, Apparel, & Fashions",
            "type":"Retail Goods"
        }
    ],
    "sg:phone":"+39 39035832922",
    "sg:postcode":"24064",
    "sg:province":"Bergamo",
    "sg:tags":[
        "clothing",
        "accessory"
    ],
    "sg:website":"http://www.paginegialle.it/lgs",
    "wof:name":"L.g.s. Di Lazzari G.",
    "wof:placetype":"venue"
},
  "geometry": {"coordinates":[9.882402,45.636295],"type":"Point"}
}