{
  "type": "Feature",
  "properties": {
    "addr:full":"10, Via Carlo Ceresa 24048 Treviolo Treviolo Bergamo 24048",
    "addr:postcode":"24048;24048",
    "addr:street":"Via Carlo Ceresa",
    "iso:country":"IT",
    "sg:address":"10, Via Carlo Ceresa 24048 Treviolo",
    "sg:city":"Treviolo",
    "sg:classifiers":[
        {
            "category":"Manufacturing",
            "subcategory":"Metals",
            "type":"Manufacturing & Wholesale Goods"
        }
    ],
    "sg:phone":"+39 39035691050",
    "sg:postcode":"24048",
    "sg:province":"Bergamo",
    "sg:tags":[
        "processing"
    ],
    "wof:name":"Iseco Srl",
    "wof:placetype":"venue"
},
  "geometry": {"coordinates":[9.6133518219,45.6673736572],"type":"Point"}
}