{
  "type": "Feature",
  "properties": {
    "addr:full":"36066 Sandrigo Sandrigo Vicenza 36066",
    "addr:postcode":"36066;36066",
    "iso:country":"IT",
    "sg:address":"36066 Sandrigo",
    "sg:city":"Sandrigo",
    "sg:orig_category":"Abbigliamento Esterno, Maglierie E Pelliccerie. Calzature, Pelletterie E Pelli",
    "sg:phone":"+39 0444 659976",
    "sg:postcode":"36066",
    "sg:province":"Vicenza",
    "wof:name":"Bmi Due S.r.l.",
    "wof:placetype":"venue"
},
  "geometry": {"coordinates":[11.550232,45.633148],"type":"Point"}
}