{
  "type": "Feature",
  "properties": {
    "iso:country":"IT",
    "sg:address":"57126 Livorno",
    "sg:city":"Livorno",
    "sg:orig_category":"Alimenti Dietetici, Macrobiotici E Biologici - Vendita Al Dettaglio",
    "sg:phone":"+39 0586 811631",
    "sg:postcode":"57126",
    "sg:province":"Livorno",
    "wof:name":"Fitness Planet Di Furiani Daniele",
    "wof:placetype":"venue"
},
  "geometry": {"coordinates":[10.311573,43.544048],"type":"Point"}
}