{
  "type": "Feature",
  "properties": {
    "iso:country":"IT",
    "sg:address":"10156 Torino",
    "sg:city":"Torino",
    "sg:orig_category":"Macchine Utensili E Impianti",
    "sg:phone":"+39 011 274 2004",
    "sg:postcode":"10156",
    "sg:province":"Torino",
    "sg:website":"http://www.sitav.com",
    "wof:name":"Sitav Srl",
    "wof:placetype":"venue"
},
  "geometry": {"coordinates":[7.741034,45.102909],"type":"Point"}
}