{
  "type": "Feature",
  "properties": {
    "iso:country":"IT",
    "sg:address":"Via Mirabello 2, 42100 Reggio Emilia, Re",
    "sg:classifiers":[
        {
            "category":"Banks & Credit Unions",
            "subcategory":"Bank",
            "type":"Services"
        }
    ],
    "sg:phone":"+39 0522 402611",
    "sg:postcode":"42100",
    "sg:province":"Reggio Nell'Emilia",
    "wof:name":"Credemleasing Spa",
    "wof:placetype":"venue"
},
  "geometry": {"coordinates":[10.6424684525,44.694026947],"type":"Point"}
}