{
  "type": "Feature",
  "properties": {
    "iso:country":"IT",
    "sg:address":"41, Via Dei Lertora 16043 Chiavari",
    "sg:city":"Chiavari",
    "sg:classifiers":[
        {
            "category":"Real Estate",
            "subcategory":"Architect",
            "type":"Services"
        }
    ],
    "sg:phone":"+39 0185 307752",
    "sg:postcode":"16043",
    "sg:province":"Genova",
    "sg:tags":[
        "textile",
        "clothing"
    ],
    "wof:name":"Cooperativa A.c.l.i. - Dina (soc.coop.r.l.)",
    "wof:placetype":"venue"
},
  "geometry": {"coordinates":[9.319746,44.326385],"type":"Point"}
}