{
  "type": "Feature",
  "properties": {
    "iso:country":"IT",
    "sg:address":"40069 Zola Predosa",
    "sg:city":"Zola",
    "sg:orig_category":"Impiantistica E Prodotti Tecnologici Per Edilizia",
    "sg:phone":"+39 051 616 7466",
    "sg:postcode":"40069",
    "sg:province":"Bologna",
    "wof:name":"Designa Italia Srl",
    "wof:placetype":"venue"
},
  "geometry": {"coordinates":[11.225486,44.496483],"type":"Point"}
}