{
  "type": "Feature",
  "properties": {
    "addr:full":"34077 Ronchi Dei Legionari Ronchi dei Legionari Gorizia 34077",
    "addr:postcode":"34077;34077",
    "iso:country":"IT",
    "sg:address":"34077 Ronchi Dei Legionari",
    "sg:city":"Ronchi dei Legionari",
    "sg:orig_category":"Macchine E Forniture Per Ecologia E Smaltimento Rifiuti. Elettrodomestici. Forniture Alle Strutture Ricettive. Macchine, Strumenti Ed Apparecchi Per Attivita' Industriali",
    "sg:phone":"+39 0481 474525",
    "sg:postcode":"34077",
    "sg:province":"Gorizia",
    "wof:name":"Clipper Srl",
    "wof:placetype":"venue"
},
  "geometry": {"coordinates":[13.476831,45.821564],"type":"Point"}
}