{
  "type": "Feature",
  "properties": {
    "iso:country":"IT",
    "sg:address":"00192 Roma",
    "sg:city":"Roma",
    "sg:orig_category":"Pubblica Amministrazione",
    "sg:phone":"+39 06 320 2796",
    "sg:postcode":"00192",
    "sg:province":"Roma",
    "wof:name":"Regione Lazio",
    "wof:placetype":"venue"
},
  "geometry": {"coordinates":[12.753156662,41.8356666565],"type":"Point"}
}