{
  "type": "Feature",
  "properties": {
    "addr:full":"7, V. Bargnani25134 Brescia Brescia Brescia 25134",
    "addr:housenumber":"7",
    "addr:postcode":"bargnani25134;25134",
    "addr:street":"V.",
    "iso:country":"IT",
    "sg:address":"7, V. Bargnani25134 Brescia",
    "sg:city":"Brescia",
    "sg:classifiers":[
        {
            "category":"Manufacturing",
            "subcategory":"Rubber & Plastics",
            "type":"Manufacturing & Wholesale Goods"
        }
    ],
    "sg:phone":"+39 030 336 3211",
    "sg:postcode":"25134",
    "sg:province":"Brescia",
    "sg:website":"http://www.spm-mould.com:ws_end: :mark:ws:http://www.paginegialle.it/spm-05",
    "wof:name":"S.p.m. Srl",
    "wof:placetype":"venue"
},
  "geometry": {"coordinates":[10.2229576111,45.5398292542],"type":"Point"}
}