{
  "type": "Feature",
  "properties": {
    "iso:country":"IT",
    "sg:address":"80143 Napoli",
    "sg:city":"Napoli",
    "sg:orig_category":"Agenzie D'affari E Servizi Commerciali",
    "sg:phone":"+39 081 284217",
    "sg:postcode":"80143",
    "sg:province":"Napoli",
    "sg:website":"http://www.eic-it352.it",
    "wof:name":"Eurosportello Azienda Speciale Della Cciaa Di Napoli",
    "wof:placetype":"venue"
},
  "geometry": {"coordinates":[14.274412,40.854565],"type":"Point"}
}