{
  "type": "Feature",
  "properties": {
    "addr:full":"90128 Palermo Palermo Palermo 90128",
    "addr:postcode":"90128;90128",
    "iso:country":"IT",
    "sg:address":"90128 Palermo",
    "sg:city":"Palermo",
    "sg:orig_category":"Servizi Ausiliari Di Certificati, Riproduzioni, Disegni E Foto",
    "sg:phone":"+39 091 426999",
    "sg:postcode":"90128",
    "sg:province":"Palermo",
    "wof:name":"Eliografica Di Alcamisi Francesco",
    "wof:placetype":"venue"
},
  "geometry": {"coordinates":[13.353635,38.106743],"type":"Point"}
}