{
  "type": "Feature",
  "properties": {
    "addr:full":"3, Via Vittime Del Vajont 10024 Moncalieri Moncalieri Torino 10024",
    "addr:postcode":"10024;10024",
    "addr:street":"Via Vittime Del Vajont",
    "iso:country":"IT",
    "sg:address":"3, Via Vittime Del Vajont 10024 Moncalieri",
    "sg:city":"Moncalieri",
    "sg:classifiers":[
        {
            "category":"Manufacturing",
            "subcategory":"Metals",
            "type":"Manufacturing & Wholesale Goods"
        }
    ],
    "sg:phone":"+39 011 647 2420",
    "sg:postcode":"10024",
    "sg:province":"Torino",
    "sg:tags":[
        "metallurgy",
        "metalworking"
    ],
    "wof:name":"Provind Di Lepore Gian Domenico & C. S.n.c.",
    "wof:placetype":"venue"
},
  "geometry": {"coordinates":[7.7234172821,44.9747390747],"type":"Point"}
}