{
  "type": "Feature",
  "properties": {
    "iso:country":"IT",
    "sg:address":"Via Matteotti 8/a; Treviglio; 24047",
    "sg:city":"Treviglio",
    "sg:classifiers":[
        {
            "category":"Banks & Credit Unions",
            "subcategory":"Bank",
            "type":"Services"
        }
    ],
    "sg:phone":"+39 036 330 2155",
    "sg:postcode":"24047",
    "sg:province":"Bergamo",
    "wof:name":"Banca Popolare Di Lecco Spa",
    "wof:placetype":"venue"
},
  "geometry": {"coordinates":[9.590835,45.520073],"type":"Point"}
}