{
  "type": "Feature",
  "properties": {
    "iso:country":"IT",
    "sg:address":"20020 Arese",
    "sg:city":"Arese",
    "sg:classifiers":[
        {
            "category":"Sports & Exercise",
            "subcategory":"Tennis Court",
            "type":"Entertainment"
        }
    ],
    "sg:phone":"+39 02 938 5147",
    "sg:postcode":"20020",
    "sg:province":"Milano",
    "sg:tags":[
        "e",
        "lo",
        "tempo",
        "libero",
        "per",
        "impianti",
        "il",
        "attrezzature"
    ],
    "sg:website":"http://www.playsport.it",
    "wof:name":"Playsport Srl",
    "wof:placetype":"venue"
},
  "geometry": {"coordinates":[9.087329,45.536068],"type":"Point"}
}