{
  "type": "Feature",
  "properties": {
    "iso:country":"IT",
    "sg:address":"51013 Chiesina Uzzanese",
    "sg:city":"Chiesina Uzzanese",
    "sg:orig_category":"Abiti Da Sposa E Cerimonia",
    "sg:phone":"+39 0572 411113",
    "sg:postcode":"51013",
    "sg:province":"Pistoia",
    "sg:website":"http://www.lidiasposi.it",
    "wof:name":"Lidia Sposi",
    "wof:placetype":"venue"
},
  "geometry": {"coordinates":[10.719263,43.837593],"type":"Point"}
}