{
  "type": "Feature",
  "properties": {
    "iso:country":"IT",
    "sg:address":"24040 Canonica D'adda",
    "sg:orig_category":"Prodotti E Manufatti In Materie Plastiche. Forniture Per Attivita' Industriali",
    "sg:phone":"+39 02 9098 8344",
    "sg:postcode":"24040",
    "sg:province":"Bergamo",
    "wof:name":"Pisoni S.n.c. Di Pisoni Lodovico & C.",
    "wof:placetype":"venue"
},
  "geometry": {"coordinates":[9.5427055359,45.5719108582],"type":"Point"}
}