{
  "type": "Feature",
  "properties": {
    "iso:country":"IT",
    "sg:address":"09124 Cagliari",
    "sg:city":"Cagliari",
    "sg:orig_category":"Servizi E Lavori Per Edilizia E Lavori Pubblici. Servizi E Lavori Per Ecologia E Smaltimento Rifiuti. Macchine E Forniture Per Ecologia E Smaltimento Rifiuti. Acqua, Luce, Gas E Societa' Di Esercizio ",
    "sg:phone":"+39 070 651204",
    "sg:postcode":"09124",
    "sg:province":"Cagliari",
    "wof:name":"Soccorso Alpino Della Sardegna",
    "wof:placetype":"venue"
},
  "geometry": {"coordinates":[9.113797,39.218624],"type":"Point"}
}