{
  "type": "Feature",
  "properties": {
    "iso:country":"IT",
    "sg:address":"36021 Barbarano Vicentino",
    "sg:city":"Barbarano Vicentino",
    "sg:orig_category":"Elettrotecnica Professionale E Di Consumo",
    "sg:phone":"+39 0444 795398",
    "sg:postcode":"36021",
    "sg:province":"Vicenza",
    "wof:name":"Moonlight Di Malfatto Luciano & C. Snc",
    "wof:placetype":"venue"
},
  "geometry": {"coordinates":[11.581705,45.394947],"type":"Point"}
}