{
  "type": "Feature",
  "properties": {
    "addr:full":"70043 Monopoli Monopoli Bari 70043",
    "addr:postcode":"70043;70043",
    "iso:country":"IT",
    "sg:address":"70043 Monopoli",
    "sg:city":"Monopoli",
    "sg:classifiers":[
        {
            "category":"Health Services",
            "subcategory":"Health Practitioner",
            "type":"Services"
        }
    ],
    "sg:phone":"+39 080 808363",
    "sg:postcode":"70043",
    "sg:province":"Bari",
    "sg:tags":[
        "medici"
    ],
    "wof:name":"Pinto Domenico",
    "wof:placetype":"venue"
},
  "geometry": {"coordinates":[17.2939472198,40.9535865784],"type":"Point"}
}