{
  "type": "Feature",
  "properties": {
    "iso:country":"IT",
    "sg:address":"27/1, Via Giacomo Matteotti 35020 Arzergrande",
    "sg:city":"Arzergrande",
    "sg:classifiers":[
        {
            "category":"Shopping",
            "subcategory":"Clothing, Apparel, & Fashions",
            "type":"Retail Goods"
        }
    ],
    "sg:phone":"+39 049 972 0455",
    "sg:postcode":"35020",
    "sg:province":"Padova",
    "sg:tags":[
        "clothes"
    ],
    "wof:name":"Confezioni Karisma Di Perlita E Massimiliano Ferretto (s.n.c.)",
    "wof:placetype":"venue"
},
  "geometry": {"coordinates":[12.046714,45.278358],"type":"Point"}
}