{
  "type": "Feature",
  "properties": {
    "addr:full":"33087 Rivarotta Rivarotta Pordenone 33087",
    "addr:postcode":"33087;33087",
    "addr:street":"Rivarotta",
    "iso:country":"IT",
    "sg:address":"33087 Rivarotta",
    "sg:city":"Rivarotta",
    "sg:orig_category":"Prodotti E Manufatti In Materie Plastiche",
    "sg:phone":"+39 0434 626029",
    "sg:postcode":"33087",
    "sg:province":"Pordenone",
    "wof:name":"Industrie Ilpea (s.p.a.)",
    "wof:placetype":"venue"
},
  "geometry": {"coordinates":[12.5801820755,45.8487663269],"type":"Point"}
}