{
  "type": "Feature",
  "properties": {
    "addr:full":"Via A. Novella, 4 - Talacchio 61022 Colbordolo Colbordolo Pesaro E Urbino 61022",
    "addr:housenumber":"4",
    "addr:postcode":"61022;61022",
    "addr:street":"Via A. Novella",
    "iso:country":"IT",
    "sg:address":"Via A. Novella, 4 - Talacchio 61022 Colbordolo",
    "sg:city":"Colbordolo",
    "sg:orig_category":"Chipboards",
    "sg:phone":"+39 0721 905611",
    "sg:postcode":"61022",
    "sg:province":"Pesaro E Urbino",
    "wof:name":"F.i.a. Spa - Furniture Industrial Accessories",
    "wof:placetype":"venue"
},
  "geometry": {"coordinates":[12.719912,43.837784],"type":"Point"}
}