{
  "type": "Feature",
  "properties": {
    "addr:full":"12, Via Lazzaretto 21050 Saltrio Saltrio Varese 21050",
    "addr:postcode":"21050;21050",
    "addr:street":"Via Lazzaretto",
    "iso:country":"IT",
    "sg:address":"12, Via Lazzaretto 21050 Saltrio",
    "sg:city":"Saltrio",
    "sg:classifiers":[
        {
            "category":"Manufacturing",
            "subcategory":"Metals",
            "type":"Manufacturing & Wholesale Goods"
        }
    ],
    "sg:phone":"+39 0332 487261",
    "sg:postcode":"21050",
    "sg:province":"Varese",
    "sg:tags":[
        "metallurgy",
        "metalworking"
    ],
    "wof:name":"L.n.i. Italia S.p.a.",
    "wof:placetype":"venue"
},
  "geometry": {"coordinates":[8.9180450439,45.8700828552],"type":"Point"}
}