{
  "type": "Feature",
  "properties": {
    "iso:country":"IT",
    "sg:address":"203/10, Via Cassanese 20090 Segrate",
    "sg:city":"Segrate",
    "sg:classifiers":[
        {
            "category":"Bars & Pubs",
            "subcategory":"Nightclub",
            "type":"Food & Drink"
        }
    ],
    "sg:phone":"+39 39022132195",
    "sg:postcode":"20090",
    "sg:province":"Milano",
    "sg:tags":[
        "cake",
        "bread"
    ],
    "wof:name":"Debora (s.r.l.)",
    "wof:placetype":"venue"
},
  "geometry": {"coordinates":[9.282232,45.494598],"type":"Point"}
}