{
  "type": "Feature",
  "properties": {
    "addr:full":"10148 Torino Torino Torino 10148",
    "addr:postcode":"10148;10148",
    "iso:country":"IT",
    "sg:address":"10148 Torino",
    "sg:city":"Torino",
    "sg:orig_category":"Forniture Per Attivita' Industriali",
    "sg:phone":"+39 011 220 0370",
    "sg:postcode":"10148",
    "sg:province":"Torino",
    "wof:name":"Priora A. E Degiovanni S.d.f.",
    "wof:placetype":"venue"
},
  "geometry": {"coordinates":[7.6764235497,45.1070671082],"type":"Point"}
}