{
  "type": "Feature",
  "properties": {
    "addr:full":"20046 Biassono Biassono Milano 20046",
    "addr:postcode":"20046;20046",
    "iso:country":"IT",
    "sg:address":"20046 Biassono",
    "sg:city":"Biassono",
    "sg:classifiers":[
        {
            "category":"Shopping",
            "subcategory":"Stationery & Office Supplies",
            "type":"Retail Goods"
        }
    ],
    "sg:phone":"+39 039 491918",
    "sg:postcode":"20046",
    "sg:province":"Milano",
    "sg:tags":[
        "equipment",
        "furniture",
        "furnishing",
        "professional"
    ],
    "sg:website":"http://www.alpaarredamenti.com",
    "wof:name":"Alpa Srl",
    "wof:placetype":"venue"
},
  "geometry": {"coordinates":[9.2628622055,45.6173477173],"type":"Point"}
}