{
  "type": "Feature",
  "properties": {
    "addr:full":"45021 Badia Polesine Badia Polesine Rovigo 45021",
    "addr:postcode":"45021;45021",
    "iso:country":"IT",
    "sg:address":"45021 Badia Polesine",
    "sg:city":"Badia Polesine",
    "sg:classifiers":[
        {
            "category":"Sports & Exercise",
            "subcategory":"Tennis Court",
            "type":"Entertainment"
        }
    ],
    "sg:phone":"+39 0425 51552",
    "sg:postcode":"45021",
    "sg:province":"Rovigo",
    "sg:tags":[
        "e",
        "lo",
        "tempo",
        "libero",
        "per",
        "impianti",
        "il",
        "attrezzature"
    ],
    "wof:name":"Palanca Francesco",
    "wof:placetype":"venue"
},
  "geometry": {"coordinates":[11.498839,45.086094],"type":"Point"}
}