{
  "type": "Feature",
  "properties": {
    "iso:country":"IT",
    "sg:address":"23, Via Delle Industrie 35040 Villa Estense",
    "sg:city":"Villa Estense",
    "sg:classifiers":[
        {
            "category":"Utilities",
            "subcategory":"Electric",
            "type":"Services"
        }
    ],
    "sg:phone":"+39 39042991082",
    "sg:postcode":"35040",
    "sg:province":"Padova",
    "sg:tags":[
        "component",
        "electronic"
    ],
    "wof:name":"Ra.pe.ti.",
    "wof:placetype":"venue"
},
  "geometry": {"coordinates":[11.671587,45.182873],"type":"Point"}
}