{
  "type": "Feature",
  "properties": {
    "iso:country":"IT",
    "sg:address":"2, Via Zoboli Filippo 42100 Reggio Emilia",
    "sg:classifiers":[
        {
            "category":"Sports & Exercise",
            "subcategory":"Playing Field",
            "type":"Entertainment"
        }
    ],
    "sg:phone":"+39 0522 518800",
    "sg:postcode":"42100",
    "sg:province":"Reggio Nell'Emilia",
    "sg:tags":[
        "game"
    ],
    "wof:name":"C. And S. (s.r.l.)",
    "wof:placetype":"venue"
},
  "geometry": {"coordinates":[10.654755,44.738926],"type":"Point"}
}