{
  "type": "Feature",
  "properties": {
    "iso:country":"IT",
    "sg:address":"3, Via Melato Maria 42100 Reggio Emilia",
    "sg:classifiers":[
        {
            "category":"Wholesale",
            "subcategory":"Drugs",
            "type":"Manufacturing & Wholesale Goods"
        }
    ],
    "sg:phone":"+39 0522 265011",
    "sg:postcode":"42100",
    "sg:province":"Reggio Nell'Emilia",
    "sg:tags":[
        "chemical",
        "pharmaceutical"
    ],
    "wof:name":"Diverseylever Spa",
    "wof:placetype":"venue"
},
  "geometry": {"coordinates":[10.645284,44.689556],"type":"Point"}
}