{
  "type": "Feature",
  "properties": {
    "addr:full":"25086 Rezzato Rezzato Brescia 25086",
    "addr:postcode":"25086;25086",
    "iso:country":"IT",
    "sg:address":"25086 Rezzato",
    "sg:city":"Rezzato",
    "sg:orig_category":"Materiali E Componenti Elettronici",
    "sg:phone":"+39 030 259 4120",
    "sg:postcode":"25086",
    "sg:province":"Brescia",
    "sg:website":"http://www.detas.com",
    "wof:name":"Detas Spa",
    "wof:placetype":"venue"
},
  "geometry": {"coordinates":[10.33641,45.506577],"type":"Point"}
}