{
  "type": "Feature",
  "properties": {
    "iso:country":"IT",
    "sg:address":"Via Macello 10060 Buriasco",
    "sg:city":"Buriasco",
    "sg:classifiers":[
        {
            "category":"Shopping",
            "type":"Retail Goods"
        }
    ],
    "sg:phone":"+39 39012156355",
    "sg:postcode":"10060",
    "sg:province":"Torino",
    "sg:tags":[
        "finished",
        "-",
        "metallic"
    ],
    "wof:name":"Mollificio Rmi",
    "wof:placetype":"venue"
},
  "geometry": {"coordinates":[7.4141869545,44.8688049316],"type":"Point"}
}