{
  "type": "Feature",
  "properties": {
    "iso:country":"IT",
    "sg:address":"36016 Thiene",
    "sg:city":"Thiene",
    "sg:orig_category":"Gru - Noleggio",
    "sg:phone":"+39 0445 360270",
    "sg:postcode":"36016",
    "sg:province":"Vicenza",
    "wof:name":"Cs Noleggi",
    "wof:placetype":"venue"
},
  "geometry": {"coordinates":[11.469417,45.706799],"type":"Point"}
}