{
  "type": "Feature",
  "properties": {
    "addr:full":"Via Ponte Asolana 25010 Remedello Remedello Brescia 25010",
    "addr:postcode":"25010;25010",
    "addr:street":"Via Ponte Asolana",
    "iso:country":"IT",
    "sg:address":"Via Ponte Asolana 25010 Remedello",
    "sg:city":"Remedello",
    "sg:classifiers":[
        {
            "category":"Manufacturing",
            "subcategory":"Metals",
            "type":"Manufacturing & Wholesale Goods"
        }
    ],
    "sg:phone":"+39 39030957140",
    "sg:postcode":"25010",
    "sg:province":"Brescia",
    "sg:tags":[
        "metallurgy",
        "metalworking"
    ],
    "wof:name":"Moglia Di Moglia Giovanni & C. S.n.c.",
    "wof:placetype":"venue"
},
  "geometry": {"coordinates":[10.358830452,45.279384613],"type":"Point"}
}