{
  "type": "Feature",
  "properties": {
    "addr:full":"04022 Fondi Fondi Latina 04022",
    "addr:postcode":"04022;04022",
    "iso:country":"IT",
    "sg:address":"04022 Fondi",
    "sg:city":"Fondi",
    "sg:orig_category":"Banche E Servizi Finanziari",
    "sg:phone":"+39 0771 5181",
    "sg:postcode":"04022",
    "sg:province":"Latina",
    "sg:website":"http://www.bpfondi.it",
    "wof:name":"Banca Popolare Di Fondi Soc.coop.r.l.",
    "wof:placetype":"venue"
},
  "geometry": {"coordinates":[13.428059,41.348587],"type":"Point"}
}