{
  "type": "Feature",
  "properties": {
    "addr:full":"36, Via Mignano 25072 Bagolino Bagolino Brescia 25072",
    "addr:postcode":"25072;25072",
    "addr:street":"Via Mignano",
    "iso:country":"IT",
    "sg:address":"36, Via Mignano 25072 Bagolino",
    "sg:city":"Bagolino",
    "sg:classifiers":[
        {
            "category":"Home & Garden",
            "subcategory":"Home Furnishings",
            "type":"Retail Goods"
        }
    ],
    "sg:phone":"+39 39036599110",
    "sg:postcode":"25072",
    "sg:province":"Brescia",
    "sg:tags":[
        "household"
    ],
    "wof:name":"La Bottega Del Peltro Di Tabellini Dr Giorgio & C.(s.n.c.)",
    "wof:placetype":"venue"
},
  "geometry": {"coordinates":[10.453926,45.832359],"type":"Point"}
}