{
  "type": "Feature",
  "properties": {
    "iso:country":"IT",
    "sg:address":"14, V. Ugo Da Carpi 41012 Carpi",
    "sg:city":"Carpi",
    "sg:classifiers":[
        {
            "category":"Shopping",
            "subcategory":"Clothing, Apparel, & Fashions",
            "type":"Retail Goods"
        }
    ],
    "sg:phone":"+39 39059695171",
    "sg:postcode":"41012",
    "sg:province":"Modena",
    "sg:tags":[
        "clothes"
    ],
    "sg:website":"http://www.lefate.it",
    "wof:name":"Le Fate - Match Italia Srl",
    "wof:placetype":"venue"
},
  "geometry": {"coordinates":[10.880099,44.776184],"type":"Point"}
}