{
  "type": "Feature",
  "properties": {
    "addr:full":"21052 Busto Arsizio Busto Arsizio Varese 21052",
    "addr:postcode":"21052;21052",
    "iso:country":"IT",
    "sg:address":"21052 Busto Arsizio",
    "sg:city":"Busto Arsizio",
    "sg:orig_category":"Elettronica Industriale, Prodotti E Apparecchiature",
    "sg:phone":"+39 0331 351922",
    "sg:postcode":"21052",
    "sg:province":"Varese",
    "sg:website":"http://www.elettronova.it",
    "wof:name":"Elettronova Srl",
    "wof:placetype":"venue"
},
  "geometry": {"coordinates":[8.858616,45.597759],"type":"Point"}
}