{
  "type": "Feature",
  "properties": {
    "iso:country":"IT",
    "sg:address":"Via P L Da Palestrina 2; Milano; 20124",
    "sg:city":"Milano",
    "sg:classifiers":[
        {
            "category":"Banks & Credit Unions",
            "subcategory":"Bank",
            "type":"Services"
        }
    ],
    "sg:phone":"+39 02 6698 7454",
    "sg:postcode":"20124",
    "sg:province":"Milano",
    "wof:name":"Deutsche Bank Spa",
    "wof:placetype":"venue"
},
  "geometry": {"coordinates":[9.214989,45.484661],"type":"Point"}
}