{
  "type": "Feature",
  "properties": {
    "addr:full":"10099 S. Mauro Torinese Torino 10099",
    "addr:housenumber":"10099",
    "addr:postcode":"10099",
    "addr:street":"S. Mauro Torinese",
    "iso:country":"IT",
    "sg:address":"10099 S. Mauro Torinese",
    "sg:orig_category":"Autonoleggio",
    "sg:phone":"+39 011 223 8500",
    "sg:postcode":"10099",
    "sg:province":"Torino",
    "sg:website":"http://www.vigo-autoindustriale.com",
    "wof:name":"Autoindustriale Sas",
    "wof:placetype":"venue"
},
  "geometry": {"coordinates":[7.742496,45.115669],"type":"Point"}
}