{
  "type": "Feature",
  "properties": {
    "iso:country":"IT",
    "sg:address":"Str. Statale Sannitica. 87 Km 7,350 80026 Casoria",
    "sg:city":"Casoria",
    "sg:classifiers":[
        {
            "category":"Shopping",
            "subcategory":"Crafts & Fabrics",
            "type":"Retail Goods"
        }
    ],
    "sg:phone":"+39 081 758 3833",
    "sg:postcode":"80026",
    "sg:province":"Napoli",
    "sg:tags":[
        "trade",
        "timber"
    ],
    "sg:website":"www.riccardispa.it",
    "wof:name":"Riccardi Spa",
    "wof:placetype":"venue"
},
  "geometry": {"coordinates":[14.251636,40.840096],"type":"Point"}
}