{
  "type": "Feature",
  "properties": {
    "iso:country":"IT",
    "sg:address":"00196 Roma",
    "sg:city":"Roma",
    "sg:orig_category":"Servizi Editoriali. Servizi Per Aziende, Manifestazioni E Supporto Agli Scambi Commerciali",
    "sg:phone":"+39 06 323 3195",
    "sg:postcode":"00196",
    "sg:province":"Roma",
    "wof:name":"S.e.t. Societa' Edizioni Tecniche S.r.l.",
    "wof:placetype":"venue"
},
  "geometry": {"coordinates":[12.463854,41.927189],"type":"Point"}
}