{
  "type": "Feature",
  "properties": {
    "addr:full":"Via Nepal, 29 Rome 00144",
    "addr:housenumber":"29",
    "addr:postcode":"00144",
    "addr:street":"Via Nepal",
    "iso:country":"IT",
    "sg:address":"Via Nepal, 29",
    "sg:city":"Rome",
    "sg:classifiers":[
        {
            "category":"Professional",
            "subcategory":"Computer Services",
            "type":"Services"
        }
    ],
    "sg:postcode":"00144",
    "sg:tags":[
        "online-backup",
        "online-storage",
        "cloud-storage"
    ],
    "sg:website":"http://www.memopal.com",
    "wof:name":"Memopal",
    "wof:placetype":"venue"
},
  "geometry": {"coordinates":[12.461425,41.823172],"type":"Point"}
}