{
  "type": "Feature",
  "properties": {
    "iso:country":"IT",
    "sg:address":"71011 Apricena",
    "sg:city":"Apricena",
    "sg:orig_category":"Carni Fresche E Congelate - Lavorazione E Commercio",
    "sg:phone":"+39 0882 647657",
    "sg:postcode":"71011",
    "sg:province":"Foggia",
    "wof:name":"Italconigli Di Pasquale Pizzicoli",
    "wof:placetype":"venue"
},
  "geometry": {"coordinates":[15.477108,41.790829],"type":"Point"}
}