{
  "type": "Feature",
  "properties": {
    "addr:full":"06129 Perugia Perugia Perugia 06129",
    "addr:postcode":"06129;06129",
    "iso:country":"IT",
    "sg:address":"06129 Perugia",
    "sg:city":"Perugia",
    "sg:orig_category":"Servizi Per Aziende, Manifestazioni E Supporto Agli Scambi Commerciali",
    "sg:phone":"+39 075 505 8374",
    "sg:postcode":"06129",
    "sg:province":"Perugia",
    "wof:name":"Studio Eventi",
    "wof:placetype":"venue"
},
  "geometry": {"coordinates":[12.37674,43.101551],"type":"Point"}
}