{
  "type": "Feature",
  "properties": {
    "iso:country":"IT",
    "sg:address":"7, Via Tarroni 48012 Bagnacavallo",
    "sg:city":"Bagnacavallo",
    "sg:classifiers":[
        {
            "category":"Personal",
            "subcategory":"Shoe Repair & Shine",
            "type":"Services"
        }
    ],
    "sg:phone":"+39 39054561636",
    "sg:postcode":"48012",
    "sg:province":"Ravenna",
    "sg:tags":[
        "leather"
    ],
    "wof:name":"Calzaturificio Emanuela Srl",
    "wof:placetype":"venue"
},
  "geometry": {"coordinates":[11.984802,44.479786],"type":"Point"}
}