{
  "type": "Feature",
  "properties": {
    "iso:country":"IT",
    "sg:address":"25064 Gussago",
    "sg:city":"Gussago",
    "sg:orig_category":"Acciaierie E Fonderie. Arte Ed Artigianato Artistico",
    "sg:phone":"+39 030 277 3923",
    "sg:postcode":"25064",
    "sg:province":"Brescia",
    "wof:name":"Cola Angelo",
    "wof:placetype":"venue"
},
  "geometry": {"coordinates":[10.157985,45.599407],"type":"Point"}
}