{
  "type": "Feature",
  "properties": {
    "iso:country":"IT",
    "sg:address":"Via Val Di Foro 66010 Miglianico",
    "sg:city":"Miglianico",
    "sg:classifiers":[
        {
            "category":"Wholesale",
            "subcategory":"Machinery & Supplies",
            "type":"Manufacturing & Wholesale Goods"
        }
    ],
    "sg:phone":"+39 39087195841",
    "sg:postcode":"66010",
    "sg:province":"Chieti",
    "sg:tags":[
        "-",
        "agriculture",
        "equipment"
    ],
    "wof:name":"Sicma Spa",
    "wof:placetype":"venue"
},
  "geometry": {"coordinates":[14.24915,42.325993],"type":"Point"}
}