{
  "type": "Feature",
  "properties": {
    "addr:full":"20122 Milano Milano Milano 20122",
    "addr:postcode":"20122;20122",
    "iso:country":"IT",
    "sg:address":"20122 Milano",
    "sg:city":"Milano",
    "sg:orig_category":"Servizi Culturali E Per Lo Spettacolo",
    "sg:phone":"+39 02 7602 0048",
    "sg:postcode":"20122",
    "sg:province":"Milano",
    "wof:name":"Cinematografo Arti",
    "wof:placetype":"venue"
},
  "geometry": {"coordinates":[9.201341,45.465919],"type":"Point"}
}