{
  "type": "Feature",
  "properties": {
    "iso:country":"IT",
    "sg:address":"32031 Alano Di Piave",
    "sg:city":"Alano di Piave",
    "sg:orig_category":"Arredamento Bar E Ristoranti",
    "sg:phone":"+39 0439 789449",
    "sg:postcode":"32031",
    "sg:province":"Belluno",
    "wof:name":"Rizzotto Massimo",
    "wof:placetype":"venue"
},
  "geometry": {"coordinates":[11.887006,45.905445],"type":"Point"}
}