{
  "type": "Feature",
  "properties": {
    "iso:country":"IT",
    "sg:address":"10098 Rivoli",
    "sg:city":"Rivoli",
    "sg:orig_category":"Stampi Materie Plastiche E Gomma",
    "sg:phone":"+39 011 959 2232",
    "sg:postcode":"10098",
    "sg:province":"Torino",
    "sg:website":"http://www.strocchi.it",
    "wof:name":"Comec Spa",
    "wof:placetype":"venue"
},
  "geometry": {"coordinates":[7.588079,45.073185],"type":"Point"}
}