{
  "type": "Feature",
  "properties": {
    "addr:full":"35127 Padova Padova Padova 35127",
    "addr:postcode":"35127;35127",
    "iso:country":"IT",
    "sg:address":"35127 Padova",
    "sg:city":"Padova",
    "sg:orig_category":"Prodotti Chimici Di Base. Ospedali E Servizi Sanitari",
    "sg:phone":"+39 049 870 2295",
    "sg:postcode":"35127",
    "sg:province":"Padova",
    "wof:name":"Sapio Life (s.r.l.)",
    "wof:placetype":"venue"
},
  "geometry": {"coordinates":[11.941204071,45.3920478821],"type":"Point"}
}