{
  "type": "Feature",
  "properties": {
    "addr:full":"46029 Rivarolo Mantovano Riva Mantova 46029",
    "addr:postcode":"46029;46029",
    "addr:street":"Riva Mantova",
    "iso:country":"IT",
    "sg:address":"46029 Rivarolo Mantovano",
    "sg:city":"Riva",
    "sg:orig_category":"Macchine Utensili E Impianti",
    "sg:postcode":"46029",
    "sg:province":"Mantova",
    "wof:name":"Fantini Meccanica S.r.l.",
    "wof:placetype":"venue"
},
  "geometry": {"coordinates":[10.797698,45.160366],"type":"Point"}
}