{
  "type": "Feature",
  "properties": {
    "iso:country":"IT",
    "sg:address":"10042 Nichelino",
    "sg:city":"Nichelino",
    "sg:orig_category":"Scuole E Servizi Scolastici. Centri Di Estetica E Cosmesi E Servizi. Ricerca, Selezione E Formazione Del Personale",
    "sg:phone":"+39 011 627 5110",
    "sg:postcode":"10042",
    "sg:province":"Torino",
    "wof:name":"Broch Ciarus Anna Maria",
    "wof:placetype":"venue"
},
  "geometry": {"coordinates":[7.6457223892,44.9980316162],"type":"Point"}
}