{
  "type": "Feature",
  "properties": {
    "iso:country":"IT",
    "sg:address":"47, Vl. Carlo Felice00185 Roma",
    "sg:city":"Roma",
    "sg:classifiers":[
        {
            "category":"Shopping",
            "subcategory":"Jewelry",
            "type":"Retail Goods"
        }
    ],
    "sg:phone":"+39 06 7045 1429",
    "sg:postcode":"00185",
    "sg:province":"Roma",
    "sg:tags":[
        "jewellery"
    ],
    "sg:website":"http://www.paginegialle.it/",
    "wof:name":"Botti Mauro",
    "wof:placetype":"venue"
},
  "geometry": {"coordinates":[12.510124,41.887051],"type":"Point"}
}