{
  "type": "Feature",
  "properties": {
    "addr:full":"29010 Alseno Alseno Piacenza 29010",
    "addr:postcode":"29010;29010",
    "iso:country":"IT",
    "sg:address":"29010 Alseno",
    "sg:city":"Alseno",
    "sg:orig_category":"Pastifici - Impianti E Macchine",
    "sg:phone":"+39 0523 945404",
    "sg:postcode":"29010",
    "sg:province":"Piacenza",
    "wof:name":"Tecnomachine Srl",
    "wof:placetype":"venue"
},
  "geometry": {"coordinates":[9.9665622711,44.896987915],"type":"Point"}
}