{
  "type": "Feature",
  "properties": {
    "iso:country":"IT",
    "sg:address":"Piazza Arcivescovado 4; Ravenna; 48100",
    "sg:city":"Ravenna",
    "sg:classifiers":[
        {
            "category":"Banks & Credit Unions",
            "subcategory":"Bank",
            "type":"Services"
        }
    ],
    "sg:phone":"+39 0544 34221",
    "sg:postcode":"48100",
    "sg:province":"Ravenna",
    "wof:name":"Banca Popolare Di Ravenna",
    "wof:placetype":"venue"
},
  "geometry": {"coordinates":[12.197892,44.41555],"type":"Point"}
}