{
  "type": "Feature",
  "properties": {
    "iso:country":"IT",
    "sg:address":"24123 Bergamo",
    "sg:city":"Bergamo",
    "sg:orig_category":"Macchine Ed Impianti Per Edilizia E Lavori Pubblici",
    "sg:phone":"+39 035 347762",
    "sg:postcode":"24123",
    "sg:province":"Bergamo",
    "wof:name":"G.m.m. S.r.l.",
    "wof:placetype":"venue"
},
  "geometry": {"coordinates":[9.682084,45.715385],"type":"Point"}
}