{
  "type": "Feature",
  "properties": {
    "addr:full":"39, Via Carrara Luigi 24027 Nembro Nembro Bergamo 24027",
    "addr:postcode":"24027;24027",
    "addr:street":"Via Carrara Luigi",
    "iso:country":"IT",
    "sg:address":"39, Via Carrara Luigi 24027 Nembro",
    "sg:city":"Nembro",
    "sg:classifiers":[
        {
            "category":"Shopping",
            "type":"Retail Goods"
        }
    ],
    "sg:phone":"+39 035 416 9011",
    "sg:postcode":"24027",
    "sg:province":"Bergamo",
    "sg:tags":[
        "finished",
        "-",
        "metallic"
    ],
    "wof:name":"Carmo Srl",
    "wof:placetype":"venue"
},
  "geometry": {"coordinates":[9.6699523926,45.6949043274],"type":"Point"}
}