{
  "type": "Feature",
  "properties": {
    "addr:full":"47025 Mercato Saraceno Mercato Saraceno Forl\u00ec-Cesena 47025",
    "addr:postcode":"47025;47025",
    "iso:country":"IT",
    "sg:address":"47025 Mercato Saraceno",
    "sg:city":"Mercato Saraceno",
    "sg:orig_category":"Servizi E Lavori Per Arredamento E Industria Del Legno",
    "sg:phone":"+39 0547 96692",
    "sg:postcode":"47025",
    "sg:province":"Forl\u00ec-Cesena",
    "wof:name":"Casadei Danilo & C. Snc",
    "wof:placetype":"venue"
},
  "geometry": {"coordinates":[12.140404,43.996479],"type":"Point"}
}