{
  "type": "Feature",
  "properties": {
    "iso:country":"IT",
    "sg:address":"20030 Barlassina",
    "sg:city":"Barlassina",
    "sg:orig_category":"Legno E Semilavorati",
    "sg:phone":"+39 036 256 4933",
    "sg:postcode":"20030",
    "sg:province":"Milano",
    "wof:name":"Cardaciotto Giuseppe",
    "wof:placetype":"venue"
},
  "geometry": {"coordinates":[9.160385,45.478683],"type":"Point"}
}