{
  "type": "Feature",
  "properties": {
    "iso:country":"IT",
    "sg:address":"57126 Livorno",
    "sg:city":"Livorno",
    "sg:orig_category":"Disinfezione, Disinfestazione E Derattizzazione",
    "sg:phone":"+39 0586 800212",
    "sg:postcode":"57126",
    "sg:province":"Livorno",
    "wof:name":"First Integrated Filipino Services Snc",
    "wof:placetype":"venue"
},
  "geometry": {"coordinates":[10.307695,43.542324],"type":"Point"}
}