{
  "type": "Feature",
  "properties": {
    "addr:full":"22, V. Settola 51100 Pistoia Pistoia Pistoia 51100",
    "addr:housenumber":"22",
    "addr:postcode":"51100;51100",
    "addr:street":"V. Settola",
    "iso:country":"IT",
    "sg:address":"22, V. Settola 51100 Pistoia",
    "sg:city":"Pistoia",
    "sg:classifiers":[
        {
            "category":"Shopping",
            "subcategory":"Crafts & Fabrics",
            "type":"Retail Goods"
        }
    ],
    "sg:phone":"+39 0573 934291",
    "sg:postcode":"51100",
    "sg:province":"Pistoia",
    "sg:website":"http://www.famajersey.com",
    "wof:name":"Fama Jersey Spa",
    "wof:placetype":"venue"
},
  "geometry": {"coordinates":[10.9895572662,43.9153709412],"type":"Point"}
}