{
  "type": "Feature",
  "properties": {
    "iso:country":"IT",
    "sg:address":"6, Via Montefiorino 48024 Massa Lombarda",
    "sg:city":"Massa Lombarda",
    "sg:classifiers":[
        {
            "category":"Shopping",
            "type":"Retail Goods"
        }
    ],
    "sg:phone":"+39 0545 971080",
    "sg:postcode":"48024",
    "sg:province":"Ravenna",
    "sg:tags":[
        "finished",
        "-",
        "metallic"
    ],
    "wof:name":"Domax Di Donegaglia Domenico & C. S.a.s.",
    "wof:placetype":"venue"
},
  "geometry": {"coordinates":[11.8105888367,44.4499740601],"type":"Point"}
}