{
  "type": "Feature",
  "properties": {
    "addr:full":"74016 Massafra Massafra Taranto 74016",
    "addr:postcode":"74016;74016",
    "iso:country":"IT",
    "sg:address":"74016 Massafra",
    "sg:city":"Massafra",
    "sg:orig_category":"Servizi Culturali E Per Lo Spettacolo. Cine-foto-ottica",
    "sg:phone":"+39 099 880 4108",
    "sg:postcode":"74016",
    "sg:province":"Taranto",
    "wof:name":"Elite Video Music",
    "wof:placetype":"venue"
},
  "geometry": {"coordinates":[17.1158695221,40.5931091309],"type":"Point"}
}