{
  "type": "Feature",
  "properties": {
    "iso:country":"IT",
    "sg:address":"00197 Roma",
    "sg:city":"Roma",
    "sg:orig_category":"Banche E Servizi Finanziari",
    "sg:phone":"+39 06 807 5652",
    "sg:postcode":"00197",
    "sg:province":"Roma",
    "wof:name":"Colle Pardo Srl",
    "wof:placetype":"venue"
},
  "geometry": {"coordinates":[12.490722,41.923904],"type":"Point"}
}