{
  "type": "Feature",
  "properties": {
    "iso:country":"IT",
    "sg:address":"12 Via Xx Settembre, 09016 Iglesias",
    "sg:city":"Iglesias",
    "sg:classifiers":[
        {
            "category":"Banks & Credit Unions",
            "subcategory":"Financial Services",
            "type":"Services"
        }
    ],
    "sg:phone":"+39 39078122746",
    "sg:postcode":"09016",
    "sg:province":"Carbonia-Iglesias",
    "sg:tags":[
        "banking",
        "finance",
        "insurance"
    ],
    "wof:name":"Massa Srl",
    "wof:placetype":"venue"
},
  "geometry": {"coordinates":[8.572101593,39.2534675598],"type":"Point"}
}