{
  "type": "Feature",
  "properties": {
    "addr:full":"20040 Bellusco Bellusco Milano 20040",
    "addr:postcode":"20040;20040",
    "iso:country":"IT",
    "sg:address":"20040 Bellusco",
    "sg:city":"Bellusco",
    "sg:orig_category":"Autofficine E Centri Assistenza",
    "sg:phone":"+39 039 623542",
    "sg:postcode":"20040",
    "sg:province":"Milano",
    "wof:name":"Colombo Martino",
    "wof:placetype":"venue"
},
  "geometry": {"coordinates":[9.413554,45.617344],"type":"Point"}
}