{
  "type": "Feature",
  "properties": {
    "addr:full":"26855 Lodi Vecchio Lodi Vecchio Lodi 26855",
    "addr:postcode":"26855;26855",
    "iso:country":"IT",
    "sg:address":"26855 Lodi Vecchio",
    "sg:city":"Lodi Vecchio",
    "sg:orig_category":"Frigotecnica, Apparecchiature E Servizi",
    "sg:phone":"+39 0371 464194",
    "sg:postcode":"26855",
    "sg:province":"Lodi",
    "sg:website":"http://www.topdelta.it",
    "wof:name":"Top Frigor Srl",
    "wof:placetype":"venue"
},
  "geometry": {"coordinates":[9.41385746,45.3076057434],"type":"Point"}
}