{
  "type": "Feature",
  "properties": {
    "iso:country":"IT",
    "sg:address":"56126 Pisa",
    "sg:city":"Pisa",
    "sg:orig_category":"Audiovisivi Apparecchi Ed Impianti - Produzione, Commercio E Noleggio",
    "sg:phone":"+39 050 555977",
    "sg:postcode":"56126",
    "sg:province":"Pisa",
    "sg:website":"http://www.digitart.it",
    "wof:name":"Digitart Custhome",
    "wof:placetype":"venue"
},
  "geometry": {"coordinates":[10.747925,43.67762],"type":"Point"}
}