{
  "type": "Feature",
  "properties": {
    "iso:country":"IT",
    "sg:address":"Via Mattei Enrico 62014 Corridonia",
    "sg:city":"Corridonia",
    "sg:classifiers":[
        {
            "category":"Personal",
            "subcategory":"Shoe Repair & Shine",
            "type":"Services"
        }
    ],
    "sg:phone":"+39 0733 283090",
    "sg:postcode":"62014",
    "sg:province":"Macerata",
    "sg:tags":[
        "leather"
    ],
    "wof:name":"Pelletteria Orlandi Valentino",
    "wof:placetype":"venue"
},
  "geometry": {"coordinates":[13.487265,43.262424],"type":"Point"}
}