{
  "type": "Feature",
  "properties": {
    "iso:country":"IT",
    "sg:address":"15048 Valenza",
    "sg:city":"Valenza",
    "sg:orig_category":"Gioielleria, Oreficeria E Argenteria. Shopping",
    "sg:phone":"+39 0131 951391",
    "sg:postcode":"15048",
    "sg:province":"Alessandria",
    "wof:name":"Cerutti Gianluigi Srl",
    "wof:placetype":"venue"
},
  "geometry": {"coordinates":[8.687799,44.973511],"type":"Point"}
}