{
  "type": "Feature",
  "properties": {
    "iso:country":"IT",
    "sg:address":"07020 Monti",
    "sg:city":"Monti",
    "sg:classifiers":[
        {
            "category":"Food & Beverages",
            "subcategory":"Fruits & Vegetables",
            "type":"Retail Goods"
        }
    ],
    "sg:phone":"+39 0789 44012",
    "sg:postcode":"07020",
    "sg:province":"Olbia-Tempio",
    "sg:tags":[
        "flower",
        "liqueurs",
        "growing",
        "wine",
        "agriculture",
        "drinks"
    ],
    "sg:website":"http://www.vermentinomonti.it",
    "wof:name":"Cantina Sociale Del Vermentino Di Monti Soc.coop.r.l.",
    "wof:placetype":"venue"
},
  "geometry": {"coordinates":[9.39782,40.791534],"type":"Point"}
}