{
  "type": "Feature",
  "properties": {
    "addr:full":"00148 Roma Roma Roma 00148",
    "addr:postcode":"00148;00148",
    "iso:country":"IT",
    "sg:address":"00148 Roma",
    "sg:city":"Roma",
    "sg:orig_category":"Imprese Di Costruzioni Civili Ed Industriali",
    "sg:phone":"+39 06 6574 0571",
    "sg:postcode":"00148",
    "sg:province":"Roma",
    "wof:name":"Acme Systems Sas",
    "wof:placetype":"venue"
},
  "geometry": {"coordinates":[12.435952,41.833797],"type":"Point"}
}