{
  "type": "Feature",
  "properties": {
    "iso:country":"IT",
    "sg:address":"Monza, Mi",
    "sg:classifiers":[
        {
            "category":"Banks & Credit Unions",
            "subcategory":"Bank",
            "type":"Services"
        }
    ],
    "wof:name":"Candy",
    "wof:placetype":"venue"
},
  "geometry": {"coordinates":[9.273014,45.584007],"type":"Point"}
}