{
  "type": "Feature",
  "properties": {
    "addr:full":"Via Lomellina 880 27036 Mortara Mortara Pavia 27036",
    "addr:housenumber":"880",
    "addr:postcode":"27036;27036",
    "addr:street":"Via Lomellina",
    "iso:country":"IT",
    "sg:address":"Via Lomellina 880 27036 Mortara",
    "sg:city":"Mortara",
    "sg:classifiers":[
        {
            "category":"Banks & Credit Unions",
            "subcategory":"Investment Brokerage",
            "type":"Services"
        }
    ],
    "sg:phone":"+39 0384 98172",
    "sg:postcode":"27036",
    "sg:province":"Pavia",
    "sg:tags":[
        "interior",
        "automotive"
    ],
    "sg:website":"www.safftappeti.it",
    "wof:name":"Orsa Automotive Srl",
    "wof:placetype":"venue"
},
  "geometry": {"coordinates":[8.746616,45.241417],"type":"Point"}
}