{
  "type": "Feature",
  "properties": {
    "iso:country":"IT",
    "sg:address":"95131 Catania",
    "sg:city":"Catania",
    "sg:orig_category":"Forniture Per Uffici",
    "sg:phone":"+39 095 533010",
    "sg:postcode":"95131",
    "sg:province":"Catania",
    "wof:name":"Nocita Alessandro",
    "wof:placetype":"venue"
},
  "geometry": {"coordinates":[15.0927629471,37.5096054077],"type":"Point"}
}