{
  "type": "Feature",
  "properties": {
    "iso:country":"IT",
    "sg:address":"24050 Grassobbio",
    "sg:city":"Grassobbio",
    "sg:orig_category":"Forniture Per Edilizia E Lavori Pubblici",
    "sg:phone":"+39 035 335180",
    "sg:postcode":"24050",
    "sg:province":"Bergamo",
    "wof:name":"Cuprum Italia Srl",
    "wof:placetype":"venue"
},
  "geometry": {"coordinates":[9.7267217636,45.6578140259],"type":"Point"}
}