{
  "type": "Feature",
  "properties": {
    "iso:country":"IT",
    "sg:address":"6, Via Voitsberg 39040 Varna",
    "sg:city":"Varna",
    "sg:classifiers":[
        {
            "category":"Shopping",
            "subcategory":"Clothing, Apparel, & Fashions",
            "type":"Retail Goods"
        }
    ],
    "sg:phone":"+39 0472 832523",
    "sg:postcode":"39040",
    "sg:province":"Bolzano/Bozen",
    "sg:tags":[
        "clothes"
    ],
    "wof:name":"Navayo (s.r.l.)",
    "wof:placetype":"venue"
},
  "geometry": {"coordinates":[11.636098,46.741199],"type":"Point"}
}