{
  "type": "Feature",
  "properties": {
    "iso:country":"IT",
    "sg:address":"50053 Empoli",
    "sg:city":"Empoli",
    "sg:orig_category":"Ospedali E Servizi Sanitari. Servizi Ausiliari Di Analisi, Controllo E Ricerca",
    "sg:phone":"+39 0571 537064",
    "sg:postcode":"50053",
    "sg:province":"Firenze",
    "wof:name":"Biochem Snc",
    "wof:placetype":"venue"
},
  "geometry": {"coordinates":[11.26698,43.766815],"type":"Point"}
}