{
  "type": "Feature",
  "properties": {
    "addr:full":"00136 Roma Roma Roma 00136",
    "addr:postcode":"00136;00136",
    "iso:country":"IT",
    "sg:address":"00136 Roma",
    "sg:city":"Roma",
    "sg:orig_category":"Carte Geografiche, Topografiche E Nautiche",
    "sg:phone":"+39 06 3549 7051",
    "sg:postcode":"00136",
    "sg:province":"Roma",
    "wof:name":"Lozzi Roma Sas",
    "wof:placetype":"venue"
},
  "geometry": {"coordinates":[12.440924,41.91993],"type":"Point"}
}