{
  "type": "Feature",
  "properties": {
    "iso:country":"IT",
    "sg:address":"00151 Roma",
    "sg:city":"Roma",
    "sg:orig_category":"Caldaie Riscaldamento",
    "sg:phone":"+39 06 532821",
    "sg:postcode":"00151",
    "sg:province":"Roma",
    "wof:name":"175a De Angelis",
    "wof:placetype":"venue"
},
  "geometry": {"coordinates":[12.443309,41.871094],"type":"Point"}
}