{
  "type": "Feature",
  "properties": {
    "iso:country":"IT",
    "sg:address":"55100 Lucca",
    "sg:city":"Lucca",
    "sg:orig_category":"Agenzie D'affari E Servizi Commerciali",
    "sg:phone":"+39 0583 440523",
    "sg:postcode":"55100",
    "sg:province":"Lucca",
    "wof:name":"Callori Di Vignale Giovanni",
    "wof:placetype":"venue"
},
  "geometry": {"coordinates":[10.522768,43.848587],"type":"Point"}
}