{
  "type": "Feature",
  "properties": {
    "iso:country":"IT",
    "sg:address":"24050 Orio Al Serio",
    "sg:city":"Orio al Serio",
    "sg:orig_category":"Pubblica Amministrazione",
    "sg:phone":"+39 035 314405",
    "sg:postcode":"24050",
    "sg:province":"Bergamo",
    "wof:name":"Polizia",
    "wof:placetype":"venue"
},
  "geometry": {"coordinates":[9.7004671097,45.6681556702],"type":"Point"}
}