{
  "type": "Feature",
  "properties": {
    "addr:full":"31, V. Stezzano 24050 Zanica Zanica Bergamo 24050",
    "addr:housenumber":"31",
    "addr:postcode":"24050;24050",
    "addr:street":"V. Stezzano",
    "iso:country":"IT",
    "sg:address":"31, V. Stezzano 24050 Zanica",
    "sg:city":"Zanica",
    "sg:classifiers":[
        {
            "category":"Professional",
            "subcategory":"Engineering",
            "type":"Services"
        }
    ],
    "sg:phone":"+39 39035671191",
    "sg:postcode":"24050",
    "sg:province":"Bergamo",
    "sg:tags":[
        "machine",
        "-",
        "mechanical"
    ],
    "sg:website":"http://www.cmaasnc.it",
    "wof:name":"Cmaa Srl",
    "wof:placetype":"venue"
},
  "geometry": {"coordinates":[9.673186,45.643097],"type":"Point"}
}