{
  "type": "Feature",
  "properties": {
    "addr:full":"Via Accoppe' Fratte 11 30035 Mirano Mirano Venezia 30035",
    "addr:housenumber":"11",
    "addr:postcode":"30035;30035",
    "addr:street":"Via Accoppe ' Fratte",
    "iso:country":"IT",
    "sg:address":"Via Accoppe' Fratte 11 30035 Mirano",
    "sg:city":"Mirano",
    "sg:classifiers":[
        {
            "category":"Shopping",
            "subcategory":"Clothing, Apparel, & Fashions",
            "type":"Retail Goods"
        }
    ],
    "sg:phone":"+39 041 572 8892",
    "sg:postcode":"30035",
    "sg:province":"Venezia",
    "sg:tags":[
        "blouse",
        "ladies'",
        "dress"
    ],
    "wof:name":"Immagine S.r.l.",
    "wof:placetype":"venue"
},
  "geometry": {"coordinates":[12.338784,45.434338],"type":"Point"}
}