{
  "type": "Feature",
  "properties": {
    "iso:country":"IT",
    "sg:address":"Via Bosco Ii 84091 Battipaglia",
    "sg:city":"Battipaglia",
    "sg:classifiers":[
        {
            "category":"Banks & Credit Unions",
            "subcategory":"Investment Brokerage",
            "type":"Services"
        }
    ],
    "sg:phone":"+39 0828 304360",
    "sg:postcode":"84091",
    "sg:province":"Salerno",
    "sg:tags":[
        "packaging",
        "manufactured",
        "packagings",
        "good",
        "industrial"
    ],
    "sg:website":"www.deriblok.it",
    "wof:name":"Deriblok S.r.l.",
    "wof:placetype":"venue"
},
  "geometry": {"coordinates":[14.765912,40.677956],"type":"Point"}
}