{
  "type": "Feature",
  "properties": {
    "addr:full":"Via Enrico Fermi 10 20050 Macherio Macherio Milano 20050",
    "addr:housenumber":"10",
    "addr:postcode":"20050;20050",
    "addr:street":"Via Enrico Fermi",
    "iso:country":"IT",
    "sg:address":"Via Enrico Fermi 10 20050 Macherio",
    "sg:city":"Macherio",
    "sg:classifiers":[
        {
            "category":"Autos & Motor Vehicles",
            "subcategory":"Boat Sales",
            "type":"Retail Goods"
        }
    ],
    "sg:phone":"+39 039 201 3066",
    "sg:postcode":"20050",
    "sg:province":"Milano",
    "sg:tags":[
        "dyeing",
        "machine",
        "equipment"
    ],
    "wof:name":"Master Sas",
    "wof:placetype":"venue"
},
  "geometry": {"coordinates":[9.258492,45.638767],"type":"Point"}
}