{
  "type": "Feature",
  "properties": {
    "addr:full":"23801 Calolziocorte Calolziocorte Lecco 23801",
    "addr:postcode":"23801;23801",
    "iso:country":"IT",
    "sg:address":"23801 Calolziocorte",
    "sg:city":"Calolziocorte",
    "sg:orig_category":"Prodotti E Manufatti In Materie Plastiche. Articoli Per Imballaggio E Confezionamento",
    "sg:phone":"+39 0341 633078",
    "sg:postcode":"23801",
    "sg:province":"Lecco",
    "wof:name":"Plasticlario Snc Di Moro Maria & C.",
    "wof:placetype":"venue"
},
  "geometry": {"coordinates":[9.4175262451,45.8029632568],"type":"Point"}
}