{
  "type": "Feature",
  "properties": {
    "addr:full":"74016 Massafra Massafra Taranto 74016",
    "addr:postcode":"74016;74016",
    "iso:country":"IT",
    "sg:address":"74016 Massafra",
    "sg:city":"Massafra",
    "sg:orig_category":"Cine-foto-ottica",
    "sg:phone":"+39 099 880 5150",
    "sg:postcode":"74016",
    "sg:province":"Taranto",
    "wof:name":"Oliva Marcello Fotocolor Liuzzi",
    "wof:placetype":"venue"
},
  "geometry": {"coordinates":[17.11454,40.584888],"type":"Point"}
}