{
  "type": "Feature",
  "properties": {
    "iso:country":"IT",
    "sg:address":"10143 Torino",
    "sg:city":"Torino",
    "sg:orig_category":"Scuole Di Ballo E Danza Classica E Moderna",
    "sg:phone":"+39 011 437 5686",
    "sg:postcode":"10143",
    "sg:province":"Torino",
    "sg:website":"http://www.scuolamontessori.it",
    "wof:name":"Scuola Montessori Srl",
    "wof:placetype":"venue"
},
  "geometry": {"coordinates":[7.659177,45.079277],"type":"Point"}
}