{
  "type": "Feature",
  "properties": {
    "iso:country":"IT",
    "sg:address":"20021 Baranzate",
    "sg:city":"Baranzate",
    "sg:orig_category":"Materiali E Componenti Elettronici",
    "sg:phone":"+39 02 3820 1461",
    "sg:postcode":"20021",
    "sg:province":"Milano",
    "wof:name":"Nowel S.r.l.",
    "wof:placetype":"venue"
},
  "geometry": {"coordinates":[9.117011,45.52739],"type":"Point"}
}