{
  "type": "Feature",
  "properties": {
    "addr:full":"33100 Udine Udine Udine 33100",
    "addr:postcode":"33100;33100",
    "iso:country":"IT",
    "sg:address":"33100 Udine",
    "sg:city":"Udine",
    "sg:orig_category":"Cartotecnica E Servizi. Composizione, Stampa E Confezione. Forniture E Prodotti Informatici. Forniture Per Congressi, Fiere E Manifestazioni",
    "sg:phone":"+39 0432 229882",
    "sg:postcode":"33100",
    "sg:province":"Udine",
    "wof:name":"Paytron S.p.a.",
    "wof:placetype":"venue"
},
  "geometry": {"coordinates":[13.234128,46.069042],"type":"Point"}
}