{
  "type": "Feature",
  "properties": {
    "iso:country":"IT",
    "sg:address":"30175 Venezia",
    "sg:city":"Venezia",
    "sg:orig_category":"Servizi E Lavori Per Ecologia E Smaltimento Rifiuti",
    "sg:phone":"+39 041 920622",
    "sg:postcode":"30175",
    "sg:province":"Venezia",
    "sg:website":"http://www.paginegialle.it/sangiustoi",
    "wof:name":"Cooperativa S. Giusto Rinascita Soc.coop.r.l.",
    "wof:placetype":"venue"
},
  "geometry": {"coordinates":[12.21224,45.45187],"type":"Point"}
}