{
  "type": "Feature",
  "properties": {
    "addr:full":"03013 Ferentino Ferentino Frosinone 03013",
    "addr:postcode":"03013;03013",
    "iso:country":"IT",
    "sg:address":"03013 Ferentino",
    "sg:city":"Ferentino",
    "sg:orig_category":"Antenne Radio-televisione",
    "sg:phone":"+39 0775 397024",
    "sg:postcode":"03013",
    "sg:province":"Frosinone",
    "wof:name":"Eavc Di Concutelli Giancarlo",
    "wof:placetype":"venue"
},
  "geometry": {"coordinates":[13.319136,41.657337],"type":"Point"}
}