{
  "type": "Feature",
  "properties": {
    "iso:country":"IT",
    "sg:address":"70126 Bari",
    "sg:city":"Bari",
    "sg:orig_category":"Automobili E Mezzi Di Trasporto",
    "sg:phone":"+39 080 548 2410",
    "sg:postcode":"70126",
    "sg:province":"Bari",
    "wof:name":"Mazzoni Pietro Spa",
    "wof:placetype":"venue"
},
  "geometry": {"coordinates":[16.90365,41.08189],"type":"Point"}
}