{
  "type": "Feature",
  "properties": {
    "iso:country":"IT",
    "sg:address":"35127 Padova",
    "sg:city":"Padova",
    "sg:orig_category":"Informatica - Consulenza E Servizi. Pubblicita', Marketing E Comunicazione",
    "sg:phone":"+39 049 806 1213",
    "sg:postcode":"35127",
    "sg:province":"Padova",
    "sg:website":"http://www.saifo.it",
    "wof:name":"Saifo Srl",
    "wof:placetype":"venue"
},
  "geometry": {"coordinates":[11.928375,45.388134],"type":"Point"}
}