{
  "type": "Feature",
  "properties": {
    "iso:country":"IT",
    "sg:address":"55041 Camaiore",
    "sg:city":"Camaiore",
    "sg:orig_category":"Agenzie D'affari E Servizi Commerciali",
    "sg:phone":"+39 0584 969657",
    "sg:postcode":"55041",
    "sg:province":"Lucca",
    "wof:name":"Matilda Srl",
    "wof:placetype":"venue"
},
  "geometry": {"coordinates":[10.358208,43.860233],"type":"Point"}
}