{
  "type": "Feature",
  "properties": {
    "iso:country":"IT",
    "sg:address":"10132 Torino",
    "sg:city":"Torino",
    "sg:orig_category":"Fotografia Apparecchi E Materiali - Produzione E Ingrosso",
    "sg:phone":"+39 011 81441",
    "sg:postcode":"10132",
    "sg:province":"Torino",
    "wof:name":"Fowa Spa",
    "wof:placetype":"venue"
},
  "geometry": {"coordinates":[7.7218904495,45.0668373108],"type":"Point"}
}