{
  "type": "Feature",
  "properties": {
    "addr:full":"74020 Leporano Leporano Taranto 74020",
    "addr:postcode":"74020;74020",
    "addr:street":"Leporano Leporano Taranto",
    "iso:country":"IT",
    "sg:address":"74020 Leporano",
    "sg:city":"Leporano",
    "sg:orig_category":"Manufacturers: Prefabbricati",
    "sg:phone":"+39 099 531 5436",
    "sg:postcode":"74020",
    "sg:province":"Taranto",
    "wof:name":"F.lli Frascella",
    "wof:placetype":"venue"
},
  "geometry": {"coordinates":[17.334181,40.383007],"type":"Point"}
}