{
  "type": "Feature",
  "properties": {
    "iso:country":"IT",
    "sg:address":"145, V. Brandizzo 10088 Volpiano",
    "sg:city":"Volpiano",
    "sg:classifiers":[
        {
            "category":"Shopping",
            "type":"Retail Goods"
        }
    ],
    "sg:phone":"+39 011 995 1514",
    "sg:postcode":"10088",
    "sg:province":"Torino",
    "sg:tags":[
        "finished",
        "-",
        "metallic"
    ],
    "sg:website":"http://www.isap.it",
    "wof:name":"Isap Srl - Taube",
    "wof:placetype":"venue"
},
  "geometry": {"coordinates":[7.8302564621,45.1729545593],"type":"Point"}
}