{
  "type": "Feature",
  "properties": {
    "iso:country":"IT",
    "sg:address":"40, V. Dossi 25050 Pian Camuno",
    "sg:city":"Pian Camuno",
    "sg:classifiers":[
        {
            "category":"Shopping",
            "type":"Retail Goods"
        }
    ],
    "sg:phone":"+39 036 459 8985",
    "sg:postcode":"25050",
    "sg:province":"Brescia",
    "sg:tags":[
        "finished",
        "-",
        "metallic"
    ],
    "sg:website":"http://www.camfart.it",
    "wof:name":"Camfart Srl",
    "wof:placetype":"venue"
},
  "geometry": {"coordinates":[10.135269165,45.8389778137],"type":"Point"}
}