{
  "type": "Feature",
  "properties": {
    "addr:full":"50142 Firenze Firenze Firenze 50142",
    "addr:postcode":"50142;50142",
    "iso:country":"IT",
    "sg:address":"50142 Firenze",
    "sg:city":"Firenze",
    "sg:orig_category":"Arredo Cucina Ed Elettrodomestici. Elettrodomestici",
    "sg:phone":"+39 055 732 4652",
    "sg:postcode":"50142",
    "sg:province":"Firenze",
    "wof:name":"Fiordelmondo Roberto",
    "wof:placetype":"venue"
},
  "geometry": {"coordinates":[11.195197,43.769115],"type":"Point"}
}