{
  "type": "Feature",
  "properties": {
    "addr:full":"V F Cavallotti 21; Montichiari; 25018 Montichiari Brescia 25018",
    "addr:housenumber":"21",
    "addr:postcode":"25018;25018",
    "addr:street":"V F Cavallotti",
    "iso:country":"IT",
    "sg:address":"V F Cavallotti 21; Montichiari; 25018",
    "sg:city":"Montichiari",
    "sg:classifiers":[
        {
            "category":"Banks & Credit Unions",
            "subcategory":"Bank",
            "type":"Services"
        }
    ],
    "sg:phone":"+39 030 964884",
    "sg:postcode":"25018",
    "sg:province":"Brescia",
    "wof:name":"Credito Agrario Bresciano",
    "wof:placetype":"venue"
},
  "geometry": {"coordinates":[10.392487,45.414467],"type":"Point"}
}