{
  "type": "Feature",
  "properties": {
    "addr:full":"21042 Caronno Pertusella Caronno Pertusella Varese 21042",
    "addr:postcode":"21042;pertusella;21042",
    "addr:street":"Pertusella",
    "iso:country":"IT",
    "sg:address":"21042 Caronno Pertusella",
    "sg:city":"Caronno Pertusella",
    "sg:orig_category":"Trattamenti Termici E Superficiali Metalli, Galvanotecnica",
    "sg:phone":"+39 02 965 9394",
    "sg:postcode":"21042",
    "sg:province":"Varese",
    "wof:name":"Ds Di Diaco E Spinelli Snc",
    "wof:placetype":"venue"
},
  "geometry": {"coordinates":[9.046051,45.610065],"type":"Point"}
}