{
  "type": "Feature",
  "properties": {
    "iso:country":"IT",
    "sg:address":"24042 Capriate San Gervasio",
    "sg:city":"Capriate San Gervasio",
    "sg:orig_category":"Fibre Ottiche",
    "sg:phone":"+39 02 9096 3287",
    "sg:postcode":"24042",
    "sg:province":"Bergamo",
    "wof:name":"Lightech Srl",
    "wof:placetype":"venue"
},
  "geometry": {"coordinates":[9.5394773483,45.6101112366],"type":"Point"}
}