{
  "type": "Feature",
  "properties": {
    "iso:country":"IT",
    "sg:address":"22100 Como",
    "sg:city":"Como",
    "sg:orig_category":"Servizi E Lavori Per Abbigliamento E Pelletterie",
    "sg:phone":"+39 031 591237",
    "sg:postcode":"22100",
    "sg:province":"Como",
    "wof:name":"Butti Renato",
    "wof:placetype":"venue"
},
  "geometry": {"coordinates":[8.998615,45.803604],"type":"Point"}
}