{
  "type": "Feature",
  "properties": {
    "iso:country":"IT",
    "sg:address":"Via Guido D'arezzo 19 20145 Milano",
    "sg:city":"Milano",
    "sg:classifiers":[
        {
            "category":"Real Estate",
            "subcategory":"Architect",
            "type":"Services"
        }
    ],
    "sg:phone":"+39 02 498 1395",
    "sg:postcode":"20145",
    "sg:province":"Milano",
    "sg:tags":[
        "men's",
        "shirts",
        "shirt"
    ],
    "wof:name":"Marchall Di Rubin Claudio",
    "wof:placetype":"venue"
},
  "geometry": {"coordinates":[9.161366,45.468315],"type":"Point"}
}