{
  "type": "Feature",
  "properties": {
    "iso:country":"IT",
    "sg:address":"90020 Roccapalumba",
    "sg:city":"Roccapalumba",
    "sg:orig_category":"Pubblica Amministrazione",
    "sg:phone":"+39 091 825 7133",
    "sg:postcode":"90020",
    "sg:province":"Palermo",
    "wof:name":"Carabinieri",
    "wof:placetype":"venue"
},
  "geometry": {"coordinates":[13.6391706467,37.8059463501],"type":"Point"}
}