{
  "type": "Feature",
  "properties": {
    "iso:country":"IT",
    "sg:address":"00177 Roma",
    "sg:city":"Roma",
    "sg:orig_category":"Servizi Ausiliari Di Certificati, Riproduzioni, Disegni E Foto",
    "sg:phone":"+39 06 2780 0054",
    "sg:postcode":"00177",
    "sg:province":"Roma",
    "wof:name":"Fotostudio Leandro Ricci",
    "wof:placetype":"venue"
},
  "geometry": {"coordinates":[12.549688,41.894863],"type":"Point"}
}