{
  "type": "Feature",
  "properties": {
    "addr:full":"20142 Milano Milano Milano 20142",
    "addr:postcode":"20142;20142",
    "iso:country":"IT",
    "sg:address":"20142 Milano",
    "sg:city":"Milano",
    "sg:orig_category":"Studi E Consulenze Amministrative, Commerciali E Aziendali. Consulenze Tecniche, Amministrative E Perizie",
    "sg:phone":"+39 02 8950 6269",
    "sg:postcode":"20142",
    "sg:province":"Milano",
    "sg:website":"http://www.ciamformazione.it",
    "wof:name":"Centro Informatico Addestramento Multimediale",
    "wof:placetype":"venue"
},
  "geometry": {"coordinates":[9.171266,45.441936],"type":"Point"}
}