{
  "type": "Feature",
  "properties": {
    "iso:country":"IT",
    "sg:address":"37126 Verona",
    "sg:city":"Verona",
    "sg:classifiers":[
        {
            "category":"Health Services",
            "subcategory":"Health Practitioner",
            "type":"Services"
        }
    ],
    "sg:phone":"+39 045 835 2342",
    "sg:postcode":"37126",
    "sg:province":"Verona",
    "sg:tags":[
        "medici"
    ],
    "wof:name":"Bucci Stefano",
    "wof:placetype":"venue"
},
  "geometry": {"coordinates":[10.888469,45.347473],"type":"Point"}
}