{
  "type": "Feature",
  "properties": {
    "iso:country":"IT",
    "sg:address":"Viale Roma 65/67; Castelvetrano; 91022",
    "sg:city":"Castelvetrano",
    "sg:classifiers":[
        {
            "category":"Banks & Credit Unions",
            "subcategory":"Bank",
            "type":"Services"
        }
    ],
    "sg:phone":"+39 0924 906092",
    "sg:postcode":"91022",
    "sg:province":"Trapani",
    "wof:name":"Credito Emiliano Spa",
    "wof:placetype":"venue"
},
  "geometry": {"coordinates":[12.797087,37.685986],"type":"Point"}
}