{
  "type": "Feature",
  "properties": {
    "addr:full":"12120 Cuneo CN",
    "addr:postcode":"12120",
    "iso:country":"IT",
    "sg:address":"12120 Cuneo",
    "sg:orig_category":"Biciclette - Produzione E Ingrosso",
    "sg:phone":"+39 0171 689030",
    "sg:province":"CN",
    "wof:name":"Lucchino Biciclette Snc Dei F.lli Danilo E Roberto",
    "wof:placetype":"venue"
},
  "geometry": {"coordinates":[7.52921,44.444988],"type":"Point"}
}