{
  "type": "Feature",
  "properties": {
    "addr:full":"64100 Teramo Teramo Teramo 64100",
    "addr:postcode":"64100;64100",
    "iso:country":"IT",
    "sg:address":"64100 Teramo",
    "sg:city":"Teramo",
    "sg:orig_category":"Arredamenti - Produzione E Ingrosso",
    "sg:phone":"+39 0861 587344",
    "sg:postcode":"64100",
    "sg:province":"Teramo",
    "sg:website":"http://www.abf.it",
    "wof:name":"Barnabei Alfiero & C. Snc",
    "wof:placetype":"venue"
},
  "geometry": {"coordinates":[13.70575,42.677277],"type":"Point"}
}