{
  "type": "Feature",
  "properties": {
    "iso:country":"IT",
    "sg:address":"Piazza Cavour 17a; Foggia; 71100",
    "sg:city":"Foggia",
    "sg:classifiers":[
        {
            "category":"Banks & Credit Unions",
            "subcategory":"Bank",
            "type":"Services"
        }
    ],
    "sg:phone":"+39 0881 25654",
    "sg:postcode":"71100",
    "sg:province":"Foggia",
    "wof:name":"Banco Di Santo Spirito",
    "wof:placetype":"venue"
},
  "geometry": {"coordinates":[15.552787,41.462387],"type":"Point"}
}