{
  "type": "Feature",
  "properties": {
    "iso:country":"IT",
    "sg:address":"08020 Lula",
    "sg:city":"Lula",
    "sg:orig_category":"Alluminio E Leghe",
    "sg:phone":"+39 0784 416710",
    "sg:postcode":"08020",
    "sg:province":"Nuoro",
    "wof:name":"F.lli Sanguinetti Snc Di Sanguinetti Giovanni & Graziano",
    "wof:placetype":"venue"
},
  "geometry": {"coordinates":[9.485869,40.469986],"type":"Point"}
}