{
  "type": "Feature",
  "properties": {
    "addr:full":"10138 Torino Torino Torino 10138",
    "addr:housenumber":"10138",
    "addr:postcode":"10138",
    "iso:country":"IT",
    "sg:address":"10138 Torino",
    "sg:city":"Torino",
    "sg:orig_category":"Armadi Guardaroba",
    "sg:phone":"+39 011 434 0585",
    "sg:postcode":"10138",
    "sg:province":"Torino",
    "wof:name":"Domus Nova",
    "wof:placetype":"venue"
},
  "geometry": {"coordinates":[7.567663,45.063061],"type":"Point"}
}