{
  "type": "Feature",
  "properties": {
    "iso:country":"IT",
    "sg:address":"50053 Empoli",
    "sg:city":"Empoli",
    "sg:orig_category":"Bevande, Vini E Liquori",
    "sg:phone":"+39 0571 592683",
    "sg:postcode":"50053",
    "sg:province":"Firenze",
    "wof:name":"Martini Silvano Sas",
    "wof:placetype":"venue"
},
  "geometry": {"coordinates":[10.970949,43.719498],"type":"Point"}
}