{
  "type": "Feature",
  "properties": {
    "iso:country":"IT",
    "sg:address":"73100 Lecce",
    "sg:city":"Lecce",
    "sg:classifiers":[
        {
            "category":"Shopping",
            "subcategory":"Clothing, Apparel, & Fashions",
            "type":"Retail Goods"
        }
    ],
    "sg:phone":"+39 0832 349228",
    "sg:postcode":"73100",
    "sg:province":"Lecce",
    "sg:tags":[
        "activities",
        "goods",
        "supply",
        "leather",
        "commercial",
        "artisan",
        "supplies",
        "clothing"
    ],
    "wof:name":"Studiopack Srl",
    "wof:placetype":"venue"
},
  "geometry": {"coordinates":[18.178135,40.349041],"type":"Point"}
}