{
  "type": "Feature",
  "properties": {
    "iso:country":"IT",
    "sg:address":"16124 Genova",
    "sg:city":"Genova",
    "sg:orig_category":"Valvole E Apparecchiature Di Misura",
    "sg:phone":"+39 010 246 5937",
    "sg:postcode":"16124",
    "sg:province":"Genova",
    "wof:name":"Lipari S.n.c. Di De Mattei Sergio E Carlini Riccardo",
    "wof:placetype":"venue"
},
  "geometry": {"coordinates":[8.932124,44.41267],"type":"Point"}
}