{
  "type": "Feature",
  "properties": {
    "addr:full":"83042 Atripalda Atripalda Avellino 83042",
    "addr:postcode":"83042;83042",
    "iso:country":"IT",
    "sg:address":"83042 Atripalda",
    "sg:city":"Atripalda",
    "sg:orig_category":"Ceramiche: Prodotti E Lavorazioni. Forniture Per Attivita' Industriali",
    "sg:phone":"+39 0825 626584",
    "sg:postcode":"83042",
    "sg:province":"Avellino",
    "wof:name":"D.g. 2 Ceramiche Srl",
    "wof:placetype":"venue"
},
  "geometry": {"coordinates":[14.827076,40.915218],"type":"Point"}
}