{
  "type": "Feature",
  "properties": {
    "addr:full":"52047 Marciano Della Chiana Cesa Arezzo 52047",
    "addr:postcode":"52047;52047",
    "iso:country":"IT",
    "sg:address":"52047 Marciano Della Chiana",
    "sg:city":"Cesa",
    "sg:orig_category":"Materassi - Produzione E Ingrosso",
    "sg:phone":"+39 0575 842219",
    "sg:postcode":"52047",
    "sg:province":"Arezzo",
    "sg:website":"http://www.idormibene.it",
    "wof:name":"Idormibene",
    "wof:placetype":"venue"
},
  "geometry": {"coordinates":[11.813806,43.324768],"type":"Point"}
}