{
  "type": "Feature",
  "properties": {
    "addr:full":"60, Via Girardengo Nicolo 15067 Novi Ligure Novi Ligure Alessandria 15067",
    "addr:postcode":"15067;15067",
    "addr:street":"Via Girardengo Nicolo",
    "iso:country":"IT",
    "sg:address":"60, Via Girardengo Nicolo 15067 Novi Ligure",
    "sg:city":"Novi Ligure",
    "sg:classifiers":[
        {
            "category":"Shopping",
            "subcategory":"Crafts & Fabrics",
            "type":"Retail Goods"
        }
    ],
    "sg:phone":"+39 39014378707",
    "sg:postcode":"15067",
    "sg:province":"Alessandria",
    "wof:name":"Manifattura Foderami F.lli Broglia (s.p.a.)",
    "wof:placetype":"venue"
},
  "geometry": {"coordinates":[8.6169509888,44.9132156372],"type":"Point"}
}