{
  "type": "Feature",
  "properties": {
    "iso:country":"IT",
    "sg:address":"Viale Giovanni Xxiii 32a,; Boretto; 42022",
    "sg:classifiers":[
        {
            "category":"Banks & Credit Unions",
            "subcategory":"Bank",
            "type":"Services"
        }
    ],
    "sg:phone":"+39 0522 965321",
    "sg:postcode":"42022",
    "sg:province":"Reggio Nell'Emilia",
    "wof:name":"Credito Emiliano Spa",
    "wof:placetype":"venue"
},
  "geometry": {"coordinates":[10.551849,44.9049],"type":"Point"}
}