{
  "type": "Feature",
  "properties": {
    "addr:full":"04100 Latina Latina Latina 04100",
    "addr:postcode":"04100;04100",
    "iso:country":"IT",
    "sg:address":"04100 Latina",
    "sg:city":"Latina",
    "sg:orig_category":"Arredamento Bar E Ristoranti",
    "sg:phone":"+39 0773 242027",
    "sg:postcode":"04100",
    "sg:province":"Latina",
    "wof:name":"Vescovo Arredamenti Di Vescovo Dante & C. Sas",
    "wof:placetype":"venue"
},
  "geometry": {"coordinates":[13.104555,41.298759],"type":"Point"}
}