{
  "type": "Feature",
  "properties": {
    "iso:country":"IT",
    "sg:address":"6, Via Elio Donato 00136 Roma",
    "sg:city":"Roma",
    "sg:classifiers":[
        {
            "category":"Banks & Credit Unions",
            "subcategory":"Financial Services",
            "type":"Services"
        }
    ],
    "sg:phone":"+39 06 3973 9400",
    "sg:postcode":"00136",
    "sg:province":"Roma",
    "sg:tags":[
        "banking",
        "finance",
        "insurance"
    ],
    "wof:name":"Sofasoft Srl",
    "wof:placetype":"venue"
},
  "geometry": {"coordinates":[12.443275,41.912014],"type":"Point"}
}