{
  "type": "Feature",
  "properties": {
    "iso:country":"IT",
    "sg:address":"Via Mattei 10 20010 Mesero",
    "sg:city":"Mesero",
    "sg:orig_category":"Fabrics, Dyeable And Printable",
    "sg:phone":"+39 02 9728 9808",
    "sg:postcode":"20010",
    "sg:province":"Milano",
    "sg:website":"www.tatsrl.it",
    "wof:name":"Tat Srl",
    "wof:placetype":"venue"
},
  "geometry": {"coordinates":[8.8605184555,45.4912490845],"type":"Point"}
}