{
  "type": "Feature",
  "properties": {
    "addr:full":"21052 Busto Arsizio Busto Arsizio Varese 21052",
    "addr:postcode":"21052;21052",
    "iso:country":"IT",
    "sg:address":"21052 Busto Arsizio",
    "sg:city":"Busto Arsizio",
    "sg:orig_category":"Prodotti E Manufatti In Gomma. Servizi E Lavori Industria Della Gomma. Ricambi E Componenti Dei Mezzi Di Trasporto. Riparazione Dei Mezzi Di Trasporto",
    "sg:phone":"+39 0331 684463",
    "sg:postcode":"21052",
    "sg:province":"Varese",
    "sg:website":"http://www.steel-net.it/bustogomme",
    "wof:name":"Busto Gomme Snc",
    "wof:placetype":"venue"
},
  "geometry": {"coordinates":[8.8385820389,45.6140556335],"type":"Point"}
}