{
  "type": "Feature",
  "properties": {
    "iso:country":"IT",
    "sg:address":"2, Via Del Torre Zona Industriale 33047 Remanzacco",
    "sg:city":"Remanzacco",
    "sg:classifiers":[
        {
            "category":"Manufacturing",
            "subcategory":"Metals",
            "type":"Manufacturing & Wholesale Goods"
        }
    ],
    "sg:phone":"+39 0432 668820",
    "sg:postcode":"33047",
    "sg:province":"Udine",
    "sg:tags":[
        "metallurgy",
        "metalworking"
    ],
    "wof:name":"Cividale S.p.a.",
    "wof:placetype":"venue"
},
  "geometry": {"coordinates":[10.441069603,44.8438987732],"type":"Point"}
}