{
  "type": "Feature",
  "properties": {
    "addr:full":"13, Via Larga 40138 Bologna Bologna Bologna 40138",
    "addr:postcode":"40138;40138",
    "addr:street":"Via Larga",
    "iso:country":"IT",
    "sg:address":"13, Via Larga 40138 Bologna",
    "sg:city":"Bologna",
    "sg:orig_category":"Miscellaneous Products",
    "sg:phone":"+39 39051530165",
    "sg:postcode":"40138",
    "sg:province":"Bologna",
    "wof:name":"Pennellificio Omega (s.p.a.)",
    "wof:placetype":"venue"
},
  "geometry": {"coordinates":[11.3946437836,44.499546051],"type":"Point"}
}