{
  "type": "Feature",
  "properties": {
    "iso:country":"IT",
    "sg:address":"00142 Roma",
    "sg:city":"Roma",
    "sg:orig_category":"Prodotti E Manufatti In Gomma",
    "sg:phone":"+39 06 543 0164",
    "sg:postcode":"00142",
    "sg:province":"Roma",
    "wof:name":"Cervoni Sandro",
    "wof:placetype":"venue"
},
  "geometry": {"coordinates":[12.4801721573,41.8446006775],"type":"Point"}
}