{
  "type": "Feature",
  "properties": {
    "iso:country":"IT",
    "sg:address":"61032 Fano",
    "sg:city":"Fano",
    "sg:orig_category":"Centri Di Estetica E Cosmesi E Servizi",
    "sg:phone":"+39 0721 809765",
    "sg:postcode":"61032",
    "sg:province":"Pesaro E Urbino",
    "wof:name":"Giuliani Cinzia",
    "wof:placetype":"venue"
},
  "geometry": {"coordinates":[12.529803,43.633556],"type":"Point"}
}