{
  "type": "Feature",
  "properties": {
    "iso:country":"IT",
    "sg:address":"40012 Calderara Di Reno",
    "sg:city":"Calderara di Reno",
    "sg:orig_category":"Petroli, Gas E Combustibili",
    "sg:phone":"+39 051 414 8511",
    "sg:postcode":"40012",
    "sg:province":"Bologna",
    "wof:name":"Cer Gas Scarl",
    "wof:placetype":"venue"
},
  "geometry": {"coordinates":[11.2654485703,44.5486335754],"type":"Point"}
}