{
  "type": "Feature",
  "properties": {
    "iso:country":"IT",
    "sg:address":"Via Caccianotti, 22; Biandrate; 28061",
    "sg:city":"Biandrate",
    "sg:classifiers":[
        {
            "category":"Banks & Credit Unions",
            "subcategory":"Bank",
            "type":"Services"
        }
    ],
    "sg:phone":"+39 0321 83183",
    "sg:postcode":"28061",
    "sg:province":"Novara",
    "wof:name":"Banca Crt",
    "wof:placetype":"venue"
},
  "geometry": {"coordinates":[8.462482,45.454388],"type":"Point"}
}