{
  "type": "Feature",
  "properties": {
    "addr:full":"87045 Dipignano Dipignano Cosenza 87045",
    "addr:postcode":"87045;87045",
    "iso:country":"IT",
    "sg:address":"87045 Dipignano",
    "sg:city":"Dipignano",
    "sg:orig_category":"Servizi Per Aziende, Manifestazioni E Supporto Agli Scambi Commerciali",
    "sg:phone":"+39 0984 445640",
    "sg:postcode":"87045",
    "sg:province":"Cosenza",
    "wof:name":"Recred Sas Di Francesco Mancuso & C.",
    "wof:placetype":"venue"
},
  "geometry": {"coordinates":[16.244032,39.285217],"type":"Point"}
}