{
  "type": "Feature",
  "properties": {
    "iso:country":"IT",
    "sg:address":"42019 Scandiano",
    "sg:orig_category":"Lavorazioni Meccaniche E Servizi",
    "sg:phone":"+39 0522 989460",
    "sg:postcode":"42019",
    "sg:province":"Reggio Nell'Emilia",
    "wof:name":"C. & G. Di Capelli Paolo & C. Snc",
    "wof:placetype":"venue"
},
  "geometry": {"coordinates":[10.728274,44.625233],"type":"Point"}
}