{
  "type": "Feature",
  "properties": {
    "iso:country":"IT",
    "sg:address":"33100 Udine",
    "sg:city":"Udine",
    "sg:classifiers":[
        {
            "category":"Health Services",
            "subcategory":"Health Practitioner",
            "type":"Services"
        }
    ],
    "sg:phone":"+39 0432 204086",
    "sg:postcode":"33100",
    "sg:province":"Udine",
    "sg:tags":[
        "medici"
    ],
    "wof:name":"Andreoli Sandro",
    "wof:placetype":"venue"
},
  "geometry": {"coordinates":[13.246072,46.068909],"type":"Point"}
}