{
  "type": "Feature",
  "properties": {
    "iso:country":"IT",
    "sg:address":"Via Puccini 73020 Carpignano Salentino",
    "sg:city":"Carpignano Salentino",
    "sg:classifiers":[
        {
            "category":"Wholesale",
            "subcategory":"Drugs",
            "type":"Manufacturing & Wholesale Goods"
        }
    ],
    "sg:phone":"+39 0836 580415",
    "sg:postcode":"73020",
    "sg:province":"Lecce",
    "sg:tags":[
        "chemical",
        "pharmaceutical"
    ],
    "wof:name":"Gamma Sas Di Vanzanelli Antonio Costantino",
    "wof:placetype":"venue"
},
  "geometry": {"coordinates":[18.33613,40.196468],"type":"Point"}
}