{
  "type": "Feature",
  "properties": {
    "iso:country":"IT",
    "sg:address":"59016 Poggio A Caiano",
    "sg:city":"Poggio a Caiano",
    "sg:orig_category":"Macchine, Impianti Ed Attrezzature Per Abbigliamento E Pelletterie",
    "sg:phone":"+39 055 879 8451",
    "sg:postcode":"59016",
    "sg:province":"Prato",
    "wof:name":"Malevolti Giuliano Di Malevolti Leonardo",
    "wof:placetype":"venue"
},
  "geometry": {"coordinates":[11.036278,43.813015],"type":"Point"}
}