{
  "type": "Feature",
  "properties": {
    "iso:country":"IT",
    "sg:address":"50013 Campi Bisenzio",
    "sg:city":"Campi Bisenzio",
    "sg:orig_category":"Articoli Regalo - Produzione E Ingrosso",
    "sg:phone":"+39 055 895 3672",
    "sg:postcode":"50013",
    "sg:province":"Firenze",
    "wof:name":"Tropicalia Di Eros Giordano",
    "wof:placetype":"venue"
},
  "geometry": {"coordinates":[11.130652,43.832478],"type":"Point"}
}