{
  "type": "Feature",
  "properties": {
    "addr:full":"20060 Pozzo D'adda Milano 20060",
    "addr:postcode":"20060;20060",
    "iso:country":"IT",
    "sg:address":"20060 Pozzo D'adda",
    "sg:orig_category":"Pannelli Prefabbricati",
    "sg:phone":"+39 02 9096 7273",
    "sg:postcode":"20060",
    "sg:province":"Milano",
    "wof:name":"Cipriani Lorenzo Lo.ve",
    "wof:placetype":"venue"
},
  "geometry": {"coordinates":[9.5551986694,45.6056251526],"type":"Point"}
}