{
  "type": "Feature",
  "properties": {
    "addr:full":"Via Corcolle; Roma",
    "addr:street":"Via Corcolle",
    "iso:country":"IT",
    "sg:address":"Via Corcolle; Roma",
    "sg:classifiers":[
        {
            "category":"Banks & Credit Unions",
            "subcategory":"Bank",
            "type":"Services"
        }
    ],
    "sg:phone":"+39 06 4079 6286",
    "wof:name":"Banca Di Roma",
    "wof:placetype":"venue"
},
  "geometry": {"coordinates":[12.620841,41.932693],"type":"Point"}
}