{
  "type": "Feature",
  "properties": {
    "iso:country":"IT",
    "sg:address":"52028 Terranuova Bracciolini",
    "sg:city":"Penna",
    "sg:orig_category":"Macchine, Impianti Ed Attrezzature Industria Delle Materie Plastiche E Gomma",
    "sg:phone":"+39 055 970 5207",
    "sg:postcode":"52028",
    "sg:province":"Arezzo",
    "sg:website":"http://www.val.it",
    "wof:name":"O.m.v. Di Vieri Enzo",
    "wof:placetype":"venue"
},
  "geometry": {"coordinates":[11.593027,43.563049],"type":"Point"}
}