{
  "type": "Feature",
  "properties": {
    "iso:country":"IT",
    "sg:address":"20021 Bollate",
    "sg:city":"Bollate",
    "sg:orig_category":"Sport - Articoli E Forniture",
    "sg:phone":"+39 02 350 3276",
    "sg:postcode":"20021",
    "sg:province":"Milano",
    "wof:name":"Pierangeli Luciano",
    "wof:placetype":"venue"
},
  "geometry": {"coordinates":[9.110592,45.539589],"type":"Point"}
}