{
  "type": "Feature",
  "properties": {
    "iso:country":"IT",
    "sg:address":"30030 Martellago",
    "sg:city":"Martellago",
    "sg:classifiers":[
        {
            "category":"Manufacturing",
            "subcategory":"Glass & Minerals",
            "type":"Manufacturing & Wholesale Goods"
        }
    ],
    "sg:phone":"+39 041 540 1188",
    "sg:postcode":"30030",
    "sg:province":"Venezia",
    "sg:tags":[
        "decorative",
        "product",
        "processing",
        "furnishings",
        "objects"
    ],
    "sg:website":"http://www.muranopoint.com",
    "wof:name":"Murano Point Sas",
    "wof:placetype":"venue"
},
  "geometry": {"coordinates":[12.1487579346,45.5480270386],"type":"Point"}
}