{
  "type": "Feature",
  "properties": {
    "iso:country":"IT",
    "sg:address":"20026 Novate Milanese",
    "sg:city":"Novate Milanese",
    "sg:orig_category":"Articoli Per Imballaggio E Confezionamento",
    "sg:phone":"+39 02 356 6488",
    "sg:postcode":"20026",
    "sg:province":"Milano",
    "wof:name":"Pistillo & C. (s.a.s.)",
    "wof:placetype":"venue"
},
  "geometry": {"coordinates":[9.12613,45.527172],"type":"Point"}
}