{
  "type": "Feature",
  "properties": {
    "addr:full":"20092 Cinisello Balsamo Cinisello Balsamo Milano 20092",
    "addr:postcode":"20092;20092",
    "iso:country":"IT",
    "sg:address":"20092 Cinisello Balsamo",
    "sg:city":"Cinisello Balsamo",
    "sg:orig_category":"Lavorazioni Metalli, Stampaggio E Saldatura",
    "sg:phone":"+39 02 618 4521",
    "sg:postcode":"20092",
    "sg:province":"Milano",
    "wof:name":"Tornilastra (s.r.l.)",
    "wof:placetype":"venue"
},
  "geometry": {"coordinates":[9.200261,45.554745],"type":"Point"}
}