{
  "type": "Feature",
  "properties": {
    "iso:country":"IT",
    "sg:address":"Strada Cipata 79 46038 Frassino Mantovano",
    "sg:classifiers":[
        {
            "category":"Manufacturing",
            "subcategory":"Petroleum Products",
            "type":"Manufacturing & Wholesale Goods"
        }
    ],
    "sg:phone":"+39 0376 3781",
    "sg:province":"MN",
    "sg:tags":[
        "plant",
        "refining"
    ],
    "sg:website":"www.iesitaliana.com",
    "wof:name":"Ies Spa",
    "wof:placetype":"venue"
},
  "geometry": {"coordinates":[10.7753610611,45.1667709351],"type":"Point"}
}