{
  "type": "Feature",
  "properties": {
    "iso:country":"IT",
    "sg:address":"3, Via Del Melocotogno 70014 Conversano",
    "sg:city":"Conversano",
    "sg:classifiers":[
        {
            "category":"Food & Beverages",
            "subcategory":"Groceries & Convenience Stores",
            "type":"Retail Goods"
        }
    ],
    "sg:phone":"+39 080 495 4605",
    "sg:postcode":"70014",
    "sg:province":"Bari",
    "sg:tags":[
        "product",
        "related"
    ],
    "wof:name":"Di Palma Donato & Figli (s.n.c.)",
    "wof:placetype":"venue"
},
  "geometry": {"coordinates":[17.1090431213,40.977394104],"type":"Point"}
}