{
  "type": "Feature",
  "properties": {
    "addr:full":"60022 Castelfidardo Castelfidardo Ancona 60022",
    "addr:postcode":"60022;60022",
    "iso:country":"IT",
    "sg:address":"60022 Castelfidardo",
    "sg:city":"Castelfidardo",
    "sg:orig_category":"Argenteria - Lavorazione E Ingrosso",
    "sg:phone":"+39 071 780 8898",
    "sg:postcode":"60022",
    "sg:province":"Ancona",
    "wof:name":"Ri.pa. Srl",
    "wof:placetype":"venue"
},
  "geometry": {"coordinates":[13.537025,43.449814],"type":"Point"}
}