{
  "type": "Feature",
  "properties": {
    "iso:country":"IT",
    "sg:address":"20080 Albairate",
    "sg:city":"Albairate",
    "sg:orig_category":"Ristorazione E Locali Pubblici Affini. Servizi Per Lo Sport E Il Tempo Libero. Alberghi E Strutture Extra Alberghiere. Ristoranti Ed Esercizi Affini",
    "sg:phone":"+39 02 940 6603",
    "sg:postcode":"20080",
    "sg:province":"Milano",
    "sg:website":"http://www.agriturismoriazzolo.com",
    "wof:name":"Agriturismo Cascina Riazzolo",
    "wof:placetype":"venue"
},
  "geometry": {"coordinates":[8.937536,45.418011],"type":"Point"}
}