{
  "type": "Feature",
  "properties": {
    "iso:country":"IT",
    "sg:address":"20124 Milano",
    "sg:city":"Milano",
    "sg:orig_category":"Abbigliamento Esterno, Maglierie E Pelliccerie",
    "sg:phone":"+39 02 2952 6383",
    "sg:postcode":"20124",
    "sg:province":"Milano",
    "wof:name":"Prenatal",
    "wof:placetype":"venue"
},
  "geometry": {"coordinates":[9.208748,45.478111],"type":"Point"}
}