{
  "type": "Feature",
  "properties": {
    "iso:country":"IT",
    "sg:address":"21040 Cislago",
    "sg:city":"Cislago",
    "sg:orig_category":"Gioielleria, Oreficeria E Argenteria",
    "sg:phone":"+39 02 9638 0794",
    "sg:postcode":"21040",
    "sg:province":"Varese",
    "wof:name":"Avogadri Cesare",
    "wof:placetype":"venue"
},
  "geometry": {"coordinates":[8.841767,45.810905],"type":"Point"}
}