{
  "type": "Feature",
  "properties": {
    "iso:country":"IT",
    "sg:address":"Via Gallo, 769 - Borello 47023 Cesena",
    "sg:city":"Borello",
    "sg:classifiers":[
        {
            "category":"Home & Garden",
            "subcategory":"Home Furnishings",
            "type":"Retail Goods"
        }
    ],
    "sg:phone":"+39 0547 372881",
    "sg:postcode":"47023",
    "sg:province":"Forl\u00ec-Cesena",
    "sg:tags":[
        "bathroom",
        "wc",
        "fitting"
    ],
    "sg:website":"www.effegibi.it",
    "wof:name":"Effegibi Srl",
    "wof:placetype":"venue"
},
  "geometry": {"coordinates":[12.18074,44.058998],"type":"Point"}
}