{
  "type": "Feature",
  "properties": {
    "iso:country":"IT",
    "sg:address":"25085 Gavardo",
    "sg:city":"Gavardo",
    "sg:orig_category":"Edilizia - Materiali",
    "sg:phone":"+39 036 537 1012",
    "sg:postcode":"25085",
    "sg:province":"Brescia",
    "sg:website":"http://www.geopietra.com",
    "wof:name":"Abita Snc Di Scalfi & C.",
    "wof:placetype":"venue"
},
  "geometry": {"coordinates":[10.419898,45.589684],"type":"Point"}
}