{
  "type": "Feature",
  "properties": {
    "iso:country":"IT",
    "sg:address":"20123 Milano",
    "sg:city":"Milano",
    "sg:orig_category":"Gioielleria, Oreficeria E Argenteria. Shopping",
    "sg:phone":"+39 02 8699 6378",
    "sg:postcode":"20123",
    "sg:province":"Milano",
    "wof:name":"Nishyda Srl",
    "wof:placetype":"venue"
},
  "geometry": {"coordinates":[9.189801,45.46273],"type":"Point"}
}