{
  "type": "Feature",
  "properties": {
    "addr:full":"8, Via Martiri Liberta' 10076 Nole Nole Torino 10076",
    "addr:postcode":"10076;10076",
    "addr:street":"Via Martiri Liberta '",
    "iso:country":"IT",
    "sg:address":"8, Via Martiri Liberta' 10076 Nole",
    "sg:city":"Nole",
    "sg:classifiers":[
        {
            "category":"Shopping",
            "subcategory":"Crafts & Fabrics",
            "type":"Retail Goods"
        }
    ],
    "sg:phone":"+39 011 926 0606",
    "sg:postcode":"10076",
    "sg:province":"Torino",
    "wof:name":"Manifattura Tessile Di Nole S.p.a.",
    "wof:placetype":"venue"
},
  "geometry": {"coordinates":[7.5421872139,45.258518219],"type":"Point"}
}