{
  "type": "Feature",
  "properties": {
    "addr:full":"Strada Romana Nord 6/a 46027 San Benedetto Po San Benedetto Po Mantova 46027",
    "addr:housenumber":"6 / a",
    "addr:postcode":"46027;46027",
    "addr:street":"Strada;Nord;Po",
    "iso:country":"IT",
    "sg:address":"Strada Romana Nord 6/a 46027 San Benedetto Po",
    "sg:city":"San Benedetto Po",
    "sg:classifiers":[
        {
            "category":"Utilities",
            "subcategory":"Fuel Oil & Lpg",
            "type":"Services"
        }
    ],
    "sg:phone":"+39 0376 623111",
    "sg:postcode":"46027",
    "sg:province":"Mantova",
    "sg:tags":[
        "off-road",
        "accessory"
    ],
    "sg:website":"www.berman.it",
    "wof:name":"Berman Spa",
    "wof:placetype":"venue"
},
  "geometry": {"coordinates":[10.797698,45.160366],"type":"Point"}
}