{
  "type": "Feature",
  "properties": {
    "iso:country":"IT",
    "sg:address":"92026 Favara",
    "sg:city":"Favara",
    "sg:orig_category":"Macchine Ed Impianti Per Edilizia E Lavori Pubblici",
    "sg:phone":"+39 0922 436859",
    "sg:postcode":"92026",
    "sg:province":"Agrigento",
    "wof:name":"Bellavia Carmelo Impresa",
    "wof:placetype":"venue"
},
  "geometry": {"coordinates":[13.671883,37.323143],"type":"Point"}
}