{
  "type": "Feature",
  "properties": {
    "iso:country":"IT",
    "sg:address":"Via Monza 2 22069 Rovellasca",
    "sg:city":"Rovellasca",
    "sg:classifiers":[
        {
            "category":"Shopping",
            "subcategory":"Clothing, Apparel, & Fashions",
            "type":"Retail Goods"
        }
    ],
    "sg:phone":"+39 02 9634 3935",
    "sg:postcode":"22069",
    "sg:province":"Como",
    "sg:tags":[
        "lingerie"
    ],
    "sg:website":"www.nicollingerie.it",
    "wof:name":"Nicol Lingerie Snc Di Alberganti Renzo & C.",
    "wof:placetype":"venue"
},
  "geometry": {"coordinates":[9.0568,45.664639],"type":"Point"}
}