{
  "type": "Feature",
  "properties": {
    "iso:country":"IT",
    "sg:address":"20146 Milano",
    "sg:city":"Milano",
    "sg:orig_category":"Ospedali E Servizi Sanitari",
    "sg:phone":"+39 02 468301",
    "sg:postcode":"20146",
    "sg:province":"Milano",
    "wof:name":"Medicina Riabilitativa (s.r.l.)",
    "wof:placetype":"venue"
},
  "geometry": {"coordinates":[9.150573,45.464809],"type":"Point"}
}