{
  "type": "Feature",
  "properties": {
    "iso:country":"IT",
    "sg:address":"41049 Sassuolo",
    "sg:city":"Sassuolo",
    "sg:orig_category":"Antenne Radio-televisione",
    "sg:phone":"+39 0536 881700",
    "sg:postcode":"41049",
    "sg:province":"Modena",
    "wof:name":"Carrara Emilio",
    "wof:placetype":"venue"
},
  "geometry": {"coordinates":[10.937873,44.62809],"type":"Point"}
}