{
  "type": "Feature",
  "properties": {
    "addr:full":"20147 Milano Milano Milano 20147",
    "addr:postcode":"20147;20147",
    "iso:country":"IT",
    "sg:address":"20147 Milano",
    "sg:city":"Milano",
    "sg:orig_category":"Macchine, Impianti Ed Attrezzature Industria Chimica. Attrezzature E Forniture Per Officine Riparazione E Servizi Ausiliari",
    "sg:phone":"+39 02 418638",
    "sg:postcode":"20147",
    "sg:province":"Milano",
    "wof:name":"Belluzzo Erika",
    "wof:placetype":"venue"
},
  "geometry": {"coordinates":[9.141659,45.451706],"type":"Point"}
}