{
  "type": "Feature",
  "properties": {
    "addr:full":"12, Via Toscana 61020 Sant'angelo In Lizzola Pesaro E Urbino 61020",
    "addr:postcode":"61020;61020",
    "addr:street":"Via Toscana;Lizzola Pesaro E Urbino",
    "iso:country":"IT",
    "sg:address":"12, Via Toscana 61020 Sant'angelo In Lizzola",
    "sg:classifiers":[
        {
            "category":"Professional",
            "subcategory":"Engineering",
            "type":"Services"
        }
    ],
    "sg:phone":"+39 39072149451",
    "sg:postcode":"61020",
    "sg:province":"Pesaro E Urbino",
    "sg:tags":[
        "machine",
        "-",
        "mechanical"
    ],
    "wof:name":"Tecnometal",
    "wof:placetype":"venue"
},
  "geometry": {"coordinates":[12.784623,43.856297],"type":"Point"}
}