{
  "type": "Feature",
  "properties": {
    "iso:country":"IT",
    "sg:address":"20086 Motta Visconti",
    "sg:city":"Motta Visconti",
    "sg:orig_category":"Professionisti - Studi E Servizi Ed Associazioni Di Interesse Aziendale. Associazioni Ed Organismi Di Interesse Pubblico",
    "sg:phone":"+39 02 9000 9444",
    "sg:postcode":"20086",
    "sg:province":"Milano",
    "wof:name":"Alleanza Nazionale",
    "wof:placetype":"venue"
},
  "geometry": {"coordinates":[9.0775203705,45.5526580811],"type":"Point"}
}