{
  "type": "Feature",
  "properties": {
    "addr:full":"88100 Catanzaro Catanzaro Catanzaro 88100",
    "addr:postcode":"88100;88100",
    "iso:country":"IT",
    "sg:address":"88100 Catanzaro",
    "sg:city":"Catanzaro",
    "sg:orig_category":"Servizi Per Lo Sport E Il Tempo Libero. Servizi Ausiliari Dei Mezzi Di Trasporto",
    "sg:phone":"+39 0961 719006",
    "sg:postcode":"88100",
    "sg:province":"Catanzaro",
    "wof:name":"Nanci Raffaele",
    "wof:placetype":"venue"
},
  "geometry": {"coordinates":[16.615612,38.82077],"type":"Point"}
}