{
  "type": "Feature",
  "properties": {
    "iso:country":"IT",
    "sg:address":"6, Via Del Panieraio 95033 Biancavilla",
    "sg:city":"Biancavilla",
    "sg:classifiers":[
        {
            "category":"Farming",
            "subcategory":"Livestock Farm",
            "type":"Manufacturing & Wholesale Goods"
        }
    ],
    "sg:phone":"+39 39095687878",
    "sg:postcode":"95033",
    "sg:province":"Catania",
    "sg:tags":[
        "agriculture"
    ],
    "wof:name":"Ortofrutta Palmeri Srl",
    "wof:placetype":"venue"
},
  "geometry": {"coordinates":[14.832051,37.660141],"type":"Point"}
}