{
  "type": "Feature",
  "properties": {
    "iso:country":"IT",
    "sg:address":"61010 Tavullia",
    "sg:city":"Tavullia",
    "sg:orig_category":"Legno E Semilavorati",
    "sg:phone":"+39 0721 201887",
    "sg:postcode":"61010",
    "sg:province":"Pesaro E Urbino",
    "wof:name":"A.l.p.i. Spa",
    "wof:placetype":"venue"
},
  "geometry": {"coordinates":[12.822832,43.886456],"type":"Point"}
}