{
  "type": "Feature",
  "properties": {
    "iso:country":"IT",
    "sg:address":"43044 Collecchio",
    "sg:city":"Collecchio",
    "sg:orig_category":"Studi E Consulenze Amministrative, Commerciali E Aziendali. Consulenze Tecniche, Amministrative E Perizie",
    "sg:phone":"+39 0521 304020",
    "sg:postcode":"43044",
    "sg:province":"Parma",
    "sg:website":"http://www.sygest.it",
    "wof:name":"Sygest Srl",
    "wof:placetype":"venue"
},
  "geometry": {"coordinates":[10.263463,44.772038],"type":"Point"}
}