{
  "type": "Feature",
  "properties": {
    "addr:full":"22020 Drezzo Drezzo Como 22020",
    "addr:postcode":"22020;22020",
    "addr:street":"Drezzo",
    "iso:country":"IT",
    "sg:address":"22020 Drezzo",
    "sg:city":"Drezzo",
    "sg:classifiers":[
        {
            "category":"Military Area",
            "subcategory":"Air Force Base",
            "type":"Public Place"
        }
    ],
    "sg:phone":"+39 031 550044",
    "sg:postcode":"22020",
    "sg:province":"Como",
    "sg:tags":[
        "cave",
        "e",
        "miniere"
    ],
    "wof:name":"Inerti Barella Srl",
    "wof:placetype":"venue"
},
  "geometry": {"coordinates":[8.9959440231,45.8162574768],"type":"Point"}
}