{
  "type": "Feature",
  "properties": {
    "addr:full":"15, Via Assisi 21013 Gallarate Gallarate Varese 21013",
    "addr:postcode":"21013;21013",
    "addr:street":"Via Assisi",
    "iso:country":"IT",
    "sg:address":"15, Via Assisi 21013 Gallarate",
    "sg:city":"Gallarate",
    "sg:classifiers":[
        {
            "category":"Shopping",
            "subcategory":"Crafts & Fabrics",
            "type":"Retail Goods"
        }
    ],
    "sg:phone":"+39 0331 779134",
    "sg:postcode":"21013",
    "sg:province":"Varese",
    "wof:name":"Manifattura Pozzi Aldo (s.n.c.)",
    "wof:placetype":"venue"
},
  "geometry": {"coordinates":[8.7820291519,45.6768188477],"type":"Point"}
}