{
  "type": "Feature",
  "properties": {
    "addr:full":"32020 Limana Limana Belluno 32020",
    "addr:postcode":"32020;32020",
    "iso:country":"IT",
    "sg:address":"32020 Limana",
    "sg:city":"Limana",
    "sg:orig_category":"Macchine Utensili E Impianti",
    "sg:phone":"+39 0437 967422",
    "sg:postcode":"32020",
    "sg:province":"Belluno",
    "wof:name":"Tormen Guerrino & C. Snc",
    "wof:placetype":"venue"
},
  "geometry": {"coordinates":[12.156329,46.102066],"type":"Point"}
}