{
  "type": "Feature",
  "properties": {
    "iso:country":"IT",
    "sg:address":"56, Via Sanvito Silvestro 21100 Varese",
    "sg:city":"Varese",
    "sg:classifiers":[
        {
            "category":"Banks & Credit Unions",
            "subcategory":"Bank",
            "type":"Services"
        }
    ],
    "sg:phone":"+39 0332 242767",
    "sg:postcode":"21100",
    "sg:province":"Varese",
    "sg:tags":[
        "banking",
        "institution"
    ],
    "wof:name":"Interleasing S.p.a.",
    "wof:placetype":"venue"
},
  "geometry": {"coordinates":[8.826385,45.817604],"type":"Point"}
}