{
  "type": "Feature",
  "properties": {
    "iso:country":"IT",
    "sg:address":"1, Viale Europa 38060 Aldeno",
    "sg:city":"Aldeno",
    "sg:classifiers":[
        {
            "category":"Professional",
            "subcategory":"Printing & Photocopies",
            "type":"Services"
        }
    ],
    "sg:phone":"+39 0461 842222",
    "sg:postcode":"38060",
    "sg:province":"Trento",
    "wof:name":"Igf S.r.l.",
    "wof:placetype":"venue"
},
  "geometry": {"coordinates":[11.0955734253,45.9814491272],"type":"Point"}
}