{
  "type": "Feature",
  "properties": {
    "iso:country":"IT",
    "sg:address":"70059 Trani",
    "sg:city":"Trani",
    "sg:orig_category":"Scuole E Servizi Scolastici. Servizi Per Lo Sport E Il Tempo Libero",
    "sg:phone":"+39 0883 482477",
    "sg:postcode":"70059",
    "sg:province":"Bari",
    "wof:name":"Di Tondo Vincenzo",
    "wof:placetype":"venue"
},
  "geometry": {"coordinates":[16.872042,41.124985],"type":"Point"}
}