{
  "type": "Feature",
  "properties": {
    "iso:country":"IT",
    "sg:address":"2/a, Via Torricelli Evangelista 37135 Verona",
    "sg:city":"Verona",
    "sg:classifiers":[
        {
            "category":"Autos & Motor Vehicles",
            "subcategory":"Boat Sales",
            "type":"Retail Goods"
        }
    ],
    "sg:phone":"+39 39045508877",
    "sg:postcode":"37135",
    "sg:province":"Verona",
    "wof:name":"M.e.p. - Pellegrini Marine Equipment (s.r.l.)",
    "wof:placetype":"venue"
},
  "geometry": {"coordinates":[10.972294,45.403458],"type":"Point"}
}