{
  "type": "Feature",
  "properties": {
    "iso:country":"IT",
    "sg:address":"00174 Roma",
    "sg:city":"Roma",
    "sg:orig_category":"Impiantistica E Prodotti Tecnologici Per Edilizia. Elettrotecnica Professionale E Di Consumo. Telecomunicazioni E Telefonia, Impianti, Apparecchi E Servizi",
    "sg:phone":"+39 06 7691 0410",
    "sg:postcode":"00174",
    "sg:province":"Roma",
    "sg:website":"http://www.micanet.it/amicosat",
    "wof:name":"Amico Sat Srl",
    "wof:placetype":"venue"
},
  "geometry": {"coordinates":[12.579594,41.8465],"type":"Point"}
}