{
  "type": "Feature",
  "properties": {
    "addr:full":"Via Einaudi 154 10040 Rivalta Di Torino Rivalta di Torino Torino 10040",
    "addr:housenumber":"154",
    "addr:postcode":"10040;10040",
    "addr:street":"Via Einaudi",
    "iso:country":"IT",
    "sg:address":"Via Einaudi 154 10040 Rivalta Di Torino",
    "sg:city":"Rivalta di Torino",
    "sg:orig_category":"Steering Wheels, Airbag Steering Wheels For Cars",
    "sg:phone":"+39 011 90281",
    "sg:postcode":"10040",
    "sg:province":"Torino",
    "wof:name":"Gallino Spa",
    "wof:placetype":"venue"
},
  "geometry": {"coordinates":[7.686619,45.07056],"type":"Point"}
}