{
  "type": "Feature",
  "properties": {
    "iso:country":"IT",
    "sg:address":"28, Via Botteghe 10060 Scalenghe",
    "sg:city":"Scalenghe",
    "sg:orig_category":"Miscellaneous Products",
    "sg:phone":"+39 011 986 6479",
    "sg:postcode":"10060",
    "sg:province":"Torino",
    "wof:name":"Cabex Co. S.n.c.",
    "wof:placetype":"venue"
},
  "geometry": {"coordinates":[7.427028656,44.9026870728],"type":"Point"}
}