{
  "type": "Feature",
  "properties": {
    "addr:full":"00176 Roma Roma Roma 00176",
    "addr:postcode":"00176;00176",
    "iso:country":"IT",
    "sg:address":"00176 Roma",
    "sg:city":"Roma",
    "sg:orig_category":"Articoli Da Regalo. Regalistica Aziendale",
    "sg:phone":"+39 06 275 4996",
    "sg:postcode":"00176",
    "sg:province":"Roma",
    "wof:name":"Carolini Sandra",
    "wof:placetype":"venue"
},
  "geometry": {"coordinates":[12.533304,41.885338],"type":"Point"}
}