{
  "type": "Feature",
  "properties": {
    "iso:country":"IT",
    "sg:address":"50054 Fucecchio",
    "sg:city":"Fucecchio",
    "sg:orig_category":"Servizi E Lavori Per Abbigliamento E Pelletterie",
    "sg:phone":"+39 0571 297358",
    "sg:postcode":"50054",
    "sg:province":"Firenze",
    "wof:name":"Conceria Zabri Spa",
    "wof:placetype":"venue"
},
  "geometry": {"coordinates":[10.785638,43.738682],"type":"Point"}
}