{
  "type": "Feature",
  "properties": {
    "addr:full":"10020 Cavagnolo Cavagnolo Torino 10020",
    "addr:housenumber":"10020",
    "addr:postcode":"10020",
    "addr:street":"Cavagnolo Cavagnolo",
    "iso:country":"IT",
    "sg:address":"10020 Cavagnolo",
    "sg:city":"Cavagnolo",
    "sg:orig_category":"Elettronica Professionale E Di Consumo. Musica",
    "sg:phone":"+39 011 915 1683",
    "sg:postcode":"10020",
    "sg:province":"Torino",
    "wof:name":"Pansera Antica Famiglia Organara Di Rosso Renzo",
    "wof:placetype":"venue"
},
  "geometry": {"coordinates":[7.63763,45.051826],"type":"Point"}
}