{
  "type": "Feature",
  "properties": {
    "iso:country":"IT",
    "sg:address":"20131 Milano",
    "sg:city":"Milano",
    "sg:orig_category":"Articoli Da Regalo. Regalistica Aziendale",
    "sg:phone":"+39 02 204 6264",
    "sg:postcode":"20131",
    "sg:province":"Milano",
    "wof:name":"Il Ciocco Di Mirisola Giuseppa Sas",
    "wof:placetype":"venue"
},
  "geometry": {"coordinates":[9.21716,45.484051],"type":"Point"}
}