{
  "type": "Feature",
  "properties": {
    "iso:country":"IT",
    "sg:address":"Via Dell' Artigianato, 28/30 36043 Camisano Vicentino",
    "sg:city":"Camisano Vicentino",
    "sg:classifiers":[
        {
            "category":"Ice Cream",
            "type":"Food & Drink"
        }
    ],
    "sg:phone":"+39 0444 610443",
    "sg:postcode":"36043",
    "sg:province":"Vicenza",
    "sg:tags":[
        "ice-cream"
    ],
    "sg:website":"www.semigel.com",
    "wof:name":"Semigel Spa Group 34 Camisano Vicentino Dolce Freddo",
    "wof:placetype":"venue"
},
  "geometry": {"coordinates":[11.712019,45.506374],"type":"Point"}
}