{
  "type": "Feature",
  "properties": {
    "iso:country":"IT",
    "sg:address":"17031 Albenga",
    "sg:city":"Albenga",
    "sg:orig_category":"Frutta E Verdura - Ingrosso",
    "sg:phone":"+39 0182 555333",
    "sg:postcode":"17031",
    "sg:province":"Savona",
    "wof:name":"Carloberra Srl",
    "wof:placetype":"venue"
},
  "geometry": {"coordinates":[8.212594986,44.0575942993],"type":"Point"}
}