{
  "type": "Feature",
  "properties": {
    "addr:full":"Via Della Salute 85/10/bcd 40132 Bologna Bologna Bologna 40132",
    "addr:housenumber":"85 / 10 / bcd",
    "addr:postcode":"40132;40132",
    "addr:street":"Via Della Salute",
    "iso:country":"IT",
    "sg:address":"Via Della Salute 85/10/bcd 40132 Bologna",
    "sg:city":"Bologna",
    "sg:classifiers":[
        {
            "category":"Manufacturing",
            "subcategory":"Motor Vehicles & Parts",
            "type":"Manufacturing & Wholesale Goods"
        }
    ],
    "sg:phone":"+39 051 406517",
    "sg:postcode":"40132",
    "sg:province":"Bologna",
    "sg:tags":[
        "pneumatic",
        "component",
        "accessory"
    ],
    "sg:website":"www.sistemp.com",
    "wof:name":"Sistem Pneumatica Srl",
    "wof:placetype":"venue"
},
  "geometry": {"coordinates":[11.346481,44.494221],"type":"Point"}
}