{
  "type": "Feature",
  "properties": {
    "addr:full":"81030 San Marcellino San Marcellino Caserta 81030",
    "addr:housenumber":"81030",
    "addr:postcode":"81030",
    "addr:street":"San Marcellino San Marcellino Caserta",
    "iso:country":"IT",
    "sg:address":"81030 San Marcellino",
    "sg:city":"San Marcellino",
    "sg:orig_category":"Automazione E Macchine Per Ufficio",
    "sg:phone":"+39 081 812 3145",
    "sg:postcode":"81030",
    "sg:province":"Caserta",
    "sg:website":"http://www.lanota.it",
    "wof:name":"La Nota Srl",
    "wof:placetype":"venue"
},
  "geometry": {"coordinates":[14.177629,40.986233],"type":"Point"}
}