{
  "type": "Feature",
  "properties": {
    "iso:country":"IT",
    "sg:address":"29100 Piacenza",
    "sg:city":"Piacenza",
    "sg:orig_category":"Motori Ed Organi Di Trasmissione. Ricambi E Componenti Dei Mezzi Di Trasporto",
    "sg:phone":"+39 0523 571504",
    "sg:postcode":"29100",
    "sg:province":"Piacenza",
    "wof:name":"Mazzocchi Di Dimroci Nicola & C. Snc",
    "wof:placetype":"venue"
},
  "geometry": {"coordinates":[9.7184400558,45.0400466919],"type":"Point"}
}