{
  "type": "Feature",
  "properties": {
    "addr:full":"28, Via Palazzi 56010 Pisa Pisa 56010",
    "addr:postcode":"56010;56010",
    "addr:street":"Via Palazzi",
    "iso:country":"IT",
    "sg:address":"28, Via Palazzi 56010 Pisa",
    "sg:classifiers":[
        {
            "category":"Farming",
            "subcategory":"Livestock Farm",
            "type":"Manufacturing & Wholesale Goods"
        }
    ],
    "sg:phone":"+39 39050989102",
    "sg:postcode":"56010",
    "sg:province":"Pisa",
    "sg:tags":[
        "agriculture"
    ],
    "wof:name":"Cooperativa Agricola Le Rene (s.r.l.)",
    "wof:placetype":"venue"
},
  "geometry": {"coordinates":[10.393212,43.639317],"type":"Point"}
}