{
  "type": "Feature",
  "properties": {
    "iso:country":"IT",
    "sg:address":"00138 Roma",
    "sg:city":"Roma",
    "sg:orig_category":"Articoli Da Regalo. Tempo Libero - Articoli E Forniture. Regalistica Aziendale",
    "sg:phone":"+39 06 880 2773",
    "sg:postcode":"00138",
    "sg:province":"Roma",
    "sg:website":"http://www.paginegialle.it/mondogioco",
    "wof:name":"Mondo Gioco 98",
    "wof:placetype":"venue"
},
  "geometry": {"coordinates":[12.510241,41.971874],"type":"Point"}
}