{
  "type": "Feature",
  "properties": {
    "iso:country":"IT",
    "sg:address":"84125 Salerno",
    "sg:city":"Salerno",
    "sg:orig_category":"Bruciatori Nafta, Gasolio E Kerosene - Installazione E Manutenzione",
    "sg:phone":"+39 089 254224",
    "sg:postcode":"84125",
    "sg:province":"Salerno",
    "wof:name":"Marino Impianti",
    "wof:placetype":"venue"
},
  "geometry": {"coordinates":[14.749177,40.687378],"type":"Point"}
}