{
  "type": "Feature",
  "properties": {
    "addr:full":"128, Via S. Martino 80046 San Giorgio A Cremano San Giorgio a Cremano Napoli 80046",
    "addr:housenumber":"128",
    "addr:postcode":"80046;80046",
    "addr:street":"Via S. Martino",
    "iso:country":"IT",
    "sg:address":"128, Via S. Martino 80046 San Giorgio A Cremano",
    "sg:city":"San Giorgio a Cremano",
    "sg:classifiers":[
        {
            "category":"Shopping",
            "type":"Retail Goods"
        }
    ],
    "sg:phone":"+39 39081472119",
    "sg:postcode":"80046",
    "sg:province":"Napoli",
    "sg:tags":[
        "finished",
        "-",
        "metallic"
    ],
    "wof:name":"Sud Pont S.r.l.",
    "wof:placetype":"venue"
},
  "geometry": {"coordinates":[14.3317756653,40.8346977234],"type":"Point"}
}