{
  "type": "Feature",
  "properties": {
    "addr:full":"22, Via Brindisi 70031 Andria Andria Bari 70031",
    "addr:postcode":"70031;70031",
    "addr:street":"Via Brindisi",
    "iso:country":"IT",
    "sg:address":"22, Via Brindisi 70031 Andria",
    "sg:city":"Andria",
    "sg:classifiers":[
        {
            "category":"Wholesale",
            "subcategory":"Drugs",
            "type":"Manufacturing & Wholesale Goods"
        }
    ],
    "sg:phone":"+39 0883 599536",
    "sg:postcode":"70031",
    "sg:province":"Bari",
    "sg:tags":[
        "chemical",
        "pharmaceutical"
    ],
    "wof:name":"Ri.pa. Adesivi E Sigillanti",
    "wof:placetype":"venue"
},
  "geometry": {"coordinates":[16.302408,41.230503],"type":"Point"}
}