{
  "type": "Feature",
  "properties": {
    "addr:full":"00152 Roma Roma Roma 00152",
    "addr:postcode":"00152;00152",
    "iso:country":"IT",
    "sg:address":"00152 Roma",
    "sg:city":"Roma",
    "sg:orig_category":"Scuole E Servizi Scolastici. Ospedali E Servizi Sanitari",
    "sg:phone":"+39 06 655 6510",
    "sg:postcode":"00152",
    "sg:province":"Roma",
    "wof:name":"Associazione Anni Verdi",
    "wof:placetype":"venue"
},
  "geometry": {"coordinates":[12.412887,41.846691],"type":"Point"}
}