{
  "type": "Feature",
  "properties": {
    "iso:country":"IT",
    "sg:address":"56033 Capannoli",
    "sg:city":"Capannoli",
    "sg:orig_category":"Termotecnica E Riscaldamento, Apparecchiature E Servizi. Prodotti Vari In Metallo",
    "sg:phone":"+39 0587 609944",
    "sg:postcode":"56033",
    "sg:province":"Pisa",
    "wof:name":"Termocasa Snc",
    "wof:placetype":"venue"
},
  "geometry": {"coordinates":[10.747925,43.67762],"type":"Point"}
}