{
  "type": "Feature",
  "properties": {
    "iso:country":"IT",
    "sg:address":"22100 Como",
    "sg:city":"Como",
    "sg:orig_category":"Servizi E Lavori Per Abbigliamento E Pelletterie",
    "sg:phone":"+39 031 265517",
    "sg:postcode":"22100",
    "sg:province":"Como",
    "wof:name":"Zei Giuliana",
    "wof:placetype":"venue"
},
  "geometry": {"coordinates":[9.091822,45.807259],"type":"Point"}
}