{
  "type": "Feature",
  "properties": {
    "addr:full":"00182 Roma Roma Roma 00182",
    "addr:postcode":"00182;00182",
    "iso:country":"IT",
    "sg:address":"00182 Roma",
    "sg:city":"Roma",
    "sg:orig_category":"Analisi Cliniche - Centri E Laboratori",
    "sg:phone":"+39 06 7720 5951",
    "sg:postcode":"00182",
    "sg:province":"Roma",
    "wof:name":"Premedica Prevenzione Medica Srl",
    "wof:placetype":"venue"
},
  "geometry": {"coordinates":[12.512421,41.885063],"type":"Point"}
}