{
  "type": "Feature",
  "properties": {
    "iso:country":"IT",
    "sg:address":"Via Pastrengo 3, 25122 Brescia, Bs",
    "sg:city":"Brescia",
    "sg:classifiers":[
        {
            "category":"Banks & Credit Unions",
            "subcategory":"Bank",
            "type":"Services"
        }
    ],
    "sg:postcode":"25122",
    "sg:province":"Brescia",
    "wof:name":"Fin-eco Holding Spa",
    "wof:placetype":"venue"
},
  "geometry": {"coordinates":[10.213443,45.546688],"type":"Point"}
}