{
  "type": "Feature",
  "properties": {
    "addr:full":"00154 Roma Roma Roma 00154",
    "addr:postcode":"00154;00154",
    "iso:country":"IT",
    "sg:address":"00154 Roma",
    "sg:city":"Roma",
    "sg:orig_category":"Servizi E Lavori Per Abbigliamento E Pelletterie",
    "sg:phone":"+39 06 575 9010",
    "sg:postcode":"00154",
    "sg:province":"Roma",
    "wof:name":"Gasparini Olga",
    "wof:placetype":"venue"
},
  "geometry": {"coordinates":[12.487007,41.86787],"type":"Point"}
}