{
  "type": "Feature",
  "properties": {
    "iso:country":"IT",
    "sg:address":"56017 San Giuliano Terme",
    "sg:city":"San Giuliano Terme",
    "sg:orig_category":"Servizi E Lavori Per Agricoltura E Zootecnia. Imprese Di Costruzioni Civili Ed Industriali",
    "sg:phone":"+39 050 879949",
    "sg:postcode":"56017",
    "sg:province":"Pisa",
    "wof:name":"Ecosit Snc",
    "wof:placetype":"venue"
},
  "geometry": {"coordinates":[10.42067,43.725044],"type":"Point"}
}