{
  "type": "Feature",
  "properties": {
    "addr:full":"29/e, Via Pasubio 25128 Brescia Brescia Brescia 25128",
    "addr:housenumber":"29 / e",
    "addr:postcode":"25128;25128",
    "addr:street":"Via Pasubio",
    "iso:country":"IT",
    "sg:address":"29/e, Via Pasubio 25128 Brescia",
    "sg:city":"Brescia",
    "sg:classifiers":[
        {
            "category":"Manufacturing",
            "subcategory":"Rubber & Plastics",
            "type":"Manufacturing & Wholesale Goods"
        }
    ],
    "sg:phone":"+39 39030301904",
    "sg:postcode":"25128",
    "sg:province":"Brescia",
    "wof:name":"Elite Casa Di Pasotti Giacomina & C. S.n.c.",
    "wof:placetype":"venue"
},
  "geometry": {"coordinates":[10.2174043655,45.5524368286],"type":"Point"}
}