{
  "type": "Feature",
  "properties": {
    "addr:full":"20077 Melegnano Melegnano Milano 20077",
    "addr:postcode":"20077;20077",
    "iso:country":"IT",
    "sg:address":"20077 Melegnano",
    "sg:city":"Melegnano",
    "sg:orig_category":"Metalli E Leghe",
    "sg:phone":"+39 02 983 4578",
    "sg:postcode":"20077",
    "sg:province":"Milano",
    "wof:name":"W.c.b. Ice Cream Italy Srl",
    "wof:placetype":"venue"
},
  "geometry": {"coordinates":[9.3265371323,45.3502349854],"type":"Point"}
}