{
  "type": "Feature",
  "properties": {
    "iso:country":"IT",
    "sg:address":"40050 Argelato",
    "sg:city":"Argelato",
    "sg:orig_category":"Abbigliamento Uomo - Produzione E Ingrosso",
    "sg:phone":"+39 051 664 6510",
    "sg:postcode":"40050",
    "sg:province":"Bologna",
    "wof:name":"Iniziative Moda Italiana Srl",
    "wof:placetype":"venue"
},
  "geometry": {"coordinates":[11.379539,44.584305],"type":"Point"}
}