{
  "type": "Feature",
  "properties": {
    "addr:full":"95123 Catania Catania Catania 95123",
    "addr:postcode":"95123;95123",
    "iso:country":"IT",
    "sg:address":"95123 Catania",
    "sg:city":"Catania",
    "sg:orig_category":"Serigrafia",
    "sg:phone":"+39 095 359030",
    "sg:postcode":"95123",
    "sg:province":"Catania",
    "wof:name":"Print & Service Di Marino Giovanni",
    "wof:placetype":"venue"
},
  "geometry": {"coordinates":[15.055021,37.510403],"type":"Point"}
}