{
  "type": "Feature",
  "properties": {
    "addr:full":"38, Viale Lombardia 20056 Trezzo Sull'adda Milano 20056",
    "addr:housenumber":"38",
    "addr:postcode":"20056;20056",
    "addr:street":"Viale Lombardia",
    "iso:country":"IT",
    "sg:address":"38, Viale Lombardia 20056 Trezzo Sull'adda",
    "sg:classifiers":[
        {
            "category":"Banks & Credit Unions",
            "subcategory":"Investment Brokerage",
            "type":"Services"
        }
    ],
    "sg:phone":"+39 02 9096 3500",
    "sg:postcode":"20056",
    "sg:province":"Milano",
    "sg:tags":[
        "-",
        "transport",
        "related"
    ],
    "wof:name":"Cidem Spa",
    "wof:placetype":"venue"
},
  "geometry": {"coordinates":[9.540328,45.575859],"type":"Point"}
}