{
  "type": "Feature",
  "properties": {
    "iso:country":"IT",
    "sg:address":"47023 Cesena",
    "sg:city":"Cesena",
    "sg:classifiers":[
        {
            "category":"Home & Garden",
            "subcategory":"Building Materials",
            "type":"Retail Goods"
        }
    ],
    "sg:phone":"+39 0547 334134",
    "sg:postcode":"47023",
    "sg:province":"Forl\u00ec-Cesena",
    "sg:tags":[
        "gas",
        "caldaie"
    ],
    "wof:name":"Ati Di Mariani Mario & C. Snc",
    "wof:placetype":"venue"
},
  "geometry": {"coordinates":[12.20623,44.150021],"type":"Point"}
}