{
  "type": "Feature",
  "properties": {
    "iso:country":"IT",
    "sg:address":"590, V. Radici In Piano 41049 Sassuolo",
    "sg:city":"Sassuolo",
    "sg:classifiers":[
        {
            "category":"Manufacturing",
            "subcategory":"Rubber & Plastics",
            "type":"Manufacturing & Wholesale Goods"
        }
    ],
    "sg:phone":"+39 0536 807272",
    "sg:postcode":"41049",
    "sg:province":"Modena",
    "sg:website":"http://www.ferrirenzo.it:ws_end: :mark:ws:http://www.paginegialle.it/ferrirenzo",
    "wof:name":"Ferri Renzo & C. Snc",
    "wof:placetype":"venue"
},
  "geometry": {"coordinates":[10.833138,44.582958],"type":"Point"}
}