{
  "type": "Feature",
  "properties": {
    "iso:country":"IT",
    "sg:address":"28, Localita' Pannellia 33039 Sedegliano",
    "sg:city":"Sedegliano",
    "sg:classifiers":[
        {
            "category":"Home & Garden",
            "subcategory":"Home Furnishings",
            "type":"Retail Goods"
        }
    ],
    "sg:phone":"+39 0432 918133",
    "sg:postcode":"33039",
    "sg:province":"Udine",
    "sg:tags":[
        "household"
    ],
    "wof:name":"Nuovo Mobilificio Tagliamento (s.r.l.)",
    "wof:placetype":"venue"
},
  "geometry": {"coordinates":[12.932684,45.992584],"type":"Point"}
}