{
  "type": "Feature",
  "properties": {
    "addr:full":"35010 Marsango Marsango Padova 35010",
    "addr:postcode":"35010;35010",
    "addr:street":"Marsango",
    "iso:country":"IT",
    "sg:address":"35010 Marsango",
    "sg:city":"Marsango",
    "sg:orig_category":"Macchine, Impianti Ed Attrezzature Per Agricoltura E Zootecnia",
    "sg:phone":"+39 049 963 0588",
    "sg:postcode":"35010",
    "sg:province":"Padova",
    "wof:name":"Facco & C. Officine (s.p.a.)",
    "wof:placetype":"venue"
},
  "geometry": {"coordinates":[11.979535,45.421543],"type":"Point"}
}