{
  "type": "Feature",
  "properties": {
    "iso:country":"IT",
    "sg:address":"Corso Garibaldi 2bcd; Afragola; 80021",
    "sg:city":"Afragola",
    "sg:classifiers":[
        {
            "category":"Banks & Credit Unions",
            "subcategory":"Bank",
            "type":"Services"
        }
    ],
    "sg:phone":"+39 081 851 2505",
    "sg:postcode":"80021",
    "sg:province":"Napoli",
    "wof:name":"Credito Emiliano Spa",
    "wof:placetype":"venue"
},
  "geometry": {"coordinates":[14.326827,40.927467],"type":"Point"}
}