{
  "type": "Feature",
  "properties": {
    "addr:full":"31040 Pederobba Pederobba Treviso 31040",
    "addr:postcode":"31040;31040",
    "iso:country":"IT",
    "sg:address":"31040 Pederobba",
    "sg:city":"Pederobba",
    "sg:orig_category":"Materiali Semilavorati Metallici",
    "sg:phone":"+39 0423 688456",
    "sg:postcode":"31040",
    "sg:province":"Treviso",
    "wof:name":"Omega Srl",
    "wof:placetype":"venue"
},
  "geometry": {"coordinates":[11.967734,45.867458],"type":"Point"}
}