{
  "type": "Feature",
  "properties": {
    "iso:country":"IT",
    "sg:address":"43, Strada Castelfirmiano 39057 Appiano Sulla Strada Del Vino",
    "sg:city":"Appiano sulla strada del vino",
    "sg:classifiers":[
        {
            "category":"Professional",
            "subcategory":"Engineering",
            "type":"Services"
        }
    ],
    "sg:phone":"+39 0471 633422",
    "sg:postcode":"39057",
    "sg:province":"Bolzano/Bozen",
    "sg:tags":[
        "machine",
        "-",
        "mechanical"
    ],
    "wof:name":"Eric-son S.a.s.",
    "wof:placetype":"venue"
},
  "geometry": {"coordinates":[11.29663,46.478413],"type":"Point"}
}