{
  "type": "Feature",
  "properties": {
    "iso:country":"IT",
    "sg:address":"Via Liguria 59100 Prato",
    "sg:city":"Prato",
    "sg:classifiers":[
        {
            "category":"Shopping",
            "subcategory":"Clothing, Apparel, & Fashions",
            "type":"Retail Goods"
        }
    ],
    "sg:phone":"+39 0574 623101",
    "sg:postcode":"59100",
    "sg:province":"Prato",
    "sg:tags":[
        "clothes"
    ],
    "wof:name":"Confezioni Emanuela Srl",
    "wof:placetype":"venue"
},
  "geometry": {"coordinates":[11.057356,43.859478],"type":"Point"}
}