{
  "type": "Feature",
  "properties": {
    "iso:country":"IT",
    "sg:address":"2, Via Toscana 40069 Zola Predosa",
    "sg:city":"Zola",
    "sg:classifiers":[
        {
            "category":"Professional",
            "subcategory":"Engineering",
            "type":"Services"
        }
    ],
    "sg:phone":"+39 39051758209",
    "sg:postcode":"40069",
    "sg:province":"Bologna",
    "sg:tags":[
        "machine",
        "-",
        "mechanical"
    ],
    "wof:name":"M.w.m. (s.r.l.)",
    "wof:placetype":"venue"
},
  "geometry": {"coordinates":[11.233917,44.492844],"type":"Point"}
}