{
  "type": "Feature",
  "properties": {
    "iso:country":"IT",
    "sg:address":"Via Osservatorio 80077 Ischia",
    "sg:city":"Ischia",
    "sg:classifiers":[
        {
            "category":"Travel",
            "subcategory":"Travel Agent",
            "type":"Entertainment"
        }
    ],
    "sg:phone":"+39 39081993890",
    "sg:postcode":"80077",
    "sg:province":"Napoli",
    "sg:tags":[
        "business"
    ],
    "wof:name":"Albergo Terme President (s.r.l.)",
    "wof:placetype":"venue"
},
  "geometry": {"coordinates":[13.940675,40.740471],"type":"Point"}
}