{
  "type": "Feature",
  "properties": {
    "iso:country":"IT",
    "sg:address":"48095 Cervia",
    "sg:orig_category":"Vigilanza E Sorveglianza",
    "sg:phone":"+39 0544 33226",
    "sg:province":"RA",
    "wof:name":"Cities Service Police",
    "wof:placetype":"venue"
},
  "geometry": {"coordinates":[-83.046875,42.779438],"type":"Point"}
}