{
  "type": "Feature",
  "properties": {
    "addr:full":"1, Localita' Rabuiese 34015 Muggia Muggia Trieste 34015",
    "addr:postcode":"34015;34015",
    "addr:street":"Localita ' Rabuiese",
    "iso:country":"IT",
    "sg:address":"1, Localita' Rabuiese 34015 Muggia",
    "sg:city":"Muggia",
    "sg:classifiers":[
        {
            "category":"Banks & Credit Unions",
            "subcategory":"Investment Brokerage",
            "type":"Services"
        }
    ],
    "sg:phone":"+39 39040232215",
    "sg:postcode":"34015",
    "sg:province":"Trieste",
    "sg:tags":[
        "-",
        "transport",
        "related"
    ],
    "wof:name":"De Palo (s.r.l.)",
    "wof:placetype":"venue"
},
  "geometry": {"coordinates":[13.796179,45.590328],"type":"Point"}
}