{
  "type": "Feature",
  "properties": {
    "addr:full":"142/m, Via Castronella 50013 Campi Bisenzio Campi Bisenzio Firenze 50013",
    "addr:housenumber":"142",
    "addr:postcode":"50013;50013",
    "addr:street":"/ M Via Castronella;Bisenzio",
    "iso:country":"IT",
    "sg:address":"142/m, Via Castronella 50013 Campi Bisenzio",
    "sg:city":"Campi Bisenzio",
    "sg:classifiers":[
        {
            "category":"Shopping",
            "subcategory":"Computers & Home Electronics",
            "type":"Retail Goods"
        }
    ],
    "sg:phone":"+39 055 895 1955",
    "sg:postcode":"50013",
    "sg:province":"Firenze",
    "sg:tags":[
        "electronic",
        "electrical",
        "equipment"
    ],
    "wof:name":"P.r. Studio Snc",
    "wof:placetype":"venue"
},
  "geometry": {"coordinates":[11.122739,43.830864],"type":"Point"}
}