{
  "type": "Feature",
  "properties": {
    "iso:country":"IT",
    "sg:address":"10036 Settimo Torinese",
    "sg:city":"Settimo Torinese",
    "sg:classifiers":[
        {
            "category":"Shopping",
            "subcategory":"Computers & Home Electronics",
            "type":"Retail Goods"
        }
    ],
    "sg:phone":"+39 011 816 5311",
    "sg:postcode":"10036",
    "sg:province":"Torino",
    "sg:tags":[
        "personal",
        "ed",
        "accessori"
    ],
    "sg:website":"http://www.precision.it",
    "wof:name":"Precision Spa",
    "wof:placetype":"venue"
},
  "geometry": {"coordinates":[7.7342433929,45.1457557678],"type":"Point"}
}