{
  "type": "Feature",
  "properties": {
    "addr:full":"Localita' Le Pont 11, 11015 La Salle, Ao La Salle Aosta 11015",
    "addr:housenumber":"11",
    "addr:postcode":"11015;11015",
    "addr:street":"Localita ' Le Pont;Salle Aosta",
    "iso:country":"IT",
    "sg:address":"Localita' Le Pont 11, 11015 La Salle, Ao",
    "sg:city":"La Salle",
    "sg:classifiers":[
        {
            "category":"Banks & Credit Unions",
            "subcategory":"Bank",
            "type":"Services"
        }
    ],
    "sg:postcode":"11015",
    "sg:province":"Aosta",
    "wof:name":"Banca Di Credito Cooperativo Del Monte Bianco-la Salle (ao)",
    "wof:placetype":"venue"
},
  "geometry": {"coordinates":[7.064126,45.744354],"type":"Point"}
}