{
  "type": "Feature",
  "properties": {
    "addr:full":"36014 Santorso Santorso Vicenza 36014",
    "addr:postcode":"36014;36014",
    "iso:country":"IT",
    "sg:address":"36014 Santorso",
    "sg:city":"Santorso",
    "sg:classifiers":[
        {
            "category":"Social Services",
            "subcategory":"Job Training",
            "type":"Services"
        }
    ],
    "sg:phone":"+39 0445 641632",
    "sg:postcode":"36014",
    "sg:province":"Vicenza",
    "sg:tags":[
        "flange"
    ],
    "wof:name":"Padovani Automazione Srl",
    "wof:placetype":"venue"
},
  "geometry": {"coordinates":[11.3878688812,45.7271385193],"type":"Point"}
}