{
  "type": "Feature",
  "properties": {
    "addr:full":"52020 Castelfranco Di Sopra Castelfranco di Sopra Arezzo 52020",
    "addr:postcode":"52020;52020",
    "addr:street":"Di Sopra",
    "iso:country":"IT",
    "sg:address":"52020 Castelfranco Di Sopra",
    "sg:city":"Castelfranco di Sopra",
    "sg:orig_category":"Mobili - Produzione E Ingrosso",
    "sg:phone":"+39 055 914 9909",
    "sg:postcode":"52020",
    "sg:province":"Arezzo",
    "sg:website":"http://www.creazioniartistichefiorentine.it",
    "wof:name":"Creazioni Artistiche Fiorentine Srl",
    "wof:placetype":"venue"
},
  "geometry": {"coordinates":[11.538599968,43.6133995056],"type":"Point"}
}