{
  "type": "Feature",
  "properties": {
    "iso:country":"IT",
    "sg:address":"2, Via Cimone 36077 Altavilla Vicentina",
    "sg:city":"Altavilla Vicentina",
    "sg:classifiers":[
        {
            "category":"Shopping",
            "subcategory":"Jewelry",
            "type":"Retail Goods"
        }
    ],
    "sg:phone":"+39 0444 375025",
    "sg:postcode":"36077",
    "sg:province":"Vicenza",
    "sg:tags":[
        "jewellery"
    ],
    "wof:name":"Marotto",
    "wof:placetype":"venue"
},
  "geometry": {"coordinates":[11.493488,45.500107],"type":"Point"}
}