{
  "type": "Feature",
  "properties": {
    "iso:country":"IT",
    "sg:address":"40033 Casalecchio Di Reno",
    "sg:city":"Casalecchio di Reno",
    "sg:orig_category":"Macchine Utensili E Impianti",
    "sg:phone":"+39 051 575198",
    "sg:postcode":"40033",
    "sg:province":"Bologna",
    "wof:name":"Azzali Gabriele",
    "wof:placetype":"venue"
},
  "geometry": {"coordinates":[11.265979,44.490467],"type":"Point"}
}