{
  "type": "Feature",
  "properties": {
    "iso:country":"IT",
    "sg:address":"64032 Atri",
    "sg:city":"Atri",
    "sg:orig_category":"Arredo Cucina Ed Elettrodomestici",
    "sg:phone":"+39 085 879 8341",
    "sg:postcode":"64032",
    "sg:province":"Teramo",
    "sg:website":"http://www.iezzicucine.it",
    "wof:name":"Iezzi Cucine Componibili Srl",
    "wof:placetype":"venue"
},
  "geometry": {"coordinates":[13.717269,42.670391],"type":"Point"}
}