{
  "type": "Feature",
  "properties": {
    "iso:country":"IT",
    "sg:address":"20070 Vizzolo Predabissi",
    "sg:city":"Vizzolo Predabissi",
    "sg:orig_category":"Prodotti Chimici Secondari. Prodotti Cosmetici E Da Toeletta",
    "sg:phone":"+39 02 983 7674",
    "sg:postcode":"20070",
    "sg:province":"Milano",
    "wof:name":"Com.es. Srl",
    "wof:placetype":"venue"
},
  "geometry": {"coordinates":[9.347454071,45.3557510376],"type":"Point"}
}