{
  "type": "Feature",
  "properties": {
    "iso:country":"IT",
    "sg:address":"37129 Verona",
    "sg:city":"Verona",
    "sg:orig_category":"Centri Di Estetica E Cosmesi E Servizi",
    "sg:phone":"+39 045 590578",
    "sg:postcode":"37129",
    "sg:province":"Verona",
    "wof:name":"Sem Scuola Estetica Moderna",
    "wof:placetype":"venue"
},
  "geometry": {"coordinates":[11.005755,45.446079],"type":"Point"}
}