{
  "type": "Feature",
  "properties": {
    "addr:full":"Via Tiburtina Valeria, Km. 110.700 67051 Avezzano L'Aquila 67051",
    "addr:postcode":"67051;67051",
    "addr:street":"Via Tiburtina Valeria Km. 110.700",
    "iso:country":"IT",
    "sg:address":"Via Tiburtina Valeria, Km. 110.700 67051 Avezzano",
    "sg:classifiers":[
        {
            "category":"Conference Center",
            "type":"Public Place"
        }
    ],
    "sg:phone":"+39 0863 413637",
    "sg:postcode":"67051",
    "sg:province":"L'Aquila",
    "sg:tags":[
        "chair",
        "back",
        "bottom"
    ],
    "wof:name":"3 C Spa",
    "wof:placetype":"venue"
},
  "geometry": {"coordinates":[13.431372,42.039116],"type":"Point"}
}