{
  "type": "Feature",
  "properties": {
    "addr:full":"90141 Palermo Palermo Palermo 90141",
    "addr:postcode":"90141;90141",
    "iso:country":"IT",
    "sg:address":"90141 Palermo",
    "sg:city":"Palermo",
    "sg:orig_category":"Trasporti E Spedizioni Merci",
    "sg:phone":"+39 091 681 1913",
    "sg:postcode":"90141",
    "sg:province":"Palermo",
    "wof:name":"Trenitalia Spa - Direzione Zona Passeggeri Sicilia",
    "wof:placetype":"venue"
},
  "geometry": {"coordinates":[13.345983,38.122589],"type":"Point"}
}