{
  "type": "Feature",
  "properties": {
    "iso:country":"IT",
    "sg:address":"24046 Osio Sotto",
    "sg:city":"Osio Sotto",
    "sg:classifiers":[
        {
            "category":"Health Services",
            "subcategory":"Health Practitioner",
            "type":"Services"
        }
    ],
    "sg:phone":"+39 035 807171",
    "sg:postcode":"24046",
    "sg:province":"Bergamo",
    "sg:tags":[
        "medici"
    ],
    "wof:name":"Serraglio Angelo",
    "wof:placetype":"venue"
},
  "geometry": {"coordinates":[9.6581945419,45.6471786499],"type":"Point"}
}