{
  "type": "Feature",
  "properties": {
    "iso:country":"IT",
    "sg:address":"86100 Campobasso",
    "sg:city":"Campobasso",
    "sg:classifiers":[
        {
            "category":"Health Services",
            "subcategory":"Health Practitioner",
            "type":"Services"
        }
    ],
    "sg:phone":"+39 0874 91720",
    "sg:postcode":"86100",
    "sg:province":"Campobasso",
    "sg:tags":[
        "medici"
    ],
    "wof:name":"Centro Radiologico Dott. Domenico & Francesco Potito Sas",
    "wof:placetype":"venue"
},
  "geometry": {"coordinates":[14.658061,41.553272],"type":"Point"}
}