{
  "type": "Feature",
  "properties": {
    "addr:full":"Viale Montegrappa 34 27100 Pavia Pavia Pavia 27100",
    "addr:housenumber":"34",
    "addr:postcode":"27100;27100",
    "addr:street":"Viale Montegrappa",
    "iso:country":"IT",
    "sg:address":"Viale Montegrappa 34 27100 Pavia",
    "sg:city":"Pavia",
    "sg:classifiers":[
        {
            "category":"Manufacturing",
            "subcategory":"Tools & Machinery",
            "type":"Manufacturing & Wholesale Goods"
        }
    ],
    "sg:phone":"+39 0382 466701",
    "sg:postcode":"27100",
    "sg:province":"Pavia",
    "sg:tags":[
        "machine"
    ],
    "wof:name":"Cergil Srl",
    "wof:placetype":"venue"
},
  "geometry": {"coordinates":[9.177626,45.181671],"type":"Point"}
}