{
  "type": "Feature",
  "properties": {
    "iso:country":"IT",
    "sg:address":"20046 Biassono",
    "sg:city":"Biassono",
    "sg:orig_category":"Prodotti E Manufatti In Gomma. Forniture Per Attivita' Industriali",
    "sg:phone":"+39 039 275 3626",
    "sg:postcode":"20046",
    "sg:province":"Milano",
    "wof:name":"Pigomma Spa",
    "wof:placetype":"venue"
},
  "geometry": {"coordinates":[9.2620725632,45.6279449463],"type":"Point"}
}