{
  "type": "Feature",
  "properties": {
    "iso:country":"IT",
    "sg:address":"35020 Polverara",
    "sg:city":"Polverara",
    "sg:orig_category":"Ricami - Vendita Al Dettaglio",
    "sg:phone":"+39 049 977 2005",
    "sg:postcode":"35020",
    "sg:province":"Padova",
    "sg:website":"http://richermes.com",
    "wof:name":"Richermes Srl",
    "wof:placetype":"venue"
},
  "geometry": {"coordinates":[11.96188,45.315674],"type":"Point"}
}