{
  "type": "Feature",
  "properties": {
    "addr:full":"160, Via Nazionale 25051 Cedegolo Cedegolo Brescia 25051",
    "addr:housenumber":"160",
    "addr:postcode":"25051;25051",
    "addr:street":"Via Nazionale",
    "iso:country":"IT",
    "sg:address":"160, Via Nazionale 25051 Cedegolo",
    "sg:city":"Cedegolo",
    "sg:classifiers":[
        {
            "category":"Real Estate",
            "subcategory":"Architect",
            "type":"Services"
        }
    ],
    "sg:phone":"+39 39036462045",
    "sg:postcode":"25051",
    "sg:province":"Brescia",
    "sg:tags":[
        "textile",
        "clothing"
    ],
    "wof:name":"Sport Wear Valle Camonica Srl",
    "wof:placetype":"venue"
},
  "geometry": {"coordinates":[10.346884,46.0821],"type":"Point"}
}