{
  "type": "Feature",
  "properties": {
    "iso:country":"IT",
    "sg:address":"21, Via D. Alighieri 47018 Santa Sofia",
    "sg:city":"Santa Sofia",
    "sg:classifiers":[
        {
            "category":"Shopping",
            "type":"Retail Goods"
        }
    ],
    "sg:phone":"+39 0543 970116",
    "sg:postcode":"47018",
    "sg:province":"Forl\u00ec-Cesena",
    "sg:tags":[
        "finished",
        "-",
        "metallic"
    ],
    "wof:name":"A.c.i.s. Azienda Costruzioni Installazioni Segnale",
    "wof:placetype":"venue"
},
  "geometry": {"coordinates":[11.9804611206,43.9947662354],"type":"Point"}
}