{
  "type": "Feature",
  "properties": {
    "iso:country":"IT",
    "sg:address":"20025 Legnano",
    "sg:city":"Legnano",
    "sg:orig_category":"Minuterie Metalliche E Ferramenta",
    "sg:phone":"+39 0331 540711",
    "sg:postcode":"20025",
    "sg:province":"Milano",
    "wof:name":"Flange Ragit Sas Di Melfi Loiacono Lavezzari & C.",
    "wof:placetype":"venue"
},
  "geometry": {"coordinates":[9.1716718674,45.4437637329],"type":"Point"}
}