{
  "type": "Feature",
  "properties": {
    "iso:country":"IT",
    "sg:address":"16121 Genova",
    "sg:city":"Genova",
    "sg:orig_category":"Acciaierie E Fonderie",
    "sg:phone":"+39 010 570 4533",
    "sg:postcode":"16121",
    "sg:province":"Genova",
    "wof:name":"Devin",
    "wof:placetype":"venue"
},
  "geometry": {"coordinates":[8.942063,44.403416],"type":"Point"}
}