{
  "type": "Feature",
  "properties": {
    "iso:country":"IT",
    "sg:address":"25054 Marone",
    "sg:city":"Marone",
    "sg:orig_category":"Materiali Edili",
    "sg:phone":"+39 030 98851",
    "sg:postcode":"25054",
    "sg:province":"Brescia",
    "wof:name":"Dolomite Franchi S.p.a.",
    "wof:placetype":"venue"
},
  "geometry": {"coordinates":[10.221169,45.536572],"type":"Point"}
}