{
  "type": "Feature",
  "properties": {
    "addr:full":"Via Vittorio Emanuele 62 45031 Arqua' Polesine Rovigo 45031",
    "addr:housenumber":"62",
    "addr:postcode":"45031;45031",
    "addr:street":"Via Vittorio Emanuele",
    "iso:country":"IT",
    "sg:address":"Via Vittorio Emanuele 62 45031 Arqua' Polesine",
    "sg:classifiers":[
        {
            "category":"Manufacturing",
            "subcategory":"Chemicals & Compounds",
            "type":"Manufacturing & Wholesale Goods"
        }
    ],
    "sg:phone":"+39 0425 918128",
    "sg:postcode":"45031",
    "sg:province":"Rovigo",
    "sg:tags":[
        "product",
        "firework",
        "pyrotechnic"
    ],
    "sg:website":"www.pirotecnicaarquatese.it",
    "wof:name":"I.p.e. Srl",
    "wof:placetype":"venue"
},
  "geometry": {"coordinates":[11.7414302826,45.0089454651],"type":"Point"}
}