{
  "type": "Feature",
  "properties": {
    "iso:country":"IT",
    "sg:address":"129, Via Gen.dalla Chiesa 84010 San Marzano Sul Sarno",
    "sg:city":"San Marzano sul Sarno",
    "sg:classifiers":[
        {
            "category":"Food & Beverages",
            "subcategory":"Groceries & Convenience Stores",
            "type":"Retail Goods"
        }
    ],
    "sg:phone":"+39 081 518 5820",
    "sg:postcode":"84010",
    "sg:province":"Salerno",
    "sg:tags":[
        "product",
        "related"
    ],
    "wof:name":"La Palmierina Di Palmieri Giovanni",
    "wof:placetype":"venue"
},
  "geometry": {"coordinates":[14.765912056,40.6779556274],"type":"Point"}
}