{
  "type": "Feature",
  "properties": {
    "iso:country":"IT",
    "sg:address":"63019 Sant'elpidio A Mare",
    "sg:city":"Castellano",
    "sg:orig_category":"Calzature, Pelletterie E Pelli",
    "sg:phone":"+39 0734 990104",
    "sg:postcode":"63019",
    "sg:province":"Ascoli Piceno",
    "wof:name":"Calzaturificio Glover Di Marcaccio Albano & C. Snc",
    "wof:placetype":"venue"
},
  "geometry": {"coordinates":[13.743244,43.274578],"type":"Point"}
}