{
  "type": "Feature",
  "properties": {
    "iso:country":"IT",
    "sg:address":"Piazza S Ambrogio 2; Vanzaghello; 20020",
    "sg:city":"Vanzaghello",
    "sg:classifiers":[
        {
            "category":"Banks & Credit Unions",
            "subcategory":"Bank",
            "type":"Services"
        }
    ],
    "sg:phone":"+39 0331 658043",
    "sg:postcode":"20020",
    "sg:province":"Milano",
    "wof:name":"Istituto Bancario, San Paolo Di Torino Spa",
    "wof:placetype":"venue"
},
  "geometry": {"coordinates":[8.782254,45.579113],"type":"Point"}
}