{
  "type": "Feature",
  "properties": {
    "iso:country":"IT",
    "sg:address":"Piazza Vittorio; Pieve Di Soligo; 31053",
    "sg:city":"Pieve di Soligo",
    "sg:classifiers":[
        {
            "category":"Banks & Credit Unions",
            "subcategory":"Bank",
            "type":"Services"
        }
    ],
    "sg:phone":"+39 0438 980000",
    "sg:postcode":"31053",
    "sg:province":"Treviso",
    "wof:name":"Banco Ambrosiano Veneto Spa",
    "wof:placetype":"venue"
},
  "geometry": {"coordinates":[12.172661,45.899677],"type":"Point"}
}