{
  "type": "Feature",
  "properties": {
    "addr:full":"Via Calcinaro 1450 47023 Cesena Cesena Forl\u00ec-Cesena 47023",
    "addr:housenumber":"1450",
    "addr:postcode":"47023;47023",
    "addr:street":"Via Calcinaro",
    "iso:country":"IT",
    "sg:address":"Via Calcinaro 1450 47023 Cesena",
    "sg:city":"Cesena",
    "sg:orig_category":"Fodder-beet Seeds",
    "sg:phone":"+39 0547 643511",
    "sg:postcode":"47023",
    "sg:province":"Forl\u00ec-Cesena",
    "sg:website":"www.cacseeds.it",
    "wof:name":"Coop Agricola Cesenate Scrl",
    "wof:placetype":"venue"
},
  "geometry": {"coordinates":[12.2599563599,44.1678276062],"type":"Point"}
}