{
  "type": "Feature",
  "properties": {
    "addr:full":"43019 Soragna Soragna Parma 43019",
    "addr:postcode":"43019;43019",
    "iso:country":"IT",
    "sg:address":"43019 Soragna",
    "sg:city":"Soragna",
    "sg:orig_category":"Apparecchiature Ed Attrezzature Meccaniche",
    "sg:phone":"+39 0524 597916",
    "sg:postcode":"43019",
    "sg:province":"Parma",
    "sg:website":"http://www.ar-com.it",
    "wof:name":"Ar.com. Srl",
    "wof:placetype":"venue"
},
  "geometry": {"coordinates":[10.134587,44.933437],"type":"Point"}
}