{
  "type": "Feature",
  "properties": {
    "addr:full":"39010 San Martino In Passiria San Martino in Passiria Bolzano/Bozen 39010",
    "addr:postcode":"39010;39010",
    "iso:country":"IT",
    "sg:address":"39010 San Martino In Passiria",
    "sg:city":"San Martino in Passiria",
    "sg:orig_category":"Pubblica Amministrazione",
    "sg:phone":"+39 0473 645650",
    "sg:postcode":"39010",
    "sg:province":"Bolzano/Bozen",
    "wof:name":"Vigili Del Fuoco Volontari Saltusio",
    "wof:placetype":"venue"
},
  "geometry": {"coordinates":[11.1976623535,46.7296295166],"type":"Point"}
}