{
  "type": "Feature",
  "properties": {
    "iso:country":"IT",
    "sg:address":"84, Viale Vespa 53025 Piancastagnaio",
    "sg:city":"Piancastagnaio",
    "sg:classifiers":[
        {
            "category":"Shopping",
            "subcategory":"Stationery & Office Supplies",
            "type":"Retail Goods"
        }
    ],
    "sg:phone":"+39 0577 786019",
    "sg:postcode":"53025",
    "sg:province":"Siena",
    "sg:tags":[
        "professional"
    ],
    "wof:name":"Mobilificio F.lli Furzi Snc Di Furzi Maria Iula & C.",
    "wof:placetype":"venue"
},
  "geometry": {"coordinates":[11.6886014938,42.8515586853],"type":"Point"}
}