{
  "type": "Feature",
  "properties": {
    "iso:country":"IT",
    "sg:address":"71/73, Via Montello 20038 Seregno",
    "sg:city":"Seregno",
    "sg:classifiers":[
        {
            "category":"Home & Garden",
            "subcategory":"Home Furnishings",
            "type":"Retail Goods"
        }
    ],
    "sg:phone":"+39 036 223 8510",
    "sg:postcode":"20038",
    "sg:province":"Milano",
    "sg:tags":[
        "household"
    ],
    "wof:name":"Ratti Fratelli",
    "wof:placetype":"venue"
},
  "geometry": {"coordinates":[9.225981,45.649963],"type":"Point"}
}