{
  "type": "Feature",
  "properties": {
    "iso:country":"IT",
    "sg:address":"25020 Flero",
    "sg:city":"Flero",
    "sg:orig_category":"Macchine Utensili E Impianti",
    "sg:phone":"+39 030 256 0110",
    "sg:postcode":"25020",
    "sg:province":"Brescia",
    "wof:name":"Mecolpress (s.p.a.)",
    "wof:placetype":"venue"
},
  "geometry": {"coordinates":[10.177735,45.474953],"type":"Point"}
}