{
  "type": "Feature",
  "properties": {
    "iso:country":"IT",
    "sg:address":"34, Via Delle Arnasche 20023 Cerro Maggiore",
    "sg:city":"Cerro Maggiore",
    "sg:classifiers":[
        {
            "category":"Professional",
            "subcategory":"Engineering",
            "type":"Services"
        }
    ],
    "sg:phone":"+39 0331 519550",
    "sg:postcode":"20023",
    "sg:province":"Milano",
    "sg:tags":[
        "machine",
        "-",
        "mechanical"
    ],
    "wof:name":"Minini 2000 S.r.l.",
    "wof:placetype":"venue"
},
  "geometry": {"coordinates":[8.9559879303,45.585105896],"type":"Point"}
}