{
  "type": "Feature",
  "properties": {
    "iso:country":"IT",
    "sg:address":"20121 Milano",
    "sg:city":"Milano",
    "sg:orig_category":"Banche E Servizi Finanziari. Avvocati, Notai E Servizi Legali",
    "sg:phone":"+39 02 659 0434",
    "sg:postcode":"20121",
    "sg:province":"Milano",
    "wof:name":"Professional Pool Srl",
    "wof:placetype":"venue"
},
  "geometry": {"coordinates":[9.187058,45.477249],"type":"Point"}
}