{
  "type": "Feature",
  "properties": {
    "iso:country":"IT",
    "sg:address":"00187 Roma",
    "sg:city":"Roma",
    "sg:classifiers":[
        {
            "category":"Banks & Credit Unions",
            "subcategory":"Bureau De Change",
            "type":"Services"
        }
    ],
    "sg:phone":"+39 06 4201 1199",
    "sg:postcode":"00187",
    "sg:province":"Roma",
    "sg:tags":[
        "services",
        "tourism",
        "public",
        "private",
        "transport"
    ],
    "sg:website":"http://www.ethiopianairlines.com",
    "wof:name":"Ethiopian Airlines",
    "wof:placetype":"venue"
},
  "geometry": {"coordinates":[12.491043,41.9044],"type":"Point"}
}