{
  "type": "Feature",
  "properties": {
    "addr:full":"46, Via Vittorio Emanuele Ii 15026 Oviglio Oviglio Alessandria 15026",
    "addr:postcode":"15026;15026",
    "addr:street":"Via Vittorio Emanuele Ii",
    "iso:country":"IT",
    "sg:address":"46, Via Vittorio Emanuele Ii 15026 Oviglio",
    "sg:city":"Oviglio",
    "sg:classifiers":[
        {
            "category":"Shopping",
            "type":"Retail Goods"
        }
    ],
    "sg:phone":"+39 0131 776497",
    "sg:postcode":"15026",
    "sg:province":"Alessandria",
    "sg:tags":[
        "finished",
        "-",
        "metallic"
    ],
    "wof:name":"Maestrello Di Maestrello Franco & C. (s.n.c.)",
    "wof:placetype":"venue"
},
  "geometry": {"coordinates":[8.4848613739,44.8642921448],"type":"Point"}
}