{
  "type": "Feature",
  "properties": {
    "iso:country":"IT",
    "sg:address":"Via Grassi Giovanni Battista 93 20157 Milano",
    "sg:city":"Milano",
    "sg:classifiers":[
        {
            "category":"Farming",
            "subcategory":"Orchard",
            "type":"Manufacturing & Wholesale Goods"
        }
    ],
    "sg:phone":"+39 02 3579 0257",
    "sg:postcode":"20157",
    "sg:province":"Milano",
    "sg:tags":[
        "switchgear"
    ],
    "sg:website":"www.galileoavionicaspa.it",
    "wof:name":"Galileo Avionica Spa",
    "wof:placetype":"venue"
},
  "geometry": {"coordinates":[9.203226,45.482468],"type":"Point"}
}