{
  "type": "Feature",
  "properties": {
    "iso:country":"IT",
    "sg:address":"Via Palmanova 185 20132 Milano",
    "sg:city":"Milano",
    "sg:classifiers":[
        {
            "category":"Organizations",
            "subcategory":"Community Association",
            "type":"Services"
        }
    ],
    "sg:phone":"+39 02 259281",
    "sg:postcode":"20132",
    "sg:province":"Milano",
    "sg:tags":[
        "transactional",
        "system"
    ],
    "sg:website":"www.prod-el.com",
    "wof:name":"Prod - El Spa",
    "wof:placetype":"venue"
},
  "geometry": {"coordinates":[9.249118,45.506477],"type":"Point"}
}