{
  "type": "Feature",
  "properties": {
    "iso:country":"IT",
    "sg:address":"21040 Venegono Inferiore",
    "sg:city":"Venegono Inferiore",
    "sg:orig_category":"Articoli Medico-sanitari Ed Ortopedici. Impianti, Attrezzature E Forniture Sanitarie Ed Ospedaliere",
    "sg:phone":"+39 0331 827520",
    "sg:postcode":"21040",
    "sg:province":"Varese",
    "sg:website":"http://www.relaxgym.it",
    "wof:name":"Relax Di Brogliato Lorenzo & C. Sas",
    "wof:placetype":"venue"
},
  "geometry": {"coordinates":[8.900614,45.737915],"type":"Point"}
}