{
  "type": "Feature",
  "properties": {
    "iso:country":"IT",
    "sg:address":"20099 Sesto San Giovanni",
    "sg:city":"Sesto San Giovanni",
    "sg:orig_category":"Arti Grafiche",
    "sg:phone":"+39 02 2622 0178",
    "sg:postcode":"20099",
    "sg:province":"Milano",
    "wof:name":"Pubbligrafica Di Ignizio R. & C. Snc",
    "wof:placetype":"venue"
},
  "geometry": {"coordinates":[9.234526,45.530319],"type":"Point"}
}