{
  "type": "Feature",
  "properties": {
    "iso:country":"IT",
    "sg:address":"24012 Brembilla",
    "sg:city":"Brembilla",
    "sg:orig_category":"Arredamenti - Produzione E Ingrosso",
    "sg:phone":"+39 0345 98108",
    "sg:postcode":"24012",
    "sg:province":"Bergamo",
    "sg:website":"http://www.fapasalvi.com",
    "wof:name":"F.a.p.a. Salvi Di Salvi Marco",
    "wof:placetype":"venue"
},
  "geometry": {"coordinates":[9.572093,45.693508],"type":"Point"}
}