{
  "type": "Feature",
  "properties": {
    "addr:full":"60020 Ancona Ancona 60020",
    "addr:postcode":"60020;60020",
    "iso:country":"IT",
    "sg:address":"60020 Ancona",
    "sg:orig_category":"Dolciumi E Gelati",
    "sg:phone":"+39 071 804 7093",
    "sg:postcode":"60020",
    "sg:province":"Ancona",
    "wof:name":"Giampaoli Industria Dolciaria Spa",
    "wof:placetype":"venue"
},
  "geometry": {"coordinates":[13.510361,43.549339],"type":"Point"}
}