{
  "type": "Feature",
  "properties": {
    "iso:country":"IT",
    "sg:address":"6/a, Via Del Capanno 26900 Lodi",
    "sg:city":"Lodi",
    "sg:classifiers":[
        {
            "category":"Professional",
            "subcategory":"Printing & Photocopies",
            "type":"Services"
        }
    ],
    "sg:phone":"+39 0371 413177",
    "sg:postcode":"26900",
    "sg:province":"Lodi",
    "wof:name":"Tipolitografia Senzalari Srl",
    "wof:placetype":"venue"
},
  "geometry": {"coordinates":[9.4985656738,45.3227386475],"type":"Point"}
}