{
  "type": "Feature",
  "properties": {
    "iso:country":"IT",
    "sg:address":"50037 San Piero A Sieve",
    "sg:city":"San Piero a Sieve",
    "sg:orig_category":"Tempo Libero - Articoli E Forniture. Forniture Per Congressi, Fiere E Manifestazioni. Regalistica Aziendale",
    "sg:postcode":"50037",
    "sg:province":"Firenze",
    "wof:name":"Robermap (s.r.l.)",
    "wof:placetype":"venue"
},
  "geometry": {"coordinates":[11.318495,43.959244],"type":"Point"}
}