{
  "type": "Feature",
  "properties": {
    "addr:full":"09125 Cagliari Cagliari Cagliari 09125",
    "addr:postcode":"09125;09125",
    "iso:country":"IT",
    "sg:address":"09125 Cagliari",
    "sg:city":"Cagliari",
    "sg:orig_category":"Sport - Articoli E Forniture",
    "sg:phone":"+39 070 663344",
    "sg:postcode":"09125",
    "sg:province":"Cagliari",
    "wof:name":"Manos Di Vincenzo & Ignazio Snc",
    "wof:placetype":"venue"
},
  "geometry": {"coordinates":[9.126246,39.208622],"type":"Point"}
}