{
  "type": "Feature",
  "properties": {
    "iso:country":"IT",
    "sg:address":"00010 Tivoli",
    "sg:city":"Tivoli",
    "sg:orig_category":"Lavanderie Industriali E Noleggio Biancheria",
    "sg:phone":"+39 0774 382319",
    "sg:postcode":"00010",
    "sg:province":"Roma",
    "wof:name":"Lavanderie Italiane Srl",
    "wof:placetype":"venue"
},
  "geometry": {"coordinates":[12.776485,41.952866],"type":"Point"}
}