{
  "type": "Feature",
  "properties": {
    "iso:country":"IT",
    "sg:address":"75, Via Fanti D'italia 43013 Langhirano",
    "sg:city":"Langhirano",
    "sg:classifiers":[
        {
            "category":"Food & Beverages",
            "subcategory":"Groceries & Convenience Stores",
            "type":"Retail Goods"
        }
    ],
    "sg:phone":"+39 0521 853348",
    "sg:postcode":"43013",
    "sg:province":"Parma",
    "sg:tags":[
        "product",
        "related"
    ],
    "wof:name":"Bedogni Egidio Spa",
    "wof:placetype":"venue"
},
  "geometry": {"coordinates":[10.2625379562,44.6065483093],"type":"Point"}
}