{
  "type": "Feature",
  "properties": {
    "addr:full":"Sda Statale, 544 Km 44,500 71049 Trinitapoli Trinitapoli Foggia 71049",
    "addr:housenumber":"44,500",
    "addr:postcode":"71049;71049",
    "addr:street":"544 Km",
    "iso:country":"IT",
    "sg:address":"Sda Statale, 544 Km 44,500 71049 Trinitapoli",
    "sg:city":"Trinitapoli",
    "sg:classifiers":[
        {
            "category":"Food & Beverages",
            "subcategory":"Liquor & Beverages",
            "type":"Retail Goods"
        }
    ],
    "sg:phone":"+39 0883 634032",
    "sg:postcode":"71049",
    "sg:province":"Foggia",
    "sg:tags":[
        "wine",
        "italian"
    ],
    "sg:website":"www.casaltrinita.it",
    "wof:name":"Cantina Cooperativa Produttori Agricoli Soc Coop Srl",
    "wof:placetype":"venue"
},
  "geometry": {"coordinates":[15.5447,41.462334],"type":"Point"}
}