{
  "type": "Feature",
  "properties": {
    "iso:country":"IT",
    "sg:address":"20093 Cologno Monzese",
    "sg:city":"Cologno Monzese",
    "sg:classifiers":[
        {
            "category":"Health Services",
            "subcategory":"Health Practitioner",
            "type":"Services"
        }
    ],
    "sg:phone":"+39 02 254 1624",
    "sg:postcode":"20093",
    "sg:province":"Milano",
    "sg:tags":[
        "medici"
    ],
    "wof:name":"Micali Carlo Olindo",
    "wof:placetype":"venue"
},
  "geometry": {"coordinates":[9.274766,45.522957],"type":"Point"}
}