{
  "type": "Feature",
  "properties": {
    "iso:country":"IT",
    "sg:address":"90036 Misilmeri",
    "sg:city":"Misilmeri",
    "sg:orig_category":"Scuole E Servizi Scolastici. Servizi Per Lo Sport E Il Tempo Libero",
    "sg:phone":"+39 091 871 2813",
    "sg:postcode":"90036",
    "sg:province":"Palermo",
    "wof:name":"Spazio Danza Club Di Giusy E Teresa Sole",
    "wof:placetype":"venue"
},
  "geometry": {"coordinates":[13.447509,38.026028],"type":"Point"}
}