{
  "type": "Feature",
  "properties": {
    "iso:country":"IT",
    "sg:address":"81025 Marcianise",
    "sg:city":"Marcianise",
    "sg:orig_category":"Forniture Per Edilizia E Lavori Pubblici",
    "sg:phone":"+39 0823 821009",
    "sg:postcode":"81025",
    "sg:province":"Caserta",
    "wof:name":"Laezza Spa",
    "wof:placetype":"venue"
},
  "geometry": {"coordinates":[14.3296785355,41.0266571045],"type":"Point"}
}