{
  "type": "Feature",
  "properties": {
    "iso:country":"IT",
    "sg:address":"64, Via Putignano 70013 Castellana Grotte",
    "sg:city":"Castellana Grotte",
    "sg:classifiers":[
        {
            "category":"Utilities",
            "subcategory":"Telephone",
            "type":"Services"
        }
    ],
    "sg:phone":"+39 080 496 8138",
    "sg:postcode":"70013",
    "sg:province":"Bari",
    "sg:tags":[
        "telecommunication"
    ],
    "wof:name":"Radio Puglia S.r.l.",
    "wof:placetype":"venue"
},
  "geometry": {"coordinates":[17.160454,40.879047],"type":"Point"}
}