{
  "type": "Feature",
  "properties": {
    "iso:country":"IT",
    "sg:address":"35042 Este",
    "sg:city":"Este",
    "sg:orig_category":"Studi E Consulenze Amministrative, Commerciali E Aziendali. Consulenze Tecniche, Amministrative E Perizie",
    "sg:phone":"+39 0429 602122",
    "sg:postcode":"35042",
    "sg:province":"Padova",
    "sg:website":"http://www.studiogest.it",
    "wof:name":"Studio Gest Srl",
    "wof:placetype":"venue"
},
  "geometry": {"coordinates":[11.651368,45.222122],"type":"Point"}
}