{
  "type": "Feature",
  "properties": {
    "iso:country":"IT",
    "sg:address":"25030 Paratico",
    "sg:city":"Paratico",
    "sg:orig_category":"Non-classified Establishments",
    "sg:phone":"+39 035 910558",
    "sg:postcode":"25030",
    "sg:province":"Brescia",
    "wof:name":"Gervasoni Graziano",
    "wof:placetype":"venue"
},
  "geometry": {"coordinates":[9.966609,45.656853],"type":"Point"}
}