{
  "type": "Feature",
  "properties": {
    "iso:country":"IT",
    "sg:address":"02015 Cittaducale",
    "sg:city":"Cittaducale",
    "sg:orig_category":"Non-classified Establishments",
    "sg:phone":"+39 0746 607308",
    "sg:postcode":"02015",
    "sg:province":"Rieti",
    "wof:name":"Arredamenti Rustici A.v.a.r. Di Tagliaferri Angelo Snc",
    "wof:placetype":"venue"
},
  "geometry": {"coordinates":[12.917609,42.41235],"type":"Point"}
}