{
  "type": "Feature",
  "properties": {
    "iso:country":"IT",
    "sg:address":"48018 Faenza",
    "sg:city":"Faenza",
    "sg:orig_category":"Valvole E Apparecchiature Di Misura. Forniture Per Attivita' Industriali",
    "sg:phone":"+39 0546 623100",
    "sg:postcode":"48018",
    "sg:province":"Ravenna",
    "wof:name":"Automazione Romagna Di Alberghi Devis & C. Sas",
    "wof:placetype":"venue"
},
  "geometry": {"coordinates":[11.911987,44.283077],"type":"Point"}
}