{
  "type": "Feature",
  "properties": {
    "iso:country":"IT",
    "sg:address":"193, Localita' Cheverel 11015 La Salle",
    "sg:city":"La Salle",
    "sg:classifiers":[
        {
            "category":"Manufacturing",
            "subcategory":"Lumber",
            "type":"Manufacturing & Wholesale Goods"
        }
    ],
    "sg:phone":"+39 0165 861077",
    "sg:postcode":"11015",
    "sg:province":"Aosta",
    "sg:tags":[
        "wood"
    ],
    "wof:name":"Bonoldi Gino & C. (s.n.c.)",
    "wof:placetype":"venue"
},
  "geometry": {"coordinates":[7.068046,45.764492],"type":"Point"}
}