{
  "type": "Feature",
  "properties": {
    "iso:country":"IT",
    "sg:address":"41015 Nonantola",
    "sg:city":"Nonantola",
    "sg:orig_category":"Arredi Ed Attrezzature Per Uffici",
    "sg:phone":"+39 059 548655",
    "sg:postcode":"41015",
    "sg:province":"Modena",
    "wof:name":"Alice Club S.a.s.",
    "wof:placetype":"venue"
},
  "geometry": {"coordinates":[11.017141,44.676186],"type":"Point"}
}