{
  "type": "Feature",
  "properties": {
    "iso:country":"IT",
    "sg:address":"20093 Cologno Monzese",
    "sg:city":"Cologno Monzese",
    "sg:orig_category":"Termotecnica E Riscaldamento, Apparecchiature E Servizi",
    "sg:phone":"+39 02 254 3190",
    "sg:postcode":"20093",
    "sg:province":"Milano",
    "wof:name":"Uniterm (s.r.l.)",
    "wof:placetype":"venue"
},
  "geometry": {"coordinates":[9.279947,45.544281],"type":"Point"}
}