{
  "type": "Feature",
  "properties": {
    "addr:full":"58100 Grosseto Grosseto Grosseto 58100",
    "addr:postcode":"58100;58100",
    "iso:country":"IT",
    "sg:address":"58100 Grosseto",
    "sg:city":"Grosseto",
    "sg:orig_category":"Banche E Servizi Finanziari",
    "sg:phone":"+39 0564 34453",
    "sg:postcode":"58100",
    "sg:province":"Grosseto",
    "wof:name":"Banca Di Credito Cooperativo Della Maremma Grossetana Scrl",
    "wof:placetype":"venue"
},
  "geometry": {"coordinates":[11.119008,42.776909],"type":"Point"}
}