{
  "type": "Feature",
  "properties": {
    "addr:full":"20017 Rho Rho Milano 20017",
    "addr:postcode":"20017;20017",
    "iso:country":"IT",
    "sg:address":"20017 Rho",
    "sg:city":"Rho",
    "sg:classifiers":[
        {
            "category":"Health Services",
            "subcategory":"Health Practitioner",
            "type":"Services"
        }
    ],
    "sg:phone":"+39 02 9390 1839",
    "sg:postcode":"20017",
    "sg:province":"Milano",
    "sg:tags":[
        "medici"
    ],
    "wof:name":"Banderali Giorgio",
    "wof:placetype":"venue"
},
  "geometry": {"coordinates":[9.073622,45.530712],"type":"Point"}
}