{
  "type": "Feature",
  "properties": {
    "iso:country":"IT",
    "sg:address":"Km. 90, Via Salaria Per Roma 02015 Cittaducale",
    "sg:city":"Cittaducale",
    "sg:classifiers":[
        {
            "category":"Building & Trades",
            "subcategory":"Construction",
            "type":"Services"
        }
    ],
    "sg:phone":"+39 0746 606128",
    "sg:postcode":"02015",
    "sg:province":"Rieti",
    "sg:tags":[
        "work",
        "public"
    ],
    "wof:name":"S.i.c.e.p. S.r.l.",
    "wof:placetype":"venue"
},
  "geometry": {"coordinates":[12.861179,42.403057],"type":"Point"}
}