{
  "type": "Feature",
  "properties": {
    "iso:country":"IT",
    "sg:address":"20149 Milano",
    "sg:city":"Milano",
    "sg:orig_category":"Petroli, Gas E Combustibili. Servizi E Lavori Industria Chimica. Servizi E Lavori Per Edilizia E Lavori Pubblici. Acqua, Luce, Gas E Societa' Di Esercizio Pubblico",
    "sg:phone":"+39 02 317669",
    "sg:postcode":"20149",
    "sg:province":"Milano",
    "wof:name":"Metangas (s.r.l.)",
    "wof:placetype":"venue"
},
  "geometry": {"coordinates":[9.1578397751,45.4838180542],"type":"Point"}
}