{
  "type": "Feature",
  "properties": {
    "addr:full":"Centro Direzionale 80143 Napoli Napoli Napoli 80143",
    "addr:postcode":"80143;80143",
    "iso:country":"IT",
    "sg:address":"Centro Direzionale 80143 Napoli",
    "sg:city":"Napoli",
    "sg:classifiers":[
        {
            "category":"Wholesale",
            "subcategory":"Machinery & Supplies",
            "type":"Manufacturing & Wholesale Goods"
        }
    ],
    "sg:phone":"+39 081 787 9859",
    "sg:postcode":"80143",
    "sg:province":"Napoli",
    "sg:tags":[
        "equipment",
        "precision"
    ],
    "wof:name":"Campus Srl",
    "wof:placetype":"venue"
},
  "geometry": {"coordinates":[14.2820453644,40.8569908142],"type":"Point"}
}