{
  "type": "Feature",
  "properties": {
    "addr:full":"Via Nicolardi Eduardo 4/12 80131 Napoli Napoli Napoli 80131",
    "addr:housenumber":"4 / 12",
    "addr:postcode":"80131;80131",
    "addr:street":"Via Nicolardi Eduardo",
    "iso:country":"IT",
    "sg:address":"Via Nicolardi Eduardo 4/12 80131 Napoli",
    "sg:city":"Napoli",
    "sg:orig_category":"Ladies' Shoes",
    "sg:phone":"+39 081 743 4000",
    "sg:postcode":"80131",
    "sg:province":"Napoli",
    "wof:name":"Attilio Spa",
    "wof:placetype":"venue"
},
  "geometry": {"coordinates":[14.251636,40.840096],"type":"Point"}
}