{
  "type": "Feature",
  "properties": {
    "iso:country":"IT",
    "sg:address":"Viale De Gasperi 16; S. Donato Milanese",
    "sg:classifiers":[
        {
            "category":"Banks & Credit Unions",
            "subcategory":"Bank",
            "type":"Services"
        }
    ],
    "sg:phone":"+39 02 5203 2168",
    "wof:name":"Banca Di Roma",
    "wof:placetype":"venue"
},
  "geometry": {"coordinates":[9.269878,45.423218],"type":"Point"}
}