{
  "type": "Feature",
  "properties": {
    "iso:country":"IT",
    "sg:address":"23900 Lecco",
    "sg:city":"Lecco",
    "sg:orig_category":"Imbiancatura",
    "sg:phone":"+39 0341 353385",
    "sg:postcode":"23900",
    "sg:province":"Lecco",
    "wof:name":"Fantasy Color Di Masciadri Franco",
    "wof:placetype":"venue"
},
  "geometry": {"coordinates":[9.415548,45.849552],"type":"Point"}
}