{
  "type": "Feature",
  "properties": {
    "iso:country":"IT",
    "sg:address":"56126 Pisa",
    "sg:city":"Pisa",
    "sg:orig_category":"Elaboratori Elettronici - Periferiche",
    "sg:phone":"+39 050 562286",
    "sg:postcode":"56126",
    "sg:province":"Pisa",
    "sg:website":"http://www.hibit.it",
    "wof:name":"Puccini Silvano - Hibit",
    "wof:placetype":"venue"
},
  "geometry": {"coordinates":[10.391387,43.72472],"type":"Point"}
}