{
  "type": "Feature",
  "properties": {
    "addr:full":"Via Oberdan, 41; Rivalta; 15010 Alessandria 15010",
    "addr:housenumber":"41",
    "addr:postcode":"15010;15010",
    "addr:street":"Via Oberdan",
    "iso:country":"IT",
    "sg:address":"Via Oberdan, 41; Rivalta; 15010",
    "sg:classifiers":[
        {
            "category":"Banks & Credit Unions",
            "subcategory":"Bank",
            "type":"Services"
        }
    ],
    "sg:phone":"+39 0144 72172",
    "sg:postcode":"15010",
    "sg:province":"Alessandria",
    "wof:name":"Cassa Di Risparmio Di Alessandria",
    "wof:placetype":"venue"
},
  "geometry": {"coordinates":[8.549345,44.709419],"type":"Point"}
}