{
  "type": "Feature",
  "properties": {
    "iso:country":"IT",
    "sg:address":"50131 Firenze",
    "sg:city":"Firenze",
    "sg:orig_category":"Termotecnica E Riscaldamento, Apparecchiature E Servizi. Prodotti Vari In Metallo",
    "sg:phone":"+39 055 57351",
    "sg:postcode":"50131",
    "sg:province":"Firenze",
    "sg:website":"http://www.paginegialle.it/ferramentacobianchi",
    "wof:name":"Ferramenta Cobianchi Spa",
    "wof:placetype":"venue"
},
  "geometry": {"coordinates":[11.274969,43.781193],"type":"Point"}
}