{
  "type": "Feature",
  "properties": {
    "addr:full":"Via Di Sesto 12 40037 Sasso Marconi Sasso Marconi Bologna 40037",
    "addr:housenumber":"12",
    "addr:postcode":"40037;40037",
    "addr:street":"Via Di Sesto",
    "iso:country":"IT",
    "sg:address":"Via Di Sesto 12 40037 Sasso Marconi",
    "sg:city":"Sasso Marconi",
    "sg:classifiers":[
        {
            "category":"Utilities",
            "subcategory":"Fuel Oil & Lpg",
            "type":"Services"
        }
    ],
    "sg:phone":"+39 051 841347",
    "sg:postcode":"40037",
    "sg:province":"Bologna",
    "sg:tags":[
        "fluid",
        "mechanic"
    ],
    "wof:name":"Nuova S.e.c.o. Srl",
    "wof:placetype":"venue"
},
  "geometry": {"coordinates":[11.3214960098,44.4225502014],"type":"Point"}
}