{
  "type": "Feature",
  "properties": {
    "iso:country":"IT",
    "sg:address":"Via Galileo Ferraris 1 10040 Val Della Torre",
    "sg:city":"Val della Torre",
    "sg:orig_category":"Plastic Spare Part Manufacturing, Contract Work",
    "sg:phone":"+39 011 968 9070",
    "sg:postcode":"10040",
    "sg:province":"Torino",
    "wof:name":"Bdm Plast Srl",
    "wof:placetype":"venue"
},
  "geometry": {"coordinates":[7.5303688049,45.1409034729],"type":"Point"}
}