{
  "type": "Feature",
  "properties": {
    "iso:country":"IT",
    "sg:address":"31020 Revine Lago",
    "sg:city":"Lago",
    "sg:orig_category":"Non-classified Establishments",
    "sg:phone":"+39 0438 929177",
    "sg:postcode":"31020",
    "sg:province":"Treviso",
    "wof:name":"Tempora S.r.l.",
    "wof:placetype":"venue"
},
  "geometry": {"coordinates":[12.206882,45.982655],"type":"Point"}
}