{
  "type": "Feature",
  "properties": {
    "iso:country":"IT",
    "sg:address":"20131 Milano",
    "sg:city":"Milano",
    "sg:orig_category":"Macchine E Forniture Per Ecologia E Smaltimento Rifiuti. Termotecnica E Riscaldamento, Apparecchiature E Servizi",
    "sg:phone":"+39 02 202 2101",
    "sg:postcode":"20131",
    "sg:province":"Milano",
    "wof:name":"Med Services Srl",
    "wof:placetype":"venue"
},
  "geometry": {"coordinates":[9.217151,45.485336],"type":"Point"}
}