{
  "type": "Feature",
  "properties": {
    "iso:country":"IT",
    "sg:address":"3, Via Pergolesi Giovanni Battista 00198 Roma",
    "sg:city":"Roma",
    "sg:classifiers":[
        {
            "category":"Professional",
            "subcategory":"Business Services",
            "type":"Services"
        }
    ],
    "sg:phone":"+39 39068440141",
    "sg:postcode":"00198",
    "sg:province":"Roma",
    "sg:tags":[
        "advice"
    ],
    "wof:name":"Ambasciata Presso Lo Stato Italiano Austria",
    "wof:placetype":"venue"
},
  "geometry": {"coordinates":[12.482325,41.895466],"type":"Point"}
}