{
  "type": "Feature",
  "properties": {
    "iso:country":"IT",
    "sg:address":"08100 Nuoro",
    "sg:city":"Nuoro",
    "sg:orig_category":"Campeggio. Accessori Dei Mezzi Di Trasporto",
    "sg:phone":"+39 0784 32077",
    "sg:postcode":"08100",
    "sg:province":"Nuoro",
    "wof:name":"Pulina Tende E Sistemi Per Tende",
    "wof:placetype":"venue"
},
  "geometry": {"coordinates":[9.328871,40.31831],"type":"Point"}
}