{
  "type": "Feature",
  "properties": {
    "addr:full":"14, Via Dei Sandron 31044 Montebelluna Montebelluna Treviso 31044",
    "addr:postcode":"31044;31044",
    "addr:street":"Via Dei Sandron",
    "iso:country":"IT",
    "sg:address":"14, Via Dei Sandron 31044 Montebelluna",
    "sg:city":"Montebelluna",
    "sg:classifiers":[
        {
            "category":"Personal",
            "subcategory":"Shoe Repair & Shine",
            "type":"Services"
        }
    ],
    "sg:phone":"+39 0423 601211",
    "sg:postcode":"31044",
    "sg:province":"Treviso",
    "sg:tags":[
        "leather"
    ],
    "wof:name":"Inprex (s.r.l.)",
    "wof:placetype":"venue"
},
  "geometry": {"coordinates":[12.035375,45.763378],"type":"Point"}
}