{
  "type": "Feature",
  "properties": {
    "iso:country":"IT",
    "sg:address":"00036 Palestrina",
    "sg:city":"Palestrina",
    "sg:orig_category":"Automobili E Mezzi Di Trasporto",
    "sg:phone":"+39 06 2323 9367",
    "sg:postcode":"00036",
    "sg:province":"Roma",
    "wof:name":"Emmebi Moto Sas Di Baccelli Silvia & C.",
    "wof:placetype":"venue"
},
  "geometry": {"coordinates":[12.885187,41.83242],"type":"Point"}
}