{
  "type": "Feature",
  "properties": {
    "iso:country":"IT",
    "sg:address":"57127 Livorno",
    "sg:city":"Livorno",
    "sg:orig_category":"Servizi E Lavori Per Abbigliamento E Pelletterie",
    "sg:phone":"+39 0586 805205",
    "sg:postcode":"57127",
    "sg:province":"Livorno",
    "wof:name":"Lavanderia S. Jacopo",
    "wof:placetype":"venue"
},
  "geometry": {"coordinates":[10.30412,43.532532],"type":"Point"}
}