{
  "type": "Feature",
  "properties": {
    "iso:country":"IT",
    "sg:address":"14100 Asti",
    "sg:city":"Asti",
    "sg:orig_category":"Prodotti Chimici Di Base",
    "sg:phone":"+39 0141 351925",
    "sg:postcode":"14100",
    "sg:province":"Asti",
    "wof:name":"Maxi Import Srl",
    "wof:placetype":"venue"
},
  "geometry": {"coordinates":[8.2654676437,44.8719100952],"type":"Point"}
}