{
  "type": "Feature",
  "properties": {
    "addr:full":"25073 Bovezzo Bovezzo Brescia 25073",
    "addr:postcode":"25073;25073",
    "iso:country":"IT",
    "sg:address":"25073 Bovezzo",
    "sg:city":"Bovezzo",
    "sg:orig_category":"Bevande, Vini E Liquori",
    "sg:phone":"+39 030 271 3242",
    "sg:postcode":"25073",
    "sg:province":"Brescia",
    "wof:name":"Rivetti E Zammarchi Snc",
    "wof:placetype":"venue"
},
  "geometry": {"coordinates":[10.234959,45.591145],"type":"Point"}
}