{
  "type": "Feature",
  "properties": {
    "addr:full":"21/b, Via Alla Pineta 38068 Rovereto Rovereto Trento 38068",
    "addr:housenumber":"21 / b",
    "addr:postcode":"38068;38068",
    "addr:street":"Via Alla Pineta",
    "iso:country":"IT",
    "sg:address":"21/b, Via Alla Pineta 38068 Rovereto",
    "sg:city":"Rovereto",
    "sg:classifiers":[
        {
            "category":"Utilities",
            "subcategory":"Electric",
            "type":"Services"
        }
    ],
    "sg:phone":"+39 0464 486208",
    "sg:postcode":"38068",
    "sg:province":"Trento",
    "sg:tags":[
        "component",
        "electronic"
    ],
    "wof:name":"Fabbrica Trentina Conduttori S.r.l.",
    "wof:placetype":"venue"
},
  "geometry": {"coordinates":[11.007529,45.863983],"type":"Point"}
}