{
  "type": "Feature",
  "properties": {
    "iso:country":"IT",
    "sg:address":"2, Via Etna 21010 Cardano Al Campo",
    "sg:city":"Cardano al Campo",
    "sg:classifiers":[
        {
            "category":"Shopping",
            "subcategory":"Crafts & Fabrics",
            "type":"Retail Goods"
        }
    ],
    "sg:phone":"+39 0331 730551",
    "sg:postcode":"21010",
    "sg:province":"Varese",
    "wof:name":"I.t.s. Di Pigni A. & C. (s.n.c.)",
    "wof:placetype":"venue"
},
  "geometry": {"coordinates":[8.7598237991,45.6509780884],"type":"Point"}
}