{
  "type": "Feature",
  "properties": {
    "iso:country":"IT",
    "sg:address":"20123 Milano",
    "sg:city":"Milano",
    "sg:orig_category":"Ceramiche: Prodotti E Lavorazioni. Forniture Per Attivita' Industriali",
    "sg:phone":"+39 02 805 3332",
    "sg:postcode":"20123",
    "sg:province":"Milano",
    "wof:name":"Capello Maria Grazia",
    "wof:placetype":"venue"
},
  "geometry": {"coordinates":[9.173432,45.464714],"type":"Point"}
}