{
  "type": "Feature",
  "properties": {
    "iso:country":"IT",
    "sg:address":"Via Erbosa 2/b 47030 Gatteo",
    "sg:classifiers":[
        {
            "category":"Shopping",
            "subcategory":"Event Tickets",
            "type":"Retail Goods"
        }
    ],
    "sg:phone":"+39 0541 816311",
    "sg:postcode":"47030",
    "sg:province":"Forl\u00ec-Cesena",
    "sg:tags":[
        "billfold"
    ],
    "sg:website":"www.pollini.com",
    "wof:name":"Pollini Spa",
    "wof:placetype":"venue"
},
  "geometry": {"coordinates":[11.980461,43.994766],"type":"Point"}
}