{
  "type": "Feature",
  "properties": {
    "iso:country":"IT",
    "sg:address":"10143 Torino",
    "sg:city":"Torino",
    "sg:orig_category":"Pubblica Amministrazione",
    "sg:phone":"+39 011 751918",
    "sg:postcode":"10143",
    "sg:province":"Torino",
    "wof:name":"Provincia Di Torino",
    "wof:placetype":"venue"
},
  "geometry": {"coordinates":[7.6468243599,45.0786399841],"type":"Point"}
}