{
  "type": "Feature",
  "properties": {
    "addr:full":"Ctr Pezzamandra 95045 Misterbianco Misterbianco Catania 95045",
    "addr:postcode":"95045;95045",
    "iso:country":"IT",
    "sg:address":"Ctr Pezzamandra 95045 Misterbianco",
    "sg:city":"Misterbianco",
    "sg:classifiers":[
        {
            "category":"Manufacturing",
            "subcategory":"Metals",
            "type":"Manufacturing & Wholesale Goods"
        }
    ],
    "sg:phone":"+39 095 474547",
    "sg:postcode":"95045",
    "sg:province":"Catania",
    "sg:tags":[
        "machine",
        "cutting",
        "automatic",
        "precision"
    ],
    "sg:website":"www.trafime.it",
    "wof:name":"Tra.fi.me. S.p.a.",
    "wof:placetype":"venue"
},
  "geometry": {"coordinates":[15.020676,37.529091],"type":"Point"}
}