{
  "type": "Feature",
  "properties": {
    "addr:full":"24020 Schilpario Schilpario Bergamo 24020",
    "addr:postcode":"24020;24020",
    "iso:country":"IT",
    "sg:address":"24020 Schilpario",
    "sg:city":"Schilpario",
    "sg:orig_category":"Servizi E Lavori Per Arredamento E Industria Del Legno",
    "sg:phone":"+39 0346 55217",
    "sg:postcode":"24020",
    "sg:province":"Bergamo",
    "wof:name":"Piantoni Lucio Srl",
    "wof:placetype":"venue"
},
  "geometry": {"coordinates":[10.110931,45.978798],"type":"Point"}
}