{
  "type": "Feature",
  "properties": {
    "iso:country":"IT",
    "sg:address":"50019 Sesto Fiorentino",
    "sg:city":"Sesto Fiorentino",
    "sg:orig_category":"Gas Auto Impianti - Produzione, Commercio E Installazione",
    "sg:phone":"+39 055 420 1432",
    "sg:postcode":"50019",
    "sg:province":"Firenze",
    "wof:name":"Bigas Di Bigliotti Alfredo E C. Snc",
    "wof:placetype":"venue"
},
  "geometry": {"coordinates":[11.180806,43.832012],"type":"Point"}
}