{
  "type": "Feature",
  "properties": {
    "iso:country":"IT",
    "sg:address":"14/c, Via Leopardi 60010 Ostra Vetere",
    "sg:city":"Ostra",
    "sg:classifiers":[
        {
            "category":"Shopping",
            "subcategory":"Clothing, Apparel, & Fashions",
            "type":"Retail Goods"
        }
    ],
    "sg:phone":"+39 39071965077",
    "sg:postcode":"60010",
    "sg:province":"Ancona",
    "sg:tags":[
        "clothes"
    ],
    "wof:name":"Tecnoconf Di Ciarloni Lino",
    "wof:placetype":"venue"
},
  "geometry": {"coordinates":[13.518757,43.615856],"type":"Point"}
}