{
  "type": "Feature",
  "properties": {
    "iso:country":"IT",
    "sg:address":"95014 Giarre",
    "sg:city":"Giarre",
    "sg:orig_category":"Abbigliamento Intimo, Calze E Costumi Da Bagno. Articoli Medico-sanitari Ed Ortopedici",
    "sg:phone":"+39 095 937324",
    "sg:postcode":"95014",
    "sg:province":"Catania",
    "wof:name":"Raciti Giovanni",
    "wof:placetype":"venue"
},
  "geometry": {"coordinates":[15.192063,37.725338],"type":"Point"}
}