{
  "type": "Feature",
  "properties": {
    "iso:country":"IT",
    "sg:address":"20077 Melegnano",
    "sg:city":"Melegnano",
    "sg:orig_category":"Finanziamenti E Mutui",
    "sg:phone":"+39 02 9812 7310",
    "sg:postcode":"20077",
    "sg:province":"Milano",
    "wof:name":"Lotty Fin Srl",
    "wof:placetype":"venue"
},
  "geometry": {"coordinates":[9.2502441406,45.3935050964],"type":"Point"}
}