{
  "type": "Feature",
  "properties": {
    "iso:country":"IT",
    "sg:address":"20090 Pieve Emanuele",
    "sg:city":"Pieve Emanuele",
    "sg:orig_category":"Autotrasporti",
    "sg:phone":"+39 02 9042 7149",
    "sg:postcode":"20090",
    "sg:province":"Milano",
    "wof:name":"M.t.c. Snc",
    "wof:placetype":"venue"
},
  "geometry": {"coordinates":[9.185452,45.370743],"type":"Point"}
}