{
  "type": "Feature",
  "properties": {
    "iso:country":"IT",
    "sg:address":"23801 Calolziocorte",
    "sg:city":"Calolziocorte",
    "sg:orig_category":"Bevande, Vini E Liquori",
    "sg:phone":"+39 0341 641131",
    "sg:postcode":"23801",
    "sg:province":"Lecco",
    "wof:name":"Cora'l Snc Di Riva Umberto & C.",
    "wof:placetype":"venue"
},
  "geometry": {"coordinates":[9.436275,45.789406],"type":"Point"}
}