{
  "type": "Feature",
  "properties": {
    "iso:country":"IT",
    "sg:address":"35030 Selvazzano Dentro",
    "sg:city":"Caselle",
    "sg:orig_category":"Videogiochi, Flippers E Biliardini - Produzione E Ingrosso",
    "sg:phone":"+39 049 633910",
    "sg:postcode":"35030",
    "sg:province":"Padova",
    "wof:name":"Microhard Elettronica Srl",
    "wof:placetype":"venue"
},
  "geometry": {"coordinates":[11.815688,45.403782],"type":"Point"}
}