{
  "type": "Feature",
  "properties": {
    "addr:full":"296, Via De Gasperi Alcide 84018 Scafati Scafati Salerno 84018",
    "addr:housenumber":"296",
    "addr:postcode":"84018;84018",
    "addr:street":"Via De Gasperi Alcide",
    "iso:country":"IT",
    "sg:address":"296, Via De Gasperi Alcide 84018 Scafati",
    "sg:city":"Scafati",
    "sg:classifiers":[
        {
            "category":"Home & Garden",
            "subcategory":"Home Furnishings",
            "type":"Retail Goods"
        }
    ],
    "sg:phone":"+39 081 863 6349",
    "sg:postcode":"84018",
    "sg:province":"Salerno",
    "sg:tags":[
        "household"
    ],
    "wof:name":"Pompei Art Di De Micco Pasquale",
    "wof:placetype":"venue"
},
  "geometry": {"coordinates":[14.765912,40.677956],"type":"Point"}
}