{
  "type": "Feature",
  "properties": {
    "iso:country":"IT",
    "sg:address":"00182 Roma",
    "sg:city":"Roma",
    "sg:orig_category":"Abbigliamento Esterno, Maglierie E Pelliccerie",
    "sg:phone":"+39 06 701 7706",
    "sg:postcode":"00182",
    "sg:province":"Roma",
    "wof:name":"Agostini Sartoria",
    "wof:placetype":"venue"
},
  "geometry": {"coordinates":[12.519804,41.87886],"type":"Point"}
}