{
  "type": "Feature",
  "properties": {
    "iso:country":"IT",
    "sg:address":"Via Centro Industriale Europeo 29 22078 Turate",
    "sg:city":"Turate",
    "sg:classifiers":[
        {
            "category":"Shopping",
            "subcategory":"Clothing, Apparel, & Fashions",
            "type":"Retail Goods"
        }
    ],
    "sg:phone":"+39 02 968 2135",
    "sg:postcode":"22078",
    "sg:province":"Como",
    "sg:tags":[
        "clothing",
        "fabric"
    ],
    "wof:name":"Lyontess Srl",
    "wof:placetype":"venue"
},
  "geometry": {"coordinates":[9.012887,45.650463],"type":"Point"}
}