{
  "type": "Feature",
  "properties": {
    "iso:country":"IT",
    "sg:address":"5, Via Dell' Industria 36054 Montebello Vicentino",
    "sg:city":"Montebello Vicentino",
    "sg:classifiers":[
        {
            "category":"Wholesale",
            "subcategory":"Drugs",
            "type":"Manufacturing & Wholesale Goods"
        }
    ],
    "sg:phone":"+39 0444 440700",
    "sg:postcode":"36054",
    "sg:province":"Vicenza",
    "sg:tags":[
        "chemical",
        "pharmaceutical"
    ],
    "wof:name":"Neochimica Italia S.r.l.",
    "wof:placetype":"venue"
},
  "geometry": {"coordinates":[11.372439,45.4417],"type":"Point"}
}