{
  "type": "Feature",
  "properties": {
    "addr:full":"17, Via Cecinese 51036 Larciano Larciano Pistoia 51036",
    "addr:postcode":"51036;51036",
    "addr:street":"Via Cecinese",
    "iso:country":"IT",
    "sg:address":"17, Via Cecinese 51036 Larciano",
    "sg:city":"Larciano",
    "sg:classifiers":[
        {
            "category":"Manufacturing",
            "subcategory":"Rubber & Plastics",
            "type":"Manufacturing & Wholesale Goods"
        }
    ],
    "sg:phone":"+39 39057384547",
    "sg:postcode":"51036",
    "sg:province":"Pistoia",
    "wof:name":"L.s. Di Lotti Stefano",
    "wof:placetype":"venue"
},
  "geometry": {"coordinates":[10.8575515747,43.8363189697],"type":"Point"}
}