{
  "type": "Feature",
  "properties": {
    "addr:full":"21047 Saronno Saronno Varese 21047",
    "addr:postcode":"21047;21047",
    "iso:country":"IT",
    "sg:address":"21047 Saronno",
    "sg:city":"Saronno",
    "sg:orig_category":"Serramenti Ed Infissi",
    "sg:phone":"+39 02 9670 0244",
    "sg:postcode":"21047",
    "sg:province":"Varese",
    "wof:name":"Gierre Automazioni Snc",
    "wof:placetype":"venue"
},
  "geometry": {"coordinates":[9.046243,45.625366],"type":"Point"}
}