{
  "type": "Feature",
  "properties": {
    "iso:country":"IT",
    "sg:address":"90133 Palermo",
    "sg:city":"Palermo",
    "sg:orig_category":"Ricambi E Componenti Dei Mezzi Di Trasporto",
    "sg:phone":"+39 091 611 8475",
    "sg:postcode":"90133",
    "sg:province":"Palermo",
    "wof:name":"Evoluzione Moto Di Arcara Antonino",
    "wof:placetype":"venue"
},
  "geometry": {"coordinates":[13.365949,38.115482],"type":"Point"}
}