{
  "type": "Feature",
  "properties": {
    "iso:country":"IT",
    "sg:address":"Via G. Di Vittorio, 2/1 43056 San Polo",
    "sg:city":"San Polo",
    "sg:orig_category":"Basketball Courts",
    "sg:phone":"+39 0521 310211",
    "sg:postcode":"43056",
    "sg:province":"Parma",
    "sg:website":"www.errea.it",
    "wof:name":"Errea Sport S.p.a.",
    "wof:placetype":"venue"
},
  "geometry": {"coordinates":[10.357239,44.886486],"type":"Point"}
}