{
  "type": "Feature",
  "properties": {
    "iso:country":"IT",
    "sg:address":"20154 Milano",
    "sg:city":"Milano",
    "sg:orig_category":"Scuole E Servizi Scolastici. Ricerca, Selezione E Formazione Del Personale. Pubblica Amministrazione",
    "sg:phone":"+39 02 331 5587",
    "sg:postcode":"20154",
    "sg:province":"Milano",
    "wof:name":"Scuole Pubbliche/scuole Elementari/masch. G. Giusti Segreteria",
    "wof:placetype":"venue"
},
  "geometry": {"coordinates":[9.176764,45.480106],"type":"Point"}
}