{
  "type": "Feature",
  "properties": {
    "iso:country":"IT",
    "sg:address":"20052 Monza",
    "sg:city":"Monza",
    "sg:orig_category":"Lampade A Snodo, A Stelo E Da Tavolo",
    "sg:phone":"+39 039 746889",
    "sg:postcode":"20052",
    "sg:province":"Milano",
    "wof:name":"Dada Naty Di Daniela Mantegazza",
    "wof:placetype":"venue"
},
  "geometry": {"coordinates":[9.198614,45.456535],"type":"Point"}
}