{
  "type": "Feature",
  "properties": {
    "iso:country":"IT",
    "sg:address":"20021 Bollate",
    "sg:city":"Bollate",
    "sg:orig_category":"Termotecnica E Riscaldamento, Apparecchiature E Servizi. Valvole E Apparecchiature Di Misura. Macchine, Strumenti Ed Apparecchi Per Attivita' Industriali",
    "sg:postcode":"20021",
    "sg:province":"Milano",
    "wof:name":"Ter.man.90 Strumentazione Industriale (s.r.l.)",
    "wof:placetype":"venue"
},
  "geometry": {"coordinates":[9.08859,45.505161],"type":"Point"}
}