{
  "type": "Feature",
  "properties": {
    "iso:country":"IT",
    "sg:address":"02030 San Giovanni Reatino",
    "sg:orig_category":"Impianti Sportivi E Ricreativi - Esercizio",
    "sg:phone":"+39 338 988 6884",
    "sg:postcode":"02030",
    "sg:province":"Rieti",
    "wof:name":"Ass. Culturale E Ricreativa Fontellisola",
    "wof:placetype":"venue"
},
  "geometry": {"coordinates":[12.4814,42.362358],"type":"Point"}
}