{
  "type": "Feature",
  "properties": {
    "iso:country":"IT",
    "sg:address":"162, Via Duomo 80138 Napoli",
    "sg:city":"Napoli",
    "sg:classifiers":[
        {
            "category":"Shopping",
            "subcategory":"Jewelry",
            "type":"Retail Goods"
        }
    ],
    "sg:phone":"+39 39081441942",
    "sg:postcode":"80138",
    "sg:province":"Napoli",
    "sg:tags":[
        "jewellery"
    ],
    "wof:name":"Taiwan Di Crispo Carlo & C. S.n.c.",
    "wof:placetype":"venue"
},
  "geometry": {"coordinates":[14.259453,40.852707],"type":"Point"}
}