{
  "type": "Feature",
  "properties": {
    "iso:country":"IT",
    "sg:address":"22/c, V. Dell'artigianato 36045 Lonigo",
    "sg:city":"Lonigo",
    "sg:classifiers":[
        {
            "category":"Manufacturing",
            "subcategory":"Textiles",
            "type":"Manufacturing & Wholesale Goods"
        }
    ],
    "sg:phone":"+39 0444 831411",
    "sg:postcode":"36045",
    "sg:province":"Vicenza",
    "sg:tags":[
        "leather",
        "raw",
        "material",
        "-"
    ],
    "sg:website":"http://www.paginegialle.it/conceriasvp",
    "wof:name":"S.v.p. - Societ\u00c0 Vicentina Pellami Srl",
    "wof:placetype":"venue"
},
  "geometry": {"coordinates":[11.540307,45.545906],"type":"Point"}
}