{
  "type": "Feature",
  "properties": {
    "addr:full":"04019 Terracina Terracina Latina 04019",
    "addr:postcode":"04019;04019",
    "iso:country":"IT",
    "sg:address":"04019 Terracina",
    "sg:city":"Terracina",
    "sg:orig_category":"Studi E Consulenze Amministrative, Commerciali E Aziendali. Studi E Consulenze Tecniche E Industriali. Consulenze Tecniche, Amministrative E Perizie",
    "sg:phone":"+39 0773 726495",
    "sg:postcode":"04019",
    "sg:province":"Latina",
    "wof:name":"Baraldi P.i. Paolo",
    "wof:placetype":"venue"
},
  "geometry": {"coordinates":[13.246299,41.28949],"type":"Point"}
}