{
  "type": "Feature",
  "properties": {
    "addr:full":"10077 San Maurizio Canavese San Maurizio Canavese Torino 10077",
    "addr:housenumber":"10077",
    "addr:postcode":"10077",
    "addr:street":"San",
    "iso:country":"IT",
    "sg:address":"10077 San Maurizio Canavese",
    "sg:city":"San Maurizio Canavese",
    "sg:orig_category":"Pareti Mobili E Divisorie",
    "sg:phone":"+39 011 924 4542",
    "sg:postcode":"10077",
    "sg:province":"Torino",
    "sg:website":"http://www.bromar.it",
    "wof:name":"Bromar Di Bronzi Gaspare",
    "wof:placetype":"venue"
},
  "geometry": {"coordinates":[7.6406373978,45.2084655762],"type":"Point"}
}