{
  "type": "Feature",
  "properties": {
    "iso:country":"IT",
    "sg:address":"20060 Basiano",
    "sg:city":"Basiano",
    "sg:orig_category":"Prodotti Chimici Di Base. Macchine E Forniture Per Ecologia E Smaltimento Rifiuti",
    "sg:phone":"+39 02 9576 2001",
    "sg:postcode":"20060",
    "sg:province":"Milano",
    "wof:name":"Pica Italia Spa",
    "wof:placetype":"venue"
},
  "geometry": {"coordinates":[9.1097898483,45.4295158386],"type":"Point"}
}