{
  "type": "Feature",
  "properties": {
    "addr:full":"22100 Como Como Como 22100",
    "addr:postcode":"22100;22100",
    "iso:country":"IT",
    "sg:address":"22100 Como",
    "sg:city":"Como",
    "sg:orig_category":"Studi E Consulenze Tecniche E Industriali. Consulenze Tecniche, Amministrative E Perizie. Professionisti - Studi E Servizi Ed Associazioni Di Interesse Aziendale",
    "sg:phone":"+39 031 260740",
    "sg:postcode":"22100",
    "sg:province":"Como",
    "wof:name":"Di Gloria Fabrizio",
    "wof:placetype":"venue"
},
  "geometry": {"coordinates":[9.092408,45.800983],"type":"Point"}
}