{
  "type": "Feature",
  "properties": {
    "iso:country":"IT",
    "sg:address":"37059 Zevio",
    "sg:city":"Zevio",
    "sg:orig_category":"Articoli Pulizia",
    "sg:phone":"+39 045 873 2070",
    "sg:postcode":"37059",
    "sg:province":"Verona",
    "sg:website":"http://www.rossignoli.net",
    "wof:name":"Rossignoli Franco & C. Snc",
    "wof:placetype":"venue"
},
  "geometry": {"coordinates":[11.042271,45.36388],"type":"Point"}
}