{
  "type": "Feature",
  "properties": {
    "iso:country":"IT",
    "sg:address":"20144 Milano",
    "sg:city":"Milano",
    "sg:orig_category":"Macchine, Impianti E Forniture Per Industria Grafica, Cartaria E Cartotecnica. Prodotti Chimici Secondari",
    "sg:phone":"+39 02 837 5455",
    "sg:postcode":"20144",
    "sg:province":"Milano",
    "wof:name":"Colorgraf (s.p.a.)",
    "wof:placetype":"venue"
},
  "geometry": {"coordinates":[9.163307,45.454525],"type":"Point"}
}