{
  "type": "Feature",
  "properties": {
    "addr:full":"90010 Campofelice Roccella Palermo 90010",
    "addr:postcode":"90010;90010",
    "addr:street":"Roccella",
    "iso:country":"IT",
    "sg:address":"90010 Campofelice Roccella",
    "sg:orig_category":"Alberghi",
    "sg:phone":"+39 0921 933815",
    "sg:postcode":"90010",
    "sg:province":"Palermo",
    "wof:name":"Plaia D'himera Park Hotel",
    "wof:placetype":"venue"
},
  "geometry": {"coordinates":[13.886421,37.991039],"type":"Point"}
}