{
  "type": "Feature",
  "properties": {
    "iso:country":"IT",
    "sg:address":"9, V. Piemonte 35043 Monselice",
    "sg:city":"Monselice",
    "sg:classifiers":[
        {
            "category":"Professional",
            "subcategory":"Engineering",
            "type":"Services"
        }
    ],
    "sg:phone":"+39 0429 784669",
    "sg:postcode":"35043",
    "sg:province":"Padova",
    "sg:tags":[
        "machine",
        "-",
        "mechanical"
    ],
    "sg:website":"http://www.paginegialle.it/",
    "wof:name":"Ge.i.cos",
    "wof:placetype":"venue"
},
  "geometry": {"coordinates":[11.747706,45.22274],"type":"Point"}
}