{
  "type": "Feature",
  "properties": {
    "iso:country":"IT",
    "sg:address":"06128 Perugia",
    "sg:city":"Perugia",
    "sg:orig_category":"Climatizzazione E Condizionamento, Apparecchiature E Servizi. Accessori Dei Mezzi Di Trasporto",
    "sg:phone":"+39 075 528 9697",
    "sg:postcode":"06128",
    "sg:province":"Perugia",
    "wof:name":"Cielle Snc Di Laloni N. & C.",
    "wof:placetype":"venue"
},
  "geometry": {"coordinates":[12.360706,43.093658],"type":"Point"}
}