{
  "type": "Feature",
  "properties": {
    "iso:country":"IT",
    "sg:address":"25016 Ghedi",
    "sg:city":"Ghedi",
    "sg:orig_category":"Acciaierie E Fonderie",
    "sg:phone":"+39 030 905 8411",
    "sg:postcode":"25016",
    "sg:province":"Brescia",
    "wof:name":"L.a.s. Laminazione Acciai Speciali Spa",
    "wof:placetype":"venue"
},
  "geometry": {"coordinates":[9.975315,45.552372],"type":"Point"}
}