{
  "type": "Feature",
  "properties": {
    "addr:full":"09094 Marrubiu Marrubiu Oristano 09094",
    "addr:postcode":"09094;09094",
    "iso:country":"IT",
    "sg:address":"09094 Marrubiu",
    "sg:city":"Marrubiu",
    "sg:orig_category":"Serramenti Ed Infissi",
    "sg:phone":"+39 0783 859393",
    "sg:postcode":"09094",
    "sg:province":"Oristano",
    "wof:name":"Cicu Giuseppe",
    "wof:placetype":"venue"
},
  "geometry": {"coordinates":[8.671061,39.769875],"type":"Point"}
}