{
  "type": "Feature",
  "properties": {
    "iso:country":"IT",
    "sg:address":"00199 Roma",
    "sg:city":"Roma",
    "sg:orig_category":"Scuole E Servizi Scolastici. Servizi Per Lo Sport E Il Tempo Libero",
    "sg:phone":"+39 06 8621 8225",
    "sg:postcode":"00199",
    "sg:province":"Roma",
    "wof:name":"A.s. Club Olimpico Romano",
    "wof:placetype":"venue"
},
  "geometry": {"coordinates":[12.514036,41.927052],"type":"Point"}
}