{
  "type": "Feature",
  "properties": {
    "iso:country":"IT",
    "sg:address":"00156 Roma",
    "sg:city":"Roma",
    "sg:orig_category":"Servizi Di Magazzinaggio E Movimentazione",
    "sg:phone":"+39 06 411 2531",
    "sg:postcode":"00156",
    "sg:province":"Roma",
    "wof:name":"Mirazita Massimo",
    "wof:placetype":"venue"
},
  "geometry": {"coordinates":[12.990834,42.010174],"type":"Point"}
}