{
  "type": "Feature",
  "properties": {
    "iso:country":"IT",
    "sg:address":"00151 Roma",
    "sg:city":"Roma",
    "sg:classifiers":[
        {
            "category":"Sports & Exercise",
            "subcategory":"Tennis Court",
            "type":"Entertainment"
        }
    ],
    "sg:phone":"+39 06 6574 3811",
    "sg:postcode":"00151",
    "sg:province":"Roma",
    "sg:tags":[
        "e",
        "lo",
        "tempo",
        "libero",
        "per",
        "impianti",
        "il",
        "attrezzature"
    ],
    "wof:name":"Pisanelli Maria",
    "wof:placetype":"venue"
},
  "geometry": {"coordinates":[12.441634,41.858139],"type":"Point"}
}