{
  "type": "Feature",
  "properties": {
    "addr:full":"51036 Larciano Larciano Pistoia 51036",
    "addr:postcode":"51036;51036",
    "iso:country":"IT",
    "sg:address":"51036 Larciano",
    "sg:city":"Larciano",
    "sg:orig_category":"Forniture Per Uffici. Servizi Vari Di Interesse Pubblico",
    "sg:phone":"+39 0573 83117",
    "sg:postcode":"51036",
    "sg:province":"Pistoia",
    "wof:name":"Bonfanti Paolo",
    "wof:placetype":"venue"
},
  "geometry": {"coordinates":[10.9172201157,43.869342804],"type":"Point"}
}