{
  "type": "Feature",
  "properties": {
    "iso:country":"IT",
    "sg:address":"41013 Castelfranco Emilia",
    "sg:city":"Castelfranco Emilia",
    "sg:orig_category":"Marmo Ed Affini - Commercio",
    "sg:phone":"+39 059 921428",
    "sg:postcode":"41013",
    "sg:province":"Modena",
    "sg:website":"http://www.aitec.it/polledro",
    "wof:name":"Poliedro Srl",
    "wof:placetype":"venue"
},
  "geometry": {"coordinates":[11.03335,44.600716],"type":"Point"}
}