{
  "type": "Feature",
  "properties": {
    "iso:country":"IT",
    "sg:address":"20051 Limbiate",
    "sg:city":"Limbiate",
    "sg:orig_category":"Non-classified Establishments",
    "sg:phone":"+39 02 9905 6975",
    "sg:postcode":"20051",
    "sg:province":"Milano",
    "wof:name":"Sgarbi Sergio",
    "wof:placetype":"venue"
},
  "geometry": {"coordinates":[9.103564,45.538593],"type":"Point"}
}