{
  "type": "Feature",
  "properties": {
    "addr:full":"70022 Altamura Altamura Bari 70022",
    "addr:postcode":"70022;70022",
    "iso:country":"IT",
    "sg:address":"70022 Altamura",
    "sg:city":"Altamura",
    "sg:orig_category":"Banche Ed Istituti Di Credito E Risparmio",
    "sg:phone":"+39 080 871 0111",
    "sg:postcode":"70022",
    "sg:province":"Bari",
    "sg:website":"http://www.bankpuliabas.it",
    "wof:name":"Banca Popolare Di Puglia E Basilicata",
    "wof:placetype":"venue"
},
  "geometry": {"coordinates":[16.58198,40.831211],"type":"Point"}
}