{
  "type": "Feature",
  "properties": {
    "addr:full":"23900 Lecco Lecco Lecco 23900",
    "addr:postcode":"23900;23900",
    "iso:country":"IT",
    "sg:address":"23900 Lecco",
    "sg:city":"Lecco",
    "sg:orig_category":"Utensili Meccanici E Materiali. Elettrotecnica Industriale, Prodotti E Apparecchiature",
    "sg:phone":"+39 0341 366281",
    "sg:postcode":"23900",
    "sg:province":"Lecco",
    "wof:name":"Sala Carlo Di Sala Maria & C. Snc",
    "wof:placetype":"venue"
},
  "geometry": {"coordinates":[9.386555,45.85778],"type":"Point"}
}