{
  "type": "Feature",
  "properties": {
    "iso:country":"IT",
    "sg:address":"80144 Napoli",
    "sg:city":"Napoli",
    "sg:orig_category":"Automazione E Macchine Per Ufficio. Servizi Ausiliari Di Certificati, Riproduzioni, Disegni E Foto",
    "sg:phone":"+39 081 736 1552",
    "sg:postcode":"80144",
    "sg:province":"Napoli",
    "wof:name":"R.c.m.italia S.a.s.",
    "wof:placetype":"venue"
},
  "geometry": {"coordinates":[14.26978,40.883347],"type":"Point"}
}