{
  "type": "Feature",
  "properties": {
    "iso:country":"IT",
    "sg:address":"46042 Castel Goffredo",
    "sg:city":"Castel Goffredo",
    "sg:orig_category":"Materie Plastiche - Commercio",
    "sg:phone":"+39 0376 780238",
    "sg:postcode":"46042",
    "sg:province":"Mantova",
    "wof:name":"Nuova Recurplast Snc",
    "wof:placetype":"venue"
},
  "geometry": {"coordinates":[10.470673,45.288177],"type":"Point"}
}