{
  "type": "Feature",
  "properties": {
    "iso:country":"IT",
    "sg:address":"Via Paletti 1 41051 Castelnuovo Rangone",
    "sg:city":"Castelnuovo Rangone",
    "sg:classifiers":[
        {
            "category":"Food & Beverages",
            "subcategory":"Meat & Fish",
            "type":"Retail Goods"
        }
    ],
    "sg:phone":"+39 059 534111",
    "sg:postcode":"41051",
    "sg:province":"Modena",
    "sg:tags":[
        "meal",
        "animal"
    ],
    "wof:name":"S.a.p.i. Spa",
    "wof:placetype":"venue"
},
  "geometry": {"coordinates":[10.924236,44.542152],"type":"Point"}
}