{
  "type": "Feature",
  "properties": {
    "iso:country":"IT",
    "sg:address":"31029 Vittorio Veneto",
    "sg:city":"Vittorio Veneto",
    "sg:orig_category":"Forniture Per Edilizia E Lavori Pubblici",
    "sg:phone":"+39 0438 53495",
    "sg:postcode":"31029",
    "sg:province":"Treviso",
    "sg:website":"http://www.parvit/it",
    "wof:name":"Parvit Srl",
    "wof:placetype":"venue"
},
  "geometry": {"coordinates":[12.3065738678,45.9829597473],"type":"Point"}
}