{
  "type": "Feature",
  "properties": {
    "addr:full":"24030 Brembate Di Sopra Brembate di Sopra Bergamo 24030",
    "addr:postcode":"24030;24030",
    "iso:country":"IT",
    "sg:address":"24030 Brembate Di Sopra",
    "sg:city":"Brembate di Sopra",
    "sg:orig_category":"Materiali E Componenti Elettrotecnici",
    "sg:phone":"+39 035 332396",
    "sg:postcode":"24030",
    "sg:province":"Bergamo",
    "wof:name":"I.v.l. Innovative Valve Lab S.r.l.",
    "wof:placetype":"venue"
},
  "geometry": {"coordinates":[9.575945,45.708378],"type":"Point"}
}