{
  "type": "Feature",
  "properties": {
    "iso:country":"IT",
    "sg:address":"25080 Padenghe Sul Garda",
    "sg:city":"Padenghe sul Garda",
    "sg:orig_category":"Materiali Semilavorati Metallici",
    "sg:phone":"+39 030 990 0000",
    "sg:postcode":"25080",
    "sg:province":"Brescia",
    "wof:name":"Bresciana Grondaie Srl",
    "wof:placetype":"venue"
},
  "geometry": {"coordinates":[10.507519,45.510647],"type":"Point"}
}