{
  "type": "Feature",
  "properties": {
    "iso:country":"IT",
    "sg:address":"Via Roma 69 81035 Roccamonfina",
    "sg:city":"Roccamonfina",
    "sg:classifiers":[
        {
            "category":"Coffee & Tea",
            "type":"Food & Drink"
        }
    ],
    "sg:phone":"+39 0823 679003",
    "sg:postcode":"81035",
    "sg:province":"Caserta",
    "sg:tags":[
        "chestnut",
        "european"
    ],
    "sg:website":"www.demscam.it",
    "wof:name":"Demscam Srl",
    "wof:placetype":"venue"
},
  "geometry": {"coordinates":[13.984732,41.292061],"type":"Point"}
}