{
  "type": "Feature",
  "properties": {
    "addr:full":"Via Caovilla 27/b 35020 Saonara Saonara Padova 35020",
    "addr:housenumber":"27 / b",
    "addr:postcode":"35020;35020",
    "addr:street":"Via Caovilla",
    "iso:country":"IT",
    "sg:address":"Via Caovilla 27/b 35020 Saonara",
    "sg:city":"Saonara",
    "sg:orig_category":"Tree Nursery Machines And Equipment",
    "sg:phone":"+39 049 640282",
    "sg:postcode":"35020",
    "sg:province":"Padova",
    "wof:name":"F.lli Berto Snc",
    "wof:placetype":"venue"
},
  "geometry": {"coordinates":[11.876589,45.409569],"type":"Point"}
}