{
  "type": "Feature",
  "properties": {
    "addr:full":"48100 Marina Di Ravenna Marina di Ravenna Ravenna 48100",
    "addr:postcode":"48100;48100",
    "addr:street":"Di Ravenna",
    "iso:country":"IT",
    "sg:address":"48100 Marina Di Ravenna",
    "sg:city":"Marina di Ravenna",
    "sg:orig_category":"Ristorazione E Locali Pubblici Affini. Ristoranti Ed Esercizi Affini. Servizi Ausiliari Di Ristorazione E Di Intrattenimento",
    "sg:phone":"+39 0544 530231",
    "sg:postcode":"48100",
    "sg:province":"Ravenna",
    "wof:name":"Trattoria Cubana - Da Irma E Pino",
    "wof:placetype":"venue"
},
  "geometry": {"coordinates":[12.280118,44.491539],"type":"Point"}
}