{
  "type": "Feature",
  "properties": {
    "addr:full":"Via Leno 2/d 25025 Manerbio Manerbio Brescia 25025",
    "addr:housenumber":"2 / d",
    "addr:postcode":"25025;25025",
    "addr:street":"Via Leno",
    "iso:country":"IT",
    "sg:address":"Via Leno 2/d 25025 Manerbio",
    "sg:city":"Manerbio",
    "sg:classifiers":[
        {
            "category":"Manufacturing",
            "subcategory":"Electronics",
            "type":"Manufacturing & Wholesale Goods"
        }
    ],
    "sg:phone":"+39 030 993 8400",
    "sg:postcode":"25025",
    "sg:province":"Brescia",
    "sg:tags":[
        "large",
        "machine",
        "industrial",
        "electrical",
        "equipment"
    ],
    "sg:website":"www.sgm-magnetcs.com",
    "wof:name":"Sgm Spa",
    "wof:placetype":"venue"
},
  "geometry": {"coordinates":[10.171247,45.368397],"type":"Point"}
}