{
  "type": "Feature",
  "properties": {
    "iso:country":"IT",
    "sg:address":"10122 Torino",
    "sg:city":"Torino",
    "sg:orig_category":"Professionisti - Studi E Servizi Ed Associazioni Di Interesse Aziendale. Associazioni Ed Organismi Di Interesse Pubblico",
    "sg:phone":"+39 011 521 4648",
    "sg:postcode":"10122",
    "sg:province":"Torino",
    "wof:name":"Associazione Provinciale Della Propriet\u00c0 Edilizia",
    "wof:placetype":"venue"
},
  "geometry": {"coordinates":[7.4055814743,45.0844573975],"type":"Point"}
}