{
  "type": "Feature",
  "properties": {
    "iso:country":"IT",
    "sg:address":"80133 Napoli",
    "sg:city":"Napoli",
    "sg:orig_category":"Studi E Consulenze Amministrative, Commerciali E Aziendali. Consulenze Tecniche, Amministrative E Perizie. Professionisti - Studi E Servizi Ed Associazioni Di Interesse Aziendale",
    "sg:phone":"+39 081 551 5302",
    "sg:postcode":"80133",
    "sg:province":"Napoli",
    "wof:name":"Civa Srl",
    "wof:placetype":"venue"
},
  "geometry": {"coordinates":[14.255583,40.841072],"type":"Point"}
}