{
  "type": "Feature",
  "properties": {
    "iso:country":"IT",
    "sg:address":"04100 Latina",
    "sg:city":"Latina",
    "sg:classifiers":[
        {
            "category":"Health Services",
            "subcategory":"Health Practitioner",
            "type":"Services"
        }
    ],
    "sg:phone":"+39 0773 480272",
    "sg:postcode":"04100",
    "sg:province":"Latina",
    "sg:tags":[
        "medici"
    ],
    "wof:name":"Favalli Cartesio",
    "wof:placetype":"venue"
},
  "geometry": {"coordinates":[12.985874,41.547729],"type":"Point"}
}