{
  "type": "Feature",
  "properties": {
    "iso:country":"IT",
    "sg:address":"32, Via Dell' Artigianato 48018 Faenza",
    "sg:city":"Faenza",
    "sg:classifiers":[
        {
            "category":"Autos & Motor Vehicles",
            "subcategory":"Automobile Sales",
            "type":"Retail Goods"
        }
    ],
    "sg:phone":"+39 0546 620026",
    "sg:postcode":"48018",
    "sg:province":"Ravenna",
    "sg:tags":[
        "motor-cars"
    ],
    "wof:name":"O.m.m.a. S.r.l.",
    "wof:placetype":"venue"
},
  "geometry": {"coordinates":[11.8660469055,44.2961921692],"type":"Point"}
}