{
  "type": "Feature",
  "properties": {
    "iso:country":"IT",
    "sg:address":"Via Fiorolle 48 36060 Romano D'ezzelino",
    "sg:classifiers":[
        {
            "category":"Shopping",
            "subcategory":"Stationery & Office Supplies",
            "type":"Retail Goods"
        }
    ],
    "sg:phone":"+39 0424 513320",
    "sg:postcode":"36060",
    "sg:province":"Vicenza",
    "sg:tags":[
        "adhesive",
        "label"
    ],
    "sg:website":"www.grafort.it",
    "wof:name":"Grafort Srl Unipersonale",
    "wof:placetype":"venue"
},
  "geometry": {"coordinates":[11.777277,45.780392],"type":"Point"}
}