{
  "type": "Feature",
  "properties": {
    "addr:full":"20144 Milano Milano Milano 20144",
    "addr:postcode":"20144;20144",
    "iso:country":"IT",
    "sg:address":"20144 Milano",
    "sg:city":"Milano",
    "sg:classifiers":[
        {
            "category":"Health Services",
            "subcategory":"Health Practitioner",
            "type":"Services"
        }
    ],
    "sg:phone":"+39 02 837 8534",
    "sg:postcode":"20144",
    "sg:province":"Milano",
    "sg:tags":[
        "medici"
    ],
    "wof:name":"Gaita Denis",
    "wof:placetype":"venue"
},
  "geometry": {"coordinates":[9.171288,45.454308],"type":"Point"}
}