{
  "type": "Feature",
  "properties": {
    "addr:full":"20, Via Bordigona 54100 Massa Massa Massa-Carrara 54100",
    "addr:postcode":"54100;54100",
    "addr:street":"Via Bordigona",
    "iso:country":"IT",
    "sg:address":"20, Via Bordigona 54100 Massa",
    "sg:city":"Massa",
    "sg:classifiers":[
        {
            "category":"Manufacturing",
            "subcategory":"Metals",
            "type":"Manufacturing & Wholesale Goods"
        }
    ],
    "sg:phone":"+39 0585 251668",
    "sg:postcode":"54100",
    "sg:province":"Massa-Carrara",
    "sg:tags":[
        "processing"
    ],
    "wof:name":"Apuazinco (s.r.l.)",
    "wof:placetype":"venue"
},
  "geometry": {"coordinates":[10.1045351028,44.031879425],"type":"Point"}
}