{
  "type": "Feature",
  "properties": {
    "addr:full":"20132 Milano Milano Milano 20132",
    "addr:postcode":"20132;20132",
    "iso:country":"IT",
    "sg:address":"20132 Milano",
    "sg:city":"Milano",
    "sg:orig_category":"Elettrotecnica Industriale, Prodotti E Apparecchiature. Elettrotecnica Professionale E Di Consumo",
    "sg:phone":"+39 02 2720 3060",
    "sg:postcode":"20132",
    "sg:province":"Milano",
    "wof:name":"Amel S.r.l.",
    "wof:placetype":"venue"
},
  "geometry": {"coordinates":[9.24183,45.502522],"type":"Point"}
}