{
  "type": "Feature",
  "properties": {
    "addr:full":"10048 Vinovo Vinovo Torino 10048",
    "addr:housenumber":"10048",
    "addr:postcode":"10048",
    "addr:street":"Vinovo",
    "iso:country":"IT",
    "sg:address":"10048 Vinovo",
    "sg:city":"Vinovo",
    "sg:orig_category":"Apparecchiature E Sistemi Per Magazzinaggio E Movimentazione",
    "sg:phone":"+39 011 965 1305",
    "sg:postcode":"10048",
    "sg:province":"Torino",
    "wof:name":"Bauducco Gru Snc",
    "wof:placetype":"venue"
},
  "geometry": {"coordinates":[7.635317,44.959862],"type":"Point"}
}