{
  "type": "Feature",
  "properties": {
    "iso:country":"IT",
    "sg:address":"Via Don A. Camera 25 21020 Bardello",
    "sg:city":"Bardello",
    "sg:orig_category":"Non-classified Establishments",
    "sg:phone":"+39 0332 731088",
    "sg:postcode":"21020",
    "sg:province":"Varese",
    "sg:website":"www.acmengineering.it",
    "wof:name":"Acm Engineering Spa",
    "wof:placetype":"venue"
},
  "geometry": {"coordinates":[8.826385,45.817604],"type":"Point"}
}