{
  "type": "Feature",
  "properties": {
    "iso:country":"IT",
    "sg:address":"03032 Arce",
    "sg:city":"Arce",
    "sg:orig_category":"Ristorazione E Locali Pubblici Affini. Ristoranti Ed Esercizi Affini. Servizi Ausiliari Di Ristorazione E Di Intrattenimento",
    "sg:phone":"+39 0776 529240",
    "sg:postcode":"03032",
    "sg:province":"Frosinone",
    "wof:name":"Le Villette - Ristorante - Pizzeria",
    "wof:placetype":"venue"
},
  "geometry": {"coordinates":[13.546574,41.527668],"type":"Point"}
}