{
  "type": "Feature",
  "properties": {
    "iso:country":"IT",
    "sg:address":"4, Corso S. Nicola 83030 Venticano",
    "sg:city":"Venticano",
    "sg:classifiers":[
        {
            "category":"Professional",
            "subcategory":"Engineering",
            "type":"Services"
        }
    ],
    "sg:phone":"+39 0825 965666",
    "sg:postcode":"83030",
    "sg:province":"Avellino",
    "sg:tags":[
        "machine",
        "-",
        "mechanical"
    ],
    "wof:name":"Euro Stek Di Liucci Dr.m. & C. S.a.s.",
    "wof:placetype":"venue"
},
  "geometry": {"coordinates":[14.792723,40.914749],"type":"Point"}
}