{
  "type": "Feature",
  "properties": {
    "addr:full":"88021 Borgia Borgia Catanzaro 88021",
    "addr:postcode":"88021;88021",
    "iso:country":"IT",
    "sg:address":"88021 Borgia",
    "sg:city":"Borgia",
    "sg:orig_category":"Prodotti Alimentari",
    "sg:phone":"+39 0961 391492",
    "sg:postcode":"88021",
    "sg:province":"Catanzaro",
    "wof:name":"La Casa Della Pasta Fresca Di Migali Placido",
    "wof:placetype":"venue"
},
  "geometry": {"coordinates":[16.4870491028,38.8827857971],"type":"Point"}
}