{
  "type": "Feature",
  "properties": {
    "iso:country":"IT",
    "sg:address":"87036 Rende",
    "sg:city":"Rende",
    "sg:orig_category":"Impiantistica E Prodotti Tecnologici Per Edilizia. Elettrotecnica Industriale, Prodotti E Apparecchiature",
    "sg:phone":"+39 0984 401840",
    "sg:postcode":"87036",
    "sg:province":"Cosenza",
    "wof:name":"Baldo Nicola",
    "wof:placetype":"venue"
},
  "geometry": {"coordinates":[16.243977,39.351257],"type":"Point"}
}