{
  "type": "Feature",
  "properties": {
    "iso:country":"IT",
    "sg:address":"20146 Milano",
    "sg:city":"Milano",
    "sg:orig_category":"Sport - Articoli E Forniture",
    "sg:phone":"+39 02 423 3080",
    "sg:postcode":"20146",
    "sg:province":"Milano",
    "wof:name":"Maioli Marisa",
    "wof:placetype":"venue"
},
  "geometry": {"coordinates":[9.148506,45.458439],"type":"Point"}
}