{
  "type": "Feature",
  "properties": {
    "iso:country":"IT",
    "sg:address":"00185 Roma",
    "sg:city":"Roma",
    "sg:orig_category":"Editoria",
    "sg:phone":"+39 06 496164",
    "sg:postcode":"00185",
    "sg:province":"Roma",
    "wof:name":"Prima (s.r.l.)",
    "wof:placetype":"venue"
},
  "geometry": {"coordinates":[12.729101,41.955891],"type":"Point"}
}