{
  "type": "Feature",
  "properties": {
    "addr:full":"Via Broseta 64/b; Bergamo; 24100",
    "addr:housenumber":"64 / b",
    "addr:postcode":"24100",
    "addr:street":"Via Broseta",
    "iso:country":"IT",
    "sg:address":"Via Broseta 64/b; Bergamo; 24100",
    "sg:classifiers":[
        {
            "category":"Banks & Credit Unions",
            "subcategory":"Bank",
            "type":"Services"
        }
    ],
    "sg:phone":"+39 035 257630",
    "wof:name":"Banca Popolare Di Sondrio Scarl",
    "wof:placetype":"venue"
},
  "geometry": {"coordinates":[9.649968,45.693569],"type":"Point"}
}