{
  "type": "Feature",
  "properties": {
    "iso:country":"IT",
    "sg:address":"20134 Milano",
    "sg:city":"Milano",
    "sg:orig_category":"Alimentari - Produzione E Ingrosso",
    "sg:phone":"+39 02 215 3406",
    "sg:postcode":"20134",
    "sg:province":"Milano",
    "wof:name":"L'artigiana Del Dolce Di Gagliasso Giuseppe",
    "wof:placetype":"venue"
},
  "geometry": {"coordinates":[9.237045,45.489162],"type":"Point"}
}