{
  "type": "Feature",
  "properties": {
    "iso:country":"IT",
    "sg:address":"37045 Legnago",
    "sg:city":"Legnago",
    "sg:orig_category":"Macchine E Forniture Per Ecologia E Smaltimento Rifiuti. Macchine, Strumenti Ed Apparecchi Per Attivita' Industriali",
    "sg:phone":"+39 0442 22294",
    "sg:postcode":"37045",
    "sg:province":"Verona",
    "wof:name":"New Clean Srl",
    "wof:placetype":"venue"
},
  "geometry": {"coordinates":[11.31587,45.174767],"type":"Point"}
}