{
  "type": "Feature",
  "properties": {
    "addr:full":"20032 Cormano Cormano Milano 20032",
    "addr:postcode":"20032;20032",
    "iso:country":"IT",
    "sg:address":"20032 Cormano",
    "sg:city":"Cormano",
    "sg:orig_category":"Macchine, Impianti E Forniture Per Industria Grafica, Cartaria E Cartotecnica. Prodotti Chimici Secondari",
    "sg:phone":"+39 02 6630 2772",
    "sg:postcode":"20032",
    "sg:province":"Milano",
    "sg:website":"http://www.inkmaloberti.it",
    "wof:name":"Ink Maloberti Srl",
    "wof:placetype":"venue"
},
  "geometry": {"coordinates":[9.156115,45.5341],"type":"Point"}
}