{
  "type": "Feature",
  "properties": {
    "iso:country":"IT",
    "sg:address":"84012 Angri",
    "sg:city":"Angri",
    "sg:orig_category":"Ceramiche Artistiche",
    "sg:phone":"+39 081 513 5078",
    "sg:postcode":"84012",
    "sg:province":"Salerno",
    "wof:name":"S.c.d. Srl Special Ceramic Distribution",
    "wof:placetype":"venue"
},
  "geometry": {"coordinates":[14.574756,40.743599],"type":"Point"}
}