{
  "type": "Feature",
  "properties": {
    "iso:country":"IT",
    "sg:address":"70126 Bari",
    "sg:city":"Bari",
    "sg:orig_category":"Materiali Semilavorati Metallici",
    "sg:phone":"+39 080 549 1139",
    "sg:postcode":"70126",
    "sg:province":"Bari",
    "wof:name":"Metal Trafilsud",
    "wof:placetype":"venue"
},
  "geometry": {"coordinates":[16.761116,40.887756],"type":"Point"}
}