{
  "type": "Feature",
  "properties": {
    "iso:country":"IT",
    "sg:address":"20159 Milano",
    "sg:city":"Milano",
    "sg:orig_category":"Servizi Vari Di Interesse Pubblico",
    "sg:phone":"+39 02 688 3949",
    "sg:postcode":"20159",
    "sg:province":"Milano",
    "wof:name":"Di Leonardo Bruno",
    "wof:placetype":"venue"
},
  "geometry": {"coordinates":[9.189116,45.489811],"type":"Point"}
}