{
  "type": "Feature",
  "properties": {
    "iso:country":"IT",
    "sg:address":"10, Via Cascina Borniola 10036 Settimo Torinese",
    "sg:city":"Settimo Torinese",
    "sg:orig_category":"Miscellaneous Products",
    "sg:phone":"+39 011 800 5071",
    "sg:postcode":"10036",
    "sg:province":"Torino",
    "wof:name":"Elle Erre Srl",
    "wof:placetype":"venue"
},
  "geometry": {"coordinates":[7.7314710617,45.1460189819],"type":"Point"}
}