{
  "type": "Feature",
  "properties": {
    "addr:full":"92024 Canicatt\u00ec Agrigento 92024",
    "addr:postcode":"92024;92024",
    "iso:country":"IT",
    "sg:address":"92024 Canicatt\u00ec",
    "sg:orig_category":"Forniture Per Abbigliamento E Pelletterie",
    "sg:phone":"+39 0922 856670",
    "sg:postcode":"92024",
    "sg:province":"Agrigento",
    "wof:name":"Furore Di Condello",
    "wof:placetype":"venue"
},
  "geometry": {"coordinates":[13.8539171219,37.3557128906],"type":"Point"}
}