{
  "type": "Feature",
  "properties": {
    "addr:full":"00196 Roma Roma Roma 00196",
    "addr:postcode":"00196;00196",
    "iso:country":"IT",
    "sg:address":"00196 Roma",
    "sg:city":"Roma",
    "sg:orig_category":"Legno E Semilavorati",
    "sg:phone":"+39 06 361 0109",
    "sg:postcode":"00196",
    "sg:province":"Roma",
    "wof:name":"Perelli Erasmo",
    "wof:placetype":"venue"
},
  "geometry": {"coordinates":[12.463854,41.927189],"type":"Point"}
}