{
  "type": "Feature",
  "properties": {
    "addr:full":"10076 Nole Nole Torino 10076",
    "addr:postcode":"10076;10076",
    "iso:country":"IT",
    "sg:address":"10076 Nole",
    "sg:city":"Nole",
    "sg:orig_category":"Servizi E Lavori Per Arredamento E Industria Del Legno. Servizi E Lavori Per Edilizia E Lavori Pubblici",
    "sg:phone":"+39 011 929 6386",
    "sg:postcode":"10076",
    "sg:province":"Torino",
    "wof:name":"Patella Peppino",
    "wof:placetype":"venue"
},
  "geometry": {"coordinates":[7.574758,45.242489],"type":"Point"}
}