{
  "type": "Feature",
  "properties": {
    "iso:country":"IT",
    "sg:address":"Via Iv Novembre 97; Ercolano; 80056",
    "sg:city":"Ercolano",
    "sg:classifiers":[
        {
            "category":"Banks & Credit Unions",
            "subcategory":"Bank",
            "type":"Services"
        }
    ],
    "sg:phone":"+39 081 777 2095",
    "sg:postcode":"80056",
    "sg:province":"Napoli",
    "wof:name":"Credito Italiano Spa",
    "wof:placetype":"venue"
},
  "geometry": {"coordinates":[14.385011,40.821007],"type":"Point"}
}