{
  "type": "Feature",
  "properties": {
    "addr:full":"25122 Brescia Brescia Brescia 25122",
    "addr:postcode":"25122;25122",
    "iso:country":"IT",
    "sg:address":"25122 Brescia",
    "sg:city":"Brescia",
    "sg:orig_category":"Servizi Ausiliari Di Sorveglianza, Manutenzione E Pulizia",
    "sg:phone":"+39 030 289 3911",
    "sg:postcode":"25122",
    "sg:province":"Brescia",
    "wof:name":"Vigilanza Notturna Per La Citt\u00c0 Di Brescia",
    "wof:placetype":"venue"
},
  "geometry": {"coordinates":[10.010855,45.534485],"type":"Point"}
}