{
  "type": "Feature",
  "properties": {
    "iso:country":"IT",
    "sg:address":"26010 Ricengo",
    "sg:city":"Ricengo",
    "sg:orig_category":"Motori Elettrici E Componenti",
    "sg:phone":"+39 0373 267753",
    "sg:postcode":"26010",
    "sg:province":"Cremona",
    "wof:name":"Elettromeccanica Riceng Snc",
    "wof:placetype":"venue"
},
  "geometry": {"coordinates":[9.8709630966,45.4011116028],"type":"Point"}
}