{
  "type": "Feature",
  "properties": {
    "addr:full":"Via Francesco Baracca 37 52100 Arezzo Arezzo Arezzo 52100",
    "addr:housenumber":"37",
    "addr:postcode":"52100;52100",
    "addr:street":"Via Francesco Baracca",
    "iso:country":"IT",
    "sg:address":"Via Francesco Baracca 37 52100 Arezzo",
    "sg:city":"Arezzo",
    "sg:classifiers":[
        {
            "category":"Transit Center",
            "subcategory":"Passenger",
            "type":"Transportation"
        }
    ],
    "sg:phone":"+39 0575 21329",
    "sg:postcode":"52100",
    "sg:province":"Arezzo",
    "sg:tags":[
        "goldsmith's",
        "tool"
    ],
    "wof:name":"Ceab Di Bichi Guglielmo Eredi Snc",
    "wof:placetype":"venue"
},
  "geometry": {"coordinates":[11.845579,43.46125],"type":"Point"}
}