{
  "type": "Feature",
  "properties": {
    "iso:country":"IT",
    "sg:address":"84047 Capaccio",
    "sg:city":"Capaccio",
    "sg:orig_category":"Macchine Ed Impianti Per Edilizia E Lavori Pubblici",
    "sg:phone":"+39 0828 601043",
    "sg:postcode":"84047",
    "sg:province":"Salerno",
    "wof:name":"Super Sele (s.r.l.)",
    "wof:placetype":"venue"
},
  "geometry": {"coordinates":[15.015183,40.483761],"type":"Point"}
}