{
  "type": "Feature",
  "properties": {
    "iso:country":"IT",
    "sg:address":"Via F. Turati 14 40010 Tavernelle Emilia",
    "sg:classifiers":[
        {
            "category":"Manufacturing",
            "subcategory":"Tools & Machinery",
            "type":"Manufacturing & Wholesale Goods"
        }
    ],
    "sg:phone":"+39 051 681 4575",
    "sg:postcode":"40010",
    "sg:province":"Bologna",
    "sg:tags":[
        "die",
        "injection",
        "moulding",
        "casting"
    ],
    "wof:name":"Comest Srl",
    "wof:placetype":"venue"
},
  "geometry": {"coordinates":[11.268054,44.563972],"type":"Point"}
}