{
  "type": "Feature",
  "properties": {
    "iso:country":"IT",
    "sg:address":"Via Lombardia 13 20098 Sesto Ulteriano",
    "sg:city":"Sesto Ulteriano",
    "sg:classifiers":[
        {
            "category":"Autos & Motor Vehicles",
            "subcategory":"Recreational Vehicle Sales",
            "type":"Retail Goods"
        }
    ],
    "sg:phone":"+39 02 9828 1751",
    "sg:postcode":"20098",
    "sg:province":"Milano",
    "sg:tags":[
        "machine",
        "spring",
        "manufacturing"
    ],
    "sg:website":"www.simplexrapid.it",
    "wof:name":"Simplex Rapid Srl",
    "wof:placetype":"venue"
},
  "geometry": {"coordinates":[9.253379,45.397606],"type":"Point"}
}