{
  "type": "Feature",
  "properties": {
    "addr:full":"Via Del Commercio 11 25030 Roccafranca Roccafranca Brescia 25030",
    "addr:housenumber":"11",
    "addr:postcode":"25030;25030",
    "addr:street":"Via Del Commercio",
    "iso:country":"IT",
    "sg:address":"Via Del Commercio 11 25030 Roccafranca",
    "sg:city":"Roccafranca",
    "sg:classifiers":[
        {
            "category":"Metro Station",
            "type":"Transportation"
        }
    ],
    "sg:phone":"+39 030 709 0602",
    "sg:postcode":"25030",
    "sg:province":"Brescia",
    "sg:tags":[
        "varnish",
        "special"
    ],
    "wof:name":"Prodotti Fuoco Di Bonassi Filippo E C. S.a.s.",
    "wof:placetype":"venue"
},
  "geometry": {"coordinates":[9.9214859009,45.4475631714],"type":"Point"}
}