{
  "type": "Feature",
  "properties": {
    "iso:country":"IT",
    "sg:address":"89063 Melito Porto Salvo",
    "sg:orig_category":"Antiquariato",
    "sg:phone":"+39 0965 788298",
    "sg:postcode":"89063",
    "sg:province":"Reggio Di Calabria",
    "wof:name":"Pontari Rosa",
    "wof:placetype":"venue"
},
  "geometry": {"coordinates":[15.650137,38.114689],"type":"Point"}
}