{
  "type": "Feature",
  "properties": {
    "iso:country":"IT",
    "sg:address":"24128 Bergamo",
    "sg:city":"Bergamo",
    "sg:orig_category":"Prodotti Finiti Stampati. Forniture Per Uffici",
    "sg:phone":"+39 035 403451",
    "sg:postcode":"24128",
    "sg:province":"Bergamo",
    "wof:name":"Gamberoni Roberto Gamberoni Service",
    "wof:placetype":"venue"
},
  "geometry": {"coordinates":[9.6500797272,45.6935806274],"type":"Point"}
}