{
  "type": "Feature",
  "properties": {
    "addr:full":"31010 Castello Roganzuolo Di San Fior Treviso 31010",
    "addr:housenumber":"31010;fior",
    "addr:postcode":"31010",
    "addr:street":"Castello;Di San",
    "iso:country":"IT",
    "sg:address":"31010 Castello Roganzuolo Di San Fior",
    "sg:orig_category":"Chiodi",
    "sg:phone":"+39 0438 777241",
    "sg:postcode":"31010",
    "sg:province":"Treviso",
    "sg:website":"http://www.peronmetallurgica.com",
    "wof:name":"Peron Metallurgica Di Peron G. & C. Snc",
    "wof:placetype":"venue"
},
  "geometry": {"coordinates":[12.242072,45.666286],"type":"Point"}
}