{
  "type": "Feature",
  "properties": {
    "iso:country":"IT",
    "sg:address":"46042 Castel Goffredo",
    "sg:city":"Castel Goffredo",
    "sg:orig_category":"Calze E Collants - Produzione E Ingrosso",
    "sg:phone":"+39 0376 771780",
    "sg:postcode":"46042",
    "sg:province":"Mantova",
    "wof:name":"Calze Lo.m.a. Di Morbini Andrea",
    "wof:placetype":"venue"
},
  "geometry": {"coordinates":[10.473772,45.294811],"type":"Point"}
}