{
  "type": "Feature",
  "properties": {
    "addr:full":"44100 Ferrara Ferrara Ferrara 44100",
    "addr:postcode":"44100;44100",
    "iso:country":"IT",
    "sg:address":"44100 Ferrara",
    "sg:city":"Ferrara",
    "sg:classifiers":[
        {
            "category":"Shopping",
            "subcategory":"Computers & Home Electronics",
            "type":"Retail Goods"
        }
    ],
    "sg:phone":"+39 0532 249909",
    "sg:postcode":"44100",
    "sg:province":"Ferrara",
    "sg:tags":[
        "personal",
        "ed",
        "accessori"
    ],
    "wof:name":"Videostar Di Bovolenta Marco",
    "wof:placetype":"venue"
},
  "geometry": {"coordinates":[11.6411933899,44.8167533875],"type":"Point"}
}