{
  "type": "Feature",
  "properties": {
    "addr:full":"25076 Odolo Odolo Brescia 25076",
    "addr:postcode":"25076;25076",
    "iso:country":"IT",
    "sg:address":"25076 Odolo",
    "sg:city":"Odolo",
    "sg:orig_category":"Acciaierie E Fonderie",
    "sg:postcode":"25076",
    "sg:province":"Brescia",
    "wof:name":"Ferriera Valsabbia (s.p.a.)",
    "wof:placetype":"venue"
},
  "geometry": {"coordinates":[10.224953,45.552235],"type":"Point"}
}