{
  "type": "Feature",
  "properties": {
    "addr:full":"80053 Castellammare Di Stabia Castellammare di Stabia Napoli 80053",
    "addr:postcode":"80053;80053",
    "iso:country":"IT",
    "sg:address":"80053 Castellammare Di Stabia",
    "sg:city":"Castellammare di Stabia",
    "sg:orig_category":"Accessori Dei Mezzi Di Trasporto. Riparazione Dei Mezzi Di Trasporto",
    "sg:phone":"+39 081 871 8405",
    "sg:postcode":"80053",
    "sg:province":"Napoli",
    "wof:name":"Gallotti Vincenzo",
    "wof:placetype":"venue"
},
  "geometry": {"coordinates":[14.485476,40.701313],"type":"Point"}
}