{
  "type": "Feature",
  "properties": {
    "iso:country":"IT",
    "sg:address":"80146 Napoli",
    "sg:city":"Napoli",
    "sg:orig_category":"Riparazione Dei Mezzi Di Trasporto. Servizi Ausiliari Dei Mezzi Di Trasporto",
    "sg:phone":"+39 081 559 1240",
    "sg:postcode":"80146",
    "sg:province":"Napoli",
    "wof:name":"La Nuova Meccanica Navale",
    "wof:placetype":"venue"
},
  "geometry": {"coordinates":[14.292728,40.840012],"type":"Point"}
}