{
  "type": "Feature",
  "properties": {
    "iso:country":"IT",
    "sg:address":"Via Sanvincenzo 24",
    "sg:city":"Milan",
    "sg:classifiers":[
        {
            "category":"Professional",
            "subcategory":"Computer Services",
            "type":"Services"
        }
    ],
    "sg:postcode":"20132",
    "sg:tags":[
        "user-generated-content",
        "crowdsourcing",
        "vertical-social-network",
        "web-2-0",
        "social-advertising"
    ],
    "sg:website":"http://www.theblogtv.it",
    "wof:name":"TheBlogTV",
    "wof:placetype":"venue"
},
  "geometry": {"coordinates":[9.2389188,45.4929324],"type":"Point"}
}