{
  "type": "Feature",
  "properties": {
    "iso:country":"IT",
    "sg:address":"44100 Ferrara",
    "sg:city":"Ferrara",
    "sg:orig_category":"Scuole E Servizi Scolastici. Ricerca, Selezione E Formazione Del Personale",
    "sg:phone":"+39 0532 293111",
    "sg:postcode":"44100",
    "sg:province":"Ferrara",
    "sg:website":"http://www.unife.it",
    "wof:name":"Universit\u00c0 Degli Studi Di Ferrara",
    "wof:placetype":"venue"
},
  "geometry": {"coordinates":[11.625973,44.833458],"type":"Point"}
}