{
  "type": "Feature",
  "properties": {
    "iso:country":"IT",
    "sg:address":"Piazza Della Repubblica 32 20124 Milano",
    "sg:city":"Milano",
    "sg:orig_category":"Pumice Powder And Granules",
    "sg:phone":"+39 02 6698 1471",
    "sg:postcode":"20124",
    "sg:province":"Milano",
    "sg:website":"www.europomice.it",
    "wof:name":"Europomice Srl",
    "wof:placetype":"venue"
},
  "geometry": {"coordinates":[9.1974830627,45.4786338806],"type":"Point"}
}