{
  "type": "Feature",
  "properties": {
    "iso:country":"IT",
    "sg:address":"25068 Sarezzo",
    "sg:city":"Sarezzo",
    "sg:orig_category":"Macchine Utensili E Impianti",
    "sg:phone":"+39 030 801841",
    "sg:postcode":"25068",
    "sg:province":"Brescia",
    "wof:name":"Cht Tecnoservice Snc",
    "wof:placetype":"venue"
},
  "geometry": {"coordinates":[10.204451,45.648136],"type":"Point"}
}