{
  "type": "Feature",
  "properties": {
    "addr:full":"Via Nazionale - Lima Piteglio Pistoia 51020",
    "addr:postcode":"51020",
    "addr:street":"Via Nazionale Lima",
    "iso:country":"IT",
    "sg:address":"Via Nazionale - Lima",
    "sg:city":"Piteglio",
    "sg:classifiers":[
        {
            "category":"Shopping",
            "type":"Retail Goods"
        }
    ],
    "sg:phone":"+39 0573 671220",
    "sg:postcode":"51020",
    "sg:province":"Pistoia",
    "sg:tags":[
        "finished",
        "-",
        "metallic"
    ],
    "wof:name":"Vibach Di Viviano Michele Baldini E Chierroni Snc",
    "wof:placetype":"venue"
},
  "geometry": {"coordinates":[10.9185237885,43.9321556091],"type":"Point"}
}