{
  "type": "Feature",
  "properties": {
    "addr:full":"27010 Siziano Siziano Pavia 27010",
    "addr:postcode":"27010;27010",
    "iso:country":"IT",
    "sg:address":"27010 Siziano",
    "sg:city":"Siziano",
    "sg:orig_category":"Macchine, Impianti Ed Attrezzature Industria Delle Materie Plastiche E Gomma",
    "sg:phone":"+39 0382 678211",
    "sg:postcode":"27010",
    "sg:province":"Pavia",
    "wof:name":"Tecno Compounds Div. Di Saiag Industrie S.r.l.",
    "wof:placetype":"venue"
},
  "geometry": {"coordinates":[9.218682,45.326233],"type":"Point"}
}