{
  "type": "Feature",
  "properties": {
    "iso:country":"IT",
    "sg:address":"V. Nuova Lecce - Z.a. 73024 Maglie",
    "sg:city":"Maglie",
    "sg:classifiers":[
        {
            "category":"Shopping",
            "subcategory":"Computers & Home Electronics",
            "type":"Retail Goods"
        }
    ],
    "sg:phone":"+39 0836 428263",
    "sg:postcode":"73024",
    "sg:province":"Lecce",
    "sg:tags":[
        "electronic",
        "electrical",
        "equipment"
    ],
    "sg:website":"http://www.decagnaluminarie.com:ws_end: :mark:ws:http://www.paginegialle.it/decagnaluminarie",
    "wof:name":"L.c.d.c. Luminarie Cesario De Cagna",
    "wof:placetype":"venue"
},
  "geometry": {"coordinates":[18.174015,40.353291],"type":"Point"}
}