{
  "type": "Feature",
  "properties": {
    "iso:country":"IT",
    "sg:address":"Via Pascoli, 4/6 20010 Vittuone",
    "sg:city":"Vittuone",
    "sg:classifiers":[
        {
            "category":"Home & Garden",
            "subcategory":"Carpets & Floor Coverings",
            "type":"Retail Goods"
        }
    ],
    "sg:phone":"+39 02 902 5181",
    "sg:postcode":"20010",
    "sg:province":"Milano",
    "sg:tags":[
        "tile",
        "ceramic",
        "printed"
    ],
    "sg:website":"www.bardelli.it",
    "wof:name":"Altaeco Spa - Ceramica Bardelli",
    "wof:placetype":"venue"
},
  "geometry": {"coordinates":[8.996796608,45.4462127686],"type":"Point"}
}