{
  "type": "Feature",
  "properties": {
    "iso:country":"IT",
    "sg:address":"66, Via Delle Monachelle 00040 Pomezia",
    "sg:city":"Pomezia",
    "sg:classifiers":[
        {
            "category":"Manufacturing",
            "subcategory":"Food",
            "type":"Manufacturing & Wholesale Goods"
        }
    ],
    "sg:phone":"+39 06 9160 2967",
    "sg:postcode":"00040",
    "sg:province":"Roma",
    "sg:tags":[
        "equipment",
        "processing",
        "-",
        "machinery"
    ],
    "wof:name":"Co.fr.i.me.l.l. Di Zicarelli Mario E C.sas",
    "wof:placetype":"venue"
},
  "geometry": {"coordinates":[12.5436410904,41.6864509583],"type":"Point"}
}