{
  "type": "Feature",
  "properties": {
    "iso:country":"IT",
    "sg:address":"24042 Capriate San Gervasio",
    "sg:city":"Capriate San Gervasio",
    "sg:orig_category":"Serigrafia",
    "sg:phone":"+39 02 909 0569",
    "sg:postcode":"24042",
    "sg:province":"Bergamo",
    "wof:name":"Siti Targhe Srl",
    "wof:placetype":"venue"
},
  "geometry": {"coordinates":[9.528478,45.613209],"type":"Point"}
}