{
  "type": "Feature",
  "properties": {
    "addr:full":"04100 Priverno Latina 04100",
    "addr:postcode":"04100;04100",
    "iso:country":"IT",
    "sg:address":"04100 Priverno",
    "sg:orig_category":"Materiali Edili",
    "sg:phone":"+39 0773 622804",
    "sg:postcode":"04100",
    "sg:province":"Latina",
    "wof:name":"Masella Cave",
    "wof:placetype":"venue"
},
  "geometry": {"coordinates":[13.144153,41.48761],"type":"Point"}
}