{
  "type": "Feature",
  "properties": {
    "addr:full":"73055 Racale Racale Lecce 73055",
    "addr:postcode":"73055;73055",
    "iso:country":"IT",
    "sg:address":"73055 Racale",
    "sg:city":"Racale",
    "sg:orig_category":"Abbigliamento Intimo, Calze E Costumi Da Bagno",
    "sg:phone":"+39 0833 585775",
    "sg:postcode":"73055",
    "sg:province":"Lecce",
    "wof:name":"Santantonio Giulio",
    "wof:placetype":"venue"
},
  "geometry": {"coordinates":[18.196001,40.358681],"type":"Point"}
}