{
  "type": "Feature",
  "properties": {
    "addr:full":"56, Via Del Roseto 50012 Bagno A Ripoli Bagno a Ripoli Firenze 50012",
    "addr:postcode":"50012;50012",
    "addr:street":"Via Del Roseto;A",
    "iso:country":"IT",
    "sg:address":"56, Via Del Roseto 50012 Bagno A Ripoli",
    "sg:city":"Bagno a Ripoli",
    "sg:classifiers":[
        {
            "category":"Shopping",
            "type":"Retail Goods"
        }
    ],
    "sg:phone":"+39 39055696051",
    "sg:postcode":"50012",
    "sg:province":"Firenze",
    "sg:tags":[
        "finished",
        "-",
        "metallic"
    ],
    "wof:name":"Rubinetterie Zazzeri Spa",
    "wof:placetype":"venue"
},
  "geometry": {"coordinates":[11.3633041382,43.775844574],"type":"Point"}
}