{
  "type": "Feature",
  "properties": {
    "iso:country":"IT",
    "sg:address":"10147 Torino",
    "sg:city":"Torino",
    "sg:orig_category":"Servizi E Lavori Per Ecologia E Smaltimento Rifiuti. Servizi Ausiliari Di Sorveglianza, Manutenzione E Pulizia",
    "sg:phone":"+39 011 248 7052",
    "sg:postcode":"10147",
    "sg:province":"Torino",
    "sg:website":"http://www.igiencontrol.com",
    "wof:name":"Igiencontrol Srl",
    "wof:placetype":"venue"
},
  "geometry": {"coordinates":[7.678714,45.102089],"type":"Point"}
}