{
  "type": "Feature",
  "properties": {
    "iso:country":"IT",
    "sg:address":"21018 Sesto Calende",
    "sg:city":"Sesto Calende",
    "sg:orig_category":"Valvole E Apparecchiature Di Misura. Apparecchiature E Sistemi Per Imballaggio E Confezionamento",
    "sg:phone":"+39 0331 921222",
    "sg:postcode":"21018",
    "sg:province":"Varese",
    "wof:name":"Tecno Fluss Sas Di Marengo Stefano & C.",
    "wof:placetype":"venue"
},
  "geometry": {"coordinates":[8.753414,45.787594],"type":"Point"}
}