{
  "type": "Feature",
  "properties": {
    "iso:country":"IT",
    "sg:address":"1, Via Filippo Brunelleschi 37053 Cerea",
    "sg:city":"Cerea",
    "sg:classifiers":[
        {
            "category":"Utilities",
            "subcategory":"Electric",
            "type":"Services"
        }
    ],
    "sg:phone":"+39 39044283525",
    "sg:postcode":"37053",
    "sg:province":"Verona",
    "sg:tags":[
        "component",
        "electronic"
    ],
    "wof:name":"Bertelli & Partners S.r.l.",
    "wof:placetype":"venue"
},
  "geometry": {"coordinates":[11.179736,45.22121],"type":"Point"}
}