{
  "type": "Feature",
  "properties": {
    "addr:full":"84010 Maiori Maiori Salerno 84010",
    "addr:postcode":"84010;maiori;84010",
    "addr:street":"Salerno",
    "iso:country":"IT",
    "sg:address":"84010 Maiori",
    "sg:city":"Maiori",
    "sg:orig_category":"Prodotti Alimentari. Agricoltura, Orticoltura E Floricoltura",
    "sg:phone":"+39 089 852924",
    "sg:postcode":"84010",
    "sg:province":"Salerno",
    "wof:name":"Boccuti Salvatore",
    "wof:placetype":"venue"
},
  "geometry": {"coordinates":[14.6404151917,40.6484413147],"type":"Point"}
}