{
  "type": "Feature",
  "properties": {
    "iso:country":"IT",
    "sg:address":"24127 Bergamo",
    "sg:city":"Bergamo",
    "sg:orig_category":"Prodotti Vari In Metallo",
    "sg:phone":"+39 035 400758",
    "sg:postcode":"24127",
    "sg:province":"Bergamo",
    "wof:name":"Santini Funi Srl",
    "wof:placetype":"venue"
},
  "geometry": {"coordinates":[9.6453456879,45.6796607971],"type":"Point"}
}