{
  "type": "Feature",
  "properties": {
    "iso:country":"IT",
    "sg:address":"89125 Reggio Calabria",
    "sg:orig_category":"Climatizzazione E Condizionamento, Apparecchiature E Servizi",
    "sg:phone":"+39 0965 52500",
    "sg:province":"RC",
    "wof:name":"Termoidea Di Giuseppe Sera & C. Sas",
    "wof:placetype":"venue"
},
  "geometry": {"coordinates":[15.647851,38.110126],"type":"Point"}
}