{
  "type": "Feature",
  "properties": {
    "iso:country":"IT",
    "sg:address":"7, Via Della Industria 60035 Jesi",
    "sg:city":"Jesi",
    "sg:classifiers":[
        {
            "category":"Wholesale",
            "subcategory":"Machinery & Supplies",
            "type":"Manufacturing & Wholesale Goods"
        }
    ],
    "sg:phone":"+39 0731 214551",
    "sg:postcode":"60035",
    "sg:province":"Ancona",
    "sg:tags":[
        "-",
        "agriculture",
        "equipment"
    ],
    "wof:name":"Nuova Sjat Spa",
    "wof:placetype":"venue"
},
  "geometry": {"coordinates":[13.35832,43.532978],"type":"Point"}
}