{
  "type": "Feature",
  "properties": {
    "iso:country":"IT",
    "sg:address":"21053 Busto Arsizio",
    "sg:orig_category":"Elaborazione Dati - Servizio Conto Terzi",
    "sg:phone":"+39 0331 670916",
    "sg:postcode":"21053",
    "sg:province":"Varese",
    "wof:name":"Easytech",
    "wof:placetype":"venue"
},
  "geometry": {"coordinates":[8.848162,45.830078],"type":"Point"}
}