{
  "type": "Feature",
  "properties": {
    "addr:full":"5, Via Piacente Don 70056 Molfetta Molfetta Bari 70056",
    "addr:postcode":"70056;70056",
    "addr:street":"Via Piacente Don",
    "iso:country":"IT",
    "sg:address":"5, Via Piacente Don 70056 Molfetta",
    "sg:city":"Molfetta",
    "sg:orig_category":"Miscellaneous Products",
    "sg:phone":"+39 080 338 9383",
    "sg:postcode":"70056",
    "sg:province":"Bari",
    "wof:name":"Europel Di Centrone Nicoletta",
    "wof:placetype":"venue"
},
  "geometry": {"coordinates":[16.8692913055,41.1260528564],"type":"Point"}
}