{
  "type": "Feature",
  "properties": {
    "iso:country":"IT",
    "sg:address":"9, Traversa Ii Cervi Fratelli 81030 Sant'arpino",
    "sg:classifiers":[
        {
            "category":"Shopping",
            "subcategory":"Clothing, Apparel, & Fashions",
            "type":"Retail Goods"
        }
    ],
    "sg:phone":"+39 081 501 4052",
    "sg:postcode":"81030",
    "sg:province":"Caserta",
    "sg:tags":[
        "clothes"
    ],
    "wof:name":"Euroconf Srl",
    "wof:placetype":"venue"
},
  "geometry": {"coordinates":[14.332194,41.075417],"type":"Point"}
}