{
  "type": "Feature",
  "properties": {
    "iso:country":"IT",
    "sg:address":"38100 Trento",
    "sg:city":"Trento",
    "sg:orig_category":"Elettrotecnica Industriale, Prodotti E Apparecchiature. Ricambi E Componenti Dei Mezzi Di Trasporto",
    "sg:phone":"+39 0461 822466",
    "sg:postcode":"38100",
    "sg:province":"Trento",
    "wof:name":"Autoelettroricambi Ochner Bruno Snc",
    "wof:placetype":"venue"
},
  "geometry": {"coordinates":[11.115751,46.092403],"type":"Point"}
}