{
  "type": "Feature",
  "properties": {
    "iso:country":"IT",
    "sg:address":"00040 Pomezia",
    "sg:city":"Pomezia",
    "sg:orig_category":"Servizi E Lavori Per Ecologia E Smaltimento Rifiuti",
    "sg:phone":"+39 06 9160 1333",
    "sg:postcode":"00040",
    "sg:province":"Roma",
    "wof:name":"Ecocontrol",
    "wof:placetype":"venue"
},
  "geometry": {"coordinates":[13.00851,41.732178],"type":"Point"}
}