{
  "type": "Feature",
  "properties": {
    "addr:full":"Via Verniero 03030 Castelliri Castelliri Frosinone 03030",
    "addr:postcode":"03030;03030",
    "addr:street":"Via Verniero",
    "iso:country":"IT",
    "sg:address":"Via Verniero 03030 Castelliri",
    "sg:city":"Castelliri",
    "sg:classifiers":[
        {
            "category":"Shopping",
            "subcategory":"Crafts & Fabrics",
            "type":"Retail Goods"
        }
    ],
    "sg:phone":"+39 0776 809121",
    "sg:postcode":"03030",
    "sg:province":"Frosinone",
    "wof:name":"Liritex S.p.a.",
    "wof:placetype":"venue"
},
  "geometry": {"coordinates":[13.3519020081,41.6401367188],"type":"Point"}
}