{
  "type": "Feature",
  "properties": {
    "iso:country":"IT",
    "sg:address":"Via Casale 113 15040 Gerlotti Alessandria",
    "sg:city":"Alessandria",
    "sg:orig_category":"Ladies' Shoes",
    "sg:phone":"+39 0131 238591",
    "sg:postcode":"15040",
    "sg:province":"Alessandria",
    "sg:website":"www.antinea.it",
    "wof:name":"Calzaturificio Antinea Srl",
    "wof:placetype":"venue"
},
  "geometry": {"coordinates":[8.616951,44.913216],"type":"Point"}
}