{
  "type": "Feature",
  "properties": {
    "iso:country":"IT",
    "sg:address":"20057 Vedano Al Lambro",
    "sg:city":"Vedano al Lambro",
    "sg:orig_category":"Bagno - Accessori E Mobili",
    "sg:phone":"+39 039 492968",
    "sg:postcode":"20057",
    "sg:province":"Milano",
    "wof:name":"Ceramiche In Sas Di Puppo Sandra",
    "wof:placetype":"venue"
},
  "geometry": {"coordinates":[9.269281,45.610836],"type":"Point"}
}