{
  "type": "Feature",
  "properties": {
    "iso:country":"IT",
    "sg:address":"Via Cesare Battisti 21 28073 Fara Novarese",
    "sg:city":"Fara Novarese",
    "sg:classifiers":[
        {
            "category":"Food & Beverages",
            "subcategory":"Liquor & Beverages",
            "type":"Retail Goods"
        }
    ],
    "sg:phone":"+39 0321 829252",
    "sg:postcode":"28073",
    "sg:province":"Novara",
    "sg:tags":[
        "wine",
        "italian"
    ],
    "wof:name":"Dessilani Luigi E Figlio S.r.l.",
    "wof:placetype":"venue"
},
  "geometry": {"coordinates":[8.459826,45.554314],"type":"Point"}
}