{
  "type": "Feature",
  "properties": {
    "iso:country":"IT",
    "sg:address":"13816 Sagliano Micca",
    "sg:city":"Sagliano Micca",
    "sg:orig_category":"Servizi E Lavori Per Abbigliamento E Pelletterie",
    "sg:phone":"+39 015 473753",
    "sg:postcode":"13816",
    "sg:province":"Biella",
    "wof:name":"Roc Wool Di Peron Bianca Rosa",
    "wof:placetype":"venue"
},
  "geometry": {"coordinates":[8.045614,45.609261],"type":"Point"}
}