{
  "type": "Feature",
  "properties": {
    "iso:country":"IT",
    "sg:address":"57123 Livorno",
    "sg:city":"Livorno",
    "sg:orig_category":"Hobbistica",
    "sg:phone":"+39 0586 210160",
    "sg:postcode":"57123",
    "sg:province":"Livorno",
    "wof:name":"Salvamondi Livorno Di Luisi G. E C. Sas",
    "wof:placetype":"venue"
},
  "geometry": {"coordinates":[10.306538,43.554577],"type":"Point"}
}