{
  "type": "Feature",
  "properties": {
    "iso:country":"IT",
    "sg:address":"Via Sandroni 46 21040 Sumirago",
    "sg:city":"Sumirago",
    "sg:classifiers":[
        {
            "category":"Manufacturing",
            "subcategory":"Rubber & Plastics",
            "type":"Manufacturing & Wholesale Goods"
        }
    ],
    "sg:phone":"+39 0331 909175",
    "sg:postcode":"21040",
    "sg:province":"Varese",
    "sg:tags":[
        "dip",
        "processed"
    ],
    "sg:website":"www.sisgomma.it",
    "wof:name":"S.i.s Srl",
    "wof:placetype":"venue"
},
  "geometry": {"coordinates":[8.785254,45.735634],"type":"Point"}
}