{
  "type": "Feature",
  "properties": {
    "addr:full":"36016 Thiene Thiene Vicenza 36016",
    "addr:postcode":"36016;36016",
    "iso:country":"IT",
    "sg:address":"36016 Thiene",
    "sg:city":"Thiene",
    "sg:orig_category":"Metalli E Leghe",
    "sg:phone":"+39 0445 367377",
    "sg:postcode":"36016",
    "sg:province":"Vicenza",
    "sg:website":"http://www.aluservice.it",
    "wof:name":"Alu-service Srl",
    "wof:placetype":"venue"
},
  "geometry": {"coordinates":[11.4839019775,45.692401886],"type":"Point"}
}