{
  "type": "Feature",
  "properties": {
    "addr:full":"74019 Palagiano Palagiano Taranto 74019",
    "addr:postcode":"74019;74019",
    "iso:country":"IT",
    "sg:address":"74019 Palagiano",
    "sg:city":"Palagiano",
    "sg:orig_category":"Materiali Edili",
    "sg:phone":"+39 099 888 3911",
    "sg:postcode":"74019",
    "sg:province":"Taranto",
    "wof:name":"Calce Mori Srl",
    "wof:placetype":"venue"
},
  "geometry": {"coordinates":[17.018513,40.558895],"type":"Point"}
}