{
  "type": "Feature",
  "properties": {
    "addr:full":"13/15, Viale Dell' Industria 35010 Curtarolo Curtarolo Padova 35010",
    "addr:housenumber":"13 / 15",
    "addr:postcode":"35010;35010",
    "addr:street":"Viale Dell ' Industria",
    "iso:country":"IT",
    "sg:address":"13/15, Viale Dell' Industria 35010 Curtarolo",
    "sg:city":"Curtarolo",
    "sg:classifiers":[
        {
            "category":"Shopping",
            "type":"Retail Goods"
        }
    ],
    "sg:phone":"+39 049 962 0255",
    "sg:postcode":"35010",
    "sg:province":"Padova",
    "sg:tags":[
        "finished",
        "-",
        "metallic"
    ],
    "wof:name":"Europrofilam (s.r.l.)",
    "wof:placetype":"venue"
},
  "geometry": {"coordinates":[11.8765888214,45.4095687866],"type":"Point"}
}