{
  "type": "Feature",
  "properties": {
    "iso:country":"IT",
    "sg:address":"35010 Limena",
    "sg:city":"Limena",
    "sg:orig_category":"Macchine Ed Impianti Per Edilizia E Lavori Pubblici",
    "sg:phone":"+39 049 767973",
    "sg:postcode":"35010",
    "sg:province":"Padova",
    "wof:name":"P.m.dai Pra' Marcello Di Dott. Dai Pra' Paola",
    "wof:placetype":"venue"
},
  "geometry": {"coordinates":[11.840283,45.472507],"type":"Point"}
}