{
  "type": "Feature",
  "properties": {
    "addr:full":"51010 Massa E Cozzile Massa e Cozzile Pistoia 51010",
    "addr:postcode":"51010;51010",
    "iso:country":"IT",
    "sg:address":"51010 Massa E Cozzile",
    "sg:city":"Massa e Cozzile",
    "sg:classifiers":[
        {
            "category":"Manufacturing",
            "subcategory":"Leather Goods",
            "type":"Manufacturing & Wholesale Goods"
        }
    ],
    "sg:phone":"+39 0572 79261",
    "sg:postcode":"51010",
    "sg:province":"Pistoia",
    "sg:tags":[
        "goods",
        "clothing",
        "supply"
    ],
    "sg:website":"http://bottonificioideal.nodalis.it",
    "wof:name":"Bottonificio Ideal Di Taci Giuseppe E C. Snc",
    "wof:placetype":"venue"
},
  "geometry": {"coordinates":[10.744135,43.909386],"type":"Point"}
}