{
  "type": "Feature",
  "properties": {
    "iso:country":"IT",
    "sg:address":"36015 Schio",
    "sg:city":"Schio",
    "sg:orig_category":"Arredo Bagno Ed Idrosanitari. Forniture Alle Strutture Ricettive. Apparecchi, Attrezzature E Forniture Per Centri Estetici",
    "sg:phone":"+39 0445 513024",
    "sg:postcode":"36015",
    "sg:province":"Vicenza",
    "wof:name":"Chaboros",
    "wof:placetype":"venue"
},
  "geometry": {"coordinates":[11.362141,45.709492],"type":"Point"}
}