{
  "type": "Feature",
  "properties": {
    "iso:country":"IT",
    "sg:address":"Km. 1.400, Via Epitaffio 04100 Latina",
    "sg:city":"Latina",
    "sg:classifiers":[
        {
            "category":"Professional",
            "subcategory":"Engineering",
            "type":"Services"
        }
    ],
    "sg:phone":"+39 0773 696707",
    "sg:postcode":"04100",
    "sg:province":"Latina",
    "sg:tags":[
        "machine",
        "-",
        "mechanical"
    ],
    "wof:name":"Manzo Riscaldamenti S.n.c.",
    "wof:placetype":"venue"
},
  "geometry": {"coordinates":[12.931159,41.508556],"type":"Point"}
}