{
  "type": "Feature",
  "properties": {
    "iso:country":"IT",
    "sg:address":"25060 Marcheno",
    "sg:city":"Marcheno",
    "sg:orig_category":"Sport - Articoli E Forniture",
    "sg:phone":"+39 030 861 0062",
    "sg:postcode":"25060",
    "sg:province":"Brescia",
    "wof:name":"Zoli Orsola & C. (s.n.c.)",
    "wof:placetype":"venue"
},
  "geometry": {"coordinates":[10.232441,45.726032],"type":"Point"}
}