{
  "type": "Feature",
  "properties": {
    "iso:country":"IT",
    "sg:address":"20129 Milano",
    "sg:city":"Milano",
    "sg:orig_category":"Trasporto Pubblico E Privato",
    "sg:phone":"+39 02 551 3422",
    "sg:postcode":"20129",
    "sg:province":"Milano",
    "wof:name":"Taxi",
    "wof:placetype":"venue"
},
  "geometry": {"coordinates":[9.207071,45.462078],"type":"Point"}
}