{
  "type": "Feature",
  "properties": {
    "addr:full":"80010 Villaricca Villaricca Napoli 80010",
    "addr:postcode":"80010;80010",
    "iso:country":"IT",
    "sg:address":"80010 Villaricca",
    "sg:city":"Villaricca",
    "sg:orig_category":"Carta Uso Igienico E Domestico",
    "sg:phone":"+39 081 330 3390",
    "sg:postcode":"80010",
    "sg:province":"Napoli",
    "wof:name":"Maxiclean Srl",
    "wof:placetype":"venue"
},
  "geometry": {"coordinates":[14.197062,40.917965],"type":"Point"}
}