{
  "type": "Feature",
  "properties": {
    "addr:full":"87100 Cosenza Cosenza Cosenza 87100",
    "addr:postcode":"87100;87100",
    "iso:country":"IT",
    "sg:address":"87100 Cosenza",
    "sg:city":"Cosenza",
    "sg:orig_category":"Manufacturers: Prefabbricati. Servizi E Lavori Per Ecologia E Smaltimento Rifiuti",
    "sg:phone":"+39 0984 32887",
    "sg:postcode":"87100",
    "sg:province":"Cosenza",
    "wof:name":"A.a.a.a. Autoespurgo Adolfo Fortino Sas",
    "wof:placetype":"venue"
},
  "geometry": {"coordinates":[16.248182,39.30822],"type":"Point"}
}