{
  "type": "Feature",
  "properties": {
    "addr:full":"20052 Monza Monza Milano 20052",
    "addr:postcode":"20052;20052",
    "iso:country":"IT",
    "sg:address":"20052 Monza",
    "sg:city":"Monza",
    "sg:orig_category":"Servizi E Lavori Per Edilizia E Lavori Pubblici",
    "sg:phone":"+39 039 200 1885",
    "sg:postcode":"20052",
    "sg:province":"Milano",
    "wof:name":"Peschiera Silvano",
    "wof:placetype":"venue"
},
  "geometry": {"coordinates":[9.223154,45.519226],"type":"Point"}
}