{
  "type": "Feature",
  "properties": {
    "iso:country":"IT",
    "sg:address":"41051 Castelnuovo Rangone",
    "sg:city":"Castelnuovo Rangone",
    "sg:orig_category":"Forniture Per Agricoltura E Zootecnia. Animali Domestici",
    "sg:phone":"+39 059 538280",
    "sg:postcode":"41051",
    "sg:province":"Modena",
    "wof:name":"Gre.mo Di Gregorini Emilio &c.(s.n.c.)",
    "wof:placetype":"venue"
},
  "geometry": {"coordinates":[10.9244880676,44.5478820801],"type":"Point"}
}