{
  "type": "Feature",
  "properties": {
    "addr:full":"Via Sommacampagna 59/c 37137 Verona Verona Verona 37137",
    "addr:housenumber":"59 / c",
    "addr:postcode":"37137;37137",
    "addr:street":"Via Sommacampagna",
    "iso:country":"IT",
    "sg:address":"Via Sommacampagna 59/c 37137 Verona",
    "sg:city":"Verona",
    "sg:classifiers":[
        {
            "category":"Communications",
            "subcategory":"Television Station",
            "type":"Services"
        }
    ],
    "sg:phone":"+39 045 862 4211",
    "sg:postcode":"37137",
    "sg:province":"Verona",
    "sg:tags":[
        "chiller"
    ],
    "wof:name":"Officine Cailotto Di Silvio Cailotto",
    "wof:placetype":"venue"
},
  "geometry": {"coordinates":[10.928185,45.417313],"type":"Point"}
}