{
  "type": "Feature",
  "properties": {
    "iso:country":"IT",
    "sg:address":"Via Leonardo Di Vinci 62, Brescia, Bs",
    "sg:classifiers":[
        {
            "category":"Banks & Credit Unions",
            "subcategory":"Bank",
            "type":"Services"
        }
    ],
    "wof:name":"Fin-eco Leasing Spa",
    "wof:placetype":"venue"
},
  "geometry": {"coordinates":[10.2153,45.546196],"type":"Point"}
}