{
  "type": "Feature",
  "properties": {
    "addr:full":"Via Guido Rossa 36 41011 Campogalliano Campogalliano Modena 41011",
    "addr:housenumber":"36",
    "addr:postcode":"41011;41011",
    "addr:street":"Via Guido Rossa",
    "iso:country":"IT",
    "sg:address":"Via Guido Rossa 36 41011 Campogalliano",
    "sg:city":"Campogalliano",
    "sg:classifiers":[
        {
            "category":"Communications",
            "subcategory":"Film & Video Production",
            "type":"Services"
        }
    ],
    "sg:phone":"+39 059 525500",
    "sg:postcode":"41011",
    "sg:province":"Modena",
    "sg:tags":[
        "hair",
        "ware"
    ],
    "sg:website":"www.lascozzese.it",
    "wof:name":"Doccia La Scozzese Srl",
    "wof:placetype":"venue"
},
  "geometry": {"coordinates":[10.92522,44.647079],"type":"Point"}
}