{
  "type": "Feature",
  "properties": {
    "iso:country":"IT",
    "sg:address":"44100 Ferrara",
    "sg:city":"Ferrara",
    "sg:orig_category":"Medici Specialisti - Andrologia",
    "sg:phone":"+39 0532 200847",
    "sg:postcode":"44100",
    "sg:province":"Ferrara",
    "wof:name":"Cavallini Giorgio",
    "wof:placetype":"venue"
},
  "geometry": {"coordinates":[11.62737,44.838779],"type":"Point"}
}