{
  "type": "Feature",
  "properties": {
    "addr:full":"73100 Lecce Lecce Lecce 73100",
    "addr:postcode":"73100;73100",
    "iso:country":"IT",
    "sg:address":"73100 Lecce",
    "sg:city":"Lecce",
    "sg:orig_category":"Macchine, Impianti Ed Attrezzature Per Agricoltura E Zootecnia",
    "sg:phone":"+39 0832 348854",
    "sg:postcode":"73100",
    "sg:province":"Lecce",
    "wof:name":"De Pascalis Francesco",
    "wof:placetype":"venue"
},
  "geometry": {"coordinates":[18.184326,40.350254],"type":"Point"}
}