{
  "type": "Feature",
  "properties": {
    "addr:full":"20089 Rozzano Rozzano Milano 20089",
    "addr:postcode":"20089;20089",
    "iso:country":"IT",
    "sg:address":"20089 Rozzano",
    "sg:city":"Rozzano",
    "sg:orig_category":"Abbigliamento Esterno, Maglierie E Pelliccerie. Calzature, Pelletterie E Pelli. Shopping",
    "sg:phone":"+39 02 825 3889",
    "sg:postcode":"20089",
    "sg:province":"Milano",
    "wof:name":"I Morosini Srl",
    "wof:placetype":"venue"
},
  "geometry": {"coordinates":[9.162158,45.379581],"type":"Point"}
}