{
  "type": "Feature",
  "properties": {
    "addr:full":"56029 Santa Croce Sull'arno Pisa 56029",
    "addr:postcode":"56029;56029",
    "iso:country":"IT",
    "sg:address":"56029 Santa Croce Sull'arno",
    "sg:orig_category":"Pelli E Pellami - Produzione E Commercio",
    "sg:phone":"+39 0571 360798",
    "sg:postcode":"56029",
    "sg:province":"Pisa",
    "wof:name":"New Entry Pellami Srl",
    "wof:placetype":"venue"
},
  "geometry": {"coordinates":[10.7788105011,43.7103004456],"type":"Point"}
}