{
  "type": "Feature",
  "properties": {
    "iso:country":"IT",
    "sg:address":"20128 Milano",
    "sg:city":"Milano",
    "sg:orig_category":"Servizi Di Magazzinaggio E Movimentazione. Servizi Ausiliari Di Sorveglianza, Manutenzione E Pulizia",
    "sg:phone":"+39 02 2553 9034",
    "sg:postcode":"20128",
    "sg:province":"Milano",
    "wof:name":"General Service",
    "wof:placetype":"venue"
},
  "geometry": {"coordinates":[9.23082,45.506058],"type":"Point"}
}