{
  "type": "Feature",
  "properties": {
    "iso:country":"IT",
    "sg:address":"36075 Montecchio Maggiore",
    "sg:city":"Montecchio Maggiore",
    "sg:classifiers":[
        {
            "category":"Wholesale",
            "subcategory":"Auto Parts",
            "type":"Manufacturing & Wholesale Goods"
        }
    ],
    "sg:phone":"+39 0444 709311",
    "sg:postcode":"36075",
    "sg:province":"Vicenza",
    "sg:tags":[
        "product",
        "industrial",
        "vehicles",
        "component",
        "equipment",
        "engineering",
        "electrical",
        "motor",
        "spare"
    ],
    "wof:name":"F.i.a.m.m. Spa",
    "wof:placetype":"venue"
},
  "geometry": {"coordinates":[11.486393,45.505367],"type":"Point"}
}