{
  "type": "Feature",
  "properties": {
    "iso:country":"IT",
    "sg:address":"60100 Ancona",
    "sg:orig_category":"Abbigliamento Intimo, Calze E Costumi Da Bagno",
    "sg:phone":"+39 071 280 1459",
    "sg:province":"AN",
    "wof:name":"Angy's Moda Srl",
    "wof:placetype":"venue"
},
  "geometry": {"coordinates":[13.06563,43.442204],"type":"Point"}
}