{
  "type": "Feature",
  "properties": {
    "iso:country":"IT",
    "sg:address":"09040 Donori",
    "sg:orig_category":"Trattamenti Termici E Superficiali Metalli, Galvanotecnica",
    "sg:phone":"+39 070 981374",
    "sg:postcode":"09040",
    "sg:province":"Cagliari",
    "wof:name":"Zinco L.a.s.a. Srl",
    "wof:placetype":"venue"
},
  "geometry": {"coordinates":[9.052055,39.275482],"type":"Point"}
}