{
  "type": "Feature",
  "properties": {
    "addr:full":"58037 Santa Fiora Santa Fiora Grosseto 58037",
    "addr:postcode":"58037;58037",
    "iso:country":"IT",
    "sg:address":"58037 Santa Fiora",
    "sg:city":"Santa Fiora",
    "sg:orig_category":"Materiali E Componenti Elettrotecnici",
    "sg:phone":"+39 0564 979511",
    "sg:postcode":"58037",
    "sg:province":"Grosseto",
    "wof:name":"Cooperativa Di Consumo Unione Amiatina",
    "wof:placetype":"venue"
},
  "geometry": {"coordinates":[11.581654,42.828278],"type":"Point"}
}