{
  "type": "Feature",
  "properties": {
    "iso:country":"IT",
    "sg:address":"15048 Valenza",
    "sg:city":"Valenza",
    "sg:classifiers":[
        {
            "category":"Shopping",
            "subcategory":"Jewelry",
            "type":"Retail Goods"
        }
    ],
    "sg:phone":"+39 0131 953777",
    "sg:postcode":"15048",
    "sg:province":"Alessandria",
    "sg:tags":[
        "watchmaker",
        "jewelers",
        "gold",
        "silversmiths"
    ],
    "sg:website":"http://pwhux.tin.it/vccgdu",
    "wof:name":"Vaccari & C. Di Guido Vaccari Sas",
    "wof:placetype":"venue"
},
  "geometry": {"coordinates":[8.608182,44.912571],"type":"Point"}
}