{
  "type": "Feature",
  "properties": {
    "addr:full":"70121 Bari Bari Bari 70121",
    "addr:postcode":"70121;70121",
    "iso:country":"IT",
    "sg:address":"70121 Bari",
    "sg:city":"Bari",
    "sg:orig_category":"Elaboratori Elettronici - Periferiche",
    "sg:phone":"+39 080 558 6747",
    "sg:postcode":"70121",
    "sg:province":"Bari",
    "wof:name":"Triforce Computer",
    "wof:placetype":"venue"
},
  "geometry": {"coordinates":[16.878059,41.12038],"type":"Point"}
}