{
  "type": "Feature",
  "properties": {
    "iso:country":"IT",
    "sg:address":"00161 Roma",
    "sg:city":"Roma",
    "sg:orig_category":"Bevande, Vini E Liquori",
    "sg:phone":"+39 06 4425 4321",
    "sg:postcode":"00161",
    "sg:province":"Roma",
    "wof:name":"Tesciuba Alessio",
    "wof:placetype":"venue"
},
  "geometry": {"coordinates":[12.518141,41.914631],"type":"Point"}
}