{
  "type": "Feature",
  "properties": {
    "iso:country":"IT",
    "sg:address":"20019 Settimo Milanese",
    "sg:city":"Settimo Milanese",
    "sg:orig_category":"Servizi E Lavori Per Arredamento E Industria Del Legno. Forniture Per Congressi, Fiere E Manifestazioni. Servizi Per Aziende, Manifestazioni E Supporto Agli Scambi Commerciali",
    "sg:phone":"+39 02 328 7244",
    "sg:postcode":"20019",
    "sg:province":"Milano",
    "wof:name":"Tecnovision Luminarie Srl",
    "wof:placetype":"venue"
},
  "geometry": {"coordinates":[9.058551,45.465012],"type":"Point"}
}