{
  "type": "Feature",
  "properties": {
    "iso:country":"IT",
    "sg:address":"Vle Martiri Della Resistenza 61 06049 Spoleto",
    "sg:city":"Spoleto",
    "sg:classifiers":[
        {
            "category":"Professional",
            "subcategory":"Printing & Photocopies",
            "type":"Services"
        }
    ],
    "sg:phone":"+39 0743 23041",
    "sg:postcode":"06049",
    "sg:province":"Perugia",
    "sg:tags":[
        "shop",
        "industrial"
    ],
    "wof:name":"Nuova Panetto & Petrelli Spa",
    "wof:placetype":"venue"
},
  "geometry": {"coordinates":[12.389172,43.110703],"type":"Point"}
}