{
  "type": "Feature",
  "properties": {
    "iso:country":"IT",
    "sg:address":"80126 Napoli",
    "sg:city":"Napoli",
    "sg:orig_category":"Materiali Semilavorati Metallici",
    "sg:phone":"+39 081 726 7160",
    "sg:postcode":"80126",
    "sg:province":"Napoli",
    "wof:name":"Della Bella Maria",
    "wof:placetype":"venue"
},
  "geometry": {"coordinates":[14.175657,40.857288],"type":"Point"}
}