{
  "type": "Feature",
  "properties": {
    "addr:full":"70012 Carbonara BA",
    "addr:postcode":"70012",
    "iso:country":"IT",
    "sg:address":"70012 Carbonara",
    "sg:orig_category":"Accessori Dei Mezzi Di Trasporto. Riparazione Dei Mezzi Di Trasporto",
    "sg:phone":"+39 080 565 0133",
    "sg:province":"BA",
    "wof:name":"Ledi (s.n.c.)",
    "wof:placetype":"venue"
},
  "geometry": {"coordinates":[16.869015,41.066822],"type":"Point"}
}