{
  "type": "Feature",
  "properties": {
    "iso:country":"IT",
    "sg:address":"30/36, Via G. Galilei 36030 Costabissara",
    "sg:city":"Costabissara",
    "sg:classifiers":[
        {
            "category":"Professional",
            "subcategory":"Engineering",
            "type":"Services"
        }
    ],
    "sg:phone":"+39 0444 557311",
    "sg:postcode":"36030",
    "sg:province":"Vicenza",
    "sg:tags":[
        "machine",
        "-",
        "mechanical"
    ],
    "wof:name":"Cmp Di Pilastro (s.n.c.)",
    "wof:placetype":"venue"
},
  "geometry": {"coordinates":[11.503628,45.589024],"type":"Point"}
}