{
  "type": "Feature",
  "properties": {
    "iso:country":"IT",
    "sg:address":"00013 Mentana",
    "sg:city":"Mentana",
    "sg:orig_category":"Non-classified Establishments",
    "sg:phone":"+39 06 9053 2480",
    "sg:postcode":"00013",
    "sg:province":"Roma",
    "wof:name":"Evans Chris",
    "wof:placetype":"venue"
},
  "geometry": {"coordinates":[12.638505,41.994446],"type":"Point"}
}