{
  "type": "Feature",
  "properties": {
    "addr:full":"Zona Industriale, 86039 Termoli, Cb Termoli Campobasso 86039",
    "addr:postcode":"86039;cb;86039",
    "addr:street":"Zona Industriale",
    "iso:country":"IT",
    "sg:address":"Zona Industriale, 86039 Termoli, Cb",
    "sg:city":"Termoli",
    "sg:classifiers":[
        {
            "category":"Banks & Credit Unions",
            "subcategory":"Bank",
            "type":"Services"
        }
    ],
    "sg:postcode":"86039",
    "sg:province":"Campobasso",
    "wof:name":"Consorzio Di Sviluppo Industriale Della Valle Del Biferno",
    "wof:placetype":"venue"
},
  "geometry": {"coordinates":[14.664799,41.560085],"type":"Point"}
}