{
  "type": "Feature",
  "properties": {
    "iso:country":"IT",
    "sg:address":"Via Matteotti 34; Bagnacavallo; 48012",
    "sg:city":"Bagnacavallo",
    "sg:classifiers":[
        {
            "category":"Banks & Credit Unions",
            "subcategory":"Bank",
            "type":"Services"
        }
    ],
    "sg:phone":"+39 0545 62243",
    "sg:postcode":"48012",
    "sg:province":"Ravenna",
    "wof:name":"Rolo Banca 1473 Spa",
    "wof:placetype":"venue"
},
  "geometry": {"coordinates":[11.979165,44.415752],"type":"Point"}
}