{
  "type": "Feature",
  "properties": {
    "iso:country":"IT",
    "sg:address":"31044 Montebelluna",
    "sg:city":"Montebelluna",
    "sg:orig_category":"Ricerca, Selezione E Formazione Del Personale",
    "sg:phone":"+39 0423 604664",
    "sg:postcode":"31044",
    "sg:province":"Treviso",
    "wof:name":"Umana Spa",
    "wof:placetype":"venue"
},
  "geometry": {"coordinates":[12.235806,45.662197],"type":"Point"}
}