{
  "type": "Feature",
  "properties": {
    "iso:country":"IT",
    "sg:address":"31040 Mansu\u00e8",
    "sg:orig_category":"Arredamenti - Produzione E Ingrosso",
    "sg:phone":"+39 0422 741519",
    "sg:postcode":"31040",
    "sg:province":"Treviso",
    "sg:website":"http://www.paginegialle.it/melodysrl",
    "wof:name":"Melody Srl",
    "wof:placetype":"venue"
},
  "geometry": {"coordinates":[12.2416,45.646084],"type":"Point"}
}