{
  "type": "Feature",
  "properties": {
    "addr:full":"25018 Montichiari Montichiari Brescia 25018",
    "addr:postcode":"25018;25018",
    "iso:country":"IT",
    "sg:address":"25018 Montichiari",
    "sg:city":"Montichiari",
    "sg:orig_category":"Analisi Chimiche, Industriali E Merceologiche",
    "sg:phone":"+39 030 996 1102",
    "sg:postcode":"25018",
    "sg:province":"Brescia",
    "wof:name":"Crc Centro Ricerche Chimiche Srl",
    "wof:placetype":"venue"
},
  "geometry": {"coordinates":[10.360884,45.42651],"type":"Point"}
}