{
  "type": "Feature",
  "properties": {
    "addr:full":"00041 Albano Laziale Albano Laziale Roma 00041",
    "addr:postcode":"00041;00041",
    "addr:street":"Roma",
    "iso:country":"IT",
    "sg:address":"00041 Albano Laziale",
    "sg:city":"Albano Laziale",
    "sg:orig_category":"Macchine, Impianti E Forniture Per Industria Grafica, Cartaria E Cartotecnica. Prodotti Chimici Secondari",
    "sg:phone":"+39 06 934 1665",
    "sg:postcode":"00041",
    "sg:province":"Roma",
    "wof:name":"Piercolor Srl",
    "wof:placetype":"venue"
},
  "geometry": {"coordinates":[12.652925,41.69754],"type":"Point"}
}