{
  "type": "Feature",
  "properties": {
    "iso:country":"IT",
    "sg:address":"94, Via Camisano 19031 Ameglia",
    "sg:city":"Ameglia",
    "sg:classifiers":[
        {
            "category":"Travel",
            "subcategory":"Travel Agent",
            "type":"Entertainment"
        }
    ],
    "sg:phone":"+39 0187 600501",
    "sg:postcode":"19031",
    "sg:province":"La Spezia",
    "sg:tags":[
        "business"
    ],
    "wof:name":"Hotel Ala Bianca",
    "wof:placetype":"venue"
},
  "geometry": {"coordinates":[9.962879,44.077629],"type":"Point"}
}