{
  "type": "Feature",
  "properties": {
    "iso:country":"IT",
    "sg:address":"6, Corso Europa 24030 Valbrembo",
    "sg:city":"Valbrembo",
    "sg:classifiers":[
        {
            "category":"Professional",
            "subcategory":"Engineering",
            "type":"Services"
        }
    ],
    "sg:phone":"+39 39035528032",
    "sg:postcode":"24030",
    "sg:province":"Bergamo",
    "sg:tags":[
        "machine",
        "-",
        "mechanical"
    ],
    "wof:name":"A.z. - F.i.u.s. (s.p.a.)",
    "wof:placetype":"venue"
},
  "geometry": {"coordinates":[9.601133,45.716274],"type":"Point"}
}