{
  "type": "Feature",
  "properties": {
    "addr:full":"10, Via B. Buozzi 13875 Ponderano Ponderano Biella 13875",
    "addr:postcode":"13875;13875",
    "addr:street":"Via B. Buozzi",
    "iso:country":"IT",
    "sg:address":"10, Via B. Buozzi 13875 Ponderano",
    "sg:city":"Ponderano",
    "sg:classifiers":[
        {
            "category":"Manufacturing",
            "subcategory":"Motor Vehicles & Parts",
            "type":"Manufacturing & Wholesale Goods"
        }
    ],
    "sg:phone":"+39 39015541355",
    "sg:postcode":"13875",
    "sg:province":"Biella",
    "sg:tags":[
        "engine"
    ],
    "wof:name":"Prina Officina Meccanica Di Prina Mello Mario & C.",
    "wof:placetype":"venue"
},
  "geometry": {"coordinates":[8.054609,45.543114],"type":"Point"}
}