{
  "type": "Feature",
  "properties": {
    "iso:country":"IT",
    "sg:address":"19037 Santo Stefano Magra",
    "sg:orig_category":"Imprese Di Costruzioni Civili Ed Industriali",
    "sg:phone":"+39 0187 699179",
    "sg:postcode":"19037",
    "sg:province":"La Spezia",
    "wof:name":"Scardino Davide",
    "wof:placetype":"venue"
},
  "geometry": {"coordinates":[9.868692,44.148312],"type":"Point"}
}