{
  "type": "Feature",
  "properties": {
    "addr:full":"149, Via Valle Po 12100 Cuneo Cuneo Cuneo 12100",
    "addr:housenumber":"149",
    "addr:postcode":"12100;12100",
    "addr:street":"Via Valle Po",
    "iso:country":"IT",
    "sg:address":"149, Via Valle Po 12100 Cuneo",
    "sg:city":"Cuneo",
    "sg:classifiers":[
        {
            "category":"Parking",
            "subcategory":"Lot",
            "type":"Transportation"
        }
    ],
    "sg:phone":"+39 0171 410311",
    "sg:postcode":"12100",
    "sg:province":"Cuneo",
    "sg:tags":[
        "transport",
        "road"
    ],
    "wof:name":"Lannutti Autotrasporti Srl",
    "wof:placetype":"venue"
},
  "geometry": {"coordinates":[7.541436,44.426941],"type":"Point"}
}