{
  "type": "Feature",
  "properties": {
    "addr:full":"1 Piazza A. Torre, 84076 Torchiara Torchiara Salerno 84076",
    "addr:postcode":"84076;84076",
    "addr:street":"Piazza A. Torre",
    "iso:country":"IT",
    "sg:address":"1 Piazza A. Torre, 84076 Torchiara",
    "sg:city":"Torchiara",
    "sg:classifiers":[
        {
            "category":"Banks & Credit Unions",
            "subcategory":"Financial Services",
            "type":"Services"
        }
    ],
    "sg:phone":"+39 0974 831032",
    "sg:postcode":"84076",
    "sg:province":"Salerno",
    "sg:tags":[
        "banking",
        "finance",
        "insurance"
    ],
    "wof:name":"Banca Credito Cooperativo Comuni Cilentani",
    "wof:placetype":"venue"
},
  "geometry": {"coordinates":[14.765912056,40.6779556274],"type":"Point"}
}