{
  "type": "Feature",
  "properties": {
    "iso:country":"IT",
    "sg:address":"Vle Della Repubblica 79 20053 Muggio'",
    "sg:classifiers":[
        {
            "category":"Bars & Pubs",
            "subcategory":"Dive Bar",
            "type":"Food & Drink"
        }
    ],
    "sg:phone":"+39 039 278 0791",
    "sg:postcode":"20053",
    "sg:province":"Milano",
    "sg:tags":[
        "extractor",
        "hood",
        "kitchen"
    ],
    "wof:name":"Pessi Snc Di Luigi E Pietro Pessi",
    "wof:placetype":"venue"
},
  "geometry": {"coordinates":[9.172639,45.569447],"type":"Point"}
}