{
  "type": "Feature",
  "properties": {
    "iso:country":"IT",
    "sg:address":"37135 Verona",
    "sg:city":"Verona",
    "sg:orig_category":"Forniture Per Edilizia E Lavori Pubblici",
    "sg:phone":"+39 045 820 4250",
    "sg:postcode":"37135",
    "sg:province":"Verona",
    "wof:name":"Sicontraf Srl",
    "wof:placetype":"venue"
},
  "geometry": {"coordinates":[10.9740009308,45.4010734558],"type":"Point"}
}