{
  "type": "Feature",
  "properties": {
    "addr:full":"70123 Bari Bari Bari 70123",
    "addr:postcode":"70123;70123",
    "iso:country":"IT",
    "sg:address":"70123 Bari",
    "sg:city":"Bari",
    "sg:orig_category":"Forniture Per Agricoltura E Zootecnia. Animali Domestici",
    "sg:phone":"+39 080 534 8402",
    "sg:postcode":"70123",
    "sg:province":"Bari",
    "wof:name":"Croce Azzurra Farmaceutici Srl",
    "wof:placetype":"venue"
},
  "geometry": {"coordinates":[16.8783054352,41.001914978],"type":"Point"}
}