{
  "type": "Feature",
  "properties": {
    "addr:full":"8, Via Ferraris Galileo 30038 Spinea Spinea Venezia 30038",
    "addr:postcode":"30038;30038",
    "addr:street":"Via Ferraris Galileo",
    "iso:country":"IT",
    "sg:address":"8, Via Ferraris Galileo 30038 Spinea",
    "sg:city":"Spinea",
    "sg:classifiers":[
        {
            "category":"Manufacturing",
            "subcategory":"Metals",
            "type":"Manufacturing & Wholesale Goods"
        }
    ],
    "sg:phone":"+39 041 541 1452",
    "sg:postcode":"30038",
    "sg:province":"Venezia",
    "sg:tags":[
        "metallurgy",
        "metalworking"
    ],
    "wof:name":"Mondi Impianti Di Mondi A & C. (s.n.c.)",
    "wof:placetype":"venue"
},
  "geometry": {"coordinates":[12.1458845139,45.5071296692],"type":"Point"}
}