{
  "type": "Feature",
  "properties": {
    "iso:country":"IT",
    "sg:address":"Via Resegone 48 20025 Legnano",
    "sg:city":"Legnano",
    "sg:classifiers":[
        {
            "category":"Utilities",
            "subcategory":"Telephone",
            "type":"Services"
        }
    ],
    "sg:phone":"+39 0323 887344",
    "sg:postcode":"20025",
    "sg:province":"Milano",
    "sg:tags":[
        "device",
        "electromechanical",
        "assembly",
        "electronic"
    ],
    "sg:website":"www.bdm.it",
    "wof:name":"Italstamp Srl",
    "wof:placetype":"venue"
},
  "geometry": {"coordinates":[8.92016,45.604191],"type":"Point"}
}