{
  "type": "Feature",
  "properties": {
    "iso:country":"IT",
    "sg:address":"20077 Melegnano",
    "sg:city":"Melegnano",
    "sg:orig_category":"Servizi E Lavori Per Abbigliamento E Pelletterie. Scuole E Servizi Scolastici. Ricerca, Selezione E Formazione Del Personale",
    "sg:phone":"+39 02 983 6500",
    "sg:postcode":"20077",
    "sg:province":"Milano",
    "wof:name":"Bittarelli Cesare",
    "wof:placetype":"venue"
},
  "geometry": {"coordinates":[9.325457,45.35445],"type":"Point"}
}