{
  "type": "Feature",
  "properties": {
    "iso:country":"IT",
    "sg:address":"Via Milano, 3/4/5 - Gallo 61020 Petriano",
    "sg:city":"Gallo",
    "sg:orig_category":"Postforming Elements",
    "sg:phone":"+39 0722 35521",
    "sg:postcode":"61020",
    "sg:province":"Pesaro E Urbino",
    "sg:website":"www.fabgroup.com",
    "wof:name":"Fab Srl",
    "wof:placetype":"venue"
},
  "geometry": {"coordinates":[12.5298032761,43.633556366],"type":"Point"}
}