{
  "type": "Feature",
  "properties": {
    "iso:country":"IT",
    "sg:address":"30, Via Marcello Benedetto 20124 Milano",
    "sg:city":"Milano",
    "sg:classifiers":[
        {
            "category":"Professional",
            "subcategory":"Computer Services",
            "type":"Services"
        }
    ],
    "sg:phone":"+39 02 2952 6084",
    "sg:postcode":"20124",
    "sg:province":"Milano",
    "sg:tags":[
        "information",
        "technology"
    ],
    "wof:name":"Gsm Gruppo Media Service Srl",
    "wof:placetype":"venue"
},
  "geometry": {"coordinates":[9.209229,45.481716],"type":"Point"}
}