{
  "type": "Feature",
  "properties": {
    "iso:country":"IT",
    "sg:address":"00165 Roma",
    "sg:city":"Roma",
    "sg:orig_category":"Dentisti Medici Chirurghi Ed Odontoiatri",
    "sg:phone":"+39 06 663 7738",
    "sg:postcode":"00165",
    "sg:province":"Roma",
    "sg:website":"http://www.dentisti.it",
    "wof:name":"Studio Associato Dr. Santini E Dr. Pecoraino",
    "wof:placetype":"venue"
},
  "geometry": {"coordinates":[12.432912,41.895123],"type":"Point"}
}