{
  "type": "Feature",
  "properties": {
    "addr:full":"43100 Parma Parma Parma 43100",
    "addr:postcode":"43100;43100",
    "iso:country":"IT",
    "sg:address":"43100 Parma",
    "sg:city":"Parma",
    "sg:orig_category":"Apparecchiature E Sistemi Per Imballaggio E Confezionamento",
    "sg:phone":"+39 0521 275111",
    "sg:postcode":"43100",
    "sg:province":"Parma",
    "wof:name":"Ocme Srl",
    "wof:placetype":"venue"
},
  "geometry": {"coordinates":[10.332099,44.823841],"type":"Point"}
}