{
  "type": "Feature",
  "properties": {
    "iso:country":"IT",
    "sg:address":"30, Via Newton 40017 San Giovanni In Persiceto",
    "sg:city":"San Giovanni in Persiceto",
    "sg:classifiers":[
        {
            "category":"Shopping",
            "subcategory":"Crafts & Fabrics",
            "type":"Retail Goods"
        }
    ],
    "sg:phone":"+39 39051824201",
    "sg:postcode":"40017",
    "sg:province":"Bologna",
    "wof:name":"Arem Due Srl C/socio Unico",
    "wof:placetype":"venue"
},
  "geometry": {"coordinates":[11.2003545761,44.6216812134],"type":"Point"}
}