{
  "type": "Feature",
  "properties": {
    "addr:full":"Ss Regina, Km 3,300 62018 Potenza Picena Potenza Picena Macerata 62018",
    "addr:housenumber":"km 3,300",
    "addr:postcode":"62018;62018",
    "iso:country":"IT",
    "sg:address":"Ss Regina, Km 3,300 62018 Potenza Picena",
    "sg:city":"Potenza Picena",
    "sg:orig_category":"Ladies' Shoes",
    "sg:phone":"+39 0733 884004",
    "sg:postcode":"62018",
    "sg:province":"Macerata",
    "sg:website":"www.laregina.it",
    "wof:name":"Calzaturificio La Regina Srl",
    "wof:placetype":"venue"
},
  "geometry": {"coordinates":[13.456262,43.300747],"type":"Point"}
}