{
  "type": "Feature",
  "properties": {
    "iso:country":"IT",
    "sg:address":"88900 Crotone",
    "sg:city":"Crotone",
    "sg:orig_category":"Servizi Vari Di Interesse Pubblico",
    "sg:phone":"+39 0962 29212",
    "sg:postcode":"88900",
    "sg:province":"Crotone",
    "sg:website":"http://www.eamore.it",
    "wof:name":"Agenzia Matrimoniale E' Amore",
    "wof:placetype":"venue"
},
  "geometry": {"coordinates":[17.077566,39.100124],"type":"Point"}
}