{
  "type": "Feature",
  "properties": {
    "addr:full":"56038 Ponsacco Ponsacco Pisa 56038",
    "addr:postcode":"56038;56038",
    "iso:country":"IT",
    "sg:address":"56038 Ponsacco",
    "sg:city":"Ponsacco",
    "sg:orig_category":"Studi E Consulenze Amministrative, Commerciali E Aziendali. Consulenze Tecniche, Amministrative E Perizie. Professionisti - Studi E Servizi Ed Associazioni Di Interesse Aziendale",
    "sg:phone":"+39 0587 731616",
    "sg:postcode":"56038",
    "sg:province":"Pisa",
    "wof:name":"Dastoli Mario Commercialista",
    "wof:placetype":"venue"
},
  "geometry": {"coordinates":[10.636548,43.614178],"type":"Point"}
}