{
  "type": "Feature",
  "properties": {
    "addr:full":"40139 Bologna Bologna Bologna 40139",
    "addr:postcode":"40139;40139",
    "iso:country":"IT",
    "sg:address":"40139 Bologna",
    "sg:city":"Bologna",
    "sg:orig_category":"Macchine, Impianti Ed Attrezzature Industria Chimica. Vetro: Prodotti E Lavorazioni",
    "sg:phone":"+39 051 546084",
    "sg:postcode":"40139",
    "sg:province":"Bologna",
    "wof:name":"Zarri Raffaele",
    "wof:placetype":"venue"
},
  "geometry": {"coordinates":[11.389488,44.478462],"type":"Point"}
}