{
  "type": "Feature",
  "properties": {
    "iso:country":"IT",
    "sg:address":"03011 Alatri",
    "sg:city":"Alatri",
    "sg:orig_category":"Parchi Divertimento Ed Acquatici",
    "sg:phone":"+39 0775 409290",
    "sg:postcode":"03011",
    "sg:province":"Frosinone",
    "wof:name":"Park Club Sdf",
    "wof:placetype":"venue"
},
  "geometry": {"coordinates":[13.3554315567,41.6536903381],"type":"Point"}
}