{
  "type": "Feature",
  "properties": {
    "iso:country":"IT",
    "sg:address":"37026 Pescantina",
    "sg:city":"Pescantina",
    "sg:orig_category":"Legno E Semilavorati. Materiali Edili",
    "sg:phone":"+39 045 670 0620",
    "sg:postcode":"37026",
    "sg:province":"Verona",
    "wof:name":"Lovato Alessandro Legnami Srl",
    "wof:placetype":"venue"
},
  "geometry": {"coordinates":[10.91269,45.480362],"type":"Point"}
}