{
  "type": "Feature",
  "properties": {
    "addr:full":"35018 S.martino Di Lupari Padova 35018",
    "addr:postcode":"35018;35018",
    "iso:country":"IT",
    "sg:address":"35018 S.martino Di Lupari",
    "sg:orig_category":"Abbigliamento Sportivo - Produzione E Ingrosso",
    "sg:phone":"+39 049 595 3120",
    "sg:postcode":"35018",
    "sg:province":"Padova",
    "wof:name":"Agostini Borse Sportive Snc Di Agostini",
    "wof:placetype":"venue"
},
  "geometry": {"coordinates":[11.97932,45.345516],"type":"Point"}
}