{
  "type": "Feature",
  "properties": {
    "iso:country":"IT",
    "sg:address":"10126 Torino",
    "sg:city":"Torino",
    "sg:orig_category":"Minuterie Metalliche E Ferramenta",
    "sg:phone":"+39 011 663 0523",
    "sg:postcode":"10126",
    "sg:province":"Torino",
    "wof:name":"Bulviti Sas",
    "wof:placetype":"venue"
},
  "geometry": {"coordinates":[7.6681323051,45.038444519],"type":"Point"}
}