{
  "type": "Feature",
  "properties": {
    "iso:country":"IT",
    "sg:address":"14, Via Calendoni 23887 Olgiate Molgora",
    "sg:city":"Olgiate Molgora",
    "sg:classifiers":[
        {
            "category":"Manufacturing",
            "subcategory":"Rubber & Plastics",
            "type":"Manufacturing & Wholesale Goods"
        }
    ],
    "sg:phone":"+39 039 991 0448",
    "sg:postcode":"23887",
    "sg:province":"Lecco",
    "wof:name":"Sintetica (s.r.l.)",
    "wof:placetype":"venue"
},
  "geometry": {"coordinates":[9.3900709152,45.8529815674],"type":"Point"}
}