{
  "type": "Feature",
  "properties": {
    "iso:country":"IT",
    "sg:address":"38020 Pellizzano",
    "sg:city":"Pellizzano",
    "sg:orig_category":"Servizi E Lavori Per Edilizia E Lavori Pubblici. Acqua, Luce, Gas E Societa' Di Esercizio Pubblico",
    "sg:phone":"+39 0463 751495",
    "sg:postcode":"38020",
    "sg:province":"Trento",
    "wof:name":"Adonaj 2 R Snc Di Ruffini Roberto & C.",
    "wof:placetype":"venue"
},
  "geometry": {"coordinates":[10.760665,46.309719],"type":"Point"}
}