{
  "type": "Feature",
  "properties": {
    "addr:full":"10, V. Pastore 31038 Postioma Di Paese Paese Treviso 31038",
    "addr:housenumber":"10",
    "addr:postcode":"31038;31038",
    "addr:street":"V. Pastore;Paese Paese",
    "iso:country":"IT",
    "sg:address":"10, V. Pastore 31038 Postioma Di Paese",
    "sg:city":"Paese",
    "sg:classifiers":[
        {
            "category":"Professional",
            "subcategory":"Engineering",
            "type":"Services"
        }
    ],
    "sg:phone":"+39 0422 484212",
    "sg:postcode":"31038",
    "sg:province":"Treviso",
    "sg:tags":[
        "machine",
        "-",
        "mechanical"
    ],
    "sg:website":"http://www.rctcompact.it",
    "wof:name":"R.c.t. Di Scattolon & C. Snc",
    "wof:placetype":"venue"
},
  "geometry": {"coordinates":[12.15737,45.714535],"type":"Point"}
}