{
  "type": "Feature",
  "properties": {
    "iso:country":"IT",
    "sg:address":"25018 Montichiari",
    "sg:city":"Montichiari",
    "sg:orig_category":"Accessori Moda D'abbigliamento",
    "sg:phone":"+39 030 996 0782",
    "sg:postcode":"25018",
    "sg:province":"Brescia",
    "wof:name":"Zappettini Enos",
    "wof:placetype":"venue"
},
  "geometry": {"coordinates":[10.388635,45.40345],"type":"Point"}
}