{
  "type": "Feature",
  "properties": {
    "iso:country":"IT",
    "sg:address":"Via Piero Gobbetti 30 52100 Arezzo",
    "sg:city":"Arezzo",
    "sg:classifiers":[
        {
            "category":"Manufacturing",
            "subcategory":"Jewelry",
            "type":"Manufacturing & Wholesale Goods"
        }
    ],
    "sg:phone":"+39 0575 352243",
    "sg:postcode":"52100",
    "sg:province":"Arezzo",
    "sg:tags":[
        "miscellaneous",
        "jewellery",
        "machines"
    ],
    "sg:website":"www.energopresse.com",
    "wof:name":"Energo Snc",
    "wof:placetype":"venue"
},
  "geometry": {"coordinates":[11.863062,43.471203],"type":"Point"}
}