{
  "type": "Feature",
  "properties": {
    "iso:country":"IT",
    "sg:address":"Corso Svizzera 185 10149 Torino",
    "sg:city":"Torino",
    "sg:classifiers":[
        {
            "category":"Professional",
            "subcategory":"Printing & Photocopies",
            "type":"Services"
        }
    ],
    "sg:phone":"+39 011 777 3111",
    "sg:postcode":"10149",
    "sg:province":"Torino",
    "sg:tags":[
        "large-format"
    ],
    "wof:name":"Nuovo Editoriale Srl",
    "wof:placetype":"venue"
},
  "geometry": {"coordinates":[7.830617,45.487606],"type":"Point"}
}