{
  "type": "Feature",
  "properties": {
    "addr:full":"4, Via Civerchi 25036 Palazzolo Sull'oglio Brescia 25036",
    "addr:postcode":"25036;25036",
    "addr:street":"Via Civerchi",
    "iso:country":"IT",
    "sg:address":"4, Via Civerchi 25036 Palazzolo Sull'oglio",
    "sg:classifiers":[
        {
            "category":"Shopping",
            "type":"Retail Goods"
        }
    ],
    "sg:phone":"+39 030 743 5135",
    "sg:postcode":"25036",
    "sg:province":"Brescia",
    "sg:tags":[
        "finished",
        "-",
        "metallic"
    ],
    "wof:name":"Tecaut (s.r.l.)",
    "wof:placetype":"venue"
},
  "geometry": {"coordinates":[9.8738079071,45.6020622253],"type":"Point"}
}