{
  "type": "Feature",
  "properties": {
    "iso:country":"IT",
    "sg:address":"37051 Bovolone",
    "sg:city":"Bovolone",
    "sg:orig_category":"Macchine E Forniture Per Arredamento E Industria Del Legno. Utensili Meccanici E Materiali",
    "sg:phone":"+39 045 710 1141",
    "sg:postcode":"37051",
    "sg:province":"Verona",
    "wof:name":"Leitz Servizio Srl",
    "wof:placetype":"venue"
},
  "geometry": {"coordinates":[11.109788,45.257645],"type":"Point"}
}