{
  "type": "Feature",
  "properties": {
    "addr:full":"28028 Pettenasco Pettenasco Novara 28028",
    "addr:postcode":"28028;28028",
    "iso:country":"IT",
    "sg:address":"28028 Pettenasco",
    "sg:city":"Pettenasco",
    "sg:orig_category":"Arredo Bagno Ed Idrosanitari",
    "sg:phone":"+39 0323 89694",
    "sg:postcode":"28028",
    "sg:province":"Novara",
    "sg:website":"http://www.laris.it",
    "wof:name":"Laris Srl",
    "wof:placetype":"venue"
},
  "geometry": {"coordinates":[8.404904,45.818733],"type":"Point"}
}