{
  "type": "Feature",
  "properties": {
    "iso:country":"IT",
    "sg:address":"20090 Opera",
    "sg:city":"Opera",
    "sg:orig_category":"Studi E Consulenze Amministrative, Commerciali E Aziendali. Consulenze Tecniche, Amministrative E Perizie",
    "sg:phone":"+39 02 5760 0046",
    "sg:postcode":"20090",
    "sg:province":"Milano",
    "wof:name":"Rag. Raffaella Ciardi",
    "wof:placetype":"venue"
},
  "geometry": {"coordinates":[9.216736,45.376236],"type":"Point"}
}