{
  "type": "Feature",
  "properties": {
    "iso:country":"IT",
    "sg:address":"22030 Montorfano",
    "sg:city":"Montorfano",
    "sg:orig_category":"Materiali Semilavorati Metallici",
    "sg:phone":"+39 031 200453",
    "sg:postcode":"22030",
    "sg:province":"Como",
    "wof:name":"Molteni Ernesto",
    "wof:placetype":"venue"
},
  "geometry": {"coordinates":[9.157701,45.784561],"type":"Point"}
}