{
  "type": "Feature",
  "properties": {
    "iso:country":"IT",
    "sg:address":"20090 Pantigliate",
    "sg:city":"Pantigliate",
    "sg:orig_category":"Macchine, Impianti Ed Attrezzature Per Abbigliamento E Pelletterie",
    "sg:phone":"+39 02 9068 6884",
    "sg:postcode":"20090",
    "sg:province":"Milano",
    "wof:name":"Cornali Attilio S.r.l.",
    "wof:placetype":"venue"
},
  "geometry": {"coordinates":[9.06834,45.470146],"type":"Point"}
}