{
  "type": "Feature",
  "properties": {
    "iso:country":"IT",
    "sg:address":"53, Via Brescia 25014 Castenedolo",
    "sg:city":"Castenedolo",
    "sg:classifiers":[
        {
            "category":"Sports & Exercise",
            "subcategory":"Playing Field",
            "type":"Entertainment"
        }
    ],
    "sg:phone":"+39 030 273 2076",
    "sg:postcode":"25014",
    "sg:province":"Brescia",
    "sg:tags":[
        "game"
    ],
    "wof:name":"Baby Gaia Di Formentini Cinzia & C. (s.n.c.)",
    "wof:placetype":"venue"
},
  "geometry": {"coordinates":[10.283542,45.483551],"type":"Point"}
}