{
  "type": "Feature",
  "properties": {
    "iso:country":"IT",
    "sg:address":"74100 Taranto",
    "sg:city":"Taranto",
    "sg:orig_category":"Nautica. Ricambi E Componenti Dei Mezzi Di Trasporto",
    "sg:phone":"+39 099 470 7578",
    "sg:postcode":"74100",
    "sg:province":"Taranto",
    "wof:name":"Elledue Srl",
    "wof:placetype":"venue"
},
  "geometry": {"coordinates":[17.226618,40.480236],"type":"Point"}
}