{
  "type": "Feature",
  "properties": {
    "addr:full":"3, Via Del Lavoro 20040 Busnago Busnago Milano 20040",
    "addr:postcode":"20040;20040",
    "addr:street":"Via Del Lavoro",
    "iso:country":"IT",
    "sg:address":"3, Via Del Lavoro 20040 Busnago",
    "sg:city":"Busnago",
    "sg:classifiers":[
        {
            "category":"Utilities",
            "subcategory":"Electric",
            "type":"Services"
        }
    ],
    "sg:phone":"+39 039 695 6704",
    "sg:postcode":"20040",
    "sg:province":"Milano",
    "sg:tags":[
        "component",
        "electronic"
    ],
    "wof:name":"Isolan Plast Di Grifa V. Srl",
    "wof:placetype":"venue"
},
  "geometry": {"coordinates":[9.464347,45.610294],"type":"Point"}
}