{
  "type": "Feature",
  "properties": {
    "addr:full":"40057 Granarolo Dell'emilia Bologna 40057",
    "addr:postcode":"40057;40057",
    "iso:country":"IT",
    "sg:address":"40057 Granarolo Dell'emilia",
    "sg:orig_category":"Servizi E Lavori Per Agricoltura E Zootecnia",
    "sg:phone":"+39 051 767048",
    "sg:postcode":"40057",
    "sg:province":"Bologna",
    "wof:name":"Cesari Mario",
    "wof:placetype":"venue"
},
  "geometry": {"coordinates":[11.430633,44.540581],"type":"Point"}
}