{
  "type": "Feature",
  "properties": {
    "iso:country":"IT",
    "sg:address":"91100 Trapani",
    "sg:city":"Trapani",
    "sg:orig_category":"Metalli E Leghe",
    "sg:phone":"+39 0923 538717",
    "sg:postcode":"91100",
    "sg:province":"Trapani",
    "wof:name":"Cardinale Srl",
    "wof:placetype":"venue"
},
  "geometry": {"coordinates":[12.5351161957,38.0023422241],"type":"Point"}
}