{
  "type": "Feature",
  "properties": {
    "iso:country":"IT",
    "sg:address":"05018 Orvieto",
    "sg:city":"Orvieto",
    "sg:orig_category":"Materiali E Componenti Elettronici",
    "sg:phone":"+39 0763 3961",
    "sg:postcode":"05018",
    "sg:province":"Terni",
    "sg:website":"http://www.itelco.it",
    "wof:name":"Itelco Spa",
    "wof:placetype":"venue"
},
  "geometry": {"coordinates":[12.097055,42.726723],"type":"Point"}
}