{
  "type": "Feature",
  "properties": {
    "addr:full":"43044 Collecchio Collecchio Parma 43044",
    "addr:postcode":"43044;43044",
    "iso:country":"IT",
    "sg:address":"43044 Collecchio",
    "sg:city":"Collecchio",
    "sg:classifiers":[
        {
            "category":"Autos & Motor Vehicles",
            "subcategory":"Fuel & Gas Station",
            "type":"Retail Goods"
        }
    ],
    "sg:phone":"+39 0521 804325",
    "sg:postcode":"43044",
    "sg:province":"Parma",
    "sg:tags":[
        "activities",
        "industrial",
        "instrument",
        "equipment",
        "pumps",
        "machines"
    ],
    "sg:website":"http://www.caffinipumps.it",
    "wof:name":"Caffini Cipriano Srl",
    "wof:placetype":"venue"
},
  "geometry": {"coordinates":[10.2618551254,44.7752189636],"type":"Point"}
}