{
  "type": "Feature",
  "properties": {
    "iso:country":"IT",
    "sg:address":"Via Caduti Per La Patria 83 20050 Lesmo",
    "sg:city":"Lesmo",
    "sg:classifiers":[
        {
            "category":"Manufacturing",
            "subcategory":"Rubber & Plastics",
            "type":"Manufacturing & Wholesale Goods"
        }
    ],
    "sg:phone":"+39 039 606 4616",
    "sg:postcode":"20050",
    "sg:province":"Milano",
    "sg:tags":[
        "hose"
    ],
    "sg:website":"www.thorspa.it",
    "wof:name":"Tubi Thor Spa",
    "wof:placetype":"venue"
},
  "geometry": {"coordinates":[9.296324,45.640984],"type":"Point"}
}