{
  "type": "Feature",
  "properties": {
    "addr:full":"70029 Santeramo In Colle Santeramo in Colle Bari 70029",
    "addr:postcode":"70029;70029",
    "iso:country":"IT",
    "sg:address":"70029 Santeramo In Colle",
    "sg:city":"Santeramo in Colle",
    "sg:orig_category":"Pubblica Amministrazione",
    "sg:phone":"+39 080 302 6308",
    "sg:postcode":"70029",
    "sg:province":"Bari",
    "wof:name":"Carabinieri",
    "wof:placetype":"venue"
},
  "geometry": {"coordinates":[16.7618732452,40.8021011353],"type":"Point"}
}