{
  "type": "Feature",
  "properties": {
    "addr:full":"25126 Brescia Brescia Brescia 25126",
    "addr:postcode":"25126;25126",
    "iso:country":"IT",
    "sg:address":"25126 Brescia",
    "sg:city":"Brescia",
    "sg:orig_category":"Forniture Per Agricoltura E Zootecnia. Prodotti Chimici Secondari",
    "sg:phone":"+39 030 375 9785",
    "sg:postcode":"25126",
    "sg:province":"Brescia",
    "wof:name":"Regeo Srl",
    "wof:placetype":"venue"
},
  "geometry": {"coordinates":[10.1961212158,45.54088974],"type":"Point"}
}