{
  "type": "Feature",
  "properties": {
    "addr:full":"125, V. Provinciale 23819 Primaluna Primaluna Lecco 23819",
    "addr:housenumber":"125",
    "addr:postcode":"23819;23819",
    "addr:street":"V. Provinciale",
    "iso:country":"IT",
    "sg:address":"125, V. Provinciale 23819 Primaluna",
    "sg:city":"Primaluna",
    "sg:classifiers":[
        {
            "category":"Shopping",
            "type":"Retail Goods"
        }
    ],
    "sg:phone":"+39 0341 980397",
    "sg:postcode":"23819",
    "sg:province":"Lecco",
    "sg:tags":[
        "finished",
        "-",
        "metallic"
    ],
    "sg:website":"http://www.metalforch.it",
    "wof:name":"Metalforch Srl",
    "wof:placetype":"venue"
},
  "geometry": {"coordinates":[9.4518918991,45.9328613281],"type":"Point"}
}