{
  "type": "Feature",
  "properties": {
    "addr:full":"90133 Palermo Palermo Palermo 90133",
    "addr:postcode":"90133;90133",
    "iso:country":"IT",
    "sg:address":"90133 Palermo",
    "sg:city":"Palermo",
    "sg:orig_category":"Forniture Alberghi, Bar, Ristoranti E Comunita'",
    "sg:phone":"+39 347 832 3083",
    "sg:postcode":"90133",
    "sg:province":"Palermo",
    "wof:name":"Spitalieri Gaetano",
    "wof:placetype":"venue"
},
  "geometry": {"coordinates":[13.3659486771,38.1154823303],"type":"Point"}
}