{
  "type": "Feature",
  "properties": {
    "addr:full":"Via Bognetti 154 51100 Pistoia Pistoia Pistoia 51100",
    "addr:housenumber":"154",
    "addr:postcode":"51100;51100",
    "addr:street":"Via Bognetti",
    "iso:country":"IT",
    "sg:address":"Via Bognetti 154 51100 Pistoia",
    "sg:city":"Pistoia",
    "sg:orig_category":"Nightwear, Pyjamas, Nightgowns",
    "sg:phone":"+39 0573 533058",
    "sg:postcode":"51100",
    "sg:province":"Pistoia",
    "sg:website":"www.gruppointimoitaliano.com",
    "wof:name":"Gruppo Intimo Italiano Srl",
    "wof:placetype":"venue"
},
  "geometry": {"coordinates":[10.948342,43.929504],"type":"Point"}
}