{
  "type": "Feature",
  "properties": {
    "iso:country":"IT",
    "sg:address":"83100 Avellino",
    "sg:city":"Avellino",
    "sg:orig_category":"Forniture Per Agricoltura E Zootecnia. Animali Domestici",
    "sg:phone":"+39 0825 32805",
    "sg:postcode":"83100",
    "sg:province":"Avellino",
    "wof:name":"Zoomania Di Siciliano Rita",
    "wof:placetype":"venue"
},
  "geometry": {"coordinates":[14.7989759445,40.9202690125],"type":"Point"}
}