{
  "type": "Feature",
  "properties": {
    "iso:country":"IT",
    "sg:address":"23801 Calolziocorte",
    "sg:city":"Calolziocorte",
    "sg:orig_category":"Macchine Utensili E Impianti. Utensili Meccanici E Materiali",
    "sg:phone":"+39 0341 633237",
    "sg:postcode":"23801",
    "sg:province":"Lecco",
    "wof:name":"Sala Punzoni (s.r.l.)",
    "wof:placetype":"venue"
},
  "geometry": {"coordinates":[9.420949,45.802822],"type":"Point"}
}