{
  "type": "Feature",
  "properties": {
    "iso:country":"IT",
    "sg:address":"90147 Palermo",
    "sg:city":"Palermo",
    "sg:orig_category":"Forniture Per Edilizia E Lavori Pubblici",
    "sg:phone":"+39 091 688 4155",
    "sg:postcode":"90147",
    "sg:province":"Palermo",
    "wof:name":"Lo Castro Spa",
    "wof:placetype":"venue"
},
  "geometry": {"coordinates":[13.3188152313,38.1564064026],"type":"Point"}
}