{
  "type": "Feature",
  "properties": {
    "addr:full":"Via Provinciale 72 44035 Formignana Formignana Ferrara 44035",
    "addr:housenumber":"72",
    "addr:postcode":"44035;44035",
    "addr:street":"Via Provinciale",
    "iso:country":"IT",
    "sg:address":"Via Provinciale 72 44035 Formignana",
    "sg:city":"Formignana",
    "sg:classifiers":[
        {
            "category":"Manufacturing",
            "subcategory":"Tools & Machinery",
            "type":"Manufacturing & Wholesale Goods"
        }
    ],
    "sg:phone":"+39 0533 59186",
    "sg:postcode":"44035",
    "sg:province":"Ferrara",
    "sg:tags":[
        "industry",
        "pneumatic",
        "metallurgical",
        "iron"
    ],
    "sg:website":"www.sichim.it",
    "wof:name":"Sichim Alfa Srl",
    "wof:placetype":"venue"
},
  "geometry": {"coordinates":[11.8530607224,44.8389854431],"type":"Point"}
}