{
  "type": "Feature",
  "properties": {
    "iso:country":"IT",
    "sg:address":"Viale Aldo Borletti 61/63; Corbetta; Milano; 20011",
    "sg:city":"Corbetta",
    "sg:classifiers":[
        {
            "category":"Industrial Area",
            "type":"Public Place"
        }
    ],
    "sg:phone":"+39 02 9722 7111",
    "sg:postcode":"20011",
    "sg:province":"Milano",
    "sg:tags":[
        "large",
        "private"
    ],
    "sg:website":"www.marelli.it",
    "wof:name":"Magneti Marelli S.p.a.",
    "wof:placetype":"venue"
},
  "geometry": {"coordinates":[8.9339237213,45.4641494751],"type":"Point"}
}