{
  "type": "Feature",
  "properties": {
    "addr:full":"7/b, Via Fratelli Pagani 24060 Castelli Calepio Castelli Calepio Bergamo 24060",
    "addr:housenumber":"7 / b",
    "addr:postcode":"24060;24060",
    "addr:street":"Via Fratelli Pagani",
    "iso:country":"IT",
    "sg:address":"7/b, Via Fratelli Pagani 24060 Castelli Calepio",
    "sg:city":"Castelli Calepio",
    "sg:classifiers":[
        {
            "category":"Shopping",
            "subcategory":"Clothing, Apparel, & Fashions",
            "type":"Retail Goods"
        }
    ],
    "sg:phone":"+39 030 743 5501",
    "sg:postcode":"24060",
    "sg:province":"Bergamo",
    "sg:tags":[
        "clothing",
        "accessory"
    ],
    "wof:name":"A.b.t. Trading Di Belotti Mauro & C. Snc",
    "wof:placetype":"venue"
},
  "geometry": {"coordinates":[9.669952,45.694904],"type":"Point"}
}