{
  "type": "Feature",
  "properties": {
    "iso:country":"IT",
    "sg:address":"Via E. Montale 35 25018 Montichiari",
    "sg:city":"Montichiari",
    "sg:classifiers":[
        {
            "category":"Manufacturing",
            "subcategory":"Tools & Machinery",
            "type":"Manufacturing & Wholesale Goods"
        }
    ],
    "sg:phone":"+39 030 996 0215",
    "sg:postcode":"25018",
    "sg:province":"Brescia",
    "sg:tags":[
        "machine",
        "agriculture",
        "special"
    ],
    "sg:website":"www.moreni.it",
    "wof:name":"Moreni S.n.c. Di Gianantonio & Mauro",
    "wof:placetype":"venue"
},
  "geometry": {"coordinates":[10.222958,45.539829],"type":"Point"}
}