{
  "type": "Feature",
  "properties": {
    "iso:country":"IT",
    "sg:address":"Piazza S. Marco 40/42; Prato; 50047",
    "sg:classifiers":[
        {
            "category":"Banks & Credit Unions",
            "subcategory":"Bank",
            "type":"Services"
        }
    ],
    "sg:phone":"+39 0574 607679",
    "wof:name":"Banca Fideuram Spa",
    "wof:placetype":"venue"
},
  "geometry": {"coordinates":[11.101511,43.877678],"type":"Point"}
}