{
  "type": "Feature",
  "properties": {
    "iso:country":"IT",
    "sg:address":"46042 Castel Goffredo",
    "sg:city":"Castel Goffredo",
    "sg:orig_category":"Forniture Per Abbigliamento E Pelletterie",
    "sg:phone":"+39 0376 770247",
    "sg:postcode":"46042",
    "sg:province":"Mantova",
    "wof:name":"Redini Luigi (s.n.c.)",
    "wof:placetype":"venue"
},
  "geometry": {"coordinates":[10.4796571732,45.298740387],"type":"Point"}
}