{
  "type": "Feature",
  "properties": {
    "addr:full":"5750, Via Per S. Giorgio 74100 Taranto Taranto Taranto 74100",
    "addr:housenumber":"5750",
    "addr:postcode":"74100;74100",
    "addr:street":"Via Per S. Giorgio",
    "iso:country":"IT",
    "sg:address":"5750, Via Per S. Giorgio 74100 Taranto",
    "sg:city":"Taranto",
    "sg:classifiers":[
        {
            "category":"Banks & Credit Unions",
            "subcategory":"Investment Brokerage",
            "type":"Services"
        }
    ],
    "sg:phone":"+39 099 779 4747",
    "sg:postcode":"74100",
    "sg:province":"Taranto",
    "sg:tags":[
        "-",
        "transport",
        "related"
    ],
    "wof:name":"Ready Service S.n.c.",
    "wof:placetype":"venue"
},
  "geometry": {"coordinates":[17.240009,40.469238],"type":"Point"}
}