{
  "type": "Feature",
  "properties": {
    "addr:full":"Via Locatelli Antonio 24c 24121 Bergamo Bergamo Bergamo 24121",
    "addr:housenumber":"24c",
    "addr:postcode":"24121;24121",
    "addr:street":"Via Locatelli Antonio",
    "iso:country":"IT",
    "sg:address":"Via Locatelli Antonio 24c 24121 Bergamo",
    "sg:city":"Bergamo",
    "sg:classifiers":[
        {
            "category":"Shopping",
            "subcategory":"Clothing, Apparel, & Fashions",
            "type":"Retail Goods"
        }
    ],
    "sg:phone":"+39 035 230242",
    "sg:postcode":"24121",
    "sg:province":"Bergamo",
    "sg:tags":[
        "image",
        "clothing",
        "basic"
    ],
    "wof:name":"T. Leader Spa",
    "wof:placetype":"venue"
},
  "geometry": {"coordinates":[9.669227,45.698311],"type":"Point"}
}