{
  "type": "Feature",
  "properties": {
    "addr:full":"20083 San Vito San Vito Milano 20083",
    "addr:housenumber":"20083",
    "addr:postcode":"20083",
    "addr:street":"San",
    "iso:country":"IT",
    "sg:address":"20083 San Vito",
    "sg:city":"San Vito",
    "sg:orig_category":"Materiali Edili",
    "sg:phone":"+39 02 9084 4752",
    "sg:postcode":"20083",
    "sg:province":"Milano",
    "wof:name":"Bellomia Massimo",
    "wof:placetype":"venue"
},
  "geometry": {"coordinates":[9.015427,45.4175],"type":"Point"}
}