{
  "type": "Feature",
  "properties": {
    "iso:country":"IT",
    "sg:address":"46042 Castel Goffredo",
    "sg:city":"Castel Goffredo",
    "sg:orig_category":"Macchine, Impianti Ed Attrezzature Per Abbigliamento E Pelletterie",
    "sg:phone":"+39 0376 780183",
    "sg:postcode":"46042",
    "sg:province":"Mantova",
    "wof:name":"Boggiani Renato",
    "wof:placetype":"venue"
},
  "geometry": {"coordinates":[10.477046,45.282532],"type":"Point"}
}