{
  "type": "Feature",
  "properties": {
    "iso:country":"IT",
    "sg:address":"80146 Napoli",
    "sg:city":"Napoli",
    "sg:orig_category":"Legno Compensato E Profilati - Produzione E Ingrosso",
    "sg:phone":"+39 081 752 3726",
    "sg:postcode":"80146",
    "sg:province":"Napoli",
    "sg:website":"http://www.casilloporte.com",
    "wof:name":"Francesco Casillo Srl",
    "wof:placetype":"venue"
},
  "geometry": {"coordinates":[14.327458,40.856915],"type":"Point"}
}