{
  "type": "Feature",
  "properties": {
    "iso:country":"IT",
    "sg:address":"22072 Cermenate",
    "sg:city":"Cermenate",
    "sg:orig_category":"Articoli Per Imballaggio E Confezionamento",
    "sg:phone":"+39 031 771086",
    "sg:postcode":"22072",
    "sg:province":"Como",
    "wof:name":"Woba Plast",
    "wof:placetype":"venue"
},
  "geometry": {"coordinates":[9.124588,45.735931],"type":"Point"}
}