{
  "type": "Feature",
  "properties": {
    "iso:country":"IT",
    "sg:address":"Via Idice 219; Monterenzio; 40050",
    "sg:city":"Monterenzio",
    "sg:classifiers":[
        {
            "category":"Banks & Credit Unions",
            "subcategory":"Bank",
            "type":"Services"
        }
    ],
    "sg:phone":"+39 051 922 9915",
    "sg:postcode":"40050",
    "sg:province":"Bologna",
    "wof:name":"Rolo Banca 1473 Spa",
    "wof:placetype":"venue"
},
  "geometry": {"coordinates":[11.404718,44.325855],"type":"Point"}
}