{
  "type": "Feature",
  "properties": {
    "iso:country":"IT",
    "sg:address":"46042 Castel Goffredo",
    "sg:city":"Castel Goffredo",
    "sg:orig_category":"Frigotecnica, Apparecchiature E Servizi. Servizi Di Magazzinaggio E Movimentazione",
    "sg:phone":"+39 0376 780305",
    "sg:postcode":"46042",
    "sg:province":"Mantova",
    "wof:name":"Morando (s.p.a.)",
    "wof:placetype":"venue"
},
  "geometry": {"coordinates":[10.4796571732,45.298740387],"type":"Point"}
}