{
  "type": "Feature",
  "properties": {
    "iso:country":"IT",
    "sg:address":"28, Piazza Bernina 41049 Sassuolo",
    "sg:city":"Sassuolo",
    "sg:classifiers":[
        {
            "category":"Shopping",
            "subcategory":"Crafts & Fabrics",
            "type":"Retail Goods"
        }
    ],
    "sg:phone":"+39 0536 802156",
    "sg:postcode":"41049",
    "sg:province":"Modena",
    "sg:tags":[
        "ceramic"
    ],
    "wof:name":"Smec (s.n.c.)",
    "wof:placetype":"venue"
},
  "geometry": {"coordinates":[10.859138,44.588428],"type":"Point"}
}