{
  "type": "Feature",
  "properties": {
    "iso:country":"IT",
    "sg:address":"39058 Sarentino",
    "sg:city":"Sarentino",
    "sg:orig_category":"Servizi E Lavori Per Abbigliamento E Pelletterie. Arte Ed Artigianato Artistico. Shopping",
    "sg:phone":"+39 0471 623258",
    "sg:postcode":"39058",
    "sg:province":"Bolzano/Bozen",
    "wof:name":"Thaler Johann",
    "wof:placetype":"venue"
},
  "geometry": {"coordinates":[11.352437,46.639557],"type":"Point"}
}