{
  "type": "Feature",
  "properties": {
    "addr:full":"41018 San Cesario Sul Panaro San Cesario sul Panaro Modena 41018",
    "addr:housenumber":"41018",
    "addr:postcode":"cesario;panaro;41018",
    "addr:street":"San",
    "iso:country":"IT",
    "sg:address":"41018 San Cesario Sul Panaro",
    "sg:city":"San Cesario sul Panaro",
    "sg:orig_category":"Forniture Per Attivita' Industriali",
    "sg:phone":"+39 059 933154",
    "sg:postcode":"41018",
    "sg:province":"Modena",
    "wof:name":"Bieffe Di Fasanella Barbara",
    "wof:placetype":"venue"
},
  "geometry": {"coordinates":[11.014840126,44.5887260437],"type":"Point"}
}