{
  "type": "Feature",
  "properties": {
    "addr:full":"03023 Ceccano Ceccano Frosinone 03023",
    "addr:postcode":"03023;03023",
    "iso:country":"IT",
    "sg:address":"03023 Ceccano",
    "sg:city":"Ceccano",
    "sg:orig_category":"Serramenti Ed Infissi",
    "sg:phone":"+39 0775 291059",
    "sg:postcode":"03023",
    "sg:province":"Frosinone",
    "wof:name":"Bucci Nicolina",
    "wof:placetype":"venue"
},
  "geometry": {"coordinates":[13.304436,41.61343],"type":"Point"}
}