{
  "type": "Feature",
  "properties": {
    "iso:country":"IT",
    "sg:address":"80132 Napoli",
    "sg:city":"Napoli",
    "sg:orig_category":"Nautica. Automobili E Mezzi Di Trasporto",
    "sg:phone":"+39 081 245 5324",
    "sg:postcode":"80132",
    "sg:province":"Napoli",
    "sg:website":"http://www.southseas.it",
    "wof:name":"International South Seas Yacht Broker & Charter Srl",
    "wof:placetype":"venue"
},
  "geometry": {"coordinates":[14.24953,40.830444],"type":"Point"}
}