{
  "type": "Feature",
  "properties": {
    "iso:country":"IT",
    "sg:address":"20049 Concorezzo",
    "sg:city":"Concorezzo",
    "sg:orig_category":"Porte Industriali Flessibili",
    "sg:phone":"+39 039 620 3160",
    "sg:postcode":"20049",
    "sg:province":"Milano",
    "wof:name":"Cordisco Snc",
    "wof:placetype":"venue"
},
  "geometry": {"coordinates":[9.3368177414,45.5933952332],"type":"Point"}
}