{
  "type": "Feature",
  "properties": {
    "addr:full":"11, Via Gramsci A. 42013 Casalgrande Reggio Nell'Emilia 42013",
    "addr:postcode":"42013;42013",
    "addr:street":"Via Gramsci A.",
    "iso:country":"IT",
    "sg:address":"11, Via Gramsci A. 42013 Casalgrande",
    "sg:classifiers":[
        {
            "category":"Shopping",
            "subcategory":"Clothing, Apparel, & Fashions",
            "type":"Retail Goods"
        }
    ],
    "sg:phone":"+39 0522 840432",
    "sg:postcode":"42013",
    "sg:province":"Reggio Nell'Emilia",
    "sg:tags":[
        "clothes"
    ],
    "wof:name":"The Best Di Rossi Dino & C. S.n.c.",
    "wof:placetype":"venue"
},
  "geometry": {"coordinates":[10.691072,44.596607],"type":"Point"}
}