{
  "type": "Feature",
  "properties": {
    "iso:country":"IT",
    "sg:address":"85021 Avigliano",
    "sg:city":"Avigliano",
    "sg:orig_category":"Abbigliamento Esterno, Maglierie E Pelliccerie. Shopping",
    "sg:phone":"+39 0971 81820",
    "sg:postcode":"85021",
    "sg:province":"Potenza",
    "wof:name":"Moon Flower Di Tolve & Labella Snc",
    "wof:placetype":"venue"
},
  "geometry": {"coordinates":[15.726397,40.73159],"type":"Point"}
}