{
  "type": "Feature",
  "properties": {
    "addr:full":"Via Villanova; Castenaso; 40050 Bologna 40050",
    "addr:postcode":"40050;40050",
    "addr:street":"Via Villanova",
    "iso:country":"IT",
    "sg:address":"Via Villanova; Castenaso; 40050",
    "sg:classifiers":[
        {
            "category":"Banks & Credit Unions",
            "subcategory":"Bank",
            "type":"Services"
        }
    ],
    "sg:phone":"+39 051 781188",
    "sg:postcode":"40050",
    "sg:province":"Bologna",
    "wof:name":"Banco Ambrosiano Veneto Spa",
    "wof:placetype":"venue"
},
  "geometry": {"coordinates":[11.424816,44.490654],"type":"Point"}
}