{
  "type": "Feature",
  "properties": {
    "iso:country":"IT",
    "sg:address":"11, Corso Asti 10078 Venaria",
    "sg:classifiers":[
        {
            "category":"Shopping",
            "type":"Retail Goods"
        }
    ],
    "sg:phone":"+39 011 424 2035",
    "sg:postcode":"10078",
    "sg:province":"Torino",
    "sg:tags":[
        "finished",
        "-",
        "metallic"
    ],
    "wof:name":"A.c.s.a. S.r.l.",
    "wof:placetype":"venue"
},
  "geometry": {"coordinates":[7.6287755966,45.1141815186],"type":"Point"}
}