{
  "type": "Feature",
  "properties": {
    "addr:full":"Via F.lli Rosselli 12 20090 Settala Settala Milano 20090",
    "addr:housenumber":"12",
    "addr:postcode":"20090;20090",
    "addr:street":"Via F.Lli Rosselli",
    "iso:country":"IT",
    "sg:address":"Via F.lli Rosselli 12 20090 Settala",
    "sg:city":"Settala",
    "sg:classifiers":[
        {
            "category":"Manufacturing",
            "subcategory":"Metals",
            "type":"Manufacturing & Wholesale Goods"
        }
    ],
    "sg:phone":"+39 02 9577 0008",
    "sg:postcode":"20090",
    "sg:province":"Milano",
    "sg:tags":[
        "box",
        "machine",
        "sheet"
    ],
    "wof:name":"Klinghammer Italia Costruzioni Srl",
    "wof:placetype":"venue"
},
  "geometry": {"coordinates":[9.188141,45.463688],"type":"Point"}
}