{
  "type": "Feature",
  "properties": {
    "iso:country":"IT",
    "sg:address":"16154 Genova",
    "sg:city":"Genova",
    "sg:orig_category":"Trasporti E Spedizioni Merci",
    "sg:phone":"+39 010 651 5357",
    "sg:postcode":"16154",
    "sg:province":"Genova",
    "wof:name":"Containers Fidenza Soc.coop.r.l.",
    "wof:placetype":"venue"
},
  "geometry": {"coordinates":[8.853261,44.415356],"type":"Point"}
}