{
  "type": "Feature",
  "properties": {
    "iso:country":"IT",
    "sg:address":"17, Viale Pesenti 38060 Villa Lagarina",
    "sg:city":"Villa Lagarina",
    "sg:classifiers":[
        {
            "category":"Banks & Credit Unions",
            "subcategory":"Investment Brokerage",
            "type":"Services"
        }
    ],
    "sg:phone":"+39 0464 411500",
    "sg:postcode":"38060",
    "sg:province":"Trento",
    "sg:tags":[
        "-",
        "transport",
        "related"
    ],
    "wof:name":"Frisinghelli (s.r.l.)",
    "wof:placetype":"venue"
},
  "geometry": {"coordinates":[11.035868,45.919899],"type":"Point"}
}