{
  "type": "Feature",
  "properties": {
    "addr:full":"42020 San Polo D'enza Reggio Nell'Emilia 42020",
    "addr:housenumber":"42020",
    "addr:postcode":"42020",
    "addr:street":"San",
    "iso:country":"IT",
    "sg:address":"42020 San Polo D'enza",
    "sg:orig_category":"Materiali Edili",
    "sg:phone":"+39 0522 241087",
    "sg:postcode":"42020",
    "sg:province":"Reggio Nell'Emilia",
    "wof:name":"Fortlan S.p.a.",
    "wof:placetype":"venue"
},
  "geometry": {"coordinates":[10.649392,44.686756],"type":"Point"}
}