{
  "type": "Feature",
  "properties": {
    "iso:country":"IT",
    "sg:address":"56, Viale Porta Adige 45100 Rovigo",
    "sg:city":"Rovigo",
    "sg:classifiers":[
        {
            "category":"Shopping",
            "type":"Retail Goods"
        }
    ],
    "sg:phone":"+39 0425 485458",
    "sg:postcode":"45100",
    "sg:province":"Rovigo",
    "sg:tags":[
        "finished",
        "-",
        "metallic"
    ],
    "wof:name":"Idros.art Srl",
    "wof:placetype":"venue"
},
  "geometry": {"coordinates":[11.7857313156,45.0963478088],"type":"Point"}
}