{
  "type": "Feature",
  "properties": {
    "addr:full":"Corso S Trentin 54; S. Dona Di Piave; 30027 Venezia 30027",
    "addr:housenumber":"54",
    "addr:postcode":"30027;30027",
    "addr:street":"Corso S Trentin;S. Dona Di Piave",
    "iso:country":"IT",
    "sg:address":"Corso S Trentin 54; S. Dona Di Piave; 30027",
    "sg:classifiers":[
        {
            "category":"Banks & Credit Unions",
            "subcategory":"Bank",
            "type":"Services"
        }
    ],
    "sg:phone":"+39 0421 560200",
    "sg:postcode":"30027",
    "sg:province":"Venezia",
    "wof:name":"Rolo Banca 1473 Spa",
    "wof:placetype":"venue"
},
  "geometry": {"coordinates":[12.564393,45.628567],"type":"Point"}
}