{
  "type": "Feature",
  "properties": {
    "addr:full":"20090 Trezzano Sul Naviglio Trezzano sul Naviglio Milano 20090",
    "addr:postcode":"20090;20090",
    "iso:country":"IT",
    "sg:address":"20090 Trezzano Sul Naviglio",
    "sg:city":"Trezzano sul Naviglio",
    "sg:orig_category":"Forniture Alle Strutture Ricettive. Macchine E Impianti Per Attivita' Commerciali Ed Artigianali",
    "sg:phone":"+39 02 4840 3122",
    "sg:postcode":"20090",
    "sg:province":"Milano",
    "wof:name":"Vibropompe City (s.r.l.)",
    "wof:placetype":"venue"
},
  "geometry": {"coordinates":[9.0697717667,45.4264068604],"type":"Point"}
}