{
  "type": "Feature",
  "properties": {
    "addr:full":"06055 Marsciano Marsciano Perugia 06055",
    "addr:postcode":"06055;06055",
    "iso:country":"IT",
    "sg:address":"06055 Marsciano",
    "sg:city":"Marsciano",
    "sg:classifiers":[
        {
            "category":"Building & Trades",
            "subcategory":"Construction",
            "type":"Services"
        }
    ],
    "sg:phone":"+39 075 874091",
    "sg:postcode":"06055",
    "sg:province":"Perugia",
    "sg:tags":[
        "industry",
        "work",
        "plastic"
    ],
    "wof:name":"Shandrani Italia Srl",
    "wof:placetype":"venue"
},
  "geometry": {"coordinates":[12.3234815598,42.9517211914],"type":"Point"}
}