{
  "type": "Feature",
  "properties": {
    "addr:full":"60122 Ancona Ancona Ancona 60122",
    "addr:postcode":"60122;60122",
    "iso:country":"IT",
    "sg:address":"60122 Ancona",
    "sg:city":"Ancona",
    "sg:orig_category":"Agenzie Marittime",
    "sg:phone":"+39 071 204915",
    "sg:postcode":"60122",
    "sg:province":"Ancona",
    "wof:name":"Maritime Agency Srl",
    "wof:placetype":"venue"
},
  "geometry": {"coordinates":[13.513328,43.613216],"type":"Point"}
}