{
  "type": "Feature",
  "properties": {
    "iso:country":"IT",
    "sg:address":"59100 Prato",
    "sg:city":"Prato",
    "sg:orig_category":"Elettrotecnica Industriale, Prodotti E Apparecchiature",
    "sg:phone":"+39 0574 662348",
    "sg:postcode":"59100",
    "sg:province":"Prato",
    "sg:website":"http://www.ventilatori.toscana.it",
    "wof:name":"Motovent Srl",
    "wof:placetype":"venue"
},
  "geometry": {"coordinates":[11.07289,43.893753],"type":"Point"}
}