{
  "type": "Feature",
  "properties": {
    "addr:full":"98100 Messina ME",
    "addr:postcode":"98100",
    "iso:country":"IT",
    "sg:address":"98100 Messina",
    "sg:orig_category":"Cine-foto-ottica",
    "sg:phone":"+39 090 675493",
    "sg:province":"ME",
    "wof:name":"Mondello Ottica Di Lorenzo E Figli Snc",
    "wof:placetype":"venue"
},
  "geometry": {"coordinates":[15.494688,38.197247],"type":"Point"}
}