{
  "type": "Feature",
  "properties": {
    "addr:full":"84087 Sarno Sarno Salerno 84087",
    "addr:postcode":"84087;84087",
    "iso:country":"IT",
    "sg:address":"84087 Sarno",
    "sg:city":"Sarno",
    "sg:orig_category":"Forniture Per Abbigliamento E Pelletterie",
    "sg:phone":"+39 081 513 6323",
    "sg:postcode":"84087",
    "sg:province":"Salerno",
    "wof:name":"Carillo E Squitieri Snc Di Carillo Patrizia",
    "wof:placetype":"venue"
},
  "geometry": {"coordinates":[14.6238050461,40.8152351379],"type":"Point"}
}