{
  "type": "Feature",
  "properties": {
    "addr:full":"43010 Pilastro Pilastro Parma 43010",
    "addr:postcode":"43010;43010",
    "iso:country":"IT",
    "sg:address":"43010 Pilastro",
    "sg:city":"Pilastro",
    "sg:orig_category":"Forniture Per Agricoltura E Zootecnia. Animali Domestici",
    "sg:phone":"+39 0521 630430",
    "sg:postcode":"43010",
    "sg:province":"Parma",
    "wof:name":"Agrifarma S.r.l.",
    "wof:placetype":"venue"
},
  "geometry": {"coordinates":[10.2881813049,44.6819763184],"type":"Point"}
}