{
  "type": "Feature",
  "properties": {
    "addr:full":"Ctr Risicone S. N. 95049 Vizzini Vizzini Catania 95049",
    "addr:postcode":"95049;95049",
    "iso:country":"IT",
    "sg:address":"Ctr Risicone S. N. 95049 Vizzini",
    "sg:city":"Vizzini",
    "sg:classifiers":[
        {
            "category":"Autos & Motor Vehicles",
            "subcategory":"Motorcycle Sales",
            "type":"Retail Goods"
        }
    ],
    "sg:phone":"+39 095 940384",
    "sg:postcode":"95049",
    "sg:province":"Catania",
    "sg:tags":[
        "light",
        "bicycle",
        "motorized",
        "motorcycles"
    ],
    "sg:website":"www.diblasi.it",
    "wof:name":"Di Blasi Industriale S.r.l.",
    "wof:placetype":"venue"
},
  "geometry": {"coordinates":[14.750078,37.16132],"type":"Point"}
}