{
  "type": "Feature",
  "properties": {
    "iso:country":"IT",
    "sg:address":"21, Via Del Prato 50055 Lastra A Signa",
    "sg:city":"Lastra a Signa",
    "sg:classifiers":[
        {
            "category":"Shopping",
            "subcategory":"Clothing, Apparel, & Fashions",
            "type":"Retail Goods"
        }
    ],
    "sg:phone":"+39 055 872 0001",
    "sg:postcode":"50055",
    "sg:province":"Firenze",
    "sg:tags":[
        "clothes"
    ],
    "wof:name":"Maglificio Bomar",
    "wof:placetype":"venue"
},
  "geometry": {"coordinates":[11.104953,43.77029],"type":"Point"}
}