{
  "type": "Feature",
  "properties": {
    "iso:country":"IT",
    "sg:address":"82, Corso Trieste 12012 Boves",
    "sg:city":"Boves",
    "sg:classifiers":[
        {
            "category":"Autos & Motor Vehicles",
            "subcategory":"Automobile Sales",
            "type":"Retail Goods"
        }
    ],
    "sg:phone":"+39 0171 380367",
    "sg:postcode":"12012",
    "sg:province":"Cuneo",
    "sg:tags":[
        "motor-cars"
    ],
    "wof:name":"Marro",
    "wof:placetype":"venue"
},
  "geometry": {"coordinates":[7.5482554436,44.3318023682],"type":"Point"}
}