{
  "type": "Feature",
  "properties": {
    "iso:country":"IT",
    "sg:address":"46047 Porto Mantovano",
    "sg:city":"Porto Mantovano",
    "sg:orig_category":"Servizi E Lavori Per Agricoltura E Zootecnia. Animali Domestici",
    "sg:phone":"+39 0376 396785",
    "sg:postcode":"46047",
    "sg:province":"Mantova",
    "wof:name":"Bluzoo Di Moreschi Paola & C. Snc",
    "wof:placetype":"venue"
},
  "geometry": {"coordinates":[10.793889,45.200062],"type":"Point"}
}