{
  "type": "Feature",
  "properties": {
    "addr:full":"25018 Montichiari Montichiari Brescia 25018",
    "addr:postcode":"25018;25018",
    "iso:country":"IT",
    "sg:address":"25018 Montichiari",
    "sg:city":"Montichiari",
    "sg:orig_category":"Impiantistica E Prodotti Tecnologici Per Edilizia",
    "sg:phone":"+39 030 965 1759",
    "sg:postcode":"25018",
    "sg:province":"Brescia",
    "wof:name":"Idealpark S.r.l.",
    "wof:placetype":"venue"
},
  "geometry": {"coordinates":[10.360525,45.426769],"type":"Point"}
}