{
  "type": "Feature",
  "properties": {
    "iso:country":"IT",
    "sg:address":"30020 Meolo",
    "sg:city":"Meolo",
    "sg:orig_category":"Abbigliamento - Vendita Al Dettaglio",
    "sg:phone":"+39 0421 618652",
    "sg:postcode":"30020",
    "sg:province":"Venezia",
    "wof:name":"Fregonese Giuseppe - Pellicceria Bieffe",
    "wof:placetype":"venue"
},
  "geometry": {"coordinates":[12.456178,45.621696],"type":"Point"}
}