{
  "type": "Feature",
  "properties": {
    "addr:full":"20019 Settimo Milanese Settimo Milanese Milano 20019",
    "addr:postcode":"20019;20019",
    "iso:country":"IT",
    "sg:address":"20019 Settimo Milanese",
    "sg:city":"Settimo Milanese",
    "sg:classifiers":[
        {
            "category":"Banks & Credit Unions",
            "subcategory":"Financial Services",
            "type":"Services"
        }
    ],
    "sg:phone":"+39 02 3350 2473",
    "sg:postcode":"20019",
    "sg:province":"Milano",
    "sg:tags":[
        "articles",
        "product",
        "plastics",
        "industry",
        "work",
        "plastic"
    ],
    "wof:name":"Pelosi Sas Di Veronelli",
    "wof:placetype":"venue"
},
  "geometry": {"coordinates":[9.0688648224,45.4653663635],"type":"Point"}
}