{
  "type": "Feature",
  "properties": {
    "iso:country":"IT",
    "sg:address":"50041 Calenzano",
    "sg:city":"Calenzano",
    "sg:orig_category":"Lubrificanti - Produzione E Commercio",
    "sg:phone":"+39 055 882 5016",
    "sg:postcode":"50041",
    "sg:province":"Firenze",
    "wof:name":"Lubrificanti Firenze Srl",
    "wof:placetype":"venue"
},
  "geometry": {"coordinates":[11.16291,43.850151],"type":"Point"}
}