{
  "type": "Feature",
  "properties": {
    "addr:full":"Via Volta 13 22060 Arosio Arosio Como 22060",
    "addr:housenumber":"13",
    "addr:postcode":"22060;22060",
    "addr:street":"Via Volta",
    "iso:country":"IT",
    "sg:address":"Via Volta 13 22060 Arosio",
    "sg:city":"Arosio",
    "sg:orig_category":"Furniture, General",
    "sg:phone":"+39 031 761333",
    "sg:postcode":"22060",
    "sg:province":"Como",
    "sg:website":"www.imel.it",
    "wof:name":"Imel Spa",
    "wof:placetype":"venue"
},
  "geometry": {"coordinates":[9.0854558945,45.8119659424],"type":"Point"}
}