{
  "type": "Feature",
  "properties": {
    "iso:country":"IT",
    "sg:address":"16154 Genova",
    "sg:city":"Genova",
    "sg:orig_category":"Non-classified Establishments",
    "sg:phone":"+39 010 653 1826",
    "sg:postcode":"16154",
    "sg:province":"Genova",
    "wof:name":"Caroleo Sas",
    "wof:placetype":"venue"
},
  "geometry": {"coordinates":[8.848056,44.422501],"type":"Point"}
}