{
  "type": "Feature",
  "properties": {
    "iso:country":"IT",
    "sg:address":"21, Via Oltrecolle 22030 Lipomo",
    "sg:city":"Lipomo",
    "sg:classifiers":[
        {
            "category":"Shopping",
            "subcategory":"Clothing, Apparel, & Fashions",
            "type":"Retail Goods"
        }
    ],
    "sg:phone":"+39 39031283103",
    "sg:postcode":"22030",
    "sg:province":"Como",
    "sg:tags":[
        "clothing",
        "accessory"
    ],
    "wof:name":"Bianchi Giovanni S.r.l.",
    "wof:placetype":"venue"
},
  "geometry": {"coordinates":[9.101192,45.792774],"type":"Point"}
}