{
  "type": "Feature",
  "properties": {
    "iso:country":"IT",
    "sg:address":"25020 Flero",
    "sg:city":"Flero",
    "sg:orig_category":"Materiali E Componenti Elettrotecnici",
    "sg:phone":"+39 030 358 3065",
    "sg:postcode":"25020",
    "sg:province":"Brescia",
    "wof:name":"Moretti Di Gasperi Rag. Giulio",
    "wof:placetype":"venue"
},
  "geometry": {"coordinates":[10.163067,45.496315],"type":"Point"}
}