{
  "type": "Feature",
  "properties": {
    "iso:country":"IT",
    "sg:address":"10036 Settimo Torinese",
    "sg:city":"Settimo Torinese",
    "sg:orig_category":"Utensili Meccanici E Materiali",
    "sg:phone":"+39 011 800 5068",
    "sg:postcode":"10036",
    "sg:province":"Torino",
    "wof:name":"Simec Srl",
    "wof:placetype":"venue"
},
  "geometry": {"coordinates":[7.751669,45.151646],"type":"Point"}
}