{
  "type": "Feature",
  "properties": {
    "iso:country":"IT",
    "sg:address":"11, Via Manara Luciano 21100 Varese",
    "sg:city":"Varese",
    "sg:classifiers":[
        {
            "category":"Travel",
            "subcategory":"Travel Agent",
            "type":"Entertainment"
        }
    ],
    "sg:phone":"+39 0332 312870",
    "sg:postcode":"21100",
    "sg:province":"Varese",
    "sg:tags":[
        "business"
    ],
    "wof:name":"Hotel Palace",
    "wof:placetype":"venue"
},
  "geometry": {"coordinates":[8.826385,45.817604],"type":"Point"}
}