{
  "type": "Feature",
  "properties": {
    "iso:country":"IT",
    "sg:address":"26027 Rivolta D'adda",
    "sg:orig_category":"Servizi E Lavori Per Agricoltura E Zootecnia. Servizi Ausiliari Di Analisi, Controllo E Ricerca",
    "sg:phone":"+39 036 377311",
    "sg:postcode":"26027",
    "sg:province":"Cremona",
    "wof:name":"Istituto Sperimentale Italiano Spallanzani",
    "wof:placetype":"venue"
},
  "geometry": {"coordinates":[9.520851,45.459209],"type":"Point"}
}