{
  "type": "Feature",
  "properties": {
    "iso:country":"IT",
    "sg:address":"12043 Canale",
    "sg:city":"Canale",
    "sg:classifiers":[
        {
            "category":"Bars & Pubs",
            "subcategory":"Oxygen Bar",
            "type":"Food & Drink"
        }
    ],
    "sg:phone":"+39 0173 98344",
    "sg:postcode":"12043",
    "sg:province":"Cuneo",
    "sg:tags":[
        "liqueurs",
        "drinks",
        "shopping",
        "wine"
    ],
    "wof:name":"La Roerina Di Martino Giancarlo",
    "wof:placetype":"venue"
},
  "geometry": {"coordinates":[7.523633,44.401699],"type":"Point"}
}