{
  "type": "Feature",
  "properties": {
    "addr:full":"18, Viale Europa 86036 Montenero Di Bisaccia Montenero di Bisaccia Campobasso 86036",
    "addr:housenumber":"18",
    "addr:postcode":"86036;di bisaccia;86036",
    "addr:street":"Viale Europa",
    "iso:country":"IT",
    "sg:address":"18, Viale Europa 86036 Montenero Di Bisaccia",
    "sg:city":"Montenero di Bisaccia",
    "sg:classifiers":[
        {
            "category":"Real Estate",
            "subcategory":"Architect",
            "type":"Services"
        }
    ],
    "sg:phone":"+39 0875 966776",
    "sg:postcode":"86036",
    "sg:province":"Campobasso",
    "sg:tags":[
        "textile",
        "clothing"
    ],
    "wof:name":"Benedetto Evelina",
    "wof:placetype":"venue"
},
  "geometry": {"coordinates":[14.781617,41.960117],"type":"Point"}
}