{
  "type": "Feature",
  "properties": {
    "iso:country":"IT",
    "sg:address":"37069 Dossobuono",
    "sg:orig_category":"Pompe. Macchine, Strumenti Ed Apparecchi Per Attivita' Industriali",
    "sg:phone":"+39 045 862 1617",
    "sg:postcode":"37069",
    "sg:province":"Verona",
    "wof:name":"Abiclima Srl",
    "wof:placetype":"venue"
},
  "geometry": {"coordinates":[11.0050868988,45.2323951721],"type":"Point"}
}