{
  "type": "Feature",
  "properties": {
    "addr:full":"40045 Ponte Della Venturina Ponte della Venturina Bologna 40045",
    "addr:postcode":"40045;40045",
    "addr:street":"Ponte Della Venturina Ponte Della Venturina",
    "iso:country":"IT",
    "sg:address":"40045 Ponte Della Venturina",
    "sg:city":"Ponte della Venturina",
    "sg:orig_category":"Apparecchiature Ed Attrezzature Meccaniche. Ricambi E Componenti Dei Mezzi Di Trasporto",
    "sg:phone":"+39 0534 60111",
    "sg:postcode":"40045",
    "sg:province":"Bologna",
    "wof:name":"Sebac Italia S.r.l.",
    "wof:placetype":"venue"
},
  "geometry": {"coordinates":[10.946794,44.108917],"type":"Point"}
}