{
  "type": "Feature",
  "properties": {
    "iso:country":"IT",
    "sg:address":"20050 Ronco Briantino",
    "sg:city":"Ronco Briantino",
    "sg:orig_category":"Manufacturers: Prefabbricati. Impianti E Attrezzature Per Lo Sport E Il Tempo Libero",
    "sg:phone":"+39 039 681 5107",
    "sg:postcode":"20050",
    "sg:province":"Milano",
    "wof:name":"Eagle Enterprises (s.r.l.)",
    "wof:placetype":"venue"
},
  "geometry": {"coordinates":[9.416094,45.664875],"type":"Point"}
}