{
  "type": "Feature",
  "properties": {
    "iso:country":"IT",
    "sg:address":"23/b, Via Villabella 37047 San Bonifacio",
    "sg:city":"San Bonifacio",
    "sg:classifiers":[
        {
            "category":"Professional",
            "subcategory":"Engineering",
            "type":"Services"
        }
    ],
    "sg:phone":"+39 045 610 0969",
    "sg:postcode":"37047",
    "sg:province":"Verona",
    "sg:tags":[
        "machine",
        "-",
        "mechanical"
    ],
    "wof:name":"Maxa Srl",
    "wof:placetype":"venue"
},
  "geometry": {"coordinates":[10.991748,45.438366],"type":"Point"}
}