{
  "type": "Feature",
  "properties": {
    "iso:country":"IT",
    "sg:address":"35030 Rubano",
    "sg:city":"Rubano",
    "sg:orig_category":"Macchine, Impianti Ed Attrezzature Industria Delle Materie Plastiche E Gomma",
    "sg:phone":"+39 049 634608",
    "sg:postcode":"35030",
    "sg:province":"Padova",
    "wof:name":"Irs Ruote Segalina Snc",
    "wof:placetype":"venue"
},
  "geometry": {"coordinates":[11.801424,45.420578],"type":"Point"}
}