{
  "type": "Feature",
  "properties": {
    "iso:country":"IT",
    "sg:address":"97019 Vittoria",
    "sg:city":"Vittoria",
    "sg:orig_category":"Scuole E Servizi Scolastici. Ospedali E Servizi Sanitari",
    "sg:phone":"+39 0932 867252",
    "sg:postcode":"97019",
    "sg:province":"Ragusa",
    "wof:name":"Assoc.tra Professionisti Centro Studi Paideia",
    "wof:placetype":"venue"
},
  "geometry": {"coordinates":[14.532043,36.951004],"type":"Point"}
}