{
  "type": "Feature",
  "properties": {
    "addr:full":"31015 Conegliano Conegliano Treviso 31015",
    "addr:postcode":"31015;31015",
    "iso:country":"IT",
    "sg:address":"31015 Conegliano",
    "sg:city":"Conegliano",
    "sg:orig_category":"Ospedali E Servizi Sanitari",
    "sg:phone":"+39 0438 22261",
    "sg:postcode":"31015",
    "sg:province":"Treviso",
    "wof:name":"Antismoking Center Di Bianchi Giacinto",
    "wof:placetype":"venue"
},
  "geometry": {"coordinates":[12.29753,45.887619],"type":"Point"}
}