{
  "type": "Feature",
  "properties": {
    "iso:country":"IT",
    "sg:address":"37139 Verona",
    "sg:city":"Verona",
    "sg:orig_category":"Elettrotecnica Professionale E Di Consumo",
    "sg:phone":"+39 045 890 5203",
    "sg:postcode":"37139",
    "sg:province":"Verona",
    "wof:name":"Menini Maurizio",
    "wof:placetype":"venue"
},
  "geometry": {"coordinates":[10.918837,45.447353],"type":"Point"}
}