{
  "type": "Feature",
  "properties": {
    "addr:full":"20129 Milano Milano Milano 20129",
    "addr:postcode":"20129;20129",
    "iso:country":"IT",
    "sg:address":"20129 Milano",
    "sg:city":"Milano",
    "sg:classifiers":[
        {
            "category":"Health Services",
            "subcategory":"Health Practitioner",
            "type":"Services"
        }
    ],
    "sg:phone":"+39 02 236 5160",
    "sg:postcode":"20129",
    "sg:province":"Milano",
    "sg:tags":[
        "medici"
    ],
    "wof:name":"De Leon Alberto",
    "wof:placetype":"venue"
},
  "geometry": {"coordinates":[9.221722,45.475197],"type":"Point"}
}