{
  "type": "Feature",
  "properties": {
    "iso:country":"IT",
    "sg:address":"Via Nazionale 33038 San Daniele Del Friuli",
    "sg:city":"San Daniele del Friuli",
    "sg:classifiers":[
        {
            "category":"Food & Beverages",
            "subcategory":"Groceries & Convenience Stores",
            "type":"Retail Goods"
        }
    ],
    "sg:phone":"+39 0432 956195",
    "sg:postcode":"33038",
    "sg:province":"Udine",
    "sg:tags":[
        "product",
        "related"
    ],
    "wof:name":"Centro Dolce Friuli (s.r.l.)",
    "wof:placetype":"venue"
},
  "geometry": {"coordinates":[12.9706678391,46.1331596375],"type":"Point"}
}