{
  "type": "Feature",
  "properties": {
    "iso:country":"IT",
    "sg:address":"83042 Atripalda",
    "sg:city":"Atripalda",
    "sg:orig_category":"Editoria Elettronica E Multimediale",
    "sg:phone":"+39 0825 625273",
    "sg:postcode":"83042",
    "sg:province":"Avellino",
    "sg:website":"http://www.avionpage.it",
    "wof:name":"Avion Page Web Agency",
    "wof:placetype":"venue"
},
  "geometry": {"coordinates":[14.8329,40.919567],"type":"Point"}
}