{
  "type": "Feature",
  "properties": {
    "iso:country":"IT",
    "sg:address":"18010 Badalucco",
    "sg:city":"Badalucco",
    "sg:orig_category":"Caminetti, Forni Da Giardino E Barbecues",
    "sg:phone":"+39 0184 408050",
    "sg:postcode":"18010",
    "sg:province":"Imperia",
    "wof:name":"M.e.c. Fer Di Fogliarini Massimiliano",
    "wof:placetype":"venue"
},
  "geometry": {"coordinates":[7.846762,43.916992],"type":"Point"}
}