{
  "type": "Feature",
  "properties": {
    "iso:country":"IT",
    "sg:address":"74100 Taranto",
    "sg:city":"Taranto",
    "sg:orig_category":"Abbigliamento Esterno, Maglierie E Pelliccerie. Shopping",
    "sg:phone":"+39 099 453 4923",
    "sg:postcode":"74100",
    "sg:province":"Taranto",
    "wof:name":"Kent Srl",
    "wof:placetype":"venue"
},
  "geometry": {"coordinates":[17.237787,40.470726],"type":"Point"}
}