{
  "type": "Feature",
  "properties": {
    "addr:full":"30, Via Monte Comun 37057 San Giovanni Lupatoto San Giovanni Lupatoto Verona 37057",
    "addr:postcode":"37057;37057",
    "addr:street":"Via Monte Comun;Verona",
    "iso:country":"IT",
    "sg:address":"30, Via Monte Comun 37057 San Giovanni Lupatoto",
    "sg:city":"San Giovanni Lupatoto",
    "sg:classifiers":[
        {
            "category":"Manufacturing",
            "subcategory":"Printing",
            "type":"Manufacturing & Wholesale Goods"
        }
    ],
    "sg:phone":"+39 045 925 1790",
    "sg:postcode":"37057",
    "sg:province":"Verona",
    "sg:tags":[
        "publishing"
    ],
    "wof:name":"Editoriale Bortolazzi Stei (s.r.l.)",
    "wof:placetype":"venue"
},
  "geometry": {"coordinates":[11.0281677246,45.3910255432],"type":"Point"}
}