{
  "type": "Feature",
  "properties": {
    "iso:country":"IT",
    "sg:address":"72100 Brindisi",
    "sg:city":"Brindisi",
    "sg:orig_category":"Apparecchiature Ed Attrezzature Meccaniche",
    "sg:phone":"+39 0831 512234",
    "sg:postcode":"72100",
    "sg:province":"Brindisi",
    "wof:name":"Alo Fulvio Interflon",
    "wof:placetype":"venue"
},
  "geometry": {"coordinates":[17.939177,40.630878],"type":"Point"}
}