{
  "type": "Feature",
  "properties": {
    "addr:full":"31020 Refrontolo Refrontolo Treviso 31020",
    "addr:postcode":"31020;31020",
    "iso:country":"IT",
    "sg:address":"31020 Refrontolo",
    "sg:city":"Refrontolo",
    "sg:orig_category":"Arredamenti E Mobili Professionali. Arredi Ed Attrezzature Per Uffici",
    "sg:phone":"+39 0438 841841",
    "sg:postcode":"31020",
    "sg:province":"Treviso",
    "sg:website":"http://www.dielle.it",
    "wof:name":"Mobilificio Dielle Spa",
    "wof:placetype":"venue"
},
  "geometry": {"coordinates":[12.198383,45.907795],"type":"Point"}
}