{
  "type": "Feature",
  "properties": {
    "iso:country":"IT",
    "sg:address":"83, Via Tavagnacco 33100 Udine",
    "sg:city":"Udine",
    "sg:classifiers":[
        {
            "category":"Professional",
            "subcategory":"Computer Services",
            "type":"Services"
        }
    ],
    "sg:phone":"+39 0432 482750",
    "sg:postcode":"33100",
    "sg:province":"Udine",
    "sg:tags":[
        "information",
        "technology"
    ],
    "wof:name":"Piano (s.r.l.)",
    "wof:placetype":"venue"
},
  "geometry": {"coordinates":[13.228445,46.09235],"type":"Point"}
}