{
  "type": "Feature",
  "properties": {
    "iso:country":"IT",
    "sg:address":"01100 Viterbo",
    "sg:city":"Viterbo",
    "sg:orig_category":"Abbigliamento Esterno, Maglierie E Pelliccerie. Calzature, Pelletterie E Pelli",
    "sg:phone":"+39 0761 307037",
    "sg:postcode":"01100",
    "sg:province":"Viterbo",
    "wof:name":"Feliziani Maria",
    "wof:placetype":"venue"
},
  "geometry": {"coordinates":[12.104309,42.419544],"type":"Point"}
}