{
  "type": "Feature",
  "properties": {
    "iso:country":"IT",
    "sg:address":"Km. 141, Strada Statale 113 98072 Caronia",
    "sg:city":"Caronia",
    "sg:classifiers":[
        {
            "category":"Building & Trades",
            "subcategory":"Construction",
            "type":"Services"
        }
    ],
    "sg:phone":"+39 0921 335550",
    "sg:postcode":"98072",
    "sg:province":"Messina",
    "sg:tags":[
        "work",
        "public"
    ],
    "wof:name":"Portale E Pagliarotto S.c.a.r.l.",
    "wof:placetype":"venue"
},
  "geometry": {"coordinates":[15.555523,38.192333],"type":"Point"}
}