{
  "type": "Feature",
  "properties": {
    "iso:country":"IT",
    "sg:address":"57123 Livorno",
    "sg:city":"Livorno",
    "sg:orig_category":"Nautica - Noleggio",
    "sg:phone":"+39 0586 210709",
    "sg:postcode":"57123",
    "sg:province":"Livorno",
    "sg:website":"http://www.civela.it",
    "wof:name":"Centro Italiano Vela Srl",
    "wof:placetype":"venue"
},
  "geometry": {"coordinates":[10.310501,43.577747],"type":"Point"}
}