{
  "type": "Feature",
  "properties": {
    "addr:full":"Via Turi Ang; Cursi; 73020 Cursi Lecce 73020",
    "addr:postcode":"73020;73020",
    "addr:street":"Via Turi Ang",
    "iso:country":"IT",
    "sg:address":"Via Turi Ang; Cursi; 73020",
    "sg:city":"Cursi",
    "sg:classifiers":[
        {
            "category":"Banks & Credit Unions",
            "subcategory":"Bank",
            "type":"Services"
        }
    ],
    "sg:phone":"+39 0836 332036",
    "sg:postcode":"73020",
    "sg:province":"Lecce",
    "wof:name":"Rolo Banca 1473 Spa",
    "wof:placetype":"venue"
},
  "geometry": {"coordinates":[18.31563,40.150631],"type":"Point"}
}