{
  "type": "Feature",
  "properties": {
    "iso:country":"IT",
    "sg:address":"20081 Abbiategrasso",
    "sg:city":"Abbiategrasso",
    "sg:orig_category":"Macchine Utensili E Impianti. Apparecchiature Ed Attrezzature Meccaniche",
    "sg:phone":"+39 02 9469 9467",
    "sg:postcode":"20081",
    "sg:province":"Milano",
    "wof:name":"De Paoli Marco",
    "wof:placetype":"venue"
},
  "geometry": {"coordinates":[9.209391,45.455139],"type":"Point"}
}