{
  "type": "Feature",
  "properties": {
    "addr:full":"Via Invrea Giovanni Tomaso 9/4 A 16129 Genova Genova Genova 16129",
    "addr:housenumber":"9 / 4 a",
    "addr:postcode":"16129;16129",
    "addr:street":"Via Invrea Giovanni Tomaso",
    "iso:country":"IT",
    "sg:address":"Via Invrea Giovanni Tomaso 9/4 A 16129 Genova",
    "sg:city":"Genova",
    "sg:classifiers":[
        {
            "category":"Transit Center",
            "subcategory":"Freight",
            "type":"Transportation"
        }
    ],
    "sg:phone":"+39 010 589550",
    "sg:postcode":"16129",
    "sg:province":"Genova",
    "sg:tags":[
        "windows",
        "ship",
        "porthole"
    ],
    "sg:website":"www.coapind.it",
    "wof:name":"Coapind Costruzione Apparecchiature Industriali Srl",
    "wof:placetype":"venue"
},
  "geometry": {"coordinates":[8.933989,44.407063],"type":"Point"}
}