{
  "type": "Feature",
  "properties": {
    "iso:country":"IT",
    "sg:address":"65121 Pescara",
    "sg:city":"Pescara",
    "sg:orig_category":"Pubblica Amministrazione",
    "sg:phone":"+39 085 37241",
    "sg:postcode":"65121",
    "sg:province":"Pescara",
    "sg:website":"http://www.provincia.pescara.it",
    "wof:name":"Amministrazione Provinciale Di Pescara",
    "wof:placetype":"venue"
},
  "geometry": {"coordinates":[14.2141866684,42.4642219543],"type":"Point"}
}