{
  "type": "Feature",
  "properties": {
    "addr:full":"55012 Capannori Capannori Lucca 55012",
    "addr:postcode":"55012;55012",
    "iso:country":"IT",
    "sg:address":"55012 Capannori",
    "sg:city":"Capannori",
    "sg:orig_category":"Prodotti Finiti Stampati. Forniture E Materiali Per Imballaggio E Confezionamento. Forniture Per Attivita' Commerciali Ed Artigianali",
    "sg:phone":"+39 0583 403240",
    "sg:postcode":"55012",
    "sg:province":"Lucca",
    "sg:website":"http://www.toscocarta.it",
    "wof:name":"Toscocarta Spa",
    "wof:placetype":"venue"
},
  "geometry": {"coordinates":[10.5858783722,43.8416061401],"type":"Point"}
}