{
  "type": "Feature",
  "properties": {
    "iso:country":"IT",
    "sg:address":"Via Ss.303 Km.3500 83040 Fontanarosa",
    "sg:city":"Fontanarosa",
    "sg:classifiers":[
        {
            "category":"Manufacturing",
            "subcategory":"Tools & Machinery",
            "type":"Manufacturing & Wholesale Goods"
        }
    ],
    "sg:phone":"+39 0825 475540",
    "sg:postcode":"83040",
    "sg:province":"Avellino",
    "sg:tags":[
        "environment",
        "equipment",
        "-"
    ],
    "wof:name":"Mondial Pin Srl",
    "wof:placetype":"venue"
},
  "geometry": {"coordinates":[14.792723,40.914749],"type":"Point"}
}