{
  "type": "Feature",
  "properties": {
    "iso:country":"IT",
    "sg:address":"30123 Venezia",
    "sg:city":"Dorsoduro",
    "sg:orig_category":"Pubblica Amministrazione",
    "sg:phone":"+39 041 520 5792",
    "sg:postcode":"30123",
    "sg:province":"Venezia",
    "wof:name":"Uffici Giudiziari",
    "wof:placetype":"venue"
},
  "geometry": {"coordinates":[12.322385788,45.4328422546],"type":"Point"}
}