{
  "type": "Feature",
  "properties": {
    "iso:country":"IT",
    "sg:address":"84013 Cava De'tirreni",
    "sg:orig_category":"Nautica. Forniture Per Attivita' Commerciali Ed Artigianali",
    "sg:phone":"+39 089 461417",
    "sg:postcode":"84013",
    "sg:province":"Salerno",
    "wof:name":"Lamberti Gennaro E Vincenzo (s.n.c.)",
    "wof:placetype":"venue"
},
  "geometry": {"coordinates":[14.693768,40.706985],"type":"Point"}
}