{
  "type": "Feature",
  "properties": {
    "iso:country":"IT",
    "sg:address":"18, Via Santarcangiolese 47825 Torriana",
    "sg:city":"Torriana",
    "sg:orig_category":"Miscellaneous Products",
    "sg:phone":"+39 0541 675280",
    "sg:postcode":"47825",
    "sg:province":"Rimini",
    "wof:name":"K E K Logistics Spa",
    "wof:placetype":"venue"
},
  "geometry": {"coordinates":[12.4294319153,44.0447998047],"type":"Point"}
}