{
  "type": "Feature",
  "properties": {
    "addr:full":"Contrada Ronchi 3 36054 Montebello Vicentino Montebello Vicentino Vicenza 36054",
    "addr:housenumber":"3",
    "addr:postcode":"36054;36054",
    "addr:street":"Contrada Ronchi",
    "iso:country":"IT",
    "sg:address":"Contrada Ronchi 3 36054 Montebello Vicentino",
    "sg:city":"Montebello Vicentino",
    "sg:classifiers":[
        {
            "category":"Utilities",
            "subcategory":"Electric",
            "type":"Services"
        }
    ],
    "sg:phone":"+39 0444 440254",
    "sg:postcode":"36054",
    "sg:province":"Vicenza",
    "sg:tags":[
        "transformer"
    ],
    "sg:website":"www.celmesrl.com",
    "wof:name":"Celme Srl",
    "wof:placetype":"venue"
},
  "geometry": {"coordinates":[11.403111,45.456909],"type":"Point"}
}