{
  "type": "Feature",
  "properties": {
    "addr:full":"25078 Vestone Vestone Brescia 25078",
    "addr:postcode":"25078;25078",
    "iso:country":"IT",
    "sg:address":"25078 Vestone",
    "sg:city":"Vestone",
    "sg:orig_category":"Metalli E Leghe",
    "sg:phone":"+39 036 582 0128",
    "sg:postcode":"25078",
    "sg:province":"Brescia",
    "wof:name":"Tieffe Di Turelli Fiorangela",
    "wof:placetype":"venue"
},
  "geometry": {"coordinates":[10.3949670792,45.7068595886],"type":"Point"}
}