{
  "type": "Feature",
  "properties": {
    "iso:country":"IT",
    "sg:address":"30020 Marcon",
    "sg:city":"Marcon",
    "sg:orig_category":"Apparecchiature Ed Attrezzature Meccaniche",
    "sg:phone":"+39 041 595 1882",
    "sg:postcode":"30020",
    "sg:province":"Venezia",
    "wof:name":"R.p. Trading Di Pellico Claudio & C. Sas",
    "wof:placetype":"venue"
},
  "geometry": {"coordinates":[12.291923,45.54739],"type":"Point"}
}