{
  "type": "Feature",
  "properties": {
    "addr:full":"20122 Milano Milano Milano 20122",
    "addr:postcode":"20122;20122",
    "iso:country":"IT",
    "sg:address":"20122 Milano",
    "sg:city":"Milano",
    "sg:orig_category":"Ospedali E Servizi Sanitari. Centri Di Estetica E Cosmesi E Servizi",
    "sg:phone":"+39 02 7202 3512",
    "sg:postcode":"20122",
    "sg:province":"Milano",
    "wof:name":"Centro Podologico G.m.c. (s.n.c.)",
    "wof:placetype":"venue"
},
  "geometry": {"coordinates":[9.193591,45.464287],"type":"Point"}
}