{
  "type": "Feature",
  "properties": {
    "iso:country":"IT",
    "sg:address":"71, Via Foggia 70051 Barletta",
    "sg:city":"Barletta",
    "sg:classifiers":[
        {
            "category":"Personal",
            "subcategory":"Shoe Repair & Shine",
            "type":"Services"
        }
    ],
    "sg:phone":"+39 0883 525863",
    "sg:postcode":"70051",
    "sg:province":"Bari",
    "sg:tags":[
        "leather"
    ],
    "wof:name":"Arpex Accessori Di Musti Cataldo Snc",
    "wof:placetype":"venue"
},
  "geometry": {"coordinates":[16.234631,41.32383],"type":"Point"}
}