{
  "type": "Feature",
  "properties": {
    "iso:country":"IT",
    "sg:address":"80070 Barano D'ischia",
    "sg:orig_category":"Alberghi E Strutture Extra Alberghiere. Ospedali E Servizi Sanitari",
    "sg:phone":"+39 081 990127",
    "sg:postcode":"80070",
    "sg:province":"Napoli",
    "wof:name":"Leonic Srl",
    "wof:placetype":"venue"
},
  "geometry": {"coordinates":[13.912453,40.701935],"type":"Point"}
}