{
  "type": "Feature",
  "properties": {
    "iso:country":"IT",
    "sg:address":"00122 Lido Di Ostia",
    "sg:orig_category":"Pubblica Amministrazione",
    "sg:phone":"+39 06 5647 1049",
    "sg:postcode":"00122",
    "sg:province":"Roma",
    "wof:name":"Regione Lazio Assessorato Opere E Reti Di Servizi E Mobilita'",
    "wof:placetype":"venue"
},
  "geometry": {"coordinates":[12.3078632355,41.7178344727],"type":"Point"}
}