{
  "type": "Feature",
  "properties": {
    "addr:full":"Via Delle Industrie 5 30020 Fossalta Di Piave Fossalta di Piave Venezia 30020",
    "addr:housenumber":"5",
    "addr:postcode":"30020;30020",
    "addr:street":"Via Delle Industrie",
    "iso:country":"IT",
    "sg:address":"Via Delle Industrie 5 30020 Fossalta Di Piave",
    "sg:city":"Fossalta di Piave",
    "sg:classifiers":[
        {
            "category":"Military Area",
            "subcategory":"Air Force Base",
            "type":"Public Place"
        }
    ],
    "sg:phone":"+39 0421 67222",
    "sg:postcode":"30020",
    "sg:province":"Venezia",
    "sg:tags":[
        "wooden",
        "double",
        "windows",
        "pane"
    ],
    "sg:website":"www.lunardelli.net",
    "wof:name":"Lunardelli Angelo",
    "wof:placetype":"venue"
},
  "geometry": {"coordinates":[12.501241,45.643299],"type":"Point"}
}