{
  "type": "Feature",
  "properties": {
    "addr:full":"30175 Mestre Mestre Venezia 30175",
    "addr:postcode":"30175;30175",
    "addr:street":"Mestre Mestre Venezia",
    "iso:country":"IT",
    "sg:address":"30175 Mestre",
    "sg:city":"Mestre",
    "sg:orig_category":"Zootecnia E Pesca, Allevamento Piccoli Animali. Animali Domestici",
    "sg:phone":"+39 041 535 2063",
    "sg:postcode":"30175",
    "sg:province":"Venezia",
    "wof:name":"Acquario Di Jenny S.n.c. Di Rigo Giorgio & C.",
    "wof:placetype":"venue"
},
  "geometry": {"coordinates":[12.247819,45.49538],"type":"Point"}
}