{
  "type": "Feature",
  "properties": {
    "iso:country":"IT",
    "sg:address":"36075 Montecchio Maggiore",
    "sg:city":"Montecchio Maggiore",
    "sg:orig_category":"Calcestruzzo Preconfezionato",
    "sg:phone":"+39 0444 499237",
    "sg:postcode":"36075",
    "sg:province":"Vicenza",
    "wof:name":"Calcestruzzi Castello Srl",
    "wof:placetype":"venue"
},
  "geometry": {"coordinates":[11.450907,45.52351],"type":"Point"}
}