{
  "type": "Feature",
  "properties": {
    "iso:country":"IT",
    "sg:address":"Via Bassa Della Vergine 47 51100 Pistoia",
    "sg:city":"Pistoia",
    "sg:classifiers":[
        {
            "category":"Shopping",
            "subcategory":"Clothing, Apparel, & Fashions",
            "type":"Retail Goods"
        }
    ],
    "sg:phone":"+39 0573 534359",
    "sg:postcode":"51100",
    "sg:province":"Pistoia",
    "sg:tags":[
        "lingerie"
    ],
    "wof:name":"Bindi Fratelli Paolo & Anna Paola S.r.l.",
    "wof:placetype":"venue"
},
  "geometry": {"coordinates":[10.922599,43.922676],"type":"Point"}
}