{
  "type": "Feature",
  "properties": {
    "addr:full":"51016 Montecatini Terme Pistoia 51016",
    "addr:postcode":"51016;51016",
    "iso:country":"IT",
    "sg:address":"51016 Montecatini Terme",
    "sg:classifiers":[
        {
            "category":"Professional",
            "type":"Services"
        }
    ],
    "sg:phone":"+39 0572 913006",
    "sg:postcode":"51016",
    "sg:province":"Pistoia",
    "sg:tags":[
        "activities",
        "supply",
        "commercial",
        "artisan",
        "supplies",
        "accommodation"
    ],
    "wof:name":"Alex Alberghiera Di Siccardi Alessandro",
    "wof:placetype":"venue"
},
  "geometry": {"coordinates":[10.767347,43.874077],"type":"Point"}
}