{
  "type": "Feature",
  "properties": {
    "iso:country":"IT",
    "sg:address":"00163 Roma",
    "sg:city":"Roma",
    "sg:classifiers":[
        {
            "category":"Autos & Motor Vehicles",
            "subcategory":"Fuel & Gas Station",
            "type":"Retail Goods"
        }
    ],
    "sg:phone":"+39 06 6577 1249",
    "sg:postcode":"00163",
    "sg:province":"Roma",
    "sg:tags":[
        "petroleum",
        "products"
    ],
    "wof:name":"Petro Service 90 Srl",
    "wof:placetype":"venue"
},
  "geometry": {"coordinates":[12.3696451187,41.8631744385],"type":"Point"}
}