{
  "type": "Feature",
  "properties": {
    "iso:country":"IT",
    "sg:address":"21018 Sesto Calende",
    "sg:city":"Sesto Calende",
    "sg:classifiers":[
        {
            "category":"Personal",
            "subcategory":"Beauty Salon",
            "type":"Services"
        }
    ],
    "sg:phone":"+39 0331 920888",
    "sg:postcode":"21018",
    "sg:province":"Varese",
    "sg:tags":[
        "salons",
        "activities",
        "product",
        "industrial",
        "hospital",
        "equipment",
        "engineering",
        "health",
        "systems",
        "mechanical",
        "supplies",
        "electronic",
        "mach"
    ],
    "sg:website":"http://www.laservall.com",
    "wof:name":"Laservall Spa",
    "wof:placetype":"venue"
},
  "geometry": {"coordinates":[8.652465,45.729813],"type":"Point"}
}