{
  "type": "Feature",
  "properties": {
    "addr:full":"25065 Lumezzane Lumezzane Brescia 25065",
    "addr:postcode":"25065;25065",
    "iso:country":"IT",
    "sg:address":"25065 Lumezzane",
    "sg:city":"Lumezzane",
    "sg:orig_category":"Utensili Meccanici E Materiali",
    "sg:phone":"+39 030 897 1113",
    "sg:postcode":"25065",
    "sg:province":"Brescia",
    "wof:name":"Stamber Di Bertoli Roberto & C. Snc",
    "wof:placetype":"venue"
},
  "geometry": {"coordinates":[10.244138,45.653793],"type":"Point"}
}