{
  "type": "Feature",
  "properties": {
    "addr:full":"24121 Bergamo Bergamo Bergamo 24121",
    "addr:postcode":"24121;24121",
    "iso:country":"IT",
    "sg:address":"24121 Bergamo",
    "sg:city":"Bergamo",
    "sg:orig_category":"Banche E Servizi Finanziari",
    "sg:phone":"+39 035 211171",
    "sg:postcode":"24121",
    "sg:province":"Bergamo",
    "wof:name":"S.a.m. Srl",
    "wof:placetype":"venue"
},
  "geometry": {"coordinates":[9.675341,45.694351],"type":"Point"}
}