{
  "type": "Feature",
  "properties": {
    "iso:country":"IT",
    "sg:address":"45100 Rovigo",
    "sg:city":"Rovigo",
    "sg:orig_category":"Macchine, Impianti Ed Attrezzature Industria Chimica. Macchine Ed Impianti Per Edilizia E Lavori Pubblici",
    "sg:phone":"+39 0425 475393",
    "sg:postcode":"45100",
    "sg:province":"Rovigo",
    "wof:name":"Schiesari F.lli Snc Di Gianni E Gabriele & C.",
    "wof:placetype":"venue"
},
  "geometry": {"coordinates":[11.779519,45.051567],"type":"Point"}
}