{
  "type": "Feature",
  "properties": {
    "iso:country":"IT",
    "sg:address":"24030 Mozzo",
    "sg:city":"Mozzo",
    "sg:orig_category":"Saldatrici - Produzione E Commercio",
    "sg:phone":"+39 035 528500",
    "sg:postcode":"24030",
    "sg:province":"Bergamo",
    "wof:name":"Mangili Macchine Srl",
    "wof:placetype":"venue"
},
  "geometry": {"coordinates":[9.606055,45.709595],"type":"Point"}
}