{
  "type": "Feature",
  "properties": {
    "iso:country":"IT",
    "sg:address":"Sda Statale Padana Superiore 14 20063 Cernusco Sul Naviglio",
    "sg:city":"Cernusco sul Naviglio",
    "sg:classifiers":[
        {
            "category":"Manufacturing",
            "subcategory":"Motor Vehicles & Parts",
            "type":"Manufacturing & Wholesale Goods"
        }
    ],
    "sg:phone":"+39 02 9210 7588",
    "sg:postcode":"20063",
    "sg:province":"Milano",
    "sg:tags":[
        "automotive",
        "chassis"
    ],
    "sg:website":"www.plasticbike.com",
    "wof:name":"Plastic Bike Di Odasso Ivo E C Snc",
    "wof:placetype":"venue"
},
  "geometry": {"coordinates":[9.188141,45.463688],"type":"Point"}
}