{
  "type": "Feature",
  "properties": {
    "addr:full":"2/a, Via Goldaniga 26013 Crema Crema Cremona 26013",
    "addr:housenumber":"2 / a",
    "addr:postcode":"26013;26013",
    "addr:street":"Via Goldaniga",
    "iso:country":"IT",
    "sg:address":"2/a, Via Goldaniga 26013 Crema",
    "sg:city":"Crema",
    "sg:classifiers":[
        {
            "category":"Manufacturing",
            "subcategory":"Printing",
            "type":"Manufacturing & Wholesale Goods"
        }
    ],
    "sg:phone":"+39 0373 256350",
    "sg:postcode":"26013",
    "sg:province":"Cremona",
    "sg:tags":[
        "publishing"
    ],
    "wof:name":"Giornale Il Nuovo Torrazzo",
    "wof:placetype":"venue"
},
  "geometry": {"coordinates":[10.0261354446,45.1334991455],"type":"Point"}
}