{
  "type": "Feature",
  "properties": {
    "addr:full":"Zona Industriale 73044 Galatone Galatone Lecce 73044",
    "addr:postcode":"73044;73044",
    "addr:street":"Zona Industriale",
    "iso:country":"IT",
    "sg:address":"Zona Industriale 73044 Galatone",
    "sg:city":"Galatone",
    "sg:classifiers":[
        {
            "category":"Shopping",
            "type":"Retail Goods"
        }
    ],
    "sg:phone":"+39 0833 832220",
    "sg:postcode":"73044",
    "sg:province":"Lecce",
    "sg:tags":[
        "finished",
        "-",
        "metallic"
    ],
    "wof:name":"Nuova Fise (s.r.l.)",
    "wof:placetype":"venue"
},
  "geometry": {"coordinates":[18.1740150452,40.3532905579],"type":"Point"}
}