{
  "type": "Feature",
  "properties": {
    "iso:country":"IT",
    "sg:address":"62032 Camerino",
    "sg:city":"Camerino",
    "sg:orig_category":"Abbigliamento Esterno, Maglierie E Pelliccerie. Sport - Articoli E Forniture. Shopping",
    "sg:phone":"+39 0737 632145",
    "sg:postcode":"62032",
    "sg:province":"Macerata",
    "wof:name":"Jacky-o Sportswear Srl",
    "wof:placetype":"venue"
},
  "geometry": {"coordinates":[13.443267,43.298729],"type":"Point"}
}