{
  "type": "Feature",
  "properties": {
    "iso:country":"IT",
    "sg:address":"31, Via Provinciale 25030 Erbusco",
    "sg:city":"Erbusco",
    "sg:classifiers":[
        {
            "category":"Shopping",
            "subcategory":"Clothing, Apparel, & Fashions",
            "type":"Retail Goods"
        }
    ],
    "sg:phone":"+39 39030723748",
    "sg:postcode":"25030",
    "sg:province":"Brescia",
    "sg:tags":[
        "clothes"
    ],
    "wof:name":"P.m.c. Di Monsi Plebani (s.r.l.)",
    "wof:placetype":"venue"
},
  "geometry": {"coordinates":[9.957673,45.62022],"type":"Point"}
}