{
  "type": "Feature",
  "properties": {
    "addr:full":"06024 Gubbio Gubbio Perugia 06024",
    "addr:postcode":"06024;06024",
    "iso:country":"IT",
    "sg:address":"06024 Gubbio",
    "sg:city":"Gubbio",
    "sg:orig_category":"Vetrate Artistiche",
    "sg:phone":"+39 075 927 3804",
    "sg:postcode":"06024",
    "sg:province":"Perugia",
    "wof:name":"Vetreria Eugubina Snc",
    "wof:placetype":"venue"
},
  "geometry": {"coordinates":[12.56097,43.358456],"type":"Point"}
}