{
  "type": "Feature",
  "properties": {
    "iso:country":"IT",
    "sg:address":"00186 Roma",
    "sg:city":"Roma",
    "sg:orig_category":"Servizi Per Lo Sport E Il Tempo Libero. Associazioni Ed Organismi Di Interesse Pubblico",
    "sg:phone":"+39 347 658 9455",
    "sg:postcode":"00186",
    "sg:province":"Roma",
    "wof:name":"Juke Box Club A.c.",
    "wof:placetype":"venue"
},
  "geometry": {"coordinates":[12.278121,42.087643],"type":"Point"}
}