{
  "type": "Feature",
  "properties": {
    "addr:full":"Via Brandizzo 176 10088 Volpiano Volpiano Torino 10088",
    "addr:housenumber":"176",
    "addr:postcode":"10088;10088",
    "addr:street":"Via Brandizzo",
    "iso:country":"IT",
    "sg:address":"Via Brandizzo 176 10088 Volpiano",
    "sg:city":"Volpiano",
    "sg:classifiers":[
        {
            "category":"Real Estate",
            "subcategory":"Real Estate Services",
            "type":"Services"
        }
    ],
    "sg:phone":"+39 011 988 1833",
    "sg:postcode":"10088",
    "sg:province":"Torino",
    "sg:tags":[
        "development",
        "management"
    ],
    "wof:name":"F.m. S.r.l.",
    "wof:placetype":"venue"
},
  "geometry": {"coordinates":[7.813622,45.174004],"type":"Point"}
}