{
  "type": "Feature",
  "properties": {
    "addr:full":"91011 Alcamo Alcamo Trapani 91011",
    "addr:postcode":"91011;91011",
    "iso:country":"IT",
    "sg:address":"91011 Alcamo",
    "sg:city":"Alcamo",
    "sg:orig_category":"Autoaccessori - Commercio",
    "sg:phone":"+39 0924 21371",
    "sg:postcode":"91011",
    "sg:province":"Trapani",
    "wof:name":"Li.vi. Alcafodere Di Lipari V.za & C. Snc",
    "wof:placetype":"venue"
},
  "geometry": {"coordinates":[12.966582,37.954071],"type":"Point"}
}