{
  "type": "Feature",
  "properties": {
    "addr:full":"47, Via Bassanese 31037 Loria Loria Treviso 31037",
    "addr:postcode":"31037;31037",
    "addr:street":"Via Bassanese",
    "iso:country":"IT",
    "sg:address":"47, Via Bassanese 31037 Loria",
    "sg:city":"Loria",
    "sg:classifiers":[
        {
            "category":"Home & Garden",
            "subcategory":"Home Furnishings",
            "type":"Retail Goods"
        }
    ],
    "sg:phone":"+39 0423 470258",
    "sg:postcode":"31037",
    "sg:province":"Treviso",
    "sg:tags":[
        "household"
    ],
    "wof:name":"Arte Antiqua - Zen Adriano",
    "wof:placetype":"venue"
},
  "geometry": {"coordinates":[11.827924,45.731884],"type":"Point"}
}