{
  "type": "Feature",
  "properties": {
    "addr:full":"Corso Della Repubblica 27; Ferrera Erbognone; 27032 Ferrera Erbognone Pavia 27032",
    "addr:housenumber":"27",
    "addr:postcode":"27032;27032",
    "addr:street":"Corso Della Repubblica",
    "iso:country":"IT",
    "sg:address":"Corso Della Repubblica 27; Ferrera Erbognone; 27032",
    "sg:city":"Ferrera Erbognone",
    "sg:classifiers":[
        {
            "category":"Banks & Credit Unions",
            "subcategory":"Bank",
            "type":"Services"
        }
    ],
    "sg:phone":"+39 0382 998101",
    "sg:postcode":"27032",
    "sg:province":"Pavia",
    "wof:name":"Istituto Bancario, San Paolo Di Torino Spa",
    "wof:placetype":"venue"
},
  "geometry": {"coordinates":[8.866102,45.114349],"type":"Point"}
}