{
  "type": "Feature",
  "properties": {
    "addr:full":"37057 S. Giovanni Lupatoto Verona 37057",
    "addr:housenumber":"37057",
    "addr:postcode":"37057",
    "addr:street":"S. Giovanni Lupatoto",
    "iso:country":"IT",
    "sg:address":"37057 S. Giovanni Lupatoto",
    "sg:classifiers":[
        {
            "category":"Manufacturing",
            "subcategory":"Food",
            "type":"Manufacturing & Wholesale Goods"
        }
    ],
    "sg:phone":"+39 045 877 8521",
    "sg:postcode":"37057",
    "sg:province":"Verona",
    "sg:tags":[
        "product"
    ],
    "wof:name":"Rigodanza Serafino & C. Spa",
    "wof:placetype":"venue"
},
  "geometry": {"coordinates":[11.0293102264,45.3776168823],"type":"Point"}
}