{
  "type": "Feature",
  "properties": {
    "iso:country":"IT",
    "sg:address":"38/2, Via King Martin Luther 40132 Bologna",
    "sg:city":"Bologna",
    "sg:classifiers":[
        {
            "category":"Airport",
            "subcategory":"General Aviation",
            "type":"Transportation"
        }
    ],
    "sg:phone":"+39 051 641 0811",
    "sg:postcode":"40132",
    "sg:province":"Bologna",
    "sg:tags":[
        "transport",
        "air"
    ],
    "wof:name":"Merzario Spa",
    "wof:placetype":"venue"
},
  "geometry": {"coordinates":[11.346481,44.494221],"type":"Point"}
}