{
  "type": "Feature",
  "properties": {
    "iso:country":"IT",
    "sg:address":"Via Gustavo Protti 32013 Longarone",
    "sg:city":"Longarone",
    "sg:classifiers":[
        {
            "category":"Professional",
            "subcategory":"Engineering",
            "type":"Services"
        }
    ],
    "sg:phone":"+39 0437 771859",
    "sg:postcode":"32013",
    "sg:province":"Belluno",
    "sg:tags":[
        "machine",
        "-",
        "mechanical"
    ],
    "wof:name":"Mir (s.r.l.)",
    "wof:placetype":"venue"
},
  "geometry": {"coordinates":[12.304387,46.264423],"type":"Point"}
}