{
  "type": "Feature",
  "properties": {
    "iso:country":"IT",
    "sg:address":"70033 Corato",
    "sg:city":"Corato",
    "sg:classifiers":[
        {
            "category":"Health Services",
            "subcategory":"Health Practitioner",
            "type":"Services"
        }
    ],
    "sg:phone":"+39 080 372 0018",
    "sg:postcode":"70033",
    "sg:province":"Bari",
    "sg:tags":[
        "medici"
    ],
    "wof:name":"Mangano Silvana",
    "wof:placetype":"venue"
},
  "geometry": {"coordinates":[16.417408,41.150368],"type":"Point"}
}