{
  "type": "Feature",
  "properties": {
    "iso:country":"IT",
    "sg:address":"70022 Altamura",
    "sg:city":"Altamura",
    "sg:orig_category":"Prodotti E Manufatti In Materie Plastiche. Articoli Per Imballaggio E Confezionamento",
    "sg:phone":"+39 080 314 4999",
    "sg:postcode":"70022",
    "sg:province":"Bari",
    "wof:name":"Monteplastica Di Rossini M.",
    "wof:placetype":"venue"
},
  "geometry": {"coordinates":[16.5629272461,40.8265342712],"type":"Point"}
}