{
  "type": "Feature",
  "properties": {
    "addr:full":"20157 Milano Milano Milano 20157",
    "addr:postcode":"20157;20157",
    "iso:country":"IT",
    "sg:address":"20157 Milano",
    "sg:city":"Milano",
    "sg:orig_category":"Abbigliamento Intimo, Calze E Costumi Da Bagno. Articoli Medico-sanitari Ed Ortopedici",
    "sg:phone":"+39 02 355 0706",
    "sg:postcode":"20157",
    "sg:province":"Milano",
    "wof:name":"Ortopedia Nesler",
    "wof:placetype":"venue"
},
  "geometry": {"coordinates":[9.148871,45.488914],"type":"Point"}
}