{
  "type": "Feature",
  "properties": {
    "addr:full":"33017 Tarcento Tarcento Udine 33017",
    "addr:postcode":"33017;33017",
    "iso:country":"IT",
    "sg:address":"33017 Tarcento",
    "sg:city":"Tarcento",
    "sg:orig_category":"Pubblica Amministrazione",
    "sg:phone":"+39 0432 793294",
    "sg:postcode":"33017",
    "sg:province":"Udine",
    "wof:name":"Comunita' Montana Delle Valli Del Torre",
    "wof:placetype":"venue"
},
  "geometry": {"coordinates":[13.2212982178,46.2214622498],"type":"Point"}
}