{
  "type": "Feature",
  "properties": {
    "addr:full":"Vle Colombo 112 50054 Fucecchio Fucecchio Firenze 50054",
    "addr:housenumber":"112",
    "addr:postcode":"50054;50054",
    "addr:street":"Vle Colombo",
    "iso:country":"IT",
    "sg:address":"Vle Colombo 112 50054 Fucecchio",
    "sg:city":"Fucecchio",
    "sg:orig_category":"Ladies' Shoes",
    "sg:phone":"+39 0571 261185",
    "sg:postcode":"50054",
    "sg:province":"Firenze",
    "sg:website":"www.pellegrinishoes.com",
    "wof:name":"Pellegrini G.b. Shoes Srl",
    "wof:placetype":"venue"
},
  "geometry": {"coordinates":[11.256902,43.768734],"type":"Point"}
}