{
  "type": "Feature",
  "properties": {
    "addr:full":"34, Via Garziere 36010 Zane' Vicenza 36010",
    "addr:postcode":"36010;36010",
    "addr:street":"Via Garziere",
    "iso:country":"IT",
    "sg:address":"34, Via Garziere 36010 Zane'",
    "sg:classifiers":[
        {
            "category":"Manufacturing",
            "subcategory":"Rubber & Plastics",
            "type":"Manufacturing & Wholesale Goods"
        }
    ],
    "sg:phone":"+39 0445 314104",
    "sg:postcode":"36010",
    "sg:province":"Vicenza",
    "wof:name":"A.t.i.p.",
    "wof:placetype":"venue"
},
  "geometry": {"coordinates":[11.4639720917,45.7130699158],"type":"Point"}
}