{
  "type": "Feature",
  "properties": {
    "addr:full":"5, Via Oristano 20128 Milano Milano Milano 20128",
    "addr:postcode":"20128;20128",
    "addr:street":"Via Oristano",
    "iso:country":"IT",
    "sg:address":"5, Via Oristano 20128 Milano",
    "sg:city":"Milano",
    "sg:classifiers":[
        {
            "category":"Food & Beverages",
            "subcategory":"Groceries & Convenience Stores",
            "type":"Retail Goods"
        }
    ],
    "sg:phone":"+39 39022571069",
    "sg:postcode":"20128",
    "sg:province":"Milano",
    "sg:tags":[
        "product",
        "related"
    ],
    "wof:name":"Poli Giulia Di Vergani Giacomo & Luigi (s.n.c.)",
    "wof:placetype":"venue"
},
  "geometry": {"coordinates":[9.2291212082,45.5043869019],"type":"Point"}
}