{
  "type": "Feature",
  "properties": {
    "iso:country":"IT",
    "sg:address":"87100 Cosenza",
    "sg:city":"Cosenza",
    "sg:classifiers":[
        {
            "category":"Bars & Pubs",
            "subcategory":"Champagne Bar",
            "type":"Food & Drink"
        }
    ],
    "sg:phone":"+39 0984 969582",
    "sg:postcode":"87100",
    "sg:province":"Cosenza",
    "sg:tags":[
        "caffe'",
        "e"
    ],
    "wof:name":"Bosco R. & Figlio Snc",
    "wof:placetype":"venue"
},
  "geometry": {"coordinates":[16.287521,39.266655],"type":"Point"}
}