{
  "type": "Feature",
  "properties": {
    "iso:country":"IT",
    "sg:address":"3/c, Via I Maggio 12023 Caraglio",
    "sg:city":"Caraglio",
    "sg:classifiers":[
        {
            "category":"Autos & Motor Vehicles",
            "subcategory":"Automobile Sales",
            "type":"Retail Goods"
        }
    ],
    "sg:phone":"+39 0171 817441",
    "sg:postcode":"12023",
    "sg:province":"Cuneo",
    "sg:tags":[
        "motor-cars"
    ],
    "wof:name":"Solaria Special Cars Di Otta E Dutto S.n.c.",
    "wof:placetype":"venue"
},
  "geometry": {"coordinates":[7.4230380058,44.4319725037],"type":"Point"}
}