{
  "type": "Feature",
  "properties": {
    "addr:full":"10, Via Volpe Gioacchino Ospedaletto 56121 Pisa Pisa Pisa 56121",
    "addr:postcode":"56121;56121",
    "addr:street":"Via Volpe Gioacchino",
    "iso:country":"IT",
    "sg:address":"10, Via Volpe Gioacchino Ospedaletto 56121 Pisa",
    "sg:city":"Pisa",
    "sg:classifiers":[
        {
            "category":"Professional",
            "subcategory":"Computer Services",
            "type":"Services"
        }
    ],
    "sg:phone":"+39 39050984449",
    "sg:postcode":"56121",
    "sg:province":"Pisa",
    "sg:tags":[
        "information",
        "technology"
    ],
    "wof:name":"Caribel Programmazione (s.r.l.)",
    "wof:placetype":"venue"
},
  "geometry": {"coordinates":[10.396585,43.716137],"type":"Point"}
}