{
  "type": "Feature",
  "properties": {
    "addr:full":"70123 Bari Bari Bari 70123",
    "addr:postcode":"70123;70123",
    "iso:country":"IT",
    "sg:address":"70123 Bari",
    "sg:city":"Bari",
    "sg:orig_category":"Prodotti E Manufatti In Materie Plastiche. Forniture Per Edilizia E Lavori Pubblici",
    "sg:phone":"+39 080 531 3782",
    "sg:postcode":"70123",
    "sg:province":"Bari",
    "wof:name":"Tre Z Plast Srl",
    "wof:placetype":"venue"
},
  "geometry": {"coordinates":[16.8035945892,41.1079902649],"type":"Point"}
}