{
  "type": "Feature",
  "properties": {
    "iso:country":"IT",
    "sg:address":"13814 Pollone",
    "sg:city":"Pollone",
    "sg:orig_category":"Ortopedia - Articoli",
    "sg:phone":"+39 015 256 3008",
    "sg:postcode":"13814",
    "sg:province":"Biella",
    "wof:name":"Demarta Virginio Sas",
    "wof:placetype":"venue"
},
  "geometry": {"coordinates":[8.000951,45.587208],"type":"Point"}
}