{
  "type": "Feature",
  "properties": {
    "addr:full":"51016 Montecatini Terme Pistoia 51016",
    "addr:postcode":"51016;51016",
    "iso:country":"IT",
    "sg:address":"51016 Montecatini Terme",
    "sg:orig_category":"Ospedali E Servizi Sanitari",
    "sg:phone":"+39 0572 767578",
    "sg:postcode":"51016",
    "sg:province":"Pistoia",
    "wof:name":"Sodini Annamaria",
    "wof:placetype":"venue"
},
  "geometry": {"coordinates":[10.758413,43.89146],"type":"Point"}
}