{
  "type": "Feature",
  "properties": {
    "iso:country":"IT",
    "sg:address":"Via Alessandria 53 14049 Nizza Monferrato",
    "sg:city":"Nizza Monferrato",
    "sg:classifiers":[
        {
            "category":"Bars & Pubs",
            "subcategory":"Sports Bar",
            "type":"Food & Drink"
        }
    ],
    "sg:phone":"+39 0141 793582",
    "sg:postcode":"14049",
    "sg:province":"Asti",
    "sg:tags":[
        "packaging",
        "manufacturing",
        "customized"
    ],
    "sg:website":"www.comalsrl.com",
    "wof:name":"Comal S.r.l.",
    "wof:placetype":"venue"
},
  "geometry": {"coordinates":[8.3086423874,44.8265953064],"type":"Point"}
}