{
  "type": "Feature",
  "properties": {
    "iso:country":"IT",
    "sg:address":"13, Via Dei Mille 20098 San Giuliano Milanese",
    "sg:city":"San Giuliano Milanese",
    "sg:classifiers":[
        {
            "category":"Manufacturing",
            "subcategory":"Glass & Minerals",
            "type":"Manufacturing & Wholesale Goods"
        }
    ],
    "sg:phone":"+39 02 9824 0849",
    "sg:postcode":"20098",
    "sg:province":"Milano",
    "wof:name":"Industrialvetro Bagno S.r.l.",
    "wof:placetype":"venue"
},
  "geometry": {"coordinates":[9.297728,45.392414],"type":"Point"}
}