{
  "type": "Feature",
  "properties": {
    "addr:full":"25, Via Campia 84012 Angri Angri Salerno 84012",
    "addr:postcode":"84012;84012",
    "addr:street":"Via Campia",
    "iso:country":"IT",
    "sg:address":"25, Via Campia 84012 Angri",
    "sg:city":"Angri",
    "sg:classifiers":[
        {
            "category":"Bars & Pubs",
            "subcategory":"Nightclub",
            "type":"Food & Drink"
        }
    ],
    "sg:phone":"+39 081 513 2864",
    "sg:postcode":"84012",
    "sg:province":"Salerno",
    "sg:tags":[
        "cake",
        "bread"
    ],
    "wof:name":"F.lli Tedesco Di Tedesco Raffaele E C. S.n.c.",
    "wof:placetype":"venue"
},
  "geometry": {"coordinates":[14.560987,40.739273],"type":"Point"}
}