{
  "type": "Feature",
  "properties": {
    "iso:country":"IT",
    "sg:address":"44, Via Cicella 80040 San Gennaro Vesuviano",
    "sg:city":"San Gennaro Vesuviano",
    "sg:classifiers":[
        {
            "category":"Real Estate",
            "subcategory":"Architect",
            "type":"Services"
        }
    ],
    "sg:phone":"+39 081 528 6958",
    "sg:postcode":"80040",
    "sg:province":"Napoli",
    "sg:tags":[
        "textile",
        "clothing"
    ],
    "wof:name":"Maris Confezioni Srl",
    "wof:placetype":"venue"
},
  "geometry": {"coordinates":[14.522182,40.863361],"type":"Point"}
}