{
  "type": "Feature",
  "properties": {
    "iso:country":"IT",
    "sg:address":"Via Airauda 12 10044 Pianezza",
    "sg:city":"Pianezza",
    "sg:orig_category":"Resistance Measuring Devices For Contact Materials",
    "sg:phone":"+39 011 966 4038",
    "sg:postcode":"10044",
    "sg:province":"Torino",
    "sg:website":"www.ceast.com",
    "wof:name":"Compagnia Europea Apparecchi Scientifici Torino Ceast Spa",
    "wof:placetype":"venue"
},
  "geometry": {"coordinates":[7.560952,45.096771],"type":"Point"}
}