{
  "type": "Feature",
  "properties": {
    "addr:full":"V. Rolandino Maffei37050 Vallese Di Oppeano Oppeano Verona 37050",
    "addr:housenumber":"maffei37050;oppeano",
    "addr:postcode":"37050",
    "addr:street":"V. Rolandino",
    "iso:country":"IT",
    "sg:address":"V. Rolandino Maffei37050 Vallese Di Oppeano",
    "sg:city":"Oppeano",
    "sg:classifiers":[
        {
            "category":"Real Estate",
            "subcategory":"Surveying",
            "type":"Services"
        }
    ],
    "sg:phone":"+39 39045548003",
    "sg:postcode":"37050",
    "sg:province":"Verona",
    "sg:tags":[
        "equipment",
        "material",
        "good",
        "-",
        "handling"
    ],
    "sg:website":"http://www.perinellirulli.com",
    "wof:name":"Perinelli Rulli Srl",
    "wof:placetype":"venue"
},
  "geometry": {"coordinates":[10.991748,45.438366],"type":"Point"}
}