{
  "type": "Feature",
  "properties": {
    "addr:full":"20154 Milano Milano Milano 20154",
    "addr:postcode":"20154;20154",
    "iso:country":"IT",
    "sg:address":"20154 Milano",
    "sg:city":"Milano",
    "sg:orig_category":"Servizi Per Aziende, Manifestazioni E Supporto Agli Scambi Commerciali. Ambasciate Ed Enti Internazionali",
    "sg:phone":"+39 02 331 1122",
    "sg:postcode":"20154",
    "sg:province":"Milano",
    "wof:name":"O.r.i.a. Organizzazione Rapporti Internazionali Artistici Snc",
    "wof:placetype":"venue"
},
  "geometry": {"coordinates":[9.165394,45.481529],"type":"Point"}
}