{
  "type": "Feature",
  "properties": {
    "addr:full":"20129 Milano Milano Milano 20129",
    "addr:postcode":"20129;20129",
    "iso:country":"IT",
    "sg:address":"20129 Milano",
    "sg:city":"Milano",
    "sg:orig_category":"Forniture Per Abbigliamento E Pelletterie. Complementi Di Arredamento",
    "sg:postcode":"20129",
    "sg:province":"Milano",
    "wof:name":"Passamaneria Di G. E T. Pavani & C. (s.a.s.)",
    "wof:placetype":"venue"
},
  "geometry": {"coordinates":[9.2092790604,45.4741744995],"type":"Point"}
}