{
  "type": "Feature",
  "properties": {
    "iso:country":"IT",
    "sg:address":"Via Del Lazzaretto 52 20049 Concorezzo",
    "sg:city":"Concorezzo",
    "sg:classifiers":[
        {
            "category":"Manufacturing",
            "subcategory":"Tools & Machinery",
            "type":"Manufacturing & Wholesale Goods"
        }
    ],
    "sg:phone":"+39 039 604 9853",
    "sg:postcode":"20049",
    "sg:province":"Milano",
    "sg:tags":[
        "machine",
        "cnc"
    ],
    "sg:website":"www.mexim.it",
    "wof:name":"Mexim Italia Srl",
    "wof:placetype":"venue"
},
  "geometry": {"coordinates":[9.335285,45.578915],"type":"Point"}
}