{
  "type": "Feature",
  "properties": {
    "iso:country":"IT",
    "sg:address":"25081 Bedizzole",
    "sg:city":"Bedizzole",
    "sg:orig_category":"Utensili Meccanici E Materiali",
    "sg:phone":"+39 030 687 1541",
    "sg:postcode":"25081",
    "sg:province":"Brescia",
    "wof:name":"Studio Gv Srl",
    "wof:placetype":"venue"
},
  "geometry": {"coordinates":[10.390179,45.508408],"type":"Point"}
}