{
  "type": "Feature",
  "properties": {
    "iso:country":"IT",
    "sg:address":"56012 Fornacette",
    "sg:city":"Fornacette",
    "sg:orig_category":"Non-classified Establishments",
    "sg:phone":"+39 0587 420190",
    "sg:postcode":"56012",
    "sg:province":"Pisa",
    "wof:name":"Marconcini",
    "wof:placetype":"venue"
},
  "geometry": {"coordinates":[10.527763,43.678822],"type":"Point"}
}