{
  "type": "Feature",
  "properties": {
    "iso:country":"IT",
    "sg:address":"27028 San Martino Siccomario",
    "sg:city":"San Martino Siccomario",
    "sg:orig_category":"Forniture Per Attivita' Commerciali Ed Artigianali",
    "sg:phone":"+39 0382 498056",
    "sg:postcode":"27028",
    "sg:province":"Pavia",
    "wof:name":"Seriprint Snc",
    "wof:placetype":"venue"
},
  "geometry": {"coordinates":[9.1339273453,45.1548118591],"type":"Point"}
}