{
  "type": "Feature",
  "properties": {
    "iso:country":"IT",
    "sg:address":"10036 Settimo Torinese",
    "sg:city":"Settimo Torinese",
    "sg:orig_category":"Articoli Da Regalo. Forniture Per Uffici. Regalistica Aziendale",
    "sg:phone":"+39 011 897 7734",
    "sg:postcode":"10036",
    "sg:province":"Torino",
    "wof:name":"Elle Erre S.r.l.",
    "wof:placetype":"venue"
},
  "geometry": {"coordinates":[7.731337,45.146053],"type":"Point"}
}