{
  "type": "Feature",
  "properties": {
    "addr:full":"06049 Spoleto Spoleto Perugia 06049",
    "addr:postcode":"06049;06049",
    "iso:country":"IT",
    "sg:address":"06049 Spoleto",
    "sg:city":"Spoleto",
    "sg:classifiers":[
        {
            "category":"Manufacturing",
            "subcategory":"Metals",
            "type":"Manufacturing & Wholesale Goods"
        }
    ],
    "sg:phone":"+39 0743 277059",
    "sg:postcode":"06049",
    "sg:province":"Perugia",
    "sg:tags":[
        "forming",
        "working",
        "welding"
    ],
    "wof:name":"Lainox Srl",
    "wof:placetype":"venue"
},
  "geometry": {"coordinates":[12.6905326843,42.7190284729],"type":"Point"}
}