{
  "type": "Feature",
  "properties": {
    "addr:full":"34128 Trieste Trieste Trieste 34128",
    "addr:postcode":"34128;34128",
    "iso:country":"IT",
    "sg:address":"34128 Trieste",
    "sg:city":"Trieste",
    "sg:orig_category":"Petroli, Gas E Combustibili. Materiali Edili",
    "sg:phone":"+39 040 570 8000",
    "sg:postcode":"34128",
    "sg:province":"Trieste",
    "wof:name":"Edilcem Srl",
    "wof:placetype":"venue"
},
  "geometry": {"coordinates":[13.8634338379,45.6416473389],"type":"Point"}
}