{
  "type": "Feature",
  "properties": {
    "addr:full":"20089 Rozzano Rozzano Milano 20089",
    "addr:postcode":"20089;20089",
    "iso:country":"IT",
    "sg:address":"20089 Rozzano",
    "sg:city":"Rozzano",
    "sg:orig_category":"Servizi E Lavori Per Arredamento E Industria Del Legno. Servizi E Lavori Per Edilizia E Lavori Pubblici",
    "sg:phone":"+39 02 824 2781",
    "sg:postcode":"20089",
    "sg:province":"Milano",
    "wof:name":"Pinetti Domenico",
    "wof:placetype":"venue"
},
  "geometry": {"coordinates":[9.149868,45.378216],"type":"Point"}
}