{
  "type": "Feature",
  "properties": {
    "addr:full":"1, Zona Industriale 86097 Sessano Del Molise Sessano del Molise Isernia 86097",
    "addr:housenumber":"1",
    "addr:postcode":"86097;86097",
    "addr:street":"Zona Industriale;Del Molise",
    "iso:country":"IT",
    "sg:address":"1, Zona Industriale 86097 Sessano Del Molise",
    "sg:city":"Sessano del Molise",
    "sg:classifiers":[
        {
            "category":"Manufacturing",
            "subcategory":"Paper Products",
            "type":"Manufacturing & Wholesale Goods"
        }
    ],
    "sg:phone":"+39 0865 930000",
    "sg:postcode":"86097",
    "sg:province":"Isernia",
    "sg:tags":[
        "cardboard"
    ],
    "wof:name":"Euro Tubi S.r.l.",
    "wof:placetype":"venue"
},
  "geometry": {"coordinates":[14.2308273315,41.5943336487],"type":"Point"}
}