{
  "type": "Feature",
  "properties": {
    "iso:country":"IT",
    "sg:address":"43100 Parma",
    "sg:city":"Fontana",
    "sg:orig_category":"Termotecnica E Riscaldamento, Apparecchiature E Servizi",
    "sg:phone":"+39 0521 674088",
    "sg:postcode":"43100",
    "sg:province":"Parma",
    "wof:name":"Lpv Caldaie Srl",
    "wof:placetype":"venue"
},
  "geometry": {"coordinates":[10.215752,44.606274],"type":"Point"}
}