{
  "type": "Feature",
  "properties": {
    "addr:full":"00040 Lanuvio Lanuvio Roma 00040",
    "addr:postcode":"00040;roma 00040",
    "iso:country":"IT",
    "sg:address":"00040 Lanuvio",
    "sg:city":"Lanuvio",
    "sg:orig_category":"Petroli, Gas E Combustibili",
    "sg:phone":"+39 06 937 4315",
    "sg:postcode":"00040",
    "sg:province":"Roma",
    "wof:name":"Franconi Ludovico",
    "wof:placetype":"venue"
},
  "geometry": {"coordinates":[12.6617298126,41.677406311],"type":"Point"}
}