{
  "type": "Feature",
  "properties": {
    "iso:country":"IT",
    "sg:address":"07014 Ozieri",
    "sg:city":"Ozieri",
    "sg:classifiers":[
        {
            "category":"Manufacturing",
            "subcategory":"Food",
            "type":"Manufacturing & Wholesale Goods"
        }
    ],
    "sg:phone":"+39 079 780425",
    "sg:postcode":"07014",
    "sg:province":"Sassari",
    "sg:tags":[
        "product"
    ],
    "wof:name":"Nieddu Antonino",
    "wof:placetype":"venue"
},
  "geometry": {"coordinates":[8.9466142654,40.6319541931],"type":"Point"}
}