{
  "type": "Feature",
  "properties": {
    "iso:country":"IT",
    "sg:address":"20052 Monza",
    "sg:city":"Monza",
    "sg:orig_category":"Macchine E Forniture Per Arredamento E Industria Del Legno. Utensili Meccanici E Materiali",
    "sg:phone":"+39 039 386961",
    "sg:postcode":"20052",
    "sg:province":"Milano",
    "sg:website":"http://www.finktools.com",
    "wof:name":"Fink Srl",
    "wof:placetype":"venue"
},
  "geometry": {"coordinates":[9.231892,45.543854],"type":"Point"}
}