{
  "type": "Feature",
  "properties": {
    "iso:country":"IT",
    "sg:address":"40050 Funo",
    "sg:city":"Funo",
    "sg:orig_category":"Macchine, Impianti Ed Attrezzature Per Abbigliamento E Pelletterie",
    "sg:phone":"+39 051 664 6198",
    "sg:postcode":"40050",
    "sg:province":"Bologna",
    "wof:name":"Eurmeccanica Shoes (s.r.l.)",
    "wof:placetype":"venue"
},
  "geometry": {"coordinates":[11.366193,44.609528],"type":"Point"}
}