{
  "type": "Feature",
  "properties": {
    "iso:country":"IT",
    "sg:address":"Via Delle Calandre 11 50041 Calenzano",
    "sg:city":"Calenzano",
    "sg:classifiers":[
        {
            "category":"Shopping",
            "subcategory":"Clothing, Apparel, & Fashions",
            "type":"Retail Goods"
        }
    ],
    "sg:phone":"+39 055 887 9155",
    "sg:postcode":"50041",
    "sg:province":"Firenze",
    "sg:tags":[
        "clothing",
        "fabric"
    ],
    "wof:name":"Coiano Tessile Srl",
    "wof:placetype":"venue"
},
  "geometry": {"coordinates":[11.161922,43.847622],"type":"Point"}
}