{
  "type": "Feature",
  "properties": {
    "iso:country":"IT",
    "sg:address":"59015 Carmignano",
    "sg:city":"Carmignano",
    "sg:orig_category":"Tessuti E Stoffe. Forniture Per Attivita' Industriali",
    "sg:phone":"+39 055 871 9346",
    "sg:postcode":"59015",
    "sg:province":"Prato",
    "wof:name":"Mp Spa",
    "wof:placetype":"venue"
},
  "geometry": {"coordinates":[11.060027,43.803223],"type":"Point"}
}