{
  "type": "Feature",
  "properties": {
    "addr:full":"55010 Capannori Capannori Lucca 55010",
    "addr:postcode":"55010;55010",
    "iso:country":"IT",
    "sg:address":"55010 Capannori",
    "sg:city":"Capannori",
    "sg:classifiers":[
        {
            "category":"Wholesale",
            "subcategory":"Machinery & Supplies",
            "type":"Manufacturing & Wholesale Goods"
        }
    ],
    "sg:phone":"+39 0583 429429",
    "sg:postcode":"55010",
    "sg:province":"Lucca",
    "sg:tags":[
        "activities",
        "industrial"
    ],
    "sg:website":"http://www.itechsite.com",
    "wof:name":"Elfi Srl",
    "wof:placetype":"venue"
},
  "geometry": {"coordinates":[10.579061,43.857315],"type":"Point"}
}