{
  "type": "Feature",
  "properties": {
    "iso:country":"IT",
    "sg:address":"6, Via Rovereto 00198 Roma",
    "sg:city":"Roma",
    "sg:classifiers":[
        {
            "category":"Manufacturing",
            "subcategory":"Printing",
            "type":"Manufacturing & Wholesale Goods"
        }
    ],
    "sg:phone":"+39 39068552649",
    "sg:postcode":"00198",
    "sg:province":"Roma",
    "sg:tags":[
        "publishing"
    ],
    "wof:name":"Progest (s.r.l.)",
    "wof:placetype":"venue"
},
  "geometry": {"coordinates":[12.5126485825,41.9199104309],"type":"Point"}
}