{
  "type": "Feature",
  "properties": {
    "addr:full":"24, Via Carrara Angelo 16147 Genova Genova Genova 16147",
    "addr:postcode":"16147;16147",
    "addr:street":"Via Carrara Angelo",
    "iso:country":"IT",
    "sg:address":"24, Via Carrara Angelo 16147 Genova",
    "sg:city":"Genova",
    "sg:classifiers":[
        {
            "category":"Autos & Motor Vehicles",
            "subcategory":"Boat Sales",
            "type":"Retail Goods"
        }
    ],
    "sg:phone":"+39 010 373 0779",
    "sg:postcode":"16147",
    "sg:province":"Genova",
    "wof:name":"Wartsila Navim Diesel (s.r.l.)",
    "wof:placetype":"venue"
},
  "geometry": {"coordinates":[8.933989,44.407063],"type":"Point"}
}