{
  "type": "Feature",
  "properties": {
    "iso:country":"IT",
    "sg:address":"10071 Borgaro Torinese",
    "sg:city":"Borgaro Torinese",
    "sg:orig_category":"Vellutazione",
    "sg:phone":"+39 011 262 1714",
    "sg:postcode":"10071",
    "sg:province":"Torino",
    "wof:name":"C.m.a. Sas",
    "wof:placetype":"venue"
},
  "geometry": {"coordinates":[7.692804,45.134525],"type":"Point"}
}