{
  "type": "Feature",
  "properties": {
    "iso:country":"IT",
    "sg:address":"25125 Brescia",
    "sg:city":"Brescia",
    "sg:orig_category":"Servizi E Lavori Per Edilizia E Lavori Pubblici",
    "sg:phone":"+39 030 242 2954",
    "sg:postcode":"25125",
    "sg:province":"Brescia",
    "wof:name":"Zorzi Luciano",
    "wof:placetype":"venue"
},
  "geometry": {"coordinates":[10.205365,45.529339],"type":"Point"}
}