{
  "type": "Feature",
  "properties": {
    "addr:full":"48, Via Formica Gian Battista 34170 Gorizia Gorizia Gorizia 34170",
    "addr:postcode":"34170;34170",
    "addr:street":"Via Formica Gian Battista",
    "iso:country":"IT",
    "sg:address":"48, Via Formica Gian Battista 34170 Gorizia",
    "sg:city":"Gorizia",
    "sg:classifiers":[
        {
            "category":"Manufacturing",
            "subcategory":"Metals",
            "type":"Manufacturing & Wholesale Goods"
        }
    ],
    "sg:phone":"+39 0481 535024",
    "sg:postcode":"34170",
    "sg:province":"Gorizia",
    "sg:tags":[
        "metallurgy",
        "metalworking"
    ],
    "wof:name":"Cantarin F.lli S.r.l.",
    "wof:placetype":"venue"
},
  "geometry": {"coordinates":[13.6215457916,45.9413032532],"type":"Point"}
}