{
  "type": "Feature",
  "properties": {
    "addr:full":"00042 Anzio Anzio Roma 00042",
    "addr:postcode":"00042;roma 00042",
    "iso:country":"IT",
    "sg:address":"00042 Anzio",
    "sg:city":"Anzio",
    "sg:orig_category":"Palificazioni, Fondazioni E Consolidamenti",
    "sg:phone":"+39 06 981 9436",
    "sg:postcode":"00042",
    "sg:province":"Roma",
    "wof:name":"Sit Snc",
    "wof:placetype":"venue"
},
  "geometry": {"coordinates":[12.6101398468,41.5113487244],"type":"Point"}
}