{
  "type": "Feature",
  "properties": {
    "addr:full":"45, Via Valcuvia 21033 Cittiglio Cittiglio Varese 21033",
    "addr:postcode":"21033;21033",
    "addr:street":"Via Valcuvia",
    "iso:country":"IT",
    "sg:address":"45, Via Valcuvia 21033 Cittiglio",
    "sg:city":"Cittiglio",
    "sg:classifiers":[
        {
            "category":"Real Estate",
            "subcategory":"Architect",
            "type":"Services"
        }
    ],
    "sg:phone":"+39 0332 610179",
    "sg:postcode":"21033",
    "sg:province":"Varese",
    "sg:tags":[
        "textile",
        "clothing"
    ],
    "wof:name":"Di Vivo Antonella",
    "wof:placetype":"venue"
},
  "geometry": {"coordinates":[8.684959,45.893269],"type":"Point"}
}