{
  "type": "Feature",
  "properties": {
    "addr:full":"16142 Genova Genova Genova 16142",
    "addr:postcode":"16142;16142",
    "iso:country":"IT",
    "sg:address":"16142 Genova",
    "sg:city":"Genova",
    "sg:orig_category":"Caratteri Trasferibili E Da Applicare",
    "sg:phone":"+39 010 873899",
    "sg:postcode":"16142",
    "sg:province":"Genova",
    "wof:name":"P. Zeta Srl",
    "wof:placetype":"venue"
},
  "geometry": {"coordinates":[8.960798,44.418846],"type":"Point"}
}