{
  "type": "Feature",
  "properties": {
    "iso:country":"IT",
    "sg:address":"28, Via Della Chimica 41042 Fiorano Modenese",
    "sg:city":"Fiorano Modenese",
    "sg:classifiers":[
        {
            "category":"Professional",
            "subcategory":"Engineering",
            "type":"Services"
        }
    ],
    "sg:phone":"+39 0536 920490",
    "sg:postcode":"41042",
    "sg:province":"Modena",
    "sg:tags":[
        "machine",
        "-",
        "mechanical"
    ],
    "wof:name":"Nbp (s.r.l.)",
    "wof:placetype":"venue"
},
  "geometry": {"coordinates":[10.839223,44.539059],"type":"Point"}
}