{
  "type": "Feature",
  "properties": {
    "iso:country":"IT",
    "sg:address":"20, Via Vecchia Per Monza 20056 Trezzo Sull'adda",
    "sg:classifiers":[
        {
            "category":"Wholesale",
            "subcategory":"Machinery & Supplies",
            "type":"Manufacturing & Wholesale Goods"
        }
    ],
    "sg:phone":"+39 02 9096 4566",
    "sg:postcode":"20056",
    "sg:province":"Milano",
    "sg:tags":[
        "equipment",
        "-",
        "instrument",
        "measurement"
    ],
    "wof:name":"Wunder Sa.bi. S.r.l.",
    "wof:placetype":"venue"
},
  "geometry": {"coordinates":[9.513161,45.606476],"type":"Point"}
}