{
  "type": "Feature",
  "properties": {
    "iso:country":"IT",
    "sg:address":"00186 Roma",
    "sg:city":"Roma",
    "sg:orig_category":"Nautica. Accessori Dei Mezzi Di Trasporto",
    "sg:phone":"+39 06 361 2091",
    "sg:postcode":"00186",
    "sg:province":"Roma",
    "sg:website":"http://www.ilmare.com",
    "wof:name":"Il Mare Srl",
    "wof:placetype":"venue"
},
  "geometry": {"coordinates":[12.476027,41.908585],"type":"Point"}
}