{
  "type": "Feature",
  "properties": {
    "addr:full":"20035 Lissone Lissone Milano 20035",
    "addr:postcode":"20035;20035",
    "iso:country":"IT",
    "sg:address":"20035 Lissone",
    "sg:city":"Lissone",
    "sg:orig_category":"Minuterie Metalliche E Ferramenta",
    "sg:phone":"+39 039 462362",
    "sg:postcode":"20035",
    "sg:province":"Milano",
    "wof:name":"Sigma Dott. Ing. U.m. Spezia (s.a.s.)",
    "wof:placetype":"venue"
},
  "geometry": {"coordinates":[9.1886615753,45.4793663025],"type":"Point"}
}