{
  "type": "Feature",
  "properties": {
    "iso:country":"IT",
    "sg:address":"36014 Santorso",
    "sg:city":"Santorso",
    "sg:orig_category":"Studi E Consulenze Tecniche E Industriali. Assicurazioni E Servizi Assicurativi. Consulenze Tecniche, Amministrative E Perizie",
    "sg:phone":"+39 0445 540075",
    "sg:postcode":"36014",
    "sg:province":"Vicenza",
    "wof:name":"S.t.r.a.d.a. Srl",
    "wof:placetype":"venue"
},
  "geometry": {"coordinates":[11.387869,45.727139],"type":"Point"}
}