{
  "type": "Feature",
  "properties": {
    "addr:full":"40121 Bologna Bologna Bologna 40121",
    "addr:postcode":"40121;40121",
    "iso:country":"IT",
    "sg:address":"40121 Bologna",
    "sg:city":"Bologna",
    "sg:orig_category":"Tempo Libero - Articoli E Forniture. Regalistica Aziendale",
    "sg:phone":"+39 051 261103",
    "sg:postcode":"40121",
    "sg:province":"Bologna",
    "wof:name":"Coin Art Division (s.r.l.)",
    "wof:placetype":"venue"
},
  "geometry": {"coordinates":[11.656878,44.977913],"type":"Point"}
}