{
  "type": "Feature",
  "properties": {
    "addr:full":"18, V. Millelire -, 20147 Milano Milano Milano 20147",
    "addr:housenumber":"18",
    "addr:postcode":"20147;20147",
    "addr:street":"V. Millelire",
    "iso:country":"IT",
    "sg:address":"18, V. Millelire -, 20147 Milano",
    "sg:city":"Milano",
    "sg:classifiers":[
        {
            "category":"Banks & Credit Unions",
            "subcategory":"Financial Services",
            "type":"Services"
        }
    ],
    "sg:phone":"+39 02 4871 2450",
    "sg:postcode":"20147",
    "sg:province":"Milano",
    "sg:tags":[
        "banking",
        "finance",
        "insurance"
    ],
    "sg:website":"http://www.paginegialle.it/",
    "wof:name":"Studio Rossi Maria Elena",
    "wof:placetype":"venue"
},
  "geometry": {"coordinates":[9.1283226013,45.4663009644],"type":"Point"}
}