{
  "type": "Feature",
  "properties": {
    "iso:country":"IT",
    "sg:address":"50142 Firenze",
    "sg:city":"Firenze",
    "sg:orig_category":"Servizi Per Lo Sport E Il Tempo Libero. Servizi Ausiliari Dei Mezzi Di Trasporto",
    "sg:phone":"+39 055 754339",
    "sg:postcode":"50142",
    "sg:province":"Firenze",
    "wof:name":"Il Cerchio (s.n.c.)",
    "wof:placetype":"venue"
},
  "geometry": {"coordinates":[11.127742,43.759525],"type":"Point"}
}