{
  "type": "Feature",
  "properties": {
    "iso:country":"IT",
    "sg:address":"33100 Udine",
    "sg:city":"Udine",
    "sg:orig_category":"Banche E Servizi Finanziari",
    "sg:phone":"+39 0432 245511",
    "sg:postcode":"33100",
    "sg:province":"Udine",
    "sg:website":"http://www.mediocredito.fvg.it",
    "wof:name":"Mediocredito Del Friuli Venezia Giulia Spa",
    "wof:placetype":"venue"
},
  "geometry": {"coordinates":[13.208191,46.090508],"type":"Point"}
}