{
  "type": "Feature",
  "properties": {
    "addr:full":"Via Duomo 20; Nardo; 73048 Lecce 73048",
    "addr:housenumber":"20",
    "addr:postcode":"73048;73048",
    "addr:street":"Via Duomo;Nardo",
    "iso:country":"IT",
    "sg:address":"Via Duomo 20; Nardo; 73048",
    "sg:classifiers":[
        {
            "category":"Banks & Credit Unions",
            "subcategory":"Bank",
            "type":"Services"
        }
    ],
    "sg:phone":"+39 0833 811013",
    "sg:postcode":"73048",
    "sg:province":"Lecce",
    "wof:name":"Banca Di Roma",
    "wof:placetype":"venue"
},
  "geometry": {"coordinates":[18.029734,40.180508],"type":"Point"}
}