{
  "type": "Feature",
  "properties": {
    "iso:country":"IT",
    "sg:address":"20049 Concorezzo",
    "sg:city":"Concorezzo",
    "sg:orig_category":"Servizi E Lavori Per Abbigliamento E Pelletterie",
    "sg:phone":"+39 039 604 0865",
    "sg:postcode":"20049",
    "sg:province":"Milano",
    "wof:name":"Texservice Srl",
    "wof:placetype":"venue"
},
  "geometry": {"coordinates":[9.368515,45.608009],"type":"Point"}
}