{
  "type": "Feature",
  "properties": {
    "iso:country":"IT",
    "sg:address":"16015 Soglio",
    "sg:orig_category":"Marmo, Pietre Ed Affini",
    "sg:phone":"+39 0185 334024",
    "sg:postcode":"16015",
    "sg:province":"Genova",
    "wof:name":"Italardesia Srl",
    "wof:placetype":"venue"
},
  "geometry": {"coordinates":[8.869603,44.415802],"type":"Point"}
}