{
  "type": "Feature",
  "properties": {
    "addr:full":"38030 Ziano Di Fiemme Ziano di Fiemme Trento 38030",
    "addr:postcode":"38030;38030",
    "addr:street":"Di Fiemme Trento",
    "iso:country":"IT",
    "sg:address":"38030 Ziano Di Fiemme",
    "sg:city":"Ziano di Fiemme",
    "sg:orig_category":"Arredamenti - Produzione E Ingrosso",
    "sg:phone":"+39 0462 571255",
    "sg:postcode":"38030",
    "sg:province":"Trento",
    "wof:name":"Arredamenti Zorzi Di Zorzi Luigi & C. Snc",
    "wof:placetype":"venue"
},
  "geometry": {"coordinates":[11.553823,46.282318],"type":"Point"}
}