{
  "type": "Feature",
  "properties": {
    "iso:country":"IT",
    "sg:address":"7, Ctr. Casale 65010 Nocciano",
    "sg:city":"Nocciano",
    "sg:classifiers":[
        {
            "category":"Food & Beverages",
            "subcategory":"Groceries & Convenience Stores",
            "type":"Retail Goods"
        }
    ],
    "sg:phone":"+39 39085847345",
    "sg:postcode":"65010",
    "sg:province":"Pescara",
    "sg:tags":[
        "drink"
    ],
    "sg:website":"http://www.nestorebosco.com",
    "wof:name":"Bosco Nestore & C. Snc",
    "wof:placetype":"venue"
},
  "geometry": {"coordinates":[14.214094,42.464825],"type":"Point"}
}