{
  "type": "Feature",
  "properties": {
    "iso:country":"IT",
    "sg:address":"Via Industria 33 41100 Modena",
    "sg:city":"Modena",
    "sg:classifiers":[
        {
            "category":"Wholesale",
            "subcategory":"Farm Supplies",
            "type":"Manufacturing & Wholesale Goods"
        }
    ],
    "sg:phone":"+39 059 284000",
    "sg:postcode":"41100",
    "sg:province":"Modena",
    "sg:tags":[
        "agricultural",
        "part",
        "spare",
        "machinery",
        "accessory"
    ],
    "sg:website":"www.gbricambi.it",
    "wof:name":"G.b. Ricambi Spa",
    "wof:placetype":"venue"
},
  "geometry": {"coordinates":[10.92522,44.647079],"type":"Point"}
}