{
  "type": "Feature",
  "properties": {
    "addr:full":"Via Toscana 42-44 50052 Certaldo Certaldo Firenze 50052",
    "addr:housenumber":"42-44",
    "addr:postcode":"50052;50052",
    "addr:street":"Via Toscana",
    "iso:country":"IT",
    "sg:address":"Via Toscana 42-44 50052 Certaldo",
    "sg:city":"Certaldo",
    "sg:classifiers":[
        {
            "category":"Home & Garden",
            "subcategory":"Home Furnishings",
            "type":"Retail Goods"
        }
    ],
    "sg:phone":"+39 0571 652121",
    "sg:postcode":"50052",
    "sg:province":"Firenze",
    "sg:tags":[
        "bathroom",
        "wc",
        "fitting"
    ],
    "sg:website":"www.treesseci.it",
    "wof:name":"Treesseci Srl",
    "wof:placetype":"venue"
},
  "geometry": {"coordinates":[11.03678,43.554775],"type":"Point"}
}