{
  "type": "Feature",
  "properties": {
    "iso:country":"IT",
    "sg:address":"92010 Realmonte",
    "sg:city":"Realmonte",
    "sg:orig_category":"Antiquariato",
    "sg:phone":"+39 340 656 633",
    "sg:postcode":"92010",
    "sg:province":"Agrigento",
    "wof:name":"Schembri Maurizio",
    "wof:placetype":"venue"
},
  "geometry": {"coordinates":[13.422656,37.335606],"type":"Point"}
}