{
  "type": "Feature",
  "properties": {
    "iso:country":"IT",
    "sg:address":"18, Via Coronata 16152 Genova",
    "sg:city":"Genova",
    "sg:classifiers":[
        {
            "category":"Autos & Motor Vehicles",
            "subcategory":"Automobile Sales",
            "type":"Retail Goods"
        }
    ],
    "sg:phone":"+39 010 651 9651",
    "sg:postcode":"16152",
    "sg:province":"Genova",
    "sg:tags":[
        "equipment",
        "transport"
    ],
    "wof:name":"Ceab Piccone Sas I Brancatelli C. & C.",
    "wof:placetype":"venue"
},
  "geometry": {"coordinates":[8.876612,44.422924],"type":"Point"}
}