{
  "type": "Feature",
  "properties": {
    "iso:country":"IT",
    "sg:address":"80141 Napoli",
    "sg:city":"Napoli",
    "sg:orig_category":"Medici. Assicurazioni E Servizi Assicurativi. Avvocati, Notai E Servizi Legali. Professionisti - Studi E Servizi Ed Associazioni Di Interesse Aziendale",
    "sg:phone":"+39 081 595 5338",
    "sg:postcode":"80141",
    "sg:province":"Napoli",
    "wof:name":"Fati Sergio",
    "wof:placetype":"venue"
},
  "geometry": {"coordinates":[14.2567472458,40.8690872192],"type":"Point"}
}