{
  "type": "Feature",
  "properties": {
    "addr:full":"16011 Arenzano Arenzano Genova 16011",
    "addr:postcode":"16011;16011",
    "iso:country":"IT",
    "sg:address":"16011 Arenzano",
    "sg:city":"Arenzano",
    "sg:orig_category":"Prodotti Chimici Di Base. Ospedali E Servizi Sanitari",
    "sg:phone":"+39 010 913 0292",
    "sg:postcode":"16011",
    "sg:province":"Genova",
    "wof:name":"Esse Tre Srl",
    "wof:placetype":"venue"
},
  "geometry": {"coordinates":[8.6626930237,44.4045524597],"type":"Point"}
}