{
  "type": "Feature",
  "properties": {
    "addr:full":"03100 Frosinone Frosinone Frosinone 03100",
    "addr:postcode":"03100;03100",
    "iso:country":"IT",
    "sg:address":"03100 Frosinone",
    "sg:city":"Frosinone",
    "sg:classifiers":[
        {
            "category":"Banks & Credit Unions",
            "subcategory":"Financial Services",
            "type":"Services"
        }
    ],
    "sg:phone":"+39 0775 292040",
    "sg:postcode":"03100",
    "sg:province":"Frosinone",
    "sg:tags":[
        "articles",
        "product",
        "plastics",
        "industry",
        "work",
        "plastic"
    ],
    "wof:name":"Salvastecno",
    "wof:placetype":"venue"
},
  "geometry": {"coordinates":[13.342795372,41.6396331787],"type":"Point"}
}