{
  "type": "Feature",
  "properties": {
    "addr:full":"27100 Pavia Pavia Pavia 27100",
    "addr:postcode":"27100;27100",
    "iso:country":"IT",
    "sg:address":"27100 Pavia",
    "sg:city":"Pavia",
    "sg:orig_category":"Geologia, Geotecnica E Topografia - Studi E Servizi",
    "sg:phone":"+39 0382 579783",
    "sg:postcode":"27100",
    "sg:province":"Pavia",
    "wof:name":"Studio Geologico Associato Dr. Geol. G. Nascimbene - Dr. Geol. O. Ragni",
    "wof:placetype":"venue"
},
  "geometry": {"coordinates":[9.182778,45.223866],"type":"Point"}
}