{
  "type": "Feature",
  "properties": {
    "addr:full":"15076 Ovada Ovada Alessandria 15076",
    "addr:postcode":"15076;15076",
    "iso:country":"IT",
    "sg:address":"15076 Ovada",
    "sg:city":"Ovada",
    "sg:orig_category":"Marmo, Pietre Ed Affini",
    "sg:phone":"+39 0143 81073",
    "sg:postcode":"15076",
    "sg:province":"Alessandria",
    "sg:website":"http://www.marmiarata.com",
    "wof:name":"Marmi Arata Giobatta Di Arata G.d. & C. Snc",
    "wof:placetype":"venue"
},
  "geometry": {"coordinates":[8.601741,44.619705],"type":"Point"}
}