{
  "type": "Feature",
  "properties": {
    "iso:country":"IT",
    "sg:address":"36071 Arzignano",
    "sg:city":"Arzignano",
    "sg:orig_category":"Calzature, Pelletterie E Pelli",
    "sg:phone":"+39 0444 450266",
    "sg:postcode":"36071",
    "sg:province":"Vicenza",
    "wof:name":"B.p. Di Benetti Pierino & C. Sas",
    "wof:placetype":"venue"
},
  "geometry": {"coordinates":[11.363189,45.501377],"type":"Point"}
}