{
  "type": "Feature",
  "properties": {
    "iso:country":"IT",
    "sg:address":"20091 Bresso",
    "sg:city":"Bresso",
    "sg:orig_category":"Prodotti Vari In Metallo",
    "sg:phone":"+39 02 610 0304",
    "sg:postcode":"20091",
    "sg:province":"Milano",
    "wof:name":"Mariani Fratelli (s.p.a.)",
    "wof:placetype":"venue"
},
  "geometry": {"coordinates":[9.1851177216,45.53465271],"type":"Point"}
}