{
  "type": "Feature",
  "properties": {
    "addr:full":"9, Via Cal Resana 31028 Vazzola Vazzola Treviso 31028",
    "addr:postcode":"31028;31028",
    "addr:street":"Via Cal",
    "iso:country":"IT",
    "sg:address":"9, Via Cal Resana 31028 Vazzola",
    "sg:city":"Vazzola",
    "sg:classifiers":[
        {
            "category":"Sports & Exercise",
            "subcategory":"Playing Field",
            "type":"Entertainment"
        }
    ],
    "sg:phone":"+39 39043828446",
    "sg:postcode":"31028",
    "sg:province":"Treviso",
    "sg:tags":[
        "game"
    ],
    "wof:name":"Fome (s.r.l.)",
    "wof:placetype":"venue"
},
  "geometry": {"coordinates":[12.360209,45.819473],"type":"Point"}
}