{
  "type": "Feature",
  "properties": {
    "iso:country":"IT",
    "sg:address":"16162 Genova",
    "sg:city":"Genova",
    "sg:orig_category":"Macchine, Impianti Ed Attrezzature Per Abbigliamento E Pelletterie",
    "sg:phone":"+39 010 720152",
    "sg:postcode":"16162",
    "sg:province":"Genova",
    "wof:name":"Keyclean (s.r.l.)",
    "wof:placetype":"venue"
},
  "geometry": {"coordinates":[8.89543,44.469631],"type":"Point"}
}