{
  "type": "Feature",
  "properties": {
    "addr:full":"40128 Bologna Bologna Bologna 40128",
    "addr:postcode":"40128;40128",
    "iso:country":"IT",
    "sg:address":"40128 Bologna",
    "sg:city":"Bologna",
    "sg:orig_category":"Servizi Culturali E Per Lo Spettacolo. Cine-foto-ottica",
    "sg:phone":"+39 051 357325",
    "sg:postcode":"40128",
    "sg:province":"Bologna",
    "wof:name":"Monari Ivan",
    "wof:placetype":"venue"
},
  "geometry": {"coordinates":[11.352573,44.518658],"type":"Point"}
}