{
  "type": "Feature",
  "properties": {
    "addr:full":"90047 Partinico Partinico Palermo 90047",
    "addr:postcode":"90047;90047",
    "iso:country":"IT",
    "sg:address":"90047 Partinico",
    "sg:city":"Partinico",
    "sg:orig_category":"Ricerca, Selezione E Formazione Del Personale. Pubblica Amministrazione",
    "sg:phone":"+39 091 890 5123",
    "sg:postcode":"90047",
    "sg:province":"Palermo",
    "wof:name":"Ispettorato Provinciale Agricoltura",
    "wof:placetype":"venue"
},
  "geometry": {"coordinates":[13.120675,38.048019],"type":"Point"}
}