{
  "type": "Feature",
  "properties": {
    "addr:full":"15, Via Fiume 81027 San Felice A Cancello San Felice a Cancello Caserta 81027",
    "addr:housenumber":"cancello",
    "addr:postcode":"81027;cancello;81027",
    "addr:street":"Via Fiume;Felice A;Felice A",
    "iso:country":"IT",
    "sg:address":"15, Via Fiume 81027 San Felice A Cancello",
    "sg:city":"San Felice a Cancello",
    "sg:classifiers":[
        {
            "category":"Personal",
            "subcategory":"Shoe Repair & Shine",
            "type":"Services"
        }
    ],
    "sg:phone":"+39 0823 806382",
    "sg:postcode":"81027",
    "sg:province":"Caserta",
    "sg:tags":[
        "leather"
    ],
    "wof:name":"Calzaturificio Lina De Matteis S.a.s. Di De Matteis",
    "wof:placetype":"venue"
},
  "geometry": {"coordinates":[14.532826,40.898472],"type":"Point"}
}