{
  "type": "Feature",
  "properties": {
    "addr:full":"42100 Reggio Emilia Reggio Nell'Emilia 42100",
    "addr:postcode":"42100;42100",
    "iso:country":"IT",
    "sg:address":"42100 Reggio Emilia",
    "sg:orig_category":"Apparecchiature Elettroniche",
    "sg:phone":"+39 0522 511829",
    "sg:postcode":"42100",
    "sg:province":"Reggio Nell'Emilia",
    "wof:name":"Ema Di Trippitelli Maria Grazia",
    "wof:placetype":"venue"
},
  "geometry": {"coordinates":[10.649611,44.720947],"type":"Point"}
}