{
  "type": "Feature",
  "properties": {
    "addr:full":"20019 Settimo Milanese Settimo Milanese Milano 20019",
    "addr:postcode":"20019;20019",
    "iso:country":"IT",
    "sg:address":"20019 Settimo Milanese",
    "sg:city":"Settimo Milanese",
    "sg:orig_category":"Prodotti Chimici Di Base",
    "sg:phone":"+39 02 328 8191",
    "sg:postcode":"20019",
    "sg:province":"Milano",
    "wof:name":"Aimex S.n.c.",
    "wof:placetype":"venue"
},
  "geometry": {"coordinates":[9.0647058487,45.4645996094],"type":"Point"}
}