{
  "type": "Feature",
  "properties": {
    "iso:country":"IT",
    "sg:address":"31046 Oderzo",
    "sg:city":"Oderzo",
    "sg:orig_category":"Frigotecnica, Apparecchiature E Servizi. Servizi Di Magazzinaggio E Movimentazione",
    "sg:phone":"+39 0422 712435",
    "sg:postcode":"31046",
    "sg:province":"Treviso",
    "wof:name":"S.a.l.p.a. (s.r.l.)",
    "wof:placetype":"venue"
},
  "geometry": {"coordinates":[12.4992685318,45.7622795105],"type":"Point"}
}