{
  "type": "Feature",
  "properties": {
    "iso:country":"IT",
    "sg:address":"37024 Negrar",
    "sg:city":"Arbizzano",
    "sg:orig_category":"Servizi E Lavori Per Edilizia E Lavori Pubblici. Servizi Ausiliari Di Sorveglianza, Manutenzione E Pulizia",
    "sg:phone":"+39 045 751 4944",
    "sg:postcode":"37024",
    "sg:province":"Verona",
    "wof:name":"Rewal Snc",
    "wof:placetype":"venue"
},
  "geometry": {"coordinates":[10.935775,45.484928],"type":"Point"}
}