{
  "type": "Feature",
  "properties": {
    "addr:full":"62, Via Enrico Mattei 31055 Quinto Di Treviso Quinto di Treviso Treviso 31055",
    "addr:postcode":"31055;31055",
    "addr:street":"Via Enrico Mattei",
    "iso:country":"IT",
    "sg:address":"62, Via Enrico Mattei 31055 Quinto Di Treviso",
    "sg:city":"Quinto di Treviso",
    "sg:classifiers":[
        {
            "category":"Manufacturing",
            "subcategory":"Paper Products",
            "type":"Manufacturing & Wholesale Goods"
        }
    ],
    "sg:phone":"+39 0422 370722",
    "sg:postcode":"31055",
    "sg:province":"Treviso",
    "sg:tags":[
        "cardboard"
    ],
    "wof:name":"E. D.tecno System Di Annoe' A.",
    "wof:placetype":"venue"
},
  "geometry": {"coordinates":[12.1596956253,45.62733078],"type":"Point"}
}