{
  "type": "Feature",
  "properties": {
    "addr:full":"40121 Bologna Bologna Bologna 40121",
    "addr:postcode":"40121;40121",
    "iso:country":"IT",
    "sg:address":"40121 Bologna",
    "sg:city":"Bologna",
    "sg:orig_category":"Scuole Di Ballo E Danza Classica E Moderna",
    "sg:phone":"+39 051 649 0476",
    "sg:postcode":"40121",
    "sg:province":"Bologna",
    "wof:name":"Centro Studio Danza Gymmoving",
    "wof:placetype":"venue"
},
  "geometry": {"coordinates":[11.335316,44.50177],"type":"Point"}
}