{
  "type": "Feature",
  "properties": {
    "addr:full":"00198 Roma Roma Roma 00198",
    "addr:postcode":"00198;00198",
    "iso:country":"IT",
    "sg:address":"00198 Roma",
    "sg:city":"Roma",
    "sg:orig_category":"Arredo Camera Letto E Complementi",
    "sg:phone":"+39 06 841 3612",
    "sg:postcode":"00198",
    "sg:province":"Roma",
    "wof:name":"Treca (s.r.l.)",
    "wof:placetype":"venue"
},
  "geometry": {"coordinates":[12.493546,41.917614],"type":"Point"}
}