{
  "type": "Feature",
  "properties": {
    "iso:country":"IT",
    "sg:address":"Via Delle Moie 25073 Bovezzo",
    "sg:city":"Bovezzo",
    "sg:classifiers":[
        {
            "category":"Professional",
            "subcategory":"Engineering",
            "type":"Services"
        }
    ],
    "sg:phone":"+39 030 271 1371",
    "sg:postcode":"25073",
    "sg:province":"Brescia",
    "sg:tags":[
        "machine",
        "-",
        "mechanical"
    ],
    "wof:name":"O.m.v. (s.r.l.)",
    "wof:placetype":"venue"
},
  "geometry": {"coordinates":[10.246169,45.58783],"type":"Point"}
}