{
  "type": "Feature",
  "properties": {
    "addr:full":"Piazza Dell' Insurrezi 1 35137 Padova Padova Padova 35137",
    "addr:housenumber":"1",
    "addr:postcode":"35137;35137",
    "addr:street":"Piazza Dell ' Insurrezi",
    "iso:country":"IT",
    "sg:address":"Piazza Dell' Insurrezi 1 35137 Padova",
    "sg:city":"Padova",
    "sg:orig_category":"Spirometers",
    "sg:phone":"+39 049 875 1644",
    "sg:postcode":"35137",
    "sg:province":"Padova",
    "sg:website":"www.biomedin.com",
    "wof:name":"Biomedin",
    "wof:placetype":"venue"
},
  "geometry": {"coordinates":[11.844167,45.397499],"type":"Point"}
}