{
  "type": "Feature",
  "properties": {
    "addr:full":"36030 Montecchio Precalcino Montecchio Precalcino Vicenza 36030",
    "addr:postcode":"36030;36030",
    "iso:country":"IT",
    "sg:address":"36030 Montecchio Precalcino",
    "sg:city":"Montecchio Precalcino",
    "sg:orig_category":"Servizi E Lavori Per Abbigliamento E Pelletterie",
    "sg:phone":"+39 0445 864567",
    "sg:postcode":"36030",
    "sg:province":"Vicenza",
    "wof:name":"Roncaglia Nadia",
    "wof:placetype":"venue"
},
  "geometry": {"coordinates":[11.533084,45.683857],"type":"Point"}
}