{
  "type": "Feature",
  "properties": {
    "iso:country":"IT",
    "sg:address":"24, Via Martiri Liberta' 31030 Casier",
    "sg:city":"Casier",
    "sg:classifiers":[
        {
            "category":"Home & Garden",
            "subcategory":"Home Furnishings",
            "type":"Retail Goods"
        }
    ],
    "sg:phone":"+39 0422 381448",
    "sg:postcode":"31030",
    "sg:province":"Treviso",
    "sg:tags":[
        "household"
    ],
    "wof:name":"F.lli Zanatta Di Ernesto & Ferruccio (s.n.c.)",
    "wof:placetype":"venue"
},
  "geometry": {"coordinates":[12.261639,45.617607],"type":"Point"}
}