{
  "type": "Feature",
  "properties": {
    "iso:country":"IT",
    "sg:address":"41100 Modena",
    "sg:city":"Modena",
    "sg:orig_category":"Non-classified Establishments",
    "sg:phone":"+39 059 250440",
    "sg:postcode":"41100",
    "sg:province":"Modena",
    "sg:website":"http://www.marchi-contract.com",
    "wof:name":"Marchi Srl",
    "wof:placetype":"venue"
},
  "geometry": {"coordinates":[10.924488,44.547882],"type":"Point"}
}