{
  "type": "Feature",
  "properties": {
    "addr:full":"00141 Roma Roma Roma 00141",
    "addr:postcode":"00141;00141",
    "iso:country":"IT",
    "sg:address":"00141 Roma",
    "sg:city":"Roma",
    "sg:orig_category":"Motori Ed Organi Di Trasmissione. Ricambi E Componenti Dei Mezzi Di Trasporto",
    "sg:phone":"+39 06 8864 0137",
    "sg:postcode":"00141",
    "sg:province":"Roma",
    "wof:name":"Melchiorri Ermanno",
    "wof:placetype":"venue"
},
  "geometry": {"coordinates":[12.5293312073,41.9428253174],"type":"Point"}
}