{
  "type": "Feature",
  "properties": {
    "addr:full":"21, Via Buonarroti Michelangelo 20093 Cologno Monzese Cologno Monzese Milano 20093",
    "addr:postcode":"20093;20093",
    "addr:street":"Via Buonarroti Michelangelo",
    "iso:country":"IT",
    "sg:address":"21, Via Buonarroti Michelangelo 20093 Cologno Monzese",
    "sg:city":"Cologno Monzese",
    "sg:classifiers":[
        {
            "category":"Utilities",
            "subcategory":"Telephone",
            "type":"Services"
        }
    ],
    "sg:phone":"+39 390 227 3251",
    "sg:postcode":"20093",
    "sg:province":"Milano",
    "sg:tags":[
        "telecommunication"
    ],
    "wof:name":"Siae Microelettronica S.p.a.",
    "wof:placetype":"venue"
},
  "geometry": {"coordinates":[9.273587,45.534359],"type":"Point"}
}