{
  "type": "Feature",
  "properties": {
    "addr:full":"Via I Maggio - Schianno 21045 Gazzada Gazzada Varese 21045",
    "addr:postcode":"21045;21045",
    "addr:street":"Via I Maggio Schianno",
    "iso:country":"IT",
    "sg:address":"Via I Maggio - Schianno 21045 Gazzada",
    "sg:city":"Gazzada",
    "sg:classifiers":[
        {
            "category":"Professional",
            "subcategory":"Art Services",
            "type":"Services"
        }
    ],
    "sg:phone":"+39 0332 462313",
    "sg:postcode":"21045",
    "sg:province":"Varese",
    "sg:tags":[
        "catalogue"
    ],
    "wof:name":"New Grafiche E. Pozzi Srl",
    "wof:placetype":"venue"
},
  "geometry": {"coordinates":[8.839374,45.786377],"type":"Point"}
}