{
  "type": "Feature",
  "properties": {
    "iso:country":"IT",
    "sg:address":"10, V. Clanio 81030 Orta Di Atella",
    "sg:city":"Orta di Atella",
    "sg:classifiers":[
        {
            "category":"Shopping",
            "subcategory":"Clothing, Apparel, & Fashions",
            "type":"Retail Goods"
        }
    ],
    "sg:phone":"+39 081 502 2051",
    "sg:postcode":"81030",
    "sg:province":"Caserta",
    "sg:tags":[
        "clothes"
    ],
    "sg:website":"http://www.siridemantree.com:ws_end: :mark:ws:http://www.paginegialle.it/siridemantree",
    "wof:name":"Siri De Mantree",
    "wof:placetype":"venue"
},
  "geometry": {"coordinates":[14.273656,40.97031],"type":"Point"}
}