{
  "type": "Feature",
  "properties": {
    "addr:full":"20143 Milano Milano Milano 20143",
    "addr:postcode":"20143;20143",
    "iso:country":"IT",
    "sg:address":"20143 Milano",
    "sg:city":"Milano",
    "sg:orig_category":"Servizi Per Aziende, Manifestazioni E Supporto Agli Scambi Commerciali",
    "sg:phone":"+39 02 8918 1290",
    "sg:postcode":"20143",
    "sg:province":"Milano",
    "wof:name":"Silvestrin & Silvestrin",
    "wof:placetype":"venue"
},
  "geometry": {"coordinates":[9.156797,45.444038],"type":"Point"}
}