{
  "type": "Feature",
  "properties": {
    "iso:country":"IT",
    "sg:address":"1, Via Tiburtina Valeria 67069 Tagliacozzo",
    "sg:classifiers":[
        {
            "category":"Manufacturing",
            "subcategory":"Rubber & Plastics",
            "type":"Manufacturing & Wholesale Goods"
        }
    ],
    "sg:phone":"+39 39086367457",
    "sg:postcode":"67069",
    "sg:province":"L'Aquila",
    "wof:name":"Penta Plast",
    "wof:placetype":"venue"
},
  "geometry": {"coordinates":[13.2685394287,42.0684318542],"type":"Point"}
}