{
  "type": "Feature",
  "properties": {
    "addr:full":"00135 Roma Roma Roma 00135",
    "addr:postcode":"00135;00135",
    "iso:country":"IT",
    "sg:address":"00135 Roma",
    "sg:city":"Roma",
    "sg:orig_category":"Servizi Per Lo Sport E Il Tempo Libero. Servizi Vari Di Interesse Pubblico",
    "sg:phone":"+39 06 3081 0456",
    "sg:postcode":"00135",
    "sg:province":"Roma",
    "wof:name":"Agenzia Ippica Primavalle Srl",
    "wof:placetype":"venue"
},
  "geometry": {"coordinates":[12.403639,41.96558],"type":"Point"}
}