{
  "type": "Feature",
  "properties": {
    "iso:country":"IT",
    "sg:address":"37, Via Salotti Sisto 29100 Piacenza",
    "sg:city":"Piacenza",
    "sg:classifiers":[
        {
            "category":"Professional",
            "subcategory":"Printing & Photocopies",
            "type":"Services"
        }
    ],
    "sg:phone":"+39 0523 380102",
    "sg:postcode":"29100",
    "sg:province":"Piacenza",
    "wof:name":"Tipografia Tip.le.co (s.n.c.)",
    "wof:placetype":"venue"
},
  "geometry": {"coordinates":[9.6951417923,45.0537719727],"type":"Point"}
}