{
  "type": "Feature",
  "properties": {
    "iso:country":"IT",
    "sg:address":"47037 Rimini",
    "sg:orig_category":"Forniture Per Agricoltura E Zootecnia",
    "sg:phone":"+39 0541 778260",
    "sg:province":"RN",
    "wof:name":"Agricasa Snc Di Campana Primo & C.",
    "wof:placetype":"venue"
},
  "geometry": {"coordinates":[-85.3342971802,39.1651725769],"type":"Point"}
}