{
  "type": "Feature",
  "properties": {
    "iso:country":"IT",
    "sg:address":"00195 Roma",
    "sg:city":"Roma",
    "sg:orig_category":"Calzature, Pelletterie E Pelli. Servizi E Lavori Per Abbigliamento E Pelletterie",
    "sg:phone":"+39 06 372 5437",
    "sg:postcode":"00195",
    "sg:province":"Roma",
    "wof:name":"Maulicino Giovanni",
    "wof:placetype":"venue"
},
  "geometry": {"coordinates":[12.340014,42.083736],"type":"Point"}
}