{
  "type": "Feature",
  "properties": {
    "iso:country":"IT",
    "sg:address":"50141 Firenze",
    "sg:city":"Firenze",
    "sg:orig_category":"Campeggio, Tende, Attrezzature Ed Articoli - Produzione E Ingrosso",
    "sg:phone":"+39 055 437 3287",
    "sg:postcode":"50141",
    "sg:province":"Firenze",
    "wof:name":"Tecno Costruzioni Srl",
    "wof:placetype":"venue"
},
  "geometry": {"coordinates":[11.265472,43.772881],"type":"Point"}
}