{
  "type": "Feature",
  "properties": {
    "iso:country":"IT",
    "sg:address":"1, Via Ghiacciaia 37045 Legnago",
    "sg:city":"Legnago",
    "sg:classifiers":[
        {
            "category":"Utilities",
            "subcategory":"Electric",
            "type":"Services"
        }
    ],
    "sg:phone":"+39 39044223800",
    "sg:postcode":"37045",
    "sg:province":"Verona",
    "sg:tags":[
        "component",
        "electronic"
    ],
    "wof:name":"Menber's (s.p.a.)",
    "wof:placetype":"venue"
},
  "geometry": {"coordinates":[11.286391,45.185963],"type":"Point"}
}