{
  "type": "Feature",
  "properties": {
    "iso:country":"IT",
    "sg:address":"Via Duca Degli Abruzzi 80077 Ischia",
    "sg:city":"Ischia",
    "sg:classifiers":[
        {
            "category":"Sports & Exercise",
            "subcategory":"Playing Field",
            "type":"Entertainment"
        }
    ],
    "sg:phone":"+39 39081989852",
    "sg:postcode":"80077",
    "sg:province":"Napoli",
    "sg:tags":[
        "game"
    ],
    "wof:name":"Ischia Print S.r.l.",
    "wof:placetype":"venue"
},
  "geometry": {"coordinates":[14.251636,40.840096],"type":"Point"}
}