{
  "type": "Feature",
  "properties": {
    "addr:full":"Via Sant'eusebio 4/g 41014 Castelvetro Di Modena Castelvetro di Modena Modena 41014",
    "addr:housenumber":"4 / g;castelvetro di modena",
    "addr:postcode":"41014;41014",
    "addr:street":"Via Sant'Eusebio;Di Modena;Modena",
    "iso:country":"IT",
    "sg:address":"Via Sant'eusebio 4/g 41014 Castelvetro Di Modena",
    "sg:city":"Castelvetro di Modena",
    "sg:classifiers":[
        {
            "category":"Building & Trades",
            "subcategory":"Equipment Rental",
            "type":"Services"
        }
    ],
    "sg:phone":"+39 059 702712",
    "sg:postcode":"41014",
    "sg:province":"Modena",
    "sg:tags":[
        "apartment",
        "door",
        "room"
    ],
    "sg:website":"www.cooplegno.it",
    "wof:name":"Coop Legno Scrl",
    "wof:placetype":"venue"
},
  "geometry": {"coordinates":[10.92522,44.647079],"type":"Point"}
}