{
  "type": "Feature",
  "properties": {
    "addr:full":"25011 Calcinato Calcinato Brescia 25011",
    "addr:postcode":"25011;25011",
    "iso:country":"IT",
    "sg:address":"25011 Calcinato",
    "sg:city":"Calcinato",
    "sg:orig_category":"Prodotti Chimici Secondari. Macchine E Forniture Per Ecologia E Smaltimento Rifiuti. Forniture Per Attivita' Commerciali Ed Artigianali",
    "sg:phone":"+39 030 358 1511",
    "sg:postcode":"25011",
    "sg:province":"Brescia",
    "wof:name":"Unichem Srl",
    "wof:placetype":"venue"
},
  "geometry": {"coordinates":[10.3956031799,45.4584960938],"type":"Point"}
}