{
  "type": "Feature",
  "properties": {
    "addr:full":"Km. 8, Strada Provinciale Bari-modugno 70026 Modugno Modugno Bari 70026",
    "addr:postcode":"70026;70026",
    "addr:street":"Strada Provinciale Bari-Modugno",
    "iso:country":"IT",
    "sg:address":"Km. 8, Strada Provinciale Bari-modugno 70026 Modugno",
    "sg:city":"Modugno",
    "sg:classifiers":[
        {
            "category":"Professional",
            "subcategory":"Computer Services",
            "type":"Services"
        }
    ],
    "sg:phone":"+39 080 532 1004",
    "sg:postcode":"70026",
    "sg:province":"Bari",
    "sg:tags":[
        "information",
        "technology"
    ],
    "wof:name":"Organizzazione Grafica Meridionale Di Leonardo Zaccagni",
    "wof:placetype":"venue"
},
  "geometry": {"coordinates":[16.869291,41.126053],"type":"Point"}
}