{
  "type": "Feature",
  "properties": {
    "iso:country":"IT",
    "sg:address":"58043 Castiglione Della Pescaia",
    "sg:city":"Castiglione della Pescaia",
    "sg:orig_category":"Scuole E Servizi Scolastici. Servizi Per Lo Sport E Il Tempo Libero",
    "sg:phone":"+39 0564 933918",
    "sg:postcode":"58043",
    "sg:province":"Grosseto",
    "wof:name":"Centro Servizi Nautici Snc Di Papini",
    "wof:placetype":"venue"
},
  "geometry": {"coordinates":[10.883298,42.764935],"type":"Point"}
}