{
  "type": "Feature",
  "properties": {
    "addr:full":"46100 Mantova Mantova Mantova 46100",
    "addr:postcode":"46100;46100",
    "iso:country":"IT",
    "sg:address":"46100 Mantova",
    "sg:city":"Mantova",
    "sg:orig_category":"Avvocati - Studi",
    "sg:phone":"+39 0376 320318",
    "sg:postcode":"46100",
    "sg:province":"Mantova",
    "wof:name":"Avanzini Avv. Lucio & Ennio",
    "wof:placetype":"venue"
},
  "geometry": {"coordinates":[10.7905168533,45.1548576355],"type":"Point"}
}