{
  "type": "Feature",
  "properties": {
    "iso:country":"IT",
    "sg:address":"92024 Canicatt\u00ec",
    "sg:orig_category":"Poltrone E Divani - Vendita Al Dettaglio",
    "sg:phone":"+39 0922 833512",
    "sg:postcode":"92024",
    "sg:province":"Agrigento",
    "wof:name":"Divani Forma Di Cimino Luigi",
    "wof:placetype":"venue"
},
  "geometry": {"coordinates":[13.8332195282,37.362953186],"type":"Point"}
}