{
  "type": "Feature",
  "properties": {
    "iso:country":"IT",
    "sg:address":"31020 Villorba",
    "sg:city":"Villorba",
    "sg:orig_category":"Imprese Di Costruzioni Civili Ed Industriali",
    "sg:phone":"+39 0422 918445",
    "sg:postcode":"31020",
    "sg:province":"Treviso",
    "wof:name":"Geoservizi Srl",
    "wof:placetype":"venue"
},
  "geometry": {"coordinates":[12.259639,45.708614],"type":"Point"}
}