{
  "type": "Feature",
  "properties": {
    "addr:full":"00143 Roma Roma Roma 00143",
    "addr:postcode":"00143;00143",
    "iso:country":"IT",
    "sg:address":"00143 Roma",
    "sg:city":"Roma",
    "sg:orig_category":"Abbigliamento Esterno, Maglierie E Pelliccerie",
    "sg:phone":"+39 06 501 0458",
    "sg:postcode":"00143",
    "sg:province":"Roma",
    "wof:name":"Fioravanti Romano Oliva",
    "wof:placetype":"venue"
},
  "geometry": {"coordinates":[12.4876661301,41.8125801086],"type":"Point"}
}