{
  "type": "Feature",
  "properties": {
    "iso:country":"IT",
    "sg:address":"20138 Milano",
    "sg:city":"Milano",
    "sg:orig_category":"Macchine, Impianti E Forniture Per Industria Grafica, Cartaria E Cartotecnica",
    "sg:phone":"+39 02 506 2866",
    "sg:postcode":"20138",
    "sg:province":"Milano",
    "wof:name":"Multi Tecnic Snc",
    "wof:placetype":"venue"
},
  "geometry": {"coordinates":[9.251227,45.453423],"type":"Point"}
}