{
  "type": "Feature",
  "properties": {
    "iso:country":"IT",
    "sg:address":"39012 Merano",
    "sg:city":"Merano",
    "sg:orig_category":"Forniture Per Edilizia E Lavori Pubblici",
    "sg:phone":"+39 0473 447737",
    "sg:postcode":"39012",
    "sg:province":"Bolzano/Bozen",
    "sg:website":"http://www.ragespi.it",
    "wof:name":"Ragespi Snc & Ragespi Acustic",
    "wof:placetype":"venue"
},
  "geometry": {"coordinates":[11.352355957,46.4985961914],"type":"Point"}
}