{
  "type": "Feature",
  "properties": {
    "addr:full":"26858 Sordio Sordio Lodi 26858",
    "addr:postcode":"26858;26858",
    "iso:country":"IT",
    "sg:address":"26858 Sordio",
    "sg:city":"Sordio",
    "sg:orig_category":"Zootecnia E Pesca, Allevamento Piccoli Animali",
    "sg:phone":"+39 02 9826 0488",
    "sg:postcode":"26858",
    "sg:province":"Lodi",
    "wof:name":"Associazione Provinciale Allevatori",
    "wof:placetype":"venue"
},
  "geometry": {"coordinates":[9.373434,45.341026],"type":"Point"}
}