{
  "type": "Feature",
  "properties": {
    "iso:country":"IT",
    "sg:address":"2/a, Piazza Principessa Iolanda 95129 Catania",
    "sg:city":"Catania",
    "sg:classifiers":[
        {
            "category":"Shopping",
            "subcategory":"Gifts & Souvenirs",
            "type":"Retail Goods"
        }
    ],
    "sg:phone":"+39 39095538462",
    "sg:postcode":"95129",
    "sg:province":"Catania",
    "wof:name":"La Bacheca S.r.l",
    "wof:placetype":"venue"
},
  "geometry": {"coordinates":[15.097342,37.512779],"type":"Point"}
}