{
  "type": "Feature",
  "properties": {
    "iso:country":"IT",
    "sg:address":"Via Censi Dell' Arco 24 80040 Cercola",
    "sg:city":"Cercola",
    "sg:classifiers":[
        {
            "category":"Manufacturing",
            "subcategory":"Rubber & Plastics",
            "type":"Manufacturing & Wholesale Goods"
        }
    ],
    "sg:phone":"+39 081 733 1978",
    "sg:postcode":"80040",
    "sg:province":"Napoli",
    "sg:tags":[
        "item",
        "household",
        "made"
    ],
    "wof:name":"Ce.pla.n. Cecio Plastica Napoli Sas Di Ida Cecio & C",
    "wof:placetype":"venue"
},
  "geometry": {"coordinates":[14.348969,40.851784],"type":"Point"}
}