{
  "type": "Feature",
  "properties": {
    "iso:country":"IT",
    "sg:address":"00122 Lido Di Ostia",
    "sg:orig_category":"Tempo Libero - Articoli E Forniture. Regalistica Aziendale",
    "sg:phone":"+39 06 568 2291",
    "sg:postcode":"00122",
    "sg:province":"Roma",
    "wof:name":"Valeria Lido Distribuzione Srl",
    "wof:placetype":"venue"
},
  "geometry": {"coordinates":[12.293451,41.731945],"type":"Point"}
}