{
  "type": "Feature",
  "properties": {
    "iso:country":"IT",
    "sg:address":"Via Mameli 9 33041 Aiello Del Friuli",
    "sg:city":"Aiello del Friuli",
    "sg:classifiers":[
        {
            "category":"Building & Trades",
            "subcategory":"Construction",
            "type":"Services"
        }
    ],
    "sg:phone":"+39 0432 997218",
    "sg:postcode":"33041",
    "sg:province":"Udine",
    "sg:tags":[
        "carpenter's",
        "work",
        "supraregional"
    ],
    "sg:website":"www.simeoncarpenterie.it",
    "wof:name":"Simeon Carpenterie Srl",
    "wof:placetype":"venue"
},
  "geometry": {"coordinates":[13.230724,46.064941],"type":"Point"}
}