{
  "type": "Feature",
  "properties": {
    "iso:country":"IT",
    "sg:address":"41034 Finale Emilia",
    "sg:city":"Finale Emilia",
    "sg:classifiers":[
        {
            "category":"Manufacturing",
            "subcategory":"Rubber & Plastics",
            "type":"Manufacturing & Wholesale Goods"
        }
    ],
    "sg:phone":"+39 0535 98202",
    "sg:postcode":"41034",
    "sg:province":"Modena",
    "sg:tags":[
        "equipment",
        "industry",
        "machinery"
    ],
    "sg:website":"http://www.prtsrl.it",
    "wof:name":"Prt Srl",
    "wof:placetype":"venue"
},
  "geometry": {"coordinates":[11.2500343323,44.829460144],"type":"Point"}
}