{
  "type": "Feature",
  "properties": {
    "iso:country":"IT",
    "sg:address":"53, Piazza Zumbini Bonaventura 87100 Cosenza",
    "sg:city":"Cosenza",
    "sg:classifiers":[
        {
            "category":"Real Estate",
            "subcategory":"Surveying",
            "type":"Services"
        }
    ],
    "sg:phone":"+39 39098434899",
    "sg:postcode":"87100",
    "sg:province":"Cosenza",
    "sg:tags":[
        "equipment",
        "material",
        "good",
        "-",
        "handling"
    ],
    "wof:name":"Muglia Elevatori S.r.l.",
    "wof:placetype":"venue"
},
  "geometry": {"coordinates":[16.253809,39.298264],"type":"Point"}
}