{
  "type": "Feature",
  "properties": {
    "iso:country":"IT",
    "sg:address":"20141 Milano",
    "sg:city":"Milano",
    "sg:orig_category":"Carta, Cartone E Prodotti Primari",
    "sg:phone":"+39 02 8953 1736",
    "sg:postcode":"20141",
    "sg:province":"Milano",
    "wof:name":"Magnacarta Snc",
    "wof:placetype":"venue"
},
  "geometry": {"coordinates":[9.199751,45.423962],"type":"Point"}
}