{
  "type": "Feature",
  "properties": {
    "addr:full":"21040 Jerago Con Orago Jerago con Orago Varese 21040",
    "addr:postcode":"21040;orago;21040",
    "addr:street":"Con Orago;Con",
    "iso:country":"IT",
    "sg:address":"21040 Jerago Con Orago",
    "sg:city":"Jerago con Orago",
    "sg:orig_category":"Prodotti E Manufatti In Materie Plastiche. Prodotti Cosmetici E Da Toeletta. Forniture Per Attivita' Industriali",
    "sg:phone":"+39 0331 217230",
    "sg:postcode":"21040",
    "sg:province":"Varese",
    "wof:name":"Tani Guglielmo & C. (s.a.s.)",
    "wof:placetype":"venue"
},
  "geometry": {"coordinates":[8.8004512787,45.7036056519],"type":"Point"}
}