{
  "type": "Feature",
  "properties": {
    "addr:full":"Via De Medici 5 20013 Magenta Magenta Milano 20013",
    "addr:housenumber":"5",
    "addr:postcode":"20013;20013",
    "addr:street":"Via De Medici",
    "iso:country":"IT",
    "sg:address":"Via De Medici 5 20013 Magenta",
    "sg:city":"Magenta",
    "sg:classifiers":[
        {
            "category":"Shopping",
            "subcategory":"Stationery & Office Supplies",
            "type":"Retail Goods"
        }
    ],
    "sg:phone":"+39 02 979601",
    "sg:postcode":"20013",
    "sg:province":"Milano",
    "sg:tags":[
        "cardboard"
    ],
    "sg:website":"www.renodemedici.it",
    "wof:name":"Reno De Medici Spa",
    "wof:placetype":"venue"
},
  "geometry": {"coordinates":[9.181119,45.460762],"type":"Point"}
}