{
  "type": "Feature",
  "properties": {
    "iso:country":"IT",
    "sg:address":"5, Viale Giovanni Da Verrazzano 54033 Carrara",
    "sg:city":"Carrara",
    "sg:classifiers":[
        {
            "category":"Marine",
            "type":"Transportation"
        }
    ],
    "sg:phone":"+39 390 585 7711",
    "sg:postcode":"54033",
    "sg:province":"Massa-Carrara",
    "sg:tags":[
        "transport",
        "sea"
    ],
    "wof:name":"Bm Shipping Group Srl",
    "wof:placetype":"venue"
},
  "geometry": {"coordinates":[10.035966,44.221401],"type":"Point"}
}