{
  "type": "Feature",
  "properties": {
    "iso:country":"IT",
    "sg:address":"80125 Napoli",
    "sg:city":"Napoli",
    "sg:orig_category":"Macchine, Impianti Ed Attrezzature Per Industria Alimentare E Bevande. Macchine E Impianti Per Attivita' Commerciali Ed Artigianali",
    "sg:phone":"+39 081 230 3496",
    "sg:postcode":"80125",
    "sg:province":"Napoli",
    "wof:name":"Ge.ma. Srl",
    "wof:placetype":"venue"
},
  "geometry": {"coordinates":[14.162399,40.833569],"type":"Point"}
}