{
  "type": "Feature",
  "properties": {
    "iso:country":"IT",
    "sg:address":"20, Via Uccelliera 41100 Modena",
    "sg:city":"Modena",
    "sg:classifiers":[
        {
            "category":"Shopping",
            "subcategory":"Crafts & Fabrics",
            "type":"Retail Goods"
        }
    ],
    "sg:phone":"+39 39059820633",
    "sg:postcode":"41100",
    "sg:province":"Modena",
    "wof:name":"Ricamificio Antonella Srl",
    "wof:placetype":"venue"
},
  "geometry": {"coordinates":[10.8934926987,44.6573066711],"type":"Point"}
}