{
  "type": "Feature",
  "properties": {
    "iso:country":"IT",
    "sg:address":"20048 Carate Brianza",
    "sg:city":"Carate Brianza",
    "sg:orig_category":"Macchine, Impianti Ed Attrezzature Per Abbigliamento E Pelletterie",
    "sg:phone":"+39 036 299 0982",
    "sg:postcode":"20048",
    "sg:province":"Milano",
    "wof:name":"Farina Edmondo & C. Snc",
    "wof:placetype":"venue"
},
  "geometry": {"coordinates":[9.244577,45.675076],"type":"Point"}
}