{
  "type": "Feature",
  "properties": {
    "iso:country":"IT",
    "sg:address":"21055 Gorla Minore",
    "sg:city":"Gorla Minore",
    "sg:orig_category":"Accoppiatura E Spalmatura",
    "sg:phone":"+39 0331 365300",
    "sg:postcode":"21055",
    "sg:province":"Varese",
    "wof:name":"Gencla Srl",
    "wof:placetype":"venue"
},
  "geometry": {"coordinates":[8.909954,45.646717],"type":"Point"}
}