{
  "type": "Feature",
  "properties": {
    "addr:full":"59100 Prato Prato Prato 59100",
    "addr:postcode":"59100;59100",
    "iso:country":"IT",
    "sg:address":"59100 Prato",
    "sg:city":"Prato",
    "sg:orig_category":"Accessori Moda D'abbigliamento. Forniture Per Abbigliamento E Pelletterie",
    "sg:phone":"+39 0574 625222",
    "sg:postcode":"59100",
    "sg:province":"Prato",
    "wof:name":"Fiorenzatulle Spa",
    "wof:placetype":"venue"
},
  "geometry": {"coordinates":[11.089396,43.875061],"type":"Point"}
}