{
  "type": "Feature",
  "properties": {
    "addr:full":"Via Del Lazzeretto 115 59100 Prato Prato Prato 59100",
    "addr:housenumber":"115",
    "addr:postcode":"59100;59100",
    "addr:street":"Via Del Lazzeretto",
    "iso:country":"IT",
    "sg:address":"Via Del Lazzeretto 115 59100 Prato",
    "sg:city":"Prato",
    "sg:classifiers":[
        {
            "category":"Parking",
            "subcategory":"Lot",
            "type":"Transportation"
        }
    ],
    "sg:phone":"+39 0574 542350",
    "sg:postcode":"59100",
    "sg:province":"Prato",
    "sg:tags":[
        "stockinette",
        "yarn"
    ],
    "wof:name":"Nanni Filati Srl",
    "wof:placetype":"venue"
},
  "geometry": {"coordinates":[11.092091,43.85453],"type":"Point"}
}