{
  "type": "Feature",
  "properties": {
    "iso:country":"IT",
    "sg:address":"20161 Milano",
    "sg:city":"Milano",
    "sg:orig_category":"Impiantistica E Prodotti Tecnologici Per Edilizia. Servizi Ausiliari Di Sorveglianza, Manutenzione E Pulizia",
    "sg:phone":"+39 02 6620 1985",
    "sg:postcode":"20161",
    "sg:province":"Milano",
    "wof:name":"Sofir Srl",
    "wof:placetype":"venue"
},
  "geometry": {"coordinates":[9.17084,45.523651],"type":"Point"}
}