{
  "type": "Feature",
  "properties": {
    "iso:country":"IT",
    "sg:address":"Z.a. Toldo Di Trambileno 38068 Trambileno",
    "sg:city":"Trambileno",
    "sg:classifiers":[
        {
            "category":"Manufacturing",
            "subcategory":"Tools & Machinery",
            "type":"Manufacturing & Wholesale Goods"
        }
    ],
    "sg:phone":"+39 0464 868159",
    "sg:postcode":"38068",
    "sg:province":"Trento",
    "sg:tags":[
        "environment",
        "equipment",
        "-"
    ],
    "sg:website":"http://www.salvadori.com",
    "wof:name":"Salvadori E Figli Sas",
    "wof:placetype":"venue"
},
  "geometry": {"coordinates":[11.075122,45.870407],"type":"Point"}
}