{
  "type": "Feature",
  "properties": {
    "iso:country":"IT",
    "sg:address":"10153 Torino",
    "sg:city":"Torino",
    "sg:orig_category":"Carrozzerie Automobili",
    "sg:phone":"+39 011 888768",
    "sg:postcode":"10153",
    "sg:province":"Torino",
    "wof:name":"Carrozzeria Alma 2000 Srl",
    "wof:placetype":"venue"
},
  "geometry": {"coordinates":[7.706464,45.07407],"type":"Point"}
}