{
  "type": "Feature",
  "properties": {
    "iso:country":"IT",
    "sg:address":"70124 Bari",
    "sg:city":"Bari",
    "sg:orig_category":"Antifurto",
    "sg:phone":"+39 080 556 5584",
    "sg:postcode":"70124",
    "sg:province":"Bari",
    "wof:name":"Alfallarm Snc Di Tenzone & C.",
    "wof:placetype":"venue"
},
  "geometry": {"coordinates":[16.870365,41.11203],"type":"Point"}
}