{
  "type": "Feature",
  "properties": {
    "iso:country":"IT",
    "sg:address":"06132 San Sisto",
    "sg:orig_category":"Pompe. Elettrotecnica Industriale, Prodotti E Apparecchiature",
    "sg:phone":"+39 075 527 1154",
    "sg:postcode":"06132",
    "sg:province":"Perugia",
    "wof:name":"S.c.a.t. Impianti Di Pompei Ferruccio & C. Sas",
    "wof:placetype":"venue"
},
  "geometry": {"coordinates":[12.3461513519,43.0848350525],"type":"Point"}
}