{
  "type": "Feature",
  "properties": {
    "iso:country":"IT",
    "sg:address":"20098 San Giuliano Milanese",
    "sg:city":"San Giuliano Milanese",
    "sg:orig_category":"Materiali E Componenti Elettronici",
    "sg:phone":"+39 02 983 4621",
    "sg:postcode":"20098",
    "sg:province":"Milano",
    "wof:name":"San Giuliano Srl",
    "wof:placetype":"venue"
},
  "geometry": {"coordinates":[9.223941,45.376736],"type":"Point"}
}