{
  "type": "Feature",
  "properties": {
    "addr:full":"09025 Sanluri Sanluri Medio Campidano 09025",
    "addr:postcode":"09025;09025",
    "iso:country":"IT",
    "sg:address":"09025 Sanluri",
    "sg:city":"Sanluri",
    "sg:orig_category":"Armi E Munizioni - Vendita Al Dettaglio",
    "sg:phone":"+39 070 937 3118",
    "sg:postcode":"09025",
    "sg:province":"Medio Campidano",
    "wof:name":"Il Pescacciatore",
    "wof:placetype":"venue"
},
  "geometry": {"coordinates":[8.904516,39.479176],"type":"Point"}
}