{
  "type": "Feature",
  "properties": {
    "iso:country":"IT",
    "sg:address":"17014 Cairo Montenotte",
    "sg:city":"Cairo Montenotte",
    "sg:orig_category":"Pompe. Ricambi E Componenti Dei Mezzi Di Trasporto",
    "sg:phone":"+39 019 504105",
    "sg:postcode":"17014",
    "sg:province":"Savona",
    "wof:name":"Officina Baccino",
    "wof:placetype":"venue"
},
  "geometry": {"coordinates":[8.2839832306,44.4005279541],"type":"Point"}
}