{
  "type": "Feature",
  "properties": {
    "addr:full":"03012 Anagni Anagni Frosinone 03012",
    "addr:postcode":"03012;03012",
    "iso:country":"IT",
    "sg:address":"03012 Anagni",
    "sg:city":"Anagni",
    "sg:orig_category":"Serramenti Ed Infissi",
    "sg:phone":"+39 0775 769791",
    "sg:postcode":"03012",
    "sg:province":"Frosinone",
    "sg:website":"http://www.anticolanainfissi.com",
    "wof:name":"Anticolana Infissi Srl",
    "wof:placetype":"venue"
},
  "geometry": {"coordinates":[13.150968,41.734631],"type":"Point"}
}