{
  "type": "Feature",
  "properties": {
    "addr:full":"95125 Catania Catania Catania 95125",
    "addr:postcode":"95125;95125",
    "iso:country":"IT",
    "sg:address":"95125 Catania",
    "sg:city":"Catania",
    "sg:orig_category":"Servizi Culturali E Per Lo Spettacolo",
    "sg:phone":"+39 095 334866",
    "sg:postcode":"95125",
    "sg:province":"Catania",
    "sg:website":"http://www.multisalaplanet.it",
    "wof:name":"Cinema Planet",
    "wof:placetype":"venue"
},
  "geometry": {"coordinates":[15.09398,37.536095],"type":"Point"}
}