{
  "type": "Feature",
  "properties": {
    "iso:country":"IT",
    "sg:address":"25032 Chiari",
    "sg:city":"Chiari",
    "sg:orig_category":"Televisori, Videoregistratori E Radio - Vendita Al Dettaglio",
    "sg:phone":"+39 030 711465",
    "sg:postcode":"25032",
    "sg:province":"Brescia",
    "wof:name":"Gamefree Srl",
    "wof:placetype":"venue"
},
  "geometry": {"coordinates":[9.614247,45.640415],"type":"Point"}
}