{
  "type": "Feature",
  "properties": {
    "addr:full":"Piazza Vittorio; Negrar; 37024 Negrar Verona 37024",
    "addr:postcode":"37024;37024",
    "addr:street":"Piazza Vittorio Negrar",
    "iso:country":"IT",
    "sg:address":"Piazza Vittorio; Negrar; 37024",
    "sg:city":"Negrar",
    "sg:classifiers":[
        {
            "category":"Banks & Credit Unions",
            "subcategory":"Bank",
            "type":"Services"
        }
    ],
    "sg:phone":"+39 045 750 0900",
    "sg:postcode":"37024",
    "sg:province":"Verona",
    "wof:name":"Cariverona Banca Spa",
    "wof:placetype":"venue"
},
  "geometry": {"coordinates":[10.938515,45.530605],"type":"Point"}
}