{
  "type": "Feature",
  "properties": {
    "iso:country":"IT",
    "sg:address":"38068 Rovereto",
    "sg:city":"Rovereto",
    "sg:orig_category":"Scuole E Servizi Scolastici. Servizi Ausiliari Dei Mezzi Di Trasporto. Ricerca, Selezione E Formazione Del Personale",
    "sg:phone":"+39 0464 434121",
    "sg:postcode":"38068",
    "sg:province":"Trento",
    "wof:name":"Caldiroli Enrico",
    "wof:placetype":"venue"
},
  "geometry": {"coordinates":[11.03987,45.890648],"type":"Point"}
}