{
  "type": "Feature",
  "properties": {
    "iso:country":"IT",
    "sg:address":"1, Via Acquachiara 04022 Fondi",
    "sg:city":"Fondi",
    "sg:classifiers":[
        {
            "category":"Manufacturing",
            "subcategory":"Food",
            "type":"Manufacturing & Wholesale Goods"
        }
    ],
    "sg:phone":"+39 0771 511929",
    "sg:postcode":"04022",
    "sg:province":"Latina",
    "sg:tags":[
        "equipment",
        "processing",
        "-",
        "machinery"
    ],
    "wof:name":"I.co.el. Srl",
    "wof:placetype":"venue"
},
  "geometry": {"coordinates":[13.3932247162,41.3365783691],"type":"Point"}
}