{
  "type": "Feature",
  "properties": {
    "iso:country":"IT",
    "sg:address":"S. Regolo 53013 Gaiole In Chianti",
    "sg:city":"Gaiole in Chianti",
    "sg:classifiers":[
        {
            "category":"Food & Beverages",
            "subcategory":"Groceries & Convenience Stores",
            "type":"Retail Goods"
        }
    ],
    "sg:phone":"+39 0577 747188",
    "sg:postcode":"53013",
    "sg:province":"Siena",
    "sg:tags":[
        "drink"
    ],
    "wof:name":"Fattoria Castello Di Brolio",
    "wof:placetype":"venue"
},
  "geometry": {"coordinates":[11.330514,43.318661],"type":"Point"}
}