{
  "type": "Feature",
  "properties": {
    "iso:country":"IT",
    "sg:address":"95047 Patern\u00f2",
    "sg:orig_category":"Scuole E Servizi Scolastici. Servizi Per Lo Sport E Il Tempo Libero",
    "sg:phone":"+39 095 797 7764",
    "sg:postcode":"95047",
    "sg:province":"Catania",
    "wof:name":"A.c. Balletto Etneo",
    "wof:placetype":"venue"
},
  "geometry": {"coordinates":[14.868813,37.559101],"type":"Point"}
}