{
  "type": "Feature",
  "properties": {
    "addr:full":"87036 Rende Rende Cosenza 87036",
    "addr:postcode":"87036;87036",
    "iso:country":"IT",
    "sg:address":"87036 Rende",
    "sg:city":"Rende",
    "sg:orig_category":"Articoli Da Regalo. Hobbistica. Shopping",
    "sg:phone":"+39 0984 402242",
    "sg:postcode":"87036",
    "sg:province":"Cosenza",
    "wof:name":"Natura & Dintorni Di Raso Concetta",
    "wof:placetype":"venue"
},
  "geometry": {"coordinates":[16.24412,39.351288],"type":"Point"}
}