{
  "type": "Feature",
  "properties": {
    "iso:country":"IT",
    "sg:address":"23818 Pasturo",
    "sg:city":"Pasturo",
    "sg:orig_category":"Materiali Edili",
    "sg:phone":"+39 0341 919939",
    "sg:postcode":"23818",
    "sg:province":"Lecco",
    "wof:name":"Bergamini Giovanni Alessandro",
    "wof:placetype":"venue"
},
  "geometry": {"coordinates":[9.430552,45.908775],"type":"Point"}
}