{
  "type": "Feature",
  "properties": {
    "iso:country":"IT",
    "sg:address":"17, Via Bernini Gian Lorenzo 42100 Reggio Emilia",
    "sg:classifiers":[
        {
            "category":"Shopping",
            "subcategory":"Clothing, Apparel, & Fashions",
            "type":"Retail Goods"
        }
    ],
    "sg:phone":"+39 0522 513519",
    "sg:postcode":"42100",
    "sg:province":"Reggio Nell'Emilia",
    "sg:tags":[
        "clothes"
    ],
    "wof:name":"Maglificio Severi (s.n.c.)",
    "wof:placetype":"venue"
},
  "geometry": {"coordinates":[10.644171,44.733406],"type":"Point"}
}