{
  "type": "Feature",
  "properties": {
    "iso:country":"IT",
    "sg:address":"95129 Catania",
    "sg:city":"Catania",
    "sg:orig_category":"Apparecchiature Ed Attrezzature Meccaniche. Ricambi E Componenti Dei Mezzi Di Trasporto",
    "sg:phone":"+39 095 534884",
    "sg:postcode":"95129",
    "sg:province":"Catania",
    "wof:name":"Lo Re Domenico",
    "wof:placetype":"venue"
},
  "geometry": {"coordinates":[15.098457,37.508938],"type":"Point"}
}