{
  "type": "Feature",
  "properties": {
    "iso:country":"IT",
    "sg:address":"2, Via Prosecco 34016 Trieste",
    "sg:orig_category":"Miscellaneous Products",
    "sg:phone":"+39 39040215340",
    "sg:postcode":"34016",
    "sg:province":"Trieste",
    "wof:name":"Braut",
    "wof:placetype":"venue"
},
  "geometry": {"coordinates":[13.7885513306,45.6882820129],"type":"Point"}
}