{
  "type": "Feature",
  "properties": {
    "iso:country":"IT",
    "sg:address":"20019 Settimo Milanese",
    "sg:city":"Settimo Milanese",
    "sg:orig_category":"Macchine Utensili - Produzione",
    "sg:phone":"+39 02 3350 3710",
    "sg:postcode":"20019",
    "sg:province":"Milano",
    "wof:name":"Miraglia Di R. Pecorelli",
    "wof:placetype":"venue"
},
  "geometry": {"coordinates":[9.058551,45.465012],"type":"Point"}
}