{
  "type": "Feature",
  "properties": {
    "addr:full":"23, Via Fra' Nazareno Scolaro 95028 Valverde Valverde Catania 95028",
    "addr:postcode":"95028;95028",
    "addr:street":"Via Fra ' Nazareno Scolaro",
    "iso:country":"IT",
    "sg:address":"23, Via Fra' Nazareno Scolaro 95028 Valverde",
    "sg:city":"Valverde",
    "sg:classifiers":[
        {
            "category":"Manufacturing",
            "subcategory":"Rubber & Plastics",
            "type":"Manufacturing & Wholesale Goods"
        }
    ],
    "sg:phone":"+39 39095524866",
    "sg:postcode":"95028",
    "sg:province":"Catania",
    "wof:name":"2 P.v. (s.r.l.)",
    "wof:placetype":"venue"
},
  "geometry": {"coordinates":[15.1229715347,37.5808944702],"type":"Point"}
}