{
  "type": "Feature",
  "properties": {
    "iso:country":"IT",
    "sg:address":"152, Frazione Marischio 60044 Fabriano",
    "sg:city":"Fabriano",
    "sg:classifiers":[
        {
            "category":"Shopping",
            "subcategory":"Computers & Home Electronics",
            "type":"Retail Goods"
        }
    ],
    "sg:phone":"+39 39073221944",
    "sg:postcode":"60044",
    "sg:province":"Ancona",
    "sg:tags":[
        "electronic",
        "electrical",
        "equipment"
    ],
    "wof:name":"Eurokappa S.r.l",
    "wof:placetype":"venue"
},
  "geometry": {"coordinates":[12.870876,43.340626],"type":"Point"}
}