{
  "type": "Feature",
  "properties": {
    "addr:full":"01033 Civita Castellana Civita Castellana Viterbo 01033",
    "addr:postcode":"01033;01033",
    "iso:country":"IT",
    "sg:address":"01033 Civita Castellana",
    "sg:city":"Civita Castellana",
    "sg:orig_category":"Prodotti Finiti Stampati. Forniture Per Attivita' Commerciali Ed Artigianali",
    "sg:phone":"+39 0761 518152",
    "sg:postcode":"01033",
    "sg:province":"Viterbo",
    "wof:name":"Polistampa Linea Decoro Srl",
    "wof:placetype":"venue"
},
  "geometry": {"coordinates":[12.4161987305,42.3235473633],"type":"Point"}
}