{
  "type": "Feature",
  "properties": {
    "addr:full":"88041 Decollatura Decollatura Catanzaro 88041",
    "addr:postcode":"88041;88041",
    "iso:country":"IT",
    "sg:address":"88041 Decollatura",
    "sg:city":"Decollatura",
    "sg:orig_category":"Prodotti E Manufatti In Materie Plastiche. Articoli Per Imballaggio E Confezionamento",
    "sg:phone":"+39 0968 663826",
    "sg:postcode":"88041",
    "sg:province":"Catanzaro",
    "wof:name":"Ecoplast Sas",
    "wof:placetype":"venue"
},
  "geometry": {"coordinates":[16.3581523895,39.0538864136],"type":"Point"}
}