{
  "type": "Feature",
  "properties": {
    "iso:country":"IT",
    "sg:address":"20090 Assago",
    "sg:city":"Assago",
    "sg:orig_category":"Legatorie",
    "sg:phone":"+39 02 4570 1680",
    "sg:postcode":"20090",
    "sg:province":"Milano",
    "wof:name":"Giovanazzi Aldo Legatoria Volvinio",
    "wof:placetype":"venue"
},
  "geometry": {"coordinates":[9.122938,45.405048],"type":"Point"}
}