{
  "type": "Feature",
  "properties": {
    "addr:full":"Via Gallarate 273/6 20151 Milano Milano Milano 20151",
    "addr:housenumber":"273 / 6",
    "addr:postcode":"20151;20151",
    "addr:street":"Via Gallarate",
    "iso:country":"IT",
    "sg:address":"Via Gallarate 273/6 20151 Milano",
    "sg:city":"Milano",
    "sg:orig_category":"Calendar Hangers, String Hangers",
    "sg:phone":"+39 02 3800 9031",
    "sg:postcode":"20151",
    "sg:province":"Milano",
    "sg:website":"www.amia.it",
    "wof:name":"Amia Binding Srl",
    "wof:placetype":"venue"
},
  "geometry": {"coordinates":[9.117256,45.501209],"type":"Point"}
}