{
  "type": "Feature",
  "properties": {
    "iso:country":"IT",
    "sg:address":"25020 Bassano Bresciano",
    "sg:city":"Bassano Bresciano",
    "sg:orig_category":"Poliuretano",
    "sg:phone":"+39 030 993 5002",
    "sg:postcode":"25020",
    "sg:province":"Brescia",
    "sg:website":"http://www.pelma.com",
    "wof:name":"Pelma Spa",
    "wof:placetype":"venue"
},
  "geometry": {"coordinates":[10.1256380081,45.3272895813],"type":"Point"}
}