{
  "type": "Feature",
  "properties": {
    "iso:country":"IT",
    "sg:address":"8, Via Della Porta Giacomo 22100 Como",
    "sg:city":"Como",
    "sg:classifiers":[
        {
            "category":"Real Estate",
            "subcategory":"Architect",
            "type":"Services"
        }
    ],
    "sg:phone":"+39 39031523290",
    "sg:postcode":"22100",
    "sg:province":"Como",
    "sg:tags":[
        "textile",
        "clothing"
    ],
    "wof:name":"Tessiture Cavalleri & C. (s.a.s.)",
    "wof:placetype":"venue"
},
  "geometry": {"coordinates":[9.085456,45.811966],"type":"Point"}
}