{
  "type": "Feature",
  "properties": {
    "addr:full":"25010 Isorella Isorella Brescia 25010",
    "addr:postcode":"25010;25010",
    "iso:country":"IT",
    "sg:address":"25010 Isorella",
    "sg:city":"Isorella",
    "sg:orig_category":"Forniture Per Agricoltura E Zootecnia",
    "sg:phone":"+39 030 995 2150",
    "sg:postcode":"25010",
    "sg:province":"Brescia",
    "wof:name":"Zizioli Carlo & Figli Di Zizioli Enio E C. S.n.c.",
    "wof:placetype":"venue"
},
  "geometry": {"coordinates":[10.3211421967,45.305065155],"type":"Point"}
}