{
  "type": "Feature",
  "properties": {
    "iso:country":"IT",
    "sg:address":"Contrada Fornelle 84030 Monte San Giacomo",
    "sg:city":"Monte San Giacomo",
    "sg:classifiers":[
        {
            "category":"Real Estate",
            "subcategory":"Architect",
            "type":"Services"
        }
    ],
    "sg:phone":"+39 39097575585",
    "sg:postcode":"84030",
    "sg:province":"Salerno",
    "sg:tags":[
        "textile",
        "clothing"
    ],
    "wof:name":"Indossa S.r.l.",
    "wof:placetype":"venue"
},
  "geometry": {"coordinates":[14.765912,40.677956],"type":"Point"}
}