{
  "type": "Feature",
  "properties": {
    "addr:full":"92/96, Strada S. Secondo 10064 Pinerolo Pinerolo Torino 10064",
    "addr:housenumber":"92 / 96",
    "addr:postcode":"10064;10064",
    "addr:street":"Strada S. Secondo",
    "iso:country":"IT",
    "sg:address":"92/96, Strada S. Secondo 10064 Pinerolo",
    "sg:city":"Pinerolo",
    "sg:classifiers":[
        {
            "category":"Shopping",
            "type":"Retail Goods"
        }
    ],
    "sg:phone":"+39 39012175144",
    "sg:postcode":"10064",
    "sg:province":"Torino",
    "sg:tags":[
        "finished",
        "-",
        "metallic"
    ],
    "wof:name":"Tecnolinea Di Buson Francesco",
    "wof:placetype":"venue"
},
  "geometry": {"coordinates":[7.6866188049,45.0705604553],"type":"Point"}
}