{
  "type": "Feature",
  "properties": {
    "addr:full":"Via Ciarpi 6 55016 Porcari Porcari Lucca 55016",
    "addr:housenumber":"6",
    "addr:postcode":"55016;55016",
    "addr:street":"Via Ciarpi",
    "iso:country":"IT",
    "sg:address":"Via Ciarpi 6 55016 Porcari",
    "sg:city":"Porcari",
    "sg:classifiers":[
        {
            "category":"Utilities",
            "subcategory":"Natural Gas",
            "type":"Services"
        }
    ],
    "sg:phone":"+39 0583 295855",
    "sg:postcode":"55016",
    "sg:province":"Lucca",
    "sg:tags":[
        "plant"
    ],
    "sg:website":"www.nuovaomma.it",
    "wof:name":"Nuova Omma Srl",
    "wof:placetype":"venue"
},
  "geometry": {"coordinates":[10.6048717499,43.8495788574],"type":"Point"}
}