{
  "type": "Feature",
  "properties": {
    "iso:country":"IT",
    "sg:address":"06089 Torgiano",
    "sg:city":"Torgiano",
    "sg:orig_category":"Marmo, Pietre Ed Affini",
    "sg:phone":"+39 075 982542",
    "sg:postcode":"06089",
    "sg:province":"Perugia",
    "wof:name":"International Marmi Srl",
    "wof:placetype":"venue"
},
  "geometry": {"coordinates":[12.413372,43.0233],"type":"Point"}
}