{
  "type": "Feature",
  "properties": {
    "iso:country":"IT",
    "sg:address":"46100 Mantova",
    "sg:city":"Mantova",
    "sg:orig_category":"Abbigliamento Esterno, Maglierie E Pelliccerie. Shopping",
    "sg:phone":"+39 0376 363635",
    "sg:postcode":"46100",
    "sg:province":"Mantova",
    "wof:name":"Abm Marketing Snc",
    "wof:placetype":"venue"
},
  "geometry": {"coordinates":[10.79214,45.157013],"type":"Point"}
}