{
  "type": "Feature",
  "properties": {
    "addr:full":"1/3, Cascina S. Lucia 26020 Agnadello Agnadello Cremona 26020",
    "addr:housenumber":"1 / 3",
    "addr:postcode":"26020;26020",
    "addr:street":"Cascina S. Lucia",
    "iso:country":"IT",
    "sg:address":"1/3, Cascina S. Lucia 26020 Agnadello",
    "sg:city":"Agnadello",
    "sg:classifiers":[
        {
            "category":"Food & Beverages",
            "subcategory":"Dairy",
            "type":"Retail Goods"
        }
    ],
    "sg:phone":"+39 39037393048",
    "sg:postcode":"26020",
    "sg:province":"Cremona",
    "sg:tags":[
        "product"
    ],
    "wof:name":"Caseificio Del Cigno (s.p.a.)",
    "wof:placetype":"venue"
},
  "geometry": {"coordinates":[10.026135,45.133499],"type":"Point"}
}