{
  "type": "Feature",
  "properties": {
    "addr:full":"13871 Verrone Verrone Biella 13871",
    "addr:postcode":"13871;13871",
    "iso:country":"IT",
    "sg:address":"13871 Verrone",
    "sg:city":"Verrone",
    "sg:orig_category":"Filati E Materie Prime Tessili",
    "sg:phone":"+39 015 255 8056",
    "sg:postcode":"13871",
    "sg:province":"Biella",
    "wof:name":"Novalfa Di Gian Piero Argentero & C. (s.a.s.)",
    "wof:placetype":"venue"
},
  "geometry": {"coordinates":[8.0969457626,45.5593109131],"type":"Point"}
}