{
  "type": "Feature",
  "properties": {
    "addr:full":"6/8, Via Verga Giovanni 20020 Lainate Lainate Milano 20020",
    "addr:housenumber":"6 / 8",
    "addr:postcode":"20020;20020",
    "addr:street":"Via Verga Giovanni",
    "iso:country":"IT",
    "sg:address":"6/8, Via Verga Giovanni 20020 Lainate",
    "sg:city":"Lainate",
    "sg:classifiers":[
        {
            "category":"Manufacturing",
            "subcategory":"Metals",
            "type":"Manufacturing & Wholesale Goods"
        }
    ],
    "sg:phone":"+39 02 9357 1012",
    "sg:postcode":"20020",
    "sg:province":"Milano",
    "sg:tags":[
        "metallurgy",
        "metalworking"
    ],
    "wof:name":"Gtg (s.p.a.)",
    "wof:placetype":"venue"
},
  "geometry": {"coordinates":[9.1881408691,45.4636878967],"type":"Point"}
}