{
  "type": "Feature",
  "properties": {
    "addr:full":"00044 Frascati Frascati Roma 00044",
    "addr:postcode":"00044;00044",
    "iso:country":"IT",
    "sg:address":"00044 Frascati",
    "sg:city":"Frascati",
    "sg:orig_category":"Valvole E Apparecchiature Di Misura",
    "sg:phone":"+39 06 942 4573",
    "sg:postcode":"00044",
    "sg:province":"Roma",
    "wof:name":"D'agostini Gastone",
    "wof:placetype":"venue"
},
  "geometry": {"coordinates":[12.680842,41.810047],"type":"Point"}
}