{
  "type": "Feature",
  "properties": {
    "iso:country":"IT",
    "sg:address":"22, Via Della Concordia 06063 Magione",
    "sg:city":"Magione",
    "sg:classifiers":[
        {
            "category":"Travel",
            "subcategory":"Travel Agent",
            "type":"Entertainment"
        }
    ],
    "sg:phone":"+39 075 847 9246",
    "sg:postcode":"06063",
    "sg:province":"Perugia",
    "sg:tags":[
        "business"
    ],
    "wof:name":"Towers Hotel Srl",
    "wof:placetype":"venue"
},
  "geometry": {"coordinates":[12.257149,43.085518],"type":"Point"}
}