{
  "type": "Feature",
  "properties": {
    "addr:full":"80046 San Giorgio A Cremano San Giorgio a Cremano Napoli 80046",
    "addr:housenumber":"80046",
    "addr:postcode":"80046",
    "addr:street":"San",
    "iso:country":"IT",
    "sg:address":"80046 San Giorgio A Cremano",
    "sg:city":"San Giorgio a Cremano",
    "sg:orig_category":"Abiti Da Sposa E Cerimonia",
    "sg:phone":"+39 081 273235",
    "sg:postcode":"80046",
    "sg:province":"Napoli",
    "wof:name":"Di Tuoro Luciana",
    "wof:placetype":"venue"
},
  "geometry": {"coordinates":[14.334578,40.831291],"type":"Point"}
}