{
  "type": "Feature",
  "properties": {
    "iso:country":"IT",
    "sg:address":"50122 Firenze",
    "sg:city":"Firenze",
    "sg:classifiers":[
        {
            "category":"Professional",
            "subcategory":"Advertising",
            "type":"Services"
        }
    ],
    "sg:phone":"+39 055 267171",
    "sg:postcode":"50122",
    "sg:province":"Firenze",
    "sg:tags":[
        "marketing",
        "communication"
    ],
    "wof:name":"Centro Di Telemarketing Spa",
    "wof:placetype":"venue"
},
  "geometry": {"coordinates":[11.256194,43.773697],"type":"Point"}
}