{
  "type": "Feature",
  "properties": {
    "addr:full":"41043 Formigine Formigine Modena 41043",
    "addr:postcode":"41043;41043",
    "iso:country":"IT",
    "sg:address":"41043 Formigine",
    "sg:city":"Formigine",
    "sg:orig_category":"Fonderie",
    "sg:phone":"+39 059 552342",
    "sg:postcode":"41043",
    "sg:province":"Modena",
    "wof:name":"Sin-mecc Srl",
    "wof:placetype":"venue"
},
  "geometry": {"coordinates":[10.8544740677,44.5595855713],"type":"Point"}
}