{
  "type": "Feature",
  "properties": {
    "addr:full":"10125 Torino Torino Torino 10125",
    "addr:postcode":"10125;10125",
    "iso:country":"IT",
    "sg:address":"10125 Torino",
    "sg:city":"Torino",
    "sg:orig_category":"Prodotti Finiti Stampati. Shopping. Regalistica Aziendale",
    "sg:phone":"+39 011 650 4636",
    "sg:postcode":"10125",
    "sg:province":"Torino",
    "wof:name":"Ediposters Srl",
    "wof:placetype":"venue"
},
  "geometry": {"coordinates":[7.6810922623,45.0576133728],"type":"Point"}
}