{
  "type": "Feature",
  "properties": {
    "iso:country":"IT",
    "sg:address":"10144 Torino",
    "sg:city":"Torino",
    "sg:orig_category":"Servizi Culturali E Per Lo Spettacolo. Arte Ed Artigianato Artistico. Servizi Al Turismo",
    "sg:phone":"+39 011 437 7770",
    "sg:postcode":"10144",
    "sg:province":"Torino",
    "wof:name":"Galleria Sant'agostino",
    "wof:placetype":"venue"
},
  "geometry": {"coordinates":[7.656007,45.08379],"type":"Point"}
}