{
  "type": "Feature",
  "properties": {
    "iso:country":"IT",
    "sg:address":"Via Rosson 32020 Rivamonte Agordino",
    "sg:city":"Rivamonte Agordino",
    "sg:classifiers":[
        {
            "category":"Manufacturing",
            "subcategory":"Glass & Minerals",
            "type":"Manufacturing & Wholesale Goods"
        }
    ],
    "sg:phone":"+39 0437 60071",
    "sg:postcode":"32020",
    "sg:province":"Belluno",
    "sg:tags":[
        "frame"
    ],
    "wof:name":"Gailo Srl",
    "wof:placetype":"venue"
},
  "geometry": {"coordinates":[12.02352,46.253433],"type":"Point"}
}