{
  "type": "Feature",
  "properties": {
    "iso:country":"IT",
    "sg:address":"00136 Roma",
    "sg:city":"Roma",
    "sg:orig_category":"Servizi E Lavori Industria Della Gomma",
    "sg:phone":"+39 06 3540 2639",
    "sg:postcode":"00136",
    "sg:province":"Roma",
    "wof:name":"F.lli Farnese Srl",
    "wof:placetype":"venue"
},
  "geometry": {"coordinates":[12.438209,41.91795],"type":"Point"}
}