{
  "type": "Feature",
  "properties": {
    "iso:country":"IT",
    "sg:address":"50062 Dicomano",
    "sg:city":"Dicomano",
    "sg:orig_category":"Borse E Borsette - Produzione E Ingrosso",
    "sg:phone":"+39 055 838 6904",
    "sg:postcode":"50062",
    "sg:province":"Firenze",
    "wof:name":"Dream.net Srl",
    "wof:placetype":"venue"
},
  "geometry": {"coordinates":[11.216123,43.711266],"type":"Point"}
}