{
  "type": "Feature",
  "properties": {
    "addr:full":"41100 Modena Modena Modena 41100",
    "addr:postcode":"41100;41100",
    "iso:country":"IT",
    "sg:address":"41100 Modena",
    "sg:city":"Modena",
    "sg:orig_category":"Metalli Non Ferrosi E Leghe",
    "sg:phone":"+39 059 250411",
    "sg:postcode":"41100",
    "sg:province":"Modena",
    "wof:name":"Emilbronzo 2000 Srl",
    "wof:placetype":"venue"
},
  "geometry": {"coordinates":[10.9605064392,44.6529541016],"type":"Point"}
}