{
  "type": "Feature",
  "properties": {
    "addr:full":"10042 Nichelino Nichelino Torino 10042",
    "addr:postcode":"10042;10042",
    "iso:country":"IT",
    "sg:address":"10042 Nichelino",
    "sg:city":"Nichelino",
    "sg:orig_category":"Minuterie Metalliche E Ferramenta",
    "sg:phone":"+39 011 624476",
    "sg:postcode":"10042",
    "sg:province":"Torino",
    "wof:name":"Mollificio Comino & Stucchi S.n.c. Di Fontanella Fulvio & C.",
    "wof:placetype":"venue"
},
  "geometry": {"coordinates":[7.6369752884,44.9739494324],"type":"Point"}
}