{
  "type": "Feature",
  "properties": {
    "iso:country":"IT",
    "sg:address":"09100 Cagliari",
    "sg:orig_category":"Formaggi E Latticini - Vendita Al Dettaglio",
    "sg:phone":"+39 070 543230",
    "sg:province":"CA",
    "wof:name":"Potentina Srl",
    "wof:placetype":"venue"
},
  "geometry": {"coordinates":[9.0414896011,44.512260437],"type":"Point"}
}