{
  "type": "Feature",
  "properties": {
    "iso:country":"IT",
    "sg:address":"20121 Milano",
    "sg:city":"Milano",
    "sg:orig_category":"Servizi Di Magazzinaggio E Movimentazione",
    "sg:phone":"+39 02 722151",
    "sg:postcode":"20121",
    "sg:province":"Milano",
    "wof:name":"Magazzini Generali Fiduciari Della Cassa Di Risparmio Delle Provincie Lombarde (s.p.a.)",
    "wof:placetype":"venue"
},
  "geometry": {"coordinates":[9.184058,45.471512],"type":"Point"}
}