{
  "type": "Feature",
  "properties": {
    "addr:full":"50022 Greve In Chianti Greve in Chianti Firenze 50022",
    "addr:postcode":"50022;50022",
    "iso:country":"IT",
    "sg:address":"50022 Greve In Chianti",
    "sg:city":"Greve in Chianti",
    "sg:classifiers":[
        {
            "category":"Manufacturing",
            "subcategory":"Paper Products",
            "type":"Manufacturing & Wholesale Goods"
        }
    ],
    "sg:phone":"+39 055 858 8816",
    "sg:postcode":"50022",
    "sg:province":"Firenze",
    "sg:tags":[
        "supply",
        "material",
        "primary",
        "packaging",
        "packing",
        "products",
        "cardboard"
    ],
    "wof:name":"Grafiche Arcobaleno Snc",
    "wof:placetype":"venue"
},
  "geometry": {"coordinates":[11.3204164505,43.5906410217],"type":"Point"}
}