{
  "type": "Feature",
  "properties": {
    "iso:country":"IT",
    "sg:address":"61020 Sant'angelo In Lizzola",
    "sg:city":"Montecchio",
    "sg:orig_category":"Etichette Autoadesive",
    "sg:phone":"+39 0721 499332",
    "sg:postcode":"61020",
    "sg:province":"Pesaro E Urbino",
    "sg:website":"http://www.pesaro.com/studio83",
    "wof:name":"Studio 83 Di Piovaticci A. & C. Snc",
    "wof:placetype":"venue"
},
  "geometry": {"coordinates":[12.802631,43.826019],"type":"Point"}
}