{
  "type": "Feature",
  "properties": {
    "iso:country":"IT",
    "sg:address":"60121 Ancona",
    "sg:city":"Ancona",
    "sg:orig_category":"Gioielleria, Oreficeria E Argenteria. Shopping",
    "sg:phone":"+39 071 203679",
    "sg:postcode":"60121",
    "sg:province":"Ancona",
    "sg:website":"http://gioielleriagiorgi.it",
    "wof:name":"Giorgi Mario & C. Snc Gioielleria",
    "wof:placetype":"venue"
},
  "geometry": {"coordinates":[13.514827,43.618267],"type":"Point"}
}