{
  "type": "Feature",
  "properties": {
    "addr:full":"Via Masi 249; S. Bartolomeo In Bosco; 44040",
    "addr:housenumber":"249",
    "addr:postcode":"44040",
    "addr:street":"Via Masi;S. Bartolomeo In Bosco",
    "iso:country":"IT",
    "sg:address":"Via Masi 249; S. Bartolomeo In Bosco; 44040",
    "sg:classifiers":[
        {
            "category":"Banks & Credit Unions",
            "subcategory":"Bank",
            "type":"Services"
        }
    ],
    "sg:phone":"+39 0532 725800",
    "wof:name":"Rolo Banca 1473 Spa",
    "wof:placetype":"venue"
},
  "geometry": {"coordinates":[11.63302,44.731125],"type":"Point"}
}