{
  "type": "Feature",
  "properties": {
    "iso:country":"IT",
    "sg:address":"Via Empoli 14a 06016 San Giustino",
    "sg:city":"San Giustino",
    "sg:classifiers":[
        {
            "category":"Manufacturing",
            "subcategory":"Metals",
            "type":"Manufacturing & Wholesale Goods"
        }
    ],
    "sg:phone":"+39 075 856278",
    "sg:postcode":"06016",
    "sg:province":"Perugia",
    "sg:tags":[
        "mould",
        "aluminium",
        "industry",
        "plastic"
    ],
    "sg:website":"www.combossrl.com",
    "wof:name":"Combos Srl",
    "wof:placetype":"venue"
},
  "geometry": {"coordinates":[12.16721,43.556904],"type":"Point"}
}