{
  "type": "Feature",
  "properties": {
    "iso:country":"IT",
    "sg:address":"20154 Milano",
    "sg:city":"Milano",
    "sg:orig_category":"Termotecnica E Riscaldamento, Apparecchiature E Servizi",
    "sg:phone":"+39 02 315832",
    "sg:postcode":"20154",
    "sg:province":"Milano",
    "wof:name":"M.g.m. Di Moretti Giancarlo",
    "wof:placetype":"venue"
},
  "geometry": {"coordinates":[9.17468,45.481865],"type":"Point"}
}