{
  "type": "Feature",
  "properties": {
    "addr:full":"12020 Venasca Venasca Cuneo 12020",
    "addr:housenumber":"12020",
    "addr:postcode":"12020",
    "addr:street":"Venasca Venasca",
    "iso:country":"IT",
    "sg:address":"12020 Venasca",
    "sg:city":"Venasca",
    "sg:orig_category":"Non-classified Establishments",
    "sg:phone":"+39 0175 567364",
    "sg:postcode":"12020",
    "sg:province":"Cuneo",
    "wof:name":"Allasina Lorenzina",
    "wof:placetype":"venue"
},
  "geometry": {"coordinates":[7.394256,44.562721],"type":"Point"}
}