{
  "type": "Feature",
  "properties": {
    "addr:full":"10060 Pancalieri Pancalieri Torino 10060",
    "addr:postcode":"10060;10060",
    "iso:country":"IT",
    "sg:address":"10060 Pancalieri",
    "sg:city":"Pancalieri",
    "sg:orig_category":"Prodotti Di Base E Forniture Per Industria Alimentare E Bevande. Prodotti Chimici Di Base",
    "sg:phone":"+39 011 973 5077",
    "sg:postcode":"10060",
    "sg:province":"Torino",
    "wof:name":"Chialva Nicolao Di Dr. Franco Chialva E C. (s.a.s.)",
    "wof:placetype":"venue"
},
  "geometry": {"coordinates":[7.6882667542,45.0674858093],"type":"Point"}
}