{
  "type": "Feature",
  "properties": {
    "addr:full":"15033 Casale Monferrato Casale Monferrato Alessandria 15033",
    "addr:postcode":"15033;15033",
    "iso:country":"IT",
    "sg:address":"15033 Casale Monferrato",
    "sg:city":"Casale Monferrato",
    "sg:orig_category":"Forniture Per Attivita' Commerciali Ed Artigianali",
    "sg:phone":"+39 0142 74970",
    "sg:postcode":"15033",
    "sg:province":"Alessandria",
    "wof:name":"Tuttobocce Di Martinotti Roberto",
    "wof:placetype":"venue"
},
  "geometry": {"coordinates":[8.4690694809,45.1263008118],"type":"Point"}
}