{
  "type": "Feature",
  "properties": {
    "addr:full":"21049 Tradate Tradate Varese 21049",
    "addr:postcode":"21049;21049",
    "iso:country":"IT",
    "sg:address":"21049 Tradate",
    "sg:city":"Tradate",
    "sg:orig_category":"Assemblaggio Conto Terzi",
    "sg:phone":"+39 0331 843929",
    "sg:postcode":"21049",
    "sg:province":"Varese",
    "wof:name":"M. V. Di Iseppi Claudio",
    "wof:placetype":"venue"
},
  "geometry": {"coordinates":[8.822273,45.824196],"type":"Point"}
}