{
  "type": "Feature",
  "properties": {
    "addr:full":"Zona Pip 85020 Atella Atella Potenza 85020",
    "addr:postcode":"85020;85020",
    "addr:street":"Zona Pip",
    "iso:country":"IT",
    "sg:address":"Zona Pip 85020 Atella",
    "sg:city":"Atella",
    "sg:classifiers":[
        {
            "category":"Food & Beverages",
            "subcategory":"Fruits & Vegetables",
            "type":"Retail Goods"
        }
    ],
    "sg:phone":"+39 0972 715212",
    "sg:postcode":"85020",
    "sg:province":"Potenza",
    "sg:tags":[
        "juice",
        "nectar"
    ],
    "sg:website":"www.midisucci.it",
    "wof:name":"Midi' Srl",
    "wof:placetype":"venue"
},
  "geometry": {"coordinates":[15.8022212982,40.6372413635],"type":"Point"}
}