{
  "type": "Feature",
  "properties": {
    "iso:country":"IT",
    "sg:address":"06084 Bettona",
    "sg:city":"Bettona",
    "sg:orig_category":"Serramenti Ed Infissi",
    "sg:phone":"+39 075 986 9818",
    "sg:postcode":"06084",
    "sg:province":"Perugia",
    "wof:name":"Ferplastik Sas",
    "wof:placetype":"venue"
},
  "geometry": {"coordinates":[12.50817,43.021717],"type":"Point"}
}