{
  "type": "Feature",
  "properties": {
    "iso:country":"IT",
    "sg:address":"15, Via Filzi Fabio 20026 Novate Milanese",
    "sg:city":"Novate Milanese",
    "sg:classifiers":[
        {
            "category":"Professional",
            "subcategory":"Engineering",
            "type":"Services"
        }
    ],
    "sg:phone":"+39 39023542304",
    "sg:postcode":"20026",
    "sg:province":"Milano",
    "sg:tags":[
        "machine",
        "-",
        "mechanical"
    ],
    "wof:name":"Secem (s.r.l.)",
    "wof:placetype":"venue"
},
  "geometry": {"coordinates":[9.150859,45.526516],"type":"Point"}
}