{
  "type": "Feature",
  "properties": {
    "addr:full":"80136 Napoli Napoli Napoli 80136",
    "addr:housenumber":"80136",
    "addr:postcode":"80136",
    "iso:country":"IT",
    "sg:address":"80136 Napoli",
    "sg:city":"Napoli",
    "sg:orig_category":"Gioielleria, Oreficeria E Argenteria. Shopping",
    "sg:phone":"+39 081 544 3724",
    "sg:postcode":"80136",
    "sg:province":"Napoli",
    "wof:name":"F.lli Petacca Snc Gioielli",
    "wof:placetype":"venue"
},
  "geometry": {"coordinates":[14.235469,40.854733],"type":"Point"}
}