{
  "type": "Feature",
  "properties": {
    "addr:full":"40068 San Lazzaro Di Savena San Lazzaro Bologna 40068",
    "addr:housenumber":"40068",
    "addr:postcode":"40068",
    "addr:street":"San;San;Bologna",
    "iso:country":"IT",
    "sg:address":"40068 San Lazzaro Di Savena",
    "sg:city":"San Lazzaro",
    "sg:orig_category":"Servizi E Lavori Industria Chimica. Riparazione Dei Mezzi Di Trasporto",
    "sg:phone":"+39 051 625 5211",
    "sg:postcode":"40068",
    "sg:province":"Bologna",
    "wof:name":"Verniciatura Emiliana Snc Di Braglia",
    "wof:placetype":"venue"
},
  "geometry": {"coordinates":[11.392478,44.504509],"type":"Point"}
}