{
  "type": "Feature",
  "properties": {
    "iso:country":"IT",
    "sg:address":"20135 Milano",
    "sg:city":"Milano",
    "sg:orig_category":"Macchine E Forniture Per Arredamento E Industria Del Legno",
    "sg:phone":"+39 02 5518 0123",
    "sg:postcode":"20135",
    "sg:province":"Milano",
    "wof:name":"Pianeta Porte",
    "wof:placetype":"venue"
},
  "geometry": {"coordinates":[9.149718,45.388054],"type":"Point"}
}