{
  "type": "Feature",
  "properties": {
    "iso:country":"IT",
    "sg:address":"1, Zona Industriale 66030 Treglio",
    "sg:city":"Treglio",
    "sg:classifiers":[
        {
            "category":"Food & Beverages",
            "subcategory":"Groceries & Convenience Stores",
            "type":"Retail Goods"
        }
    ],
    "sg:phone":"+39 39087243981",
    "sg:postcode":"66030",
    "sg:province":"Chieti",
    "sg:tags":[
        "product",
        "related"
    ],
    "wof:name":"Sansifici Vecere Srl",
    "wof:placetype":"venue"
},
  "geometry": {"coordinates":[14.4314279556,42.2632904053],"type":"Point"}
}