{
  "type": "Feature",
  "properties": {
    "addr:full":"6/10, Via Adda 21043 Castiglione Olona Castiglione Olona Varese 21043",
    "addr:housenumber":"6 / 10",
    "addr:postcode":"21043;21043",
    "addr:street":"Via Adda",
    "iso:country":"IT",
    "sg:address":"6/10, Via Adda 21043 Castiglione Olona",
    "sg:city":"Castiglione Olona",
    "sg:classifiers":[
        {
            "category":"Professional",
            "subcategory":"Engineering",
            "type":"Services"
        }
    ],
    "sg:phone":"+39 0331 850606",
    "sg:postcode":"21043",
    "sg:province":"Varese",
    "sg:tags":[
        "machine",
        "-",
        "mechanical"
    ],
    "wof:name":"Tecnogamma (s.n.c.)",
    "wof:placetype":"venue"
},
  "geometry": {"coordinates":[8.870505,45.7873],"type":"Point"}
}