{
  "type": "Feature",
  "properties": {
    "iso:country":"IT",
    "sg:address":"03100 Frosinone",
    "sg:city":"Frosinone",
    "sg:orig_category":"Mobili Artistici In Stile - Vendita Al Dettaglio",
    "sg:phone":"+39 0775 200622",
    "sg:postcode":"03100",
    "sg:province":"Frosinone",
    "wof:name":"Ceccarelli Luigi E Salvatore",
    "wof:placetype":"venue"
},
  "geometry": {"coordinates":[13.337975502,41.6211013794],"type":"Point"}
}