{
  "type": "Feature",
  "properties": {
    "iso:country":"IT",
    "sg:address":"70023 Gioia Del Colle",
    "sg:city":"Gioia del Colle",
    "sg:orig_category":"Frigotecnica, Apparecchiature E Servizi. Climatizzazione E Condizionamento, Apparecchiature E Servizi",
    "sg:phone":"+39 080 343 2248",
    "sg:postcode":"70023",
    "sg:province":"Bari",
    "wof:name":"Master-milk Di Posa Giuseppe & Colucci Vito Antonio Snc",
    "wof:placetype":"venue"
},
  "geometry": {"coordinates":[16.8638286591,41.1275787354],"type":"Point"}
}