{
  "type": "Feature",
  "properties": {
    "addr:full":"20145 Milano Milano Milano 20145",
    "addr:postcode":"20145;20145",
    "iso:country":"IT",
    "sg:address":"20145 Milano",
    "sg:city":"Milano",
    "sg:orig_category":"Forniture Per Abbigliamento E Pelletterie",
    "sg:phone":"+39 02 4801 5954",
    "sg:postcode":"20145",
    "sg:province":"Milano",
    "wof:name":"Bengal",
    "wof:placetype":"venue"
},
  "geometry": {"coordinates":[9.1558046341,45.4685401917],"type":"Point"}
}