{
  "type": "Feature",
  "properties": {
    "addr:full":"80047 San Giuseppe Vesuviano San Giuseppe Vesuviano Napoli 80047",
    "addr:postcode":"80047;80047",
    "iso:country":"IT",
    "sg:address":"80047 San Giuseppe Vesuviano",
    "sg:city":"San Giuseppe Vesuviano",
    "sg:orig_category":"Ceramiche: Prodotti E Lavorazioni",
    "sg:phone":"+39 081 827 2292",
    "sg:postcode":"80047",
    "sg:province":"Napoli",
    "wof:name":"Cozzolino Ceramiche Sas",
    "wof:placetype":"venue"
},
  "geometry": {"coordinates":[14.550258,40.841335],"type":"Point"}
}