{
  "type": "Feature",
  "properties": {
    "iso:country":"IT",
    "sg:address":"20135 Milano",
    "sg:city":"Milano",
    "sg:orig_category":"Avvocati, Notai E Servizi Legali. Consulenze Tecniche, Amministrative E Perizie",
    "sg:postcode":"20135",
    "sg:province":"Milano",
    "wof:name":"Porta Checcacci & Associati Spa",
    "wof:placetype":"venue"
},
  "geometry": {"coordinates":[9.200465,45.451206],"type":"Point"}
}