{
  "type": "Feature",
  "properties": {
    "iso:country":"IT",
    "sg:address":"88050 Simeri Crichi",
    "sg:city":"Crichi",
    "sg:orig_category":"Articoli Regalo - Vendita Al Dettaglio",
    "sg:phone":"+39 0961 799074",
    "sg:postcode":"88050",
    "sg:province":"Catanzaro",
    "sg:website":"http://www.lorientale.com",
    "wof:name":"Haldeman Marie Louise",
    "wof:placetype":"venue"
},
  "geometry": {"coordinates":[16.641096,38.954853],"type":"Point"}
}