{
  "type": "Feature",
  "properties": {
    "iso:country":"IT",
    "sg:address":"00176 Roma",
    "sg:city":"Roma",
    "sg:orig_category":"Impianti, Attrezzature E Forniture Sanitarie Ed Ospedaliere",
    "sg:phone":"+39 06 298042",
    "sg:postcode":"00176",
    "sg:province":"Roma",
    "wof:name":"F.lli Della Marca Srl",
    "wof:placetype":"venue"
},
  "geometry": {"coordinates":[12.528592,41.885792],"type":"Point"}
}