{
  "type": "Feature",
  "properties": {
    "iso:country":"IT",
    "sg:address":"5, Via Stoppani 21013 Gallarate",
    "sg:city":"Gallarate",
    "sg:classifiers":[
        {
            "category":"Professional",
            "subcategory":"Engineering",
            "type":"Services"
        }
    ],
    "sg:phone":"+39 0331 782062",
    "sg:postcode":"21013",
    "sg:province":"Varese",
    "sg:tags":[
        "machine",
        "-",
        "mechanical"
    ],
    "wof:name":"Sommaruga (s.r.l.)",
    "wof:placetype":"venue"
},
  "geometry": {"coordinates":[8.786658,45.666584],"type":"Point"}
}