{
  "type": "Feature",
  "properties": {
    "addr:full":"22063 Cantu' Como 22063",
    "addr:postcode":"22063;22063",
    "addr:street":"Cantu ' Como",
    "iso:country":"IT",
    "sg:address":"22063 Cantu'",
    "sg:classifiers":[
        {
            "category":"Home & Garden",
            "subcategory":"Furniture",
            "type":"Retail Goods"
        }
    ],
    "sg:phone":"+39 031 707 3228",
    "sg:postcode":"22063",
    "sg:province":"Como",
    "sg:tags":[
        "furnishing"
    ],
    "wof:name":"Roberto Ventura Snc",
    "wof:placetype":"venue"
},
  "geometry": {"coordinates":[9.1188201904,45.7320785522],"type":"Point"}
}