{
  "type": "Feature",
  "properties": {
    "iso:country":"IT",
    "sg:address":"20144 Milano",
    "sg:city":"Milano",
    "sg:orig_category":"Agenzie D'affari E Servizi Commerciali",
    "sg:phone":"+39 02 481 7772",
    "sg:postcode":"20144",
    "sg:province":"Milano",
    "wof:name":"Chimienti Rocco Angelo",
    "wof:placetype":"venue"
},
  "geometry": {"coordinates":[9.164074,45.463657],"type":"Point"}
}