{
  "type": "Feature",
  "properties": {
    "iso:country":"IT",
    "sg:address":"1, Via Dell' Aeroporto 00054 Fiumicino",
    "sg:city":"Fiumicino",
    "sg:classifiers":[
        {
            "category":"Airport",
            "subcategory":"General Aviation",
            "type":"Transportation"
        }
    ],
    "sg:phone":"+39 390 665 951",
    "sg:postcode":"00054",
    "sg:province":"Roma",
    "sg:tags":[
        "transport",
        "air"
    ],
    "wof:name":"Aeroporti Di Roma Aeroporto L. Da Vinci",
    "wof:placetype":"venue"
},
  "geometry": {"coordinates":[12.266081,41.763523],"type":"Point"}
}