{
  "type": "Feature",
  "properties": {
    "iso:country":"IT",
    "sg:address":"80027 Frattamaggiore",
    "sg:city":"Frattamaggiore",
    "sg:orig_category":"Carni, Salumi E Pesci",
    "sg:phone":"+39 081 834 6047",
    "sg:postcode":"80027",
    "sg:province":"Napoli",
    "wof:name":"De Francesco Biagio",
    "wof:placetype":"venue"
},
  "geometry": {"coordinates":[14.272583,40.94202],"type":"Point"}
}