{
  "type": "Feature",
  "properties": {
    "iso:country":"IT",
    "sg:address":"73039 Tricase",
    "sg:city":"Tricase",
    "sg:classifiers":[
        {
            "category":"Health Services",
            "subcategory":"Health Practitioner",
            "type":"Services"
        }
    ],
    "sg:phone":"+39 0833 545154",
    "sg:postcode":"73039",
    "sg:province":"Lecce",
    "sg:tags":[
        "medici"
    ],
    "wof:name":"Bios Srl",
    "wof:placetype":"venue"
},
  "geometry": {"coordinates":[18.353846,39.936619],"type":"Point"}
}