{
  "type": "Feature",
  "properties": {
    "addr:full":"35139 Padova Padova Padova 35139",
    "addr:postcode":"35139;35139",
    "iso:country":"IT",
    "sg:address":"35139 Padova",
    "sg:city":"Padova",
    "sg:orig_category":"Audiovisivi Apparecchi Ed Impianti - Produzione, Commercio E Noleggio",
    "sg:phone":"+39 049 875 8755",
    "sg:postcode":"35139",
    "sg:province":"Padova",
    "wof:name":"Emme G. Elettricit\u00c0 Srl",
    "wof:placetype":"venue"
},
  "geometry": {"coordinates":[11.865628,45.358311],"type":"Point"}
}