{
  "type": "Feature",
  "properties": {
    "iso:country":"IT",
    "sg:address":"Strada Statale 88 84084 Fisciano",
    "sg:city":"Fisciano",
    "sg:classifiers":[
        {
            "category":"Autos & Motor Vehicles",
            "subcategory":"Automobile Sales",
            "type":"Retail Goods"
        }
    ],
    "sg:phone":"+39 39089826183",
    "sg:postcode":"84084",
    "sg:province":"Salerno",
    "sg:tags":[
        "industrial"
    ],
    "wof:name":"D'auria Gennaro",
    "wof:placetype":"venue"
},
  "geometry": {"coordinates":[14.766699,40.778896],"type":"Point"}
}