{
  "type": "Feature",
  "properties": {
    "iso:country":"IT",
    "sg:address":"Via Carlo Cattaneo, 1/3 24030 Ambivere",
    "sg:city":"Ambivere",
    "sg:orig_category":"Handrails Of Light Metal",
    "sg:phone":"+39 035 493 2114",
    "sg:postcode":"24030",
    "sg:province":"Bergamo",
    "sg:website":"www.c-sgroup.it",
    "wof:name":"C/s Group Italia S.r.l.",
    "wof:placetype":"venue"
},
  "geometry": {"coordinates":[9.544931,45.726921],"type":"Point"}
}