{
  "type": "Feature",
  "properties": {
    "addr:full":"40068 San Lazzaro Di Savena San Lazzaro Bologna 40068",
    "addr:housenumber":"40068",
    "addr:postcode":"40068",
    "addr:street":"San;San;Bologna",
    "iso:country":"IT",
    "sg:address":"40068 San Lazzaro Di Savena",
    "sg:city":"San Lazzaro",
    "sg:orig_category":"Musica. Shopping",
    "sg:phone":"+39 051 622 6611",
    "sg:postcode":"40068",
    "sg:province":"Bologna",
    "sg:website":"http://www.nannucci.it",
    "wof:name":"Magazzini Nannucci Spa",
    "wof:placetype":"venue"
},
  "geometry": {"coordinates":[11.4272937775,44.4654502869],"type":"Point"}
}