{
  "type": "Feature",
  "properties": {
    "iso:country":"IT",
    "sg:address":"Via Ambrosetti N.2; Morbegno; 23017",
    "sg:city":"Morbegno",
    "sg:classifiers":[
        {
            "category":"Banks & Credit Unions",
            "subcategory":"Bank",
            "type":"Services"
        }
    ],
    "sg:phone":"+39 0342 610011",
    "sg:postcode":"23017",
    "sg:province":"Sondrio",
    "wof:name":"Credito Valtellinese Scarl",
    "wof:placetype":"venue"
},
  "geometry": {"coordinates":[9.568869,46.13459],"type":"Point"}
}