{
  "type": "Feature",
  "properties": {
    "iso:country":"IT",
    "sg:address":"Zona Industriale, Vii Strada, 15; Padua; 35129",
    "sg:classifiers":[
        {
            "category":"Industrial Area",
            "type":"Public Place"
        }
    ],
    "sg:phone":"+39 049 698 5111",
    "sg:postcode":"35129",
    "sg:province":"Padova",
    "sg:tags":[
        "large",
        "private"
    ],
    "sg:website":"www.safilo.com",
    "wof:name":"Safilo Spa",
    "wof:placetype":"venue"
},
  "geometry": {"coordinates":[11.9259986877,45.4266471863],"type":"Point"}
}