{
  "type": "Feature",
  "properties": {
    "addr:full":"50142 Firenze Firenze Firenze 50142",
    "addr:postcode":"50142;50142",
    "iso:country":"IT",
    "sg:address":"50142 Firenze",
    "sg:city":"Firenze",
    "sg:orig_category":"Articoli Da Regalo. Forniture Per Uffici. Regalistica Aziendale",
    "sg:phone":"+39 055 732 5203",
    "sg:postcode":"50142",
    "sg:province":"Firenze",
    "wof:name":"Stipula Firenze Srl",
    "wof:placetype":"venue"
},
  "geometry": {"coordinates":[10.747925,43.67762],"type":"Point"}
}