{
  "type": "Feature",
  "properties": {
    "addr:full":"Via Adige 1-15; Lamezia Terme; 88046 Lamezia Terme Catanzaro 88046",
    "addr:housenumber":"1-15",
    "addr:postcode":"88046;88046",
    "addr:street":"Via Adige",
    "iso:country":"IT",
    "sg:address":"Via Adige 1-15; Lamezia Terme; 88046",
    "sg:city":"Lamezia Terme",
    "sg:classifiers":[
        {
            "category":"Banks & Credit Unions",
            "subcategory":"Bank",
            "type":"Services"
        }
    ],
    "sg:phone":"+39 0968 22021",
    "sg:postcode":"88046",
    "sg:province":"Catanzaro",
    "wof:name":"Banco Di Napoli Spa",
    "wof:placetype":"venue"
},
  "geometry": {"coordinates":[16.319708,38.971718],"type":"Point"}
}