{
  "type": "Feature",
  "properties": {
    "addr:full":"98054 Furnari Furnari Messina 98054",
    "addr:postcode":"98054;98054",
    "iso:country":"IT",
    "sg:address":"98054 Furnari",
    "sg:city":"Furnari",
    "sg:orig_category":"Servizi E Lavori Per Agricoltura E Zootecnia. Servizi E Lavori Per Edilizia E Lavori Pubblici",
    "sg:phone":"+39 0941 874091",
    "sg:postcode":"98054",
    "sg:province":"Messina",
    "wof:name":"Ginevra Srl",
    "wof:placetype":"venue"
},
  "geometry": {"coordinates":[15.113583,38.125336],"type":"Point"}
}