{
  "type": "Feature",
  "properties": {
    "iso:country":"IT",
    "sg:address":"82, Viale Santuario 15048 Valenza",
    "sg:city":"Valenza",
    "sg:classifiers":[
        {
            "category":"Shopping",
            "subcategory":"Jewelry",
            "type":"Retail Goods"
        }
    ],
    "sg:phone":"+39 0131 924275",
    "sg:postcode":"15048",
    "sg:province":"Alessandria",
    "sg:tags":[
        "jewellery"
    ],
    "wof:name":"Art Line (s.n.c.)",
    "wof:placetype":"venue"
},
  "geometry": {"coordinates":[8.636395,45.007759],"type":"Point"}
}