{
  "type": "Feature",
  "properties": {
    "addr:full":"47838 Riccione Riccione Rimini 47838",
    "addr:postcode":"47838;47838",
    "iso:country":"IT",
    "sg:address":"47838 Riccione",
    "sg:city":"Riccione",
    "sg:orig_category":"Zootecnia E Pesca, Allevamento Piccoli Animali. Animali Domestici",
    "sg:phone":"+39 0541 603100",
    "sg:postcode":"47838",
    "sg:province":"Rimini",
    "wof:name":"Adriatic Sea Aquarium E Equipment Srl",
    "wof:placetype":"venue"
},
  "geometry": {"coordinates":[12.584417,44.041321],"type":"Point"}
}