{
  "type": "Feature",
  "properties": {
    "iso:country":"IT",
    "sg:address":"16162 Genova",
    "sg:city":"Genova",
    "sg:orig_category":"Lavorazioni Meccaniche E Servizi. Riparazione Dei Mezzi Di Trasporto",
    "sg:phone":"+39 010 745 5171",
    "sg:postcode":"16162",
    "sg:province":"Genova",
    "wof:name":"De.ca. Srl",
    "wof:placetype":"venue"
},
  "geometry": {"coordinates":[8.904123,44.456394],"type":"Point"}
}