{
  "type": "Feature",
  "properties": {
    "iso:country":"IT",
    "sg:address":"98042 Pace Del Mela",
    "sg:city":"Pace del Mela",
    "sg:orig_category":"Cartotecnica E Servizi. Forniture Per Uffici",
    "sg:phone":"+39 090 938 7027",
    "sg:postcode":"98042",
    "sg:province":"Messina",
    "sg:website":"http://www.grafomatica.com",
    "wof:name":"Grafomatica Di Laudani Rosa",
    "wof:placetype":"venue"
},
  "geometry": {"coordinates":[15.307264,38.191399],"type":"Point"}
}