{
  "type": "Feature",
  "properties": {
    "iso:country":"IT",
    "sg:address":"00175 Roma",
    "sg:city":"Roma",
    "sg:orig_category":"Ottica, Lenti A Contatto Ed Occhiali - Vendita Al Dettaglio",
    "sg:phone":"+39 06 7154 5807",
    "sg:postcode":"00175",
    "sg:province":"Roma",
    "wof:name":"Ottica Jolly Foto",
    "wof:placetype":"venue"
},
  "geometry": {"coordinates":[12.428433,41.837948],"type":"Point"}
}