{
  "type": "Feature",
  "properties": {
    "addr:full":"19126 La Spezia SP",
    "addr:housenumber":"19126",
    "iso:country":"IT",
    "sg:address":"19126 La Spezia",
    "sg:orig_category":"Pozzi Neri",
    "sg:phone":"+39 0187 965 5720",
    "sg:province":"SP",
    "wof:name":"Luigini Sas",
    "wof:placetype":"venue"
},
  "geometry": {"coordinates":[9.8545379639,44.1127815247],"type":"Point"}
}