{
  "type": "Feature",
  "properties": {
    "iso:country":"IT",
    "sg:address":"22075 Lurate Caccivio",
    "sg:city":"Lurate Caccivio",
    "sg:orig_category":"Servizi E Lavori Per Abbigliamento E Pelletterie",
    "sg:phone":"+39 031 390925",
    "sg:postcode":"22075",
    "sg:province":"Como",
    "wof:name":"Tintoria Fevit Snc",
    "wof:placetype":"venue"
},
  "geometry": {"coordinates":[9.00661,45.768272],"type":"Point"}
}