{
  "type": "Feature",
  "properties": {
    "addr:full":"34131 Trieste Trieste Trieste 34131",
    "addr:postcode":"34131;34131",
    "iso:country":"IT",
    "sg:address":"34131 Trieste",
    "sg:city":"Trieste",
    "sg:orig_category":"Ospedali E Servizi Sanitari. Centri Di Estetica E Cosmesi E Servizi",
    "sg:phone":"+39 040 636850",
    "sg:postcode":"34131",
    "sg:province":"Trieste",
    "wof:name":"Estetica Dimensione Alfa Di A. Colucci & L. Domini Snc",
    "wof:placetype":"venue"
},
  "geometry": {"coordinates":[13.778231,45.64851],"type":"Point"}
}