{
  "type": "Feature",
  "properties": {
    "addr:full":"25070 Sabbio Chiese Sabbio Chiese Brescia 25070",
    "addr:postcode":"25070;25070",
    "addr:street":"Chiese",
    "iso:country":"IT",
    "sg:address":"25070 Sabbio Chiese",
    "sg:city":"Sabbio Chiese",
    "sg:orig_category":"Abrasivi",
    "sg:phone":"+39 036 585128",
    "sg:postcode":"25070",
    "sg:province":"Brescia",
    "wof:name":"F.rai.d. Dischi Snc Di Raineri G. & C.",
    "wof:placetype":"venue"
},
  "geometry": {"coordinates":[10.430076,45.648781],"type":"Point"}
}