{
  "type": "Feature",
  "properties": {
    "addr:full":"73056 Taurisano Taurisano Lecce 73056",
    "addr:postcode":"73056;73056",
    "iso:country":"IT",
    "sg:address":"73056 Taurisano",
    "sg:city":"Taurisano",
    "sg:orig_category":"Oli Alimentari E Frantoi Oleari",
    "sg:phone":"+39 0833 625310",
    "sg:postcode":"73056",
    "sg:province":"Lecce",
    "wof:name":"Olearia Caroli' Sas",
    "wof:placetype":"venue"
},
  "geometry": {"coordinates":[18.225889,39.953545],"type":"Point"}
}