{
  "type": "Feature",
  "properties": {
    "iso:country":"IT",
    "sg:address":"36063 Marostica",
    "sg:city":"Marostica",
    "sg:orig_category":"Manufacturers: Prefabbricati. Forniture Per Edilizia E Lavori Pubblici",
    "sg:phone":"+39 0424 702464",
    "sg:postcode":"36063",
    "sg:province":"Vicenza",
    "wof:name":"Casson Antonio",
    "wof:placetype":"venue"
},
  "geometry": {"coordinates":[11.530325,45.550968],"type":"Point"}
}