{
  "type": "Feature",
  "properties": {
    "addr:full":"Via Agogna 28024 Gozzano Gozzano Novara 28024",
    "addr:postcode":"28024;28024",
    "addr:street":"Via Agogna",
    "iso:country":"IT",
    "sg:address":"Via Agogna 28024 Gozzano",
    "sg:city":"Gozzano",
    "sg:classifiers":[
        {
            "category":"Shopping",
            "type":"Retail Goods"
        }
    ],
    "sg:phone":"+39 39032293814",
    "sg:postcode":"28024",
    "sg:province":"Novara",
    "sg:tags":[
        "finished",
        "-",
        "metallic"
    ],
    "wof:name":"Erbea (s.n.c.)",
    "wof:placetype":"venue"
},
  "geometry": {"coordinates":[8.4454488754,45.731212616],"type":"Point"}
}