{
  "type": "Feature",
  "properties": {
    "iso:country":"IT",
    "sg:address":"103/a, Lg. Parolini 36061 Bassano Del Grappa",
    "sg:city":"Bassano del Grappa",
    "sg:classifiers":[
        {
            "category":"Wholesale",
            "subcategory":"Machinery & Supplies",
            "type":"Manufacturing & Wholesale Goods"
        }
    ],
    "sg:phone":"+39 0424 522290",
    "sg:postcode":"36061",
    "sg:province":"Vicenza",
    "sg:tags":[
        "equipment",
        "precision"
    ],
    "sg:website":"http://www.sind.it",
    "wof:name":"Sind",
    "wof:placetype":"venue"
},
  "geometry": {"coordinates":[11.540307045,45.5459060669],"type":"Point"}
}