{
  "type": "Feature",
  "properties": {
    "iso:country":"IT",
    "sg:address":"8, V. S. Vincenzo 22063 Cant\u00f9",
    "sg:classifiers":[
        {
            "category":"Home & Garden",
            "subcategory":"Home Furnishings",
            "type":"Retail Goods"
        }
    ],
    "sg:phone":"+39 39031700543",
    "sg:postcode":"22063",
    "sg:province":"Como",
    "sg:tags":[
        "household"
    ],
    "sg:website":"http://www.errestudio.it:ws_end: :mark:ws:http://www.paginegialle.it/errestudio",
    "wof:name":"Erre Studio Srl",
    "wof:placetype":"venue"
},
  "geometry": {"coordinates":[9.08468,45.781857],"type":"Point"}
}