{
  "type": "Feature",
  "properties": {
    "addr:full":"90141 Palermo Palermo Palermo 90141",
    "addr:postcode":"90141;90141",
    "iso:country":"IT",
    "sg:address":"90141 Palermo",
    "sg:city":"Palermo",
    "sg:orig_category":"Abbigliamento Esterno, Maglierie E Pelliccerie. Sport - Articoli E Forniture",
    "sg:phone":"+39 091 342647",
    "sg:postcode":"90141",
    "sg:province":"Palermo",
    "wof:name":"D'agostaro Salvatore",
    "wof:placetype":"venue"
},
  "geometry": {"coordinates":[13.369371,38.145027],"type":"Point"}
}