{
  "type": "Feature",
  "properties": {
    "iso:country":"IT",
    "sg:address":"90144 Palermo",
    "sg:city":"Palermo",
    "sg:orig_category":"Termotecnica E Riscaldamento, Apparecchiature E Servizi. Prodotti Vari In Metallo",
    "sg:phone":"+39 091 670 7554",
    "sg:postcode":"90144",
    "sg:province":"Palermo",
    "wof:name":"Edil Multimpianti Srl",
    "wof:placetype":"venue"
},
  "geometry": {"coordinates":[13.332253,38.147572],"type":"Point"}
}