{
  "type": "Feature",
  "properties": {
    "addr:full":"Via Della Pace 2/a 40010 Sala Bolognese Sala Bolognese Bologna 40010",
    "addr:housenumber":"2 / a",
    "addr:postcode":"40010;40010",
    "addr:street":"Via Della Pace;Bolognese",
    "iso:country":"IT",
    "sg:address":"Via Della Pace 2/a 40010 Sala Bolognese",
    "sg:city":"Sala Bolognese",
    "sg:classifiers":[
        {
            "category":"Banks & Credit Unions",
            "subcategory":"Atm",
            "type":"Services"
        }
    ],
    "sg:phone":"+39 051 828139",
    "sg:postcode":"40010",
    "sg:province":"Bologna",
    "sg:tags":[
        "machine",
        "flat",
        "knitting"
    ],
    "sg:website":"www.emm-knittingmachines.com",
    "wof:name":"Emm Srl",
    "wof:placetype":"venue"
},
  "geometry": {"coordinates":[11.2726297379,44.5622634888],"type":"Point"}
}