{
  "type": "Feature",
  "properties": {
    "iso:country":"IT",
    "sg:address":"44028 Poggio Renatico",
    "sg:city":"Gallo",
    "sg:orig_category":"Manufacturers: Prefabbricati. Forniture Per Edilizia E Lavori Pubblici",
    "sg:phone":"+39 0532 820028",
    "sg:postcode":"44028",
    "sg:province":"Ferrara",
    "wof:name":"Busi Recinzioni Srl",
    "wof:placetype":"venue"
},
  "geometry": {"coordinates":[11.544009,44.723068],"type":"Point"}
}