{
  "type": "Feature",
  "properties": {
    "iso:country":"IT",
    "sg:address":"20122 Milano",
    "sg:city":"Milano",
    "sg:orig_category":"Studi E Consulenze Tecniche E Industriali. Assicurazioni E Servizi Assicurativi. Consulenze Tecniche, Amministrative E Perizie",
    "sg:phone":"+39 02 545 6169",
    "sg:postcode":"20122",
    "sg:province":"Milano",
    "wof:name":"Datteri Lorenzo",
    "wof:placetype":"venue"
},
  "geometry": {"coordinates":[9.204492,45.46072],"type":"Point"}
}