{
  "type": "Feature",
  "properties": {
    "addr:full":"80026 Casoria Casoria Napoli 80026",
    "addr:postcode":"80026;80026",
    "iso:country":"IT",
    "sg:address":"80026 Casoria",
    "sg:city":"Casoria",
    "sg:orig_category":"Macchine Utensili E Impianti",
    "sg:phone":"+39 081 759 9404",
    "sg:postcode":"80026",
    "sg:province":"Napoli",
    "sg:website":"http://www.amigroup-it.com",
    "wof:name":"Ami Srl",
    "wof:placetype":"venue"
},
  "geometry": {"coordinates":[14.323475,40.887745],"type":"Point"}
}