{
  "type": "Feature",
  "properties": {
    "iso:country":"IT",
    "sg:address":"76, Via Gramsci 20019 Settimo Milanese",
    "sg:city":"Settimo Milanese",
    "sg:classifiers":[
        {
            "category":"Wholesale",
            "subcategory":"Drugs",
            "type":"Manufacturing & Wholesale Goods"
        }
    ],
    "sg:phone":"+39 02 3350 1283",
    "sg:postcode":"20019",
    "sg:province":"Milano",
    "sg:tags":[
        "chemical",
        "pharmaceutical"
    ],
    "sg:website":"http://www.borman.it",
    "wof:name":"Borman Italiana Sas",
    "wof:placetype":"venue"
},
  "geometry": {"coordinates":[9.064458,45.488285],"type":"Point"}
}