{
  "type": "Feature",
  "properties": {
    "iso:country":"IT",
    "sg:address":"Via Dell'artigianato 21 35020 Albignasego",
    "sg:city":"Albignasego",
    "sg:classifiers":[
        {
            "category":"Wholesale",
            "subcategory":"Chemicals & Plastics",
            "type":"Manufacturing & Wholesale Goods"
        }
    ],
    "sg:phone":"+39 049 710200",
    "sg:postcode":"35020",
    "sg:province":"Padova",
    "sg:tags":[
        "cleaning",
        "surface"
    ],
    "sg:website":"www.martelloigiene.it",
    "wof:name":"Martello Srl",
    "wof:placetype":"venue"
},
  "geometry": {"coordinates":[11.839084,45.357407],"type":"Point"}
}