{
  "type": "Feature",
  "properties": {
    "iso:country":"IT",
    "sg:address":"31046 Oderzo",
    "sg:city":"Oderzo",
    "sg:orig_category":"Autotrasporti",
    "sg:phone":"+39 0422 815666",
    "sg:postcode":"31046",
    "sg:province":"Treviso",
    "wof:name":"Sbrissa Rag. Giuseppe Every Prompt Transport",
    "wof:placetype":"venue"
},
  "geometry": {"coordinates":[12.499269,45.76228],"type":"Point"}
}