{
  "type": "Feature",
  "properties": {
    "addr:full":"108, Via Cornaggia 22076 Mozzate Mozzate Como 22076",
    "addr:housenumber":"108",
    "addr:postcode":"22076;22076",
    "addr:street":"Via Cornaggia",
    "iso:country":"IT",
    "sg:address":"108, Via Cornaggia 22076 Mozzate",
    "sg:city":"Mozzate",
    "sg:classifiers":[
        {
            "category":"Professional",
            "subcategory":"Engineering",
            "type":"Services"
        }
    ],
    "sg:phone":"+39 0331 836201",
    "sg:postcode":"22076",
    "sg:province":"Como",
    "sg:tags":[
        "machine",
        "-",
        "mechanical"
    ],
    "wof:name":"Ebm Ziehl S.r.l.",
    "wof:placetype":"venue"
},
  "geometry": {"coordinates":[8.951271,45.671047],"type":"Point"}
}