{
  "type": "Feature",
  "properties": {
    "addr:full":"18, Via Giuseppe Parini 22070 Valmorea Valmorea Como 22070",
    "addr:postcode":"22070;22070",
    "addr:street":"Via Giuseppe Parini",
    "iso:country":"IT",
    "sg:address":"18, Via Giuseppe Parini 22070 Valmorea",
    "sg:city":"Valmorea",
    "sg:classifiers":[
        {
            "category":"Shopping",
            "subcategory":"Clothing, Apparel, & Fashions",
            "type":"Retail Goods"
        }
    ],
    "sg:phone":"+39 031 350 9115",
    "sg:postcode":"22070",
    "sg:province":"Como",
    "sg:tags":[
        "clothes"
    ],
    "wof:name":"Maglificio G.p. (s.a.s.)",
    "wof:placetype":"venue"
},
  "geometry": {"coordinates":[8.940243,45.816525],"type":"Point"}
}