{
  "type": "Feature",
  "properties": {
    "addr:full":"Via Del Marmo 794 37020 Volargne Volargne Verona 37020",
    "addr:housenumber":"794",
    "addr:postcode":"37020;37020",
    "addr:street":"Via Del Marmo",
    "iso:country":"IT",
    "sg:address":"Via Del Marmo 794 37020 Volargne",
    "sg:city":"Volargne",
    "sg:classifiers":[
        {
            "category":"Home & Garden",
            "subcategory":"Carpets & Floor Coverings",
            "type":"Retail Goods"
        }
    ],
    "sg:phone":"+39 045 773 1328",
    "sg:postcode":"37020",
    "sg:province":"Verona",
    "sg:tags":[
        "marble",
        "flooring"
    ],
    "sg:website":"www.colombare.it",
    "wof:name":"Marmi Colombare Srl",
    "wof:placetype":"venue"
},
  "geometry": {"coordinates":[10.810169,45.532169],"type":"Point"}
}