{
  "type": "Feature",
  "properties": {
    "iso:country":"IT",
    "sg:address":"27, Viale Dell' Artigianato 35021 Agna",
    "sg:city":"Agna",
    "sg:classifiers":[
        {
            "category":"Real Estate",
            "subcategory":"Architect",
            "type":"Services"
        }
    ],
    "sg:phone":"+39 049 951 5027",
    "sg:postcode":"35021",
    "sg:province":"Padova",
    "sg:tags":[
        "textile",
        "clothing"
    ],
    "wof:name":"Agnense Manifattura S.r.l.",
    "wof:placetype":"venue"
},
  "geometry": {"coordinates":[11.970855,45.173912],"type":"Point"}
}