{
  "type": "Feature",
  "properties": {
    "addr:full":"21053 Castellanza Castellanza Varese 21053",
    "addr:postcode":"21053;21053",
    "iso:country":"IT",
    "sg:address":"21053 Castellanza",
    "sg:city":"Castellanza",
    "sg:orig_category":"Servizi Per Aziende, Manifestazioni E Supporto Agli Scambi Commerciali",
    "sg:phone":"+39 0331 504124",
    "sg:postcode":"21053",
    "sg:province":"Varese",
    "sg:website":"http://www.gobboallestimenti.com",
    "wof:name":"Gobbo Allestimenti Snc Di Roberto E Fabio Gobbo",
    "wof:placetype":"venue"
},
  "geometry": {"coordinates":[8.994537,45.634224],"type":"Point"}
}