{
  "type": "Feature",
  "properties": {
    "iso:country":"IT",
    "sg:address":"43, Via Piovese 35020 Sant'angelo Di Piove Di Sacco",
    "sg:classifiers":[
        {
            "category":"Home & Garden",
            "subcategory":"Home Furnishings",
            "type":"Retail Goods"
        }
    ],
    "sg:phone":"+39 049 584 2837",
    "sg:postcode":"35020",
    "sg:province":"Padova",
    "sg:tags":[
        "household"
    ],
    "wof:name":"Mobilcucina",
    "wof:placetype":"venue"
},
  "geometry": {"coordinates":[12.013824,45.313446],"type":"Point"}
}