{
  "type": "Feature",
  "properties": {
    "iso:country":"IT",
    "sg:address":"57, Via Faentina Nord 48026 Russi",
    "sg:city":"Russi",
    "sg:orig_category":"Miscellaneous Products",
    "sg:phone":"+39 0544 583402",
    "sg:postcode":"48026",
    "sg:province":"Ravenna",
    "wof:name":"Fora Chicom Italia S.r.l.",
    "wof:placetype":"venue"
},
  "geometry": {"coordinates":[12.0432739258,44.385887146],"type":"Point"}
}