{
  "type": "Feature",
  "properties": {
    "iso:country":"IT",
    "sg:address":"Via Bligny 8 10093 Collegno",
    "sg:city":"Collegno",
    "sg:classifiers":[
        {
            "category":"Manufacturing",
            "subcategory":"Motor Vehicles & Parts",
            "type":"Manufacturing & Wholesale Goods"
        }
    ],
    "sg:phone":"+39 011 411 1073",
    "sg:postcode":"10093",
    "sg:province":"Torino",
    "sg:tags":[
        "engine",
        "diesel",
        "accessory"
    ],
    "wof:name":"Icat Italia S.r.l.",
    "wof:placetype":"venue"
},
  "geometry": {"coordinates":[7.595184,45.072754],"type":"Point"}
}