{
  "type": "Feature",
  "properties": {
    "addr:full":"35018 San Martino Di Lupari San Martino di Lupari Padova 35018",
    "addr:housenumber":"35018",
    "addr:postcode":"di lupari;35018",
    "iso:country":"IT",
    "sg:address":"35018 San Martino Di Lupari",
    "sg:city":"San Martino di Lupari",
    "sg:orig_category":"Prodotti Chimici Di Base",
    "sg:phone":"+39 049 595 2522",
    "sg:postcode":"35018",
    "sg:province":"Padova",
    "wof:name":"Seep Srl",
    "wof:placetype":"venue"
},
  "geometry": {"coordinates":[11.8734455109,45.6377754211],"type":"Point"}
}