{
  "type": "Feature",
  "properties": {
    "addr:full":"10099 San Mauro Torinese San Mauro Torinese Torino 10099",
    "addr:housenumber":"10099",
    "addr:postcode":"10099",
    "addr:street":"San",
    "iso:country":"IT",
    "sg:address":"10099 San Mauro Torinese",
    "sg:city":"San Mauro Torinese",
    "sg:orig_category":"Macchine Utensili E Impianti. Elettrotecnica Industriale, Prodotti E Apparecchiature",
    "sg:phone":"+39 011 223 8316",
    "sg:postcode":"10099",
    "sg:province":"Torino",
    "wof:name":"Miyachi Technos Europe Gmbh Srl",
    "wof:placetype":"venue"
},
  "geometry": {"coordinates":[7.748993,45.115379],"type":"Point"}
}