{
  "type": "Feature",
  "properties": {
    "iso:country":"IT",
    "sg:address":"30173 Venezia",
    "sg:city":"Venezia",
    "sg:orig_category":"Servizi Al Turismo. Servizi Ausiliari Dei Mezzi Di Trasporto. Servizi Ausiliari Per Il Trasporto. Acqua, Luce, Gas E Societa' Di Esercizio Pubblico",
    "sg:phone":"+39 041 534 3200",
    "sg:postcode":"30173",
    "sg:province":"Venezia",
    "wof:name":"Martini Bus Srl",
    "wof:placetype":"venue"
},
  "geometry": {"coordinates":[12.315138,45.513855],"type":"Point"}
}