{
  "type": "Feature",
  "properties": {
    "addr:full":"06065 Passignano Trasimeno Perugia 06065",
    "addr:postcode":"06065;trasimeno;06065",
    "iso:country":"IT",
    "sg:address":"06065 Passignano Trasimeno",
    "sg:orig_category":"Servizi E Lavori Per Edilizia E Lavori Pubblici. Consulenze Tecniche, Amministrative E Perizie",
    "sg:phone":"+39 075 829 6208",
    "sg:postcode":"06065",
    "sg:province":"Perugia",
    "wof:name":"Studio Commerciale Vestri Dott. Riccardo",
    "wof:placetype":"venue"
},
  "geometry": {"coordinates":[12.134294,43.186672],"type":"Point"}
}