{
  "type": "Feature",
  "properties": {
    "iso:country":"IT",
    "sg:address":"26018 Trigolo",
    "sg:city":"Trigolo",
    "sg:orig_category":"Trasporti E Spedizioni Merci",
    "sg:phone":"+39 0374 370130",
    "sg:postcode":"26018",
    "sg:province":"Cremona",
    "sg:website":"http://www.marcariniennio.com",
    "wof:name":"Marcarini Ennio Autotrasporti",
    "wof:placetype":"venue"
},
  "geometry": {"coordinates":[9.820853,45.32737],"type":"Point"}
}