{
  "type": "Feature",
  "properties": {
    "iso:country":"IT",
    "sg:address":"38016 Mezzocorona",
    "sg:city":"Mezzocorona",
    "sg:orig_category":"Apparecchiature E Sistemi Per Magazzinaggio E Movimentazione",
    "sg:phone":"+39 0461 601000",
    "sg:postcode":"38016",
    "sg:province":"Trento",
    "sg:website":"http://www.baumac.it",
    "wof:name":"Baumac Srl",
    "wof:placetype":"venue"
},
  "geometry": {"coordinates":[11.122227,46.214275],"type":"Point"}
}