{
  "type": "Feature",
  "properties": {
    "addr:full":"84131 Salerno Salerno Salerno 84131",
    "addr:postcode":"84131;84131",
    "iso:country":"IT",
    "sg:address":"84131 Salerno",
    "sg:city":"Salerno",
    "sg:orig_category":"Forniture Per Attivita' Industriali",
    "sg:phone":"+39 089 771177",
    "sg:postcode":"84131",
    "sg:province":"Salerno",
    "wof:name":"Casa Del Cuscinetto Sas",
    "wof:placetype":"venue"
},
  "geometry": {"coordinates":[14.8413724899,40.6398429871],"type":"Point"}
}