{
  "type": "Feature",
  "properties": {
    "iso:country":"IT",
    "sg:address":"Via Veregrense 211 63014 Montegranaro",
    "sg:city":"Montegranaro",
    "sg:classifiers":[
        {
            "category":"Personal",
            "subcategory":"Shoe Repair & Shine",
            "type":"Services"
        }
    ],
    "sg:phone":"+39 0734 891486",
    "sg:postcode":"63014",
    "sg:province":"Ascoli Piceno",
    "sg:tags":[
        "rand"
    ],
    "sg:website":"www.angeletti.com",
    "wof:name":"B.a. Angeletti Srl",
    "wof:placetype":"venue"
},
  "geometry": {"coordinates":[13.647666,43.243279],"type":"Point"}
}