{
  "type": "Feature",
  "properties": {
    "iso:country":"IT",
    "sg:address":"15/21, Viale Delle Industrie 20020 Arese",
    "sg:city":"Arese",
    "sg:classifiers":[
        {
            "category":"Real Estate",
            "subcategory":"Surveying",
            "type":"Services"
        }
    ],
    "sg:phone":"+39 02 9358 3164",
    "sg:postcode":"20020",
    "sg:province":"Milano",
    "sg:tags":[
        "equipment",
        "material",
        "good",
        "-",
        "handling"
    ],
    "wof:name":"Fib Di Bosi Giorgio E Sergio (s.n.c.)",
    "wof:placetype":"venue"
},
  "geometry": {"coordinates":[9.087852,45.535484],"type":"Point"}
}