{
  "type": "Feature",
  "properties": {
    "iso:country":"IT",
    "sg:address":"Via Panciatichi 40 50127 Firenze",
    "sg:city":"Firenze",
    "sg:classifiers":[
        {
            "category":"Shopping",
            "subcategory":"Gifts & Souvenirs",
            "type":"Retail Goods"
        }
    ],
    "sg:phone":"+39 055 429261",
    "sg:postcode":"50127",
    "sg:province":"Firenze",
    "sg:tags":[
        "item"
    ],
    "wof:name":"Frank Corsi International Srl",
    "wof:placetype":"venue"
},
  "geometry": {"coordinates":[11.233955,43.800133],"type":"Point"}
}