{
  "type": "Feature",
  "properties": {
    "iso:country":"IT",
    "sg:address":"25076 Odolo",
    "sg:city":"Odolo",
    "sg:orig_category":"Officine Meccaniche",
    "sg:phone":"+39 036 586 0208",
    "sg:postcode":"25076",
    "sg:province":"Brescia",
    "wof:name":"O.to.ci Srl",
    "wof:placetype":"venue"
},
  "geometry": {"coordinates":[10.382999,45.636036],"type":"Point"}
}