{
  "type": "Feature",
  "properties": {
    "addr:full":"Castel Di Lama; 63030 Ascoli Piceno 63030",
    "addr:postcode":"63030;63030",
    "iso:country":"IT",
    "sg:address":"Castel Di Lama; 63030",
    "sg:classifiers":[
        {
            "category":"Banks & Credit Unions",
            "subcategory":"Bank",
            "type":"Services"
        }
    ],
    "sg:phone":"+39 0736 814793",
    "sg:postcode":"63030",
    "sg:province":"Ascoli Piceno",
    "wof:name":"Banca Popolare Di Ancona",
    "wof:placetype":"venue"
},
  "geometry": {"coordinates":[13.713649,42.87059],"type":"Point"}
}