{
  "type": "Feature",
  "properties": {
    "iso:country":"IT",
    "sg:address":"20090 Cesano Boscone",
    "sg:city":"Cesano Boscone",
    "sg:orig_category":"Pubblica Amministrazione",
    "sg:phone":"+39 02 4860 1457",
    "sg:postcode":"20090",
    "sg:province":"Milano",
    "wof:name":"Poste Italiane S.p.a.",
    "wof:placetype":"venue"
},
  "geometry": {"coordinates":[9.0986385345,45.4456558228],"type":"Point"}
}