{
  "type": "Feature",
  "properties": {
    "addr:full":"2, Via De Gasperi 20090 Pantigliate Pantigliate Milano 20090",
    "addr:postcode":"20090;20090",
    "addr:street":"Via De Gasperi",
    "iso:country":"IT",
    "sg:address":"2, Via De Gasperi 20090 Pantigliate",
    "sg:city":"Pantigliate",
    "sg:classifiers":[
        {
            "category":"Manufacturing",
            "subcategory":"Wood Products",
            "type":"Manufacturing & Wholesale Goods"
        }
    ],
    "sg:phone":"+39 39029067079",
    "sg:postcode":"20090",
    "sg:province":"Milano",
    "sg:tags":[
        "furniture"
    ],
    "wof:name":"Frattoloni Emilio & C. (s.n.c.)",
    "wof:placetype":"venue"
},
  "geometry": {"coordinates":[9.188141,45.463688],"type":"Point"}
}