{
  "type": "Feature",
  "properties": {
    "iso:country":"IT",
    "sg:address":"42, Via Antonelli 10093 Collegno",
    "sg:city":"Collegno",
    "sg:classifiers":[
        {
            "category":"Professional",
            "subcategory":"Engineering",
            "type":"Services"
        }
    ],
    "sg:phone":"+39 011 411 4025",
    "sg:postcode":"10093",
    "sg:province":"Torino",
    "sg:tags":[
        "machine",
        "-",
        "mechanical"
    ],
    "wof:name":"Piscazzi Lavorazioni Meccaniche (s.r.l.)",
    "wof:placetype":"venue"
},
  "geometry": {"coordinates":[7.591805,45.07375],"type":"Point"}
}