{
  "type": "Feature",
  "properties": {
    "iso:country":"IT",
    "sg:address":"Localit\u00e0 Aniceti 3 13019 Varallo",
    "sg:city":"Varallo",
    "sg:classifiers":[
        {
            "category":"Government",
            "subcategory":"Fire Station",
            "type":"Public Place"
        }
    ],
    "sg:phone":"+39 0163 560700",
    "sg:postcode":"13019",
    "sg:province":"Vercelli",
    "sg:tags":[
        "brass",
        "aluminium",
        "washer"
    ],
    "sg:website":"www.fuselli.it",
    "wof:name":"Arnaldo Fuselli Di Ennio E Francesc O E C Snc",
    "wof:placetype":"venue"
},
  "geometry": {"coordinates":[8.256048,45.814022],"type":"Point"}
}