{
  "type": "Feature",
  "properties": {
    "iso:country":"IT",
    "sg:address":"60027 Osimo",
    "sg:city":"Osimo",
    "sg:orig_category":"Servizi E Lavori Industria Chimica. Trattamenti Termici E Superficiali Metalli, Galvanotecnica",
    "sg:phone":"+39 071 710 0538",
    "sg:postcode":"60027",
    "sg:province":"Ancona",
    "sg:website":"http://www.metalcontrol.it",
    "wof:name":"Metalcontrol Snc",
    "wof:placetype":"venue"
},
  "geometry": {"coordinates":[13.501481,43.600822],"type":"Point"}
}