{
  "type": "Feature",
  "properties": {
    "iso:country":"IT",
    "sg:address":"20123 Milano",
    "sg:city":"Milano",
    "sg:orig_category":"Alberghi",
    "sg:phone":"+39 02 801371",
    "sg:postcode":"20123",
    "sg:province":"Milano",
    "wof:name":"Albergo Cairoli Srl",
    "wof:placetype":"venue"
},
  "geometry": {"coordinates":[9.182493,45.467148],"type":"Point"}
}