{
  "type": "Feature",
  "properties": {
    "addr:full":"89048 Siderno Siderno Reggio Di Calabria 89048",
    "addr:postcode":"89048;89048",
    "iso:country":"IT",
    "sg:address":"89048 Siderno",
    "sg:city":"Siderno",
    "sg:orig_category":"Porte",
    "sg:phone":"+39 0964 343394",
    "sg:postcode":"89048",
    "sg:province":"Reggio Di Calabria",
    "wof:name":"Co.all. Antonio Costera - Serramenti In Alluminio",
    "wof:placetype":"venue"
},
  "geometry": {"coordinates":[15.6501369476,38.1146888733],"type":"Point"}
}