{
  "type": "Feature",
  "properties": {
    "iso:country":"IT",
    "sg:address":"23845 Costa Masnaga",
    "sg:city":"Costa Masnaga",
    "sg:orig_category":"Macchine, Impianti Ed Attrezzature Per Agricoltura E Zootecnia",
    "sg:phone":"+39 031 855252",
    "sg:postcode":"23845",
    "sg:province":"Lecco",
    "wof:name":"Colombo Roberta",
    "wof:placetype":"venue"
},
  "geometry": {"coordinates":[9.278628,45.764385],"type":"Point"}
}