{
  "type": "Feature",
  "properties": {
    "addr:full":"28100 Novara Lumellogno Novara 28100",
    "addr:postcode":"28100;28100",
    "iso:country":"IT",
    "sg:address":"28100 Novara",
    "sg:city":"Lumellogno",
    "sg:orig_category":"Servizi Per Aziende, Manifestazioni E Supporto Agli Scambi Commerciali",
    "sg:phone":"+39 0321 469184",
    "sg:postcode":"28100",
    "sg:province":"Novara",
    "wof:name":"Strategica Srl",
    "wof:placetype":"venue"
},
  "geometry": {"coordinates":[8.575814,45.420311],"type":"Point"}
}