{
  "type": "Feature",
  "properties": {
    "addr:full":"80132 Napoli Napoli Napoli 80132",
    "addr:housenumber":"80132",
    "addr:postcode":"80132",
    "iso:country":"IT",
    "sg:address":"80132 Napoli",
    "sg:city":"Napoli",
    "sg:orig_category":"Abbigliamento Esterno, Maglierie E Pelliccerie. Calzature, Pelletterie E Pelli",
    "sg:phone":"+39 081 552 3918",
    "sg:postcode":"80132",
    "sg:province":"Napoli",
    "wof:name":"Imperatrice L.",
    "wof:placetype":"venue"
},
  "geometry": {"coordinates":[14.246861,40.834728],"type":"Point"}
}