{
  "type": "Feature",
  "properties": {
    "addr:full":"Via Dragonetti; L'aquila; 67100 L'Aquila 67100",
    "addr:postcode":"67100;67100",
    "addr:street":"Via Dragonetti L'Aquila",
    "iso:country":"IT",
    "sg:address":"Via Dragonetti; L'aquila; 67100",
    "sg:classifiers":[
        {
            "category":"Banks & Credit Unions",
            "subcategory":"Bank",
            "type":"Services"
        }
    ],
    "sg:phone":"+39 0862 61755",
    "sg:postcode":"67100",
    "sg:province":"L'Aquila",
    "wof:name":"Cassa Di Risparmio Di Roma",
    "wof:placetype":"venue"
},
  "geometry": {"coordinates":[13.398994,42.348297],"type":"Point"}
}