{
  "type": "Feature",
  "properties": {
    "iso:country":"IT",
    "sg:address":"15, Piazza Marconi Guglielmo 26100 Cremona",
    "sg:city":"Cremona",
    "sg:classifiers":[
        {
            "category":"Building & Trades",
            "subcategory":"Construction",
            "type":"Services"
        }
    ],
    "sg:phone":"+39 39037225685",
    "sg:postcode":"26100",
    "sg:province":"Cremona",
    "sg:tags":[
        "work",
        "public"
    ],
    "wof:name":"Tirri Felice (s.r.l.)",
    "wof:placetype":"venue"
},
  "geometry": {"coordinates":[10.026135,45.133499],"type":"Point"}
}