{
  "type": "Feature",
  "properties": {
    "iso:country":"IT",
    "sg:address":"Via Mazzini 129; Bogliasco; 16031",
    "sg:city":"Bogliasco",
    "sg:classifiers":[
        {
            "category":"Banks & Credit Unions",
            "subcategory":"Bank",
            "type":"Services"
        }
    ],
    "sg:phone":"+39 010 347 0186",
    "sg:postcode":"16031",
    "sg:province":"Genova",
    "wof:name":"Banca Carige Spa",
    "wof:placetype":"venue"
},
  "geometry": {"coordinates":[9.069069,44.379093],"type":"Point"}
}