{
  "type": "Feature",
  "properties": {
    "iso:country":"IT",
    "sg:address":"47, Via Fonda Di Mezzana 59100 Prato",
    "sg:city":"Mezzana",
    "sg:classifiers":[
        {
            "category":"Shopping",
            "subcategory":"Crafts & Fabrics",
            "type":"Retail Goods"
        }
    ],
    "sg:phone":"+39 0574 592741",
    "sg:postcode":"59100",
    "sg:province":"Prato",
    "wof:name":"Tintoria Ritmo (s.p.a.)",
    "wof:placetype":"venue"
},
  "geometry": {"coordinates":[11.0997447968,43.847858429],"type":"Point"}
}