{
  "type": "Feature",
  "properties": {
    "addr:full":"20122 Milano Milano Milano 20122",
    "addr:postcode":"20122;20122",
    "iso:country":"IT",
    "sg:address":"20122 Milano",
    "sg:city":"Milano",
    "sg:orig_category":"Servizi Per Aziende, Manifestazioni E Supporto Agli Scambi Commerciali",
    "sg:phone":"+39 02 5831 3700",
    "sg:postcode":"20122",
    "sg:province":"Milano",
    "wof:name":"Moroni Diego",
    "wof:placetype":"venue"
},
  "geometry": {"coordinates":[9.18691,45.45311],"type":"Point"}
}