{
  "type": "Feature",
  "properties": {
    "iso:country":"IT",
    "sg:address":"90143 Palermo",
    "sg:city":"Palermo",
    "sg:orig_category":"Scuole E Servizi Scolastici. Ricerca, Selezione E Formazione Del Personale",
    "sg:phone":"+39 091 625 1435",
    "sg:postcode":"90143",
    "sg:province":"Palermo",
    "wof:name":"Istituto Platone",
    "wof:placetype":"venue"
},
  "geometry": {"coordinates":[13.350065,38.141975],"type":"Point"}
}