{
  "type": "Feature",
  "properties": {
    "addr:full":"00191 Roma Roma Roma 00191",
    "addr:postcode":"00191;00191",
    "iso:country":"IT",
    "sg:address":"00191 Roma",
    "sg:city":"Roma",
    "sg:orig_category":"Cine-foto-ottica",
    "sg:phone":"+39 06 333 6552",
    "sg:postcode":"00191",
    "sg:province":"Roma",
    "sg:website":"http://www.",
    "wof:name":"Fotoshop Di Guarino",
    "wof:placetype":"venue"
},
  "geometry": {"coordinates":[12.47323,41.943989],"type":"Point"}
}