{
  "type": "Feature",
  "properties": {
    "iso:country":"IT",
    "sg:address":"00161 Roma",
    "sg:city":"Roma",
    "sg:orig_category":"Servizi Culturali E Per Lo Spettacolo",
    "sg:phone":"+39 06 440 2719",
    "sg:postcode":"00161",
    "sg:province":"Roma",
    "wof:name":"Cinematografo Nomentano",
    "wof:placetype":"venue"
},
  "geometry": {"coordinates":[12.507981,41.913445],"type":"Point"}
}