{
  "type": "Feature",
  "properties": {
    "addr:full":"22018 Porlezza Porlezza Como 22018",
    "addr:postcode":"22018;22018",
    "iso:country":"IT",
    "sg:address":"22018 Porlezza",
    "sg:city":"Porlezza",
    "sg:orig_category":"Prodotti Chimici Di Base. Forniture Per Attivita' Industriali",
    "sg:phone":"+39 0344 62822",
    "sg:postcode":"22018",
    "sg:province":"Como",
    "wof:name":"Dawiltex Sas",
    "wof:placetype":"venue"
},
  "geometry": {"coordinates":[9.1378412247,46.0373039246],"type":"Point"}
}