{
  "type": "Feature",
  "properties": {
    "addr:full":"38/40, Via Friuli 40024 Castel San Pietro Terme Castel San Pietro Terme Bologna 40024",
    "addr:housenumber":"38 / 40",
    "addr:postcode":"40024;40024",
    "addr:street":"Via Friuli",
    "iso:country":"IT",
    "sg:address":"38/40, Via Friuli 40024 Castel San Pietro Terme",
    "sg:city":"Castel San Pietro Terme",
    "sg:classifiers":[
        {
            "category":"Professional",
            "subcategory":"Engineering",
            "type":"Services"
        }
    ],
    "sg:phone":"+39 39051946070",
    "sg:postcode":"40024",
    "sg:province":"Bologna",
    "sg:tags":[
        "machine",
        "-",
        "mechanical"
    ],
    "wof:name":"G.s. Divisione Verniciatura (s.r.l.)",
    "wof:placetype":"venue"
},
  "geometry": {"coordinates":[11.520237,44.433193],"type":"Point"}
}