{
  "type": "Feature",
  "properties": {
    "iso:country":"IT",
    "sg:address":"Via Battisti 83034 Casalbore",
    "sg:city":"Casalbore",
    "sg:classifiers":[
        {
            "category":"Shopping",
            "subcategory":"Clothing, Apparel, & Fashions",
            "type":"Retail Goods"
        }
    ],
    "sg:phone":"+39 0825 849167",
    "sg:postcode":"83034",
    "sg:province":"Avellino",
    "sg:tags":[
        "clothes"
    ],
    "wof:name":"Emmesse 093 S.r.l",
    "wof:placetype":"venue"
},
  "geometry": {"coordinates":[14.999333,41.226871],"type":"Point"}
}