{
  "type": "Feature",
  "properties": {
    "iso:country":"IT",
    "sg:address":"20132 Milano",
    "sg:city":"Milano",
    "sg:orig_category":"Servizi E Lavori Per Agricoltura E Zootecnia",
    "sg:phone":"+39 02 282 2059",
    "sg:postcode":"20132",
    "sg:province":"Milano",
    "wof:name":"Associazione Lombarda Delle Cooperative Di Consumatori",
    "wof:placetype":"venue"
},
  "geometry": {"coordinates":[9.232408,45.49313],"type":"Point"}
}