{
  "type": "Feature",
  "properties": {
    "iso:country":"IT",
    "sg:address":"140, Via Torino 13040 Palazzolo Vercellese",
    "sg:city":"Palazzolo Vercellese",
    "sg:classifiers":[
        {
            "category":"Professional",
            "subcategory":"Engineering",
            "type":"Services"
        }
    ],
    "sg:phone":"+39 0161 818555",
    "sg:postcode":"13040",
    "sg:province":"Vercelli",
    "sg:tags":[
        "machine",
        "-",
        "mechanical"
    ],
    "wof:name":"Co.ve.ca. Di Coatti Claudio & C. S.n.c.",
    "wof:placetype":"venue"
},
  "geometry": {"coordinates":[8.235801,45.188892],"type":"Point"}
}