{
  "type": "Feature",
  "properties": {
    "addr:full":"224, Via Del Vigna 57121 Livorno Livorno Livorno 57121",
    "addr:housenumber":"224",
    "addr:postcode":"57121;57121",
    "addr:street":"Via Del Vigna",
    "iso:country":"IT",
    "sg:address":"224, Via Del Vigna 57121 Livorno",
    "sg:city":"Livorno",
    "sg:classifiers":[
        {
            "category":"Home & Garden",
            "subcategory":"Home Furnishings",
            "type":"Retail Goods"
        }
    ],
    "sg:phone":"+39 0586 410668",
    "sg:postcode":"57121",
    "sg:province":"Livorno",
    "sg:tags":[
        "household"
    ],
    "wof:name":"Fa.ma",
    "wof:placetype":"venue"
},
  "geometry": {"coordinates":[10.329053,43.559277],"type":"Point"}
}