{
  "type": "Feature",
  "properties": {
    "iso:country":"IT",
    "sg:address":"12, Via Caduti Di Bologna 73034 Gagliano Del Capo",
    "sg:city":"Gagliano del Capo",
    "sg:classifiers":[
        {
            "category":"Shopping",
            "subcategory":"Clothing, Apparel, & Fashions",
            "type":"Retail Goods"
        }
    ],
    "sg:phone":"+39 0833 547207",
    "sg:postcode":"73034",
    "sg:province":"Lecce",
    "sg:tags":[
        "clothes"
    ],
    "wof:name":"Calzificio Ri.ma. Snc Di Protopapa R. & Trane A",
    "wof:placetype":"venue"
},
  "geometry": {"coordinates":[18.361082,39.84977],"type":"Point"}
}