{
  "type": "Feature",
  "properties": {
    "iso:country":"IT",
    "sg:address":"10036 Settimo Torinese",
    "sg:city":"Settimo Torinese",
    "sg:orig_category":"Macchine Utensili - Commercio",
    "sg:phone":"+39 011 897 5051",
    "sg:postcode":"10036",
    "sg:province":"Torino",
    "sg:website":"http://www.exagon.to",
    "wof:name":"Exagon Srl",
    "wof:placetype":"venue"
},
  "geometry": {"coordinates":[7.745976,45.148163],"type":"Point"}
}