{
  "type": "Feature",
  "properties": {
    "addr:full":"40068 San Lazzaro Di Savena San Lazzaro Bologna 40068",
    "addr:housenumber":"40068",
    "addr:postcode":"40068",
    "addr:street":"San;San;Bologna",
    "iso:country":"IT",
    "sg:address":"40068 San Lazzaro Di Savena",
    "sg:city":"San Lazzaro",
    "sg:orig_category":"Materiali E Componenti Elettronici",
    "sg:phone":"+39 051 625 8116",
    "sg:postcode":"40068",
    "sg:province":"Bologna",
    "wof:name":"Giucar Service Spa",
    "wof:placetype":"venue"
},
  "geometry": {"coordinates":[11.42886,44.467205],"type":"Point"}
}