{
  "type": "Feature",
  "properties": {
    "iso:country":"IT",
    "sg:address":"114/p, Via Dismano 48100 Ravenna",
    "sg:city":"Ravenna",
    "sg:classifiers":[
        {
            "category":"Communications",
            "subcategory":"Television Station",
            "type":"Services"
        }
    ],
    "sg:phone":"+39 39054462211",
    "sg:postcode":"48100",
    "sg:province":"Ravenna",
    "sg:tags":[
        "audio-visual"
    ],
    "wof:name":"Er Elettronica S.r.l.",
    "wof:placetype":"venue"
},
  "geometry": {"coordinates":[12.213957,44.263042],"type":"Point"}
}