{
  "type": "Feature",
  "properties": {
    "iso:country":"IT",
    "sg:address":"70027 Palo Del Colle",
    "sg:city":"Palo del Colle",
    "sg:orig_category":"Enologia Macchine E Prodotti - Vendita Al Dettaglio",
    "sg:phone":"+39 080 625462",
    "sg:postcode":"70027",
    "sg:province":"Bari",
    "wof:name":"Paver Srl",
    "wof:placetype":"venue"
},
  "geometry": {"coordinates":[16.664501,41.045094],"type":"Point"}
}