{
  "type": "Feature",
  "properties": {
    "iso:country":"IT",
    "sg:address":"91025 Marsala",
    "sg:city":"Marsala",
    "sg:orig_category":"Elettronica Professionale E Di Consumo. Tempo Libero - Articoli E Forniture",
    "sg:phone":"+39 0923 719506",
    "sg:postcode":"91025",
    "sg:province":"Trapani",
    "wof:name":"Falcone Noemi",
    "wof:placetype":"venue"
},
  "geometry": {"coordinates":[12.43629,37.796276],"type":"Point"}
}