{
  "type": "Feature",
  "properties": {
    "iso:country":"IT",
    "sg:address":"Via Ticino, 4/5 21013 Gallarate",
    "sg:city":"Gallarate",
    "sg:classifiers":[
        {
            "category":"Autos & Motor Vehicles",
            "subcategory":"Auto Supplies",
            "type":"Retail Goods"
        }
    ],
    "sg:phone":"+39 0331 796500",
    "sg:postcode":"21013",
    "sg:province":"Varese",
    "sg:tags":[
        "automobile",
        "accessory"
    ],
    "wof:name":"G.f.c. S.r.l.",
    "wof:placetype":"venue"
},
  "geometry": {"coordinates":[8.787714,45.656555],"type":"Point"}
}