{
  "type": "Feature",
  "properties": {
    "addr:full":"74023 Grottaglie Grottaglie Taranto 74023",
    "addr:postcode":"74023;74023",
    "iso:country":"IT",
    "sg:address":"74023 Grottaglie",
    "sg:city":"Grottaglie",
    "sg:orig_category":"Nautica. Automobili E Mezzi Di Trasporto",
    "sg:phone":"+39 099 561 1910",
    "sg:postcode":"74023",
    "sg:province":"Taranto",
    "wof:name":"B&c Nautica Di Bonfrate Donato E Cordella Fedele S.d.f.",
    "wof:placetype":"venue"
},
  "geometry": {"coordinates":[17.440437,40.54467],"type":"Point"}
}