{
  "type": "Feature",
  "properties": {
    "addr:full":"49, Via E. Caorsi 16030 Sori Sori Genova 16030",
    "addr:postcode":"16030;16030",
    "addr:street":"Via E. Caorsi",
    "iso:country":"IT",
    "sg:address":"49, Via E. Caorsi 16030 Sori",
    "sg:city":"Sori",
    "sg:classifiers":[
        {
            "category":"Food & Beverages",
            "subcategory":"Groceries & Convenience Stores",
            "type":"Retail Goods"
        }
    ],
    "sg:phone":"+39 0185 700965",
    "sg:postcode":"16030",
    "sg:province":"Genova",
    "sg:tags":[
        "drink"
    ],
    "wof:name":"Repetto Edoardo",
    "wof:placetype":"venue"
},
  "geometry": {"coordinates":[9.10913,44.379646],"type":"Point"}
}