{
  "type": "Feature",
  "properties": {
    "iso:country":"IT",
    "sg:address":"6, Corso Potenza 10143 Torino",
    "sg:city":"Torino",
    "sg:classifiers":[
        {
            "category":"Professional",
            "subcategory":"Engineering",
            "type":"Services"
        }
    ],
    "sg:phone":"+39 39011757354",
    "sg:postcode":"10143",
    "sg:province":"Torino",
    "sg:tags":[
        "machine",
        "-",
        "mechanical"
    ],
    "wof:name":"Cemag (s.r.l.)",
    "wof:placetype":"venue"
},
  "geometry": {"coordinates":[7.652315,45.088058],"type":"Point"}
}