{
  "type": "Feature",
  "properties": {
    "iso:country":"IT",
    "sg:address":"10143 Torino",
    "sg:city":"Torino",
    "sg:orig_category":"Centri Di Estetica E Cosmesi E Servizi",
    "sg:phone":"+39 011 749 6494",
    "sg:postcode":"10143",
    "sg:province":"Torino",
    "wof:name":"Gemini Di Benetti Viviana",
    "wof:placetype":"venue"
},
  "geometry": {"coordinates":[7.652268,45.082767],"type":"Point"}
}