{
  "type": "Feature",
  "properties": {
    "iso:country":"IT",
    "sg:address":"00197 Roma",
    "sg:city":"Roma",
    "sg:orig_category":"Ambasciate Ed Enti Internazionali",
    "sg:phone":"+39 06 808 1463",
    "sg:postcode":"00197",
    "sg:province":"Roma",
    "wof:name":"Ambasciata Presso La S. Sede Portogallo",
    "wof:placetype":"venue"
},
  "geometry": {"coordinates":[12.479581,41.926895],"type":"Point"}
}