{
  "type": "Feature",
  "properties": {
    "iso:country":"IT",
    "sg:address":"20142 Milano",
    "sg:city":"Milano",
    "sg:orig_category":"Servizi Editoriali. Professionisti - Studi E Servizi Ed Associazioni Di Interesse Aziendale",
    "sg:phone":"+39 02 8930 1747",
    "sg:postcode":"20142",
    "sg:province":"Milano",
    "wof:name":"Bastia Luca",
    "wof:placetype":"venue"
},
  "geometry": {"coordinates":[9.178861,45.419224],"type":"Point"}
}