{
  "type": "Feature",
  "properties": {
    "iso:country":"IT",
    "sg:address":"25060 Lodrino",
    "sg:city":"Lodrino",
    "sg:orig_category":"Cartotecnica",
    "sg:phone":"+39 030 850298",
    "sg:postcode":"25060",
    "sg:province":"Brescia",
    "wof:name":"Cartotecnica Falc",
    "wof:placetype":"venue"
},
  "geometry": {"coordinates":[10.276831,45.719738],"type":"Point"}
}