{
  "type": "Feature",
  "properties": {
    "addr:full":"Via Dei Laghi 1 61030 Saltara Saltara Pesaro E Urbino 61030",
    "addr:housenumber":"1",
    "addr:postcode":"61030;61030",
    "addr:street":"Via Dei Laghi",
    "iso:country":"IT",
    "sg:address":"Via Dei Laghi 1 61030 Saltara",
    "sg:city":"Saltara",
    "sg:classifiers":[
        {
            "category":"Building & Trades",
            "subcategory":"Construction",
            "type":"Services"
        }
    ],
    "sg:phone":"+39 0721 899500",
    "sg:postcode":"61030",
    "sg:province":"Pesaro E Urbino",
    "sg:tags":[
        "installation",
        "heating"
    ],
    "sg:website":"www.imeaimpianti.it",
    "wof:name":"Imea Impianti Srl",
    "wof:placetype":"venue"
},
  "geometry": {"coordinates":[12.529803,43.633556],"type":"Point"}
}