{
  "type": "Feature",
  "properties": {
    "iso:country":"IT",
    "sg:address":"Piazza Cantoniera 95030 Nicolosi",
    "sg:city":"Nicolosi",
    "sg:classifiers":[
        {
            "category":"Travel",
            "subcategory":"Travel Agent",
            "type":"Entertainment"
        }
    ],
    "sg:phone":"+39 39095914122",
    "sg:postcode":"95030",
    "sg:province":"Catania",
    "sg:tags":[
        "business"
    ],
    "wof:name":"Corsaro",
    "wof:placetype":"venue"
},
  "geometry": {"coordinates":[15.020676,37.65406],"type":"Point"}
}