{
  "type": "Feature",
  "properties": {
    "iso:country":"IT",
    "sg:address":"22046 Merone",
    "sg:city":"Merone",
    "sg:orig_category":"Tessuti E Stoffe",
    "sg:phone":"+39 031 650106",
    "sg:postcode":"22046",
    "sg:province":"Como",
    "wof:name":"Industrie Tessili Bresciane (s.p.a.)",
    "wof:placetype":"venue"
},
  "geometry": {"coordinates":[9.248996,45.786018],"type":"Point"}
}