{
  "type": "Feature",
  "properties": {
    "addr:full":"24028 Ponte Nossa Ponte Nossa Bergamo 24028",
    "addr:postcode":"24028;24028",
    "iso:country":"IT",
    "sg:address":"24028 Ponte Nossa",
    "sg:city":"Ponte Nossa",
    "sg:orig_category":"Imprese Di Costruzioni Civili Ed Industriali",
    "sg:phone":"+39 035 706024",
    "sg:postcode":"24028",
    "sg:province":"Bergamo",
    "wof:name":"Duesse Coperture Srl",
    "wof:placetype":"venue"
},
  "geometry": {"coordinates":[9.936003,45.888203],"type":"Point"}
}