{
  "type": "Feature",
  "properties": {
    "iso:country":"IT",
    "sg:address":"15, Via Toscana 59100 Prato",
    "sg:city":"Prato",
    "sg:classifiers":[
        {
            "category":"Shopping",
            "subcategory":"Clothing, Apparel, & Fashions",
            "type":"Retail Goods"
        }
    ],
    "sg:phone":"+39 39800611490",
    "sg:postcode":"59100",
    "sg:province":"Prato",
    "sg:tags":[
        "clothes"
    ],
    "wof:name":"Sasch S.p.a.",
    "wof:placetype":"venue"
},
  "geometry": {"coordinates":[11.101062,43.963589],"type":"Point"}
}