{
  "type": "Feature",
  "properties": {
    "addr:full":"20131 Milano Milano Milano 20131",
    "addr:postcode":"20131;20131",
    "iso:country":"IT",
    "sg:address":"20131 Milano",
    "sg:city":"Milano",
    "sg:orig_category":"Servizi Ausiliari Dei Mezzi Di Trasporto",
    "sg:phone":"+39 02 266 4969",
    "sg:postcode":"20131",
    "sg:province":"Milano",
    "wof:name":"Mangione Pasquale",
    "wof:placetype":"venue"
},
  "geometry": {"coordinates":[9.230123,45.482635],"type":"Point"}
}