{
  "type": "Feature",
  "properties": {
    "iso:country":"IT",
    "sg:address":"25030 Rudiano",
    "sg:city":"Rudiano",
    "sg:orig_category":"Forniture Per Abbigliamento E Pelletterie",
    "sg:phone":"+39 030 716257",
    "sg:postcode":"25030",
    "sg:province":"Brescia",
    "wof:name":"Iperbottoni Di Mercandelli Domenico & C. S.n.c.",
    "wof:placetype":"venue"
},
  "geometry": {"coordinates":[10.2856149673,45.4820594788],"type":"Point"}
}