{
  "type": "Feature",
  "properties": {
    "iso:country":"IT",
    "sg:address":"Via Due Portoni 23 40132 Bologna",
    "sg:city":"Bologna",
    "sg:orig_category":"Actuators, Linear",
    "sg:phone":"+39 051 402221",
    "sg:postcode":"40132",
    "sg:province":"Bologna",
    "sg:website":"www.ognibene.biol.it",
    "wof:name":"Ognibene Elettromeccanica Srl",
    "wof:placetype":"venue"
},
  "geometry": {"coordinates":[11.275235,44.528698],"type":"Point"}
}