{
  "type": "Feature",
  "properties": {
    "addr:full":"13100 Vercelli Vercelli Vercelli 13100",
    "addr:postcode":"13100;13100",
    "iso:country":"IT",
    "sg:address":"13100 Vercelli",
    "sg:city":"Vercelli",
    "sg:orig_category":"Studi E Consulenze Tecniche E Industriali. Servizi E Lavori Per Edilizia E Lavori Pubblici. Professionisti - Studi E Servizi Ed Associazioni Di Interesse Aziendale",
    "sg:phone":"+39 0161 502080",
    "sg:postcode":"13100",
    "sg:province":"Vercelli",
    "wof:name":"Meucci Arch. Donatella",
    "wof:placetype":"venue"
},
  "geometry": {"coordinates":[8.424092,45.324757],"type":"Point"}
}