{
  "type": "Feature",
  "properties": {
    "iso:country":"IT",
    "sg:address":"Piazza Giovanni; Strada Casentino; 52018",
    "sg:city":"Strada",
    "sg:classifiers":[
        {
            "category":"Banks & Credit Unions",
            "subcategory":"Bank",
            "type":"Services"
        }
    ],
    "sg:phone":"+39 0575 57915",
    "sg:postcode":"52018",
    "sg:province":"Arezzo",
    "wof:name":"Banca Toscana Spa",
    "wof:placetype":"venue"
},
  "geometry": {"coordinates":[11.649913,43.718239],"type":"Point"}
}