{
  "type": "Feature",
  "properties": {
    "iso:country":"IT",
    "sg:address":"39046 Ortisei",
    "sg:city":"Ortisei",
    "sg:orig_category":"Arredi Sacri",
    "sg:phone":"+39 0471 796148",
    "sg:postcode":"39046",
    "sg:province":"Bolzano/Bozen",
    "wof:name":"Otco - Comploj Sas",
    "wof:placetype":"venue"
},
  "geometry": {"coordinates":[11.677456,46.573448],"type":"Point"}
}