{
  "type": "Feature",
  "properties": {
    "iso:country":"IT",
    "sg:address":"10, V. Roma 31010 Godega Di Sant'urbano",
    "sg:classifiers":[
        {
            "category":"Autos & Motor Vehicles",
            "subcategory":"Automobile Sales",
            "type":"Retail Goods"
        }
    ],
    "sg:phone":"+39 39043838181",
    "sg:postcode":"31010",
    "sg:province":"Treviso",
    "sg:tags":[
        "industrial"
    ],
    "sg:website":"http://www.paginegialle.it/piaveammor",
    "wof:name":"Ammortizzatori Piave",
    "wof:placetype":"venue"
},
  "geometry": {"coordinates":[12.393686,45.928169],"type":"Point"}
}