{
  "type": "Feature",
  "properties": {
    "addr:full":"20093 Cologno Monzese Cologno Monzese Milano 20093",
    "addr:postcode":"20093;20093",
    "iso:country":"IT",
    "sg:address":"20093 Cologno Monzese",
    "sg:city":"Cologno Monzese",
    "sg:orig_category":"Servizi E Lavori Industria Della Gomma",
    "sg:phone":"+39 02 254 9632",
    "sg:postcode":"20093",
    "sg:province":"Milano",
    "wof:name":"Andreoli Nastri Snc",
    "wof:placetype":"venue"
},
  "geometry": {"coordinates":[9.279129,45.541409],"type":"Point"}
}