{
  "type": "Feature",
  "properties": {
    "iso:country":"IT",
    "sg:address":"00050 Roma",
    "sg:orig_category":"Non-classified Establishments",
    "sg:phone":"+39 06 6500 2901",
    "sg:postcode":"00050",
    "sg:province":"Roma",
    "wof:name":"Ebc European Business Consultancy Srl",
    "wof:placetype":"venue"
},
  "geometry": {"coordinates":[12.467308,41.839008],"type":"Point"}
}