{
  "type": "Feature",
  "properties": {
    "iso:country":"IT",
    "sg:address":"95, V. Della Concia 36071 Arzignano",
    "sg:city":"Arzignano",
    "sg:classifiers":[
        {
            "category":"Manufacturing",
            "subcategory":"Textiles",
            "type":"Manufacturing & Wholesale Goods"
        }
    ],
    "sg:phone":"+39 0444 472322",
    "sg:postcode":"36071",
    "sg:province":"Vicenza",
    "sg:tags":[
        "leather",
        "raw",
        "material",
        "-"
    ],
    "sg:website":"http://www.flora.it",
    "wof:name":"New Castle Spa",
    "wof:placetype":"venue"
},
  "geometry": {"coordinates":[11.540307,45.545906],"type":"Point"}
}