{
  "type": "Feature",
  "properties": {
    "addr:full":"39026 Prato Allo Stelvio Prato allo Stelvio Bolzano/Bozen 39026",
    "addr:postcode":"39026;39026",
    "iso:country":"IT",
    "sg:address":"39026 Prato Allo Stelvio",
    "sg:city":"Prato allo Stelvio",
    "sg:orig_category":"Ceramiche: Prodotti E Lavorazioni",
    "sg:phone":"+39 0473 616315",
    "sg:postcode":"39026",
    "sg:province":"Bolzano/Bozen",
    "wof:name":"Internform Snc Di Koch Waldner & Co.",
    "wof:placetype":"venue"
},
  "geometry": {"coordinates":[10.58814,46.62746],"type":"Point"}
}