{
  "type": "Feature",
  "properties": {
    "iso:country":"IT",
    "sg:address":"43, V. Cattaneo 09016 Iglesias",
    "sg:city":"Iglesias",
    "sg:classifiers":[
        {
            "category":"Autos & Motor Vehicles",
            "subcategory":"Automobile Sales",
            "type":"Retail Goods"
        }
    ],
    "sg:phone":"+39 39078123540",
    "sg:postcode":"09016",
    "sg:province":"Carbonia-Iglesias",
    "sg:tags":[
        "motor-cars"
    ],
    "sg:website":"http://www.autoprestigeiglesias.it",
    "wof:name":"Autoprestige Iglesias Srl",
    "wof:placetype":"venue"
},
  "geometry": {"coordinates":[8.5270614624,39.3117446899],"type":"Point"}
}