{
  "type": "Feature",
  "properties": {
    "addr:full":"71010 Serracapriola Serracapriola Foggia 71010",
    "addr:postcode":"71010;71010",
    "iso:country":"IT",
    "sg:address":"71010 Serracapriola",
    "sg:city":"Serracapriola",
    "sg:orig_category":"Prodotti Alimentari",
    "sg:phone":"+39 0882 682690",
    "sg:postcode":"71010",
    "sg:province":"Foggia",
    "wof:name":"D'amicis Egidia",
    "wof:placetype":"venue"
},
  "geometry": {"coordinates":[15.1600923538,41.8087005615],"type":"Point"}
}