{
  "type": "Feature",
  "properties": {
    "iso:country":"IT",
    "sg:address":"15100 Alessandria",
    "sg:city":"Alessandria",
    "sg:orig_category":"Riparazione Dei Mezzi Di Trasporto",
    "sg:phone":"+39 0131 342074",
    "sg:postcode":"15100",
    "sg:province":"Alessandria",
    "sg:website":"http://www.raiterisnc.it",
    "wof:name":"Garage Raiteri Di Raiteri Roberto & C. Snc",
    "wof:placetype":"venue"
},
  "geometry": {"coordinates":[8.603693,44.900925],"type":"Point"}
}