{
  "type": "Feature",
  "properties": {
    "iso:country":"IT",
    "sg:address":"37020 Volargne",
    "sg:city":"Volargne",
    "sg:orig_category":"Arredo Urbano",
    "sg:phone":"+39 045 686 1521",
    "sg:postcode":"37020",
    "sg:province":"Verona",
    "sg:website":"http://www.marmimondini.it",
    "wof:name":"Marmi Mondini Snc",
    "wof:placetype":"venue"
},
  "geometry": {"coordinates":[10.82313,45.547371],"type":"Point"}
}