{
  "type": "Feature",
  "properties": {
    "addr:full":"26, Viale Dell' Industria 36016 Thiene Thiene Vicenza 36016",
    "addr:housenumber":"26",
    "addr:postcode":"36016;36016",
    "addr:street":"Viale Dell ' Industria",
    "iso:country":"IT",
    "sg:address":"26, Viale Dell' Industria 36016 Thiene",
    "sg:city":"Thiene",
    "sg:classifiers":[
        {
            "category":"Communications",
            "subcategory":"Television Station",
            "type":"Services"
        }
    ],
    "sg:phone":"+39 0445 380737",
    "sg:postcode":"36016",
    "sg:province":"Vicenza",
    "sg:tags":[
        "audio-visual"
    ],
    "wof:name":"Sertech Elettronica (s.r.l.)",
    "wof:placetype":"venue"
},
  "geometry": {"coordinates":[11.512132,45.705952],"type":"Point"}
}