{
  "type": "Feature",
  "properties": {
    "iso:country":"IT",
    "sg:address":"27025 Gambol\u00f2",
    "sg:orig_category":"Carrozzerie Automobili",
    "sg:phone":"+39 0381 930659",
    "sg:postcode":"27025",
    "sg:province":"Pavia",
    "sg:website":"http://www.users.iol.it/pastocar",
    "wof:name":"Carrozzeria Artigiana Di Pastormerlo Giuseppe",
    "wof:placetype":"venue"
},
  "geometry": {"coordinates":[8.85974,45.258156],"type":"Point"}
}