{
  "type": "Feature",
  "properties": {
    "addr:full":"18033 Camporosso Camporosso Imperia 18033",
    "addr:postcode":"18033;18033",
    "iso:country":"IT",
    "sg:address":"18033 Camporosso",
    "sg:city":"Camporosso",
    "sg:orig_category":"Legno E Semilavorati",
    "sg:phone":"+39 0184 250796",
    "sg:postcode":"18033",
    "sg:province":"Imperia",
    "sg:website":"http://www.bosiolignum.it",
    "wof:name":"Bosio Lignum Di Gio' Battista Bosio & C. Snc",
    "wof:placetype":"venue"
},
  "geometry": {"coordinates":[7.6331768036,43.7958602905],"type":"Point"}
}