{
  "type": "Feature",
  "properties": {
    "addr:full":"Via Roma 21a 21045 Gazzada Gazzada Varese 21045",
    "addr:housenumber":"21a",
    "addr:postcode":"21045;21045",
    "addr:street":"Via Roma",
    "iso:country":"IT",
    "sg:address":"Via Roma 21a 21045 Gazzada",
    "sg:city":"Gazzada",
    "sg:classifiers":[
        {
            "category":"Food & Beverages",
            "subcategory":"Chocolate",
            "type":"Retail Goods"
        }
    ],
    "sg:phone":"+39 0332 872111",
    "sg:postcode":"21045",
    "sg:province":"Varese",
    "sg:tags":[
        "export"
    ],
    "sg:website":"www.gbianchi.it",
    "wof:name":"Giuseppe Bianchi Spa",
    "wof:placetype":"venue"
},
  "geometry": {"coordinates":[8.7706880569,45.7761116028],"type":"Point"}
}