{
  "type": "Feature",
  "properties": {
    "iso:country":"IT",
    "sg:address":"87100 Corigliano",
    "sg:classifiers":[
        {
            "category":"Communications",
            "subcategory":"Film & Video Production",
            "type":"Services"
        }
    ],
    "sg:phone":"+39 0983 857836",
    "sg:postcode":"87100",
    "sg:province":"Cosenza",
    "sg:tags":[
        "cracker",
        "e",
        "biscotti"
    ],
    "wof:name":"Lombisani Aldo Giorgio",
    "wof:placetype":"venue"
},
  "geometry": {"coordinates":[16.538309,39.654221],"type":"Point"}
}