{
  "type": "Feature",
  "properties": {
    "iso:country":"IT",
    "sg:address":"26, Via Giuseppe Di Vittorio 50067 Rignano Sull'arno",
    "sg:classifiers":[
        {
            "category":"Bars & Pubs",
            "subcategory":"Nightclub",
            "type":"Food & Drink"
        }
    ],
    "sg:phone":"+39 055 834 8807",
    "sg:postcode":"50067",
    "sg:province":"Firenze",
    "sg:tags":[
        "cake",
        "bread"
    ],
    "wof:name":"Il Pasticcere Srl",
    "wof:placetype":"venue"
},
  "geometry": {"coordinates":[11.256902,43.768734],"type":"Point"}
}