{
  "type": "Feature",
  "properties": {
    "iso:country":"IT",
    "sg:address":"33041 Aiello Del Friuli",
    "sg:city":"Aiello del Friuli",
    "sg:classifiers":[
        {
            "category":"Shopping",
            "subcategory":"Hobbies, Toys, & Games",
            "type":"Retail Goods"
        }
    ],
    "sg:phone":"+39 0431 99555",
    "sg:postcode":"33041",
    "sg:province":"Udine",
    "sg:tags":[
        "article",
        "sport",
        "supply"
    ],
    "wof:name":"Dana Sport Snc",
    "wof:placetype":"venue"
},
  "geometry": {"coordinates":[13.35304,45.871696],"type":"Point"}
}