{
  "type": "Feature",
  "properties": {
    "iso:country":"IT",
    "sg:address":"95029 Viagrande",
    "sg:city":"Viagrande",
    "sg:orig_category":"Medicali Ed Elettromedicali Impianti Ed Apparecchi - Produzione",
    "sg:phone":"+39 095 789 0358",
    "sg:postcode":"95029",
    "sg:province":"Catania",
    "wof:name":"Lanzafame Carmelo",
    "wof:placetype":"venue"
},
  "geometry": {"coordinates":[15.089988,37.564751],"type":"Point"}
}