{
  "type": "Feature",
  "properties": {
    "addr:full":"00054 Fiumicino Fiumicino Roma 00054",
    "addr:postcode":"00054;roma 00054",
    "iso:country":"IT",
    "sg:address":"00054 Fiumicino",
    "sg:city":"Fiumicino",
    "sg:orig_category":"Nautica. Automobili E Mezzi Di Trasporto",
    "sg:phone":"+39 06 652 2410",
    "sg:postcode":"00054",
    "sg:province":"Roma",
    "wof:name":"Agostinelli Vinicio",
    "wof:placetype":"venue"
},
  "geometry": {"coordinates":[12.262609,41.766525],"type":"Point"}
}