{
  "type": "Feature",
  "properties": {
    "iso:country":"IT",
    "sg:address":"00199 Roma",
    "sg:city":"Roma",
    "sg:orig_category":"Non-classified Establishments",
    "sg:phone":"+39 06 8620 6966",
    "sg:postcode":"00199",
    "sg:province":"Roma",
    "wof:name":"Aerre Srl",
    "wof:placetype":"venue"
},
  "geometry": {"coordinates":[12.510372,41.92683],"type":"Point"}
}