{
  "type": "Feature",
  "properties": {
    "addr:full":"65129 Pescara Pescara Pescara 65129",
    "addr:postcode":"65129;65129",
    "iso:country":"IT",
    "sg:address":"65129 Pescara",
    "sg:city":"Pescara",
    "sg:orig_category":"Antifurto",
    "sg:phone":"+39 085 431 0433",
    "sg:postcode":"65129",
    "sg:province":"Pescara",
    "wof:name":"Custos Di Franco Marsilii",
    "wof:placetype":"venue"
},
  "geometry": {"coordinates":[14.222154,42.435329],"type":"Point"}
}