{
  "type": "Feature",
  "properties": {
    "iso:country":"IT",
    "sg:address":"24040 Fornovo San Giovanni",
    "sg:city":"Fornovo San Giovanni",
    "sg:classifiers":[
        {
            "category":"Utilities",
            "subcategory":"Natural Gas",
            "type":"Services"
        }
    ],
    "sg:phone":"+39 036 357697",
    "sg:postcode":"24040",
    "sg:province":"Bergamo",
    "sg:tags":[
        "alloy",
        "metal"
    ],
    "sg:website":"http://www.tecnoalloy.com",
    "wof:name":"Tecnoalloy Srl",
    "wof:placetype":"venue"
},
  "geometry": {"coordinates":[9.6987981796,45.4864082336],"type":"Point"}
}