{
  "type": "Feature",
  "properties": {
    "addr:full":"37012 Bussolengo Bussolengo Verona 37012",
    "addr:postcode":"37012;37012",
    "iso:country":"IT",
    "sg:address":"37012 Bussolengo",
    "sg:city":"Bussolengo",
    "sg:orig_category":"Ristorazione E Locali Pubblici Affini. Ristoranti Ed Esercizi Affini",
    "sg:phone":"+39 045 675 8222",
    "sg:postcode":"37012",
    "sg:province":"Verona",
    "wof:name":"Albergo Roma Srl",
    "wof:placetype":"venue"
},
  "geometry": {"coordinates":[10.846689,45.472919],"type":"Point"}
}