{
  "type": "Feature",
  "properties": {
    "iso:country":"IT",
    "sg:address":"24044 Dalmine",
    "sg:city":"Dalmine",
    "sg:orig_category":"Ricambi E Componenti Dei Mezzi Di Trasporto",
    "sg:phone":"+39 035 370455",
    "sg:postcode":"24044",
    "sg:province":"Bergamo",
    "wof:name":"Meccanica Brembana Srl",
    "wof:placetype":"venue"
},
  "geometry": {"coordinates":[9.626537,45.650749],"type":"Point"}
}