{
  "type": "Feature",
  "properties": {
    "iso:country":"IT",
    "sg:address":"10032 Brandizzo",
    "sg:city":"Brandizzo",
    "sg:orig_category":"Banche E Servizi Finanziari. Acqua, Luce, Gas E Societa' Di Esercizio Pubblico",
    "sg:phone":"+39 011 917 8243",
    "sg:postcode":"10032",
    "sg:province":"Torino",
    "wof:name":"Uniriscossioni Spa",
    "wof:placetype":"venue"
},
  "geometry": {"coordinates":[7.757177,45.146152],"type":"Point"}
}