{
  "type": "Feature",
  "properties": {
    "iso:country":"IT",
    "sg:address":"51030 Serravalle Pistoiese",
    "sg:city":"Serravalle Pistoiese",
    "sg:orig_category":"Elettrotecnica Industriale, Prodotti E Apparecchiature",
    "sg:phone":"+39 0573 526632",
    "sg:postcode":"51030",
    "sg:province":"Pistoia",
    "sg:website":"http://www.veltha.it",
    "wof:name":"Veltha Elettromeccanica Sas",
    "wof:placetype":"venue"
},
  "geometry": {"coordinates":[10.83431,43.906147],"type":"Point"}
}