{
  "type": "Feature",
  "properties": {
    "addr:full":"25020 Milzano Milzano Brescia 25020",
    "addr:postcode":"25020;25020",
    "iso:country":"IT",
    "sg:address":"25020 Milzano",
    "sg:city":"Milzano",
    "sg:orig_category":"Zootecnia E Pesca, Allevamento Piccoli Animali",
    "sg:phone":"+39 030 954 7492",
    "sg:postcode":"25020",
    "sg:province":"Brescia",
    "wof:name":"Azienda Agricola Aquilini Wanda E Antonio",
    "wof:placetype":"venue"
},
  "geometry": {"coordinates":[10.195004,45.272789],"type":"Point"}
}