{
  "type": "Feature",
  "properties": {
    "iso:country":"IT",
    "sg:address":"35010 Fratte",
    "sg:city":"Fratte",
    "sg:orig_category":"Macchine E Forniture Per Industria Orafa E Per Orologeria",
    "sg:phone":"+39 049 932 3777",
    "sg:postcode":"35010",
    "sg:province":"Padova",
    "wof:name":"Morellato S.p.a.",
    "wof:placetype":"venue"
},
  "geometry": {"coordinates":[11.903748,45.578758],"type":"Point"}
}