{
  "type": "Feature",
  "properties": {
    "iso:country":"IT",
    "sg:address":"28, Viale S. Eufemia 25135 Brescia",
    "sg:city":"Brescia",
    "sg:classifiers":[
        {
            "category":"Autos & Motor Vehicles",
            "subcategory":"Automobile Sales",
            "type":"Retail Goods"
        }
    ],
    "sg:phone":"+39 39030371851",
    "sg:postcode":"25135",
    "sg:province":"Brescia",
    "sg:tags":[
        "motor-cars"
    ],
    "wof:name":"Bonera (s.p.a.)",
    "wof:placetype":"venue"
},
  "geometry": {"coordinates":[10.2805194855,45.4932403564],"type":"Point"}
}