{
  "type": "Feature",
  "properties": {
    "iso:country":"IT",
    "sg:address":"5, Via Enrico Fermi 27052 Godiasco",
    "sg:city":"Godiasco",
    "sg:classifiers":[
        {
            "category":"Travel",
            "subcategory":"Travel Agent",
            "type":"Entertainment"
        }
    ],
    "sg:phone":"+39 39038391941",
    "sg:postcode":"27052",
    "sg:province":"Pavia",
    "sg:tags":[
        "business"
    ],
    "wof:name":"President Hotel Terme",
    "wof:placetype":"venue"
},
  "geometry": {"coordinates":[9.055069,44.897251],"type":"Point"}
}