{
  "type": "Feature",
  "properties": {
    "iso:country":"IT",
    "sg:address":"11, Via Palumbo Gino 84013 Cava De' Tirreni",
    "sg:classifiers":[
        {
            "category":"Farming",
            "subcategory":"Livestock Farm",
            "type":"Manufacturing & Wholesale Goods"
        }
    ],
    "sg:phone":"+39 39089343037",
    "sg:postcode":"84013",
    "sg:province":"Salerno",
    "sg:tags":[
        "agriculture"
    ],
    "wof:name":"D'amico Mario (s.r.l.)",
    "wof:placetype":"venue"
},
  "geometry": {"coordinates":[14.765912,40.677956],"type":"Point"}
}