{
  "type": "Feature",
  "properties": {
    "iso:country":"IT",
    "sg:address":"21054 Fagnano Olona",
    "sg:city":"Fagnano Olona",
    "sg:orig_category":"Elettrodomestici. Elettronica Professionale E Di Consumo. Arredi Ed Attrezzature Per Attivita' Commerciali Ed Artigianali. Macchine, Strumenti Ed Apparecchi Per Attivita' Industriali",
    "sg:phone":"+39 0331 685532",
    "sg:postcode":"21054",
    "sg:province":"Varese",
    "wof:name":"Luoni & Scampini Snc",
    "wof:placetype":"venue"
},
  "geometry": {"coordinates":[8.818511,45.641552],"type":"Point"}
}