{
  "type": "Feature",
  "properties": {
    "iso:country":"IT",
    "sg:address":"31, Via Goito 10042 Nichelino",
    "sg:city":"Nichelino",
    "sg:classifiers":[
        {
            "category":"Manufacturing",
            "subcategory":"Metals",
            "type":"Manufacturing & Wholesale Goods"
        }
    ],
    "sg:phone":"+39 011 680 7788",
    "sg:postcode":"10042",
    "sg:province":"Torino",
    "sg:tags":[
        "processing"
    ],
    "wof:name":"O.s.a.i S.r.l.",
    "wof:placetype":"venue"
},
  "geometry": {"coordinates":[7.6393322945,44.976146698],"type":"Point"}
}