{
  "type": "Feature",
  "properties": {
    "iso:country":"IT",
    "sg:address":"00187 Roma",
    "sg:city":"Roma",
    "sg:orig_category":"Apparecchi, Attrezzature E Forniture Per Centri Estetici",
    "sg:phone":"+39 06 3211 0246",
    "sg:postcode":"00187",
    "sg:province":"Roma",
    "wof:name":"Biosan World Corporation S.r.l.",
    "wof:placetype":"venue"
},
  "geometry": {"coordinates":[12.480508,41.907169],"type":"Point"}
}