{
  "type": "Feature",
  "properties": {
    "iso:country":"IT",
    "sg:address":"20121 Milano",
    "sg:city":"Milano",
    "sg:orig_category":"Ospedali E Servizi Sanitari",
    "sg:phone":"+39 02 780173",
    "sg:postcode":"20121",
    "sg:province":"Milano",
    "wof:name":"N.s.r. Srl",
    "wof:placetype":"venue"
},
  "geometry": {"coordinates":[9.197164,45.469215],"type":"Point"}
}