{
  "type": "Feature",
  "properties": {
    "iso:country":"IT",
    "sg:address":"16131 Genova",
    "sg:city":"Genova",
    "sg:classifiers":[
        {
            "category":"Health Services",
            "subcategory":"Health Practitioner",
            "type":"Services"
        }
    ],
    "sg:phone":"+39 010 315622",
    "sg:postcode":"16131",
    "sg:province":"Genova",
    "sg:tags":[
        "medici"
    ],
    "wof:name":"Boccia Dr. Flavio",
    "wof:placetype":"venue"
},
  "geometry": {"coordinates":[8.962623,44.404549],"type":"Point"}
}