{
  "type": "Feature",
  "properties": {
    "addr:full":"90129 Palermo Palermo Palermo 90129",
    "addr:postcode":"90129;90129",
    "iso:country":"IT",
    "sg:address":"90129 Palermo",
    "sg:city":"Palermo",
    "sg:orig_category":"Servizi Di Magazzinaggio E Movimentazione. Servizi Ausiliari Di Sorveglianza, Manutenzione E Pulizia",
    "sg:phone":"+39 091 420572",
    "sg:postcode":"90129",
    "sg:province":"Palermo",
    "wof:name":"Autotraslochi Salamone Antonino",
    "wof:placetype":"venue"
},
  "geometry": {"coordinates":[13.329555,38.096218],"type":"Point"}
}