{
  "type": "Feature",
  "properties": {
    "iso:country":"IT",
    "sg:address":"Via Fontenoce 62019 Recanati",
    "sg:city":"Recanati",
    "sg:classifiers":[
        {
            "category":"Sports & Exercise",
            "subcategory":"Playing Field",
            "type":"Entertainment"
        }
    ],
    "sg:phone":"+39 390 717 5811",
    "sg:postcode":"62019",
    "sg:province":"Macerata",
    "sg:tags":[
        "game"
    ],
    "wof:name":"Clementoni (s.p.a.)",
    "wof:placetype":"venue"
},
  "geometry": {"coordinates":[13.456262,43.300747],"type":"Point"}
}