{
  "type": "Feature",
  "properties": {
    "iso:country":"IT",
    "sg:address":"40056 Crespellano",
    "sg:city":"Crespellano",
    "sg:classifiers":[
        {
            "category":"Parking",
            "subcategory":"Lot",
            "type":"Transportation"
        }
    ],
    "sg:phone":"+39 051 969367",
    "sg:postcode":"40056",
    "sg:province":"Bologna",
    "sg:tags":[
        "good",
        "shipment",
        "transport"
    ],
    "wof:name":"Botrans Srl",
    "wof:placetype":"venue"
},
  "geometry": {"coordinates":[11.129846,44.521412],"type":"Point"}
}