{
  "type": "Feature",
  "properties": {
    "iso:country":"IT",
    "sg:address":"50053 Empoli",
    "sg:city":"Empoli",
    "sg:orig_category":"Autofficine E Centri Assistenza",
    "sg:phone":"+39 0571 83791",
    "sg:postcode":"50053",
    "sg:province":"Firenze",
    "wof:name":"Autofficina Guastamacchia Mario",
    "wof:placetype":"venue"
},
  "geometry": {"coordinates":[11.309132,43.767101],"type":"Point"}
}