{
  "type": "Feature",
  "properties": {
    "addr:full":"21, Viale Vittorio Veneto 20052 Monza Monza Milano 20052",
    "addr:housenumber":"21",
    "addr:postcode":"20052;20052",
    "addr:street":"Viale Vittorio Veneto",
    "iso:country":"IT",
    "sg:address":"21, Viale Vittorio Veneto 20052 Monza",
    "sg:city":"Monza",
    "sg:classifiers":[
        {
            "category":"Utilities",
            "subcategory":"Electric",
            "type":"Services"
        }
    ],
    "sg:phone":"+39 390 392 0841",
    "sg:postcode":"20052",
    "sg:province":"Milano",
    "sg:tags":[
        "component",
        "electronic"
    ],
    "wof:name":"Exhibo S.p.a.",
    "wof:placetype":"venue"
},
  "geometry": {"coordinates":[9.212162,45.552273],"type":"Point"}
}