{
  "type": "Feature",
  "properties": {
    "addr:full":"65123 Pescara Pescara Pescara 65123",
    "addr:postcode":"65123;65123",
    "iso:country":"IT",
    "sg:address":"65123 Pescara",
    "sg:city":"Pescara",
    "sg:orig_category":"Servizi Editoriali",
    "sg:phone":"+39 085 471 1460",
    "sg:postcode":"65123",
    "sg:province":"Pescara",
    "wof:name":"Di Fonzo Antonella",
    "wof:placetype":"venue"
},
  "geometry": {"coordinates":[14.164102,42.400593],"type":"Point"}
}