{
  "type": "Feature",
  "properties": {
    "addr:full":"20096 Pioltello Pioltello Milano 20096",
    "addr:postcode":"20096;20096",
    "iso:country":"IT",
    "sg:address":"20096 Pioltello",
    "sg:city":"Pioltello",
    "sg:orig_category":"Serbatoi - Produzione E Commercio",
    "sg:phone":"+39 02 926 6535",
    "sg:postcode":"20096",
    "sg:province":"Milano",
    "wof:name":"Bevilacqua Costruzioni E Impianti Spa",
    "wof:placetype":"venue"
},
  "geometry": {"coordinates":[9.321445,45.485615],"type":"Point"}
}