{
  "type": "Feature",
  "properties": {
    "iso:country":"IT",
    "sg:address":"25125 Brescia",
    "sg:city":"Brescia",
    "sg:orig_category":"Elettrotecnica Professionale E Di Consumo. Forniture Alle Strutture Ricettive. Arredi Ed Attrezzature Per Attivita' Commerciali Ed Artigianali",
    "sg:phone":"+39 030 354 0266",
    "sg:postcode":"25125",
    "sg:province":"Brescia",
    "wof:name":"Cartemani Asciugamani In Carta S.r.l.",
    "wof:placetype":"venue"
},
  "geometry": {"coordinates":[10.189363,45.526676],"type":"Point"}
}