{
  "type": "Feature",
  "properties": {
    "addr:full":"20021 Bollate Bollate Milano 20021",
    "addr:postcode":"20021;20021",
    "iso:country":"IT",
    "sg:address":"20021 Bollate",
    "sg:city":"Bollate",
    "sg:orig_category":"Studi E Consulenze Legali E Notarili. Avvocati, Notai E Servizi Legali. Professionisti - Studi E Servizi Ed Associazioni Di Interesse Aziendale",
    "sg:phone":"+39 02 350 2741",
    "sg:postcode":"20021",
    "sg:province":"Milano",
    "wof:name":"Guidobono Cavalchini Claudio",
    "wof:placetype":"venue"
},
  "geometry": {"coordinates":[9.118803,45.543953],"type":"Point"}
}