{
  "type": "Feature",
  "properties": {
    "addr:full":"25080 Serle Serle Brescia 25080",
    "addr:postcode":"25080;25080",
    "iso:country":"IT",
    "sg:address":"25080 Serle",
    "sg:city":"Serle",
    "sg:orig_category":"Petroli, Gas E Combustibili",
    "sg:phone":"+39 030 691 0071",
    "sg:postcode":"25080",
    "sg:province":"Brescia",
    "wof:name":"Bresciani Aldo",
    "wof:placetype":"venue"
},
  "geometry": {"coordinates":[10.3760480881,45.5587043762],"type":"Point"}
}