{
  "type": "Feature",
  "properties": {
    "addr:full":"33080 Zoppola Zoppola Pordenone 33080",
    "addr:postcode":"33080;33080",
    "iso:country":"IT",
    "sg:address":"33080 Zoppola",
    "sg:city":"Zoppola",
    "sg:orig_category":"Macchine Ed Impianti Per Edilizia E Lavori Pubblici",
    "sg:phone":"+39 0434 574531",
    "sg:postcode":"33080",
    "sg:province":"Pordenone",
    "wof:name":"Bauma Edilservice Spa",
    "wof:placetype":"venue"
},
  "geometry": {"coordinates":[12.762796,45.950314],"type":"Point"}
}