{
  "type": "Feature",
  "properties": {
    "iso:country":"IT",
    "sg:address":"21, V. Firenze 95030 Nicolosi",
    "sg:city":"Nicolosi",
    "sg:classifiers":[
        {
            "category":"Food & Beverages",
            "subcategory":"Groceries & Convenience Stores",
            "type":"Retail Goods"
        }
    ],
    "sg:phone":"+39 39095914198",
    "sg:postcode":"95030",
    "sg:province":"Catania",
    "sg:tags":[
        "drink"
    ],
    "sg:website":"http://www.vinipappalardo.it",
    "wof:name":"Casa Vinicola Pappalardo",
    "wof:placetype":"venue"
},
  "geometry": {"coordinates":[15.028641,37.593792],"type":"Point"}
}