{
  "type": "Feature",
  "properties": {
    "iso:country":"IT",
    "sg:address":"24040 Canonica D'adda",
    "sg:orig_category":"Minuterie Metalliche E Ferramenta",
    "sg:phone":"+39 02 909 4085",
    "sg:postcode":"24040",
    "sg:province":"Bergamo",
    "wof:name":"Panzeri S.a.s. Di Panzeri Massimo E C.",
    "wof:placetype":"venue"
},
  "geometry": {"coordinates":[9.5400238037,45.5761489868],"type":"Point"}
}