{
  "type": "Feature",
  "properties": {
    "iso:country":"IT",
    "sg:address":"06070 Perugia",
    "sg:orig_category":"Non-classified Establishments",
    "sg:phone":"+39 075 528 0903",
    "sg:postcode":"06070",
    "sg:province":"Perugia",
    "wof:name":"Bragiola Spa",
    "wof:placetype":"venue"
},
  "geometry": {"coordinates":[12.294537,43.165943],"type":"Point"}
}