{
  "type": "Feature",
  "properties": {
    "iso:country":"IT",
    "sg:address":"11, Via Gioberti 51036 Larciano",
    "sg:city":"Larciano",
    "sg:classifiers":[
        {
            "category":"Personal",
            "subcategory":"Shoe Repair & Shine",
            "type":"Services"
        }
    ],
    "sg:phone":"+39 39057384124",
    "sg:postcode":"51036",
    "sg:province":"Pistoia",
    "sg:tags":[
        "leather"
    ],
    "wof:name":"Marzia Di Tavernari Valerio E C. Snc",
    "wof:placetype":"venue"
},
  "geometry": {"coordinates":[10.840899,43.817574],"type":"Point"}
}