{
  "type": "Feature",
  "properties": {
    "addr:full":"20063 Cernusco Sul Naviglio Cernusco sul Naviglio Milano 20063",
    "addr:postcode":"20063;20063",
    "iso:country":"IT",
    "sg:address":"20063 Cernusco Sul Naviglio",
    "sg:city":"Cernusco sul Naviglio",
    "sg:orig_category":"Servizi E Lavori Per Abbigliamento E Pelletterie",
    "sg:phone":"+39 02 924 0023",
    "sg:postcode":"20063",
    "sg:province":"Milano",
    "wof:name":"Brambilla Pisoni Felice",
    "wof:placetype":"venue"
},
  "geometry": {"coordinates":[9.278947,45.52943],"type":"Point"}
}