{
  "type": "Feature",
  "properties": {
    "iso:country":"IT",
    "sg:address":"51, Via Guido Rossa 25060 Cellatica",
    "sg:city":"Cellatica",
    "sg:classifiers":[
        {
            "category":"Food & Beverages",
            "subcategory":"Bakery",
            "type":"Retail Goods"
        }
    ],
    "sg:phone":"+39 030 252 1666",
    "sg:postcode":"25060",
    "sg:province":"Brescia",
    "sg:tags":[
        "grain",
        "cereal"
    ],
    "wof:name":"Germinal Italia (s.r.l)",
    "wof:placetype":"venue"
},
  "geometry": {"coordinates":[10.168385,45.579952],"type":"Point"}
}