{
  "type": "Feature",
  "properties": {
    "iso:country":"IT",
    "sg:address":"Via Marco Polo - Pieve Fissiraga 26854 Cornegliano Laudense",
    "sg:city":"Cornegliano Laudense",
    "sg:classifiers":[
        {
            "category":"Professional",
            "type":"Services"
        }
    ],
    "sg:phone":"+39 0371 97230",
    "sg:postcode":"26854",
    "sg:province":"Lodi",
    "sg:tags":[
        "transport"
    ],
    "wof:name":"C.f. Trasporti S.r.l.",
    "wof:placetype":"venue"
},
  "geometry": {"coordinates":[9.445941,45.273941],"type":"Point"}
}