{
  "type": "Feature",
  "properties": {
    "iso:country":"IT",
    "sg:address":"80131 Napoli",
    "sg:city":"Napoli",
    "sg:orig_category":"Consulenze Turistiche",
    "sg:phone":"+39 081 770 2131",
    "sg:postcode":"80131",
    "sg:province":"Napoli",
    "wof:name":"Zimone Antonio",
    "wof:placetype":"venue"
},
  "geometry": {"coordinates":[14.228732,40.860531],"type":"Point"}
}