{
  "type": "Feature",
  "properties": {
    "addr:full":"13811 Andorno Micca Andorno Micca Biella 13811",
    "addr:postcode":"13811;13811",
    "iso:country":"IT",
    "sg:address":"13811 Andorno Micca",
    "sg:city":"Andorno Micca",
    "sg:orig_category":"Pubblica Amministrazione",
    "sg:phone":"+39 015 247 6008",
    "sg:postcode":"13811",
    "sg:province":"Biella",
    "wof:name":"Comunita' Montana Bassa Valle Cervo",
    "wof:placetype":"venue"
},
  "geometry": {"coordinates":[8.0562372208,45.6112060547],"type":"Point"}
}