{
  "type": "Feature",
  "properties": {
    "iso:country":"IT",
    "sg:address":"Via Puccini 5 37019 Peschiera Del Garda",
    "sg:city":"Peschiera del Garda",
    "sg:classifiers":[
        {
            "category":"Food & Beverages",
            "subcategory":"Ethnic Foods",
            "type":"Retail Goods"
        }
    ],
    "sg:phone":"+39 045 755 3533",
    "sg:postcode":"37019",
    "sg:province":"Verona",
    "sg:tags":[
        "equipment",
        "pizzeria"
    ],
    "sg:website":"www.ziopepe.com",
    "wof:name":"Zio Pepe S.n.c. Di Speri Silvano E Anselmi Raffaella",
    "wof:placetype":"venue"
},
  "geometry": {"coordinates":[10.9917478561,45.4383659363],"type":"Point"}
}