{
  "type": "Feature",
  "properties": {
    "addr:full":"20010 Buscate Buscate Milano 20010",
    "addr:postcode":"20010;20010",
    "iso:country":"IT",
    "sg:address":"20010 Buscate",
    "sg:city":"Buscate",
    "sg:orig_category":"Manufacturers: Prefabbricati",
    "sg:phone":"+39 0331 800157",
    "sg:postcode":"20010",
    "sg:province":"Milano",
    "wof:name":"E.ma Prefabbricati Di Mascazzini",
    "wof:placetype":"venue"
},
  "geometry": {"coordinates":[8.867537,45.57214],"type":"Point"}
}