{
  "type": "Feature",
  "properties": {
    "iso:country":"IT",
    "sg:address":"44100 Cassana - Ferrara",
    "sg:city":"Cassana",
    "sg:orig_category":"Servizi Ausiliari Di Analisi, Controllo E Ricerca",
    "sg:phone":"+39 0532 730058",
    "sg:postcode":"44100",
    "sg:province":"Ferrara",
    "wof:name":"Istituto Zooprofilattico",
    "wof:placetype":"venue"
},
  "geometry": {"coordinates":[11.574821,44.847794],"type":"Point"}
}