{
  "type": "Feature",
  "properties": {
    "iso:country":"IT",
    "sg:address":"6, Contrada Ripoli 64023 Mosciano Sant'angelo",
    "sg:classifiers":[
        {
            "category":"Home & Garden",
            "subcategory":"Home Furnishings",
            "type":"Retail Goods"
        }
    ],
    "sg:phone":"+39 085 807 1124",
    "sg:postcode":"64023",
    "sg:province":"Teramo",
    "sg:tags":[
        "household"
    ],
    "wof:name":"Linea Sedia S.n.c. Di Di Lazzaro A. & C.",
    "wof:placetype":"venue"
},
  "geometry": {"coordinates":[13.907412,42.717152],"type":"Point"}
}