{
  "type": "Feature",
  "properties": {
    "addr:full":"40061 Minerbio Minerbio Bologna 40061",
    "addr:postcode":"40061;minerbio bologna 40061",
    "iso:country":"IT",
    "sg:address":"40061 Minerbio",
    "sg:city":"Minerbio",
    "sg:orig_category":"Ricerca, Selezione E Formazione Del Personale. Pubblica Amministrazione",
    "sg:phone":"+39 051 878298",
    "sg:postcode":"40061",
    "sg:province":"Bologna",
    "wof:name":"Centro Per L'impiego Della Provincia",
    "wof:placetype":"venue"
},
  "geometry": {"coordinates":[11.445513,44.556744],"type":"Point"}
}