{
  "type": "Feature",
  "properties": {
    "iso:country":"IT",
    "sg:address":"64023 Mosciano Sant'angelo",
    "sg:orig_category":"Abbigliamento Esterno, Maglierie E Pelliccerie. Sport - Articoli E Forniture",
    "sg:phone":"+39 085 807 1887",
    "sg:postcode":"64023",
    "sg:province":"Teramo",
    "wof:name":"Unika Sport Italia Sas",
    "wof:placetype":"venue"
},
  "geometry": {"coordinates":[13.906031,42.724266],"type":"Point"}
}