{
  "type": "Feature",
  "properties": {
    "addr:full":"37059 Zevio Campagnola Verona 37059",
    "addr:postcode":"37059;37059",
    "iso:country":"IT",
    "sg:address":"37059 Zevio",
    "sg:city":"Campagnola",
    "sg:orig_category":"Falegnami",
    "sg:phone":"+39 045 873 0179",
    "sg:postcode":"37059",
    "sg:province":"Verona",
    "sg:website":"http://www.bonadiman-serramenti.it",
    "wof:name":"Bonadiman Giuseppe & C. Snc",
    "wof:placetype":"venue"
},
  "geometry": {"coordinates":[11.0570821762,45.3544197083],"type":"Point"}
}