{
  "type": "Feature",
  "properties": {
    "iso:country":"IT",
    "sg:address":"06063 Magione",
    "sg:city":"Magione",
    "sg:orig_category":"Dolciumi E Gelati",
    "sg:phone":"+39 075 847 2084",
    "sg:postcode":"06063",
    "sg:province":"Perugia",
    "wof:name":"Associazione Produttori Apistici Umbri",
    "wof:placetype":"venue"
},
  "geometry": {"coordinates":[12.23599,43.145874],"type":"Point"}
}