{
  "type": "Feature",
  "properties": {
    "iso:country":"IT",
    "sg:address":"57125 Livorno",
    "sg:city":"Livorno",
    "sg:classifiers":[
        {
            "category":"Travel",
            "subcategory":"Hotels & Motels",
            "type":"Entertainment"
        }
    ],
    "sg:phone":"+39 0586 856508",
    "sg:postcode":"57125",
    "sg:province":"Livorno",
    "sg:tags":[
        "support",
        "companies",
        "trade",
        "facilities",
        "events",
        "hotels"
    ],
    "sg:website":"http://www.aracongressi.it",
    "wof:name":"Ara Congressi",
    "wof:placetype":"venue"
},
  "geometry": {"coordinates":[10.318918,43.546062],"type":"Point"}
}