{
  "type": "Feature",
  "properties": {
    "iso:country":"IT",
    "sg:address":"30, Strada Per Rivarolo 10080 Oglianico",
    "sg:city":"Oglianico",
    "sg:classifiers":[
        {
            "category":"Shopping",
            "subcategory":"Stationery & Office Supplies",
            "type":"Retail Goods"
        }
    ],
    "sg:phone":"+39 0124 348530",
    "sg:postcode":"10080",
    "sg:province":"Torino",
    "sg:tags":[
        "professional"
    ],
    "wof:name":"Direct - Service (s.p.a.)",
    "wof:placetype":"venue"
},
  "geometry": {"coordinates":[7.6866188049,45.0705604553],"type":"Point"}
}