{
  "type": "Feature",
  "properties": {
    "addr:full":"51, Via Corti Alfredo 24126 Bergamo Bergamo Bergamo 24126",
    "addr:postcode":"24126;24126",
    "addr:street":"Via Corti Alfredo",
    "iso:country":"IT",
    "sg:address":"51, Via Corti Alfredo 24126 Bergamo",
    "sg:city":"Bergamo",
    "sg:classifiers":[
        {
            "category":"Professional",
            "subcategory":"Printing & Photocopies",
            "type":"Services"
        }
    ],
    "sg:phone":"+39 035 424 3057",
    "sg:postcode":"24126",
    "sg:province":"Bergamo",
    "wof:name":"Gi-erre S.n.c.",
    "wof:placetype":"venue"
},
  "geometry": {"coordinates":[9.6699523926,45.6949043274],"type":"Point"}
}