{
  "type": "Feature",
  "properties": {
    "addr:full":"88, Via Catalano Domenico 84018 Scafati Scafati Salerno 84018",
    "addr:postcode":"84018;84018",
    "addr:street":"Via Catalano Domenico",
    "iso:country":"IT",
    "sg:address":"88, Via Catalano Domenico 84018 Scafati",
    "sg:city":"Scafati",
    "sg:classifiers":[
        {
            "category":"Shopping",
            "subcategory":"Computers & Home Electronics",
            "type":"Retail Goods"
        }
    ],
    "sg:phone":"+39 081 850 7087",
    "sg:postcode":"84018",
    "sg:province":"Salerno",
    "sg:tags":[
        "electronic",
        "electrical",
        "equipment"
    ],
    "wof:name":"Cotrafo Srl",
    "wof:placetype":"venue"
},
  "geometry": {"coordinates":[14.765912,40.677956],"type":"Point"}
}