{
  "type": "Feature",
  "properties": {
    "iso:country":"IT",
    "sg:address":"200, Via S. Antonino 31100 Treviso",
    "sg:city":"Treviso",
    "sg:classifiers":[
        {
            "category":"Shopping",
            "subcategory":"Clothing, Apparel, & Fashions",
            "type":"Retail Goods"
        }
    ],
    "sg:phone":"+39 0422 404500",
    "sg:postcode":"31100",
    "sg:province":"Treviso",
    "sg:tags":[
        "clothes"
    ],
    "wof:name":"Manifattura Ronchi S.r.l.",
    "wof:placetype":"venue"
},
  "geometry": {"coordinates":[12.20272,45.651211],"type":"Point"}
}