{
  "type": "Feature",
  "properties": {
    "iso:country":"IT",
    "sg:address":"11024 Chatillon",
    "sg:city":"Chatillon",
    "sg:orig_category":"Pubblica Amministrazione",
    "sg:phone":"+39 0166 61537",
    "sg:postcode":"11024",
    "sg:province":"Aosta",
    "wof:name":"Comunita' Montana Monte Cervino",
    "wof:placetype":"venue"
},
  "geometry": {"coordinates":[7.6187777519,45.7526664734],"type":"Point"}
}