{
  "type": "Feature",
  "properties": {
    "iso:country":"IT",
    "sg:address":"16, Via Sella Quintino 20094 Corsico",
    "sg:city":"Corsico",
    "sg:classifiers":[
        {
            "category":"Shopping",
            "subcategory":"Clothing, Apparel, & Fashions",
            "type":"Retail Goods"
        }
    ],
    "sg:phone":"+39 02 4860 1530",
    "sg:postcode":"20094",
    "sg:province":"Milano",
    "sg:tags":[
        "clothes"
    ],
    "wof:name":"Suardi Industria Confezioni S.a.s.",
    "wof:placetype":"venue"
},
  "geometry": {"coordinates":[9.109643,45.449394],"type":"Point"}
}