{
  "type": "Feature",
  "properties": {
    "addr:full":"53, Via Darwin 20019 Settimo Milanese Settimo Milanese Milano 20019",
    "addr:postcode":"20019;20019",
    "addr:street":"Via Darwin",
    "iso:country":"IT",
    "sg:address":"53, Via Darwin 20019 Settimo Milanese",
    "sg:city":"Settimo Milanese",
    "sg:classifiers":[
        {
            "category":"Shopping",
            "subcategory":"Stationery & Office Supplies",
            "type":"Retail Goods"
        }
    ],
    "sg:phone":"+39 39023282213",
    "sg:postcode":"20019",
    "sg:province":"Milano",
    "sg:tags":[
        "professional"
    ],
    "wof:name":"Arche' Allestimenti Srl",
    "wof:placetype":"venue"
},
  "geometry": {"coordinates":[9.0557422638,45.4619750977],"type":"Point"}
}