{
  "type": "Feature",
  "properties": {
    "iso:country":"IT",
    "sg:address":"53034 Colle Di Val D'elsa",
    "sg:orig_category":"Servizi E Lavori Industria Chimica. Trattamenti Termici E Superficiali Metalli, Galvanotecnica",
    "sg:phone":"+39 0577 909045",
    "sg:postcode":"53034",
    "sg:province":"Siena",
    "sg:website":"http://www.imelprivet.com",
    "wof:name":"Rossi Giovanni Maria",
    "wof:placetype":"venue"
},
  "geometry": {"coordinates":[11.093808,43.384811],"type":"Point"}
}