{
  "type": "Feature",
  "properties": {
    "iso:country":"IT",
    "sg:address":"20048 Carate Brianza",
    "sg:city":"Carate Brianza",
    "sg:classifiers":[
        {
            "category":"Restaurant",
            "type":"Food & Drink"
        }
    ],
    "sg:phone":"+39 036 299 0053",
    "sg:postcode":"20048",
    "sg:province":"Milano",
    "sg:tags":[
        "supplies",
        "product",
        "chemicals",
        "industry",
        "basic"
    ],
    "sg:website":"http://www.litalaromi.it",
    "wof:name":"L'italiana Aromi Srl",
    "wof:placetype":"venue"
},
  "geometry": {"coordinates":[9.2268199921,45.6705322266],"type":"Point"}
}