{
  "type": "Feature",
  "properties": {
    "iso:country":"IT",
    "sg:address":"Borgo San Giovanni 2/c; Portogruaro; 30026",
    "sg:city":"Portogruaro",
    "sg:classifiers":[
        {
            "category":"Banks & Credit Unions",
            "subcategory":"Bank",
            "type":"Services"
        }
    ],
    "sg:phone":"+39 0421 72267",
    "sg:postcode":"30026",
    "sg:province":"Venezia",
    "wof:name":"Banco Ambrosiano Veneto Spa",
    "wof:placetype":"venue"
},
  "geometry": {"coordinates":[12.839069,45.774063],"type":"Point"}
}