{
  "type": "Feature",
  "properties": {
    "addr:full":"21052 Busto Arsizio Busto Arsizio Varese 21052",
    "addr:postcode":"21052;21052",
    "iso:country":"IT",
    "sg:address":"21052 Busto Arsizio",
    "sg:city":"Busto Arsizio",
    "sg:orig_category":"Forniture Per Attivita' Commerciali Ed Artigianali",
    "sg:phone":"+39 0331 629684",
    "sg:postcode":"21052",
    "sg:province":"Varese",
    "wof:name":"Cassicol S.n.c",
    "wof:placetype":"venue"
},
  "geometry": {"coordinates":[8.8321199417,45.6088294983],"type":"Point"}
}