{
  "type": "Feature",
  "properties": {
    "addr:full":"95037 San Giovanni La Punta San Giovanni la Punta Catania 95037",
    "addr:housenumber":"95037",
    "addr:postcode":"95037",
    "iso:country":"IT",
    "sg:address":"95037 San Giovanni La Punta",
    "sg:city":"San Giovanni la Punta",
    "sg:orig_category":"Sport - Articoli E Forniture",
    "sg:phone":"+39 095 751 2646",
    "sg:postcode":"95037",
    "sg:province":"Catania",
    "wof:name":"Ventaloro Andrea Salvatore",
    "wof:placetype":"venue"
},
  "geometry": {"coordinates":[15.087005,37.573265],"type":"Point"}
}