{
  "type": "Feature",
  "properties": {
    "addr:full":"7, Via Mignano 25072 Bagolino Bagolino Brescia 25072",
    "addr:postcode":"25072;25072",
    "addr:street":"Via Mignano",
    "iso:country":"IT",
    "sg:address":"7, Via Mignano 25072 Bagolino",
    "sg:city":"Bagolino",
    "sg:classifiers":[
        {
            "category":"Manufacturing",
            "subcategory":"Metals",
            "type":"Manufacturing & Wholesale Goods"
        }
    ],
    "sg:phone":"+39 39036599225",
    "sg:postcode":"25072",
    "sg:province":"Brescia",
    "sg:tags":[
        "metallurgy",
        "metalworking"
    ],
    "wof:name":"Alberti Livio & C. (s.a.s.)",
    "wof:placetype":"venue"
},
  "geometry": {"coordinates":[10.4558763504,45.829574585],"type":"Point"}
}