{
  "type": "Feature",
  "properties": {
    "addr:full":"1, Via Garigliano 50053 Empoli Empoli Firenze 50053",
    "addr:postcode":"50053;50053",
    "addr:street":"Via Garigliano",
    "iso:country":"IT",
    "sg:address":"1, Via Garigliano 50053 Empoli",
    "sg:city":"Empoli",
    "sg:classifiers":[
        {
            "category":"Utilities",
            "subcategory":"Electric",
            "type":"Services"
        }
    ],
    "sg:phone":"+39 390 571 9901",
    "sg:postcode":"50053",
    "sg:province":"Firenze",
    "sg:tags":[
        "energy"
    ],
    "wof:name":"Publiser Spa",
    "wof:placetype":"venue"
},
  "geometry": {"coordinates":[10.954268,43.728138],"type":"Point"}
}