{
  "type": "Feature",
  "properties": {
    "addr:full":"10154 Torino Torino Torino 10154",
    "addr:postcode":"10154;10154",
    "iso:country":"IT",
    "sg:address":"10154 Torino",
    "sg:city":"Torino",
    "sg:orig_category":"Gas Compressi E Liquefatti - Produzione E Ingrosso",
    "sg:phone":"+39 011 205 6612",
    "sg:postcode":"10154",
    "sg:province":"Torino",
    "wof:name":"Eurogas Di Pace Carmelo",
    "wof:placetype":"venue"
},
  "geometry": {"coordinates":[7.709631,45.090912],"type":"Point"}
}