{
  "type": "Feature",
  "properties": {
    "addr:full":"10135 Torino Torino Torino 10135",
    "addr:postcode":"10135;10135",
    "iso:country":"IT",
    "sg:address":"10135 Torino",
    "sg:city":"Torino",
    "sg:orig_category":"Prodotti E Manufatti In Materie Plastiche",
    "sg:phone":"+39 011 347 1871",
    "sg:postcode":"10135",
    "sg:province":"Torino",
    "wof:name":"Model Resine (s.r.l.)",
    "wof:placetype":"venue"
},
  "geometry": {"coordinates":[7.5956048965,45.0194549561],"type":"Point"}
}