{
  "type": "Feature",
  "properties": {
    "iso:country":"IT",
    "sg:address":"93013 Mazzarino",
    "sg:city":"Mazzarino",
    "sg:orig_category":"Macchine Ed Impianti Per Edilizia E Lavori Pubblici",
    "sg:phone":"+39 0934 381317",
    "sg:postcode":"93013",
    "sg:province":"Caltanissetta",
    "wof:name":"Zafarana Filippo & C. Snc",
    "wof:placetype":"venue"
},
  "geometry": {"coordinates":[14.102963,37.501019],"type":"Point"}
}