{
  "type": "Feature",
  "properties": {
    "iso:country":"IT",
    "sg:address":"19, V. Villamagna",
    "sg:city":"Bagno a Ripoli",
    "sg:classifiers":[
        {
            "category":"Shopping",
            "subcategory":"Crafts & Fabrics",
            "type":"Retail Goods"
        }
    ],
    "sg:phone":"+39 39055630079",
    "sg:postcode":"50012",
    "sg:province":"Firenze",
    "sg:tags":[
        "ceramic"
    ],
    "sg:website":"http://www.manzanigraniglie.it",
    "wof:name":"Manzani Graniglie Srl",
    "wof:placetype":"venue"
},
  "geometry": {"coordinates":[11.256902,43.768734],"type":"Point"}
}