{
  "type": "Feature",
  "properties": {
    "addr:full":"25, Via Donizetti 25010 Borgosatollo Borgosatollo Brescia 25010",
    "addr:postcode":"25010;25010",
    "addr:street":"Via Donizetti",
    "iso:country":"IT",
    "sg:address":"25, Via Donizetti 25010 Borgosatollo",
    "sg:city":"Borgosatollo",
    "sg:classifiers":[
        {
            "category":"Shopping",
            "subcategory":"Crafts & Fabrics",
            "type":"Retail Goods"
        }
    ],
    "sg:phone":"+39 030 270 1371",
    "sg:postcode":"25010",
    "sg:province":"Brescia",
    "wof:name":"Roversi",
    "wof:placetype":"venue"
},
  "geometry": {"coordinates":[10.239862442,45.4669647217],"type":"Point"}
}