{
  "type": "Feature",
  "properties": {
    "addr:full":"00184 Roma Roma Roma 00184",
    "addr:postcode":"00184;00184",
    "iso:country":"IT",
    "sg:address":"00184 Roma",
    "sg:city":"Roma",
    "sg:orig_category":"Prodotti Chimici Secondari. Prodotti Cosmetici E Da Toeletta",
    "sg:phone":"+39 06 488 0017",
    "sg:postcode":"00184",
    "sg:province":"Roma",
    "wof:name":"L'eplattenier Jacquelin",
    "wof:placetype":"venue"
},
  "geometry": {"coordinates":[12.4907674789,41.8980712891],"type":"Point"}
}