{
  "type": "Feature",
  "properties": {
    "addr:full":"00198 Roma Roma Roma 00198",
    "addr:postcode":"00198;00198",
    "iso:country":"IT",
    "sg:address":"00198 Roma",
    "sg:city":"Roma",
    "sg:orig_category":"Forniture Per Uffici. Regalistica Aziendale",
    "sg:phone":"+39 06 860 6395",
    "sg:postcode":"00198",
    "sg:province":"Roma",
    "wof:name":"Capuani Sas Di Capuani Sergio",
    "wof:placetype":"venue"
},
  "geometry": {"coordinates":[12.5039920807,41.917881012],"type":"Point"}
}