{
  "type": "Feature",
  "properties": {
    "addr:full":"61, Via Sommacampagna 37137 Verona Verona Verona 37137",
    "addr:postcode":"37137;37137",
    "addr:street":"Via Sommacampagna",
    "iso:country":"IT",
    "sg:address":"61, Via Sommacampagna 37137 Verona",
    "sg:city":"Verona",
    "sg:classifiers":[
        {
            "category":"Parking",
            "subcategory":"Lot",
            "type":"Transportation"
        }
    ],
    "sg:phone":"+39 045 828 0111",
    "sg:postcode":"37137",
    "sg:province":"Verona",
    "sg:tags":[
        "transport",
        "road"
    ],
    "wof:name":"Giacomelli Spedizioni S.r.l.",
    "wof:placetype":"venue"
},
  "geometry": {"coordinates":[10.92664,45.416664],"type":"Point"}
}