{
  "type": "Feature",
  "properties": {
    "iso:country":"IT",
    "sg:address":"20129 Milano",
    "sg:city":"Milano",
    "sg:orig_category":"Forniture Per Abbigliamento E Pelletterie. Complementi Di Arredamento",
    "sg:phone":"+39 02 2940 6391",
    "sg:postcode":"20129",
    "sg:province":"Milano",
    "wof:name":"Passamaneria Di G. E T. Pavani & C. (s.a.s.)",
    "wof:placetype":"venue"
},
  "geometry": {"coordinates":[9.209479332,45.474193573],"type":"Point"}
}