{
  "type": "Feature",
  "properties": {
    "iso:country":"IT",
    "sg:address":"16121 Genova",
    "sg:city":"Genova",
    "sg:orig_category":"Medici Specialisti - Chirurgia Generale",
    "sg:phone":"+39 010 595 9130",
    "sg:postcode":"16121",
    "sg:province":"Genova",
    "wof:name":"Fuda Dott. Natale",
    "wof:placetype":"venue"
},
  "geometry": {"coordinates":[8.9421577454,44.4037666321],"type":"Point"}
}