{
  "type": "Feature",
  "properties": {
    "addr:full":"30125 Venezia Venezia Venezia 30125",
    "addr:postcode":"30125;30125",
    "iso:country":"IT",
    "sg:address":"30125 Venezia",
    "sg:city":"Venezia",
    "sg:orig_category":"Prodotti Alimentari",
    "sg:phone":"+39 041 523 1257",
    "sg:postcode":"30125",
    "sg:province":"Venezia",
    "wof:name":"Naccari Sas Di Naccari Dario & C.",
    "wof:placetype":"venue"
},
  "geometry": {"coordinates":[12.1576442719,45.5282897949],"type":"Point"}
}