{
  "type": "Feature",
  "properties": {
    "iso:country":"IT",
    "sg:address":"28078 Romagnano Sesia",
    "sg:city":"Romagnano Sesia",
    "sg:orig_category":"Caccia E Pesca Articoli, Attrezzature Ed Abbigliamento - Vendita Al Dettaglio",
    "sg:phone":"+39 0163 833232",
    "sg:postcode":"28078",
    "sg:province":"Novara",
    "wof:name":"Il Pescatore Di Temporelli Lorenza",
    "wof:placetype":"venue"
},
  "geometry": {"coordinates":[8.401513,45.619843],"type":"Point"}
}