{
  "type": "Feature",
  "properties": {
    "iso:country":"IT",
    "sg:address":"37136 Verona",
    "sg:city":"Verona",
    "sg:orig_category":"Carta, Cartone E Prodotti Primari. Forniture E Materiali Per Imballaggio E Confezionamento",
    "sg:phone":"+39 045 504169",
    "sg:postcode":"37136",
    "sg:province":"Verona",
    "wof:name":"Scatolificio Cadore Snc",
    "wof:placetype":"venue"
},
  "geometry": {"coordinates":[10.981045,45.420441],"type":"Point"}
}