{
  "type": "Feature",
  "properties": {
    "iso:country":"IT",
    "sg:address":"31058 Susegana",
    "sg:city":"Susegana",
    "sg:orig_category":"Serramenti Ed Infissi",
    "sg:phone":"+39 0438 435496",
    "sg:postcode":"31058",
    "sg:province":"Treviso",
    "sg:website":"http://www.tecnicosrl.com",
    "wof:name":"Tecnico Srl",
    "wof:placetype":"venue"
},
  "geometry": {"coordinates":[12.277253,45.872833],"type":"Point"}
}