{
  "type": "Feature",
  "properties": {
    "iso:country":"IT",
    "sg:address":"Via Battisti ,24 - Schianno 21045 Gazzada",
    "sg:city":"Gazzada",
    "sg:classifiers":[
        {
            "category":"Manufacturing",
            "subcategory":"Rubber & Plastics",
            "type":"Manufacturing & Wholesale Goods"
        }
    ],
    "sg:phone":"+39 0332 462310",
    "sg:postcode":"21045",
    "sg:province":"Varese",
    "sg:tags":[
        "mould",
        "industry"
    ],
    "wof:name":"Rachelli Elio & C Snc",
    "wof:placetype":"venue"
},
  "geometry": {"coordinates":[8.8175096512,45.7698631287],"type":"Point"}
}