{
  "type": "Feature",
  "properties": {
    "iso:country":"IT",
    "sg:address":"16043 Chiavari",
    "sg:city":"Chiavari",
    "sg:orig_category":"Macchine E Forniture Per Arredamento E Industria Del Legno. Colori, Vernici E Smalti",
    "sg:phone":"+39 0185 303717",
    "sg:postcode":"16043",
    "sg:province":"Genova",
    "wof:name":"Az Color",
    "wof:placetype":"venue"
},
  "geometry": {"coordinates":[8.960983,44.393658],"type":"Point"}
}