{
  "type": "Feature",
  "properties": {
    "iso:country":"IT",
    "sg:address":"16/b, Via Guglielmo Marconi 26040 Bonemerse",
    "sg:city":"Bonemerse",
    "sg:orig_category":"Miscellaneous Products",
    "sg:phone":"+39 0372 496222",
    "sg:postcode":"26040",
    "sg:province":"Cremona",
    "wof:name":"Sun Helmet S.r.l.",
    "wof:placetype":"venue"
},
  "geometry": {"coordinates":[10.0768432617,45.104927063],"type":"Point"}
}