{
  "type": "Feature",
  "properties": {
    "addr:full":"10043 Orbassano Orbassano Torino 10043",
    "addr:postcode":"10043;10043",
    "iso:country":"IT",
    "sg:address":"10043 Orbassano",
    "sg:city":"Orbassano",
    "sg:orig_category":"Pompe. Ricambi E Componenti Dei Mezzi Di Trasporto",
    "sg:phone":"+39 011 903 2501",
    "sg:postcode":"10043",
    "sg:province":"Torino",
    "wof:name":"Elasis-sis.ric. Fiat Nel Mezzogiorno-soc.cons. Per Azioni",
    "wof:placetype":"venue"
},
  "geometry": {"coordinates":[7.5478730202,45.0084190369],"type":"Point"}
}