{
  "type": "Feature",
  "properties": {
    "addr:full":"Via Ronchetti 25 21040 Oggiona Con Santo Stefano Oggiona Varese 21040",
    "addr:housenumber":"25",
    "addr:postcode":"21040;21040",
    "addr:street":"Via Ronchetti",
    "iso:country":"IT",
    "sg:address":"Via Ronchetti 25 21040 Oggiona Con Santo Stefano",
    "sg:city":"Oggiona",
    "sg:orig_category":"Bed Ticking And Bed-ticking Materials, Downs And Feathers",
    "sg:phone":"+39 0331 217082",
    "sg:postcode":"21040",
    "sg:province":"Varese",
    "sg:website":"www.ghiringhelliezio.it",
    "wof:name":"Ezio Ghiringhelli Spa",
    "wof:placetype":"venue"
},
  "geometry": {"coordinates":[8.8118,45.699272],"type":"Point"}
}