{
  "type": "Feature",
  "properties": {
    "iso:country":"IT",
    "sg:address":"20020 Arese",
    "sg:city":"Arese",
    "sg:orig_category":"Articoli Da Regalo. Arte Ed Artigianato Artistico. Shopping",
    "sg:phone":"+39 02 938 5117",
    "sg:postcode":"20020",
    "sg:province":"Milano",
    "wof:name":"Elefante Bianco Di Milani A.",
    "wof:placetype":"venue"
},
  "geometry": {"coordinates":[9.079914,45.550243],"type":"Point"}
}