{
  "type": "Feature",
  "properties": {
    "iso:country":"IT",
    "sg:address":"04012 Cisterna Di Latina",
    "sg:city":"Cisterna di Latina",
    "sg:orig_category":"Abbigliamento Esterno, Maglierie E Pelliccerie. Servizi E Lavori Per Abbigliamento E Pelletterie",
    "sg:phone":"+39 06 969 8050",
    "sg:postcode":"04012",
    "sg:province":"Latina",
    "wof:name":"Magnanti Manuela",
    "wof:placetype":"venue"
},
  "geometry": {"coordinates":[12.829253,41.589752],"type":"Point"}
}