{
  "type": "Feature",
  "properties": {
    "iso:country":"IT",
    "sg:address":"33049 San Pietro Al Natisone",
    "sg:city":"San Pietro al Natisone",
    "sg:orig_category":"Dolciumi E Gelati",
    "sg:phone":"+39 0432 727647",
    "sg:postcode":"33049",
    "sg:province":"Udine",
    "wof:name":"Al.frut. Di Zanuttigh E. & C. S.n.c.",
    "wof:placetype":"venue"
},
  "geometry": {"coordinates":[13.492221,46.136234],"type":"Point"}
}