{
  "type": "Feature",
  "properties": {
    "addr:full":"16019 Ronco Scrivia Ronco Scrivia Genova 16019",
    "addr:postcode":"16019;16019",
    "iso:country":"IT",
    "sg:address":"16019 Ronco Scrivia",
    "sg:city":"Ronco Scrivia",
    "sg:orig_category":"Accessori Dei Mezzi Di Trasporto",
    "sg:phone":"+39 010 935 0591",
    "sg:postcode":"16019",
    "sg:province":"Genova",
    "wof:name":"O.m.p. Racing S.r.l.",
    "wof:placetype":"venue"
},
  "geometry": {"coordinates":[8.935574,44.603554],"type":"Point"}
}