{
  "type": "Feature",
  "properties": {
    "iso:country":"IT",
    "sg:address":"22, Via Ivrea 10019 Strambino",
    "sg:city":"Strambino",
    "sg:classifiers":[
        {
            "category":"Home & Garden",
            "subcategory":"Home Furnishings",
            "type":"Retail Goods"
        }
    ],
    "sg:phone":"+39 0125 718223",
    "sg:postcode":"10019",
    "sg:province":"Torino",
    "sg:tags":[
        "household"
    ],
    "wof:name":"Nuova Robert Ross - S.r.l.",
    "wof:placetype":"venue"
},
  "geometry": {"coordinates":[7.847695,45.407139],"type":"Point"}
}