{
  "type": "Feature",
  "properties": {
    "addr:full":"10060 None None Torino 10060",
    "addr:postcode":"10060;10060",
    "iso:country":"IT",
    "sg:address":"10060 None",
    "sg:city":"None",
    "sg:orig_category":"Servizi Per Lo Sport E Il Tempo Libero. Servizi Al Turismo. Acqua, Luce, Gas E Societa' Di Esercizio Pubblico",
    "sg:phone":"+39 011 986 3396",
    "sg:postcode":"10060",
    "sg:province":"Torino",
    "wof:name":"Agrifav S.r.l.",
    "wof:placetype":"venue"
},
  "geometry": {"coordinates":[7.541259,44.934242],"type":"Point"}
}