{
  "type": "Feature",
  "properties": {
    "iso:country":"IT",
    "sg:address":"20098 San Giuliano Milanese",
    "sg:city":"San Giuliano Milanese",
    "sg:orig_category":"Ospedali E Servizi Sanitari. Servizi Sociali. Associazioni Ed Organismi Di Interesse Pubblico",
    "sg:phone":"+39 02 988 0779",
    "sg:postcode":"20098",
    "sg:province":"Milano",
    "wof:name":"Cooperativa Sociale Promozione Umana A R.l.",
    "wof:placetype":"venue"
},
  "geometry": {"coordinates":[9.258322,45.398476],"type":"Point"}
}