{
  "type": "Feature",
  "properties": {
    "iso:country":"IT",
    "sg:address":"36050 Cartigliano",
    "sg:city":"Cartigliano",
    "sg:orig_category":"Utensili Meccanici E Materiali",
    "sg:phone":"+39 0424 590421",
    "sg:postcode":"36050",
    "sg:province":"Vicenza",
    "wof:name":"Italstampi Srl",
    "wof:placetype":"venue"
},
  "geometry": {"coordinates":[11.65027,45.718643],"type":"Point"}
}