{
  "type": "Feature",
  "properties": {
    "iso:country":"IT",
    "sg:address":"Via Maggior Belleno 19 15070 Castelferro",
    "sg:classifiers":[
        {
            "category":"Manufacturing",
            "subcategory":"Printing",
            "type":"Manufacturing & Wholesale Goods"
        }
    ],
    "sg:phone":"+39 0131 710003",
    "sg:postcode":"15070",
    "sg:province":"Alessandria",
    "sg:tags":[
        "plastic"
    ],
    "wof:name":"Studioplast Service Sas Di Niceti Enrico",
    "wof:placetype":"venue"
},
  "geometry": {"coordinates":[8.6213321686,44.7581863403],"type":"Point"}
}