{
  "type": "Feature",
  "properties": {
    "iso:country":"IT",
    "sg:address":"20141 Milano",
    "sg:city":"Milano",
    "sg:orig_category":"Servizi Per Lo Sport E Il Tempo Libero. Associazioni Ed Organismi Di Interesse Pubblico",
    "sg:phone":"+39 02 569 3053",
    "sg:postcode":"20141",
    "sg:province":"Milano",
    "wof:name":"Centro Sportivo Fatima",
    "wof:placetype":"venue"
},
  "geometry": {"coordinates":[9.199751,45.423962],"type":"Point"}
}