{
  "type": "Feature",
  "properties": {
    "addr:full":"10024 Moncalieri Moncalieri Torino 10024",
    "addr:postcode":"10024;10024",
    "iso:country":"IT",
    "sg:address":"10024 Moncalieri",
    "sg:city":"Moncalieri",
    "sg:orig_category":"Motori Ed Organi Di Trasmissione. Ricambi E Componenti Dei Mezzi Di Trasporto",
    "sg:phone":"+39 011 640 8118",
    "sg:postcode":"10024",
    "sg:province":"Torino",
    "wof:name":"Autoricambi Moncalieri Srl",
    "wof:placetype":"venue"
},
  "geometry": {"coordinates":[7.6715068817,44.9934387207],"type":"Point"}
}