{
  "type": "Feature",
  "properties": {
    "iso:country":"IT",
    "sg:address":"P.le Cappuccini 2 62019 Recanati",
    "sg:city":"Recanati",
    "sg:classifiers":[
        {
            "category":"Home & Garden",
            "subcategory":"Hardware",
            "type":"Retail Goods"
        }
    ],
    "sg:phone":"+39 071 757 0129",
    "sg:postcode":"62019",
    "sg:province":"Macerata",
    "sg:tags":[
        "component",
        "electronic"
    ],
    "sg:website":"www.johnvox.com",
    "wof:name":"Johnvox Srl",
    "wof:placetype":"venue"
},
  "geometry": {"coordinates":[13.552495,43.397785],"type":"Point"}
}