{
  "type": "Feature",
  "properties": {
    "iso:country":"IT",
    "sg:address":"90011 Bagheria",
    "sg:city":"Bagheria",
    "sg:orig_category":"Termotecnica E Riscaldamento, Apparecchiature E Servizi",
    "sg:phone":"+39 091 960532",
    "sg:postcode":"90011",
    "sg:province":"Palermo",
    "wof:name":"Fa.es. Di G. Cici",
    "wof:placetype":"venue"
},
  "geometry": {"coordinates":[13.447397,38.073086],"type":"Point"}
}