{
  "type": "Feature",
  "properties": {
    "addr:full":"106, Via Della Costituzione 42042 Fabbrico Reggio Nell'Emilia 42042",
    "addr:housenumber":"106",
    "addr:postcode":"42042;42042",
    "addr:street":"Via Della Costituzione",
    "iso:country":"IT",
    "sg:address":"106, Via Della Costituzione 42042 Fabbrico",
    "sg:classifiers":[
        {
            "category":"Manufacturing",
            "subcategory":"Metals",
            "type":"Manufacturing & Wholesale Goods"
        }
    ],
    "sg:phone":"+39 0522 650167",
    "sg:postcode":"42042",
    "sg:province":"Reggio Nell'Emilia",
    "sg:tags":[
        "processing"
    ],
    "wof:name":"T.t.f. Sacchetti (s.r.l.)",
    "wof:placetype":"venue"
},
  "geometry": {"coordinates":[10.8411750793,44.8709411621],"type":"Point"}
}