{
  "type": "Feature",
  "properties": {
    "addr:full":"13878 Candelo Candelo Biella 13878",
    "addr:postcode":"13878;13878",
    "iso:country":"IT",
    "sg:address":"13878 Candelo",
    "sg:city":"Candelo",
    "sg:orig_category":"Macchine, Impianti Ed Attrezzature Per Agricoltura E Zootecnia. Macchine E Forniture Per Arredamento E Industria Del Legno",
    "sg:phone":"+39 015 253 9604",
    "sg:postcode":"13878",
    "sg:province":"Biella",
    "wof:name":"Casa Della Motosega",
    "wof:placetype":"venue"
},
  "geometry": {"coordinates":[8.105316,45.53751],"type":"Point"}
}