{
  "type": "Feature",
  "properties": {
    "iso:country":"IT",
    "sg:address":"Km. 18, Strada Statale 100 70010 Casamassima",
    "sg:city":"Casamassima",
    "sg:classifiers":[
        {
            "category":"Farming",
            "subcategory":"Livestock Farm",
            "type":"Manufacturing & Wholesale Goods"
        }
    ],
    "sg:phone":"+39 080 697 0322",
    "sg:postcode":"70010",
    "sg:province":"Bari",
    "sg:tags":[
        "agriculture"
    ],
    "wof:name":"Tatone Fiori Srl",
    "wof:placetype":"venue"
},
  "geometry": {"coordinates":[16.869291,41.126053],"type":"Point"}
}