{
  "type": "Feature",
  "properties": {
    "addr:full":"20037 Paderno Dugnano Paderno Dugnano Milano 20037",
    "addr:postcode":"20037;20037",
    "iso:country":"IT",
    "sg:address":"20037 Paderno Dugnano",
    "sg:city":"Paderno Dugnano",
    "sg:orig_category":"Fibre Ottiche",
    "sg:phone":"+39 02 9108 0364",
    "sg:postcode":"20037",
    "sg:province":"Milano",
    "sg:website":"http://www.macron.it",
    "wof:name":"Macron Srl",
    "wof:placetype":"venue"
},
  "geometry": {"coordinates":[9.1651544571,45.5692901611],"type":"Point"}
}