{
  "type": "Feature",
  "properties": {
    "iso:country":"IT",
    "sg:address":"24, Via Tonale 10127 Torino",
    "sg:city":"Torino",
    "sg:classifiers":[
        {
            "category":"Home & Garden",
            "subcategory":"Home Furnishings",
            "type":"Retail Goods"
        }
    ],
    "sg:phone":"+39 39011618247",
    "sg:postcode":"10127",
    "sg:province":"Torino",
    "sg:tags":[
        "household"
    ],
    "wof:name":"Biogenesys Srl",
    "wof:placetype":"venue"
},
  "geometry": {"coordinates":[7.655012,45.019291],"type":"Point"}
}