{
  "type": "Feature",
  "properties": {
    "addr:full":"35, Via Gabriele Luigi Pecile 33034 Fagagna Fagagna Udine 33034",
    "addr:postcode":"33034;33034",
    "addr:street":"Via Gabriele Luigi Pecile",
    "iso:country":"IT",
    "sg:address":"35, Via Gabriele Luigi Pecile 33034 Fagagna",
    "sg:city":"Fagagna",
    "sg:classifiers":[
        {
            "category":"Banks & Credit Unions",
            "subcategory":"Investment Brokerage",
            "type":"Services"
        }
    ],
    "sg:phone":"+39 0432 810450",
    "sg:postcode":"33034",
    "sg:province":"Udine",
    "sg:tags":[
        "-",
        "transport",
        "related"
    ],
    "wof:name":"So.tra.co. (s.p.a.)",
    "wof:placetype":"venue"
},
  "geometry": {"coordinates":[13.082063,46.110554],"type":"Point"}
}