{
  "type": "Feature",
  "properties": {
    "addr:full":"63100 Ascoli Piceno Ascoli Piceno Ascoli Piceno 63100",
    "addr:postcode":"63100;63100",
    "iso:country":"IT",
    "sg:address":"63100 Ascoli Piceno",
    "sg:city":"Ascoli Piceno",
    "sg:orig_category":"Editoria",
    "sg:phone":"+39 0736 259228",
    "sg:postcode":"63100",
    "sg:province":"Ascoli Piceno",
    "wof:name":"Corriere Adriatico",
    "wof:placetype":"venue"
},
  "geometry": {"coordinates":[13.576212,42.856293],"type":"Point"}
}