{
  "type": "Feature",
  "properties": {
    "addr:full":"80065 Sant'agnello Napoli 80065",
    "addr:postcode":"80065;80065",
    "iso:country":"IT",
    "sg:address":"80065 Sant'agnello",
    "sg:orig_category":"Prodotti Alimentari",
    "sg:phone":"+39 081 807 1490",
    "sg:postcode":"80065",
    "sg:province":"Napoli",
    "wof:name":"Deia Di Iaccarino P.paolo & C. S.n.c.",
    "wof:placetype":"venue"
},
  "geometry": {"coordinates":[14.405380249,40.6222267151],"type":"Point"}
}