{
  "type": "Feature",
  "properties": {
    "addr:full":"56, Vicolo Fiorito 24048 Treviolo Treviolo Bergamo 24048",
    "addr:housenumber":"56",
    "addr:postcode":"24048;24048",
    "addr:street":"Vicolo Fiorito",
    "iso:country":"IT",
    "sg:address":"56, Vicolo Fiorito 24048 Treviolo",
    "sg:city":"Treviolo",
    "sg:classifiers":[
        {
            "category":"Professional",
            "subcategory":"Computer Services",
            "type":"Services"
        }
    ],
    "sg:phone":"+39 39035201496",
    "sg:postcode":"24048",
    "sg:province":"Bergamo",
    "sg:tags":[
        "information",
        "technology"
    ],
    "wof:name":"F.m. Automazione Srl",
    "wof:placetype":"venue"
},
  "geometry": {"coordinates":[9.621953,45.675667],"type":"Point"}
}