{
  "type": "Feature",
  "properties": {
    "iso:country":"IT",
    "sg:address":"2, Via Colderove 31049 Valdobbiadene",
    "sg:city":"Valdobbiadene",
    "sg:classifiers":[
        {
            "category":"Food & Beverages",
            "subcategory":"Groceries & Convenience Stores",
            "type":"Retail Goods"
        }
    ],
    "sg:phone":"+39 39800243883",
    "sg:postcode":"31049",
    "sg:province":"Treviso",
    "sg:tags":[
        "drink"
    ],
    "wof:name":"Mionetto Spumanti (s.r.l.)",
    "wof:placetype":"venue"
},
  "geometry": {"coordinates":[11.989608,45.896313],"type":"Point"}
}