{
  "type": "Feature",
  "properties": {
    "iso:country":"IT",
    "sg:address":"53, Piazza Roma 15057 Tortona",
    "sg:city":"Tortona",
    "sg:classifiers":[
        {
            "category":"Utilities",
            "subcategory":"Electric",
            "type":"Services"
        }
    ],
    "sg:phone":"+39 0131 812581",
    "sg:postcode":"15057",
    "sg:province":"Alessandria",
    "sg:tags":[
        "component",
        "electronic"
    ],
    "wof:name":"Stem Elettronica Di Mirabelli & C. S.n.c.",
    "wof:placetype":"venue"
},
  "geometry": {"coordinates":[8.861649,44.893562],"type":"Point"}
}