{
  "type": "Feature",
  "properties": {
    "addr:full":"36/38, Viale Manzoni Alessandro 20081 Abbiategrasso Abbiategrasso Milano 20081",
    "addr:housenumber":"36 / 38",
    "addr:postcode":"20081;20081",
    "addr:street":"Viale Manzoni Alessandro",
    "iso:country":"IT",
    "sg:address":"36/38, Viale Manzoni Alessandro 20081 Abbiategrasso",
    "sg:city":"Abbiategrasso",
    "sg:classifiers":[
        {
            "category":"Food & Beverages",
            "subcategory":"Groceries & Convenience Stores",
            "type":"Retail Goods"
        }
    ],
    "sg:phone":"+39 02 9469 9198",
    "sg:postcode":"20081",
    "sg:province":"Milano",
    "sg:tags":[
        "drink"
    ],
    "wof:name":"Lurisia Acque Minerali Srl",
    "wof:placetype":"venue"
},
  "geometry": {"coordinates":[9.188141,45.463688],"type":"Point"}
}