{
  "type": "Feature",
  "properties": {
    "addr:full":"20148 Milano Milano Milano 20148",
    "addr:postcode":"20148;20148",
    "iso:country":"IT",
    "sg:address":"20148 Milano",
    "sg:city":"Milano",
    "sg:orig_category":"Servizi Vari Di Interesse Pubblico",
    "sg:phone":"+39 02 403 9018",
    "sg:postcode":"20148",
    "sg:province":"Milano",
    "wof:name":"People Game Sas Di Anna De Nigris & C.",
    "wof:placetype":"venue"
},
  "geometry": {"coordinates":[9.137388,45.474083],"type":"Point"}
}