{
  "type": "Feature",
  "properties": {
    "addr:full":"80026 Casoria Casoria Napoli 80026",
    "addr:postcode":"80026;80026",
    "iso:country":"IT",
    "sg:address":"80026 Casoria",
    "sg:city":"Casoria",
    "sg:classifiers":[
        {
            "category":"Wholesale",
            "subcategory":"Machinery & Supplies",
            "type":"Manufacturing & Wholesale Goods"
        }
    ],
    "sg:phone":"+39 081 757 7115",
    "sg:postcode":"80026",
    "sg:province":"Napoli",
    "sg:tags":[
        "component",
        "engineering",
        "material",
        "electrical"
    ],
    "wof:name":"Tedicon Russo Ferdinando",
    "wof:placetype":"venue"
},
  "geometry": {"coordinates":[14.28966,40.920151],"type":"Point"}
}