{
  "type": "Feature",
  "properties": {
    "iso:country":"IT",
    "sg:address":"10127 Torino",
    "sg:city":"Torino",
    "sg:orig_category":"Impiantistica E Prodotti Tecnologici Per Edilizia. Elettronica Professionale E Di Consumo",
    "sg:phone":"+39 011 316 1385",
    "sg:postcode":"10127",
    "sg:province":"Torino",
    "wof:name":"Gi.pi. Di Pizzigallo G.",
    "wof:placetype":"venue"
},
  "geometry": {"coordinates":[7.654738,45.021843],"type":"Point"}
}