{
  "type": "Feature",
  "properties": {
    "iso:country":"IT",
    "sg:address":"21019 Somma Lombardo",
    "sg:city":"Somma Lombardo",
    "sg:orig_category":"Automobili E Mezzi Di Trasporto",
    "sg:phone":"+39 0331 711111",
    "sg:postcode":"21019",
    "sg:province":"Varese",
    "wof:name":"Agusta Spa",
    "wof:placetype":"venue"
},
  "geometry": {"coordinates":[8.704931,45.637447],"type":"Point"}
}