{
  "type": "Feature",
  "properties": {
    "addr:full":"30125 Venezia Venezia Venezia 30125",
    "addr:postcode":"30125;30125",
    "iso:country":"IT",
    "sg:address":"30125 Venezia",
    "sg:city":"Venezia",
    "sg:orig_category":"Filati E Materie Prime Tessili",
    "sg:phone":"+39 041 523 7000",
    "sg:postcode":"30125",
    "sg:province":"Venezia",
    "wof:name":"Lane Bollato",
    "wof:placetype":"venue"
},
  "geometry": {"coordinates":[12.3314847946,45.4374351501],"type":"Point"}
}