{
  "type": "Feature",
  "properties": {
    "iso:country":"IT",
    "sg:address":"980, Via Nonantolana 41100 Modena",
    "sg:city":"Modena",
    "sg:classifiers":[
        {
            "category":"Autos & Motor Vehicles",
            "subcategory":"Automobile Sales",
            "type":"Retail Goods"
        }
    ],
    "sg:phone":"+39 39059250396",
    "sg:postcode":"41100",
    "sg:province":"Modena",
    "sg:tags":[
        "motor-cars"
    ],
    "wof:name":"Pelloni Auto Spa",
    "wof:placetype":"venue"
},
  "geometry": {"coordinates":[10.9684886932,44.6612091064],"type":"Point"}
}