{
  "type": "Feature",
  "properties": {
    "addr:full":"29010 Calendasco Calendasco Piacenza 29010",
    "addr:postcode":"29010;29010",
    "iso:country":"IT",
    "sg:address":"29010 Calendasco",
    "sg:city":"Calendasco",
    "sg:orig_category":"Motori Ed Organi Di Trasmissione",
    "sg:phone":"+39 0523 764611",
    "sg:postcode":"29010",
    "sg:province":"Piacenza",
    "wof:name":"G&d Italia Spa",
    "wof:placetype":"venue"
},
  "geometry": {"coordinates":[9.630522728,45.0578575134],"type":"Point"}
}