{
  "type": "Feature",
  "properties": {
    "iso:country":"IT",
    "sg:address":"20154 Milano",
    "sg:city":"Milano",
    "sg:orig_category":"Ristoranti",
    "sg:phone":"+39 02 3360 0687",
    "sg:postcode":"20154",
    "sg:province":"Milano",
    "wof:name":"Trattoria Il Palio",
    "wof:placetype":"venue"
},
  "geometry": {"coordinates":[9.166847,45.487503],"type":"Point"}
}