{
  "type": "Feature",
  "properties": {
    "iso:country":"IT",
    "sg:address":"62019 Recanati",
    "sg:city":"Recanati",
    "sg:orig_category":"Banche Ed Istituti Di Credito E Risparmio",
    "sg:phone":"+39 071 980 0173",
    "sg:postcode":"62019",
    "sg:province":"Macerata",
    "sg:website":"http://www.recanati.bcc.it",
    "wof:name":"Banca Credito Cooperativo Di Recanati E Colmurano Soc.coop.r.l.",
    "wof:placetype":"venue"
},
  "geometry": {"coordinates":[13.436096,43.363476],"type":"Point"}
}