{
  "type": "Feature",
  "properties": {
    "addr:full":"35010 Cadoneghe Cadoneghe Padova 35010",
    "addr:postcode":"35010;35010",
    "iso:country":"IT",
    "sg:address":"35010 Cadoneghe",
    "sg:city":"Cadoneghe",
    "sg:orig_category":"Legno E Semilavorati",
    "sg:phone":"+39 049 887 0654",
    "sg:postcode":"35010",
    "sg:province":"Padova",
    "wof:name":"Scalco Eufelio Nico & C. Snc",
    "wof:placetype":"venue"
},
  "geometry": {"coordinates":[11.932343,45.449776],"type":"Point"}
}