{
  "type": "Feature",
  "properties": {
    "addr:full":"29, Via Oratorio 42015 Correggio Reggio Nell'Emilia 42015",
    "addr:postcode":"42015;42015",
    "addr:street":"Via Oratorio",
    "iso:country":"IT",
    "sg:address":"29, Via Oratorio 42015 Correggio",
    "sg:classifiers":[
        {
            "category":"Manufacturing",
            "subcategory":"Paper Products",
            "type":"Manufacturing & Wholesale Goods"
        }
    ],
    "sg:phone":"+39 0522 642410",
    "sg:postcode":"42015",
    "sg:province":"Reggio Nell'Emilia",
    "sg:tags":[
        "cardboard"
    ],
    "wof:name":"Lebez (s.p.a.)",
    "wof:placetype":"venue"
},
  "geometry": {"coordinates":[10.8155889511,44.7681732178],"type":"Point"}
}