{
  "type": "Feature",
  "properties": {
    "iso:country":"IT",
    "sg:address":"22, Foro Buonaparte 20121 Milano",
    "sg:city":"Milano",
    "sg:classifiers":[
        {
            "category":"Professional",
            "subcategory":"Advertising",
            "type":"Services"
        }
    ],
    "sg:phone":"+39 02 7202 3535",
    "sg:postcode":"20121",
    "sg:province":"Milano",
    "sg:tags":[
        "communication",
        "medium"
    ],
    "wof:name":"Barabino & Partners",
    "wof:placetype":"venue"
},
  "geometry": {"coordinates":[9.183358,45.471066],"type":"Point"}
}