{
  "type": "Feature",
  "properties": {
    "addr:full":"10098 Rivoli Rivoli Torino 10098",
    "addr:postcode":"10098;10098",
    "iso:country":"IT",
    "sg:address":"10098 Rivoli",
    "sg:city":"Rivoli",
    "sg:classifiers":[
        {
            "category":"Autos & Motor Vehicles",
            "subcategory":"Automobile Sales",
            "type":"Retail Goods"
        }
    ],
    "sg:phone":"+39 011 955 9711",
    "sg:postcode":"10098",
    "sg:province":"Torino",
    "sg:tags":[
        "car"
    ],
    "sg:website":"http://www.ilmas.it",
    "wof:name":"Ilmas Spa",
    "wof:placetype":"venue"
},
  "geometry": {"coordinates":[7.55768013,45.0670547485],"type":"Point"}
}