{
  "type": "Feature",
  "properties": {
    "addr:full":"Piazza Montegrappa 3; Frascati; 00044 Frascati Roma 00044",
    "addr:housenumber":"3",
    "addr:postcode":"00044;roma 00044",
    "addr:street":"Piazza Montegrappa",
    "iso:country":"IT",
    "sg:address":"Piazza Montegrappa 3; Frascati; 00044",
    "sg:city":"Frascati",
    "sg:classifiers":[
        {
            "category":"Banks & Credit Unions",
            "subcategory":"Bank",
            "type":"Services"
        }
    ],
    "sg:phone":"+39 06 941 9437",
    "sg:postcode":"00044",
    "sg:province":"Roma",
    "wof:name":"Credito Italiano Spa",
    "wof:placetype":"venue"
},
  "geometry": {"coordinates":[12.673301,41.823296],"type":"Point"}
}