{
  "type": "Feature",
  "properties": {
    "iso:country":"IT",
    "sg:address":"Via Galilei 2 46025 Poggio Rusco",
    "sg:city":"Poggio Rusco",
    "sg:orig_category":"Polyvinyl Chloride Pvc Extrudates",
    "sg:phone":"+39 0386 51910",
    "sg:postcode":"46025",
    "sg:province":"Mantova",
    "sg:website":"www.vetroresinapadana.com",
    "wof:name":"Vetroresina Padana Srl",
    "wof:placetype":"venue"
},
  "geometry": {"coordinates":[10.7976980209,45.1603660583],"type":"Point"}
}