{
  "type": "Feature",
  "properties": {
    "iso:country":"IT",
    "sg:address":"28053 Castelletto Ticino",
    "sg:orig_category":"Articoli Regalo - Vendita Al Dettaglio",
    "sg:phone":"+39 0331 922037",
    "sg:postcode":"28053",
    "sg:province":"Novara",
    "wof:name":"Maduzzi Dario E C. Snc",
    "wof:placetype":"venue"
},
  "geometry": {"coordinates":[8.611388,45.719585],"type":"Point"}
}