{
  "type": "Feature",
  "properties": {
    "addr:full":"21043 Castiglione Olona Castiglione Olona Varese 21043",
    "addr:postcode":"21043;21043",
    "iso:country":"IT",
    "sg:address":"21043 Castiglione Olona",
    "sg:city":"Castiglione Olona",
    "sg:classifiers":[
        {
            "category":"Manufacturing",
            "subcategory":"Chemicals & Compounds",
            "type":"Manufacturing & Wholesale Goods"
        }
    ],
    "sg:phone":"+39 0331 857614",
    "sg:postcode":"21043",
    "sg:province":"Varese",
    "sg:tags":[
        "equipment",
        "industry",
        "machinery"
    ],
    "sg:website":"http://space.tin.it/economia/ginocamp/",
    "wof:name":"Ditta Campagnaro Gino Di Campagnaro Marco",
    "wof:placetype":"venue"
},
  "geometry": {"coordinates":[8.870648,45.787102],"type":"Point"}
}