{
  "type": "Feature",
  "properties": {
    "iso:country":"IT",
    "sg:address":"03047 San Giorgio A Liri",
    "sg:city":"San Giorgio a Liri",
    "sg:orig_category":"Non-classified Establishments",
    "sg:phone":"+39 0776 910503",
    "sg:postcode":"03047",
    "sg:province":"Frosinone",
    "wof:name":"Eurocarta Di Di Raimo Raffaele",
    "wof:placetype":"venue"
},
  "geometry": {"coordinates":[13.768529,41.411522],"type":"Point"}
}