{
  "type": "Feature",
  "properties": {
    "addr:full":"22023 Castiglione D'intelvi Como 22023",
    "addr:postcode":"22023;22023",
    "iso:country":"IT",
    "sg:address":"22023 Castiglione D'intelvi",
    "sg:orig_category":"Servizi E Lavori Per Arredamento E Industria Del Legno. Servizi E Lavori Per Edilizia E Lavori Pubblici",
    "sg:phone":"+39 031 830940",
    "sg:postcode":"22023",
    "sg:province":"Como",
    "wof:name":"Botta Lucio",
    "wof:placetype":"venue"
},
  "geometry": {"coordinates":[9.085421,45.961613],"type":"Point"}
}