{
  "type": "Feature",
  "properties": {
    "iso:country":"IT",
    "sg:address":"1, Via Degli Albari 40126 Bologna",
    "sg:city":"Bologna",
    "sg:classifiers":[
        {
            "category":"Communications",
            "subcategory":"Newspaper",
            "type":"Services"
        }
    ],
    "sg:phone":"+39 39051269055",
    "sg:postcode":"40126",
    "sg:province":"Bologna",
    "sg:tags":[
        "advertising"
    ],
    "wof:name":"Medical & Technical Equipment (s.r.l.)",
    "wof:placetype":"venue"
},
  "geometry": {"coordinates":[11.344993,44.495327],"type":"Point"}
}