{
  "type": "Feature",
  "properties": {
    "iso:country":"IT",
    "sg:address":"90144 Palermo",
    "sg:city":"Palermo",
    "sg:orig_category":"Climatizzazione E Condizionamento, Apparecchiature E Servizi. Elettrodomestici",
    "sg:phone":"+39 091 516816",
    "sg:postcode":"90144",
    "sg:province":"Palermo",
    "wof:name":"Botta Service Coop. A R.l.",
    "wof:placetype":"venue"
},
  "geometry": {"coordinates":[13.338514,38.143307],"type":"Point"}
}