{
  "type": "Feature",
  "properties": {
    "addr:full":"56031 Bientina Bientina Pisa 56031",
    "addr:postcode":"56031;56031",
    "iso:country":"IT",
    "sg:address":"56031 Bientina",
    "sg:city":"Bientina",
    "sg:orig_category":"Articoli Per Imballaggio E Confezionamento",
    "sg:phone":"+39 0587 754111",
    "sg:postcode":"56031",
    "sg:province":"Pisa",
    "sg:website":"http://www.toscanapallets.it",
    "wof:name":"Toscana Pallets Sas Di Vierucci Franco & C.",
    "wof:placetype":"venue"
},
  "geometry": {"coordinates":[10.622279,43.710129],"type":"Point"}
}