{
  "type": "Feature",
  "properties": {
    "iso:country":"IT",
    "sg:address":"36042 Breganze",
    "sg:city":"Breganze",
    "sg:orig_category":"Petroli, Gas E Combustibili",
    "sg:phone":"+39 0445 873308",
    "sg:postcode":"36042",
    "sg:province":"Vicenza",
    "wof:name":"Lievore Luigi Srl",
    "wof:placetype":"venue"
},
  "geometry": {"coordinates":[11.5857248306,45.7011909485],"type":"Point"}
}