{
  "type": "Feature",
  "properties": {
    "iso:country":"IT",
    "sg:address":"40027 Mordano",
    "sg:city":"Mordano",
    "sg:orig_category":"Materiali Edili",
    "sg:phone":"+39 0542 56811",
    "sg:postcode":"40027",
    "sg:province":"Bologna",
    "wof:name":"Wienerberger Brunori S.r.l.",
    "wof:placetype":"venue"
},
  "geometry": {"coordinates":[11.780035,44.421745],"type":"Point"}
}