{
  "type": "Feature",
  "properties": {
    "addr:full":"23, Via Dei Benci 50122 Firenze Firenze Firenze 50122",
    "addr:postcode":"50122;50122",
    "addr:street":"Via Dei Benci",
    "iso:country":"IT",
    "sg:address":"23, Via Dei Benci 50122 Firenze",
    "sg:city":"Firenze",
    "sg:classifiers":[
        {
            "category":"Manufacturing",
            "subcategory":"Tools & Machinery",
            "type":"Manufacturing & Wholesale Goods"
        }
    ],
    "sg:phone":"+39 055 247 9692",
    "sg:postcode":"50122",
    "sg:province":"Firenze",
    "sg:tags":[
        "environment",
        "equipment",
        "-"
    ],
    "wof:name":"Teseco (s.r.l.)",
    "wof:placetype":"venue"
},
  "geometry": {"coordinates":[11.256902,43.768734],"type":"Point"}
}