{
  "type": "Feature",
  "properties": {
    "iso:country":"IT",
    "sg:address":"23900 Lecco",
    "sg:city":"Lecco",
    "sg:orig_category":"Materiali E Componenti Elettrotecnici",
    "sg:phone":"+39 0341 365404",
    "sg:postcode":"23900",
    "sg:province":"Lecco",
    "wof:name":"A.s.f.i.",
    "wof:placetype":"venue"
},
  "geometry": {"coordinates":[9.397094,45.859901],"type":"Point"}
}