{
  "type": "Feature",
  "properties": {
    "iso:country":"IT",
    "sg:address":"48018 Faenza",
    "sg:city":"Faenza",
    "sg:orig_category":"Prodotti Chimici Di Base",
    "sg:phone":"+39 0546 43121",
    "sg:postcode":"48018",
    "sg:province":"Ravenna",
    "wof:name":"Albonetti Gino E Figli S.n.c.",
    "wof:placetype":"venue"
},
  "geometry": {"coordinates":[12.2018499374,44.4159202576],"type":"Point"}
}