{
  "type": "Feature",
  "properties": {
    "iso:country":"IT",
    "sg:address":"52020 Castelfranco Di Sopra",
    "sg:city":"Castelfranco di Sopra",
    "sg:orig_category":"Articoli Medico-sanitari Ed Ortopedici. Impianti, Attrezzature E Forniture Sanitarie Ed Ospedaliere",
    "sg:phone":"+39 055 914 9682",
    "sg:postcode":"52020",
    "sg:province":"Arezzo",
    "wof:name":"Mediconf - Italia-",
    "wof:placetype":"venue"
},
  "geometry": {"coordinates":[11.557054,43.62112],"type":"Point"}
}