{
  "type": "Feature",
  "properties": {
    "iso:country":"IT",
    "sg:address":"22036 Erba",
    "sg:city":"Erba",
    "sg:orig_category":"Macchine, Impianti Ed Attrezzature Per Agricoltura E Zootecnia. Prodotti Vari In Metallo. Apparecchiature E Sistemi Per Magazzinaggio E Movimentazione",
    "sg:phone":"+39 031 610883",
    "sg:postcode":"22036",
    "sg:province":"Como",
    "wof:name":"Gi.minor (s.a.s.)",
    "wof:placetype":"venue"
},
  "geometry": {"coordinates":[9.224789,45.801147],"type":"Point"}
}