{
  "type": "Feature",
  "properties": {
    "addr:full":"3, Via A. Rossi 60010 Ostra Vetere Ostra Ancona 60010",
    "addr:postcode":"60010;60010",
    "addr:street":"Via A. Rossi",
    "iso:country":"IT",
    "sg:address":"3, Via A. Rossi 60010 Ostra Vetere",
    "sg:city":"Ostra",
    "sg:classifiers":[
        {
            "category":"Manufacturing",
            "subcategory":"Rubber & Plastics",
            "type":"Manufacturing & Wholesale Goods"
        }
    ],
    "sg:phone":"+39 39071964044",
    "sg:postcode":"60010",
    "sg:province":"Ancona",
    "sg:tags":[
        "packaging",
        "material",
        "-"
    ],
    "wof:name":"Unibag S.r.l.",
    "wof:placetype":"venue"
},
  "geometry": {"coordinates":[13.0955696106,43.5996856689],"type":"Point"}
}