{
  "type": "Feature",
  "properties": {
    "iso:country":"IT",
    "sg:address":"40050 Castello Serravalle",
    "sg:classifiers":[
        {
            "category":"Travel",
            "subcategory":"Hotels & Motels",
            "type":"Entertainment"
        }
    ],
    "sg:phone":"+39 051 670 3218",
    "sg:postcode":"40050",
    "sg:province":"Bologna",
    "sg:tags":[
        "camping",
        "facility"
    ],
    "wof:name":"Cardelli Paola Fattoria Quercia",
    "wof:placetype":"venue"
},
  "geometry": {"coordinates":[11.117418,44.438179],"type":"Point"}
}