{
  "type": "Feature",
  "properties": {
    "iso:country":"IT",
    "sg:address":"24066 Pedrengo",
    "sg:city":"Pedrengo",
    "sg:orig_category":"Prodotti Alimentari",
    "sg:phone":"+39 035 661231",
    "sg:postcode":"24066",
    "sg:province":"Bergamo",
    "wof:name":"Ovo Ben Dei F.lli Benigni (s.n.c.)",
    "wof:placetype":"venue"
},
  "geometry": {"coordinates":[9.7290897369,45.6992721558],"type":"Point"}
}