{
  "type": "Feature",
  "properties": {
    "iso:country":"IT",
    "sg:address":"20, Via Dell' Elettricita' 30100 Venezia",
    "sg:classifiers":[
        {
            "category":"Marine",
            "type":"Transportation"
        }
    ],
    "sg:phone":"+39 39041921033",
    "sg:province":"VE",
    "sg:tags":[
        "transport",
        "sea"
    ],
    "wof:name":"Barbagelata Adriatica (s.r.l.)",
    "wof:placetype":"venue"
},
  "geometry": {"coordinates":[12.230532,45.468624],"type":"Point"}
}