{
  "type": "Feature",
  "properties": {
    "iso:country":"IT",
    "sg:address":"28100 Novara",
    "sg:city":"Novara",
    "sg:orig_category":"Servizi E Lavori Per Agricoltura E Zootecnia. Servizi E Lavori Industria Chimica. Servizi Ausiliari Di Analisi, Controllo E Ricerca",
    "sg:phone":"+39 0321 697234",
    "sg:postcode":"28100",
    "sg:province":"Novara",
    "wof:name":"Molecular Biotechnology Srl",
    "wof:placetype":"venue"
},
  "geometry": {"coordinates":[8.635806,45.449203],"type":"Point"}
}