{
  "type": "Feature",
  "properties": {
    "addr:full":"1, Localita' Tossilo 08015 Macomer Macomer Nuoro 08015",
    "addr:postcode":"08015;08015",
    "addr:street":"Localita ' Tossilo",
    "iso:country":"IT",
    "sg:address":"1, Localita' Tossilo 08015 Macomer",
    "sg:city":"Macomer",
    "sg:classifiers":[
        {
            "category":"Shopping",
            "subcategory":"Crafts & Fabrics",
            "type":"Retail Goods"
        }
    ],
    "sg:phone":"+39 39078572683",
    "sg:postcode":"08015",
    "sg:province":"Nuoro",
    "wof:name":"Gruppo Tessile Mediterraneo Srl",
    "wof:placetype":"venue"
},
  "geometry": {"coordinates":[9.3304357529,40.3210067749],"type":"Point"}
}