{
  "type": "Feature",
  "properties": {
    "addr:full":"90139 Palermo Palermo Palermo 90139",
    "addr:postcode":"90139;90139",
    "iso:country":"IT",
    "sg:address":"90139 Palermo",
    "sg:city":"Palermo",
    "sg:orig_category":"Medici Specialisti - Radiologia E Radioterapia",
    "sg:phone":"+39 091 329283",
    "sg:postcode":"90139",
    "sg:province":"Palermo",
    "wof:name":"Cappellino Dr. Giuseppe",
    "wof:placetype":"venue"
},
  "geometry": {"coordinates":[13.361819,38.120174],"type":"Point"}
}