{
  "type": "Feature",
  "properties": {
    "addr:full":"59014 Prato PO",
    "addr:postcode":"59014",
    "iso:country":"IT",
    "sg:address":"59014 Prato",
    "sg:orig_category":"Servizi E Lavori Per Abbigliamento E Pelletterie",
    "sg:phone":"+39 0574 622089",
    "sg:province":"PO",
    "wof:name":"Masterpelle Srl",
    "wof:placetype":"venue"
},
  "geometry": {"coordinates":[-108.805351,45.177357],"type":"Point"}
}