{
  "type": "Feature",
  "properties": {
    "iso:country":"IT",
    "sg:address":"Via Consolazione 70 83029 Solofra",
    "sg:city":"Solofra",
    "sg:classifiers":[
        {
            "category":"Shopping",
            "subcategory":"Luggage & Leather Goods",
            "type":"Retail Goods"
        }
    ],
    "sg:phone":"+39 0825 582559",
    "sg:postcode":"83029",
    "sg:province":"Avellino",
    "sg:tags":[
        "clothing"
    ],
    "wof:name":"New Leather Srl",
    "wof:placetype":"venue"
},
  "geometry": {"coordinates":[14.823683,40.829796],"type":"Point"}
}