{
  "type": "Feature",
  "properties": {
    "addr:full":"Via Matteotti 54; Caivano; 80023 Caivano Napoli 80023",
    "addr:housenumber":"54",
    "addr:postcode":"80023;80023",
    "addr:street":"Via Matteotti",
    "iso:country":"IT",
    "sg:address":"Via Matteotti 54; Caivano; 80023",
    "sg:city":"Caivano",
    "sg:classifiers":[
        {
            "category":"Banks & Credit Unions",
            "subcategory":"Bank",
            "type":"Services"
        }
    ],
    "sg:phone":"+39 081 831 2222",
    "sg:postcode":"80023",
    "sg:province":"Napoli",
    "wof:name":"Banco Di Napoli Spa",
    "wof:placetype":"venue"
},
  "geometry": {"coordinates":[14.30267,40.956116],"type":"Point"}
}