{
  "type": "Feature",
  "properties": {
    "iso:country":"IT",
    "sg:address":"35020 Brenta Dell'abba",
    "sg:orig_category":"Gioielleria, Oreficeria E Argenteria. Articoli Da Regalo. Shopping",
    "sg:phone":"+39 049 580 7076",
    "sg:postcode":"35020",
    "sg:province":"Padova",
    "wof:name":"Biasin Fratelli",
    "wof:placetype":"venue"
},
  "geometry": {"coordinates":[12.099765,45.232475],"type":"Point"}
}