{
  "type": "Feature",
  "properties": {
    "iso:country":"IT",
    "sg:address":"10082 Cuorgne'",
    "sg:orig_category":"Non-classified Establishments",
    "sg:phone":"+39 0124 657152",
    "sg:postcode":"10082",
    "sg:province":"Torino",
    "wof:name":"Cena Giovanni",
    "wof:placetype":"venue"
},
  "geometry": {"coordinates":[7.660776,45.041771],"type":"Point"}
}