{
  "type": "Feature",
  "properties": {
    "addr:full":"31010 Cimadolmo Cimadolmo Treviso 31010",
    "addr:postcode":"31010;31010",
    "iso:country":"IT",
    "sg:address":"31010 Cimadolmo",
    "sg:city":"Cimadolmo",
    "sg:orig_category":"Servizi E Lavori Industria Delle Materie Plastiche",
    "sg:phone":"+39 0422 856645",
    "sg:postcode":"31010",
    "sg:province":"Treviso",
    "wof:name":"Vegaplast Srl",
    "wof:placetype":"venue"
},
  "geometry": {"coordinates":[12.364006,45.784561],"type":"Point"}
}