{
  "type": "Feature",
  "properties": {
    "iso:country":"IT",
    "sg:address":"87040 Mendicino",
    "sg:city":"Mendicino",
    "sg:orig_category":"Abbigliamento Esterno, Maglierie E Pelliccerie. Shopping",
    "sg:phone":"+39 0984 632089",
    "sg:postcode":"87040",
    "sg:province":"Cosenza",
    "wof:name":"Galleria Della Sposa Srl",
    "wof:placetype":"venue"
},
  "geometry": {"coordinates":[16.203485,39.275887],"type":"Point"}
}