{
  "type": "Feature",
  "properties": {
    "addr:full":"60025 Loreto Loreto Ancona 60025",
    "addr:postcode":"60025;60025",
    "iso:country":"IT",
    "sg:address":"60025 Loreto",
    "sg:city":"Loreto",
    "sg:orig_category":"Astucci",
    "sg:phone":"+39 071 978905",
    "sg:postcode":"60025",
    "sg:province":"Ancona",
    "sg:website":"http://www.fpgroup.it",
    "wof:name":"Fp Di Pazzaglia Fabrizio",
    "wof:placetype":"venue"
},
  "geometry": {"coordinates":[13.618908,43.43631],"type":"Point"}
}