{
  "type": "Feature",
  "properties": {
    "addr:full":"10024 Moncalieri Moncalieri Torino 10024",
    "addr:postcode":"10024;10024",
    "iso:country":"IT",
    "sg:address":"10024 Moncalieri",
    "sg:city":"Moncalieri",
    "sg:orig_category":"Ecologia - Studi Consulenza E Servizi",
    "sg:phone":"+39 011 661 1511",
    "sg:postcode":"10024",
    "sg:province":"Torino",
    "sg:website":"http://www.trasportigiavara.it",
    "wof:name":"Ecogiavara Srl",
    "wof:placetype":"venue"
},
  "geometry": {"coordinates":[7.682525,45.014004],"type":"Point"}
}