{
  "type": "Feature",
  "properties": {
    "addr:full":"Piazza Vittorio; Carmignano; 50042",
    "addr:postcode":"50042",
    "addr:street":"Piazza Vittorio Carmignano",
    "iso:country":"IT",
    "sg:address":"Piazza Vittorio; Carmignano; 50042",
    "sg:classifiers":[
        {
            "category":"Banks & Credit Unions",
            "subcategory":"Bank",
            "type":"Services"
        }
    ],
    "sg:phone":"+39 055 871 2017",
    "wof:name":"Banca Toscana Spa",
    "wof:placetype":"venue"
},
  "geometry": {"coordinates":[11.023093,43.735107],"type":"Point"}
}