{
  "type": "Feature",
  "properties": {
    "addr:full":"34125 Trieste Trieste Trieste 34125",
    "addr:postcode":"34125;34125",
    "iso:country":"IT",
    "sg:address":"34125 Trieste",
    "sg:city":"Trieste",
    "sg:orig_category":"Prodotti Alimentari",
    "sg:phone":"+39 040 766660",
    "sg:postcode":"34125",
    "sg:province":"Trieste",
    "wof:name":"Il Pan Giusto Di Romano Ernesto Snc",
    "wof:placetype":"venue"
},
  "geometry": {"coordinates":[13.7816028595,45.6517486572],"type":"Point"}
}