{
  "type": "Feature",
  "properties": {
    "addr:full":"9, Via Pio Ix 73035 Miggiano Miggiano Lecce 73035",
    "addr:postcode":"73035;73035",
    "addr:street":"Via Pio Ix",
    "iso:country":"IT",
    "sg:address":"9, Via Pio Ix 73035 Miggiano",
    "sg:city":"Miggiano",
    "sg:classifiers":[
        {
            "category":"Home & Garden",
            "subcategory":"Home Furnishings",
            "type":"Retail Goods"
        }
    ],
    "sg:phone":"+39 0833 761940",
    "sg:postcode":"73035",
    "sg:province":"Lecce",
    "sg:tags":[
        "household"
    ],
    "wof:name":"Schirinzi Semilavorati S.r.l.",
    "wof:placetype":"venue"
},
  "geometry": {"coordinates":[18.313824,39.966877],"type":"Point"}
}