{
  "type": "Feature",
  "properties": {
    "iso:country":"IT",
    "sg:address":"Sda Statale Padana Superiore 317 20090 Vimodrone",
    "sg:city":"Vimodrone",
    "sg:classifiers":[
        {
            "category":"Health Services",
            "subcategory":"Nursing And Care Facility",
            "type":"Services"
        }
    ],
    "sg:phone":"+39 02 2740 9243",
    "sg:postcode":"20090",
    "sg:province":"Milano",
    "sg:tags":[
        "electro-medical",
        "apparatus"
    ],
    "sg:website":"www.fazzini.it",
    "wof:name":"Fazzini Srl",
    "wof:placetype":"venue"
},
  "geometry": {"coordinates":[9.188141,45.463688],"type":"Point"}
}