{
  "type": "Feature",
  "properties": {
    "iso:country":"IT",
    "sg:address":"56023 Cascina",
    "sg:city":"Cascina",
    "sg:orig_category":"Servizi E Lavori Per Industria Alimentare E Bevande. Servizi E Lavori Per Abbigliamento E Pelletterie. Servizi E Lavori Per Arredamento E Industria Del Legno",
    "sg:phone":"+39 050 772722",
    "sg:postcode":"56023",
    "sg:province":"Pisa",
    "wof:name":"Magazzini Del Carratore",
    "wof:placetype":"venue"
},
  "geometry": {"coordinates":[10.459246,43.691776],"type":"Point"}
}