{
  "type": "Feature",
  "properties": {
    "iso:country":"IT",
    "sg:address":"36050 Zermeghedo",
    "sg:city":"Zermeghedo",
    "sg:orig_category":"Macchine, Impianti Ed Attrezzature Per Abbigliamento E Pelletterie",
    "sg:phone":"+39 0444 686182",
    "sg:postcode":"36050",
    "sg:province":"Vicenza",
    "wof:name":"Delfa Commerciale (s.r.l.)",
    "wof:placetype":"venue"
},
  "geometry": {"coordinates":[11.380621,45.475212],"type":"Point"}
}