{
  "type": "Feature",
  "properties": {
    "iso:country":"IT",
    "sg:address":"407, Via Ravegnana 47100 Forli'",
    "sg:classifiers":[
        {
            "category":"Autos & Motor Vehicles",
            "subcategory":"Automobile Sales",
            "type":"Retail Goods"
        }
    ],
    "sg:phone":"+39 0543 723303",
    "sg:postcode":"47100",
    "sg:province":"Forl\u00ec-Cesena",
    "sg:tags":[
        "motor-cars"
    ],
    "wof:name":"Romagnauto (s.a.s.)",
    "wof:placetype":"venue"
},
  "geometry": {"coordinates":[11.9804611206,43.9947662354],"type":"Point"}
}