{
  "type": "Feature",
  "properties": {
    "iso:country":"IT",
    "sg:address":"00178 Roma",
    "sg:city":"Roma",
    "sg:classifiers":[
        {
            "category":"Health Services",
            "subcategory":"Health Practitioner",
            "type":"Services"
        }
    ],
    "sg:phone":"+39 06 718 3836",
    "sg:postcode":"00178",
    "sg:province":"Roma",
    "sg:tags":[
        "medici"
    ],
    "wof:name":"Puglisi Sebastiano",
    "wof:placetype":"venue"
},
  "geometry": {"coordinates":[12.5575046539,41.8393821716],"type":"Point"}
}