{
  "type": "Feature",
  "properties": {
    "addr:full":"Via Industriale, 14 - San Faustino 25070 Bione Bione Brescia 25070",
    "addr:housenumber":"14",
    "addr:postcode":"25070;25070",
    "addr:street":"Via Industriale;San Faustino",
    "iso:country":"IT",
    "sg:address":"Via Industriale, 14 - San Faustino 25070 Bione",
    "sg:city":"Bione",
    "sg:classifiers":[
        {
            "category":"Building & Trades",
            "subcategory":"Plumbing",
            "type":"Services"
        }
    ],
    "sg:phone":"+39 036 589 7941",
    "sg:postcode":"25070",
    "sg:province":"Brescia",
    "sg:tags":[
        "fixture"
    ],
    "sg:website":"www.omptea.com",
    "wof:name":"Omp S.p.a.",
    "wof:placetype":"venue"
},
  "geometry": {"coordinates":[10.3496236801,45.6619796753],"type":"Point"}
}