{
  "type": "Feature",
  "properties": {
    "iso:country":"IT",
    "sg:address":"20054 Nova Milanese",
    "sg:city":"Nova Milanese",
    "sg:orig_category":"Utensili Meccanici E Materiali. Forniture Per Attivita' Industriali",
    "sg:phone":"+39 036 236 6459",
    "sg:postcode":"20054",
    "sg:province":"Milano",
    "wof:name":"La Acciai Speciali S.r.l.",
    "wof:placetype":"venue"
},
  "geometry": {"coordinates":[9.186524,45.582783],"type":"Point"}
}