{
  "type": "Feature",
  "properties": {
    "addr:full":"81100 Caserta Caserta Caserta 81100",
    "addr:postcode":"81100;81100",
    "iso:country":"IT",
    "sg:address":"81100 Caserta",
    "sg:city":"Caserta",
    "sg:orig_category":"Ospedali E Servizi Sanitari. Centri Di Estetica E Cosmesi E Servizi",
    "sg:phone":"+39 0823 422618",
    "sg:postcode":"81100",
    "sg:province":"Caserta",
    "wof:name":"Bellezze In... Forma Srl",
    "wof:placetype":"venue"
},
  "geometry": {"coordinates":[14.332002,41.062759],"type":"Point"}
}