{
  "type": "Feature",
  "properties": {
    "iso:country":"IT",
    "sg:address":"92, Via Olona 21013 Gallarate",
    "sg:city":"Gallarate",
    "sg:classifiers":[
        {
            "category":"Shopping",
            "subcategory":"Clothing, Apparel, & Fashions",
            "type":"Retail Goods"
        }
    ],
    "sg:phone":"+39 0331 790331",
    "sg:postcode":"21013",
    "sg:province":"Varese",
    "sg:tags":[
        "clothes"
    ],
    "wof:name":"Copreca (s.a.s.)",
    "wof:placetype":"venue"
},
  "geometry": {"coordinates":[8.812714,45.651188],"type":"Point"}
}