{
  "type": "Feature",
  "properties": {
    "iso:country":"IT",
    "sg:address":"07041 Alghero",
    "sg:city":"Alghero",
    "sg:orig_category":"Macchine, Impianti Ed Attrezzature Per Agricoltura E Zootecnia. Forniture Per Agricoltura E Zootecnia",
    "sg:phone":"+39 079 999018",
    "sg:postcode":"07041",
    "sg:province":"Sassari",
    "wof:name":"Be.ma. Snc",
    "wof:placetype":"venue"
},
  "geometry": {"coordinates":[8.271418,40.661808],"type":"Point"}
}