{
  "type": "Feature",
  "properties": {
    "iso:country":"IT",
    "sg:address":"14, Via Della Fonderia 50142 Firenze",
    "sg:city":"Firenze",
    "sg:classifiers":[
        {
            "category":"Personal",
            "subcategory":"Shoe Repair & Shine",
            "type":"Services"
        }
    ],
    "sg:phone":"+39 055 229 8906",
    "sg:postcode":"50142",
    "sg:province":"Firenze",
    "sg:tags":[
        "leather"
    ],
    "wof:name":"Carrai",
    "wof:placetype":"venue"
},
  "geometry": {"coordinates":[11.236385,43.773098],"type":"Point"}
}