{
  "type": "Feature",
  "properties": {
    "addr:full":"Via Uopini, 100 - Badesse 53035 Monteriggioni Badesse Siena 53035",
    "addr:housenumber":"100",
    "addr:postcode":"53035;53035",
    "addr:street":"Via Uopini",
    "iso:country":"IT",
    "sg:address":"Via Uopini, 100 - Badesse 53035 Monteriggioni",
    "sg:city":"Badesse",
    "sg:orig_category":"Ladies' Shoes",
    "sg:phone":"+39 0577 309423",
    "sg:postcode":"53035",
    "sg:province":"Siena",
    "wof:name":"Calzaturificio Ilaria S.r.l.",
    "wof:placetype":"venue"
},
  "geometry": {"coordinates":[11.288877,43.362103],"type":"Point"}
}