{
  "type": "Feature",
  "properties": {
    "iso:country":"IT",
    "sg:address":"Piazza Borelli 1; Pavullo Nel Frignano; 41026",
    "sg:city":"Pavullo nel Frignano",
    "sg:classifiers":[
        {
            "category":"Banks & Credit Unions",
            "subcategory":"Bank",
            "type":"Services"
        }
    ],
    "sg:phone":"+39 0536 20163",
    "sg:postcode":"41026",
    "sg:province":"Modena",
    "wof:name":"Rolo Banca 1473 Spa",
    "wof:placetype":"venue"
},
  "geometry": {"coordinates":[10.833657,44.336777],"type":"Point"}
}