{
  "type": "Feature",
  "properties": {
    "iso:country":"IT",
    "sg:address":"36071 Arzignano",
    "sg:city":"Arzignano",
    "sg:orig_category":"Macchine, Impianti Ed Attrezzature Per Abbigliamento E Pelletterie",
    "sg:phone":"+39 0444 670544",
    "sg:postcode":"36071",
    "sg:province":"Vicenza",
    "wof:name":"Nuova Everest Srl",
    "wof:placetype":"venue"
},
  "geometry": {"coordinates":[11.344789,45.51786],"type":"Point"}
}