{
  "type": "Feature",
  "properties": {
    "addr:full":"80040 Pollena Trocchia Pollena Trocchia Napoli 80040",
    "addr:postcode":"80040;80040",
    "addr:street":"Trocchia",
    "iso:country":"IT",
    "sg:address":"80040 Pollena Trocchia",
    "sg:city":"Pollena Trocchia",
    "sg:orig_category":"Accessori Dei Mezzi Di Trasporto",
    "sg:phone":"+39 081 531 2448",
    "sg:postcode":"80040",
    "sg:province":"Napoli",
    "wof:name":"Giammetti Annamaria",
    "wof:placetype":"venue"
},
  "geometry": {"coordinates":[14.375579,40.851387],"type":"Point"}
}