{
  "type": "Feature",
  "properties": {
    "addr:full":"98070 Acquedolci Acquedolci Messina 98070",
    "addr:postcode":"98070;98070",
    "iso:country":"IT",
    "sg:address":"98070 Acquedolci",
    "sg:city":"Acquedolci",
    "sg:orig_category":"Legna Da Ardere",
    "sg:phone":"+39 0941 726312",
    "sg:postcode":"98070",
    "sg:province":"Messina",
    "wof:name":"Alioto Catena",
    "wof:placetype":"venue"
},
  "geometry": {"coordinates":[14.589706,38.05711],"type":"Point"}
}