{
  "type": "Feature",
  "properties": {
    "addr:full":"Via Leonardo Da Vinci 53048 Sinalunga Sinalunga Siena 53048",
    "addr:postcode":"53048;53048",
    "addr:street":"Via Leonardo Da Vinci",
    "iso:country":"IT",
    "sg:address":"Via Leonardo Da Vinci 53048 Sinalunga",
    "sg:city":"Sinalunga",
    "sg:classifiers":[
        {
            "category":"Professional",
            "subcategory":"Engineering",
            "type":"Services"
        }
    ],
    "sg:phone":"+39 0577 632811",
    "sg:postcode":"53048",
    "sg:province":"Siena",
    "sg:tags":[
        "machine",
        "-",
        "mechanical"
    ],
    "wof:name":"C.t.c. S.r.l.",
    "wof:placetype":"venue"
},
  "geometry": {"coordinates":[11.751298,43.222149],"type":"Point"}
}