{
  "type": "Feature",
  "properties": {
    "addr:full":"60121 Ancona Ancona Ancona 60121",
    "addr:postcode":"60121;60121",
    "iso:country":"IT",
    "sg:address":"60121 Ancona",
    "sg:city":"Ancona",
    "sg:orig_category":"Elaborazione Dati - Servizio Conto Terzi",
    "sg:phone":"+39 071 207 5840",
    "sg:postcode":"60121",
    "sg:province":"Ancona",
    "sg:website":"http://www.paginegialle.it/accountmassimo",
    "wof:name":"Account Di Massimo D'alterio & C. Sas",
    "wof:placetype":"venue"
},
  "geometry": {"coordinates":[13.517809,43.618393],"type":"Point"}
}