{
  "type": "Feature",
  "properties": {
    "iso:country":"IT",
    "sg:address":"10024 Moncalieri",
    "sg:city":"Moncalieri",
    "sg:orig_category":"Acciaierie E Fonderie",
    "sg:phone":"+39 011 640 5357",
    "sg:postcode":"10024",
    "sg:province":"Torino",
    "wof:name":"Tvp Di Altran W. & C. Srl",
    "wof:placetype":"venue"
},
  "geometry": {"coordinates":[7.668644,44.997833],"type":"Point"}
}