{
  "type": "Feature",
  "properties": {
    "iso:country":"IT",
    "sg:address":"Via De Gasperi 56b 26013 Crema",
    "sg:city":"Crema",
    "sg:classifiers":[
        {
            "category":"Manufacturing",
            "subcategory":"Metals",
            "type":"Manufacturing & Wholesale Goods"
        }
    ],
    "sg:phone":"+39 0373 204082",
    "sg:postcode":"26013",
    "sg:province":"Cremona",
    "sg:tags":[
        "aluminium"
    ],
    "wof:name":"Crema Alluminio Srl",
    "wof:placetype":"venue"
},
  "geometry": {"coordinates":[9.676215,45.359905],"type":"Point"}
}