{
  "type": "Feature",
  "properties": {
    "iso:country":"IT",
    "sg:address":"275, Via Emilia 40068 San Lazzaro Di Savena",
    "sg:city":"San Lazzaro",
    "sg:classifiers":[
        {
            "category":"Building & Trades",
            "subcategory":"Construction",
            "type":"Services"
        }
    ],
    "sg:phone":"+39 051 625 6001",
    "sg:postcode":"40068",
    "sg:province":"Bologna",
    "sg:tags":[
        "work",
        "public"
    ],
    "wof:name":"Simongavina Paradisoterrestre (s.r.l.)",
    "wof:placetype":"venue"
},
  "geometry": {"coordinates":[11.423903,44.464764],"type":"Point"}
}