{
  "type": "Feature",
  "properties": {
    "addr:full":"19, Via Ponte Manco 35020 Due Carrare Due Carrare Padova 35020",
    "addr:postcode":"35020;35020",
    "addr:street":"Via Ponte Manco",
    "iso:country":"IT",
    "sg:address":"19, Via Ponte Manco 35020 Due Carrare",
    "sg:city":"Due Carrare",
    "sg:classifiers":[
        {
            "category":"Food & Beverages",
            "subcategory":"Groceries & Convenience Stores",
            "type":"Retail Goods"
        }
    ],
    "sg:phone":"+39 39049525888",
    "sg:postcode":"35020",
    "sg:province":"Padova",
    "sg:tags":[
        "product",
        "related"
    ],
    "wof:name":"Rossato E. (s.a.s.)",
    "wof:placetype":"venue"
},
  "geometry": {"coordinates":[11.8325462341,45.294216156],"type":"Point"}
}