{
  "type": "Feature",
  "properties": {
    "addr:full":"21/r, Via Del Rile 21019 Somma Lombardo Somma Lombardo Varese 21019",
    "addr:housenumber":"21 / r",
    "addr:postcode":"21019;21019",
    "addr:street":"Via Del Rile",
    "iso:country":"IT",
    "sg:address":"21/r, Via Del Rile 21019 Somma Lombardo",
    "sg:city":"Somma Lombardo",
    "sg:classifiers":[
        {
            "category":"Professional",
            "subcategory":"Engineering",
            "type":"Services"
        }
    ],
    "sg:phone":"+39 0331 251918",
    "sg:postcode":"21019",
    "sg:province":"Varese",
    "sg:tags":[
        "machine",
        "-",
        "mechanical"
    ],
    "wof:name":"A.c.s. Attrezzature Costruzioni Stampi Minuterie M",
    "wof:placetype":"venue"
},
  "geometry": {"coordinates":[8.826385,45.817604],"type":"Point"}
}