{
  "type": "Feature",
  "properties": {
    "iso:country":"IT",
    "sg:address":"98041 Monforte San Giorgio",
    "sg:city":"Monforte San Giorgio",
    "sg:orig_category":"Macchine Agricole - Accessori E Parti",
    "sg:phone":"+39 090 991 0474",
    "sg:postcode":"98041",
    "sg:province":"Messina",
    "wof:name":"Agricol Di Grillo Giuseppe & C. Snc",
    "wof:placetype":"venue"
},
  "geometry": {"coordinates":[15.415669,38.164543],"type":"Point"}
}