{
  "type": "Feature",
  "properties": {
    "iso:country":"IT",
    "sg:address":"Zona Ind. Pian Dei Mori 53018 Sovicille",
    "sg:city":"Sovicille",
    "sg:classifiers":[
        {
            "category":"Food & Beverages",
            "subcategory":"Bakery",
            "type":"Retail Goods"
        }
    ],
    "sg:phone":"+39 0577 349338",
    "sg:postcode":"53018",
    "sg:province":"Siena",
    "sg:tags":[
        "cake",
        "special"
    ],
    "sg:website":"www.fabbricadelpanforte.com",
    "wof:name":"La Fabbrica Del Panforte S.r.l.",
    "wof:placetype":"venue"
},
  "geometry": {"coordinates":[11.254167,43.257221],"type":"Point"}
}