{
  "type": "Feature",
  "properties": {
    "iso:country":"IT",
    "sg:address":"63, Via Staiti 91100 Trapani",
    "sg:city":"Trapani",
    "sg:classifiers":[
        {
            "category":"Building & Trades",
            "subcategory":"Construction",
            "type":"Services"
        }
    ],
    "sg:phone":"+39 0923 593794",
    "sg:postcode":"91100",
    "sg:province":"Trapani",
    "sg:tags":[
        "work",
        "public"
    ],
    "wof:name":"Soc.consortile Porto Di Trapani Sc.r.l",
    "wof:placetype":"venue"
},
  "geometry": {"coordinates":[12.513309,38.013634],"type":"Point"}
}