{
  "type": "Feature",
  "properties": {
    "iso:country":"IT",
    "sg:address":"56028 San Miniato Basso",
    "sg:city":"San Miniato",
    "sg:orig_category":"Abbigliamento Esterno, Maglierie E Pelliccerie. Shopping",
    "sg:phone":"+39 0571 419182",
    "sg:postcode":"56028",
    "sg:province":"Pisa",
    "sg:website":"http://www.anita-ateliersposi.it",
    "wof:name":"Anita Atelier",
    "wof:placetype":"venue"
},
  "geometry": {"coordinates":[10.845268,43.695049],"type":"Point"}
}