{
  "type": "Feature",
  "properties": {
    "iso:country":"IT",
    "sg:address":"Via Vegri 40 36010 Zane'",
    "sg:classifiers":[
        {
            "category":"Wholesale",
            "subcategory":"Medical Equipment & Supplies",
            "type":"Manufacturing & Wholesale Goods"
        }
    ],
    "sg:phone":"+39 0445 318555",
    "sg:postcode":"36010",
    "sg:province":"Vicenza",
    "sg:tags":[
        "dispenser"
    ],
    "sg:website":"www.videosystem.it",
    "wof:name":"Video System Italia S.r.l.",
    "wof:placetype":"venue"
},
  "geometry": {"coordinates":[11.432974,45.718681],"type":"Point"}
}