{
  "type": "Feature",
  "properties": {
    "iso:country":"IT",
    "sg:address":"38057 Pergine Valsugana",
    "sg:city":"Canezza",
    "sg:orig_category":"Legno E Semilavorati",
    "sg:phone":"+39 0461 531049",
    "sg:postcode":"38057",
    "sg:province":"Trento",
    "wof:name":"Valfersina Legnami Snc Di Planchel Roberto E Claudia",
    "wof:placetype":"venue"
},
  "geometry": {"coordinates":[11.243464,46.058067],"type":"Point"}
}