{
  "type": "Feature",
  "properties": {
    "iso:country":"IT",
    "sg:address":"13854 Quaregna",
    "sg:city":"Quaregna",
    "sg:orig_category":"Servizi E Lavori Per Abbigliamento E Pelletterie",
    "sg:phone":"+39 015 922756",
    "sg:postcode":"13854",
    "sg:province":"Biella",
    "wof:name":"Grafic Line",
    "wof:placetype":"venue"
},
  "geometry": {"coordinates":[8.165067,45.588421],"type":"Point"}
}