{
  "type": "Feature",
  "properties": {
    "iso:country":"IT",
    "sg:address":"1, Via Michellorie 37041 Albaredo D'adige",
    "sg:city":"Michellorie",
    "sg:classifiers":[
        {
            "category":"Bars & Pubs",
            "subcategory":"Nightclub",
            "type":"Food & Drink"
        }
    ],
    "sg:phone":"+39 045 702 5039",
    "sg:postcode":"37041",
    "sg:province":"Verona",
    "sg:tags":[
        "cake",
        "bread"
    ],
    "wof:name":"Biscottificio Baroni (s.p.a.)",
    "wof:placetype":"venue"
},
  "geometry": {"coordinates":[11.299624,45.288033],"type":"Point"}
}