{
  "type": "Feature",
  "properties": {
    "addr:full":"21, Via Ponte 35022 Anguillara Veneta Anguillara Veneta Padova 35022",
    "addr:postcode":"35022;35022",
    "addr:street":"Via Ponte",
    "iso:country":"IT",
    "sg:address":"21, Via Ponte 35022 Anguillara Veneta",
    "sg:city":"Anguillara Veneta",
    "sg:classifiers":[
        {
            "category":"Manufacturing",
            "subcategory":"Metals",
            "type":"Manufacturing & Wholesale Goods"
        }
    ],
    "sg:phone":"+39 049 534 1013",
    "sg:postcode":"35022",
    "sg:province":"Padova",
    "sg:tags":[
        "processing"
    ],
    "wof:name":"S.t.m.a. Di Cavalletto Silvestro & C. (s.n.c.)",
    "wof:placetype":"venue"
},
  "geometry": {"coordinates":[11.8285675049,45.3544540405],"type":"Point"}
}