{
  "type": "Feature",
  "properties": {
    "addr:full":"Via Arici Vittorio 104 25134 Brescia Brescia Brescia 25134",
    "addr:housenumber":"104",
    "addr:postcode":"25134;25134",
    "addr:street":"Via Arici Vittorio",
    "iso:country":"IT",
    "sg:address":"Via Arici Vittorio 104 25134 Brescia",
    "sg:city":"Brescia",
    "sg:classifiers":[
        {
            "category":"Farming",
            "subcategory":"Fish & Marine Products",
            "type":"Manufacturing & Wholesale Goods"
        }
    ],
    "sg:phone":"+39 030 230 1761",
    "sg:postcode":"25134",
    "sg:province":"Brescia",
    "sg:tags":[
        "hotel",
        "dishwashing",
        "cleaning",
        "restaurant"
    ],
    "sg:website":"www.aeb-group.com",
    "wof:name":"Aeb Spa",
    "wof:placetype":"venue"
},
  "geometry": {"coordinates":[10.222958,45.539829],"type":"Point"}
}