{
  "type": "Feature",
  "properties": {
    "addr:full":"60022 Castelfidardo Castelfidardo Ancona 60022",
    "addr:postcode":"60022;60022",
    "iso:country":"IT",
    "sg:address":"60022 Castelfidardo",
    "sg:city":"Castelfidardo",
    "sg:orig_category":"Stampi Materie Plastiche E Gomma",
    "sg:phone":"+39 071 781 9769",
    "sg:postcode":"60022",
    "sg:province":"Ancona",
    "wof:name":"Depa Stampi Snc Di Brilli P. & Lucarini D.",
    "wof:placetype":"venue"
},
  "geometry": {"coordinates":[13.560651,43.492695],"type":"Point"}
}