{
  "type": "Feature",
  "properties": {
    "iso:country":"IT",
    "sg:address":"20136 Milano",
    "sg:city":"Milano",
    "sg:orig_category":"Servizi E Lavori Per Arredamento E Industria Del Legno. Servizi E Lavori Per Edilizia E Lavori Pubblici",
    "sg:phone":"+39 02 832 3426",
    "sg:postcode":"20136",
    "sg:province":"Milano",
    "wof:name":"Verta (s.n.c.)",
    "wof:placetype":"venue"
},
  "geometry": {"coordinates":[9.182829,45.452118],"type":"Point"}
}