{
  "type": "Feature",
  "properties": {
    "iso:country":"IT",
    "sg:address":"20146 Milano",
    "sg:city":"Milano",
    "sg:orig_category":"Servizi E Lavori Per Abbigliamento E Pelletterie",
    "sg:phone":"+39 02 403 9504",
    "sg:postcode":"20146",
    "sg:province":"Milano",
    "wof:name":"Tintoria Miral Di Fondelli Teresa",
    "wof:placetype":"venue"
},
  "geometry": {"coordinates":[9.1376,45.465054],"type":"Point"}
}