{
  "type": "Feature",
  "properties": {
    "addr:full":"5, V. Miglioli 20090 Segrate Segrate Milano 20090",
    "addr:housenumber":"5",
    "addr:postcode":"20090;20090",
    "addr:street":"V. Miglioli",
    "iso:country":"IT",
    "sg:address":"5, V. Miglioli 20090 Segrate",
    "sg:city":"Segrate",
    "sg:classifiers":[
        {
            "category":"Wholesale",
            "subcategory":"Machinery & Supplies",
            "type":"Manufacturing & Wholesale Goods"
        }
    ],
    "sg:phone":"+39 022699181835",
    "sg:postcode":"20090",
    "sg:province":"Milano",
    "sg:tags":[
        "equipment",
        "-",
        "instrument",
        "measurement"
    ],
    "wof:name":"Alpa Srl",
    "wof:placetype":"venue"
},
  "geometry": {"coordinates":[9.297943,45.500908],"type":"Point"}
}