{
  "type": "Feature",
  "properties": {
    "addr:full":"23822 Bellano Bellano Lecco 23822",
    "addr:postcode":"23822;23822",
    "iso:country":"IT",
    "sg:address":"23822 Bellano",
    "sg:city":"Bellano",
    "sg:orig_category":"Musica",
    "sg:phone":"+39 0341 810336",
    "sg:postcode":"23822",
    "sg:province":"Lecco",
    "wof:name":"Valtellina Giuochi Di Spandrio Alberto E Tarabini R. Snc",
    "wof:placetype":"venue"
},
  "geometry": {"coordinates":[9.303486824,46.0415267944],"type":"Point"}
}