{
  "type": "Feature",
  "properties": {
    "iso:country":"IT",
    "sg:address":"10144 Torino",
    "sg:city":"Torino",
    "sg:orig_category":"Servizi Di Magazzinaggio E Movimentazione",
    "sg:phone":"+39 011 473 2153",
    "sg:postcode":"10144",
    "sg:province":"Torino",
    "wof:name":"Roma Roberto",
    "wof:placetype":"venue"
},
  "geometry": {"coordinates":[7.120077,45.126019],"type":"Point"}
}