{
  "type": "Feature",
  "properties": {
    "iso:country":"IT",
    "sg:address":"46030 Dosolo",
    "sg:city":"Dosolo",
    "sg:orig_category":"Legno E Semilavorati. Articoli Per Imballaggio E Confezionamento",
    "sg:phone":"+39 0375 838112",
    "sg:postcode":"46030",
    "sg:province":"Mantova",
    "sg:website":"http://www.bedogna.it",
    "wof:name":"Bedogna Fratelli Srl",
    "wof:placetype":"venue"
},
  "geometry": {"coordinates":[10.640906,44.953835],"type":"Point"}
}