{
  "type": "Feature",
  "properties": {
    "iso:country":"IT",
    "sg:address":"Strada S. Per La Futa 50033 Firenzuola",
    "sg:city":"Firenzuola",
    "sg:orig_category":"Large Sand-lime Bricks, Customized",
    "sg:phone":"+39 055 819696",
    "sg:postcode":"50033",
    "sg:province":"Firenze",
    "sg:website":"www.lapietratoscana.com",
    "wof:name":"La Pietra Toscana Srl",
    "wof:placetype":"venue"
},
  "geometry": {"coordinates":[11.256902,43.768734],"type":"Point"}
}