{
  "type": "Feature",
  "properties": {
    "addr:full":"20148 Milano Milano Milano 20148",
    "addr:postcode":"20148;20148",
    "iso:country":"IT",
    "sg:address":"20148 Milano",
    "sg:city":"Milano",
    "sg:orig_category":"Incisione Metalli E Plastica",
    "sg:phone":"+39 02 4540 9071",
    "sg:postcode":"20148",
    "sg:province":"Milano",
    "wof:name":"Dottincisioni Di Andrea Dotti",
    "wof:placetype":"venue"
},
  "geometry": {"coordinates":[9.142817,45.474697],"type":"Point"}
}