{
  "type": "Feature",
  "properties": {
    "iso:country":"IT",
    "sg:address":"Via Padre Semeria, 10/12 20035 Lissone",
    "sg:city":"Lissone",
    "sg:classifiers":[
        {
            "category":"Government",
            "subcategory":"Fire Station",
            "type":"Public Place"
        }
    ],
    "sg:phone":"+39 039 278 1193",
    "sg:postcode":"20035",
    "sg:province":"Milano",
    "sg:tags":[
        "steel",
        "band",
        "sections",
        "punching",
        "dy"
    ],
    "sg:website":"www.vismarafratelli.it",
    "wof:name":"Fratelli Vismara Snc Di Vismara Marco",
    "wof:placetype":"venue"
},
  "geometry": {"coordinates":[9.229349,45.602501],"type":"Point"}
}