{
  "type": "Feature",
  "properties": {
    "iso:country":"IT",
    "sg:address":"Via G.boccaccio, 21/23 20090 Trezzano Sul Naviglio",
    "sg:city":"Trezzano sul Naviglio",
    "sg:classifiers":[
        {
            "category":"Military Area",
            "subcategory":"Air Force Base",
            "type":"Public Place"
        }
    ],
    "sg:phone":"+39 02 4846 3366",
    "sg:postcode":"20090",
    "sg:province":"Milano",
    "sg:tags":[
        "cylinder",
        "electric",
        "lifting"
    ],
    "sg:website":"www.linak.it",
    "wof:name":"Linak Italia S.r.l.",
    "wof:placetype":"venue"
},
  "geometry": {"coordinates":[9.052544,45.416573],"type":"Point"}
}