{
  "type": "Feature",
  "properties": {
    "addr:full":"13856 Vigliano Biellese Vigliano Biellese Biella 13856",
    "addr:postcode":"13856;13856",
    "iso:country":"IT",
    "sg:address":"13856 Vigliano Biellese",
    "sg:city":"Vigliano Biellese",
    "sg:orig_category":"Macchine Tessili",
    "sg:phone":"+39 015 510107",
    "sg:postcode":"13856",
    "sg:province":"Biella",
    "wof:name":"Buratti Ing. Luigi Sas Di A. Buratti & C.",
    "wof:placetype":"venue"
},
  "geometry": {"coordinates":[8.103606,45.563892],"type":"Point"}
}