{
  "type": "Feature",
  "properties": {
    "iso:country":"IT",
    "sg:address":"06049 Spoleto",
    "sg:city":"Spoleto",
    "sg:orig_category":"Modellismo",
    "sg:phone":"+39 0743 261310",
    "sg:postcode":"06049",
    "sg:province":"Perugia",
    "wof:name":"Am Model Di Antonelli Mariano",
    "wof:placetype":"venue"
},
  "geometry": {"coordinates":[12.6905326843,42.7190284729],"type":"Point"}
}