{
  "type": "Feature",
  "properties": {
    "addr:full":"36028 Rossano Veneto Rossano Veneto Vicenza 36028",
    "addr:postcode":"36028;36028",
    "addr:street":"Veneto",
    "iso:country":"IT",
    "sg:address":"36028 Rossano Veneto",
    "sg:city":"Rossano Veneto",
    "sg:classifiers":[
        {
            "category":"Home & Garden",
            "subcategory":"Home Furnishings",
            "type":"Retail Goods"
        }
    ],
    "sg:phone":"+39 0424 541081",
    "sg:postcode":"36028",
    "sg:province":"Vicenza",
    "sg:tags":[
        "professional",
        "furniture",
        "accommodation",
        "supply"
    ],
    "wof:name":"Teorema Snc",
    "wof:placetype":"venue"
},
  "geometry": {"coordinates":[11.791639328,45.6747131348],"type":"Point"}
}