{
  "type": "Feature",
  "properties": {
    "addr:full":"95030 Gravina Di Catania Gravina di Catania Catania 95030",
    "addr:postcode":"95030;95030",
    "iso:country":"IT",
    "sg:address":"95030 Gravina Di Catania",
    "sg:city":"Gravina di Catania",
    "sg:orig_category":"Forniture Per Edilizia E Lavori Pubblici",
    "sg:phone":"+39 095 242886",
    "sg:postcode":"95030",
    "sg:province":"Catania",
    "wof:name":"Linea Posa Di Cucchiara Emanuele",
    "wof:placetype":"venue"
},
  "geometry": {"coordinates":[15.0687322617,37.5384101868],"type":"Point"}
}