{
  "type": "Feature",
  "properties": {
    "iso:country":"IT",
    "sg:address":"04026 Minturno",
    "sg:city":"Minturno",
    "sg:orig_category":"Abbigliamento Esterno, Maglierie E Pelliccerie. Shopping",
    "sg:phone":"+39 0771 65129",
    "sg:postcode":"04026",
    "sg:province":"Latina",
    "wof:name":"Camiceria Artigianale 'lucyll' Di Fedele Lucilla",
    "wof:placetype":"venue"
},
  "geometry": {"coordinates":[13.740502,41.261879],"type":"Point"}
}