{
  "type": "Feature",
  "properties": {
    "addr:full":"62/18, Via Centallo 10156 Torino Torino Torino 10156",
    "addr:housenumber":"62 / 18",
    "addr:postcode":"10156;10156",
    "addr:street":"Via Centallo",
    "iso:country":"IT",
    "sg:address":"62/18, Via Centallo 10156 Torino",
    "sg:city":"Torino",
    "sg:classifiers":[
        {
            "category":"Wholesale",
            "subcategory":"Machinery & Supplies",
            "type":"Manufacturing & Wholesale Goods"
        }
    ],
    "sg:phone":"+39 011 273 0668",
    "sg:postcode":"10156",
    "sg:province":"Torino",
    "sg:tags":[
        "equipment",
        "-",
        "instrument",
        "measurement"
    ],
    "wof:name":"Giuliani Tecnologie S.r.l.",
    "wof:placetype":"venue"
},
  "geometry": {"coordinates":[7.723953,45.10218],"type":"Point"}
}