{
  "type": "Feature",
  "properties": {
    "iso:country":"IT",
    "sg:address":"Via Nazionale Est 19 43044 Collecchio",
    "sg:city":"Collecchio",
    "sg:classifiers":[
        {
            "category":"Wholesale",
            "subcategory":"Vending Machines",
            "type":"Manufacturing & Wholesale Goods"
        }
    ],
    "sg:phone":"+39 0521 800800",
    "sg:postcode":"43044",
    "sg:province":"Parma",
    "sg:tags":[
        "inspection"
    ],
    "sg:website":"www.protec-italy.com",
    "wof:name":"Protec Srl",
    "wof:placetype":"venue"
},
  "geometry": {"coordinates":[10.238701,44.759155],"type":"Point"}
}