{
  "type": "Feature",
  "properties": {
    "iso:country":"IT",
    "sg:address":"68, Strada Cebrosa 10036 Settimo Torinese",
    "sg:city":"Settimo Torinese",
    "sg:classifiers":[
        {
            "category":"Autos & Motor Vehicles",
            "subcategory":"Automobile Sales",
            "type":"Retail Goods"
        }
    ],
    "sg:phone":"+39 011 897 7804",
    "sg:postcode":"10036",
    "sg:province":"Torino",
    "sg:tags":[
        "industrial"
    ],
    "wof:name":"Covind S.p.a.",
    "wof:placetype":"venue"
},
  "geometry": {"coordinates":[7.742116,45.142673],"type":"Point"}
}