{
  "type": "Feature",
  "properties": {
    "addr:full":"20157 Milano Milano Milano 20157",
    "addr:postcode":"20157;20157",
    "iso:country":"IT",
    "sg:address":"20157 Milano",
    "sg:city":"Milano",
    "sg:orig_category":"Minuterie Metalliche E Ferramenta",
    "sg:phone":"+39 02 357 4046",
    "sg:postcode":"20157",
    "sg:province":"Milano",
    "wof:name":"Artinox Srl",
    "wof:placetype":"venue"
},
  "geometry": {"coordinates":[9.1358633041,45.5145835876],"type":"Point"}
}