{
  "type": "Feature",
  "properties": {
    "addr:full":"90133 Palermo Palermo Palermo 90133",
    "addr:postcode":"90133;90133",
    "iso:country":"IT",
    "sg:address":"90133 Palermo",
    "sg:city":"Palermo",
    "sg:orig_category":"Prodotti Di Base E Forniture Per Industria Alimentare E Bevande. Forniture E Materiali Per Imballaggio E Confezionamento",
    "sg:phone":"+39 091 580139",
    "sg:postcode":"90133",
    "sg:province":"Palermo",
    "wof:name":"Russo Giuseppe",
    "wof:placetype":"venue"
},
  "geometry": {"coordinates":[13.3659486771,38.1154823303],"type":"Point"}
}