{
  "type": "Feature",
  "properties": {
    "addr:full":"19, Via Montello 28066 Galliate Galliate Novara 28066",
    "addr:postcode":"28066;28066",
    "addr:street":"Via Montello",
    "iso:country":"IT",
    "sg:address":"19, Via Montello 28066 Galliate",
    "sg:city":"Galliate",
    "sg:classifiers":[
        {
            "category":"Manufacturing",
            "subcategory":"Paper Products",
            "type":"Manufacturing & Wholesale Goods"
        }
    ],
    "sg:phone":"+39 0321 866780",
    "sg:postcode":"28066",
    "sg:province":"Novara",
    "sg:tags":[
        "cardboard"
    ],
    "wof:name":"Im.ca. Srl",
    "wof:placetype":"venue"
},
  "geometry": {"coordinates":[8.6877317429,45.4722061157],"type":"Point"}
}