{
  "type": "Feature",
  "properties": {
    "addr:full":"Via Torino 158 12045 Fossano Fossano Cuneo 12045",
    "addr:housenumber":"158",
    "addr:postcode":"12045;12045",
    "addr:street":"Via Torino",
    "iso:country":"IT",
    "sg:address":"Via Torino 158 12045 Fossano",
    "sg:city":"Fossano",
    "sg:classifiers":[
        {
            "category":"Building & Trades",
            "subcategory":"Construction",
            "type":"Services"
        }
    ],
    "sg:phone":"+39 0172 61972",
    "sg:postcode":"12045",
    "sg:province":"Cuneo",
    "sg:tags":[
        "insulation",
        "material",
        "moisture-proof"
    ],
    "wof:name":"Panizzolo Valentino E C. - S.n.c.",
    "wof:placetype":"venue"
},
  "geometry": {"coordinates":[7.5863018036,44.5046157837],"type":"Point"}
}