{
  "type": "Feature",
  "properties": {
    "iso:country":"IT",
    "sg:address":"24020 Vilminore Di Scalve",
    "sg:city":"Vilminore",
    "sg:orig_category":"Macchine E Forniture Per Arredamento E Industria Del Legno",
    "sg:phone":"+39 0346 51485",
    "sg:postcode":"24020",
    "sg:province":"Bergamo",
    "sg:website":"http://www.duci.it",
    "wof:name":"Duci Fratelli Snc",
    "wof:placetype":"venue"
},
  "geometry": {"coordinates":[10.094595,45.996593],"type":"Point"}
}