{
  "type": "Feature",
  "properties": {
    "addr:full":"Via Oderzo 42 31040 Mansue' Treviso 31040",
    "addr:housenumber":"42",
    "addr:postcode":"31040;31040",
    "addr:street":"Via Oderzo",
    "iso:country":"IT",
    "sg:address":"Via Oderzo 42 31040 Mansue'",
    "sg:classifiers":[
        {
            "category":"Wholesale",
            "subcategory":"Auto Parts",
            "type":"Manufacturing & Wholesale Goods"
        }
    ],
    "sg:phone":"+39 0422 741186",
    "sg:postcode":"31040",
    "sg:province":"Treviso",
    "sg:tags":[
        "shutter",
        "component",
        "roller"
    ],
    "sg:website":"www.dalex.it",
    "wof:name":"Dalex Srl",
    "wof:placetype":"venue"
},
  "geometry": {"coordinates":[12.529111,45.806576],"type":"Point"}
}