{
  "type": "Feature",
  "properties": {
    "addr:full":"43010 Trecasali Trecasali Parma 43010",
    "addr:postcode":"43010;43010",
    "addr:street":"Trecasali",
    "iso:country":"IT",
    "sg:address":"43010 Trecasali",
    "sg:city":"Trecasali",
    "sg:orig_category":"Riparazione Dei Mezzi Di Trasporto",
    "sg:phone":"+39 0521 605172",
    "sg:postcode":"43010",
    "sg:province":"Parma",
    "wof:name":"Carrozzeria Cfm Srl",
    "wof:placetype":"venue"
},
  "geometry": {"coordinates":[10.254668,44.879711],"type":"Point"}
}