{
  "type": "Feature",
  "properties": {
    "iso:country":"IT",
    "sg:address":"36, Viale Cassala 20143 Milano",
    "sg:city":"Milano",
    "sg:classifiers":[
        {
            "category":"Manufacturing",
            "subcategory":"Food",
            "type":"Manufacturing & Wholesale Goods"
        }
    ],
    "sg:phone":"+39 02 8940 6013",
    "sg:postcode":"20143",
    "sg:province":"Milano",
    "sg:tags":[
        "equipment",
        "processing",
        "-",
        "machinery"
    ],
    "wof:name":"E.dragoni Snc Di Emilio E Leonardo Dragoni",
    "wof:placetype":"venue"
},
  "geometry": {"coordinates":[9.1652498245,45.4441986084],"type":"Point"}
}