{
  "type": "Feature",
  "properties": {
    "iso:country":"IT",
    "sg:address":"54100 Massa",
    "sg:city":"Massa",
    "sg:orig_category":"Telecomunicazioni E Telefonia, Impianti, Apparecchi E Servizi",
    "sg:phone":"+39 0585 44697",
    "sg:postcode":"54100",
    "sg:province":"Massa-Carrara",
    "wof:name":"Mauri Hi-fi Car 2 Sas Di Marchi Gianluca & C.",
    "wof:placetype":"venue"
},
  "geometry": {"coordinates":[10.135584,44.037197],"type":"Point"}
}