{
  "type": "Feature",
  "properties": {
    "addr:full":"20060 Bussero Bussero Milano 20060",
    "addr:postcode":"20060;20060",
    "iso:country":"IT",
    "sg:address":"20060 Bussero",
    "sg:city":"Bussero",
    "sg:orig_category":"Macchine, Impianti Ed Attrezzature Per Industria Alimentare E Bevande",
    "sg:phone":"+39 02 9503 8111",
    "sg:postcode":"20060",
    "sg:province":"Milano",
    "wof:name":"Agnelli Macchine Srl",
    "wof:placetype":"venue"
},
  "geometry": {"coordinates":[9.196656,45.547565],"type":"Point"}
}