{
  "type": "Feature",
  "properties": {
    "iso:country":"IT",
    "sg:address":"11/a, Via G. Di Vittorio 42030 Vezzano Sul Crostolo",
    "sg:classifiers":[
        {
            "category":"Shopping",
            "subcategory":"Computers & Home Electronics",
            "type":"Retail Goods"
        }
    ],
    "sg:phone":"+39 0522 606334",
    "sg:postcode":"42030",
    "sg:province":"Reggio Nell'Emilia",
    "sg:tags":[
        "electronic",
        "electrical",
        "equipment"
    ],
    "wof:name":"Elettromeccanica Garimberti (s.n.c.)",
    "wof:placetype":"venue"
},
  "geometry": {"coordinates":[10.548081,44.609661],"type":"Point"}
}