{
  "type": "Feature",
  "properties": {
    "iso:country":"IT",
    "sg:address":"25135 Brescia",
    "sg:city":"Brescia",
    "sg:orig_category":"Macchine, Impianti E Forniture Per Industria Grafica, Cartaria E Cartotecnica",
    "sg:phone":"+39 030 360458",
    "sg:postcode":"25135",
    "sg:province":"Brescia",
    "wof:name":"Ero S.r.l.",
    "wof:placetype":"venue"
},
  "geometry": {"coordinates":[10.290583,45.518475],"type":"Point"}
}