{
  "type": "Feature",
  "properties": {
    "iso:country":"IT",
    "sg:address":"23020 Montagna Valtellina",
    "sg:orig_category":"Elettrotecnica Professionale E Di Consumo. Forniture Per Attivita' Commerciali Ed Artigianali",
    "sg:phone":"+39 0342 515317",
    "sg:postcode":"23020",
    "sg:province":"Sondrio",
    "wof:name":"Nuova Artigian Neon Snc Di Bormetti Dario & C.",
    "wof:placetype":"venue"
},
  "geometry": {"coordinates":[9.905475,46.165756],"type":"Point"}
}