{
  "type": "Feature",
  "properties": {
    "addr:full":"10098 Rivoli Cascine vica Torino 10098",
    "addr:postcode":"10098;10098",
    "iso:country":"IT",
    "sg:address":"10098 Rivoli",
    "sg:city":"Cascine vica",
    "sg:orig_category":"Forniture Per Attivita' Industriali",
    "sg:phone":"+39 011 959 1626",
    "sg:postcode":"10098",
    "sg:province":"Torino",
    "wof:name":"Camar Spa",
    "wof:placetype":"venue"
},
  "geometry": {"coordinates":[7.5561304092,45.0623664856],"type":"Point"}
}