{
  "type": "Feature",
  "properties": {
    "iso:country":"IT",
    "sg:address":"20131 Milano",
    "sg:city":"Milano",
    "sg:orig_category":"Ricerca, Selezione E Formazione Del Personale",
    "sg:phone":"+39 02 2611 3059",
    "sg:postcode":"20131",
    "sg:province":"Milano",
    "wof:name":"Adecco Societa' Di Fornitura Di Lavoro Temporaneo Spa",
    "wof:placetype":"venue"
},
  "geometry": {"coordinates":[9.219283,45.486187],"type":"Point"}
}