{
  "type": "Feature",
  "properties": {
    "iso:country":"IT",
    "sg:address":"64/2, Via Macario Fratelli 10098 Rivoli",
    "sg:city":"Rivoli",
    "sg:classifiers":[
        {
            "category":"Professional",
            "subcategory":"Computer Services",
            "type":"Services"
        }
    ],
    "sg:phone":"+39 011 959 2888",
    "sg:postcode":"10098",
    "sg:province":"Torino",
    "sg:tags":[
        "information",
        "technology"
    ],
    "wof:name":"Vela Informatics Srl",
    "wof:placetype":"venue"
},
  "geometry": {"coordinates":[7.538417,45.068199],"type":"Point"}
}