{
  "type": "Feature",
  "properties": {
    "addr:full":"Via Pavia 1 27010 Cura Carpignano Cura Carpignano Pavia 27010",
    "addr:housenumber":"1",
    "addr:postcode":"27010;27010",
    "addr:street":"Via Pavia",
    "iso:country":"IT",
    "sg:address":"Via Pavia 1 27010 Cura Carpignano",
    "sg:city":"Cura Carpignano",
    "sg:classifiers":[
        {
            "category":"Professional",
            "subcategory":"Advertising",
            "type":"Services"
        }
    ],
    "sg:phone":"+39 0382 483408",
    "sg:postcode":"27010",
    "sg:province":"Pavia",
    "sg:tags":[
        "outdoor",
        "system"
    ],
    "wof:name":"Ondavision S.p.a.",
    "wof:placetype":"venue"
},
  "geometry": {"coordinates":[9.229157,45.159992],"type":"Point"}
}