{
  "type": "Feature",
  "properties": {
    "iso:country":"IT",
    "sg:address":"8, Via Redipuglia 20010 Bareggio",
    "sg:city":"Bareggio",
    "sg:classifiers":[
        {
            "category":"Manufacturing",
            "subcategory":"Tools & Machinery",
            "type":"Manufacturing & Wholesale Goods"
        }
    ],
    "sg:phone":"+39 390 290 3011",
    "sg:postcode":"20010",
    "sg:province":"Milano",
    "sg:tags":[
        "environment",
        "equipment",
        "-"
    ],
    "wof:name":"Silvani Antincendi S.p.a.",
    "wof:placetype":"venue"
},
  "geometry": {"coordinates":[8.997144,45.489902],"type":"Point"}
}