{
  "type": "Feature",
  "properties": {
    "iso:country":"IT",
    "sg:address":"40138 Bologna",
    "sg:city":"Bologna",
    "sg:orig_category":"Tessuti Arredamento, Tende E Tappeti",
    "sg:phone":"+39 051 601 4178",
    "sg:postcode":"40138",
    "sg:province":"Bologna",
    "wof:name":"Vettaflex Snc",
    "wof:placetype":"venue"
},
  "geometry": {"coordinates":[11.418701,44.50301],"type":"Point"}
}