{
  "type": "Feature",
  "properties": {
    "addr:full":"04014 Pontinia Pontinia Latina 04014",
    "addr:postcode":"04014;04014",
    "iso:country":"IT",
    "sg:address":"04014 Pontinia",
    "sg:city":"Pontinia",
    "sg:orig_category":"Materiali E Componenti Elettrotecnici",
    "sg:phone":"+39 0773 86134",
    "sg:postcode":"04014",
    "sg:province":"Latina",
    "wof:name":"Porcelli Luisa",
    "wof:placetype":"venue"
},
  "geometry": {"coordinates":[12.906703,41.465729],"type":"Point"}
}