{
  "type": "Feature",
  "properties": {
    "iso:country":"IT",
    "sg:address":"34123 Trieste",
    "sg:city":"Trieste",
    "sg:orig_category":"Studi E Consulenze Tecniche E Industriali. Consulenze Tecniche, Amministrative E Perizie. Professionisti - Studi E Servizi Ed Associazioni Di Interesse Aziendale",
    "sg:phone":"+39 040 313190",
    "sg:postcode":"34123",
    "sg:province":"Trieste",
    "wof:name":"Tromba Ciro",
    "wof:placetype":"venue"
},
  "geometry": {"coordinates":[13.758304,45.644783],"type":"Point"}
}