{
  "type": "Feature",
  "properties": {
    "iso:country":"IT",
    "sg:address":"Via Corridoni, 20/22 56024 Ponte A Egola",
    "sg:city":"Ponte a egola",
    "sg:orig_category":"Ladies' Handbags",
    "sg:phone":"+39 0571 49424",
    "sg:postcode":"56024",
    "sg:province":"Pisa",
    "sg:website":"www.tuscans.it",
    "wof:name":"Tuscan's Creation Srl",
    "wof:placetype":"venue"
},
  "geometry": {"coordinates":[10.791217,43.687515],"type":"Point"}
}