{
  "type": "Feature",
  "properties": {
    "iso:country":"IT",
    "sg:address":"95129 Catania",
    "sg:city":"Catania",
    "sg:orig_category":"Articoli Da Regalo. Shopping. Regalistica Aziendale",
    "sg:phone":"+39 095 746 2020",
    "sg:postcode":"95129",
    "sg:province":"Catania",
    "wof:name":"Bagliori Del Millennio Di Rigoli Gianfranco",
    "wof:placetype":"venue"
},
  "geometry": {"coordinates":[15.102775,37.512924],"type":"Point"}
}