{
  "type": "Feature",
  "properties": {
    "addr:full":"16, Via Bersaglio 22015 Gravedona Gravedona Como 22015",
    "addr:postcode":"22015;22015",
    "addr:street":"Via Bersaglio",
    "iso:country":"IT",
    "sg:address":"16, Via Bersaglio 22015 Gravedona",
    "sg:city":"Gravedona",
    "sg:classifiers":[
        {
            "category":"Autos & Motor Vehicles",
            "subcategory":"Boat Sales",
            "type":"Retail Goods"
        }
    ],
    "sg:phone":"+39 39034480914",
    "sg:postcode":"22015",
    "sg:province":"Como",
    "wof:name":"Belatti",
    "wof:placetype":"venue"
},
  "geometry": {"coordinates":[9.297488,46.144756],"type":"Point"}
}