{
  "type": "Feature",
  "properties": {
    "iso:country":"IT",
    "sg:address":"8/a, Via Settembrini Luigi 60027 Osimo",
    "sg:city":"Osimo",
    "sg:classifiers":[
        {
            "category":"Manufacturing",
            "subcategory":"Metals",
            "type":"Manufacturing & Wholesale Goods"
        }
    ],
    "sg:phone":"+39 39071781075",
    "sg:postcode":"60027",
    "sg:province":"Ancona",
    "sg:tags":[
        "metallurgy",
        "metalworking"
    ],
    "wof:name":"Filippini",
    "wof:placetype":"venue"
},
  "geometry": {"coordinates":[13.5187568665,43.6158561707],"type":"Point"}
}