{
  "type": "Feature",
  "properties": {
    "addr:full":"10128 Torino Torino Torino 10128",
    "addr:postcode":"10128;10128",
    "iso:country":"IT",
    "sg:address":"10128 Torino",
    "sg:city":"Torino",
    "sg:orig_category":"Servizi Per Aziende, Manifestazioni E Supporto Agli Scambi Commerciali",
    "sg:phone":"+39 011 504317",
    "sg:postcode":"10128",
    "sg:province":"Torino",
    "wof:name":"Centro Uffici Manageriali Snc",
    "wof:placetype":"venue"
},
  "geometry": {"coordinates":[7.671986,45.054905],"type":"Point"}
}