{
  "type": "Feature",
  "properties": {
    "iso:country":"IT",
    "sg:address":"34077 Ronchi Dei Legionari",
    "sg:city":"Ronchi dei Legionari",
    "sg:orig_category":"Campeggio",
    "sg:phone":"+39 0481 779088",
    "sg:postcode":"34077",
    "sg:province":"Gorizia",
    "wof:name":"Il Giro Del Sole (s.a.s.)",
    "wof:placetype":"venue"
},
  "geometry": {"coordinates":[13.47296,45.81918],"type":"Point"}
}