{
  "type": "Feature",
  "properties": {
    "addr:full":"63017 Porto San Giorgio Porto San Giorgio Ascoli Piceno 63017",
    "addr:postcode":"63017;63017",
    "addr:street":"Piceno",
    "iso:country":"IT",
    "sg:address":"63017 Porto San Giorgio",
    "sg:city":"Porto San Giorgio",
    "sg:orig_category":"Ceramiche: Prodotti E Lavorazioni",
    "sg:phone":"+39 0734 676245",
    "sg:postcode":"63017",
    "sg:province":"Ascoli Piceno",
    "wof:name":"Santarelli Vittorio E Figlie",
    "wof:placetype":"venue"
},
  "geometry": {"coordinates":[13.794389,43.183777],"type":"Point"}
}