{
  "type": "Feature",
  "properties": {
    "addr:full":"80056 Ercolano Ercolano Napoli 80056",
    "addr:postcode":"80056;80056",
    "iso:country":"IT",
    "sg:address":"80056 Ercolano",
    "sg:city":"Ercolano",
    "sg:orig_category":"Abbigliamento Esterno, Maglierie E Pelliccerie",
    "sg:phone":"+39 081 739 7508",
    "sg:postcode":"80056",
    "sg:province":"Napoli",
    "wof:name":"Confezioni Vip Di Occhiello Salvatore & C. Sas",
    "wof:placetype":"venue"
},
  "geometry": {"coordinates":[14.357792,40.805691],"type":"Point"}
}