{
  "type": "Feature",
  "properties": {
    "iso:country":"IT",
    "sg:address":"37016 Garda",
    "sg:city":"Garda",
    "sg:orig_category":"Alberghi",
    "sg:phone":"+39 045 725 6688",
    "sg:postcode":"37016",
    "sg:province":"Verona",
    "wof:name":"Societ\u00c1 Regina Srl",
    "wof:placetype":"venue"
},
  "geometry": {"coordinates":[10.671072,45.571083],"type":"Point"}
}