{
  "type": "Feature",
  "properties": {
    "iso:country":"IT",
    "sg:address":"Via Milano 248 20021 Bollate",
    "sg:city":"Bollate",
    "sg:classifiers":[
        {
            "category":"Professional",
            "subcategory":"Detective & Security Services",
            "type":"Services"
        }
    ],
    "sg:phone":"+39 02 3820 0510",
    "sg:postcode":"20021",
    "sg:province":"Milano",
    "sg:tags":[
        "dust",
        "protection",
        "mask"
    ],
    "sg:website":"www.spasciani.com",
    "wof:name":"Riccardo Spasciani Spa",
    "wof:placetype":"venue"
},
  "geometry": {"coordinates":[9.113177,45.525639],"type":"Point"}
}