{
  "type": "Feature",
  "properties": {
    "iso:country":"IT",
    "sg:address":"10138 Torino",
    "sg:city":"Torino",
    "sg:orig_category":"Articoli Religiosi",
    "sg:phone":"+39 011 447 6695",
    "sg:postcode":"10138",
    "sg:province":"Torino",
    "wof:name":"Libreria Della Consolata - Misco Srl",
    "wof:placetype":"venue"
},
  "geometry": {"coordinates":[7.657862,45.069744],"type":"Point"}
}