{
  "type": "Feature",
  "properties": {
    "iso:country":"IT",
    "sg:address":"72 Ausserprags; Prags; 39030",
    "sg:classifiers":[
        {
            "category":"Banks & Credit Unions",
            "subcategory":"Bank",
            "type":"Services"
        }
    ],
    "sg:phone":"+39 0474 78615",
    "sg:postcode":"39030",
    "sg:province":"Bolzano/Bozen",
    "wof:name":"Raiffeisen Zentralkasse, Niederdorf",
    "wof:placetype":"venue"
},
  "geometry": {"coordinates":[12.140523,46.729137],"type":"Point"}
}