{
  "type": "Feature",
  "properties": {
    "addr:full":"Via Quattropassi 1/4 41043 Formigine Formigine Modena 41043",
    "addr:housenumber":"1 / 4",
    "addr:postcode":"41043;41043",
    "addr:street":"Via Quattropassi",
    "iso:country":"IT",
    "sg:address":"Via Quattropassi 1/4 41043 Formigine",
    "sg:city":"Formigine",
    "sg:classifiers":[
        {
            "category":"Manufacturing",
            "subcategory":"Motor Vehicles & Parts",
            "type":"Manufacturing & Wholesale Goods"
        }
    ],
    "sg:phone":"+39 0536 819411",
    "sg:postcode":"41043",
    "sg:province":"Modena",
    "sg:tags":[
        "electromechanical"
    ],
    "sg:website":"www.motovario.it",
    "wof:name":"Motovario Spa",
    "wof:placetype":"venue"
},
  "geometry": {"coordinates":[10.92522,44.647079],"type":"Point"}
}