{
  "type": "Feature",
  "properties": {
    "iso:country":"IT",
    "sg:address":"28, Via Piossasco 10152 Torino",
    "sg:city":"Torino",
    "sg:classifiers":[
        {
            "category":"Manufacturing",
            "subcategory":"Printing",
            "type":"Manufacturing & Wholesale Goods"
        }
    ],
    "sg:phone":"+39 011 248 2036",
    "sg:postcode":"10152",
    "sg:province":"Torino",
    "sg:tags":[
        "publishing"
    ],
    "wof:name":"Brandoni Carlo (s.n.c.)",
    "wof:placetype":"venue"
},
  "geometry": {"coordinates":[7.5556430817,45.0077667236],"type":"Point"}
}