{
  "type": "Feature",
  "properties": {
    "iso:country":"IT",
    "sg:address":"40138 Bologna",
    "sg:city":"Bologna",
    "sg:classifiers":[
        {
            "category":"Parking",
            "subcategory":"Lot",
            "type":"Transportation"
        }
    ],
    "sg:phone":"+39 051 601 3472",
    "sg:postcode":"40138",
    "sg:province":"Bologna",
    "sg:tags":[
        "good",
        "shipment",
        "transport"
    ],
    "wof:name":"Luciani Albertino",
    "wof:placetype":"venue"
},
  "geometry": {"coordinates":[11.39497,44.489056],"type":"Point"}
}