{
  "type": "Feature",
  "properties": {
    "iso:country":"IT",
    "sg:address":"20092 Cinisello Balsamo",
    "sg:city":"Cinisello Balsamo",
    "sg:orig_category":"Servizi Per Imballaggio E Confezionamento",
    "sg:phone":"+39 02 612 5999",
    "sg:postcode":"20092",
    "sg:province":"Milano",
    "wof:name":"New General Work",
    "wof:placetype":"venue"
},
  "geometry": {"coordinates":[9.217986,45.553581],"type":"Point"}
}