{
  "type": "Feature",
  "properties": {
    "iso:country":"IT",
    "sg:address":"40043 Pian Di Venola",
    "sg:city":"Pian di Venola",
    "sg:orig_category":"Macchine Ed Impianti Per Edilizia E Lavori Pubblici",
    "sg:phone":"+39 051 932833",
    "sg:postcode":"40043",
    "sg:province":"Bologna",
    "wof:name":"Lolli Mario",
    "wof:placetype":"venue"
},
  "geometry": {"coordinates":[11.190981,44.333694],"type":"Point"}
}