{
  "type": "Feature",
  "properties": {
    "iso:country":"IT",
    "sg:address":"34, Via Maggiore 33039 Sedegliano",
    "sg:city":"Sedegliano",
    "sg:classifiers":[
        {
            "category":"Shopping",
            "subcategory":"Computers & Home Electronics",
            "type":"Retail Goods"
        }
    ],
    "sg:phone":"+39 0432 916262",
    "sg:postcode":"33039",
    "sg:province":"Udine",
    "sg:tags":[
        "electronic",
        "electrical",
        "equipment"
    ],
    "wof:name":"Elettrica Friulana Snc Di Tonizzo Ugo & C.",
    "wof:placetype":"venue"
},
  "geometry": {"coordinates":[12.959771,46.000397],"type":"Point"}
}