{
  "type": "Feature",
  "properties": {
    "addr:full":"Via Annunziata 17 12064 La Morra La Morra Cuneo 12064",
    "addr:housenumber":"17",
    "addr:postcode":"12064;12064",
    "addr:street":"Via Annunziata",
    "iso:country":"IT",
    "sg:address":"Via Annunziata 17 12064 La Morra",
    "sg:city":"La Morra",
    "sg:classifiers":[
        {
            "category":"Shopping",
            "subcategory":"Gifts & Souvenirs",
            "type":"Retail Goods"
        }
    ],
    "sg:phone":"+39 0173 509471",
    "sg:postcode":"12064",
    "sg:province":"Cuneo",
    "sg:tags":[
        "item"
    ],
    "sg:website":"www.soledisanmartino.com",
    "wof:name":"Sole Di San Martino Di Veglio E C. Srl",
    "wof:placetype":"venue"
},
  "geometry": {"coordinates":[7.922998,44.67141],"type":"Point"}
}