{
  "type": "Feature",
  "properties": {
    "iso:country":"IT",
    "sg:address":"27057 Varzi",
    "sg:city":"Varzi",
    "sg:orig_category":"Metalli E Leghe",
    "sg:phone":"+39 0383 5481",
    "sg:postcode":"27057",
    "sg:province":"Pavia",
    "wof:name":"Ilva Spa",
    "wof:placetype":"venue"
},
  "geometry": {"coordinates":[9.2126312256,44.8055953979],"type":"Point"}
}