{
  "type": "Feature",
  "properties": {
    "iso:country":"IT",
    "sg:address":"3, Via Del Marginone 55012 Capannori",
    "sg:city":"Capannori",
    "sg:classifiers":[
        {
            "category":"Wholesale",
            "subcategory":"Machinery & Supplies",
            "type":"Manufacturing & Wholesale Goods"
        }
    ],
    "sg:phone":"+39 0583 981388",
    "sg:postcode":"55012",
    "sg:province":"Lucca",
    "sg:tags":[
        "equipment",
        "-",
        "instrument",
        "measurement"
    ],
    "wof:name":"S.a.m.p.i. Spa",
    "wof:placetype":"venue"
},
  "geometry": {"coordinates":[10.551678,43.837135],"type":"Point"}
}