{
  "type": "Feature",
  "properties": {
    "addr:full":"41058 Vignola Vignola Modena 41058",
    "addr:postcode":"41058;41058",
    "iso:country":"IT",
    "sg:address":"41058 Vignola",
    "sg:city":"Vignola",
    "sg:orig_category":"Forniture Per Agricoltura E Zootecnia. Prodotti Chimici Secondari. Macchine E Forniture Per Ecologia E Smaltimento Rifiuti",
    "sg:phone":"+39 059 773354",
    "sg:postcode":"41058",
    "sg:province":"Modena",
    "sg:website":"http://www.springprotezione.it",
    "wof:name":"Spring Protezione Srl",
    "wof:placetype":"venue"
},
  "geometry": {"coordinates":[11.0150470734,44.4793624878],"type":"Point"}
}