{
  "type": "Feature",
  "properties": {
    "iso:country":"IT",
    "sg:address":"1, Via Caboto Giovanni 37036 San Martino Buon Albergo",
    "sg:city":"San Martino Buon Albergo",
    "sg:classifiers":[
        {
            "category":"Autos & Motor Vehicles",
            "subcategory":"Automobile Sales",
            "type":"Retail Goods"
        }
    ],
    "sg:phone":"+39 39045992966",
    "sg:postcode":"37036",
    "sg:province":"Verona",
    "sg:tags":[
        "motor-cars"
    ],
    "wof:name":"Autovitt Italia (s.r.l.)",
    "wof:placetype":"venue"
},
  "geometry": {"coordinates":[11.1092309952,45.4192657471],"type":"Point"}
}