{
  "type": "Feature",
  "properties": {
    "iso:country":"IT",
    "sg:address":"43040 Vicofertile",
    "sg:orig_category":"Carta, Cartone E Prodotti Primari. Forniture E Materiali Per Imballaggio E Confezionamento",
    "sg:phone":"+39 0521 674084",
    "sg:postcode":"43040",
    "sg:province":"Parma",
    "wof:name":"Idea Srl",
    "wof:placetype":"venue"
},
  "geometry": {"coordinates":[10.261057,44.782543],"type":"Point"}
}