{
  "type": "Feature",
  "properties": {
    "iso:country":"IT",
    "sg:address":"10, Via Empedocle 93100 Caltanissetta",
    "sg:city":"Caltanissetta",
    "sg:classifiers":[
        {
            "category":"Wholesale",
            "subcategory":"Drugs",
            "type":"Manufacturing & Wholesale Goods"
        }
    ],
    "sg:phone":"+39 0934 585233",
    "sg:postcode":"93100",
    "sg:province":"Caltanissetta",
    "sg:tags":[
        "chemical",
        "pharmaceutical"
    ],
    "wof:name":"Societa' Centro Resina S.a.s.",
    "wof:placetype":"venue"
},
  "geometry": {"coordinates":[14.054385,37.465145],"type":"Point"}
}