{
  "type": "Feature",
  "properties": {
    "addr:full":"20125 Milano Milano Milano 20125",
    "addr:postcode":"20125;20125",
    "iso:country":"IT",
    "sg:address":"20125 Milano",
    "sg:city":"Milano",
    "sg:orig_category":"Materiali Edili",
    "sg:phone":"+39 02 6680 0417",
    "sg:postcode":"20125",
    "sg:province":"Milano",
    "wof:name":"Valdata Laterizi Prefabbricati Srl",
    "wof:placetype":"venue"
},
  "geometry": {"coordinates":[9.183043,45.459446],"type":"Point"}
}