{
  "type": "Feature",
  "properties": {
    "addr:full":"41012 Carpi Carpi Modena 41012",
    "addr:postcode":"41012;41012",
    "iso:country":"IT",
    "sg:address":"41012 Carpi",
    "sg:city":"Carpi",
    "sg:orig_category":"Forniture Per Abbigliamento E Pelletterie. Forniture Per Attivita' Commerciali Ed Artigianali",
    "sg:phone":"+39 059 689293",
    "sg:postcode":"41012",
    "sg:province":"Modena",
    "wof:name":"L'accessorio Oscar Sacchi & C. Srl",
    "wof:placetype":"venue"
},
  "geometry": {"coordinates":[10.8953857422,44.7975196838],"type":"Point"}
}