{
  "type": "Feature",
  "properties": {
    "iso:country":"IT",
    "sg:address":"51031 Agliana",
    "sg:city":"Agliana",
    "sg:classifiers":[
        {
            "category":"Community Center",
            "subcategory":"Youth",
            "type":"Public Place"
        }
    ],
    "sg:phone":"+39 0574 718413",
    "sg:postcode":"51031",
    "sg:province":"Pistoia",
    "sg:tags":[
        "underwear",
        "bathing",
        "stocking",
        "costume"
    ],
    "wof:name":"Mazzei Lydia",
    "wof:placetype":"venue"
},
  "geometry": {"coordinates":[11.005964,43.909294],"type":"Point"}
}