{
  "type": "Feature",
  "properties": {
    "addr:full":"Via Degli Astronauti; Montemiletto; 83038 Montemiletto Avellino 83038",
    "addr:postcode":"83038;83038",
    "addr:street":"Via Degli Astronauti",
    "iso:country":"IT",
    "sg:address":"Via Degli Astronauti; Montemiletto; 83038",
    "sg:city":"Montemiletto",
    "sg:classifiers":[
        {
            "category":"Banks & Credit Unions",
            "subcategory":"Bank",
            "type":"Services"
        }
    ],
    "sg:phone":"+39 0825 968350",
    "sg:postcode":"83038",
    "sg:province":"Avellino",
    "wof:name":"Banco Di Napoli Spa",
    "wof:placetype":"venue"
},
  "geometry": {"coordinates":[14.907926,41.010185],"type":"Point"}
}