{
  "type": "Feature",
  "properties": {
    "iso:country":"IT",
    "sg:address":"10053 Bussoleno",
    "sg:city":"Bussoleno",
    "sg:orig_category":"Servizi Ausiliari Dei Mezzi Di Trasporto",
    "sg:phone":"+39 0122 48846",
    "sg:postcode":"10053",
    "sg:province":"Torino",
    "sg:website":"http://www.centrorevisioni.it",
    "wof:name":"C.r.a. Valsusa Srl",
    "wof:placetype":"venue"
},
  "geometry": {"coordinates":[7.128462,45.142849],"type":"Point"}
}