{
  "type": "Feature",
  "properties": {
    "addr:full":"20090 Settala Settala Milano 20090",
    "addr:postcode":"20090;20090",
    "iso:country":"IT",
    "sg:address":"20090 Settala",
    "sg:city":"Settala",
    "sg:classifiers":[
        {
            "category":"Bars & Pubs",
            "subcategory":"Lounge",
            "type":"Food & Drink"
        }
    ],
    "sg:phone":"+39 02 9577 0008",
    "sg:postcode":"20090",
    "sg:province":"Milano",
    "sg:tags":[
        "e",
        "-",
        "spray",
        "aerosol",
        "prodotti",
        "confezionamenti"
    ],
    "wof:name":"Costruzioni Klinghammer Italia Srl",
    "wof:placetype":"venue"
},
  "geometry": {"coordinates":[9.395608,45.452396],"type":"Point"}
}