{
  "type": "Feature",
  "properties": {
    "addr:full":"90144 Palermo Palermo Palermo 90144",
    "addr:postcode":"90144;90144",
    "iso:country":"IT",
    "sg:address":"90144 Palermo",
    "sg:city":"Palermo",
    "sg:orig_category":"Valvole E Apparecchiature Di Misura. Ricambi E Componenti Dei Mezzi Di Trasporto",
    "sg:phone":"+39 091 730 8321",
    "sg:postcode":"90144",
    "sg:province":"Palermo",
    "wof:name":"Alliedsignal Automotive Italia S.p.a.",
    "wof:placetype":"venue"
},
  "geometry": {"coordinates":[13.340271,38.140957],"type":"Point"}
}