{
  "type": "Feature",
  "properties": {
    "iso:country":"IT",
    "sg:address":"Via Rivarotta 6 36061 Bassano Del Grappa",
    "sg:city":"Bassano del Grappa",
    "sg:classifiers":[
        {
            "category":"Home & Garden",
            "subcategory":"Home Furnishings",
            "type":"Retail Goods"
        }
    ],
    "sg:phone":"+39 0424 590088",
    "sg:postcode":"36061",
    "sg:province":"Vicenza",
    "sg:tags":[
        "household",
        "ceramic"
    ],
    "sg:website":"www.ceramicheelios.com",
    "wof:name":"Ceramiche Elios Snc",
    "wof:placetype":"venue"
},
  "geometry": {"coordinates":[11.6895,45.737953],"type":"Point"}
}