{
  "type": "Feature",
  "properties": {
    "iso:country":"IT",
    "sg:address":"20058 Villasanta",
    "sg:city":"Villasanta",
    "sg:orig_category":"Lavorazioni Metalli, Stampaggio E Saldatura",
    "sg:phone":"+39 039 232 5060",
    "sg:postcode":"20058",
    "sg:province":"Milano",
    "wof:name":"Stampinox Galbiati S.r.l.",
    "wof:placetype":"venue"
},
  "geometry": {"coordinates":[9.208785,45.464081],"type":"Point"}
}