{
  "type": "Feature",
  "properties": {
    "iso:country":"IT",
    "sg:address":"95030 Gravina Di Catania",
    "sg:city":"Gravina di Catania",
    "sg:orig_category":"Arredi Ed Attrezzature Per Uffici",
    "sg:phone":"+39 095 421616",
    "sg:postcode":"95030",
    "sg:province":"Catania",
    "wof:name":"Marketing Coffee Srl",
    "wof:placetype":"venue"
},
  "geometry": {"coordinates":[15.06561,37.556789],"type":"Point"}
}