{
  "type": "Feature",
  "properties": {
    "iso:country":"IT",
    "sg:address":"P.zza Matteotti 30; Siena; 53100",
    "sg:city":"Siena",
    "sg:classifiers":[
        {
            "category":"Shopping",
            "subcategory":"Computers & Home Electronics",
            "type":"Retail Goods"
        }
    ],
    "sg:phone":"+39 0577 202511",
    "sg:postcode":"53100",
    "sg:province":"Siena",
    "sg:tags":[
        "chamber",
        "commerce"
    ],
    "wof:name":"Siena Cci",
    "wof:placetype":"venue"
},
  "geometry": {"coordinates":[11.328681,43.321445],"type":"Point"}
}