{
  "type": "Feature",
  "properties": {
    "addr:full":"10156 Torino Torino Torino 10156",
    "addr:postcode":"10156;10156",
    "iso:country":"IT",
    "sg:address":"10156 Torino",
    "sg:city":"Torino",
    "sg:orig_category":"Dolciumi E Gelati",
    "sg:phone":"+39 011 273 2441",
    "sg:postcode":"10156",
    "sg:province":"Torino",
    "sg:website":"http://www.piemontcioccolato.com",
    "wof:name":"Piemont Snc",
    "wof:placetype":"venue"
},
  "geometry": {"coordinates":[7.746955,45.099705],"type":"Point"}
}