{
  "type": "Feature",
  "properties": {
    "iso:country":"IT",
    "sg:address":"37064 Povegliano Veronese",
    "sg:city":"Povegliano Veronese",
    "sg:orig_category":"Macchine Ed Impianti Per Edilizia E Lavori Pubblici. Forniture Per Edilizia E Lavori Pubblici",
    "sg:phone":"+39 045 797 1903",
    "sg:postcode":"37064",
    "sg:province":"Verona",
    "sg:website":"http://www.edilponte.it",
    "wof:name":"Officine Ferron Renato Snc Di Silvestri Giovanni E C.",
    "wof:placetype":"venue"
},
  "geometry": {"coordinates":[10.896791,45.449554],"type":"Point"}
}