{
  "type": "Feature",
  "properties": {
    "iso:country":"IT",
    "sg:address":"20148 Milano",
    "sg:city":"Milano",
    "sg:orig_category":"Servizi Ausiliari Dei Mezzi Di Trasporto",
    "sg:phone":"+39 02 406336",
    "sg:postcode":"20148",
    "sg:province":"Milano",
    "wof:name":"Garage Dolci Di Agostinetto Gianni E C. (s.n.c.)",
    "wof:placetype":"venue"
},
  "geometry": {"coordinates":[9.142104,45.473137],"type":"Point"}
}