{
  "type": "Feature",
  "properties": {
    "iso:country":"IT",
    "sg:address":"91100 Trapani",
    "sg:city":"Trapani",
    "sg:orig_category":"Box Prefabbricati",
    "sg:phone":"+39 0923 537788",
    "sg:postcode":"91100",
    "sg:province":"Trapani",
    "wof:name":"Giacalone Nicolo'",
    "wof:placetype":"venue"
},
  "geometry": {"coordinates":[12.552751,37.91608],"type":"Point"}
}