{
  "type": "Feature",
  "properties": {
    "iso:country":"IT",
    "sg:address":"86039 Termoli",
    "sg:city":"Termoli",
    "sg:orig_category":"Autofficine E Centri Assistenza",
    "sg:phone":"+39 0875 85088",
    "sg:postcode":"86039",
    "sg:province":"Campobasso",
    "wof:name":"Iadanza Luciano",
    "wof:placetype":"venue"
},
  "geometry": {"coordinates":[14.674158,41.562511],"type":"Point"}
}