{
  "type": "Feature",
  "properties": {
    "iso:country":"IT",
    "sg:address":"13856 Vigliano Biellese",
    "sg:city":"Vigliano Biellese",
    "sg:orig_category":"Scuole E Servizi Scolastici. Servizi Per Lo Sport E Il Tempo Libero",
    "sg:phone":"+39 015 812 3166",
    "sg:postcode":"13856",
    "sg:province":"Biella",
    "wof:name":"Pgs Pallavolo Vigliano",
    "wof:placetype":"venue"
},
  "geometry": {"coordinates":[8.112238,45.56369],"type":"Point"}
}