{
  "type": "Feature",
  "properties": {
    "iso:country":"IT",
    "sg:address":"284, Via Gazzotti Luigi 41100 Modena",
    "sg:city":"Modena",
    "sg:classifiers":[
        {
            "category":"Wholesale",
            "subcategory":"Machinery & Supplies",
            "type":"Manufacturing & Wholesale Goods"
        }
    ],
    "sg:phone":"+39 39059284084",
    "sg:postcode":"41100",
    "sg:province":"Modena",
    "sg:tags":[
        "-",
        "agriculture",
        "equipment"
    ],
    "wof:name":"C.b.m. (s.p.a.)",
    "wof:placetype":"venue"
},
  "geometry": {"coordinates":[10.92522,44.647079],"type":"Point"}
}