{
  "type": "Feature",
  "properties": {
    "iso:country":"IT",
    "sg:address":"20144 Milano",
    "sg:city":"Milano",
    "sg:classifiers":[
        {
            "category":"Health Services",
            "subcategory":"Health Practitioner",
            "type":"Services"
        }
    ],
    "sg:phone":"+39 02 423 1768",
    "sg:postcode":"20144",
    "sg:province":"Milano",
    "sg:tags":[
        "medici"
    ],
    "wof:name":"Mandelli Massimo",
    "wof:placetype":"venue"
},
  "geometry": {"coordinates":[9.1566524506,45.4564437866],"type":"Point"}
}