{
  "type": "Feature",
  "properties": {
    "addr:full":"50/c, Via Croce 41014 Castelvetro Modena 41014",
    "addr:housenumber":"50 / c",
    "addr:postcode":"41014;41014",
    "addr:street":"Via Croce",
    "iso:country":"IT",
    "sg:address":"50/c, Via Croce 41014 Castelvetro",
    "sg:classifiers":[
        {
            "category":"Manufacturing",
            "subcategory":"Glass & Minerals",
            "type":"Manufacturing & Wholesale Goods"
        }
    ],
    "sg:phone":"+39 39059778411",
    "sg:postcode":"41014",
    "sg:province":"Modena",
    "sg:tags":[
        "building",
        "material"
    ],
    "wof:name":"Ceramiche Ascot Srl",
    "wof:placetype":"venue"
},
  "geometry": {"coordinates":[10.92522,44.647079],"type":"Point"}
}