{
  "type": "Feature",
  "properties": {
    "iso:country":"IT",
    "sg:address":"73047 Monteroni Di Lecce",
    "sg:city":"Monteroni di Lecce",
    "sg:orig_category":"Tempo Libero - Articoli E Forniture. Automobili E Mezzi Di Trasporto. Riparazione Dei Mezzi Di Trasporto",
    "sg:phone":"+39 0832 323080",
    "sg:postcode":"73047",
    "sg:province":"Lecce",
    "wof:name":"Cicli Manca Di Manca Silvio",
    "wof:placetype":"venue"
},
  "geometry": {"coordinates":[18.097595,40.32299],"type":"Point"}
}