{
  "type": "Feature",
  "properties": {
    "addr:full":"41, Via Alighieri Dante 20035 Lissone Lissone Milano 20035",
    "addr:postcode":"20035;20035",
    "addr:street":"Via Alighieri Dante",
    "iso:country":"IT",
    "sg:address":"41, Via Alighieri Dante 20035 Lissone",
    "sg:city":"Lissone",
    "sg:classifiers":[
        {
            "category":"Communications",
            "subcategory":"Television Station",
            "type":"Services"
        }
    ],
    "sg:phone":"+39 390 392 4461",
    "sg:postcode":"20035",
    "sg:province":"Milano",
    "sg:tags":[
        "audio-visual"
    ],
    "wof:name":"Formenti Seleco Spa",
    "wof:placetype":"venue"
},
  "geometry": {"coordinates":[9.188141,45.463688],"type":"Point"}
}