{
  "type": "Feature",
  "properties": {
    "addr:full":"10137 Torino Torino Torino 10137",
    "addr:postcode":"10137;10137",
    "iso:country":"IT",
    "sg:address":"10137 Torino",
    "sg:city":"Torino",
    "sg:classifiers":[
        {
            "category":"Shopping",
            "subcategory":"Bicycles & Sporting Goods",
            "type":"Retail Goods"
        }
    ],
    "sg:phone":"+39 011 311 3178",
    "sg:postcode":"10137",
    "sg:province":"Torino",
    "sg:tags":[
        "tempo",
        "lo",
        "-",
        "libero",
        "per",
        "servizi",
        "forniture",
        "articoli",
        "e",
        "sport",
        "il"
    ],
    "wof:name":"A Nord Ovest Ascaniosub Store Di Scarano Massimo",
    "wof:placetype":"venue"
},
  "geometry": {"coordinates":[7.633161,45.036667],"type":"Point"}
}