{
  "type": "Feature",
  "properties": {
    "addr:full":"37063 Isola Della Scala Isola della Scala Verona 37063",
    "addr:postcode":"37063;37063",
    "addr:street":"Scala Verona",
    "iso:country":"IT",
    "sg:address":"37063 Isola Della Scala",
    "sg:city":"Isola della Scala",
    "sg:classifiers":[
        {
            "category":"Restaurant",
            "type":"Food & Drink"
        }
    ],
    "sg:phone":"+39 045 663 0882",
    "sg:postcode":"37063",
    "sg:province":"Verona",
    "sg:tags":[
        "auxiliary",
        "entertainment",
        "premises",
        "related",
        "catering",
        "similar",
        "public",
        "restaurants"
    ],
    "wof:name":"Risosteria Biffi",
    "wof:placetype":"venue"
},
  "geometry": {"coordinates":[11.006858,45.273132],"type":"Point"}
}