{
  "type": "Feature",
  "properties": {
    "iso:country":"IT",
    "sg:address":"31056 Roncade",
    "sg:city":"Roncade",
    "sg:orig_category":"Sport And Leisure, Services. Tourism, Services. Motor Vehicles, Auxiliary Services. Transport, Auxiliary Services",
    "sg:phone":"+39 0422 707113",
    "sg:postcode":"31056",
    "sg:province":"Treviso",
    "sg:website":"http://www.vianellogiuseppe.it",
    "wof:name":"Vianello Giuseppe",
    "wof:placetype":"venue"
},
  "geometry": {"coordinates":[12.386034,45.638996],"type":"Point"}
}