{
  "type": "Feature",
  "properties": {
    "iso:country":"IT",
    "sg:address":"17, V. Cascina Girola 21040 Uboldo",
    "sg:city":"Uboldo",
    "sg:classifiers":[
        {
            "category":"Real Estate",
            "subcategory":"Surveying",
            "type":"Services"
        }
    ],
    "sg:phone":"+39 02 9678 1454",
    "sg:postcode":"21040",
    "sg:province":"Varese",
    "sg:tags":[
        "equipment",
        "material",
        "good",
        "-",
        "handling"
    ],
    "sg:website":"http://www.grupollastri.com",
    "wof:name":"Gru Pollastri Srl",
    "wof:placetype":"venue"
},
  "geometry": {"coordinates":[9.031157,45.61779],"type":"Point"}
}