{
  "type": "Feature",
  "properties": {
    "iso:country":"IT",
    "sg:address":"Via Sottomori 710 37020 Volargne",
    "sg:city":"Volargne",
    "sg:classifiers":[
        {
            "category":"Juice Bar",
            "subcategory":"None",
            "type":"Food & Drink"
        }
    ],
    "sg:phone":"+39 045 686 1351",
    "sg:postcode":"37020",
    "sg:province":"Verona",
    "sg:tags":[
        "granite",
        "slab"
    ],
    "wof:name":"Marmi Vicenzi Spa",
    "wof:placetype":"venue"
},
  "geometry": {"coordinates":[10.817053,45.54089],"type":"Point"}
}