{
  "type": "Feature",
  "properties": {
    "iso:country":"IT",
    "sg:address":"20089 Rozzano",
    "sg:city":"Rozzano",
    "sg:orig_category":"Cine-foto-ottica",
    "sg:phone":"+39 02 824 1021",
    "sg:postcode":"20089",
    "sg:province":"Milano",
    "wof:name":"Rowi Italiana (s.r.l.)",
    "wof:placetype":"venue"
},
  "geometry": {"coordinates":[9.147222,45.385002],"type":"Point"}
}