{
  "type": "Feature",
  "properties": {
    "addr:full":"5/a, V. Valle Molini37060 Custoza Verona 37060",
    "addr:housenumber":"5 / a;molini37060",
    "addr:postcode":"37060",
    "addr:street":"V. Valle",
    "iso:country":"IT",
    "sg:address":"5/a, V. Valle Molini37060 Custoza",
    "sg:classifiers":[
        {
            "category":"Food & Beverages",
            "subcategory":"Groceries & Convenience Stores",
            "type":"Retail Goods"
        }
    ],
    "sg:phone":"+39 045 630 9000",
    "sg:postcode":"37060",
    "sg:province":"Verona",
    "sg:tags":[
        "drink"
    ],
    "sg:website":"http://www.cantinaimolini.com:ws_end: :mark:ws:http://www.paginegialle.it/imolini",
    "wof:name":"Cantina I Molini",
    "wof:placetype":"venue"
},
  "geometry": {"coordinates":[10.788004,45.3731],"type":"Point"}
}