{
  "type": "Feature",
  "properties": {
    "iso:country":"IT",
    "sg:address":"131, Via Orazio 65128 Pescara",
    "sg:city":"Pescara",
    "sg:classifiers":[
        {
            "category":"Food & Beverages",
            "subcategory":"Groceries & Convenience Stores",
            "type":"Retail Goods"
        }
    ],
    "sg:phone":"+39 39085690545",
    "sg:postcode":"65128",
    "sg:province":"Pescara",
    "sg:tags":[
        "product",
        "related"
    ],
    "wof:name":"De Cecco (s.p.a.)",
    "wof:placetype":"venue"
},
  "geometry": {"coordinates":[14.2121973038,42.4585533142],"type":"Point"}
}