{
  "type": "Feature",
  "properties": {
    "addr:full":"20094 Corsico Corsico Milano 20094",
    "addr:postcode":"20094;20094",
    "iso:country":"IT",
    "sg:address":"20094 Corsico",
    "sg:city":"Corsico",
    "sg:orig_category":"Abbigliamento Industria - Macchine Ed Attrezzature",
    "sg:phone":"+39 02 440 9137",
    "sg:postcode":"20094",
    "sg:province":"Milano",
    "wof:name":"B. Invernizzi Snc",
    "wof:placetype":"venue"
},
  "geometry": {"coordinates":[9.117037,45.434963],"type":"Point"}
}