{
  "type": "Feature",
  "properties": {
    "addr:full":"22070 Cagno Cagno Como 22070",
    "addr:postcode":"22070;22070",
    "iso:country":"IT",
    "sg:address":"22070 Cagno",
    "sg:city":"Cagno",
    "sg:orig_category":"Sport - Articoli E Forniture",
    "sg:postcode":"22070",
    "sg:province":"Como",
    "wof:name":"Esche Rene' Italia (s.r.l.)",
    "wof:placetype":"venue"
},
  "geometry": {"coordinates":[8.924195,45.807533],"type":"Point"}
}