{
  "type": "Feature",
  "properties": {
    "iso:country":"IT",
    "sg:address":"20125 Milano",
    "sg:city":"Milano",
    "sg:orig_category":"Marmo, Pietre Ed Affini. Arte Ed Artigianato Artistico",
    "sg:phone":"+39 02 6707 4068",
    "sg:postcode":"20125",
    "sg:province":"Milano",
    "wof:name":"Accademia Del Mosaico Milano",
    "wof:placetype":"venue"
},
  "geometry": {"coordinates":[9.205497,45.493526],"type":"Point"}
}