{
  "type": "Feature",
  "properties": {
    "addr:full":"Via Dante 36 21050 Cairate Cairate Varese 21050",
    "addr:housenumber":"36",
    "addr:postcode":"21050;21050",
    "addr:street":"Via Dante",
    "iso:country":"IT",
    "sg:address":"Via Dante 36 21050 Cairate",
    "sg:city":"Cairate",
    "sg:classifiers":[
        {
            "category":"Utilities",
            "subcategory":"Refuse",
            "type":"Services"
        }
    ],
    "sg:phone":"+39 0331 360920",
    "sg:postcode":"21050",
    "sg:province":"Varese",
    "sg:tags":[
        "feather",
        "pillow",
        "duvet"
    ],
    "wof:name":"A. Molina E C. S.p.a",
    "wof:placetype":"venue"
},
  "geometry": {"coordinates":[8.872908,45.688404],"type":"Point"}
}