{
  "type": "Feature",
  "properties": {
    "iso:country":"IT",
    "sg:address":"63, Via Direttissima Del Conero 60021 Camerano",
    "sg:city":"Camerano",
    "sg:classifiers":[
        {
            "category":"Manufacturing",
            "subcategory":"Paper Products",
            "type":"Manufacturing & Wholesale Goods"
        }
    ],
    "sg:phone":"+39 390 719 5130",
    "sg:postcode":"60021",
    "sg:province":"Ancona",
    "sg:tags":[
        "cardboard"
    ],
    "wof:name":"Ondulato Adriatico S.r.l.",
    "wof:placetype":"venue"
},
  "geometry": {"coordinates":[13.5401363373,43.5142974854],"type":"Point"}
}