{
  "type": "Feature",
  "properties": {
    "iso:country":"IT",
    "sg:address":"Carige 58011 Capalbio",
    "sg:city":"Capalbio",
    "sg:classifiers":[
        {
            "category":"Food & Beverages",
            "subcategory":"Groceries & Convenience Stores",
            "type":"Retail Goods"
        }
    ],
    "sg:phone":"+39 0564 890396",
    "sg:postcode":"58011",
    "sg:province":"Grosseto",
    "sg:tags":[
        "drink"
    ],
    "wof:name":"Cantina Sociale Cooperativa",
    "wof:placetype":"venue"
},
  "geometry": {"coordinates":[11.42797,42.430431],"type":"Point"}
}