{
  "type": "Feature",
  "properties": {
    "iso:country":"IT",
    "sg:address":"20143 Milano",
    "sg:city":"Milano",
    "sg:orig_category":"Calzature, Pelletterie E Pelli. Servizi E Lavori Per Abbigliamento E Pelletterie",
    "sg:phone":"+39 02 5810 4029",
    "sg:postcode":"20143",
    "sg:province":"Milano",
    "wof:name":"Pizzino Giuseppe",
    "wof:placetype":"venue"
},
  "geometry": {"coordinates":[9.172457,45.45116],"type":"Point"}
}