{
  "type": "Feature",
  "properties": {
    "addr:full":"25032 Chiari Chiari Brescia 25032",
    "addr:postcode":"25032;25032",
    "iso:country":"IT",
    "sg:address":"25032 Chiari",
    "sg:city":"Chiari",
    "sg:orig_category":"Acciaierie E Fonderie. Arte Ed Artigianato Artistico",
    "sg:phone":"+39 030 700 0340",
    "sg:postcode":"25032",
    "sg:province":"Brescia",
    "wof:name":"Fonderie Bosetti S.r.l.",
    "wof:placetype":"venue"
},
  "geometry": {"coordinates":[9.947044,45.544937],"type":"Point"}
}