{
  "type": "Feature",
  "properties": {
    "addr:full":"24, Via Pioga Sud 35011 Campodarsego Campodarsego Padova 35011",
    "addr:postcode":"35011;35011",
    "addr:street":"Via Pioga Sud",
    "iso:country":"IT",
    "sg:address":"24, Via Pioga Sud 35011 Campodarsego",
    "sg:city":"Campodarsego",
    "sg:classifiers":[
        {
            "category":"Manufacturing",
            "subcategory":"Rubber & Plastics",
            "type":"Manufacturing & Wholesale Goods"
        }
    ],
    "sg:phone":"+39 049 556 4166",
    "sg:postcode":"35011",
    "sg:province":"Padova",
    "wof:name":"Nuova Ume Veneto (s.r.l.)",
    "wof:placetype":"venue"
},
  "geometry": {"coordinates":[11.8765888214,45.4095687866],"type":"Point"}
}