{
  "type": "Feature",
  "properties": {
    "addr:full":"21, Via Loria 36022 Cassola Cassola Vicenza 36022",
    "addr:postcode":"36022;36022",
    "addr:street":"Via Loria",
    "iso:country":"IT",
    "sg:address":"21, Via Loria 36022 Cassola",
    "sg:city":"Cassola",
    "sg:classifiers":[
        {
            "category":"Autos & Motor Vehicles",
            "subcategory":"Automobile Sales",
            "type":"Retail Goods"
        }
    ],
    "sg:phone":"+39 0424 533275",
    "sg:postcode":"36022",
    "sg:province":"Vicenza",
    "sg:tags":[
        "equipment",
        "transport"
    ],
    "wof:name":"Viero (s.r.l.)",
    "wof:placetype":"venue"
},
  "geometry": {"coordinates":[11.800226,45.732662],"type":"Point"}
}