{
  "type": "Feature",
  "properties": {
    "iso:country":"IT",
    "sg:address":"00183 Roma",
    "sg:city":"Roma",
    "sg:orig_category":"Ospedali E Servizi Sanitari",
    "sg:phone":"+39 06 700 5552",
    "sg:postcode":"00183",
    "sg:province":"Roma",
    "wof:name":"Messana S.r.l.",
    "wof:placetype":"venue"
},
  "geometry": {"coordinates":[12.502488,41.881283],"type":"Point"}
}