{
  "type": "Feature",
  "properties": {
    "iso:country":"IT",
    "sg:address":"Via Spada Cenami 6/8; Massarosa; 55050",
    "sg:classifiers":[
        {
            "category":"Banks & Credit Unions",
            "subcategory":"Bank",
            "type":"Services"
        }
    ],
    "sg:phone":"+39 0584 937373",
    "wof:name":"Cassa Di Risparmio Di Carrara Spa",
    "wof:placetype":"venue"
},
  "geometry": {"coordinates":[10.342215,43.870274],"type":"Point"}
}