{
  "type": "Feature",
  "properties": {
    "addr:full":"00125 Roma Roma Roma 00125",
    "addr:postcode":"00125;00125",
    "iso:country":"IT",
    "sg:address":"00125 Roma",
    "sg:city":"Roma",
    "sg:orig_category":"Abbigliamento Esterno, Maglierie E Pelliccerie. Shopping",
    "sg:phone":"+39 06 509 0154",
    "sg:postcode":"00125",
    "sg:province":"Roma",
    "wof:name":"Marino E.",
    "wof:placetype":"venue"
},
  "geometry": {"coordinates":[12.367993,41.756123],"type":"Point"}
}