{
  "type": "Feature",
  "properties": {
    "iso:country":"IT",
    "sg:address":"47100 Forli'",
    "sg:city":"Rovere",
    "sg:orig_category":"Abbigliamento Esterno, Maglierie E Pelliccerie. Servizi E Lavori Per Abbigliamento E Pelletterie",
    "sg:phone":"+39 0543 478000",
    "sg:postcode":"47100",
    "sg:province":"Forl\u00ec-Cesena",
    "wof:name":"Abir Creazioni Di Ferrero S.",
    "wof:placetype":"venue"
},
  "geometry": {"coordinates":[11.980991,44.200287],"type":"Point"}
}