{
  "type": "Feature",
  "properties": {
    "iso:country":"IT",
    "sg:address":"23020 Montagna In Valtellina",
    "sg:city":"Montagna in Valtellina",
    "sg:orig_category":"Campeggio. Automobili E Mezzi Di Trasporto",
    "sg:phone":"+39 0342 200336",
    "sg:postcode":"23020",
    "sg:province":"Sondrio",
    "wof:name":"Eurocar Srl",
    "wof:placetype":"venue"
},
  "geometry": {"coordinates":[9.902822,46.169914],"type":"Point"}
}