{
  "type": "Feature",
  "properties": {
    "addr:full":"54, Via S. Antonio 25065 Lumezzane Lumezzane Brescia 25065",
    "addr:postcode":"25065;25065",
    "addr:street":"Via S. Antonio",
    "iso:country":"IT",
    "sg:address":"54, Via S. Antonio 25065 Lumezzane",
    "sg:city":"Lumezzane",
    "sg:classifiers":[
        {
            "category":"Shopping",
            "type":"Retail Goods"
        }
    ],
    "sg:phone":"+39 030 897 0731",
    "sg:postcode":"25065",
    "sg:province":"Brescia",
    "sg:tags":[
        "finished",
        "-",
        "metallic"
    ],
    "wof:name":"Team Armaturen S.r.l.",
    "wof:placetype":"venue"
},
  "geometry": {"coordinates":[10.2210130692,45.6015319824],"type":"Point"}
}