{
  "type": "Feature",
  "properties": {
    "iso:country":"IT",
    "sg:address":"2, Via Caduti Pieve 25065 Lumezzane",
    "sg:city":"Lumezzane",
    "sg:classifiers":[
        {
            "category":"Shopping",
            "type":"Retail Goods"
        }
    ],
    "sg:phone":"+39 030 897 0600",
    "sg:postcode":"25065",
    "sg:province":"Brescia",
    "sg:tags":[
        "finished",
        "-",
        "metallic"
    ],
    "wof:name":"Tecnovielle (s.p.a.)",
    "wof:placetype":"venue"
},
  "geometry": {"coordinates":[10.2229642868,45.6011047363],"type":"Point"}
}