{
  "type": "Feature",
  "properties": {
    "addr:full":"Via Ghirlandaio 2/4 20096 Pioltello Pioltello Milano 20096",
    "addr:housenumber":"2 / 4",
    "addr:postcode":"20096;20096",
    "addr:street":"Via Ghirlandaio",
    "iso:country":"IT",
    "sg:address":"Via Ghirlandaio 2/4 20096 Pioltello",
    "sg:city":"Pioltello",
    "sg:classifiers":[
        {
            "category":"Building & Trades",
            "subcategory":"Construction",
            "type":"Services"
        }
    ],
    "sg:phone":"+39 02 9210 3459",
    "sg:postcode":"20096",
    "sg:province":"Milano",
    "sg:tags":[
        "valve"
    ],
    "sg:website":"www.galassiortolani.com",
    "wof:name":"Galassi & Ortolani Spa",
    "wof:placetype":"venue"
},
  "geometry": {"coordinates":[9.332683,45.509022],"type":"Point"}
}