{
  "type": "Feature",
  "properties": {
    "addr:full":"50025 Montespertoli Montespertoli Firenze 50025",
    "addr:postcode":"50025;50025",
    "iso:country":"IT",
    "sg:address":"50025 Montespertoli",
    "sg:city":"Montespertoli",
    "sg:orig_category":"Enoteche E Vendita Vini",
    "sg:phone":"+39 0571 609519",
    "sg:postcode":"50025",
    "sg:province":"Firenze",
    "wof:name":"Conti Romolo & Figli Sas",
    "wof:placetype":"venue"
},
  "geometry": {"coordinates":[11.048549,43.655426],"type":"Point"}
}