{
  "type": "Feature",
  "properties": {
    "iso:country":"IT",
    "sg:address":"00131 Roma",
    "sg:city":"Roma",
    "sg:orig_category":"Banche E Servizi Finanziari. Avvocati, Notai E Servizi Legali",
    "sg:phone":"+39 06 417261",
    "sg:postcode":"00131",
    "sg:province":"Roma",
    "wof:name":"Intellcredit Srl",
    "wof:placetype":"venue"
},
  "geometry": {"coordinates":[12.609928,41.93214],"type":"Point"}
}