{
  "type": "Feature",
  "properties": {
    "iso:country":"IT",
    "sg:address":"Contrada Larciano 63020 Monte Vidon Corrado",
    "sg:city":"Monte Vidon Corrado",
    "sg:classifiers":[
        {
            "category":"Personal",
            "subcategory":"Shoe Repair & Shine",
            "type":"Services"
        }
    ],
    "sg:phone":"+39 0734 759585",
    "sg:postcode":"63020",
    "sg:province":"Ascoli Piceno",
    "sg:tags":[
        "leather"
    ],
    "wof:name":"Tronelli Renato",
    "wof:placetype":"venue"
},
  "geometry": {"coordinates":[13.474747,43.124035],"type":"Point"}
}