{
  "type": "Feature",
  "properties": {
    "iso:country":"IT",
    "sg:address":"10143 Torino",
    "sg:city":"Torino",
    "sg:orig_category":"Elettronica Professionale E Di Consumo. Musica. Accessori Dei Mezzi Di Trasporto",
    "sg:phone":"+39 011 776 4741",
    "sg:postcode":"10143",
    "sg:province":"Torino",
    "wof:name":"Stereo Service Snc",
    "wof:placetype":"venue"
},
  "geometry": {"coordinates":[7.646424,45.076653],"type":"Point"}
}