{
  "type": "Feature",
  "properties": {
    "addr:full":"19, V. Legnano 20020 Robecchetto Con Induno Robecchetto con Induno Milano 20020",
    "addr:housenumber":"19",
    "addr:postcode":"20020;20020",
    "addr:street":"V. Legnano;Con Induno",
    "iso:country":"IT",
    "sg:address":"19, V. Legnano 20020 Robecchetto Con Induno",
    "sg:city":"Robecchetto con Induno",
    "sg:classifiers":[
        {
            "category":"Personal",
            "subcategory":"Shoe Repair & Shine",
            "type":"Services"
        }
    ],
    "sg:phone":"+39 0331 875895",
    "sg:postcode":"20020",
    "sg:province":"Milano",
    "sg:tags":[
        "leather"
    ],
    "sg:website":"http://www.paginegialle.it/lange",
    "wof:name":"Tessitura Lang\u00c8 Srl",
    "wof:placetype":"venue"
},
  "geometry": {"coordinates":[8.773232,45.529144],"type":"Point"}
}