{
  "type": "Feature",
  "properties": {
    "iso:country":"IT",
    "sg:address":"558, Via Provinciale Pisana 57121 Livorno",
    "sg:city":"Livorno",
    "sg:classifiers":[
        {
            "category":"Marine",
            "type":"Transportation"
        }
    ],
    "sg:phone":"+39 0586 429582",
    "sg:postcode":"57121",
    "sg:province":"Livorno",
    "sg:tags":[
        "transport",
        "sea"
    ],
    "wof:name":"Mediterranea Trasporti Srl",
    "wof:placetype":"venue"
},
  "geometry": {"coordinates":[10.340185,43.575478],"type":"Point"}
}