{
  "type": "Feature",
  "properties": {
    "iso:country":"IT",
    "sg:address":"3, Via Marconi 36050 Bolzano Vicentino",
    "sg:city":"Bolzano Vicentino",
    "sg:classifiers":[
        {
            "category":"Manufacturing",
            "subcategory":"Rubber & Plastics",
            "type":"Manufacturing & Wholesale Goods"
        }
    ],
    "sg:phone":"+39 0444 350785",
    "sg:postcode":"36050",
    "sg:province":"Vicenza",
    "wof:name":"Pieffe Plast (s.r.l.)",
    "wof:placetype":"venue"
},
  "geometry": {"coordinates":[11.6406002045,45.5934143066],"type":"Point"}
}