{
  "type": "Feature",
  "properties": {
    "iso:country":"IT",
    "sg:address":"20133 Milano",
    "sg:city":"Milano",
    "sg:orig_category":"Servizi E Lavori Per Abbigliamento E Pelletterie",
    "sg:phone":"+39 02 266 3772",
    "sg:postcode":"20133",
    "sg:province":"Milano",
    "wof:name":"Celli Maria",
    "wof:placetype":"venue"
},
  "geometry": {"coordinates":[9.23659,45.48288],"type":"Point"}
}