{
  "type": "Feature",
  "properties": {
    "addr:full":"60010 Ostra Vetere Ostra Ancona 60010",
    "addr:postcode":"60010;60010",
    "iso:country":"IT",
    "sg:address":"60010 Ostra Vetere",
    "sg:city":"Ostra",
    "sg:orig_category":"Utensili Meccanici E Materiali",
    "sg:phone":"+39 071 964328",
    "sg:postcode":"60010",
    "sg:province":"Ancona",
    "wof:name":"Modelleria G.r. Snc",
    "wof:placetype":"venue"
},
  "geometry": {"coordinates":[13.060962,43.605366],"type":"Point"}
}