{
  "type": "Feature",
  "properties": {
    "iso:country":"IT",
    "sg:address":"28041 Arona",
    "sg:city":"Arona",
    "sg:orig_category":"Informatica - Consulenza E Servizi. Automazione E Macchine Per Ufficio. Servizi Ausiliari Di Analisi, Controllo E Ricerca. Servizi Per Aziende, Manifestazioni E Supporto Agli Scambi Commerciali",
    "sg:phone":"+39 0322 240759",
    "sg:postcode":"28041",
    "sg:province":"Novara",
    "sg:website":"http://www.newdata.it",
    "wof:name":"New Data Systems Srl",
    "wof:placetype":"venue"
},
  "geometry": {"coordinates":[8.556936,45.76115],"type":"Point"}
}