{
  "type": "Feature",
  "properties": {
    "iso:country":"IT",
    "sg:address":"34/b, Via Trento 26044 Grontardo",
    "sg:city":"Grontardo",
    "sg:classifiers":[
        {
            "category":"Shopping",
            "subcategory":"Computers & Home Electronics",
            "type":"Retail Goods"
        }
    ],
    "sg:phone":"+39 39037289122",
    "sg:postcode":"26044",
    "sg:province":"Cremona",
    "sg:tags":[
        "electronic",
        "electrical",
        "equipment"
    ],
    "wof:name":"Telestar (s.n.c.)",
    "wof:placetype":"venue"
},
  "geometry": {"coordinates":[10.128023,45.167507],"type":"Point"}
}