{
  "type": "Feature",
  "properties": {
    "iso:country":"IT",
    "sg:address":"51, Via Primo Settembre 98122 Messina",
    "sg:city":"Messina",
    "sg:classifiers":[
        {
            "category":"Shopping",
            "subcategory":"Clothing, Apparel, & Fashions",
            "type":"Retail Goods"
        }
    ],
    "sg:phone":"+39 39090673623",
    "sg:postcode":"98122",
    "sg:province":"Messina",
    "sg:tags":[
        "clothes"
    ],
    "wof:name":"Fatima S.r.l.",
    "wof:placetype":"venue"
},
  "geometry": {"coordinates":[15.55621,38.190193],"type":"Point"}
}