{
  "type": "Feature",
  "properties": {
    "addr:full":"13, Via G. Rossa 46020 Pegognaga Pegognaga Mantova 46020",
    "addr:postcode":"46020;46020",
    "addr:street":"Via G. Rossa",
    "iso:country":"IT",
    "sg:address":"13, Via G. Rossa 46020 Pegognaga",
    "sg:city":"Pegognaga",
    "sg:classifiers":[
        {
            "category":"Shopping",
            "subcategory":"Clothing, Apparel, & Fashions",
            "type":"Retail Goods"
        }
    ],
    "sg:phone":"+39 0376 550240",
    "sg:postcode":"46020",
    "sg:province":"Mantova",
    "sg:tags":[
        "clothes"
    ],
    "wof:name":"Confezioni Lory",
    "wof:placetype":"venue"
},
  "geometry": {"coordinates":[10.797698,45.160366],"type":"Point"}
}