{
  "type": "Feature",
  "properties": {
    "addr:full":"28040 Oleggio Castello Oleggio Castello Novara 28040",
    "addr:postcode":"28040;28040",
    "iso:country":"IT",
    "sg:address":"28040 Oleggio Castello",
    "sg:city":"Oleggio Castello",
    "sg:orig_category":"Macchine, Impianti Ed Attrezzature Per Abbigliamento E Pelletterie. Macchine E Impianti Per Attivita' Commerciali Ed Artigianali",
    "sg:phone":"+39 0322 538578",
    "sg:postcode":"28040",
    "sg:province":"Novara",
    "wof:name":"Unica Snc Di Belluscio E Gambaro",
    "wof:placetype":"venue"
},
  "geometry": {"coordinates":[8.527649,45.748348],"type":"Point"}
}