{
  "type": "Feature",
  "properties": {
    "iso:country":"IT",
    "sg:address":"Via Amendola 2/h 40011 Anzola Dell'emilia",
    "sg:orig_category":"Worms",
    "sg:phone":"+39 051 734600",
    "sg:postcode":"40011",
    "sg:province":"Bologna",
    "sg:website":"www.meccanicawp.com",
    "wof:name":"Meccanica W.p. Di Dallan Roberto & C. Snc",
    "wof:placetype":"venue"
},
  "geometry": {"coordinates":[11.222018,44.543747],"type":"Point"}
}