{
  "type": "Feature",
  "properties": {
    "iso:country":"IT",
    "sg:address":"65125 Pescara",
    "sg:city":"Pescara",
    "sg:orig_category":"Istituti Di Bellezza",
    "sg:phone":"+39 085 73675",
    "sg:postcode":"65125",
    "sg:province":"Pescara",
    "wof:name":"Mda Snc",
    "wof:placetype":"venue"
},
  "geometry": {"coordinates":[14.195603,42.478848],"type":"Point"}
}