{
  "type": "Feature",
  "properties": {
    "iso:country":"IT",
    "sg:address":"65015 Montesilvano",
    "sg:city":"Montesilvano",
    "sg:orig_category":"Discoteche, Locali Notturni E Sale Da Ballo",
    "sg:phone":"+39 085 445 1625",
    "sg:postcode":"65015",
    "sg:province":"Pescara",
    "wof:name":"Discoteca Florence New Club",
    "wof:placetype":"venue"
},
  "geometry": {"coordinates":[14.156824,42.510845],"type":"Point"}
}