{
  "type": "Feature",
  "properties": {
    "iso:country":"IT",
    "sg:address":"11, Via Delle Industrie 30020 Fossalta Di Piave",
    "sg:city":"Fossalta di Piave",
    "sg:classifiers":[
        {
            "category":"Manufacturing",
            "subcategory":"Metals",
            "type":"Manufacturing & Wholesale Goods"
        }
    ],
    "sg:phone":"+39 39042167200",
    "sg:postcode":"30020",
    "sg:province":"Venezia",
    "sg:tags":[
        "processing"
    ],
    "wof:name":"Ossida (s.r.l.)",
    "wof:placetype":"venue"
},
  "geometry": {"coordinates":[12.5017976761,45.6442070007],"type":"Point"}
}