{
  "type": "Feature",
  "properties": {
    "iso:country":"IT",
    "sg:address":"90123 Palermo",
    "sg:city":"Palermo",
    "sg:orig_category":"Trasporti E Spedizioni Merci",
    "sg:phone":"+39 091 617 0034",
    "sg:postcode":"90123",
    "sg:province":"Palermo",
    "wof:name":"Trenitalia Spa - Direzione Zona Passeggeri Sicilia",
    "wof:placetype":"venue"
},
  "geometry": {"coordinates":[13.440869,38.077572],"type":"Point"}
}