{
  "type": "Feature",
  "properties": {
    "addr:full":"11, Via Ghisolfi Guareschi 43015 Noceto Noceto Parma 43015",
    "addr:postcode":"43015;43015",
    "addr:street":"Via Ghisolfi Guareschi",
    "iso:country":"IT",
    "sg:address":"11, Via Ghisolfi Guareschi 43015 Noceto",
    "sg:city":"Noceto",
    "sg:classifiers":[
        {
            "category":"Manufacturing",
            "subcategory":"Metals",
            "type":"Manufacturing & Wholesale Goods"
        }
    ],
    "sg:phone":"+39 0521 627721",
    "sg:postcode":"43015",
    "sg:province":"Parma",
    "sg:tags":[
        "processing"
    ],
    "wof:name":"Verilla S.r.l.",
    "wof:placetype":"venue"
},
  "geometry": {"coordinates":[10.3295478821,44.8078651428],"type":"Point"}
}