{
  "type": "Feature",
  "properties": {
    "iso:country":"IT",
    "sg:address":"Via Pace 94/a 40010 Padulle",
    "sg:city":"Padulle",
    "sg:classifiers":[
        {
            "category":"Shopping",
            "subcategory":"Clothing, Apparel, & Fashions",
            "type":"Retail Goods"
        }
    ],
    "sg:phone":"+39 051 828266",
    "sg:postcode":"40010",
    "sg:province":"Bologna",
    "sg:tags":[
        "leather",
        "clothing"
    ],
    "sg:website":"www.articosnc.it",
    "wof:name":"Artico Snc",
    "wof:placetype":"venue"
},
  "geometry": {"coordinates":[11.346481,44.494221],"type":"Point"}
}