{
  "type": "Feature",
  "properties": {
    "addr:full":"Z.i. - Loc. Le Capanne 05021 Acquasparta Acquasparta Terni 05021",
    "addr:postcode":"05021;05021",
    "addr:street":"Z.I. Loc. Le Capanne",
    "iso:country":"IT",
    "sg:address":"Z.i. - Loc. Le Capanne 05021 Acquasparta",
    "sg:city":"Acquasparta",
    "sg:classifiers":[
        {
            "category":"Manufacturing",
            "subcategory":"Glass & Minerals",
            "type":"Manufacturing & Wholesale Goods"
        }
    ],
    "sg:phone":"+39 0744 943180",
    "sg:postcode":"05021",
    "sg:province":"Terni",
    "wof:name":"Firenze Vetro Srl",
    "wof:placetype":"venue"
},
  "geometry": {"coordinates":[12.646781,42.560219],"type":"Point"}
}