{
  "type": "Feature",
  "properties": {
    "iso:country":"IT",
    "sg:address":"55, Strada Della Bonifica 64010 Controguerra",
    "sg:city":"Controguerra",
    "sg:classifiers":[
        {
            "category":"Manufacturing",
            "subcategory":"Metals",
            "type":"Manufacturing & Wholesale Goods"
        }
    ],
    "sg:phone":"+39 39086189578",
    "sg:postcode":"64010",
    "sg:province":"Teramo",
    "sg:tags":[
        "processing"
    ],
    "wof:name":"Metalcolor (s.r.l.)",
    "wof:placetype":"venue"
},
  "geometry": {"coordinates":[13.6985311508,42.6612701416],"type":"Point"}
}