{
  "type": "Feature",
  "properties": {
    "iso:country":"IT",
    "sg:address":"10128 Torino",
    "sg:city":"Torino",
    "sg:orig_category":"Studi E Consulenze Legali E Notarili. Avvocati, Notai E Servizi Legali. Professionisti - Studi E Servizi Ed Associazioni Di Interesse Aziendale",
    "sg:phone":"+39 011 581 3666",
    "sg:postcode":"10128",
    "sg:province":"Torino",
    "wof:name":"Studio Benessia Maccagno",
    "wof:placetype":"venue"
},
  "geometry": {"coordinates":[8.39892,45.462345],"type":"Point"}
}