{
  "type": "Feature",
  "properties": {
    "iso:country":"IT",
    "sg:address":"Via Marco Minghetti 17; Rome; 00187",
    "sg:classifiers":[
        {
            "category":"Industrial Area",
            "type":"Public Place"
        }
    ],
    "sg:phone":"+39 390 654 451",
    "sg:postcode":"00187",
    "sg:province":"Roma",
    "sg:tags":[
        "large",
        "private"
    ],
    "sg:website":"www.capitalia.it",
    "wof:name":"Capitalia S.p.a.",
    "wof:placetype":"venue"
},
  "geometry": {"coordinates":[12.4813289642,41.899887085],"type":"Point"}
}