{
  "type": "Feature",
  "properties": {
    "iso:country":"IT",
    "sg:address":"14, Via Pizzo Bernina 00141 Roma",
    "sg:city":"Roma",
    "sg:classifiers":[
        {
            "category":"Parking",
            "subcategory":"Lot",
            "type":"Transportation"
        }
    ],
    "sg:phone":"+39 39068292636",
    "sg:postcode":"00141",
    "sg:province":"Roma",
    "sg:tags":[
        "transport",
        "road"
    ],
    "wof:name":"Croce Bianca Italiana Srl",
    "wof:placetype":"venue"
},
  "geometry": {"coordinates":[12.540345,41.939045],"type":"Point"}
}