{
  "type": "Feature",
  "properties": {
    "addr:full":"74100 Taranto Taranto Taranto 74100",
    "addr:postcode":"74100;74100",
    "iso:country":"IT",
    "sg:address":"74100 Taranto",
    "sg:city":"Taranto",
    "sg:orig_category":"Servizi E Lavori Per Ecologia E Smaltimento Rifiuti",
    "sg:phone":"+39 099 730 2939",
    "sg:postcode":"74100",
    "sg:province":"Taranto",
    "wof:name":"So.fi.med. S.r.l.",
    "wof:placetype":"venue"
},
  "geometry": {"coordinates":[17.251005,40.459999],"type":"Point"}
}