{
  "type": "Feature",
  "properties": {
    "addr:full":"20037 Paderno Dugnano Paderno Dugnano Milano 20037",
    "addr:postcode":"20037;20037",
    "iso:country":"IT",
    "sg:address":"20037 Paderno Dugnano",
    "sg:city":"Paderno Dugnano",
    "sg:orig_category":"Apparecchiature Ed Attrezzature Meccaniche",
    "sg:phone":"+39 02 9904 8540",
    "sg:postcode":"20037",
    "sg:province":"Milano",
    "wof:name":"Maruflex Srl",
    "wof:placetype":"venue"
},
  "geometry": {"coordinates":[9.154222,45.56559],"type":"Point"}
}