{
  "type": "Feature",
  "properties": {
    "iso:country":"IT",
    "sg:address":"8, V. Dei Fabbri 25016 Ghedi",
    "sg:city":"Ghedi",
    "sg:classifiers":[
        {
            "category":"Food & Beverages",
            "subcategory":"Groceries & Convenience Stores",
            "type":"Retail Goods"
        }
    ],
    "sg:phone":"+39 030 903 2848",
    "sg:postcode":"25016",
    "sg:province":"Brescia",
    "sg:tags":[
        "drink"
    ],
    "sg:website":"http://www.tenuteformentini.com",
    "wof:name":"Tenute Formentini Dal 1917 Libero Formentini Srl",
    "wof:placetype":"venue"
},
  "geometry": {"coordinates":[10.290298,45.39608],"type":"Point"}
}