{
  "type": "Feature",
  "properties": {
    "iso:country":"IT",
    "sg:address":"80143 Napoli",
    "sg:city":"Napoli",
    "sg:orig_category":"Macchine E Forniture Per Arredamento E Industria Del Legno. Forniture Per Edilizia E Lavori Pubblici",
    "sg:phone":"+39 081 553 6049",
    "sg:postcode":"80143",
    "sg:province":"Napoli",
    "sg:website":"http://www.poliplastdangelo.com",
    "wof:name":"Poliplast Dangelo Srl",
    "wof:placetype":"venue"
},
  "geometry": {"coordinates":[14.312211,40.915291],"type":"Point"}
}