{
  "type": "Feature",
  "properties": {
    "addr:full":"40069 Zola Predosa Zola Bologna 40069",
    "addr:postcode":"40069;40069",
    "iso:country":"IT",
    "sg:address":"40069 Zola Predosa",
    "sg:city":"Zola",
    "sg:orig_category":"Carpenterie Metalliche",
    "sg:phone":"+39 051 758615",
    "sg:postcode":"40069",
    "sg:province":"Bologna",
    "wof:name":"Italmeccanica Srl",
    "wof:placetype":"venue"
},
  "geometry": {"coordinates":[11.233848,44.494183],"type":"Point"}
}