{
  "type": "Feature",
  "properties": {
    "addr:full":"243, Via Bastia 48017 Conselice Conselice Ravenna 48017",
    "addr:housenumber":"243",
    "addr:postcode":"48017;48017",
    "addr:street":"Via Bastia",
    "iso:country":"IT",
    "sg:address":"243, Via Bastia 48017 Conselice",
    "sg:city":"Conselice",
    "sg:classifiers":[
        {
            "category":"Food & Beverages",
            "subcategory":"Groceries & Convenience Stores",
            "type":"Retail Goods"
        }
    ],
    "sg:phone":"+39 39054580607",
    "sg:postcode":"48017",
    "sg:province":"Ravenna",
    "sg:tags":[
        "product",
        "related"
    ],
    "wof:name":"Pastificio Bacchini Di Bacchini Roberto & C. (s.n.",
    "wof:placetype":"venue"
},
  "geometry": {"coordinates":[11.8746433258,44.5613365173],"type":"Point"}
}