{
  "type": "Feature",
  "properties": {
    "iso:country":"IT",
    "sg:address":"Via Della Stazione 137; Appiano; 39057",
    "sg:classifiers":[
        {
            "category":"Banks & Credit Unions",
            "subcategory":"Bank",
            "type":"Services"
        }
    ],
    "sg:phone":"+39 0471 661616",
    "sg:postcode":"39057",
    "sg:province":"Bolzano/Bozen",
    "wof:name":"Banca Di Trento E Bolzano Spa",
    "wof:placetype":"venue"
},
  "geometry": {"coordinates":[11.264543,46.45446],"type":"Point"}
}