{
  "type": "Feature",
  "properties": {
    "iso:country":"IT",
    "sg:address":"Via Cecci, 1; Santa Maria Degli Angeli Pg",
    "sg:classifiers":[
        {
            "category":"Travel",
            "subcategory":"Travel Agent",
            "type":"Entertainment"
        }
    ],
    "wof:name":"Italian Center For Advanced Studies In Tourism",
    "wof:placetype":"venue"
},
  "geometry": {"coordinates":[12.590405,43.049896],"type":"Point"}
}