{
  "type": "Feature",
  "properties": {
    "addr:full":"55012 Capannori Capannori Lucca 55012",
    "addr:postcode":"55012;55012",
    "iso:country":"IT",
    "sg:address":"55012 Capannori",
    "sg:city":"Capannori",
    "sg:orig_category":"Prodotti Chimici Di Base",
    "sg:phone":"+39 0583 94416",
    "sg:postcode":"55012",
    "sg:province":"Lucca",
    "wof:name":"Martinelli Italo",
    "wof:placetype":"venue"
},
  "geometry": {"coordinates":[10.5275688171,43.8205223083],"type":"Point"}
}