{
  "type": "Feature",
  "properties": {
    "iso:country":"IT",
    "sg:address":"24, Via Avigliana 10040 Rivalta Di Torino",
    "sg:city":"Rivalta di Torino",
    "sg:classifiers":[
        {
            "category":"Manufacturing",
            "subcategory":"Metals",
            "type":"Manufacturing & Wholesale Goods"
        }
    ],
    "sg:phone":"+39 011 903 2797",
    "sg:postcode":"10040",
    "sg:province":"Torino",
    "sg:tags":[
        "processing"
    ],
    "wof:name":"F.lli Peirano S.p.a.",
    "wof:placetype":"venue"
},
  "geometry": {"coordinates":[7.584654808,45.0237503052],"type":"Point"}
}