{
  "type": "Feature",
  "properties": {
    "addr:full":"41056 Savignano Sul Panaro Savignano sul Panaro Modena 41056",
    "addr:postcode":"41056;41056",
    "iso:country":"IT",
    "sg:address":"41056 Savignano Sul Panaro",
    "sg:city":"Savignano sul Panaro",
    "sg:orig_category":"Metalli E Leghe",
    "sg:phone":"+39 059 796339",
    "sg:postcode":"41056",
    "sg:province":"Modena",
    "wof:name":"Del Carlo Ivo",
    "wof:placetype":"venue"
},
  "geometry": {"coordinates":[11.0579471588,44.5095977783],"type":"Point"}
}