{
  "type": "Feature",
  "properties": {
    "iso:country":"IT",
    "sg:address":"Largo Sciacca 10/12; Patti; 98066",
    "sg:city":"Patti",
    "sg:classifiers":[
        {
            "category":"Banks & Credit Unions",
            "subcategory":"Bank",
            "type":"Services"
        }
    ],
    "sg:phone":"+39 0941 22806",
    "sg:postcode":"98066",
    "sg:province":"Messina",
    "wof:name":"Banco Di Sicilia Spa",
    "wof:placetype":"venue"
},
  "geometry": {"coordinates":[15.035997,38.13279],"type":"Point"}
}