{
  "type": "Feature",
  "properties": {
    "addr:full":"Contrada Donna Mazza 88046 Lamezia Terme Lamezia Terme Catanzaro 88046",
    "addr:postcode":"88046;88046",
    "addr:street":"Contrada Donna Mazza",
    "iso:country":"IT",
    "sg:address":"Contrada Donna Mazza 88046 Lamezia Terme",
    "sg:city":"Lamezia Terme",
    "sg:classifiers":[
        {
            "category":"Manufacturing",
            "subcategory":"Printing",
            "type":"Manufacturing & Wholesale Goods"
        }
    ],
    "sg:phone":"+39 0968 462509",
    "sg:postcode":"88046",
    "sg:province":"Catanzaro",
    "sg:tags":[
        "publishing"
    ],
    "wof:name":"C. & C. Arti Grafiche Spa",
    "wof:placetype":"venue"
},
  "geometry": {"coordinates":[16.5876789093,38.9105987549],"type":"Point"}
}