{
  "type": "Feature",
  "properties": {
    "iso:country":"IT",
    "sg:address":"52, Via Mazzini 46043 Castiglione Delle Stiviere",
    "sg:city":"Castiglione delle Stiviere",
    "sg:classifiers":[
        {
            "category":"Manufacturing",
            "subcategory":"Metals",
            "type":"Manufacturing & Wholesale Goods"
        }
    ],
    "sg:phone":"+39 0376 943911",
    "sg:postcode":"46043",
    "sg:province":"Mantova",
    "sg:tags":[
        "metallurgy",
        "metalworking"
    ],
    "wof:name":"Ferramenta Cima Spa",
    "wof:placetype":"venue"
},
  "geometry": {"coordinates":[10.7976980209,45.1603660583],"type":"Point"}
}