{
  "type": "Feature",
  "properties": {
    "addr:full":"24, Via Roma 24020 Gorle Gorle Bergamo 24020",
    "addr:postcode":"24020;24020",
    "addr:street":"Via Roma",
    "iso:country":"IT",
    "sg:address":"24, Via Roma 24020 Gorle",
    "sg:city":"Gorle",
    "sg:classifiers":[
        {
            "category":"Shopping",
            "type":"Retail Goods"
        }
    ],
    "sg:phone":"+39 39035293580",
    "sg:postcode":"24020",
    "sg:province":"Bergamo",
    "sg:tags":[
        "finished",
        "-",
        "metallic"
    ],
    "wof:name":"Pagani Srl",
    "wof:placetype":"venue"
},
  "geometry": {"coordinates":[9.7037153244,45.7226638794],"type":"Point"}
}