{
  "type": "Feature",
  "properties": {
    "iso:country":"IT",
    "sg:address":"20124 Milano",
    "sg:city":"Milano",
    "sg:orig_category":"Abbigliamento - Produzione E Ingrosso",
    "sg:phone":"+39 02 6698 8289",
    "sg:postcode":"20124",
    "sg:province":"Milano",
    "sg:website":"http://www.calmarini.it",
    "wof:name":"Calmarini Srl",
    "wof:placetype":"venue"
},
  "geometry": {"coordinates":[9.201685,45.482941],"type":"Point"}
}