{
  "type": "Feature",
  "properties": {
    "iso:country":"IT",
    "sg:address":"Via Bourges 6 47100 Forli'",
    "sg:classifiers":[
        {
            "category":"Train Station",
            "subcategory":"Rail",
            "type":"Transportation"
        }
    ],
    "sg:phone":"+39 0543 480004",
    "sg:postcode":"47100",
    "sg:province":"Forl\u00ec-Cesena",
    "sg:tags":[
        "barrier"
    ],
    "sg:website":"www.steebitalia.it",
    "wof:name":"Steeb Italia Srl",
    "wof:placetype":"venue"
},
  "geometry": {"coordinates":[12.012815,44.189278],"type":"Point"}
}