{
  "type": "Feature",
  "properties": {
    "iso:country":"IT",
    "sg:address":"Ctr Cucullo",
    "sg:city":"Ortona",
    "sg:classifiers":[
        {
            "category":"Food & Beverages",
            "subcategory":"Supermarket",
            "type":"Retail Goods"
        }
    ],
    "sg:phone":"+39 085 905101",
    "sg:postcode":"66026",
    "sg:province":"Chieti",
    "sg:tags":[
        "flour",
        "organic"
    ],
    "sg:website":"www.molinoalimonti.com",
    "wof:name":"Molino Alimonti Spa",
    "wof:placetype":"venue"
},
  "geometry": {"coordinates":[14.167151,42.351791],"type":"Point"}
}