{
  "type": "Feature",
  "properties": {
    "iso:country":"IT",
    "sg:address":"20068 Peschiera Borromeo",
    "sg:city":"Peschiera Borromeo",
    "sg:orig_category":"Apparecchiature Ed Attrezzature Meccaniche",
    "sg:phone":"+39 02 547 0392",
    "sg:postcode":"20068",
    "sg:province":"Milano",
    "wof:name":"Bini Guido",
    "wof:placetype":"venue"
},
  "geometry": {"coordinates":[9.285974,45.429493],"type":"Point"}
}