{
  "type": "Feature",
  "properties": {
    "iso:country":"IT",
    "sg:address":"48, V. 7 Case 36061 Bassano Del Grappa",
    "sg:city":"Bassano del Grappa",
    "sg:classifiers":[
        {
            "category":"Home & Garden",
            "subcategory":"Home Furnishings",
            "type":"Retail Goods"
        }
    ],
    "sg:phone":"+39 0424 504478",
    "sg:postcode":"36061",
    "sg:province":"Vicenza",
    "sg:tags":[
        "household"
    ],
    "sg:website":"http://www.paginegialle.it/bassano-01",
    "wof:name":"Bassano International Srl",
    "wof:placetype":"venue"
},
  "geometry": {"coordinates":[11.756231,45.76746],"type":"Point"}
}