{
  "type": "Feature",
  "properties": {
    "addr:full":"31050 Vedelago Vedelago Treviso 31050",
    "addr:postcode":"31050;31050",
    "iso:country":"IT",
    "sg:address":"31050 Vedelago",
    "sg:city":"Vedelago",
    "sg:orig_category":"Forniture Per Abbigliamento E Pelletterie",
    "sg:phone":"+39 0423 452068",
    "sg:postcode":"31050",
    "sg:province":"Treviso",
    "wof:name":"Fasten Italia Srl",
    "wof:placetype":"venue"
},
  "geometry": {"coordinates":[12.0091152191,45.6646499634],"type":"Point"}
}