{
  "type": "Feature",
  "properties": {
    "iso:country":"IT",
    "sg:address":"Pizza Dei Giudici 3, Florence, Fi",
    "sg:classifiers":[
        {
            "category":"Banks & Credit Unions",
            "subcategory":"Bank",
            "type":"Services"
        }
    ],
    "wof:name":"Mercato Mobiliare Italia Centrale Spa",
    "wof:placetype":"venue"
},
  "geometry": {"coordinates":[11.256271,43.767826],"type":"Point"}
}