{
  "type": "Feature",
  "properties": {
    "iso:country":"IT",
    "sg:address":"20125 Milano",
    "sg:city":"Milano",
    "sg:orig_category":"Espositori, Displays E Articoli Pubblicitari Punto Vendita",
    "sg:phone":"+39 02 669 7667",
    "sg:postcode":"20125",
    "sg:province":"Milano",
    "wof:name":"La Plex Di Beretta Emilio Snc",
    "wof:placetype":"venue"
},
  "geometry": {"coordinates":[9.207193,45.49437],"type":"Point"}
}