{
  "type": "Feature",
  "properties": {
    "iso:country":"IT",
    "sg:address":"87, Via Strera 28047 Oleggio",
    "sg:city":"Oleggio",
    "sg:classifiers":[
        {
            "category":"Shopping",
            "subcategory":"Clothing, Apparel, & Fashions",
            "type":"Retail Goods"
        }
    ],
    "sg:phone":"+39 0321 960855",
    "sg:postcode":"28047",
    "sg:province":"Novara",
    "sg:tags":[
        "clothes"
    ],
    "wof:name":"Linea Verde S.n.c. Di De Tomasi & C.",
    "wof:placetype":"venue"
},
  "geometry": {"coordinates":[8.654281,45.59877],"type":"Point"}
}