{
  "type": "Feature",
  "properties": {
    "iso:country":"IT",
    "sg:address":"17, Via Soperga 20127 Milano",
    "sg:city":"Milano",
    "sg:classifiers":[
        {
            "category":"Manufacturing",
            "subcategory":"Motor Vehicles & Parts",
            "type":"Manufacturing & Wholesale Goods"
        }
    ],
    "sg:phone":"+39 39026690651",
    "sg:postcode":"20127",
    "sg:province":"Milano",
    "sg:tags":[
        "engine"
    ],
    "wof:name":"Marzorati (s.p.a.)",
    "wof:placetype":"venue"
},
  "geometry": {"coordinates":[9.209663,45.488071],"type":"Point"}
}