{
  "type": "Feature",
  "properties": {
    "addr:full":"20020 Busto Garolfo Busto Garolfo Milano 20020",
    "addr:postcode":"20020;20020",
    "iso:country":"IT",
    "sg:address":"20020 Busto Garolfo",
    "sg:city":"Busto Garolfo",
    "sg:classifiers":[
        {
            "category":"Health Services",
            "subcategory":"Health Practitioner",
            "type":"Services"
        }
    ],
    "sg:phone":"+39 0331 536645",
    "sg:postcode":"20020",
    "sg:province":"Milano",
    "sg:tags":[
        "medici"
    ],
    "wof:name":"Centro Alto Milanese Di Medicina Sportiva S.r.l.",
    "wof:placetype":"venue"
},
  "geometry": {"coordinates":[8.882233,45.552742],"type":"Point"}
}