{
  "type": "Feature",
  "properties": {
    "addr:full":"24040 Filago Filago Bergamo 24040",
    "addr:postcode":"24040;24040",
    "iso:country":"IT",
    "sg:address":"24040 Filago",
    "sg:city":"Filago",
    "sg:orig_category":"Servizi E Lavori Per Edilizia E Lavori Pubblici. Acqua, Luce, Gas E Societa' Di Esercizio Pubblico",
    "sg:phone":"+39 035 991168",
    "sg:postcode":"24040",
    "sg:province":"Bergamo",
    "wof:name":"S.i.a. Reti S.r.l.",
    "wof:placetype":"venue"
},
  "geometry": {"coordinates":[9.667855,45.699104],"type":"Point"}
}