{
  "type": "Feature",
  "properties": {
    "addr:full":"50065 Pontassieve Montebonello Firenze 50065",
    "addr:postcode":"50065;50065",
    "addr:street":"Montebonello",
    "iso:country":"IT",
    "sg:address":"50065 Pontassieve",
    "sg:city":"Montebonello",
    "sg:orig_category":"Falegnami",
    "sg:phone":"+39 055 839 7433",
    "sg:postcode":"50065",
    "sg:province":"Firenze",
    "sg:website":"http://www.mirriremo.com",
    "wof:name":"Mirri Remo & C. Snc",
    "wof:placetype":"venue"
},
  "geometry": {"coordinates":[11.4866676331,43.8306922913],"type":"Point"}
}