{
  "type": "Feature",
  "properties": {
    "addr:full":"58/11, Corso Bramante Torino Torino 10126",
    "addr:housenumber":"58 / 11",
    "addr:postcode":"10126",
    "addr:street":"Corso Bramante",
    "iso:country":"IT",
    "sg:address":"58/11, Corso Bramante",
    "sg:city":"Torino",
    "sg:classifiers":[
        {
            "category":"Utilities",
            "subcategory":"Electric",
            "type":"Services"
        }
    ],
    "sg:phone":"+39 011 630 5011",
    "sg:postcode":"10126",
    "sg:province":"Torino",
    "sg:tags":[
        "component",
        "electronic"
    ],
    "wof:name":"Kopa Engineering S.r.l.",
    "wof:placetype":"venue"
},
  "geometry": {"coordinates":[7.686619,45.07056],"type":"Point"}
}