{
  "type": "Feature",
  "properties": {
    "iso:country":"IT",
    "sg:address":"15048 Valenza",
    "sg:city":"Valenza",
    "sg:orig_category":"Gioielleria E Oreficeria - Lavorazione E Ingrosso",
    "sg:phone":"+39 0131 947888",
    "sg:postcode":"15048",
    "sg:province":"Alessandria",
    "wof:name":"Griff Srl",
    "wof:placetype":"venue"
},
  "geometry": {"coordinates":[8.642259,45.008583],"type":"Point"}
}