{
  "type": "Feature",
  "properties": {
    "addr:full":"55, Via S. Clemente 20023 Cerro Maggiore Cerro Maggiore Milano 20023",
    "addr:housenumber":"20023",
    "addr:postcode":"20023",
    "addr:street":"Via S. Clemente",
    "iso:country":"IT",
    "sg:address":"55, Via S. Clemente 20023 Cerro Maggiore",
    "sg:city":"Cerro Maggiore",
    "sg:classifiers":[
        {
            "category":"Shopping",
            "type":"Retail Goods"
        }
    ],
    "sg:phone":"+39 0331 519200",
    "sg:postcode":"20023",
    "sg:province":"Milano",
    "sg:tags":[
        "finished",
        "-",
        "metallic"
    ],
    "wof:name":"Officina Fonderia Cerrese Eugenio Carugo S.a.s.",
    "wof:placetype":"venue"
},
  "geometry": {"coordinates":[9.1881408691,45.4636878967],"type":"Point"}
}