{
  "type": "Feature",
  "properties": {
    "iso:country":"IT",
    "sg:address":"20091 Bresso",
    "sg:city":"Bresso",
    "sg:orig_category":"Forniture Per Agricoltura E Zootecnia. Animali Domestici",
    "sg:phone":"+39 02 6650 4974",
    "sg:postcode":"20091",
    "sg:province":"Milano",
    "wof:name":"International Pet Shop Srl",
    "wof:placetype":"venue"
},
  "geometry": {"coordinates":[9.1966028214,45.5313835144],"type":"Point"}
}