{
  "type": "Feature",
  "properties": {
    "iso:country":"IT",
    "sg:address":"Vle Nobel 14 10051 Avigliana",
    "sg:city":"Avigliana",
    "sg:classifiers":[
        {
            "category":"Building & Trades",
            "subcategory":"Construction",
            "type":"Services"
        }
    ],
    "sg:phone":"+39 011 936 7068",
    "sg:postcode":"10051",
    "sg:province":"Torino",
    "sg:tags":[
        "carpenter's",
        "work",
        "supraregional"
    ],
    "sg:website":"www.finestreefinestre.com",
    "wof:name":"Fo.c.ca.m Di Cataldi Francesco",
    "wof:placetype":"venue"
},
  "geometry": {"coordinates":[7.386297,45.088829],"type":"Point"}
}