{
  "type": "Feature",
  "properties": {
    "addr:full":"14, Piazza Della Liberta' 48018 Faenza Faenza Ravenna 48018",
    "addr:postcode":"48018;48018",
    "addr:street":"Piazza Della Liberta '",
    "iso:country":"IT",
    "sg:address":"14, Piazza Della Liberta' 48018 Faenza",
    "sg:city":"Faenza",
    "sg:classifiers":[
        {
            "category":"Banks & Credit Unions",
            "subcategory":"Bank",
            "type":"Services"
        }
    ],
    "sg:phone":"+39 0546 690111",
    "sg:postcode":"48018",
    "sg:province":"Ravenna",
    "sg:tags":[
        "banking",
        "institution"
    ],
    "wof:name":"Banche Credito Cooperativo Provincia Di Ravenna",
    "wof:placetype":"venue"
},
  "geometry": {"coordinates":[12.072701,44.362309],"type":"Point"}
}