{
  "type": "Feature",
  "properties": {
    "iso:country":"IT",
    "sg:address":"9 Viale Delle Nazioni, 37135 Verona",
    "sg:city":"Verona",
    "sg:classifiers":[
        {
            "category":"Banks & Credit Unions",
            "subcategory":"Financial Services",
            "type":"Services"
        }
    ],
    "sg:phone":"+39 045 829 0411",
    "sg:postcode":"37135",
    "sg:province":"Verona",
    "sg:tags":[
        "banking",
        "finance",
        "insurance"
    ],
    "wof:name":"Assicurazione Arag Assicurazioni",
    "wof:placetype":"venue"
},
  "geometry": {"coordinates":[10.9741830826,45.4031066895],"type":"Point"}
}