{
  "type": "Feature",
  "properties": {
    "iso:country":"IT",
    "sg:address":"Via Valsugana 67 35010 Curtarolo",
    "sg:city":"Curtarolo",
    "sg:classifiers":[
        {
            "category":"Utilities",
            "subcategory":"Refuse",
            "type":"Services"
        }
    ],
    "sg:phone":"+39 049 969 8411",
    "sg:postcode":"35010",
    "sg:province":"Padova",
    "sg:tags":[
        "equipment",
        "anti-theft"
    ],
    "sg:website":"www.avselectronics.com",
    "wof:name":"Avs Electronics Spa",
    "wof:placetype":"venue"
},
  "geometry": {"coordinates":[11.820482,45.545494],"type":"Point"}
}