{
  "type": "Feature",
  "properties": {
    "iso:country":"IT",
    "sg:address":"20122 Milano",
    "sg:city":"Milano",
    "sg:orig_category":"Ospedali E Servizi Sanitari. Centri Di Estetica E Cosmesi E Servizi",
    "sg:phone":"+39 02 5830 4803",
    "sg:postcode":"20122",
    "sg:province":"Milano",
    "wof:name":"Lucchini Italo",
    "wof:placetype":"venue"
},
  "geometry": {"coordinates":[9.194568,45.461208],"type":"Point"}
}