{
  "type": "Feature",
  "properties": {
    "addr:full":"90011 Bagheria Bagheria Palermo 90011",
    "addr:postcode":"90011;90011",
    "iso:country":"IT",
    "sg:address":"90011 Bagheria",
    "sg:city":"Bagheria",
    "sg:orig_category":"Forniture Per Agricoltura E Zootecnia. Prodotti Chimici Secondari. Macchine E Forniture Per Ecologia E Smaltimento Rifiuti",
    "sg:phone":"+39 091 931448",
    "sg:postcode":"90011",
    "sg:province":"Palermo",
    "wof:name":"Cirafici Angelo",
    "wof:placetype":"venue"
},
  "geometry": {"coordinates":[13.4916439056,38.0762443542],"type":"Point"}
}