{
  "type": "Feature",
  "properties": {
    "iso:country":"IT",
    "sg:address":"10090 Rivalba",
    "sg:city":"Rivalba",
    "sg:orig_category":"Materiali Edili",
    "sg:phone":"+39 011 960 4513",
    "sg:postcode":"10090",
    "sg:province":"Torino",
    "wof:name":"Fir Di Sergio Cacciotto & C. (s.n.c.)",
    "wof:placetype":"venue"
},
  "geometry": {"coordinates":[7.129241,44.945629],"type":"Point"}
}