{
  "type": "Feature",
  "properties": {
    "addr:full":"19, V. Venosa 20137 Milano Milano Milano 20137",
    "addr:housenumber":"19",
    "addr:postcode":"20137;20137",
    "addr:street":"V. Venosa",
    "iso:country":"IT",
    "sg:address":"19, V. Venosa 20137 Milano",
    "sg:city":"Milano",
    "sg:classifiers":[
        {
            "category":"Manufacturing",
            "subcategory":"Glass & Minerals",
            "type":"Manufacturing & Wholesale Goods"
        }
    ],
    "sg:phone":"+39 39025466337",
    "sg:postcode":"20137",
    "sg:province":"Milano",
    "sg:website":"http://www.marcomarchini.it:ws_end: :mark:ws:http://www.paginegialle.it/marcomarchini",
    "wof:name":"Marchini Marco",
    "wof:placetype":"venue"
},
  "geometry": {"coordinates":[9.222687,45.449291],"type":"Point"}
}