{
  "type": "Feature",
  "properties": {
    "iso:country":"IT",
    "sg:address":"25030 Castel Mella",
    "sg:city":"Castel Mella",
    "sg:orig_category":"Servizi E Lavori Per Abbigliamento E Pelletterie",
    "sg:phone":"+39 030 258 4479",
    "sg:postcode":"25030",
    "sg:province":"Brescia",
    "wof:name":"Giulistir",
    "wof:placetype":"venue"
},
  "geometry": {"coordinates":[10.14538,45.50951],"type":"Point"}
}