{
  "type": "Feature",
  "properties": {
    "addr:full":"07028 S. Teresa Gallura Olbia-Tempio 07028",
    "addr:housenumber":"07028",
    "addr:postcode":"07028",
    "addr:street":"S. Teresa Gallura",
    "iso:country":"IT",
    "sg:address":"07028 S. Teresa Gallura",
    "sg:orig_category":"Agenzie Viaggi E Turismo",
    "sg:phone":"+39 0789 756111",
    "sg:postcode":"07028",
    "sg:province":"Olbia-Tempio",
    "wof:name":"Consorzio Operatori Turistici Santa Teresa Di Gallura",
    "wof:placetype":"venue"
},
  "geometry": {"coordinates":[9.278559,40.826839],"type":"Point"}
}