{
  "type": "Feature",
  "properties": {
    "iso:country":"IT",
    "sg:address":"6, Via Oberdan 57025 Piombino",
    "sg:city":"Piombino",
    "sg:classifiers":[
        {
            "category":"Bars & Pubs",
            "subcategory":"Nightclub",
            "type":"Food & Drink"
        }
    ],
    "sg:phone":"+39 39056532216",
    "sg:postcode":"57025",
    "sg:province":"Livorno",
    "sg:tags":[
        "cake",
        "bread"
    ],
    "wof:name":"Panificio Maner Pa Srl",
    "wof:placetype":"venue"
},
  "geometry": {"coordinates":[10.308011,43.551876],"type":"Point"}
}