{
  "type": "Feature",
  "properties": {
    "iso:country":"IT",
    "sg:address":"80059 Torre Del Greco",
    "sg:city":"Torre del Greco",
    "sg:orig_category":"Materiali Edili",
    "sg:phone":"+39 081 881 9284",
    "sg:postcode":"80059",
    "sg:province":"Napoli",
    "wof:name":"Tecnotetto Sas",
    "wof:placetype":"venue"
},
  "geometry": {"coordinates":[14.381945,40.779335],"type":"Point"}
}