{
  "type": "Feature",
  "properties": {
    "iso:country":"IT",
    "sg:address":"50, Viale Pasubio 36036 Torrebelvicino",
    "sg:city":"Torrebelvicino",
    "sg:classifiers":[
        {
            "category":"Professional",
            "subcategory":"Engineering",
            "type":"Services"
        }
    ],
    "sg:phone":"+39 0445 661290",
    "sg:postcode":"36036",
    "sg:province":"Vicenza",
    "sg:tags":[
        "machine",
        "-",
        "mechanical"
    ],
    "wof:name":"Casolin Giorgio & C. S.n.c.",
    "wof:placetype":"venue"
},
  "geometry": {"coordinates":[11.319479,45.715641],"type":"Point"}
}