{
  "type": "Feature",
  "properties": {
    "iso:country":"IT",
    "sg:address":"20158 Milano",
    "sg:city":"Milano",
    "sg:orig_category":"Bilance, Bilici E Bascule",
    "sg:phone":"+39 02 3932 1776",
    "sg:postcode":"20158",
    "sg:province":"Milano",
    "sg:website":"http://www.ormabilance.com",
    "wof:name":"Orma Srl",
    "wof:placetype":"venue"
},
  "geometry": {"coordinates":[9.169043,45.500031],"type":"Point"}
}