{
  "type": "Feature",
  "properties": {
    "addr:full":"Strada Statale 126, Chilometro 95 Z 09036 Guspini Guspini Medio Campidano 09036",
    "addr:housenumber":"126;95 z",
    "addr:postcode":"09036;09036",
    "addr:street":"Strada Statale",
    "iso:country":"IT",
    "sg:address":"Strada Statale 126, Chilometro 95 Z 09036 Guspini",
    "sg:city":"Guspini",
    "sg:classifiers":[
        {
            "category":"Manufacturing",
            "subcategory":"Rubber & Plastics",
            "type":"Manufacturing & Wholesale Goods"
        }
    ],
    "sg:phone":"+39 070 970048",
    "sg:postcode":"09036",
    "sg:province":"Medio Campidano",
    "sg:tags":[
        "material"
    ],
    "sg:website":"www.usaiplast.it",
    "wof:name":"Usai Materie Plastiche Srl",
    "wof:placetype":"venue"
},
  "geometry": {"coordinates":[8.7040748596,39.5317382812],"type":"Point"}
}