{
  "type": "Feature",
  "properties": {
    "iso:country":"IT",
    "sg:address":"46042 Castel Goffredo",
    "sg:city":"Castel Goffredo",
    "sg:orig_category":"Impiantistica E Prodotti Tecnologici Per Edilizia. Elettrotecnica Industriale, Prodotti E Apparecchiature",
    "sg:phone":"+39 0376 781094",
    "sg:postcode":"46042",
    "sg:province":"Mantova",
    "sg:website":"http://www.amlux.it",
    "wof:name":"Amlux Srl",
    "wof:placetype":"venue"
},
  "geometry": {"coordinates":[10.479657,45.29874],"type":"Point"}
}