{
  "type": "Feature",
  "properties": {
    "iso:country":"IT",
    "sg:address":"37050 Concamarise",
    "sg:city":"Concamarise",
    "sg:orig_category":"Macchine E Forniture Per Arredamento E Industria Del Legno",
    "sg:phone":"+39 0442 374007",
    "sg:postcode":"37050",
    "sg:province":"Verona",
    "wof:name":"Sandri Daniele",
    "wof:placetype":"venue"
},
  "geometry": {"coordinates":[11.143184,45.199013],"type":"Point"}
}