{
  "type": "Feature",
  "properties": {
    "addr:full":"16, Via Dei Delfini 00186 Roma Roma Roma 00186",
    "addr:postcode":"00186;00186",
    "addr:street":"Via Dei Delfini",
    "iso:country":"IT",
    "sg:address":"16, Via Dei Delfini 00186 Roma",
    "sg:city":"Roma",
    "sg:classifiers":[
        {
            "category":"Airport",
            "subcategory":"General Aviation",
            "type":"Transportation"
        }
    ],
    "sg:phone":"+39 39066979231",
    "sg:postcode":"00186",
    "sg:province":"Roma",
    "sg:tags":[
        "transport",
        "air"
    ],
    "wof:name":"Unitainer System Italia Srl",
    "wof:placetype":"venue"
},
  "geometry": {"coordinates":[12.479352,41.893829],"type":"Point"}
}