{
  "type": "Feature",
  "properties": {
    "addr:full":"Via Roma, 26; Cerignola; 71042 Cerignola Foggia 71042",
    "addr:housenumber":"26",
    "addr:postcode":"71042;71042",
    "addr:street":"Via Roma",
    "iso:country":"IT",
    "sg:address":"Via Roma, 26; Cerignola; 71042",
    "sg:city":"Cerignola",
    "sg:classifiers":[
        {
            "category":"Banks & Credit Unions",
            "subcategory":"Bank",
            "type":"Services"
        }
    ],
    "sg:phone":"+39 0885 414023",
    "sg:postcode":"71042",
    "sg:province":"Foggia",
    "wof:name":"Banca Cattolica Popolare",
    "wof:placetype":"venue"
},
  "geometry": {"coordinates":[15.902811,41.26453],"type":"Point"}
}