{
  "type": "Feature",
  "properties": {
    "iso:country":"IT",
    "sg:address":"24036 Ponte San Pietro",
    "sg:city":"Ponte San Pietro",
    "sg:orig_category":"Studi E Consulenze Tecniche E Industriali. Consulenze Tecniche, Amministrative E Perizie. Professionisti - Studi E Servizi Ed Associazioni Di Interesse Aziendale",
    "sg:phone":"+39 035 437 6620",
    "sg:postcode":"24036",
    "sg:province":"Bergamo",
    "wof:name":"Omini Marco",
    "wof:placetype":"venue"
},
  "geometry": {"coordinates":[9.590847,45.697651],"type":"Point"}
}