{
  "type": "Feature",
  "properties": {
    "iso:country":"IT",
    "sg:address":"15060 Bosio",
    "sg:city":"Bosio",
    "sg:orig_category":"Pubblica Amministrazione",
    "sg:phone":"+39 0143 684014",
    "sg:postcode":"15060",
    "sg:province":"Alessandria",
    "wof:name":"Vivaio Forestale Aldec",
    "wof:placetype":"venue"
},
  "geometry": {"coordinates":[8.7735128403,44.5510368347],"type":"Point"}
}