{
  "type": "Feature",
  "properties": {
    "iso:country":"IT",
    "sg:address":"29, Strada Comunale Nuova Villa 80146 Napoli",
    "sg:city":"Napoli",
    "sg:classifiers":[
        {
            "category":"Manufacturing",
            "subcategory":"Metals",
            "type":"Manufacturing & Wholesale Goods"
        }
    ],
    "sg:phone":"+39 081 752 3788",
    "sg:postcode":"80146",
    "sg:province":"Napoli",
    "sg:tags":[
        "metallurgy",
        "metalworking"
    ],
    "wof:name":"Jannone Arm. (s.p.a.)",
    "wof:placetype":"venue"
},
  "geometry": {"coordinates":[14.2516355515,40.84009552],"type":"Point"}
}