{
  "type": "Feature",
  "properties": {
    "addr:full":"86046 San Martino In Pensilis San Martino in Pensilis Campobasso 86046",
    "addr:housenumber":"86046",
    "addr:postcode":"pensilis;pensilis;86046",
    "iso:country":"IT",
    "sg:address":"86046 San Martino In Pensilis",
    "sg:city":"San Martino in Pensilis",
    "sg:orig_category":"Antenne Radio-televisione",
    "sg:phone":"+39 0875 603205",
    "sg:postcode":"86046",
    "sg:province":"Campobasso",
    "wof:name":"Elettronic System Di Marrano Giuseppe",
    "wof:placetype":"venue"
},
  "geometry": {"coordinates":[15.044052,41.859257],"type":"Point"}
}