{
  "type": "Feature",
  "properties": {
    "iso:country":"IT",
    "sg:address":"01100 Viterbo",
    "sg:city":"Viterbo",
    "sg:orig_category":"Animali Domestici - Allevamento E Addestramento",
    "sg:phone":"+39 0761 227019",
    "sg:postcode":"01100",
    "sg:province":"Viterbo",
    "wof:name":"Allevamento Di Casa Bartolomei",
    "wof:placetype":"venue"
},
  "geometry": {"coordinates":[12.048979,42.441536],"type":"Point"}
}