{
  "type": "Feature",
  "properties": {
    "addr:full":"Via Aniene 1; Filettino",
    "addr:housenumber":"1",
    "addr:street":"Via Aniene",
    "iso:country":"IT",
    "sg:address":"Via Aniene 1; Filettino",
    "sg:classifiers":[
        {
            "category":"Banks & Credit Unions",
            "subcategory":"Bank",
            "type":"Services"
        }
    ],
    "sg:phone":"+39 0775 58812",
    "wof:name":"Banca Di Roma",
    "wof:placetype":"venue"
},
  "geometry": {"coordinates":[13.324909,41.891365],"type":"Point"}
}