{
  "type": "Feature",
  "properties": {
    "iso:country":"IT",
    "sg:address":"62027 San Severino Marche",
    "sg:city":"San Severino Marche",
    "sg:orig_category":"Marmo, Granito E Pietre Lavorazione - Macchine",
    "sg:phone":"+39 0733 633092",
    "sg:postcode":"62027",
    "sg:province":"Macerata",
    "wof:name":"Della Mora Giordano & Figli Snc",
    "wof:placetype":"venue"
},
  "geometry": {"coordinates":[13.197106,43.273075],"type":"Point"}
}