{
  "type": "Feature",
  "properties": {
    "addr:full":"35010 Bevadoro Padova 35010",
    "addr:postcode":"35010;35010",
    "iso:country":"IT",
    "sg:address":"35010 Bevadoro",
    "sg:orig_category":"Prodotti Alimentari. Agricoltura, Orticoltura E Floricoltura",
    "sg:phone":"+39 049 906 5122",
    "sg:postcode":"35010",
    "sg:province":"Padova",
    "wof:name":"Riseria Veneta Di Facco A.e C. (s.n.c.)",
    "wof:placetype":"venue"
},
  "geometry": {"coordinates":[11.7538938522,45.5151977539],"type":"Point"}
}