{
  "type": "Feature",
  "properties": {
    "iso:country":"IT",
    "sg:address":"5, Zona Artigianale - Casteldarne 39030 Chienes",
    "sg:city":"Casteldarne",
    "sg:classifiers":[
        {
            "category":"Professional",
            "subcategory":"Engineering",
            "type":"Services"
        }
    ],
    "sg:phone":"+39 0474 565253",
    "sg:postcode":"39030",
    "sg:province":"Bolzano/Bozen",
    "sg:tags":[
        "machine",
        "-",
        "mechanical"
    ],
    "sg:website":"http://www.weger.it",
    "wof:name":"Weger Walter & Co. Snc",
    "wof:placetype":"venue"
},
  "geometry": {"coordinates":[11.842582,46.80088],"type":"Point"}
}