{
  "type": "Feature",
  "properties": {
    "iso:country":"IT",
    "sg:address":"35128 Padova",
    "sg:city":"Padova",
    "sg:orig_category":"Cine-foto-ottica. Shopping",
    "sg:phone":"+39 049 807 8618",
    "sg:postcode":"35128",
    "sg:province":"Padova",
    "wof:name":"Sexy-shop Sesto Passo",
    "wof:placetype":"venue"
},
  "geometry": {"coordinates":[11.904662,45.3979],"type":"Point"}
}