{
  "type": "Feature",
  "properties": {
    "addr:full":"25087 Salo' Brescia 25087",
    "addr:postcode":"25087;25087",
    "iso:country":"IT",
    "sg:address":"25087 Salo'",
    "sg:orig_category":"Forniture Per Attivita' Industriali. Servizi Ausiliari Di Sorveglianza, Manutenzione E Pulizia",
    "sg:phone":"+39 036 552 0515",
    "sg:postcode":"25087",
    "sg:province":"Brescia",
    "wof:name":"S.a.i.t. Metalli Srl",
    "wof:placetype":"venue"
},
  "geometry": {"coordinates":[10.5166873932,45.6086044312],"type":"Point"}
}