{
  "type": "Feature",
  "properties": {
    "iso:country":"IT",
    "sg:address":"43036 Fidenza",
    "sg:city":"Fidenza",
    "sg:orig_category":"Elettrodomestici. Elettronica Professionale E Di Consumo. Arredi Ed Attrezzature Per Attivita' Commerciali Ed Artigianali. Macchine, Strumenti Ed Apparecchi Per Attivita' Industriali",
    "sg:phone":"+39 0524 523361",
    "sg:postcode":"43036",
    "sg:province":"Parma",
    "sg:website":"http://www.artigiana.com",
    "wof:name":"L'artigiana Snc",
    "wof:placetype":"venue"
},
  "geometry": {"coordinates":[10.074601,44.853424],"type":"Point"}
}