{
  "type": "Feature",
  "properties": {
    "iso:country":"IT",
    "sg:address":"20090 Buccinasco",
    "sg:city":"Buccinasco",
    "sg:orig_category":"Macchine Utensili - Commercio",
    "sg:phone":"+39 02 488 2360",
    "sg:postcode":"20090",
    "sg:province":"Milano",
    "sg:website":"http://www.etiessetransfer.com",
    "wof:name":"Etiesse Srl",
    "wof:placetype":"venue"
},
  "geometry": {"coordinates":[9.114737,45.419228],"type":"Point"}
}