{
  "type": "Feature",
  "properties": {
    "iso:country":"IT",
    "sg:address":"Via P. Valussi 3/2 33040 Premariacco",
    "sg:city":"Premariacco",
    "sg:classifiers":[
        {
            "category":"Wholesale",
            "subcategory":"Home Furnishings",
            "type":"Manufacturing & Wholesale Goods"
        }
    ],
    "sg:phone":"+39 0432 716169",
    "sg:postcode":"33040",
    "sg:province":"Udine",
    "sg:tags":[
        "chair"
    ],
    "sg:website":"www.forsedia.it",
    "wof:name":"Forsedia Srl",
    "wof:placetype":"venue"
},
  "geometry": {"coordinates":[13.30171,46.030575],"type":"Point"}
}