{
  "type": "Feature",
  "properties": {
    "iso:country":"IT",
    "sg:address":"20093 Cologno Monzese",
    "sg:city":"Cologno Monzese",
    "sg:orig_category":"Rottami Metallici",
    "sg:phone":"+39 02 254 0121",
    "sg:postcode":"20093",
    "sg:province":"Milano",
    "wof:name":"Nuova Cavaliere Sas",
    "wof:placetype":"venue"
},
  "geometry": {"coordinates":[9.264935,45.53323],"type":"Point"}
}