{
  "type": "Feature",
  "properties": {
    "iso:country":"IT",
    "sg:address":"Via Belvedere 26865 San Rocco Al Porto",
    "sg:city":"San Rocco al Porto",
    "sg:classifiers":[
        {
            "category":"Manufacturing",
            "subcategory":"Rubber & Plastics",
            "type":"Manufacturing & Wholesale Goods"
        }
    ],
    "sg:phone":"+39 0377 569384",
    "sg:postcode":"26865",
    "sg:province":"Lodi",
    "wof:name":"Pitiemme Italiana S.a.s",
    "wof:placetype":"venue"
},
  "geometry": {"coordinates":[9.6976594925,45.0944061279],"type":"Point"}
}