{
  "type": "Feature",
  "properties": {
    "addr:full":"8, Via Ropa C. 40012 Calderara Di Reno Calderara di Reno Bologna 40012",
    "addr:housenumber":"c.",
    "addr:postcode":"40012;40012",
    "addr:street":"Via Ropa",
    "iso:country":"IT",
    "sg:address":"8, Via Ropa C. 40012 Calderara Di Reno",
    "sg:city":"Calderara di Reno",
    "sg:classifiers":[
        {
            "category":"Sports & Exercise",
            "subcategory":"Playing Field",
            "type":"Entertainment"
        }
    ],
    "sg:phone":"+39 39051727315",
    "sg:postcode":"40012",
    "sg:province":"Bologna",
    "sg:tags":[
        "game"
    ],
    "wof:name":"A.p.a. (s.p.a.)",
    "wof:placetype":"venue"
},
  "geometry": {"coordinates":[11.265198,44.543827],"type":"Point"}
}