{
  "type": "Feature",
  "properties": {
    "iso:country":"IT",
    "sg:address":"Via Sporting Mirasole 2- 20090 Opera",
    "sg:city":"Opera",
    "sg:orig_category":"Processing Plants For Cement, Lime And Plaster",
    "sg:phone":"+39 02 5760 4767",
    "sg:postcode":"20090",
    "sg:province":"Milano",
    "sg:website":"www.sic-lime.it",
    "wof:name":"Societa' Impianti Calce Srl",
    "wof:placetype":"venue"
},
  "geometry": {"coordinates":[9.2117137909,45.3937225342],"type":"Point"}
}