{
  "type": "Feature",
  "properties": {
    "iso:country":"IT",
    "sg:address":"7, Via Zambra 00052 Cerveteri",
    "sg:city":"Cerveteri",
    "sg:classifiers":[
        {
            "category":"Shopping",
            "subcategory":"Stationery & Office Supplies",
            "type":"Retail Goods"
        }
    ],
    "sg:phone":"+39 39069904701",
    "sg:postcode":"00052",
    "sg:province":"Roma",
    "sg:tags":[
        "professional"
    ],
    "wof:name":"Merlo Spa",
    "wof:placetype":"venue"
},
  "geometry": {"coordinates":[12.0784454346,41.9955215454],"type":"Point"}
}