{
  "type": "Feature",
  "properties": {
    "iso:country":"IT",
    "sg:address":"98030 Giardini Naxos",
    "sg:orig_category":"Abbigliamento Sportivo, Jeans E Casuals - Vendita Al Dettaglio",
    "sg:phone":"+39 0942 51050",
    "sg:postcode":"98030",
    "sg:province":"Messina",
    "wof:name":"La Nike Sport Di Aiello",
    "wof:placetype":"venue"
},
  "geometry": {"coordinates":[15.269,37.825001],"type":"Point"}
}