{
  "type": "Feature",
  "properties": {
    "addr:full":"9, Via S.marco-soci 52011 Bibbiena Bibbiena Arezzo 52011",
    "addr:postcode":"52011;52011",
    "addr:street":"Via S.Marco-Soci",
    "iso:country":"IT",
    "sg:address":"9, Via S.marco-soci 52011 Bibbiena",
    "sg:city":"Bibbiena",
    "sg:classifiers":[
        {
            "category":"Shopping",
            "subcategory":"Stationery & Office Supplies",
            "type":"Retail Goods"
        }
    ],
    "sg:phone":"+39 0575 560231",
    "sg:postcode":"52011",
    "sg:province":"Arezzo",
    "sg:tags":[
        "professional"
    ],
    "wof:name":"Bendoni Inox S.r.l.",
    "wof:placetype":"venue"
},
  "geometry": {"coordinates":[11.8630619049,43.4712028503],"type":"Point"}
}