{
  "type": "Feature",
  "properties": {
    "iso:country":"IT",
    "sg:address":"Localit\u00e0 Verduzio 48 84040 Casalvelino",
    "sg:orig_category":"Fruits, Dried",
    "sg:phone":"+39 0974 64281",
    "sg:postcode":"84040",
    "sg:province":"Salerno",
    "sg:website":"www.stelladelsudsrl.com",
    "wof:name":"Stella Del Sud Srl",
    "wof:placetype":"venue"
},
  "geometry": {"coordinates":[14.765912056,40.6779556274],"type":"Point"}
}