{
  "type": "Feature",
  "properties": {
    "iso:country":"IT",
    "sg:address":"33030 Campoformido",
    "sg:city":"Campoformido",
    "sg:orig_category":"Carrozzerie Automobili",
    "sg:phone":"+39 0432 663393",
    "sg:postcode":"33030",
    "sg:province":"Udine",
    "sg:website":"http://www.avicar.it",
    "wof:name":"A.v.i. Di G. Croce & C. Snc",
    "wof:placetype":"venue"
},
  "geometry": {"coordinates":[13.169673,46.025501],"type":"Point"}
}