{
  "type": "Feature",
  "properties": {
    "iso:country":"IT",
    "sg:address":"34/36, Via Rimini 20142 Milano",
    "sg:city":"Milano",
    "sg:classifiers":[
        {
            "category":"Utilities",
            "subcategory":"Electric",
            "type":"Services"
        }
    ],
    "sg:phone":"+39 390 289 5201",
    "sg:postcode":"20142",
    "sg:province":"Milano",
    "sg:tags":[
        "energy"
    ],
    "wof:name":"Cap Gestione S.p.a.",
    "wof:placetype":"venue"
},
  "geometry": {"coordinates":[9.169293,45.440784],"type":"Point"}
}