{
  "type": "Feature",
  "properties": {
    "addr:full":"00183 Roma Roma Roma 00183",
    "addr:postcode":"00183;00183",
    "iso:country":"IT",
    "sg:address":"00183 Roma",
    "sg:city":"Roma",
    "sg:orig_category":"Hobbistica",
    "sg:phone":"+39 06 7759 0328",
    "sg:postcode":"00183",
    "sg:province":"Roma",
    "wof:name":"Collezionando Di Luigi Parentini Sas",
    "wof:placetype":"venue"
},
  "geometry": {"coordinates":[12.502913,41.881187],"type":"Point"}
}