{
  "type": "Feature",
  "properties": {
    "addr:full":"10156 Torino Torino Torino 10156",
    "addr:postcode":"10156;10156",
    "iso:country":"IT",
    "sg:address":"10156 Torino",
    "sg:city":"Torino",
    "sg:orig_category":"Frigotecnica, Apparecchiature E Servizi. Climatizzazione E Condizionamento, Apparecchiature E Servizi",
    "sg:phone":"+39 011 262 1246",
    "sg:postcode":"10156",
    "sg:province":"Torino",
    "wof:name":"Aspex Soc. A R.l.",
    "wof:placetype":"venue"
},
  "geometry": {"coordinates":[7.5548243523,45.06798172],"type":"Point"}
}