{
  "type": "Feature",
  "properties": {
    "addr:full":"7, Via Pizzamiglia 42016 Guastalla Reggio Nell'Emilia 42016",
    "addr:postcode":"42016;42016",
    "addr:street":"Via Pizzamiglia",
    "iso:country":"IT",
    "sg:address":"7, Via Pizzamiglia 42016 Guastalla",
    "sg:classifiers":[
        {
            "category":"Home & Garden",
            "subcategory":"Home Furnishings",
            "type":"Retail Goods"
        }
    ],
    "sg:phone":"+39 0522 228058",
    "sg:postcode":"42016",
    "sg:province":"Reggio Nell'Emilia",
    "sg:tags":[
        "household"
    ],
    "wof:name":"Sarmog Spa",
    "wof:placetype":"venue"
},
  "geometry": {"coordinates":[10.728281,44.925491],"type":"Point"}
}