{
  "type": "Feature",
  "properties": {
    "addr:full":"36040 Brendola Brendola Vicenza 36040",
    "addr:postcode":"36040;36040",
    "iso:country":"IT",
    "sg:address":"36040 Brendola",
    "sg:city":"Brendola",
    "sg:orig_category":"Aria Compressa - Impianti Ed Attrezzature",
    "sg:phone":"+39 0444 401138",
    "sg:postcode":"36040",
    "sg:province":"Vicenza",
    "wof:name":"Gav Di Ghiotto Angelo & C. Snc",
    "wof:placetype":"venue"
},
  "geometry": {"coordinates":[11.513499,45.508739],"type":"Point"}
}