{
  "type": "Feature",
  "properties": {
    "iso:country":"IT",
    "sg:address":"00193 Roma",
    "sg:city":"Roma",
    "sg:orig_category":"Articoli Da Regalo. Shopping. Regalistica Aziendale",
    "sg:phone":"+39 06 6880 6809",
    "sg:postcode":"00193",
    "sg:province":"Roma",
    "wof:name":"Galleria Aurora S.r.l.",
    "wof:placetype":"venue"
},
  "geometry": {"coordinates":[12.459362,41.902287],"type":"Point"}
}