{
  "type": "Feature",
  "properties": {
    "iso:country":"IT",
    "sg:address":"20131 Milano",
    "sg:city":"Milano",
    "sg:orig_category":"Cine-foto-ottica",
    "sg:phone":"+39 02 7063 1534",
    "sg:postcode":"20131",
    "sg:province":"Milano",
    "sg:website":"http://www.nicam.it",
    "wof:name":"Nicam Srl",
    "wof:placetype":"venue"
},
  "geometry": {"coordinates":[9.234087,45.485149],"type":"Point"}
}