{
  "type": "Feature",
  "properties": {
    "addr:full":"40033 Casalecchio Di Reno Casalecchio di Reno Bologna 40033",
    "addr:postcode":"40033;40033",
    "addr:street":"Di Reno",
    "iso:country":"IT",
    "sg:address":"40033 Casalecchio Di Reno",
    "sg:city":"Casalecchio di Reno",
    "sg:orig_category":"Prodotti Chimici Secondari. Materiali Edili",
    "sg:phone":"+39 051 619 9688",
    "sg:postcode":"40033",
    "sg:province":"Bologna",
    "wof:name":"Casalini & Co. S.r.l.",
    "wof:placetype":"venue"
},
  "geometry": {"coordinates":[11.2669811249,44.4658432007],"type":"Point"}
}