{
  "type": "Feature",
  "properties": {
    "iso:country":"IT",
    "sg:address":"41012 Carpi",
    "sg:city":"Carpi",
    "sg:orig_category":"Macchine, Impianti Ed Attrezzature Per Abbigliamento E Pelletterie",
    "sg:phone":"+39 059 640795",
    "sg:postcode":"41012",
    "sg:province":"Modena",
    "wof:name":"Ballestrazzi Alessandro & C.",
    "wof:placetype":"venue"
},
  "geometry": {"coordinates":[10.946481,44.757256],"type":"Point"}
}