{
  "type": "Feature",
  "properties": {
    "iso:country":"IT",
    "sg:address":"Via Della Rocca 21 10123 Torino",
    "sg:city":"Torino",
    "sg:classifiers":[
        {
            "category":"Professional",
            "subcategory":"Employment Agencies",
            "type":"Services"
        }
    ],
    "sg:phone":"+39 011 839 5754",
    "sg:postcode":"10123",
    "sg:province":"Torino",
    "sg:tags":[
        "pr",
        "relation",
        "public"
    ],
    "wof:name":"Compact Srl",
    "wof:placetype":"venue"
},
  "geometry": {"coordinates":[8.3989200592,45.4623451233],"type":"Point"}
}