{
  "type": "Feature",
  "properties": {
    "iso:country":"IT",
    "sg:address":"00169 Roma",
    "sg:city":"Roma",
    "sg:orig_category":"Ospedali E Servizi Sanitari. Pubblica Amministrazione. Servizi Sociali",
    "sg:phone":"+39 06 260247",
    "sg:postcode":"00169",
    "sg:province":"Roma",
    "wof:name":"Azienda Usl Roma 'b' (ex Usl Rm3-rm 5)",
    "wof:placetype":"venue"
},
  "geometry": {"coordinates":[12.600892,41.867748],"type":"Point"}
}