{
  "type": "Feature",
  "properties": {
    "iso:country":"IT",
    "sg:address":"16126 Genova",
    "sg:city":"Genova",
    "sg:orig_category":"Servizi Culturali E Per Lo Spettacolo. Servizi Al Turismo. Acqua, Luce, Gas E Societa' Di Esercizio Pubblico",
    "sg:phone":"+39 010 255509",
    "sg:postcode":"16126",
    "sg:province":"Genova",
    "wof:name":"Arti Doria Pamphilj",
    "wof:placetype":"venue"
},
  "geometry": {"coordinates":[8.920556,44.416668],"type":"Point"}
}