{
  "type": "Feature",
  "properties": {
    "iso:country":"IT",
    "sg:address":"20132 Milano",
    "sg:city":"Milano",
    "sg:orig_category":"Materiali Edili",
    "sg:phone":"+39 02 2720 7010",
    "sg:postcode":"20132",
    "sg:province":"Milano",
    "wof:name":"Coperture Scardo Srl",
    "wof:placetype":"venue"
},
  "geometry": {"coordinates":[9.244388,45.500156],"type":"Point"}
}