{
  "type": "Feature",
  "properties": {
    "addr:full":"5, Via Calabria 21013 Gallarate Gallarate Varese 21013",
    "addr:postcode":"21013;21013",
    "addr:street":"Via Calabria",
    "iso:country":"IT",
    "sg:address":"5, Via Calabria 21013 Gallarate",
    "sg:city":"Gallarate",
    "sg:classifiers":[
        {
            "category":"Shopping",
            "subcategory":"Crafts & Fabrics",
            "type":"Retail Goods"
        }
    ],
    "sg:phone":"+39 0331 794575",
    "sg:postcode":"21013",
    "sg:province":"Varese",
    "wof:name":"Prina Tessuti S.r.l.",
    "wof:placetype":"venue"
},
  "geometry": {"coordinates":[8.7909107208,45.668926239],"type":"Point"}
}