{
  "type": "Feature",
  "properties": {
    "addr:full":"09071 Abbasanta Abbasanta Oristano 09071",
    "addr:postcode":"09071;09071",
    "iso:country":"IT",
    "sg:address":"09071 Abbasanta",
    "sg:city":"Abbasanta",
    "sg:orig_category":"Apparecchiature Ed Attrezzature Meccaniche",
    "sg:phone":"+39 0785 52694",
    "sg:postcode":"09071",
    "sg:province":"Oristano",
    "wof:name":"Ricauto Srl",
    "wof:placetype":"venue"
},
  "geometry": {"coordinates":[8.759131,40.150589],"type":"Point"}
}