{
  "type": "Feature",
  "properties": {
    "iso:country":"IT",
    "sg:address":"20034 Paina",
    "sg:city":"Paina",
    "sg:orig_category":"Non-classified Establishments",
    "sg:phone":"+39 036 286 1424",
    "sg:postcode":"20034",
    "sg:province":"Milano",
    "wof:name":"Comma (s.a.s.)",
    "wof:placetype":"venue"
},
  "geometry": {"coordinates":[9.205823,45.676823],"type":"Point"}
}