{
  "type": "Feature",
  "properties": {
    "addr:full":"60019 Senigallia Senigallia Ancona 60019",
    "addr:postcode":"60019;60019",
    "iso:country":"IT",
    "sg:address":"60019 Senigallia",
    "sg:city":"Senigallia",
    "sg:orig_category":"Musica. Shopping",
    "sg:phone":"+39 071 659711",
    "sg:postcode":"60019",
    "sg:province":"Ancona",
    "wof:name":"World Music",
    "wof:placetype":"venue"
},
  "geometry": {"coordinates":[13.1971063614,43.6896095276],"type":"Point"}
}