{
  "type": "Feature",
  "properties": {
    "iso:country":"IT",
    "sg:address":"28, Piazza Marx Carlo 75024 Montescaglioso",
    "sg:city":"Montescaglioso",
    "sg:classifiers":[
        {
            "category":"Shopping",
            "subcategory":"Clothing, Apparel, & Fashions",
            "type":"Retail Goods"
        }
    ],
    "sg:phone":"+39 0835 208787",
    "sg:postcode":"75024",
    "sg:province":"Matera",
    "sg:tags":[
        "clothes"
    ],
    "wof:name":"Confezioni Baby Rosa S.r.l.",
    "wof:placetype":"venue"
},
  "geometry": {"coordinates":[16.660093,40.549618],"type":"Point"}
}