{
  "type": "Feature",
  "properties": {
    "iso:country":"IT",
    "sg:address":"00184 Roma",
    "sg:city":"Roma",
    "sg:orig_category":"Fotografia Apparecchi E Materiali - Produzione E Ingrosso",
    "sg:phone":"+39 06 481 4376",
    "sg:postcode":"00184",
    "sg:province":"Roma",
    "wof:name":"Emme Toffolo",
    "wof:placetype":"venue"
},
  "geometry": {"coordinates":[12.5985326767,41.8014755249],"type":"Point"}
}