{
  "type": "Feature",
  "properties": {
    "addr:full":"Via Marconi 29, 60010 Ostra Vetere, An Ostra Ancona 60010",
    "addr:housenumber":"29",
    "addr:postcode":"60010;60010",
    "addr:street":"Via Marconi",
    "iso:country":"IT",
    "sg:address":"Via Marconi 29, 60010 Ostra Vetere, An",
    "sg:city":"Ostra",
    "sg:classifiers":[
        {
            "category":"Banks & Credit Unions",
            "subcategory":"Bank",
            "type":"Services"
        }
    ],
    "sg:postcode":"60010",
    "sg:province":"Ancona",
    "wof:name":"Banca Di Credito Cooperativo Di Ostra Vetere (ancona)",
    "wof:placetype":"venue"
},
  "geometry": {"coordinates":[13.518757,43.615856],"type":"Point"}
}