{
  "type": "Feature",
  "properties": {
    "addr:full":"00142 Roma Roma Roma 00142",
    "addr:postcode":"00142;00142",
    "iso:country":"IT",
    "sg:address":"00142 Roma",
    "sg:city":"Roma",
    "sg:orig_category":"Apparecchi, Attrezzature E Forniture Per Centri Estetici",
    "sg:phone":"+39 06 5195 7113",
    "sg:postcode":"00142",
    "sg:province":"Roma",
    "wof:name":"Charme International Srl",
    "wof:placetype":"venue"
},
  "geometry": {"coordinates":[12.504013,41.836437],"type":"Point"}
}