{
  "type": "Feature",
  "properties": {
    "iso:country":"IT",
    "sg:address":"47031 Repubblica Di San Marino",
    "sg:orig_category":"Ospedali E Servizi Sanitari",
    "sg:phone":"+39 0549 906042",
    "sg:province":"SM",
    "wof:name":"Muccioli Massimo",
    "wof:placetype":"venue"
},
  "geometry": {"coordinates":[12.441867,43.944237],"type":"Point"}
}