{
  "type": "Feature",
  "properties": {
    "addr:full":"40012 Calderara Di Reno Bargellino Bologna 40012",
    "addr:postcode":"40012;bologna 40012",
    "iso:country":"IT",
    "sg:address":"40012 Calderara Di Reno",
    "sg:city":"Bargellino",
    "sg:orig_category":"Arredo Camera Letto E Complementi",
    "sg:phone":"+39 051 727204",
    "sg:postcode":"40012",
    "sg:province":"Bologna",
    "wof:name":"Mobilificio F.lli Baiesi Snc",
    "wof:placetype":"venue"
},
  "geometry": {"coordinates":[11.264453,44.542595],"type":"Point"}
}