{
  "type": "Feature",
  "properties": {
    "iso:country":"IT",
    "sg:address":"80053 Castellammare Di Stabia",
    "sg:city":"Castellammare di Stabia",
    "sg:orig_category":"Carni, Salumi E Pesci",
    "sg:phone":"+39 081 870 4615",
    "sg:postcode":"80053",
    "sg:province":"Napoli",
    "wof:name":"Arctic Fish Di De Cesare Pasquale E Finizio Ferdinando",
    "wof:placetype":"venue"
},
  "geometry": {"coordinates":[14.482512,40.706249],"type":"Point"}
}