{
  "type": "Feature",
  "properties": {
    "iso:country":"IT",
    "sg:address":"20, Via Menotti Ciro 20092 Cinisello Balsamo",
    "sg:city":"Cinisello Balsamo",
    "sg:classifiers":[
        {
            "category":"Building & Trades",
            "subcategory":"Construction",
            "type":"Services"
        }
    ],
    "sg:phone":"+39 02 6129 0045",
    "sg:postcode":"20092",
    "sg:province":"Milano",
    "sg:tags":[
        "work",
        "public"
    ],
    "wof:name":"Impredil Gelfi (s.p.a.)",
    "wof:placetype":"venue"
},
  "geometry": {"coordinates":[9.266374,45.545448],"type":"Point"}
}