{
  "type": "Feature",
  "properties": {
    "iso:country":"IT",
    "sg:address":"Via Dell' Industria 9 42010 Cavola",
    "sg:classifiers":[
        {
            "category":"Wholesale",
            "subcategory":"Painting Supplies",
            "type":"Manufacturing & Wholesale Goods"
        }
    ],
    "sg:phone":"+39 0522 818420",
    "sg:postcode":"42010",
    "sg:province":"Reggio Nell'Emilia",
    "sg:tags":[
        "ceramic"
    ],
    "sg:website":"www.creativititile.it",
    "wof:name":"Creativi Ti Tile Snc",
    "wof:placetype":"venue"
},
  "geometry": {"coordinates":[10.627794,44.696228],"type":"Point"}
}