{
  "type": "Feature",
  "properties": {
    "iso:country":"IT",
    "sg:address":"Piazza Meda 1; Milano; 20124",
    "sg:city":"Milano",
    "sg:classifiers":[
        {
            "category":"Banks & Credit Unions",
            "subcategory":"Bank",
            "type":"Services"
        }
    ],
    "sg:phone":"+39 02 655 5833",
    "sg:postcode":"20124",
    "sg:province":"Milano",
    "wof:name":"Canadian Imperial Bank Of Commerce",
    "wof:placetype":"venue"
},
  "geometry": {"coordinates":[9.193152,45.467049],"type":"Point"}
}