{
  "type": "Feature",
  "properties": {
    "addr:full":"Via Bovio 2/a/h 42100 Reggio Emilia Reggio Nell'Emilia 42100",
    "addr:housenumber":"2 / a / h",
    "addr:postcode":"42100;42100",
    "addr:street":"Via Bovio",
    "iso:country":"IT",
    "sg:address":"Via Bovio 2/a/h 42100 Reggio Emilia",
    "sg:classifiers":[
        {
            "category":"Shopping",
            "subcategory":"Hobbies, Toys, & Games",
            "type":"Retail Goods"
        }
    ],
    "sg:phone":"+39 0522 515336",
    "sg:postcode":"42100",
    "sg:province":"Reggio Nell'Emilia",
    "sg:tags":[
        "electronic"
    ],
    "sg:website":"www.memopark.it",
    "wof:name":"Memo Park Di Incerti Fornaciari Bruno & C. Sas",
    "wof:placetype":"venue"
},
  "geometry": {"coordinates":[10.65301,44.733803],"type":"Point"}
}