{
  "type": "Feature",
  "properties": {
    "iso:country":"IT",
    "sg:address":"Via Tiberina Sud 300 06053 Deruta",
    "sg:city":"Deruta",
    "sg:classifiers":[
        {
            "category":"Shopping",
            "subcategory":"Gifts & Souvenirs",
            "type":"Retail Goods"
        }
    ],
    "sg:phone":"+39 075 972016",
    "sg:postcode":"06053",
    "sg:province":"Perugia",
    "sg:tags":[
        "item",
        "ceramic"
    ],
    "sg:website":"www.gpderuta.com",
    "wof:name":"G & P Ceramiche Artistiche",
    "wof:placetype":"venue"
},
  "geometry": {"coordinates":[12.409933,43.043915],"type":"Point"}
}