{
  "type": "Feature",
  "properties": {
    "addr:full":"Via San Gregorio 27 20124 Milano Milano Milano 20124",
    "addr:housenumber":"27",
    "addr:postcode":"20124;20124",
    "addr:street":"Via San Gregorio",
    "iso:country":"IT",
    "sg:address":"Via San Gregorio 27 20124 Milano",
    "sg:city":"Milano",
    "sg:classifiers":[
        {
            "category":"Shopping",
            "subcategory":"Clothing, Apparel, & Fashions",
            "type":"Retail Goods"
        }
    ],
    "sg:phone":"+39 02 2953 1193",
    "sg:postcode":"20124",
    "sg:province":"Milano",
    "sg:tags":[
        "children's",
        "clothing"
    ],
    "wof:name":"Intertam Corporation Di Fumiaki Tamada",
    "wof:placetype":"venue"
},
  "geometry": {"coordinates":[9.20483,45.479343],"type":"Point"}
}