{
  "type": "Feature",
  "properties": {
    "iso:country":"IT",
    "sg:address":"37060 Castel D'azzano",
    "sg:city":"Azzano",
    "sg:orig_category":"Servizi Di Magazzinaggio E Movimentazione",
    "sg:phone":"+39 045 852 0935",
    "sg:postcode":"37060",
    "sg:province":"Verona",
    "sg:website":"http://www.grossmarket-srl.com",
    "wof:name":"Gross Market Srl",
    "wof:placetype":"venue"
},
  "geometry": {"coordinates":[10.968734,45.361],"type":"Point"}
}