{
  "type": "Feature",
  "properties": {
    "addr:full":"10099 San Mauro Torinese San Mauro Torinese Torino 10099",
    "addr:housenumber":"10099",
    "addr:postcode":"10099",
    "addr:street":"San",
    "iso:country":"IT",
    "sg:address":"10099 San Mauro Torinese",
    "sg:city":"San Mauro Torinese",
    "sg:orig_category":"Macchine Utensili E Impianti",
    "sg:phone":"+39 011 2236 7767",
    "sg:postcode":"10099",
    "sg:province":"Torino",
    "sg:website":"http://www.azetamacchineutensili.it",
    "wof:name":"Azeta Srl",
    "wof:placetype":"venue"
},
  "geometry": {"coordinates":[7.748488,45.118332],"type":"Point"}
}