{
  "type": "Feature",
  "properties": {
    "iso:country":"IT",
    "sg:address":"Localita' Pian Dell'olmino 53034 Colle Di Val D'elsa",
    "sg:classifiers":[
        {
            "category":"Shopping",
            "subcategory":"Stationery & Office Supplies",
            "type":"Retail Goods"
        }
    ],
    "sg:phone":"+39 0577 904402",
    "sg:postcode":"53034",
    "sg:province":"Siena",
    "sg:tags":[
        "professional"
    ],
    "wof:name":"Panels Spa - Industria Pannelli Compositi",
    "wof:placetype":"venue"
},
  "geometry": {"coordinates":[11.3305139542,43.3186607361],"type":"Point"}
}