{
  "type": "Feature",
  "properties": {
    "iso:country":"IT",
    "sg:address":"20092 Cinisello Balsamo",
    "sg:city":"Cinisello Balsamo",
    "sg:orig_category":"Alimentare E Conserviera Industria - Macchine",
    "sg:phone":"+39 02 614561",
    "sg:postcode":"20092",
    "sg:province":"Milano",
    "sg:website":"http://www.scolarieng.com",
    "wof:name":"Scolari Engineering Srl",
    "wof:placetype":"venue"
},
  "geometry": {"coordinates":[9.20505,45.548653],"type":"Point"}
}