{
  "type": "Feature",
  "properties": {
    "addr:full":"64023 Mosciano S. Angelo Teramo 64023",
    "addr:postcode":"64023;64023",
    "addr:street":"Mosciano S. Angelo Teramo",
    "iso:country":"IT",
    "sg:address":"64023 Mosciano S. Angelo",
    "sg:orig_category":"Miele E Prodotti Apistici",
    "sg:phone":"+39 085 806 1082",
    "sg:postcode":"64023",
    "sg:province":"Teramo",
    "wof:name":"Azienda Apistica Mantovan",
    "wof:placetype":"venue"
},
  "geometry": {"coordinates":[13.7339076996,42.6783866882],"type":"Point"}
}