{
  "type": "Feature",
  "properties": {
    "addr:full":"9, Via Monte Napoleone 20121 Milano Milano Milano 20121",
    "addr:postcode":"20121;20121",
    "addr:street":"Via Monte Napoleone",
    "iso:country":"IT",
    "sg:address":"9, Via Monte Napoleone 20121 Milano",
    "sg:city":"Milano",
    "sg:classifiers":[
        {
            "category":"Manufacturing",
            "subcategory":"Printing",
            "type":"Manufacturing & Wholesale Goods"
        }
    ],
    "sg:phone":"+39 390 279 4181",
    "sg:postcode":"20121",
    "sg:province":"Milano",
    "sg:tags":[
        "publishing"
    ],
    "wof:name":"Iht Gruppo Editoriale (s.r.l.)",
    "wof:placetype":"venue"
},
  "geometry": {"coordinates":[9.1952190399,45.4682159424],"type":"Point"}
}