{
  "type": "Feature",
  "properties": {
    "iso:country":"IT",
    "sg:address":"102, Via Cordellina 36050 Sovizzo",
    "sg:city":"Sovizzo",
    "sg:classifiers":[
        {
            "category":"Professional",
            "subcategory":"Engineering",
            "type":"Services"
        }
    ],
    "sg:phone":"+39 0444 370251",
    "sg:postcode":"36050",
    "sg:province":"Vicenza",
    "sg:tags":[
        "machine",
        "-",
        "mechanical"
    ],
    "wof:name":"Trevisan Macchine Utensili (s.p.a.)",
    "wof:placetype":"venue"
},
  "geometry": {"coordinates":[11.446514,45.513397],"type":"Point"}
}