{
  "type": "Feature",
  "properties": {
    "iso:country":"IT",
    "sg:address":"20097 San Donato Milanese",
    "sg:city":"San Donato Milanese",
    "sg:orig_category":"Macchine, Impianti Ed Attrezzature Industria Chimica. Attrezzature E Forniture Per Officine Riparazione E Servizi Ausiliari",
    "sg:phone":"+39 02 5180 0056",
    "sg:postcode":"20097",
    "sg:province":"Milano",
    "wof:name":"Lombarda Manutenzioni S.r.l.",
    "wof:placetype":"venue"
},
  "geometry": {"coordinates":[9.268738,45.416649],"type":"Point"}
}