{
  "type": "Feature",
  "properties": {
    "addr:full":"34149 Trieste Trieste Trieste 34149",
    "addr:postcode":"34149;34149",
    "iso:country":"IT",
    "sg:address":"34149 Trieste",
    "sg:city":"Trieste",
    "sg:classifiers":[
        {
            "category":"Banks & Credit Unions",
            "subcategory":"Investment Brokerage",
            "type":"Services"
        }
    ],
    "sg:phone":"+39 040 391389",
    "sg:postcode":"34149",
    "sg:province":"Trieste",
    "sg:tags":[
        "vehicles",
        "auxiliary",
        "motor"
    ],
    "wof:name":"Orlandi Srl Superauto",
    "wof:placetype":"venue"
},
  "geometry": {"coordinates":[13.8003911972,45.6349411011],"type":"Point"}
}