{
  "type": "Feature",
  "properties": {
    "iso:country":"IT",
    "sg:address":"20060 Masate",
    "sg:city":"Masate",
    "sg:orig_category":"Zootecnia E Pesca, Allevamento Piccoli Animali",
    "sg:phone":"+39 02 9576 1513",
    "sg:postcode":"20060",
    "sg:province":"Milano",
    "wof:name":"Manzoni Alessandro",
    "wof:placetype":"venue"
},
  "geometry": {"coordinates":[9.458633,45.565529],"type":"Point"}
}