{
  "type": "Feature",
  "properties": {
    "addr:full":"50127 Firenze Firenze Firenze 50127",
    "addr:postcode":"50127;50127",
    "iso:country":"IT",
    "sg:address":"50127 Firenze",
    "sg:city":"Firenze",
    "sg:classifiers":[
        {
            "category":"Utilities",
            "subcategory":"Refuse",
            "type":"Services"
        }
    ],
    "sg:phone":"+39 055 435860",
    "sg:postcode":"50127",
    "sg:province":"Firenze",
    "sg:tags":[
        "auxiliary",
        "disposal",
        "surveillance",
        "environmental",
        "protection",
        "cleaning",
        "maintenance",
        "works"
    ],
    "wof:name":"Bassi Remo E C. Snc",
    "wof:placetype":"venue"
},
  "geometry": {"coordinates":[11.225059,43.798275],"type":"Point"}
}