{
  "type": "Feature",
  "properties": {
    "iso:country":"IT",
    "sg:address":"21042 Caronno Pertusella",
    "sg:city":"Caronno Pertusella",
    "sg:orig_category":"Arredamenti E Mobili Professionali. Impianti, Attrezzature E Forniture Sanitarie Ed Ospedaliere",
    "sg:phone":"+39 02 965 0233",
    "sg:postcode":"21042",
    "sg:province":"Varese",
    "wof:name":"Bottigelli (s.p.a.)",
    "wof:placetype":"venue"
},
  "geometry": {"coordinates":[9.045978,45.597878],"type":"Point"}
}