{
  "type": "Feature",
  "properties": {
    "addr:full":"29010 Sarmato Sarmato Piacenza 29010",
    "addr:postcode":"29010;29010",
    "iso:country":"IT",
    "sg:address":"29010 Sarmato",
    "sg:city":"Sarmato",
    "sg:orig_category":"Pizzi E Merletti",
    "sg:phone":"+39 0523 886144",
    "sg:postcode":"29010",
    "sg:province":"Piacenza",
    "wof:name":"Merlettificio Freguia Luigi Snc",
    "wof:placetype":"venue"
},
  "geometry": {"coordinates":[9.4934444427,45.0579795837],"type":"Point"}
}