{
  "type": "Feature",
  "properties": {
    "addr:full":"20123 Milano Milano Milano 20123",
    "addr:postcode":"20123;20123",
    "iso:country":"IT",
    "sg:address":"20123 Milano",
    "sg:city":"Milano",
    "sg:orig_category":"Servizi Editoriali. Professionisti - Studi E Servizi Ed Associazioni Di Interesse Aziendale",
    "sg:phone":"+39 02 836 1578",
    "sg:postcode":"20123",
    "sg:province":"Milano",
    "wof:name":"Goj Emilio",
    "wof:placetype":"venue"
},
  "geometry": {"coordinates":[9.178435,45.453114],"type":"Point"}
}