{
  "type": "Feature",
  "properties": {
    "iso:country":"IT",
    "sg:address":"1, Contrada Ornano Grande 64042 Colledara",
    "sg:city":"Colledara",
    "sg:classifiers":[
        {
            "category":"Utilities",
            "subcategory":"Electric",
            "type":"Services"
        }
    ],
    "sg:phone":"+39 0861 698479",
    "sg:postcode":"64042",
    "sg:province":"Teramo",
    "sg:tags":[
        "component",
        "electronic"
    ],
    "wof:name":"M.t.a. Elettronica Dei F.lli Martucci (s.n.c.)",
    "wof:placetype":"venue"
},
  "geometry": {"coordinates":[13.698531,42.66127],"type":"Point"}
}