{
  "type": "Feature",
  "properties": {
    "addr:full":"30020 Fossalta Di Piave Fossalta di Piave Venezia 30020",
    "addr:postcode":"30020;30020",
    "iso:country":"IT",
    "sg:address":"30020 Fossalta Di Piave",
    "sg:city":"Fossalta di Piave",
    "sg:orig_category":"Frigotecnica, Apparecchiature E Servizi. Climatizzazione E Condizionamento, Apparecchiature E Servizi",
    "sg:phone":"+39 0421 67221",
    "sg:postcode":"30020",
    "sg:province":"Venezia",
    "wof:name":"Elve S.r.l.",
    "wof:placetype":"venue"
},
  "geometry": {"coordinates":[12.9704551697,45.810092926],"type":"Point"}
}