{
  "type": "Feature",
  "properties": {
    "iso:country":"IT",
    "sg:address":"20093 Cologno Monzese",
    "sg:city":"Cologno Monzese",
    "sg:orig_category":"Macchine Ed Impianti Per Edilizia E Lavori Pubblici. Apparecchiature Ed Attrezzature Meccaniche",
    "sg:phone":"+39 02 2730 4374",
    "sg:postcode":"20093",
    "sg:province":"Milano",
    "wof:name":"Vibrotec Snc",
    "wof:placetype":"venue"
},
  "geometry": {"coordinates":[9.26615,45.535221],"type":"Point"}
}