{
  "type": "Feature",
  "properties": {
    "iso:country":"IT",
    "sg:address":"88100 Catanzaro",
    "sg:city":"Catanzaro",
    "sg:orig_category":"Non-classified Establishments",
    "sg:phone":"+39 0961 738713",
    "sg:postcode":"88100",
    "sg:province":"Catanzaro",
    "wof:name":"Rizzuto Giovanni",
    "wof:placetype":"venue"
},
  "geometry": {"coordinates":[16.611887,38.825706],"type":"Point"}
}