{
  "type": "Feature",
  "properties": {
    "iso:country":"IT",
    "sg:address":"09018 Sarroch",
    "sg:city":"Sarroch",
    "sg:orig_category":"Petroli, Gas E Combustibili. Servizi E Lavori Industria Chimica",
    "sg:phone":"+39 070 900193",
    "sg:postcode":"09018",
    "sg:province":"Cagliari",
    "wof:name":"Saras (s.p.a.)",
    "wof:placetype":"venue"
},
  "geometry": {"coordinates":[9.0259847641,39.0758323669],"type":"Point"}
}