{
  "type": "Feature",
  "properties": {
    "iso:country":"IT",
    "sg:address":"Regione Monforte 3 14053 Canelli",
    "sg:city":"Canelli",
    "sg:classifiers":[
        {
            "category":"Wholesale",
            "subcategory":"Medical Equipment & Supplies",
            "type":"Manufacturing & Wholesale Goods"
        }
    ],
    "sg:phone":"+39 0141 835075",
    "sg:postcode":"14053",
    "sg:province":"Asti",
    "sg:tags":[
        "hospital",
        "waste",
        "container"
    ],
    "sg:website":"www.aptaca.it",
    "wof:name":"Nuova Aptaca S.r.l.",
    "wof:placetype":"venue"
},
  "geometry": {"coordinates":[8.302933,44.717979],"type":"Point"}
}