{
  "type": "Feature",
  "properties": {
    "iso:country":"IT",
    "sg:address":"11020 Pollein",
    "sg:city":"Pollein",
    "sg:classifiers":[
        {
            "category":"Bars & Pubs",
            "subcategory":"Oxygen Bar",
            "type":"Food & Drink"
        }
    ],
    "sg:phone":"+39 0165 253604",
    "sg:postcode":"11020",
    "sg:province":"Aosta",
    "sg:tags":[
        "liqueurs",
        "drinks",
        "shopping",
        "wine"
    ],
    "sg:website":"http://www.compagnieantichefattorie.com",
    "wof:name":"Compagnie Antiche Fattorie Di Lara Belgrado",
    "wof:placetype":"venue"
},
  "geometry": {"coordinates":[7.353752,45.728092],"type":"Point"}
}