{
  "type": "Feature",
  "properties": {
    "addr:full":"8, Via Santa Croce 20122 Milano Milano Milano 20122",
    "addr:postcode":"20122;20122",
    "addr:street":"Via Santa Croce",
    "iso:country":"IT",
    "sg:address":"8, Via Santa Croce 20122 Milano",
    "sg:city":"Milano",
    "sg:classifiers":[
        {
            "category":"Professional",
            "subcategory":"Engineering",
            "type":"Services"
        }
    ],
    "sg:phone":"+39 39028378958",
    "sg:postcode":"20122",
    "sg:province":"Milano",
    "sg:tags":[
        "machine",
        "-",
        "mechanical"
    ],
    "wof:name":"Formac (s.r.l.)",
    "wof:placetype":"venue"
},
  "geometry": {"coordinates":[9.183733,45.455959],"type":"Point"}
}