{
  "type": "Feature",
  "properties": {
    "iso:country":"IT",
    "sg:address":"4/2, Via Saliceto 40010 Bentivoglio",
    "sg:city":"Bentivoglio",
    "sg:classifiers":[
        {
            "category":"Manufacturing",
            "subcategory":"Metals",
            "type":"Manufacturing & Wholesale Goods"
        }
    ],
    "sg:phone":"+39 39051860644",
    "sg:postcode":"40010",
    "sg:province":"Bologna",
    "sg:tags":[
        "processing"
    ],
    "wof:name":"Tosi Fratelli",
    "wof:placetype":"venue"
},
  "geometry": {"coordinates":[11.3818778992,44.5712509155],"type":"Point"}
}