{
  "type": "Feature",
  "properties": {
    "addr:full":"20122 Milano Milano Milano 20122",
    "addr:postcode":"20122;20122",
    "iso:country":"IT",
    "sg:address":"20122 Milano",
    "sg:city":"Milano",
    "sg:orig_category":"Pubblicita', Marketing E Comunicazione",
    "sg:phone":"+39 02 794715",
    "sg:postcode":"20122",
    "sg:province":"Milano",
    "wof:name":"Federazione Industria Musicale Italiana",
    "wof:placetype":"venue"
},
  "geometry": {"coordinates":[9.196805954,45.4597930908],"type":"Point"}
}