{
  "type": "Feature",
  "properties": {
    "iso:country":"IT",
    "sg:address":"20149 Milano",
    "sg:city":"Milano",
    "sg:orig_category":"Macchine, Impianti Ed Attrezzature Industria Chimica. Vetro: Prodotti E Lavorazioni",
    "sg:phone":"+39 02 4391 1745",
    "sg:postcode":"20149",
    "sg:province":"Milano",
    "wof:name":"Vetrerie Bruni Srl",
    "wof:placetype":"venue"
},
  "geometry": {"coordinates":[9.148067,45.475773],"type":"Point"}
}