{
  "type": "Feature",
  "properties": {
    "iso:country":"IT",
    "sg:address":"12060 Verduno",
    "sg:city":"Verduno",
    "sg:orig_category":"Prodotti Alimentari",
    "sg:phone":"+39 0172 470272",
    "sg:postcode":"12060",
    "sg:province":"Cuneo",
    "wof:name":"Panealba Di Bergese Caterina & C. Snc",
    "wof:placetype":"venue"
},
  "geometry": {"coordinates":[7.9281620979,44.6754837036],"type":"Point"}
}