{
  "type": "Feature",
  "properties": {
    "iso:country":"IT",
    "sg:address":"236, Via Roma 06061 Castiglione Del Lago",
    "sg:city":"Castiglione del Lago",
    "sg:classifiers":[
        {
            "category":"Food & Beverages",
            "subcategory":"Groceries & Convenience Stores",
            "type":"Retail Goods"
        }
    ],
    "sg:phone":"+39 075 965 2493",
    "sg:postcode":"06061",
    "sg:province":"Perugia",
    "sg:tags":[
        "drink"
    ],
    "wof:name":"Cantina Del Trasimeno Soc.coop.a R.l.",
    "wof:placetype":"venue"
},
  "geometry": {"coordinates":[12.04409,43.122864],"type":"Point"}
}