{
  "type": "Feature",
  "properties": {
    "iso:country":"IT",
    "sg:address":"28, Via Turati Filippo 20121 Milano",
    "sg:city":"Milano",
    "sg:classifiers":[
        {
            "category":"Wholesale",
            "subcategory":"Drugs",
            "type":"Manufacturing & Wholesale Goods"
        }
    ],
    "sg:phone":"+39 02 2901 3593",
    "sg:postcode":"20121",
    "sg:province":"Milano",
    "sg:tags":[
        "chemical",
        "pharmaceutical"
    ],
    "wof:name":"Parexel International S.r.l.",
    "wof:placetype":"venue"
},
  "geometry": {"coordinates":[9.195099,45.476337],"type":"Point"}
}