{
  "type": "Feature",
  "properties": {
    "iso:country":"IT",
    "sg:address":"Via Picca' Grolli, 2 Quater 35030 Rubano",
    "sg:city":"Rubano",
    "sg:classifiers":[
        {
            "category":"Shopping",
            "subcategory":"Hobbies, Toys, & Games",
            "type":"Retail Goods"
        }
    ],
    "sg:phone":"+39 049 897 6176",
    "sg:postcode":"35030",
    "sg:province":"Padova",
    "sg:tags":[
        "video"
    ],
    "sg:website":"www.elmac.com",
    "wof:name":"Elmac Di Tredese Tiziano",
    "wof:placetype":"venue"
},
  "geometry": {"coordinates":[11.876589,45.409569],"type":"Point"}
}