{
  "type": "Feature",
  "properties": {
    "iso:country":"IT",
    "sg:address":"8, Via Loc. Madonna Dei Campi 27030 Castelnovetto",
    "sg:city":"Castelnovetto",
    "sg:classifiers":[
        {
            "category":"Manufacturing",
            "subcategory":"Rubber & Plastics",
            "type":"Manufacturing & Wholesale Goods"
        }
    ],
    "sg:phone":"+39 0384 679229",
    "sg:postcode":"27030",
    "sg:province":"Pavia",
    "wof:name":"R.t.m. S.r.l.",
    "wof:placetype":"venue"
},
  "geometry": {"coordinates":[9.1565628052,45.1858863831],"type":"Point"}
}