{
  "type": "Feature",
  "properties": {
    "iso:country":"IT",
    "sg:address":"06059 Todi",
    "sg:city":"Todi",
    "sg:orig_category":"Ristorazione E Locali Pubblici Affini. Servizi Per Lo Sport E Il Tempo Libero. Alberghi E Strutture Extra Alberghiere. Ristoranti Ed Esercizi Affini",
    "sg:phone":"+39 075 894 5225",
    "sg:postcode":"06059",
    "sg:province":"Perugia",
    "sg:website":"http://www.anticogelso.it",
    "wof:name":"L'antico Gelso Srl",
    "wof:placetype":"venue"
},
  "geometry": {"coordinates":[12.415133,42.788071],"type":"Point"}
}