{
  "type": "Feature",
  "properties": {
    "iso:country":"IT",
    "sg:address":"Via Spagna 20 37069 Villafranca Di Verona",
    "sg:city":"Villafranca di Verona",
    "sg:classifiers":[
        {
            "category":"Food & Beverages",
            "subcategory":"Chocolate",
            "type":"Retail Goods"
        }
    ],
    "sg:phone":"+39 045 630 4380",
    "sg:postcode":"37069",
    "sg:province":"Verona",
    "sg:website":"www.socado.com",
    "wof:name":"Socado Societa' Alimentare Dolciaria Srl",
    "wof:placetype":"venue"
},
  "geometry": {"coordinates":[10.859742,45.36911],"type":"Point"}
}