{
  "type": "Feature",
  "properties": {
    "iso:country":"IT",
    "sg:address":"40064 Ozzano Dell'emilia",
    "sg:orig_category":"Impiantistica E Prodotti Tecnologici Per Edilizia. Forniture Industriali Per Prevenzione, Controllo E Sicurezza",
    "sg:phone":"+39 051 790197",
    "sg:postcode":"40064",
    "sg:province":"Bologna",
    "sg:website":"http://www.systemline.com",
    "wof:name":"System Line Srl",
    "wof:placetype":"venue"
},
  "geometry": {"coordinates":[11.46176,44.508011],"type":"Point"}
}