{
  "type": "Feature",
  "properties": {
    "iso:country":"IT",
    "sg:address":"13, Via Boito Arrigo 20026 Novate Milanese",
    "sg:city":"Novate Milanese",
    "sg:classifiers":[
        {
            "category":"Shopping",
            "subcategory":"Crafts & Fabrics",
            "type":"Retail Goods"
        }
    ],
    "sg:phone":"+39 39023548834",
    "sg:postcode":"20026",
    "sg:province":"Milano",
    "wof:name":"Josar Srl",
    "wof:placetype":"venue"
},
  "geometry": {"coordinates":[9.1522130966,45.5294075012],"type":"Point"}
}