{
  "type": "Feature",
  "properties": {
    "addr:full":"Via E Morsini 20; Roma",
    "addr:housenumber":"20",
    "addr:street":"Via E Morsini",
    "iso:country":"IT",
    "sg:address":"Via E Morsini 20; Roma",
    "sg:classifiers":[
        {
            "category":"Banks & Credit Unions",
            "subcategory":"Bank",
            "type":"Services"
        }
    ],
    "sg:phone":"+39 06 5833 2258",
    "wof:name":"Cassa Di Risparmio In Bologna Spa",
    "wof:placetype":"venue"
},
  "geometry": {"coordinates":[12.468719,41.886082],"type":"Point"}
}