{
  "type": "Feature",
  "properties": {
    "iso:country":"IT",
    "sg:address":"73010 Surbo",
    "sg:city":"Surbo",
    "sg:orig_category":"Nautica. Automobili E Mezzi Di Trasporto",
    "sg:phone":"+39 0832 361922",
    "sg:postcode":"73010",
    "sg:province":"Lecce",
    "wof:name":"Nautica Di Calvara Bruno",
    "wof:placetype":"venue"
},
  "geometry": {"coordinates":[18.126532,40.390442],"type":"Point"}
}