{
  "type": "Feature",
  "properties": {
    "iso:country":"IT",
    "sg:address":"34, V. Val Di Lima55022 Bagni Di Lucca",
    "sg:city":"Bagni di Lucca",
    "sg:orig_category":"Miscellaneous Products",
    "sg:phone":"+39 39058387882",
    "sg:postcode":"55022",
    "sg:province":"Lucca",
    "sg:website":"http://www.artebarsanti.it",
    "wof:name":"Arte Barsanti Di Fiori Simone",
    "wof:placetype":"venue"
},
  "geometry": {"coordinates":[10.5079936981,43.8430137634],"type":"Point"}
}