{
  "type": "Feature",
  "properties": {
    "iso:country":"IT",
    "sg:address":"42011 Bagnolo In Piano",
    "sg:orig_category":"Sabbiatura Metalli",
    "sg:phone":"+39 0522 951596",
    "sg:postcode":"42011",
    "sg:province":"Reggio Nell'Emilia",
    "wof:name":"Nuova S.m. Di Ronzoni Giorgio Snc",
    "wof:placetype":"venue"
},
  "geometry": {"coordinates":[10.614964,44.706955],"type":"Point"}
}