{
  "type": "Feature",
  "properties": {
    "addr:full":"27, V. Saturno 37135 Verona Verona Verona 37135",
    "addr:housenumber":"27",
    "addr:postcode":"37135;37135",
    "addr:street":"V. Saturno",
    "iso:country":"IT",
    "sg:address":"27, V. Saturno 37135 Verona",
    "sg:city":"Verona",
    "sg:classifiers":[
        {
            "category":"Sports & Exercise",
            "subcategory":"Playing Field",
            "type":"Entertainment"
        }
    ],
    "sg:phone":"+39 045 856 9142",
    "sg:postcode":"37135",
    "sg:province":"Verona",
    "sg:tags":[
        "game"
    ],
    "sg:website":"http://www.loralflags.com",
    "wof:name":"Loral",
    "wof:placetype":"venue"
},
  "geometry": {"coordinates":[10.971216,45.388832],"type":"Point"}
}