{
  "type": "Feature",
  "properties": {
    "iso:country":"IT",
    "sg:address":"18027 Sarola",
    "sg:orig_category":"Macchine, Impianti Ed Attrezzature Per Agricoltura E Zootecnia",
    "sg:phone":"+39 0183 5211",
    "sg:postcode":"18027",
    "sg:province":"Imperia",
    "wof:name":"Euroemme Spa",
    "wof:placetype":"venue"
},
  "geometry": {"coordinates":[7.996741,43.955482],"type":"Point"}
}