{
  "type": "Feature",
  "properties": {
    "addr:full":"25023 Gottolengo Gottolengo Brescia 25023",
    "addr:postcode":"25023;25023",
    "iso:country":"IT",
    "sg:address":"25023 Gottolengo",
    "sg:city":"Gottolengo",
    "sg:orig_category":"Casalinghi",
    "sg:phone":"+39 030 995 1233",
    "sg:postcode":"25023",
    "sg:province":"Brescia",
    "sg:website":"http://www.gottinghen.it",
    "wof:name":"Gottinghen Spa",
    "wof:placetype":"venue"
},
  "geometry": {"coordinates":[10.209789,45.305996],"type":"Point"}
}