{
  "type": "Feature",
  "properties": {
    "addr:full":"15040 Valmadonna Valmadonna Alessandria 15040",
    "addr:postcode":"15040;15040",
    "iso:country":"IT",
    "sg:address":"15040 Valmadonna",
    "sg:city":"Valmadonna",
    "sg:orig_category":"Prodotti Vari In Metallo",
    "sg:phone":"+39 0131 507671",
    "sg:postcode":"15040",
    "sg:province":"Alessandria",
    "wof:name":"Giuntani Luciano",
    "wof:placetype":"venue"
},
  "geometry": {"coordinates":[8.6099243164,44.9714851379],"type":"Point"}
}