{
  "type": "Feature",
  "properties": {
    "iso:country":"IT",
    "sg:address":"22100 Como",
    "sg:city":"Como",
    "sg:orig_category":"Spedizioni Aeree, Marittime E Terrestri",
    "sg:phone":"+39 031 542252",
    "sg:postcode":"22100",
    "sg:province":"Como",
    "wof:name":"E. Garofano E C. Pratiche Doganali Sas",
    "wof:placetype":"venue"
},
  "geometry": {"coordinates":[9.03629,45.832966],"type":"Point"}
}