{
  "type": "Feature",
  "properties": {
    "iso:country":"IT",
    "sg:address":"4, Via De Lai 39100 Bolzano",
    "sg:city":"Bolzano",
    "sg:orig_category":"Miscellaneous Products",
    "sg:phone":"+39 0471 971405",
    "sg:postcode":"39100",
    "sg:province":"Bolzano/Bozen",
    "wof:name":"Weigang Organisation",
    "wof:placetype":"venue"
},
  "geometry": {"coordinates":[11.3282394409,46.461643219],"type":"Point"}
}