{
  "type": "Feature",
  "properties": {
    "iso:country":"IT",
    "sg:address":"13060 Roasio",
    "sg:city":"Roasio",
    "sg:orig_category":"Prodotti E Manufatti In Materie Plastiche",
    "sg:phone":"+39 0163 860396",
    "sg:postcode":"13060",
    "sg:province":"Vercelli",
    "wof:name":"Tecnovinil Spa",
    "wof:placetype":"venue"
},
  "geometry": {"coordinates":[8.2784786224,45.5936889648],"type":"Point"}
}