{
  "type": "Feature",
  "properties": {
    "iso:country":"IT",
    "sg:address":"51017 Pescia",
    "sg:city":"Pescia",
    "sg:orig_category":"Articoli Per Imballaggio E Confezionamento. Forniture Per Uffici. Forniture Per Attivita' Commerciali Ed Artigianali",
    "sg:phone":"+39 0583 478023",
    "sg:postcode":"51017",
    "sg:province":"Pistoia",
    "wof:name":"A.t.d. Di Dreucci Carlo",
    "wof:placetype":"venue"
},
  "geometry": {"coordinates":[10.775805,44.024403],"type":"Point"}
}