{
  "type": "Feature",
  "properties": {
    "iso:country":"IT",
    "sg:address":"03043 Cassino",
    "sg:city":"Cassino",
    "sg:orig_category":"Servizi Ausiliari Per Il Trasporto. Servizi Vari Di Interesse Pubblico",
    "sg:phone":"+39 0776 325604",
    "sg:postcode":"03043",
    "sg:province":"Frosinone",
    "wof:name":"Onoranze Funebri Cece",
    "wof:placetype":"venue"
},
  "geometry": {"coordinates":[13.36665,41.629826],"type":"Point"}
}