{
  "type": "Feature",
  "properties": {
    "addr:full":"86039 Termoli Termoli Campobasso 86039",
    "addr:postcode":"86039;86039",
    "iso:country":"IT",
    "sg:address":"86039 Termoli",
    "sg:city":"Termoli",
    "sg:orig_category":"Arredamento Uffici",
    "sg:phone":"+39 0875 709912",
    "sg:postcode":"86039",
    "sg:province":"Campobasso",
    "wof:name":"Tecnooffice Di Tozzi Aurelio",
    "wof:placetype":"venue"
},
  "geometry": {"coordinates":[14.99728,42.000889],"type":"Point"}
}