{
  "type": "Feature",
  "properties": {
    "addr:full":"20094 Corsico Corsico Milano 20094",
    "addr:postcode":"20094;20094",
    "iso:country":"IT",
    "sg:address":"20094 Corsico",
    "sg:city":"Corsico",
    "sg:orig_category":"Forniture Per Attivita' Industriali",
    "sg:phone":"+39 02 4860 0606",
    "sg:postcode":"20094",
    "sg:province":"Milano",
    "sg:website":"http://www.coatem.it",
    "wof:name":"Coatem Srl",
    "wof:placetype":"venue"
},
  "geometry": {"coordinates":[9.1067295074,45.4457511902],"type":"Point"}
}