{
  "type": "Feature",
  "properties": {
    "iso:country":"IT",
    "sg:address":"00192 Roma",
    "sg:city":"Roma",
    "sg:orig_category":"Servizi Culturali E Per Lo Spettacolo. Servizi Al Turismo. Acqua, Luce, Gas E Societa' Di Esercizio Pubblico",
    "sg:phone":"+39 06 6880 1020",
    "sg:postcode":"00192",
    "sg:province":"Roma",
    "wof:name":"Museo Storico Dell'arma Dei Carabinieri",
    "wof:placetype":"venue"
},
  "geometry": {"coordinates":[12.450273,42.10537],"type":"Point"}
}