{
  "type": "Feature",
  "properties": {
    "iso:country":"IT",
    "sg:address":"41, Via Del Ponte Alle Riffe 50133 Firenze",
    "sg:city":"Firenze",
    "sg:classifiers":[
        {
            "category":"Shopping",
            "subcategory":"Jewelry",
            "type":"Retail Goods"
        }
    ],
    "sg:phone":"+39 39055571353",
    "sg:postcode":"50133",
    "sg:province":"Firenze",
    "sg:tags":[
        "jewellery"
    ],
    "wof:name":"Meli",
    "wof:placetype":"venue"
},
  "geometry": {"coordinates":[11.270001,43.789612],"type":"Point"}
}