{
  "type": "Feature",
  "properties": {
    "iso:country":"IT",
    "sg:address":"92025 Casteltermini",
    "sg:city":"Casteltermini",
    "sg:orig_category":"Antiquariato",
    "sg:phone":"+39 0922 916650",
    "sg:postcode":"92025",
    "sg:province":"Agrigento",
    "wof:name":"Super Mobili P. Capozza",
    "wof:placetype":"venue"
},
  "geometry": {"coordinates":[13.61085,37.284756],"type":"Point"}
}