{
  "type": "Feature",
  "properties": {
    "iso:country":"IT",
    "sg:address":"20154 Milano",
    "sg:city":"Milano",
    "sg:orig_category":"Bevande, Vini E Liquori",
    "sg:phone":"+39 02 3493 8185",
    "sg:postcode":"20154",
    "sg:province":"Milano",
    "wof:name":"Studio Cbcr S.r.l.",
    "wof:placetype":"venue"
},
  "geometry": {"coordinates":[9.168768,45.490597],"type":"Point"}
}