{
  "type": "Feature",
  "properties": {
    "addr:full":"35010 Campodoro Campodoro Padova 35010",
    "addr:postcode":"35010;35010",
    "iso:country":"IT",
    "sg:address":"35010 Campodoro",
    "sg:city":"Campodoro",
    "sg:orig_category":"Lucernari",
    "sg:phone":"+39 049 906 5125",
    "sg:postcode":"35010",
    "sg:province":"Padova",
    "sg:website":"http://www.campesato.com",
    "wof:name":"Campesato Guido & C. Snc",
    "wof:placetype":"venue"
},
  "geometry": {"coordinates":[11.115941,45.418343],"type":"Point"}
}