{
  "type": "Feature",
  "properties": {
    "addr:full":"14, Via Neo Ottoni 40026 Imola Imola Bologna 40026",
    "addr:postcode":"40026;40026",
    "addr:street":"Via Neo Ottoni",
    "iso:country":"IT",
    "sg:address":"14, Via Neo Ottoni 40026 Imola",
    "sg:city":"Imola",
    "sg:classifiers":[
        {
            "category":"Wholesale",
            "subcategory":"Machinery & Supplies",
            "type":"Manufacturing & Wholesale Goods"
        }
    ],
    "sg:phone":"+39 0542 640044",
    "sg:postcode":"40026",
    "sg:province":"Bologna",
    "sg:tags":[
        "-",
        "agriculture",
        "equipment"
    ],
    "wof:name":"Mattioli Aratri (s.n.c.)",
    "wof:placetype":"venue"
},
  "geometry": {"coordinates":[11.720532,44.374161],"type":"Point"}
}