{
  "type": "Feature",
  "properties": {
    "addr:full":"72026 San Pancrazio Salentino San Pancrazio Salentino Brindisi 72026",
    "addr:housenumber":"72026;salentino",
    "addr:postcode":"salentino;72026",
    "addr:street":"San",
    "iso:country":"IT",
    "sg:address":"72026 San Pancrazio Salentino",
    "sg:city":"San Pancrazio Salentino",
    "sg:orig_category":"Medici. Assicurazioni E Servizi Assicurativi. Avvocati, Notai E Servizi Legali. Professionisti - Studi E Servizi Ed Associazioni Di Interesse Aziendale",
    "sg:phone":"+39 0831 666173",
    "sg:postcode":"72026",
    "sg:province":"Brindisi",
    "wof:name":"Ap Ce.s.m.i.t. Srl",
    "wof:placetype":"venue"
},
  "geometry": {"coordinates":[17.9251728058,40.4483375549],"type":"Point"}
}