{
  "type": "Feature",
  "properties": {
    "iso:country":"IT",
    "sg:address":"Via Calzoni Alfredo 2 40128 Bologna",
    "sg:city":"Bologna",
    "sg:classifiers":[
        {
            "category":"Utilities",
            "subcategory":"Cable",
            "type":"Services"
        }
    ],
    "sg:phone":"+39 051 631 9411",
    "sg:postcode":"40128",
    "sg:province":"Bologna",
    "sg:tags":[
        "machine",
        "take-up"
    ],
    "sg:website":"www.sampsistemi.it",
    "wof:name":"Sampsistemi Spa",
    "wof:placetype":"venue"
},
  "geometry": {"coordinates":[11.346481,44.494221],"type":"Point"}
}