{
  "type": "Feature",
  "properties": {
    "iso:country":"IT",
    "sg:address":"37/39, Strada Bairo 10081 Castellamonte",
    "sg:city":"Castellamonte",
    "sg:classifiers":[
        {
            "category":"Autos & Motor Vehicles",
            "subcategory":"Automobile Sales",
            "type":"Retail Goods"
        }
    ],
    "sg:phone":"+39 0124 581808",
    "sg:postcode":"10081",
    "sg:province":"Torino",
    "sg:tags":[
        "industrial"
    ],
    "wof:name":"Lag Auto S.r.l.",
    "wof:placetype":"venue"
},
  "geometry": {"coordinates":[7.731704,45.385906],"type":"Point"}
}