{
  "type": "Feature",
  "properties": {
    "iso:country":"IT",
    "sg:address":"55049 Viareggio",
    "sg:city":"Viareggio",
    "sg:orig_category":"Nautica. Automobili E Mezzi Di Trasporto",
    "sg:phone":"+39 0584 384722",
    "sg:postcode":"55049",
    "sg:province":"Lucca",
    "wof:name":"International Mackenzie Srl",
    "wof:placetype":"venue"
},
  "geometry": {"coordinates":[10.24331,43.862305],"type":"Point"}
}