{
  "type": "Feature",
  "properties": {
    "iso:country":"IT",
    "sg:address":"10081 Castellamonte",
    "sg:city":"Castellamonte",
    "sg:orig_category":"Lavorazioni Metalli, Stampaggio E Saldatura",
    "sg:phone":"+39 0124 518555",
    "sg:postcode":"10081",
    "sg:province":"Torino",
    "wof:name":"Massucco Industrie Spa",
    "wof:placetype":"venue"
},
  "geometry": {"coordinates":[7.656714,45.387421],"type":"Point"}
}