{
  "type": "Feature",
  "properties": {
    "addr:full":"18, Via Industria 22070 Luisago Luisago Como 22070",
    "addr:postcode":"22070;22070",
    "addr:street":"Via Industria",
    "iso:country":"IT",
    "sg:address":"18, Via Industria 22070 Luisago",
    "sg:city":"Luisago",
    "sg:classifiers":[
        {
            "category":"Shopping",
            "subcategory":"Clothing, Apparel, & Fashions",
            "type":"Retail Goods"
        }
    ],
    "sg:phone":"+39 39031929044",
    "sg:postcode":"22070",
    "sg:province":"Como",
    "sg:tags":[
        "clothing",
        "accessory"
    ],
    "wof:name":"Ostinelli Seta Spa",
    "wof:placetype":"venue"
},
  "geometry": {"coordinates":[9.055482,45.761963],"type":"Point"}
}