{
  "type": "Feature",
  "properties": {
    "iso:country":"IT",
    "sg:address":"22036 Erba",
    "sg:city":"Erba",
    "sg:orig_category":"Accessori Dei Mezzi Di Trasporto. Riparazione Dei Mezzi Di Trasporto",
    "sg:phone":"+39 031 627632",
    "sg:postcode":"22036",
    "sg:province":"Como",
    "wof:name":"Giussani Giorgio",
    "wof:placetype":"venue"
},
  "geometry": {"coordinates":[9.166714,45.779671],"type":"Point"}
}