{
  "type": "Feature",
  "properties": {
    "iso:country":"IT",
    "sg:address":"6, Via Dell' Artigianato 13040 Rovasenda",
    "sg:city":"Rovasenda",
    "sg:classifiers":[
        {
            "category":"Manufacturing",
            "subcategory":"Lumber",
            "type":"Manufacturing & Wholesale Goods"
        }
    ],
    "sg:phone":"+39 0161 879797",
    "sg:postcode":"13040",
    "sg:province":"Vercelli",
    "sg:tags":[
        "wood"
    ],
    "wof:name":"Basso Legnami S.r.l.",
    "wof:placetype":"venue"
},
  "geometry": {"coordinates":[8.305339,45.535809],"type":"Point"}
}