{
  "type": "Feature",
  "properties": {
    "iso:country":"IT",
    "sg:address":"4, Via Giuseppe Mazzini 25037 Pontoglio",
    "sg:city":"Pontoglio",
    "sg:classifiers":[
        {
            "category":"Wholesale",
            "subcategory":"Machinery & Supplies",
            "type":"Manufacturing & Wholesale Goods"
        }
    ],
    "sg:phone":"+39 030 747 0901",
    "sg:postcode":"25037",
    "sg:province":"Brescia",
    "sg:tags":[
        "equipment",
        "-",
        "instrument",
        "measurement"
    ],
    "wof:name":"I.d.f. Srl",
    "wof:placetype":"venue"
},
  "geometry": {"coordinates":[9.855825,45.57679],"type":"Point"}
}