{
  "type": "Feature",
  "properties": {
    "addr:full":"17031 Albenga Albenga Savona 17031",
    "addr:postcode":"17031;17031",
    "iso:country":"IT",
    "sg:address":"17031 Albenga",
    "sg:city":"Albenga",
    "sg:classifiers":[
        {
            "category":"Sports & Exercise",
            "subcategory":"Tennis Court",
            "type":"Entertainment"
        }
    ],
    "sg:phone":"+39 0182 543739",
    "sg:postcode":"17031",
    "sg:province":"Savona",
    "sg:tags":[
        "e",
        "lo",
        "tempo",
        "libero",
        "per",
        "impianti",
        "il",
        "attrezzature"
    ],
    "wof:name":"Ramasso Piscine Sas",
    "wof:placetype":"venue"
},
  "geometry": {"coordinates":[8.188495,44.058578],"type":"Point"}
}