{
  "type": "Feature",
  "properties": {
    "iso:country":"IT",
    "sg:address":"299, Via Idice 40050 Monterenzio",
    "sg:city":"Monterenzio",
    "sg:classifiers":[
        {
            "category":"Food & Beverages",
            "subcategory":"Bakery",
            "type":"Retail Goods"
        }
    ],
    "sg:phone":"+39 39051920283",
    "sg:postcode":"40050",
    "sg:province":"Bologna",
    "sg:tags":[
        "grain",
        "cereal"
    ],
    "wof:name":"Conapi S.c.r.l. Consorzio Apicoltori E Agricoltori Biologici Italiani",
    "wof:placetype":"venue"
},
  "geometry": {"coordinates":[11.439822,44.430504],"type":"Point"}
}