{
  "type": "Feature",
  "properties": {
    "addr:full":"70052 Bisceglie Bisceglie Bari 70052",
    "addr:postcode":"70052;70052",
    "iso:country":"IT",
    "sg:address":"70052 Bisceglie",
    "sg:city":"Bisceglie",
    "sg:orig_category":"Forniture Per Congressi, Fiere E Manifestazioni",
    "sg:phone":"+39 080 395 3862",
    "sg:postcode":"70052",
    "sg:province":"Bari",
    "wof:name":"Academy - Arte Musica Spettacolo",
    "wof:placetype":"venue"
},
  "geometry": {"coordinates":[16.4759254456,41.2100715637],"type":"Point"}
}