{
  "type": "Feature",
  "properties": {
    "iso:country":"IT",
    "sg:address":"Piazza Vittorio Emanuele; Avio; 38063",
    "sg:city":"Avio",
    "sg:classifiers":[
        {
            "category":"Banks & Credit Unions",
            "subcategory":"Bank",
            "type":"Services"
        }
    ],
    "sg:phone":"+39 0464 64040",
    "sg:postcode":"38063",
    "sg:province":"Trento",
    "wof:name":"Casse Rurali Di Ala",
    "wof:placetype":"venue"
},
  "geometry": {"coordinates":[10.940996,45.735096],"type":"Point"}
}