{
  "type": "Feature",
  "properties": {
    "iso:country":"IT",
    "sg:address":"31033 Castelfranco Veneto",
    "sg:city":"Castelfranco Veneto",
    "sg:orig_category":"Macchine Utensili E Impianti",
    "sg:phone":"+39 0423 723040",
    "sg:postcode":"31033",
    "sg:province":"Treviso",
    "wof:name":"Kuntec Srl",
    "wof:placetype":"venue"
},
  "geometry": {"coordinates":[11.951897,45.67329],"type":"Point"}
}