{
  "type": "Feature",
  "properties": {
    "iso:country":"IT",
    "sg:address":"21015 Lonate Pozzolo",
    "sg:city":"Lonate Pozzolo",
    "sg:orig_category":"Acciaierie E Fonderie",
    "sg:phone":"+39 0331 668075",
    "sg:postcode":"21015",
    "sg:province":"Varese",
    "wof:name":"Santa Caterina Di Toniolo Gianfranco & C. Sas",
    "wof:placetype":"venue"
},
  "geometry": {"coordinates":[8.780088,45.597122],"type":"Point"}
}