{
  "type": "Feature",
  "properties": {
    "iso:country":"IT",
    "sg:address":"10148 Torino",
    "sg:city":"Torino",
    "sg:orig_category":"Trasporti E Spedizioni Merci",
    "sg:phone":"+39 011 226 4101",
    "sg:postcode":"10148",
    "sg:province":"Torino",
    "wof:name":"Canavesana Servizi Aziendali Integrati Srl",
    "wof:placetype":"venue"
},
  "geometry": {"coordinates":[7.680319,45.110508],"type":"Point"}
}