{
  "type": "Feature",
  "properties": {
    "addr:full":"13100 Vercelli Vercelli Vercelli 13100",
    "addr:postcode":"13100;13100",
    "iso:country":"IT",
    "sg:address":"13100 Vercelli",
    "sg:city":"Vercelli",
    "sg:orig_category":"Metalli E Leghe",
    "sg:phone":"+39 0161 393969",
    "sg:postcode":"13100",
    "sg:province":"Vercelli",
    "wof:name":"Definis Francesco",
    "wof:placetype":"venue"
},
  "geometry": {"coordinates":[8.3978652954,45.3128356934],"type":"Point"}
}