{
  "type": "Feature",
  "properties": {
    "iso:country":"IT",
    "sg:address":"23811 Ballabio",
    "sg:city":"Ballabio",
    "sg:orig_category":"Minuterie Metalliche E Ferramenta",
    "sg:phone":"+39 0341 531077",
    "sg:postcode":"23811",
    "sg:province":"Lecco",
    "sg:website":"http://www.minutex.net",
    "wof:name":"Minutex Dei F. Lli Paroli Srl",
    "wof:placetype":"venue"
},
  "geometry": {"coordinates":[9.4467821121,45.8900756836],"type":"Point"}
}