{
  "type": "Feature",
  "properties": {
    "iso:country":"IT",
    "sg:address":"36, Via Ca' Bianca 21052 Busto Arsizio",
    "sg:city":"Busto Arsizio",
    "sg:classifiers":[
        {
            "category":"Farming",
            "subcategory":"Livestock Farm",
            "type":"Manufacturing & Wholesale Goods"
        }
    ],
    "sg:phone":"+39 0331 628282",
    "sg:postcode":"21052",
    "sg:province":"Varese",
    "sg:tags":[
        "agriculture"
    ],
    "wof:name":"Mirto Srl",
    "wof:placetype":"venue"
},
  "geometry": {"coordinates":[8.878015,45.613373],"type":"Point"}
}