{
  "type": "Feature",
  "properties": {
    "addr:full":"10099 San Mauro Torinese San Mauro Torinese Torino 10099",
    "addr:housenumber":"10099",
    "addr:postcode":"10099",
    "addr:street":"San",
    "iso:country":"IT",
    "sg:address":"10099 San Mauro Torinese",
    "sg:city":"San Mauro Torinese",
    "sg:orig_category":"Forniture Per Attivita' Industriali",
    "sg:phone":"+39 011 273 4464",
    "sg:postcode":"10099",
    "sg:province":"Torino",
    "sg:website":"http://www.azarticolitecnici.it",
    "wof:name":"Az Service Srl",
    "wof:placetype":"venue"
},
  "geometry": {"coordinates":[7.7563285828,45.0962677002],"type":"Point"}
}