{
  "type": "Feature",
  "properties": {
    "iso:country":"IT",
    "sg:address":"144, V. Circumvallazione 80036 Palma Campania",
    "sg:city":"Palma Campania",
    "sg:classifiers":[
        {
            "category":"Manufacturing",
            "subcategory":"Printing",
            "type":"Manufacturing & Wholesale Goods"
        }
    ],
    "sg:phone":"+39 081 510 1992",
    "sg:postcode":"80036",
    "sg:province":"Napoli",
    "sg:tags":[
        "publishing"
    ],
    "sg:website":"http://www.paginegialle.it/santaniellocosimo",
    "wof:name":"Santaniello Cosimo",
    "wof:placetype":"venue"
},
  "geometry": {"coordinates":[14.5492668152,40.8601303101],"type":"Point"}
}