{
  "type": "Feature",
  "properties": {
    "iso:country":"IT",
    "sg:address":"25123 Brescia",
    "sg:city":"Brescia",
    "sg:orig_category":"Bullonerie",
    "sg:phone":"+39 030 230 6861",
    "sg:postcode":"25123",
    "sg:province":"Brescia",
    "sg:website":"http://www.bsviti.com",
    "wof:name":"Brescia Viti Srl",
    "wof:placetype":"venue"
},
  "geometry": {"coordinates":[10.240229,45.527435],"type":"Point"}
}