{
  "type": "Feature",
  "properties": {
    "iso:country":"IT",
    "sg:address":"61022 Colbordolo",
    "sg:city":"Colbordolo",
    "sg:classifiers":[
        {
            "category":"Professional",
            "subcategory":"Engineering",
            "type":"Services"
        }
    ],
    "sg:phone":"+39 0721 478445",
    "sg:postcode":"61022",
    "sg:province":"Pesaro E Urbino",
    "sg:tags":[
        "equipment",
        "product",
        "industrial",
        "electrical"
    ],
    "wof:name":"Lutan Srl",
    "wof:placetype":"venue"
},
  "geometry": {"coordinates":[12.722537,43.834019],"type":"Point"}
}