{
  "type": "Feature",
  "properties": {
    "iso:country":"IT",
    "sg:address":"51028 San Marcello Pistoiese",
    "sg:city":"San Marcello Pistoiese",
    "sg:orig_category":"Serramenti Ed Infissi",
    "sg:phone":"+39 0573 629319",
    "sg:postcode":"51028",
    "sg:province":"Pistoia",
    "sg:website":"http://www.pmimontagnapistoiese.it/gam",
    "wof:name":"Gam Serramenti Snc",
    "wof:placetype":"venue"
},
  "geometry": {"coordinates":[10.822574,44.055042],"type":"Point"}
}