{
  "type": "Feature",
  "properties": {
    "iso:country":"IT",
    "sg:address":"45100 Rovigo",
    "sg:city":"Rovigo",
    "sg:orig_category":"Articoli Medico-sanitari Ed Ortopedici",
    "sg:phone":"+39 0425 27516",
    "sg:postcode":"45100",
    "sg:province":"Rovigo",
    "wof:name":"Dall'occo Maria Pia",
    "wof:placetype":"venue"
},
  "geometry": {"coordinates":[11.784701,45.075577],"type":"Point"}
}