{
  "type": "Feature",
  "properties": {
    "addr:full":"51100 Pistoia Pistoia Pistoia 51100",
    "addr:postcode":"51100;51100",
    "iso:country":"IT",
    "sg:address":"51100 Pistoia",
    "sg:city":"Pistoia",
    "sg:orig_category":"Macchine Utensili E Impianti",
    "sg:phone":"+39 0573 533067",
    "sg:postcode":"51100",
    "sg:province":"Pistoia",
    "wof:name":"Landucci (s.r.l.)",
    "wof:placetype":"venue"
},
  "geometry": {"coordinates":[10.927833,43.934151],"type":"Point"}
}