{
  "type": "Feature",
  "properties": {
    "addr:full":"20089 Rozzano Rozzano Milano 20089",
    "addr:postcode":"20089;20089",
    "iso:country":"IT",
    "sg:address":"20089 Rozzano",
    "sg:city":"Rozzano",
    "sg:orig_category":"Hobbistica",
    "sg:phone":"+39 02 824 6220",
    "sg:postcode":"20089",
    "sg:province":"Milano",
    "wof:name":"Abafil",
    "wof:placetype":"venue"
},
  "geometry": {"coordinates":[9.166783,45.399185],"type":"Point"}
}