{
  "type": "Feature",
  "properties": {
    "addr:full":"3, Str. Racconigi 12030 Caramagna Piemonte Caramagna Piemonte Cuneo 12030",
    "addr:postcode":"12030;piemonte;12030",
    "addr:street":"Str. Racconigi;Piemonte",
    "iso:country":"IT",
    "sg:address":"3, Str. Racconigi 12030 Caramagna Piemonte",
    "sg:city":"Caramagna Piemonte",
    "sg:classifiers":[
        {
            "category":"Shopping",
            "type":"Retail Goods"
        }
    ],
    "sg:phone":"+39 39017289168",
    "sg:postcode":"12030",
    "sg:province":"Cuneo",
    "sg:tags":[
        "finished",
        "-",
        "metallic"
    ],
    "sg:website":"http://www.giinox.com",
    "wof:name":"Ginox Srl",
    "wof:placetype":"venue"
},
  "geometry": {"coordinates":[7.5471105576,44.38879776],"type":"Point"}
}