{
  "type": "Feature",
  "properties": {
    "addr:full":"68, Corso Umberto I 70058 Spinazzola Spinazzola Bari 70058",
    "addr:postcode":"70058;70058",
    "addr:street":"Corso Umberto I",
    "iso:country":"IT",
    "sg:address":"68, Corso Umberto I 70058 Spinazzola",
    "sg:city":"Spinazzola",
    "sg:orig_category":"Miscellaneous Products",
    "sg:phone":"+39 0883 681782",
    "sg:postcode":"70058",
    "sg:province":"Bari",
    "wof:name":"Red Horse Dei F.lli Michele E Domenico Pizzulli Snc",
    "wof:placetype":"venue"
},
  "geometry": {"coordinates":[16.0904178619,40.9682579041],"type":"Point"}
}