{
  "type": "Feature",
  "properties": {
    "iso:country":"IT",
    "sg:address":"20096 Pioltello",
    "sg:city":"Pioltello",
    "sg:orig_category":"Prodotti Chimici Di Base",
    "sg:phone":"+39 02 926 7205",
    "sg:postcode":"20096",
    "sg:province":"Milano",
    "wof:name":"Chimica L.g.m. Di Bois Laura E Massimiliano S.n.c.",
    "wof:placetype":"venue"
},
  "geometry": {"coordinates":[9.3142356873,45.4921913147],"type":"Point"}
}