{
  "type": "Feature",
  "properties": {
    "iso:country":"IT",
    "sg:address":"Via Nazionale 115 43045 Fornovo Di Taro",
    "sg:city":"Fornovo di Taro",
    "sg:classifiers":[
        {
            "category":"Autos & Motor Vehicles",
            "subcategory":"Automobile Sales",
            "type":"Retail Goods"
        }
    ],
    "sg:phone":"+39 390 525 2741",
    "sg:postcode":"43045",
    "sg:province":"Parma",
    "sg:tags":[
        "motor-cars"
    ],
    "wof:name":"Lombatti Fratelli (s.p.a.)",
    "wof:placetype":"venue"
},
  "geometry": {"coordinates":[10.0963897705,44.6842422485],"type":"Point"}
}