{
  "type": "Feature",
  "properties": {
    "iso:country":"IT",
    "sg:address":"51100 Pontelungo",
    "sg:city":"Pontelungo",
    "sg:orig_category":"Abbigliamento Esterno, Maglierie E Pelliccerie. Forniture Per Abbigliamento E Pelletterie",
    "sg:phone":"+39 0573 571298",
    "sg:postcode":"51100",
    "sg:province":"Pistoia",
    "wof:name":"Tessitura Aleari Di Petrucci Alessandro & C. S.n.c.",
    "wof:placetype":"venue"
},
  "geometry": {"coordinates":[10.8896,43.924564],"type":"Point"}
}