{
  "type": "Feature",
  "properties": {
    "addr:full":"10040 La Loggia La Loggia Torino 10040",
    "addr:housenumber":"10040",
    "addr:postcode":"10040",
    "addr:street":"La",
    "iso:country":"IT",
    "sg:address":"10040 La Loggia",
    "sg:city":"La Loggia",
    "sg:orig_category":"Paste Alimentari - Produzione E Ingrosso",
    "sg:phone":"+39 011 962 8126",
    "sg:postcode":"10040",
    "sg:province":"Torino",
    "wof:name":"Italpasta Spa",
    "wof:placetype":"venue"
},
  "geometry": {"coordinates":[7.6737346649,44.9212417603],"type":"Point"}
}