{
  "type": "Feature",
  "properties": {
    "iso:country":"IT",
    "sg:address":"13895 Muzzano",
    "sg:city":"Muzzano",
    "sg:orig_category":"Zootecnia E Pesca, Allevamento Piccoli Animali",
    "sg:phone":"+39 015 63130",
    "sg:postcode":"13895",
    "sg:province":"Biella",
    "wof:name":"Favre Marino",
    "wof:placetype":"venue"
},
  "geometry": {"coordinates":[7.987638,45.561409],"type":"Point"}
}