{
  "type": "Feature",
  "properties": {
    "iso:country":"IT",
    "sg:address":"35027 Noventa Padovana",
    "sg:city":"Noventa Padovana",
    "sg:classifiers":[
        {
            "category":"Health Services",
            "subcategory":"Health Practitioner",
            "type":"Services"
        }
    ],
    "sg:phone":"+39 049 725087",
    "sg:postcode":"35027",
    "sg:province":"Padova",
    "sg:tags":[
        "medici"
    ],
    "wof:name":"Matarweh Teresa",
    "wof:placetype":"venue"
},
  "geometry": {"coordinates":[11.971463,45.410946],"type":"Point"}
}