{
  "type": "Feature",
  "properties": {
    "iso:country":"IT",
    "sg:address":"261, Via Carriona 54033 Carrara",
    "sg:city":"Carrara",
    "sg:classifiers":[
        {
            "category":"Real Estate",
            "subcategory":"Architect",
            "type":"Services"
        }
    ],
    "sg:phone":"+39 0585 857001",
    "sg:postcode":"54033",
    "sg:province":"Massa-Carrara",
    "sg:tags":[
        "textile",
        "clothing"
    ],
    "wof:name":"Manifatture Generali",
    "wof:placetype":"venue"
},
  "geometry": {"coordinates":[10.0765743256,44.0636672974],"type":"Point"}
}