{
  "type": "Feature",
  "properties": {
    "iso:country":"IT",
    "sg:address":"20038 Seregno",
    "sg:city":"Seregno",
    "sg:orig_category":"Arredo Bagno Ed Idrosanitari. Complementi Di Arredamento. Vetro: Prodotti E Lavorazioni",
    "sg:phone":"+39 036 223 9487",
    "sg:postcode":"20038",
    "sg:province":"Milano",
    "wof:name":"Giannobi S.r.l.",
    "wof:placetype":"venue"
},
  "geometry": {"coordinates":[9.161294,45.474594],"type":"Point"}
}