{
  "type": "Feature",
  "properties": {
    "iso:country":"IT",
    "sg:address":"Via Principe Amedeo 43/b 10026 Santena",
    "sg:city":"Santena",
    "sg:classifiers":[
        {
            "category":"Autos & Motor Vehicles",
            "subcategory":"Recreational Vehicle Sales",
            "type":"Retail Goods"
        }
    ],
    "sg:phone":"+39 011 945 4541",
    "sg:postcode":"10026",
    "sg:province":"Torino",
    "sg:tags":[
        "machine",
        "tool",
        "accessory"
    ],
    "wof:name":"Ceramet Carbide Srl",
    "wof:placetype":"venue"
},
  "geometry": {"coordinates":[7.686619,45.07056],"type":"Point"}
}