{
  "type": "Feature",
  "properties": {
    "addr:full":"21029 Vergiate Vergiate Varese 21029",
    "addr:postcode":"21029;21029",
    "iso:country":"IT",
    "sg:address":"21029 Vergiate",
    "sg:city":"Vergiate",
    "sg:orig_category":"Lavorazioni Metalli, Stampaggio E Saldatura",
    "sg:phone":"+39 0331 948905",
    "sg:postcode":"21029",
    "sg:province":"Varese",
    "wof:name":"Tecnostampi Service Srl",
    "wof:placetype":"venue"
},
  "geometry": {"coordinates":[8.730906,45.797798],"type":"Point"}
}