{
  "type": "Feature",
  "properties": {
    "iso:country":"IT",
    "sg:address":"12084 Mondov\u00ec",
    "sg:orig_category":"Macchine E Forniture Per Ecologia E Smaltimento Rifiuti. Macchine, Strumenti Ed Apparecchi Per Attivita' Industriali",
    "sg:phone":"+39 0174 43118",
    "sg:postcode":"12084",
    "sg:province":"Cuneo",
    "wof:name":"Idroclean Di Rossi G. & C. Snc",
    "wof:placetype":"venue"
},
  "geometry": {"coordinates":[7.81776,44.404976],"type":"Point"}
}