{
  "type": "Feature",
  "properties": {
    "addr:full":"23/a, Via Padule 50018 Scandicci Scandicci Firenze 50018",
    "addr:housenumber":"23 / a",
    "addr:postcode":"50018;50018",
    "addr:street":"Via Padule",
    "iso:country":"IT",
    "sg:address":"23/a, Via Padule 50018 Scandicci",
    "sg:city":"Scandicci",
    "sg:classifiers":[
        {
            "category":"Shopping",
            "subcategory":"Jewelry",
            "type":"Retail Goods"
        }
    ],
    "sg:phone":"+39 39055751815",
    "sg:postcode":"50018",
    "sg:province":"Firenze",
    "sg:tags":[
        "jewellery"
    ],
    "wof:name":"Raddi Renato Di Raddi & C. (s.n.c.)",
    "wof:placetype":"venue"
},
  "geometry": {"coordinates":[11.166104,43.763489],"type":"Point"}
}