{
  "type": "Feature",
  "properties": {
    "addr:full":"Borgo Padova 32; Castelfranco Veneto; 31033 Castelfranco Veneto Treviso 31033",
    "addr:housenumber":"32",
    "addr:postcode":"31033;31033",
    "addr:street":"Borgo Padova",
    "iso:country":"IT",
    "sg:address":"Borgo Padova 32; Castelfranco Veneto; 31033",
    "sg:city":"Castelfranco Veneto",
    "sg:classifiers":[
        {
            "category":"Banks & Credit Unions",
            "subcategory":"Bank",
            "type":"Services"
        }
    ],
    "sg:phone":"+39 0423 721774",
    "sg:postcode":"31033",
    "sg:province":"Treviso",
    "wof:name":"Banca Popolare Di Castelfranco, Veneto Spa",
    "wof:placetype":"venue"
},
  "geometry": {"coordinates":[11.9345,45.663296],"type":"Point"}
}