{
  "type": "Feature",
  "properties": {
    "addr:full":"30, Via Del Gambero 00187 Roma Roma Roma 00187",
    "addr:postcode":"00187;00187",
    "addr:street":"Via Del Gambero",
    "iso:country":"IT",
    "sg:address":"30, Via Del Gambero 00187 Roma",
    "sg:city":"Roma",
    "sg:orig_category":"Miscellaneous Products",
    "sg:phone":"+39 06 6994 1412",
    "sg:postcode":"00187",
    "sg:province":"Roma",
    "wof:name":"Adamas",
    "wof:placetype":"venue"
},
  "geometry": {"coordinates":[12.48462677,41.8962631226],"type":"Point"}
}