{
  "type": "Feature",
  "properties": {
    "iso:country":"IT",
    "sg:address":"Via I Maggio 6/10 10071 Borgaro Torinese",
    "sg:city":"Borgaro Torinese",
    "sg:classifiers":[
        {
            "category":"Building & Trades",
            "subcategory":"Landscaping Services",
            "type":"Services"
        }
    ],
    "sg:phone":"+39 011 470 2872",
    "sg:postcode":"10071",
    "sg:province":"Torino",
    "sg:tags":[
        "component",
        "electronic"
    ],
    "wof:name":"M.c.e. Di Nigro Vincenzo E C. S.a.s",
    "wof:placetype":"venue"
},
  "geometry": {"coordinates":[7.653447,45.157341],"type":"Point"}
}