{
  "type": "Feature",
  "properties": {
    "iso:country":"IT",
    "sg:address":"06083 Bastia",
    "sg:city":"Bastia",
    "sg:orig_category":"Tessuti Arredamento, Tende E Tappeti",
    "sg:phone":"+39 075 800 1565",
    "sg:postcode":"06083",
    "sg:province":"Perugia",
    "wof:name":"Farshiran",
    "wof:placetype":"venue"
},
  "geometry": {"coordinates":[12.550882,43.067913],"type":"Point"}
}