{
  "type": "Feature",
  "properties": {
    "iso:country":"IT",
    "sg:address":"06043 Cascia",
    "sg:city":"Cascia",
    "sg:orig_category":"Alberghi E Strutture Extra Alberghiere. Servizi Per Aziende, Manifestazioni E Supporto Agli Scambi Commerciali",
    "sg:phone":"+39 0743 76348",
    "sg:postcode":"06043",
    "sg:province":"Perugia",
    "wof:name":"Santuario S. Rita",
    "wof:placetype":"venue"
},
  "geometry": {"coordinates":[12.963445,42.715168],"type":"Point"}
}