{
  "type": "Feature",
  "properties": {
    "iso:country":"IT",
    "sg:address":"35020 Albignasego",
    "sg:city":"Albignasego",
    "sg:orig_category":"Arredo Bagno Ed Idrosanitari. Idrosanitari E Accessori. Minuterie Metalliche E Ferramenta",
    "sg:phone":"+39 049 710277",
    "sg:postcode":"35020",
    "sg:province":"Padova",
    "sg:website":"http://tico-pd.com",
    "wof:name":"Tico Di Malpeli Claudio & Massimo Snc",
    "wof:placetype":"venue"
},
  "geometry": {"coordinates":[11.843641,45.357277],"type":"Point"}
}