{
  "type": "Feature",
  "properties": {
    "addr:full":"P. Iv Novembre 16-17-18; Orbetello; 58015 Orbetello Grosseto 58015",
    "addr:postcode":"16-17-18;58015;58015",
    "addr:street":"P. Iv Novembre",
    "iso:country":"IT",
    "sg:address":"P. Iv Novembre 16-17-18; Orbetello; 58015",
    "sg:city":"Orbetello",
    "sg:classifiers":[
        {
            "category":"Banks & Credit Unions",
            "subcategory":"Bank",
            "type":"Services"
        }
    ],
    "sg:phone":"+39 0564 867009",
    "sg:postcode":"58015",
    "sg:province":"Grosseto",
    "wof:name":"Banco Di Roma",
    "wof:placetype":"venue"
},
  "geometry": {"coordinates":[11.229711,42.525593],"type":"Point"}
}