{
  "type": "Feature",
  "properties": {
    "iso:country":"IT",
    "sg:address":"00124 Roma",
    "sg:city":"Roma",
    "sg:orig_category":"Ospedali E Servizi Sanitari",
    "sg:phone":"+39 06 509 8439",
    "sg:postcode":"00124",
    "sg:province":"Roma",
    "wof:name":"Ronconi Antonio Studio Radiologico Fisioterapico Casalpalocco (s.a.s.)",
    "wof:placetype":"venue"
},
  "geometry": {"coordinates":[12.357842,41.735615],"type":"Point"}
}