{
  "type": "Feature",
  "properties": {
    "iso:country":"IT",
    "sg:address":"73048 Nard\u00f2",
    "sg:orig_category":"Disinfezione, Disinfestazione E Derattizzazione",
    "sg:phone":"+39 0833 562573",
    "sg:postcode":"73048",
    "sg:province":"Lecce",
    "sg:website":"http://www.eurorecuperi-srl.it",
    "wof:name":"Eurorecuperi Srl",
    "wof:placetype":"venue"
},
  "geometry": {"coordinates":[17.976887,40.202019],"type":"Point"}
}