{
  "type": "Feature",
  "properties": {
    "iso:country":"IT",
    "sg:address":"37059 Zevio",
    "sg:city":"Zevio",
    "sg:orig_category":"Non-classified Establishments",
    "sg:phone":"+39 045 787 5266",
    "sg:postcode":"37059",
    "sg:province":"Verona",
    "sg:website":"http://users.iol.it/aldegherigus",
    "wof:name":"Aldegheri Gustavo",
    "wof:placetype":"venue"
},
  "geometry": {"coordinates":[11.002517,45.374687],"type":"Point"}
}