{
  "type": "Feature",
  "properties": {
    "addr:full":"39043 Chiusa Chiusa Bolzano/Bozen 39043",
    "addr:postcode":"39043;39043",
    "iso:country":"IT",
    "sg:address":"39043 Chiusa",
    "sg:city":"Chiusa",
    "sg:orig_category":"Arredamenti - Produzione E Ingrosso",
    "sg:phone":"+39 0472 847455",
    "sg:postcode":"39043",
    "sg:province":"Bolzano/Bozen",
    "wof:name":"Frener Design Snc Dei Fratelli A. & H. Frener",
    "wof:placetype":"venue"
},
  "geometry": {"coordinates":[11.274051,46.511307],"type":"Point"}
}