{
  "type": "Feature",
  "properties": {
    "addr:full":"V. I Trav. Barletta 71046 San Ferdinando Di Puglia San Ferdinando di Puglia Foggia 71046",
    "addr:housenumber":"ferdinando di",
    "addr:postcode":"71046;ferdinando di;71046",
    "addr:street":"V. I Trav.;Puglia;Puglia",
    "iso:country":"IT",
    "sg:address":"V. I Trav. Barletta 71046 San Ferdinando Di Puglia",
    "sg:city":"San Ferdinando di Puglia",
    "sg:classifiers":[
        {
            "category":"Food & Beverages",
            "subcategory":"Groceries & Convenience Stores",
            "type":"Retail Goods"
        }
    ],
    "sg:phone":"+39 0883 629870",
    "sg:postcode":"71046",
    "sg:province":"Foggia",
    "sg:tags":[
        "product",
        "related"
    ],
    "sg:website":"http://www.agricomm.it",
    "wof:name":"Agricomm Srl",
    "wof:placetype":"venue"
},
  "geometry": {"coordinates":[15.5446996689,41.4623336792],"type":"Point"}
}