{
  "type": "Feature",
  "properties": {
    "addr:full":"11/13, Strada Di Valminier 14019 Villanova D'asti Asti 14019",
    "addr:housenumber":"11 / 13",
    "addr:postcode":"14019;14019",
    "addr:street":"Strada Di Valminier",
    "iso:country":"IT",
    "sg:address":"11/13, Strada Di Valminier 14019 Villanova D'asti",
    "sg:classifiers":[
        {
            "category":"Autos & Motor Vehicles",
            "subcategory":"Automobile Sales",
            "type":"Retail Goods"
        }
    ],
    "sg:phone":"+39 0141 948491",
    "sg:postcode":"14019",
    "sg:province":"Asti",
    "sg:tags":[
        "industrial"
    ],
    "wof:name":"A.n.d. Service Srl",
    "wof:placetype":"venue"
},
  "geometry": {"coordinates":[7.917299,44.951168],"type":"Point"}
}