{
  "type": "Feature",
  "properties": {
    "iso:country":"IT",
    "sg:address":"18100 Imperia",
    "sg:city":"Imperia",
    "sg:orig_category":"Non-classified Establishments",
    "sg:phone":"+39 0183 61831",
    "sg:postcode":"18100",
    "sg:province":"Imperia",
    "wof:name":"Strescino Pasquale",
    "wof:placetype":"venue"
},
  "geometry": {"coordinates":[7.992963,43.886799],"type":"Point"}
}