{
  "type": "Feature",
  "properties": {
    "iso:country":"IT",
    "sg:address":"00042 Anzio",
    "sg:city":"Anzio",
    "sg:orig_category":"Macchine E Forniture Per Arredamento E Industria Del Legno. Forniture Per Edilizia E Lavori Pubblici",
    "sg:phone":"+39 06 984 6591",
    "sg:postcode":"00042",
    "sg:province":"Roma",
    "wof:name":"Veleria Nautica Palmieri Ombretta Ombretta",
    "wof:placetype":"venue"
},
  "geometry": {"coordinates":[12.61014,41.511349],"type":"Point"}
}