{
  "type": "Feature",
  "properties": {
    "addr:full":"80021 Afragola Afragola Napoli 80021",
    "addr:postcode":"80021;80021",
    "iso:country":"IT",
    "sg:address":"80021 Afragola",
    "sg:city":"Afragola",
    "sg:orig_category":"Forniture Per Abbigliamento E Pelletterie",
    "sg:phone":"+39 081 851 2169",
    "sg:postcode":"80021",
    "sg:province":"Napoli",
    "wof:name":"Rocco Rachele",
    "wof:placetype":"venue"
},
  "geometry": {"coordinates":[14.3104686737,40.9150123596],"type":"Point"}
}