{
  "type": "Feature",
  "properties": {
    "addr:full":"35010 Vigodarzere Vigodarzere Padova 35010",
    "addr:postcode":"35010;35010",
    "iso:country":"IT",
    "sg:address":"35010 Vigodarzere",
    "sg:city":"Vigodarzere",
    "sg:orig_category":"Abbigliamento Esterno, Maglierie E Pelliccerie. Calzature, Pelletterie E Pelli. Sport - Articoli E Forniture",
    "sg:phone":"+39 049 767829",
    "sg:postcode":"35010",
    "sg:province":"Padova",
    "sg:website":"http://www.paginegialle.it/faccosergio",
    "wof:name":"Facco Sergio",
    "wof:placetype":"venue"
},
  "geometry": {"coordinates":[11.857758,45.476612],"type":"Point"}
}