{
  "type": "Feature",
  "properties": {
    "addr:full":"29, Via Lepetit Roberto 20124 Milano Milano Milano 20124",
    "addr:postcode":"20124;20124",
    "addr:street":"Via Lepetit Roberto",
    "iso:country":"IT",
    "sg:address":"29, Via Lepetit Roberto 20124 Milano",
    "sg:city":"Milano",
    "sg:classifiers":[
        {
            "category":"Personal",
            "subcategory":"Shoe Repair & Shine",
            "type":"Services"
        }
    ],
    "sg:phone":"+39 39026692566",
    "sg:postcode":"20124",
    "sg:province":"Milano",
    "sg:tags":[
        "leather"
    ],
    "wof:name":"Strada F.lli (s.r.l.)",
    "wof:placetype":"venue"
},
  "geometry": {"coordinates":[9.205166,45.483814],"type":"Point"}
}