{
  "type": "Feature",
  "properties": {
    "iso:country":"IT",
    "sg:address":"10034 Chivasso",
    "sg:city":"Chivasso",
    "sg:orig_category":"Legno E Semilavorati. Macchine E Forniture Per Arredamento E Industria Del Legno. Hobbistica",
    "sg:phone":"+39 011 911 3521",
    "sg:postcode":"10034",
    "sg:province":"Torino",
    "wof:name":"C.b.l. Di Ponsetto E Chiara Snc",
    "wof:placetype":"venue"
},
  "geometry": {"coordinates":[7.903459,45.204662],"type":"Point"}
}