{
  "type": "Feature",
  "properties": {
    "iso:country":"IT",
    "sg:address":"Via Oberdan 2 28010 Briga Novarese",
    "sg:city":"Briga Novarese",
    "sg:classifiers":[
        {
            "category":"Shopping",
            "subcategory":"Stationery & Office Supplies",
            "type":"Retail Goods"
        }
    ],
    "sg:phone":"+39 0322 94609",
    "sg:postcode":"28010",
    "sg:province":"Novara",
    "sg:tags":[
        "packaging"
    ],
    "sg:website":"www.nuovabienne.com",
    "wof:name":"Nuova Bienne Srl",
    "wof:placetype":"venue"
},
  "geometry": {"coordinates":[8.4541292191,45.7220115662],"type":"Point"}
}