{
  "type": "Feature",
  "properties": {
    "addr:full":"47, Via Del Gallitello 85100 Potenza Potenza Potenza 85100",
    "addr:postcode":"85100;85100",
    "addr:street":"Via Del Gallitello",
    "iso:country":"IT",
    "sg:address":"47, Via Del Gallitello 85100 Potenza",
    "sg:city":"Potenza",
    "sg:classifiers":[
        {
            "category":"Building & Trades",
            "subcategory":"Construction",
            "type":"Services"
        }
    ],
    "sg:phone":"+39 39097155137",
    "sg:postcode":"85100",
    "sg:province":"Potenza",
    "sg:tags":[
        "work",
        "public"
    ],
    "wof:name":"Cai (s.r.l.)",
    "wof:placetype":"venue"
},
  "geometry": {"coordinates":[15.794261,40.628666],"type":"Point"}
}