{
  "type": "Feature",
  "properties": {
    "iso:country":"IT",
    "sg:address":"Cso Savona 86 10024 Moncalieri",
    "sg:city":"Moncalieri",
    "sg:classifiers":[
        {
            "category":"Shopping",
            "subcategory":"Stationery & Office Supplies",
            "type":"Retail Goods"
        }
    ],
    "sg:phone":"+39 011 647 1002",
    "sg:postcode":"10024",
    "sg:province":"Torino",
    "sg:tags":[
        "cardboard"
    ],
    "wof:name":"F.t.c. Srl",
    "wof:placetype":"venue"
},
  "geometry": {"coordinates":[7.690634,44.995239],"type":"Point"}
}