{
  "type": "Feature",
  "properties": {
    "iso:country":"IT",
    "sg:address":"00199 Roma",
    "sg:city":"Roma",
    "sg:orig_category":"Zootecnia E Pesca, Allevamento Piccoli Animali",
    "sg:phone":"+39 06 8632 8963",
    "sg:postcode":"00199",
    "sg:province":"Roma",
    "wof:name":"Aquatech Srl",
    "wof:placetype":"venue"
},
  "geometry": {"coordinates":[12.403953,42.079884],"type":"Point"}
}