{
  "type": "Feature",
  "properties": {
    "addr:full":"Via Pastrengo 24068 Seriate Seriate Bergamo 24068",
    "addr:postcode":"24068;24068",
    "addr:street":"Via Pastrengo",
    "iso:country":"IT",
    "sg:address":"Via Pastrengo 24068 Seriate",
    "sg:city":"Seriate",
    "sg:classifiers":[
        {
            "category":"Manufacturing",
            "subcategory":"Metals",
            "type":"Manufacturing & Wholesale Goods"
        }
    ],
    "sg:phone":"+39 39035302200",
    "sg:postcode":"24068",
    "sg:province":"Bergamo",
    "sg:tags":[
        "processing"
    ],
    "wof:name":"Vat (s.p.a.)",
    "wof:placetype":"venue"
},
  "geometry": {"coordinates":[9.7442407608,45.6675949097],"type":"Point"}
}