{
  "type": "Feature",
  "properties": {
    "iso:country":"IT",
    "sg:address":"V. Roma 27; Pramaggiore; 30020",
    "sg:city":"Pramaggiore",
    "sg:classifiers":[
        {
            "category":"Banks & Credit Unions",
            "subcategory":"Bank",
            "type":"Services"
        }
    ],
    "sg:phone":"+39 0421 799034",
    "sg:postcode":"30020",
    "sg:province":"Venezia",
    "wof:name":"Cassa Rurale Ed Artigiana",
    "wof:placetype":"venue"
},
  "geometry": {"coordinates":[12.738313,45.814224],"type":"Point"}
}