{
  "type": "Feature",
  "properties": {
    "addr:full":"10143 Torino Torino Torino 10143",
    "addr:postcode":"10143;10143",
    "iso:country":"IT",
    "sg:address":"10143 Torino",
    "sg:city":"Torino",
    "sg:orig_category":"Servizi Editoriali",
    "sg:phone":"+39 011 771 0595",
    "sg:postcode":"10143",
    "sg:province":"Torino",
    "wof:name":"Pro Piemonte Soc. Coop.r.l.",
    "wof:placetype":"venue"
},
  "geometry": {"coordinates":[7.653913,45.077259],"type":"Point"}
}