{
  "type": "Feature",
  "properties": {
    "addr:full":"24, Via Legnano 20027 Rescaldina Rescaldina Milano 20027",
    "addr:postcode":"20027;20027",
    "addr:street":"Via Legnano",
    "iso:country":"IT",
    "sg:address":"24, Via Legnano 20027 Rescaldina",
    "sg:city":"Rescaldina",
    "sg:classifiers":[
        {
            "category":"Shopping",
            "subcategory":"Crafts & Fabrics",
            "type":"Retail Goods"
        }
    ],
    "sg:phone":"+39 0331 448111",
    "sg:postcode":"20027",
    "sg:province":"Milano",
    "wof:name":"Bassetti S.p.a.",
    "wof:placetype":"venue"
},
  "geometry": {"coordinates":[8.9459371567,45.6120491028],"type":"Point"}
}