{
  "type": "Feature",
  "properties": {
    "iso:country":"IT",
    "sg:address":"04022 Fondi",
    "sg:city":"Fondi",
    "sg:orig_category":"Alberghi",
    "sg:phone":"+39 0771 599254",
    "sg:postcode":"04022",
    "sg:province":"Latina",
    "sg:website":"http://www.camping.it/santanastasia",
    "wof:name":"Residence Camping S. Anastasia Sas",
    "wof:placetype":"venue"
},
  "geometry": {"coordinates":[13.43237,41.355167],"type":"Point"}
}