{
  "type": "Feature",
  "properties": {
    "iso:country":"IT",
    "sg:address":"40050 Dozza",
    "sg:orig_category":"Servizi E Lavori Per Edilizia E Lavori Pubblici",
    "sg:phone":"+39 0542 674579",
    "sg:postcode":"40050",
    "sg:province":"Bologna",
    "wof:name":"Pirrone Giovanni",
    "wof:placetype":"venue"
},
  "geometry": {"coordinates":[11.628897,44.359562],"type":"Point"}
}