{
  "type": "Feature",
  "properties": {
    "iso:country":"IT",
    "sg:address":"26100 Cremona",
    "sg:city":"Cremona",
    "sg:orig_category":"Pianoforti",
    "sg:phone":"+39 0372 496348",
    "sg:postcode":"26100",
    "sg:province":"Cremona",
    "wof:name":"Nazzari Luciano",
    "wof:placetype":"venue"
},
  "geometry": {"coordinates":[10.0701580048,45.1118125916],"type":"Point"}
}