{
  "type": "Feature",
  "properties": {
    "addr:full":"91, V. Giorgione 30027 San Don\u00e0 Di Piave Venezia 30027",
    "addr:housenumber":"91",
    "addr:postcode":"30027;30027",
    "addr:street":"V. Giorgione",
    "iso:country":"IT",
    "sg:address":"91, V. Giorgione 30027 San Don\u00e0 Di Piave",
    "sg:classifiers":[
        {
            "category":"Shopping",
            "subcategory":"Computers & Home Electronics",
            "type":"Retail Goods"
        }
    ],
    "sg:phone":"+39 0421 225174",
    "sg:postcode":"30027",
    "sg:province":"Venezia",
    "sg:tags":[
        "electronic",
        "electrical",
        "equipment"
    ],
    "sg:website":"http://www.europaest.it",
    "wof:name":"Europa Est Sas",
    "wof:placetype":"venue"
},
  "geometry": {"coordinates":[12.584385,45.625904],"type":"Point"}
}