{
  "type": "Feature",
  "properties": {
    "iso:country":"IT",
    "sg:address":"00193 Roma",
    "sg:city":"Roma",
    "sg:orig_category":"Scuole E Servizi Scolastici. Ricerca, Selezione E Formazione Del Personale",
    "sg:phone":"+39 06 6880 5845",
    "sg:postcode":"00193",
    "sg:province":"Roma",
    "sg:website":"http://www.uetitalia.it",
    "wof:name":"Uet - Italia",
    "wof:placetype":"venue"
},
  "geometry": {"coordinates":[12.458809,41.905579],"type":"Point"}
}