{
  "type": "Feature",
  "properties": {
    "addr:full":"12, Via Nazionale 38087 Lardaro Lardaro Trento 38087",
    "addr:postcode":"38087;38087",
    "addr:street":"Via Nazionale",
    "iso:country":"IT",
    "sg:address":"12, Via Nazionale 38087 Lardaro",
    "sg:city":"Lardaro",
    "sg:classifiers":[
        {
            "category":"Professional",
            "subcategory":"Engineering",
            "type":"Services"
        }
    ],
    "sg:phone":"+39 0465 901945",
    "sg:postcode":"38087",
    "sg:province":"Trento",
    "sg:tags":[
        "machine",
        "-",
        "mechanical"
    ],
    "wof:name":"Pribo (s.r.l.)",
    "wof:placetype":"venue"
},
  "geometry": {"coordinates":[10.661795,45.972099],"type":"Point"}
}