{
  "type": "Feature",
  "properties": {
    "iso:country":"IT",
    "sg:address":"45019 Taglio Di Po",
    "sg:city":"Taglio di Po",
    "sg:orig_category":"Caffe' Crudo E Torrefatto",
    "sg:phone":"+39 0426 660295",
    "sg:postcode":"45019",
    "sg:province":"Rovigo",
    "wof:name":"Pregnolato Enrico",
    "wof:placetype":"venue"
},
  "geometry": {"coordinates":[12.208009,45.008778],"type":"Point"}
}