{
  "type": "Feature",
  "properties": {
    "iso:country":"IT",
    "sg:address":"95030 Nicolosi",
    "sg:city":"Nicolosi",
    "sg:orig_category":"Rifiuti Industriali E Speciali Smaltimento E Trattamento - Servizio",
    "sg:phone":"+39 095 791 6036",
    "sg:postcode":"95030",
    "sg:province":"Catania",
    "wof:name":"Squatrito Srl",
    "wof:placetype":"venue"
},
  "geometry": {"coordinates":[15.026502,37.614254],"type":"Point"}
}