{
  "type": "Feature",
  "properties": {
    "addr:full":"3, Via Farini 44042 Cento Cento Ferrara 44042",
    "addr:postcode":"44042;44042",
    "addr:street":"Via Farini",
    "iso:country":"IT",
    "sg:address":"3, Via Farini 44042 Cento",
    "sg:city":"Cento",
    "sg:classifiers":[
        {
            "category":"Wholesale",
            "subcategory":"Drugs",
            "type":"Manufacturing & Wholesale Goods"
        }
    ],
    "sg:phone":"+39 051 683 1134",
    "sg:postcode":"44042",
    "sg:province":"Ferrara",
    "sg:tags":[
        "chemical",
        "pharmaceutical"
    ],
    "wof:name":"S.v.i. S.r.l.",
    "wof:placetype":"venue"
},
  "geometry": {"coordinates":[11.299483,44.738377],"type":"Point"}
}