{
  "type": "Feature",
  "properties": {
    "iso:country":"IT",
    "sg:address":"23813 Cortenova",
    "sg:city":"Cortenova",
    "sg:orig_category":"Ferramenta - Produzione",
    "sg:phone":"+39 0341 901154",
    "sg:postcode":"23813",
    "sg:province":"Lecco",
    "wof:name":"Melesi Angelo Snc",
    "wof:placetype":"venue"
},
  "geometry": {"coordinates":[9.4149656296,45.8470497131],"type":"Point"}
}