{
  "type": "Feature",
  "properties": {
    "iso:country":"IT",
    "sg:address":"Via Spineta 84091 Battipaglia",
    "sg:city":"Battipaglia",
    "sg:classifiers":[
        {
            "category":"Manufacturing",
            "subcategory":"Rubber & Plastics",
            "type":"Manufacturing & Wholesale Goods"
        }
    ],
    "sg:phone":"+39 0828 673103",
    "sg:postcode":"84091",
    "sg:province":"Salerno",
    "sg:tags":[
        "packaging",
        "material",
        "-"
    ],
    "wof:name":"Ci.plast. Srl",
    "wof:placetype":"venue"
},
  "geometry": {"coordinates":[14.8897800446,40.5729827881],"type":"Point"}
}