{
  "type": "Feature",
  "properties": {
    "iso:country":"IT",
    "sg:address":"Via Senna, 78 - Osmannoro 50019 Sesto Fiorentino",
    "sg:city":"Osmannoro",
    "sg:orig_category":"Menswear, Suits, Trousers, Sports Jackets",
    "sg:phone":"+39 055 301282",
    "sg:postcode":"50019",
    "sg:province":"Firenze",
    "sg:website":"www.italianacollezioni.com",
    "wof:name":"Italiana Collezioni S.r.l.",
    "wof:placetype":"venue"
},
  "geometry": {"coordinates":[11.1710147858,43.814453125],"type":"Point"}
}