{
  "type": "Feature",
  "properties": {
    "iso:country":"IT",
    "sg:address":"55045 Pietrasanta",
    "sg:city":"Pietrasanta",
    "sg:orig_category":"Marmo, Pietre Ed Affini",
    "sg:phone":"+39 0584 70112",
    "sg:postcode":"55045",
    "sg:province":"Lucca",
    "wof:name":"Amg Di L. Da Prato & C. Snc",
    "wof:placetype":"venue"
},
  "geometry": {"coordinates":[10.22637,43.950172],"type":"Point"}
}