{
  "type": "Feature",
  "properties": {
    "iso:country":"IT",
    "sg:address":"17031 Campochiesa",
    "sg:city":"Campochiesa",
    "sg:orig_category":"Termotecnica E Riscaldamento, Apparecchiature E Servizi",
    "sg:phone":"+39 0182 58651",
    "sg:postcode":"17031",
    "sg:province":"Savona",
    "wof:name":"Termotecnica Pericoli Srl",
    "wof:placetype":"venue"
},
  "geometry": {"coordinates":[8.195196,44.074776],"type":"Point"}
}