{
  "type": "Feature",
  "properties": {
    "iso:country":"IT",
    "sg:address":"8, Via Provinciale 24030 Paladina",
    "sg:city":"Paladina",
    "sg:classifiers":[
        {
            "category":"Professional",
            "subcategory":"Engineering",
            "type":"Services"
        }
    ],
    "sg:phone":"+39 39035544369",
    "sg:postcode":"24030",
    "sg:province":"Bergamo",
    "sg:tags":[
        "machine",
        "-",
        "mechanical"
    ],
    "wof:name":"Co.me.c. (s.n.c.)",
    "wof:placetype":"venue"
},
  "geometry": {"coordinates":[9.609008,45.734116],"type":"Point"}
}