{
  "type": "Feature",
  "properties": {
    "addr:full":"50126 Firenze Firenze Firenze 50126",
    "addr:postcode":"50126;50126",
    "iso:country":"IT",
    "sg:address":"50126 Firenze",
    "sg:city":"Firenze",
    "sg:orig_category":"Funi Metalliche",
    "sg:phone":"+39 055 683330",
    "sg:postcode":"50126",
    "sg:province":"Firenze",
    "wof:name":"Ceccantini E Figli Srl",
    "wof:placetype":"venue"
},
  "geometry": {"coordinates":[11.2920618057,43.7592391968],"type":"Point"}
}