{
  "type": "Feature",
  "properties": {
    "iso:country":"IT",
    "sg:address":"1, Via De Marini 16149 Genova",
    "sg:city":"Genova",
    "sg:classifiers":[
        {
            "category":"Wholesale",
            "subcategory":"Drugs",
            "type":"Manufacturing & Wholesale Goods"
        }
    ],
    "sg:phone":"+39 390 102 4011",
    "sg:postcode":"16149",
    "sg:province":"Genova",
    "sg:tags":[
        "chemical",
        "pharmaceutical"
    ],
    "wof:name":"Erg Petroli S.p.a.",
    "wof:placetype":"venue"
},
  "geometry": {"coordinates":[8.900476,44.408707],"type":"Point"}
}