{
  "type": "Feature",
  "properties": {
    "iso:country":"IT",
    "sg:address":"63100 Ascoli Piceno",
    "sg:city":"Ascoli Piceno",
    "sg:orig_category":"Termotecnica E Riscaldamento, Apparecchiature E Servizi. Prodotti Vari In Metallo",
    "sg:phone":"+39 0736 47729",
    "sg:postcode":"63100",
    "sg:province":"Ascoli Piceno",
    "wof:name":"Vitelli Franco",
    "wof:placetype":"venue"
},
  "geometry": {"coordinates":[13.566831,42.84753],"type":"Point"}
}