{
  "type": "Feature",
  "properties": {
    "addr:full":"10147 Torino Torino Torino 10147",
    "addr:postcode":"10147;10147",
    "iso:country":"IT",
    "sg:address":"10147 Torino",
    "sg:city":"Torino",
    "sg:orig_category":"Motori Ed Organi Di Trasmissione",
    "sg:phone":"+39 011 210997",
    "sg:postcode":"10147",
    "sg:province":"Torino",
    "wof:name":"Ciat",
    "wof:placetype":"venue"
},
  "geometry": {"coordinates":[7.6794481277,45.0992088318],"type":"Point"}
}