{
  "type": "Feature",
  "properties": {
    "iso:country":"IT",
    "sg:address":"80059 Santa Maria La Bruna",
    "sg:city":"Santa Maria la Bruna",
    "sg:orig_category":"Accessori Dei Mezzi Di Trasporto",
    "sg:phone":"+39 081 883 3453",
    "sg:postcode":"80059",
    "sg:province":"Napoli",
    "wof:name":"Balcar Produzioni Di Palomba Igor E C. S.a.s.",
    "wof:placetype":"venue"
},
  "geometry": {"coordinates":[14.411414,40.773205],"type":"Point"}
}