{
  "type": "Feature",
  "properties": {
    "iso:country":"IT",
    "sg:address":"Viale Dandolo 29-27; Lido",
    "sg:classifiers":[
        {
            "category":"Travel",
            "subcategory":"Travel Agent",
            "type":"Entertainment"
        }
    ],
    "sg:province":"Venice",
    "wof:name":"Biasutti Hotels Snc",
    "wof:placetype":"venue"
},
  "geometry": {"coordinates":[12.371444,45.414639],"type":"Point"}
}