{
  "type": "Feature",
  "properties": {
    "iso:country":"IT",
    "sg:address":"24121 Bergamo",
    "sg:city":"Bergamo",
    "sg:orig_category":"Arte Ed Artigianato Artistico",
    "sg:phone":"+39 035 220025",
    "sg:postcode":"24121",
    "sg:province":"Bergamo",
    "wof:name":"Franco Travi",
    "wof:placetype":"venue"
},
  "geometry": {"coordinates":[9.674936,45.699619],"type":"Point"}
}