{
  "type": "Feature",
  "properties": {
    "addr:full":"47900 Rimini Rimini Rimini 47900",
    "addr:postcode":"47900;47900",
    "iso:country":"IT",
    "sg:address":"47900 Rimini",
    "sg:city":"Rimini",
    "sg:orig_category":"Servizi E Lavori Per Edilizia E Lavori Pubblici",
    "sg:phone":"+39 335 643 5239",
    "sg:postcode":"47900",
    "sg:province":"Rimini",
    "wof:name":"Alex Service",
    "wof:placetype":"venue"
},
  "geometry": {"coordinates":[12.554964,44.037769],"type":"Point"}
}