{
  "type": "Feature",
  "properties": {
    "iso:country":"IT",
    "sg:address":"20040 Cambiago",
    "sg:city":"Cambiago",
    "sg:orig_category":"Climatizzazione E Condizionamento, Apparecchiature E Servizi",
    "sg:phone":"+39 02 9530 8362",
    "sg:postcode":"20040",
    "sg:province":"Milano",
    "wof:name":"Euro Motors Italia Spa",
    "wof:placetype":"venue"
},
  "geometry": {"coordinates":[9.441543,45.581398],"type":"Point"}
}