{
  "type": "Feature",
  "properties": {
    "addr:full":"Via Kennedy 3/7 20024 Garbagnate Milanese Garbagnate Milanese Milano 20024",
    "addr:housenumber":"3 / 7",
    "addr:postcode":"20024;20024",
    "addr:street":"Via Kennedy",
    "iso:country":"IT",
    "sg:address":"Via Kennedy 3/7 20024 Garbagnate Milanese",
    "sg:city":"Garbagnate Milanese",
    "sg:classifiers":[
        {
            "category":"Home & Garden",
            "subcategory":"Home Furnishings",
            "type":"Retail Goods"
        }
    ],
    "sg:phone":"+39 02 995 5146",
    "sg:postcode":"20024",
    "sg:province":"Milano",
    "sg:tags":[
        "bathroom",
        "wc",
        "fitting"
    ],
    "sg:website":"www.broil.it",
    "wof:name":"Broil Srl",
    "wof:placetype":"venue"
},
  "geometry": {"coordinates":[9.076573,45.550606],"type":"Point"}
}