{
  "type": "Feature",
  "properties": {
    "iso:country":"IT",
    "sg:address":"Via Principale 38, 39021 Laces, Bz",
    "sg:city":"Laces",
    "sg:classifiers":[
        {
            "category":"Banks & Credit Unions",
            "subcategory":"Bank",
            "type":"Services"
        }
    ],
    "sg:postcode":"39021",
    "sg:province":"Bolzano/Bozen",
    "wof:name":"Cassa Raiffeisen Di Laces Scrl- Raiffeisenkasse Latsch Gmbh",
    "wof:placetype":"venue"
},
  "geometry": {"coordinates":[11.358005,46.496716],"type":"Point"}
}