{
  "type": "Feature",
  "properties": {
    "iso:country":"IT",
    "sg:address":"15057 Tortona",
    "sg:city":"Tortona",
    "sg:orig_category":"Arredo Cucina Ed Elettrodomestici. Elettrodomestici",
    "sg:phone":"+39 0131 863119",
    "sg:postcode":"15057",
    "sg:province":"Alessandria",
    "wof:name":"Tosino Paolo",
    "wof:placetype":"venue"
},
  "geometry": {"coordinates":[8.885338,44.904533],"type":"Point"}
}