{
  "type": "Feature",
  "properties": {
    "iso:country":"IT",
    "sg:address":"25121 Brescia",
    "sg:city":"Brescia",
    "sg:orig_category":"Accessori Dei Mezzi Di Trasporto",
    "sg:phone":"+39 030 375 0470",
    "sg:postcode":"25121",
    "sg:province":"Brescia",
    "wof:name":"Motoforniture Di Marco Codenotti & C. Snc",
    "wof:placetype":"venue"
},
  "geometry": {"coordinates":[10.228521,45.531784],"type":"Point"}
}