{
  "type": "Feature",
  "properties": {
    "iso:country":"IT",
    "sg:address":"4, Via Reano 10141 Torino",
    "sg:city":"Torino",
    "sg:classifiers":[
        {
            "category":"Wholesale",
            "subcategory":"Drugs",
            "type":"Manufacturing & Wholesale Goods"
        }
    ],
    "sg:phone":"+39 011 385 1453",
    "sg:postcode":"10141",
    "sg:province":"Torino",
    "sg:tags":[
        "chemical",
        "pharmaceutical"
    ],
    "wof:name":"For.ma.to (s.n.c.)",
    "wof:placetype":"venue"
},
  "geometry": {"coordinates":[7.374316,45.09977],"type":"Point"}
}