{
  "type": "Feature",
  "properties": {
    "iso:country":"IT",
    "sg:address":"Via Provinciale Di Mercatale 195 50059 Vinci",
    "sg:city":"Vinci",
    "sg:classifiers":[
        {
            "category":"Manufacturing",
            "subcategory":"Paper Products",
            "type":"Manufacturing & Wholesale Goods"
        }
    ],
    "sg:phone":"+39 0571 90411",
    "sg:postcode":"50059",
    "sg:province":"Firenze",
    "sg:tags":[
        "adhesive",
        "self-adhesive",
        "labels",
        "label"
    ],
    "sg:website":"www.pizzoetichette.com",
    "wof:name":"Pizzo Etichette S.r.l.",
    "wof:placetype":"venue"
},
  "geometry": {"coordinates":[10.906584,43.755516],"type":"Point"}
}