{
  "type": "Feature",
  "properties": {
    "iso:country":"IT",
    "sg:address":"371/a/b, V. Pisana 50018 Scandicci",
    "sg:city":"Scandicci",
    "sg:classifiers":[
        {
            "category":"Parking",
            "subcategory":"Lot",
            "type":"Transportation"
        }
    ],
    "sg:phone":"+39 055 735 7835",
    "sg:postcode":"50018",
    "sg:province":"Firenze",
    "sg:tags":[
        "transport",
        "road"
    ],
    "sg:website":"http://www.coopfiorentinaservizi.it",
    "wof:name":"Cooperativa Fiorentina Servizi Srl",
    "wof:placetype":"venue"
},
  "geometry": {"coordinates":[11.180569,43.764473],"type":"Point"}
}