{
  "type": "Feature",
  "properties": {
    "addr:full":"Strada Privata Ansaldi 8, 15057 Tortona, Al Tortona Alessandria 15057",
    "addr:housenumber":"8",
    "addr:postcode":"15057;15057",
    "addr:street":"Privata Ansaldi",
    "iso:country":"IT",
    "sg:address":"Strada Privata Ansaldi 8, 15057 Tortona, Al",
    "sg:city":"Tortona",
    "sg:classifiers":[
        {
            "category":"Banks & Credit Unions",
            "subcategory":"Bank",
            "type":"Services"
        }
    ],
    "sg:postcode":"15057",
    "sg:province":"Alessandria",
    "wof:name":"Impresa Grassetto Spa",
    "wof:placetype":"venue"
},
  "geometry": {"coordinates":[8.84796,44.893482],"type":"Point"}
}