{
  "type": "Feature",
  "properties": {
    "iso:country":"IT",
    "sg:address":"20143 Milano",
    "sg:city":"Milano",
    "sg:orig_category":"Trattamenti Termici E Superficiali Metalli, Galvanotecnica",
    "sg:phone":"+39 02 8940 3851",
    "sg:postcode":"20143",
    "sg:province":"Milano",
    "wof:name":"Lazzerini Argenteria Sas Di Emilio E Stefano Lazzerini",
    "wof:placetype":"venue"
},
  "geometry": {"coordinates":[9.170254,45.443821],"type":"Point"}
}