{
  "type": "Feature",
  "properties": {
    "addr:full":"197, Via Germanico 00192 Roma Roma Roma 00192",
    "addr:housenumber":"197",
    "addr:postcode":"00192;00192",
    "addr:street":"Via Germanico",
    "iso:country":"IT",
    "sg:address":"197, Via Germanico 00192 Roma",
    "sg:city":"Roma",
    "sg:classifiers":[
        {
            "category":"Manufacturing",
            "subcategory":"Printing",
            "type":"Manufacturing & Wholesale Goods"
        }
    ],
    "sg:phone":"+39 39063241680",
    "sg:postcode":"00192",
    "sg:province":"Roma",
    "sg:tags":[
        "publishing"
    ],
    "wof:name":"Servizi Integrati Per Editoria S.r.l.",
    "wof:placetype":"venue"
},
  "geometry": {"coordinates":[12.4823246002,41.8954658508],"type":"Point"}
}