{
  "type": "Feature",
  "properties": {
    "iso:country":"IT",
    "sg:address":"25030 Castelcovati",
    "sg:city":"Castelcovati",
    "sg:orig_category":"Macchine, Impianti Ed Attrezzature Per Agricoltura E Zootecnia",
    "sg:phone":"+39 030 718 7002",
    "sg:postcode":"25030",
    "sg:province":"Brescia",
    "wof:name":"F.a.r.m.a.",
    "wof:placetype":"venue"
},
  "geometry": {"coordinates":[10.012341,45.483467],"type":"Point"}
}