{
  "type": "Feature",
  "properties": {
    "addr:full":"00121 Lido Di Ostia Roma 00121",
    "addr:postcode":"00121;00121",
    "addr:street":"Di Ostia Roma",
    "iso:country":"IT",
    "sg:address":"00121 Lido Di Ostia",
    "sg:orig_category":"Autosoccorso",
    "sg:phone":"+39 06 564 6900",
    "sg:postcode":"00121",
    "sg:province":"Roma",
    "wof:name":"Lentini Gomme Di Vincenzo Lentini",
    "wof:placetype":"venue"
},
  "geometry": {"coordinates":[12.276158,41.734657],"type":"Point"}
}