{
  "type": "Feature",
  "properties": {
    "iso:country":"IT",
    "sg:address":"45032 Bergantino",
    "sg:city":"Bergantino",
    "sg:orig_category":"Servizi Per Lo Sport E Il Tempo Libero. Servizi Al Turismo",
    "sg:phone":"+39 0425 805452",
    "sg:postcode":"45032",
    "sg:province":"Rovigo",
    "sg:website":"http://www.farfabbri.it",
    "wof:name":"Fabbri Group",
    "wof:placetype":"venue"
},
  "geometry": {"coordinates":[11.265926,45.064598],"type":"Point"}
}