{
  "type": "Feature",
  "properties": {
    "iso:country":"IT",
    "sg:address":"20137 Milano",
    "sg:city":"Milano",
    "sg:orig_category":"Grafite",
    "sg:phone":"+39 02 541 6901",
    "sg:postcode":"20137",
    "sg:province":"Milano",
    "wof:name":"Sgl Carbon Group Risomesa Spa",
    "wof:placetype":"venue"
},
  "geometry": {"coordinates":[9.22368,45.452866],"type":"Point"}
}