{
  "type": "Feature",
  "properties": {
    "iso:country":"IT",
    "sg:address":"Largo Franco Tosi, 9; Milan; 20025",
    "sg:classifiers":[
        {
            "category":"Industrial Area",
            "type":"Public Place"
        }
    ],
    "sg:phone":"+39 0331 521111",
    "sg:postcode":"20025",
    "sg:province":"Milano",
    "sg:tags":[
        "large",
        "private"
    ],
    "sg:website":"www.bancadilegnano.it",
    "wof:name":"Banca Di Legnano S.p.a.",
    "wof:placetype":"venue"
},
  "geometry": {"coordinates":[9.1557035446,45.4444274902],"type":"Point"}
}