{
  "type": "Feature",
  "properties": {
    "addr:full":"16143 Genova Genova Genova 16143",
    "addr:postcode":"16143;16143",
    "iso:country":"IT",
    "sg:address":"16143 Genova",
    "sg:city":"Genova",
    "sg:orig_category":"Prodotti Alimentari",
    "sg:phone":"+39 010 506247",
    "sg:postcode":"16143",
    "sg:province":"Genova",
    "wof:name":"Pe.al.pe. S.a.s.",
    "wof:placetype":"venue"
},
  "geometry": {"coordinates":[8.6584434509,44.4021835327],"type":"Point"}
}