{
  "type": "Feature",
  "properties": {
    "iso:country":"IT",
    "sg:address":"26845 Codogno",
    "sg:city":"Codogno",
    "sg:orig_category":"Non-classified Establishments",
    "sg:phone":"+39 0377 32889",
    "sg:postcode":"26845",
    "sg:province":"Lodi",
    "sg:website":"http://www.bassiniecighetti.it",
    "wof:name":"Falegnameria Bassini & Cighetti",
    "wof:placetype":"venue"
},
  "geometry": {"coordinates":[9.70628,45.160648],"type":"Point"}
}