{
  "type": "Feature",
  "properties": {
    "iso:country":"IT",
    "sg:address":"02100 Rieti",
    "sg:city":"Rieti",
    "sg:orig_category":"Ordini E Collegi Professionali",
    "sg:phone":"+39 0746 203741",
    "sg:postcode":"02100",
    "sg:province":"Rieti",
    "wof:name":"Ordine Degli Ingegneri Della Provincia Di Rieti",
    "wof:placetype":"venue"
},
  "geometry": {"coordinates":[12.857609,42.402481],"type":"Point"}
}