{
  "type": "Feature",
  "properties": {
    "addr:full":"99, Via Toscana 59100 Prato Prato Prato 59100",
    "addr:postcode":"59100;59100",
    "addr:street":"Via Toscana",
    "iso:country":"IT",
    "sg:address":"99, Via Toscana 59100 Prato",
    "sg:city":"Prato",
    "sg:classifiers":[
        {
            "category":"Shopping",
            "subcategory":"Crafts & Fabrics",
            "type":"Retail Goods"
        }
    ],
    "sg:phone":"+39 0574 624777",
    "sg:postcode":"59100",
    "sg:province":"Prato",
    "wof:name":"Rifinizione Lusar S.r.l",
    "wof:placetype":"venue"
},
  "geometry": {"coordinates":[11.101061821,43.9635887146],"type":"Point"}
}