{
  "type": "Feature",
  "properties": {
    "iso:country":"IT",
    "sg:address":"20093 Cologno Monzese",
    "sg:city":"Cologno Monzese",
    "sg:orig_category":"Motori Ed Organi Di Trasmissione",
    "sg:phone":"+39 02 2670 8171",
    "sg:postcode":"20093",
    "sg:province":"Milano",
    "wof:name":"Gts Trasmissioni S.a.s. Di Inglese Roberto & C.",
    "wof:placetype":"venue"
},
  "geometry": {"coordinates":[9.2779340744,45.5244407654],"type":"Point"}
}