{
  "type": "Feature",
  "properties": {
    "iso:country":"IT",
    "sg:address":"31053 Pieve Di Soligo",
    "sg:city":"Pieve di Soligo",
    "sg:orig_category":"Apparecchiature Ed Attrezzature Meccaniche",
    "sg:phone":"+39 0438 837595",
    "sg:postcode":"31053",
    "sg:province":"Treviso",
    "wof:name":"A.si.f. Di Mariotto Antonio",
    "wof:placetype":"venue"
},
  "geometry": {"coordinates":[12.180053,45.903725],"type":"Point"}
}