{
  "type": "Feature",
  "properties": {
    "iso:country":"IT",
    "sg:address":"Via Veneto 10 20090 Buccinasco",
    "sg:city":"Buccinasco",
    "sg:orig_category":"Wood Screws Of Stainless Steel",
    "sg:phone":"+39 02 4884 4875",
    "sg:postcode":"20090",
    "sg:province":"Milano",
    "sg:website":"www.europressvit.com",
    "wof:name":"Europressvit Srl",
    "wof:placetype":"venue"
},
  "geometry": {"coordinates":[9.12302,45.415401],"type":"Point"}
}