{
  "type": "Feature",
  "properties": {
    "addr:full":"15, Via Vivaldi A. 35020 Ponte San Nicolo' Padova 35020",
    "addr:postcode":"35020;35020",
    "addr:street":"Via Vivaldi A.;Nicolo ' Padova",
    "iso:country":"IT",
    "sg:address":"15, Via Vivaldi A. 35020 Ponte San Nicolo'",
    "sg:classifiers":[
        {
            "category":"Utilities",
            "subcategory":"Telephone",
            "type":"Services"
        }
    ],
    "sg:phone":"+39 049 896 8140",
    "sg:postcode":"35020",
    "sg:province":"Padova",
    "sg:tags":[
        "telecommunication"
    ],
    "wof:name":"Bergo S.n.c. Di Bergo D.-pizzocaro M. & C.",
    "wof:placetype":"venue"
},
  "geometry": {"coordinates":[11.905378,45.36414],"type":"Point"}
}