{
  "type": "Feature",
  "properties": {
    "addr:full":"43036 Fidenza Fidenza Parma 43036",
    "addr:postcode":"43036;43036",
    "iso:country":"IT",
    "sg:address":"43036 Fidenza",
    "sg:city":"Fidenza",
    "sg:orig_category":"Lavorazioni Metalli, Stampaggio E Saldatura",
    "sg:phone":"+39 0524 520210",
    "sg:postcode":"43036",
    "sg:province":"Parma",
    "wof:name":"E.t. System Srl",
    "wof:placetype":"venue"
},
  "geometry": {"coordinates":[10.063399,44.864605],"type":"Point"}
}