{
  "type": "Feature",
  "properties": {
    "iso:country":"IT",
    "sg:address":"41051 Castelnuovo Rangone",
    "sg:city":"Castelnuovo Rangone",
    "sg:classifiers":[
        {
            "category":"Manufacturing",
            "subcategory":"Tools & Machinery",
            "type":"Manufacturing & Wholesale Goods"
        }
    ],
    "sg:phone":"+39 059 530953",
    "sg:postcode":"41051",
    "sg:province":"Modena",
    "sg:tags":[
        "machining",
        "mechanical"
    ],
    "wof:name":"Pradelli Giancarlo & C. Snc",
    "wof:placetype":"venue"
},
  "geometry": {"coordinates":[10.911776,44.568401],"type":"Point"}
}