{
  "type": "Feature",
  "properties": {
    "iso:country":"IT",
    "sg:address":"20123 Milano",
    "sg:city":"Milano",
    "sg:orig_category":"Hobbistica",
    "sg:phone":"+39 02 805 7332",
    "sg:postcode":"20123",
    "sg:province":"Milano",
    "wof:name":"Carraro Gianni",
    "wof:placetype":"venue"
},
  "geometry": {"coordinates":[9.183321,45.46262],"type":"Point"}
}