{
  "type": "Feature",
  "properties": {
    "iso:country":"IT",
    "sg:address":"20011 Corbetta",
    "sg:city":"Corbetta",
    "sg:orig_category":"Prodotti E Manufatti In Materie Plastiche",
    "sg:phone":"+39 02 972 1851",
    "sg:postcode":"20011",
    "sg:province":"Milano",
    "wof:name":"Mario Lombardini S.p.a.",
    "wof:placetype":"venue"
},
  "geometry": {"coordinates":[8.9120349884,45.4725418091],"type":"Point"}
}