{
  "type": "Feature",
  "properties": {
    "iso:country":"IT",
    "sg:address":"3, V. Cellini 20129 Milano",
    "sg:city":"Milano",
    "sg:classifiers":[
        {
            "category":"Manufacturing",
            "subcategory":"Tools & Machinery",
            "type":"Manufacturing & Wholesale Goods"
        }
    ],
    "sg:phone":"+39 39025457797",
    "sg:postcode":"20129",
    "sg:province":"Milano",
    "sg:tags":[
        "environment",
        "equipment",
        "-"
    ],
    "sg:website":"http://www.paginegialle.it/filtrifink",
    "wof:name":"Filtri Fink Sas",
    "wof:placetype":"venue"
},
  "geometry": {"coordinates":[9.208834,45.462616],"type":"Point"}
}