{
  "type": "Feature",
  "properties": {
    "iso:country":"IT",
    "sg:address":"10149 Torino",
    "sg:city":"Torino",
    "sg:orig_category":"Forniture Per Attivita' Industriali",
    "sg:phone":"+39 011 739 9461",
    "sg:postcode":"10149",
    "sg:province":"Torino",
    "wof:name":"2 B Spazzole",
    "wof:placetype":"venue"
},
  "geometry": {"coordinates":[7.663629055,45.0963668823],"type":"Point"}
}