{
  "type": "Feature",
  "properties": {
    "iso:country":"IT",
    "sg:address":"15045 Sale",
    "sg:city":"Sale",
    "sg:orig_category":"Lavorazioni Meccaniche E Servizi. Servizi Per Imballaggio E Confezionamento",
    "sg:phone":"+39 0131 84105",
    "sg:postcode":"15045",
    "sg:province":"Alessandria",
    "wof:name":"Csm Di Stefano Clementini",
    "wof:placetype":"venue"
},
  "geometry": {"coordinates":[8.808053,44.968922],"type":"Point"}
}