{
  "type": "Feature",
  "properties": {
    "addr:full":"74017 Mottola Mottola Taranto 74017",
    "addr:postcode":"74017;74017",
    "iso:country":"IT",
    "sg:address":"74017 Mottola",
    "sg:city":"Mottola",
    "sg:classifiers":[
        {
            "category":"Health Services",
            "subcategory":"Health Practitioner",
            "type":"Services"
        }
    ],
    "sg:phone":"+39 099 886 6236",
    "sg:postcode":"74017",
    "sg:province":"Taranto",
    "sg:tags":[
        "medici"
    ],
    "wof:name":"Carucci Dr. Giuseppe",
    "wof:placetype":"venue"
},
  "geometry": {"coordinates":[17.436649,40.390499],"type":"Point"}
}