{
  "type": "Feature",
  "properties": {
    "addr:full":"30172 Venezia Venezia Venezia 30172",
    "addr:postcode":"30172;30172",
    "iso:country":"IT",
    "sg:address":"30172 Venezia",
    "sg:city":"Venezia",
    "sg:orig_category":"Vigilanza E Sorveglianza",
    "sg:phone":"+39 041 290 9111",
    "sg:postcode":"30172",
    "sg:province":"Venezia",
    "sg:website":"http://www.visama.it",
    "wof:name":"La Vigile San Marco Spa",
    "wof:placetype":"venue"
},
  "geometry": {"coordinates":[12.780014,45.824844],"type":"Point"}
}