{
  "type": "Feature",
  "properties": {
    "addr:full":"40018 San Pietro In Casale San Pietro in Casale Bologna 40018",
    "addr:housenumber":"40018",
    "addr:postcode":"40018",
    "addr:street":"San;Pietro In",
    "iso:country":"IT",
    "sg:address":"40018 San Pietro In Casale",
    "sg:city":"San Pietro in Casale",
    "sg:orig_category":"Agenzie Ed Enti Turistici. Consulenze Tecniche, Amministrative E Perizie",
    "sg:phone":"+39 051 666 1552",
    "sg:postcode":"40018",
    "sg:province":"Bologna",
    "sg:website":"http://www.iviaggidibrian.it",
    "wof:name":"I Viaggi Di Brian",
    "wof:placetype":"venue"
},
  "geometry": {"coordinates":[11.4018211365,44.701133728],"type":"Point"}
}