{
  "type": "Feature",
  "properties": {
    "addr:full":"00031 Artena Artena Roma 00031",
    "addr:postcode":"00031;roma 00031",
    "iso:country":"IT",
    "sg:address":"00031 Artena",
    "sg:city":"Artena",
    "sg:orig_category":"Scuole E Servizi Scolastici",
    "sg:phone":"+39 06 951 5494",
    "sg:postcode":"00031",
    "sg:province":"Roma",
    "wof:name":"Scuola Elementare",
    "wof:placetype":"venue"
},
  "geometry": {"coordinates":[12.886002,41.735683],"type":"Point"}
}