{
  "type": "Feature",
  "properties": {
    "iso:country":"IT",
    "sg:address":"20124 Milano",
    "sg:city":"Milano",
    "sg:orig_category":"Materiali Edili",
    "sg:phone":"+39 02 201993",
    "sg:postcode":"20124",
    "sg:province":"Milano",
    "wof:name":"Formenti Di Bulgarelli & C. Sas",
    "wof:placetype":"venue"
},
  "geometry": {"coordinates":[9.204963,45.4758],"type":"Point"}
}