{
  "type": "Feature",
  "properties": {
    "addr:full":"59, Strada Chivasso 10090 Gassino Torinese Gassino Torinese Torino 10090",
    "addr:postcode":"10090;10090",
    "addr:street":"Strada Chivasso;Torinese",
    "iso:country":"IT",
    "sg:address":"59, Strada Chivasso 10090 Gassino Torinese",
    "sg:city":"Gassino Torinese",
    "sg:classifiers":[
        {
            "category":"Professional",
            "subcategory":"Printing & Photocopies",
            "type":"Services"
        }
    ],
    "sg:phone":"+39 011 960 7965",
    "sg:postcode":"10090",
    "sg:province":"Torino",
    "wof:name":"Cubitalia Di Pranzo Domenico Snc",
    "wof:placetype":"venue"
},
  "geometry": {"coordinates":[8.3989200592,45.4623451233],"type":"Point"}
}