{
  "type": "Feature",
  "properties": {
    "iso:country":"IT",
    "sg:address":"20, Via Staffarda 27050 Pizzale",
    "sg:city":"Pizzale",
    "sg:classifiers":[
        {
            "category":"Parking",
            "subcategory":"Lot",
            "type":"Transportation"
        }
    ],
    "sg:phone":"+39 0383 379534",
    "sg:postcode":"27050",
    "sg:province":"Pavia",
    "sg:tags":[
        "transport",
        "road"
    ],
    "wof:name":"Industria Laterizi Pastore (s.r.l.)",
    "wof:placetype":"venue"
},
  "geometry": {"coordinates":[9.049164,45.034798],"type":"Point"}
}