{
  "type": "Feature",
  "properties": {
    "iso:country":"IT",
    "sg:address":"Via Caduti Di Via Fani 590 47032 Bertinoro",
    "sg:city":"Bertinoro",
    "sg:classifiers":[
        {
            "category":"Autos & Motor Vehicles",
            "subcategory":"Automobile Sales",
            "type":"Retail Goods"
        }
    ],
    "sg:phone":"+39 0543 449179",
    "sg:postcode":"47032",
    "sg:province":"Forl\u00ec-Cesena",
    "sg:tags":[
        "van"
    ],
    "sg:website":"www.unicar-furgonature.com",
    "wof:name":"Unicar Furgonature Spa",
    "wof:placetype":"venue"
},
  "geometry": {"coordinates":[12.165776,44.173195],"type":"Point"}
}