{
  "type": "Feature",
  "properties": {
    "iso:country":"IT",
    "sg:address":"13852 Cerreto Castello",
    "sg:city":"Cerreto Castello",
    "sg:classifiers":[
        {
            "category":"Shopping",
            "subcategory":"Crafts & Fabrics",
            "type":"Retail Goods"
        }
    ],
    "sg:phone":"+39 39015881154",
    "sg:postcode":"13852",
    "sg:province":"Biella",
    "wof:name":"Safil (s.r.l.)",
    "wof:placetype":"venue"
},
  "geometry": {"coordinates":[8.1549186707,45.5630149841],"type":"Point"}
}