{
  "type": "Feature",
  "properties": {
    "iso:country":"IT",
    "sg:address":"20149 Milano",
    "sg:city":"Milano",
    "sg:orig_category":"Ospedali E Servizi Sanitari",
    "sg:phone":"+39 02 466590",
    "sg:postcode":"20149",
    "sg:province":"Milano",
    "wof:name":"Puntoneutro",
    "wof:placetype":"venue"
},
  "geometry": {"coordinates":[9.149,45.474216],"type":"Point"}
}