{
  "type": "Feature",
  "properties": {
    "iso:country":"IT",
    "sg:address":"Via Fracastoro Girolamo 7 20128 Milano",
    "sg:city":"Milano",
    "sg:classifiers":[
        {
            "category":"Military Area",
            "subcategory":"Barracks",
            "type":"Public Place"
        }
    ],
    "sg:phone":"+39 02 259 0591",
    "sg:postcode":"20128",
    "sg:province":"Milano",
    "sg:tags":[
        "scale",
        "electronic"
    ],
    "sg:website":"www.favorit.it",
    "wof:name":"Favorit Spa",
    "wof:placetype":"venue"
},
  "geometry": {"coordinates":[9.203226,45.482468],"type":"Point"}
}