{
  "type": "Feature",
  "properties": {
    "iso:country":"IT",
    "sg:address":"41100 Modena",
    "sg:city":"Modena",
    "sg:orig_category":"Riparazione Dei Mezzi Di Trasporto",
    "sg:phone":"+39 059 828079",
    "sg:postcode":"41100",
    "sg:province":"Modena",
    "wof:name":"Carrozzeria Campana Onorio Srl",
    "wof:placetype":"venue"
},
  "geometry": {"coordinates":[10.914429,44.663944],"type":"Point"}
}