{
  "type": "Feature",
  "properties": {
    "iso:country":"IT",
    "sg:address":"Via Leopardi, 9/11 20091 Bresso",
    "sg:city":"Bresso",
    "sg:classifiers":[
        {
            "category":"Manufacturing",
            "subcategory":"Leather Goods",
            "type":"Manufacturing & Wholesale Goods"
        }
    ],
    "sg:phone":"+39 02 6650 3757",
    "sg:postcode":"20091",
    "sg:province":"Milano",
    "sg:tags":[
        "pigment"
    ],
    "wof:name":"Colortex Industria Chimica Srl",
    "wof:placetype":"venue"
},
  "geometry": {"coordinates":[9.199837,45.530464],"type":"Point"}
}