{
  "type": "Feature",
  "properties": {
    "iso:country":"IT",
    "sg:address":"67051 Avezzano",
    "sg:orig_category":"Cinematografia E Radiotelevisione. Pubblicita', Marketing E Comunicazione",
    "sg:phone":"+39 0863 441772",
    "sg:postcode":"67051",
    "sg:province":"L'Aquila",
    "wof:name":"Spot Advertising",
    "wof:placetype":"venue"
},
  "geometry": {"coordinates":[13.428733,42.029438],"type":"Point"}
}