{
  "type": "Feature",
  "properties": {
    "iso:country":"IT",
    "sg:address":"22, Contrada Gemma D'oro 91014 Castellammare Del Golfo",
    "sg:city":"Castellammare del Golfo",
    "sg:classifiers":[
        {
            "category":"Building & Trades",
            "subcategory":"Construction",
            "type":"Services"
        }
    ],
    "sg:phone":"+39 39092430500",
    "sg:postcode":"91014",
    "sg:province":"Trapani",
    "sg:tags":[
        "work",
        "public"
    ],
    "wof:name":"Sud Segnaletica S.a.s.",
    "wof:placetype":"venue"
},
  "geometry": {"coordinates":[12.892097,38.016491],"type":"Point"}
}