{
  "type": "Feature",
  "properties": {
    "iso:country":"IT",
    "sg:address":"31030 Borso Del Grappa",
    "sg:city":"Borso del Grappa",
    "sg:orig_category":"Sport - Articoli E Forniture",
    "sg:phone":"+39 0423 561727",
    "sg:postcode":"31030",
    "sg:province":"Treviso",
    "wof:name":"Dimensione Volo Srl",
    "wof:placetype":"venue"
},
  "geometry": {"coordinates":[11.783015,45.806591],"type":"Point"}
}