{
  "type": "Feature",
  "properties": {
    "iso:country":"IT",
    "sg:address":"00183 Roma",
    "sg:city":"Roma",
    "sg:orig_category":"Servizi Per Lo Sport E Il Tempo Libero. Servizi Al Turismo",
    "sg:phone":"+39 06 7720 7834",
    "sg:postcode":"00183",
    "sg:province":"Roma",
    "wof:name":"A.s. B & F Sporting Club",
    "wof:placetype":"venue"
},
  "geometry": {"coordinates":[12.508782,41.879295],"type":"Point"}
}