{
  "type": "Feature",
  "properties": {
    "iso:country":"IT",
    "sg:address":"1/3, Via Magellano 42046 Reggiolo",
    "sg:classifiers":[
        {
            "category":"Professional",
            "subcategory":"Engineering",
            "type":"Services"
        }
    ],
    "sg:phone":"+39 0522 973034",
    "sg:postcode":"42046",
    "sg:province":"Reggio Nell'Emilia",
    "sg:tags":[
        "machine",
        "-",
        "mechanical"
    ],
    "wof:name":"Fantozzi (s.r.l.)",
    "wof:placetype":"venue"
},
  "geometry": {"coordinates":[10.843853,44.907986],"type":"Point"}
}