{
  "type": "Feature",
  "properties": {
    "iso:country":"IT",
    "sg:address":"37, Regione Case Bruciate 14018 Villafranca D'asti",
    "sg:classifiers":[
        {
            "category":"Wholesale",
            "subcategory":"Drugs",
            "type":"Manufacturing & Wholesale Goods"
        }
    ],
    "sg:phone":"+39 0141 943825",
    "sg:postcode":"14018",
    "sg:province":"Asti",
    "sg:tags":[
        "chemical",
        "pharmaceutical"
    ],
    "wof:name":"Angi (s.r.l.)",
    "wof:placetype":"venue"
},
  "geometry": {"coordinates":[8.066119,44.900658],"type":"Point"}
}