{
  "type": "Feature",
  "properties": {
    "iso:country":"IT",
    "sg:address":"30035 Mirano",
    "sg:city":"Mirano",
    "sg:orig_category":"Zootecnia E Pesca, Allevamento Piccoli Animali",
    "sg:phone":"+39 041 570 0434",
    "sg:postcode":"30035",
    "sg:province":"Venezia",
    "wof:name":"Avicola Santa Maria (s.a.s.)",
    "wof:placetype":"venue"
},
  "geometry": {"coordinates":[12.106855,45.504272],"type":"Point"}
}