{
  "type": "Feature",
  "properties": {
    "iso:country":"IT",
    "sg:address":"10, Via Cella Raibano 47843 Misano Adriatico",
    "sg:city":"Cella",
    "sg:classifiers":[
        {
            "category":"Personal",
            "subcategory":"Shoe Repair & Shine",
            "type":"Services"
        }
    ],
    "sg:phone":"+39 0541 697372",
    "sg:postcode":"47843",
    "sg:province":"Rimini",
    "sg:tags":[
        "leather"
    ],
    "wof:name":"Calzaturificio Miss Di Mainardi Umberto & C. Snc",
    "wof:placetype":"venue"
},
  "geometry": {"coordinates":[12.644185,43.974129],"type":"Point"}
}