{
  "type": "Feature",
  "properties": {
    "iso:country":"IT",
    "sg:address":"00138 Roma",
    "sg:city":"Roma",
    "sg:orig_category":"Ricambi E Componenti Dei Mezzi Di Trasporto",
    "sg:phone":"+39 06 888 7608",
    "sg:postcode":"00138",
    "sg:province":"Roma",
    "wof:name":"Peruch Adriano",
    "wof:placetype":"venue"
},
  "geometry": {"coordinates":[12.521440506,42.0132369995],"type":"Point"}
}