{
  "type": "Feature",
  "properties": {
    "addr:full":"37029 San Pietro In Cariano San Pietro in Cariano Verona 37029",
    "addr:housenumber":"37029",
    "addr:postcode":"37029",
    "addr:street":"San",
    "iso:country":"IT",
    "sg:address":"37029 San Pietro In Cariano",
    "sg:city":"San Pietro in Cariano",
    "sg:orig_category":"Petroli, Gas E Combustibili",
    "sg:phone":"+39 045 770 2844",
    "sg:postcode":"37029",
    "sg:province":"Verona",
    "wof:name":"Tecnolubeseal S.n.c. Di Lodi Luciano E C.",
    "wof:placetype":"venue"
},
  "geometry": {"coordinates":[10.9373426437,45.4933662415],"type":"Point"}
}