{
  "type": "Feature",
  "properties": {
    "iso:country":"IT",
    "sg:address":"21100 Varese",
    "sg:city":"Bizzozero",
    "sg:orig_category":"Lenti A Contatto E Per Occhiali - Produzione E Ingrosso",
    "sg:phone":"+39 0332 945305",
    "sg:postcode":"21100",
    "sg:province":"Varese",
    "wof:name":"S.i.l.o. Srl",
    "wof:placetype":"venue"
},
  "geometry": {"coordinates":[8.831884,45.818241],"type":"Point"}
}