{
  "type": "Feature",
  "properties": {
    "iso:country":"IT",
    "sg:address":"80138 Napoli",
    "sg:city":"Napoli",
    "sg:orig_category":"Abbigliamento Esterno, Maglierie E Pelliccerie. Calzature, Pelletterie E Pelli",
    "sg:phone":"+39 081 551 7773",
    "sg:postcode":"80138",
    "sg:province":"Napoli",
    "wof:name":"D'ascia Michele",
    "wof:placetype":"venue"
},
  "geometry": {"coordinates":[14.272474,40.881744],"type":"Point"}
}