{
  "type": "Feature",
  "properties": {
    "addr:full":"28100 Novara Novara Novara 28100",
    "addr:postcode":"28100;28100",
    "iso:country":"IT",
    "sg:address":"28100 Novara",
    "sg:city":"Novara",
    "sg:orig_category":"Pasticcerie E Confetterie - Vendita Al Dettaglio",
    "sg:phone":"+39 0321 451303",
    "sg:postcode":"28100",
    "sg:province":"Novara",
    "wof:name":"Bottega Walter",
    "wof:placetype":"venue"
},
  "geometry": {"coordinates":[8.6002845764,45.431602478],"type":"Point"}
}