{
  "type": "Feature",
  "properties": {
    "addr:full":"18, Via Timavo 34074 Monfalcone Monfalcone Gorizia 34074",
    "addr:postcode":"34074;34074",
    "addr:street":"Via Timavo",
    "iso:country":"IT",
    "sg:address":"18, Via Timavo 34074 Monfalcone",
    "sg:city":"Monfalcone",
    "sg:classifiers":[
        {
            "category":"Autos & Motor Vehicles",
            "subcategory":"Boat Sales",
            "type":"Retail Goods"
        }
    ],
    "sg:phone":"+39 0481 411145",
    "sg:postcode":"34074",
    "sg:province":"Gorizia",
    "wof:name":"Officina Frandoli S.r.l.",
    "wof:placetype":"venue"
},
  "geometry": {"coordinates":[13.552495,45.799477],"type":"Point"}
}