{
  "type": "Feature",
  "properties": {
    "iso:country":"IT",
    "sg:address":"Strada Massetana Romana 53100 Siena",
    "sg:city":"Siena",
    "sg:classifiers":[
        {
            "category":"Autos & Motor Vehicles",
            "subcategory":"Automobile Sales",
            "type":"Retail Goods"
        }
    ],
    "sg:phone":"+39 39057747286",
    "sg:postcode":"53100",
    "sg:province":"Siena",
    "sg:tags":[
        "motor-cars"
    ],
    "wof:name":"Pampaloni Srl",
    "wof:placetype":"venue"
},
  "geometry": {"coordinates":[11.3275585175,43.30027771],"type":"Point"}
}