{
  "type": "Feature",
  "properties": {
    "iso:country":"IT",
    "sg:address":"60010 Ostra Vetere",
    "sg:city":"Ostra",
    "sg:orig_category":"Arredo Cucina Ed Elettrodomestici. Elettrodomestici",
    "sg:phone":"+39 071 965709",
    "sg:postcode":"60010",
    "sg:province":"Ancona",
    "wof:name":"F.lli Francescangeli Snc",
    "wof:placetype":"venue"
},
  "geometry": {"coordinates":[13.060962,43.605366],"type":"Point"}
}