{
  "type": "Feature",
  "properties": {
    "addr:full":"20, Via Manzoni 24030 Presezzo Presezzo Bergamo 24030",
    "addr:postcode":"24030;24030",
    "addr:street":"Via Manzoni",
    "iso:country":"IT",
    "sg:address":"20, Via Manzoni 24030 Presezzo",
    "sg:city":"Presezzo",
    "sg:classifiers":[
        {
            "category":"Manufacturing",
            "subcategory":"Rubber & Plastics",
            "type":"Manufacturing & Wholesale Goods"
        }
    ],
    "sg:phone":"+39 39035614060",
    "sg:postcode":"24030",
    "sg:province":"Bergamo",
    "wof:name":"I.l.a.p. (s.r.l.)",
    "wof:placetype":"venue"
},
  "geometry": {"coordinates":[9.574968338,45.7207489014],"type":"Point"}
}