{
  "type": "Feature",
  "properties": {
    "iso:country":"IT",
    "sg:address":"Via Grosio 10/4 20151 Milano",
    "sg:city":"Milano",
    "sg:classifiers":[
        {
            "category":"Manufacturing",
            "subcategory":"Tools & Machinery",
            "type":"Manufacturing & Wholesale Goods"
        }
    ],
    "sg:phone":"+39 0230741",
    "sg:postcode":"20151",
    "sg:province":"Milano",
    "sg:tags":[
        "graphic"
    ],
    "sg:website":"www.agfa.com",
    "wof:name":"Agfa-gevaert Spa",
    "wof:placetype":"venue"
},
  "geometry": {"coordinates":[9.121274,45.499287],"type":"Point"}
}