{
  "type": "Feature",
  "properties": {
    "iso:country":"IT",
    "sg:address":"47900 Rimini",
    "sg:city":"Rimini",
    "sg:orig_category":"Studi E Consulenze Amministrative, Commerciali E Aziendali. Consulenze Tecniche, Amministrative E Perizie. Professionisti - Studi E Servizi Ed Associazioni Di Interesse Aziendale",
    "sg:phone":"+39 0541 780602",
    "sg:postcode":"47900",
    "sg:province":"Rimini",
    "wof:name":"Studio Alaimo Commercialisti Associati",
    "wof:placetype":"venue"
},
  "geometry": {"coordinates":[12.552751,44.026459],"type":"Point"}
}