{
  "type": "Feature",
  "properties": {
    "iso:country":"IT",
    "sg:address":"20123 Milano",
    "sg:city":"Milano",
    "sg:orig_category":"Servizi Editoriali. Professionisti - Studi E Servizi Ed Associazioni Di Interesse Aziendale",
    "sg:phone":"+39 02 8646 5152",
    "sg:postcode":"20123",
    "sg:province":"Milano",
    "wof:name":"Galbraith Robert Foster",
    "wof:placetype":"venue"
},
  "geometry": {"coordinates":[9.185398,45.464699],"type":"Point"}
}