{
  "type": "Feature",
  "properties": {
    "iso:country":"IT",
    "sg:address":"10010 Barone Canavese",
    "sg:city":"Barone Canavese",
    "sg:orig_category":"Valvole E Apparecchiature Di Misura. Ricambi E Componenti Dei Mezzi Di Trasporto",
    "sg:phone":"+39 011 989 9794",
    "sg:postcode":"10010",
    "sg:province":"Torino",
    "sg:website":"http://www.osai.it",
    "wof:name":"Osai Srl",
    "wof:placetype":"venue"
},
  "geometry": {"coordinates":[7.830617,45.487606],"type":"Point"}
}