{
  "type": "Feature",
  "properties": {
    "addr:full":"20157 Milano Milano Milano 20157",
    "addr:postcode":"20157;20157",
    "iso:country":"IT",
    "sg:address":"20157 Milano",
    "sg:city":"Milano",
    "sg:orig_category":"Chiese Ed Associazioni Religiose",
    "sg:phone":"+39 02 355 9997",
    "sg:postcode":"20157",
    "sg:province":"Milano",
    "wof:name":"Suore Ausiliatrici Del Purgatorio",
    "wof:placetype":"venue"
},
  "geometry": {"coordinates":[9.137446,45.51939],"type":"Point"}
}