{
  "type": "Feature",
  "properties": {
    "addr:full":"Via Palladio, 1/1 33010 Feletto Umberto Feletto Umberto Udine 33010",
    "addr:housenumber":"1 / 1",
    "addr:postcode":"33010;33010",
    "addr:street":"Via Palladio;Feletto Umberto",
    "iso:country":"IT",
    "sg:address":"Via Palladio, 1/1 33010 Feletto Umberto",
    "sg:city":"Feletto Umberto",
    "sg:classifiers":[
        {
            "category":"Coffee & Tea",
            "type":"Food & Drink"
        }
    ],
    "sg:phone":"+39 0432 570768",
    "sg:postcode":"33010",
    "sg:province":"Udine",
    "sg:tags":[
        "roasted"
    ],
    "sg:website":"www.orocaffe.com",
    "wof:name":"Oro Caffe' Di Toppano Stefano & C. Snc",
    "wof:placetype":"venue"
},
  "geometry": {"coordinates":[13.217072,46.112144],"type":"Point"}
}