{
  "type": "Feature",
  "properties": {
    "iso:country":"IT",
    "sg:address":"39012 Merano",
    "sg:city":"Merano",
    "sg:orig_category":"Macchine Utensili E Impianti",
    "sg:phone":"+39 0473 270315",
    "sg:postcode":"39012",
    "sg:province":"Bolzano/Bozen",
    "sg:website":"http://www.alpecommerciale.it",
    "wof:name":"Alpe Commerciale Srl",
    "wof:placetype":"venue"
},
  "geometry": {"coordinates":[11.356979,46.495975],"type":"Point"}
}