{
  "type": "Feature",
  "properties": {
    "iso:country":"IT",
    "sg:address":"21, Via Fatebenefratelli 20121 Milano",
    "sg:city":"Milano",
    "sg:classifiers":[
        {
            "category":"Travel",
            "subcategory":"Travel Agent",
            "type":"Entertainment"
        }
    ],
    "sg:phone":"+39 39026572051",
    "sg:postcode":"20121",
    "sg:province":"Milano",
    "sg:tags":[
        "business"
    ],
    "wof:name":"Albergo Cavour",
    "wof:placetype":"venue"
},
  "geometry": {"coordinates":[9.191389,45.473068],"type":"Point"}
}