{
  "type": "Feature",
  "properties": {
    "iso:country":"IT",
    "sg:address":"20129 Milano",
    "sg:city":"Milano",
    "sg:orig_category":"Servizi Editoriali. Pubblicita', Marketing E Comunicazione",
    "sg:phone":"+39 02 7611 0074",
    "sg:postcode":"20129",
    "sg:province":"Milano",
    "wof:name":"Troise Nicoletta E Associati S.a.s.",
    "wof:placetype":"venue"
},
  "geometry": {"coordinates":[9.207993,45.46656],"type":"Point"}
}