{
  "type": "Feature",
  "properties": {
    "iso:country":"IT",
    "sg:address":"12038 Savigliano",
    "sg:city":"Savigliano",
    "sg:orig_category":"Pneumatici - Commercio E Riparazione",
    "sg:phone":"+39 0172 712424",
    "sg:postcode":"12038",
    "sg:province":"Cuneo",
    "wof:name":"Nuova Europneus Saviglianese Di Miretti Giacomo & C. Snc",
    "wof:placetype":"venue"
},
  "geometry": {"coordinates":[7.5605506897,44.3882369995],"type":"Point"}
}