{
  "type": "Feature",
  "properties": {
    "iso:country":"IT",
    "sg:address":"40027 Mordano",
    "sg:city":"Mordano",
    "sg:orig_category":"Prodotti Vari In Metallo. Articoli Per Imballaggio E Confezionamento",
    "sg:phone":"+39 0542 52595",
    "sg:postcode":"40027",
    "sg:province":"Bologna",
    "wof:name":"Defranceschi (s.p.a.)",
    "wof:placetype":"venue"
},
  "geometry": {"coordinates":[11.7680635452,44.4193458557],"type":"Point"}
}