{
  "type": "Feature",
  "properties": {
    "iso:country":"IT",
    "sg:address":"20098 San Giuliano Milanese",
    "sg:city":"San Giuliano Milanese",
    "sg:orig_category":"Prodotti Vari In Metallo. Articoli Per Imballaggio E Confezionamento",
    "sg:phone":"+39 02 984 3402",
    "sg:postcode":"20098",
    "sg:province":"Milano",
    "wof:name":"Legnani & Ferrari (s.r.l.)",
    "wof:placetype":"venue"
},
  "geometry": {"coordinates":[9.2977161407,45.3924026489],"type":"Point"}
}