{
  "type": "Feature",
  "properties": {
    "addr:full":"18, Via Maroncelli Pietro 59100 Prato Prato Prato 59100",
    "addr:postcode":"59100;59100",
    "addr:street":"Via Maroncelli Pietro",
    "iso:country":"IT",
    "sg:address":"18, Via Maroncelli Pietro 59100 Prato",
    "sg:city":"Prato",
    "sg:classifiers":[
        {
            "category":"Shopping",
            "subcategory":"Crafts & Fabrics",
            "type":"Retail Goods"
        }
    ],
    "sg:phone":"+39 39057422156",
    "sg:postcode":"59100",
    "sg:province":"Prato",
    "wof:name":"Lanificio Roma (s.n.c.)",
    "wof:placetype":"venue"
},
  "geometry": {"coordinates":[11.0839328766,43.8883743286],"type":"Point"}
}