{
  "type": "Feature",
  "properties": {
    "iso:country":"IT",
    "sg:address":"32/a, Via Vittorio Veneto 21010 Besnate",
    "sg:city":"Besnate",
    "sg:classifiers":[
        {
            "category":"Professional",
            "subcategory":"Engineering",
            "type":"Services"
        }
    ],
    "sg:phone":"+39 0331 274151",
    "sg:postcode":"21010",
    "sg:province":"Varese",
    "sg:tags":[
        "machine",
        "-",
        "mechanical"
    ],
    "wof:name":"Air Control Srl",
    "wof:placetype":"venue"
},
  "geometry": {"coordinates":[8.826385,45.817604],"type":"Point"}
}