{
  "type": "Feature",
  "properties": {
    "addr:full":"25123 Brescia Brescia Brescia 25123",
    "addr:postcode":"25123;25123",
    "iso:country":"IT",
    "sg:address":"25123 Brescia",
    "sg:city":"Brescia",
    "sg:orig_category":"Elettrotecnica Industriale, Prodotti E Apparecchiature",
    "sg:phone":"+39 030 336 7128",
    "sg:postcode":"25123",
    "sg:province":"Brescia",
    "wof:name":"S.m.a.r.t. Servizi Srl",
    "wof:placetype":"venue"
},
  "geometry": {"coordinates":[11.115941,45.418343],"type":"Point"}
}