{
  "type": "Feature",
  "properties": {
    "addr:full":"23877 Paderno D'adda Lecco 23877",
    "addr:postcode":"23877;23877",
    "iso:country":"IT",
    "sg:address":"23877 Paderno D'adda",
    "sg:orig_category":"Termotecnica E Riscaldamento, Apparecchiature E Servizi",
    "sg:phone":"+39 039 951 5260",
    "sg:postcode":"23877",
    "sg:province":"Lecco",
    "wof:name":"Vitaggio Claudio",
    "wof:placetype":"venue"
},
  "geometry": {"coordinates":[9.449944,45.679222],"type":"Point"}
}