{
  "type": "Feature",
  "properties": {
    "addr:full":"24060 Sovere Sovere Bergamo 24060",
    "addr:postcode":"24060;24060",
    "iso:country":"IT",
    "sg:address":"24060 Sovere",
    "sg:city":"Sovere",
    "sg:orig_category":"Analisi Chimiche, Industriali E Merceologiche",
    "sg:phone":"+39 035 981266",
    "sg:postcode":"24060",
    "sg:province":"Bergamo",
    "sg:website":"http://web.tiscalinet.it/sigieco",
    "wof:name":"Sigieco Di Carrara Dr. Bernardo",
    "wof:placetype":"venue"
},
  "geometry": {"coordinates":[10.029537,45.815334],"type":"Point"}
}