{
  "type": "Feature",
  "properties": {
    "addr:full":"20123 Milano Milano Milano 20123",
    "addr:postcode":"20123;20123",
    "iso:country":"IT",
    "sg:address":"20123 Milano",
    "sg:city":"Milano",
    "sg:orig_category":"Banche E Servizi Finanziari",
    "sg:phone":"+39 02 8942 3930",
    "sg:postcode":"20123",
    "sg:province":"Milano",
    "wof:name":"Sella Consult Simpa",
    "wof:placetype":"venue"
},
  "geometry": {"coordinates":[9.175673,45.460041],"type":"Point"}
}