{
  "type": "Feature",
  "properties": {
    "addr:full":"95036 Randazzo Randazzo Catania 95036",
    "addr:postcode":"95036;95036",
    "iso:country":"IT",
    "sg:address":"95036 Randazzo",
    "sg:city":"Randazzo",
    "sg:classifiers":[
        {
            "category":"Bars & Pubs",
            "subcategory":"Champagne Bar",
            "type":"Food & Drink"
        }
    ],
    "sg:phone":"+39 095 921196",
    "sg:postcode":"95036",
    "sg:province":"Catania",
    "sg:tags":[
        "caffe'",
        "e"
    ],
    "wof:name":"Musumeci Santo",
    "wof:placetype":"venue"
},
  "geometry": {"coordinates":[14.903973,37.567272],"type":"Point"}
}