{
  "type": "Feature",
  "properties": {
    "iso:country":"IT",
    "sg:address":"Via Gallarate 4 21020 Brunello",
    "sg:city":"Brunello",
    "sg:classifiers":[
        {
            "category":"Wholesale",
            "subcategory":"Auto Parts",
            "type":"Manufacturing & Wholesale Goods"
        }
    ],
    "sg:phone":"+39 0332 463386",
    "sg:postcode":"21020",
    "sg:province":"Varese",
    "sg:tags":[
        "wheel",
        "car",
        "alloy",
        "rims"
    ],
    "sg:website":"www.marvic.it",
    "wof:name":"Magnesium World Srl",
    "wof:placetype":"venue"
},
  "geometry": {"coordinates":[8.815958,45.771606],"type":"Point"}
}