{
  "type": "Feature",
  "properties": {
    "iso:country":"IT",
    "sg:address":"17, Via Della Meccanica 37139 Verona",
    "sg:city":"Verona",
    "sg:classifiers":[
        {
            "category":"Personal",
            "subcategory":"Shoe Repair & Shine",
            "type":"Services"
        }
    ],
    "sg:phone":"+39 045 851 0051",
    "sg:postcode":"37139",
    "sg:province":"Verona",
    "sg:tags":[
        "leather"
    ],
    "wof:name":"Scatolificio M G 2 (s.n.c.)",
    "wof:placetype":"venue"
},
  "geometry": {"coordinates":[10.889117,45.450615],"type":"Point"}
}