{
  "type": "Feature",
  "properties": {
    "iso:country":"IT",
    "sg:address":"20123 Milano",
    "sg:city":"Milano",
    "sg:orig_category":"Agenzie D'affari E Servizi Commerciali. Avvocati, Notai E Servizi Legali. Consulenze Tecniche, Amministrative E Perizie",
    "sg:phone":"+39 02 481 9197",
    "sg:postcode":"20123",
    "sg:province":"Milano",
    "wof:name":"Marino Franca Carla",
    "wof:placetype":"venue"
},
  "geometry": {"coordinates":[9.168196,45.471649],"type":"Point"}
}