{
  "type": "Feature",
  "properties": {
    "iso:country":"IT",
    "sg:address":"46, Via Liguria 60030 Monsano",
    "sg:city":"Monsano",
    "sg:classifiers":[
        {
            "category":"Home & Garden",
            "subcategory":"Home Furnishings",
            "type":"Retail Goods"
        }
    ],
    "sg:phone":"+39 0731 619116",
    "sg:postcode":"60030",
    "sg:province":"Ancona",
    "sg:tags":[
        "household"
    ],
    "wof:name":"Politecnica S.r.l.",
    "wof:placetype":"venue"
},
  "geometry": {"coordinates":[13.281013,43.559242],"type":"Point"}
}