{
  "type": "Feature",
  "properties": {
    "addr:full":"Strada Antica Per Benna 1 13871 Verrone Benna Biella 13871",
    "addr:housenumber":"1",
    "addr:postcode":"13871;13871",
    "addr:street":"Strada Antica Per Benna",
    "iso:country":"IT",
    "sg:address":"Strada Antica Per Benna 1 13871 Verrone",
    "sg:city":"Benna",
    "sg:classifiers":[
        {
            "category":"Shopping",
            "subcategory":"Clothing, Apparel, & Fashions",
            "type":"Retail Goods"
        }
    ],
    "sg:phone":"+39 015 255 6411",
    "sg:postcode":"13871",
    "sg:province":"Biella",
    "sg:tags":[
        "sportswear"
    ],
    "wof:name":"Beta Spa",
    "wof:placetype":"venue"
},
  "geometry": {"coordinates":[8.117224,45.512203],"type":"Point"}
}