{
  "type": "Feature",
  "properties": {
    "iso:country":"IT",
    "sg:address":"20129 Milano",
    "sg:city":"Milano",
    "sg:classifiers":[
        {
            "category":"Professional",
            "subcategory":"Management & Consulting",
            "type":"Services"
        }
    ],
    "sg:phone":"+39 0273931",
    "sg:postcode":"20129",
    "sg:province":"Milano",
    "sg:tags":[
        "control",
        "auxiliary",
        "technical",
        "consultant",
        "analysis",
        "research",
        "appraisers",
        "administrative"
    ],
    "wof:name":"Sgs Societe Generale De Surveillance Italia Holding Spa",
    "wof:placetype":"venue"
},
  "geometry": {"coordinates":[9.212657,45.472752],"type":"Point"}
}