{
  "type": "Feature",
  "properties": {
    "addr:full":"37020 Cerro Veronese Cerro Veronese Verona 37020",
    "addr:housenumber":"37020;veronese",
    "addr:postcode":"37020",
    "addr:street":"Cerro;Cerro",
    "iso:country":"IT",
    "sg:address":"37020 Cerro Veronese",
    "sg:city":"Cerro Veronese",
    "sg:orig_category":"Servizi E Lavori Industria Chimica",
    "sg:phone":"+39 045 708 0167",
    "sg:postcode":"37020",
    "sg:province":"Verona",
    "wof:name":"Boschi Rino",
    "wof:placetype":"venue"
},
  "geometry": {"coordinates":[11.042679,45.575447],"type":"Point"}
}