{
  "type": "Feature",
  "properties": {
    "iso:country":"IT",
    "sg:address":"80012 Calvizzano",
    "sg:city":"Calvizzano",
    "sg:orig_category":"Macchine, Impianti E Forniture Per Industria Grafica, Cartaria E Cartotecnica. Prodotti Chimici Secondari",
    "sg:phone":"+39 081 712 3484",
    "sg:postcode":"80012",
    "sg:province":"Napoli",
    "wof:name":"La Vicia Di Giuseppe Ed Enrico Veccia Snc",
    "wof:placetype":"venue"
},
  "geometry": {"coordinates":[14.16312,40.911415],"type":"Point"}
}