{
  "type": "Feature",
  "properties": {
    "iso:country":"IT",
    "sg:address":"113, Via Bellinzona 22100 Como",
    "sg:city":"Como",
    "sg:classifiers":[
        {
            "category":"Professional",
            "subcategory":"Engineering",
            "type":"Services"
        }
    ],
    "sg:phone":"+39 39031572215",
    "sg:postcode":"22100",
    "sg:province":"Como",
    "sg:tags":[
        "machine",
        "-",
        "mechanical"
    ],
    "wof:name":"Oec S.r.l.",
    "wof:placetype":"venue"
},
  "geometry": {"coordinates":[9.063951,45.817909],"type":"Point"}
}