{
  "type": "Feature",
  "properties": {
    "addr:full":"16121 Genova Genova Genova 16121",
    "addr:postcode":"16121;16121",
    "iso:country":"IT",
    "sg:address":"16121 Genova",
    "sg:city":"Genova",
    "sg:classifiers":[
        {
            "category":"Banks & Credit Unions",
            "subcategory":"Investment Brokerage",
            "type":"Services"
        }
    ],
    "sg:phone":"+39 010 565823",
    "sg:postcode":"16121",
    "sg:province":"Genova",
    "sg:tags":[
        "parrucchieri",
        "per",
        "donna"
    ],
    "wof:name":"Gino Lauria Hair Studio",
    "wof:placetype":"venue"
},
  "geometry": {"coordinates":[8.9397134781,44.4056282043],"type":"Point"}
}