{
  "type": "Feature",
  "properties": {
    "addr:full":"62, Via Brugnole 30033 Noale Noale Venezia 30033",
    "addr:postcode":"30033;30033",
    "addr:street":"Via Brugnole",
    "iso:country":"IT",
    "sg:address":"62, Via Brugnole 30033 Noale",
    "sg:city":"Noale",
    "sg:classifiers":[
        {
            "category":"Manufacturing",
            "subcategory":"Metals",
            "type":"Manufacturing & Wholesale Goods"
        }
    ],
    "sg:phone":"+39 041 443 3912",
    "sg:postcode":"30033",
    "sg:province":"Venezia",
    "sg:tags":[
        "processing"
    ],
    "wof:name":"Piccoli",
    "wof:placetype":"venue"
},
  "geometry": {"coordinates":[12.0467348099,45.5428390503],"type":"Point"}
}