{
  "type": "Feature",
  "properties": {
    "iso:country":"IT",
    "sg:address":"10149 Torino",
    "sg:city":"Torino",
    "sg:orig_category":"Apparecchiature Ed Attrezzature Meccaniche",
    "sg:phone":"+39 011 229 6278",
    "sg:postcode":"10149",
    "sg:province":"Torino",
    "wof:name":"V.r.t. H6 Di Schiesaro B. & C. Sas",
    "wof:placetype":"venue"
},
  "geometry": {"coordinates":[7.667388,45.095722],"type":"Point"}
}