{
  "type": "Feature",
  "properties": {
    "iso:country":"IT",
    "sg:address":"92026 Favara",
    "sg:city":"Favara",
    "sg:orig_category":"Minuterie Metalliche E Ferramenta. Ricambi E Componenti Dei Mezzi Di Trasporto",
    "sg:phone":"+39 0922 32260",
    "sg:postcode":"92026",
    "sg:province":"Agrigento",
    "wof:name":"Rizzuto Gaetano",
    "wof:placetype":"venue"
},
  "geometry": {"coordinates":[13.6619081497,37.3228569031],"type":"Point"}
}