{
  "type": "Feature",
  "properties": {
    "iso:country":"IT",
    "sg:address":"25050 Paderno Franciacorta",
    "sg:city":"Paderno Franciacorta",
    "sg:orig_category":"Abbigliamento Intimo, Calze E Costumi Da Bagno",
    "sg:phone":"+39 030 657030",
    "sg:postcode":"25050",
    "sg:province":"Brescia",
    "wof:name":"Zanola Pietro",
    "wof:placetype":"venue"
},
  "geometry": {"coordinates":[10.079001,45.587059],"type":"Point"}
}