{
  "type": "Feature",
  "properties": {
    "iso:country":"IT",
    "sg:address":"80132 Napoli",
    "sg:city":"Napoli",
    "sg:orig_category":"Medici Specialisti - Chirurgia Plastica E Ricostruttiva",
    "sg:phone":"+39 081 552 4783",
    "sg:postcode":"80132",
    "sg:province":"Napoli",
    "sg:website":"http://www.chirurgiaplasticaestetica.com",
    "wof:name":"Centro Medicina E Chirurgia Estetica Slender Srl",
    "wof:placetype":"venue"
},
  "geometry": {"coordinates":[14.246861,40.834728],"type":"Point"}
}