{
  "type": "Feature",
  "properties": {
    "addr:full":"18, Via Gennaro Sora 24060 Villongo Villongo Bergamo 24060",
    "addr:postcode":"24060;24060",
    "addr:street":"Via Gennaro Sora",
    "iso:country":"IT",
    "sg:address":"18, Via Gennaro Sora 24060 Villongo",
    "sg:city":"Villongo",
    "sg:classifiers":[
        {
            "category":"Shopping",
            "subcategory":"Clothing, Apparel, & Fashions",
            "type":"Retail Goods"
        }
    ],
    "sg:phone":"+39 39035929339",
    "sg:postcode":"24060",
    "sg:province":"Bergamo",
    "sg:tags":[
        "clothing",
        "accessory"
    ],
    "wof:name":"Bottonificio B.p.v. (s.r.l.)",
    "wof:placetype":"venue"
},
  "geometry": {"coordinates":[9.926172,45.674858],"type":"Point"}
}