{
  "type": "Feature",
  "properties": {
    "addr:full":"5, Via Beniamino Franklin 41012 Carpi Carpi Modena 41012",
    "addr:postcode":"41012;41012",
    "addr:street":"Via Beniamino Franklin",
    "iso:country":"IT",
    "sg:address":"5, Via Beniamino Franklin 41012 Carpi",
    "sg:city":"Carpi",
    "sg:classifiers":[
        {
            "category":"Professional",
            "subcategory":"Printing & Photocopies",
            "type":"Services"
        }
    ],
    "sg:phone":"+39 39059691118",
    "sg:postcode":"41012",
    "sg:province":"Modena",
    "wof:name":"Nuovagrafica (soc.coop.r.l.)",
    "wof:placetype":"venue"
},
  "geometry": {"coordinates":[10.8553409576,44.7823295593],"type":"Point"}
}