{
  "type": "Feature",
  "properties": {
    "iso:country":"IT",
    "sg:address":"50129 Firenze",
    "sg:city":"Firenze",
    "sg:orig_category":"Accessori Moda D'abbigliamento",
    "sg:phone":"+39 055 474957",
    "sg:postcode":"50129",
    "sg:province":"Firenze",
    "wof:name":"Farnerari Francesco Sas Di Farnerari E. & C.",
    "wof:placetype":"venue"
},
  "geometry": {"coordinates":[11.255213,43.78418],"type":"Point"}
}