{
  "type": "Feature",
  "properties": {
    "iso:country":"IT",
    "sg:address":"81030 Castel Volturno",
    "sg:city":"Castel Volturno",
    "sg:orig_category":"Ospedali E Servizi Sanitari. Centri Di Estetica E Cosmesi E Servizi",
    "sg:phone":"+39 081 509 3644",
    "sg:postcode":"81030",
    "sg:province":"Caserta",
    "wof:name":"Beauty Center Annabella Di Esposito Anna",
    "wof:placetype":"venue"
},
  "geometry": {"coordinates":[13.941737,41.033703],"type":"Point"}
}