{
  "type": "Feature",
  "properties": {
    "addr:full":"Via Dell'industria 53 40014 Crevalcore Crevalcore Bologna 40014",
    "addr:housenumber":"53",
    "addr:postcode":"40014;40014",
    "addr:street":"Via Dell'Industria",
    "iso:country":"IT",
    "sg:address":"Via Dell'industria 53 40014 Crevalcore",
    "sg:city":"Crevalcore",
    "sg:classifiers":[
        {
            "category":"Wholesale",
            "subcategory":"Construction Materials",
            "type":"Manufacturing & Wholesale Goods"
        }
    ],
    "sg:phone":"+39 051 983359",
    "sg:postcode":"40014",
    "sg:province":"Bologna",
    "sg:tags":[
        "mould",
        "tool",
        "system",
        "cad/cam"
    ],
    "sg:website":"www.aziendeemilia.com/mb",
    "wof:name":"M.b. Di Bottazzi Veronesi Ferriani Snc",
    "wof:placetype":"venue"
},
  "geometry": {"coordinates":[11.17407,44.718098],"type":"Point"}
}