{
  "type": "Feature",
  "properties": {
    "addr:full":"20045 Besana In Brianza Besana in Brianza Milano 20045",
    "addr:postcode":"20045;20045",
    "iso:country":"IT",
    "sg:address":"20045 Besana In Brianza",
    "sg:city":"Besana in Brianza",
    "sg:orig_category":"Forniture Per Edilizia E Lavori Pubblici",
    "sg:phone":"+39 036 299 5340",
    "sg:postcode":"20045",
    "sg:province":"Milano",
    "wof:name":"Cibis (s.n.c.)",
    "wof:placetype":"venue"
},
  "geometry": {"coordinates":[9.2788677216,45.7030296326],"type":"Point"}
}