{
  "type": "Feature",
  "properties": {
    "addr:full":"41030 Bomporto Bomporto Modena 41030",
    "addr:postcode":"41030;41030",
    "iso:country":"IT",
    "sg:address":"41030 Bomporto",
    "sg:city":"Bomporto",
    "sg:orig_category":"Arredamento Alberghi",
    "sg:phone":"+39 059 818001",
    "sg:postcode":"41030",
    "sg:province":"Modena",
    "sg:website":"http://www.intertecnica.it",
    "wof:name":"Intertecnica Arredamenti Srl",
    "wof:placetype":"venue"
},
  "geometry": {"coordinates":[11.007018,44.690353],"type":"Point"}
}