{
  "type": "Feature",
  "properties": {
    "iso:country":"IT",
    "sg:address":"35, Via Del Marchesato 48100 Ravenna",
    "sg:city":"Ravenna",
    "sg:classifiers":[
        {
            "category":"Manufacturing",
            "subcategory":"Chemicals & Compounds",
            "type":"Manufacturing & Wholesale Goods"
        }
    ],
    "sg:phone":"+39 0544 530152",
    "sg:postcode":"48100",
    "sg:province":"Ravenna",
    "sg:tags":[
        "chemistry"
    ],
    "wof:name":"Ambiente Mare S.p.a.",
    "wof:placetype":"venue"
},
  "geometry": {"coordinates":[12.273038,44.474754],"type":"Point"}
}