{
  "type": "Feature",
  "properties": {
    "addr:full":"90135 Palermo Palermo Palermo 90135",
    "addr:postcode":"90135;90135",
    "iso:country":"IT",
    "sg:address":"90135 Palermo",
    "sg:city":"Palermo",
    "sg:orig_category":"Non-classified Establishments",
    "sg:phone":"+39 091 673 1760",
    "sg:postcode":"90135",
    "sg:province":"Palermo",
    "wof:name":"Mobili Zito Di Zito Raffaele & Figli",
    "wof:placetype":"venue"
},
  "geometry": {"coordinates":[13.312017,38.129059],"type":"Point"}
}