{
  "type": "Feature",
  "properties": {
    "addr:full":"V.le Carlo Traversa Via Galvani 81020 San Nicola La Strada San Nicola la Strada Caserta 81020",
    "addr:postcode":"81020;81020",
    "addr:street":"V.Le Carlo Traversa Via Galvani;Strada Caserta",
    "iso:country":"IT",
    "sg:address":"V.le Carlo Traversa Via Galvani 81020 San Nicola La Strada",
    "sg:city":"San Nicola la Strada",
    "sg:classifiers":[
        {
            "category":"Autos & Motor Vehicles",
            "subcategory":"Automobile Sales",
            "type":"Retail Goods"
        }
    ],
    "sg:phone":"+39 0823 458755",
    "sg:postcode":"81020",
    "sg:province":"Caserta",
    "sg:tags":[
        "including",
        "jacks",
        "hydraulic",
        "jack"
    ],
    "wof:name":"Proma Srl",
    "wof:placetype":"venue"
},
  "geometry": {"coordinates":[14.332194,41.075417],"type":"Point"}
}