{
  "type": "Feature",
  "properties": {
    "iso:country":"IT",
    "sg:address":"225, V. I Maggio",
    "sg:classifiers":[
        {
            "category":"Wholesale",
            "subcategory":"Drugs",
            "type":"Manufacturing & Wholesale Goods"
        }
    ],
    "sg:phone":"+39 049 897 5462",
    "sg:postcode":"35031",
    "sg:province":"Padova",
    "sg:tags":[
        "chemical",
        "pharmaceutical"
    ],
    "sg:website":"http://www.tagtech.it",
    "wof:name":"T.a.g.",
    "wof:placetype":"venue"
},
  "geometry": {"coordinates":[11.876589,45.409569],"type":"Point"}
}