{
  "type": "Feature",
  "properties": {
    "iso:country":"IT",
    "sg:address":"30, Corso Europa 20090 Cusago",
    "sg:city":"Cusago",
    "sg:classifiers":[
        {
            "category":"Manufacturing",
            "subcategory":"Tools & Machinery",
            "type":"Manufacturing & Wholesale Goods"
        }
    ],
    "sg:phone":"+39 390 290 3351",
    "sg:postcode":"20090",
    "sg:province":"Milano",
    "sg:tags":[
        "environment",
        "equipment",
        "-"
    ],
    "wof:name":"Trane Italia Srl",
    "wof:placetype":"venue"
},
  "geometry": {"coordinates":[9.053082,45.430435],"type":"Point"}
}