{
  "type": "Feature",
  "properties": {
    "iso:country":"IT",
    "sg:address":"37012 Bussolengo",
    "sg:city":"Bussolengo",
    "sg:orig_category":"Servizi Ausiliari Di Certificati, Riproduzioni, Disegni E Foto",
    "sg:phone":"+39 045 715 2555",
    "sg:postcode":"37012",
    "sg:province":"Verona",
    "sg:website":"http://www.albertini-bussolengo.it",
    "wof:name":"Albertini Bussolengo Snc - M.t.s. Srl",
    "wof:placetype":"venue"
},
  "geometry": {"coordinates":[10.853309,45.468784],"type":"Point"}
}