{
  "type": "Feature",
  "properties": {
    "addr:full":"00048 Nettuno Nettuno Roma 00048",
    "addr:postcode":"00048;roma 00048",
    "iso:country":"IT",
    "sg:address":"00048 Nettuno",
    "sg:city":"Nettuno",
    "sg:orig_category":"Carte Plastiche, Magnetiche E Smart - Badges",
    "sg:phone":"+39 06 985 9379",
    "sg:postcode":"00048",
    "sg:province":"Roma",
    "wof:name":"Ciemme Nettuno Srl",
    "wof:placetype":"venue"
},
  "geometry": {"coordinates":[12.513121,41.911686],"type":"Point"}
}