{
  "type": "Feature",
  "properties": {
    "iso:country":"IT",
    "sg:address":"25062 Concesio",
    "sg:city":"Concesio",
    "sg:orig_category":"Abbigliamento Intimo, Calze E Costumi Da Bagno. Articoli Medico-sanitari Ed Ortopedici",
    "sg:phone":"+39 030 275 4221",
    "sg:postcode":"25062",
    "sg:province":"Brescia",
    "wof:name":"Essepi Srl",
    "wof:placetype":"venue"
},
  "geometry": {"coordinates":[10.220429,45.598469],"type":"Point"}
}