{
  "type": "Feature",
  "properties": {
    "addr:full":"36040 Brendola Brendola Vicenza 36040",
    "addr:postcode":"36040;36040",
    "iso:country":"IT",
    "sg:address":"36040 Brendola",
    "sg:city":"Brendola",
    "sg:orig_category":"Pompe Elettriche",
    "sg:phone":"+39 0444 401038",
    "sg:postcode":"36040",
    "sg:province":"Vicenza",
    "wof:name":"Bato Snc",
    "wof:placetype":"venue"
},
  "geometry": {"coordinates":[11.4335317612,45.47838974],"type":"Point"}
}