{
  "type": "Feature",
  "properties": {
    "iso:country":"IT",
    "sg:address":"00187 Roma",
    "sg:city":"Roma",
    "sg:orig_category":"Articoli Da Regalo. Shopping. Regalistica Aziendale",
    "sg:phone":"+39 06 6992 4835",
    "sg:postcode":"00187",
    "sg:province":"Roma",
    "sg:website":"http://www.argentolucchini.com",
    "wof:name":"L.r.s. Gestioni E Servizi Snc",
    "wof:placetype":"venue"
},
  "geometry": {"coordinates":[12.488222,41.906181],"type":"Point"}
}