{
  "type": "Feature",
  "properties": {
    "iso:country":"IT",
    "sg:address":"20141 Milano",
    "sg:city":"Milano",
    "sg:orig_category":"Ristorazione E Locali Pubblici Affini. Ristoranti Ed Esercizi Affini. Servizi Ausiliari Di Ristorazione E Di Intrattenimento",
    "sg:phone":"+39 02 8950 0548",
    "sg:postcode":"20141",
    "sg:province":"Milano",
    "sg:website":"http://www.osteriadellagraffignana.it",
    "wof:name":"Tentazione Srl Osteria Della Graffignana",
    "wof:placetype":"venue"
},
  "geometry": {"coordinates":[9.18986,45.44022],"type":"Point"}
}