{
  "type": "Feature",
  "properties": {
    "iso:country":"IT",
    "sg:address":"54033 Carrara",
    "sg:city":"Carrara",
    "sg:orig_category":"Macchine Ed Impianti Per Edilizia E Lavori Pubblici",
    "sg:phone":"+39 0585 857642",
    "sg:postcode":"54033",
    "sg:province":"Massa-Carrara",
    "wof:name":"Metaltecnica Snc",
    "wof:placetype":"venue"
},
  "geometry": {"coordinates":[10.067697,44.04464],"type":"Point"}
}