{
  "type": "Feature",
  "properties": {
    "addr:full":"00043 Ciampino Ciampino Roma 00043",
    "addr:postcode":"00043;roma 00043",
    "iso:country":"IT",
    "sg:address":"00043 Ciampino",
    "sg:city":"Ciampino",
    "sg:orig_category":"Scuole E Servizi Scolastici. Centri Di Estetica E Cosmesi E Servizi. Ricerca, Selezione E Formazione Del Personale",
    "sg:phone":"+39 06 791 8090",
    "sg:postcode":"00043",
    "sg:province":"Roma",
    "wof:name":"Arte Estetica Femminile Di Consalvo Flora & C. Sc",
    "wof:placetype":"venue"
},
  "geometry": {"coordinates":[12.598357,41.807388],"type":"Point"}
}