{
  "type": "Feature",
  "properties": {
    "iso:country":"IT",
    "sg:address":"37047 San Bonifacio",
    "sg:city":"San Bonifacio",
    "sg:orig_category":"Apparecchiature E Sistemi Per Magazzinaggio E Movimentazione",
    "sg:phone":"+39 045 761 0328",
    "sg:postcode":"37047",
    "sg:province":"Verona",
    "sg:website":"http://www.falcoautomazioni.it",
    "wof:name":"Falco Costruzioni Meccaniche Sas",
    "wof:placetype":"venue"
},
  "geometry": {"coordinates":[11.303888,45.393406],"type":"Point"}
}