{
  "type": "Feature",
  "properties": {
    "iso:country":"IT",
    "sg:address":"30174 Mestre",
    "sg:city":"Mestre",
    "sg:orig_category":"Servizi Ausiliari Di Certificati, Riproduzioni, Disegni E Foto",
    "sg:phone":"+39 041 908555",
    "sg:postcode":"30174",
    "sg:province":"Venezia",
    "wof:name":"La Castellana Di Scaggiante Ivana",
    "wof:placetype":"venue"
},
  "geometry": {"coordinates":[12.209213,45.514015],"type":"Point"}
}