{
  "type": "Feature",
  "properties": {
    "iso:country":"IT",
    "sg:address":"V. Lago Di Levico 36015 Schio",
    "sg:city":"Schio",
    "sg:classifiers":[
        {
            "category":"Manufacturing",
            "subcategory":"Metals",
            "type":"Manufacturing & Wholesale Goods"
        }
    ],
    "sg:phone":"+39 0445 575877",
    "sg:postcode":"36015",
    "sg:province":"Vicenza",
    "sg:tags":[
        "metallurgy",
        "metalworking"
    ],
    "sg:website":"http://www.sainoss.it",
    "wof:name":"Sainoss Srl",
    "wof:placetype":"venue"
},
  "geometry": {"coordinates":[11.402797699,45.7155036926],"type":"Point"}
}