{
  "type": "Feature",
  "properties": {
    "iso:country":"IT",
    "sg:address":"Via Giambello 5 21040 Jerago Con Orago",
    "sg:city":"Jerago con Orago",
    "sg:orig_category":"Plastic Profiles, Porous",
    "sg:phone":"+39 0331 217419",
    "sg:postcode":"21040",
    "sg:province":"Varese",
    "sg:website":"www.generalplast.it",
    "wof:name":"Generalplast Srl",
    "wof:placetype":"venue"
},
  "geometry": {"coordinates":[8.8058414459,45.7047233582],"type":"Point"}
}