{
  "type": "Feature",
  "properties": {
    "iso:country":"IT",
    "sg:address":"Via Alemanni 6 20095 Cusano Milanino",
    "sg:city":"Cusano Milanino",
    "sg:classifiers":[
        {
            "category":"Manufacturing",
            "subcategory":"Petroleum Products",
            "type":"Manufacturing & Wholesale Goods"
        }
    ],
    "sg:phone":"+39 02 613 1081",
    "sg:postcode":"20095",
    "sg:province":"Milano",
    "sg:tags":[
        "cosmetic",
        "distributors"
    ],
    "wof:name":"H.h.s. Italia Srl",
    "wof:placetype":"venue"
},
  "geometry": {"coordinates":[9.180757,45.548786],"type":"Point"}
}