{
  "type": "Feature",
  "properties": {
    "iso:country":"IT",
    "sg:address":"22100 Como",
    "sg:city":"Como",
    "sg:orig_category":"Brevetti D'invenzione - Consulenza Tecnica E Legale",
    "sg:phone":"+39 031 267840",
    "sg:postcode":"22100",
    "sg:province":"Como",
    "wof:name":"Ufficio Brevetti Calciati Srl",
    "wof:placetype":"venue"
},
  "geometry": {"coordinates":[9.077683,45.810627],"type":"Point"}
}