{
  "type": "Feature",
  "properties": {
    "addr:full":"44100 Ferrara Ferrara Ferrara 44100",
    "addr:postcode":"44100;44100",
    "iso:country":"IT",
    "sg:address":"44100 Ferrara",
    "sg:city":"Ferrara",
    "sg:orig_category":"Centri Di Estetica E Cosmesi E Servizi",
    "sg:phone":"+39 0532 207400",
    "sg:postcode":"44100",
    "sg:province":"Ferrara",
    "wof:name":"Bordoni Leda",
    "wof:placetype":"venue"
},
  "geometry": {"coordinates":[11.621686,44.834808],"type":"Point"}
}