{
  "type": "Feature",
  "properties": {
    "addr:full":"20151 Milano Milano Milano 20151",
    "addr:postcode":"20151;20151",
    "iso:country":"IT",
    "sg:address":"20151 Milano",
    "sg:city":"Milano",
    "sg:orig_category":"Telecomunicazioni Impianti Ed Apparecchi - Vendita Al Dettaglio",
    "sg:phone":"+39 02 4091 5254",
    "sg:postcode":"20151",
    "sg:province":"Milano",
    "sg:website":"http://www.telefuturosnc.it",
    "wof:name":"Telefuturo Snc",
    "wof:placetype":"venue"
},
  "geometry": {"coordinates":[9.103538,45.503349],"type":"Point"}
}