{
  "type": "Feature",
  "properties": {
    "iso:country":"IT",
    "sg:address":"12100 Cuneo",
    "sg:city":"Cuneo",
    "sg:orig_category":"Prodotti Di Base E Forniture Per Industria Alimentare E Bevande",
    "sg:phone":"+39 0171 681543",
    "sg:postcode":"12100",
    "sg:province":"Cuneo",
    "wof:name":"Sardo & Quaglia",
    "wof:placetype":"venue"
},
  "geometry": {"coordinates":[7.4866976738,44.5029296875],"type":"Point"}
}