{
  "type": "Feature",
  "properties": {
    "iso:country":"IT",
    "sg:address":"20033 Desio",
    "sg:city":"Desio",
    "sg:orig_category":"Carpenterie Legno",
    "sg:phone":"+39 036 262 7401",
    "sg:postcode":"20033",
    "sg:province":"Milano",
    "wof:name":"I.c.l. Sas Di Cattaneo & C.",
    "wof:placetype":"venue"
},
  "geometry": {"coordinates":[9.254733,45.461857],"type":"Point"}
}