{
  "type": "Feature",
  "properties": {
    "iso:country":"IT",
    "sg:address":"20145 Milano",
    "sg:city":"Milano",
    "sg:orig_category":"Cinematografia E Radiotelevisione. Pubblicita', Marketing E Comunicazione. Acqua, Luce, Gas E Societa' Di Esercizio Pubblico",
    "sg:phone":"+39 023888",
    "sg:postcode":"20145",
    "sg:province":"Milano",
    "wof:name":"Rai Radiotelevisione Italiana",
    "wof:placetype":"venue"
},
  "geometry": {"coordinates":[9.166914,45.479336],"type":"Point"}
}