{
  "type": "Feature",
  "properties": {
    "iso:country":"IT",
    "sg:address":"23887 Olgiate Molgora",
    "sg:city":"Olgiate Molgora",
    "sg:orig_category":"Caminetti, Forni Da Giardino E Barbecues",
    "sg:phone":"+39 039 927 4305",
    "sg:postcode":"23887",
    "sg:province":"Lecco",
    "sg:website":"http://www.piros.it",
    "wof:name":"Piros Srl",
    "wof:placetype":"venue"
},
  "geometry": {"coordinates":[9.411328,45.736061],"type":"Point"}
}