{
  "type": "Feature",
  "properties": {
    "iso:country":"IT",
    "sg:address":"Vl. Venezia, 1; Fossalta; 30025",
    "sg:classifiers":[
        {
            "category":"Banks & Credit Unions",
            "subcategory":"Bank",
            "type":"Services"
        }
    ],
    "sg:phone":"+39 0421 789292",
    "sg:postcode":"30025",
    "sg:province":"Venezia",
    "wof:name":"Cassa Rurale Ed Artigiana",
    "wof:placetype":"venue"
},
  "geometry": {"coordinates":[12.90609,45.791885],"type":"Point"}
}