{
  "type": "Feature",
  "properties": {
    "iso:country":"IT",
    "sg:address":"50131 Firenze",
    "sg:city":"Firenze",
    "sg:orig_category":"Abbigliamento - Vendita Al Dettaglio",
    "sg:phone":"+39 055 561191",
    "sg:postcode":"50131",
    "sg:province":"Firenze",
    "wof:name":"Fox Srl",
    "wof:placetype":"venue"
},
  "geometry": {"coordinates":[11.2792,43.7812],"type":"Point"}
}