{
  "type": "Feature",
  "properties": {
    "addr:full":"30175 Venezia Venezia Venezia 30175",
    "addr:postcode":"30175;30175",
    "iso:country":"IT",
    "sg:address":"30175 Venezia",
    "sg:city":"Venezia",
    "sg:orig_category":"Fodere E Tappeti Per Autoveicoli - Produzione E Ingrosso",
    "sg:phone":"+39 041 921306",
    "sg:postcode":"30175",
    "sg:province":"Venezia",
    "wof:name":"Damin Maria & C. Snc",
    "wof:placetype":"venue"
},
  "geometry": {"coordinates":[12.9704551697,45.810092926],"type":"Point"}
}