{
  "type": "Feature",
  "properties": {
    "addr:full":"00188 Roma Roma Roma 00188",
    "addr:postcode":"00188;00188",
    "iso:country":"IT",
    "sg:address":"00188 Roma",
    "sg:city":"Roma",
    "sg:orig_category":"Elettronica Professionale E Di Consumo. Forniture Per Il Settore Dello Spettacolo. Automazione E Macchine Per Ufficio. Forniture Per Congressi, Fiere E Manifestazioni",
    "sg:phone":"+39 06 3362 4240",
    "sg:postcode":"00188",
    "sg:province":"Roma",
    "sg:website":"http://www.transvideo.it",
    "wof:name":"Transvideo Srl",
    "wof:placetype":"venue"
},
  "geometry": {"coordinates":[12.484868,41.952129],"type":"Point"}
}