{
  "type": "Feature",
  "properties": {
    "iso:country":"IT",
    "sg:address":"63/d, Localita' La Penna 52028 Terranuova Bracciolini",
    "sg:city":"Penna",
    "sg:classifiers":[
        {
            "category":"Shopping",
            "subcategory":"Clothing, Apparel, & Fashions",
            "type":"Retail Goods"
        }
    ],
    "sg:phone":"+39 055 970 5155",
    "sg:postcode":"52028",
    "sg:province":"Arezzo",
    "sg:tags":[
        "clothes"
    ],
    "wof:name":"Fipel S.r.l.",
    "wof:placetype":"venue"
},
  "geometry": {"coordinates":[11.737691,43.50536],"type":"Point"}
}