{
  "type": "Feature",
  "properties": {
    "iso:country":"IT",
    "sg:address":"25089 Villanuova Sul Clisi",
    "sg:city":"Villanuova sul Clisi",
    "sg:orig_category":"Elettrotecnica Industriale, Prodotti E Apparecchiature",
    "sg:phone":"+39 036 537 3997",
    "sg:postcode":"25089",
    "sg:province":"Brescia",
    "wof:name":"Fioletti Lorenzo",
    "wof:placetype":"venue"
},
  "geometry": {"coordinates":[10.454535,45.602814],"type":"Point"}
}