{
  "type": "Feature",
  "properties": {
    "iso:country":"IT",
    "sg:address":"95128 Catania",
    "sg:city":"Catania",
    "sg:classifiers":[
        {
            "category":"Health Services",
            "subcategory":"Health Practitioner",
            "type":"Services"
        }
    ],
    "sg:phone":"+39 095 551468",
    "sg:postcode":"95128",
    "sg:province":"Catania",
    "sg:tags":[
        "medici"
    ],
    "wof:name":"Perna Dr. Gaetano",
    "wof:placetype":"venue"
},
  "geometry": {"coordinates":[15.0830821991,37.5264892578],"type":"Point"}
}