{
  "type": "Feature",
  "properties": {
    "iso:country":"IT",
    "sg:address":"Via Lomellina 43 27025 Gambolo'",
    "sg:classifiers":[
        {
            "category":"Building & Trades",
            "subcategory":"Construction",
            "type":"Services"
        }
    ],
    "sg:phone":"+39 0381 930313",
    "sg:postcode":"27025",
    "sg:province":"Pavia",
    "sg:tags":[
        "small",
        "component",
        "industry",
        "assembly"
    ],
    "wof:name":"S.p.s. Srl",
    "wof:placetype":"venue"
},
  "geometry": {"coordinates":[8.860512,45.265629],"type":"Point"}
}