{
  "type": "Feature",
  "properties": {
    "iso:country":"IT",
    "sg:address":"37069 Villafranca Di Verona",
    "sg:city":"Villafranca di Verona",
    "sg:orig_category":"Pubblica Amministrazione",
    "sg:phone":"+39 045 630 5136",
    "sg:postcode":"37069",
    "sg:province":"Verona",
    "wof:name":"Aeronautica Militare - Reparto Mobile Di Supporto",
    "wof:placetype":"venue"
},
  "geometry": {"coordinates":[10.8371896744,45.3600502014],"type":"Point"}
}