{
  "type": "Feature",
  "properties": {
    "addr:full":"90146 Palermo Palermo Palermo 90146",
    "addr:postcode":"90146;90146",
    "iso:country":"IT",
    "sg:address":"90146 Palermo",
    "sg:city":"Palermo",
    "sg:orig_category":"Macchine, Impianti Ed Attrezzature Per Industria Alimentare E Bevande",
    "sg:phone":"+39 091 452212",
    "sg:postcode":"90146",
    "sg:province":"Palermo",
    "wof:name":"C.i.v.a.p.a.n. Sas",
    "wof:placetype":"venue"
},
  "geometry": {"coordinates":[13.323562,38.186623],"type":"Point"}
}