{
  "type": "Feature",
  "properties": {
    "iso:country":"IT",
    "sg:address":"60131 Ancona",
    "sg:city":"Ancona",
    "sg:orig_category":"Prodotti Finiti Stampati. Forniture E Materiali Per Imballaggio E Confezionamento. Forniture Per Attivita' Commerciali Ed Artigianali",
    "sg:phone":"+39 071 804085",
    "sg:postcode":"60131",
    "sg:province":"Ancona",
    "wof:name":"Flexotec Srl",
    "wof:placetype":"venue"
},
  "geometry": {"coordinates":[13.4858617783,43.5704956055],"type":"Point"}
}