{
  "type": "Feature",
  "properties": {
    "addr:full":"04100 Latina Latina Latina 04100",
    "addr:postcode":"04100;04100",
    "iso:country":"IT",
    "sg:address":"04100 Latina",
    "sg:city":"Latina",
    "sg:orig_category":"Scavi E Demolizioni",
    "sg:phone":"+39 0773 623672",
    "sg:postcode":"04100",
    "sg:province":"Latina",
    "sg:website":"http://www.agorascavi.it",
    "wof:name":"Agora Scavi E Trasporti",
    "wof:placetype":"venue"
},
  "geometry": {"coordinates":[12.874495,41.452148],"type":"Point"}
}