{
  "type": "Feature",
  "properties": {
    "addr:full":"Frazione Marino Del Tronto Snc2 63100 Ascoli Piceno Ascoli Piceno Ascoli Piceno 63100",
    "addr:postcode":"63100;63100",
    "addr:street":"Frazione Marino Del Tronto Snc2",
    "iso:country":"IT",
    "sg:address":"Frazione Marino Del Tronto Snc2 63100 Ascoli Piceno",
    "sg:city":"Ascoli Piceno",
    "sg:classifiers":[
        {
            "category":"Manufacturing",
            "subcategory":"Paper Products",
            "type":"Manufacturing & Wholesale Goods"
        }
    ],
    "sg:phone":"+39 390 736 4001",
    "sg:postcode":"63100",
    "sg:province":"Ascoli Piceno",
    "sg:tags":[
        "cardboard"
    ],
    "wof:name":"Ahlstrom Turin Spa",
    "wof:placetype":"venue"
},
  "geometry": {"coordinates":[13.5749769211,42.8554000854],"type":"Point"}
}