{
  "type": "Feature",
  "properties": {
    "addr:full":"3, Via Giovanni Da Udine 20156 Milano Milano Milano 20156",
    "addr:postcode":"20156;20156",
    "addr:street":"Via Giovanni Da Udine",
    "iso:country":"IT",
    "sg:address":"3, Via Giovanni Da Udine 20156 Milano",
    "sg:city":"Milano",
    "sg:classifiers":[
        {
            "category":"Autos & Motor Vehicles",
            "subcategory":"Automobile Sales",
            "type":"Retail Goods"
        }
    ],
    "sg:phone":"+39 390 230 791",
    "sg:postcode":"20156",
    "sg:province":"Milano",
    "sg:tags":[
        "motor-cars"
    ],
    "wof:name":"M.m. Automobili Italia Srl",
    "wof:placetype":"venue"
},
  "geometry": {"coordinates":[9.2032260895,45.4824676514],"type":"Point"}
}