{
  "type": "Feature",
  "properties": {
    "iso:country":"IT",
    "sg:address":"20089 Rozzano",
    "sg:city":"Rozzano",
    "sg:orig_category":"Macchine, Impianti Ed Attrezzature Per Agricoltura E Zootecnia",
    "sg:phone":"+39 02 824 3729",
    "sg:postcode":"20089",
    "sg:province":"Milano",
    "wof:name":"A.p.i. Italia Srl",
    "wof:placetype":"venue"
},
  "geometry": {"coordinates":[9.168729,45.380142],"type":"Point"}
}