{
  "type": "Feature",
  "properties": {
    "addr:full":"Via Val D'elsa 47/49 50053 Empoli Empoli Firenze 50053",
    "addr:housenumber":"47 / 49",
    "addr:postcode":"50053;50053",
    "addr:street":"Via Val D'Elsa",
    "iso:country":"IT",
    "sg:address":"Via Val D'elsa 47/49 50053 Empoli",
    "sg:city":"Empoli",
    "sg:classifiers":[
        {
            "category":"Manufacturing",
            "subcategory":"Glass & Minerals",
            "type":"Manufacturing & Wholesale Goods"
        }
    ],
    "sg:phone":"+39 0571 931593",
    "sg:postcode":"50053",
    "sg:province":"Firenze",
    "sg:tags":[
        "item",
        "gift",
        "crystal"
    ],
    "sg:website":"www.nuovacev.it",
    "wof:name":"Nuova C.e.v. Scrl",
    "wof:placetype":"venue"
},
  "geometry": {"coordinates":[10.891708,43.707378],"type":"Point"}
}