{
  "type": "Feature",
  "properties": {
    "iso:country":"IT",
    "sg:address":"81020 Recale",
    "sg:city":"Recale",
    "sg:orig_category":"Autoaccessori - Vendita Al Dettaglio",
    "sg:phone":"+39 0823 491442",
    "sg:postcode":"81020",
    "sg:province":"Caserta",
    "wof:name":"Stazione Di Servizio Ip Di Piccirillo Teresa",
    "wof:placetype":"venue"
},
  "geometry": {"coordinates":[14.307749,41.064693],"type":"Point"}
}