{
  "type": "Feature",
  "properties": {
    "iso:country":"IT",
    "sg:address":"4/6, Via Di Villa Sacchetti 00197 Roma",
    "sg:city":"Roma",
    "sg:classifiers":[
        {
            "category":"Professional",
            "subcategory":"Business Services",
            "type":"Services"
        }
    ],
    "sg:phone":"+39 390 680 9511",
    "sg:postcode":"00197",
    "sg:province":"Roma",
    "sg:tags":[
        "advice"
    ],
    "wof:name":"Ambasciata Presso La S. Sede Germania",
    "wof:placetype":"venue"
},
  "geometry": {"coordinates":[12.485959,41.919617],"type":"Point"}
}