{
  "type": "Feature",
  "properties": {
    "iso:country":"IT",
    "sg:address":"5/a, Via Ungheri 40012 Calderara Di Reno",
    "sg:city":"Calderara di Reno",
    "sg:classifiers":[
        {
            "category":"Banks & Credit Unions",
            "subcategory":"Investment Brokerage",
            "type":"Services"
        }
    ],
    "sg:phone":"+39 39051726244",
    "sg:postcode":"40012",
    "sg:province":"Bologna",
    "sg:tags":[
        "-",
        "transport",
        "related"
    ],
    "wof:name":"Tag General Air Transport (s.p.a.)",
    "wof:placetype":"venue"
},
  "geometry": {"coordinates":[11.303563,44.546242],"type":"Point"}
}