{
  "type": "Feature",
  "properties": {
    "addr:full":"21042 Caronno Pertusella Caronno Pertusella Varese 21042",
    "addr:postcode":"21042;pertusella;21042",
    "addr:street":"Pertusella",
    "iso:country":"IT",
    "sg:address":"21042 Caronno Pertusella",
    "sg:city":"Caronno Pertusella",
    "sg:orig_category":"Arti Grafiche - Accessori E Forniture",
    "sg:phone":"+39 02 9645 9119",
    "sg:postcode":"21042",
    "sg:province":"Varese",
    "sg:website":"http://www.dedweb.com",
    "wof:name":"D&d Sas",
    "wof:placetype":"venue"
},
  "geometry": {"coordinates":[9.059188,45.59473],"type":"Point"}
}