{
  "type": "Feature",
  "properties": {
    "iso:country":"IT",
    "sg:address":"62, Via Carpi Ravarino 41019 Soliera",
    "sg:city":"Soliera",
    "sg:classifiers":[
        {
            "category":"Shopping",
            "subcategory":"Clothing, Apparel, & Fashions",
            "type":"Retail Goods"
        }
    ],
    "sg:phone":"+39 39059565109",
    "sg:postcode":"41019",
    "sg:province":"Modena",
    "sg:tags":[
        "clothes"
    ],
    "wof:name":"Confezioni Marilyn",
    "wof:placetype":"venue"
},
  "geometry": {"coordinates":[10.96887,44.751347],"type":"Point"}
}