{
  "type": "Feature",
  "properties": {
    "addr:full":"25020 Flero Flero Brescia 25020",
    "addr:postcode":"25020;25020",
    "iso:country":"IT",
    "sg:address":"25020 Flero",
    "sg:city":"Flero",
    "sg:orig_category":"Automobili E Mezzi Di Trasporto. Riparazione Dei Mezzi Di Trasporto",
    "sg:phone":"+39 030 268 0909",
    "sg:postcode":"25020",
    "sg:province":"Brescia",
    "wof:name":"Pulimetal Snc Di Serena Luigi & C.",
    "wof:placetype":"venue"
},
  "geometry": {"coordinates":[10.183835,45.491535],"type":"Point"}
}