{
  "type": "Feature",
  "properties": {
    "addr:full":"35129 Padova Padova Padova 35129",
    "addr:postcode":"35129;35129",
    "iso:country":"IT",
    "sg:address":"35129 Padova",
    "sg:city":"Padova",
    "sg:orig_category":"Architetti - Studi",
    "sg:phone":"+39 049 807 5958",
    "sg:postcode":"35129",
    "sg:province":"Padova",
    "sg:website":"http://www.artufficio.com",
    "wof:name":"Artufficio Srl",
    "wof:placetype":"venue"
},
  "geometry": {"coordinates":[11.912044,45.41069],"type":"Point"}
}