{
  "type": "Feature",
  "properties": {
    "addr:full":"25031 Capriolo Capriolo Brescia 25031",
    "addr:postcode":"25031;25031",
    "iso:country":"IT",
    "sg:address":"25031 Capriolo",
    "sg:city":"Capriolo",
    "sg:orig_category":"Biliardi Ed Accessori",
    "sg:phone":"+39 030 736004",
    "sg:postcode":"25031",
    "sg:province":"Brescia",
    "wof:name":"Volpini Pietro",
    "wof:placetype":"venue"
},
  "geometry": {"coordinates":[10.183167,45.528931],"type":"Point"}
}