{
  "type": "Feature",
  "properties": {
    "iso:country":"IT",
    "sg:address":"16, Via Lago Di Albano 36015 Schio",
    "sg:city":"Schio",
    "sg:classifiers":[
        {
            "category":"Shopping",
            "subcategory":"Clothing, Apparel, & Fashions",
            "type":"Retail Goods"
        }
    ],
    "sg:phone":"+39 0445 575779",
    "sg:postcode":"36015",
    "sg:province":"Vicenza",
    "sg:tags":[
        "clothes"
    ],
    "wof:name":"Vecotex (s.r.l.)",
    "wof:placetype":"venue"
},
  "geometry": {"coordinates":[11.41405,45.717377],"type":"Point"}
}