{
  "type": "Feature",
  "properties": {
    "iso:country":"IT",
    "sg:address":"40123 Bologna",
    "sg:city":"Bologna",
    "sg:orig_category":"Trattamenti Termici E Superficiali Metalli, Galvanotecnica",
    "sg:phone":"+39 051 230537",
    "sg:postcode":"40123",
    "sg:province":"Bologna",
    "wof:name":"Righi Federico",
    "wof:placetype":"venue"
},
  "geometry": {"coordinates":[11.34156,44.493256],"type":"Point"}
}