{
  "type": "Feature",
  "properties": {
    "addr:full":"60128 Ancona Ancona Ancona 60128",
    "addr:postcode":"60128;60128",
    "iso:country":"IT",
    "sg:address":"60128 Ancona",
    "sg:city":"Ancona",
    "sg:orig_category":"Abbigliamento Esterno, Maglierie E Pelliccerie",
    "sg:phone":"+39 071 34389",
    "sg:postcode":"60128",
    "sg:province":"Ancona",
    "wof:name":"Mamma Serena Sas",
    "wof:placetype":"venue"
},
  "geometry": {"coordinates":[13.539152,43.603954],"type":"Point"}
}