{
  "type": "Feature",
  "properties": {
    "iso:country":"IT",
    "sg:address":"24046 Osio Sotto",
    "sg:city":"Osio Sotto",
    "sg:orig_category":"Macchine Utensili E Impianti",
    "sg:phone":"+39 035 482 3251",
    "sg:postcode":"24046",
    "sg:province":"Bergamo",
    "wof:name":"A.g.r. Di Bugini Ing. Giancarlo E C. (s.a.s.)",
    "wof:placetype":"venue"
},
  "geometry": {"coordinates":[9.607411,45.644283],"type":"Point"}
}