{
  "type": "Feature",
  "properties": {
    "addr:full":"20026 Novate Milanese Novate Milanese Milano 20026",
    "addr:postcode":"20026;20026",
    "iso:country":"IT",
    "sg:address":"20026 Novate Milanese",
    "sg:city":"Novate Milanese",
    "sg:orig_category":"Macchine Utensili E Impianti",
    "sg:phone":"+39 02 354 4909",
    "sg:postcode":"20026",
    "sg:province":"Milano",
    "wof:name":"B.p.f. Fratelli Bassi Snc",
    "wof:placetype":"venue"
},
  "geometry": {"coordinates":[9.148479,45.533169],"type":"Point"}
}