{
  "type": "Feature",
  "properties": {
    "addr:full":"71/a, Via Italia 25080 Paitone Paitone Brescia 25080",
    "addr:housenumber":"71 / a",
    "addr:postcode":"25080;25080",
    "addr:street":"Italia",
    "iso:country":"IT",
    "sg:address":"71/a, Via Italia 25080 Paitone",
    "sg:city":"Paitone",
    "sg:classifiers":[
        {
            "category":"Food & Beverages",
            "subcategory":"Groceries & Convenience Stores",
            "type":"Retail Goods"
        }
    ],
    "sg:phone":"+39 030 689 6941",
    "sg:postcode":"25080",
    "sg:province":"Brescia",
    "sg:tags":[
        "product",
        "related"
    ],
    "wof:name":"Zabe Di Zanetti Beniamino & C. (s.n.c.)",
    "wof:placetype":"venue"
},
  "geometry": {"coordinates":[10.2229576111,45.5398292542],"type":"Point"}
}