{
  "type": "Feature",
  "properties": {
    "addr:full":"Via Ludovico Di Breme 33 20156 Milano Milano Milano 20156",
    "addr:housenumber":"33",
    "addr:postcode":"20156;20156",
    "addr:street":"Via Ludovico Di Breme",
    "iso:country":"IT",
    "sg:address":"Via Ludovico Di Breme 33 20156 Milano",
    "sg:city":"Milano",
    "sg:classifiers":[
        {
            "category":"Real Estate",
            "subcategory":"Real Estate Services",
            "type":"Services"
        }
    ],
    "sg:phone":"+39 02 308 5441",
    "sg:postcode":"20156",
    "sg:province":"Milano",
    "sg:tags":[
        "pharmaceutical",
        "material",
        "raw"
    ],
    "wof:name":"Amsa Anonima Materie Sintetiche E Affini Spa",
    "wof:placetype":"venue"
},
  "geometry": {"coordinates":[9.1389732361,45.498046875],"type":"Point"}
}