{
  "type": "Feature",
  "properties": {
    "addr:full":"07100 Sassari Sassari Sassari 07100",
    "addr:postcode":"07100;07100",
    "iso:country":"IT",
    "sg:address":"07100 Sassari",
    "sg:city":"Sassari",
    "sg:orig_category":"Autoaccessori - Commercio",
    "sg:phone":"+39 079 263 3019",
    "sg:postcode":"07100",
    "sg:province":"Sassari",
    "wof:name":"Torresauto Srl",
    "wof:placetype":"venue"
},
  "geometry": {"coordinates":[8.537682,40.739014],"type":"Point"}
}