{
  "type": "Feature",
  "properties": {
    "addr:full":"15, Via Xxv Luglio 84019 Vietri Sul Mare Vietri sul Mare Salerno 84019",
    "addr:housenumber":"mare",
    "addr:postcode":"84019;84019",
    "addr:street":"Via Xxv Luglio",
    "iso:country":"IT",
    "sg:address":"15, Via Xxv Luglio 84019 Vietri Sul Mare",
    "sg:city":"Vietri sul Mare",
    "sg:classifiers":[
        {
            "category":"Manufacturing",
            "subcategory":"Glass & Minerals",
            "type":"Manufacturing & Wholesale Goods"
        }
    ],
    "sg:phone":"+39 39089210048",
    "sg:postcode":"84019",
    "sg:province":"Salerno",
    "sg:tags":[
        "building",
        "material"
    ],
    "wof:name":"Ceramica Vietri Mare Fratelli Solimene",
    "wof:placetype":"venue"
},
  "geometry": {"coordinates":[14.765912,40.677956],"type":"Point"}
}