{
  "type": "Feature",
  "properties": {
    "iso:country":"IT",
    "sg:address":"20017 Rho",
    "sg:city":"Rho",
    "sg:orig_category":"Ricambi E Componenti Dei Mezzi Di Trasporto",
    "sg:phone":"+39 02 9390 4655",
    "sg:postcode":"20017",
    "sg:province":"Milano",
    "wof:name":"Elring Klinger S.p.a.",
    "wof:placetype":"venue"
},
  "geometry": {"coordinates":[9.077853,45.528698],"type":"Point"}
}