{
  "type": "Feature",
  "properties": {
    "addr:full":"7/7/a, Via C. Colombo 30030 Vigonovo Vigonovo Venezia 30030",
    "addr:housenumber":"7 / 7 / a",
    "addr:postcode":"30030;30030",
    "addr:street":"Via C. Colombo",
    "iso:country":"IT",
    "sg:address":"7/7/a, Via C. Colombo 30030 Vigonovo",
    "sg:city":"Vigonovo",
    "sg:classifiers":[
        {
            "category":"Wholesale",
            "subcategory":"Drugs",
            "type":"Manufacturing & Wholesale Goods"
        }
    ],
    "sg:phone":"+39 39049502855",
    "sg:postcode":"30030",
    "sg:province":"Venezia",
    "sg:tags":[
        "chemical",
        "pharmaceutical"
    ],
    "wof:name":"Kollant Industrie Chimiche (s.p.a.)",
    "wof:placetype":"venue"
},
  "geometry": {"coordinates":[12.338784,45.434338],"type":"Point"}
}