{
  "type": "Feature",
  "properties": {
    "iso:country":"IT",
    "sg:address":"56017 San Giuliano Terme",
    "sg:city":"San Giuliano Terme",
    "sg:orig_category":"Sport - Articoli E Forniture",
    "sg:phone":"+39 050 815063",
    "sg:postcode":"56017",
    "sg:province":"Pisa",
    "wof:name":"Nobel Sport Martignoni Spa",
    "wof:placetype":"venue"
},
  "geometry": {"coordinates":[10.433986,43.74614],"type":"Point"}
}