{
  "type": "Feature",
  "properties": {
    "iso:country":"IT",
    "sg:address":"24129 Bergamo",
    "sg:city":"Bergamo",
    "sg:orig_category":"Orologeria. Shopping",
    "sg:phone":"+39 035 251125",
    "sg:postcode":"24129",
    "sg:province":"Bergamo",
    "sg:website":"http://www.gioielleriaruggieri.it",
    "wof:name":"Gioielleria Ruggieri",
    "wof:placetype":"venue"
},
  "geometry": {"coordinates":[9.631822,45.693687],"type":"Point"}
}