{
  "type": "Feature",
  "properties": {
    "iso:country":"IT",
    "sg:address":"46100 Mantova",
    "sg:city":"Mantova",
    "sg:orig_category":"Riparazione Dei Mezzi Di Trasporto",
    "sg:phone":"+39 0376 398177",
    "sg:postcode":"46100",
    "sg:province":"Mantova",
    "wof:name":"Bianchi Giovanni Di Bianchi Fausto & C. Sas",
    "wof:placetype":"venue"
},
  "geometry": {"coordinates":[10.782097,45.181141],"type":"Point"}
}