{
  "type": "Feature",
  "properties": {
    "iso:country":"IT",
    "sg:address":"84099 San Cipriano Picentino",
    "sg:city":"San Cipriano Picentino",
    "sg:orig_category":"Scuole E Servizi Scolastici. Servizi Ausiliari Dei Mezzi Di Trasporto. Ricerca, Selezione E Formazione Del Personale",
    "sg:phone":"+39 089 881296",
    "sg:postcode":"84099",
    "sg:province":"Salerno",
    "wof:name":"Autoscuola Marino Matteo",
    "wof:placetype":"venue"
},
  "geometry": {"coordinates":[14.863244,40.698833],"type":"Point"}
}