{
  "type": "Feature",
  "properties": {
    "iso:country":"IT",
    "sg:address":"42100 Reggio Emilia",
    "sg:orig_category":"Servizi Di Magazzinaggio E Movimentazione",
    "sg:phone":"+39 0522 306785",
    "sg:postcode":"42100",
    "sg:province":"Reggio Nell'Emilia",
    "wof:name":"Gruppo Facchini Emiliano",
    "wof:placetype":"venue"
},
  "geometry": {"coordinates":[10.614607,44.694843],"type":"Point"}
}