{
  "type": "Feature",
  "properties": {
    "iso:country":"IT",
    "sg:address":"24040 Madone",
    "sg:city":"Madone",
    "sg:orig_category":"Macchine Utensili E Impianti. Macchine, Strumenti Ed Apparecchi Per Attivita' Industriali",
    "sg:phone":"+39 035 499 7224",
    "sg:postcode":"24040",
    "sg:province":"Bergamo",
    "wof:name":"Gigliotti Daniele",
    "wof:placetype":"venue"
},
  "geometry": {"coordinates":[9.553348,45.653526],"type":"Point"}
}