{
  "type": "Feature",
  "properties": {
    "iso:country":"IT",
    "sg:address":"Via Anselmo Guerrieri Gonzaga 28 46023 Gonzaga",
    "sg:city":"Gonzaga",
    "sg:classifiers":[
        {
            "category":"Wholesale",
            "subcategory":"Machinery & Supplies",
            "type":"Manufacturing & Wholesale Goods"
        }
    ],
    "sg:phone":"+39 0376 5891",
    "sg:postcode":"46023",
    "sg:province":"Mantova",
    "sg:tags":[
        "agricultural",
        "equipment"
    ],
    "sg:website":"www.grecav.it",
    "wof:name":"Grecav S.p.a.",
    "wof:placetype":"venue"
},
  "geometry": {"coordinates":[10.800282,44.964504],"type":"Point"}
}