{
  "type": "Feature",
  "properties": {
    "addr:full":"21100 Varese Varese Varese 21100",
    "addr:postcode":"21100;21100",
    "iso:country":"IT",
    "sg:address":"21100 Varese",
    "sg:city":"Varese",
    "sg:orig_category":"Arte Ed Artigianato Artistico. Scuole E Servizi Scolastici. Servizi Ausiliari Di Analisi, Controllo E Ricerca",
    "sg:phone":"+39 0332 334738",
    "sg:postcode":"21100",
    "sg:province":"Varese",
    "wof:name":"Scuola Di Musica Tenzi Di Tenzi Alberto",
    "wof:placetype":"venue"
},
  "geometry": {"coordinates":[8.866539,45.784531],"type":"Point"}
}