{
  "type": "Feature",
  "properties": {
    "iso:country":"IT",
    "sg:address":"20131 Milano",
    "sg:city":"Milano",
    "sg:orig_category":"Elettricisti",
    "sg:phone":"+39 02 2689 2525",
    "sg:postcode":"20131",
    "sg:province":"Milano",
    "wof:name":"Associazione Artigiani",
    "wof:placetype":"venue"
},
  "geometry": {"coordinates":[9.227928,45.488018],"type":"Point"}
}