{
  "type": "Feature",
  "properties": {
    "iso:country":"IT",
    "sg:address":"486, Via Torino 10032 Brandizzo",
    "sg:city":"Brandizzo",
    "sg:classifiers":[
        {
            "category":"Manufacturing",
            "subcategory":"Metals",
            "type":"Manufacturing & Wholesale Goods"
        }
    ],
    "sg:phone":"+39 011 917 0202",
    "sg:postcode":"10032",
    "sg:province":"Torino",
    "sg:tags":[
        "processing"
    ],
    "wof:name":"V.i.m.i.t. (s.r.l.)",
    "wof:placetype":"venue"
},
  "geometry": {"coordinates":[7.7571768761,45.1461524963],"type":"Point"}
}