{
  "type": "Feature",
  "properties": {
    "addr:full":"17035 Cisano Sul Neva Cisano sul Neva Savona 17035",
    "addr:housenumber":"17035;neva",
    "addr:postcode":"17035",
    "addr:street":"Cisano Sul Neva",
    "iso:country":"IT",
    "sg:address":"17035 Cisano Sul Neva",
    "sg:city":"Cisano sul Neva",
    "sg:orig_category":"Autocarri",
    "sg:phone":"+39 0182 594002",
    "sg:postcode":"17035",
    "sg:province":"Savona",
    "wof:name":"Rossi E Aschero Srl",
    "wof:placetype":"venue"
},
  "geometry": {"coordinates":[8.162585,44.074104],"type":"Point"}
}