{
  "type": "Feature",
  "properties": {
    "addr:full":"06024 Gubbio Gubbio Perugia 06024",
    "addr:postcode":"06024;06024",
    "iso:country":"IT",
    "sg:address":"06024 Gubbio",
    "sg:city":"Gubbio",
    "sg:orig_category":"Prodotti Chimici Di Base. Forniture Per Attivita' Industriali",
    "sg:phone":"+39 075 927 3579",
    "sg:postcode":"06024",
    "sg:province":"Perugia",
    "wof:name":"Cereria Artigiana Umbra Snc",
    "wof:placetype":"venue"
},
  "geometry": {"coordinates":[12.5757026672,43.3630447388],"type":"Point"}
}