{
  "type": "Feature",
  "properties": {
    "iso:country":"IT",
    "sg:address":"Via Pierucciani 51030 Serravalle Pistoiese",
    "sg:city":"Serravalle Pistoiese",
    "sg:classifiers":[
        {
            "category":"Home & Garden",
            "subcategory":"Home Furnishings",
            "type":"Retail Goods"
        }
    ],
    "sg:phone":"+39 0573 946222",
    "sg:postcode":"51030",
    "sg:province":"Pistoia",
    "sg:tags":[
        "household"
    ],
    "wof:name":"Giovannetti Collezioni D'arredamento Srl",
    "wof:placetype":"venue"
},
  "geometry": {"coordinates":[10.9325,43.886292],"type":"Point"}
}