{
  "type": "Feature",
  "properties": {
    "iso:country":"IT",
    "sg:address":"00148 Roma",
    "sg:city":"Roma",
    "sg:orig_category":"Zootecnia E Pesca, Allevamento Piccoli Animali. Animali Domestici",
    "sg:phone":"+39 06 653 6421",
    "sg:postcode":"00148",
    "sg:province":"Roma",
    "wof:name":"Rossi Giuseppe",
    "wof:placetype":"venue"
},
  "geometry": {"coordinates":[12.435841,41.846035],"type":"Point"}
}