{
  "type": "Feature",
  "properties": {
    "iso:country":"IT",
    "sg:address":"27 Via Fara Gustavo, 20124 Milano",
    "sg:city":"Milano",
    "sg:classifiers":[
        {
            "category":"Banks & Credit Unions",
            "subcategory":"Financial Services",
            "type":"Services"
        }
    ],
    "sg:phone":"+39 390 266 7291",
    "sg:postcode":"20124",
    "sg:province":"Milano",
    "sg:tags":[
        "banking",
        "finance",
        "insurance"
    ],
    "wof:name":"Abbey National Bank",
    "wof:placetype":"venue"
},
  "geometry": {"coordinates":[9.198387146,45.4838829041],"type":"Point"}
}