{
  "type": "Feature",
  "properties": {
    "iso:country":"IT",
    "sg:address":"62012 Civitanova Marche",
    "sg:city":"Civitanova Marche",
    "sg:orig_category":"Forniture Per Attivita' Industriali",
    "sg:phone":"+39 0733 70246",
    "sg:postcode":"62012",
    "sg:province":"Macerata",
    "wof:name":"Valentini Giorgio & C. Sas",
    "wof:placetype":"venue"
},
  "geometry": {"coordinates":[13.6941671371,43.3182144165],"type":"Point"}
}