{
  "type": "Feature",
  "properties": {
    "addr:full":"55054 Massarosa Massarosa Lucca 55054",
    "addr:postcode":"55054;55054",
    "iso:country":"IT",
    "sg:address":"55054 Massarosa",
    "sg:city":"Massarosa",
    "sg:orig_category":"Servizi E Lavori Per Agricoltura E Zootecnia. Servizi E Lavori Per Edilizia E Lavori Pubblici",
    "sg:phone":"+39 0584 93029",
    "sg:postcode":"55054",
    "sg:province":"Lucca",
    "wof:name":"Buchignani Angela - Ivano Gardening",
    "wof:placetype":"venue"
},
  "geometry": {"coordinates":[10.332,43.874001],"type":"Point"}
}