{
  "type": "Feature",
  "properties": {
    "iso:country":"IT",
    "sg:address":"Via Delle Puglie 17 80026 Casoria",
    "sg:city":"Casoria",
    "sg:classifiers":[
        {
            "category":"Banks & Credit Unions",
            "subcategory":"Investment Brokerage",
            "type":"Services"
        }
    ],
    "sg:phone":"+39 081 759 7890",
    "sg:postcode":"80026",
    "sg:province":"Napoli",
    "sg:tags":[
        "table",
        "lamp"
    ],
    "sg:website":"www.abatjour.it",
    "wof:name":"Severino Abat Jour Di Severino Michele",
    "wof:placetype":"venue"
},
  "geometry": {"coordinates":[14.308117,40.876049],"type":"Point"}
}