{
  "type": "Feature",
  "properties": {
    "iso:country":"IT",
    "sg:address":"06049 Spoleto",
    "sg:city":"Spoleto",
    "sg:orig_category":"Professionisti - Studi E Servizi Ed Associazioni Di Interesse Aziendale. Associazioni Ed Organismi Di Interesse Pubblico",
    "sg:phone":"+39 0743 43744",
    "sg:postcode":"06049",
    "sg:province":"Perugia",
    "wof:name":"Italia Lavoro Spa Ufficio Regionale Umbria",
    "wof:placetype":"venue"
},
  "geometry": {"coordinates":[12.738866806,42.7416763306],"type":"Point"}
}