{
  "type": "Feature",
  "properties": {
    "iso:country":"IT",
    "sg:address":"25014 Castenedolo",
    "sg:city":"Castenedolo",
    "sg:orig_category":"Petroli, Gas E Combustibili",
    "sg:phone":"+39 030 213 0440",
    "sg:postcode":"25014",
    "sg:province":"Brescia",
    "sg:website":"http://www.comlube.it",
    "wof:name":"Comlube Srl",
    "wof:placetype":"venue"
},
  "geometry": {"coordinates":[10.2847938538,45.4792404175],"type":"Point"}
}