{
  "type": "Feature",
  "properties": {
    "addr:full":"7, Via Roma 24030 Medolago Medolago Bergamo 24030",
    "addr:postcode":"24030;24030",
    "addr:street":"Via Roma",
    "iso:country":"IT",
    "sg:address":"7, Via Roma 24030 Medolago",
    "sg:city":"Medolago",
    "sg:classifiers":[
        {
            "category":"Shopping",
            "subcategory":"Clothing, Apparel, & Fashions",
            "type":"Retail Goods"
        }
    ],
    "sg:phone":"+39 035 494 8259",
    "sg:postcode":"24030",
    "sg:province":"Bergamo",
    "sg:tags":[
        "clothes"
    ],
    "wof:name":"New Trend Snc Di Rota Celestino E C.",
    "wof:placetype":"venue"
},
  "geometry": {"coordinates":[9.529735,45.685635],"type":"Point"}
}