{
  "type": "Feature",
  "properties": {
    "addr:full":"Viali Risorgimento 26 61041 Acqualagna Acqualagna Pesaro E Urbino 61041",
    "addr:housenumber":"26",
    "addr:postcode":"61041;61041",
    "addr:street":"Risorgimento",
    "iso:country":"IT",
    "sg:address":"Viali Risorgimento 26 61041 Acqualagna",
    "sg:city":"Acqualagna",
    "sg:classifiers":[
        {
            "category":"Coffee & Tea",
            "type":"Food & Drink"
        }
    ],
    "sg:phone":"+39 0721 798629",
    "sg:postcode":"61041",
    "sg:province":"Pesaro E Urbino",
    "sg:tags":[
        "truffle",
        "chocolate"
    ],
    "sg:website":"www.publi.it/marini",
    "wof:name":"Marini Azzolini - Tartufi",
    "wof:placetype":"venue"
},
  "geometry": {"coordinates":[12.529803,43.633556],"type":"Point"}
}