{
  "type": "Feature",
  "properties": {
    "iso:country":"IT",
    "sg:address":"2, Viale Del Lavoro 37040 Arcole",
    "sg:city":"Arcole",
    "sg:classifiers":[
        {
            "category":"Manufacturing",
            "subcategory":"Metals",
            "type":"Manufacturing & Wholesale Goods"
        }
    ],
    "sg:phone":"+39 045 614 4040",
    "sg:postcode":"37040",
    "sg:province":"Verona",
    "sg:tags":[
        "metallurgy",
        "metalworking"
    ],
    "wof:name":"Alkom Alluminio (s.r.l.)",
    "wof:placetype":"venue"
},
  "geometry": {"coordinates":[10.9917478561,45.4383659363],"type":"Point"}
}