{
  "type": "Feature",
  "properties": {
    "addr:full":"13, Via Lodovico Ariosto 42023 Cadelbosco Di Sopra Reggio Nell'Emilia 42023",
    "addr:postcode":"42023;42023",
    "addr:street":"Via Lodovico Ariosto",
    "iso:country":"IT",
    "sg:address":"13, Via Lodovico Ariosto 42023 Cadelbosco Di Sopra",
    "sg:classifiers":[
        {
            "category":"Autos & Motor Vehicles",
            "subcategory":"Automobile Sales",
            "type":"Retail Goods"
        }
    ],
    "sg:phone":"+39 0522 919263",
    "sg:postcode":"42023",
    "sg:province":"Reggio Nell'Emilia",
    "sg:tags":[
        "motor-cars"
    ],
    "wof:name":"Telergo (s.r.l.)",
    "wof:placetype":"venue"
},
  "geometry": {"coordinates":[10.6277942657,44.6962280273],"type":"Point"}
}