{
  "type": "Feature",
  "properties": {
    "iso:country":"IT",
    "sg:address":"40033 Casalecchio Di Reno",
    "sg:city":"Casalecchio di Reno",
    "sg:classifiers":[
        {
            "category":"Health Services",
            "subcategory":"Nursing And Care Facility",
            "type":"Services"
        }
    ],
    "sg:phone":"+39 051 619 2222",
    "sg:postcode":"40033",
    "sg:province":"Bologna",
    "sg:tags":[
        "case",
        "cura",
        "private",
        "di"
    ],
    "wof:name":"Villa Chiara Spa",
    "wof:placetype":"venue"
},
  "geometry": {"coordinates":[11.286637,44.482513],"type":"Point"}
}