{
  "type": "Feature",
  "properties": {
    "addr:full":"06087 Perugia PG",
    "addr:postcode":"06087",
    "addr:street":"Pg",
    "iso:country":"IT",
    "sg:address":"06087 Perugia",
    "sg:orig_category":"Ricambi E Componenti Dei Mezzi Di Trasporto",
    "sg:phone":"+39 075 396645",
    "sg:province":"PG",
    "sg:website":"http://www.palmerini.com",
    "wof:name":"Seim Srl",
    "wof:placetype":"venue"
},
  "geometry": {"coordinates":[-72.88690200000001,41.757599],"type":"Point"}
}