{
  "type": "Feature",
  "properties": {
    "addr:full":"00185 Roma Roma Roma 00185",
    "addr:postcode":"00185;00185",
    "iso:country":"IT",
    "sg:address":"00185 Roma",
    "sg:city":"Roma",
    "sg:orig_category":"Macchine E Forniture Per Industria Orafa E Per Orologeria",
    "sg:phone":"+39 06 445 7236",
    "sg:postcode":"00185",
    "sg:province":"Roma",
    "wof:name":"Di Francescantonio Snc",
    "wof:placetype":"venue"
},
  "geometry": {"coordinates":[12.503658,41.897968],"type":"Point"}
}