{
  "type": "Feature",
  "properties": {
    "iso:country":"IT",
    "sg:address":"57123 Livorno",
    "sg:city":"Livorno",
    "sg:orig_category":"Servizi E Lavori Per Agricoltura E Zootecnia. Servizi Ausiliari Di Analisi, Controllo E Ricerca",
    "sg:phone":"+39 0586 219343",
    "sg:postcode":"57123",
    "sg:province":"Livorno",
    "wof:name":"Societa' Per Il Polo Scientifico E Tecnologico Dell'area Livornese Srl",
    "wof:placetype":"venue"
},
  "geometry": {"coordinates":[10.302999,43.547668],"type":"Point"}
}