{
  "type": "Feature",
  "properties": {
    "addr:full":"19, Via Monte Grappa 20095 Cusano Milanino Cusano Milanino Milano 20095",
    "addr:postcode":"20095;20095",
    "addr:street":"Via Monte Grappa",
    "iso:country":"IT",
    "sg:address":"19, Via Monte Grappa 20095 Cusano Milanino",
    "sg:city":"Cusano Milanino",
    "sg:classifiers":[
        {
            "category":"Manufacturing",
            "subcategory":"Metals",
            "type":"Manufacturing & Wholesale Goods"
        }
    ],
    "sg:phone":"+39 39026196550",
    "sg:postcode":"20095",
    "sg:province":"Milano",
    "sg:tags":[
        "metallurgy",
        "metalworking"
    ],
    "wof:name":"Navit (s.r.l.)",
    "wof:placetype":"venue"
},
  "geometry": {"coordinates":[9.1794500351,45.5566749573],"type":"Point"}
}