{
  "type": "Feature",
  "properties": {
    "iso:country":"IT",
    "sg:address":"Km. 5,900, Strada Statale 580 74013 Ginosa",
    "sg:city":"Ginosa",
    "sg:classifiers":[
        {
            "category":"Real Estate",
            "subcategory":"Architect",
            "type":"Services"
        }
    ],
    "sg:phone":"+39 099 829 4093",
    "sg:postcode":"74013",
    "sg:province":"Taranto",
    "sg:tags":[
        "textile",
        "clothing"
    ],
    "wof:name":"Intelligere Moda S.n.c. Di Costantino Pasquale & C.",
    "wof:placetype":"venue"
},
  "geometry": {"coordinates":[17.240009,40.469238],"type":"Point"}
}