{
  "type": "Feature",
  "properties": {
    "iso:country":"IT",
    "sg:address":"80075 Forio",
    "sg:city":"Forio",
    "sg:orig_category":"Agenzie Di Spettacolo E Di Animazione",
    "sg:phone":"+39 081 507 1199",
    "sg:postcode":"80075",
    "sg:province":"Napoli",
    "wof:name":"Animatissima Di Josy Mattera",
    "wof:placetype":"venue"
},
  "geometry": {"coordinates":[13.873803,40.725731],"type":"Point"}
}