{
  "type": "Feature",
  "properties": {
    "iso:country":"IT",
    "sg:address":"8, Via A.costa 40057 Granarolo Dell'emilia",
    "sg:classifiers":[
        {
            "category":"Professional",
            "subcategory":"Computer Services",
            "type":"Services"
        }
    ],
    "sg:phone":"+39 39051765228",
    "sg:postcode":"40057",
    "sg:province":"Bologna",
    "sg:tags":[
        "information",
        "technology"
    ],
    "wof:name":"Oxi (s.r.l.)",
    "wof:placetype":"venue"
},
  "geometry": {"coordinates":[11.397237,44.55249],"type":"Point"}
}