{
  "type": "Feature",
  "properties": {
    "addr:full":"25054 Marone Marone Brescia 25054",
    "addr:postcode":"25054;25054",
    "iso:country":"IT",
    "sg:address":"25054 Marone",
    "sg:city":"Marone",
    "sg:orig_category":"Forniture Per Abbigliamento E Pelletterie. Forniture E Materiali Per Imballaggio E Confezionamento",
    "sg:phone":"+39 030 987 7977",
    "sg:postcode":"25054",
    "sg:province":"Brescia",
    "wof:name":"Turra Eliseo E C. (s.n.c.)",
    "wof:placetype":"venue"
},
  "geometry": {"coordinates":[10.0924463272,45.7354278564],"type":"Point"}
}