{
  "type": "Feature",
  "properties": {
    "addr:full":"35012 Camposampiero Camposampiero Padova 35012",
    "addr:postcode":"35012;35012",
    "iso:country":"IT",
    "sg:address":"35012 Camposampiero",
    "sg:city":"Camposampiero",
    "sg:orig_category":"Medici. Assicurazioni E Servizi Assicurativi. Avvocati, Notai E Servizi Legali. Professionisti - Studi E Servizi Ed Associazioni Di Interesse Aziendale",
    "sg:phone":"+39 049 930 1734",
    "sg:postcode":"35012",
    "sg:province":"Padova",
    "wof:name":"Ser.si S.r.l.",
    "wof:placetype":"venue"
},
  "geometry": {"coordinates":[11.8834733963,45.4251251221],"type":"Point"}
}