{
  "type": "Feature",
  "properties": {
    "iso:country":"IT",
    "sg:address":"20090 Segrate",
    "sg:city":"Segrate",
    "sg:orig_category":"Metalli E Leghe",
    "sg:phone":"+39 02 213 5550",
    "sg:postcode":"20090",
    "sg:province":"Milano",
    "wof:name":"Nagel & C. Snc Di Nangel F. E Sparaneo A.",
    "wof:placetype":"venue"
},
  "geometry": {"coordinates":[9.2877025604,45.4998703003],"type":"Point"}
}