{
  "type": "Feature",
  "properties": {
    "iso:country":"IT",
    "sg:address":"42/b, Via Pietramarina Sovigliana Spicchio 50059 Vinci",
    "sg:city":"Sovigliana",
    "sg:classifiers":[
        {
            "category":"Manufacturing",
            "subcategory":"Tools & Machinery",
            "type":"Manufacturing & Wholesale Goods"
        }
    ],
    "sg:phone":"+39 0571 509523",
    "sg:postcode":"50059",
    "sg:province":"Firenze",
    "sg:tags":[
        "environment",
        "equipment",
        "-"
    ],
    "wof:name":"Corme S.r.l.",
    "wof:placetype":"venue"
},
  "geometry": {"coordinates":[11.256902,43.768734],"type":"Point"}
}