{
  "type": "Feature",
  "properties": {
    "addr:full":"91014 Castellammare Del Golfo Castellammare del Golfo Trapani 91014",
    "addr:postcode":"91014;91014",
    "iso:country":"IT",
    "sg:address":"91014 Castellammare Del Golfo",
    "sg:city":"Castellammare del Golfo",
    "sg:orig_category":"Carta, Cartone E Prodotti Primari. Forniture Per Uffici",
    "sg:phone":"+39 0924 39351",
    "sg:postcode":"91014",
    "sg:province":"Trapani",
    "wof:name":"So.la.ce. (s.a.s.)",
    "wof:placetype":"venue"
},
  "geometry": {"coordinates":[12.828477,38.011082],"type":"Point"}
}