{
  "type": "Feature",
  "properties": {
    "iso:country":"IT",
    "sg:address":"09045 Quartu Sant'elena",
    "sg:orig_category":"Abiti Da Lavoro Ed Indumenti Protettivi",
    "sg:phone":"+39 070 881736",
    "sg:postcode":"09045",
    "sg:province":"Cagliari",
    "wof:name":"S.a.in.tec Sas",
    "wof:placetype":"venue"
},
  "geometry": {"coordinates":[9.178533,39.239071],"type":"Point"}
}