{
  "type": "Feature",
  "properties": {
    "iso:country":"IT",
    "sg:address":"80142 Napoli",
    "sg:city":"Napoli",
    "sg:orig_category":"Imballaggi - Produzione E Commercio",
    "sg:phone":"+39 081 261996",
    "sg:postcode":"80142",
    "sg:province":"Napoli",
    "wof:name":"Siervoplast Di Luciano Siervo",
    "wof:placetype":"venue"
},
  "geometry": {"coordinates":[14.277564,40.848957],"type":"Point"}
}