{
  "type": "Feature",
  "properties": {
    "iso:country":"IT",
    "sg:address":"16, P. Repubblica 41028 Serramazzoni",
    "sg:city":"Serramazzoni",
    "sg:orig_category":"Miscellaneous Products",
    "sg:phone":"+39 0536 955409",
    "sg:postcode":"41028",
    "sg:province":"Modena",
    "sg:website":"http://www.paginegialle.it/exit-mo",
    "wof:name":"Ex.it Italian Export Srl",
    "wof:placetype":"venue"
},
  "geometry": {"coordinates":[10.9252195358,44.6470794678],"type":"Point"}
}