{
  "type": "Feature",
  "properties": {
    "addr:full":"20123 Milano Milano Milano 20123",
    "addr:postcode":"20123;20123",
    "iso:country":"IT",
    "sg:address":"20123 Milano",
    "sg:city":"Milano",
    "sg:orig_category":"Servizi E Lavori Per Edilizia E Lavori Pubblici. Banche E Servizi Finanziari",
    "sg:phone":"+39 02 879 0801",
    "sg:postcode":"20123",
    "sg:province":"Milano",
    "wof:name":"Aedes Societa' Per Azioni Ligure Lombarda Per Imprese E Costruzioni",
    "wof:placetype":"venue"
},
  "geometry": {"coordinates":[9.180733,45.462738],"type":"Point"}
}