{
  "type": "Feature",
  "properties": {
    "addr:full":"12030 Caramagna Piemonte Caramagna Piemonte Cuneo 12030",
    "addr:housenumber":"12030",
    "addr:postcode":"piemonte;12030",
    "addr:street":"Caramagna Piemonte",
    "iso:country":"IT",
    "sg:address":"12030 Caramagna Piemonte",
    "sg:city":"Caramagna Piemonte",
    "sg:orig_category":"Prodotti E Manufatti In Materie Plastiche",
    "sg:phone":"+39 0172 829723",
    "sg:postcode":"12030",
    "sg:province":"Cuneo",
    "wof:name":"Co.ma.v. Soc. Coop. Ar.l.",
    "wof:placetype":"venue"
},
  "geometry": {"coordinates":[7.7389726639,44.7802734375],"type":"Point"}
}