{
  "type": "Feature",
  "properties": {
    "iso:country":"IT",
    "sg:address":"21057 Olgiate Olona",
    "sg:city":"Olgiate Olona",
    "sg:orig_category":"Arti Grafiche - Accessori E Forniture",
    "sg:phone":"+39 0331 379063",
    "sg:postcode":"21057",
    "sg:province":"Varese",
    "sg:website":"http://www.apex-italy.it",
    "wof:name":"Apex Italy Srl",
    "wof:placetype":"venue"
},
  "geometry": {"coordinates":[8.879784,45.61853],"type":"Point"}
}