{
  "type": "Feature",
  "properties": {
    "addr:full":"17100 Savona Savona Savona 17100",
    "addr:postcode":"17100;17100",
    "iso:country":"IT",
    "sg:address":"17100 Savona",
    "sg:city":"Savona",
    "sg:orig_category":"Elettronica Professionale E Di Consumo. Tempo Libero - Articoli E Forniture",
    "sg:phone":"+39 019 848 5928",
    "sg:postcode":"17100",
    "sg:province":"Savona",
    "wof:name":"Net Sas",
    "wof:placetype":"venue"
},
  "geometry": {"coordinates":[8.416951,44.303646],"type":"Point"}
}