{
  "type": "Feature",
  "properties": {
    "iso:country":"IT",
    "sg:address":"59100 Prato",
    "sg:city":"Prato",
    "sg:orig_category":"Macchine, Impianti Ed Attrezzature Per Abbigliamento E Pelletterie",
    "sg:phone":"+39 0574 440068",
    "sg:postcode":"59100",
    "sg:province":"Prato",
    "wof:name":"Il Telaio Di Zhang Xiang Ding",
    "wof:placetype":"venue"
},
  "geometry": {"coordinates":[11.060285,43.876511],"type":"Point"}
}