{
  "type": "Feature",
  "properties": {
    "addr:full":"59100 Prato Prato Prato 59100",
    "addr:postcode":"59100;59100",
    "iso:country":"IT",
    "sg:address":"59100 Prato",
    "sg:city":"Prato",
    "sg:orig_category":"Tessuti E Stoffe",
    "sg:phone":"+39 0574 663274",
    "sg:postcode":"59100",
    "sg:province":"Prato",
    "wof:name":"S.t.t. Srl",
    "wof:placetype":"venue"
},
  "geometry": {"coordinates":[11.093808,43.878033],"type":"Point"}
}