{
  "type": "Feature",
  "properties": {
    "iso:country":"IT",
    "sg:address":"Via Martiri E Caduti; Demonte; 12014",
    "sg:city":"Demonte",
    "sg:classifiers":[
        {
            "category":"Banks & Credit Unions",
            "subcategory":"Bank",
            "type":"Services"
        }
    ],
    "sg:phone":"+39 0171 95123",
    "sg:postcode":"12014",
    "sg:province":"Cuneo",
    "wof:name":"Cassa Di Risparmio Di Cuneo",
    "wof:placetype":"venue"
},
  "geometry": {"coordinates":[7.297718,44.315083],"type":"Point"}
}