{
  "type": "Feature",
  "properties": {
    "addr:full":"70125 Bari Bari Bari 70125",
    "addr:postcode":"70125;70125",
    "iso:country":"IT",
    "sg:address":"70125 Bari",
    "sg:city":"Bari",
    "sg:orig_category":"Telecomunicazioni E Telefonia, Impianti, Apparecchi E Servizi",
    "sg:phone":"+39 080 556 3579",
    "sg:postcode":"70125",
    "sg:province":"Bari",
    "wof:name":"Williams Computer Center Snc",
    "wof:placetype":"venue"
},
  "geometry": {"coordinates":[16.798628,41.000782],"type":"Point"}
}