{
  "type": "Feature",
  "properties": {
    "addr:full":"25046 Cazzago San Martino Cazzago San Martino Brescia 25046",
    "addr:postcode":"25046;25046",
    "iso:country":"IT",
    "sg:address":"25046 Cazzago San Martino",
    "sg:city":"Cazzago San Martino",
    "sg:orig_category":"Forniture Per Agricoltura E Zootecnia. Prodotti Chimici Secondari",
    "sg:phone":"+39 030 775 0224",
    "sg:postcode":"25046",
    "sg:province":"Brescia",
    "wof:name":"Eurovix S.r.l.",
    "wof:placetype":"venue"
},
  "geometry": {"coordinates":[10.0353794098,45.5717124939],"type":"Point"}
}