{
  "type": "Feature",
  "properties": {
    "iso:country":"IT",
    "sg:address":"10091 Alpignano",
    "sg:city":"Alpignano",
    "sg:orig_category":"Elaboratori Elettronici",
    "sg:phone":"+39 011 968 2517",
    "sg:postcode":"10091",
    "sg:province":"Torino",
    "sg:website":"http://www.gruppoaccademia.it",
    "wof:name":"Accademia Srl",
    "wof:placetype":"venue"
},
  "geometry": {"coordinates":[7.516633,45.099113],"type":"Point"}
}