{
  "type": "Feature",
  "properties": {
    "iso:country":"IT",
    "sg:address":"Via Efrem Nobili 2 40062 Molinella",
    "sg:city":"Molinella",
    "sg:classifiers":[
        {
            "category":"Bus Stop",
            "subcategory":"None",
            "type":"Transportation"
        }
    ],
    "sg:phone":"+39 051 690 6111",
    "sg:postcode":"40062",
    "sg:province":"Bologna",
    "sg:tags":[
        "trucks",
        "buses",
        "cars",
        "system",
        "driver's",
        "air-conditioning",
        "cab",
        "crane"
    ],
    "sg:website":"www.delphi.com",
    "wof:name":"Delphi Italia Automotive Systems Srl",
    "wof:placetype":"venue"
},
  "geometry": {"coordinates":[11.665204,44.611679],"type":"Point"}
}