{
  "type": "Feature",
  "properties": {
    "iso:country":"IT",
    "sg:address":"20155 Milano",
    "sg:city":"Milano",
    "sg:orig_category":"Agenzie D'affari E Servizi Commerciali",
    "sg:phone":"+39 02 317007",
    "sg:postcode":"20155",
    "sg:province":"Milano",
    "wof:name":"Ambroso Vincenzo",
    "wof:placetype":"venue"
},
  "geometry": {"coordinates":[9.159795,45.488979],"type":"Point"}
}