{
  "type": "Feature",
  "properties": {
    "iso:country":"IT",
    "sg:address":"50129 Firenze",
    "sg:city":"Firenze",
    "sg:orig_category":"Chiese Ed Associazioni Religiose",
    "sg:phone":"+39 055 490148",
    "sg:postcode":"50129",
    "sg:province":"Firenze",
    "wof:name":"Chiesa Di Altri Culti Russa Ortodossa",
    "wof:placetype":"venue"
},
  "geometry": {"coordinates":[11.254499,43.78389],"type":"Point"}
}