{
  "type": "Feature",
  "properties": {
    "iso:country":"IT",
    "sg:address":"98039 Taormina",
    "sg:city":"Taormina",
    "sg:classifiers":[
        {
            "category":"Travel",
            "subcategory":"Hotels & Motels",
            "type":"Entertainment"
        }
    ],
    "sg:phone":"+39 0942 578238",
    "sg:postcode":"98039",
    "sg:province":"Messina",
    "sg:tags":[
        "hotels",
        "facility"
    ],
    "wof:name":"Cundari Nino Spa",
    "wof:placetype":"venue"
},
  "geometry": {"coordinates":[15.247752,37.832092],"type":"Point"}
}