{
  "type": "Feature",
  "properties": {
    "iso:country":"IT",
    "sg:address":"Via 25 Giugno, 1/3 26029 Soncino",
    "sg:city":"Soncino",
    "sg:classifiers":[
        {
            "category":"Autos & Motor Vehicles",
            "subcategory":"Fuel & Gas Station",
            "type":"Retail Goods"
        }
    ],
    "sg:phone":"+39 0374 84913",
    "sg:postcode":"26029",
    "sg:province":"Cremona",
    "sg:tags":[
        "automobile",
        "industry",
        "inlet",
        "silencer"
    ],
    "sg:website":"www.gbf-tecnomet.com",
    "wof:name":"G.b.f. Tecnomec Srl",
    "wof:placetype":"venue"
},
  "geometry": {"coordinates":[9.853354,45.387096],"type":"Point"}
}