{
  "type": "Feature",
  "properties": {
    "addr:full":"20, Via Mandelli 20050 Ronco Briantino Ronco Briantino Milano 20050",
    "addr:postcode":"20050;20050",
    "addr:street":"Via Mandelli",
    "iso:country":"IT",
    "sg:address":"20, Via Mandelli 20050 Ronco Briantino",
    "sg:city":"Ronco Briantino",
    "sg:classifiers":[
        {
            "category":"Shopping",
            "type":"Retail Goods"
        }
    ],
    "sg:phone":"+39 039 607 9035",
    "sg:postcode":"20050",
    "sg:province":"Milano",
    "sg:tags":[
        "finished",
        "-",
        "metallic"
    ],
    "wof:name":"M.d.c. (s.r.l.)",
    "wof:placetype":"venue"
},
  "geometry": {"coordinates":[9.3989572525,45.6663360596],"type":"Point"}
}