{
  "type": "Feature",
  "properties": {
    "iso:country":"IT",
    "sg:address":"79, Strada Torino-druento 10093 Collegno",
    "sg:city":"Collegno",
    "sg:classifiers":[
        {
            "category":"Wholesale",
            "subcategory":"Machinery & Supplies",
            "type":"Manufacturing & Wholesale Goods"
        }
    ],
    "sg:phone":"+39 011 424 0150",
    "sg:postcode":"10093",
    "sg:province":"Torino",
    "sg:tags":[
        "-",
        "agriculture",
        "equipment"
    ],
    "wof:name":"Torincab 2 (s.n.c.)",
    "wof:placetype":"venue"
},
  "geometry": {"coordinates":[7.601273,45.097523],"type":"Point"}
}