{
  "type": "Feature",
  "properties": {
    "iso:country":"IT",
    "sg:address":"33040 Pradamano",
    "sg:city":"Pradamano",
    "sg:orig_category":"Batterie, Accumulatori E Pile - Commercio",
    "sg:phone":"+39 0432 670573",
    "sg:postcode":"33040",
    "sg:province":"Udine",
    "wof:name":"Sacer Uliana Srl",
    "wof:placetype":"venue"
},
  "geometry": {"coordinates":[13.248307,46.06052],"type":"Point"}
}