{
  "type": "Feature",
  "properties": {
    "iso:country":"IT",
    "sg:address":"Via A. B. Sabin, 1/4 59100 Prato",
    "sg:city":"Prato",
    "sg:classifiers":[
        {
            "category":"Utilities",
            "subcategory":"Natural Gas",
            "type":"Services"
        }
    ],
    "sg:phone":"+39 0574 620000",
    "sg:postcode":"59100",
    "sg:province":"Prato",
    "sg:tags":[
        "current",
        "converter"
    ],
    "wof:name":"Fin - Job Srl",
    "wof:placetype":"venue"
},
  "geometry": {"coordinates":[11.096313,43.8797],"type":"Point"}
}