{
  "type": "Feature",
  "properties": {
    "addr:full":"81100 Caserta Caserta Caserta 81100",
    "addr:postcode":"81100;81100",
    "iso:country":"IT",
    "sg:address":"81100 Caserta",
    "sg:city":"Caserta",
    "sg:orig_category":"Analisi Cliniche - Centri E Laboratori",
    "sg:phone":"+39 0823 354374",
    "sg:postcode":"81100",
    "sg:province":"Caserta",
    "wof:name":"Ce.t.a.c. Srl",
    "wof:placetype":"venue"
},
  "geometry": {"coordinates":[14.331113,41.066261],"type":"Point"}
}