{
  "type": "Feature",
  "properties": {
    "iso:country":"IT",
    "sg:address":"65, V. G. Salvemini 00177 Roma",
    "sg:city":"Roma",
    "sg:classifiers":[
        {
            "category":"Home & Garden",
            "subcategory":"Home Furnishings",
            "type":"Retail Goods"
        }
    ],
    "sg:phone":"+39 39062417764",
    "sg:postcode":"00177",
    "sg:province":"Roma",
    "sg:tags":[
        "household"
    ],
    "sg:website":"http://www.paginegialle.it/dittarossi",
    "wof:name":"Ditta Antonella Rossi",
    "wof:placetype":"venue"
},
  "geometry": {"coordinates":[12.547831,41.874485],"type":"Point"}
}