{
  "type": "Feature",
  "properties": {
    "iso:country":"IT",
    "sg:address":"19020 Calice Al Cornoviglio",
    "sg:city":"Calice al Cornoviglio",
    "sg:orig_category":"Ristorazione E Locali Pubblici Affini. Servizi Per Lo Sport E Il Tempo Libero. Alberghi E Strutture Extra Alberghiere. Ristoranti Ed Esercizi Affini",
    "sg:phone":"+39 0187 936471",
    "sg:postcode":"19020",
    "sg:province":"La Spezia",
    "sg:website":"http://www.tiscalinet.it/ilcampaccio",
    "wof:name":"Agriturismo Il Campaccio",
    "wof:placetype":"venue"
},
  "geometry": {"coordinates":[9.837204,44.243927],"type":"Point"}
}