{
  "type": "Feature",
  "properties": {
    "iso:country":"IT",
    "sg:address":"Via Del Progresso, 61030 Calcinelli",
    "sg:city":"Calcinelli",
    "sg:classifiers":[
        {
            "category":"Manufacturing",
            "subcategory":"Glass & Minerals",
            "type":"Manufacturing & Wholesale Goods"
        }
    ],
    "sg:phone":"+39 0721 894877",
    "sg:postcode":"61030",
    "sg:province":"Pesaro E Urbino",
    "sg:tags":[
        "heat-insulating"
    ],
    "wof:name":"Isovetro Srl",
    "wof:placetype":"venue"
},
  "geometry": {"coordinates":[12.919232,43.744923],"type":"Point"}
}