{
  "type": "Feature",
  "properties": {
    "iso:country":"IT",
    "sg:address":"00040 Pomezia",
    "sg:city":"Pomezia",
    "sg:orig_category":"Sport - Articoli E Forniture",
    "sg:phone":"+39 06 911 2207",
    "sg:postcode":"00040",
    "sg:province":"Roma",
    "wof:name":"Sammuri Carla",
    "wof:placetype":"venue"
},
  "geometry": {"coordinates":[12.501258,41.671318],"type":"Point"}
}