{
  "type": "Feature",
  "properties": {
    "iso:country":"IT",
    "sg:address":"48015 Cervia",
    "sg:city":"Cervia",
    "sg:orig_category":"Animali Domestici - Vendita",
    "sg:phone":"+39 0544 970368",
    "sg:postcode":"48015",
    "sg:province":"Ravenna",
    "wof:name":"Simba Di Pletto & C. Snc",
    "wof:placetype":"venue"
},
  "geometry": {"coordinates":[12.323482,44.238918],"type":"Point"}
}