{
  "type": "Feature",
  "properties": {
    "iso:country":"IT",
    "sg:address":"00197 Roma",
    "sg:city":"Roma",
    "sg:orig_category":"Banche E Servizi Finanziari",
    "sg:phone":"+39 06 802241",
    "sg:postcode":"00197",
    "sg:province":"Roma",
    "wof:name":"Banca Fideuram Spa",
    "wof:placetype":"venue"
},
  "geometry": {"coordinates":[12.490662,41.928326],"type":"Point"}
}