{
  "type": "Feature",
  "properties": {
    "addr:full":"91011 Alcamo Alcamo Trapani 91011",
    "addr:postcode":"91011;91011",
    "iso:country":"IT",
    "sg:address":"91011 Alcamo",
    "sg:city":"Alcamo",
    "sg:orig_category":"Prodotti Chimici Di Base. Forniture Per Attivita' Industriali",
    "sg:phone":"+39 0924 22252",
    "sg:postcode":"91011",
    "sg:province":"Trapani",
    "wof:name":"Gapir Snc",
    "wof:placetype":"venue"
},
  "geometry": {"coordinates":[12.9665822983,37.9540710449],"type":"Point"}
}