{
  "type": "Feature",
  "properties": {
    "iso:country":"IT",
    "sg:address":"29, Via Garibaldi Giuseppe 71037 Monte Sant'angelo",
    "sg:classifiers":[
        {
            "category":"Food & Beverages",
            "subcategory":"Groceries & Convenience Stores",
            "type":"Retail Goods"
        }
    ],
    "sg:phone":"+39 0884 565326",
    "sg:postcode":"71037",
    "sg:province":"Foggia",
    "sg:tags":[
        "product",
        "related"
    ],
    "wof:name":"Italmare S.a.s.",
    "wof:placetype":"venue"
},
  "geometry": {"coordinates":[15.5446996689,41.4623336792],"type":"Point"}
}