{
  "type": "Feature",
  "properties": {
    "iso:country":"IT",
    "sg:address":"18, Via Trebbia 20135 Milano",
    "sg:city":"Milano",
    "sg:classifiers":[
        {
            "category":"Shopping",
            "subcategory":"Computers & Home Electronics",
            "type":"Retail Goods"
        }
    ],
    "sg:phone":"+39 02 5830 6601",
    "sg:postcode":"20135",
    "sg:province":"Milano",
    "sg:tags":[
        "electronic",
        "electrical",
        "equipment"
    ],
    "wof:name":"Saldea (s.r.l.)",
    "wof:placetype":"venue"
},
  "geometry": {"coordinates":[9.202195,45.447872],"type":"Point"}
}