{
  "type": "Feature",
  "properties": {
    "iso:country":"IT",
    "sg:address":"40010 Sala Bolognese",
    "sg:city":"Sala Bolognese",
    "sg:orig_category":"Non-classified Establishments",
    "sg:phone":"+39 051 828854",
    "sg:postcode":"40010",
    "sg:province":"Bologna",
    "sg:website":"http://www.international-bags.com",
    "wof:name":"International Bags Sas Di Morten Giuseppe",
    "wof:placetype":"venue"
},
  "geometry": {"coordinates":[11.27263,44.562263],"type":"Point"}
}