{
  "type": "Feature",
  "properties": {
    "iso:country":"IT",
    "sg:address":"57121 Livorno",
    "sg:city":"Livorno",
    "sg:orig_category":"Autoveicoli Industriali",
    "sg:phone":"+39 0586 426861",
    "sg:postcode":"57121",
    "sg:province":"Livorno",
    "wof:name":"Bi-elle Di Bianchini Bruno & C. Snc",
    "wof:placetype":"venue"
},
  "geometry": {"coordinates":[10.344175,43.56517],"type":"Point"}
}