{
  "type": "Feature",
  "properties": {
    "addr:full":"39033 Corvara In Badia Corvara in Badia Bolzano/Bozen 39033",
    "addr:postcode":"39033;39033",
    "iso:country":"IT",
    "sg:address":"39033 Corvara In Badia",
    "sg:city":"Corvara in Badia",
    "sg:orig_category":"Agenzie Ed Enti Turistici. Acqua, Luce, Gas E Societa' Di Esercizio Pubblico",
    "sg:phone":"+39 0471 836176",
    "sg:postcode":"39033",
    "sg:province":"Bolzano/Bozen",
    "sg:website":"http://www.dolomitisuperski.com/altabadia",
    "wof:name":"Associazione Turistica Corvara - Colfosco",
    "wof:placetype":"venue"
},
  "geometry": {"coordinates":[11.856683,46.548943],"type":"Point"}
}