{
  "type": "Feature",
  "properties": {
    "addr:full":"38/40, Via Pisana 50018 Scandicci Scandicci Firenze 50018",
    "addr:housenumber":"38 / 40",
    "addr:postcode":"50018;50018",
    "addr:street":"Via Pisana",
    "iso:country":"IT",
    "sg:address":"38/40, Via Pisana 50018 Scandicci",
    "sg:city":"Scandicci",
    "sg:classifiers":[
        {
            "category":"Shopping",
            "type":"Retail Goods"
        }
    ],
    "sg:phone":"+39 39055753054",
    "sg:postcode":"50018",
    "sg:province":"Firenze",
    "sg:tags":[
        "finished",
        "-",
        "metallic"
    ],
    "wof:name":"Cardin S.a.s.",
    "wof:placetype":"venue"
},
  "geometry": {"coordinates":[11.1779184341,43.7639808655],"type":"Point"}
}