{
  "type": "Feature",
  "properties": {
    "iso:country":"IT",
    "sg:address":"33, Localita' Pont D'avisod Chesallet 11010 Sarre",
    "sg:city":"Chesallet",
    "sg:classifiers":[
        {
            "category":"Travel",
            "subcategory":"Travel Agent",
            "type":"Entertainment"
        }
    ],
    "sg:phone":"+39 0165 551246",
    "sg:postcode":"11010",
    "sg:province":"Aosta",
    "sg:tags":[
        "business"
    ],
    "wof:name":"Albergo Hotel Panoramique",
    "wof:placetype":"venue"
},
  "geometry": {"coordinates":[7.313234,45.735001],"type":"Point"}
}