{
  "type": "Feature",
  "properties": {
    "iso:country":"IT",
    "sg:address":"98070 Longi",
    "sg:city":"Longi",
    "sg:orig_category":"Servizi E Lavori Per Agricoltura E Zootecnia. Servizi E Lavori Per Ecologia E Smaltimento Rifiuti. Servizi Ausiliari Di Sorveglianza, Manutenzione E Pulizia",
    "sg:phone":"+39 0941 485054",
    "sg:postcode":"98070",
    "sg:province":"Messina",
    "wof:name":"Il Grifone Piccola Societa' Cooperativa Arl",
    "wof:placetype":"venue"
},
  "geometry": {"coordinates":[15.559126,38.202816],"type":"Point"}
}