{
  "type": "Feature",
  "properties": {
    "iso:country":"IT",
    "sg:address":"80126 Napoli",
    "sg:city":"Napoli",
    "sg:orig_category":"Tende Da Sole",
    "sg:phone":"+39 081 767 4944",
    "sg:postcode":"80126",
    "sg:province":"Napoli",
    "sg:website":"http://www.rapacciuolo.it",
    "wof:name":"Materie Plastiche Di Paolo Rapacciuolo & C. Snc",
    "wof:placetype":"venue"
},
  "geometry": {"coordinates":[14.206306,40.846462],"type":"Point"}
}