{
  "type": "Feature",
  "properties": {
    "iso:country":"IT",
    "sg:address":"17051 Andora",
    "sg:city":"Andora",
    "sg:orig_category":"Servizi Per Lo Sport E Il Tempo Libero. Servizi Al Turismo",
    "sg:phone":"+39 0182 87366",
    "sg:postcode":"17051",
    "sg:province":"Savona",
    "wof:name":"Gulliver",
    "wof:placetype":"venue"
},
  "geometry": {"coordinates":[8.122932,43.987587],"type":"Point"}
}