{
  "type": "Feature",
  "properties": {
    "iso:country":"IT",
    "sg:address":"44100 Ferrara",
    "sg:city":"Ferrara",
    "sg:orig_category":"Materiali Edili",
    "sg:phone":"+39 0532 731564",
    "sg:postcode":"44100",
    "sg:province":"Ferrara",
    "sg:website":"http://www.impar.it",
    "wof:name":"Impar Impianti Srl",
    "wof:placetype":"venue"
},
  "geometry": {"coordinates":[11.557549,44.862057],"type":"Point"}
}