{
  "type": "Feature",
  "properties": {
    "iso:country":"IT",
    "sg:address":"20124 Milano",
    "sg:city":"Milano",
    "sg:classifiers":[
        {
            "category":"Professional",
            "subcategory":"Lawyer & Legal Services",
            "type":"Services"
        }
    ],
    "sg:phone":"+39 02 670 5717",
    "sg:postcode":"20124",
    "sg:province":"Milano",
    "sg:tags":[
        "lawyers",
        "technical",
        "consultant",
        "services",
        "notary",
        "administrative",
        "appraiser"
    ],
    "wof:name":"Ferraiolo Srl",
    "wof:placetype":"venue"
},
  "geometry": {"coordinates":[9.203623,45.481125],"type":"Point"}
}