{
  "type": "Feature",
  "properties": {
    "iso:country":"IT",
    "sg:address":"04010 Maenza",
    "sg:city":"Maenza",
    "sg:orig_category":"Vetro: Prodotti E Lavorazioni",
    "sg:phone":"+39 0773 951417",
    "sg:postcode":"04010",
    "sg:province":"Latina",
    "wof:name":"Vecciarelli Roberto",
    "wof:placetype":"venue"
},
  "geometry": {"coordinates":[13.182134,41.522919],"type":"Point"}
}