{
  "type": "Feature",
  "properties": {
    "addr:full":"25081 Bedizzole Bedizzole Brescia 25081",
    "addr:postcode":"25081;25081",
    "iso:country":"IT",
    "sg:address":"25081 Bedizzole",
    "sg:city":"Bedizzole",
    "sg:orig_category":"Pompe. Apparecchiature E Sistemi Per Imballaggio E Confezionamento",
    "sg:phone":"+39 030 687 1184",
    "sg:postcode":"25081",
    "sg:province":"Brescia",
    "wof:name":"Watson Marlow Srl",
    "wof:placetype":"venue"
},
  "geometry": {"coordinates":[10.1886491776,45.5531692505],"type":"Point"}
}