{
  "type": "Feature",
  "properties": {
    "iso:country":"IT",
    "sg:address":"37033 Verona",
    "sg:orig_category":"Materiali Edili",
    "sg:phone":"+39 045 892 0250",
    "sg:province":"VR",
    "wof:name":"Segala Luciano Srl",
    "wof:placetype":"venue"
},
  "geometry": {"coordinates":[11.074022,45.442986],"type":"Point"}
}