{
  "type": "Feature",
  "properties": {
    "iso:country":"IT",
    "sg:address":"3, Viale Pavia 26900 Lodi",
    "sg:city":"Lodi",
    "sg:classifiers":[
        {
            "category":"Shopping",
            "subcategory":"Computers & Home Electronics",
            "type":"Retail Goods"
        }
    ],
    "sg:phone":"+39 0371 430609",
    "sg:postcode":"26900",
    "sg:province":"Lodi",
    "sg:tags":[
        "electronic",
        "electrical",
        "equipment"
    ],
    "wof:name":"Abb Adda S.r.l.",
    "wof:placetype":"venue"
},
  "geometry": {"coordinates":[9.493102,45.305775],"type":"Point"}
}