{
  "type": "Feature",
  "properties": {
    "iso:country":"IT",
    "sg:address":"36073 Cornedo Vicentino",
    "sg:city":"Cornedo Vicentino",
    "sg:orig_category":"Elettrotecnica Industriale, Prodotti E Apparecchiature",
    "sg:phone":"+39 0445 951190",
    "sg:postcode":"36073",
    "sg:province":"Vicenza",
    "wof:name":"Elettromeccanica Fioraso Snc",
    "wof:placetype":"venue"
},
  "geometry": {"coordinates":[11.373348,45.594433],"type":"Point"}
}