{
  "type": "Feature",
  "properties": {
    "iso:country":"IT",
    "sg:address":"Via Marconi 26 48017 Conselice",
    "sg:city":"Conselice",
    "sg:classifiers":[
        {
            "category":"Manufacturing",
            "subcategory":"Motor Vehicles & Parts",
            "type":"Manufacturing & Wholesale Goods"
        }
    ],
    "sg:phone":"+39 0545 89584",
    "sg:postcode":"48017",
    "sg:province":"Ravenna",
    "sg:tags":[
        "industry",
        "metallurgical",
        "vendor"
    ],
    "wof:name":"Taroni Fratelli Snc",
    "wof:placetype":"venue"
},
  "geometry": {"coordinates":[11.83298,44.510078],"type":"Point"}
}