{
  "type": "Feature",
  "properties": {
    "iso:country":"IT",
    "sg:address":"00048 Nettuno",
    "sg:city":"Nettuno",
    "sg:orig_category":"Servizi Per Lo Sport E Il Tempo Libero. Alberghi E Strutture Extra Alberghiere",
    "sg:phone":"+39 06 980 3245",
    "sg:postcode":"00048",
    "sg:province":"Roma",
    "wof:name":"Stabilimento Balneare Le Sirene (a.r.l.)",
    "wof:placetype":"venue"
},
  "geometry": {"coordinates":[12.640043,42.032772],"type":"Point"}
}