{
  "type": "Feature",
  "properties": {
    "iso:country":"IT",
    "sg:address":"63039 San Benedetto Del Tronto",
    "sg:city":"San Benedetto del Tronto",
    "sg:orig_category":"Alberghi",
    "sg:phone":"+39 0735 81822",
    "sg:postcode":"63039",
    "sg:province":"Ascoli Piceno",
    "wof:name":"Hotel Villa Corallo Di Calvaresi Marco E C. Snc",
    "wof:placetype":"venue"
},
  "geometry": {"coordinates":[13.873803,42.929726],"type":"Point"}
}