{
  "type": "Feature",
  "properties": {
    "iso:country":"IT",
    "sg:address":"Via Enrico Fermi 635 21042 Caronno Pertusella",
    "sg:city":"Caronno Pertusella",
    "sg:classifiers":[
        {
            "category":"Utilities",
            "subcategory":"Cable",
            "type":"Services"
        }
    ],
    "sg:phone":"+39 02 964531",
    "sg:postcode":"21042",
    "sg:province":"Varese",
    "sg:tags":[
        "winding",
        "technology",
        "system",
        "guiding"
    ],
    "sg:website":"www.kinomat.it",
    "wof:name":"De Angeli Kinomat S.p.a. (dak)",
    "wof:placetype":"venue"
},
  "geometry": {"coordinates":[9.039872,45.60857],"type":"Point"}
}