{
  "type": "Feature",
  "properties": {
    "iso:country":"IT",
    "sg:address":"73018 Squinzano",
    "sg:city":"Squinzano",
    "sg:classifiers":[
        {
            "category":"Shopping Center",
            "type":"Public Place"
        }
    ],
    "sg:phone":"+39 0832 781734",
    "sg:postcode":"73018",
    "sg:province":"Lecce",
    "sg:tags":[
        "sausage",
        "meat",
        "restaurant",
        "premises",
        "fish",
        "related"
    ],
    "sg:website":"http://www.produzionigioia.it",
    "wof:name":"La.ra. Srl",
    "wof:placetype":"venue"
},
  "geometry": {"coordinates":[18.04368,40.431278],"type":"Point"}
}