{
  "type": "Feature",
  "properties": {
    "iso:country":"IT",
    "sg:address":"35, Via Piemonte 04012 Cisterna Di Latina",
    "sg:city":"Cisterna di Latina",
    "sg:classifiers":[
        {
            "category":"Real Estate",
            "subcategory":"Surveying",
            "type":"Services"
        }
    ],
    "sg:phone":"+39 39069692169",
    "sg:postcode":"04012",
    "sg:province":"Latina",
    "sg:tags":[
        "equipment",
        "material",
        "good",
        "-",
        "handling"
    ],
    "wof:name":"Co.me.car Srl",
    "wof:placetype":"venue"
},
  "geometry": {"coordinates":[12.801047,41.548286],"type":"Point"}
}