{
  "type": "Feature",
  "properties": {
    "addr:full":"20146 Milano Milano Milano 20146",
    "addr:postcode":"20146;20146",
    "iso:country":"IT",
    "sg:address":"20146 Milano",
    "sg:city":"Milano",
    "sg:orig_category":"Motori Ed Organi Di Trasmissione",
    "sg:phone":"+39 02 4801 5885",
    "sg:postcode":"20146",
    "sg:province":"Milano",
    "wof:name":"Eurel Srl",
    "wof:placetype":"venue"
},
  "geometry": {"coordinates":[9.1530504227,45.4589233398],"type":"Point"}
}