{
  "type": "Feature",
  "properties": {
    "iso:country":"IT",
    "sg:address":"Via Divino Amore 01022 Bagnoregio",
    "sg:city":"Bagnoregio",
    "sg:classifiers":[
        {
            "category":"Manufacturing",
            "subcategory":"Rubber & Plastics",
            "type":"Manufacturing & Wholesale Goods"
        }
    ],
    "sg:phone":"+39 0761 780820",
    "sg:postcode":"01022",
    "sg:province":"Viterbo",
    "wof:name":"Marucci Enzo",
    "wof:placetype":"venue"
},
  "geometry": {"coordinates":[12.084534,42.629272],"type":"Point"}
}