{
  "type": "Feature",
  "properties": {
    "iso:country":"IT",
    "sg:address":"36, Via Caprile Centro 44021 Codigoro",
    "sg:city":"Codigoro",
    "sg:classifiers":[
        {
            "category":"Personal",
            "subcategory":"Shoe Repair & Shine",
            "type":"Services"
        }
    ],
    "sg:phone":"+39 0533 932082",
    "sg:postcode":"44021",
    "sg:province":"Ferrara",
    "sg:tags":[
        "leather"
    ],
    "wof:name":"Benasciutti Albonea",
    "wof:placetype":"venue"
},
  "geometry": {"coordinates":[11.62044,44.837894],"type":"Point"}
}