{
  "type": "Feature",
  "properties": {
    "iso:country":"IT",
    "sg:address":"56028 S. Miniato",
    "sg:orig_category":"Automobili E Mezzi Di Trasporto",
    "sg:phone":"+39 0571 401200",
    "sg:postcode":"56028",
    "sg:province":"Pisa",
    "wof:name":"Autolinee A. Danti Di Ferrera Salvatore",
    "wof:placetype":"venue"
},
  "geometry": {"coordinates":[10.396585,43.716137],"type":"Point"}
}