{
  "type": "Feature",
  "properties": {
    "iso:country":"IT",
    "sg:address":"25022 Acqualunga",
    "sg:orig_category":"Zootecnia E Pesca, Allevamento Piccoli Animali",
    "sg:phone":"+39 030 994 8328",
    "sg:postcode":"25022",
    "sg:province":"Brescia",
    "wof:name":"Lughignani Giulio",
    "wof:placetype":"venue"
},
  "geometry": {"coordinates":[9.953999,45.326118],"type":"Point"}
}