{
  "type": "Feature",
  "properties": {
    "iso:country":"IT",
    "sg:address":"13, Via Tagliamento 23900 Lecco",
    "sg:city":"Lecco",
    "sg:classifiers":[
        {
            "category":"Shopping",
            "subcategory":"Computers & Home Electronics",
            "type":"Retail Goods"
        }
    ],
    "sg:phone":"+39 0341 494512",
    "sg:postcode":"23900",
    "sg:province":"Lecco",
    "sg:tags":[
        "electronic",
        "electrical",
        "equipment"
    ],
    "wof:name":"Sintel (s.r.l.)",
    "wof:placetype":"venue"
},
  "geometry": {"coordinates":[9.407143,45.854195],"type":"Point"}
}