{
  "type": "Feature",
  "properties": {
    "addr:full":"15066 Gavi Gavi Alessandria 15066",
    "addr:postcode":"15066;15066",
    "iso:country":"IT",
    "sg:address":"15066 Gavi",
    "sg:city":"Gavi",
    "sg:orig_category":"Ceramiche: Prodotti E Lavorazioni",
    "sg:phone":"+39 0143 642715",
    "sg:postcode":"15066",
    "sg:province":"Alessandria",
    "wof:name":"Dellacasa Fratelli Snc",
    "wof:placetype":"venue"
},
  "geometry": {"coordinates":[8.699023,44.869598],"type":"Point"}
}