{
  "type": "Feature",
  "properties": {
    "iso:country":"IT",
    "sg:address":"33054 Lignano Sabbiadoro",
    "sg:city":"Lignano Sabbiadoro",
    "sg:orig_category":"Nautica. Accessori Dei Mezzi Di Trasporto",
    "sg:phone":"+39 0431 70315",
    "sg:postcode":"33054",
    "sg:province":"Udine",
    "wof:name":"Marina Punta Faro - Adriatica Marina Spa",
    "wof:placetype":"venue"
},
  "geometry": {"coordinates":[13.105357,45.669388],"type":"Point"}
}