{
  "type": "Feature",
  "properties": {
    "addr:full":"20089 Rozzano Rozzano Milano 20089",
    "addr:postcode":"20089;20089",
    "iso:country":"IT",
    "sg:address":"20089 Rozzano",
    "sg:city":"Rozzano",
    "sg:orig_category":"Macchine, Impianti E Forniture Per Industria Grafica, Cartaria E Cartotecnica",
    "sg:phone":"+39 02 5751 0841",
    "sg:postcode":"20089",
    "sg:province":"Milano",
    "wof:name":"Tecnorulli (s.r.l.)",
    "wof:placetype":"venue"
},
  "geometry": {"coordinates":[9.156353,45.395107],"type":"Point"}
}