{
  "type": "Feature",
  "properties": {
    "iso:country":"IT",
    "sg:address":"80121 Napoli",
    "sg:city":"Napoli",
    "sg:orig_category":"Forniture Per Abbigliamento E Pelletterie. Complementi Di Arredamento",
    "sg:phone":"+39 081 417272",
    "sg:postcode":"80121",
    "sg:province":"Napoli",
    "wof:name":"Au Passementier",
    "wof:placetype":"venue"
},
  "geometry": {"coordinates":[14.284444809,40.9027862549],"type":"Point"}
}