{
  "type": "Feature",
  "properties": {
    "iso:country":"IT",
    "sg:address":"20122 Milano",
    "sg:city":"Milano",
    "sg:orig_category":"Scuole E Servizi Scolastici. Ricerca, Selezione E Formazione Del Personale",
    "sg:phone":"+39 02 584 5980",
    "sg:postcode":"20122",
    "sg:province":"Milano",
    "sg:website":"http://www.alphatest.it",
    "wof:name":"Alpha Test Srl",
    "wof:placetype":"venue"
},
  "geometry": {"coordinates":[9.188889,45.455448],"type":"Point"}
}