{
  "type": "Feature",
  "properties": {
    "addr:full":"51011 Borgo A Buggiano Borgo a buggiano Pistoia 51011",
    "addr:postcode":"51011;51011",
    "iso:country":"IT",
    "sg:address":"51011 Borgo A Buggiano",
    "sg:city":"Borgo a buggiano",
    "sg:orig_category":"Metalli E Leghe",
    "sg:phone":"+39 0572 32216",
    "sg:postcode":"51011",
    "sg:province":"Pistoia",
    "wof:name":"Ghidi Metalli Srl",
    "wof:placetype":"venue"
},
  "geometry": {"coordinates":[10.7280235291,43.8796806335],"type":"Point"}
}