{
  "type": "Feature",
  "properties": {
    "iso:country":"IT",
    "sg:address":"21, Via Predda Niedda Nord Z.i. 07100 Sassari",
    "sg:city":"Sassari",
    "sg:classifiers":[
        {
            "category":"Home & Garden",
            "subcategory":"Home Furnishings",
            "type":"Retail Goods"
        }
    ],
    "sg:phone":"+39 39079260490",
    "sg:postcode":"07100",
    "sg:province":"Sassari",
    "sg:tags":[
        "household"
    ],
    "wof:name":"Cadelano & Cadelano",
    "wof:placetype":"venue"
},
  "geometry": {"coordinates":[8.553889,40.729443],"type":"Point"}
}