{
  "type": "Feature",
  "properties": {
    "iso:country":"IT",
    "sg:address":"Via Rossini 28/30 20093 Cologno Monzese",
    "sg:city":"Cologno Monzese",
    "sg:orig_category":"Filters For The Food Industry",
    "sg:phone":"+39 02 253 6041",
    "sg:postcode":"20093",
    "sg:province":"Milano",
    "sg:website":"www.industrialfiltro.com",
    "wof:name":"Industrialfiltro S.r.l.",
    "wof:placetype":"venue"
},
  "geometry": {"coordinates":[9.2779321671,45.5400886536],"type":"Point"}
}