{
  "type": "Feature",
  "properties": {
    "iso:country":"IT",
    "sg:address":"145/147, Corso Mazzini Giuseppe 87100 Cosenza",
    "sg:city":"Cosenza",
    "sg:classifiers":[
        {
            "category":"Shopping",
            "subcategory":"Clothing, Apparel, & Fashions",
            "type":"Retail Goods"
        }
    ],
    "sg:phone":"+39 39098424094",
    "sg:postcode":"87100",
    "sg:province":"Cosenza",
    "sg:tags":[
        "clothes"
    ],
    "wof:name":"G. Mazzocca & C. (s.r.l.)",
    "wof:placetype":"venue"
},
  "geometry": {"coordinates":[16.253809,39.298264],"type":"Point"}
}