{
  "type": "Feature",
  "properties": {
    "addr:full":"22031 Albavilla Albavilla Como 22031",
    "addr:postcode":"22031;22031",
    "iso:country":"IT",
    "sg:address":"22031 Albavilla",
    "sg:city":"Albavilla",
    "sg:orig_category":"Officine Meccaniche",
    "sg:phone":"+39 031 644104",
    "sg:postcode":"22031",
    "sg:province":"Como",
    "sg:website":"http://cdfsrl.com",
    "wof:name":"C.d.f. Srl",
    "wof:placetype":"venue"
},
  "geometry": {"coordinates":[9.142936,45.779831],"type":"Point"}
}