{
  "type": "Feature",
  "properties": {
    "iso:country":"IT",
    "sg:address":"Via Indipendenza 4 33044 Manzano",
    "sg:city":"Manzano",
    "sg:classifiers":[
        {
            "category":"Wholesale",
            "subcategory":"Home Furnishings",
            "type":"Manufacturing & Wholesale Goods"
        }
    ],
    "sg:phone":"+39 0432 754133",
    "sg:postcode":"33044",
    "sg:province":"Udine",
    "sg:tags":[
        "chair"
    ],
    "sg:website":"www.potocco.it",
    "wof:name":"Potocco Spa",
    "wof:placetype":"venue"
},
  "geometry": {"coordinates":[13.376351,45.986137],"type":"Point"}
}