{
  "type": "Feature",
  "properties": {
    "addr:full":"40, Via Orlando Vittorio Emanuele 20039 Varedo Varedo Milano 20039",
    "addr:postcode":"20039;20039",
    "addr:street":"Via Orlando Vittorio Emanuele",
    "iso:country":"IT",
    "sg:address":"40, Via Orlando Vittorio Emanuele 20039 Varedo",
    "sg:city":"Varedo",
    "sg:classifiers":[
        {
            "category":"Utilities",
            "subcategory":"Electric",
            "type":"Services"
        }
    ],
    "sg:phone":"+39 036 255 5016",
    "sg:postcode":"20039",
    "sg:province":"Milano",
    "sg:tags":[
        "component",
        "electronic"
    ],
    "wof:name":"Global Circuit Srl",
    "wof:placetype":"venue"
},
  "geometry": {"coordinates":[9.188141,45.463688],"type":"Point"}
}