{
  "type": "Feature",
  "properties": {
    "addr:full":"44, Via Roma 37060 Mozzecane Mozzecane Verona 37060",
    "addr:postcode":"37060;37060",
    "addr:street":"Via Roma",
    "iso:country":"IT",
    "sg:address":"44, Via Roma 37060 Mozzecane",
    "sg:city":"Mozzecane",
    "sg:classifiers":[
        {
            "category":"Shopping",
            "subcategory":"Clothing, Apparel, & Fashions",
            "type":"Retail Goods"
        }
    ],
    "sg:phone":"+39 045 634 0444",
    "sg:postcode":"37060",
    "sg:province":"Verona",
    "sg:tags":[
        "clothes"
    ],
    "wof:name":"Produttori Moda Noi (s.r.l.)",
    "wof:placetype":"venue"
},
  "geometry": {"coordinates":[10.810324,45.299519],"type":"Point"}
}