{
  "type": "Feature",
  "properties": {
    "iso:country":"IT",
    "sg:address":"16, Viale Galilei Galileo 30030 Venezia",
    "sg:classifiers":[
        {
            "category":"Airport",
            "subcategory":"General Aviation",
            "type":"Transportation"
        }
    ],
    "sg:phone":"+39 041 541 5155",
    "sg:postcode":"30030",
    "sg:province":"Venezia",
    "sg:tags":[
        "transport",
        "air"
    ],
    "wof:name":"A.elle Cargo S.r.l.",
    "wof:placetype":"venue"
},
  "geometry": {"coordinates":[12.847058,45.780174],"type":"Point"}
}