{
  "type": "Feature",
  "properties": {
    "addr:full":"Via Gramsci, 2/3 38100 Trento Trento Trento 38100",
    "addr:housenumber":"2 / 3",
    "addr:postcode":"38100;38100",
    "addr:street":"Via Gramsci",
    "iso:country":"IT",
    "sg:address":"Via Gramsci, 2/3 38100 Trento",
    "sg:city":"Trento",
    "sg:classifiers":[
        {
            "category":"Building & Trades",
            "subcategory":"Cleaning & Sanitation",
            "type":"Services"
        }
    ],
    "sg:phone":"+39 0461 922019",
    "sg:postcode":"38100",
    "sg:province":"Trento",
    "sg:tags":[
        "sanitary",
        "supply"
    ],
    "wof:name":"Miar S.r.l.",
    "wof:placetype":"venue"
},
  "geometry": {"coordinates":[11.128215,46.052925],"type":"Point"}
}