{
  "type": "Feature",
  "properties": {
    "iso:country":"IT",
    "sg:address":"25, Via Fermi Enrico 36071 Arzignano",
    "sg:city":"Arzignano",
    "sg:classifiers":[
        {
            "category":"Shopping",
            "subcategory":"Clothing, Apparel, & Fashions",
            "type":"Retail Goods"
        }
    ],
    "sg:phone":"+39 0444 672377",
    "sg:postcode":"36071",
    "sg:province":"Vicenza",
    "sg:tags":[
        "clothes"
    ],
    "wof:name":"Confezioni Griffin's",
    "wof:placetype":"venue"
},
  "geometry": {"coordinates":[11.540307,45.545906],"type":"Point"}
}