{
  "type": "Feature",
  "properties": {
    "iso:country":"IT",
    "sg:address":"Via Gozzano ,38 Bis 21052 Busto Arsizio",
    "sg:city":"Busto Arsizio",
    "sg:classifiers":[
        {
            "category":"Manufacturing",
            "subcategory":"Electronics",
            "type":"Manufacturing & Wholesale Goods"
        }
    ],
    "sg:phone":"+39 0331 628244",
    "sg:postcode":"21052",
    "sg:province":"Varese",
    "sg:tags":[
        "amplifier"
    ],
    "sg:website":"www.karmaitaliana.it",
    "wof:name":"Karma Italiana Srl",
    "wof:placetype":"venue"
},
  "geometry": {"coordinates":[8.826385,45.817604],"type":"Point"}
}