{
  "type": "Feature",
  "properties": {
    "iso:country":"IT",
    "sg:address":"91026 Mazara Del Vallo",
    "sg:city":"Mazara del Vallo",
    "sg:orig_category":"Arredamenti Ed Architettura D'interni",
    "sg:phone":"+39 0923 906985",
    "sg:postcode":"91026",
    "sg:province":"Trapani",
    "wof:name":"Fioccarredi Di Fiocca Alberto",
    "wof:placetype":"venue"
},
  "geometry": {"coordinates":[12.606861,37.650059],"type":"Point"}
}