{
  "type": "Feature",
  "properties": {
    "iso:country":"IT",
    "sg:address":"09126 Cagliari",
    "sg:city":"Cagliari",
    "sg:orig_category":"Alimentari - Vendita Al Dettaglio",
    "sg:phone":"+39 070 340089",
    "sg:postcode":"09126",
    "sg:province":"Cagliari",
    "wof:name":"Pitzalis Gino",
    "wof:placetype":"venue"
},
  "geometry": {"coordinates":[9.133618,39.20723],"type":"Point"}
}