{
  "type": "Feature",
  "properties": {
    "addr:full":"36010 Roana Roana Vicenza 36010",
    "addr:postcode":"36010;36010",
    "iso:country":"IT",
    "sg:address":"36010 Roana",
    "sg:city":"Roana",
    "sg:orig_category":"Legno E Semilavorati. Materiali Edili",
    "sg:phone":"+39 0424 692050",
    "sg:postcode":"36010",
    "sg:province":"Vicenza",
    "wof:name":"Frigo Riccardo Frigo Tetti",
    "wof:placetype":"venue"
},
  "geometry": {"coordinates":[11.51467,45.875507],"type":"Point"}
}