{
  "type": "Feature",
  "properties": {
    "iso:country":"IT",
    "sg:address":"00013 Tor Lupara",
    "sg:city":"Tor lupara",
    "sg:orig_category":"Sport - Articoli E Forniture",
    "sg:phone":"+39 06 905 7533",
    "sg:postcode":"00013",
    "sg:province":"Roma",
    "wof:name":"Troiani Lucilla",
    "wof:placetype":"venue"
},
  "geometry": {"coordinates":[12.617401,41.996166],"type":"Point"}
}