{
  "type": "Feature",
  "properties": {
    "iso:country":"IT",
    "sg:address":"25011 Calcinato",
    "sg:city":"Calcinato",
    "sg:orig_category":"Lavorazioni Meccaniche E Servizi. Servizi Per Imballaggio E Confezionamento",
    "sg:phone":"+39 030 963261",
    "sg:postcode":"25011",
    "sg:province":"Brescia",
    "wof:name":"Malagnini Dionora",
    "wof:placetype":"venue"
},
  "geometry": {"coordinates":[10.405047,45.455574],"type":"Point"}
}