{
  "type": "Feature",
  "properties": {
    "iso:country":"IT",
    "sg:address":"71036 Lucera",
    "sg:city":"Lucera",
    "sg:orig_category":"Prodotti E Manufatti In Gomma. Servizi E Lavori Industria Della Gomma. Ricambi E Componenti Dei Mezzi Di Trasporto",
    "sg:phone":"+39 0881 529922",
    "sg:postcode":"71036",
    "sg:province":"Foggia",
    "wof:name":"Schiavone Vittorio & Figli Snc",
    "wof:placetype":"venue"
},
  "geometry": {"coordinates":[15.3599567413,41.4755096436],"type":"Point"}
}