{
  "type": "Feature",
  "properties": {
    "iso:country":"IT",
    "sg:address":"24030 Ambivere",
    "sg:city":"Ambivere",
    "sg:orig_category":"Minuterie Metalliche E Ferramenta",
    "sg:phone":"+39 035 908109",
    "sg:postcode":"24030",
    "sg:province":"Bergamo",
    "wof:name":"Riva Walter",
    "wof:placetype":"venue"
},
  "geometry": {"coordinates":[9.5814285278,45.7391586304],"type":"Point"}
}