{
  "type": "Feature",
  "properties": {
    "iso:country":"IT",
    "sg:address":"33037 Pasian Di Prato",
    "sg:city":"Pasian di Prato",
    "sg:orig_category":"Climatizzazione E Condizionamento, Apparecchiature E Servizi. Accessori Dei Mezzi Di Trasporto",
    "sg:phone":"+39 0432 400379",
    "sg:postcode":"33037",
    "sg:province":"Udine",
    "wof:name":"Ceconi Roberto",
    "wof:placetype":"venue"
},
  "geometry": {"coordinates":[13.182693,46.089756],"type":"Point"}
}