{
  "type": "Feature",
  "properties": {
    "iso:country":"IT",
    "sg:address":"20121 Milano",
    "sg:city":"Milano",
    "sg:orig_category":"Servizi Editoriali. Professionisti - Studi E Servizi Ed Associazioni Di Interesse Aziendale",
    "sg:phone":"+39 02 659 0860",
    "sg:postcode":"20121",
    "sg:province":"Milano",
    "wof:name":"Pavesi Enrico Giovanni",
    "wof:placetype":"venue"
},
  "geometry": {"coordinates":[9.183888,45.472157],"type":"Point"}
}