{
  "type": "Feature",
  "properties": {
    "iso:country":"IT",
    "sg:address":"Via Della Meccanica 8/10 35127 Padova",
    "sg:city":"Padova",
    "sg:classifiers":[
        {
            "category":"Professional",
            "subcategory":"Research",
            "type":"Services"
        }
    ],
    "sg:phone":"+39 049 870 3015",
    "sg:postcode":"35127",
    "sg:province":"Padova",
    "sg:tags":[
        "shock",
        "testing",
        "machinery"
    ],
    "sg:website":"www.jofa.it",
    "wof:name":"Jofa Srl",
    "wof:placetype":"venue"
},
  "geometry": {"coordinates":[11.934133,45.401344],"type":"Point"}
}