{
  "type": "Feature",
  "properties": {
    "iso:country":"IT",
    "sg:address":"00199 Roma",
    "sg:city":"Roma",
    "sg:orig_category":"Ospedali E Servizi Sanitari. Centri Di Estetica E Cosmesi E Servizi",
    "sg:phone":"+39 06 8632 6445",
    "sg:postcode":"00199",
    "sg:province":"Roma",
    "wof:name":"Efoa - University",
    "wof:placetype":"venue"
},
  "geometry": {"coordinates":[12.515662,41.927696],"type":"Point"}
}