{
  "type": "Feature",
  "properties": {
    "iso:country":"IT",
    "sg:address":"34017 Trieste",
    "sg:city":"Prosecco",
    "sg:orig_category":"Calce",
    "sg:phone":"+39 040 251044",
    "sg:postcode":"34017",
    "sg:province":"Trieste",
    "wof:name":"Edil Porfidi Trentina",
    "wof:placetype":"venue"
},
  "geometry": {"coordinates":[13.733682,45.707535],"type":"Point"}
}