{
  "type": "Feature",
  "properties": {
    "iso:country":"IT",
    "sg:address":"70033 Corato",
    "sg:city":"Corato",
    "sg:orig_category":"Motori Ed Organi Di Trasmissione",
    "sg:phone":"+39 080 898 7214",
    "sg:postcode":"70033",
    "sg:province":"Bari",
    "wof:name":"Frivent S.n.c.",
    "wof:placetype":"venue"
},
  "geometry": {"coordinates":[16.4008674622,41.1594581604],"type":"Point"}
}