{
  "type": "Feature",
  "properties": {
    "iso:country":"IT",
    "sg:address":"35043 Monselice",
    "sg:city":"Monselice",
    "sg:orig_category":"Studi E Consulenze Amministrative, Commerciali E Aziendali. Consulenze Tecniche, Amministrative E Perizie. Professionisti - Studi E Servizi Ed Associazioni Di Interesse Aziendale",
    "sg:phone":"+39 0429 781292",
    "sg:postcode":"35043",
    "sg:province":"Padova",
    "wof:name":"Bussolin Rag. Giuseppe",
    "wof:placetype":"venue"
},
  "geometry": {"coordinates":[11.752158,45.230679],"type":"Point"}
}