{
  "type": "Feature",
  "properties": {
    "iso:country":"IT",
    "sg:address":"20139 Milano",
    "sg:city":"Milano",
    "sg:orig_category":"Macchine, Impianti E Forniture Per Industria Grafica, Cartaria E Cartotecnica. Automazione E Macchine Per Ufficio",
    "sg:phone":"+39 0253561",
    "sg:postcode":"20139",
    "sg:province":"Milano",
    "sg:website":"http://www.nashuatec.com",
    "wof:name":"Nashuatec - Divisione Di Nrg Italia Spa",
    "wof:placetype":"venue"
},
  "geometry": {"coordinates":[9.227516,45.428825],"type":"Point"}
}