{
  "type": "Feature",
  "properties": {
    "iso:country":"IT",
    "sg:address":"16, V. Dell'artigianato 22079 Villa Guardia",
    "sg:city":"Villa Guardia",
    "sg:classifiers":[
        {
            "category":"Shopping",
            "type":"Retail Goods"
        }
    ],
    "sg:phone":"+39 39031480350",
    "sg:postcode":"22079",
    "sg:province":"Como",
    "sg:tags":[
        "finished",
        "-",
        "metallic"
    ],
    "sg:website":"http://www.ttmrossi.it",
    "wof:name":"Tessitura Tele Metalliche Rossi Oliviero & C. Srl",
    "wof:placetype":"venue"
},
  "geometry": {"coordinates":[9.033788681,45.7699050903],"type":"Point"}
}