{
  "type": "Feature",
  "properties": {
    "addr:full":"20080 Casarile Casarile Milano 20080",
    "addr:postcode":"20080;20080",
    "iso:country":"IT",
    "sg:address":"20080 Casarile",
    "sg:city":"Casarile",
    "sg:orig_category":"Non-classified Establishments",
    "sg:phone":"+39 02 905 3899",
    "sg:postcode":"20080",
    "sg:province":"Milano",
    "wof:name":"Vetreria Artevetro Di Longo Paolo Paolo",
    "wof:placetype":"venue"
},
  "geometry": {"coordinates":[9.110614,45.547634],"type":"Point"}
}