{
  "type": "Feature",
  "properties": {
    "iso:country":"IT",
    "sg:address":"16040 Ne",
    "sg:city":"Ne",
    "sg:orig_category":"Abbigliamento Sportivo - Produzione E Ingrosso",
    "sg:phone":"+39 0185 337162",
    "sg:postcode":"16040",
    "sg:province":"Genova",
    "wof:name":"Giada Snc",
    "wof:placetype":"venue"
},
  "geometry": {"coordinates":[8.933094,44.411079],"type":"Point"}
}