{
  "type": "Feature",
  "properties": {
    "iso:country":"IT",
    "sg:address":"Via Pian Dei Peschi 53036 Poggibonsi",
    "sg:city":"Poggibonsi",
    "sg:classifiers":[
        {
            "category":"Sports & Exercise",
            "subcategory":"Playing Field",
            "type":"Entertainment"
        }
    ],
    "sg:phone":"+39 0577 979220",
    "sg:postcode":"53036",
    "sg:province":"Siena",
    "sg:tags":[
        "game"
    ],
    "wof:name":"Nuova Foribruc Sdf",
    "wof:placetype":"venue"
},
  "geometry": {"coordinates":[11.330514,43.318661],"type":"Point"}
}