{
  "type": "Feature",
  "properties": {
    "addr:full":"60015 Falconara Marittima Falconara Marittima Ancona 60015",
    "addr:postcode":"60015;60015",
    "iso:country":"IT",
    "sg:address":"60015 Falconara Marittima",
    "sg:city":"Falconara Marittima",
    "sg:classifiers":[
        {
            "category":"Banks & Credit Unions",
            "subcategory":"Bank",
            "type":"Services"
        }
    ],
    "sg:phone":"+39 071 916 1378",
    "sg:postcode":"60015",
    "sg:province":"Ancona",
    "sg:tags":[
        "services",
        "publishing",
        "supply"
    ],
    "sg:website":"http://www.sagraf.it",
    "wof:name":"Sagraf Sabatini Grafiche Srl",
    "wof:placetype":"venue"
},
  "geometry": {"coordinates":[13.3677349091,43.6114730835],"type":"Point"}
}