{
  "type": "Feature",
  "properties": {
    "addr:full":"70022 Altamura Altamura Bari 70022",
    "addr:postcode":"70022;70022",
    "iso:country":"IT",
    "sg:address":"70022 Altamura",
    "sg:city":"Altamura",
    "sg:orig_category":"Servizi E Lavori Industria Della Gomma",
    "sg:phone":"+39 080 314 2508",
    "sg:postcode":"70022",
    "sg:province":"Bari",
    "wof:name":"Simone Giuseppe",
    "wof:placetype":"venue"
},
  "geometry": {"coordinates":[16.559803,40.834507],"type":"Point"}
}