{
  "type": "Feature",
  "properties": {
    "addr:full":"66, Via Cervi Fratelli 42100 Reggio Emilia Reggio Nell'Emilia 42100",
    "addr:postcode":"42100;42100",
    "addr:street":"Via Cervi",
    "iso:country":"IT",
    "sg:address":"66, Via Cervi Fratelli 42100 Reggio Emilia",
    "sg:classifiers":[
        {
            "category":"Shopping",
            "subcategory":"Clothing, Apparel, & Fashions",
            "type":"Retail Goods"
        }
    ],
    "sg:phone":"+39 390 522 7991",
    "sg:postcode":"42100",
    "sg:province":"Reggio Nell'Emilia",
    "sg:tags":[
        "clothes"
    ],
    "wof:name":"Max Mara S.r.l.",
    "wof:placetype":"venue"
},
  "geometry": {"coordinates":[10.593707,44.711521],"type":"Point"}
}