{
  "type": "Feature",
  "properties": {
    "iso:country":"IT",
    "sg:address":"20090 Rodano",
    "sg:city":"Rodano",
    "sg:orig_category":"Materiali E Componenti Elettrotecnici",
    "sg:phone":"+39 02 9532 8014",
    "sg:postcode":"20090",
    "sg:province":"Milano",
    "wof:name":"Mauri Elettroforniture S.p.a.",
    "wof:placetype":"venue"
},
  "geometry": {"coordinates":[9.33537,45.469845],"type":"Point"}
}