{
  "type": "Feature",
  "properties": {
    "addr:full":"41037 Mirandola Mirandola Modena 41037",
    "addr:postcode":"41037;41037",
    "iso:country":"IT",
    "sg:address":"41037 Mirandola",
    "sg:city":"Mirandola",
    "sg:orig_category":"Petroli, Gas E Combustibili",
    "sg:phone":"+39 0535 20037",
    "sg:postcode":"41037",
    "sg:province":"Modena",
    "sg:website":"http://www.grazipetroli.com",
    "wof:name":"Grazi Snc",
    "wof:placetype":"venue"
},
  "geometry": {"coordinates":[11.088470459,44.9287910461],"type":"Point"}
}