{
  "type": "Feature",
  "properties": {
    "iso:country":"IT",
    "sg:address":"32, Via Quasimodo Salvatore 20025 Legnano",
    "sg:city":"Legnano",
    "sg:classifiers":[
        {
            "category":"Shopping",
            "subcategory":"Clothing, Apparel, & Fashions",
            "type":"Retail Goods"
        }
    ],
    "sg:phone":"+39 0331 464286",
    "sg:postcode":"20025",
    "sg:province":"Milano",
    "sg:tags":[
        "clothes"
    ],
    "wof:name":"Alberto Aspesi & C. (s.a.s.)",
    "wof:placetype":"venue"
},
  "geometry": {"coordinates":[9.188141,45.463688],"type":"Point"}
}