{
  "type": "Feature",
  "properties": {
    "addr:full":"04010 Cori Cori Latina 04010",
    "addr:postcode":"04010;04010",
    "iso:country":"IT",
    "sg:address":"04010 Cori",
    "sg:city":"Cori",
    "sg:orig_category":"Pubblica Amministrazione",
    "sg:phone":"+39 06 967 8700",
    "sg:postcode":"04010",
    "sg:province":"Latina",
    "wof:name":"Corpo Forestale Dello Stato",
    "wof:placetype":"venue"
},
  "geometry": {"coordinates":[12.9080934525,41.6446914673],"type":"Point"}
}