{
  "type": "Feature",
  "properties": {
    "iso:country":"IT",
    "sg:address":"62012 Civitanova Marche",
    "sg:city":"Civitanova Marche",
    "sg:orig_category":"Agenzie Investigative",
    "sg:phone":"+39 0733 811332",
    "sg:postcode":"62012",
    "sg:province":"Macerata",
    "sg:website":"http://www.investigazionimorgan.it",
    "wof:name":"Carolla Renato",
    "wof:placetype":"venue"
},
  "geometry": {"coordinates":[13.705146,43.295986],"type":"Point"}
}