{
  "type": "Feature",
  "properties": {
    "addr:full":"10090 Trana Trana Torino 10090",
    "addr:postcode":"10090;10090",
    "iso:country":"IT",
    "sg:address":"10090 Trana",
    "sg:city":"Trana",
    "sg:orig_category":"Mole, Dischi E Lame Abrasive E Diamantate",
    "sg:phone":"+39 011 933117",
    "sg:postcode":"10090",
    "sg:province":"Torino",
    "wof:name":"Impa Di Benetto E C. Snc",
    "wof:placetype":"venue"
},
  "geometry": {"coordinates":[7.4622964859,45.0217323303],"type":"Point"}
}