{
  "type": "Feature",
  "properties": {
    "addr:full":"10138 Torino Torino Torino 10138",
    "addr:housenumber":"10138",
    "addr:postcode":"10138",
    "iso:country":"IT",
    "sg:address":"10138 Torino",
    "sg:city":"Torino",
    "sg:orig_category":"Arredo Bagno Ed Idrosanitari. Complementi Di Arredamento. Vetro: Prodotti E Lavorazioni",
    "sg:phone":"+39 011 433 5161",
    "sg:postcode":"10138",
    "sg:province":"Torino",
    "wof:name":"Airone (s.n.c.)",
    "wof:placetype":"venue"
},
  "geometry": {"coordinates":[7.46887,44.989964],"type":"Point"}
}