{
  "type": "Feature",
  "properties": {
    "iso:country":"IT",
    "sg:address":"00171 Roma",
    "sg:city":"Roma",
    "sg:orig_category":"Valvole E Apparecchiature Di Misura. Ricambi E Componenti Dei Mezzi Di Trasporto",
    "sg:phone":"+39 06 2180 1997",
    "sg:postcode":"00171",
    "sg:province":"Roma",
    "wof:name":"Aleo Giuseppe",
    "wof:placetype":"venue"
},
  "geometry": {"coordinates":[12.884376,41.889793],"type":"Point"}
}