{
  "type": "Feature",
  "properties": {
    "iso:country":"IT",
    "sg:address":"Via Capitello 7; Vidor; 31020",
    "sg:city":"Vidor",
    "sg:classifiers":[
        {
            "category":"Banks & Credit Unions",
            "subcategory":"Bank",
            "type":"Services"
        }
    ],
    "sg:phone":"+39 0423 987121",
    "sg:postcode":"31020",
    "sg:province":"Treviso",
    "wof:name":"Banca Popolare C.piva, Di Valdobbiadene Scarl",
    "wof:placetype":"venue"
},
  "geometry": {"coordinates":[12.045099,45.857685],"type":"Point"}
}