{
  "type": "Feature",
  "properties": {
    "iso:country":"IT",
    "sg:address":"22044 Inverigo",
    "sg:city":"Inverigo",
    "sg:orig_category":"Zootecnia E Pesca, Allevamento Piccoli Animali",
    "sg:phone":"+39 031 605181",
    "sg:postcode":"22044",
    "sg:province":"Como",
    "wof:name":"Pescasport Carpanea",
    "wof:placetype":"venue"
},
  "geometry": {"coordinates":[9.243153,45.748905],"type":"Point"}
}