{
  "type": "Feature",
  "properties": {
    "addr:full":"02015 Cittaducale Cittaducale Rieti 02015",
    "addr:postcode":"02015;02015",
    "iso:country":"IT",
    "sg:address":"02015 Cittaducale",
    "sg:city":"Cittaducale",
    "sg:orig_category":"Articoli Per Imballaggio E Confezionamento",
    "sg:phone":"+39 0746 606351",
    "sg:postcode":"02015",
    "sg:province":"Rieti",
    "wof:name":"Torda Fratelli Spa",
    "wof:placetype":"venue"
},
  "geometry": {"coordinates":[12.882006,42.405903],"type":"Point"}
}