{
  "type": "Feature",
  "properties": {
    "iso:country":"IT",
    "sg:address":"Via Pellissier, 17/a; Chatillon; 11024",
    "sg:city":"Chatillon",
    "sg:classifiers":[
        {
            "category":"Banks & Credit Unions",
            "subcategory":"Bank",
            "type":"Services"
        }
    ],
    "sg:phone":"+39 0166 61842",
    "sg:postcode":"11024",
    "sg:province":"Aosta",
    "wof:name":"Banca Popolare Di Novara",
    "wof:placetype":"venue"
},
  "geometry": {"coordinates":[7.615304,45.750267],"type":"Point"}
}