{
  "type": "Feature",
  "properties": {
    "addr:full":"00045 Genzano Di Roma Genzano di Roma Roma 00045",
    "addr:postcode":"00045;00045",
    "iso:country":"IT",
    "sg:address":"00045 Genzano Di Roma",
    "sg:city":"Genzano di Roma",
    "sg:orig_category":"Macchine, Impianti Ed Attrezzature Per Industria Alimentare E Bevande",
    "sg:phone":"+39 06 939 7344",
    "sg:postcode":"00045",
    "sg:province":"Roma",
    "wof:name":"Silvestri Vincenzo",
    "wof:placetype":"venue"
},
  "geometry": {"coordinates":[12.691291,41.704308],"type":"Point"}
}