{
  "type": "Feature",
  "properties": {
    "iso:country":"IT",
    "sg:address":"21, Via Della Lora 50031 Barberino Di Mugello",
    "sg:city":"Barberino di Mugello",
    "sg:classifiers":[
        {
            "category":"Manufacturing",
            "subcategory":"Paper Products",
            "type":"Manufacturing & Wholesale Goods"
        }
    ],
    "sg:phone":"+39 055 841 8061",
    "sg:postcode":"50031",
    "sg:province":"Firenze",
    "sg:tags":[
        "cardboard"
    ],
    "wof:name":"Sei Esse S.p.a.",
    "wof:placetype":"venue"
},
  "geometry": {"coordinates":[11.2305326462,43.994846344],"type":"Point"}
}