{
  "type": "Feature",
  "properties": {
    "iso:country":"IT",
    "sg:address":"Villaggio Montefeltro 1 61023 Macerata Feltria",
    "sg:city":"Macerata Feltria",
    "sg:classifiers":[
        {
            "category":"Parking",
            "subcategory":"Lot",
            "type":"Transportation"
        }
    ],
    "sg:phone":"+39 0722 74266",
    "sg:postcode":"61023",
    "sg:province":"Pesaro E Urbino",
    "sg:tags":[
        "box",
        "cardboard",
        "shipping"
    ],
    "wof:name":"Gestione La Feltresca Impresa Individuale",
    "wof:placetype":"venue"
},
  "geometry": {"coordinates":[12.447937,43.800217],"type":"Point"}
}