{
  "type": "Feature",
  "properties": {
    "addr:full":"87019 Spezzano Albanese Spezzano Albanese Cosenza 87019",
    "addr:postcode":"87019;87019",
    "addr:street":"Albanese",
    "iso:country":"IT",
    "sg:address":"87019 Spezzano Albanese",
    "sg:city":"Spezzano Albanese",
    "sg:orig_category":"Banche E Servizi Finanziari",
    "sg:phone":"+39 0981 953004",
    "sg:postcode":"87019",
    "sg:province":"Cosenza",
    "wof:name":"Banca Di Credito Cooperativo Della Sibaritide Di Spezzano Albanese",
    "wof:placetype":"venue"
},
  "geometry": {"coordinates":[16.311062,39.686733],"type":"Point"}
}