{
  "type": "Feature",
  "properties": {
    "iso:country":"IT",
    "sg:address":"26100 Cremona",
    "sg:city":"Cremona",
    "sg:orig_category":"Ricerca, Selezione E Formazione Del Personale. Pubblica Amministrazione",
    "sg:phone":"+39 0372 403011",
    "sg:postcode":"26100",
    "sg:province":"Cremona",
    "wof:name":"Ufficio Provinciale Del Lavoro",
    "wof:placetype":"venue"
},
  "geometry": {"coordinates":[10.022127,45.134495],"type":"Point"}
}