{
  "type": "Feature",
  "properties": {
    "iso:country":"IT",
    "sg:address":"Contrada Piritino 95032 Belpasso",
    "sg:city":"Belpasso",
    "sg:classifiers":[
        {
            "category":"Manufacturing",
            "subcategory":"Metals",
            "type":"Manufacturing & Wholesale Goods"
        }
    ],
    "sg:phone":"+39 095 713 1968",
    "sg:postcode":"95032",
    "sg:province":"Catania",
    "sg:tags":[
        "processing"
    ],
    "wof:name":"Etnall (s.p.a.)",
    "wof:placetype":"venue"
},
  "geometry": {"coordinates":[14.9272041321,37.5203170776],"type":"Point"}
}