{
  "type": "Feature",
  "properties": {
    "iso:country":"IT",
    "sg:address":"31030 Dosson",
    "sg:city":"Dosson",
    "sg:orig_category":"Macchine Utensili E Impianti",
    "sg:phone":"+39 0422 497411",
    "sg:postcode":"31030",
    "sg:province":"Treviso",
    "wof:name":"Serconsult (s.r.l.)",
    "wof:placetype":"venue"
},
  "geometry": {"coordinates":[12.246207,45.626431],"type":"Point"}
}