{
  "type": "Feature",
  "properties": {
    "iso:country":"IT",
    "sg:address":"5, Piazza Monte Rosa 21028 Travedona Monate",
    "sg:classifiers":[
        {
            "category":"Food & Beverages",
            "subcategory":"Dairy",
            "type":"Retail Goods"
        }
    ],
    "sg:phone":"+39 0332 977061",
    "sg:postcode":"21028",
    "sg:province":"Varese",
    "sg:tags":[
        "product"
    ],
    "wof:name":"Latteria Lago Monate S.r.l.",
    "wof:placetype":"venue"
},
  "geometry": {"coordinates":[8.735325,45.832695],"type":"Point"}
}