{
  "type": "Feature",
  "properties": {
    "iso:country":"IT",
    "sg:address":"14033 Castell'alfero",
    "sg:orig_category":"Servizi E Lavori Industria Della Gomma. Servizi E Lavori Industria Delle Materie Plastiche. Forniture Per Edilizia E Lavori Pubblici",
    "sg:phone":"+39 0141 405701",
    "sg:postcode":"14033",
    "sg:province":"Asti",
    "wof:name":"T&g Srl",
    "wof:placetype":"venue"
},
  "geometry": {"coordinates":[8.225271,44.983681],"type":"Point"}
}