{
  "type": "Feature",
  "properties": {
    "addr:full":"35010 Padova Padova 35010",
    "addr:postcode":"35010;35010",
    "iso:country":"IT",
    "sg:address":"35010 Padova",
    "sg:orig_category":"Cine-foto-ottica. Articoli Medico-sanitari Ed Ortopedici",
    "sg:phone":"+39 049 618030",
    "sg:postcode":"35010",
    "sg:province":"Padova",
    "wof:name":"Ottica Toffoli",
    "wof:placetype":"venue"
},
  "geometry": {"coordinates":[11.876589,45.409569],"type":"Point"}
}