{
  "type": "Feature",
  "properties": {
    "iso:country":"IT",
    "sg:address":"20129 Milano",
    "sg:city":"Milano",
    "sg:orig_category":"Ospedali E Servizi Sanitari",
    "sg:phone":"+39 02 730756",
    "sg:postcode":"20129",
    "sg:province":"Milano",
    "wof:name":"Viarengo Anna Rita",
    "wof:placetype":"venue"
},
  "geometry": {"coordinates":[9.289258,45.434875],"type":"Point"}
}