{
  "type": "Feature",
  "properties": {
    "iso:country":"IT",
    "sg:address":"Via Del Chianti 36 50028 Tavarnelle Val Di Pesa",
    "sg:city":"Tavarnelle Val di Pesa",
    "sg:classifiers":[
        {
            "category":"Bars & Pubs",
            "subcategory":"Sports Bar",
            "type":"Food & Drink"
        }
    ],
    "sg:phone":"+39 055 805 0374",
    "sg:postcode":"50028",
    "sg:province":"Firenze",
    "sg:tags":[
        "packaging",
        "manufacturing",
        "customized"
    ],
    "sg:website":"www.fiorentinifirenze.it",
    "wof:name":"Fiorentini Firenze Spa",
    "wof:placetype":"venue"
},
  "geometry": {"coordinates":[11.2205896378,43.5380554199],"type":"Point"}
}