{
  "type": "Feature",
  "properties": {
    "iso:country":"IT",
    "sg:address":"Via Artigianale 34 25082 Botticino Sera",
    "sg:city":"Botticino",
    "sg:classifiers":[
        {
            "category":"Home & Garden",
            "subcategory":"Building Materials",
            "type":"Retail Goods"
        }
    ],
    "sg:phone":"+39 030 219 0811",
    "sg:postcode":"25082",
    "sg:province":"Brescia",
    "sg:tags":[
        "installation",
        "electric"
    ],
    "sg:website":"www.steltronic.com",
    "wof:name":"Steltronic Srl",
    "wof:placetype":"venue"
},
  "geometry": {"coordinates":[10.313312,45.529068],"type":"Point"}
}