{
  "type": "Feature",
  "properties": {
    "iso:country":"IT",
    "sg:address":"00154 Roma",
    "sg:city":"Roma",
    "sg:orig_category":"Agricoltura, Orticoltura E Floricoltura",
    "sg:phone":"+39 06 571 7711",
    "sg:postcode":"00154",
    "sg:province":"Roma",
    "wof:name":"Ente Tabacchi Italiani E.t.i.",
    "wof:placetype":"venue"
},
  "geometry": {"coordinates":[12.486789,41.870888],"type":"Point"}
}