{
  "type": "Feature",
  "properties": {
    "addr:full":"29, V. Pieri 33100 Udine Udine Udine 33100",
    "addr:housenumber":"29",
    "addr:postcode":"33100;33100",
    "addr:street":"V. Pieri",
    "iso:country":"IT",
    "sg:address":"29, V. Pieri 33100 Udine",
    "sg:city":"Udine",
    "sg:classifiers":[
        {
            "category":"Wholesale",
            "subcategory":"Machinery & Supplies",
            "type":"Manufacturing & Wholesale Goods"
        }
    ],
    "sg:phone":"+39 390 432 4971",
    "sg:postcode":"33100",
    "sg:province":"Udine",
    "sg:tags":[
        "equipment",
        "precision"
    ],
    "sg:website":"http://www.solari.it",
    "wof:name":"Solari Di Udine Spa",
    "wof:placetype":"venue"
},
  "geometry": {"coordinates":[13.225859642,46.0751686096],"type":"Point"}
}