{
  "type": "Feature",
  "properties": {
    "iso:country":"IT",
    "sg:address":"42100 Reggio Emilia",
    "sg:orig_category":"Hospital And Health Services. Public Administration. Social Services",
    "sg:phone":"+39 0522 335111",
    "sg:postcode":"42100",
    "sg:province":"Reggio Nell'Emilia",
    "sg:website":"http://www.ausl.re.it",
    "wof:name":"Azienda Usl Di Reggio Emilia",
    "wof:placetype":"venue"
},
  "geometry": {"coordinates":[10.659644,44.68853],"type":"Point"}
}