{
  "type": "Feature",
  "properties": {
    "iso:country":"IT",
    "sg:address":"55100 Antraccoli",
    "sg:orig_category":"Elettrodomestici. Forniture Alle Strutture Ricettive",
    "sg:phone":"+39 0583 495555",
    "sg:postcode":"55100",
    "sg:province":"Lucca",
    "wof:name":"Eurotec Srl Divisione Colged",
    "wof:placetype":"venue"
},
  "geometry": {"coordinates":[10.551924,43.841736],"type":"Point"}
}