{
  "type": "Feature",
  "properties": {
    "iso:country":"IT",
    "sg:address":"Viale E. Mattei 4 25030 Coccaglio",
    "sg:city":"Coccaglio",
    "sg:classifiers":[
        {
            "category":"Home & Garden",
            "subcategory":"Home Furnishings",
            "type":"Retail Goods"
        }
    ],
    "sg:phone":"+39 030 772 1389",
    "sg:postcode":"25030",
    "sg:province":"Brescia",
    "sg:tags":[
        "bathroom",
        "wc",
        "fitting"
    ],
    "sg:website":"www.insab.net",
    "wof:name":"I.n.s.a.b. Spa",
    "wof:placetype":"venue"
},
  "geometry": {"coordinates":[10.222958,45.539829],"type":"Point"}
}