{
  "type": "Feature",
  "properties": {
    "iso:country":"IT",
    "sg:address":"Via Calabria 06019 Umbertide",
    "sg:city":"Umbertide",
    "sg:classifiers":[
        {
            "category":"Shopping",
            "type":"Retail Goods"
        }
    ],
    "sg:phone":"+39 075 941 2506",
    "sg:postcode":"06019",
    "sg:province":"Perugia",
    "sg:tags":[
        "finished",
        "-",
        "metallic"
    ],
    "wof:name":"Overmek S.r.l.",
    "wof:placetype":"venue"
},
  "geometry": {"coordinates":[12.3336839676,43.2984848022],"type":"Point"}
}