{
  "type": "Feature",
  "properties": {
    "iso:country":"IT",
    "sg:address":"93017 San Cataldo",
    "sg:city":"San Cataldo",
    "sg:orig_category":"Decoratori",
    "sg:phone":"+39 339 743 0855",
    "sg:postcode":"93017",
    "sg:province":"Caltanissetta",
    "wof:name":"Dec\u00d2ra Studio Delle Arti Decorative Di Rosario Aiera",
    "wof:placetype":"venue"
},
  "geometry": {"coordinates":[13.987685,37.48254],"type":"Point"}
}