{
  "type": "Feature",
  "properties": {
    "iso:country":"IT",
    "sg:address":"Corso Nazionale 5 19126 La Spezia",
    "sg:classifiers":[
        {
            "category":"Professional",
            "subcategory":"Employment Agencies",
            "type":"Services"
        }
    ],
    "sg:phone":"+39 0187 506285",
    "sg:province":"SP",
    "sg:tags":[
        "cargo"
    ],
    "wof:name":"Ma.gna.ni S.r.l.",
    "wof:placetype":"venue"
},
  "geometry": {"coordinates":[9.841599,44.111446],"type":"Point"}
}