{
  "type": "Feature",
  "properties": {
    "iso:country":"IT",
    "sg:address":"137/bis, Viale Venezia 31015 Conegliano",
    "sg:city":"Conegliano",
    "sg:classifiers":[
        {
            "category":"Real Estate",
            "subcategory":"Architect",
            "type":"Services"
        }
    ],
    "sg:phone":"+39 39043862202",
    "sg:postcode":"31015",
    "sg:province":"Treviso",
    "sg:tags":[
        "textile",
        "clothing"
    ],
    "wof:name":"Tintoria Di Conegliano (s.r.l.)",
    "wof:placetype":"venue"
},
  "geometry": {"coordinates":[12.242072,45.666286],"type":"Point"}
}