{
  "type": "Feature",
  "properties": {
    "addr:full":"74013 Ginosa Ginosa Taranto 74013",
    "addr:postcode":"74013;74013",
    "addr:street":"Ginosa Taranto",
    "iso:country":"IT",
    "sg:address":"74013 Ginosa",
    "sg:city":"Ginosa",
    "sg:orig_category":"Forniture Per Agricoltura E Zootecnia. Prodotti Chimici Secondari. Macchine E Forniture Per Ecologia E Smaltimento Rifiuti",
    "sg:phone":"+39 099 829 4679",
    "sg:postcode":"74013",
    "sg:province":"Taranto",
    "wof:name":"Calabrese Leonardo - Fitofarmaci",
    "wof:placetype":"venue"
},
  "geometry": {"coordinates":[16.7577629089,40.5704879761],"type":"Point"}
}