{
  "type": "Feature",
  "properties": {
    "addr:full":"06128 Perugia Perugia Perugia 06128",
    "addr:postcode":"06128;06128",
    "iso:country":"IT",
    "sg:address":"06128 Perugia",
    "sg:city":"Perugia",
    "sg:orig_category":"Autofficine E Centri Assistenza",
    "sg:phone":"+39 075 500 5250",
    "sg:postcode":"06128",
    "sg:province":"Perugia",
    "wof:name":"Intermotor Srl",
    "wof:placetype":"venue"
},
  "geometry": {"coordinates":[12.360706,43.093658],"type":"Point"}
}