{
  "type": "Feature",
  "properties": {
    "addr:full":"50134 Firenze Firenze Firenze 50134",
    "addr:postcode":"50134;50134",
    "iso:country":"IT",
    "sg:address":"50134 Firenze",
    "sg:city":"Firenze",
    "sg:orig_category":"Trasporti E Spedizioni Merci",
    "sg:phone":"+39 055 436 8776",
    "sg:postcode":"50134",
    "sg:province":"Firenze",
    "wof:name":"Ci.erre Sas",
    "wof:placetype":"venue"
},
  "geometry": {"coordinates":[11.246607,43.788742],"type":"Point"}
}