{
  "type": "Feature",
  "properties": {
    "iso:country":"IT",
    "sg:address":"60037 Monte San Vito",
    "sg:city":"Monte San Vito",
    "sg:orig_category":"Pubblica Amministrazione",
    "sg:phone":"+39 071 748931",
    "sg:postcode":"60037",
    "sg:province":"Ancona",
    "wof:name":"Comune Monte San Vito",
    "wof:placetype":"venue"
},
  "geometry": {"coordinates":[13.2721195221,43.600605011],"type":"Point"}
}