{
  "type": "Feature",
  "properties": {
    "iso:country":"IT",
    "sg:address":"35, Via S. Vitale 40054 Budrio",
    "sg:city":"Budrio",
    "sg:classifiers":[
        {
            "category":"Home & Garden",
            "subcategory":"Home Furnishings",
            "type":"Retail Goods"
        }
    ],
    "sg:phone":"+39 39051806911",
    "sg:postcode":"40054",
    "sg:province":"Bologna",
    "sg:tags":[
        "household"
    ],
    "wof:name":"Cem S.p.a.",
    "wof:placetype":"venue"
},
  "geometry": {"coordinates":[11.603824,44.49078],"type":"Point"}
}