{
  "type": "Feature",
  "properties": {
    "addr:full":"Piazza Italia 17/18; Perugia; 06100",
    "addr:housenumber":"17 / 18",
    "addr:postcode":"06100",
    "addr:street":"Piazza Italia",
    "iso:country":"IT",
    "sg:address":"Piazza Italia 17/18; Perugia; 06100",
    "sg:classifiers":[
        {
            "category":"Banks & Credit Unions",
            "subcategory":"Bank",
            "type":"Services"
        }
    ],
    "sg:phone":"+39 0752941",
    "wof:name":"Banco Di Perugia Spa",
    "wof:placetype":"venue"
},
  "geometry": {"coordinates":[12.387872,43.1091],"type":"Point"}
}