{
  "type": "Feature",
  "properties": {
    "iso:country":"IT",
    "sg:address":"20040 Bellusco",
    "sg:city":"Bellusco",
    "sg:orig_category":"Prodotti E Manufatti In Materie Plastiche",
    "sg:postcode":"20040",
    "sg:province":"Milano",
    "wof:name":"Mirex (s.r.l.)",
    "wof:placetype":"venue"
},
  "geometry": {"coordinates":[9.4429864883,45.6165046692],"type":"Point"}
}