{
  "type": "Feature",
  "properties": {
    "addr:full":"19, Via Della Meccanica 04011 Aprilia Aprilia Latina 04011",
    "addr:postcode":"04011;04011",
    "addr:street":"Via Della Meccanica",
    "iso:country":"IT",
    "sg:address":"19, Via Della Meccanica 04011 Aprilia",
    "sg:city":"Aprilia",
    "sg:classifiers":[
        {
            "category":"Banks & Credit Unions",
            "subcategory":"Investment Brokerage",
            "type":"Services"
        }
    ],
    "sg:phone":"+39 39069280793",
    "sg:postcode":"04011",
    "sg:province":"Latina",
    "sg:tags":[
        "-",
        "transport",
        "related"
    ],
    "wof:name":"Romasped S.p.a.",
    "wof:placetype":"venue"
},
  "geometry": {"coordinates":[12.9037,41.467598],"type":"Point"}
}