{
  "type": "Feature",
  "properties": {
    "addr:full":"00193 Roma Roma Roma 00193",
    "addr:postcode":"00193;00193",
    "iso:country":"IT",
    "sg:address":"00193 Roma",
    "sg:city":"Roma",
    "sg:orig_category":"Bevande, Vini E Liquori",
    "sg:phone":"+39 06 320 3575",
    "sg:postcode":"00193",
    "sg:province":"Roma",
    "wof:name":"Costantini Piero Enoteca",
    "wof:placetype":"venue"
},
  "geometry": {"coordinates":[12.495065,41.896439],"type":"Point"}
}