{
  "type": "Feature",
  "properties": {
    "addr:full":"00040 Pomezia Pomezia Roma 00040",
    "addr:postcode":"00040;roma 00040",
    "iso:country":"IT",
    "sg:address":"00040 Pomezia",
    "sg:city":"Pomezia",
    "sg:orig_category":"Espositori, Displays E Articoli Pubblicitari Punto Vendita",
    "sg:phone":"+39 06 9160 2714",
    "sg:postcode":"00040",
    "sg:province":"Roma",
    "wof:name":"F.t. Figurative Tecnique",
    "wof:placetype":"venue"
},
  "geometry": {"coordinates":[12.520862,41.664127],"type":"Point"}
}