{
  "type": "Feature",
  "properties": {
    "iso:country":"IT",
    "sg:address":"22060 Arosio",
    "sg:city":"Arosio",
    "sg:orig_category":"Servizi E Lavori Per Ecologia E Smaltimento Rifiuti. Arte Ed Artigianato Artistico. Servizi Ausiliari Di Sorveglianza, Manutenzione E Pulizia",
    "sg:phone":"+39 031 761406",
    "sg:postcode":"22060",
    "sg:province":"Como",
    "wof:name":"Fiorindo Rossano",
    "wof:placetype":"venue"
},
  "geometry": {"coordinates":[9.209241,45.717983],"type":"Point"}
}