{
  "type": "Feature",
  "properties": {
    "iso:country":"IT",
    "sg:address":"07010 Chilivani",
    "sg:orig_category":"Pompe. Elettrotecnica Industriale, Prodotti E Apparecchiature",
    "sg:phone":"+39 079 758700",
    "sg:postcode":"07010",
    "sg:province":"Sassari",
    "wof:name":"Martinez Srl",
    "wof:placetype":"venue"
},
  "geometry": {"coordinates":[8.5584688187,40.7271652222],"type":"Point"}
}