{
  "type": "Feature",
  "properties": {
    "iso:country":"IT",
    "sg:address":"20146 Milano",
    "sg:city":"Milano",
    "sg:orig_category":"Cinematografia E Radiotelevisione",
    "sg:phone":"+39 02 498 7433",
    "sg:postcode":"20146",
    "sg:province":"Milano",
    "wof:name":"Schmid Luigi",
    "wof:placetype":"venue"
},
  "geometry": {"coordinates":[9.154963,45.460819],"type":"Point"}
}