{
  "type": "Feature",
  "properties": {
    "iso:country":"IT",
    "sg:address":"18, Viale Della Repubblica 35010 Limena",
    "sg:city":"Limena",
    "sg:classifiers":[
        {
            "category":"Shopping",
            "subcategory":"Computers & Home Electronics",
            "type":"Retail Goods"
        }
    ],
    "sg:phone":"+39 049 884 8130",
    "sg:postcode":"35010",
    "sg:province":"Padova",
    "sg:tags":[
        "electronic",
        "electrical",
        "equipment"
    ],
    "wof:name":"Label Elettronica (s.r.l.)",
    "wof:placetype":"venue"
},
  "geometry": {"coordinates":[11.849541,45.462605],"type":"Point"}
}