{
  "type": "Feature",
  "properties": {
    "addr:full":"2, Corso Unione Sovietica 37038 Soave Soave Verona 37038",
    "addr:postcode":"37038;37038",
    "addr:street":"Corso Unione Sovietica",
    "iso:country":"IT",
    "sg:address":"2, Corso Unione Sovietica 37038 Soave",
    "sg:city":"Soave",
    "sg:classifiers":[
        {
            "category":"Shopping",
            "subcategory":"Computers & Home Electronics",
            "type":"Retail Goods"
        }
    ],
    "sg:phone":"+39 045 613 2132",
    "sg:postcode":"37038",
    "sg:province":"Verona",
    "sg:tags":[
        "electronic",
        "electrical",
        "equipment"
    ],
    "wof:name":"Midac S.p.a.",
    "wof:placetype":"venue"
},
  "geometry": {"coordinates":[11.242103,45.407551],"type":"Point"}
}