{
  "type": "Feature",
  "properties": {
    "iso:country":"IT",
    "sg:address":"73020 Cavallino",
    "sg:city":"Castromediano",
    "sg:orig_category":"Climatizzazione E Condizionamento, Apparecchiature E Servizi. Elettrodomestici",
    "sg:phone":"+39 0832 348988",
    "sg:postcode":"73020",
    "sg:province":"Lecce",
    "sg:website":"http://www.acquaservice.it",
    "wof:name":"Acquaservice Srl",
    "wof:placetype":"venue"
},
  "geometry": {"coordinates":[18.20126,40.31361],"type":"Point"}
}