{
  "type": "Feature",
  "properties": {
    "iso:country":"IT",
    "sg:address":"Via Dell' Industria 4b 42019 Scandiano",
    "sg:classifiers":[
        {
            "category":"Home & Garden",
            "subcategory":"Carpets & Floor Coverings",
            "type":"Retail Goods"
        }
    ],
    "sg:phone":"+39 0522 763411",
    "sg:postcode":"42019",
    "sg:province":"Reggio Nell'Emilia",
    "sg:tags":[
        "tile",
        "ceramic",
        "printed"
    ],
    "wof:name":"Runway S.r.l.",
    "wof:placetype":"venue"
},
  "geometry": {"coordinates":[10.6725149155,44.6220932007],"type":"Point"}
}