{
  "type": "Feature",
  "properties": {
    "iso:country":"IT",
    "sg:address":"35020 Brugine",
    "sg:city":"Brugine",
    "sg:orig_category":"Frigoriferi - Accessori E Parti",
    "sg:phone":"+39 049 580 6018",
    "sg:postcode":"35020",
    "sg:province":"Padova",
    "wof:name":"O.c.s.",
    "wof:placetype":"venue"
},
  "geometry": {"coordinates":[11.9410772324,45.3279647827],"type":"Point"}
}