{
  "type": "Feature",
  "properties": {
    "addr:full":"41058 Vignola Vignola Modena 41058",
    "addr:postcode":"41058;41058",
    "iso:country":"IT",
    "sg:address":"41058 Vignola",
    "sg:city":"Vignola",
    "sg:orig_category":"Motori Ed Organi Di Trasmissione",
    "sg:phone":"+39 059 772724",
    "sg:postcode":"41058",
    "sg:province":"Modena",
    "wof:name":"Ciclotecnica Ghiaroni Efrem Di Ghiaroni Carlo Alberto & C. Snc",
    "wof:placetype":"venue"
},
  "geometry": {"coordinates":[11.0000257492,44.4936714172],"type":"Point"}
}