{
  "type": "Feature",
  "properties": {
    "addr:full":"8, Via Dell' Idraulico 40138 Bologna Bologna Bologna 40138",
    "addr:postcode":"40138;40138",
    "addr:street":"Via Dell ' Idraulico",
    "iso:country":"IT",
    "sg:address":"8, Via Dell' Idraulico 40138 Bologna",
    "sg:city":"Bologna",
    "sg:classifiers":[
        {
            "category":"Professional",
            "subcategory":"Engineering",
            "type":"Services"
        }
    ],
    "sg:phone":"+39 39051530006",
    "sg:postcode":"40138",
    "sg:province":"Bologna",
    "sg:tags":[
        "machine",
        "-",
        "mechanical"
    ],
    "wof:name":"Cames (s.r.l.)",
    "wof:placetype":"venue"
},
  "geometry": {"coordinates":[11.407553,44.502155],"type":"Point"}
}