{
  "type": "Feature",
  "properties": {
    "iso:country":"IT",
    "sg:address":"16038 Santa Margherita Ligure",
    "sg:city":"Santa Margherita Ligure",
    "sg:orig_category":"Trasporti E Spedizioni Merci",
    "sg:phone":"+39 0185 284638",
    "sg:postcode":"16038",
    "sg:province":"Genova",
    "wof:name":"Gi.di.mar. Snc",
    "wof:placetype":"venue"
},
  "geometry": {"coordinates":[9.1954431534,44.3254356384],"type":"Point"}
}