{
  "type": "Feature",
  "properties": {
    "addr:full":"80010 Villaricca Villaricca Napoli 80010",
    "addr:postcode":"80010;80010",
    "iso:country":"IT",
    "sg:address":"80010 Villaricca",
    "sg:city":"Villaricca",
    "sg:orig_category":"Cartotecnica E Servizi. Forniture Per Attivita' Commerciali Ed Artigianali",
    "sg:phone":"+39 081 894 3780",
    "sg:postcode":"80010",
    "sg:province":"Napoli",
    "wof:name":"Colortype Di Raffaella Esposito Sas",
    "wof:placetype":"venue"
},
  "geometry": {"coordinates":[14.1812572479,40.9202919006],"type":"Point"}
}