{
  "type": "Feature",
  "properties": {
    "iso:country":"IT",
    "sg:address":"00139 Roma",
    "sg:city":"Roma",
    "sg:orig_category":"Non-classified Establishments",
    "sg:phone":"+39 06 880 3831",
    "sg:postcode":"00139",
    "sg:province":"Roma",
    "wof:name":"Malgherini Caterina",
    "wof:placetype":"venue"
},
  "geometry": {"coordinates":[12.523963,41.964809],"type":"Point"}
}