{
  "type": "Feature",
  "properties": {
    "iso:country":"IT",
    "sg:address":"35018 San Martino Di Lupari",
    "sg:city":"San Martino di Lupari",
    "sg:orig_category":"Macchine Utensili E Impianti. Apparecchiature Ed Attrezzature Meccaniche",
    "sg:phone":"+39 049 946 1077",
    "sg:postcode":"35018",
    "sg:province":"Padova",
    "wof:name":"Novatec S.r.l.",
    "wof:placetype":"venue"
},
  "geometry": {"coordinates":[11.840178,45.652134],"type":"Point"}
}