{
  "type": "Feature",
  "properties": {
    "addr:full":"25134 Brescia Brescia Brescia 25134",
    "addr:postcode":"25134;25134",
    "iso:country":"IT",
    "sg:address":"25134 Brescia",
    "sg:city":"Brescia",
    "sg:orig_category":"Vigilanza E Sorveglianza",
    "sg:phone":"+39 030 230 2981",
    "sg:postcode":"25134",
    "sg:province":"Brescia",
    "wof:name":"Mondialpol Brescia Srl",
    "wof:placetype":"venue"
},
  "geometry": {"coordinates":[10.252946,45.513771],"type":"Point"}
}