{
  "type": "Feature",
  "properties": {
    "addr:full":"24060 Endine Gaiano Endine Bergamo 24060",
    "addr:postcode":"24060;24060",
    "addr:street":"Gaiano",
    "iso:country":"IT",
    "sg:address":"24060 Endine Gaiano",
    "sg:city":"Endine",
    "sg:orig_category":"Legno E Semilavorati",
    "sg:phone":"+39 035 825000",
    "sg:postcode":"24060",
    "sg:province":"Bergamo",
    "wof:name":"L'eurometal Srl",
    "wof:placetype":"venue"
},
  "geometry": {"coordinates":[10.003973,45.7924],"type":"Point"}
}