{
  "type": "Feature",
  "properties": {
    "addr:full":"100, Viale Marconi 10090 Bruino Bruino Torino 10090",
    "addr:postcode":"10090;10090",
    "addr:street":"Viale Marconi",
    "iso:country":"IT",
    "sg:address":"100, Viale Marconi 10090 Bruino",
    "sg:city":"Bruino",
    "sg:classifiers":[
        {
            "category":"Home & Garden",
            "subcategory":"Home Furnishings",
            "type":"Retail Goods"
        }
    ],
    "sg:phone":"+39 011 904 8378",
    "sg:postcode":"10090",
    "sg:province":"Torino",
    "sg:tags":[
        "household"
    ],
    "wof:name":"Ficco (s.r.l.)",
    "wof:placetype":"venue"
},
  "geometry": {"coordinates":[7.482678,45.013401],"type":"Point"}
}