{
  "type": "Feature",
  "properties": {
    "iso:country":"IT",
    "sg:address":"41049 Sassuolo",
    "sg:city":"Sassuolo",
    "sg:orig_category":"Ceramiche E Refrattari - Impianti, Macchine E Materiali",
    "sg:phone":"+39 0536 812122",
    "sg:postcode":"41049",
    "sg:province":"Modena",
    "wof:name":"Officina Nuova L.l. Di Teodori Tiziano & C. Snc",
    "wof:placetype":"venue"
},
  "geometry": {"coordinates":[10.798922,44.566494],"type":"Point"}
}