{
  "type": "Feature",
  "properties": {
    "iso:country":"IT",
    "sg:address":"07022 Berchidda",
    "sg:city":"Berchidda",
    "sg:orig_category":"Bevande, Vini E Liquori",
    "sg:phone":"+39 079 704163",
    "sg:postcode":"07022",
    "sg:province":"Olbia-Tempio",
    "wof:name":"Cantina Del Giogantinu Soc.coop.r.l.",
    "wof:placetype":"venue"
},
  "geometry": {"coordinates":[9.278559,40.826839],"type":"Point"}
}