{
  "type": "Feature",
  "properties": {
    "iso:country":"IT",
    "sg:address":"20066 Melzo",
    "sg:city":"Melzo",
    "sg:orig_category":"Macchine, Impianti Ed Attrezzature Per Agricoltura E Zootecnia. Macchine, Impianti Ed Attrezzature Industria Chimica. Macchine Utensili E Impianti",
    "sg:phone":"+39 02 9573 8295",
    "sg:postcode":"20066",
    "sg:province":"Milano",
    "wof:name":"Infrarr S.n.c. Di Arrighi Stefano E C.",
    "wof:placetype":"venue"
},
  "geometry": {"coordinates":[9.431144,45.506783],"type":"Point"}
}