{
  "type": "Feature",
  "properties": {
    "iso:country":"IT",
    "sg:address":"70043 Monopoli",
    "sg:city":"Monopoli",
    "sg:orig_category":"Macchine, Impianti Ed Attrezzature Industria Chimica. Impiantistica E Prodotti Tecnologici Per Edilizia. Impianti, Attrezzature E Forniture Sanitarie Ed Ospedaliere",
    "sg:phone":"+39 080 930 3193",
    "sg:postcode":"70043",
    "sg:province":"Bari",
    "wof:name":"Muolo Giuseppe Termodraulica",
    "wof:placetype":"venue"
},
  "geometry": {"coordinates":[17.26664,40.90509],"type":"Point"}
}