{
  "type": "Feature",
  "properties": {
    "addr:full":"40121 Bologna Bologna Bologna 40121",
    "addr:postcode":"40121;40121",
    "iso:country":"IT",
    "sg:address":"40121 Bologna",
    "sg:city":"Bologna",
    "sg:classifiers":[
        {
            "category":"Banks & Credit Unions",
            "subcategory":"Bureau De Change",
            "type":"Services"
        }
    ],
    "sg:phone":"+39 051 238411",
    "sg:postcode":"40121",
    "sg:province":"Bologna",
    "sg:tags":[
        "services",
        "tourism",
        "public",
        "private",
        "transport"
    ],
    "sg:website":"http://www.bigtours.com",
    "wof:name":"Bigtours Travel Service Sas Di Leati Ippolito & C.",
    "wof:placetype":"venue"
},
  "geometry": {"coordinates":[11.342312,44.497116],"type":"Point"}
}