{
  "type": "Feature",
  "properties": {
    "addr:full":"21013 Gallarate Gallarate Varese 21013",
    "addr:postcode":"21013;21013",
    "iso:country":"IT",
    "sg:address":"21013 Gallarate",
    "sg:city":"Gallarate",
    "sg:orig_category":"Avvocati - Studi",
    "sg:phone":"+39 0331 798732",
    "sg:postcode":"21013",
    "sg:province":"Varese",
    "wof:name":"Jamicella Avv. Patrizia",
    "wof:placetype":"venue"
},
  "geometry": {"coordinates":[8.792933,45.763798],"type":"Point"}
}