{
  "type": "Feature",
  "properties": {
    "iso:country":"IT",
    "sg:address":"50041 Calenzano",
    "sg:city":"Calenzano",
    "sg:orig_category":"Nautica. Automobili E Mezzi Di Trasporto",
    "sg:phone":"+39 055 883 9733",
    "sg:postcode":"50041",
    "sg:province":"Firenze",
    "wof:name":"Da Que' Ragazzi Nautica E Trasporti Di Grappolini Andrea",
    "wof:placetype":"venue"
},
  "geometry": {"coordinates":[10.747925,43.67762],"type":"Point"}
}