{
  "type": "Feature",
  "properties": {
    "iso:country":"IT",
    "sg:address":"20090 Segrate",
    "sg:city":"Segrate",
    "sg:orig_category":"Scuole E Servizi Scolastici",
    "sg:phone":"+39 02 213 1018",
    "sg:postcode":"20090",
    "sg:province":"Milano",
    "wof:name":"Asilo Infantile Causa Pia D'adda",
    "wof:placetype":"venue"
},
  "geometry": {"coordinates":[9.295061,45.490131],"type":"Point"}
}