{
  "type": "Feature",
  "properties": {
    "iso:country":"IT",
    "sg:address":"Via F. Paolieri, 14/16 59100 Prato",
    "sg:city":"Prato",
    "sg:classifiers":[
        {
            "category":"Manufacturing",
            "subcategory":"Textiles",
            "type":"Manufacturing & Wholesale Goods"
        }
    ],
    "sg:phone":"+39 0574 462253",
    "sg:postcode":"59100",
    "sg:province":"Prato",
    "sg:tags":[
        "raw",
        "material"
    ],
    "sg:website":"www.squilloni.it",
    "wof:name":"Squilloni Lamberto S.r.l.",
    "wof:placetype":"venue"
},
  "geometry": {"coordinates":[11.112711,43.902069],"type":"Point"}
}