{
  "type": "Feature",
  "properties": {
    "iso:country":"IT",
    "sg:address":"81028 S. Maria A Vico",
    "sg:orig_category":"Elettrotecnica Industriale, Prodotti E Apparecchiature",
    "sg:phone":"+39 0823 805202",
    "sg:postcode":"81028",
    "sg:province":"Caserta",
    "wof:name":"Carfora Salvatore",
    "wof:placetype":"venue"
},
  "geometry": {"coordinates":[14.332194,41.075417],"type":"Point"}
}