{
  "type": "Feature",
  "properties": {
    "addr:full":"41037 Mirandola Mirandola Modena 41037",
    "addr:postcode":"41037;41037",
    "iso:country":"IT",
    "sg:address":"41037 Mirandola",
    "sg:city":"Mirandola",
    "sg:orig_category":"Banche Ed Istituti Di Credito E Risparmio",
    "sg:phone":"+39 0535 28511",
    "sg:postcode":"41037",
    "sg:province":"Modena",
    "sg:website":"http://www.crmirandola.it",
    "wof:name":"Cassa Di Risparmio Di Mirandola",
    "wof:placetype":"venue"
},
  "geometry": {"coordinates":[10.99534,44.890881],"type":"Point"}
}