{
  "type": "Feature",
  "properties": {
    "addr:full":"37129 Verona Verona Verona 37129",
    "addr:postcode":"37129;37129",
    "iso:country":"IT",
    "sg:address":"37129 Verona",
    "sg:city":"Verona",
    "sg:orig_category":"Macchine, Impianti E Forniture Per Industria Grafica, Cartaria E Cartotecnica",
    "sg:phone":"+39 045 800 6955",
    "sg:postcode":"37129",
    "sg:province":"Verona",
    "wof:name":"Zoccatelli Angelo",
    "wof:placetype":"venue"
},
  "geometry": {"coordinates":[11.009807,45.438995],"type":"Point"}
}