{
  "type": "Feature",
  "properties": {
    "iso:country":"IT",
    "sg:address":"Via Vittorio Veneto 248 32100 Belluno",
    "sg:city":"Belluno",
    "sg:classifiers":[
        {
            "category":"Travel",
            "subcategory":"Hotels & Motels",
            "type":"Entertainment"
        }
    ],
    "sg:phone":"+39 0437 31402",
    "sg:postcode":"32100",
    "sg:province":"Belluno",
    "sg:tags":[
        "equipment",
        "hotels",
        "restaurant"
    ],
    "wof:name":"Casagrande Cucine Srl",
    "wof:placetype":"venue"
},
  "geometry": {"coordinates":[12.230458,46.152523],"type":"Point"}
}