{
  "type": "Feature",
  "properties": {
    "addr:full":"49, Viale Lombardia 20056 Trezzo Sull'adda Milano 20056",
    "addr:housenumber":"49",
    "addr:postcode":"20056;20056",
    "addr:street":"Viale Lombardia",
    "iso:country":"IT",
    "sg:address":"49, Viale Lombardia 20056 Trezzo Sull'adda",
    "sg:classifiers":[
        {
            "category":"Wholesale",
            "subcategory":"Drugs",
            "type":"Manufacturing & Wholesale Goods"
        }
    ],
    "sg:phone":"+39 02 9096 3395",
    "sg:postcode":"20056",
    "sg:province":"Milano",
    "sg:tags":[
        "chemical",
        "pharmaceutical"
    ],
    "wof:name":"Officine R.p.c. (s.r.l.)",
    "wof:placetype":"venue"
},
  "geometry": {"coordinates":[9.540328,45.575859],"type":"Point"}
}