{
  "type": "Feature",
  "properties": {
    "addr:full":"16149 Genova Genova Genova 16149",
    "addr:postcode":"16149;16149",
    "iso:country":"IT",
    "sg:address":"16149 Genova",
    "sg:city":"Genova",
    "sg:orig_category":"Prodotti Chimici Secondari. Medicinali E Prodotti Parafarmaceutici",
    "sg:phone":"+39 010 645 9761",
    "sg:postcode":"16149",
    "sg:province":"Genova",
    "wof:name":"Nuova Galenica Srl",
    "wof:placetype":"venue"
},
  "geometry": {"coordinates":[8.890124321,44.4114189148],"type":"Point"}
}