{
  "type": "Feature",
  "properties": {
    "addr:full":"63020 Falerone Falerone Ascoli Piceno 63020",
    "addr:postcode":"63020;63020",
    "iso:country":"IT",
    "sg:address":"63020 Falerone",
    "sg:city":"Falerone",
    "sg:orig_category":"Prodotti Chimici Di Base",
    "sg:phone":"+39 0734 750121",
    "sg:postcode":"63020",
    "sg:province":"Ascoli Piceno",
    "wof:name":"Big Ben Di De Minicis Manolo",
    "wof:placetype":"venue"
},
  "geometry": {"coordinates":[13.5749769211,42.8554000854],"type":"Point"}
}