{
  "type": "Feature",
  "properties": {
    "iso:country":"IT",
    "sg:address":"20159 Milano",
    "sg:city":"Milano",
    "sg:orig_category":"Arredo Cucina Ed Elettrodomestici. Elettrodomestici. Apparecchi, Attrezzature E Forniture Per Centri Estetici",
    "sg:phone":"+39 02 2614 3958",
    "sg:postcode":"20159",
    "sg:province":"Milano",
    "wof:name":"Elcat Snc Di Murolo Felice & C.",
    "wof:placetype":"venue"
},
  "geometry": {"coordinates":[9.221061,45.493103],"type":"Point"}
}