{
  "type": "Feature",
  "properties": {
    "addr:full":"47, Via Villa Glori 41012 Carpi Carpi Modena 41012",
    "addr:postcode":"41012;41012",
    "addr:street":"Via Villa Glori",
    "iso:country":"IT",
    "sg:address":"47, Via Villa Glori 41012 Carpi",
    "sg:city":"Carpi",
    "sg:classifiers":[
        {
            "category":"Shopping",
            "subcategory":"Clothing, Apparel, & Fashions",
            "type":"Retail Goods"
        }
    ],
    "sg:phone":"+39 39059686617",
    "sg:postcode":"41012",
    "sg:province":"Modena",
    "sg:tags":[
        "clothes"
    ],
    "wof:name":"Confezioni Midal (s.n.c.)",
    "wof:placetype":"venue"
},
  "geometry": {"coordinates":[10.889363,44.792583],"type":"Point"}
}