{
  "type": "Feature",
  "properties": {
    "iso:country":"IT",
    "sg:address":"62012 Civitanova Marche",
    "sg:city":"Civitanova Marche",
    "sg:orig_category":"Giocattoli E Giochi - Produzione E Ingrosso",
    "sg:phone":"+39 0733 829523",
    "sg:postcode":"62012",
    "sg:province":"Macerata",
    "wof:name":"Digivar Srl",
    "wof:placetype":"venue"
},
  "geometry": {"coordinates":[13.70585,43.294441],"type":"Point"}
}