{
  "type": "Feature",
  "properties": {
    "addr:full":"Via Vandino 190 40050 Castello Di Serravalle Castello di Serravalle Bologna 40050",
    "addr:housenumber":"190",
    "addr:postcode":"40050;40050",
    "addr:street":"Via Vandino",
    "iso:country":"IT",
    "sg:address":"Via Vandino 190 40050 Castello Di Serravalle",
    "sg:city":"Castello di Serravalle",
    "sg:classifiers":[
        {
            "category":"Manufacturing",
            "subcategory":"Food",
            "type":"Manufacturing & Wholesale Goods"
        }
    ],
    "sg:phone":"+39 051 670 5017",
    "sg:postcode":"40050",
    "sg:province":"Bologna",
    "sg:tags":[
        "frozen"
    ],
    "wof:name":"Pizza Ignazio Sas",
    "wof:placetype":"venue"
},
  "geometry": {"coordinates":[11.0744848251,44.4425506592],"type":"Point"}
}