{
  "type": "Feature",
  "properties": {
    "addr:full":"17047 Vado Ligure Vado Ligure Savona 17047",
    "addr:postcode":"17047;17047",
    "iso:country":"IT",
    "sg:address":"17047 Vado Ligure",
    "sg:city":"Vado Ligure",
    "sg:orig_category":"Petroli, Gas E Combustibili",
    "sg:phone":"+39 019 886407",
    "sg:postcode":"17047",
    "sg:province":"Savona",
    "wof:name":"Raffineria Padana Olii Minerali Sarpom Spa",
    "wof:placetype":"venue"
},
  "geometry": {"coordinates":[8.4240760803,44.2621536255],"type":"Point"}
}