{
  "type": "Feature",
  "properties": {
    "addr:full":"Via Nazionale 16 45034 Canaro Canaro Rovigo 45034",
    "addr:housenumber":"16",
    "addr:postcode":"45034;45034",
    "addr:street":"Via Nazionale",
    "iso:country":"IT",
    "sg:address":"Via Nazionale 16 45034 Canaro",
    "sg:city":"Canaro",
    "sg:classifiers":[
        {
            "category":"Shopping",
            "subcategory":"Clothing, Apparel, & Fashions",
            "type":"Retail Goods"
        }
    ],
    "sg:phone":"+39 0425 940194",
    "sg:postcode":"45034",
    "sg:province":"Rovigo",
    "sg:tags":[
        "clothes"
    ],
    "wof:name":"Bergamini",
    "wof:placetype":"venue"
},
  "geometry": {"coordinates":[11.712875,44.930115],"type":"Point"}
}