{
  "type": "Feature",
  "properties": {
    "iso:country":"IT",
    "sg:address":"16036 Recco",
    "sg:city":"Recco",
    "sg:classifiers":[
        {
            "category":"Restaurant",
            "type":"Food & Drink"
        }
    ],
    "sg:phone":"+39 0185 74224",
    "sg:postcode":"16036",
    "sg:province":"Genova",
    "sg:tags":[
        "auxiliary",
        "entertainment",
        "premises",
        "related",
        "catering",
        "similar",
        "public",
        "restaurants"
    ],
    "wof:name":"La Nuova Giara Sas",
    "wof:placetype":"venue"
},
  "geometry": {"coordinates":[9.132174,44.362019],"type":"Point"}
}