{
  "type": "Feature",
  "properties": {
    "addr:full":"19, Via Cascina Bellaria 20151 Milano Milano Milano 20151",
    "addr:postcode":"20151;20151",
    "addr:street":"Via Cascina Bellaria",
    "iso:country":"IT",
    "sg:address":"19, Via Cascina Bellaria 20151 Milano",
    "sg:city":"Milano",
    "sg:classifiers":[
        {
            "category":"Sports & Exercise",
            "subcategory":"Playing Field",
            "type":"Entertainment"
        }
    ],
    "sg:phone":"+39 390 245 2861",
    "sg:postcode":"20151",
    "sg:province":"Milano",
    "sg:tags":[
        "game"
    ],
    "wof:name":"Harbour Club Milano S.r.l.",
    "wof:placetype":"venue"
},
  "geometry": {"coordinates":[8.39892,45.462345],"type":"Point"}
}