{
  "type": "Feature",
  "properties": {
    "addr:full":"16, Via Primo Maggio 40057 Granarolo Dell'emilia Bologna 40057",
    "addr:postcode":"40057;40057",
    "addr:street":"Via Primo Maggio",
    "iso:country":"IT",
    "sg:address":"16, Via Primo Maggio 40057 Granarolo Dell'emilia",
    "sg:classifiers":[
        {
            "category":"Home & Garden",
            "subcategory":"Home Furnishings",
            "type":"Retail Goods"
        }
    ],
    "sg:phone":"+39 39051768931",
    "sg:postcode":"40057",
    "sg:province":"Bologna",
    "sg:tags":[
        "household"
    ],
    "wof:name":"Valla S.r.l.",
    "wof:placetype":"venue"
},
  "geometry": {"coordinates":[11.413461,44.531219],"type":"Point"}
}