{
  "type": "Feature",
  "properties": {
    "iso:country":"IT",
    "sg:address":"17052 Borghetto S. Spirito",
    "sg:orig_category":"Sport - Articoli E Forniture",
    "sg:phone":"+39 0182 970137",
    "sg:postcode":"17052",
    "sg:province":"Savona",
    "wof:name":"Mobili Marino Sas",
    "wof:placetype":"venue"
},
  "geometry": {"coordinates":[8.468824,44.298294],"type":"Point"}
}