{
  "type": "Feature",
  "properties": {
    "iso:country":"IT",
    "sg:address":"V Le Michelangelo 73; Menfi; 92013",
    "sg:city":"Menfi",
    "sg:classifiers":[
        {
            "category":"Banks & Credit Unions",
            "subcategory":"Bank",
            "type":"Services"
        }
    ],
    "sg:phone":"+39 0925 75233",
    "sg:postcode":"92013",
    "sg:province":"Agrigento",
    "wof:name":"Credito Emiliano Spa",
    "wof:placetype":"venue"
},
  "geometry": {"coordinates":[12.966582,37.61982],"type":"Point"}
}