{
  "type": "Feature",
  "properties": {
    "addr:full":"90, Viale Dei Mille 50131 Firenze Firenze Firenze 50131",
    "addr:housenumber":"90",
    "addr:postcode":"50131;50131",
    "addr:street":"Viale Dei Mille",
    "iso:country":"IT",
    "sg:address":"90, Viale Dei Mille 50131 Firenze",
    "sg:city":"Firenze",
    "sg:classifiers":[
        {
            "category":"Home & Garden",
            "subcategory":"Home Furnishings",
            "type":"Retail Goods"
        }
    ],
    "sg:phone":"+39 39055571471",
    "sg:postcode":"50131",
    "sg:province":"Firenze",
    "sg:tags":[
        "household"
    ],
    "wof:name":"International Design S.r.l.",
    "wof:placetype":"venue"
},
  "geometry": {"coordinates":[11.274084,43.78352],"type":"Point"}
}