{
  "type": "Feature",
  "properties": {
    "addr:full":"22036 Erba Erba Como 22036",
    "addr:postcode":"22036;22036",
    "iso:country":"IT",
    "sg:address":"22036 Erba",
    "sg:city":"Erba",
    "sg:orig_category":"Forniture Per Attivita' Commerciali Ed Artigianali. Pubblicita', Marketing E Comunicazione",
    "sg:phone":"+39 031 333 8414",
    "sg:postcode":"22036",
    "sg:province":"Como",
    "sg:website":"http://www.e-ray.it",
    "wof:name":"E-ray Srl",
    "wof:placetype":"venue"
},
  "geometry": {"coordinates":[9.2175483704,45.8035736084],"type":"Point"}
}