{
  "type": "Feature",
  "properties": {
    "iso:country":"IT",
    "sg:address":"21040 Oggiona Con Santo Stefano",
    "sg:city":"Oggiona",
    "sg:orig_category":"Imballaggi In Legno",
    "sg:phone":"+39 0331 739233",
    "sg:postcode":"21040",
    "sg:province":"Varese",
    "wof:name":"Fratelli Pietrobon Srl",
    "wof:placetype":"venue"
},
  "geometry": {"coordinates":[8.817667,45.705334],"type":"Point"}
}