{
  "type": "Feature",
  "properties": {
    "addr:full":"82/e, V. Padova 35030 Tencarola Di Selvazzano D. Tencarola Padova 35030",
    "addr:housenumber":"82 / e",
    "addr:postcode":"35030;35030",
    "addr:street":"Padova",
    "iso:country":"IT",
    "sg:address":"82/e, V. Padova 35030 Tencarola Di Selvazzano D.",
    "sg:city":"Tencarola",
    "sg:classifiers":[
        {
            "category":"Shopping",
            "subcategory":"Clothing, Apparel, & Fashions",
            "type":"Retail Goods"
        }
    ],
    "sg:phone":"+39 049 868 5520",
    "sg:postcode":"35030",
    "sg:province":"Padova",
    "sg:tags":[
        "clothing",
        "accessory"
    ],
    "wof:name":"Zuin R.g.z.",
    "wof:placetype":"venue"
},
  "geometry": {"coordinates":[11.813714,45.392075],"type":"Point"}
}