{
  "type": "Feature",
  "properties": {
    "iso:country":"IT",
    "sg:address":"25064 Gussago",
    "sg:city":"Gussago",
    "sg:orig_category":"Servizi E Lavori Per Agricoltura E Zootecnia",
    "sg:phone":"+39 030 252 9037",
    "sg:postcode":"25064",
    "sg:province":"Brescia",
    "wof:name":"Faita Felice",
    "wof:placetype":"venue"
},
  "geometry": {"coordinates":[10.151283,45.590199],"type":"Point"}
}