{
  "type": "Feature",
  "properties": {
    "addr:full":"Via Petronio 8 34147 Muggia Trieste 34147",
    "addr:housenumber":"8",
    "addr:postcode":"34147;34147",
    "addr:street":"Via Petronio",
    "iso:country":"IT",
    "sg:address":"Via Petronio 8 34147 Muggia",
    "sg:classifiers":[
        {
            "category":"Autos & Motor Vehicles",
            "subcategory":"Boat Sales",
            "type":"Retail Goods"
        }
    ],
    "sg:phone":"+39 040 239 8204",
    "sg:postcode":"34147",
    "sg:province":"Trieste",
    "sg:tags":[
        "varnish"
    ],
    "sg:website":"www.jotun.com",
    "wof:name":"Jotun Italia Spa",
    "wof:placetype":"venue"
},
  "geometry": {"coordinates":[13.804165,45.593029],"type":"Point"}
}