{
  "type": "Feature",
  "properties": {
    "iso:country":"IT",
    "sg:address":"19, Via La Torre Pio 50018 Scandicci",
    "sg:city":"Scandicci",
    "sg:classifiers":[
        {
            "category":"Personal",
            "subcategory":"Shoe Repair & Shine",
            "type":"Services"
        }
    ],
    "sg:phone":"+39 055 731 0287",
    "sg:postcode":"50018",
    "sg:province":"Firenze",
    "sg:tags":[
        "leather"
    ],
    "wof:name":"Scheilan (s.r.l.)",
    "wof:placetype":"venue"
},
  "geometry": {"coordinates":[11.132482,43.772827],"type":"Point"}
}