{
  "type": "Feature",
  "properties": {
    "iso:country":"IT",
    "sg:address":"Via A. Spedalleri, 2; Bronte; 95034",
    "sg:city":"Bronte",
    "sg:classifiers":[
        {
            "category":"Banks & Credit Unions",
            "subcategory":"Bank",
            "type":"Services"
        }
    ],
    "sg:phone":"+39 095 691080",
    "sg:postcode":"95034",
    "sg:province":"Catania",
    "wof:name":"Banca Mutua Popolare, Di Bronte Fondata",
    "wof:placetype":"venue"
},
  "geometry": {"coordinates":[14.834052,37.787113],"type":"Point"}
}