{
  "type": "Feature",
  "properties": {
    "iso:country":"IT",
    "sg:address":"140, Via Tevere 52043 Castiglion Fiorentino",
    "sg:city":"Castiglion Fiorentino",
    "sg:classifiers":[
        {
            "category":"Manufacturing",
            "subcategory":"Metals",
            "type":"Manufacturing & Wholesale Goods"
        }
    ],
    "sg:phone":"+39 0575 680146",
    "sg:postcode":"52043",
    "sg:province":"Arezzo",
    "sg:tags":[
        "metallurgy",
        "metalworking"
    ],
    "wof:name":"Arcadia (s.r.l.)",
    "wof:placetype":"venue"
},
  "geometry": {"coordinates":[11.9017887115,43.3456344604],"type":"Point"}
}