{
  "type": "Feature",
  "properties": {
    "iso:country":"IT",
    "sg:address":"84010 Minori",
    "sg:city":"Minori",
    "sg:orig_category":"Prodotti Alimentari. Agricoltura, Orticoltura E Floricoltura",
    "sg:phone":"+39 089 877829",
    "sg:postcode":"84010",
    "sg:province":"Salerno",
    "wof:name":"Gema Agrumi Di Perrelli Antonietta",
    "wof:placetype":"venue"
},
  "geometry": {"coordinates":[14.7685127258,40.6761398315],"type":"Point"}
}