{
  "type": "Feature",
  "properties": {
    "iso:country":"IT",
    "sg:address":"21, Via Dell' Industria 31050 Vedelago",
    "sg:city":"Vedelago",
    "sg:classifiers":[
        {
            "category":"Professional",
            "subcategory":"Printing & Photocopies",
            "type":"Services"
        }
    ],
    "sg:phone":"+39 0423 401360",
    "sg:postcode":"31050",
    "sg:province":"Treviso",
    "wof:name":"Consult (s.r.l.)",
    "wof:placetype":"venue"
},
  "geometry": {"coordinates":[11.9955387115,45.6817626953],"type":"Point"}
}