{
  "type": "Feature",
  "properties": {
    "addr:full":"Corso Moncenisio 5 10090 Rosta Rosta Torino 10090",
    "addr:housenumber":"5",
    "addr:postcode":"10090;10090",
    "addr:street":"Corso Moncenisio",
    "iso:country":"IT",
    "sg:address":"Corso Moncenisio 5 10090 Rosta",
    "sg:city":"Rosta",
    "sg:classifiers":[
        {
            "category":"Communications",
            "subcategory":"Radio Station",
            "type":"Services"
        }
    ],
    "sg:phone":"+39 011 956 8555",
    "sg:postcode":"10090",
    "sg:province":"Torino",
    "sg:tags":[
        "signalling",
        "audio",
        "miscellaneous",
        "devices"
    ],
    "sg:website":"www.sirena.it",
    "wof:name":"Sirena Spa",
    "wof:placetype":"venue"
},
  "geometry": {"coordinates":[7.475327,45.02338],"type":"Point"}
}