{
  "type": "Feature",
  "properties": {
    "iso:country":"IT",
    "sg:address":"00187 Roma",
    "sg:city":"Roma",
    "sg:orig_category":"Servizi E Lavori Per Agricoltura E Zootecnia. Consulenze Tecniche, Amministrative E Perizie",
    "sg:phone":"+39 06 4274 3671",
    "sg:postcode":"00187",
    "sg:province":"Roma",
    "wof:name":"Agritecno Ind Srl",
    "wof:placetype":"venue"
},
  "geometry": {"coordinates":[12.496316,41.909149],"type":"Point"}
}