{
  "type": "Feature",
  "properties": {
    "iso:country":"IT",
    "sg:address":"80059 Torre Del Greco",
    "sg:city":"Torre del Greco",
    "sg:orig_category":"Servizi Ausiliari Di Analisi, Controllo E Ricerca. Acqua, Luce, Gas E Societa' Di Esercizio Pubblico",
    "sg:phone":"+39 081 847 3750",
    "sg:postcode":"80059",
    "sg:province":"Napoli",
    "wof:name":"Osservatorio Vesuviano",
    "wof:placetype":"venue"
},
  "geometry": {"coordinates":[14.411414,40.773205],"type":"Point"}
}