{
  "type": "Feature",
  "properties": {
    "addr:full":"Viale Campi, 25; S. Felice Sul Panaro; 41038 Modena 41038",
    "addr:housenumber":"25",
    "addr:postcode":"41038;41038",
    "addr:street":"Viale Campi;S. Felice Sul Panaro",
    "iso:country":"IT",
    "sg:address":"Viale Campi, 25; S. Felice Sul Panaro; 41038",
    "sg:classifiers":[
        {
            "category":"Banks & Credit Unions",
            "subcategory":"Bank",
            "type":"Services"
        }
    ],
    "sg:phone":"+39 0535 84120",
    "sg:postcode":"41038",
    "sg:province":"Modena",
    "wof:name":"Banca Agricola Mantovana",
    "wof:placetype":"venue"
},
  "geometry": {"coordinates":[11.140896,44.837994],"type":"Point"}
}