{
  "type": "Feature",
  "properties": {
    "iso:country":"IT",
    "sg:address":"80, Via Fosdondo 42015 Correggio",
    "sg:classifiers":[
        {
            "category":"Travel",
            "subcategory":"Travel Agent",
            "type":"Entertainment"
        }
    ],
    "sg:phone":"+39 0522 690276",
    "sg:postcode":"42015",
    "sg:province":"Reggio Nell'Emilia",
    "sg:tags":[
        "business"
    ],
    "wof:name":"Hotel Rose E Crown",
    "wof:placetype":"venue"
},
  "geometry": {"coordinates":[10.730037,44.77533],"type":"Point"}
}