{
  "type": "Feature",
  "properties": {
    "addr:full":"41 Viale Pietramellara Pietro, 40121 Bologna Bologna Bologna 40121",
    "addr:housenumber":"41",
    "addr:postcode":"40121;40121",
    "addr:street":"Viale Pietramellara Pietro",
    "iso:country":"IT",
    "sg:address":"41 Viale Pietramellara Pietro, 40121 Bologna",
    "sg:city":"Bologna",
    "sg:classifiers":[
        {
            "category":"Banks & Credit Unions",
            "subcategory":"Financial Services",
            "type":"Services"
        }
    ],
    "sg:phone":"+39 051 639 4711",
    "sg:postcode":"40121",
    "sg:province":"Bologna",
    "sg:tags":[
        "banking",
        "finance",
        "insurance"
    ],
    "wof:name":"Banca Unipol Banca (spa)",
    "wof:placetype":"venue"
},
  "geometry": {"coordinates":[11.3413763046,44.5056228638],"type":"Point"}
}