{
  "type": "Feature",
  "properties": {
    "iso:country":"IT",
    "sg:address":"20135 Milano",
    "sg:city":"Milano",
    "sg:orig_category":"Chiese Ed Associazioni Religiose",
    "sg:phone":"+39 02 546 0914",
    "sg:postcode":"20135",
    "sg:province":"Milano",
    "wof:name":"Asssociazione Micaela Onlus",
    "wof:placetype":"venue"
},
  "geometry": {"coordinates":[9.268146,45.475349],"type":"Point"}
}