{
  "type": "Feature",
  "properties": {
    "iso:country":"IT",
    "sg:address":"100, Via Castellana 31023 Resana",
    "sg:city":"Resana",
    "sg:classifiers":[
        {
            "category":"Shopping",
            "subcategory":"Clothing, Apparel, & Fashions",
            "type":"Retail Goods"
        }
    ],
    "sg:phone":"+39 0423 480698",
    "sg:postcode":"31023",
    "sg:province":"Treviso",
    "sg:tags":[
        "clothes"
    ],
    "wof:name":"Tentazioni Di Bertolo Gabriella & C. S.n.c.",
    "wof:placetype":"venue"
},
  "geometry": {"coordinates":[12.09551,45.655888],"type":"Point"}
}