{
  "type": "Feature",
  "properties": {
    "addr:full":"3/5, V. Camicie Rosse 20090 Opera Opera Milano 20090",
    "addr:housenumber":"3 / 5 v. camicie",
    "addr:postcode":"20090;20090",
    "addr:street":"Rosse",
    "iso:country":"IT",
    "sg:address":"3/5, V. Camicie Rosse 20090 Opera",
    "sg:city":"Opera",
    "sg:classifiers":[
        {
            "category":"Shopping",
            "type":"Retail Goods"
        }
    ],
    "sg:phone":"+39 39025300981",
    "sg:postcode":"20090",
    "sg:province":"Milano",
    "sg:tags":[
        "finished",
        "-",
        "metallic"
    ],
    "sg:website":"http://www.ottoeconovanta.it",
    "wof:name":"Ottoeco90",
    "wof:placetype":"venue"
},
  "geometry": {"coordinates":[9.2086000443,45.3729667664],"type":"Point"}
}