{
  "type": "Feature",
  "properties": {
    "iso:country":"IT",
    "sg:address":"Via Squartabue 62019 Recanati",
    "sg:city":"Recanati",
    "sg:classifiers":[
        {
            "category":"Manufacturing",
            "subcategory":"Glass & Minerals",
            "type":"Manufacturing & Wholesale Goods"
        }
    ],
    "sg:phone":"+39 071 750 5042",
    "sg:postcode":"62019",
    "sg:province":"Macerata",
    "wof:name":"Morici & Marconi (s.n.c.)",
    "wof:placetype":"venue"
},
  "geometry": {"coordinates":[13.456262,43.300747],"type":"Point"}
}