{
  "type": "Feature",
  "properties": {
    "addr:full":"Villaggio Paradiso; Sessa Aurunca",
    "addr:street":"Villaggio",
    "iso:country":"IT",
    "sg:address":"Villaggio Paradiso; Sessa Aurunca",
    "sg:classifiers":[
        {
            "category":"Banks & Credit Unions",
            "subcategory":"Bank",
            "type":"Services"
        }
    ],
    "sg:phone":"+39 0823 930154",
    "wof:name":"Banca Di Roma",
    "wof:placetype":"venue"
},
  "geometry": {"coordinates":[13.933759,41.24189],"type":"Point"}
}