{
  "type": "Feature",
  "properties": {
    "addr:full":"Via Principessa Margherita; Stresa; 28049",
    "addr:postcode":"28049",
    "addr:street":"Via Principessa Margherita Stresa",
    "iso:country":"IT",
    "sg:address":"Via Principessa Margherita; Stresa; 28049",
    "sg:classifiers":[
        {
            "category":"Banks & Credit Unions",
            "subcategory":"Bank",
            "type":"Services"
        }
    ],
    "sg:phone":"+39 0323 33142",
    "wof:name":"Istituto Bancario, San Paolo Di Torino Spa",
    "wof:placetype":"venue"
},
  "geometry": {"coordinates":[8.53866,45.884052],"type":"Point"}
}