{
  "type": "Feature",
  "properties": {
    "iso:country":"IT",
    "sg:address":"Viale Stazione, 3/15 88811 Ciro' Marina",
    "sg:classifiers":[
        {
            "category":"Food & Beverages",
            "subcategory":"Liquor & Beverages",
            "type":"Retail Goods"
        }
    ],
    "sg:phone":"+39 0962 31279",
    "sg:postcode":"88811",
    "sg:province":"Crotone",
    "sg:tags":[
        "liqueur"
    ],
    "wof:name":"L'enologica Liotti Srl",
    "wof:placetype":"venue"
},
  "geometry": {"coordinates":[17.115412,39.368076],"type":"Point"}
}