{
  "type": "Feature",
  "properties": {
    "iso:country":"IT",
    "sg:address":"Viale F. Crispi 123 36100 Vicenza",
    "sg:city":"Vicenza",
    "sg:classifiers":[
        {
            "category":"Manufacturing",
            "subcategory":"Tools & Machinery",
            "type":"Manufacturing & Wholesale Goods"
        }
    ],
    "sg:phone":"+39 0444 385000",
    "sg:postcode":"36100",
    "sg:province":"Vicenza",
    "sg:tags":[
        "electric"
    ],
    "sg:website":"www.fiamairtools.com",
    "wof:name":"Fiam Utensili Pneumatici Spa",
    "wof:placetype":"venue"
},
  "geometry": {"coordinates":[11.526389,45.575279],"type":"Point"}
}