{
  "type": "Feature",
  "properties": {
    "addr:full":"Via Riviera Matteotti 12 30034 Mira Mira Venezia 30034",
    "addr:housenumber":"12",
    "addr:postcode":"30034;30034",
    "addr:street":"Via Riviera Matteotti",
    "iso:country":"IT",
    "sg:address":"Via Riviera Matteotti 12 30034 Mira",
    "sg:city":"Mira",
    "sg:classifiers":[
        {
            "category":"Home & Garden",
            "subcategory":"Building Materials",
            "type":"Retail Goods"
        }
    ],
    "sg:phone":"+39 041 560 0353",
    "sg:postcode":"30034",
    "sg:province":"Venezia",
    "sg:tags":[
        "cleaning",
        "agent",
        "plastic"
    ],
    "wof:name":"Zeolite Mira Srl",
    "wof:placetype":"venue"
},
  "geometry": {"coordinates":[12.338784,45.434338],"type":"Point"}
}