{
  "type": "Feature",
  "properties": {
    "iso:country":"IT",
    "sg:address":"139, Via Provinciale 23811 Ballabio",
    "sg:city":"Ballabio",
    "sg:classifiers":[
        {
            "category":"Food & Beverages",
            "subcategory":"Dairy",
            "type":"Retail Goods"
        }
    ],
    "sg:phone":"+39 0341 530440",
    "sg:postcode":"23811",
    "sg:province":"Lecco",
    "sg:tags":[
        "product"
    ],
    "wof:name":"Acquistapace (s.p.a.)",
    "wof:placetype":"venue"
},
  "geometry": {"coordinates":[9.428225,45.90419],"type":"Point"}
}