{
  "type": "Feature",
  "properties": {
    "addr:full":"00126 Roma Roma Roma 00126",
    "addr:postcode":"00126;00126",
    "iso:country":"IT",
    "sg:address":"00126 Roma",
    "sg:city":"Roma",
    "sg:orig_category":"Elettrodomestici - Riparazione E Vendita Al Dettaglio Di Accessori",
    "sg:phone":"+39 06 8632 8008",
    "sg:postcode":"00126",
    "sg:province":"Roma",
    "wof:name":"A.b.a.",
    "wof:placetype":"venue"
},
  "geometry": {"coordinates":[12.668575,41.790123],"type":"Point"}
}