{
  "type": "Feature",
  "properties": {
    "iso:country":"IT",
    "sg:address":"60035 Jesi",
    "sg:city":"Jesi",
    "sg:orig_category":"Abbigliamento Esterno, Maglierie E Pelliccerie",
    "sg:phone":"+39 0731 58630",
    "sg:postcode":"60035",
    "sg:province":"Ancona",
    "wof:name":"Esiconf Snc",
    "wof:placetype":"venue"
},
  "geometry": {"coordinates":[13.2583780289,43.5282554626],"type":"Point"}
}