{
  "type": "Feature",
  "properties": {
    "addr:full":"20019 Settimo Milanese Settimo Milanese Milano 20019",
    "addr:postcode":"20019;20019",
    "iso:country":"IT",
    "sg:address":"20019 Settimo Milanese",
    "sg:city":"Settimo Milanese",
    "sg:orig_category":"Prodotti Chimici Di Base",
    "sg:phone":"+39 02 328 7425",
    "sg:postcode":"20019",
    "sg:province":"Milano",
    "wof:name":"Biemme Sas Di Andrea Paulotto & C.",
    "wof:placetype":"venue"
},
  "geometry": {"coordinates":[9.0613098145,45.4646492004],"type":"Point"}
}