{
  "type": "Feature",
  "properties": {
    "iso:country":"IT",
    "sg:address":"27100 Pavia",
    "sg:city":"Pavia",
    "sg:classifiers":[
        {
            "category":"Bars & Pubs",
            "subcategory":"Champagne Bar",
            "type":"Food & Drink"
        }
    ],
    "sg:phone":"+39 0382 28216",
    "sg:postcode":"27100",
    "sg:province":"Pavia",
    "sg:tags":[
        "caffe'",
        "e"
    ],
    "wof:name":"Diablo Saloon Di Ardire Mario & C. Snc",
    "wof:placetype":"venue"
},
  "geometry": {"coordinates":[9.157935,45.204906],"type":"Point"}
}