{
  "type": "Feature",
  "properties": {
    "iso:country":"IT",
    "sg:address":"17, Via Marucello 59013 Montemurlo",
    "sg:city":"Montemurlo",
    "sg:classifiers":[
        {
            "category":"Shopping",
            "subcategory":"Crafts & Fabrics",
            "type":"Retail Goods"
        }
    ],
    "sg:phone":"+39 0574 686837",
    "sg:postcode":"59013",
    "sg:province":"Prato",
    "wof:name":"Bugetti Filati Srl",
    "wof:placetype":"venue"
},
  "geometry": {"coordinates":[11.0326185226,43.9205932617],"type":"Point"}
}