{
  "type": "Feature",
  "properties": {
    "addr:full":"13, Via Stendhal Henri Beyle 40128 Bologna Bologna Bologna 40128",
    "addr:postcode":"40128;40128",
    "addr:street":"Via Stendhal Henri Beyle",
    "iso:country":"IT",
    "sg:address":"13, Via Stendhal Henri Beyle 40128 Bologna",
    "sg:city":"Bologna",
    "sg:classifiers":[
        {
            "category":"Professional",
            "subcategory":"Engineering",
            "type":"Services"
        }
    ],
    "sg:phone":"+39 39051328490",
    "sg:postcode":"40128",
    "sg:province":"Bologna",
    "sg:tags":[
        "machine",
        "-",
        "mechanical"
    ],
    "wof:name":"D.a.i.n.o. (s.r.l.)",
    "wof:placetype":"venue"
},
  "geometry": {"coordinates":[11.3464813232,44.4942207336],"type":"Point"}
}