{
  "type": "Feature",
  "properties": {
    "iso:country":"IT",
    "sg:address":"10071 Borgaro Torinese",
    "sg:city":"Borgaro Torinese",
    "sg:orig_category":"Trattamenti Termici E Superficiali Metalli, Galvanotecnica",
    "sg:phone":"+39 011 262 4358",
    "sg:postcode":"10071",
    "sg:province":"Torino",
    "wof:name":"Novazinc",
    "wof:placetype":"venue"
},
  "geometry": {"coordinates":[7.677107,45.147526],"type":"Point"}
}