{
  "type": "Feature",
  "properties": {
    "addr:full":"Via Tononi 2; Pacenza; 29100 Piacenza 29100",
    "addr:housenumber":"2",
    "addr:postcode":"29100;29100",
    "addr:street":"Via Tononi",
    "iso:country":"IT",
    "sg:address":"Via Tononi 2; Pacenza; 29100",
    "sg:classifiers":[
        {
            "category":"Banks & Credit Unions",
            "subcategory":"Bank",
            "type":"Services"
        }
    ],
    "sg:phone":"+39 0523 452080",
    "sg:postcode":"29100",
    "sg:province":"Piacenza",
    "wof:name":"Banca Agricola Mantovana Scarl",
    "wof:placetype":"venue"
},
  "geometry": {"coordinates":[9.687273,45.045757],"type":"Point"}
}