{
  "type": "Feature",
  "properties": {
    "iso:country":"IT",
    "sg:address":"10146 Torino",
    "sg:city":"Torino",
    "sg:orig_category":"Adesivi",
    "sg:phone":"+39 011 779 5878",
    "sg:postcode":"10146",
    "sg:province":"Torino",
    "wof:name":"Hot Machines Srl",
    "wof:placetype":"venue"
},
  "geometry": {"coordinates":[7.619677,45.08036],"type":"Point"}
}