{
  "type": "Feature",
  "properties": {
    "iso:country":"IT",
    "sg:address":"74014 Laterza",
    "sg:city":"Laterza",
    "sg:classifiers":[
        {
            "category":"Professional",
            "subcategory":"Advertising",
            "type":"Services"
        }
    ],
    "sg:phone":"+39 099 821 6203",
    "sg:postcode":"74014",
    "sg:province":"Taranto",
    "sg:tags":[
        "marketing",
        "communication"
    ],
    "wof:name":"La Serigrafica",
    "wof:placetype":"venue"
},
  "geometry": {"coordinates":[16.794241,40.661709],"type":"Point"}
}