{
  "type": "Feature",
  "properties": {
    "iso:country":"IT",
    "sg:address":"25080 Prevalle",
    "sg:city":"Prevalle",
    "sg:orig_category":"Legno E Semilavorati. Articoli Per Imballaggio E Confezionamento",
    "sg:phone":"+39 030 680 1541",
    "sg:postcode":"25080",
    "sg:province":"Brescia",
    "wof:name":"Garda Legno Di Caravaggi U. & C. Snc",
    "wof:placetype":"venue"
},
  "geometry": {"coordinates":[10.562986,45.560436],"type":"Point"}
}