{
  "type": "Feature",
  "properties": {
    "iso:country":"IT",
    "sg:address":"80027 Frattamaggiore",
    "sg:city":"Frattamaggiore",
    "sg:orig_category":"Macchine, Impianti Ed Attrezzature Per Agricoltura E Zootecnia",
    "sg:phone":"+39 081 834 5563",
    "sg:postcode":"80027",
    "sg:province":"Napoli",
    "wof:name":"Damiani Massimo",
    "wof:placetype":"venue"
},
  "geometry": {"coordinates":[14.268698,40.940437],"type":"Point"}
}