{
  "type": "Feature",
  "properties": {
    "iso:country":"IT",
    "sg:address":"35048 Stanghella",
    "sg:city":"Stanghella",
    "sg:orig_category":"Servizi E Lavori Per Edilizia E Lavori Pubblici. Servizi Ausiliari Di Sorveglianza, Manutenzione E Pulizia",
    "sg:phone":"+39 0425 456039",
    "sg:postcode":"35048",
    "sg:province":"Padova",
    "wof:name":"Rubello Lino",
    "wof:placetype":"venue"
},
  "geometry": {"coordinates":[11.757218,45.13406],"type":"Point"}
}