{
  "type": "Feature",
  "properties": {
    "iso:country":"IT",
    "sg:address":"20016 Pero",
    "sg:city":"Pero",
    "sg:orig_category":"Cartotecnica E Servizi. Prodotti E Manufatti In Materie Plastiche. Articoli Per Imballaggio E Confezionamento",
    "sg:phone":"+39 02 353 8197",
    "sg:postcode":"20016",
    "sg:province":"Milano",
    "wof:name":"Il Contenitore Snc",
    "wof:placetype":"venue"
},
  "geometry": {"coordinates":[9.075945,45.503326],"type":"Point"}
}