{
  "type": "Feature",
  "properties": {
    "iso:country":"IT",
    "sg:address":"42011 Bagnolo In Piano",
    "sg:orig_category":"Materiali Semilavorati Metallici",
    "sg:phone":"+39 0522 953519",
    "sg:postcode":"42011",
    "sg:province":"Reggio Nell'Emilia",
    "wof:name":"D.d.m. Di Davoli Corrado & C. (s.a.s.)",
    "wof:placetype":"venue"
},
  "geometry": {"coordinates":[10.673757,44.756912],"type":"Point"}
}