{
  "type": "Feature",
  "properties": {
    "iso:country":"IT",
    "sg:address":"22020 Gironico",
    "sg:city":"Gironico",
    "sg:orig_category":"Servizi E Lavori Per Abbigliamento E Pelletterie",
    "sg:phone":"+39 031 441269",
    "sg:postcode":"22020",
    "sg:province":"Como",
    "wof:name":"Bollini Adriano",
    "wof:placetype":"venue"
},
  "geometry": {"coordinates":[9.003304,45.801155],"type":"Point"}
}