{
  "type": "Feature",
  "properties": {
    "iso:country":"IT",
    "sg:address":"Via Barletta 303 70031 Andria",
    "sg:city":"Andria",
    "sg:classifiers":[
        {
            "category":"Shopping",
            "subcategory":"Clothing, Apparel, & Fashions",
            "type":"Retail Goods"
        }
    ],
    "sg:phone":"+39 0883 553665",
    "sg:postcode":"70031",
    "sg:province":"Bari",
    "sg:tags":[
        "blouse",
        "ladies'",
        "dress"
    ],
    "wof:name":"Paparusso Giuseppe",
    "wof:placetype":"venue"
},
  "geometry": {"coordinates":[16.294245,41.240414],"type":"Point"}
}