{
  "type": "Feature",
  "properties": {
    "iso:country":"IT",
    "sg:address":"51037 Montale",
    "sg:city":"Montale",
    "sg:orig_category":"Tessuti E Stoffe. Tessuti Arredamento, Tende E Tappeti",
    "sg:phone":"+39 0573 557701",
    "sg:postcode":"51037",
    "sg:province":"Pistoia",
    "sg:website":"http://www.pugirg.it",
    "wof:name":"Pugi R.g.",
    "wof:placetype":"venue"
},
  "geometry": {"coordinates":[11.01412,43.919815],"type":"Point"}
}