{
  "type": "Feature",
  "properties": {
    "addr:full":"34/a, V. Monte Cengio 10135 Torino Torino Torino 10135",
    "addr:housenumber":"34 / a",
    "addr:postcode":"10135;10135",
    "addr:street":"V. Monte Cengio",
    "iso:country":"IT",
    "sg:address":"34/a, V. Monte Cengio 10135 Torino",
    "sg:city":"Torino",
    "sg:classifiers":[
        {
            "category":"Shopping",
            "type":"Retail Goods"
        }
    ],
    "sg:phone":"+39 011 397 8690",
    "sg:postcode":"10135",
    "sg:province":"Torino",
    "sg:tags":[
        "finished",
        "-",
        "metallic"
    ],
    "sg:website":"http://www.paginegialle.it/ve-ga",
    "wof:name":"Ve-ga Sas Di Verzotti Evo & C.",
    "wof:placetype":"venue"
},
  "geometry": {"coordinates":[7.6223735809,45.0191574097],"type":"Point"}
}