{
  "type": "Feature",
  "properties": {
    "iso:country":"IT",
    "sg:address":"Via Piangipane, 151/a; Piangipane; 48020",
    "sg:classifiers":[
        {
            "category":"Banks & Credit Unions",
            "subcategory":"Bank",
            "type":"Services"
        }
    ],
    "sg:phone":"+39 0544 418731",
    "sg:postcode":"48020",
    "sg:province":"Ravenna",
    "wof:name":"Rolo Banca 1473 Spa",
    "wof:placetype":"venue"
},
  "geometry": {"coordinates":[12.093173,44.423393],"type":"Point"}
}