{
  "type": "Feature",
  "properties": {
    "iso:country":"IT",
    "sg:address":"Via San Rocco 10 82016 Montesarchio",
    "sg:city":"Montesarchio",
    "sg:classifiers":[
        {
            "category":"Food & Beverages",
            "subcategory":"Specialty",
            "type":"Retail Goods"
        }
    ],
    "sg:phone":"+39 0824 894141",
    "sg:postcode":"82016",
    "sg:province":"Benevento",
    "sg:tags":[
        "olive-oil"
    ],
    "wof:name":"Industria Olearia Biagio Mataluni Srl",
    "wof:placetype":"venue"
},
  "geometry": {"coordinates":[14.636896,41.06501],"type":"Point"}
}