{
  "type": "Feature",
  "properties": {
    "addr:full":"35037 San Biagio San Biagio Padova 35037",
    "addr:postcode":"35037;biagio;35037",
    "addr:street":"San",
    "iso:country":"IT",
    "sg:address":"35037 San Biagio",
    "sg:city":"San Biagio",
    "sg:orig_category":"Elettrotecnica Professionale E Di Consumo. Forniture Alle Strutture Ricettive. Arredi Ed Attrezzature Per Attivita' Commerciali Ed Artigianali",
    "sg:phone":"+39 049 990 3113",
    "sg:postcode":"35037",
    "sg:province":"Padova",
    "wof:name":"Foga Servizi Sas Di Fogarin Denis E C.",
    "wof:placetype":"venue"
},
  "geometry": {"coordinates":[11.737143,45.374195],"type":"Point"}
}