{
  "type": "Feature",
  "properties": {
    "addr:full":"04011 Aprilia Aprilia Latina 04011",
    "addr:postcode":"04011;04011",
    "iso:country":"IT",
    "sg:address":"04011 Aprilia",
    "sg:city":"Aprilia",
    "sg:orig_category":"Forniture Per Abbigliamento E Pelletterie. Forniture E Materiali Per Imballaggio E Confezionamento",
    "sg:phone":"+39 06 9270 8020",
    "sg:postcode":"04011",
    "sg:province":"Latina",
    "wof:name":"Toner Line Di P. Vitiello",
    "wof:placetype":"venue"
},
  "geometry": {"coordinates":[12.6492366791,41.5967483521],"type":"Point"}
}