{
  "type": "Feature",
  "properties": {
    "iso:country":"IT",
    "sg:address":"94, Via Cuneo 12045 Fossano",
    "sg:city":"Fossano",
    "sg:classifiers":[
        {
            "category":"Manufacturing",
            "subcategory":"Lumber",
            "type":"Manufacturing & Wholesale Goods"
        }
    ],
    "sg:phone":"+39 0172 633220",
    "sg:postcode":"12045",
    "sg:province":"Cuneo",
    "sg:tags":[
        "wood"
    ],
    "wof:name":"Chiappella Fratelli",
    "wof:placetype":"venue"
},
  "geometry": {"coordinates":[7.637076,44.442184],"type":"Point"}
}