{
  "type": "Feature",
  "properties": {
    "iso:country":"IT",
    "sg:address":"Via Cividale 33 33044 Manzano",
    "sg:city":"Manzano",
    "sg:classifiers":[
        {
            "category":"Wholesale",
            "subcategory":"Home Furnishings",
            "type":"Manufacturing & Wholesale Goods"
        }
    ],
    "sg:phone":"+39 0432 750055",
    "sg:postcode":"33044",
    "sg:province":"Udine",
    "sg:tags":[
        "chair"
    ],
    "sg:website":"www.repass.it",
    "wof:name":"Repass Snc",
    "wof:placetype":"venue"
},
  "geometry": {"coordinates":[13.390733,45.996265],"type":"Point"}
}