{
  "type": "Feature",
  "properties": {
    "iso:country":"IT",
    "sg:address":"00192 Roma",
    "sg:city":"Roma",
    "sg:orig_category":"Scuole E Servizi Scolastici. Servizi Per Lo Sport E Il Tempo Libero",
    "sg:phone":"+39 06 3972 3259",
    "sg:postcode":"00192",
    "sg:province":"Roma",
    "wof:name":"Gruppo Strumentale Musica D'oggi",
    "wof:placetype":"venue"
},
  "geometry": {"coordinates":[12.459567,41.908146],"type":"Point"}
}