{
  "type": "Feature",
  "properties": {
    "addr:full":"113, Via Lucrezia Romana 00043 Ciampino Ciampino Roma 00043",
    "addr:housenumber":"113",
    "addr:postcode":"00043;roma 00043",
    "addr:street":"Via Lucrezia Romana",
    "iso:country":"IT",
    "sg:address":"113, Via Lucrezia Romana 00043 Ciampino",
    "sg:city":"Ciampino",
    "sg:classifiers":[
        {
            "category":"Communications",
            "subcategory":"Newspaper",
            "type":"Services"
        }
    ],
    "sg:phone":"+39 06 7932 0142",
    "sg:postcode":"00043",
    "sg:province":"Roma",
    "sg:tags":[
        "advertising"
    ],
    "wof:name":"Comaf Srl",
    "wof:placetype":"venue"
},
  "geometry": {"coordinates":[12.586567,41.821484],"type":"Point"}
}