{
  "type": "Feature",
  "properties": {
    "addr:full":"00153 Roma Roma Roma 00153",
    "addr:postcode":"00153;00153",
    "iso:country":"IT",
    "sg:address":"00153 Roma",
    "sg:city":"Roma",
    "sg:orig_category":"Chiese Ed Associazioni Religiose",
    "sg:phone":"+39 06 589 9011",
    "sg:postcode":"00153",
    "sg:province":"Roma",
    "wof:name":"Suore Ausiliatrici",
    "wof:placetype":"venue"
},
  "geometry": {"coordinates":[12.4657011032,41.8759078979],"type":"Point"}
}