{
  "type": "Feature",
  "properties": {
    "iso:country":"IT",
    "sg:address":"19020 Vezzano Ligure",
    "sg:city":"Fornola",
    "sg:orig_category":"Manufacturers: Prefabbricati",
    "sg:phone":"+39 0187 997518",
    "sg:postcode":"19020",
    "sg:province":"La Spezia",
    "sg:website":"http://www.sogespe.it",
    "wof:name":"So.ge.spe Srl",
    "wof:placetype":"venue"
},
  "geometry": {"coordinates":[9.899832,44.135754],"type":"Point"}
}