{
  "type": "Feature",
  "properties": {
    "iso:country":"IT",
    "sg:address":"03012 Anagni",
    "sg:city":"Anagni",
    "sg:orig_category":"Tempo Libero - Articoli E Forniture. Regalistica Aziendale",
    "sg:phone":"+39 0775 744269",
    "sg:postcode":"03012",
    "sg:province":"Frosinone",
    "wof:name":"Gismondi Valerio",
    "wof:placetype":"venue"
},
  "geometry": {"coordinates":[13.057877,41.806011],"type":"Point"}
}