{
  "type": "Feature",
  "properties": {
    "addr:full":"08100 Nuoro Nuoro Nuoro 08100",
    "addr:postcode":"08100;08100",
    "iso:country":"IT",
    "sg:address":"08100 Nuoro",
    "sg:city":"Nuoro",
    "sg:orig_category":"Petroli, Gas E Combustibili. Termotecnica E Riscaldamento, Apparecchiature E Servizi",
    "sg:phone":"+39 0784 34223",
    "sg:postcode":"08100",
    "sg:province":"Nuoro",
    "wof:name":"Co.p.p.e.a. Srl",
    "wof:placetype":"venue"
},
  "geometry": {"coordinates":[9.3270721436,40.3225250244],"type":"Point"}
}