{
  "type": "Feature",
  "properties": {
    "addr:full":"16129 Genova Genova Genova 16129",
    "addr:postcode":"16129;16129",
    "iso:country":"IT",
    "sg:address":"16129 Genova",
    "sg:city":"Genova",
    "sg:orig_category":"Impianti Elettrici Industriali E Civili - Produzione",
    "sg:phone":"+39 010 564485",
    "sg:postcode":"16129",
    "sg:province":"Genova",
    "wof:name":"I.t.i. Di Bardi Riccardo & C. Snc",
    "wof:placetype":"venue"
},
  "geometry": {"coordinates":[8.950957,44.399639],"type":"Point"}
}