{
  "type": "Feature",
  "properties": {
    "iso:country":"IT",
    "sg:address":"Via Caravaggi 24040 Levate",
    "sg:city":"Levate",
    "sg:classifiers":[
        {
            "category":"Autos & Motor Vehicles",
            "subcategory":"Automobile Sales",
            "type":"Retail Goods"
        }
    ],
    "sg:phone":"+39 035 455 8411",
    "sg:postcode":"24040",
    "sg:province":"Bergamo",
    "sg:tags":[
        "industrial"
    ],
    "wof:name":"Bradi Spa",
    "wof:placetype":"venue"
},
  "geometry": {"coordinates":[9.632586,45.620045],"type":"Point"}
}