{
  "type": "Feature",
  "properties": {
    "iso:country":"IT",
    "sg:address":"20141 Milano",
    "sg:city":"Milano",
    "sg:orig_category":"Servizi E Lavori Per Industria Alimentare E Bevande",
    "sg:phone":"+39 02 846 5822",
    "sg:postcode":"20141",
    "sg:province":"Milano",
    "wof:name":"Cooperativa Operaia Di Consumo Morivione",
    "wof:placetype":"venue"
},
  "geometry": {"coordinates":[9.188296,45.442318],"type":"Point"}
}