{
  "type": "Feature",
  "properties": {
    "addr:full":"12, Via Sauro Nazario 23826 Mandello Del Lario Mandello del Lario Lecco 23826",
    "addr:postcode":"23826;23826",
    "addr:street":"Via Sauro Nazario",
    "iso:country":"IT",
    "sg:address":"12, Via Sauro Nazario 23826 Mandello Del Lario",
    "sg:city":"Mandello del Lario",
    "sg:classifiers":[
        {
            "category":"Professional",
            "subcategory":"Engineering",
            "type":"Services"
        }
    ],
    "sg:phone":"+39 0341 731455",
    "sg:postcode":"23826",
    "sg:province":"Lecco",
    "sg:tags":[
        "machine",
        "-",
        "mechanical"
    ],
    "wof:name":"Meccanica Lafranconi S.r.l.",
    "wof:placetype":"venue"
},
  "geometry": {"coordinates":[9.341783,45.826405],"type":"Point"}
}