{
  "type": "Feature",
  "properties": {
    "iso:country":"IT",
    "sg:address":"22063 Cant\u00f9",
    "sg:orig_category":"Distributors: Automatici - Commercio E Gestione",
    "sg:phone":"+39 031 707 3320",
    "sg:postcode":"22063",
    "sg:province":"Como",
    "wof:name":"Caff\u00c8 Point Di Balsamo Marco",
    "wof:placetype":"venue"
},
  "geometry": {"coordinates":[9.122788,45.744835],"type":"Point"}
}