{
  "type": "Feature",
  "properties": {
    "iso:country":"IT",
    "sg:address":"20019 Settimo Milanese",
    "sg:city":"Settimo Milanese",
    "sg:orig_category":"Ecologia - Studi Consulenza E Servizi",
    "sg:phone":"+39 02 3351 2080",
    "sg:postcode":"20019",
    "sg:province":"Milano",
    "sg:website":"http://www.setsrl.com",
    "wof:name":"Set Subsoil Environment Technologies Srl",
    "wof:placetype":"venue"
},
  "geometry": {"coordinates":[9.07097,45.470154],"type":"Point"}
}