{
  "type": "Feature",
  "properties": {
    "addr:full":"16121 Genova Genova Genova 16121",
    "addr:postcode":"16121;16121",
    "iso:country":"IT",
    "sg:address":"16121 Genova",
    "sg:city":"Genova",
    "sg:orig_category":"Calzature, Pelletterie E Pelli",
    "sg:phone":"+39 010 591703",
    "sg:postcode":"16121",
    "sg:province":"Genova",
    "sg:website":"http://www.geit.it",
    "wof:name":"Geit Di A. Ginocchio & C. Sas",
    "wof:placetype":"venue"
},
  "geometry": {"coordinates":[8.939713,44.405628],"type":"Point"}
}