{
  "type": "Feature",
  "properties": {
    "iso:country":"IT",
    "sg:address":"20147 Milano",
    "sg:city":"Milano",
    "sg:orig_category":"Studi E Consulenze Amministrative, Commerciali E Aziendali. Consulenze Tecniche, Amministrative E Perizie",
    "sg:phone":"+39 02 4870 5765",
    "sg:postcode":"20147",
    "sg:province":"Milano",
    "sg:website":"http://www.studiobeltrami.it",
    "wof:name":"Studio Beltrami Srl",
    "wof:placetype":"venue"
},
  "geometry": {"coordinates":[9.125888,45.424442],"type":"Point"}
}