{
  "type": "Feature",
  "properties": {
    "iso:country":"IT",
    "sg:address":"13848 Zumaglia",
    "sg:city":"Zumaglia",
    "sg:orig_category":"Servizi E Lavori Per Arredamento E Industria Del Legno. Servizi E Lavori Per Edilizia E Lavori Pubblici",
    "sg:phone":"+39 015 461601",
    "sg:postcode":"13848",
    "sg:province":"Biella",
    "wof:name":"Dabenini Domenico",
    "wof:placetype":"venue"
},
  "geometry": {"coordinates":[8.076365,45.587189],"type":"Point"}
}