{
  "type": "Feature",
  "properties": {
    "iso:country":"IT",
    "sg:address":"34, Via Della Rocca 10123 Torino",
    "sg:city":"Torino",
    "sg:classifiers":[
        {
            "category":"Professional",
            "subcategory":"Advertising",
            "type":"Services"
        }
    ],
    "sg:phone":"+39 39011837767",
    "sg:postcode":"10123",
    "sg:province":"Torino",
    "sg:tags":[
        "communication",
        "medium"
    ],
    "wof:name":"Gruppo Cooper (s.r.l.)",
    "wof:placetype":"venue"
},
  "geometry": {"coordinates":[8.39892,45.462345],"type":"Point"}
}