{
  "type": "Feature",
  "properties": {
    "addr:full":"10040 Lein\u00ec Torino 10040",
    "addr:postcode":"10040;10040",
    "iso:country":"IT",
    "sg:address":"10040 Lein\u00ec",
    "sg:orig_category":"Servizi E Lavori Industria Della Gomma. Servizi E Lavori Industria Delle Materie Plastiche. Forniture Per Edilizia E Lavori Pubblici",
    "sg:phone":"+39 011 998 8733",
    "sg:postcode":"10040",
    "sg:province":"Torino",
    "sg:website":"http://www.verplast.net",
    "wof:name":"Ver Plast Srl",
    "wof:placetype":"venue"
},
  "geometry": {"coordinates":[7.722423,45.17696],"type":"Point"}
}