{
  "type": "Feature",
  "properties": {
    "addr:full":"Zona Industriale P.i.p. 33081 Aviano Aviano Pordenone 33081",
    "addr:postcode":"33081;33081",
    "addr:street":"Zona Industriale P.I.P.",
    "iso:country":"IT",
    "sg:address":"Zona Industriale P.i.p. 33081 Aviano",
    "sg:city":"Aviano",
    "sg:classifiers":[
        {
            "category":"Shopping",
            "subcategory":"Stationery & Office Supplies",
            "type":"Retail Goods"
        }
    ],
    "sg:phone":"+39 0434 651069",
    "sg:postcode":"33081",
    "sg:province":"Pordenone",
    "sg:tags":[
        "professional"
    ],
    "wof:name":"Tecno Arredamenti (s.r.l.)",
    "wof:placetype":"venue"
},
  "geometry": {"coordinates":[12.655043602,45.9626502991],"type":"Point"}
}