{
  "type": "Feature",
  "properties": {
    "iso:country":"IT",
    "sg:address":"67, Via Zerbino 25020 Flero",
    "sg:city":"Flero",
    "sg:classifiers":[
        {
            "category":"Home & Garden",
            "subcategory":"Home Furnishings",
            "type":"Retail Goods"
        }
    ],
    "sg:phone":"+39 030 268 0215",
    "sg:postcode":"25020",
    "sg:province":"Brescia",
    "sg:tags":[
        "household"
    ],
    "wof:name":"Mafezzoni Armadi Di Mafezzoni Angelo & C. S.n.c.",
    "wof:placetype":"venue"
},
  "geometry": {"coordinates":[10.167616,45.493423],"type":"Point"}
}