{
  "type": "Feature",
  "properties": {
    "addr:full":"102, V. Oropa 13900 Biella Biella Biella 13900",
    "addr:housenumber":"102",
    "addr:postcode":"13900;13900",
    "addr:street":"V. Oropa",
    "iso:country":"IT",
    "sg:address":"102, V. Oropa 13900 Biella",
    "sg:city":"Biella",
    "sg:classifiers":[
        {
            "category":"Shopping",
            "subcategory":"Crafts & Fabrics",
            "type":"Retail Goods"
        }
    ],
    "sg:phone":"+39 39015571246",
    "sg:postcode":"13900",
    "sg:province":"Biella",
    "wof:name":"Tessili Foglio Srl",
    "wof:placetype":"venue"
},
  "geometry": {"coordinates":[8.0378437042,45.5828933716],"type":"Point"}
}