{
  "type": "Feature",
  "properties": {
    "iso:country":"IT",
    "sg:address":"71, Strada S. Lucia 06121 Perugia",
    "sg:city":"Perugia",
    "sg:classifiers":[
        {
            "category":"Shopping",
            "subcategory":"Clothing, Apparel, & Fashions",
            "type":"Retail Goods"
        }
    ],
    "sg:phone":"+39 390 754 591",
    "sg:postcode":"06121",
    "sg:province":"Perugia",
    "sg:tags":[
        "clothes"
    ],
    "wof:name":"Luisa Spagnoli Spa",
    "wof:placetype":"venue"
},
  "geometry": {"coordinates":[12.389172,43.110703],"type":"Point"}
}