{
  "type": "Feature",
  "properties": {
    "addr:full":"50012 Bagno A Ripoli Bagno a Ripoli Firenze 50012",
    "addr:postcode":"50012;50012",
    "addr:street":"A",
    "iso:country":"IT",
    "sg:address":"50012 Bagno A Ripoli",
    "sg:city":"Bagno a Ripoli",
    "sg:orig_category":"Alberghi E Strutture Extra Alberghiere. Ospedali E Servizi Sanitari",
    "sg:phone":"+39 055 65741",
    "sg:postcode":"50012",
    "sg:province":"Firenze",
    "sg:website":"http://www.villasantamonica.it",
    "wof:name":"Casa Di Riposo Villa Olimpia",
    "wof:placetype":"venue"
},
  "geometry": {"coordinates":[11.34653,43.768406],"type":"Point"}
}