{
  "type": "Feature",
  "properties": {
    "addr:full":"12, Via Burcina 13814 Pollone Pollone Biella 13814",
    "addr:postcode":"13814;13814",
    "addr:street":"Via Burcina",
    "iso:country":"IT",
    "sg:address":"12, Via Burcina 13814 Pollone",
    "sg:city":"Pollone",
    "sg:classifiers":[
        {
            "category":"Professional",
            "subcategory":"Engineering",
            "type":"Services"
        }
    ],
    "sg:phone":"+39 390 156 1222",
    "sg:postcode":"13814",
    "sg:province":"Biella",
    "sg:tags":[
        "machine",
        "-",
        "mechanical"
    ],
    "wof:name":"Colongo",
    "wof:placetype":"venue"
},
  "geometry": {"coordinates":[8.011899,45.582104],"type":"Point"}
}