{
  "type": "Feature",
  "properties": {
    "iso:country":"IT",
    "sg:address":"50145 Firenze",
    "sg:city":"Firenze",
    "sg:orig_category":"Elettronica Industriale, Prodotti E Apparecchiature",
    "sg:phone":"+39 055 342 8021",
    "sg:postcode":"50145",
    "sg:province":"Firenze",
    "sg:website":"http://www.selectron.it",
    "wof:name":"Selectron Srl",
    "wof:placetype":"venue"
},
  "geometry": {"coordinates":[11.188464,43.802334],"type":"Point"}
}