{
  "type": "Feature",
  "properties": {
    "iso:country":"IT",
    "sg:address":"16131 Genova",
    "sg:city":"Genova",
    "sg:orig_category":"Trasporti E Spedizioni Merci",
    "sg:phone":"+39 010 362 9323",
    "sg:postcode":"16131",
    "sg:province":"Genova",
    "sg:website":"http://www.src-srl.it",
    "wof:name":"S R C Servizio Rapido Corrieri Srl",
    "wof:placetype":"venue"
},
  "geometry": {"coordinates":[8.974914,44.403442],"type":"Point"}
}