{
  "type": "Feature",
  "properties": {
    "iso:country":"IT",
    "sg:address":"29, V. Guglielmo Marconi",
    "sg:classifiers":[
        {
            "category":"Manufacturing",
            "subcategory":"Tools & Machinery",
            "type":"Manufacturing & Wholesale Goods"
        }
    ],
    "sg:phone":"+39 0144 364101",
    "sg:tags":[
        "leather",
        "equipment",
        "goods",
        "clothing"
    ],
    "sg:website":"http://www.stefanellimacchine.com",
    "wof:name":"Stefanelli Macchine Srl",
    "wof:placetype":"venue"
},
  "geometry": {"coordinates":[8.670866,45.950077],"type":"Point"}
}