{
  "type": "Feature",
  "properties": {
    "iso:country":"IT",
    "sg:address":"00177 Roma",
    "sg:city":"Roma",
    "sg:orig_category":"Servizi Editoriali. Servizi Ausiliari Per Il Trasporto",
    "sg:phone":"+39 06 215 4010",
    "sg:postcode":"00177",
    "sg:province":"Roma",
    "wof:name":"Rde Roma Distribuzioni Editoriali Srl",
    "wof:placetype":"venue"
},
  "geometry": {"coordinates":[12.557943,41.898991],"type":"Point"}
}