{
  "type": "Feature",
  "properties": {
    "addr:full":"00042 Anzio Anzio Roma 00042",
    "addr:postcode":"00042;roma 00042",
    "iso:country":"IT",
    "sg:address":"00042 Anzio",
    "sg:city":"Anzio",
    "sg:orig_category":"Riparazione Dei Mezzi Di Trasporto. Servizi Ausiliari Dei Mezzi Di Trasporto",
    "sg:phone":"+39 06 987 8595",
    "sg:postcode":"00042",
    "sg:province":"Roma",
    "wof:name":"Off.car. Di De Maio Antonino E C. Snc",
    "wof:placetype":"venue"
},
  "geometry": {"coordinates":[12.490653,41.930359],"type":"Point"}
}