{
  "type": "Feature",
  "properties": {
    "iso:country":"IT",
    "sg:address":"5, Via Moroni 23100 Sondrio",
    "sg:city":"Sondrio",
    "sg:classifiers":[
        {
            "category":"Building & Trades",
            "subcategory":"Construction",
            "type":"Services"
        }
    ],
    "sg:phone":"+39 0342 212114",
    "sg:postcode":"23100",
    "sg:province":"Sondrio",
    "sg:tags":[
        "work",
        "public"
    ],
    "wof:name":"Moroni Riccardo Di Moroni Riccardo & C. S.a.s.",
    "wof:placetype":"venue"
},
  "geometry": {"coordinates":[9.870186,46.167572],"type":"Point"}
}