{
  "type": "Feature",
  "properties": {
    "iso:country":"IT",
    "sg:address":"14045 Incisa Scapaccino",
    "sg:city":"Incisa Scapaccino",
    "sg:orig_category":"Non-classified Establishments",
    "sg:phone":"+39 0141 747066",
    "sg:postcode":"14045",
    "sg:province":"Asti",
    "wof:name":"Saracco Giovanni",
    "wof:placetype":"venue"
},
  "geometry": {"coordinates":[8.373262,44.806885],"type":"Point"}
}