{
  "type": "Feature",
  "properties": {
    "addr:full":"04012 Cisterna Di Latina Cisterna di Latina Latina 04012",
    "addr:postcode":"04012;04012",
    "iso:country":"IT",
    "sg:address":"04012 Cisterna Di Latina",
    "sg:city":"Cisterna di Latina",
    "sg:orig_category":"Servizi Ausiliari Per Il Trasporto. Servizi Vari Di Interesse Pubblico",
    "sg:phone":"+39 06 969 5446",
    "sg:postcode":"04012",
    "sg:province":"Latina",
    "sg:website":"http://www.paginegialle.it/onoranzefunebrimartelli",
    "wof:name":"Onoranze Funebri Martelli Srl",
    "wof:placetype":"venue"
},
  "geometry": {"coordinates":[12.830244,41.591721],"type":"Point"}
}