{
  "type": "Feature",
  "properties": {
    "iso:country":"IT",
    "sg:address":"13900 Biella",
    "sg:city":"Biella",
    "sg:orig_category":"Servizi E Lavori Per Abbigliamento E Pelletterie",
    "sg:phone":"+39 015 31210",
    "sg:postcode":"13900",
    "sg:province":"Biella",
    "wof:name":"Muce' Rosa",
    "wof:placetype":"venue"
},
  "geometry": {"coordinates":[8.063773,45.548092],"type":"Point"}
}