{
  "type": "Feature",
  "properties": {
    "addr:full":"13894 Gaglianico Gaglianico Biella 13894",
    "addr:postcode":"13894;13894",
    "iso:country":"IT",
    "sg:address":"13894 Gaglianico",
    "sg:city":"Gaglianico",
    "sg:orig_category":"Servizi E Lavori Per Abbigliamento E Pelletterie",
    "sg:phone":"+39 015 254 3571",
    "sg:postcode":"13894",
    "sg:province":"Biella",
    "wof:name":"Rammendo Borri Di Borri Carlo",
    "wof:placetype":"venue"
},
  "geometry": {"coordinates":[8.044519,45.55933],"type":"Point"}
}