{
  "type": "Feature",
  "properties": {
    "iso:country":"IT",
    "sg:address":"10060 Salza Di Pinerolo",
    "sg:city":"Salza di Pinerolo",
    "sg:orig_category":"Restaurants And Related Public Premises. Sport And Leisure, Services. Hotels And Hotel Facilities. Restaurants And Similar",
    "sg:phone":"+39 0121 801018",
    "sg:postcode":"10060",
    "sg:province":"Torino",
    "wof:name":"Agriturismo La Miando",
    "wof:placetype":"venue"
},
  "geometry": {"coordinates":[7.053634,44.940987],"type":"Point"}
}