{
  "type": "Feature",
  "properties": {
    "iso:country":"IT",
    "sg:address":"V. Provinciale Di Botriolo 52020 Castelfranco Di Sopra",
    "sg:city":"Castelfranco di Sopra",
    "sg:classifiers":[
        {
            "category":"Professional",
            "subcategory":"Engineering",
            "type":"Services"
        }
    ],
    "sg:phone":"+39 055 914 9553",
    "sg:postcode":"52020",
    "sg:province":"Arezzo",
    "sg:tags":[
        "machine",
        "-",
        "mechanical"
    ],
    "sg:website":"http://www.thermindus.com:ws_end: :mark:ws:http://www.paginegialle.it/thermindus",
    "wof:name":"Thermindus Srl",
    "wof:placetype":"venue"
},
  "geometry": {"coordinates":[11.5428,43.607899],"type":"Point"}
}