{
  "type": "Feature",
  "properties": {
    "addr:full":"10128 Torino Torino Torino 10128",
    "addr:postcode":"10128;10128",
    "iso:country":"IT",
    "sg:address":"10128 Torino",
    "sg:city":"Torino",
    "sg:orig_category":"Macchine, Impianti E Forniture Per Industria Grafica, Cartaria E Cartotecnica",
    "sg:phone":"+39 011 568 1976",
    "sg:postcode":"10128",
    "sg:province":"Torino",
    "wof:name":"Ariaudo (s.n.c.)",
    "wof:placetype":"venue"
},
  "geometry": {"coordinates":[7.670002,45.059818],"type":"Point"}
}