{
  "type": "Feature",
  "properties": {
    "iso:country":"IT",
    "sg:address":"14011 Baldichieri D'asti",
    "sg:orig_category":"Materiali E Componenti Elettrotecnici",
    "sg:phone":"+39 0141 66156",
    "sg:postcode":"14011",
    "sg:province":"Asti",
    "wof:name":"La Micanite Di Mingozzi Elvise - Daniele - Stefano S.n.c.",
    "wof:placetype":"venue"
},
  "geometry": {"coordinates":[8.092671,44.903461],"type":"Point"}
}