{
  "type": "Feature",
  "properties": {
    "iso:country":"IT",
    "sg:address":"65126 Pescara",
    "sg:city":"Pescara",
    "sg:orig_category":"Elettronica Professionale E Di Consumo. Forniture Per Il Settore Dello Spettacolo. Automazione E Macchine Per Ufficio. Forniture Per Congressi, Fiere E Manifestazioni",
    "sg:phone":"+39 085 451 4637",
    "sg:postcode":"65126",
    "sg:province":"Pescara",
    "sg:website":"http://www.cdaudiovideo.com",
    "wof:name":"Cd Audio Video Di D'attanasio Carlo",
    "wof:placetype":"venue"
},
  "geometry": {"coordinates":[14.22482,42.45879],"type":"Point"}
}