{
  "type": "Feature",
  "properties": {
    "addr:full":"Via Salara, 15/17 64026 Roseto Degli Abruzzi Roseto degli Abruzzi Teramo 64026",
    "addr:housenumber":"15 / 17",
    "addr:postcode":"64026;64026",
    "addr:street":"Via Salara",
    "iso:country":"IT",
    "sg:address":"Via Salara, 15/17 64026 Roseto Degli Abruzzi",
    "sg:city":"Roseto degli Abruzzi",
    "sg:classifiers":[
        {
            "category":"Food & Beverages",
            "subcategory":"Liquor & Beverages",
            "type":"Retail Goods"
        }
    ],
    "sg:phone":"+39 085 894531",
    "sg:postcode":"64026",
    "sg:province":"Teramo",
    "sg:tags":[
        "wine",
        "italian"
    ],
    "sg:website":"www.casalthaulero.com",
    "wof:name":"Aprutina S.r.l.",
    "wof:placetype":"venue"
},
  "geometry": {"coordinates":[14.022274,42.664684],"type":"Point"}
}