{
  "type": "Feature",
  "properties": {
    "iso:country":"IT",
    "sg:address":"00189 Roma",
    "sg:city":"Roma",
    "sg:classifiers":[
        {
            "category":"Health Services",
            "subcategory":"Health Practitioner",
            "type":"Services"
        }
    ],
    "sg:phone":"+39 06 3371 0010",
    "sg:postcode":"00189",
    "sg:province":"Roma",
    "sg:tags":[
        "medici"
    ],
    "wof:name":"Caniggia Flaminia",
    "wof:placetype":"venue"
},
  "geometry": {"coordinates":[12.449522,41.980042],"type":"Point"}
}