{
  "type": "Feature",
  "properties": {
    "iso:country":"IT",
    "sg:address":"37039 Tregnago",
    "sg:city":"Tregnago",
    "sg:orig_category":"Articoli Per Imballaggio E Confezionamento",
    "sg:phone":"+39 045 780 8549",
    "sg:postcode":"37039",
    "sg:province":"Verona",
    "wof:name":"Legnimpex Srl",
    "wof:placetype":"venue"
},
  "geometry": {"coordinates":[11.161918,45.511337],"type":"Point"}
}