{
  "type": "Feature",
  "properties": {
    "iso:country":"IT",
    "sg:address":"12, Via Buozzi Bruno 20090 Segrate",
    "sg:city":"Segrate",
    "sg:classifiers":[
        {
            "category":"Home & Garden",
            "subcategory":"Home Furnishings",
            "type":"Retail Goods"
        }
    ],
    "sg:phone":"+39 02 2692 1838",
    "sg:postcode":"20090",
    "sg:province":"Milano",
    "sg:tags":[
        "household"
    ],
    "wof:name":"Effegi Brevetti (s.r.l.)",
    "wof:placetype":"venue"
},
  "geometry": {"coordinates":[9.269237,45.546734],"type":"Point"}
}