{
  "type": "Feature",
  "properties": {
    "addr:full":"80131 Napoli Napoli Napoli 80131",
    "addr:housenumber":"80131",
    "addr:postcode":"80131",
    "iso:country":"IT",
    "sg:address":"80131 Napoli",
    "sg:city":"Napoli",
    "sg:orig_category":"Articoli Medico-sanitari Ed Ortopedici. Impianti, Attrezzature E Forniture Sanitarie Ed Ospedaliere",
    "sg:phone":"+39 081 587 5816",
    "sg:postcode":"80131",
    "sg:province":"Napoli",
    "wof:name":"Peretti Medica Sas",
    "wof:placetype":"venue"
},
  "geometry": {"coordinates":[14.188658,40.870544],"type":"Point"}
}