{
  "type": "Feature",
  "properties": {
    "addr:full":"30175 Marghera Marghera Venezia 30175",
    "addr:postcode":"30175;30175",
    "iso:country":"IT",
    "sg:address":"30175 Marghera",
    "sg:city":"Marghera",
    "sg:orig_category":"Lavorazioni Meccaniche E Servizi",
    "sg:phone":"+39 041 932502",
    "sg:postcode":"30175",
    "sg:province":"Venezia",
    "wof:name":"Rimen Srl",
    "wof:placetype":"venue"
},
  "geometry": {"coordinates":[12.228126,45.464848],"type":"Point"}
}