{
  "type": "Feature",
  "properties": {
    "iso:country":"IT",
    "sg:address":"46013 Canneto Sull'oglio",
    "sg:classifiers":[
        {
            "category":"Manufacturing",
            "subcategory":"Motor Vehicles & Parts",
            "type":"Manufacturing & Wholesale Goods"
        }
    ],
    "sg:phone":"+39 0376 70125",
    "sg:postcode":"46013",
    "sg:province":"Mantova",
    "sg:tags":[
        "drive"
    ],
    "wof:name":"Ziliani Giuseppe",
    "wof:placetype":"venue"
},
  "geometry": {"coordinates":[10.3791408539,45.1706542969],"type":"Point"}
}