{
  "type": "Feature",
  "properties": {
    "iso:country":"IT",
    "sg:address":"Via Don Sturzo 1; Erbusco; 25030",
    "sg:city":"Erbusco",
    "sg:classifiers":[
        {
            "category":"Banks & Credit Unions",
            "subcategory":"Bank",
            "type":"Services"
        }
    ],
    "sg:phone":"+39 030 726 7018",
    "sg:postcode":"25030",
    "sg:province":"Brescia",
    "wof:name":"Credito Bergamasco Spa",
    "wof:placetype":"venue"
},
  "geometry": {"coordinates":[9.969126,45.600063],"type":"Point"}
}