{
  "type": "Feature",
  "properties": {
    "iso:country":"IT",
    "sg:address":"20132 Milano",
    "sg:city":"Milano",
    "sg:orig_category":"Prodotti Alimentari",
    "sg:phone":"+39 02 215 3897",
    "sg:postcode":"20132",
    "sg:province":"Milano",
    "wof:name":"Caporusso Francesco",
    "wof:placetype":"venue"
},
  "geometry": {"coordinates":[9.2361059189,45.4907302856],"type":"Point"}
}