{
  "type": "Feature",
  "properties": {
    "iso:country":"IT",
    "sg:address":"88046 Lamezia Terme",
    "sg:city":"Lamezia Terme",
    "sg:orig_category":"Elettronica Professionale E Di Consumo. Automazione E Macchine Per Ufficio. Forniture Per Congressi, Fiere E Manifestazioni",
    "sg:phone":"+39 0968 21252",
    "sg:postcode":"88046",
    "sg:province":"Catanzaro",
    "wof:name":"Didacta Service Srl",
    "wof:placetype":"venue"
},
  "geometry": {"coordinates":[16.32992,38.958027],"type":"Point"}
}