{
  "type": "Feature",
  "properties": {
    "addr:full":"00184 Roma Roma Roma 00184",
    "addr:postcode":"00184;00184",
    "iso:country":"IT",
    "sg:address":"00184 Roma",
    "sg:city":"Roma",
    "sg:classifiers":[
        {
            "category":"Insurance",
            "subcategory":"Life Insurance",
            "type":"Services"
        }
    ],
    "sg:phone":"+39 0647651",
    "sg:postcode":"00184",
    "sg:province":"Roma",
    "sg:website":"http://www.fata-assicurazioni.it",
    "wof:name":"F.a.t.a. Assicurazioni Spa",
    "wof:placetype":"venue"
},
  "geometry": {"coordinates":[12.498258,41.889187],"type":"Point"}
}