{
  "type": "Feature",
  "properties": {
    "iso:country":"IT",
    "sg:address":"10, Via Leopoldo Di Toscana-alberoro 52048 Monte San Savino",
    "sg:city":"Alberoro",
    "sg:classifiers":[
        {
            "category":"Manufacturing",
            "subcategory":"Metals",
            "type":"Manufacturing & Wholesale Goods"
        }
    ],
    "sg:phone":"+39 0575 846058",
    "sg:postcode":"52048",
    "sg:province":"Arezzo",
    "sg:tags":[
        "metallurgy",
        "metalworking"
    ],
    "wof:name":"Blu Oro Snc",
    "wof:placetype":"venue"
},
  "geometry": {"coordinates":[11.8069896698,43.3582305908],"type":"Point"}
}