{
  "type": "Feature",
  "properties": {
    "iso:country":"IT",
    "sg:address":"50145 Firenze",
    "sg:city":"Firenze",
    "sg:orig_category":"Trasporti E Spedizioni Merci",
    "sg:phone":"+39 0553291",
    "sg:postcode":"50145",
    "sg:province":"Firenze",
    "wof:name":"Saima Avandero Spa",
    "wof:placetype":"venue"
},
  "geometry": {"coordinates":[11.192209,43.800419],"type":"Point"}
}