{
  "type": "Feature",
  "properties": {
    "addr:full":"10081 Castellamonte Castellamonte Torino 10081",
    "addr:postcode":"10081;10081",
    "iso:country":"IT",
    "sg:address":"10081 Castellamonte",
    "sg:city":"Castellamonte",
    "sg:orig_category":"Scuole Private - Professionali",
    "sg:phone":"+39 0124 582528",
    "sg:postcode":"10081",
    "sg:province":"Torino",
    "wof:name":"Collegio Marino",
    "wof:placetype":"venue"
},
  "geometry": {"coordinates":[7.42694,45.161419],"type":"Point"}
}