{
  "type": "Feature",
  "properties": {
    "iso:country":"IT",
    "sg:address":"159, Via Del Ferro 59100 Prato",
    "sg:city":"Prato",
    "sg:classifiers":[
        {
            "category":"Shopping",
            "subcategory":"Crafts & Fabrics",
            "type":"Retail Goods"
        }
    ],
    "sg:phone":"+39 0574 542443",
    "sg:postcode":"59100",
    "sg:province":"Prato",
    "wof:name":"Filati Italiani (s.r.l.)",
    "wof:placetype":"venue"
},
  "geometry": {"coordinates":[11.0885753632,43.8494720459],"type":"Point"}
}