{
  "type": "Feature",
  "properties": {
    "iso:country":"IT",
    "sg:address":"41100 Modena",
    "sg:city":"Modena",
    "sg:orig_category":"Elettrotecnica Industriale, Prodotti E Apparecchiature. Forniture Per Attivita' Commerciali Ed Artigianali",
    "sg:phone":"+39 059 310271",
    "sg:postcode":"41100",
    "sg:province":"Modena",
    "wof:name":"Neon Modena Srl",
    "wof:placetype":"venue"
},
  "geometry": {"coordinates":[10.917106,44.662903],"type":"Point"}
}