{
  "type": "Feature",
  "properties": {
    "iso:country":"IT",
    "sg:address":"Via B. Normanno; Mesagne; 72023",
    "sg:city":"Mesagne",
    "sg:classifiers":[
        {
            "category":"Banks & Credit Unions",
            "subcategory":"Bank",
            "type":"Services"
        }
    ],
    "sg:phone":"+39 0831 738352",
    "sg:postcode":"72023",
    "sg:province":"Brindisi",
    "wof:name":"Banca Del Salento",
    "wof:placetype":"venue"
},
  "geometry": {"coordinates":[17.805788,40.560123],"type":"Point"}
}