{
  "type": "Feature",
  "properties": {
    "addr:full":"34015 Muggia Muggia Trieste 34015",
    "addr:postcode":"34015;34015",
    "iso:country":"IT",
    "sg:address":"34015 Muggia",
    "sg:city":"Muggia",
    "sg:orig_category":"Prodotti Di Base E Forniture Per Industria Alimentare E Bevande. Prodotti Chimici Di Base",
    "sg:phone":"+39 040 232691",
    "sg:postcode":"34015",
    "sg:province":"Trieste",
    "wof:name":"Janousek Industriale Srl",
    "wof:placetype":"venue"
},
  "geometry": {"coordinates":[13.8077068329,45.5867385864],"type":"Point"}
}