{
  "type": "Feature",
  "properties": {
    "addr:full":"40128 Bologna Bologna Bologna 40128",
    "addr:postcode":"40128;40128",
    "iso:country":"IT",
    "sg:address":"40128 Bologna",
    "sg:city":"Bologna",
    "sg:orig_category":"Sport - Articoli E Forniture",
    "sg:phone":"+39 051 320531",
    "sg:postcode":"40128",
    "sg:province":"Bologna",
    "wof:name":"Soverini Walter (s.r.l.)",
    "wof:placetype":"venue"
},
  "geometry": {"coordinates":[11.358056,44.533138],"type":"Point"}
}