{
  "type": "Feature",
  "properties": {
    "iso:country":"IT",
    "sg:address":"17100 Savona",
    "sg:city":"Savona",
    "sg:orig_category":"Tempo Libero - Articoli E Forniture. Shopping. Regalistica Aziendale",
    "sg:phone":"+39 019 814980",
    "sg:postcode":"17100",
    "sg:province":"Savona",
    "wof:name":"Ferro Angelo",
    "wof:placetype":"venue"
},
  "geometry": {"coordinates":[8.476535,44.315304],"type":"Point"}
}