{
  "type": "Feature",
  "properties": {
    "iso:country":"IT",
    "sg:address":"Via L. Landini 19 42027 Montecchio Emilia",
    "sg:classifiers":[
        {
            "category":"Autos & Motor Vehicles",
            "subcategory":"Fuel & Gas Station",
            "type":"Retail Goods"
        }
    ],
    "sg:phone":"+39 0522 869611",
    "sg:postcode":"42027",
    "sg:province":"Reggio Nell'Emilia",
    "sg:tags":[
        "trucks",
        "tipper",
        "truck",
        "dumper",
        "dump"
    ],
    "sg:website":"www.dieci.com",
    "wof:name":"Dieci S.r.l.",
    "wof:placetype":"venue"
},
  "geometry": {"coordinates":[10.627794,44.696228],"type":"Point"}
}