{
  "type": "Feature",
  "properties": {
    "iso:country":"IT",
    "sg:address":"13, Via Reisina 10072 Caselle Torinese",
    "sg:city":"Caselle Torinese",
    "sg:classifiers":[
        {
            "category":"Professional",
            "subcategory":"Engineering",
            "type":"Services"
        }
    ],
    "sg:phone":"+39 011 996 8251",
    "sg:postcode":"10072",
    "sg:province":"Torino",
    "sg:tags":[
        "machine",
        "-",
        "mechanical"
    ],
    "wof:name":"Aster (s.r.l.)",
    "wof:placetype":"venue"
},
  "geometry": {"coordinates":[7.714168,45.151913],"type":"Point"}
}