{
  "type": "Feature",
  "properties": {
    "addr:full":"Via Carlo Del Balzo 10; Cervinara; 83012 Cervinara Avellino 83012",
    "addr:housenumber":"10",
    "addr:postcode":"83012;83012",
    "addr:street":"Via Carlo Del Balzo",
    "iso:country":"IT",
    "sg:address":"Via Carlo Del Balzo 10; Cervinara; 83012",
    "sg:city":"Cervinara",
    "sg:classifiers":[
        {
            "category":"Banks & Credit Unions",
            "subcategory":"Bank",
            "type":"Services"
        }
    ],
    "sg:phone":"+39 0824 836149",
    "sg:postcode":"83012",
    "sg:province":"Avellino",
    "wof:name":"Banco Di Napoli Spa",
    "wof:placetype":"venue"
},
  "geometry": {"coordinates":[14.622645,41.021145],"type":"Point"}
}