{
  "type": "Feature",
  "properties": {
    "iso:country":"IT",
    "sg:address":"Via Circonvallazione 90042 Borgetto",
    "sg:city":"Borgetto",
    "sg:classifiers":[
        {
            "category":"Travel",
            "subcategory":"Travel Agent",
            "type":"Entertainment"
        }
    ],
    "sg:phone":"+39 091 898 1489",
    "sg:postcode":"90042",
    "sg:province":"Palermo",
    "sg:tags":[
        "business"
    ],
    "wof:name":"New River S.r.l.",
    "wof:placetype":"venue"
},
  "geometry": {"coordinates":[13.142159,38.043648],"type":"Point"}
}