{
  "type": "Feature",
  "properties": {
    "iso:country":"IT",
    "sg:address":"00144 Roma",
    "sg:city":"Roma",
    "sg:orig_category":"Servizi Per Aziende, Manifestazioni E Supporto Agli Scambi Commerciali",
    "sg:phone":"+39 06 5224 6206",
    "sg:postcode":"00144",
    "sg:province":"Roma",
    "sg:website":"http://www.errepinet.com",
    "wof:name":"Errepi Servizi",
    "wof:placetype":"venue"
},
  "geometry": {"coordinates":[12.445158,41.823063],"type":"Point"}
}