{
  "type": "Feature",
  "properties": {
    "addr:full":"32, Via Procaccini Giulio Cesare 20154 Milano Milano Milano 20154",
    "addr:postcode":"20154;20154",
    "addr:street":"Via Procaccini Giulio Cesare",
    "iso:country":"IT",
    "sg:address":"32, Via Procaccini Giulio Cesare 20154 Milano",
    "sg:city":"Milano",
    "sg:classifiers":[
        {
            "category":"Shopping",
            "subcategory":"Crafts & Fabrics",
            "type":"Retail Goods"
        }
    ],
    "sg:phone":"+39 39023490306",
    "sg:postcode":"20154",
    "sg:province":"Milano",
    "wof:name":"Sior Team (s.r.l.)",
    "wof:placetype":"venue"
},
  "geometry": {"coordinates":[9.1704759598,45.4835700989],"type":"Point"}
}