{
  "type": "Feature",
  "properties": {
    "iso:country":"IT",
    "sg:address":"61100 Pesaro",
    "sg:city":"Pesaro",
    "sg:orig_category":"Saponi E Saponette",
    "sg:phone":"+39 0721 454052",
    "sg:postcode":"61100",
    "sg:province":"Pesaro E Urbino",
    "wof:name":"Antica Saponeria Srl",
    "wof:placetype":"venue"
},
  "geometry": {"coordinates":[12.876189,43.905159],"type":"Point"}
}