{
  "type": "Feature",
  "properties": {
    "iso:country":"IT",
    "sg:address":"90133 Palermo",
    "sg:city":"Palermo",
    "sg:orig_category":"Tessuti E Stoffe. Tessuti Arredamento, Tende E Tappeti",
    "sg:phone":"+39 091 580560",
    "sg:postcode":"90133",
    "sg:province":"Palermo",
    "wof:name":"Catalano Agostino - Casa Del Tappeto",
    "wof:placetype":"venue"
},
  "geometry": {"coordinates":[13.360331,38.121822],"type":"Point"}
}