{
  "type": "Feature",
  "properties": {
    "iso:country":"IT",
    "sg:address":"86100 Campobasso",
    "sg:city":"Campobasso",
    "sg:orig_category":"Servizi Al Turismo. Trasporto Pubblico E Privato",
    "sg:phone":"+39 0874 605211",
    "sg:postcode":"86100",
    "sg:province":"Campobasso",
    "wof:name":"Societa' Autocooperative Trasporti Italiani Arl",
    "wof:placetype":"venue"
},
  "geometry": {"coordinates":[14.694487,41.586926],"type":"Point"}
}