{
  "type": "Feature",
  "properties": {
    "iso:country":"IT",
    "sg:address":"71036 Lucera",
    "sg:city":"Lucera",
    "sg:orig_category":"Sport - Articoli E Forniture. Automobili E Mezzi Di Trasporto",
    "sg:phone":"+39 0881 540215",
    "sg:postcode":"71036",
    "sg:province":"Foggia",
    "wof:name":"D.g. Parking Di Di Giovine Antonio",
    "wof:placetype":"venue"
},
  "geometry": {"coordinates":[15.359957,41.47551],"type":"Point"}
}