{
  "type": "Feature",
  "properties": {
    "addr:full":"50, V. Murri 48018 Faenza Faenza Ravenna 48018",
    "addr:housenumber":"50",
    "addr:postcode":"48018;48018",
    "addr:street":"V. Murri",
    "iso:country":"IT",
    "sg:address":"50, V. Murri 48018 Faenza",
    "sg:city":"Faenza",
    "sg:classifiers":[
        {
            "category":"Professional",
            "subcategory":"Engineering",
            "type":"Services"
        }
    ],
    "sg:phone":"+39 0546 622727",
    "sg:postcode":"48018",
    "sg:province":"Ravenna",
    "sg:tags":[
        "machine",
        "-",
        "mechanical"
    ],
    "sg:website":"http://www.castellari.com:ws_end: :mark:ws:http://www.paginegialle.it/castellari",
    "wof:name":"Castellari Srl",
    "wof:placetype":"venue"
},
  "geometry": {"coordinates":[11.862267,44.306805],"type":"Point"}
}