{
  "type": "Feature",
  "properties": {
    "iso:country":"IT",
    "sg:address":"24, Via Ghisa 36071 Arzignano",
    "sg:city":"Arzignano",
    "sg:classifiers":[
        {
            "category":"Shopping",
            "type":"Retail Goods"
        }
    ],
    "sg:phone":"+39 0444 482301",
    "sg:postcode":"36071",
    "sg:province":"Vicenza",
    "sg:tags":[
        "finished",
        "-",
        "metallic"
    ],
    "wof:name":"Imac S.r.l.",
    "wof:placetype":"venue"
},
  "geometry": {"coordinates":[11.3839855194,45.5393638611],"type":"Point"}
}