{
  "type": "Feature",
  "properties": {
    "addr:full":"Via Nuova Moglianese 19 30030 Peseggia Peseggia Venezia 30030",
    "addr:housenumber":"19",
    "addr:postcode":"30030;30030",
    "addr:street":"Via Nuova Moglianese",
    "iso:country":"IT",
    "sg:address":"Via Nuova Moglianese 19 30030 Peseggia",
    "sg:city":"Peseggia",
    "sg:classifiers":[
        {
            "category":"Government",
            "subcategory":"Court House",
            "type":"Public Place"
        }
    ],
    "sg:phone":"+39 041 449137",
    "sg:postcode":"30030",
    "sg:province":"Venezia",
    "sg:tags":[
        "accommodation",
        "furniture"
    ],
    "sg:website":"www.arredamenticodato.it",
    "wof:name":"Arredamenti Codato Snc",
    "wof:placetype":"venue"
},
  "geometry": {"coordinates":[12.182137,45.565128],"type":"Point"}
}