{
  "type": "Feature",
  "properties": {
    "addr:full":"35010 Santa Giustina In Colle Santa Giustina in Colle Padova 35010",
    "addr:postcode":"35010;35010",
    "addr:street":"Santa Giustina In Colle;Giustina In Colle",
    "iso:country":"IT",
    "sg:address":"35010 Santa Giustina In Colle",
    "sg:city":"Santa Giustina in Colle",
    "sg:orig_category":"Prodotti E Manufatti In Materie Plastiche",
    "sg:phone":"+39 049 930 0353",
    "sg:postcode":"35010",
    "sg:province":"Padova",
    "wof:name":"Veneta Resine (s.n.c.)",
    "wof:placetype":"venue"
},
  "geometry": {"coordinates":[11.9123182297,45.5472640991],"type":"Point"}
}