{
  "type": "Feature",
  "properties": {
    "iso:country":"IT",
    "sg:address":"25013 Carpenedolo",
    "sg:city":"Carpenedolo",
    "sg:orig_category":"Apparecchiature Ed Attrezzature Meccaniche. Forniture E Materiali Per Imballaggio E Confezionamento. Apparecchiature E Sistemi Per Imballaggio E Confezionamento",
    "sg:phone":"+39 030 969 7543",
    "sg:postcode":"25013",
    "sg:province":"Brescia",
    "wof:name":"Fustel Graphic",
    "wof:placetype":"venue"
},
  "geometry": {"coordinates":[10.207627,45.567478],"type":"Point"}
}