{
  "type": "Feature",
  "properties": {
    "iso:country":"IT",
    "sg:address":"00187 Roma",
    "sg:city":"Roma",
    "sg:orig_category":"Agenzie D'affari E Servizi Commerciali. Acqua, Luce, Gas E Societa' Di Esercizio Pubblico",
    "sg:phone":"+39 06 320 1462",
    "sg:postcode":"00187",
    "sg:province":"Roma",
    "wof:name":"Telemarket Srl",
    "wof:placetype":"venue"
},
  "geometry": {"coordinates":[12.477597,41.909637],"type":"Point"}
}