{
  "type": "Feature",
  "properties": {
    "iso:country":"IT",
    "sg:address":"Via Roma 67; Grosio; 23033",
    "sg:city":"Grosio",
    "sg:classifiers":[
        {
            "category":"Banks & Credit Unions",
            "subcategory":"Bank",
            "type":"Services"
        }
    ],
    "sg:phone":"+39 0342 847144",
    "sg:postcode":"23033",
    "sg:province":"Sondrio",
    "wof:name":"Banca Popolare Di Sondrio Scarl",
    "wof:placetype":"venue"
},
  "geometry": {"coordinates":[10.275636,46.299133],"type":"Point"}
}