{
  "type": "Feature",
  "properties": {
    "iso:country":"IT",
    "sg:address":"10121 Torino",
    "sg:city":"Torino",
    "sg:orig_category":"Tempo Libero - Articoli E Forniture. Shopping. Regalistica Aziendale",
    "sg:phone":"+39 011 812 9689",
    "sg:postcode":"10121",
    "sg:province":"Torino",
    "sg:website":"http://www.natura-co.it",
    "wof:name":"Natura & Co Srl",
    "wof:placetype":"venue"
},
  "geometry": {"coordinates":[7.68714,45.06377],"type":"Point"}
}