{
  "type": "Feature",
  "properties": {
    "iso:country":"IT",
    "sg:address":"Via Mazzini 43; Pordenone",
    "sg:classifiers":[
        {
            "category":"Travel",
            "subcategory":"Travel Agent",
            "type":"Entertainment"
        }
    ],
    "wof:name":"Best Western Park Hotel",
    "wof:placetype":"venue"
},
  "geometry": {"coordinates":[12.656378,45.957554],"type":"Point"}
}