{
  "type": "Feature",
  "properties": {
    "iso:country":"IT",
    "sg:address":"25025 Manerbio",
    "sg:city":"Manerbio",
    "sg:orig_category":"Distributors: Automatici - Commercio E Gestione",
    "sg:phone":"+39 030 938 0520",
    "sg:postcode":"25025",
    "sg:province":"Brescia",
    "sg:website":"http://www.dbm2000.it",
    "wof:name":"Dbm 2000 Srl",
    "wof:placetype":"venue"
},
  "geometry": {"coordinates":[10.146845,45.368286],"type":"Point"}
}