{
  "type": "Feature",
  "properties": {
    "addr:full":"52, Strada Cardio 47031 Repubblica Di San Marino SM",
    "addr:postcode":"47031",
    "addr:street":"Strada Cardio;Marino",
    "iso:country":"IT",
    "sg:address":"52, Strada Cardio 47031 Repubblica Di San Marino",
    "sg:orig_category":"Miscellaneous Products",
    "sg:phone":"+39 0549 900255",
    "sg:province":"SM",
    "wof:name":"Fade S.a.",
    "wof:placetype":"venue"
},
  "geometry": {"coordinates":[12.4731683731,43.975566864],"type":"Point"}
}