{
  "type": "Feature",
  "properties": {
    "iso:country":"IT",
    "sg:address":"00181 Roma",
    "sg:city":"Roma",
    "sg:orig_category":"Valvole E Apparecchiature Di Misura. Ricambi E Componenti Dei Mezzi Di Trasporto",
    "sg:phone":"+39 06 761 5427",
    "sg:postcode":"00181",
    "sg:province":"Roma",
    "wof:name":"Baruffi Beniamino E C. Snc",
    "wof:placetype":"venue"
},
  "geometry": {"coordinates":[12.538077,41.869209],"type":"Point"}
}