{
  "type": "Feature",
  "properties": {
    "iso:country":"IT",
    "sg:address":"Via Val Di Stava 14 37060 Sona",
    "sg:city":"Sona",
    "sg:classifiers":[
        {
            "category":"Organizations",
            "subcategory":"Labor Organization",
            "type":"Services"
        }
    ],
    "sg:phone":"+39 045 608 1641",
    "sg:postcode":"37060",
    "sg:province":"Verona",
    "sg:tags":[
        "purification",
        "system",
        "air"
    ],
    "sg:website":"www.ecoair.it",
    "wof:name":"Linea Eco Air Srl",
    "wof:placetype":"venue"
},
  "geometry": {"coordinates":[10.844643,45.430775],"type":"Point"}
}