{
  "type": "Feature",
  "properties": {
    "iso:country":"IT",
    "sg:address":"24, Viale Industria 27024 Cilavegna",
    "sg:city":"Cilavegna",
    "sg:classifiers":[
        {
            "category":"Shopping",
            "type":"Retail Goods"
        }
    ],
    "sg:phone":"+39 0381 660121",
    "sg:postcode":"27024",
    "sg:province":"Pavia",
    "sg:tags":[
        "finished",
        "-",
        "metallic"
    ],
    "wof:name":"Mollificio Lomellino (s.r.l.)",
    "wof:placetype":"venue"
},
  "geometry": {"coordinates":[8.7489547729,45.3114776611],"type":"Point"}
}