{
  "type": "Feature",
  "properties": {
    "iso:country":"IT",
    "sg:address":"46040 Solarolo",
    "sg:orig_category":"Carni, Salumi E Pesci. Zootecnia E Pesca, Allevamento Piccoli Animali",
    "sg:phone":"+39 0376 608031",
    "sg:postcode":"46040",
    "sg:province":"Mantova",
    "wof:name":"Adalpol Di Bergnucchini A.&c. Sas",
    "wof:placetype":"venue"
},
  "geometry": {"coordinates":[10.797698,45.160366],"type":"Point"}
}