{
  "type": "Feature",
  "properties": {
    "addr:full":"55, Via Giacomo Matteotti 26030 Gabbioneta Binanuova Binanuova Cremona 26030",
    "addr:postcode":"26030;26030",
    "addr:street":"Via Giacomo Matteotti;Binanuova Cremona",
    "iso:country":"IT",
    "sg:address":"55, Via Giacomo Matteotti 26030 Gabbioneta Binanuova",
    "sg:city":"Binanuova",
    "sg:classifiers":[
        {
            "category":"Manufacturing",
            "subcategory":"Metals",
            "type":"Manufacturing & Wholesale Goods"
        }
    ],
    "sg:phone":"+39 0372 844666",
    "sg:postcode":"26030",
    "sg:province":"Cremona",
    "sg:tags":[
        "metallurgy",
        "metalworking"
    ],
    "wof:name":"Fonderia Simonelli (s.r.l.)",
    "wof:placetype":"venue"
},
  "geometry": {"coordinates":[10.0261354446,45.1334991455],"type":"Point"}
}