{
  "type": "Feature",
  "properties": {
    "addr:full":"95033 Biancavilla Biancavilla Catania 95033",
    "addr:postcode":"95033;95033",
    "iso:country":"IT",
    "sg:address":"95033 Biancavilla",
    "sg:city":"Biancavilla",
    "sg:orig_category":"Metalli E Leghe",
    "sg:phone":"+39 095 984851",
    "sg:postcode":"95033",
    "sg:province":"Catania",
    "wof:name":"Greco Dante",
    "wof:placetype":"venue"
},
  "geometry": {"coordinates":[14.8548526764,37.649936676],"type":"Point"}
}