{
  "type": "Feature",
  "properties": {
    "iso:country":"IT",
    "sg:address":"24, Viale Dell' Industria 35013 Cittadella",
    "sg:city":"Cittadella",
    "sg:classifiers":[
        {
            "category":"Professional",
            "subcategory":"Engineering",
            "type":"Services"
        }
    ],
    "sg:phone":"+39 049 940 1018",
    "sg:postcode":"35013",
    "sg:province":"Padova",
    "sg:tags":[
        "machine",
        "-",
        "mechanical"
    ],
    "wof:name":"Priore Di Priore Antonio & C. (s.n.c.)",
    "wof:placetype":"venue"
},
  "geometry": {"coordinates":[11.803695,45.663322],"type":"Point"}
}