{
  "type": "Feature",
  "properties": {
    "iso:country":"IT",
    "sg:address":"20090 Vimodrone",
    "sg:city":"Vimodrone",
    "sg:orig_category":"Termotecnica E Riscaldamento, Apparecchiature E Servizi. Valvole E Apparecchiature Di Misura. Macchine, Strumenti Ed Apparecchi Per Attivita' Industriali",
    "sg:phone":"+39 02 250 0541",
    "sg:postcode":"20090",
    "sg:province":"Milano",
    "wof:name":"Spriano S.p.a.",
    "wof:placetype":"venue"
},
  "geometry": {"coordinates":[9.297883,45.513515],"type":"Point"}
}