{
  "type": "Feature",
  "properties": {
    "addr:full":"25062 Concesio Concesio Brescia 25062",
    "addr:postcode":"25062;25062",
    "iso:country":"IT",
    "sg:address":"25062 Concesio",
    "sg:city":"Concesio",
    "sg:orig_category":"Servizi Culturali E Per Lo Spettacolo. Servizi Al Turismo. Acqua, Luce, Gas E Societa' Di Esercizio Pubblico",
    "sg:phone":"+39 030 275 1668",
    "sg:postcode":"25062",
    "sg:province":"Brescia",
    "wof:name":"Municipio",
    "wof:placetype":"venue"
},
  "geometry": {"coordinates":[10.212273,45.606434],"type":"Point"}
}