{
  "type": "Feature",
  "properties": {
    "addr:full":"41012 Carpi Carpi Modena 41012",
    "addr:postcode":"41012;41012",
    "iso:country":"IT",
    "sg:address":"41012 Carpi",
    "sg:city":"Carpi",
    "sg:orig_category":"Zootecnia E Pesca, Allevamento Piccoli Animali. Animali Domestici",
    "sg:phone":"+39 339 312 9991",
    "sg:postcode":"41012",
    "sg:province":"Modena",
    "wof:name":"Barb\u00cc Claudio",
    "wof:placetype":"venue"
},
  "geometry": {"coordinates":[10.868768,44.777672],"type":"Point"}
}