{
  "type": "Feature",
  "properties": {
    "iso:country":"IT",
    "sg:address":"Via Xxv Aprile 36 - Zona Industr. 24050 Grassobbio",
    "sg:city":"Grassobbio",
    "sg:classifiers":[
        {
            "category":"Wholesale",
            "subcategory":"Vending Machines",
            "type":"Manufacturing & Wholesale Goods"
        }
    ],
    "sg:phone":"+39 035 335434",
    "sg:postcode":"24050",
    "sg:province":"Bergamo",
    "sg:tags":[
        "mobile",
        "hot",
        "beverage",
        "dispensing",
        "machines"
    ],
    "sg:website":"www.flymax.com",
    "wof:name":"A.c.e.m. Automatic Capuccino Espresso Machines S.r.l.",
    "wof:placetype":"venue"
},
  "geometry": {"coordinates":[9.669952,45.694904],"type":"Point"}
}