{
  "type": "Feature",
  "properties": {
    "addr:full":"64011 Alba Adriatica Alba Adriatica Teramo 64011",
    "addr:postcode":"64011;64011",
    "iso:country":"IT",
    "sg:address":"64011 Alba Adriatica",
    "sg:city":"Alba Adriatica",
    "sg:orig_category":"Servizi Al Turismo. Trasporto Pubblico E Privato",
    "sg:phone":"+39 0861 712487",
    "sg:postcode":"64011",
    "sg:province":"Teramo",
    "wof:name":"Selene Mare S.r.l.",
    "wof:placetype":"venue"
},
  "geometry": {"coordinates":[13.920246,42.832561],"type":"Point"}
}