{
  "type": "Feature",
  "properties": {
    "iso:country":"IT",
    "sg:address":"50055 Lastra A Signa",
    "sg:city":"Lastra a Signa",
    "sg:orig_category":"Macchine E Forniture Per Arredamento E Industria Del Legno. Macchine Utensili E Impianti",
    "sg:phone":"+39 055 878063",
    "sg:postcode":"50055",
    "sg:province":"Firenze",
    "wof:name":"Cazzaroli Leonardo",
    "wof:placetype":"venue"
},
  "geometry": {"coordinates":[11.126517,43.754753],"type":"Point"}
}