{
  "type": "Feature",
  "properties": {
    "iso:country":"IT",
    "sg:address":"31055 Quinto Di Treviso",
    "sg:city":"Quinto di Treviso",
    "sg:orig_category":"Ospedali E Servizi Sanitari. Servizi Sociali",
    "sg:phone":"+39 349 468 0181",
    "sg:postcode":"31055",
    "sg:province":"Treviso",
    "wof:name":"Vezz\u00c0 Roberto",
    "wof:placetype":"venue"
},
  "geometry": {"coordinates":[12.162027,45.646027],"type":"Point"}
}