{
  "type": "Feature",
  "properties": {
    "addr:full":"00176 Roma Roma Roma 00176",
    "addr:postcode":"00176;00176",
    "iso:country":"IT",
    "sg:address":"00176 Roma",
    "sg:city":"Roma",
    "sg:orig_category":"Serramenti Ed Infissi",
    "sg:phone":"+39 06 295934",
    "sg:postcode":"00176",
    "sg:province":"Roma",
    "wof:name":"Euro Door Sas",
    "wof:placetype":"venue"
},
  "geometry": {"coordinates":[12.535143,41.886593],"type":"Point"}
}