{
  "type": "Feature",
  "properties": {
    "iso:country":"IT",
    "sg:address":"20144 Milano",
    "sg:city":"Milano",
    "sg:orig_category":"Studi E Consulenze Amministrative, Commerciali E Aziendali. Consulenze Tecniche, Amministrative E Perizie. Professionisti - Studi E Servizi Ed Associazioni Di Interesse Aziendale",
    "sg:phone":"+39 02 498 7120",
    "sg:postcode":"20144",
    "sg:province":"Milano",
    "wof:name":"Marino Pancrazio",
    "wof:placetype":"venue"
},
  "geometry": {"coordinates":[9.16057,45.458389],"type":"Point"}
}