{
  "type": "Feature",
  "properties": {
    "iso:country":"IT",
    "sg:address":"4, Via Privata O.t.o. 19136 La Spezia",
    "sg:classifiers":[
        {
            "category":"Autos & Motor Vehicles",
            "subcategory":"Automobile Sales",
            "type":"Retail Goods"
        }
    ],
    "sg:phone":"+39 0187 518690",
    "sg:province":"SP",
    "sg:tags":[
        "equipment",
        "transport"
    ],
    "wof:name":"Style And Performance Sas Di Bruschi Massimo E C.",
    "wof:placetype":"venue"
},
  "geometry": {"coordinates":[9.862114,44.113327],"type":"Point"}
}