{
  "type": "Feature",
  "properties": {
    "addr:full":"4, Via Ferraria 33050 Pozzuolo Del Friuli Pozzuolo del Friuli Udine 33050",
    "addr:postcode":"33050;33050",
    "addr:street":"Via Ferraria;Del Friuli",
    "iso:country":"IT",
    "sg:address":"4, Via Ferraria 33050 Pozzuolo Del Friuli",
    "sg:city":"Pozzuolo del Friuli",
    "sg:classifiers":[
        {
            "category":"Home & Garden",
            "subcategory":"Home Furnishings",
            "type":"Retail Goods"
        }
    ],
    "sg:phone":"+39 0432 665033",
    "sg:postcode":"33050",
    "sg:province":"Udine",
    "sg:tags":[
        "household"
    ],
    "wof:name":"Natco S.p.a.",
    "wof:placetype":"venue"
},
  "geometry": {"coordinates":[13.200725,45.961769],"type":"Point"}
}