{
  "type": "Feature",
  "properties": {
    "addr:full":"5, Piazza Cavour 57034 Campo Nell'elba Livorno 57034",
    "addr:postcode":"57034;57034",
    "addr:street":"Piazza Cavour",
    "iso:country":"IT",
    "sg:address":"5, Piazza Cavour 57034 Campo Nell'elba",
    "sg:classifiers":[
        {
            "category":"Shopping",
            "subcategory":"Jewelry",
            "type":"Retail Goods"
        }
    ],
    "sg:phone":"+39 0565 978101",
    "sg:postcode":"57034",
    "sg:province":"Livorno",
    "sg:tags":[
        "jewellery"
    ],
    "wof:name":"Giannini Walter Srl",
    "wof:placetype":"venue"
},
  "geometry": {"coordinates":[10.211811,42.751907],"type":"Point"}
}