{
  "type": "Feature",
  "properties": {
    "iso:country":"IT",
    "sg:address":"4, Via Stazione 37040 Zimella",
    "sg:city":"Zimella",
    "sg:classifiers":[
        {
            "category":"Utilities",
            "subcategory":"Telephone",
            "type":"Services"
        }
    ],
    "sg:phone":"+39 0442 412003",
    "sg:postcode":"37040",
    "sg:province":"Verona",
    "sg:tags":[
        "telecommunication"
    ],
    "wof:name":"Forma S.r.l.",
    "wof:placetype":"venue"
},
  "geometry": {"coordinates":[11.372843,45.348122],"type":"Point"}
}