{
  "type": "Feature",
  "properties": {
    "iso:country":"IT",
    "sg:address":"46020 Motteggiana",
    "sg:city":"Motteggiana",
    "sg:orig_category":"Materiali Edili",
    "sg:phone":"+39 0376 527521",
    "sg:postcode":"46020",
    "sg:province":"Mantova",
    "wof:name":"Metalcover Srl",
    "wof:placetype":"venue"
},
  "geometry": {"coordinates":[10.7984,45.148777],"type":"Point"}
}