{
  "type": "Feature",
  "properties": {
    "iso:country":"IT",
    "sg:address":"41011 Campogalliano",
    "sg:city":"Campogalliano",
    "sg:orig_category":"Utensili Meccanici E Materiali",
    "sg:phone":"+39 059 851668",
    "sg:postcode":"41011",
    "sg:province":"Modena",
    "wof:name":"Carbemilia Gas Srl",
    "wof:placetype":"venue"
},
  "geometry": {"coordinates":[10.840607,44.696598],"type":"Point"}
}