{
  "type": "Feature",
  "properties": {
    "iso:country":"IT",
    "sg:address":"49, Via Enrico Fermi 22030 Orsenigo",
    "sg:city":"Orsenigo",
    "sg:classifiers":[
        {
            "category":"Shopping",
            "subcategory":"Crafts & Fabrics",
            "type":"Retail Goods"
        }
    ],
    "sg:phone":"+39 39031619611",
    "sg:postcode":"22030",
    "sg:province":"Como",
    "wof:name":"Maspero Giorgio",
    "wof:placetype":"venue"
},
  "geometry": {"coordinates":[9.1212949753,45.737071991],"type":"Point"}
}