{
  "type": "Feature",
  "properties": {
    "addr:full":"37060 Castel D'azzano Azzano Verona 37060",
    "addr:postcode":"37060;37060",
    "iso:country":"IT",
    "sg:address":"37060 Castel D'azzano",
    "sg:city":"Azzano",
    "sg:classifiers":[
        {
            "category":"Sports & Exercise",
            "subcategory":"Ice Rink",
            "type":"Entertainment"
        }
    ],
    "sg:phone":"+39 045 519976",
    "sg:postcode":"37060",
    "sg:province":"Verona",
    "sg:tags":[
        "article",
        "shopping",
        "supplies"
    ],
    "wof:name":"Marangoni Angiolino",
    "wof:placetype":"venue"
},
  "geometry": {"coordinates":[10.93223,45.360847],"type":"Point"}
}