{
  "type": "Feature",
  "properties": {
    "addr:full":"32, Via Niga 25020 Azzano Mella Azzano Mella Brescia 25020",
    "addr:postcode":"25020;mella;25020",
    "addr:street":"Via Niga",
    "iso:country":"IT",
    "sg:address":"32, Via Niga 25020 Azzano Mella",
    "sg:city":"Azzano Mella",
    "sg:classifiers":[
        {
            "category":"Food & Beverages",
            "subcategory":"Groceries & Convenience Stores",
            "type":"Retail Goods"
        }
    ],
    "sg:phone":"+39 030 974 8940",
    "sg:postcode":"25020",
    "sg:province":"Brescia",
    "sg:tags":[
        "drink"
    ],
    "wof:name":"Micheli Battista Di Micheli Giuseppe & Figli S.n.c.",
    "wof:placetype":"venue"
},
  "geometry": {"coordinates":[10.112372,45.455307],"type":"Point"}
}