{
  "type": "Feature",
  "properties": {
    "addr:full":"16100 Genova GE",
    "addr:postcode":"16100",
    "iso:country":"IT",
    "sg:address":"16100 Genova",
    "sg:orig_category":"Bagno - Accessori E Mobili",
    "sg:phone":"+39 010 814843",
    "sg:province":"GE",
    "wof:name":"Della Casa Fratelli & Figli Spa",
    "wof:placetype":"venue"
},
  "geometry": {"coordinates":[8.925562,44.44828],"type":"Point"}
}