{
  "type": "Feature",
  "properties": {
    "addr:full":"22070 Vertemate Con Minoprio Minoprio Como 22070",
    "addr:postcode":"22070;22070",
    "addr:street":"Con Minoprio Minoprio",
    "iso:country":"IT",
    "sg:address":"22070 Vertemate Con Minoprio",
    "sg:city":"Minoprio",
    "sg:orig_category":"Centri Di Estetica E Cosmesi E Servizi",
    "sg:phone":"+39 031 901443",
    "sg:postcode":"22070",
    "sg:province":"Como",
    "wof:name":"Solarium Sas",
    "wof:placetype":"venue"
},
  "geometry": {"coordinates":[9.054238,45.762001],"type":"Point"}
}