{
  "type": "Feature",
  "properties": {
    "iso:country":"IT",
    "sg:address":"8, Via Per Fagnano Olona 21058 Solbiate Olona",
    "sg:city":"Solbiate Olona",
    "sg:classifiers":[
        {
            "category":"Manufacturing",
            "subcategory":"Paper Products",
            "type":"Manufacturing & Wholesale Goods"
        }
    ],
    "sg:phone":"+39 0331 649481",
    "sg:postcode":"21058",
    "sg:province":"Varese",
    "sg:tags":[
        "cardboard"
    ],
    "wof:name":"Industrie Grafiche Colombo S.r.l.",
    "wof:placetype":"venue"
},
  "geometry": {"coordinates":[8.8677406311,45.6521530151],"type":"Point"}
}