{
  "type": "Feature",
  "properties": {
    "iso:country":"IT",
    "sg:address":"7, Via Della Maggiola 62010 Montecosaro",
    "sg:city":"Montecosaro",
    "sg:classifiers":[
        {
            "category":"Personal",
            "subcategory":"Shoe Repair & Shine",
            "type":"Services"
        }
    ],
    "sg:phone":"+39 0733 564801",
    "sg:postcode":"62010",
    "sg:province":"Macerata",
    "sg:tags":[
        "leather"
    ],
    "wof:name":"Calzaturificio Men",
    "wof:placetype":"venue"
},
  "geometry": {"coordinates":[13.645617,43.278622],"type":"Point"}
}