{
  "type": "Feature",
  "properties": {
    "iso:country":"IT",
    "sg:address":"13018 Valduggia",
    "sg:city":"Valduggia",
    "sg:orig_category":"Impiantistica E Prodotti Tecnologici Per Edilizia. Forniture Industriali Per Prevenzione, Controllo E Sicurezza",
    "sg:phone":"+39 0163 47534",
    "sg:postcode":"13018",
    "sg:province":"Vercelli",
    "wof:name":"Rigamonti Ghisa Srl",
    "wof:placetype":"venue"
},
  "geometry": {"coordinates":[8.278388,45.711861],"type":"Point"}
}