{
  "type": "Feature",
  "properties": {
    "addr:full":"25081 Bedizzole Bedizzole Brescia 25081",
    "addr:postcode":"25081;25081",
    "iso:country":"IT",
    "sg:address":"25081 Bedizzole",
    "sg:city":"Bedizzole",
    "sg:orig_category":"Arredi Ed Attrezzature Per Uffici",
    "sg:phone":"+39 030 687 0675",
    "sg:postcode":"25081",
    "sg:province":"Brescia",
    "wof:name":"Gruppo Korel Srl",
    "wof:placetype":"venue"
},
  "geometry": {"coordinates":[10.440535,45.508884],"type":"Point"}
}