{
  "type": "Feature",
  "properties": {
    "iso:country":"IT",
    "sg:address":"29100 Piacenza",
    "sg:city":"Piacenza",
    "sg:orig_category":"Impianti, Attrezzature E Forniture Sanitarie Ed Ospedaliere",
    "sg:phone":"+39 0523 713368",
    "sg:postcode":"29100",
    "sg:province":"Piacenza",
    "wof:name":"Tecnomedica Di Vincenzo Coppola",
    "wof:placetype":"venue"
},
  "geometry": {"coordinates":[11.550364,45.129669],"type":"Point"}
}