{
  "type": "Feature",
  "properties": {
    "addr:full":"00189 Roma Roma Roma 00189",
    "addr:postcode":"00189;00189",
    "iso:country":"IT",
    "sg:address":"00189 Roma",
    "sg:city":"Roma",
    "sg:orig_category":"Scuole E Servizi Scolastici",
    "sg:phone":"+39 06 3031 5054",
    "sg:postcode":"00189",
    "sg:province":"Roma",
    "wof:name":"Crescere Giocando",
    "wof:placetype":"venue"
},
  "geometry": {"coordinates":[12.423966,41.985367],"type":"Point"}
}