{
  "type": "Feature",
  "properties": {
    "addr:full":"Via Crevada 9/c 31020 San Pietro Di Feletto San Pietro di Feletto Treviso 31020",
    "addr:housenumber":"9 / c;pietro di feletto",
    "addr:postcode":"31020;pietro di feletto;31020",
    "addr:street":"Via Crevada",
    "iso:country":"IT",
    "sg:address":"Via Crevada 9/c 31020 San Pietro Di Feletto",
    "sg:city":"San Pietro di Feletto",
    "sg:classifiers":[
        {
            "category":"Landmark",
            "subcategory":"Marketplace",
            "type":"Public Place"
        }
    ],
    "sg:postcode":"31020",
    "sg:province":"Treviso",
    "sg:tags":[
        "industry",
        "part",
        "bought-in",
        "furniture"
    ],
    "sg:website":"www.sitapan.it",
    "wof:name":"Sitapan Srl",
    "wof:placetype":"venue"
},
  "geometry": {"coordinates":[12.254394,45.870609],"type":"Point"}
}