{
  "type": "Feature",
  "properties": {
    "iso:country":"IT",
    "sg:address":"96100 Siracusa",
    "sg:city":"Siracusa",
    "sg:orig_category":"Serramenti Ed Infissi. Forniture Industriali Per Prevenzione, Controllo E Sicurezza",
    "sg:phone":"+39 0931 412391",
    "sg:postcode":"96100",
    "sg:province":"Siracusa",
    "wof:name":"R.rem Di Regalbuto Antonino",
    "wof:placetype":"venue"
},
  "geometry": {"coordinates":[15.211642,37.092739],"type":"Point"}
}