{
  "type": "Feature",
  "properties": {
    "addr:full":"81030 Casapesenna Casapesenna Caserta 81030",
    "addr:postcode":"81030;81030",
    "iso:country":"IT",
    "sg:address":"81030 Casapesenna",
    "sg:city":"Casapesenna",
    "sg:orig_category":"Carburanti - Produzione E Commercio",
    "sg:phone":"+39 081 892 4488",
    "sg:postcode":"81030",
    "sg:province":"Caserta",
    "wof:name":"Diana Petroli Srl",
    "wof:placetype":"venue"
},
  "geometry": {"coordinates":[14.177638,40.986057],"type":"Point"}
}