{
  "type": "Feature",
  "properties": {
    "iso:country":"IT",
    "sg:address":"23870 Cernusco Lombardone",
    "sg:city":"Cernusco Lombardone",
    "sg:classifiers":[
        {
            "category":"Health Services",
            "subcategory":"Health Practitioner",
            "type":"Services"
        }
    ],
    "sg:phone":"+39 039 990 6360",
    "sg:postcode":"23870",
    "sg:province":"Lecco",
    "sg:tags":[
        "medici"
    ],
    "wof:name":"Trezza Lorenzo",
    "wof:placetype":"venue"
},
  "geometry": {"coordinates":[9.4055023193,45.6930885315],"type":"Point"}
}