{
  "type": "Feature",
  "properties": {
    "iso:country":"IT",
    "sg:address":"Via Fulton 16 B 40017 San Giovanni In Persiceto",
    "sg:city":"San Giovanni in Persiceto",
    "sg:classifiers":[
        {
            "category":"Banks & Credit Unions",
            "subcategory":"Investment Brokerage",
            "type":"Services"
        }
    ],
    "sg:phone":"+39 051 687 1070",
    "sg:postcode":"40017",
    "sg:province":"Bologna",
    "sg:tags":[
        "cosmetic",
        "preparations",
        "bath"
    ],
    "sg:website":"www.pac-beautyprojekt.it",
    "wof:name":"Pac Beautyprojekt Srl",
    "wof:placetype":"venue"
},
  "geometry": {"coordinates":[11.200355,44.621681],"type":"Point"}
}