{
  "type": "Feature",
  "properties": {
    "iso:country":"IT",
    "sg:address":"20019 Settimo Milanese",
    "sg:city":"Settimo Milanese",
    "sg:classifiers":[
        {
            "category":"Organizations",
            "subcategory":"Community Association",
            "type":"Services"
        }
    ],
    "sg:phone":"+39 02 3350 2236",
    "sg:postcode":"20019",
    "sg:province":"Milano",
    "sg:tags":[
        "machine",
        "tool",
        "material",
        "systems",
        "mechanical"
    ],
    "sg:website":"http://www.carbonini.it",
    "wof:name":"Carbonini Santino Success. Srl",
    "wof:placetype":"venue"
},
  "geometry": {"coordinates":[9.074018,45.47644],"type":"Point"}
}