{
  "type": "Feature",
  "properties": {
    "addr:full":"37, Via Scarlatti 41019 Soliera Soliera Modena 41019",
    "addr:postcode":"41019;41019",
    "addr:street":"Via Scarlatti",
    "iso:country":"IT",
    "sg:address":"37, Via Scarlatti 41019 Soliera",
    "sg:city":"Soliera",
    "sg:classifiers":[
        {
            "category":"Shopping",
            "subcategory":"Clothing, Apparel, & Fashions",
            "type":"Retail Goods"
        }
    ],
    "sg:phone":"+39 39059566803",
    "sg:postcode":"41019",
    "sg:province":"Modena",
    "sg:tags":[
        "clothing",
        "accessory"
    ],
    "wof:name":"Diesse (s.n.c.)",
    "wof:placetype":"venue"
},
  "geometry": {"coordinates":[10.912222,44.728539],"type":"Point"}
}