{
  "type": "Feature",
  "properties": {
    "addr:full":"Via Trieste 4 20096 Pioltello Pioltello Milano 20096",
    "addr:housenumber":"4",
    "addr:postcode":"20096;20096",
    "addr:street":"Via Trieste",
    "iso:country":"IT",
    "sg:address":"Via Trieste 4 20096 Pioltello",
    "sg:city":"Pioltello",
    "sg:orig_category":"Screw Wire And Rivet Wire",
    "sg:phone":"+39 02 926 7141",
    "sg:postcode":"20096",
    "sg:province":"Milano",
    "wof:name":"Gife Srl",
    "wof:placetype":"venue"
},
  "geometry": {"coordinates":[9.318376,45.495113],"type":"Point"}
}