{
  "type": "Feature",
  "properties": {
    "addr:full":"20/22, Via John Fitzgerald Kennedy 24040 Ciserano Ciserano Bergamo 24040",
    "addr:housenumber":"20 / 22",
    "addr:postcode":"24040;24040",
    "addr:street":"Via John Fitzgerald Kennedy",
    "iso:country":"IT",
    "sg:address":"20/22, Via John Fitzgerald Kennedy 24040 Ciserano",
    "sg:city":"Ciserano",
    "sg:classifiers":[
        {
            "category":"Shopping",
            "type":"Retail Goods"
        }
    ],
    "sg:phone":"+39 39035884438",
    "sg:postcode":"24040",
    "sg:province":"Bergamo",
    "sg:tags":[
        "finished",
        "-",
        "metallic"
    ],
    "wof:name":"Maros (s.n.c.)",
    "wof:placetype":"venue"
},
  "geometry": {"coordinates":[9.5926828384,45.5837249756],"type":"Point"}
}