{
  "type": "Feature",
  "properties": {
    "iso:country":"IT",
    "sg:address":"20144 Milano",
    "sg:city":"Milano",
    "sg:orig_category":"Ospedali E Servizi Sanitari",
    "sg:phone":"+39 02 4331 9192",
    "sg:postcode":"20144",
    "sg:province":"Milano",
    "wof:name":"Studio Radiologico Trecate Srl",
    "wof:placetype":"venue"
},
  "geometry": {"coordinates":[9.165259,45.456036],"type":"Point"}
}