{
  "type": "Feature",
  "properties": {
    "addr:full":"13833 Portula Portula Biella 13833",
    "addr:housenumber":"13833",
    "addr:postcode":"13833",
    "addr:street":"Portula Portula",
    "iso:country":"IT",
    "sg:address":"13833 Portula",
    "sg:city":"Portula",
    "sg:orig_category":"Macchine Tessili",
    "sg:phone":"+39 015 767653",
    "sg:postcode":"13833",
    "sg:province":"Biella",
    "sg:website":"http://www.minox.it",
    "wof:name":"Minox Spa",
    "wof:placetype":"venue"
},
  "geometry": {"coordinates":[8.179749,45.685001],"type":"Point"}
}