{
  "type": "Feature",
  "properties": {
    "iso:country":"IT",
    "sg:address":"Via Palmentello, 18 84012 Angri",
    "sg:city":"Angri",
    "sg:classifiers":[
        {
            "category":"Manufacturing",
            "subcategory":"Chemicals & Compounds",
            "type":"Manufacturing & Wholesale Goods"
        }
    ],
    "sg:phone":"+39 081 513 8915",
    "sg:postcode":"84012",
    "sg:province":"Salerno",
    "sg:tags":[
        "laboratory"
    ],
    "sg:website":"www.chematil.it",
    "wof:name":"Chematil S.r.l.",
    "wof:placetype":"venue"
},
  "geometry": {"coordinates":[14.765912,40.677956],"type":"Point"}
}