{
  "type": "Feature",
  "properties": {
    "iso:country":"IT",
    "sg:address":"Via Brignole De Ferrari 2/8 16125 Genova",
    "sg:city":"Genova",
    "sg:classifiers":[
        {
            "category":"Manufacturing",
            "subcategory":"Rubber & Plastics",
            "type":"Manufacturing & Wholesale Goods"
        }
    ],
    "sg:phone":"+39 010 251 2128",
    "sg:postcode":"16125",
    "sg:province":"Genova",
    "sg:tags":[
        "additive"
    ],
    "wof:name":"Polichem S.r.l",
    "wof:placetype":"venue"
},
  "geometry": {"coordinates":[8.929622,44.414745],"type":"Point"}
}