{
  "type": "Feature",
  "properties": {
    "iso:country":"IT",
    "sg:address":"20094 Corsico",
    "sg:city":"Corsico",
    "sg:orig_category":"Valvole E Apparecchiature Di Misura. Elettrotecnica Industriale, Prodotti E Apparecchiature",
    "sg:phone":"+39 02 447 1865",
    "sg:postcode":"20094",
    "sg:province":"Milano",
    "wof:name":"Meccanica R.p.c.",
    "wof:placetype":"venue"
},
  "geometry": {"coordinates":[9.116317749,45.4346122742],"type":"Point"}
}