{
  "type": "Feature",
  "properties": {
    "iso:country":"IT",
    "sg:address":"00121 Lido Di Ostia",
    "sg:orig_category":"Servizi Per Aziende, Manifestazioni E Supporto Agli Scambi Commerciali",
    "sg:phone":"+39 06 561 1048",
    "sg:postcode":"00121",
    "sg:province":"Roma",
    "wof:name":"Micheli Anna",
    "wof:placetype":"venue"
},
  "geometry": {"coordinates":[12.275555,41.731773],"type":"Point"}
}