{
  "type": "Feature",
  "properties": {
    "iso:country":"IT",
    "sg:address":"10078 Venaria",
    "sg:orig_category":"Professionisti - Studi E Servizi Ed Associazioni Di Interesse Aziendale. Associazioni Ed Organismi Di Interesse Pubblico",
    "sg:phone":"+39 011 452 3311",
    "sg:postcode":"10078",
    "sg:province":"Torino",
    "wof:name":"Murdocca Antonio",
    "wof:placetype":"venue"
},
  "geometry": {"coordinates":[7.6232891083,45.1437339783],"type":"Point"}
}