{
  "type": "Feature",
  "properties": {
    "iso:country":"IT",
    "sg:address":"Via Campania 19 40024 Castel San Pietro Terme",
    "sg:city":"Castel San Pietro Terme",
    "sg:classifiers":[
        {
            "category":"Autos & Motor Vehicles",
            "subcategory":"Auto Supplies",
            "type":"Retail Goods"
        }
    ],
    "sg:phone":"+39 051 946746",
    "sg:postcode":"40024",
    "sg:province":"Bologna",
    "sg:tags":[
        "part",
        "spare",
        "motorcycle",
        "accessory"
    ],
    "sg:website":"www.pbr.it",
    "wof:name":"Pbr Sprockets Srl",
    "wof:placetype":"venue"
},
  "geometry": {"coordinates":[11.5253973007,44.4308815002],"type":"Point"}
}