{
  "type": "Feature",
  "properties": {
    "addr:full":"94100 Enna Enna Enna 94100",
    "addr:postcode":"94100;94100",
    "iso:country":"IT",
    "sg:address":"94100 Enna",
    "sg:city":"Enna",
    "sg:orig_category":"Pubblica Amministrazione",
    "sg:phone":"+39 0935 40111",
    "sg:postcode":"94100",
    "sg:province":"Enna",
    "wof:name":"Comune Di Enna",
    "wof:placetype":"venue"
},
  "geometry": {"coordinates":[14.2755346298,37.5663871765],"type":"Point"}
}