{
  "type": "Feature",
  "properties": {
    "iso:country":"IT",
    "sg:address":"Via Xx Settembre 4; Falconara; 60015",
    "sg:classifiers":[
        {
            "category":"Banks & Credit Unions",
            "subcategory":"Bank",
            "type":"Services"
        }
    ],
    "sg:phone":"+39 071 914511",
    "sg:postcode":"60015",
    "sg:province":"Ancona",
    "wof:name":"Banca Delle Marche Spa",
    "wof:placetype":"venue"
},
  "geometry": {"coordinates":[13.363377,43.615791],"type":"Point"}
}