{
  "type": "Feature",
  "properties": {
    "addr:full":"80059 Torre Del Greco Torre del Greco Napoli 80059",
    "addr:postcode":"80059;80059",
    "iso:country":"IT",
    "sg:address":"80059 Torre Del Greco",
    "sg:city":"Torre del Greco",
    "sg:orig_category":"Forniture Per Congressi, Fiere E Manifestazioni",
    "sg:phone":"+39 081 849 7428",
    "sg:postcode":"80059",
    "sg:province":"Napoli",
    "wof:name":"Beautiful Days",
    "wof:placetype":"venue"
},
  "geometry": {"coordinates":[14.3364067078,40.8139038086],"type":"Point"}
}