{
  "type": "Feature",
  "properties": {
    "addr:full":"13030 Caresanablot Caresanablot Vercelli 13030",
    "addr:housenumber":"13030",
    "addr:postcode":"13030",
    "addr:street":"Caresanablot Caresanablot",
    "iso:country":"IT",
    "sg:address":"13030 Caresanablot",
    "sg:city":"Caresanablot",
    "sg:orig_category":"Servizi E Lavori Per Agricoltura E Zootecnia. Imprese Di Costruzioni Civili Ed Industriali",
    "sg:phone":"+39 0161 33301",
    "sg:postcode":"13030",
    "sg:province":"Vercelli",
    "wof:name":"Setti Elettroidraulica Di Setti Italo & C. Sas",
    "wof:placetype":"venue"
},
  "geometry": {"coordinates":[8.388285,45.357548],"type":"Point"}
}