{
  "type": "Feature",
  "properties": {
    "addr:full":"25030 Torbole Casaglia Torbole Casaglia Brescia 25030",
    "addr:postcode":"25030;25030",
    "iso:country":"IT",
    "sg:address":"25030 Torbole Casaglia",
    "sg:city":"Torbole Casaglia",
    "sg:orig_category":"Prodotti E Manufatti In Materie Plastiche. Forniture Per Edilizia E Lavori Pubblici",
    "sg:phone":"+39 030 265 0190",
    "sg:postcode":"25030",
    "sg:province":"Brescia",
    "wof:name":"Bettoni Plastica Srl",
    "wof:placetype":"venue"
},
  "geometry": {"coordinates":[10.1165742874,45.5136108398],"type":"Point"}
}