{
  "type": "Feature",
  "properties": {
    "iso:country":"IT",
    "sg:address":"56032 Buti",
    "sg:city":"Buti",
    "sg:orig_category":"Non-classified Establishments",
    "sg:phone":"+39 0587 723220",
    "sg:postcode":"56032",
    "sg:province":"Pisa",
    "wof:name":"Vannucci Massimo Sergio & C. (s.n.c.)",
    "wof:placetype":"venue"
},
  "geometry": {"coordinates":[10.5836458206,43.7284393311],"type":"Point"}
}