{
  "type": "Feature",
  "properties": {
    "addr:full":"15, Via Galletti Giuseppe 40134 Bologna Bologna Bologna 40134",
    "addr:postcode":"40134;40134",
    "addr:street":"Via Galletti Giuseppe",
    "iso:country":"IT",
    "sg:address":"15, Via Galletti Giuseppe 40134 Bologna",
    "sg:city":"Bologna",
    "sg:classifiers":[
        {
            "category":"Manufacturing",
            "subcategory":"Metals",
            "type":"Manufacturing & Wholesale Goods"
        }
    ],
    "sg:phone":"+39 051 644 6616",
    "sg:postcode":"40134",
    "sg:province":"Bologna",
    "sg:tags":[
        "processing"
    ],
    "wof:name":"Zecchi Roberto (s.r.l.)",
    "wof:placetype":"venue"
},
  "geometry": {"coordinates":[11.3464813232,44.4942207336],"type":"Point"}
}