{
  "type": "Feature",
  "properties": {
    "iso:country":"IT",
    "sg:address":"8, Via Montello 36063 Marostica",
    "sg:city":"Marostica",
    "sg:classifiers":[
        {
            "category":"Professional",
            "subcategory":"Engineering",
            "type":"Services"
        }
    ],
    "sg:phone":"+39 0424 470822",
    "sg:postcode":"36063",
    "sg:province":"Vicenza",
    "sg:tags":[
        "machine",
        "-",
        "mechanical"
    ],
    "wof:name":"S.t.a. Mac. Snc Di Gianvito Salin & C.",
    "wof:placetype":"venue"
},
  "geometry": {"coordinates":[11.564074,45.72047],"type":"Point"}
}