{
  "type": "Feature",
  "properties": {
    "iso:country":"IT",
    "sg:address":"00183 Roma",
    "sg:city":"Roma",
    "sg:orig_category":"Cinematografia E Radiotelevisione. Forniture Per Il Settore Dello Spettacolo",
    "sg:phone":"+39 06 701 1961",
    "sg:postcode":"00183",
    "sg:province":"Roma",
    "wof:name":"Eidos Srl",
    "wof:placetype":"venue"
},
  "geometry": {"coordinates":[12.578022,41.80909],"type":"Point"}
}