{
  "type": "Feature",
  "properties": {
    "iso:country":"IT",
    "sg:address":"Via Ferraris Galileo 45021 Badia Polesine",
    "sg:city":"Badia Polesine",
    "sg:classifiers":[
        {
            "category":"Shopping",
            "subcategory":"Clothing, Apparel, & Fashions",
            "type":"Retail Goods"
        }
    ],
    "sg:phone":"+39 0425 590736",
    "sg:postcode":"45021",
    "sg:province":"Rovigo",
    "sg:tags":[
        "clothes"
    ],
    "wof:name":"Vogue (s.r.l.)",
    "wof:placetype":"venue"
},
  "geometry": {"coordinates":[11.789797,45.070736],"type":"Point"}
}