{
  "type": "Feature",
  "properties": {
    "iso:country":"IT",
    "sg:address":"Via Zona Industriale 84020 Oliveto Citra",
    "sg:city":"Oliveto Citra",
    "sg:classifiers":[
        {
            "category":"Manufacturing",
            "subcategory":"Rubber & Plastics",
            "type":"Manufacturing & Wholesale Goods"
        }
    ],
    "sg:phone":"+39 0828 995615",
    "sg:postcode":"84020",
    "sg:province":"Salerno",
    "wof:name":"Sud Gomma Sas Di C. Graziono & C.",
    "wof:placetype":"venue"
},
  "geometry": {"coordinates":[14.765912,40.677956],"type":"Point"}
}