{
  "type": "Feature",
  "properties": {
    "addr:full":"Via Africa Orientale,; Margherita Di Savoia; 71044 Margherita di Savoia Foggia 71044",
    "addr:postcode":"71044;71044",
    "addr:street":"Via Africa;Di Savoia",
    "iso:country":"IT",
    "sg:address":"Via Africa Orientale,; Margherita Di Savoia; 71044",
    "sg:city":"Margherita di Savoia",
    "sg:classifiers":[
        {
            "category":"Banks & Credit Unions",
            "subcategory":"Bank",
            "type":"Services"
        }
    ],
    "sg:phone":"+39 0883 656043",
    "sg:postcode":"71044",
    "sg:province":"Foggia",
    "wof:name":"Banca Popolare Di Bari",
    "wof:placetype":"venue"
},
  "geometry": {"coordinates":[16.147091,41.376911],"type":"Point"}
}