{
  "type": "Feature",
  "properties": {
    "iso:country":"IT",
    "sg:address":"81043 Capua",
    "sg:city":"Capua",
    "sg:orig_category":"Impianti, Attrezzature E Forniture Sanitarie Ed Ospedaliere",
    "sg:phone":"+39 0823 969315",
    "sg:postcode":"81043",
    "sg:province":"Caserta",
    "wof:name":"Teknos Srl",
    "wof:placetype":"venue"
},
  "geometry": {"coordinates":[14.266403,41.081352],"type":"Point"}
}