{
  "type": "Feature",
  "properties": {
    "addr:full":"10023 Chieri Chieri Torino 10023",
    "addr:postcode":"10023;10023",
    "iso:country":"IT",
    "sg:address":"10023 Chieri",
    "sg:city":"Chieri",
    "sg:orig_category":"Arte Ed Artigianato Artistico",
    "sg:phone":"+39 011 941 2665",
    "sg:postcode":"10023",
    "sg:province":"Torino",
    "wof:name":"Ventura Piselli Marco Ernesto",
    "wof:placetype":"venue"
},
  "geometry": {"coordinates":[7.847991,45.019928],"type":"Point"}
}