{
  "type": "Feature",
  "properties": {
    "iso:country":"IT",
    "sg:address":"20121 Milano",
    "sg:city":"Milano",
    "sg:orig_category":"Arte Ed Artigianato Artistico",
    "sg:phone":"+39 02 7202 3999",
    "sg:postcode":"20121",
    "sg:province":"Milano",
    "wof:name":"Aligi Sassu Srl",
    "wof:placetype":"venue"
},
  "geometry": {"coordinates":[9.187692,45.471329],"type":"Point"}
}