{
  "type": "Feature",
  "properties": {
    "addr:full":"16, Via Padova 20034 Giussano Giussano Milano 20034",
    "addr:postcode":"20034;20034",
    "addr:street":"Via Padova",
    "iso:country":"IT",
    "sg:address":"16, Via Padova 20034 Giussano",
    "sg:city":"Giussano",
    "sg:classifiers":[
        {
            "category":"Manufacturing",
            "subcategory":"Rubber & Plastics",
            "type":"Manufacturing & Wholesale Goods"
        }
    ],
    "sg:phone":"+39 036 231 0615",
    "sg:postcode":"20034",
    "sg:province":"Milano",
    "wof:name":"Mauri & C. Snc Di Carlo Mauri E C.",
    "wof:placetype":"venue"
},
  "geometry": {"coordinates":[9.1938562393,45.6729850769],"type":"Point"}
}