{
  "type": "Feature",
  "properties": {
    "iso:country":"IT",
    "sg:address":"30, Via Brennero 37020 Dolce'",
    "sg:classifiers":[
        {
            "category":"Shopping",
            "subcategory":"Computers & Home Electronics",
            "type":"Retail Goods"
        }
    ],
    "sg:phone":"+39 045 727 0567",
    "sg:postcode":"37020",
    "sg:province":"Verona",
    "sg:tags":[
        "electronic",
        "electrical",
        "equipment"
    ],
    "wof:name":"Genio Italia Srl",
    "wof:placetype":"venue"
},
  "geometry": {"coordinates":[11.081414,45.929028],"type":"Point"}
}