{
  "type": "Feature",
  "properties": {
    "iso:country":"IT",
    "sg:address":"30015 Chioggia",
    "sg:city":"Chioggia",
    "sg:classifiers":[
        {
            "category":"Health Services",
            "subcategory":"Health Practitioner",
            "type":"Services"
        }
    ],
    "sg:phone":"+39 041 499630",
    "sg:postcode":"30015",
    "sg:province":"Venezia",
    "sg:tags":[
        "medici"
    ],
    "wof:name":"D'alessandro Giuseppe",
    "wof:placetype":"venue"
},
  "geometry": {"coordinates":[12.188084,45.223377],"type":"Point"}
}