{
  "type": "Feature",
  "properties": {
    "iso:country":"IT",
    "sg:address":"24021 Albino",
    "sg:city":"Albino",
    "sg:orig_category":"Riparazione Dei Mezzi Di Trasporto. Servizi Ausiliari Dei Mezzi Di Trasporto",
    "sg:phone":"+39 035 760211",
    "sg:postcode":"24021",
    "sg:province":"Bergamo",
    "wof:name":"Lella Lombardi Autosport Srl",
    "wof:placetype":"venue"
},
  "geometry": {"coordinates":[9.799617,45.76907],"type":"Point"}
}