{
  "type": "Feature",
  "properties": {
    "iso:country":"IT",
    "sg:address":"88100 Catanzaro",
    "sg:city":"Catanzaro",
    "sg:orig_category":"Abbigliamento Intimo, Calze E Costumi Da Bagno",
    "sg:phone":"+39 0961 32964",
    "sg:postcode":"88100",
    "sg:province":"Catanzaro",
    "wof:name":"Leobono Enrico",
    "wof:placetype":"venue"
},
  "geometry": {"coordinates":[16.629961,38.829281],"type":"Point"}
}