{
  "type": "Feature",
  "properties": {
    "iso:country":"IT",
    "sg:address":"Via Dell'archeologia 2 00065 Fiano Romano",
    "sg:city":"Fiano Romano",
    "sg:classifiers":[
        {
            "category":"Retail",
            "subcategory":"Laundry & Dry Cleaning",
            "type":"Services"
        }
    ],
    "sg:phone":"+39 0765 456006",
    "sg:postcode":"00065",
    "sg:province":"Roma",
    "sg:tags":[
        "machine",
        "spare",
        "part",
        "washing",
        "accessory"
    ],
    "sg:website":"www.nuovafolati.it",
    "wof:name":"Nuova Folati Srl",
    "wof:placetype":"venue"
},
  "geometry": {"coordinates":[12.587123,42.136993],"type":"Point"}
}