{
  "type": "Feature",
  "properties": {
    "iso:country":"IT",
    "sg:address":"46030 Sustinente",
    "sg:city":"Sustinente",
    "sg:orig_category":"Manufacturers: Prefabbricati",
    "sg:phone":"+39 0386 71111",
    "sg:postcode":"46030",
    "sg:province":"Mantova",
    "wof:name":"S.i.l.l.a. - Societa' Industrie Lavorazione Legno E Affini S.r.l.",
    "wof:placetype":"venue"
},
  "geometry": {"coordinates":[11.019231,45.070969],"type":"Point"}
}