{
  "type": "Feature",
  "properties": {
    "iso:country":"IT",
    "sg:address":"56121 Pisa",
    "sg:city":"Pisa",
    "sg:orig_category":"Servizi Ausiliari Di Analisi, Controllo E Ricerca",
    "sg:phone":"+39 050 985730",
    "sg:postcode":"56121",
    "sg:province":"Pisa",
    "sg:website":"http://www.novachymia.com",
    "wof:name":"Novachymia Snc",
    "wof:placetype":"venue"
},
  "geometry": {"coordinates":[10.426999,43.685623],"type":"Point"}
}