{
  "type": "Feature",
  "properties": {
    "iso:country":"IT",
    "sg:address":"22100 Como",
    "sg:city":"Como",
    "sg:orig_category":"Autonoleggio",
    "sg:phone":"+39 031 591299",
    "sg:postcode":"22100",
    "sg:province":"Como",
    "wof:name":"Abc Soc. Coop. R.l.",
    "wof:placetype":"venue"
},
  "geometry": {"coordinates":[9.085126,45.785622],"type":"Point"}
}