{
  "type": "Feature",
  "properties": {
    "iso:country":"IT",
    "sg:address":"20, Via Malipiero Gianfranco 20138 Milano",
    "sg:city":"Milano",
    "sg:classifiers":[
        {
            "category":"Professional",
            "subcategory":"Engineering",
            "type":"Services"
        }
    ],
    "sg:phone":"+39 39025061281",
    "sg:postcode":"20138",
    "sg:province":"Milano",
    "sg:tags":[
        "machine",
        "-",
        "mechanical"
    ],
    "wof:name":"O.g.e.m. Officina Geom. E. Mantelli (s.r.l.)",
    "wof:placetype":"venue"
},
  "geometry": {"coordinates":[9.203226,45.482468],"type":"Point"}
}