{
  "type": "Feature",
  "properties": {
    "iso:country":"IT",
    "sg:address":"67051 Avezzano",
    "sg:orig_category":"Automobili E Mezzi Di Trasporto",
    "sg:phone":"+39 0863 48031",
    "sg:postcode":"67051",
    "sg:province":"L'Aquila",
    "wof:name":"Brenta Euroindustrie Spa",
    "wof:placetype":"venue"
},
  "geometry": {"coordinates":[13.399934,42.350697],"type":"Point"}
}