{
  "type": "Feature",
  "properties": {
    "iso:country":"IT",
    "sg:address":"20124 Milano",
    "sg:city":"Milano",
    "sg:orig_category":"Servizi Culturali E Per Lo Spettacolo. Servizi Per Lo Sport E Il Tempo Libero. Associazioni Ed Organismi Di Interesse Pubblico",
    "sg:phone":"+39 02 670 6278",
    "sg:postcode":"20124",
    "sg:province":"Milano",
    "wof:name":"Associazione Di Studi Psicoanalitici",
    "wof:placetype":"venue"
},
  "geometry": {"coordinates":[9.208534,45.485828],"type":"Point"}
}