{
  "type": "Feature",
  "properties": {
    "addr:full":"Via Po 27010 Santa Cristina E Bissone Santa Cristina e Bissone Pavia 27010",
    "addr:postcode":"27010;27010",
    "addr:street":"Via Po;Cristina;Santa Cristina E",
    "iso:country":"IT",
    "sg:address":"Via Po 27010 Santa Cristina E Bissone",
    "sg:city":"Santa Cristina e Bissone",
    "sg:classifiers":[
        {
            "category":"Professional",
            "subcategory":"Engineering",
            "type":"Services"
        }
    ],
    "sg:phone":"+39 39038270356",
    "sg:postcode":"27010",
    "sg:province":"Pavia",
    "sg:tags":[
        "machine",
        "-",
        "mechanical"
    ],
    "wof:name":"Comi - Condor (s.p.a.)",
    "wof:placetype":"venue"
},
  "geometry": {"coordinates":[9.326697,45.077068],"type":"Point"}
}