{
  "type": "Feature",
  "properties": {
    "iso:country":"IT",
    "sg:address":"20155 Milano",
    "sg:city":"Milano",
    "sg:classifiers":[
        {
            "category":"Health Services",
            "subcategory":"Health Practitioner",
            "type":"Services"
        }
    ],
    "sg:phone":"+39 02 3921 7536",
    "sg:postcode":"20155",
    "sg:province":"Milano",
    "sg:tags":[
        "medici"
    ],
    "wof:name":"Longoni Paolo",
    "wof:placetype":"venue"
},
  "geometry": {"coordinates":[9.159319,45.492985],"type":"Point"}
}