{
  "type": "Feature",
  "properties": {
    "addr:full":"20154 Milano Milano Milano 20154",
    "addr:postcode":"20154;20154",
    "iso:country":"IT",
    "sg:address":"20154 Milano",
    "sg:city":"Milano",
    "sg:orig_category":"Arredo Cucina Ed Elettrodomestici. Elettrodomestici. Apparecchi, Attrezzature E Forniture Per Centri Estetici",
    "sg:phone":"+39 02 3310 1055",
    "sg:postcode":"20154",
    "sg:province":"Milano",
    "wof:name":"Rivola Andrea",
    "wof:placetype":"venue"
},
  "geometry": {"coordinates":[9.174697,45.478825],"type":"Point"}
}