{
  "type": "Feature",
  "properties": {
    "addr:full":"4, Via Pomponio Leto 20146 Milano Milano Milano 20146",
    "addr:postcode":"20146;20146",
    "addr:street":"Via Pomponio Leto",
    "iso:country":"IT",
    "sg:address":"4, Via Pomponio Leto 20146 Milano",
    "sg:city":"Milano",
    "sg:classifiers":[
        {
            "category":"Utilities",
            "subcategory":"Telephone",
            "type":"Services"
        }
    ],
    "sg:phone":"+39 39024692592",
    "sg:postcode":"20146",
    "sg:province":"Milano",
    "sg:tags":[
        "telecommunication"
    ],
    "wof:name":"Interfono (s.r.l.)",
    "wof:placetype":"venue"
},
  "geometry": {"coordinates":[9.15182,45.459705],"type":"Point"}
}