{
  "type": "Feature",
  "properties": {
    "iso:country":"IT",
    "sg:address":"20092 Cinisello Balsamo",
    "sg:city":"Cinisello Balsamo",
    "sg:orig_category":"Lavorazioni Metalli, Stampaggio E Saldatura",
    "sg:phone":"+39 02 6604 9521",
    "sg:postcode":"20092",
    "sg:province":"Milano",
    "wof:name":"Malvestiti Ernesto Spa",
    "wof:placetype":"venue"
},
  "geometry": {"coordinates":[9.209913,45.568794],"type":"Point"}
}