{
  "type": "Feature",
  "properties": {
    "addr:full":"20126 Milano Milano Milano 20126",
    "addr:postcode":"20126;20126",
    "iso:country":"IT",
    "sg:address":"20126 Milano",
    "sg:city":"Milano",
    "sg:orig_category":"Apparecchiature Ed Attrezzature Meccaniche. Elettronica Industriale, Prodotti E Apparecchiature. Impianti, Attrezzature E Forniture Sanitarie Ed Ospedaliere. Apparecchi, Attrezzature E Forniture Per C",
    "sg:phone":"+39 02 2700 7064",
    "sg:postcode":"20126",
    "sg:province":"Milano",
    "sg:website":"http://www.laserent.com",
    "wof:name":"Laser Entertainment Srl",
    "wof:placetype":"venue"
},
  "geometry": {"coordinates":[9.222031,45.509315],"type":"Point"}
}