{
  "type": "Feature",
  "properties": {
    "iso:country":"IT",
    "sg:address":"32035 Santa Giustina",
    "sg:city":"Formegan",
    "sg:orig_category":"Edilizia - Materiali",
    "sg:phone":"+39 0437 859222",
    "sg:postcode":"32035",
    "sg:province":"Belluno",
    "wof:name":"Ediltutto Srl",
    "wof:placetype":"venue"
},
  "geometry": {"coordinates":[12.01814,46.071083],"type":"Point"}
}