{
  "type": "Feature",
  "properties": {
    "iso:country":"IT",
    "sg:address":"97019 Vittoria",
    "sg:city":"Vittoria",
    "sg:orig_category":"Pavimenti Legno",
    "sg:phone":"+39 0932 981867",
    "sg:postcode":"97019",
    "sg:province":"Ragusa",
    "wof:name":"Cassisi Di Barrano Teresa E C. Snc",
    "wof:placetype":"venue"
},
  "geometry": {"coordinates":[14.5373477936,36.9501266479],"type":"Point"}
}