{
  "type": "Feature",
  "properties": {
    "iso:country":"IT",
    "sg:address":"1, Via Ingegnere Giuseppe Taliercio 31010 Ormelle",
    "sg:classifiers":[
        {
            "category":"Home & Garden",
            "subcategory":"Home Furnishings",
            "type":"Retail Goods"
        }
    ],
    "sg:phone":"+39 0422 745900",
    "sg:postcode":"31010",
    "sg:province":"Treviso",
    "sg:tags":[
        "household"
    ],
    "wof:name":"Abm Italia S.p.a.",
    "wof:placetype":"venue"
},
  "geometry": {"coordinates":[12.242072,45.666286],"type":"Point"}
}