{
  "type": "Feature",
  "properties": {
    "addr:full":"46042 Castel Goffredo Castel Goffredo Mantova 46042",
    "addr:postcode":"46042;46042",
    "addr:street":"Goffredo",
    "iso:country":"IT",
    "sg:address":"46042 Castel Goffredo",
    "sg:city":"Castel Goffredo",
    "sg:orig_category":"Calze E Collants - Produzione E Ingrosso",
    "sg:phone":"+39 0376 779061",
    "sg:postcode":"46042",
    "sg:province":"Mantova",
    "sg:website":"http://www.solidea-calze.it",
    "wof:name":"Calzificio Pinelli Srl",
    "wof:placetype":"venue"
},
  "geometry": {"coordinates":[10.474723,45.285545],"type":"Point"}
}