{
  "type": "Feature",
  "properties": {
    "iso:country":"IT",
    "sg:address":"61/f, Via Rivarolo 16161 Genova",
    "sg:city":"Genova",
    "sg:classifiers":[
        {
            "category":"Manufacturing",
            "subcategory":"Rubber & Plastics",
            "type":"Manufacturing & Wholesale Goods"
        }
    ],
    "sg:phone":"+39 010 740 1444",
    "sg:postcode":"16161",
    "sg:province":"Genova",
    "wof:name":"Garrone (s.n.c.)",
    "wof:placetype":"venue"
},
  "geometry": {"coordinates":[8.9016952515,44.4384689331],"type":"Point"}
}