{
  "type": "Feature",
  "properties": {
    "iso:country":"IT",
    "sg:address":"24060 Rogno",
    "sg:city":"Rogno",
    "sg:orig_category":"Caminetti, Forni Da Giardino E Barbecues",
    "sg:phone":"+39 035 967382",
    "sg:postcode":"24060",
    "sg:province":"Bergamo",
    "wof:name":"G.b. 2 Srl",
    "wof:placetype":"venue"
},
  "geometry": {"coordinates":[9.664819,45.678257],"type":"Point"}
}