{
  "type": "Feature",
  "properties": {
    "addr:full":"20093 Cologno Monzese Cologno Monzese Milano 20093",
    "addr:postcode":"20093;20093",
    "iso:country":"IT",
    "sg:address":"20093 Cologno Monzese",
    "sg:city":"Cologno Monzese",
    "sg:classifiers":[
        {
            "category":"Organizations",
            "subcategory":"Labor Organization",
            "type":"Services"
        }
    ],
    "sg:phone":"+39 02 2730 4374",
    "sg:postcode":"20093",
    "sg:province":"Milano",
    "sg:tags":[
        "packaging",
        "equipment",
        "packing",
        "system"
    ],
    "wof:name":"Vibrotec Snc",
    "wof:placetype":"venue"
},
  "geometry": {"coordinates":[9.2661504745,45.5352210999],"type":"Point"}
}