{
  "type": "Feature",
  "properties": {
    "addr:full":"37020 Volargne Volargne Verona 37020",
    "addr:postcode":"37020;37020",
    "addr:street":"Volargne",
    "iso:country":"IT",
    "sg:address":"37020 Volargne",
    "sg:city":"Volargne",
    "sg:orig_category":"Marmo Ed Affini - Lavorazione",
    "sg:phone":"+39 045 686 2200",
    "sg:postcode":"37020",
    "sg:province":"Verona",
    "sg:website":"http://www.si-mar.it",
    "wof:name":"Si-mar Di Olivieri Vittorio & C. Snc",
    "wof:placetype":"venue"
},
  "geometry": {"coordinates":[10.810169,45.532169],"type":"Point"}
}