{
  "type": "Feature",
  "properties": {
    "addr:full":"10149 Torino Torino Torino 10149",
    "addr:postcode":"10149;10149",
    "iso:country":"IT",
    "sg:address":"10149 Torino",
    "sg:city":"Torino",
    "sg:orig_category":"Frigoriferi Industriali E Commerciali - Commercio",
    "sg:phone":"+39 011 216 5338",
    "sg:postcode":"10149",
    "sg:province":"Torino",
    "sg:website":"http://www.specialsistem2.it",
    "wof:name":"Special Sistem Sas",
    "wof:placetype":"venue"
},
  "geometry": {"coordinates":[7.663629055,45.0963668823],"type":"Point"}
}