{
  "type": "Feature",
  "properties": {
    "addr:full":"50, Via Lussu Emilio 63019 Sant'elpidio A Mare Ascoli Piceno 63019",
    "addr:postcode":"63019;63019",
    "addr:street":"Via Lussu Emilio",
    "iso:country":"IT",
    "sg:address":"50, Via Lussu Emilio 63019 Sant'elpidio A Mare",
    "sg:classifiers":[
        {
            "category":"Shopping",
            "subcategory":"Crafts & Fabrics",
            "type":"Retail Goods"
        }
    ],
    "sg:phone":"+39 0734 990080",
    "sg:postcode":"63019",
    "sg:province":"Ascoli Piceno",
    "wof:name":"Accoppiatura Samuel S.r.l.",
    "wof:placetype":"venue"
},
  "geometry": {"coordinates":[13.5749769211,42.8554000854],"type":"Point"}
}