{
  "type": "Feature",
  "properties": {
    "iso:country":"IT",
    "sg:address":"2, Via Montesanto 31039 Riese Pio X",
    "sg:city":"Riese Pio X",
    "sg:classifiers":[
        {
            "category":"Farming",
            "subcategory":"Livestock Farm",
            "type":"Manufacturing & Wholesale Goods"
        }
    ],
    "sg:phone":"+39 0423 745041",
    "sg:postcode":"31039",
    "sg:province":"Treviso",
    "sg:tags":[
        "agriculture"
    ],
    "wof:name":"G.v.m. (s.p.a.)",
    "wof:placetype":"venue"
},
  "geometry": {"coordinates":[12.242072,45.666286],"type":"Point"}
}