{
  "type": "Feature",
  "properties": {
    "iso:country":"IT",
    "sg:address":"40012 Calderara Di Reno",
    "sg:city":"Bargellino",
    "sg:orig_category":"Aspirapolvere E Lucidatrici Uso Industriale",
    "sg:phone":"+39 051 727280",
    "sg:postcode":"40012",
    "sg:province":"Bologna",
    "wof:name":"Racom Srl",
    "wof:placetype":"venue"
},
  "geometry": {"coordinates":[11.267476,44.538399],"type":"Point"}
}