{
  "type": "Feature",
  "properties": {
    "addr:full":"23857 Valgreghentino Valgreghentino Lecco 23857",
    "addr:postcode":"23857;23857",
    "iso:country":"IT",
    "sg:address":"23857 Valgreghentino",
    "sg:city":"Valgreghentino",
    "sg:orig_category":"Cartotecnica E Servizi. Forniture Per Uffici",
    "sg:phone":"+39 0341 604141",
    "sg:postcode":"23857",
    "sg:province":"Lecco",
    "wof:name":"G.l. Di Gilardi Battista & C. (s.n.c.)",
    "wof:placetype":"venue"
},
  "geometry": {"coordinates":[9.422088,45.784767],"type":"Point"}
}