{
  "type": "Feature",
  "properties": {
    "iso:country":"IT",
    "sg:address":"2, Via Guglielmo Marconi 23897 Vigano'",
    "sg:classifiers":[
        {
            "category":"Home & Garden",
            "subcategory":"Home Furnishings",
            "type":"Retail Goods"
        }
    ],
    "sg:phone":"+39 39039956008",
    "sg:postcode":"23897",
    "sg:province":"Lecco",
    "sg:tags":[
        "household"
    ],
    "wof:name":"Radici Snc Di Liliana Pedrazzo & C",
    "wof:placetype":"venue"
},
  "geometry": {"coordinates":[9.330137,45.725407],"type":"Point"}
}