{
  "type": "Feature",
  "properties": {
    "addr:full":"5, Via Villatega 30030 Salzano Salzano Venezia 30030",
    "addr:postcode":"30030;30030",
    "addr:street":"Via Villatega",
    "iso:country":"IT",
    "sg:address":"5, Via Villatega 30030 Salzano",
    "sg:city":"Salzano",
    "sg:classifiers":[
        {
            "category":"Food & Beverages",
            "subcategory":"Groceries & Convenience Stores",
            "type":"Retail Goods"
        }
    ],
    "sg:phone":"+39 39041437969",
    "sg:postcode":"30030",
    "sg:province":"Venezia",
    "sg:tags":[
        "product",
        "related"
    ],
    "wof:name":"Zampini Tito & Figlio (s.p.a.)",
    "wof:placetype":"venue"
},
  "geometry": {"coordinates":[12.0834770203,45.5358161926],"type":"Point"}
}