{
  "type": "Feature",
  "properties": {
    "addr:full":"107, Via Del Piano 61022 Colbordolo Colbordolo Pesaro E Urbino 61022",
    "addr:housenumber":"107",
    "addr:postcode":"61022;61022",
    "addr:street":"Via Del Piano",
    "iso:country":"IT",
    "sg:address":"107, Via Del Piano 61022 Colbordolo",
    "sg:city":"Colbordolo",
    "sg:classifiers":[
        {
            "category":"Home & Garden",
            "subcategory":"Home Furnishings",
            "type":"Retail Goods"
        }
    ],
    "sg:phone":"+39 0721 479166",
    "sg:postcode":"61022",
    "sg:province":"Pesaro E Urbino",
    "sg:tags":[
        "household"
    ],
    "wof:name":"Tiesse Assemblaggio Mobili Srl",
    "wof:placetype":"venue"
},
  "geometry": {"coordinates":[12.715957,43.833084],"type":"Point"}
}