{
  "type": "Feature",
  "properties": {
    "iso:country":"IT",
    "sg:address":"Via Pana 36 48018 Faenza",
    "sg:city":"Faenza",
    "sg:orig_category":"Groats",
    "sg:phone":"+39 0546 46583",
    "sg:postcode":"48018",
    "sg:province":"Ravenna",
    "wof:name":"Vizi & Sfizi Srl",
    "wof:placetype":"venue"
},
  "geometry": {"coordinates":[11.894357,44.323681],"type":"Point"}
}