{
  "type": "Feature",
  "properties": {
    "iso:country":"IT",
    "sg:address":"Via Colombera 30 31020 Sernaglia Della Battaglia",
    "sg:city":"Sernaglia della Battaglia",
    "sg:classifiers":[
        {
            "category":"Community Center",
            "type":"Public Place"
        }
    ],
    "sg:phone":"+39 0438 896266",
    "sg:postcode":"31020",
    "sg:province":"Treviso",
    "sg:tags":[
        "rolling",
        "section",
        "sheet"
    ],
    "wof:name":"Metallurgica Alberto Srl",
    "wof:placetype":"venue"
},
  "geometry": {"coordinates":[12.176336,45.875797],"type":"Point"}
}