{
  "type": "Feature",
  "properties": {
    "addr:full":"23027 Samolaco Samolaco Sondrio 23027",
    "addr:postcode":"23027;23027",
    "iso:country":"IT",
    "sg:address":"23027 Samolaco",
    "sg:city":"Samolaco",
    "sg:orig_category":"Non-classified Establishments",
    "sg:phone":"+39 0343 24374",
    "sg:postcode":"23027",
    "sg:province":"Sondrio",
    "wof:name":"M.v. Mobili Valchiavenna S.n.c. Di Premerlani Germano Mauro E Gianpaolo",
    "wof:placetype":"venue"
},
  "geometry": {"coordinates":[9.423964,46.24704],"type":"Point"}
}