{
  "type": "Feature",
  "properties": {
    "iso:country":"IT",
    "sg:address":"239, Via Triumplina 25136 Brescia",
    "sg:city":"Brescia",
    "sg:classifiers":[
        {
            "category":"Sports & Exercise",
            "subcategory":"Playing Field",
            "type":"Entertainment"
        }
    ],
    "sg:phone":"+39 030 200 9956",
    "sg:postcode":"25136",
    "sg:province":"Brescia",
    "sg:tags":[
        "game"
    ],
    "wof:name":"Heaven",
    "wof:placetype":"venue"
},
  "geometry": {"coordinates":[10.229609,45.578537],"type":"Point"}
}