{
  "type": "Feature",
  "properties": {
    "iso:country":"IT",
    "sg:address":"20123 Milano",
    "sg:city":"Milano",
    "sg:classifiers":[
        {
            "category":"Health Services",
            "subcategory":"Health Practitioner",
            "type":"Services"
        }
    ],
    "sg:phone":"+39 02 4802 2828",
    "sg:postcode":"20123",
    "sg:province":"Milano",
    "sg:tags":[
        "medici"
    ],
    "wof:name":"Migliara Franco",
    "wof:placetype":"venue"
},
  "geometry": {"coordinates":[9.171958,45.465717],"type":"Point"}
}