{
  "type": "Feature",
  "properties": {
    "addr:full":"16123 Genova Genova Genova 16123",
    "addr:postcode":"16123;16123",
    "iso:country":"IT",
    "sg:address":"16123 Genova",
    "sg:city":"Genova",
    "sg:classifiers":[
        {
            "category":"Shopping",
            "subcategory":"Gifts & Souvenirs",
            "type":"Retail Goods"
        }
    ],
    "sg:phone":"+39 010 247 4309",
    "sg:postcode":"16123",
    "sg:province":"Genova",
    "sg:tags":[
        "gifts",
        "business"
    ],
    "sg:website":"http://www.brizzolari.it",
    "wof:name":"Argenteria Angelo Brizzolari Snc",
    "wof:placetype":"venue"
},
  "geometry": {"coordinates":[8.931434,44.408623],"type":"Point"}
}