{
  "type": "Feature",
  "properties": {
    "iso:country":"IT",
    "sg:address":"00182 Roma",
    "sg:city":"Roma",
    "sg:orig_category":"Articoli Medico-sanitari Ed Ortopedici. Impianti, Attrezzature E Forniture Sanitarie Ed Ospedaliere",
    "sg:phone":"+39 06 701 2815",
    "sg:postcode":"00182",
    "sg:province":"Roma",
    "wof:name":"Raus Roberto",
    "wof:placetype":"venue"
},
  "geometry": {"coordinates":[12.486983,41.865913],"type":"Point"}
}