{
  "type": "Feature",
  "properties": {
    "iso:country":"IT",
    "sg:address":"53, Via Ezio Vanoni 23012 Castione Andevenno",
    "sg:city":"Castione Andevenno",
    "sg:classifiers":[
        {
            "category":"Food & Beverages",
            "subcategory":"Groceries & Convenience Stores",
            "type":"Retail Goods"
        }
    ],
    "sg:phone":"+39 0342 358449",
    "sg:postcode":"23012",
    "sg:province":"Sondrio",
    "sg:tags":[
        "product",
        "related"
    ],
    "wof:name":"Nuova Gimeval S.n.c Di Giorgi Luciano E C.",
    "wof:placetype":"venue"
},
  "geometry": {"coordinates":[9.8033304214,46.1640586853],"type":"Point"}
}