{
  "type": "Feature",
  "properties": {
    "iso:country":"IT",
    "sg:address":"9, Via Marche Zona Industriale Gello 56025 Pontedera",
    "sg:city":"Pontedera",
    "sg:classifiers":[
        {
            "category":"Manufacturing",
            "subcategory":"Metals",
            "type":"Manufacturing & Wholesale Goods"
        }
    ],
    "sg:phone":"+39 0587 292829",
    "sg:postcode":"56025",
    "sg:province":"Pisa",
    "sg:tags":[
        "metallurgy",
        "metalworking"
    ],
    "wof:name":"Baldacci (s.p.a.)",
    "wof:placetype":"venue"
},
  "geometry": {"coordinates":[10.5973739624,43.6435928345],"type":"Point"}
}