{
  "type": "Feature",
  "properties": {
    "iso:country":"IT",
    "sg:address":"Via Einaudi 20/22 20037 Paderno Dugnano",
    "sg:city":"Paderno Dugnano",
    "sg:classifiers":[
        {
            "category":"Industrial Area",
            "type":"Public Place"
        }
    ],
    "sg:phone":"+39 02 9904 8191",
    "sg:postcode":"20037",
    "sg:province":"Milano",
    "sg:tags":[
        "fan"
    ],
    "sg:website":"www.vipblade.com",
    "wof:name":"V.i.p. Di Fasolini Fausto Marco & C. S.a.s.",
    "wof:placetype":"venue"
},
  "geometry": {"coordinates":[9.181973,45.560722],"type":"Point"}
}