{
  "type": "Feature",
  "properties": {
    "iso:country":"IT",
    "sg:address":"30030 Vigonovo",
    "sg:city":"Vigonovo",
    "sg:orig_category":"Forniture Per Abbigliamento E Pelletterie",
    "sg:phone":"+39 049 980 0674",
    "sg:postcode":"30030",
    "sg:province":"Venezia",
    "wof:name":"Eurotac (s.r.l.)",
    "wof:placetype":"venue"
},
  "geometry": {"coordinates":[11.9949445724,45.397731781],"type":"Point"}
}