{
  "type": "Feature",
  "properties": {
    "addr:full":"5, V. Enna 90141 Palermo Palermo Palermo 90141",
    "addr:housenumber":"5",
    "addr:postcode":"90141;90141",
    "addr:street":"V. Enna",
    "iso:country":"IT",
    "sg:address":"5, V. Enna 90141 Palermo",
    "sg:city":"Palermo",
    "sg:classifiers":[
        {
            "category":"Wholesale",
            "subcategory":"Medical Equipment & Supplies",
            "type":"Manufacturing & Wholesale Goods"
        }
    ],
    "sg:phone":"+39 39091306321",
    "sg:postcode":"90141",
    "sg:province":"Palermo",
    "sg:tags":[
        "-",
        "health",
        "instrument"
    ],
    "sg:website":"http://www.paginegialle.it/amesan",
    "wof:name":"A.me.san.",
    "wof:placetype":"venue"
},
  "geometry": {"coordinates":[13.347946,38.127399],"type":"Point"}
}