{
  "type": "Feature",
  "properties": {
    "iso:country":"IT",
    "sg:address":"345, Viale Cortina D'ampezzo 00135 Roma",
    "sg:city":"Roma",
    "sg:classifiers":[
        {
            "category":"Building & Trades",
            "subcategory":"Construction",
            "type":"Services"
        }
    ],
    "sg:phone":"+39 39063013987",
    "sg:postcode":"00135",
    "sg:province":"Roma",
    "sg:tags":[
        "work",
        "public"
    ],
    "wof:name":"Impresa Giuseppe Orsini S.p.a.",
    "wof:placetype":"venue"
},
  "geometry": {"coordinates":[12.436212,41.942318],"type":"Point"}
}