{
  "type": "Feature",
  "properties": {
    "iso:country":"IT",
    "sg:address":"153, Via Roma 36040 Torri Di Quartesolo",
    "sg:city":"Torri di Quartesolo",
    "sg:classifiers":[
        {
            "category":"Sports & Exercise",
            "subcategory":"Playing Field",
            "type":"Entertainment"
        }
    ],
    "sg:phone":"+39 0444 583981",
    "sg:postcode":"36040",
    "sg:province":"Vicenza",
    "sg:tags":[
        "game"
    ],
    "wof:name":"Manzin F.lli (s.n.c.)",
    "wof:placetype":"venue"
},
  "geometry": {"coordinates":[11.623258,45.515285],"type":"Point"}
}