{
  "type": "Feature",
  "properties": {
    "iso:country":"IT",
    "sg:address":"Via Cassia 01019 Vetralla",
    "sg:city":"Vetralla",
    "sg:classifiers":[
        {
            "category":"Real Estate",
            "subcategory":"Architect",
            "type":"Services"
        }
    ],
    "sg:phone":"+39 0761 483172",
    "sg:postcode":"01019",
    "sg:province":"Viterbo",
    "sg:tags":[
        "textile",
        "clothing"
    ],
    "wof:name":"Scuderi S.r.l.",
    "wof:placetype":"venue"
},
  "geometry": {"coordinates":[12.05636,42.336651],"type":"Point"}
}