{
  "type": "Feature",
  "properties": {
    "iso:country":"IT",
    "sg:address":"10125 Torino",
    "sg:city":"Torino",
    "sg:orig_category":"Assicurazioni E Servizi Assicurativi. Consulenze Tecniche, Amministrative E Perizie",
    "sg:phone":"+39 011 669 2299",
    "sg:postcode":"10125",
    "sg:province":"Torino",
    "wof:name":"Assitre Srl",
    "wof:placetype":"venue"
},
  "geometry": {"coordinates":[7.548526,45.005386],"type":"Point"}
}