{
  "type": "Feature",
  "properties": {
    "iso:country":"IT",
    "sg:address":"Corso Umberto I 172 09073 Cuglieri",
    "sg:city":"Cuglieri",
    "sg:classifiers":[
        {
            "category":"Food & Beverages",
            "subcategory":"Cheese",
            "type":"Retail Goods"
        }
    ],
    "sg:phone":"+39 0785 36147",
    "sg:postcode":"09073",
    "sg:province":"Oristano",
    "sg:tags":[
        "sheep's",
        "milk"
    ],
    "sg:website":"www.pecorino.it",
    "wof:name":"Pievi Srl",
    "wof:placetype":"venue"
},
  "geometry": {"coordinates":[8.567347,40.185497],"type":"Point"}
}