{
  "type": "Feature",
  "properties": {
    "iso:country":"IT",
    "sg:address":"00139 Roma",
    "sg:city":"Roma",
    "sg:orig_category":"Servizi Culturali E Per Lo Spettacolo",
    "sg:phone":"+39 06 817 7735",
    "sg:postcode":"00139",
    "sg:province":"Roma",
    "wof:name":"Cinematografo Redentore",
    "wof:placetype":"venue"
},
  "geometry": {"coordinates":[12.528051,41.947945],"type":"Point"}
}