{
  "type": "Feature",
  "properties": {
    "iso:country":"IT",
    "sg:address":"99, Via Galcianese 59100 Prato",
    "sg:city":"Prato",
    "sg:classifiers":[
        {
            "category":"Shopping",
            "subcategory":"Crafts & Fabrics",
            "type":"Retail Goods"
        }
    ],
    "sg:phone":"+39 39057437152",
    "sg:postcode":"59100",
    "sg:province":"Prato",
    "wof:name":"Manifattura Tessuti Piemmeci Srl",
    "wof:placetype":"venue"
},
  "geometry": {"coordinates":[11.0690717697,43.881816864],"type":"Point"}
}