{
  "type": "Feature",
  "properties": {
    "iso:country":"IT",
    "sg:address":"1, Via Madonna Della Stella 81053 Riardo",
    "sg:city":"Riardo",
    "sg:classifiers":[
        {
            "category":"Home & Garden",
            "subcategory":"Home Furnishings",
            "type":"Retail Goods"
        }
    ],
    "sg:phone":"+39 0823 981627",
    "sg:postcode":"81053",
    "sg:province":"Caserta",
    "sg:tags":[
        "household"
    ],
    "wof:name":"Fiera Del Mobile S.r.l.",
    "wof:placetype":"venue"
},
  "geometry": {"coordinates":[14.154431,41.259605],"type":"Point"}
}