{
  "type": "Feature",
  "properties": {
    "iso:country":"IT",
    "sg:address":"03036 Isola Del Liri",
    "sg:city":"Isola del Liri",
    "sg:orig_category":"Macchine, Impianti E Forniture Per Industria Grafica, Cartaria E Cartotecnica",
    "sg:phone":"+39 0776 809100",
    "sg:postcode":"03036",
    "sg:province":"Frosinone",
    "wof:name":"Di Poce Robert",
    "wof:placetype":"venue"
},
  "geometry": {"coordinates":[13.575885,41.675995],"type":"Point"}
}