{
  "type": "Feature",
  "properties": {
    "iso:country":"IT",
    "sg:address":"13888 Zubiena",
    "sg:city":"Zubiena",
    "sg:orig_category":"Tessuti Arredamento, Tende E Tappeti",
    "sg:phone":"+39 015 256 4954",
    "sg:postcode":"13888",
    "sg:province":"Biella",
    "wof:name":"Immagine Design Srl",
    "wof:placetype":"venue"
},
  "geometry": {"coordinates":[8.010159,45.500008],"type":"Point"}
}