{
  "type": "Feature",
  "properties": {
    "addr:full":"97100 Ragusa Ragusa Ragusa 97100",
    "addr:postcode":"97100;97100",
    "iso:country":"IT",
    "sg:address":"97100 Ragusa",
    "sg:city":"Ragusa",
    "sg:orig_category":"Elettronica Professionale E Di Consumo. Musica",
    "sg:phone":"+39 0932 653958",
    "sg:postcode":"97100",
    "sg:province":"Ragusa",
    "wof:name":"Arte Organaria Di Bovelacci Antonio & C. Sas",
    "wof:placetype":"venue"
},
  "geometry": {"coordinates":[14.734005,36.924812],"type":"Point"}
}