{
  "type": "Feature",
  "properties": {
    "addr:full":"32, V. Guido D'arezzo 25013 Carpenedolo Carpenedolo Brescia 25013",
    "addr:housenumber":"32",
    "addr:postcode":"25013;25013",
    "addr:street":"V. Guido D'Arezzo",
    "iso:country":"IT",
    "sg:address":"32, V. Guido D'arezzo 25013 Carpenedolo",
    "sg:city":"Carpenedolo",
    "sg:classifiers":[
        {
            "category":"Professional",
            "subcategory":"Engineering",
            "type":"Services"
        }
    ],
    "sg:phone":"+39 39030969249",
    "sg:postcode":"25013",
    "sg:province":"Brescia",
    "sg:tags":[
        "machine",
        "-",
        "mechanical"
    ],
    "sg:website":"http://www.graziolicesare.com:ws_end: :mark:ws:http://www.paginegialle.it/graziolice",
    "wof:name":"Grazioli Cesare",
    "wof:placetype":"venue"
},
  "geometry": {"coordinates":[10.429168,45.368473],"type":"Point"}
}