{
  "type": "Feature",
  "properties": {
    "addr:full":"1, Via Capitello 37057 San Giovanni Lupatoto San Giovanni Lupatoto Verona 37057",
    "addr:postcode":"37057;37057",
    "addr:street":"Via Capitello;Verona",
    "iso:country":"IT",
    "sg:address":"1, Via Capitello 37057 San Giovanni Lupatoto",
    "sg:city":"San Giovanni Lupatoto",
    "sg:classifiers":[
        {
            "category":"Wholesale",
            "subcategory":"Machinery & Supplies",
            "type":"Manufacturing & Wholesale Goods"
        }
    ],
    "sg:phone":"+39 045 873 0599",
    "sg:postcode":"37057",
    "sg:province":"Verona",
    "sg:tags":[
        "-",
        "agriculture",
        "equipment"
    ],
    "wof:name":"Pagex (s.r.l.)",
    "wof:placetype":"venue"
},
  "geometry": {"coordinates":[11.047087,45.351311],"type":"Point"}
}