{
  "type": "Feature",
  "properties": {
    "iso:country":"IT",
    "sg:address":"9, Viale Galileo Galilei 36066 Sandrigo",
    "sg:city":"Sandrigo",
    "sg:classifiers":[
        {
            "category":"Manufacturing",
            "subcategory":"Metals",
            "type":"Manufacturing & Wholesale Goods"
        }
    ],
    "sg:phone":"+39 0444 658290",
    "sg:postcode":"36066",
    "sg:province":"Vicenza",
    "sg:tags":[
        "processing"
    ],
    "wof:name":"Cromador (s.r.l.)",
    "wof:placetype":"venue"
},
  "geometry": {"coordinates":[11.5502319336,45.6331481934],"type":"Point"}
}