{
  "type": "Feature",
  "properties": {
    "iso:country":"IT",
    "sg:address":"88, Via Sasse 37132 Verona",
    "sg:city":"Verona",
    "sg:classifiers":[
        {
            "category":"Shopping",
            "subcategory":"Computers & Home Electronics",
            "type":"Retail Goods"
        }
    ],
    "sg:phone":"+39 045 892 1552",
    "sg:postcode":"37132",
    "sg:province":"Verona",
    "sg:tags":[
        "electronic",
        "electrical",
        "equipment"
    ],
    "wof:name":"C.e.m. S.r.l.",
    "wof:placetype":"venue"
},
  "geometry": {"coordinates":[11.061684,45.403103],"type":"Point"}
}