{
  "type": "Feature",
  "properties": {
    "addr:full":"Via E Che Guevara 33051 Aquileia Aquileia Udine 33051",
    "addr:postcode":"33051;33051",
    "addr:street":"Via E Che Guevara",
    "iso:country":"IT",
    "sg:address":"Via E Che Guevara 33051 Aquileia",
    "sg:city":"Aquileia",
    "sg:classifiers":[
        {
            "category":"Manufacturing",
            "subcategory":"Rubber & Plastics",
            "type":"Manufacturing & Wholesale Goods"
        }
    ],
    "sg:phone":"+39 0431 919355",
    "sg:postcode":"33051",
    "sg:province":"Udine",
    "wof:name":"Omnia Nautica (s.n.c.)",
    "wof:placetype":"venue"
},
  "geometry": {"coordinates":[13.2307243347,46.0649414062],"type":"Point"}
}