{
  "type": "Feature",
  "properties": {
    "iso:country":"IT",
    "sg:address":"30, Via Ausa 47853 Coriano",
    "sg:city":"Coriano",
    "sg:classifiers":[
        {
            "category":"Shopping",
            "subcategory":"Stationery & Office Supplies",
            "type":"Retail Goods"
        }
    ],
    "sg:phone":"+39 0541 759134",
    "sg:postcode":"47853",
    "sg:province":"Rimini",
    "sg:tags":[
        "professional"
    ],
    "wof:name":"Arredamenti Bocedi S.r.l.",
    "wof:placetype":"venue"
},
  "geometry": {"coordinates":[12.5245389938,43.990020752],"type":"Point"}
}