{
  "type": "Feature",
  "properties": {
    "iso:country":"IT",
    "sg:address":"10123 Torino",
    "sg:city":"Torino",
    "sg:orig_category":"Articoli Regalo - Vendita Al Dettaglio",
    "sg:phone":"+39 011 839 4578",
    "sg:postcode":"10123",
    "sg:province":"Torino",
    "wof:name":"Il Faggio",
    "wof:placetype":"venue"
},
  "geometry": {"coordinates":[7.685223,45.06065],"type":"Point"}
}