{
  "type": "Feature",
  "properties": {
    "addr:full":"10122 Torino Torino Torino 10122",
    "addr:housenumber":"10122",
    "addr:postcode":"10122",
    "iso:country":"IT",
    "sg:address":"10122 Torino",
    "sg:city":"Torino",
    "sg:orig_category":"Prodotti Di Base E Forniture Per Industria Alimentare E Bevande. Forniture E Materiali Per Imballaggio E Confezionamento",
    "sg:phone":"+39 011 436 9438",
    "sg:postcode":"10122",
    "sg:province":"Torino",
    "wof:name":"Menietti Lodovico & C. Snc",
    "wof:placetype":"venue"
},
  "geometry": {"coordinates":[7.6791477203,45.0743598938],"type":"Point"}
}