{
  "type": "Feature",
  "properties": {
    "addr:full":"Piazza Iv Novembre 12; Palazzuolo Sul Senio; 50035 Palazzuolo sul Senio Firenze 50035",
    "addr:housenumber":"12",
    "addr:postcode":"senio 50035;50035",
    "addr:street":"Piazza Iv Novembre",
    "iso:country":"IT",
    "sg:address":"Piazza Iv Novembre 12; Palazzuolo Sul Senio; 50035",
    "sg:city":"Palazzuolo sul Senio",
    "sg:classifiers":[
        {
            "category":"Banks & Credit Unions",
            "subcategory":"Bank",
            "type":"Services"
        }
    ],
    "sg:phone":"+39 055 804 6006",
    "sg:postcode":"50035",
    "sg:province":"Firenze",
    "wof:name":"Rolo Banca 1473 Spa",
    "wof:placetype":"venue"
},
  "geometry": {"coordinates":[11.547541,44.096169],"type":"Point"}
}