{
  "type": "Feature",
  "properties": {
    "iso:country":"IT",
    "sg:address":"1, Via Intercomunale 54038 Montignoso",
    "sg:city":"Montignoso",
    "sg:classifiers":[
        {
            "category":"Airport",
            "subcategory":"General Aviation",
            "type":"Transportation"
        }
    ],
    "sg:phone":"+39 0585 807748",
    "sg:postcode":"54038",
    "sg:province":"Massa-Carrara",
    "sg:tags":[
        "transport",
        "air"
    ],
    "wof:name":"Helitalia Spa",
    "wof:placetype":"venue"
},
  "geometry": {"coordinates":[10.146532,43.986111],"type":"Point"}
}