{
  "type": "Feature",
  "properties": {
    "addr:full":"Via Volta 12 21040 Jerago Con Orago Jerago con Orago Varese 21040",
    "addr:housenumber":"12",
    "addr:postcode":"21040;orago;21040",
    "addr:street":"Via Volta;Con Orago;Con",
    "iso:country":"IT",
    "sg:address":"Via Volta 12 21040 Jerago Con Orago",
    "sg:city":"Jerago con Orago",
    "sg:classifiers":[
        {
            "category":"Transit Center",
            "subcategory":"Freight",
            "type":"Transportation"
        }
    ],
    "sg:phone":"+39 0331 217161",
    "sg:postcode":"21040",
    "sg:province":"Varese",
    "sg:tags":[
        "spring",
        "spiral"
    ],
    "sg:website":"www.mollificiovaresino.it",
    "wof:name":"Mollificio Varesino Guido Vecchietti Di Vecchietti Augusto & C. Snc",
    "wof:placetype":"venue"
},
  "geometry": {"coordinates":[8.793675,45.705704],"type":"Point"}
}