{
  "type": "Feature",
  "properties": {
    "addr:full":"13, Via Turati 40010 Sala Bolognese Sala Bolognese Bologna 40010",
    "addr:postcode":"40010;40010",
    "addr:street":"Via Turati;Bolognese",
    "iso:country":"IT",
    "sg:address":"13, Via Turati 40010 Sala Bolognese",
    "sg:city":"Sala Bolognese",
    "sg:classifiers":[
        {
            "category":"Manufacturing",
            "subcategory":"Metals",
            "type":"Manufacturing & Wholesale Goods"
        }
    ],
    "sg:phone":"+39 051 681 4329",
    "sg:postcode":"40010",
    "sg:province":"Bologna",
    "sg:tags":[
        "metallurgy",
        "metalworking"
    ],
    "wof:name":"Gi.fa.st. (s.n.c.)",
    "wof:placetype":"venue"
},
  "geometry": {"coordinates":[11.2693624496,44.5630073547],"type":"Point"}
}