{
  "type": "Feature",
  "properties": {
    "addr:full":"03012 Anagni Anagni Frosinone 03012",
    "addr:postcode":"03012;03012",
    "iso:country":"IT",
    "sg:address":"03012 Anagni",
    "sg:city":"Anagni",
    "sg:orig_category":"Prodotti Chimici Secondari. Medicinali E Prodotti Parafarmaceutici",
    "sg:phone":"+39 0775 7621",
    "sg:postcode":"03012",
    "sg:province":"Frosinone",
    "wof:name":"Bristol - Myers Squibb Spa",
    "wof:placetype":"venue"
},
  "geometry": {"coordinates":[13.150967598,41.7346305847],"type":"Point"}
}