{
  "type": "Feature",
  "properties": {
    "iso:country":"IT",
    "sg:address":"50145 Firenze",
    "sg:city":"Firenze",
    "sg:orig_category":"Cartotecnica E Servizi. Articoli Per Imballaggio E Confezionamento",
    "sg:phone":"+39 055 373576",
    "sg:postcode":"50145",
    "sg:province":"Firenze",
    "wof:name":"Imballaggi David 2000 Srl",
    "wof:placetype":"venue"
},
  "geometry": {"coordinates":[11.181557,43.796204],"type":"Point"}
}