{
  "type": "Feature",
  "properties": {
    "addr:full":"60019 Senigallia Senigallia Ancona 60019",
    "addr:postcode":"60019;60019",
    "iso:country":"IT",
    "sg:address":"60019 Senigallia",
    "sg:city":"Senigallia",
    "sg:classifiers":[
        {
            "category":"Health Services",
            "subcategory":"Health Practitioner",
            "type":"Services"
        }
    ],
    "sg:phone":"+39 071 792 6995",
    "sg:postcode":"60019",
    "sg:province":"Ancona",
    "sg:tags":[
        "medici"
    ],
    "wof:name":"Pettinari Claudio",
    "wof:placetype":"venue"
},
  "geometry": {"coordinates":[13.5281038284,43.6147956848],"type":"Point"}
}