{
  "type": "Feature",
  "properties": {
    "iso:country":"IT",
    "sg:address":"00161 Roma",
    "sg:city":"Roma",
    "sg:classifiers":[
        {
            "category":"Health Services",
            "subcategory":"Health Practitioner",
            "type":"Services"
        }
    ],
    "sg:phone":"+39 06 440 4153",
    "sg:postcode":"00161",
    "sg:province":"Roma",
    "sg:tags":[
        "medici"
    ],
    "wof:name":"Studio Lancisi S.r.l.",
    "wof:placetype":"venue"
},
  "geometry": {"coordinates":[12.5104808807,41.9088020325],"type":"Point"}
}