{
  "type": "Feature",
  "properties": {
    "iso:country":"IT",
    "sg:address":"Via Turati, 13 Bis 21010 Verghera",
    "sg:classifiers":[
        {
            "category":"Manufacturing",
            "subcategory":"Rubber & Plastics",
            "type":"Manufacturing & Wholesale Goods"
        }
    ],
    "sg:phone":"+39 0331 222440",
    "sg:postcode":"21010",
    "sg:province":"Varese",
    "sg:tags":[
        "disposal",
        "system"
    ],
    "sg:website":"www.zocchigiovanni.it",
    "wof:name":"Zocchi Giovanni",
    "wof:placetype":"venue"
},
  "geometry": {"coordinates":[8.8263845444,45.8176040649],"type":"Point"}
}