{
  "type": "Feature",
  "properties": {
    "addr:full":"190, Via Di Cervara 00155 Roma Roma Roma 00155",
    "addr:housenumber":"190",
    "addr:postcode":"00155;00155",
    "addr:street":"Via Di Cervara",
    "iso:country":"IT",
    "sg:address":"190, Via Di Cervara 00155 Roma",
    "sg:city":"Roma",
    "sg:classifiers":[
        {
            "category":"Food & Beverages",
            "subcategory":"Groceries & Convenience Stores",
            "type":"Retail Goods"
        }
    ],
    "sg:phone":"+39 39062294334",
    "sg:postcode":"00155",
    "sg:province":"Roma",
    "sg:tags":[
        "product",
        "related"
    ],
    "wof:name":"Tor Cervara Industria Alimentari (s.p.a.)",
    "wof:placetype":"venue"
},
  "geometry": {"coordinates":[12.5719099045,41.9075393677],"type":"Point"}
}