{
  "type": "Feature",
  "properties": {
    "addr:full":"Via Tibet 21 21052 Busto Arsizio Busto Arsizio Varese 21052",
    "addr:housenumber":"21",
    "addr:postcode":"21052;21052",
    "addr:street":"Via Tibet",
    "iso:country":"IT",
    "sg:address":"Via Tibet 21 21052 Busto Arsizio",
    "sg:city":"Busto Arsizio",
    "sg:classifiers":[
        {
            "category":"Exhibition Hall",
            "type":"Public Place"
        }
    ],
    "sg:phone":"+39 0331 352211",
    "sg:postcode":"21052",
    "sg:province":"Varese",
    "sg:tags":[
        "structures",
        "tent"
    ],
    "sg:website":"www.lodetex.it",
    "wof:name":"Lodetex Srl",
    "wof:placetype":"venue"
},
  "geometry": {"coordinates":[8.829103,45.584415],"type":"Point"}
}