{
  "type": "Feature",
  "properties": {
    "addr:full":"20081 Abbiategrasso Abbiategrasso Milano 20081",
    "addr:postcode":"20081;20081",
    "iso:country":"IT",
    "sg:address":"20081 Abbiategrasso",
    "sg:city":"Abbiategrasso",
    "sg:orig_category":"Automazione E Macchine Per Ufficio. Arredi Ed Attrezzature Per Attivita' Commerciali Ed Artigianali",
    "sg:phone":"+39 02 946 2609",
    "sg:postcode":"20081",
    "sg:province":"Milano",
    "sg:website":"http://www.sogesi.it/soluzioni/soluzioni.htm",
    "wof:name":"Soluzioni Ufficio Sas",
    "wof:placetype":"venue"
},
  "geometry": {"coordinates":[9.188437,45.528801],"type":"Point"}
}