{
  "type": "Feature",
  "properties": {
    "iso:country":"IT",
    "sg:address":"33170 Pordenone",
    "sg:city":"Pordenone",
    "sg:orig_category":"Studi E Consulenze Amministrative, Commerciali E Aziendali. Consulenze Tecniche, Amministrative E Perizie",
    "sg:phone":"+39 0434 208282",
    "sg:postcode":"33170",
    "sg:province":"Pordenone",
    "wof:name":"Martin Elio",
    "wof:placetype":"venue"
},
  "geometry": {"coordinates":[12.661452,45.956367],"type":"Point"}
}