{
  "type": "Feature",
  "properties": {
    "addr:full":"1/c, V. Padania Industriale - Z.i. Sud 31027 Spresiano Spresiano Treviso 31027",
    "addr:housenumber":"1 / c",
    "addr:postcode":"31027;31027",
    "iso:country":"IT",
    "sg:address":"1/c, V. Padania Industriale - Z.i. Sud 31027 Spresiano",
    "sg:city":"Spresiano",
    "sg:classifiers":[
        {
            "category":"Manufacturing",
            "subcategory":"Metals",
            "type":"Manufacturing & Wholesale Goods"
        }
    ],
    "sg:phone":"+39 0422 887602",
    "sg:postcode":"31027",
    "sg:province":"Treviso",
    "sg:tags":[
        "metallurgy",
        "metalworking"
    ],
    "sg:website":"http://www.inoxmecservice.com",
    "wof:name":"Inoxmec Service Srl",
    "wof:placetype":"venue"
},
  "geometry": {"coordinates":[12.2420721054,45.6662864685],"type":"Point"}
}