{
  "type": "Feature",
  "properties": {
    "addr:full":"16149 Genova Genova Genova 16149",
    "addr:postcode":"16149;16149",
    "iso:country":"IT",
    "sg:address":"16149 Genova",
    "sg:city":"Genova",
    "sg:orig_category":"Mobili - Vendita Al Dettaglio",
    "sg:phone":"+39 010 645 9135",
    "sg:postcode":"16149",
    "sg:province":"Genova",
    "wof:name":"Bi Tre Arredamenti Di Proget",
    "wof:placetype":"venue"
},
  "geometry": {"coordinates":[8.8933029175,44.4100074768],"type":"Point"}
}