{
  "type": "Feature",
  "properties": {
    "iso:country":"IT",
    "sg:address":"156/a, Via Statale 25011 Calcinato",
    "sg:city":"Calcinato",
    "sg:classifiers":[
        {
            "category":"Utilities",
            "subcategory":"Telephone",
            "type":"Services"
        }
    ],
    "sg:phone":"+39 030 998 0984",
    "sg:postcode":"25011",
    "sg:province":"Brescia",
    "sg:tags":[
        "telecommunication"
    ],
    "wof:name":"Partner Electric A S",
    "wof:placetype":"venue"
},
  "geometry": {"coordinates":[10.222958,45.539829],"type":"Point"}
}