{
  "type": "Feature",
  "properties": {
    "iso:country":"IT",
    "sg:address":"129, Via Cesare Battisti 64011 Alba Adriatica",
    "sg:city":"Alba Adriatica",
    "sg:classifiers":[
        {
            "category":"Personal",
            "subcategory":"Shoe Repair & Shine",
            "type":"Services"
        }
    ],
    "sg:phone":"+39 0861 712811",
    "sg:postcode":"64011",
    "sg:province":"Teramo",
    "sg:tags":[
        "leather"
    ],
    "wof:name":"Bizzarri",
    "wof:placetype":"venue"
},
  "geometry": {"coordinates":[13.926822,42.835674],"type":"Point"}
}