{
  "type": "Feature",
  "properties": {
    "iso:country":"IT",
    "sg:address":"20155 Milano",
    "sg:city":"Milano",
    "sg:orig_category":"Scuole E Servizi Scolastici. Servizi Per Lo Sport E Il Tempo Libero",
    "sg:phone":"+39 02 3453 2080",
    "sg:postcode":"20155",
    "sg:province":"Milano",
    "wof:name":"Mandelli Veruska",
    "wof:placetype":"venue"
},
  "geometry": {"coordinates":[9.158818,45.493347],"type":"Point"}
}