{
  "type": "Feature",
  "properties": {
    "iso:country":"IT",
    "sg:address":"00195 Roma",
    "sg:city":"Roma",
    "sg:orig_category":"Impianti Elettrici Industriali E Civili - Installazione E Manutenzione",
    "sg:phone":"+39 06 3975 1580",
    "sg:postcode":"00195",
    "sg:province":"Roma",
    "wof:name":"Urbe Consulting Services",
    "wof:placetype":"venue"
},
  "geometry": {"coordinates":[12.448765,42.104218],"type":"Point"}
}