{
  "type": "Feature",
  "properties": {
    "addr:full":"16153 Genova Genova Genova 16153",
    "addr:housenumber":"16153",
    "addr:postcode":"16153",
    "iso:country":"IT",
    "sg:address":"16153 Genova",
    "sg:city":"Genova",
    "sg:orig_category":"Servizi Per Lo Sport E Il Tempo Libero. Servizi Ausiliari Dei Mezzi Di Trasporto",
    "sg:phone":"+39 010 601 8222",
    "sg:postcode":"16153",
    "sg:province":"Genova",
    "wof:name":"Cecar Nautica",
    "wof:placetype":"venue"
},
  "geometry": {"coordinates":[8.860071,44.41917],"type":"Point"}
}