{
  "type": "Feature",
  "properties": {
    "addr:full":"09134 Cagliari Cagliari Cagliari 09134",
    "addr:postcode":"09134;09134",
    "iso:country":"IT",
    "sg:address":"09134 Cagliari",
    "sg:city":"Cagliari",
    "sg:orig_category":"Servizi E Lavori Per Agricoltura E Zootecnia. Servizi E Lavori Per Ecologia E Smaltimento Rifiuti",
    "sg:phone":"+39 070 554230",
    "sg:postcode":"09134",
    "sg:province":"Cagliari",
    "wof:name":"S.i.ge. Societa' Interventi Generali Srl",
    "wof:placetype":"venue"
},
  "geometry": {"coordinates":[9.121664,39.242554],"type":"Point"}
}