{
  "type": "Feature",
  "properties": {
    "iso:country":"IT",
    "sg:address":"20122 Milano",
    "sg:city":"Milano",
    "sg:orig_category":"Scuole E Servizi Scolastici. Alberghi E Strutture Extra Alberghiere",
    "sg:phone":"+39 02 7600 1425",
    "sg:postcode":"20122",
    "sg:province":"Milano",
    "wof:name":"Educandato Statale Emanuela Setti Carraro Dalla Chiesa",
    "wof:placetype":"venue"
},
  "geometry": {"coordinates":[9.202748,45.465118],"type":"Point"}
}