{
  "type": "Feature",
  "properties": {
    "addr:full":"Via Sempione 82 28040 Marano Ticino Marano Ticino Novara 28040",
    "addr:housenumber":"82",
    "addr:postcode":"28040;28040",
    "addr:street":"Via Sempione",
    "iso:country":"IT",
    "sg:address":"Via Sempione 82 28040 Marano Ticino",
    "sg:city":"Marano Ticino",
    "sg:classifiers":[
        {
            "category":"Wholesale",
            "subcategory":"Vending Machines",
            "type":"Manufacturing & Wholesale Goods"
        }
    ],
    "sg:phone":"+39 0321 9781",
    "sg:postcode":"28040",
    "sg:province":"Novara",
    "sg:tags":[
        "ceramic",
        "processing"
    ],
    "sg:website":"www.sitigroup.it",
    "wof:name":"S.i.t.i. Spa",
    "wof:placetype":"venue"
},
  "geometry": {"coordinates":[8.63668,45.606506],"type":"Point"}
}