{
  "type": "Feature",
  "properties": {
    "addr:full":"23016 Mantello Mantello Sondrio 23016",
    "addr:postcode":"23016;23016",
    "iso:country":"IT",
    "sg:address":"23016 Mantello",
    "sg:city":"Mantello",
    "sg:orig_category":"Legno E Semilavorati. Articoli Per Imballaggio E Confezionamento",
    "sg:phone":"+39 0342 680176",
    "sg:postcode":"23016",
    "sg:province":"Sondrio",
    "sg:website":"http://www.pedranzini.it",
    "wof:name":"Pedranzini F.lli Snc",
    "wof:placetype":"venue"
},
  "geometry": {"coordinates":[9.48122,46.148987],"type":"Point"}
}