{
  "type": "Feature",
  "properties": {
    "iso:country":"IT",
    "sg:address":"20090 Pieve Emanuele",
    "sg:city":"Pieve Emanuele",
    "sg:classifiers":[
        {
            "category":"Banks & Credit Unions",
            "subcategory":"Investment Brokerage",
            "type":"Services"
        }
    ],
    "sg:phone":"+39 02 9072 4915",
    "sg:postcode":"20090",
    "sg:province":"Milano",
    "sg:tags":[
        "houseware",
        "good",
        "leather",
        "utensil",
        "skins",
        "footwear",
        "kitchen"
    ],
    "wof:name":"Ermal Snc",
    "wof:placetype":"venue"
},
  "geometry": {"coordinates":[9.202671051,45.3559150696],"type":"Point"}
}