{
  "type": "Feature",
  "properties": {
    "iso:country":"IT",
    "sg:address":"03043 Cassino",
    "sg:city":"Cassino",
    "sg:orig_category":"Banche E Servizi Finanziari. Agenzie D'affari E Servizi Commerciali",
    "sg:phone":"+39 0776 21140",
    "sg:postcode":"03043",
    "sg:province":"Frosinone",
    "wof:name":"Business Consulting",
    "wof:placetype":"venue"
},
  "geometry": {"coordinates":[13.830193,41.489384],"type":"Point"}
}