{
  "type": "Feature",
  "properties": {
    "iso:country":"IT",
    "sg:address":"50, Via Catalani 50050 Cerreto Guidi",
    "sg:city":"Cerreto Guidi",
    "sg:classifiers":[
        {
            "category":"Professional",
            "subcategory":"Engineering",
            "type":"Services"
        }
    ],
    "sg:phone":"+39 0571 581901",
    "sg:postcode":"50050",
    "sg:province":"Firenze",
    "sg:tags":[
        "machine",
        "-",
        "mechanical"
    ],
    "wof:name":"Bedogni & C. S.r.l",
    "wof:placetype":"venue"
},
  "geometry": {"coordinates":[10.880778,43.721642],"type":"Point"}
}