{
  "type": "Feature",
  "properties": {
    "iso:country":"IT",
    "sg:address":"00062 Bracciano",
    "sg:city":"Bracciano",
    "sg:orig_category":"Macchine E Forniture Per Arredamento E Industria Del Legno. Forniture Per Edilizia E Lavori Pubblici",
    "sg:phone":"+39 06 9980 4172",
    "sg:postcode":"00062",
    "sg:province":"Roma",
    "wof:name":"Boggiani Glauco",
    "wof:placetype":"venue"
},
  "geometry": {"coordinates":[12.542531,41.939178],"type":"Point"}
}