{
  "type": "Feature",
  "properties": {
    "addr:full":"00041 Albano Laziale Albano Laziale Roma 00041",
    "addr:postcode":"00041;00041",
    "addr:street":"Roma",
    "iso:country":"IT",
    "sg:address":"00041 Albano Laziale",
    "sg:city":"Albano Laziale",
    "sg:orig_category":"Prodotti Alimentari",
    "sg:phone":"+39 06 932 3165",
    "sg:postcode":"00041",
    "sg:province":"Roma",
    "wof:name":"Tutto Sotto Zero Snc Di Sbordoni Daniela & C",
    "wof:placetype":"venue"
},
  "geometry": {"coordinates":[12.6652793884,41.7266654968],"type":"Point"}
}