{
  "type": "Feature",
  "properties": {
    "iso:country":"IT",
    "sg:address":"44100 Ferrara",
    "sg:city":"Ferrara",
    "sg:orig_category":"Giocattoli E Giochi - Produzione E Ingrosso",
    "sg:phone":"+39 0532 761432",
    "sg:postcode":"44100",
    "sg:province":"Ferrara",
    "wof:name":"Filippini Srl",
    "wof:placetype":"venue"
},
  "geometry": {"coordinates":[11.620569,44.82616],"type":"Point"}
}