{
  "type": "Feature",
  "properties": {
    "addr:full":"1, Via Remis 33050 San Vito Al Torre San Vito al Torre Udine 33050",
    "addr:postcode":"33050;torre;33050",
    "addr:street":"Via Remis;Al Torre",
    "iso:country":"IT",
    "sg:address":"1, Via Remis 33050 San Vito Al Torre",
    "sg:city":"San Vito al Torre",
    "sg:classifiers":[
        {
            "category":"Home & Garden",
            "subcategory":"Home Furnishings",
            "type":"Retail Goods"
        }
    ],
    "sg:phone":"+39 0432 997729",
    "sg:postcode":"33050",
    "sg:province":"Udine",
    "sg:tags":[
        "household"
    ],
    "wof:name":"Curvarredo S.r.l.",
    "wof:placetype":"venue"
},
  "geometry": {"coordinates":[13.368074,45.919502],"type":"Point"}
}