{
  "type": "Feature",
  "properties": {
    "iso:country":"IT",
    "sg:address":"80143 Napoli",
    "sg:city":"Napoli",
    "sg:orig_category":"Servizi Per Aziende, Manifestazioni E Supporto Agli Scambi Commerciali",
    "sg:phone":"+39 081 562 3035",
    "sg:postcode":"80143",
    "sg:province":"Napoli",
    "wof:name":"Simbeni Bruna",
    "wof:placetype":"venue"
},
  "geometry": {"coordinates":[14.282045,40.856991],"type":"Point"}
}