{
  "type": "Feature",
  "properties": {
    "iso:country":"IT",
    "sg:address":"70124 Bari",
    "sg:city":"Bari",
    "sg:classifiers":[
        {
            "category":"Health Services",
            "subcategory":"Dentist",
            "type":"Services"
        }
    ],
    "sg:phone":"+39 080 542 6062",
    "sg:postcode":"70124",
    "sg:province":"Bari",
    "sg:tags":[
        "hospital"
    ],
    "wof:name":"Casa Di Cura Villa Dei Gerani - Gestione 'la Nuova Sanita'' Srl",
    "wof:placetype":"venue"
},
  "geometry": {"coordinates":[16.847338,41.091347],"type":"Point"}
}