{
  "type": "Feature",
  "properties": {
    "iso:country":"IT",
    "sg:address":"Via Sabbioni 2 60035 Jesi",
    "sg:city":"Jesi",
    "sg:classifiers":[
        {
            "category":"Manufacturing",
            "subcategory":"Motor Vehicles & Parts",
            "type":"Manufacturing & Wholesale Goods"
        }
    ],
    "sg:phone":"+39 0731 53766",
    "sg:postcode":"60035",
    "sg:province":"Ancona",
    "sg:tags":[
        "pulley",
        "belt"
    ],
    "sg:website":"www.extrafond.it",
    "wof:name":"Extrafond Srl",
    "wof:placetype":"venue"
},
  "geometry": {"coordinates":[13.23783,43.539478],"type":"Point"}
}