{
  "type": "Feature",
  "properties": {
    "iso:country":"IT",
    "sg:address":"16033 Lavagna",
    "sg:city":"Lavagna",
    "sg:orig_category":"Abbigliamento Esterno, Maglierie E Pelliccerie. Forniture Per Il Settore Dello Spettacolo",
    "sg:phone":"+39 0185 397014",
    "sg:postcode":"16033",
    "sg:province":"Genova",
    "wof:name":"Bardazzi Annarita",
    "wof:placetype":"venue"
},
  "geometry": {"coordinates":[9.054869,44.380829],"type":"Point"}
}