{
  "type": "Feature",
  "properties": {
    "iso:country":"IT",
    "sg:address":"20122 Milano",
    "sg:city":"Milano",
    "sg:orig_category":"Ospedali E Servizi Sanitari",
    "sg:phone":"+39 0257991",
    "sg:postcode":"20122",
    "sg:province":"Milano",
    "wof:name":"Universita' Degli Studi/medicina E Chirurgia/istituto Di Medicina Del Lavoro",
    "wof:placetype":"venue"
},
  "geometry": {"coordinates":[9.200719,45.459198],"type":"Point"}
}