{
  "type": "Feature",
  "properties": {
    "addr:full":"306, Via Pratrivero 13835 Trivero Pratrivero Biella 13835",
    "addr:housenumber":"306",
    "addr:postcode":"13835;13835",
    "addr:street":"Via Pratrivero;Pratrivero",
    "iso:country":"IT",
    "sg:address":"306, Via Pratrivero 13835 Trivero",
    "sg:city":"Pratrivero",
    "sg:classifiers":[
        {
            "category":"Shopping",
            "subcategory":"Crafts & Fabrics",
            "type":"Retail Goods"
        }
    ],
    "sg:phone":"+39 015 738 8296",
    "sg:postcode":"13835",
    "sg:province":"Biella",
    "wof:name":"Godi Giuseppe E C. (s.a.s.)",
    "wof:placetype":"venue"
},
  "geometry": {"coordinates":[8.0582695007,45.5628356934],"type":"Point"}
}