{
  "type": "Feature",
  "properties": {
    "addr:full":"Via Torino 13; Napoli; 80142 Napoli Napoli 80142",
    "addr:housenumber":"13",
    "addr:postcode":"80142;80142",
    "addr:street":"Via Torino",
    "iso:country":"IT",
    "sg:address":"Via Torino 13; Napoli; 80142",
    "sg:city":"Napoli",
    "sg:classifiers":[
        {
            "category":"Banks & Credit Unions",
            "subcategory":"Bank",
            "type":"Services"
        }
    ],
    "sg:phone":"+39 081 260954",
    "sg:postcode":"80142",
    "sg:province":"Napoli",
    "wof:name":"Banca Nazionale Dell' Agricoltura",
    "wof:placetype":"venue"
},
  "geometry": {"coordinates":[14.269688,40.85371],"type":"Point"}
}