{
  "type": "Feature",
  "properties": {
    "iso:country":"IT",
    "sg:address":"20082 Badile",
    "sg:orig_category":"Bevande, Vini E Liquori",
    "sg:phone":"+39 02 9009 6211",
    "sg:postcode":"20082",
    "sg:province":"Milano",
    "wof:name":"Agru Mar Snc Di La Rosa Casapollo E C.",
    "wof:placetype":"venue"
},
  "geometry": {"coordinates":[9.205775,45.448963],"type":"Point"}
}