{
  "type": "Feature",
  "properties": {
    "addr:full":"Via Statale S. Maria 1 16042 Carasco Carasco Genova 16042",
    "addr:housenumber":"1",
    "addr:postcode":"16042;16042",
    "addr:street":"Via Statale;Maria",
    "iso:country":"IT",
    "sg:address":"Via Statale S. Maria 1 16042 Carasco",
    "sg:city":"Carasco",
    "sg:classifiers":[
        {
            "category":"Wholesale",
            "subcategory":"Chemicals & Plastics",
            "type":"Manufacturing & Wholesale Goods"
        }
    ],
    "sg:phone":"+39 0185 350788",
    "sg:postcode":"16042",
    "sg:province":"Genova",
    "sg:tags":[
        "laboratory",
        "disposable",
        "supply"
    ],
    "sg:website":"www.prosanfun.it",
    "wof:name":"Prosan Srl",
    "wof:placetype":"venue"
},
  "geometry": {"coordinates":[8.933989,44.407063],"type":"Point"}
}