{
  "type": "Feature",
  "properties": {
    "iso:country":"IT",
    "sg:address":"16164 Genova",
    "sg:city":"Genova",
    "sg:orig_category":"Carta, Cartone E Prodotti Primari. Forniture E Materiali Per Imballaggio E Confezionamento",
    "sg:phone":"+39 010 715076",
    "sg:postcode":"16164",
    "sg:province":"Genova",
    "wof:name":"Polcevera Carta Di Maggio Andrea",
    "wof:placetype":"venue"
},
  "geometry": {"coordinates":[8.900798,44.489151],"type":"Point"}
}