{
  "type": "Feature",
  "properties": {
    "iso:country":"IT",
    "sg:address":"21020 Bodio Lomnago",
    "sg:city":"Bodio",
    "sg:classifiers":[
        {
            "category":"Wholesale",
            "subcategory":"Chemicals & Plastics",
            "type":"Manufacturing & Wholesale Goods"
        }
    ],
    "sg:phone":"+39 0332 947121",
    "sg:postcode":"21020",
    "sg:province":"Varese",
    "sg:tags":[
        "article",
        "product",
        "plastics"
    ],
    "sg:website":"http://www.ambropol.com",
    "wof:name":"Ambropolimer Snc",
    "wof:placetype":"venue"
},
  "geometry": {"coordinates":[8.7454576492,45.7939872742],"type":"Point"}
}