{
  "type": "Feature",
  "properties": {
    "addr:full":"35010 Limena Limena Padova 35010",
    "addr:postcode":"35010;35010",
    "iso:country":"IT",
    "sg:address":"35010 Limena",
    "sg:city":"Limena",
    "sg:orig_category":"Prodotti Chimici Di Base",
    "sg:phone":"+39 049 768712",
    "sg:postcode":"35010",
    "sg:province":"Padova",
    "wof:name":"Mondial Snc",
    "wof:placetype":"venue"
},
  "geometry": {"coordinates":[11.8540964127,45.4631233215],"type":"Point"}
}