{
  "type": "Feature",
  "properties": {
    "addr:full":"Via Ciserino 4/a 23827 Lierna Lierna Lecco 23827",
    "addr:housenumber":"4 / a",
    "addr:postcode":"23827;23827",
    "addr:street":"Via Ciserino",
    "iso:country":"IT",
    "sg:address":"Via Ciserino 4/a 23827 Lierna",
    "sg:city":"Lierna",
    "sg:orig_category":"Accessories For Tap Systems",
    "sg:phone":"+39 0341 742006",
    "sg:postcode":"23827",
    "sg:province":"Lecco",
    "sg:website":"www.odl.it",
    "wof:name":"O.d.l. Srl",
    "wof:placetype":"venue"
},
  "geometry": {"coordinates":[9.390071,45.852982],"type":"Point"}
}