{
  "type": "Feature",
  "properties": {
    "iso:country":"IT",
    "sg:address":"00158 Roma",
    "sg:city":"Roma",
    "sg:orig_category":"Legno E Semilavorati",
    "sg:phone":"+39 06 450 0812",
    "sg:postcode":"00158",
    "sg:province":"Roma",
    "wof:name":"Mercuri Franco",
    "wof:placetype":"venue"
},
  "geometry": {"coordinates":[12.547679,41.922504],"type":"Point"}
}