{
  "type": "Feature",
  "properties": {
    "iso:country":"IT",
    "sg:address":"56010 Arena Metato",
    "sg:city":"Arena",
    "sg:orig_category":"Prodotti E Manufatti In Materie Plastiche",
    "sg:phone":"+39 050 810488",
    "sg:postcode":"56010",
    "sg:province":"Pisa",
    "wof:name":"Giangrosso Domenico",
    "wof:placetype":"venue"
},
  "geometry": {"coordinates":[10.3708486557,43.7719650269],"type":"Point"}
}