{
  "type": "Feature",
  "properties": {
    "addr:full":"40012 Calderara Di Reno Calderara di Reno Bologna 40012",
    "addr:postcode":"40012;40012",
    "iso:country":"IT",
    "sg:address":"40012 Calderara Di Reno",
    "sg:city":"Calderara di Reno",
    "sg:orig_category":"Materiali E Componenti Elettrotecnici",
    "sg:phone":"+39 051 722962",
    "sg:postcode":"40012",
    "sg:province":"Bologna",
    "sg:website":"http://www.felis.it",
    "wof:name":"F.el.i.s. Srl Forniture Elettriche Industriali Speciali",
    "wof:placetype":"venue"
},
  "geometry": {"coordinates":[11.273235,44.566883],"type":"Point"}
}