{
  "type": "Feature",
  "properties": {
    "addr:full":"70124 Bari Bari Bari 70124",
    "addr:postcode":"70124;70124",
    "iso:country":"IT",
    "sg:address":"70124 Bari",
    "sg:city":"Bari",
    "sg:classifiers":[
        {
            "category":"Building & Trades",
            "subcategory":"Construction",
            "type":"Services"
        }
    ],
    "sg:phone":"+39 080 502 4055",
    "sg:postcode":"70124",
    "sg:province":"Bari",
    "sg:tags":[
        "articles",
        "product",
        "plastics",
        "supply",
        "civil",
        "industry",
        "works"
    ],
    "wof:name":"Plastica Italia Srl",
    "wof:placetype":"venue"
},
  "geometry": {"coordinates":[16.8676052094,41.0973892212],"type":"Point"}
}