{
  "type": "Feature",
  "properties": {
    "iso:country":"IT",
    "sg:address":"23900 Lecco",
    "sg:city":"Lecco",
    "sg:orig_category":"Catene E Pignoni",
    "sg:phone":"+39 0341 421545",
    "sg:postcode":"23900",
    "sg:province":"Lecco",
    "sg:website":"http://www.catene3c.it",
    "wof:name":"3c Di Cortiana Walter & Luca Snc",
    "wof:placetype":"venue"
},
  "geometry": {"coordinates":[9.414315,45.829247],"type":"Point"}
}