{
  "type": "Feature",
  "properties": {
    "addr:full":"71013 S.giovanni Rotondo Foggia 71013",
    "addr:postcode":"71013;71013",
    "iso:country":"IT",
    "sg:address":"71013 S.giovanni Rotondo",
    "sg:orig_category":"Alberghi",
    "sg:phone":"+39 0882 454646",
    "sg:postcode":"71013",
    "sg:province":"Foggia",
    "wof:name":"Im.mar. Srl - Grand Hotel Degli Angeli",
    "wof:placetype":"venue"
},
  "geometry": {"coordinates":[15.730204,41.703972],"type":"Point"}
}