{
  "type": "Feature",
  "properties": {
    "iso:country":"IT",
    "sg:address":"23880 Casatenovo",
    "sg:city":"Casatenovo",
    "sg:orig_category":"Prodotti Finiti Stampati. Shopping. Regalistica Aziendale",
    "sg:phone":"+39 039 920 3980",
    "sg:postcode":"23880",
    "sg:province":"Lecco",
    "wof:name":"Bel Ami Di Keppel Hesselink Stefano E C. Soc. Di Fatto",
    "wof:placetype":"venue"
},
  "geometry": {"coordinates":[9.3330965042,45.7493095398],"type":"Point"}
}