{
  "type": "Feature",
  "properties": {
    "addr:full":"41012 Carpi Carpi Modena 41012",
    "addr:postcode":"41012;41012",
    "iso:country":"IT",
    "sg:address":"41012 Carpi",
    "sg:city":"Carpi",
    "sg:orig_category":"Accessori Moda D'abbigliamento",
    "sg:phone":"+39 059 686669",
    "sg:postcode":"41012",
    "sg:province":"Modena",
    "wof:name":"Berrettificio Medici Franco",
    "wof:placetype":"venue"
},
  "geometry": {"coordinates":[10.847861,44.705772],"type":"Point"}
}