{
  "type": "Feature",
  "properties": {
    "iso:country":"IT",
    "sg:address":"20020 Arconate",
    "sg:city":"Arconate",
    "sg:orig_category":"Articoli Per Imballaggio E Confezionamento",
    "sg:phone":"+39 0331 462439",
    "sg:postcode":"20020",
    "sg:province":"Milano",
    "wof:name":"Giuseppe Crespi Di Pinciroli M. & Piersimoni E. (s.n.c)",
    "wof:placetype":"venue"
},
  "geometry": {"coordinates":[8.84794,45.539547],"type":"Point"}
}