{
  "type": "Feature",
  "properties": {
    "addr:full":"Contrada Pesco Farese 86025 Ripalimosani Ripalimosani Campobasso 86025",
    "addr:postcode":"86025;86025",
    "addr:street":"Contrada Pesco Farese",
    "iso:country":"IT",
    "sg:address":"Contrada Pesco Farese 86025 Ripalimosani",
    "sg:city":"Ripalimosani",
    "sg:classifiers":[
        {
            "category":"Real Estate",
            "subcategory":"Architect",
            "type":"Services"
        }
    ],
    "sg:phone":"+39 0874 481430",
    "sg:postcode":"86025",
    "sg:province":"Campobasso",
    "sg:tags":[
        "textile",
        "clothing"
    ],
    "wof:name":"Gruppo Tullo Sas Di Tullo Giuseppe E C.",
    "wof:placetype":"venue"
},
  "geometry": {"coordinates":[14.670597,41.592812],"type":"Point"}
}