{
  "type": "Feature",
  "properties": {
    "addr:full":"10144 Torino Torino Torino 10144",
    "addr:postcode":"10144;10144",
    "iso:country":"IT",
    "sg:address":"10144 Torino",
    "sg:city":"Torino",
    "sg:orig_category":"Servizi E Lavori Per Industria Alimentare E Bevande. Servizi E Lavori Per Abbigliamento E Pelletterie. Servizi E Lavori Per Arredamento E Industria Del Legno. Servizi Vari Di Interesse Pubblico",
    "sg:phone":"+39 011 437 9361",
    "sg:postcode":"10144",
    "sg:province":"Torino",
    "wof:name":"Pharma Trust Srl",
    "wof:placetype":"venue"
},
  "geometry": {"coordinates":[7.665386,45.082153],"type":"Point"}
}