{
  "type": "Feature",
  "properties": {
    "addr:full":"16, Via S. Martino 25020 Poncarale Poncarale Brescia 25020",
    "addr:postcode":"25020;25020",
    "addr:street":"Via S. Martino",
    "iso:country":"IT",
    "sg:address":"16, Via S. Martino 25020 Poncarale",
    "sg:city":"Poncarale",
    "sg:classifiers":[
        {
            "category":"Shopping",
            "subcategory":"Clothing, Apparel, & Fashions",
            "type":"Retail Goods"
        }
    ],
    "sg:phone":"+39 030 264 0887",
    "sg:postcode":"25020",
    "sg:province":"Brescia",
    "sg:tags":[
        "clothes"
    ],
    "wof:name":"Bo.mo (s.r.l.)",
    "wof:placetype":"venue"
},
  "geometry": {"coordinates":[10.172099,45.481953],"type":"Point"}
}