{
  "type": "Feature",
  "properties": {
    "iso:country":"IT",
    "sg:address":"56126 Pisa",
    "sg:city":"Pisa",
    "sg:orig_category":"Pubblica Amministrazione",
    "sg:phone":"+39 050117",
    "sg:postcode":"56126",
    "sg:province":"Pisa",
    "wof:name":"Guardia Di Finanza",
    "wof:placetype":"venue"
},
  "geometry": {"coordinates":[10.4091997147,43.713470459],"type":"Point"}
}