{
  "type": "Feature",
  "properties": {
    "addr:full":"20052 Monza Monza Milano 20052",
    "addr:postcode":"20052;20052",
    "iso:country":"IT",
    "sg:address":"20052 Monza",
    "sg:city":"Monza",
    "sg:orig_category":"Disinfezione, Disinfestazione E Derattizzazione",
    "sg:phone":"+39 039 387352",
    "sg:postcode":"20052",
    "sg:province":"Milano",
    "sg:website":"http://www.pulitecnica.com",
    "wof:name":"Impresa Pulizia Pulitecnica Srl",
    "wof:placetype":"venue"
},
  "geometry": {"coordinates":[9.281158,45.583237],"type":"Point"}
}