{
  "type": "Feature",
  "properties": {
    "addr:full":"5, Via Enrico Fermi 31050 Zenson Di Piave Zenson di Piave Treviso 31050",
    "addr:housenumber":"di piave",
    "addr:postcode":"31050;31050",
    "addr:street":"Via Enrico Fermi;Di Piave",
    "iso:country":"IT",
    "sg:address":"5, Via Enrico Fermi 31050 Zenson Di Piave",
    "sg:city":"Zenson di Piave",
    "sg:classifiers":[
        {
            "category":"Home & Garden",
            "subcategory":"Home Furnishings",
            "type":"Retail Goods"
        }
    ],
    "sg:phone":"+39 0421 344171",
    "sg:postcode":"31050",
    "sg:province":"Treviso",
    "sg:tags":[
        "household"
    ],
    "wof:name":"Lamp Mobilificio (s.r.l.)",
    "wof:placetype":"venue"
},
  "geometry": {"coordinates":[12.491344,45.674217],"type":"Point"}
}