{
  "type": "Feature",
  "properties": {
    "iso:country":"IT",
    "sg:address":"30100 Venezia",
    "sg:orig_category":"Elettrotecnica Industriale, Prodotti E Apparecchiature",
    "sg:phone":"+39 041 522 4528",
    "sg:province":"VE",
    "wof:name":"Elettroforniture Michieletti & C. Snc",
    "wof:placetype":"venue"
},
  "geometry": {"coordinates":[12.290899,45.373199],"type":"Point"}
}