{
  "type": "Feature",
  "properties": {
    "addr:full":"20092 Cinisello Balsamo Cinisello Balsamo Milano 20092",
    "addr:postcode":"20092;20092",
    "iso:country":"IT",
    "sg:address":"20092 Cinisello Balsamo",
    "sg:city":"Cinisello Balsamo",
    "sg:orig_category":"Dolciumi E Gelati",
    "sg:phone":"+39 02 6601 0176",
    "sg:postcode":"20092",
    "sg:province":"Milano",
    "wof:name":"Dolcar Di M. Tragni & C. Sas",
    "wof:placetype":"venue"
},
  "geometry": {"coordinates":[9.228992,45.555416],"type":"Point"}
}