{
  "type": "Feature",
  "properties": {
    "addr:full":"36022 Cassola Cassola Vicenza 36022",
    "addr:postcode":"36022;36022",
    "iso:country":"IT",
    "sg:address":"36022 Cassola",
    "sg:city":"Cassola",
    "sg:orig_category":"Mechanical Equipment. Industrial Activities, Machines, Instruments And Equipment",
    "sg:phone":"+39 0424 571140",
    "sg:postcode":"36022",
    "sg:province":"Vicenza",
    "sg:website":"http://www.raasm.com/indicepgo.htm",
    "wof:name":"Raasm Spa",
    "wof:placetype":"venue"
},
  "geometry": {"coordinates":[11.724675,45.729885],"type":"Point"}
}