{
  "type": "Feature",
  "properties": {
    "iso:country":"IT",
    "sg:address":"Via Frattini 3; Verona; 37121",
    "sg:city":"Verona",
    "sg:classifiers":[
        {
            "category":"Banks & Credit Unions",
            "subcategory":"Bank",
            "type":"Services"
        }
    ],
    "sg:phone":"+39 045 800 0207",
    "sg:postcode":"37121",
    "sg:province":"Verona",
    "wof:name":"Ludova Banka As",
    "wof:placetype":"venue"
},
  "geometry": {"coordinates":[10.996551,45.439178],"type":"Point"}
}