{
  "type": "Feature",
  "properties": {
    "iso:country":"IT",
    "sg:address":"12048 Sommariva Del Bosco",
    "sg:city":"Sommariva del Bosco",
    "sg:classifiers":[
        {
            "category":"Manufacturing",
            "subcategory":"Metals",
            "type":"Manufacturing & Wholesale Goods"
        }
    ],
    "sg:phone":"+39 0172 55921",
    "sg:postcode":"12048",
    "sg:province":"Cuneo",
    "sg:tags":[
        "forming",
        "working",
        "welding"
    ],
    "wof:name":"Nuova M.g. Srl",
    "wof:placetype":"venue"
},
  "geometry": {"coordinates":[7.7867851257,44.7812690735],"type":"Point"}
}