{
  "type": "Feature",
  "properties": {
    "iso:country":"IT",
    "sg:address":"98028 S. Teresa Di Riva",
    "sg:orig_category":"Pelliccerie",
    "sg:phone":"+39 0942 792199",
    "sg:postcode":"98028",
    "sg:province":"Messina",
    "wof:name":"Pellicceria Manganaro",
    "wof:placetype":"venue"
},
  "geometry": {"coordinates":[15.5193157196,38.2624320984],"type":"Point"}
}