{
  "type": "Feature",
  "properties": {
    "iso:country":"IT",
    "sg:address":"04100 Latina",
    "sg:city":"Latina",
    "sg:orig_category":"Trasporti E Spedizioni Merci",
    "sg:phone":"+39 0773 660406",
    "sg:postcode":"04100",
    "sg:province":"Latina",
    "wof:name":"Fioroni Franco Latina Recapiti",
    "wof:placetype":"venue"
},
  "geometry": {"coordinates":[12.90468,41.455124],"type":"Point"}
}