{
  "type": "Feature",
  "properties": {
    "addr:full":"12022 San Chiaffredo Busca Cuneo 12022",
    "addr:housenumber":"12022",
    "addr:postcode":"12022",
    "addr:street":"San Chiaffredo Busca",
    "iso:country":"IT",
    "sg:address":"12022 San Chiaffredo",
    "sg:city":"Busca",
    "sg:orig_category":"Macchine Agricole - Commercio E Riparazione",
    "sg:phone":"+39 0171 940001",
    "sg:postcode":"12022",
    "sg:province":"Cuneo",
    "wof:name":"Giordano Renato & C. Snc",
    "wof:placetype":"venue"
},
  "geometry": {"coordinates":[7.504069,44.482136],"type":"Point"}
}