{
  "type": "Feature",
  "properties": {
    "iso:country":"IT",
    "sg:address":"40069 Zola Predosa",
    "sg:city":"Zola",
    "sg:orig_category":"Forniture Per Abbigliamento E Pelletterie",
    "sg:phone":"+39 051 758600",
    "sg:postcode":"40069",
    "sg:province":"Bologna",
    "wof:name":"Bottonificio Gianni",
    "wof:placetype":"venue"
},
  "geometry": {"coordinates":[11.2555656433,44.4967536926],"type":"Point"}
}