{
  "type": "Feature",
  "properties": {
    "iso:country":"IT",
    "sg:address":"20052 Monza",
    "sg:city":"Monza",
    "sg:orig_category":"Servizi E Lavori Per Ecologia E Smaltimento Rifiuti. Servizi Ausiliari Di Sorveglianza, Manutenzione E Pulizia",
    "sg:phone":"+39 039 200 6061",
    "sg:postcode":"20052",
    "sg:province":"Milano",
    "sg:website":"http://www.bumega.it",
    "wof:name":"Bu Mega Cleaning",
    "wof:placetype":"venue"
},
  "geometry": {"coordinates":[9.283274,45.533039],"type":"Point"}
}