{
  "type": "Feature",
  "properties": {
    "addr:full":"16152 Genova Genova Genova 16152",
    "addr:postcode":"16152;16152",
    "iso:country":"IT",
    "sg:address":"16152 Genova",
    "sg:city":"Genova",
    "sg:orig_category":"Termotecnica E Riscaldamento, Apparecchiature E Servizi",
    "sg:phone":"+39 010 650 4597",
    "sg:postcode":"16152",
    "sg:province":"Genova",
    "wof:name":"Gazzoni Giampiero",
    "wof:placetype":"venue"
},
  "geometry": {"coordinates":[8.869121,44.418819],"type":"Point"}
}