{
  "type": "Feature",
  "properties": {
    "addr:full":"Via Del Fontanile 7 22040 Brenna Brenna Como 22040",
    "addr:housenumber":"7",
    "addr:postcode":"22040;22040",
    "addr:street":"Via Del Fontanile",
    "iso:country":"IT",
    "sg:address":"Via Del Fontanile 7 22040 Brenna",
    "sg:city":"Brenna",
    "sg:classifiers":[
        {
            "category":"Manufacturing",
            "subcategory":"Food",
            "type":"Manufacturing & Wholesale Goods"
        }
    ],
    "sg:phone":"+39 031 797363",
    "sg:postcode":"22040",
    "sg:province":"Como",
    "sg:tags":[
        "packaging",
        "industry"
    ],
    "sg:website":"www.corapack.com",
    "wof:name":"Corapack Srl",
    "wof:placetype":"venue"
},
  "geometry": {"coordinates":[9.0854558945,45.8119659424],"type":"Point"}
}