{
  "type": "Feature",
  "properties": {
    "iso:country":"IT",
    "sg:address":"42017 Novellara",
    "sg:orig_category":"Articoli Per Imballaggio E Confezionamento",
    "sg:phone":"+39 0522 662060",
    "sg:postcode":"42017",
    "sg:province":"Reggio Nell'Emilia",
    "sg:website":"http://www.ghisiwalter.it",
    "wof:name":"Ghisi Walter Di Ghisi Roberto & C. Snc",
    "wof:placetype":"venue"
},
  "geometry": {"coordinates":[10.678687,44.769516],"type":"Point"}
}