{
  "type": "Feature",
  "properties": {
    "addr:full":"19125 La Spezia SP",
    "addr:housenumber":"19125",
    "iso:country":"IT",
    "sg:address":"19125 La Spezia",
    "sg:orig_category":"Associazioni Di Volontariato E Di Solidarieta'",
    "sg:phone":"+39 0187 524 5244",
    "sg:province":"SP",
    "wof:name":"Croce Rossa Italiana",
    "wof:placetype":"venue"
},
  "geometry": {"coordinates":[9.829234,44.131374],"type":"Point"}
}