{
  "type": "Feature",
  "properties": {
    "addr:full":"20123 Milano Milano Milano 20123",
    "addr:postcode":"20123;20123",
    "iso:country":"IT",
    "sg:address":"20123 Milano",
    "sg:city":"Milano",
    "sg:orig_category":"Servizi Editoriali. Pubblicita', Marketing E Comunicazione",
    "sg:phone":"+39 02 8645 5417",
    "sg:postcode":"20123",
    "sg:province":"Milano",
    "wof:name":"Media In (s.a.s.)",
    "wof:placetype":"venue"
},
  "geometry": {"coordinates":[9.183087,45.466717],"type":"Point"}
}