{
  "type": "Feature",
  "properties": {
    "addr:full":"Via Leazaccalia 5 47900 Rimini Rimini Rimini 47900",
    "addr:housenumber":"5",
    "addr:postcode":"47900;47900",
    "addr:street":"Via Leazaccalia",
    "iso:country":"IT",
    "sg:address":"Via Leazaccalia 5 47900 Rimini",
    "sg:city":"Rimini",
    "sg:classifiers":[
        {
            "category":"Home & Garden",
            "subcategory":"Building Materials",
            "type":"Retail Goods"
        }
    ],
    "sg:phone":"+39 0541 397801",
    "sg:postcode":"47900",
    "sg:province":"Rimini",
    "sg:tags":[
        "plate",
        "lathe",
        "face"
    ],
    "sg:website":"www.gsrspa.it",
    "wof:name":"Gsr Spa",
    "wof:placetype":"venue"
},
  "geometry": {"coordinates":[12.5662565231,44.0607795715],"type":"Point"}
}