{
  "type": "Feature",
  "properties": {
    "iso:country":"IT",
    "sg:address":"40136 Bologna",
    "sg:city":"Bologna",
    "sg:orig_category":"Apparecchiature E Sistemi Per Magazzinaggio E Movimentazione",
    "sg:phone":"+39 051 331567",
    "sg:postcode":"40136",
    "sg:province":"Bologna",
    "wof:name":"La Petrolifera Italo - Rumena",
    "wof:placetype":"venue"
},
  "geometry": {"coordinates":[11.333522,44.488594],"type":"Point"}
}