{
  "type": "Feature",
  "properties": {
    "iso:country":"IT",
    "sg:address":"20131 Milano",
    "sg:city":"Milano",
    "sg:orig_category":"Agenzie D'affari E Servizi Commerciali",
    "sg:phone":"+39 02 2611 2929",
    "sg:postcode":"20131",
    "sg:province":"Milano",
    "wof:name":"Piazzi Patrizia",
    "wof:placetype":"venue"
},
  "geometry": {"coordinates":[9.230941,45.489956],"type":"Point"}
}