{
  "type": "Feature",
  "properties": {
    "iso:country":"IT",
    "sg:address":"1, Via Dell' Artigianato 52017 Stia",
    "sg:city":"Stia",
    "sg:classifiers":[
        {
            "category":"Shopping",
            "subcategory":"Clothing, Apparel, & Fashions",
            "type":"Retail Goods"
        }
    ],
    "sg:phone":"+39 0575 583288",
    "sg:postcode":"52017",
    "sg:province":"Arezzo",
    "sg:tags":[
        "clothes"
    ],
    "wof:name":"Mital Srl",
    "wof:placetype":"venue"
},
  "geometry": {"coordinates":[11.863062,43.471203],"type":"Point"}
}