{
  "type": "Feature",
  "properties": {
    "iso:country":"IT",
    "sg:address":"04011 Aprilia",
    "sg:city":"Aprilia",
    "sg:orig_category":"Serramenti Ed Infissi",
    "sg:phone":"+39 06 925 5083",
    "sg:postcode":"04011",
    "sg:province":"Latina",
    "sg:website":"http://www.cyborg.it/icopar",
    "wof:name":"Icopar Srl",
    "wof:placetype":"venue"
},
  "geometry": {"coordinates":[12.749178,41.531258],"type":"Point"}
}