{
  "type": "Feature",
  "properties": {
    "iso:country":"IT",
    "sg:address":"50134 Firenze",
    "sg:city":"Firenze",
    "sg:orig_category":"Riparazione Dei Mezzi Di Trasporto",
    "sg:phone":"+39 055 473958",
    "sg:postcode":"50134",
    "sg:province":"Firenze",
    "wof:name":"Ma & Ma Snc",
    "wof:placetype":"venue"
},
  "geometry": {"coordinates":[11.2445,43.7924],"type":"Point"}
}