{
  "type": "Feature",
  "properties": {
    "addr:full":"81050 Santa Maria La Fossa Santa Maria la Fossa Caserta 81050",
    "addr:postcode":"81050;81050",
    "addr:street":"Maria;Fossa Santa Maria La Fossa Caserta",
    "iso:country":"IT",
    "sg:address":"81050 Santa Maria La Fossa",
    "sg:city":"Santa Maria la Fossa",
    "sg:orig_category":"Pubblica Amministrazione",
    "sg:phone":"+39 0823 993280",
    "sg:postcode":"81050",
    "sg:province":"Caserta",
    "wof:name":"Comune Di Santa Maria La Fossa",
    "wof:placetype":"venue"
},
  "geometry": {"coordinates":[14.0652885437,41.162853241],"type":"Point"}
}