{
  "type": "Feature",
  "properties": {
    "addr:full":"12078 Ormea Ormea Cuneo 12078",
    "addr:postcode":"12078;12078",
    "iso:country":"IT",
    "sg:address":"12078 Ormea",
    "sg:city":"Ormea",
    "sg:orig_category":"Alberghi E Strutture Extra Alberghiere. Ospedali E Servizi Sanitari",
    "sg:phone":"+39 0174 391175",
    "sg:postcode":"12078",
    "sg:province":"Cuneo",
    "wof:name":"Casa Alpina Maria Immacolata",
    "wof:placetype":"venue"
},
  "geometry": {"coordinates":[7.909849,44.147831],"type":"Point"}
}