{
  "type": "Feature",
  "properties": {
    "addr:full":"25045 Castegnato Castegnato Brescia 25045",
    "addr:postcode":"25045;25045",
    "iso:country":"IT",
    "sg:address":"25045 Castegnato",
    "sg:city":"Castegnato",
    "sg:orig_category":"Arredo Bagno Ed Idrosanitari. Idrosanitari E Accessori. Minuterie Metalliche E Ferramenta",
    "sg:phone":"+39 030 272 2361",
    "sg:postcode":"25045",
    "sg:province":"Brescia",
    "wof:name":"Valvosanitaria Bugatti Spa",
    "wof:placetype":"venue"
},
  "geometry": {"coordinates":[10.126148,45.569134],"type":"Point"}
}