{
  "type": "Feature",
  "properties": {
    "iso:country":"IT",
    "sg:address":"56121 Pisa",
    "sg:city":"Pisa",
    "sg:orig_category":"Ricambi E Componenti Dei Mezzi Di Trasporto",
    "sg:phone":"+39 050 980999",
    "sg:postcode":"56121",
    "sg:province":"Pisa",
    "wof:name":"G.carmignani & C. S.r.l.",
    "wof:placetype":"venue"
},
  "geometry": {"coordinates":[10.332812,43.55518],"type":"Point"}
}