{
  "type": "Feature",
  "properties": {
    "addr:full":"40064 Ozzano Dell'emilia Bologna 40064",
    "addr:postcode":"40064;40064",
    "iso:country":"IT",
    "sg:address":"40064 Ozzano Dell'emilia",
    "sg:orig_category":"Filtri - Produzione E Commercio",
    "sg:phone":"+39 051 798203",
    "sg:postcode":"40064",
    "sg:province":"Bologna",
    "wof:name":"Fag Snc",
    "wof:placetype":"venue"
},
  "geometry": {"coordinates":[11.5263328552,44.4264259338],"type":"Point"}
}