{
  "type": "Feature",
  "properties": {
    "addr:full":"60, Via Varesina 21040 Jerago Con Orago Jerago con Orago Varese 21040",
    "addr:postcode":"21040;orago;21040",
    "addr:street":"Via Varesina;Con Orago;Con",
    "iso:country":"IT",
    "sg:address":"60, Via Varesina 21040 Jerago Con Orago",
    "sg:city":"Jerago con Orago",
    "sg:classifiers":[
        {
            "category":"Professional",
            "subcategory":"Engineering",
            "type":"Services"
        }
    ],
    "sg:phone":"+39 0331 219939",
    "sg:postcode":"21040",
    "sg:province":"Varese",
    "sg:tags":[
        "machine",
        "-",
        "mechanical"
    ],
    "wof:name":"O.m.p. Di Pravato Emilio & C. (s.n.c.)",
    "wof:placetype":"venue"
},
  "geometry": {"coordinates":[8.803082,45.70713],"type":"Point"}
}