{
  "type": "Feature",
  "properties": {
    "addr:full":"20099 Sesto San Giovanni Sesto San Giovanni Milano 20099",
    "addr:postcode":"20099;20099",
    "iso:country":"IT",
    "sg:address":"20099 Sesto San Giovanni",
    "sg:city":"Sesto San Giovanni",
    "sg:orig_category":"Macchine Utensili E Impianti",
    "sg:phone":"+39 02 240 5451",
    "sg:postcode":"20099",
    "sg:province":"Milano",
    "wof:name":"Scumed S.r.l. Societa' Commerciale Utensilerie Macchine E Diamanti",
    "wof:placetype":"venue"
},
  "geometry": {"coordinates":[9.225194,45.524414],"type":"Point"}
}