{
  "type": "Feature",
  "properties": {
    "addr:full":"10040 Leini' Torino 10040",
    "addr:housenumber":"10040",
    "addr:postcode":"10040",
    "addr:street":"Leini ' Torino",
    "iso:country":"IT",
    "sg:address":"10040 Leini'",
    "sg:orig_category":"Vetrerie - Macchine E Forniture",
    "sg:phone":"+39 011 998 8838",
    "sg:postcode":"10040",
    "sg:province":"Torino",
    "wof:name":"T.m.g. Glass Di Bartolino Vincenzo & C.",
    "wof:placetype":"venue"
},
  "geometry": {"coordinates":[7.639202,45.171104],"type":"Point"}
}