{
  "type": "Feature",
  "properties": {
    "addr:full":"20, Viale Lombardia 20015 Parabiago Parabiago Milano 20015",
    "addr:housenumber":"20",
    "addr:postcode":"20015;20015",
    "addr:street":"Viale Lombardia",
    "iso:country":"IT",
    "sg:address":"20, Viale Lombardia 20015 Parabiago",
    "sg:city":"Parabiago",
    "sg:classifiers":[
        {
            "category":"Shopping",
            "subcategory":"Clothing, Apparel, & Fashions",
            "type":"Retail Goods"
        }
    ],
    "sg:phone":"+39 0331 559480",
    "sg:postcode":"20015",
    "sg:province":"Milano",
    "sg:tags":[
        "clothing",
        "accessory"
    ],
    "wof:name":"Tucs (s.r.l.)",
    "wof:placetype":"venue"
},
  "geometry": {"coordinates":[8.949645,45.501839],"type":"Point"}
}