{
  "type": "Feature",
  "properties": {
    "addr:full":"Via Livelli 1 26852 Casaletto Lodigiano Casaletto Lodigiano Lodi 26852",
    "addr:housenumber":"1",
    "addr:postcode":"26852;26852",
    "addr:street":"Via Livelli",
    "iso:country":"IT",
    "sg:address":"Via Livelli 1 26852 Casaletto Lodigiano",
    "sg:city":"Casaletto Lodigiano",
    "sg:classifiers":[
        {
            "category":"Shopping",
            "subcategory":"Pharmacy",
            "type":"Retail Goods"
        }
    ],
    "sg:phone":"+39 0371 739901",
    "sg:postcode":"26852",
    "sg:province":"Lodi",
    "sg:tags":[
        "pharmaceutical"
    ],
    "wof:name":"Sifavitor Spa",
    "wof:placetype":"venue"
},
  "geometry": {"coordinates":[9.3547964096,45.3164558411],"type":"Point"}
}