{
  "type": "Feature",
  "properties": {
    "iso:country":"IT",
    "sg:address":"Via Gradara 15 47838 Riccione",
    "sg:city":"Riccione",
    "sg:classifiers":[
        {
            "category":"Shopping",
            "subcategory":"Clothing, Apparel, & Fashions",
            "type":"Retail Goods"
        }
    ],
    "sg:phone":"+39 0541 655011",
    "sg:postcode":"47838",
    "sg:province":"Rimini",
    "sg:tags":[
        "image",
        "clothing",
        "basic"
    ],
    "wof:name":"Virginia Srl",
    "wof:placetype":"venue"
},
  "geometry": {"coordinates":[12.636979,43.982147],"type":"Point"}
}