{
  "type": "Feature",
  "properties": {
    "addr:full":"Via Montruglio 36024 Mossano Mossano Vicenza 36024",
    "addr:postcode":"36024;36024",
    "addr:street":"Via Montruglio",
    "iso:country":"IT",
    "sg:address":"Via Montruglio 36024 Mossano",
    "sg:city":"Mossano",
    "sg:classifiers":[
        {
            "category":"Farming",
            "subcategory":"Livestock Farm",
            "type":"Manufacturing & Wholesale Goods"
        }
    ],
    "sg:phone":"+39 0444 886222",
    "sg:postcode":"36024",
    "sg:province":"Vicenza",
    "sg:tags":[
        "agriculture"
    ],
    "wof:name":"Azienda Agricola Montruglio (s.p.a.)",
    "wof:placetype":"venue"
},
  "geometry": {"coordinates":[11.573719,45.419266],"type":"Point"}
}