{
  "type": "Feature",
  "properties": {
    "iso:country":"IT",
    "sg:address":"28877 Ornavasso",
    "sg:city":"Ornavasso",
    "sg:orig_category":"Mattatoi - Impianti E Forniture",
    "sg:phone":"+39 0323 837178",
    "sg:postcode":"28877",
    "sg:province":"Verbano-Cusio-Ossola",
    "wof:name":"Ossola Carni Srl",
    "wof:placetype":"venue"
},
  "geometry": {"coordinates":[8.272465,46.139969],"type":"Point"}
}