{
  "type": "Feature",
  "properties": {
    "addr:full":"6/3, Via Pederzana 40055 Castenaso Castenaso Bologna 40055",
    "addr:housenumber":"6 / 3",
    "addr:postcode":"40055;40055",
    "addr:street":"Via Pederzana",
    "iso:country":"IT",
    "sg:address":"6/3, Via Pederzana 40055 Castenaso",
    "sg:city":"Castenaso",
    "sg:classifiers":[
        {
            "category":"Professional",
            "subcategory":"Engineering",
            "type":"Services"
        }
    ],
    "sg:phone":"+39 39051781497",
    "sg:postcode":"40055",
    "sg:province":"Bologna",
    "sg:tags":[
        "machine",
        "-",
        "mechanical"
    ],
    "wof:name":"La Felsinea (s.r.l.)",
    "wof:placetype":"venue"
},
  "geometry": {"coordinates":[11.430782,44.505009],"type":"Point"}
}