{
  "type": "Feature",
  "properties": {
    "addr:full":"31030 Borso Del Grappa Borso del Grappa Treviso 31030",
    "addr:postcode":"31030;31030",
    "iso:country":"IT",
    "sg:address":"31030 Borso Del Grappa",
    "sg:city":"Borso del Grappa",
    "sg:orig_category":"Termotecnica E Riscaldamento, Apparecchiature E Servizi",
    "sg:phone":"+39 0423 9121",
    "sg:postcode":"31030",
    "sg:province":"Treviso",
    "wof:name":"Elba S.p.a.",
    "wof:placetype":"venue"
},
  "geometry": {"coordinates":[11.80302,45.817299],"type":"Point"}
}