{
  "type": "Feature",
  "properties": {
    "iso:country":"IT",
    "sg:address":"21013 Gallarate",
    "sg:city":"Gallarate",
    "sg:classifiers":[
        {
            "category":"Health Services",
            "subcategory":"Health Practitioner",
            "type":"Services"
        }
    ],
    "sg:phone":"+39 0331 790176",
    "sg:postcode":"21013",
    "sg:province":"Varese",
    "sg:tags":[
        "medici"
    ],
    "wof:name":"Turuani Enrico",
    "wof:placetype":"venue"
},
  "geometry": {"coordinates":[8.7992763519,45.6648635864],"type":"Point"}
}