{
  "type": "Feature",
  "properties": {
    "addr:full":"6, Strada Carignano 10024 Moncalieri Moncalieri Torino 10024",
    "addr:postcode":"10024;10024",
    "addr:street":"Strada Carignano",
    "iso:country":"IT",
    "sg:address":"6, Strada Carignano 10024 Moncalieri",
    "sg:city":"Moncalieri",
    "sg:classifiers":[
        {
            "category":"Autos & Motor Vehicles",
            "subcategory":"Automobile Sales",
            "type":"Retail Goods"
        }
    ],
    "sg:phone":"+39 011 640 7413",
    "sg:postcode":"10024",
    "sg:province":"Torino",
    "sg:tags":[
        "equipment",
        "transport"
    ],
    "wof:name":"Giobike S.n.c. Di Giovinazzo Giorgio E C.",
    "wof:placetype":"venue"
},
  "geometry": {"coordinates":[7.669981,44.992176],"type":"Point"}
}