{
  "type": "Feature",
  "properties": {
    "iso:country":"IT",
    "sg:address":"35030 Rubano",
    "sg:city":"Rubano",
    "sg:classifiers":[
        {
            "category":"Manufacturing",
            "subcategory":"Paper Products",
            "type":"Manufacturing & Wholesale Goods"
        }
    ],
    "sg:phone":"+39 049 897 5712",
    "sg:postcode":"35030",
    "sg:province":"Padova",
    "sg:tags":[
        "graphic",
        "publishing",
        "supply",
        "industry",
        "equipment",
        "machinery"
    ],
    "wof:name":"Unigraf Srl",
    "wof:placetype":"venue"
},
  "geometry": {"coordinates":[11.811914,45.421654],"type":"Point"}
}