{
  "type": "Feature",
  "properties": {
    "addr:full":"Via Elpidiense Sud 80 63014 Montegranaro Montegranaro Ascoli Piceno 63014",
    "addr:housenumber":"80",
    "addr:postcode":"63014;63014",
    "addr:street":"Via Elpidiense Sud",
    "iso:country":"IT",
    "sg:address":"Via Elpidiense Sud 80 63014 Montegranaro",
    "sg:city":"Montegranaro",
    "sg:classifiers":[
        {
            "category":"Shopping",
            "subcategory":"Shoes",
            "type":"Retail Goods"
        }
    ],
    "sg:phone":"+39 0734 891066",
    "sg:postcode":"63014",
    "sg:province":"Ascoli Piceno",
    "sg:tags":[
        "men's",
        "boot"
    ],
    "wof:name":"Lidfort Dei F.lli Fortuna & C. Snc",
    "wof:placetype":"venue"
},
  "geometry": {"coordinates":[13.6425981522,43.2348365784],"type":"Point"}
}