{
  "type": "Feature",
  "properties": {
    "iso:country":"IT",
    "sg:address":"20159 Milano",
    "sg:city":"Milano",
    "sg:orig_category":"Servizi E Lavori Per Abbigliamento E Pelletterie",
    "sg:phone":"+39 02 680405",
    "sg:postcode":"20159",
    "sg:province":"Milano",
    "wof:name":"Miotto Teresa",
    "wof:placetype":"venue"
},
  "geometry": {"coordinates":[9.189818,45.491646],"type":"Point"}
}