{
  "type": "Feature",
  "properties": {
    "iso:country":"IT",
    "sg:address":"17, Via Europa 25040 Monticelli Brusati",
    "sg:city":"Monticelli Brusati",
    "sg:classifiers":[
        {
            "category":"Shopping",
            "subcategory":"Computers & Home Electronics",
            "type":"Retail Goods"
        }
    ],
    "sg:phone":"+39 030 685 0351",
    "sg:postcode":"25040",
    "sg:province":"Brescia",
    "sg:tags":[
        "electronic",
        "electrical",
        "equipment"
    ],
    "wof:name":"C.f.cablaggi Elettrici (s.n.c.)",
    "wof:placetype":"venue"
},
  "geometry": {"coordinates":[10.085171,45.62809],"type":"Point"}
}