{
  "type": "Feature",
  "properties": {
    "iso:country":"IT",
    "sg:address":"20024 Garbagnate Milanese",
    "sg:city":"Garbagnate Milanese",
    "sg:orig_category":"Servizi E Lavori Industria Della Gomma",
    "sg:phone":"+39 02 995 5842",
    "sg:postcode":"20024",
    "sg:province":"Milano",
    "wof:name":"Trix Gomma Di Vivaldi Paolo E C. Sas",
    "wof:placetype":"venue"
},
  "geometry": {"coordinates":[9.074162,45.576591],"type":"Point"}
}