{
  "type": "Feature",
  "properties": {
    "iso:country":"IT",
    "sg:address":"1, Localita' Pantiere 61029 Urbino",
    "sg:city":"Urbino",
    "sg:classifiers":[
        {
            "category":"Home & Garden",
            "subcategory":"Home Furnishings",
            "type":"Retail Goods"
        }
    ],
    "sg:phone":"+39 0722 580273",
    "sg:postcode":"61029",
    "sg:province":"Pesaro E Urbino",
    "sg:tags":[
        "household"
    ],
    "wof:name":"Pierre Mobili",
    "wof:placetype":"venue"
},
  "geometry": {"coordinates":[12.674516,43.809906],"type":"Point"}
}