{
  "type": "Feature",
  "properties": {
    "iso:country":"IT",
    "sg:address":"81025 Marcianise",
    "sg:city":"Marcianise",
    "sg:orig_category":"Ceramiche Per Pavimenti E Rivestimenti - Vendita Al Dettaglio",
    "sg:phone":"+39 0823 832059",
    "sg:postcode":"81025",
    "sg:province":"Caserta",
    "wof:name":"Salzillo Salvatore Show Room",
    "wof:placetype":"venue"
},
  "geometry": {"coordinates":[14.29021,41.038631],"type":"Point"}
}