{
  "type": "Feature",
  "properties": {
    "iso:country":"IT",
    "sg:address":"95024 Acireale",
    "sg:city":"Acireale",
    "sg:orig_category":"Macchine, Impianti Ed Attrezzature Industria Chimica. Prodotti Vari In Metallo. Articoli Per Imballaggio E Confezionamento",
    "sg:phone":"+39 095 894259",
    "sg:postcode":"95024",
    "sg:province":"Catania",
    "wof:name":"Pennisi Salvatore Antincendio",
    "wof:placetype":"venue"
},
  "geometry": {"coordinates":[15.147313,37.554592],"type":"Point"}
}