{
  "type": "Feature",
  "properties": {
    "addr:full":"14100 Asti Asti Asti 14100",
    "addr:postcode":"14100;14100",
    "iso:country":"IT",
    "sg:address":"14100 Asti",
    "sg:city":"Asti",
    "sg:orig_category":"Motori Ed Organi Di Trasmissione",
    "sg:phone":"+39 0141 477665",
    "sg:postcode":"14100",
    "sg:province":"Asti",
    "wof:name":"Maina Organi Di Trsamissione Spa",
    "wof:placetype":"venue"
},
  "geometry": {"coordinates":[8.2209320068,44.9048614502],"type":"Point"}
}