{
  "type": "Feature",
  "properties": {
    "addr:full":"85, Via Barbariga 35010 Vigonza Vigonza Padova 35010",
    "addr:postcode":"35010;35010",
    "addr:street":"Via Barbariga",
    "iso:country":"IT",
    "sg:address":"85, Via Barbariga 35010 Vigonza",
    "sg:city":"Vigonza",
    "sg:classifiers":[
        {
            "category":"Personal",
            "subcategory":"Shoe Repair & Shine",
            "type":"Services"
        }
    ],
    "sg:phone":"+39 049 809 5606",
    "sg:postcode":"35010",
    "sg:province":"Padova",
    "sg:tags":[
        "leather"
    ],
    "wof:name":"Favaro",
    "wof:placetype":"venue"
},
  "geometry": {"coordinates":[12.014616,45.421284],"type":"Point"}
}