{
  "type": "Feature",
  "properties": {
    "iso:country":"IT",
    "sg:address":"02015 Cittaducale",
    "sg:city":"Cittaducale",
    "sg:orig_category":"Metalli E Leghe",
    "sg:phone":"+39 0746 496389",
    "sg:postcode":"02015",
    "sg:province":"Rieti",
    "wof:name":"Grillo Mario Srl",
    "wof:placetype":"venue"
},
  "geometry": {"coordinates":[12.9550676346,42.3899002075],"type":"Point"}
}