{
  "type": "Feature",
  "properties": {
    "iso:country":"IT",
    "sg:address":"29, Via Di Vittorio Giuseppe 21046 Malnate",
    "sg:city":"Malnate",
    "sg:classifiers":[
        {
            "category":"Manufacturing",
            "subcategory":"Rubber & Plastics",
            "type":"Manufacturing & Wholesale Goods"
        }
    ],
    "sg:phone":"+39 0332 426426",
    "sg:postcode":"21046",
    "sg:province":"Varese",
    "wof:name":"Pianeta S.n.c. Di Lafranconi M. & C.",
    "wof:placetype":"venue"
},
  "geometry": {"coordinates":[8.877114296,45.7864875793],"type":"Point"}
}