{
  "type": "Feature",
  "properties": {
    "addr:full":"14/16, V. Della Chimica - Spezzano Di Fiorano41040 Fiorano Modenese Modena 41040",
    "addr:housenumber":"14 / 16",
    "addr:postcode":"41040",
    "addr:street":"V. Della Chimica;Di Fiorano41040",
    "iso:country":"IT",
    "sg:address":"14/16, V. Della Chimica - Spezzano Di Fiorano41040 Fiorano Modenese",
    "sg:classifiers":[
        {
            "category":"Shopping",
            "type":"Retail Goods"
        }
    ],
    "sg:phone":"+39 0536 844854",
    "sg:postcode":"41040",
    "sg:province":"Modena",
    "sg:tags":[
        "finished",
        "-",
        "metallic"
    ],
    "sg:website":"http://www.cbmstampi.it",
    "wof:name":"Cbm Srl",
    "wof:placetype":"venue"
},
  "geometry": {"coordinates":[10.8391008377,44.5379180908],"type":"Point"}
}