{
  "type": "Feature",
  "properties": {
    "iso:country":"IT",
    "sg:address":"95024 Acireale",
    "sg:city":"Acireale",
    "sg:orig_category":"Studi E Consulenze Tecniche E Industriali. Servizi E Lavori Per Edilizia E Lavori Pubblici. Professionisti - Studi E Servizi Ed Associazioni Di Interesse Aziendale",
    "sg:phone":"+39 095 764 9686",
    "sg:postcode":"95024",
    "sg:province":"Catania",
    "wof:name":"Costanzo Geom. Rosario",
    "wof:placetype":"venue"
},
  "geometry": {"coordinates":[15.166493,37.586353],"type":"Point"}
}