{
  "type": "Feature",
  "properties": {
    "addr:full":"09125 Cagliari Cagliari Cagliari 09125",
    "addr:postcode":"09125;09125",
    "iso:country":"IT",
    "sg:address":"09125 Cagliari",
    "sg:city":"Cagliari",
    "sg:orig_category":"Prodotti Chimici Secondari",
    "sg:phone":"+39 070 340202",
    "sg:postcode":"09125",
    "sg:province":"Cagliari",
    "wof:name":"Ottelli Esplosivi S.a.s.",
    "wof:placetype":"venue"
},
  "geometry": {"coordinates":[9.1280269623,39.2099075317],"type":"Point"}
}