{
  "type": "Feature",
  "properties": {
    "addr:full":"00143 Roma Roma Roma 00143",
    "addr:postcode":"00143;00143",
    "iso:country":"IT",
    "sg:address":"00143 Roma",
    "sg:city":"Roma",
    "sg:orig_category":"Pubblica Amministrazione",
    "sg:phone":"+39 06 502 2725",
    "sg:postcode":"00143",
    "sg:province":"Roma",
    "wof:name":"Battaglione Trasporti Casilina Comando Reggimento",
    "wof:placetype":"venue"
},
  "geometry": {"coordinates":[12.4925508499,41.8036804199],"type":"Point"}
}