{
  "type": "Feature",
  "properties": {
    "iso:country":"IT",
    "sg:address":"70024 Gravina In Puglia",
    "sg:city":"Gravina in Puglia",
    "sg:orig_category":"Articoli Funerari",
    "sg:phone":"+39 080 326 7666",
    "sg:postcode":"70024",
    "sg:province":"Bari",
    "wof:name":"Cilifrese Vincenzo",
    "wof:placetype":"venue"
},
  "geometry": {"coordinates":[16.416573,40.812656],"type":"Point"}
}