{
  "type": "Feature",
  "properties": {
    "iso:country":"IT",
    "sg:address":"21020 Brebbia",
    "sg:city":"Brebbia",
    "sg:orig_category":"Manufacturers: Prefabbricati",
    "sg:phone":"+39 0332 970999",
    "sg:postcode":"21020",
    "sg:province":"Varese",
    "wof:name":"Giancarlo Graglia Snc",
    "wof:placetype":"venue"
},
  "geometry": {"coordinates":[8.643415,45.81604],"type":"Point"}
}