{
  "type": "Feature",
  "properties": {
    "addr:full":"Via Stephenson 53 20019 Settimo Milanese Settimo Milanese Milano 20019",
    "addr:housenumber":"53",
    "addr:postcode":"20019;20019",
    "addr:street":"Via Stephenson",
    "iso:country":"IT",
    "sg:address":"Via Stephenson 53 20019 Settimo Milanese",
    "sg:city":"Settimo Milanese",
    "sg:classifiers":[
        {
            "category":"Parking",
            "subcategory":"Bicycle",
            "type":"Transportation"
        }
    ],
    "sg:phone":"+39 02 4892 0025",
    "sg:postcode":"20019",
    "sg:province":"Milano",
    "sg:tags":[
        "wheel",
        "dull",
        "grinding"
    ],
    "sg:website":"www.parinimole.it",
    "wof:name":"Parini & C. Srl",
    "wof:placetype":"venue"
},
  "geometry": {"coordinates":[9.065228,45.465946],"type":"Point"}
}