{
  "type": "Feature",
  "properties": {
    "iso:country":"IT",
    "sg:address":"14, Via Guglielmo Marconi 24030 Brembate Di Sopra",
    "sg:city":"Brembate di Sopra",
    "sg:classifiers":[
        {
            "category":"Shopping",
            "subcategory":"Gifts & Souvenirs",
            "type":"Retail Goods"
        }
    ],
    "sg:phone":"+39 39035620519",
    "sg:postcode":"24030",
    "sg:province":"Bergamo",
    "wof:name":"Pubblicarta",
    "wof:placetype":"venue"
},
  "geometry": {"coordinates":[9.594802,45.712944],"type":"Point"}
}