{
  "type": "Feature",
  "properties": {
    "iso:country":"IT",
    "sg:address":"16124 Genova",
    "sg:city":"Genova",
    "sg:orig_category":"Automazione E Macchine Per Ufficio",
    "sg:phone":"+39 010 246 7833",
    "sg:postcode":"16124",
    "sg:province":"Genova",
    "sg:website":"http://devitagenova.it",
    "wof:name":"De Vita Sas",
    "wof:placetype":"venue"
},
  "geometry": {"coordinates":[8.929334,44.409637],"type":"Point"}
}