{
  "type": "Feature",
  "properties": {
    "addr:full":"5, Viale Europa Unita 33020 Sutrio Sutrio Udine 33020",
    "addr:postcode":"33020;33020",
    "addr:street":"Viale Europa Unita",
    "iso:country":"IT",
    "sg:address":"5, Viale Europa Unita 33020 Sutrio",
    "sg:city":"Sutrio",
    "sg:classifiers":[
        {
            "category":"Wholesale",
            "subcategory":"Medical Equipment & Supplies",
            "type":"Manufacturing & Wholesale Goods"
        }
    ],
    "sg:phone":"+39 0433 778678",
    "sg:postcode":"33020",
    "sg:province":"Udine",
    "sg:tags":[
        "-",
        "health",
        "instrument"
    ],
    "wof:name":"Comelstile S.n.c. Di Iob Barbara & C.",
    "wof:placetype":"venue"
},
  "geometry": {"coordinates":[12.990718,46.512672],"type":"Point"}
}