{
  "type": "Feature",
  "properties": {
    "iso:country":"IT",
    "sg:address":"Premana, Lc",
    "sg:classifiers":[
        {
            "category":"Banks & Credit Unions",
            "subcategory":"Bank",
            "type":"Services"
        }
    ],
    "wof:name":"Banca Della Valsassina-credito Cooperativo Scrl",
    "wof:placetype":"venue"
},
  "geometry": {"coordinates":[9.420869,46.052963],"type":"Point"}
}