{
  "type": "Feature",
  "properties": {
    "iso:country":"IT",
    "sg:address":"15060 Basaluzzo",
    "sg:city":"Basaluzzo",
    "sg:orig_category":"Macchine, Impianti E Forniture Per Industria Grafica, Cartaria E Cartotecnica. Forniture Per Uffici",
    "sg:phone":"+39 0143 489989",
    "sg:postcode":"15060",
    "sg:province":"Alessandria",
    "sg:website":"http://www.bngrafica.com",
    "wof:name":"B&n Snc Di Bisio Edilio & Norando Ilario",
    "wof:placetype":"venue"
},
  "geometry": {"coordinates":[8.697519,44.771999],"type":"Point"}
}