{
  "type": "Feature",
  "properties": {
    "addr:full":"50058 Signa Signa Firenze 50058",
    "addr:postcode":"50058;50058",
    "iso:country":"IT",
    "sg:address":"50058 Signa",
    "sg:city":"Signa",
    "sg:orig_category":"Pubblica Amministrazione",
    "sg:phone":"+39 055 899 9014",
    "sg:postcode":"50058",
    "sg:province":"Firenze",
    "wof:name":"Carabinieri",
    "wof:placetype":"venue"
},
  "geometry": {"coordinates":[11.1331720352,43.8021621704],"type":"Point"}
}