{
  "type": "Feature",
  "properties": {
    "iso:country":"IT",
    "sg:address":"4, Via Valle 37060 Sona",
    "sg:city":"Sona",
    "sg:classifiers":[
        {
            "category":"Personal",
            "subcategory":"Shoe Repair & Shine",
            "type":"Services"
        }
    ],
    "sg:phone":"+39 045 609 3000",
    "sg:postcode":"37060",
    "sg:province":"Verona",
    "sg:tags":[
        "leather"
    ],
    "wof:name":"Prialpas S.p.a.",
    "wof:placetype":"venue"
},
  "geometry": {"coordinates":[10.836118,45.445583],"type":"Point"}
}