{
  "type": "Feature",
  "properties": {
    "iso:country":"IT",
    "sg:address":"22034 Brunate",
    "sg:city":"Brunate",
    "sg:orig_category":"Servizi Per Lo Sport E Il Tempo Libero. Servizi Al Turismo",
    "sg:phone":"+39 031 220381",
    "sg:postcode":"22034",
    "sg:province":"Como",
    "wof:name":"Gestione Servizi Trasporti (s.r.l.)",
    "wof:placetype":"venue"
},
  "geometry": {"coordinates":[9.095997,45.819099],"type":"Point"}
}