{
  "type": "Feature",
  "properties": {
    "iso:country":"IT",
    "sg:address":"25060 Cellatica",
    "sg:city":"Cellatica",
    "sg:orig_category":"Lavorazioni Meccaniche E Servizi",
    "sg:phone":"+39 030 277 2801",
    "sg:postcode":"25060",
    "sg:province":"Brescia",
    "wof:name":"Oertli Italia (s.r.l.)",
    "wof:placetype":"venue"
},
  "geometry": {"coordinates":[10.166823,45.582645],"type":"Point"}
}