{
  "type": "Feature",
  "properties": {
    "addr:full":"Via Comm. Lazarito Bocchino 14053 Canelli Canelli Asti 14053",
    "addr:postcode":"14053;14053",
    "addr:street":"Via Comm. Lazarito Bocchino",
    "iso:country":"IT",
    "sg:address":"Via Comm. Lazarito Bocchino 14053 Canelli",
    "sg:city":"Canelli",
    "sg:classifiers":[
        {
            "category":"Coffee & Tea",
            "type":"Food & Drink"
        }
    ],
    "sg:phone":"+39 0141 8101",
    "sg:postcode":"14053",
    "sg:province":"Asti",
    "sg:tags":[
        "aquavit"
    ],
    "sg:website":"www.bocchino.it",
    "wof:name":"Distilleria Canellese C. Bocchino & C.",
    "wof:placetype":"venue"
},
  "geometry": {"coordinates":[8.206813,44.900864],"type":"Point"}
}