{
  "type": "Feature",
  "properties": {
    "iso:country":"IT",
    "sg:address":"20138 Milano",
    "sg:city":"Milano",
    "sg:orig_category":"Servizi Editoriali. Pubblicita', Marketing E Comunicazione",
    "sg:phone":"+39 02 509961",
    "sg:postcode":"20138",
    "sg:province":"Milano",
    "wof:name":"P.i.m. - Pubblicita' Italiana Multimedia Srl",
    "wof:placetype":"venue"
},
  "geometry": {"coordinates":[9.251227,45.453423],"type":"Point"}
}