{
  "type": "Feature",
  "properties": {
    "addr:full":"09025 Sanluri Sanluri Medio Campidano 09025",
    "addr:postcode":"09025;09025",
    "iso:country":"IT",
    "sg:address":"09025 Sanluri",
    "sg:city":"Sanluri",
    "sg:orig_category":"Campeggio. Automobili E Mezzi Di Trasporto",
    "sg:phone":"+39 070 937 0525",
    "sg:postcode":"09025",
    "sg:province":"Medio Campidano",
    "wof:name":"Eurogas Di Ibba G. E C. Snc",
    "wof:placetype":"venue"
},
  "geometry": {"coordinates":[8.704075,39.531738],"type":"Point"}
}