{
  "type": "Feature",
  "properties": {
    "iso:country":"IT",
    "sg:address":"95122 Catania",
    "sg:city":"Catania",
    "sg:orig_category":"Bomboniere Ed Accessori",
    "sg:phone":"+39 095 731 5622",
    "sg:postcode":"95122",
    "sg:province":"Catania",
    "sg:website":"http://www.commirsrl.com",
    "wof:name":"Commir Srl",
    "wof:placetype":"venue"
},
  "geometry": {"coordinates":[15.039861,37.565239],"type":"Point"}
}