{
  "type": "Feature",
  "properties": {
    "iso:country":"IT",
    "sg:address":"20019 Settimo Milanese",
    "sg:city":"Settimo Milanese",
    "sg:orig_category":"Centrifughe",
    "sg:phone":"+39 02 328 3641",
    "sg:postcode":"20019",
    "sg:province":"Milano",
    "wof:name":"Comi Condor Spa",
    "wof:placetype":"venue"
},
  "geometry": {"coordinates":[9.071382,45.477093],"type":"Point"}
}