{
  "type": "Feature",
  "properties": {
    "iso:country":"IT",
    "sg:address":"67 Via Mantova, 38100 Trento",
    "sg:city":"Trento",
    "sg:classifiers":[
        {
            "category":"Banks & Credit Unions",
            "subcategory":"Financial Services",
            "type":"Services"
        }
    ],
    "sg:phone":"+39 0461 982112",
    "sg:postcode":"38100",
    "sg:province":"Trento",
    "sg:tags":[
        "banking",
        "finance",
        "insurance"
    ],
    "wof:name":"Itas Istituto Trentino Alto Adige Per Assicurazioni",
    "wof:placetype":"venue"
},
  "geometry": {"coordinates":[11.1242742538,46.0668067932],"type":"Point"}
}