{
  "type": "Feature",
  "properties": {
    "iso:country":"IT",
    "sg:address":"00147 Roma",
    "sg:city":"Roma",
    "sg:orig_category":"Ospedali E Servizi Sanitari",
    "sg:phone":"+39 06 540 7892",
    "sg:postcode":"00147",
    "sg:province":"Roma",
    "wof:name":"Centro Medico Michelangelo Srl",
    "wof:placetype":"venue"
},
  "geometry": {"coordinates":[12.487101,41.848598],"type":"Point"}
}