{
  "type": "Feature",
  "properties": {
    "iso:country":"IT",
    "sg:address":"416, Via Vitruvio 04023 Formia",
    "sg:city":"Formia",
    "sg:classifiers":[
        {
            "category":"Wholesale",
            "subcategory":"Drugs",
            "type":"Manufacturing & Wholesale Goods"
        }
    ],
    "sg:phone":"+39 0771 771281",
    "sg:postcode":"04023",
    "sg:province":"Latina",
    "sg:tags":[
        "chemical",
        "pharmaceutical"
    ],
    "wof:name":"Farmaceutici Magliocco Srl",
    "wof:placetype":"venue"
},
  "geometry": {"coordinates":[13.59887,41.252937],"type":"Point"}
}