{
  "type": "Feature",
  "properties": {
    "addr:full":"41, Via Galvani 39100 Bolzano Bolzano Bolzano/Bozen 39100",
    "addr:postcode":"39100;39100",
    "addr:street":"Via Galvani",
    "iso:country":"IT",
    "sg:address":"41, Via Galvani 39100 Bolzano",
    "sg:city":"Bolzano",
    "sg:classifiers":[
        {
            "category":"Autos & Motor Vehicles",
            "subcategory":"Automobile Sales",
            "type":"Retail Goods"
        }
    ],
    "sg:phone":"+39 0471 550000",
    "sg:postcode":"39100",
    "sg:province":"Bolzano/Bozen",
    "sg:tags":[
        "motor-cars"
    ],
    "wof:name":"Autoindustriale S.r.l.",
    "wof:placetype":"venue"
},
  "geometry": {"coordinates":[11.3282394409,46.461643219],"type":"Point"}
}