{
  "type": "Feature",
  "properties": {
    "iso:country":"IT",
    "sg:address":"20090 Assago",
    "sg:city":"Assago",
    "sg:orig_category":"Prodotti Chimici Secondari. Macchine, Impianti Ed Attrezzature Industria Chimica. Servizi E Lavori Industria Chimica",
    "sg:phone":"+39 02 488 0523",
    "sg:postcode":"20090",
    "sg:province":"Milano",
    "wof:name":"Nuova Tecnosol S.r.l.",
    "wof:placetype":"venue"
},
  "geometry": {"coordinates":[9.1174621582,45.4066314697],"type":"Point"}
}