{
  "type": "Feature",
  "properties": {
    "iso:country":"IT",
    "sg:address":"09126 Cagliari",
    "sg:city":"Cagliari",
    "sg:orig_category":"Nautica. Automobili E Mezzi Di Trasporto",
    "sg:phone":"+39 070 308730",
    "sg:postcode":"09126",
    "sg:province":"Cagliari",
    "wof:name":"Cantieri Del Sole Srl",
    "wof:placetype":"venue"
},
  "geometry": {"coordinates":[9.139734,39.199669],"type":"Point"}
}