{
  "type": "Feature",
  "properties": {
    "iso:country":"IT",
    "sg:address":"74100 Taranto",
    "sg:city":"Taranto",
    "sg:orig_category":"Materiali Edili",
    "sg:phone":"+39 099 477 7250",
    "sg:postcode":"74100",
    "sg:province":"Taranto",
    "wof:name":"Chiloiro Pietro",
    "wof:placetype":"venue"
},
  "geometry": {"coordinates":[17.278446,40.398026],"type":"Point"}
}