{
  "type": "Feature",
  "properties": {
    "addr:full":"22031 Albavilla Albavilla Como 22031",
    "addr:postcode":"22031;22031",
    "iso:country":"IT",
    "sg:address":"22031 Albavilla",
    "sg:city":"Albavilla",
    "sg:orig_category":"Lavorazioni Meccaniche E Servizi",
    "sg:phone":"+39 031 627055",
    "sg:postcode":"22031",
    "sg:province":"Como",
    "sg:website":"http://www.mazzarodolfo.com",
    "wof:name":"Mazza Rodolfo Srl",
    "wof:placetype":"venue"
},
  "geometry": {"coordinates":[9.187765,45.801987],"type":"Point"}
}