{
  "type": "Feature",
  "properties": {
    "iso:country":"IT",
    "sg:address":"Via Santuario 18 20060 Ornago",
    "sg:city":"Ornago",
    "sg:classifiers":[
        {
            "category":"Autos & Motor Vehicles",
            "subcategory":"Recreational Vehicle Sales",
            "type":"Retail Goods"
        }
    ],
    "sg:phone":"+39 039 601 0396",
    "sg:postcode":"20060",
    "sg:province":"Milano",
    "sg:tags":[
        "machine",
        "manufacturing",
        "cable"
    ],
    "wof:name":"Cigiemme S.r.l.",
    "wof:placetype":"venue"
},
  "geometry": {"coordinates":[9.431003,45.59861],"type":"Point"}
}