{
  "type": "Feature",
  "properties": {
    "addr:full":"11100 Aosta Aosta Aosta 11100",
    "addr:postcode":"11100;11100",
    "iso:country":"IT",
    "sg:address":"11100 Aosta",
    "sg:city":"Aosta",
    "sg:orig_category":"Fiori E Piante - Vendita Al Dettaglio",
    "sg:phone":"+39 0165 43372",
    "sg:postcode":"11100",
    "sg:province":"Aosta",
    "wof:name":"3d Di De Matteis Caterina & C. Snc",
    "wof:placetype":"venue"
},
  "geometry": {"coordinates":[7.3156661987,45.7357330322],"type":"Point"}
}