{
  "type": "Feature",
  "properties": {
    "iso:country":"IT",
    "sg:address":"149/r, Via Romana 50125 Firenze",
    "sg:city":"Firenze",
    "sg:classifiers":[
        {
            "category":"Shopping",
            "type":"Retail Goods"
        }
    ],
    "sg:phone":"+39 39055229288",
    "sg:postcode":"50125",
    "sg:province":"Firenze",
    "sg:tags":[
        "finished",
        "-",
        "metallic"
    ],
    "wof:name":"Il Bronzetto",
    "wof:placetype":"venue"
},
  "geometry": {"coordinates":[11.2473039627,43.7642936707],"type":"Point"}
}