{
  "type": "Feature",
  "properties": {
    "iso:country":"IT",
    "sg:address":"Via Ranelletti 277; Celano; 67043",
    "sg:classifiers":[
        {
            "category":"Banks & Credit Unions",
            "subcategory":"Bank",
            "type":"Services"
        }
    ],
    "sg:phone":"+39 0863 791247",
    "sg:postcode":"67043",
    "sg:province":"L'Aquila",
    "wof:name":"Banco Di Napoli Spa",
    "wof:placetype":"venue"
},
  "geometry": {"coordinates":[13.549971,42.081287],"type":"Point"}
}