{
  "type": "Feature",
  "properties": {
    "addr:full":"Contrada Contrasto Sant' Elia 96100 Siracusa Siracusa Siracusa 96100",
    "addr:postcode":"96100;96100",
    "addr:street":"Contrada Contrasto Sant ' Elia",
    "iso:country":"IT",
    "sg:address":"Contrada Contrasto Sant' Elia 96100 Siracusa",
    "sg:city":"Siracusa",
    "sg:classifiers":[
        {
            "category":"Food & Beverages",
            "subcategory":"Fruits & Vegetables",
            "type":"Retail Goods"
        }
    ],
    "sg:phone":"+39 0931 710076",
    "sg:postcode":"96100",
    "sg:province":"Siracusa",
    "sg:website":"www.agricolturacampisi.it",
    "wof:name":"Azienda Agricola Campisi Giuseppe",
    "wof:placetype":"venue"
},
  "geometry": {"coordinates":[15.2844400406,37.0664825439],"type":"Point"}
}