{
  "type": "Feature",
  "properties": {
    "iso:country":"IT",
    "sg:address":"36061 Bassano Del Grappa",
    "sg:city":"Bassano del Grappa",
    "sg:orig_category":"Medici Specialisti - Chirurgia Plastica E Ricostruttiva",
    "sg:phone":"+39 0424 525309",
    "sg:postcode":"36061",
    "sg:province":"Vicenza",
    "wof:name":"Donolato Danilo",
    "wof:placetype":"venue"
},
  "geometry": {"coordinates":[11.695682,45.712212],"type":"Point"}
}