{
  "type": "Feature",
  "properties": {
    "addr:full":"25128 Brescia Brescia Brescia 25128",
    "addr:postcode":"25128;25128",
    "iso:country":"IT",
    "sg:address":"25128 Brescia",
    "sg:city":"Brescia",
    "sg:orig_category":"Articoli Pulizia. Macchine E Forniture Per Ecologia E Smaltimento Rifiuti. Forniture Per Attivita' Commerciali Ed Artigianali",
    "sg:phone":"+39 030 304249",
    "sg:postcode":"25128",
    "sg:province":"Brescia",
    "wof:name":"Nuova Gaber's Srl",
    "wof:placetype":"venue"
},
  "geometry": {"coordinates":[10.220082,45.557796],"type":"Point"}
}