{
  "type": "Feature",
  "properties": {
    "iso:country":"IT",
    "sg:address":"38, Via Cremasca 24052 Azzano San Paolo",
    "sg:city":"Azzano San Paolo",
    "sg:classifiers":[
        {
            "category":"Shopping",
            "subcategory":"Clothing, Apparel, & Fashions",
            "type":"Retail Goods"
        }
    ],
    "sg:phone":"+39 39035530739",
    "sg:postcode":"24052",
    "sg:province":"Bergamo",
    "sg:tags":[
        "clothes"
    ],
    "wof:name":"Confezioni Tahir",
    "wof:placetype":"venue"
},
  "geometry": {"coordinates":[9.680089,45.660496],"type":"Point"}
}