{
  "type": "Feature",
  "properties": {
    "iso:country":"IT",
    "sg:address":"70033 Corato",
    "sg:city":"Corato",
    "sg:orig_category":"Apparecchiature E Sistemi Per Magazzinaggio E Movimentazione",
    "sg:phone":"+39 080 358 8109",
    "sg:postcode":"70033",
    "sg:province":"Bari",
    "wof:name":"Giam Ascensori Sas",
    "wof:placetype":"venue"
},
  "geometry": {"coordinates":[16.369926,41.078545],"type":"Point"}
}