{
  "type": "Feature",
  "properties": {
    "addr:full":"20090 Trezzano Sul Naviglio Trezzano sul Naviglio Milano 20090",
    "addr:postcode":"20090;20090",
    "iso:country":"IT",
    "sg:address":"20090 Trezzano Sul Naviglio",
    "sg:city":"Trezzano sul Naviglio",
    "sg:orig_category":"Nautica. Accessori Dei Mezzi Di Trasporto",
    "sg:phone":"+39 02 445 1159",
    "sg:postcode":"20090",
    "sg:province":"Milano",
    "sg:website":"http://www.veleevento.com",
    "wof:name":"Vele E Vento Srl",
    "wof:placetype":"venue"
},
  "geometry": {"coordinates":[9.053175,45.421341],"type":"Point"}
}