{
  "type": "Feature",
  "properties": {
    "iso:country":"IT",
    "sg:address":"19126 La Spezia",
    "sg:orig_category":"Non-classified Establishments",
    "sg:phone":"+39 0187 500975",
    "sg:province":"SP",
    "wof:name":"Selecta Parati Srl",
    "wof:placetype":"venue"
},
  "geometry": {"coordinates":[9.840729,44.114304],"type":"Point"}
}