{
  "type": "Feature",
  "properties": {
    "iso:country":"IT",
    "sg:address":"178, Via Mammianese 51017 Pescia",
    "sg:city":"Pescia",
    "sg:classifiers":[
        {
            "category":"Manufacturing",
            "subcategory":"Rubber & Plastics",
            "type":"Manufacturing & Wholesale Goods"
        }
    ],
    "sg:phone":"+39 0572 408090",
    "sg:postcode":"51017",
    "sg:province":"Pistoia",
    "wof:name":"Nuova Pasquini E Bini S.r.l.",
    "wof:placetype":"venue"
},
  "geometry": {"coordinates":[10.7765159607,43.9624481201],"type":"Point"}
}