{
  "type": "Feature",
  "properties": {
    "iso:country":"IT",
    "sg:address":"85057 Tramutola",
    "sg:city":"Tramutola",
    "sg:orig_category":"Macchine Utensili E Impianti. Elettrotecnica Industriale, Prodotti E Apparecchiature",
    "sg:phone":"+39 0975 353210",
    "sg:postcode":"85057",
    "sg:province":"Potenza",
    "wof:name":"Grieco Michele",
    "wof:placetype":"venue"
},
  "geometry": {"coordinates":[15.788755,40.319103],"type":"Point"}
}