{
  "type": "Feature",
  "properties": {
    "iso:country":"IT",
    "sg:address":"20060 Ornago",
    "sg:city":"Ornago",
    "sg:orig_category":"Frigoriferi Industriali E Commerciali - Commercio",
    "sg:phone":"+39 039 691 9126",
    "sg:postcode":"20060",
    "sg:province":"Milano",
    "wof:name":"Frigotek Coop. Arl",
    "wof:placetype":"venue"
},
  "geometry": {"coordinates":[9.1693735123,45.5459594727],"type":"Point"}
}