{
  "type": "Feature",
  "properties": {
    "iso:country":"IT",
    "sg:address":"12, Via San Vitale 43038 Sala Baganza",
    "sg:city":"Sala Baganza",
    "sg:classifiers":[
        {
            "category":"Food & Beverages",
            "subcategory":"Groceries & Convenience Stores",
            "type":"Retail Goods"
        }
    ],
    "sg:phone":"+39 0521 335811",
    "sg:postcode":"43038",
    "sg:province":"Parma",
    "sg:tags":[
        "product",
        "related"
    ],
    "wof:name":"Fontana Ermes Spa",
    "wof:placetype":"venue"
},
  "geometry": {"coordinates":[10.2211589813,44.6955337524],"type":"Point"}
}