{
  "type": "Feature",
  "properties": {
    "addr:full":"21052 Busto Arsizio Busto Arsizio Varese 21052",
    "addr:postcode":"21052;21052",
    "iso:country":"IT",
    "sg:address":"21052 Busto Arsizio",
    "sg:city":"Busto Arsizio",
    "sg:orig_category":"Abbigliamento Sportivo - Produzione E Ingrosso",
    "sg:phone":"+39 0331 340150",
    "sg:postcode":"21052",
    "sg:province":"Varese",
    "wof:name":"Pizzoli Elio",
    "wof:placetype":"venue"
},
  "geometry": {"coordinates":[8.84652,45.593891],"type":"Point"}
}