{
  "type": "Feature",
  "properties": {
    "iso:country":"IT",
    "sg:address":"90147 Palermo",
    "sg:city":"Palermo",
    "sg:orig_category":"Minuterie Metalliche E Ferramenta. Ricambi E Componenti Dei Mezzi Di Trasporto",
    "sg:phone":"+39 091 241081",
    "sg:postcode":"90147",
    "sg:province":"Palermo",
    "wof:name":"Romeo & Schillaci",
    "wof:placetype":"venue"
},
  "geometry": {"coordinates":[13.2920217514,38.1804771423],"type":"Point"}
}