{
  "type": "Feature",
  "properties": {
    "iso:country":"IT",
    "sg:address":"Via Ancillotto 2; S. Dona Di Piave",
    "sg:classifiers":[
        {
            "category":"Banks & Credit Unions",
            "subcategory":"Bank",
            "type":"Services"
        }
    ],
    "sg:phone":"+39 0421 331104",
    "wof:name":"Banca Di Roma",
    "wof:placetype":"venue"
},
  "geometry": {"coordinates":[12.691202,45.636555],"type":"Point"}
}