{
  "type": "Feature",
  "properties": {
    "iso:country":"IT",
    "sg:address":"42100 Reggio Emilia",
    "sg:orig_category":"Autoscuole",
    "sg:phone":"+39 0522 284234",
    "sg:postcode":"42100",
    "sg:province":"Reggio Nell'Emilia",
    "wof:name":"Autoscuole Tirelli Di Barozzi Vittorio",
    "wof:placetype":"venue"
},
  "geometry": {"coordinates":[10.479119,44.277771],"type":"Point"}
}