{
  "type": "Feature",
  "properties": {
    "iso:country":"IT",
    "sg:address":"20081 Cassinetta Di Lugagnano",
    "sg:city":"Cassinetta di Lugagnano",
    "sg:orig_category":"Acciaierie E Fonderie",
    "sg:phone":"+39 02 9459 9979",
    "sg:postcode":"20081",
    "sg:province":"Milano",
    "wof:name":"Laminatoi Enef S.r.l.",
    "wof:placetype":"venue"
},
  "geometry": {"coordinates":[8.905412,45.419861],"type":"Point"}
}