{
  "type": "Feature",
  "properties": {
    "addr:full":"Piazza Baracca 24, 48022 Lugo, Ra Lugo Ravenna 48022",
    "addr:housenumber":"24",
    "addr:postcode":"48022;48022",
    "addr:street":"Piazza Baracca",
    "iso:country":"IT",
    "sg:address":"Piazza Baracca 24, 48022 Lugo, Ra",
    "sg:city":"Lugo",
    "sg:classifiers":[
        {
            "category":"Banks & Credit Unions",
            "subcategory":"Bank",
            "type":"Services"
        }
    ],
    "sg:phone":"+39 0545 39811",
    "sg:postcode":"48022",
    "sg:province":"Ravenna",
    "wof:name":"Fondazione Cassa Di Risparmio E Banca Del Monte Di Lugo",
    "wof:placetype":"venue"
},
  "geometry": {"coordinates":[12.196571,44.41573],"type":"Point"}
}