{
  "type": "Feature",
  "properties": {
    "iso:country":"IT",
    "sg:address":"06070 Corciano",
    "sg:city":"Corciano",
    "sg:orig_category":"Macchine E Forniture Per Ecologia E Smaltimento Rifiuti",
    "sg:phone":"+39 075 514 0102",
    "sg:postcode":"06070",
    "sg:province":"Perugia",
    "sg:website":"http://www.costarelli.it",
    "wof:name":"Officine Costarelli Snc",
    "wof:placetype":"venue"
},
  "geometry": {"coordinates":[12.316349,43.074615],"type":"Point"}
}