{
  "type": "Feature",
  "properties": {
    "iso:country":"IT",
    "sg:address":"10/a, Via Copernico Niccolo' 50051 Castelfiorentino",
    "sg:city":"Castelfiorentino",
    "sg:classifiers":[
        {
            "category":"Farming",
            "subcategory":"Livestock Farm",
            "type":"Manufacturing & Wholesale Goods"
        }
    ],
    "sg:phone":"+39 39057164135",
    "sg:postcode":"50051",
    "sg:province":"Firenze",
    "sg:tags":[
        "agriculture"
    ],
    "wof:name":"Simoni S.r.l.",
    "wof:placetype":"venue"
},
  "geometry": {"coordinates":[11.256902,43.768734],"type":"Point"}
}