{
  "type": "Feature",
  "properties": {
    "iso:country":"IT",
    "sg:address":"20138 Milano",
    "sg:city":"Milano",
    "sg:orig_category":"Aerotaxi",
    "sg:phone":"+39 02 756 0066",
    "sg:postcode":"20138",
    "sg:province":"Milano",
    "sg:website":"http://www.hifly.it",
    "wof:name":"Hi Fly",
    "wof:placetype":"venue"
},
  "geometry": {"coordinates":[9.26141,45.452328],"type":"Point"}
}