{
  "type": "Feature",
  "properties": {
    "iso:country":"IT",
    "sg:address":"80133 Napoli",
    "sg:city":"Napoli",
    "sg:orig_category":"Lavorazioni Meccaniche E Servizi. Riparazione Dei Mezzi Di Trasporto",
    "sg:phone":"+39 081 265358",
    "sg:postcode":"80133",
    "sg:province":"Napoli",
    "wof:name":"T.m.s.sas Di Fabbri Salvatore",
    "wof:placetype":"venue"
},
  "geometry": {"coordinates":[14.255583,40.841072],"type":"Point"}
}