{
  "type": "Feature",
  "properties": {
    "addr:full":"20, Via S. Pio X 31020 San Zenone Degli Ezzelini San Zenone degli Ezzelini Treviso 31020",
    "addr:postcode":"31020;31020",
    "addr:street":"Via S.",
    "iso:country":"IT",
    "sg:address":"20, Via S. Pio X 31020 San Zenone Degli Ezzelini",
    "sg:city":"San Zenone degli Ezzelini",
    "sg:classifiers":[
        {
            "category":"Real Estate",
            "subcategory":"Surveying",
            "type":"Services"
        }
    ],
    "sg:phone":"+39 0423 968681",
    "sg:postcode":"31020",
    "sg:province":"Treviso",
    "sg:tags":[
        "equipment",
        "material",
        "good",
        "-",
        "handling"
    ],
    "wof:name":"Costa Imballaggi (s.r.l.)",
    "wof:placetype":"venue"
},
  "geometry": {"coordinates":[12.242072,45.666286],"type":"Point"}
}