{
  "type": "Feature",
  "properties": {
    "iso:country":"IT",
    "sg:address":"40012 Calderara Di Reno",
    "sg:city":"Calderara di Reno",
    "sg:orig_category":"Riduttori Velocita'",
    "sg:phone":"+39 051 729916",
    "sg:postcode":"40012",
    "sg:province":"Bologna",
    "wof:name":"Cobra Srl",
    "wof:placetype":"venue"
},
  "geometry": {"coordinates":[11.255376,44.556087],"type":"Point"}
}