{
  "type": "Feature",
  "properties": {
    "iso:country":"IT",
    "sg:address":"13864 Crevacuore",
    "sg:city":"Crevacuore",
    "sg:orig_category":"Utensili Meccanici E Materiali",
    "sg:phone":"+39 015 768788",
    "sg:postcode":"13864",
    "sg:province":"Biella",
    "wof:name":"Nalin Livio",
    "wof:placetype":"venue"
},
  "geometry": {"coordinates":[8.246106,45.688328],"type":"Point"}
}