{
  "type": "Feature",
  "properties": {
    "addr:full":"Largo Mamiani, 2/4; Pesaro; 61100 Pesaro Pesaro E Urbino 61100",
    "addr:housenumber":"2 / 4",
    "addr:postcode":"61100;61100",
    "addr:street":"Largo Mamiani",
    "iso:country":"IT",
    "sg:address":"Largo Mamiani, 2/4; Pesaro; 61100",
    "sg:city":"Pesaro",
    "sg:classifiers":[
        {
            "category":"Banks & Credit Unions",
            "subcategory":"Bank",
            "type":"Services"
        }
    ],
    "sg:phone":"+39 0721 33661",
    "sg:postcode":"61100",
    "sg:province":"Pesaro E Urbino",
    "wof:name":"Banca Nazionale Del Lavoro",
    "wof:placetype":"venue"
},
  "geometry": {"coordinates":[12.9135,43.909863],"type":"Point"}
}