{
  "type": "Feature",
  "properties": {
    "addr:full":"50133 Firenze Firenze Firenze 50133",
    "addr:postcode":"50133;50133",
    "iso:country":"IT",
    "sg:address":"50133 Firenze",
    "sg:city":"Firenze",
    "sg:orig_category":"Medicinali E Prodotti Parafarmaceutici",
    "sg:phone":"+39 055 504 8155",
    "sg:postcode":"50133",
    "sg:province":"Firenze",
    "wof:name":"Amorovi Di Rita Vitrano",
    "wof:placetype":"venue"
},
  "geometry": {"coordinates":[11.311249733,43.8337135315],"type":"Point"}
}