{
  "type": "Feature",
  "properties": {
    "iso:country":"IT",
    "sg:address":"27100 Pavia",
    "sg:city":"Pavia",
    "sg:orig_category":"Servizi Ausiliari Per Il Trasporto. Servizi Vari Di Interesse Pubblico",
    "sg:phone":"+39 0382 24301",
    "sg:postcode":"27100",
    "sg:province":"Pavia",
    "wof:name":"Agenzie Funebri Riunite B.b.m.",
    "wof:placetype":"venue"
},
  "geometry": {"coordinates":[9.160515,45.191425],"type":"Point"}
}