{
  "type": "Feature",
  "properties": {
    "addr:full":"50019 Sesto Fiorentino Sesto Fiorentino Firenze 50019",
    "addr:postcode":"50019;50019",
    "iso:country":"IT",
    "sg:address":"50019 Sesto Fiorentino",
    "sg:city":"Sesto Fiorentino",
    "sg:orig_category":"Elettrodomestici - Riparazione E Vendita Al Dettaglio Di Accessori",
    "sg:phone":"+39 055 452 3223",
    "sg:postcode":"50019",
    "sg:province":"Firenze",
    "sg:website":"http://ofmar.it",
    "wof:name":"Of. Mar. Snc",
    "wof:placetype":"venue"
},
  "geometry": {"coordinates":[11.217437,43.822197],"type":"Point"}
}