{
  "type": "Feature",
  "properties": {
    "addr:full":"00013 Mentana Mentana Roma 00013",
    "addr:postcode":"00013;00013",
    "iso:country":"IT",
    "sg:address":"00013 Mentana",
    "sg:city":"Mentana",
    "sg:orig_category":"Scuole E Servizi Scolastici. Servizi Per Lo Sport E Il Tempo Libero",
    "sg:phone":"+39 06 906 3529",
    "sg:postcode":"00013",
    "sg:province":"Roma",
    "wof:name":"Pianeta Musica",
    "wof:placetype":"venue"
},
  "geometry": {"coordinates":[12.614895,42.000999],"type":"Point"}
}