{
  "type": "Feature",
  "properties": {
    "iso:country":"IT",
    "sg:address":"52, V. Volta 20090 Cusago",
    "sg:city":"Cusago",
    "sg:classifiers":[
        {
            "category":"Utilities",
            "subcategory":"Electric",
            "type":"Services"
        }
    ],
    "sg:phone":"+39 02 9011 9641",
    "sg:postcode":"20090",
    "sg:province":"Milano",
    "sg:tags":[
        "component",
        "electronic"
    ],
    "sg:website":"http://www.fati.com:ws_end: :mark:ws:http://www.paginegialle.it/fatiheater",
    "wof:name":"F.a.t.i. Srl",
    "wof:placetype":"venue"
},
  "geometry": {"coordinates":[9.047132,45.441761],"type":"Point"}
}