{
  "type": "Feature",
  "properties": {
    "iso:country":"IT",
    "sg:address":"118, Via Aurelia 19020 Vezzano Ligure",
    "sg:city":"Vezzano Ligure",
    "sg:classifiers":[
        {
            "category":"Sports & Exercise",
            "subcategory":"Playing Field",
            "type":"Entertainment"
        }
    ],
    "sg:phone":"+39 0187 980028",
    "sg:postcode":"19020",
    "sg:province":"La Spezia",
    "sg:tags":[
        "game"
    ],
    "wof:name":"Fiorista Simoncini Franco",
    "wof:placetype":"venue"
},
  "geometry": {"coordinates":[9.890871,44.125816],"type":"Point"}
}