{
  "type": "Feature",
  "properties": {
    "iso:country":"IT",
    "sg:address":"Via Miraglia Biagio 72 80141 Napoli",
    "sg:city":"Napoli",
    "sg:classifiers":[
        {
            "category":"Real Estate",
            "subcategory":"Architect",
            "type":"Services"
        }
    ],
    "sg:phone":"+39 081 451887",
    "sg:postcode":"80141",
    "sg:province":"Napoli",
    "sg:tags":[
        "men's",
        "shirts",
        "shirt"
    ],
    "sg:website":"www.sacar.it",
    "wof:name":"Camiceria Sacar Srl",
    "wof:placetype":"venue"
},
  "geometry": {"coordinates":[14.251636,40.840096],"type":"Point"}
}