{
  "type": "Feature",
  "properties": {
    "addr:full":"24, Viale Europa 35020 Ponte San Nicolo' Padova 35020",
    "addr:housenumber":"24",
    "addr:postcode":"35020;35020",
    "addr:street":"Viale Europa;Nicolo ' Padova",
    "iso:country":"IT",
    "sg:address":"24, Viale Europa 35020 Ponte San Nicolo'",
    "sg:classifiers":[
        {
            "category":"Communications",
            "subcategory":"Television Station",
            "type":"Services"
        }
    ],
    "sg:phone":"+39 049 896 1488",
    "sg:postcode":"35020",
    "sg:province":"Padova",
    "sg:tags":[
        "audio-visual"
    ],
    "wof:name":"Steiel Elettronica (s.r.l.)",
    "wof:placetype":"venue"
},
  "geometry": {"coordinates":[11.930796,45.355316],"type":"Point"}
}