{
  "type": "Feature",
  "properties": {
    "addr:full":"95011 Calatabiano Calatabiano Catania 95011",
    "addr:postcode":"95011;95011",
    "iso:country":"IT",
    "sg:address":"95011 Calatabiano",
    "sg:city":"Calatabiano",
    "sg:classifiers":[
        {
            "category":"Shopping",
            "subcategory":"Crafts & Fabrics",
            "type":"Retail Goods"
        }
    ],
    "sg:phone":"+39 095 645598",
    "sg:postcode":"95011",
    "sg:province":"Catania",
    "sg:tags":[
        "material"
    ],
    "sg:website":"http://www.stiltex.net",
    "wof:name":"Stiltex Srl",
    "wof:placetype":"venue"
},
  "geometry": {"coordinates":[15.2077798843,37.816619873],"type":"Point"}
}