{
  "type": "Feature",
  "properties": {
    "addr:full":"10155 Torino Torino Torino 10155",
    "addr:postcode":"10155;10155",
    "iso:country":"IT",
    "sg:address":"10155 Torino",
    "sg:city":"Torino",
    "sg:orig_category":"Lavorazioni Metalli, Stampaggio E Saldatura",
    "sg:phone":"+39 011 248 2425",
    "sg:postcode":"10155",
    "sg:province":"Torino",
    "wof:name":"Garbero Paolo",
    "wof:placetype":"venue"
},
  "geometry": {"coordinates":[7.562522,45.06562],"type":"Point"}
}