{
  "type": "Feature",
  "properties": {
    "iso:country":"IT",
    "sg:address":"33040 Visco",
    "sg:city":"Visco",
    "sg:orig_category":"Petroli, Gas E Combustibili",
    "sg:phone":"+39 800 112 277",
    "sg:postcode":"33040",
    "sg:province":"Udine",
    "wof:name":"Shell Gas Italia Spa",
    "wof:placetype":"venue"
},
  "geometry": {"coordinates":[13.3767595291,45.9134483337],"type":"Point"}
}