{
  "type": "Feature",
  "properties": {
    "addr:full":"88100 Catanzaro Catanzaro Catanzaro 88100",
    "addr:postcode":"88100;88100",
    "iso:country":"IT",
    "sg:address":"88100 Catanzaro",
    "sg:city":"Catanzaro",
    "sg:orig_category":"Geologia, Geotecnica E Topografia - Studi E Servizi",
    "sg:phone":"+39 0961 753363",
    "sg:postcode":"88100",
    "sg:province":"Catanzaro",
    "wof:name":"S.i.p.i. Sas",
    "wof:placetype":"venue"
},
  "geometry": {"coordinates":[16.597515,38.902561],"type":"Point"}
}