{
  "type": "Feature",
  "properties": {
    "iso:country":"IT",
    "sg:address":"16143 Genova",
    "sg:city":"Genova",
    "sg:orig_category":"Televisori, Videoregistratori E Radio - Riparazione",
    "sg:phone":"+39 010 511493",
    "sg:postcode":"16143",
    "sg:province":"Genova",
    "wof:name":"De Grandis",
    "wof:placetype":"venue"
},
  "geometry": {"coordinates":[8.960418,44.407516],"type":"Point"}
}