{
  "type": "Feature",
  "properties": {
    "iso:country":"IT",
    "sg:address":"35020 Due Carrare",
    "sg:city":"Due Carrare",
    "sg:orig_category":"Pubblicita', Marketing E Comunicazione",
    "sg:phone":"+39 049 912 5183",
    "sg:postcode":"35020",
    "sg:province":"Padova",
    "wof:name":"Teled Di Favarin Francesco",
    "wof:placetype":"venue"
},
  "geometry": {"coordinates":[11.8242721558,45.3288803101],"type":"Point"}
}