{
  "type": "Feature",
  "properties": {
    "iso:country":"IT",
    "sg:address":"24060 Brusaporto",
    "sg:city":"Brusaporto",
    "sg:orig_category":"Torrefazione Di Caffe' Ed Affini - Lavorazione E Ingrosso",
    "sg:phone":"+39 035 681893",
    "sg:postcode":"24060",
    "sg:province":"Bergamo",
    "wof:name":"Esserre Distribuzione Srl",
    "wof:placetype":"venue"
},
  "geometry": {"coordinates":[9.744177,45.667446],"type":"Point"}
}