{
  "type": "Feature",
  "properties": {
    "addr:full":"2/a, Via Bredina 26100 Cremona Cremona Cremona 26100",
    "addr:housenumber":"2 / a",
    "addr:postcode":"26100;26100",
    "addr:street":"Via Bredina",
    "iso:country":"IT",
    "sg:address":"2/a, Via Bredina 26100 Cremona",
    "sg:city":"Cremona",
    "sg:classifiers":[
        {
            "category":"Manufacturing",
            "subcategory":"Paper Products",
            "type":"Manufacturing & Wholesale Goods"
        }
    ],
    "sg:phone":"+39 0372 416430",
    "sg:postcode":"26100",
    "sg:province":"Cremona",
    "sg:tags":[
        "cardboard"
    ],
    "wof:name":"Cartotecnica G.bianchini (s.n.c.)",
    "wof:placetype":"venue"
},
  "geometry": {"coordinates":[10.0261354446,45.1334991455],"type":"Point"}
}