{
  "type": "Feature",
  "properties": {
    "addr:full":"00142 Roma Roma Roma 00142",
    "addr:postcode":"00142;00142",
    "iso:country":"IT",
    "sg:address":"00142 Roma",
    "sg:city":"Roma",
    "sg:orig_category":"Carni, Salumi E Pesci",
    "sg:phone":"+39 06 503 3634",
    "sg:postcode":"00142",
    "sg:province":"Roma",
    "wof:name":"Buonocore Gaetano",
    "wof:placetype":"venue"
},
  "geometry": {"coordinates":[12.503664,41.836746],"type":"Point"}
}