{
  "type": "Feature",
  "properties": {
    "addr:full":"Via S. Giuseppe 39 21050 Castelseprio Castelseprio Varese 21050",
    "addr:housenumber":"39",
    "addr:postcode":"21050;21050",
    "addr:street":"Via S. Giuseppe",
    "iso:country":"IT",
    "sg:address":"Via S. Giuseppe 39 21050 Castelseprio",
    "sg:city":"Castelseprio",
    "sg:classifiers":[
        {
            "category":"Retail",
            "subcategory":"Repair Shop",
            "type":"Services"
        }
    ],
    "sg:phone":"+39 0331 820419",
    "sg:postcode":"21050",
    "sg:province":"Varese",
    "sg:tags":[
        "lamp",
        "part"
    ],
    "sg:website":"www.nuovabetaplast.it",
    "wof:name":"Nuova Betaplast Srl",
    "wof:placetype":"venue"
},
  "geometry": {"coordinates":[8.866949,45.751453],"type":"Point"}
}