{
  "type": "Feature",
  "properties": {
    "addr:full":"Str. Per Poirino 41 14019 Villanova D'asti Asti 14019",
    "addr:housenumber":"41",
    "addr:postcode":"14019;14019",
    "addr:street":"Str. Per Poirino",
    "iso:country":"IT",
    "sg:address":"Str. Per Poirino 41 14019 Villanova D'asti",
    "sg:classifiers":[
        {
            "category":"Manufacturing",
            "subcategory":"Rubber & Plastics",
            "type":"Manufacturing & Wholesale Goods"
        }
    ],
    "sg:phone":"+39 0141 949611",
    "sg:postcode":"14019",
    "sg:province":"Asti",
    "sg:tags":[
        "product",
        "part",
        "moulded"
    ],
    "wof:name":"Rft Spa",
    "wof:placetype":"venue"
},
  "geometry": {"coordinates":[8.2068128586,44.9008636475],"type":"Point"}
}