{
  "type": "Feature",
  "properties": {
    "addr:full":"2, Via S. Agostino 51100 Pistoia Pistoia Pistoia 51100",
    "addr:postcode":"51100;51100",
    "addr:street":"Via S. Agostino",
    "iso:country":"IT",
    "sg:address":"2, Via S. Agostino 51100 Pistoia",
    "sg:city":"Pistoia",
    "sg:classifiers":[
        {
            "category":"Bars & Pubs",
            "subcategory":"Nightclub",
            "type":"Food & Drink"
        }
    ],
    "sg:phone":"+39 0573 934754",
    "sg:postcode":"51100",
    "sg:province":"Pistoia",
    "sg:tags":[
        "cake",
        "bread"
    ],
    "wof:name":"Fanti Vincenzo",
    "wof:placetype":"venue"
},
  "geometry": {"coordinates":[10.918524,43.932156],"type":"Point"}
}