{
  "type": "Feature",
  "properties": {
    "addr:full":"39, Via Caravaggio 74023 Grottaglie Grottaglie Taranto 74023",
    "addr:postcode":"74023;74023",
    "addr:street":"Via Caravaggio",
    "iso:country":"IT",
    "sg:address":"39, Via Caravaggio 74023 Grottaglie",
    "sg:city":"Grottaglie",
    "sg:classifiers":[
        {
            "category":"Manufacturing",
            "subcategory":"Glass & Minerals",
            "type":"Manufacturing & Wholesale Goods"
        }
    ],
    "sg:phone":"+39 099 566 1037",
    "sg:postcode":"74023",
    "sg:province":"Taranto",
    "sg:tags":[
        "building",
        "material"
    ],
    "wof:name":"Fasano Nicola S.r.l.",
    "wof:placetype":"venue"
},
  "geometry": {"coordinates":[17.390671,40.452572],"type":"Point"}
}