{
  "type": "Feature",
  "properties": {
    "iso:country":"IT",
    "sg:address":"42013 Casalgrande",
    "sg:orig_category":"Ecologia - Studi Consulenza E Servizi",
    "sg:phone":"+39 0522 996575",
    "sg:postcode":"42013",
    "sg:province":"Reggio Nell'Emilia",
    "wof:name":"Cooperativa Servizi Ecologici Scrl",
    "wof:placetype":"venue"
},
  "geometry": {"coordinates":[10.759011,44.557461],"type":"Point"}
}