{
  "type": "Feature",
  "properties": {
    "addr:full":"9, Via Francesca 24043 Caravaggio Caravaggio Bergamo 24043",
    "addr:postcode":"24043;24043",
    "addr:street":"Via Francesca",
    "iso:country":"IT",
    "sg:address":"9, Via Francesca 24043 Caravaggio",
    "sg:city":"Caravaggio",
    "sg:classifiers":[
        {
            "category":"Utilities",
            "subcategory":"Electric",
            "type":"Services"
        }
    ],
    "sg:phone":"+39 39036343892",
    "sg:postcode":"24043",
    "sg:province":"Bergamo",
    "sg:tags":[
        "component",
        "electronic"
    ],
    "wof:name":"Esa S.r.l.",
    "wof:placetype":"venue"
},
  "geometry": {"coordinates":[9.643003,45.524765],"type":"Point"}
}