{
  "type": "Feature",
  "properties": {
    "addr:full":"17, Strada Marziana 27020 Parona Parona Pavia 27020",
    "addr:postcode":"27020;27020",
    "addr:street":"Strada Marziana",
    "iso:country":"IT",
    "sg:address":"17, Strada Marziana 27020 Parona",
    "sg:city":"Parona",
    "sg:classifiers":[
        {
            "category":"Food & Beverages",
            "subcategory":"Groceries & Convenience Stores",
            "type":"Retail Goods"
        }
    ],
    "sg:phone":"+39 0384 253571",
    "sg:postcode":"27020",
    "sg:province":"Pavia",
    "sg:tags":[
        "product",
        "related"
    ],
    "wof:name":"Pasta Italia S.r.l.",
    "wof:placetype":"venue"
},
  "geometry": {"coordinates":[8.7791528702,45.2783126831],"type":"Point"}
}