{
  "type": "Feature",
  "properties": {
    "addr:full":"04016 Sabaudia Sabaudia Latina 04016",
    "addr:postcode":"04016;04016",
    "iso:country":"IT",
    "sg:address":"04016 Sabaudia",
    "sg:city":"Sabaudia",
    "sg:orig_category":"Trattamenti Termici E Superficiali Metalli, Galvanotecnica",
    "sg:phone":"+39 0773 562014",
    "sg:postcode":"04016",
    "sg:province":"Latina",
    "wof:name":"G.e.l. Srl",
    "wof:placetype":"venue"
},
  "geometry": {"coordinates":[13.036778,41.380951],"type":"Point"}
}