{
  "type": "Feature",
  "properties": {
    "iso:country":"IT",
    "sg:address":"126/a, Via S.donnino Marola 42033 Carpineti",
    "sg:classifiers":[
        {
            "category":"Bars & Pubs",
            "subcategory":"Nightclub",
            "type":"Food & Drink"
        }
    ],
    "sg:phone":"+39 0522 813111",
    "sg:postcode":"42033",
    "sg:province":"Reggio Nell'Emilia",
    "sg:tags":[
        "cake",
        "bread"
    ],
    "wof:name":"Cabrioni Biscotti (s.r.l.)",
    "wof:placetype":"venue"
},
  "geometry": {"coordinates":[10.627794,44.696228],"type":"Point"}
}