{
  "type": "Feature",
  "properties": {
    "iso:country":"IT",
    "sg:address":"20019 Settimo Milanese",
    "sg:city":"Settimo Milanese",
    "sg:orig_category":"Prodotti Chimici Secondari. Servizi E Lavori Per Ecologia E Smaltimento Rifiuti. Macchine E Forniture Per Ecologia E Smaltimento Rifiuti",
    "sg:phone":"+39 02 3351 0355",
    "sg:postcode":"20019",
    "sg:province":"Milano",
    "sg:website":"http://www.aernovasystem.com",
    "wof:name":"Aernova System",
    "wof:placetype":"venue"
},
  "geometry": {"coordinates":[9.0576133728,45.4635887146],"type":"Point"}
}