{
  "type": "Feature",
  "properties": {
    "addr:full":"31046 Oderzo Oderzo Treviso 31046",
    "addr:postcode":"31046;31046",
    "iso:country":"IT",
    "sg:address":"31046 Oderzo",
    "sg:city":"Oderzo",
    "sg:orig_category":"Ricambi E Componenti Dei Mezzi Di Trasporto",
    "sg:phone":"+39 0422 814728",
    "sg:postcode":"31046",
    "sg:province":"Treviso",
    "wof:name":"Midas",
    "wof:placetype":"venue"
},
  "geometry": {"coordinates":[12.467332,45.717815],"type":"Point"}
}