{
  "type": "Feature",
  "properties": {
    "iso:country":"IT",
    "sg:address":"Via L. Nobili 201 41100 Modena",
    "sg:city":"Modena",
    "sg:classifiers":[
        {
            "category":"Manufacturing",
            "subcategory":"Furniture",
            "type":"Manufacturing & Wholesale Goods"
        }
    ],
    "sg:phone":"+39 059 828809",
    "sg:postcode":"41100",
    "sg:province":"Modena",
    "sg:tags":[
        "hinge"
    ],
    "sg:website":"www.tgnhingis.com",
    "wof:name":"Tgn Spa",
    "wof:placetype":"venue"
},
  "geometry": {"coordinates":[10.9014186859,44.6478614807],"type":"Point"}
}