{
  "type": "Feature",
  "properties": {
    "iso:country":"IT",
    "sg:address":"82100 Benevento",
    "sg:city":"Benevento",
    "sg:orig_category":"Elettrotecnica Industriale, Prodotti E Apparecchiature. Elettrotecnica Professionale E Di Consumo",
    "sg:phone":"+39 0824 363695",
    "sg:postcode":"82100",
    "sg:province":"Benevento",
    "wof:name":"Alfieri Giovanni & C. Spa",
    "wof:placetype":"venue"
},
  "geometry": {"coordinates":[14.768123,41.12051],"type":"Point"}
}