{
  "type": "Feature",
  "properties": {
    "iso:country":"IT",
    "sg:address":"18, Via Visconti Giovanni 28100 Novara",
    "sg:city":"Novara",
    "sg:classifiers":[
        {
            "category":"Banks & Credit Unions",
            "subcategory":"Investment Brokerage",
            "type":"Services"
        }
    ],
    "sg:phone":"+39 0321 694197",
    "sg:postcode":"28100",
    "sg:province":"Novara",
    "sg:tags":[
        "-",
        "transport",
        "related"
    ],
    "wof:name":"Magazzini Generali Raccordati Con Silos Da Cereali (s.r.l.)",
    "wof:placetype":"venue"
},
  "geometry": {"coordinates":[8.630704,45.45108],"type":"Point"}
}