{
  "type": "Feature",
  "properties": {
    "iso:country":"IT",
    "sg:address":"33, Via Rondona 44049 Vigarano Mainarda",
    "sg:city":"Vigarano Mainarda",
    "sg:classifiers":[
        {
            "category":"Professional",
            "subcategory":"Engineering",
            "type":"Services"
        }
    ],
    "sg:phone":"+39 0532 715631",
    "sg:postcode":"44049",
    "sg:province":"Ferrara",
    "sg:tags":[
        "machine",
        "-",
        "mechanical"
    ],
    "wof:name":"Bonfiglioli Engineering (s.r.l.)",
    "wof:placetype":"venue"
},
  "geometry": {"coordinates":[11.501857,44.856556],"type":"Point"}
}