{
  "type": "Feature",
  "properties": {
    "addr:full":"66054 Vasto Vasto Chieti 66054",
    "addr:postcode":"66054;66054",
    "iso:country":"IT",
    "sg:address":"66054 Vasto",
    "sg:city":"Vasto",
    "sg:orig_category":"Abbigliamento Alta Moda E Stilisti - Boutiques",
    "sg:phone":"+39 0873 366921",
    "sg:postcode":"66054",
    "sg:province":"Chieti",
    "wof:name":"Priori Rosanna",
    "wof:placetype":"venue"
},
  "geometry": {"coordinates":[14.135697,42.330662],"type":"Point"}
}