{
  "type": "Feature",
  "properties": {
    "addr:full":"18033 Camporosso Camporosso Imperia 18033",
    "addr:postcode":"18033;18033",
    "iso:country":"IT",
    "sg:address":"18033 Camporosso",
    "sg:city":"Camporosso",
    "sg:orig_category":"Motori Ed Organi Di Trasmissione. Ricambi E Componenti Dei Mezzi Di Trasporto",
    "sg:phone":"+39 0184 250792",
    "sg:postcode":"18033",
    "sg:province":"Imperia",
    "wof:name":"Autofficina Vm Di Verducci Marco",
    "wof:placetype":"venue"
},
  "geometry": {"coordinates":[7.6222662926,43.813419342],"type":"Point"}
}