{
  "type": "Feature",
  "properties": {
    "addr:full":"13853 Lessona Lessona Biella 13853",
    "addr:postcode":"13853;13853",
    "iso:country":"IT",
    "sg:address":"13853 Lessona",
    "sg:city":"Lessona",
    "sg:orig_category":"Servizi E Lavori Per Abbigliamento E Pelletterie",
    "sg:phone":"+39 015 981304",
    "sg:postcode":"13853",
    "sg:province":"Biella",
    "wof:name":"Rammendatura Castelletta Doriana",
    "wof:placetype":"venue"
},
  "geometry": {"coordinates":[8.196429,45.586376],"type":"Point"}
}