{
  "type": "Feature",
  "properties": {
    "iso:country":"IT",
    "sg:address":"51/a, Via Emilia 40011 Anzola Dell'emilia",
    "sg:classifiers":[
        {
            "category":"Professional",
            "subcategory":"Engineering",
            "type":"Services"
        }
    ],
    "sg:phone":"+39 39051733026",
    "sg:postcode":"40011",
    "sg:province":"Bologna",
    "sg:tags":[
        "machine",
        "-",
        "mechanical"
    ],
    "wof:name":"Nuova Autosana (s.r.l.)",
    "wof:placetype":"venue"
},
  "geometry": {"coordinates":[11.206612,44.541874],"type":"Point"}
}