{
  "type": "Feature",
  "properties": {
    "iso:country":"IT",
    "sg:address":"83100 Avellino",
    "sg:city":"Avellino",
    "sg:orig_category":"Trattamenti Termici E Superficiali Metalli, Galvanotecnica",
    "sg:phone":"+39 0825 781980",
    "sg:postcode":"83100",
    "sg:province":"Avellino",
    "wof:name":"I.a. S.r.l.",
    "wof:placetype":"venue"
},
  "geometry": {"coordinates":[14.733524,40.862564],"type":"Point"}
}