{
  "type": "Feature",
  "properties": {
    "iso:country":"IT",
    "sg:address":"Piazza Fratelli Rosselli 8; Grosseto; 58100",
    "sg:city":"Grosseto",
    "sg:classifiers":[
        {
            "category":"Banks & Credit Unions",
            "subcategory":"Bank",
            "type":"Services"
        }
    ],
    "sg:phone":"+39 0564 21219",
    "sg:postcode":"58100",
    "sg:province":"Grosseto",
    "wof:name":"Cassa Di Risparmio Di Firenze Spa",
    "wof:placetype":"venue"
},
  "geometry": {"coordinates":[11.112196,42.763371],"type":"Point"}
}