{
  "type": "Feature",
  "properties": {
    "iso:country":"IT",
    "sg:address":"20033 Desio",
    "sg:city":"Desio",
    "sg:orig_category":"Servizi E Lavori Per Arredamento E Industria Del Legno",
    "sg:phone":"+39 036 262 6014",
    "sg:postcode":"20033",
    "sg:province":"Milano",
    "wof:name":"Mogicato Sergio",
    "wof:placetype":"venue"
},
  "geometry": {"coordinates":[9.213264,45.617748],"type":"Point"}
}