{
  "type": "Feature",
  "properties": {
    "iso:country":"IT",
    "sg:address":"70123 Bari",
    "sg:city":"Bari",
    "sg:orig_category":"Macchine Utensili E Impianti",
    "sg:phone":"+39 080 574 4267",
    "sg:postcode":"70123",
    "sg:province":"Bari",
    "wof:name":"Cornici & Cornici Di Violanti Livio",
    "wof:placetype":"venue"
},
  "geometry": {"coordinates":[16.869291,41.126053],"type":"Point"}
}