{
  "type": "Feature",
  "properties": {
    "addr:full":"54033 Carrara Avenza Massa-Carrara 54033",
    "addr:postcode":"54033;54033",
    "addr:street":"Avenza",
    "iso:country":"IT",
    "sg:address":"54033 Carrara",
    "sg:city":"Avenza",
    "sg:orig_category":"Elettrotecnica Industriale, Prodotti E Apparecchiature",
    "sg:phone":"+39 0585 844306",
    "sg:postcode":"54033",
    "sg:province":"Massa-Carrara",
    "wof:name":"Societa' Elettrotecnica Italiana Srl",
    "wof:placetype":"venue"
},
  "geometry": {"coordinates":[10.062383,44.046635],"type":"Point"}
}