{
  "type": "Feature",
  "properties": {
    "iso:country":"IT",
    "sg:address":"10123 Torino",
    "sg:city":"Torino",
    "sg:orig_category":"Decoratori",
    "sg:phone":"+39 011 837023",
    "sg:postcode":"10123",
    "sg:province":"Torino",
    "sg:website":"http://www.giovinetto.it",
    "wof:name":"Giovinetto - Decorazione Edilizia Restauro",
    "wof:placetype":"venue"
},
  "geometry": {"coordinates":[7.686757,45.063103],"type":"Point"}
}