{
  "type": "Feature",
  "properties": {
    "iso:country":"IT",
    "sg:address":"Via Del Turchino 43 15067 Novi Ligure",
    "sg:city":"Novi Ligure",
    "sg:classifiers":[
        {
            "category":"Professional",
            "subcategory":"Business Services",
            "type":"Services"
        }
    ],
    "sg:phone":"+39 0143 321330",
    "sg:postcode":"15067",
    "sg:province":"Alessandria",
    "sg:tags":[
        "agency",
        "export"
    ],
    "wof:name":"O.t.t. Oceanic Transport Trailers S.p.a.",
    "wof:placetype":"venue"
},
  "geometry": {"coordinates":[8.765553,44.76725],"type":"Point"}
}