{
  "type": "Feature",
  "properties": {
    "iso:country":"IT",
    "sg:address":"2, Via Canova 20090 Trezzano Sul Naviglio",
    "sg:city":"Trezzano sul Naviglio",
    "sg:classifiers":[
        {
            "category":"Communications",
            "subcategory":"Television Station",
            "type":"Services"
        }
    ],
    "sg:phone":"+39 39024452867",
    "sg:postcode":"20090",
    "sg:province":"Milano",
    "sg:tags":[
        "audio-visual"
    ],
    "wof:name":"Scofima System (s.r.l.)",
    "wof:placetype":"venue"
},
  "geometry": {"coordinates":[9.054003,45.41703],"type":"Point"}
}