{
  "type": "Feature",
  "properties": {
    "iso:country":"IT",
    "sg:address":"5, Via Grotte Portella 00044 Frascati",
    "sg:city":"Frascati",
    "sg:classifiers":[
        {
            "category":"Banks & Credit Unions",
            "subcategory":"Investment Brokerage",
            "type":"Services"
        }
    ],
    "sg:phone":"+39 39069409528",
    "sg:postcode":"00044",
    "sg:province":"Roma",
    "sg:tags":[
        "-",
        "transport",
        "related"
    ],
    "wof:name":"Mag. - Di (s.r.l.)",
    "wof:placetype":"venue"
},
  "geometry": {"coordinates":[12.655558,41.839821],"type":"Point"}
}