{
  "type": "Feature",
  "properties": {
    "addr:full":"4, Via Calvi 27028 San Martino Siccomario San Martino Siccomario Pavia 27028",
    "addr:postcode":"27028;27028",
    "addr:street":"Via Calvi",
    "iso:country":"IT",
    "sg:address":"4, Via Calvi 27028 San Martino Siccomario",
    "sg:city":"San Martino Siccomario",
    "sg:classifiers":[
        {
            "category":"Professional",
            "subcategory":"Engineering",
            "type":"Services"
        }
    ],
    "sg:phone":"+39 0382 554080",
    "sg:postcode":"27028",
    "sg:province":"Pavia",
    "sg:tags":[
        "machine",
        "-",
        "mechanical"
    ],
    "wof:name":"Baldi (s.r.l.)",
    "wof:placetype":"venue"
},
  "geometry": {"coordinates":[9.119246,45.143192],"type":"Point"}
}