{
  "type": "Feature",
  "properties": {
    "iso:country":"IT",
    "sg:address":"20149 Milano",
    "sg:city":"Milano",
    "sg:orig_category":"Servizi Editoriali",
    "sg:phone":"+39 02 498 9092",
    "sg:postcode":"20149",
    "sg:province":"Milano",
    "wof:name":"Giussani Luciano",
    "wof:placetype":"venue"
},
  "geometry": {"coordinates":[9.151528,45.47324],"type":"Point"}
}