{
  "type": "Feature",
  "properties": {
    "iso:country":"IT",
    "sg:address":"86100 Campobasso",
    "sg:city":"Campobasso",
    "sg:orig_category":"Lavorazioni Metalli, Stampaggio E Saldatura",
    "sg:phone":"+39 0874 67779",
    "sg:postcode":"86100",
    "sg:province":"Campobasso",
    "wof:name":"Perrella Aldo",
    "wof:placetype":"venue"
},
  "geometry": {"coordinates":[14.661386,41.561981],"type":"Point"}
}