{
  "type": "Feature",
  "properties": {
    "iso:country":"IT",
    "sg:address":"00040 Pomezia",
    "sg:city":"Pomezia",
    "sg:orig_category":"Prodotti Alimentari",
    "sg:phone":"+39 06 915 7829",
    "sg:postcode":"00040",
    "sg:province":"Roma",
    "wof:name":"Artic Ice Food Di Russo Ernestina",
    "wof:placetype":"venue"
},
  "geometry": {"coordinates":[12.4584827423,41.625793457],"type":"Point"}
}