{
  "type": "Feature",
  "properties": {
    "iso:country":"IT",
    "sg:address":"10, Via Col Di Lana 21040 Jerago Con Orago",
    "sg:city":"Jerago con Orago",
    "sg:classifiers":[
        {
            "category":"Professional",
            "subcategory":"Engineering",
            "type":"Services"
        }
    ],
    "sg:phone":"+39 0331 217263",
    "sg:postcode":"21040",
    "sg:province":"Varese",
    "sg:tags":[
        "machine",
        "-",
        "mechanical"
    ],
    "wof:name":"Officina Meccanica Vergani (s.r.l.)",
    "wof:placetype":"venue"
},
  "geometry": {"coordinates":[8.800327,45.701332],"type":"Point"}
}