{
  "type": "Feature",
  "properties": {
    "iso:country":"IT",
    "sg:address":"18, Via Sesia 20089 Rozzano",
    "sg:city":"Rozzano",
    "sg:orig_category":"Miscellaneous Products",
    "sg:phone":"+39 02 5751 1939",
    "sg:postcode":"20089",
    "sg:province":"Milano",
    "wof:name":"Golden Pack S.r.l.",
    "wof:placetype":"venue"
},
  "geometry": {"coordinates":[9.1656951904,45.39818573],"type":"Point"}
}