{
  "type": "Feature",
  "properties": {
    "addr:full":"80053 Castellammare Di Stabia Castellammare di Stabia Napoli 80053",
    "addr:postcode":"80053;80053",
    "iso:country":"IT",
    "sg:address":"80053 Castellammare Di Stabia",
    "sg:city":"Castellammare di Stabia",
    "sg:classifiers":[
        {
            "category":"Health Services",
            "subcategory":"Health Practitioner",
            "type":"Services"
        }
    ],
    "sg:phone":"+39 081 871 1848",
    "sg:postcode":"80053",
    "sg:province":"Napoli",
    "sg:tags":[
        "medici"
    ],
    "wof:name":"Pellegrino Catello",
    "wof:placetype":"venue"
},
  "geometry": {"coordinates":[14.4828128815,40.7046813965],"type":"Point"}
}