{
  "type": "Feature",
  "properties": {
    "iso:country":"IT",
    "sg:address":"12051 Alba",
    "sg:city":"Alba",
    "sg:orig_category":"Servizi E Lavori Industria Chimica. Trattamenti Termici E Superficiali Metalli, Galvanotecnica",
    "sg:phone":"+39 0173 440606",
    "sg:postcode":"12051",
    "sg:province":"Cuneo",
    "wof:name":"Porello Srl",
    "wof:placetype":"venue"
},
  "geometry": {"coordinates":[8.021495,44.712955],"type":"Point"}
}