{
  "type": "Feature",
  "properties": {
    "iso:country":"IT",
    "sg:address":"Via Gaeta 33; Ceccano; 03023",
    "sg:city":"Ceccano",
    "sg:classifiers":[
        {
            "category":"Banks & Credit Unions",
            "subcategory":"Bank",
            "type":"Services"
        }
    ],
    "sg:phone":"+39 0775 625372",
    "sg:postcode":"03023",
    "sg:province":"Frosinone",
    "wof:name":"Istituto Bancario, San Paolo Di Torino Spa",
    "wof:placetype":"venue"
},
  "geometry": {"coordinates":[13.336561,41.567612],"type":"Point"}
}