{
  "type": "Feature",
  "properties": {
    "addr:full":"San Marco 4216; Venezia; 30124 San Marco Venezia 30124",
    "addr:housenumber":"4216",
    "addr:postcode":"30124;30124",
    "addr:street":"San Marco;Marco",
    "iso:country":"IT",
    "sg:address":"San Marco 4216; Venezia; 30124",
    "sg:city":"San Marco",
    "sg:classifiers":[
        {
            "category":"Banks & Credit Unions",
            "subcategory":"Bank",
            "type":"Services"
        }
    ],
    "sg:phone":"+39 041 529 2270",
    "sg:postcode":"30124",
    "sg:province":"Venezia",
    "wof:name":"Cassa Di Risparmio Di Venezia",
    "wof:placetype":"venue"
},
  "geometry": {"coordinates":[12.334041,45.435383],"type":"Point"}
}