{
  "type": "Feature",
  "properties": {
    "iso:country":"IT",
    "sg:address":"60022 Castelfidardo",
    "sg:city":"Castelfidardo",
    "sg:orig_category":"Acciai Speciali - Commercio",
    "sg:phone":"+39 071 782 1107",
    "sg:postcode":"60022",
    "sg:province":"Ancona",
    "wof:name":"Balestra Udilio & Figli Snc",
    "wof:placetype":"venue"
},
  "geometry": {"coordinates":[13.55489,43.527996],"type":"Point"}
}