{
  "type": "Feature",
  "properties": {
    "iso:country":"IT",
    "sg:address":"65121 Pescara",
    "sg:city":"Pescara",
    "sg:orig_category":"Elettrodomestici - Vendita Al Dettaglio",
    "sg:phone":"+39 085 27451",
    "sg:postcode":"65121",
    "sg:province":"Pescara",
    "wof:name":"Centro Singer Di Barbara Corrente",
    "wof:placetype":"venue"
},
  "geometry": {"coordinates":[14.214333,42.468498],"type":"Point"}
}