{
  "type": "Feature",
  "properties": {
    "iso:country":"IT",
    "sg:address":"20122 Milano",
    "sg:city":"Milano",
    "sg:orig_category":"Professionisti - Studi E Servizi Ed Associazioni Di Interesse Aziendale. Associazioni Ed Organismi Di Interesse Pubblico",
    "sg:phone":"+39 02 5518 0397",
    "sg:postcode":"20122",
    "sg:province":"Milano",
    "wof:name":"Agenzia Trotta (s.r.l.)",
    "wof:placetype":"venue"
},
  "geometry": {"coordinates":[9.2025136948,45.4606361389],"type":"Point"}
}