{
  "type": "Feature",
  "properties": {
    "iso:country":"IT",
    "sg:address":"Piazza Visconti 10; Cassago Brianza; 22965",
    "sg:classifiers":[
        {
            "category":"Banks & Credit Unions",
            "subcategory":"Bank",
            "type":"Services"
        }
    ],
    "sg:phone":"+39 039 956324",
    "wof:name":"Banca Popolare Di Lecco",
    "wof:placetype":"venue"
},
  "geometry": {"coordinates":[9.296523,45.738754],"type":"Point"}
}