{
  "type": "Feature",
  "properties": {
    "iso:country":"IT",
    "sg:address":"147, Via Fratelli Scardovi 48014 Castel Bolognese",
    "sg:city":"Castel Bolognese",
    "sg:classifiers":[
        {
            "category":"Professional",
            "subcategory":"Engineering",
            "type":"Services"
        }
    ],
    "sg:phone":"+39 0546 656365",
    "sg:postcode":"48014",
    "sg:province":"Ravenna",
    "sg:tags":[
        "machine",
        "-",
        "mechanical"
    ],
    "wof:name":"C.n.s. S.r.l.",
    "wof:placetype":"venue"
},
  "geometry": {"coordinates":[11.787489,44.326904],"type":"Point"}
}