{
  "type": "Feature",
  "properties": {
    "addr:full":"00060 Capena Capena Roma 00060",
    "addr:postcode":"00060;roma 00060",
    "iso:country":"IT",
    "sg:address":"00060 Capena",
    "sg:city":"Capena",
    "sg:orig_category":"Servizi Culturali E Per Lo Spettacolo. Servizi Al Turismo. Acqua, Luce, Gas E Societa' Di Esercizio Pubblico",
    "sg:phone":"+39 06 908 5173",
    "sg:postcode":"00060",
    "sg:province":"Roma",
    "wof:name":"Museo Archeologico Lucus Feroniae",
    "wof:placetype":"venue"
},
  "geometry": {"coordinates":[12.588945,42.117622],"type":"Point"}
}