{
  "type": "Feature",
  "properties": {
    "iso:country":"IT",
    "sg:address":"25, Via Rosselli Fratelli 20098 San Giuliano Milanese",
    "sg:city":"San Giuliano Milanese",
    "sg:classifiers":[
        {
            "category":"Parking",
            "subcategory":"Lot",
            "type":"Transportation"
        }
    ],
    "sg:phone":"+39 39029846812",
    "sg:postcode":"20098",
    "sg:province":"Milano",
    "sg:tags":[
        "transport",
        "road"
    ],
    "wof:name":"Maedy (s.r.l.)",
    "wof:placetype":"venue"
},
  "geometry": {"coordinates":[9.181276,45.372059],"type":"Point"}
}