{
  "type": "Feature",
  "properties": {
    "iso:country":"IT",
    "sg:address":"10123 Torino",
    "sg:city":"Torino",
    "sg:orig_category":"Servizi Culturali E Per Lo Spettacolo. Arte Ed Artigianato Artistico. Servizi Al Turismo",
    "sg:phone":"+39 011 812 7431",
    "sg:postcode":"10123",
    "sg:province":"Torino",
    "wof:name":"Palbert Snc",
    "wof:placetype":"venue"
},
  "geometry": {"coordinates":[7.686757,45.063103],"type":"Point"}
}