{
  "type": "Feature",
  "properties": {
    "addr:full":"20156 Milano Milano Milano 20156",
    "addr:postcode":"20156;20156",
    "iso:country":"IT",
    "sg:address":"20156 Milano",
    "sg:city":"Milano",
    "sg:orig_category":"Servizi E Lavori Per Ecologia E Smaltimento Rifiuti. Termotecnica E Riscaldamento, Apparecchiature E Servizi. Servizi Ausiliari Di Sorveglianza, Manutenzione E Pulizia",
    "sg:phone":"+39 02 930 8737",
    "sg:postcode":"20156",
    "sg:province":"Milano",
    "wof:name":"Videofumi Di Fratus Francesco",
    "wof:placetype":"venue"
},
  "geometry": {"coordinates":[9.134976,45.502777],"type":"Point"}
}