{
  "type": "Feature",
  "properties": {
    "iso:country":"IT",
    "sg:address":"72, Via Degli Artigiani 16162 Genova",
    "sg:city":"Genova",
    "sg:classifiers":[
        {
            "category":"Utilities",
            "subcategory":"Telephone",
            "type":"Services"
        }
    ],
    "sg:phone":"+39 39010710724",
    "sg:postcode":"16162",
    "sg:province":"Genova",
    "sg:tags":[
        "telecommunication"
    ],
    "wof:name":"Aurora Neon",
    "wof:placetype":"venue"
},
  "geometry": {"coordinates":[8.895978,44.46991],"type":"Point"}
}