{
  "type": "Feature",
  "properties": {
    "iso:country":"IT",
    "sg:address":"5/f, Via Raffaello 42100 Reggio Emilia",
    "sg:classifiers":[
        {
            "category":"Manufacturing",
            "subcategory":"Metals",
            "type":"Manufacturing & Wholesale Goods"
        }
    ],
    "sg:phone":"+39 0522 920836",
    "sg:postcode":"42100",
    "sg:province":"Reggio Nell'Emilia",
    "sg:tags":[
        "processing"
    ],
    "wof:name":"Lovagap (s.n.c.)",
    "wof:placetype":"venue"
},
  "geometry": {"coordinates":[10.6502847672,44.7318000793],"type":"Point"}
}