{
  "type": "Feature",
  "properties": {
    "addr:full":"25020 Flero Flero Brescia 25020",
    "addr:postcode":"25020;25020",
    "iso:country":"IT",
    "sg:address":"25020 Flero",
    "sg:city":"Flero",
    "sg:classifiers":[
        {
            "category":"Manufacturing",
            "subcategory":"Tools & Machinery",
            "type":"Manufacturing & Wholesale Goods"
        }
    ],
    "sg:phone":"+39 030 264 0549",
    "sg:postcode":"25020",
    "sg:province":"Brescia",
    "sg:tags":[
        "machine",
        "system"
    ],
    "wof:name":"C.i.v. Di Geom. Violini",
    "wof:placetype":"venue"
},
  "geometry": {"coordinates":[10.178888,45.470413],"type":"Point"}
}