{
  "type": "Feature",
  "properties": {
    "iso:country":"IT",
    "sg:address":"00040 Pomezia",
    "sg:city":"Pomezia",
    "sg:orig_category":"Elettrotecnica Industriale, Prodotti E Apparecchiature",
    "sg:phone":"+39 06 9148 6244",
    "sg:postcode":"00040",
    "sg:province":"Roma",
    "wof:name":"Securtec Srl",
    "wof:placetype":"venue"
},
  "geometry": {"coordinates":[12.507566,41.670013],"type":"Point"}
}