{
  "type": "Feature",
  "properties": {
    "iso:country":"IT",
    "sg:address":"42100 Reggio Emilia",
    "sg:orig_category":"Motori Ed Organi Di Trasmissione",
    "sg:phone":"+39 0522 517237",
    "sg:postcode":"42100",
    "sg:province":"Reggio Nell'Emilia",
    "wof:name":"Saci Srl Di Manicardi G. & C.",
    "wof:placetype":"venue"
},
  "geometry": {"coordinates":[10.6478738785,44.7390022278],"type":"Point"}
}