{
  "type": "Feature",
  "properties": {
    "iso:country":"IT",
    "sg:address":"8, Via Del Lavoro 01100 Viterbo",
    "sg:city":"Viterbo",
    "sg:classifiers":[
        {
            "category":"Food & Beverages",
            "subcategory":"Groceries & Convenience Stores",
            "type":"Retail Goods"
        }
    ],
    "sg:phone":"+39 0761 252014",
    "sg:postcode":"01100",
    "sg:province":"Viterbo",
    "sg:tags":[
        "product",
        "related"
    ],
    "wof:name":"Dimar S.p.a.",
    "wof:placetype":"venue"
},
  "geometry": {"coordinates":[12.0881567001,42.4464950562],"type":"Point"}
}