{
  "type": "Feature",
  "properties": {
    "iso:country":"IT",
    "sg:address":"29010 Pontenure",
    "sg:city":"Pontenure",
    "sg:orig_category":"Apparecchiature E Sistemi Per Magazzinaggio E Movimentazione",
    "sg:postcode":"29010",
    "sg:province":"Piacenza",
    "wof:name":"Corradini (s.p.a)",
    "wof:placetype":"venue"
},
  "geometry": {"coordinates":[9.784614,45.001663],"type":"Point"}
}