{
  "type": "Feature",
  "properties": {
    "iso:country":"IT",
    "sg:address":"46046 Medole",
    "sg:city":"Medole",
    "sg:orig_category":"Arredamento Negozi E Supermercati",
    "sg:phone":"+39 0376 898186",
    "sg:postcode":"46046",
    "sg:province":"Mantova",
    "wof:name":"Linea Casa Snc",
    "wof:placetype":"venue"
},
  "geometry": {"coordinates":[10.534674,45.33017],"type":"Point"}
}