{
  "type": "Feature",
  "properties": {
    "iso:country":"IT",
    "sg:address":"21048 Solbiate Arno",
    "sg:city":"Solbiate Arno",
    "sg:orig_category":"Trasporti E Spedizioni Merci",
    "sg:phone":"+39 0331 994959",
    "sg:postcode":"21048",
    "sg:province":"Varese",
    "wof:name":"Furlan Trasporti (s.n.c.)",
    "wof:placetype":"venue"
},
  "geometry": {"coordinates":[8.810313,45.714069],"type":"Point"}
}