{
  "type": "Feature",
  "properties": {
    "addr:full":"58100 Grosseto Grosseto Grosseto 58100",
    "addr:postcode":"58100;58100",
    "iso:country":"IT",
    "sg:address":"58100 Grosseto",
    "sg:city":"Grosseto",
    "sg:classifiers":[
        {
            "category":"Health Services",
            "subcategory":"Health Practitioner",
            "type":"Services"
        }
    ],
    "sg:phone":"+39 0564 411155",
    "sg:postcode":"58100",
    "sg:province":"Grosseto",
    "sg:tags":[
        "medici"
    ],
    "wof:name":"Rossi Mauro",
    "wof:placetype":"venue"
},
  "geometry": {"coordinates":[11.1170282364,42.7650337219],"type":"Point"}
}