{
  "type": "Feature",
  "properties": {
    "iso:country":"IT",
    "sg:address":"20133 Milano",
    "sg:city":"Milano",
    "sg:orig_category":"Informatica - Consulenza E Servizi. Editoria",
    "sg:phone":"+39 02 7060 2554",
    "sg:postcode":"20133",
    "sg:province":"Milano",
    "sg:website":"http://www.cetel.it",
    "wof:name":"Cetel 90",
    "wof:placetype":"venue"
},
  "geometry": {"coordinates":[9.232347,45.473743],"type":"Point"}
}