{
  "type": "Feature",
  "properties": {
    "iso:country":"IT",
    "sg:address":"42017 Novellara",
    "sg:orig_category":"Arredamenti E Mobili Professionali. Impianti, Attrezzature E Forniture Sanitarie Ed Ospedaliere",
    "sg:phone":"+39 0522 651224",
    "sg:postcode":"42017",
    "sg:province":"Reggio Nell'Emilia",
    "wof:name":"Pac Hospital S.r.l.",
    "wof:placetype":"venue"
},
  "geometry": {"coordinates":[10.560014,44.624546],"type":"Point"}
}