{
  "type": "Feature",
  "properties": {
    "iso:country":"IT",
    "sg:address":"12, Frazione Buasca 10080 San Colombano Belmonte",
    "sg:city":"San Colombano Belmonte",
    "sg:classifiers":[
        {
            "category":"Professional",
            "subcategory":"Engineering",
            "type":"Services"
        }
    ],
    "sg:phone":"+39 39012468171",
    "sg:postcode":"10080",
    "sg:province":"Torino",
    "sg:tags":[
        "machine",
        "-",
        "mechanical"
    ],
    "wof:name":"C.m.s.",
    "wof:placetype":"venue"
},
  "geometry": {"coordinates":[7.629187,45.380932],"type":"Point"}
}