{
  "type": "Feature",
  "properties": {
    "addr:full":"97016 Pozzallo Pozzallo Ragusa 97016",
    "addr:postcode":"97016;97016",
    "iso:country":"IT",
    "sg:address":"97016 Pozzallo",
    "sg:city":"Pozzallo",
    "sg:orig_category":"Trasporto Pubblico E Privato",
    "sg:phone":"+39 0932 955467",
    "sg:postcode":"97016",
    "sg:province":"Ragusa",
    "wof:name":"Blanco Giuseppe",
    "wof:placetype":"venue"
},
  "geometry": {"coordinates":[14.862974,36.736912],"type":"Point"}
}