{
  "type": "Feature",
  "properties": {
    "iso:country":"IT",
    "sg:address":"Km. 76.760, Strada Statale 98 70032 Bitonto",
    "sg:city":"Bitonto",
    "sg:classifiers":[
        {
            "category":"Shopping",
            "subcategory":"Clothing, Apparel, & Fashions",
            "type":"Retail Goods"
        }
    ],
    "sg:phone":"+39 080 373 5641",
    "sg:postcode":"70032",
    "sg:province":"Bari",
    "sg:tags":[
        "clothes"
    ],
    "wof:name":"Anmar (s.r.l.)",
    "wof:placetype":"venue"
},
  "geometry": {"coordinates":[16.869291,41.126053],"type":"Point"}
}