{
  "type": "Feature",
  "properties": {
    "addr:full":"Via Che Guevara 25 42045 Luzzara Reggio Nell'Emilia 42045",
    "addr:housenumber":"25",
    "addr:postcode":"42045;42045",
    "addr:street":"Via Che Guevara",
    "iso:country":"IT",
    "sg:address":"Via Che Guevara 25 42045 Luzzara",
    "sg:classifiers":[
        {
            "category":"Home & Garden",
            "subcategory":"Building Materials",
            "type":"Retail Goods"
        }
    ],
    "sg:phone":"+39 0522 977471",
    "sg:postcode":"42045",
    "sg:province":"Reggio Nell'Emilia",
    "sg:tags":[
        "packaging",
        "pvc",
        "chloride",
        "plasticized",
        "polyvinyl"
    ],
    "sg:website":"www.flexibord.it",
    "wof:name":"Flexi Bord S.r.l.",
    "wof:placetype":"venue"
},
  "geometry": {"coordinates":[10.7079362869,44.9444541931],"type":"Point"}
}