{
  "type": "Feature",
  "properties": {
    "addr:full":"37023 Grezzana Grezzana Verona 37023",
    "addr:postcode":"37023;37023",
    "iso:country":"IT",
    "sg:address":"37023 Grezzana",
    "sg:city":"Grezzana",
    "sg:orig_category":"Macchine Ed Impianti Per Edilizia E Lavori Pubblici",
    "sg:phone":"+39 045 908496",
    "sg:postcode":"37023",
    "sg:province":"Verona",
    "wof:name":"Laiti & Petronilli Snc",
    "wof:placetype":"venue"
},
  "geometry": {"coordinates":[10.979713,45.40414],"type":"Point"}
}