{
  "type": "Feature",
  "properties": {
    "iso:country":"IT",
    "sg:address":"20064 Gorgonzola",
    "sg:city":"Gorgonzola",
    "sg:orig_category":"Motori Ed Organi Di Trasmissione",
    "sg:phone":"+39 02 951 3034",
    "sg:postcode":"20064",
    "sg:province":"Milano",
    "wof:name":"Belotti Dante E C.s.n.c.",
    "wof:placetype":"venue"
},
  "geometry": {"coordinates":[9.4120054245,45.5284919739],"type":"Point"}
}