{
  "type": "Feature",
  "properties": {
    "iso:country":"IT",
    "sg:address":"Via S. Lipari 5 91025 Marsala",
    "sg:city":"Marsala",
    "sg:classifiers":[
        {
            "category":"Food & Beverages",
            "subcategory":"Liquor & Beverages",
            "type":"Retail Goods"
        }
    ],
    "sg:phone":"+39 0923 999053",
    "sg:postcode":"91025",
    "sg:province":"Trapani",
    "sg:tags":[
        "wine",
        "italian"
    ],
    "sg:website":"www.cantinefici.com",
    "wof:name":"Fici Fratelli Snc",
    "wof:placetype":"venue"
},
  "geometry": {"coordinates":[12.514634,38.018589],"type":"Point"}
}