{
  "type": "Feature",
  "properties": {
    "iso:country":"IT",
    "sg:address":"Viale Marconi; Potenza; 85100",
    "sg:city":"Potenza",
    "sg:classifiers":[
        {
            "category":"Banks & Credit Unions",
            "subcategory":"Bank",
            "type":"Services"
        }
    ],
    "sg:phone":"+39 0971 601111",
    "sg:postcode":"85100",
    "sg:province":"Potenza",
    "wof:name":"Banca Di Lucania",
    "wof:placetype":"venue"
},
  "geometry": {"coordinates":[15.804572,40.632462],"type":"Point"}
}