{
  "type": "Feature",
  "properties": {
    "iso:country":"IT",
    "sg:address":"Via Garibaldi 185 95011 Calatabiano",
    "sg:city":"Calatabiano",
    "sg:classifiers":[
        {
            "category":"Food & Beverages",
            "subcategory":"Fruits & Vegetables",
            "type":"Retail Goods"
        }
    ],
    "sg:phone":"+39 095 645616",
    "sg:postcode":"95011",
    "sg:province":"Catania",
    "sg:tags":[
        "juice",
        "nectar"
    ],
    "wof:name":"F.lli Di Bartolo S.r.l.",
    "wof:placetype":"venue"
},
  "geometry": {"coordinates":[15.2329101562,37.8217506409],"type":"Point"}
}