{
  "type": "Feature",
  "properties": {
    "addr:full":"20020 Lainate Lainate Milano 20020",
    "addr:postcode":"20020;20020",
    "iso:country":"IT",
    "sg:address":"20020 Lainate",
    "sg:city":"Lainate",
    "sg:orig_category":"Elettrotecnica Industriale, Prodotti E Apparecchiature. Elettronica Industriale, Prodotti E Apparecchiature. Macchine, Strumenti Ed Apparecchi Per Attivita' Industriali",
    "sg:phone":"+39 02 9357 0720",
    "sg:postcode":"20020",
    "sg:province":"Milano",
    "wof:name":"R.p.o. Electronic Di Orizio G. & Figli S.n.c.",
    "wof:placetype":"venue"
},
  "geometry": {"coordinates":[9.028877,45.570511],"type":"Point"}
}