{
  "type": "Feature",
  "properties": {
    "iso:country":"IT",
    "sg:address":"11020 Torgnon",
    "sg:city":"Mongnod",
    "sg:orig_category":"Servizi E Lavori Per Edilizia E Lavori Pubblici. Servizi Al Turismo",
    "sg:phone":"+39 0166 540452",
    "sg:postcode":"11020",
    "sg:province":"Aosta",
    "sg:website":"http://www.immobperrin.com",
    "wof:name":"Immobiliare Perrin Di Perrin Ivo & C. Snc",
    "wof:placetype":"venue"
},
  "geometry": {"coordinates":[7.56723,45.802124],"type":"Point"}
}