{
  "type": "Feature",
  "properties": {
    "addr:full":"Via Ai Monti 3 21019 Somma Lombardo Somma Lombardo Varese 21019",
    "addr:housenumber":"3",
    "addr:postcode":"21019;21019",
    "addr:street":"Via Ai Monti",
    "iso:country":"IT",
    "sg:address":"Via Ai Monti 3 21019 Somma Lombardo",
    "sg:city":"Somma Lombardo",
    "sg:classifiers":[
        {
            "category":"Banks & Credit Unions",
            "subcategory":"Investment Brokerage",
            "type":"Services"
        }
    ],
    "sg:phone":"+39 0331 254181",
    "sg:postcode":"21019",
    "sg:province":"Varese",
    "sg:tags":[
        "embroidery",
        "hand"
    ],
    "sg:website":"www.ricamificio-gimar.it",
    "wof:name":"Ricamificio Gimar Di Gianello Mario E C Srl",
    "wof:placetype":"venue"
},
  "geometry": {"coordinates":[8.706433,45.69754],"type":"Point"}
}