{
  "type": "Feature",
  "properties": {
    "addr:full":"22035 Canzo Canzo Como 22035",
    "addr:postcode":"22035;22035",
    "iso:country":"IT",
    "sg:address":"22035 Canzo",
    "sg:city":"Canzo",
    "sg:orig_category":"Cerniere E Cardini",
    "sg:phone":"+39 031 681283",
    "sg:postcode":"22035",
    "sg:province":"Como",
    "sg:website":"http://www.delcorno.com",
    "wof:name":"Del Corno Srl",
    "wof:placetype":"venue"
},
  "geometry": {"coordinates":[9.273956,45.848408],"type":"Point"}
}