{
  "type": "Feature",
  "properties": {
    "iso:country":"IT",
    "sg:address":"54100 Massa",
    "sg:city":"Massa",
    "sg:orig_category":"Metalli E Leghe",
    "sg:phone":"+39 0585 830704",
    "sg:postcode":"54100",
    "sg:province":"Massa-Carrara",
    "wof:name":"Nicoli Srl",
    "wof:placetype":"venue"
},
  "geometry": {"coordinates":[10.1093416214,44.0254096985],"type":"Point"}
}