{
  "type": "Feature",
  "properties": {
    "iso:country":"IT",
    "sg:address":"00155 Roma",
    "sg:city":"Roma",
    "sg:orig_category":"Impiantistica E Prodotti Tecnologici Per Edilizia",
    "sg:phone":"+39 06 228 2537",
    "sg:postcode":"00155",
    "sg:province":"Roma",
    "wof:name":"Romana Parcheggi Srl",
    "wof:placetype":"venue"
},
  "geometry": {"coordinates":[12.590133,41.900597],"type":"Point"}
}