{
  "type": "Feature",
  "properties": {
    "iso:country":"IT",
    "sg:address":"Via S.s. 275 73031 Alessano",
    "sg:city":"Alessano",
    "sg:classifiers":[
        {
            "category":"Shopping",
            "subcategory":"Clothing, Apparel, & Fashions",
            "type":"Retail Goods"
        }
    ],
    "sg:phone":"+39 0833 524258",
    "sg:postcode":"73031",
    "sg:province":"Lecce",
    "sg:tags":[
        "clothes"
    ],
    "wof:name":"Aretano",
    "wof:placetype":"venue"
},
  "geometry": {"coordinates":[18.343285,39.871254],"type":"Point"}
}