{
  "type": "Feature",
  "properties": {
    "iso:country":"IT",
    "sg:address":"31020 San Vendemiano",
    "sg:city":"San Vendemiano",
    "sg:orig_category":"Impiantistica E Prodotti Tecnologici Per Edilizia. Forniture Industriali Per Prevenzione, Controllo E Sicurezza",
    "sg:phone":"+39 0438 3651",
    "sg:postcode":"31020",
    "sg:province":"Treviso",
    "sg:website":"http://www.ultrak.com",
    "wof:name":"Ultrak Italia Spa",
    "wof:placetype":"venue"
},
  "geometry": {"coordinates":[12.323076,45.890846],"type":"Point"}
}