{
  "type": "Feature",
  "properties": {
    "iso:country":"IT",
    "sg:address":"10091 Alpignano",
    "sg:city":"Alpignano",
    "sg:orig_category":"Materiali E Componenti Elettrotecnici",
    "sg:phone":"+39 011 967 6433",
    "sg:postcode":"10091",
    "sg:province":"Torino",
    "wof:name":"Carlo Gattoni",
    "wof:placetype":"venue"
},
  "geometry": {"coordinates":[7.586306,45.096252],"type":"Point"}
}