{
  "type": "Feature",
  "properties": {
    "addr:full":"Localita' Gracciano 53034 Colle Di Val D'elsa Siena 53034",
    "addr:postcode":"53034;53034",
    "addr:street":"Localita ' Gracciano",
    "iso:country":"IT",
    "sg:address":"Localita' Gracciano 53034 Colle Di Val D'elsa",
    "sg:classifiers":[
        {
            "category":"Manufacturing",
            "subcategory":"Metals",
            "type":"Manufacturing & Wholesale Goods"
        }
    ],
    "sg:phone":"+39 0577 929127",
    "sg:postcode":"53034",
    "sg:province":"Siena",
    "sg:tags":[
        "metallurgy",
        "metalworking"
    ],
    "wof:name":"Presso Fonderie (s.r.l.)",
    "wof:placetype":"venue"
},
  "geometry": {"coordinates":[11.1520233154,43.4202690125],"type":"Point"}
}