{
  "type": "Feature",
  "properties": {
    "iso:country":"IT",
    "sg:address":"50065 Pontassieve",
    "sg:city":"Pontassieve",
    "sg:orig_category":"Marmo, Pietre Ed Affini. Arte Ed Artigianato Artistico",
    "sg:phone":"+39 055 831 4509",
    "sg:postcode":"50065",
    "sg:province":"Firenze",
    "wof:name":"Bianco Bianchi E Figli S.n.c.",
    "wof:placetype":"venue"
},
  "geometry": {"coordinates":[11.42737,43.7729],"type":"Point"}
}