{
  "type": "Feature",
  "properties": {
    "iso:country":"IT",
    "sg:address":"20159 Milano",
    "sg:city":"Milano",
    "sg:classifiers":[
        {
            "category":"Health Services",
            "subcategory":"Health Practitioner",
            "type":"Services"
        }
    ],
    "sg:phone":"+39 02 6900 5634",
    "sg:postcode":"20159",
    "sg:province":"Milano",
    "sg:tags":[
        "medici"
    ],
    "wof:name":"Cozzi Alberto",
    "wof:placetype":"venue"
},
  "geometry": {"coordinates":[9.187581,45.489834],"type":"Point"}
}