{
  "type": "Feature",
  "properties": {
    "iso:country":"IT",
    "sg:address":"85038 Senise",
    "sg:city":"Senise",
    "sg:orig_category":"Servizi E Lavori Per Abbigliamento E Pelletterie",
    "sg:phone":"+39 347 603 7908",
    "sg:postcode":"85038",
    "sg:province":"Potenza",
    "wof:name":"Stranerie",
    "wof:placetype":"venue"
},
  "geometry": {"coordinates":[16.322834,40.175423],"type":"Point"}
}