{
  "type": "Feature",
  "properties": {
    "addr:full":"26, Viale Del Industria 47100 Forli' Forl\u00ec-Cesena 47100",
    "addr:housenumber":"26",
    "addr:postcode":"47100;47100",
    "addr:street":"Viale Del Industria;Forli ' Forli\u0300-Cesena",
    "iso:country":"IT",
    "sg:address":"26, Viale Del Industria 47100 Forli'",
    "sg:classifiers":[
        {
            "category":"Wholesale",
            "subcategory":"Machinery & Supplies",
            "type":"Manufacturing & Wholesale Goods"
        }
    ],
    "sg:phone":"+39 0543 723133",
    "sg:postcode":"47100",
    "sg:province":"Forl\u00ec-Cesena",
    "sg:tags":[
        "-",
        "agriculture",
        "equipment"
    ],
    "wof:name":"Sigma 4 (s.p.a.)",
    "wof:placetype":"venue"
},
  "geometry": {"coordinates":[12.059456,44.217056],"type":"Point"}
}