{
  "type": "Feature",
  "properties": {
    "iso:country":"IT",
    "sg:address":"Via Dei Rizzani 10 33100 Udine",
    "sg:city":"Udine",
    "sg:classifiers":[
        {
            "category":"Retail",
            "subcategory":"Emissions Testing",
            "type":"Services"
        }
    ],
    "sg:phone":"+39 0432 511283",
    "sg:postcode":"33100",
    "sg:province":"Udine",
    "sg:tags":[
        "consumer",
        "good",
        "export"
    ],
    "wof:name":"Eurovit Srl",
    "wof:placetype":"venue"
},
  "geometry": {"coordinates":[13.232563,46.065079],"type":"Point"}
}