{
  "type": "Feature",
  "properties": {
    "iso:country":"IT",
    "sg:address":"40061 Minerbio",
    "sg:city":"Minerbio",
    "sg:orig_category":"Agricoltura, Orticoltura E Floricoltura",
    "sg:phone":"+39 051 877582",
    "sg:postcode":"40061",
    "sg:province":"Bologna",
    "wof:name":"Baschieri Rino Di Giampaolo E Patrizio Baschieri Snc",
    "wof:placetype":"venue"
},
  "geometry": {"coordinates":[11.296618,44.493271],"type":"Point"}
}