{
  "type": "Feature",
  "properties": {
    "iso:country":"IT",
    "sg:address":"80027 Frattamaggiore",
    "sg:city":"Frattamaggiore",
    "sg:orig_category":"Non-classified Establishments",
    "sg:phone":"+39 081 830 2004",
    "sg:postcode":"80027",
    "sg:province":"Napoli",
    "wof:name":"Cabato Srl",
    "wof:placetype":"venue"
},
  "geometry": {"coordinates":[14.27763,40.947578],"type":"Point"}
}