{
  "type": "Feature",
  "properties": {
    "addr:full":"10129 Torino Torino Torino 10129",
    "addr:postcode":"10129;10129",
    "iso:country":"IT",
    "sg:address":"10129 Torino",
    "sg:city":"Torino",
    "sg:classifiers":[
        {
            "category":"Health Services",
            "subcategory":"Health Practitioner",
            "type":"Services"
        }
    ],
    "sg:phone":"+39 011 504181",
    "sg:postcode":"10129",
    "sg:province":"Torino",
    "sg:tags":[
        "medici"
    ],
    "wof:name":"Cocimano Vito",
    "wof:placetype":"venue"
},
  "geometry": {"coordinates":[7.662568,45.055973],"type":"Point"}
}