{
  "type": "Feature",
  "properties": {
    "addr:full":"40, Via Zezio 22100 Como Como Como 22100",
    "addr:postcode":"22100;22100",
    "addr:street":"Via Zezio",
    "iso:country":"IT",
    "sg:address":"40, Via Zezio 22100 Como",
    "sg:city":"Como",
    "sg:classifiers":[
        {
            "category":"Professional",
            "subcategory":"Business Services",
            "type":"Services"
        }
    ],
    "sg:phone":"+39 39031303200",
    "sg:postcode":"22100",
    "sg:province":"Como",
    "sg:tags":[
        "advice"
    ],
    "wof:name":"Artemisia Disegni (s.a.s.)",
    "wof:placetype":"venue"
},
  "geometry": {"coordinates":[9.094226,45.809235],"type":"Point"}
}