{
  "type": "Feature",
  "properties": {
    "iso:country":"IT",
    "sg:address":"15040 Litta Parodi",
    "sg:orig_category":"Prodotti Di Base E Forniture Per Industria Alimentare E Bevande. Forniture E Materiali Per Imballaggio E Confezionamento",
    "sg:phone":"+39 0131 619666",
    "sg:postcode":"15040",
    "sg:province":"Alessandria",
    "wof:name":"Sugherificio L.m. Di Lombardi Federico & C. Sas",
    "wof:placetype":"venue"
},
  "geometry": {"coordinates":[8.7109289169,44.8741264343],"type":"Point"}
}