{
  "type": "Feature",
  "properties": {
    "addr:full":"13, Via Provinciale Mantova 41016 Novi Di Modena Novi di Modena Modena 41016",
    "addr:postcode":"41016;41016",
    "addr:street":"Via Provinciale",
    "iso:country":"IT",
    "sg:address":"13, Via Provinciale Mantova 41016 Novi Di Modena",
    "sg:city":"Novi di Modena",
    "sg:classifiers":[
        {
            "category":"Manufacturing",
            "subcategory":"Lumber",
            "type":"Manufacturing & Wholesale Goods"
        }
    ],
    "sg:phone":"+39 39059677551",
    "sg:postcode":"41016",
    "sg:province":"Modena",
    "sg:tags":[
        "wood"
    ],
    "wof:name":"La Selva Legnami (s.a.s.)",
    "wof:placetype":"venue"
},
  "geometry": {"coordinates":[10.8997,44.895645],"type":"Point"}
}