{
  "type": "Feature",
  "properties": {
    "iso:country":"IT",
    "sg:address":"Via Leopoldo Montini 50; Campodipietra; 86010",
    "sg:city":"Campodipietra",
    "sg:classifiers":[
        {
            "category":"Banks & Credit Unions",
            "subcategory":"Bank",
            "type":"Services"
        }
    ],
    "sg:phone":"+39 0874 441439",
    "sg:postcode":"86010",
    "sg:province":"Campobasso",
    "wof:name":"Istituto Bancario, San Paolo Di Torino Spa",
    "wof:placetype":"venue"
},
  "geometry": {"coordinates":[14.745419,41.558575],"type":"Point"}
}