{
  "type": "Feature",
  "properties": {
    "addr:full":"20131 Milano Milano Milano 20131",
    "addr:postcode":"20131;20131",
    "iso:country":"IT",
    "sg:address":"20131 Milano",
    "sg:city":"Milano",
    "sg:classifiers":[
        {
            "category":"Health Services",
            "subcategory":"Health Practitioner",
            "type":"Services"
        }
    ],
    "sg:phone":"+39 02 236 7113",
    "sg:postcode":"20131",
    "sg:province":"Milano",
    "sg:tags":[
        "medici"
    ],
    "wof:name":"Vignati Federico",
    "wof:placetype":"venue"
},
  "geometry": {"coordinates":[9.2251148224,45.4824142456],"type":"Point"}
}