{
  "type": "Feature",
  "properties": {
    "addr:full":"5/a, Via Bevera 23845 Costa Masnaga Costa Masnaga Lecco 23845",
    "addr:housenumber":"5 / a",
    "addr:postcode":"23845;masnaga;23845",
    "addr:street":"Via Bevera",
    "iso:country":"IT",
    "sg:address":"5/a, Via Bevera 23845 Costa Masnaga",
    "sg:city":"Costa Masnaga",
    "sg:orig_category":"Miscellaneous Products",
    "sg:phone":"+39 39031879363",
    "sg:postcode":"23845",
    "sg:province":"Lecco",
    "wof:name":"Radiv Sas Di Corti Patrizia & C.",
    "wof:placetype":"venue"
},
  "geometry": {"coordinates":[9.3900709152,45.8529815674],"type":"Point"}
}