{
  "type": "Feature",
  "properties": {
    "addr:full":"10010 Alice Superiore Alice Superiore Torino 10010",
    "addr:housenumber":"10010",
    "addr:postcode":"10010",
    "addr:street":"Alice",
    "iso:country":"IT",
    "sg:address":"10010 Alice Superiore",
    "sg:city":"Alice Superiore",
    "sg:orig_category":"Pubblica Amministrazione",
    "sg:phone":"+39 0125 783103",
    "sg:postcode":"10010",
    "sg:province":"Torino",
    "wof:name":"Comunita' Montana Val Chiusella",
    "wof:placetype":"venue"
},
  "geometry": {"coordinates":[7.7774767876,45.4599151611],"type":"Point"}
}