{
  "type": "Feature",
  "properties": {
    "addr:full":"20097 San Donato Milanese San Donato Milanese Milano 20097",
    "addr:housenumber":"20097",
    "addr:postcode":"20097",
    "addr:street":"San",
    "iso:country":"IT",
    "sg:address":"20097 San Donato Milanese",
    "sg:city":"San Donato Milanese",
    "sg:orig_category":"Minuterie Metalliche E Ferramenta",
    "sg:phone":"+39 02 527 0218",
    "sg:postcode":"20097",
    "sg:province":"Milano",
    "wof:name":"A.b.e. Di Bersani Andrea",
    "wof:placetype":"venue"
},
  "geometry": {"coordinates":[9.2612400055,45.4167442322],"type":"Point"}
}