{
  "type": "Feature",
  "properties": {
    "addr:full":"20135 Milano Milano Milano 20135",
    "addr:postcode":"20135;20135",
    "iso:country":"IT",
    "sg:address":"20135 Milano",
    "sg:city":"Milano",
    "sg:orig_category":"Editoria",
    "sg:phone":"+39 02 5411 6211",
    "sg:postcode":"20135",
    "sg:province":"Milano",
    "wof:name":"Erregi Srl",
    "wof:placetype":"venue"
},
  "geometry": {"coordinates":[9.273132,45.52647],"type":"Point"}
}