{
  "type": "Feature",
  "properties": {
    "iso:country":"IT",
    "sg:address":"Via Milano 23899 Robbiate",
    "sg:city":"Robbiate",
    "sg:classifiers":[
        {
            "category":"Shopping",
            "subcategory":"Clothing, Apparel, & Fashions",
            "type":"Retail Goods"
        }
    ],
    "sg:phone":"+39 39039513189",
    "sg:postcode":"23899",
    "sg:province":"Lecco",
    "sg:tags":[
        "clothes"
    ],
    "wof:name":"Weaver Di Mazzoleni Giuseppina",
    "wof:placetype":"venue"
},
  "geometry": {"coordinates":[9.429213,45.679966],"type":"Point"}
}