{
  "type": "Feature",
  "properties": {
    "iso:country":"IT",
    "sg:address":"1, Via Del Fiume 61030 Montefelcino",
    "sg:city":"Montefelcino",
    "sg:classifiers":[
        {
            "category":"Professional",
            "subcategory":"Engineering",
            "type":"Services"
        }
    ],
    "sg:phone":"+39 0721 743045",
    "sg:postcode":"61030",
    "sg:province":"Pesaro E Urbino",
    "sg:tags":[
        "machine",
        "-",
        "mechanical"
    ],
    "wof:name":"Fimas Srl",
    "wof:placetype":"venue"
},
  "geometry": {"coordinates":[12.861181,43.716389],"type":"Point"}
}