{
  "type": "Feature",
  "properties": {
    "addr:full":"62024 Matelica Matelica Macerata 62024",
    "addr:postcode":"62024;62024",
    "iso:country":"IT",
    "sg:address":"62024 Matelica",
    "sg:city":"Matelica",
    "sg:orig_category":"Impiantistica E Prodotti Tecnologici Per Edilizia. Elettrotecnica Industriale, Prodotti E Apparecchiature",
    "sg:phone":"+39 0737 85962",
    "sg:postcode":"62024",
    "sg:province":"Macerata",
    "wof:name":"S.c.r. Nuova Immagine Di Crescenti Aldo E Graziella Sas",
    "wof:placetype":"venue"
},
  "geometry": {"coordinates":[13.011574,43.255001],"type":"Point"}
}