{
  "type": "Feature",
  "properties": {
    "addr:full":"25049 Iseo Iseo Brescia 25049",
    "addr:postcode":"25049;25049",
    "iso:country":"IT",
    "sg:address":"25049 Iseo",
    "sg:city":"Iseo",
    "sg:orig_category":"Sport - Articoli E Forniture",
    "sg:phone":"+39 030 981591",
    "sg:postcode":"25049",
    "sg:province":"Brescia",
    "wof:name":"Pezzotti Domenico",
    "wof:placetype":"venue"
},
  "geometry": {"coordinates":[10.0756902695,45.6707801819],"type":"Point"}
}