{
  "type": "Feature",
  "properties": {
    "iso:country":"IT",
    "sg:address":"64024 Notaresco",
    "sg:city":"Notaresco",
    "sg:orig_category":"Non-classified Establishments",
    "sg:phone":"+39 085 898 0039",
    "sg:postcode":"64024",
    "sg:province":"Teramo",
    "wof:name":"Athena Componibili S.r.l.",
    "wof:placetype":"venue"
},
  "geometry": {"coordinates":[13.847357,42.702679],"type":"Point"}
}