{
  "type": "Feature",
  "properties": {
    "addr:full":"20133 Milano Milano Milano 20133",
    "addr:postcode":"20133;20133",
    "iso:country":"IT",
    "sg:address":"20133 Milano",
    "sg:city":"Milano",
    "sg:orig_category":"Prodotti Alimentari",
    "sg:phone":"+39 02 7010 2626",
    "sg:postcode":"20133",
    "sg:province":"Milano",
    "wof:name":"Galbiati Maria Antonietta",
    "wof:placetype":"venue"
},
  "geometry": {"coordinates":[9.1305789948,45.4059677124],"type":"Point"}
}