{
  "type": "Feature",
  "properties": {
    "iso:country":"IT",
    "sg:address":"07017 Ploaghe",
    "sg:city":"Ploaghe",
    "sg:orig_category":"Zootecnia - Impianti, Macchine Ed Attrezzature",
    "sg:phone":"+39 079 449776",
    "sg:postcode":"07017",
    "sg:province":"Sassari",
    "wof:name":"Camboni Sebastiano",
    "wof:placetype":"venue"
},
  "geometry": {"coordinates":[8.3771,40.653797],"type":"Point"}
}