{
  "type": "Feature",
  "properties": {
    "iso:country":"IT",
    "sg:address":"16, Via Malcontenta 30100 Venezia",
    "sg:classifiers":[
        {
            "category":"Parking",
            "subcategory":"Lot",
            "type":"Transportation"
        }
    ],
    "sg:phone":"+39 39041698299",
    "sg:province":"VE",
    "sg:tags":[
        "transport",
        "road"
    ],
    "wof:name":"Corriere Mestrino S.r.l.",
    "wof:placetype":"venue"
},
  "geometry": {"coordinates":[12.212676,45.447815],"type":"Point"}
}