{
  "type": "Feature",
  "properties": {
    "iso:country":"IT",
    "sg:address":"00187 Roma",
    "sg:city":"Roma",
    "sg:orig_category":"Servizi Al Turismo. Ambasciate Ed Enti Internazionali",
    "sg:phone":"+39 06 487991",
    "sg:postcode":"00187",
    "sg:province":"Roma",
    "wof:name":"Consolato Giappone",
    "wof:placetype":"venue"
},
  "geometry": {"coordinates":[12.495299,41.908016],"type":"Point"}
}