{
  "type": "Feature",
  "properties": {
    "iso:country":"IT",
    "sg:address":"16011 Arenzano",
    "sg:city":"Arenzano",
    "sg:orig_category":"Filati E Materie Prime Tessili",
    "sg:phone":"+39 010 912 6791",
    "sg:postcode":"16011",
    "sg:province":"Genova",
    "wof:name":"Fantasie Del Borgo",
    "wof:placetype":"venue"
},
  "geometry": {"coordinates":[8.6710605621,44.4182319641],"type":"Point"}
}