{
  "type": "Feature",
  "properties": {
    "iso:country":"IT",
    "sg:address":"41100 Modena",
    "sg:city":"Modena",
    "sg:orig_category":"Forniture Per Abbigliamento E Pelletterie",
    "sg:phone":"+39 059 333445",
    "sg:postcode":"41100",
    "sg:province":"Modena",
    "wof:name":"Cappi Angela",
    "wof:placetype":"venue"
},
  "geometry": {"coordinates":[10.9293279648,44.6425170898],"type":"Point"}
}