{
  "type": "Feature",
  "properties": {
    "iso:country":"IT",
    "sg:address":"30, Via Pio' 24062 Costa Volpino",
    "sg:city":"Costa Volpino",
    "sg:classifiers":[
        {
            "category":"Manufacturing",
            "subcategory":"Metals",
            "type":"Manufacturing & Wholesale Goods"
        }
    ],
    "sg:phone":"+39 39035975611",
    "sg:postcode":"24062",
    "sg:province":"Bergamo",
    "sg:tags":[
        "metallurgy",
        "metalworking"
    ],
    "wof:name":"Dmv Stainless Italia Srl",
    "wof:placetype":"venue"
},
  "geometry": {"coordinates":[10.1109695435,45.8257369995],"type":"Point"}
}