{
  "type": "Feature",
  "properties": {
    "addr:full":"00010 Marcellina Marcellina Roma 00010",
    "addr:postcode":"00010;roma 00010",
    "iso:country":"IT",
    "sg:address":"00010 Marcellina",
    "sg:city":"Marcellina",
    "sg:orig_category":"Elettrodomestici - Vendita Al Dettaglio",
    "sg:phone":"+39 0774 424944",
    "sg:postcode":"00010",
    "sg:province":"Roma",
    "wof:name":"Iacovelli Aldo",
    "wof:placetype":"venue"
},
  "geometry": {"coordinates":[12.807276,42.022804],"type":"Point"}
}