{
  "type": "Feature",
  "properties": {
    "iso:country":"IT",
    "sg:address":"47, Viale Otranto 73100 Lecce",
    "sg:city":"Lecce",
    "sg:classifiers":[
        {
            "category":"Professional",
            "subcategory":"Computer Services",
            "type":"Services"
        }
    ],
    "sg:phone":"+39 0832 275111",
    "sg:postcode":"73100",
    "sg:province":"Lecce",
    "sg:tags":[
        "information",
        "technology"
    ],
    "wof:name":"Soft Srl",
    "wof:placetype":"venue"
},
  "geometry": {"coordinates":[18.17251,40.34782],"type":"Point"}
}