{
  "type": "Feature",
  "properties": {
    "iso:country":"IT",
    "sg:address":"40134 Bologna",
    "sg:city":"Bologna",
    "sg:orig_category":"Ricambi E Componenti Dei Mezzi Di Trasporto",
    "sg:phone":"+39 051 430003",
    "sg:postcode":"40134",
    "sg:province":"Bologna",
    "wof:name":"Pasqui Francesco",
    "wof:placetype":"venue"
},
  "geometry": {"coordinates":[11.318499,44.495407],"type":"Point"}
}