{
  "type": "Feature",
  "properties": {
    "addr:full":"53014 Monteroni D'arbia Siena 53014",
    "addr:postcode":"53014;53014",
    "iso:country":"IT",
    "sg:address":"53014 Monteroni D'arbia",
    "sg:orig_category":"Arredo Bagno Ed Idrosanitari. Idrosanitari E Accessori. Minuterie Metalliche E Ferramenta",
    "sg:phone":"+39 0577 374231",
    "sg:postcode":"53014",
    "sg:province":"Siena",
    "sg:website":"http://www.cristalquattro.it",
    "wof:name":"Cristalquattro Srl",
    "wof:placetype":"venue"
},
  "geometry": {"coordinates":[11.37715,43.213531],"type":"Point"}
}