{
  "type": "Feature",
  "properties": {
    "addr:full":"13, Via Politi 20090 Trezzano Sul Naviglio Trezzano sul Naviglio Milano 20090",
    "addr:postcode":"20090;20090",
    "addr:street":"Via Politi",
    "iso:country":"IT",
    "sg:address":"13, Via Politi 20090 Trezzano Sul Naviglio",
    "sg:city":"Trezzano sul Naviglio",
    "sg:classifiers":[
        {
            "category":"Shopping",
            "subcategory":"Stationery & Office Supplies",
            "type":"Retail Goods"
        }
    ],
    "sg:phone":"+39 02 4840 1959",
    "sg:postcode":"20090",
    "sg:province":"Milano",
    "sg:tags":[
        "professional"
    ],
    "wof:name":"Servizio Mostre E Pubblicita' (s.a.s.)",
    "wof:placetype":"venue"
},
  "geometry": {"coordinates":[9.0662488937,45.4203948975],"type":"Point"}
}