{
  "type": "Feature",
  "properties": {
    "addr:full":"1, Via Legatore 40138 Bologna Bologna Bologna 40138",
    "addr:postcode":"40138;40138",
    "addr:street":"Via Legatore",
    "iso:country":"IT",
    "sg:address":"1, Via Legatore 40138 Bologna",
    "sg:city":"Bologna",
    "sg:classifiers":[
        {
            "category":"Wholesale",
            "subcategory":"Medical Equipment & Supplies",
            "type":"Manufacturing & Wholesale Goods"
        }
    ],
    "sg:phone":"+39 39051532515",
    "sg:postcode":"40138",
    "sg:province":"Bologna",
    "sg:tags":[
        "-",
        "health",
        "instrument"
    ],
    "wof:name":"Biesse (s.r.l.)",
    "wof:placetype":"venue"
},
  "geometry": {"coordinates":[11.411795,44.50584],"type":"Point"}
}