{
  "type": "Feature",
  "properties": {
    "addr:full":"90146 Palermo Palermo Palermo 90146",
    "addr:postcode":"90146;90146",
    "iso:country":"IT",
    "sg:address":"90146 Palermo",
    "sg:city":"Palermo",
    "sg:orig_category":"Termotecnica E Riscaldamento, Apparecchiature E Servizi",
    "sg:phone":"+39 091 688 4126",
    "sg:postcode":"90146",
    "sg:province":"Palermo",
    "wof:name":"F. Lli Vasta Sas Di Biagio E Natale",
    "wof:placetype":"venue"
},
  "geometry": {"coordinates":[13.32734,38.154709],"type":"Point"}
}