{
  "type": "Feature",
  "properties": {
    "addr:full":"5, Via Romero Mons. Oscar 25018 Montichiari Montichiari Brescia 25018",
    "addr:postcode":"25018;25018",
    "addr:street":"Via Romero Mons. Oscar",
    "iso:country":"IT",
    "sg:address":"5, Via Romero Mons. Oscar 25018 Montichiari",
    "sg:city":"Montichiari",
    "sg:classifiers":[
        {
            "category":"Real Estate",
            "subcategory":"Surveying",
            "type":"Services"
        }
    ],
    "sg:phone":"+39 39030964404",
    "sg:postcode":"25018",
    "sg:province":"Brescia",
    "sg:tags":[
        "equipment",
        "material",
        "good",
        "-",
        "handling"
    ],
    "wof:name":"C.m.c. (s.r.l.)",
    "wof:placetype":"venue"
},
  "geometry": {"coordinates":[10.222958,45.539829],"type":"Point"}
}