{
  "type": "Feature",
  "properties": {
    "iso:country":"IT",
    "sg:address":"20090 Cesano Boscone",
    "sg:city":"Cesano Boscone",
    "sg:orig_category":"Chiusure Lampo",
    "sg:phone":"+39 02 4860 2598",
    "sg:postcode":"20090",
    "sg:province":"Milano",
    "sg:website":"http://www.ykk.it",
    "wof:name":"Ykk Italia Spa",
    "wof:placetype":"venue"
},
  "geometry": {"coordinates":[9.089046,45.430836],"type":"Point"}
}