{
  "type": "Feature",
  "properties": {
    "addr:full":"04011 Aprilia Aprilia Latina 04011",
    "addr:postcode":"04011;04011",
    "iso:country":"IT",
    "sg:address":"04011 Aprilia",
    "sg:city":"Aprilia",
    "sg:orig_category":"Lavorazioni Meccaniche E Servizi",
    "sg:phone":"+39 06 9274 6291",
    "sg:postcode":"04011",
    "sg:province":"Latina",
    "wof:name":"Calandro Vincenzo",
    "wof:placetype":"venue"
},
  "geometry": {"coordinates":[12.6332,41.537003],"type":"Point"}
}