{
  "type": "Feature",
  "properties": {
    "iso:country":"IT",
    "sg:address":"20090 Trezzano Sul Naviglio",
    "sg:city":"Trezzano sul Naviglio",
    "sg:orig_category":"Frigotecnica, Apparecchiature E Servizi. Servizi Di Magazzinaggio E Movimentazione",
    "sg:phone":"+39 02 4840 3638",
    "sg:postcode":"20090",
    "sg:province":"Milano",
    "wof:name":"Immobiliare Europa S.r.l.",
    "wof:placetype":"venue"
},
  "geometry": {"coordinates":[9.0638237,45.4208869934],"type":"Point"}
}