{
  "type": "Feature",
  "properties": {
    "iso:country":"IT",
    "sg:address":"00158 Roma",
    "sg:city":"Roma",
    "sg:orig_category":"Falegnami",
    "sg:phone":"+39 06 4173 2790",
    "sg:postcode":"00158",
    "sg:province":"Roma",
    "wof:name":"Fra.ma.ro. Srl",
    "wof:placetype":"venue"
},
  "geometry": {"coordinates":[12.5439653397,41.9312591553],"type":"Point"}
}