{
  "type": "Feature",
  "properties": {
    "iso:country":"IT",
    "sg:address":"27010 Albuzzano",
    "sg:city":"Albuzzano",
    "sg:orig_category":"Macchine, Impianti Ed Attrezzature Industria Chimica. Impiantistica E Prodotti Tecnologici Per Edilizia. Impianti, Attrezzature E Forniture Sanitarie Ed Ospedaliere",
    "sg:phone":"+39 0382 434111",
    "sg:postcode":"27010",
    "sg:province":"Pavia",
    "wof:name":"Fedegari Autoclavi Spa",
    "wof:placetype":"venue"
},
  "geometry": {"coordinates":[9.274096,45.186348],"type":"Point"}
}