{
  "type": "Feature",
  "properties": {
    "iso:country":"IT",
    "sg:address":"Piazza De Martino 58-60; Palma Campania; 80036",
    "sg:city":"Palma Campania",
    "sg:classifiers":[
        {
            "category":"Banks & Credit Unions",
            "subcategory":"Bank",
            "type":"Services"
        }
    ],
    "sg:phone":"+39 081 824 1007",
    "sg:postcode":"80036",
    "sg:province":"Napoli",
    "wof:name":"Banco Di Napoli Spa",
    "wof:placetype":"venue"
},
  "geometry": {"coordinates":[14.554315,40.867432],"type":"Point"}
}