{
  "type": "Feature",
  "properties": {
    "iso:country":"IT",
    "sg:address":"70017 Putignano",
    "sg:city":"Putignano",
    "sg:orig_category":"Biancheria Per Alberghi E Comunita'",
    "sg:phone":"+39 080 405817",
    "sg:postcode":"70017",
    "sg:province":"Bari",
    "wof:name":"Tessitura Mele Di Mele Domenico Cesare M.",
    "wof:placetype":"venue"
},
  "geometry": {"coordinates":[17.08938,40.843807],"type":"Point"}
}