{
  "type": "Feature",
  "properties": {
    "addr:full":"00185 Roma Roma Roma 00185",
    "addr:postcode":"00185;00185",
    "iso:country":"IT",
    "sg:address":"00185 Roma",
    "sg:city":"Roma",
    "sg:orig_category":"Espositori, Displays E Articoli Pubblicitari Punto Vendita",
    "sg:phone":"+39 06 445 3714",
    "sg:postcode":"00185",
    "sg:province":"Roma",
    "wof:name":"Fedele 82 Srl",
    "wof:placetype":"venue"
},
  "geometry": {"coordinates":[12.515044,41.893745],"type":"Point"}
}