{
  "type": "Feature",
  "properties": {
    "iso:country":"IT",
    "sg:address":"18039 Ventimiglia",
    "sg:city":"Ventimiglia",
    "sg:classifiers":[
        {
            "category":"Bars & Pubs",
            "subcategory":"Champagne Bar",
            "type":"Food & Drink"
        }
    ],
    "sg:phone":"+39 0184 33897",
    "sg:postcode":"18039",
    "sg:province":"Imperia",
    "sg:tags":[
        "caffe'",
        "e"
    ],
    "wof:name":"Ristorante Stella Marina Di Valente & Ferrauto Snc",
    "wof:placetype":"venue"
},
  "geometry": {"coordinates":[7.546389,43.827976],"type":"Point"}
}