{
  "type": "Feature",
  "properties": {
    "addr:full":"316, Via Claudia 30023 Concordia Sagittaria Concordia Sagittaria Venezia 30023",
    "addr:housenumber":"316",
    "addr:postcode":"30023;30023",
    "addr:street":"Via Claudia",
    "iso:country":"IT",
    "sg:address":"316, Via Claudia 30023 Concordia Sagittaria",
    "sg:city":"Concordia Sagittaria",
    "sg:classifiers":[
        {
            "category":"Professional",
            "subcategory":"Engineering",
            "type":"Services"
        }
    ],
    "sg:phone":"+39 0421 270962",
    "sg:postcode":"30023",
    "sg:province":"Venezia",
    "sg:tags":[
        "machine",
        "-",
        "mechanical"
    ],
    "wof:name":"Pessa (s.p.a.)",
    "wof:placetype":"venue"
},
  "geometry": {"coordinates":[12.843512,45.763336],"type":"Point"}
}