{
  "type": "Feature",
  "properties": {
    "addr:full":"25025 Manerbio Manerbio Brescia 25025",
    "addr:postcode":"25025;25025",
    "iso:country":"IT",
    "sg:address":"25025 Manerbio",
    "sg:city":"Manerbio",
    "sg:orig_category":"Manufacturers: Prefabbricati",
    "sg:phone":"+39 030 993 8674",
    "sg:postcode":"25025",
    "sg:province":"Brescia",
    "sg:website":"http://www.smichele.it",
    "wof:name":"S. Michele Spa",
    "wof:placetype":"venue"
},
  "geometry": {"coordinates":[10.141908,45.348434],"type":"Point"}
}