{
  "type": "Feature",
  "properties": {
    "iso:country":"IT",
    "sg:address":"45011 Adria",
    "sg:city":"Adria",
    "sg:orig_category":"Imprese Di Costruzioni Civili Ed Industriali",
    "sg:phone":"+39 0426 900373",
    "sg:postcode":"45011",
    "sg:province":"Rovigo",
    "wof:name":"C.r.e.o. Di Longato Sante & C. Sas",
    "wof:placetype":"venue"
},
  "geometry": {"coordinates":[12.056107,45.056396],"type":"Point"}
}