{
  "type": "Feature",
  "properties": {
    "iso:country":"IT",
    "sg:address":"92100 Agrigento",
    "sg:city":"Agrigento",
    "sg:orig_category":"Prodotti Finiti Stampati. Forniture E Prodotti Informatici. Forniture Per Uffici",
    "sg:phone":"+39 0922 604612",
    "sg:postcode":"92100",
    "sg:province":"Agrigento",
    "wof:name":"Poligrafica Agrigentina Srl",
    "wof:placetype":"venue"
},
  "geometry": {"coordinates":[13.5784015656,37.3089904785],"type":"Point"}
}