{
  "type": "Feature",
  "properties": {
    "iso:country":"IT",
    "sg:address":"63019 Sant'elpidio A Mare",
    "sg:orig_category":"Calzature - Produzione E Ingrosso",
    "sg:phone":"+39 0734 810073",
    "sg:postcode":"63019",
    "sg:province":"Ascoli Piceno",
    "wof:name":"Revenge Group Srl",
    "wof:placetype":"venue"
},
  "geometry": {"coordinates":[13.687403,43.233299],"type":"Point"}
}