{
  "type": "Feature",
  "properties": {
    "iso:country":"IT",
    "sg:address":"20090 Buccinasco",
    "sg:city":"Buccinasco",
    "sg:orig_category":"Maneggi E Scuderie Cavalli",
    "sg:phone":"+39 02 4570 8513",
    "sg:postcode":"20090",
    "sg:province":"Milano",
    "wof:name":"Centro Equestre Milanofiori",
    "wof:placetype":"venue"
},
  "geometry": {"coordinates":[9.109181,45.389393],"type":"Point"}
}