{
  "type": "Feature",
  "properties": {
    "addr:full":"69/r, Via Il Prato 50123 Firenze Firenze Firenze 50123",
    "addr:housenumber":"69 / r",
    "addr:postcode":"50123;50123",
    "addr:street":"Via Il Prato",
    "iso:country":"IT",
    "sg:address":"69/r, Via Il Prato 50123 Firenze",
    "sg:city":"Firenze",
    "sg:classifiers":[
        {
            "category":"Sports & Exercise",
            "subcategory":"Playing Field",
            "type":"Entertainment"
        }
    ],
    "sg:phone":"+39 39055211499",
    "sg:postcode":"50123",
    "sg:province":"Firenze",
    "sg:tags":[
        "game"
    ],
    "wof:name":"Onerati S.a.s.",
    "wof:placetype":"venue"
},
  "geometry": {"coordinates":[11.149096,43.834526],"type":"Point"}
}