{
  "type": "Feature",
  "properties": {
    "iso:country":"IT",
    "sg:address":"25, Via Giudici Don Pietro 20093 Cologno Monzese",
    "sg:city":"Cologno Monzese",
    "sg:classifiers":[
        {
            "category":"Manufacturing",
            "subcategory":"Rubber & Plastics",
            "type":"Manufacturing & Wholesale Goods"
        }
    ],
    "sg:phone":"+39 39022541533",
    "sg:postcode":"20093",
    "sg:province":"Milano",
    "wof:name":"Tersana (s.r.l.)",
    "wof:placetype":"venue"
},
  "geometry": {"coordinates":[9.280954361,45.5295028687],"type":"Point"}
}