{
  "type": "Feature",
  "properties": {
    "iso:country":"IT",
    "sg:address":"25011 Calcinato",
    "sg:city":"Calcinato",
    "sg:orig_category":"Macchine, Impianti Ed Attrezzature Per Industria Alimentare E Bevande",
    "sg:phone":"+39 030 996 9539",
    "sg:postcode":"25011",
    "sg:province":"Brescia",
    "wof:name":"Trolese Luigi E C. Sas",
    "wof:placetype":"venue"
},
  "geometry": {"coordinates":[10.395603,45.458496],"type":"Point"}
}