{
  "type": "Feature",
  "properties": {
    "iso:country":"IT",
    "sg:address":"Via Olona 9 21054 Fagnano Olona",
    "sg:city":"Fagnano Olona",
    "sg:classifiers":[
        {
            "category":"Transit Center",
            "subcategory":"Freight",
            "type":"Transportation"
        }
    ],
    "sg:phone":"+39 0331 614085",
    "sg:postcode":"21054",
    "sg:province":"Varese",
    "sg:tags":[
        "propeller",
        "ship's"
    ],
    "sg:website":"www.jprop.it",
    "wof:name":"Cober Srl",
    "wof:placetype":"venue"
},
  "geometry": {"coordinates":[8.808398,45.654774],"type":"Point"}
}