{
  "type": "Feature",
  "properties": {
    "addr:full":"35, Via Bernina 25042 Borno Borno Brescia 25042",
    "addr:postcode":"25042;25042",
    "addr:street":"Via Bernina",
    "iso:country":"IT",
    "sg:address":"35, Via Bernina 25042 Borno",
    "sg:city":"Borno",
    "sg:classifiers":[
        {
            "category":"Shopping",
            "subcategory":"Clothing, Apparel, & Fashions",
            "type":"Retail Goods"
        }
    ],
    "sg:phone":"+39 39036441597",
    "sg:postcode":"25042",
    "sg:province":"Brescia",
    "sg:tags":[
        "clothes"
    ],
    "wof:name":"Confezioni Lanico",
    "wof:placetype":"venue"
},
  "geometry": {"coordinates":[10.205027,45.944622],"type":"Point"}
}