{
  "type": "Feature",
  "properties": {
    "addr:full":"35046 Saletto Saletto Padova 35046",
    "addr:postcode":"35046;35046",
    "iso:country":"IT",
    "sg:address":"35046 Saletto",
    "sg:city":"Saletto",
    "sg:orig_category":"Panifici Industriali Ed Artigianali",
    "sg:phone":"+39 0429 89143",
    "sg:postcode":"35046",
    "sg:province":"Padova",
    "wof:name":"Tre Fornari Di Zuffo & Brunaldi Snc",
    "wof:placetype":"venue"
},
  "geometry": {"coordinates":[11.5582323074,45.2316856384],"type":"Point"}
}