{
  "type": "Feature",
  "properties": {
    "iso:country":"IT",
    "sg:address":"Via G Mazzini 4, 88040 Pianopoli, Cz",
    "sg:city":"Pianopoli",
    "sg:classifiers":[
        {
            "category":"Banks & Credit Unions",
            "subcategory":"Bank",
            "type":"Services"
        }
    ],
    "sg:postcode":"88040",
    "sg:province":"Catanzaro",
    "wof:name":"Cassa Rurale Ed Artigiana Di Pianopoli-credito Cooperativo Scrl",
    "wof:placetype":"venue"
},
  "geometry": {"coordinates":[16.587679,38.910599],"type":"Point"}
}