{
  "type": "Feature",
  "properties": {
    "iso:country":"IT",
    "sg:address":"10060 Bibiana",
    "sg:city":"Bibiana",
    "sg:classifiers":[
        {
            "category":"Health Services",
            "subcategory":"Nursing And Care Facility",
            "type":"Services"
        }
    ],
    "sg:phone":"+39 0121 55149",
    "sg:postcode":"10060",
    "sg:province":"Torino",
    "sg:tags":[
        "case",
        "riposo",
        "di"
    ],
    "wof:name":"Residenza Le Soleil",
    "wof:placetype":"venue"
},
  "geometry": {"coordinates":[7.695269,45.065483],"type":"Point"}
}