{
  "type": "Feature",
  "properties": {
    "iso:country":"IT",
    "sg:address":"52100 Arezzo",
    "sg:city":"Arezzo",
    "sg:orig_category":"Metalli E Leghe. Gioielleria, Oreficeria E Argenteria",
    "sg:phone":"+39 0575 383265",
    "sg:postcode":"52100",
    "sg:province":"Arezzo",
    "wof:name":"Oromax Snc",
    "wof:placetype":"venue"
},
  "geometry": {"coordinates":[11.8622102737,43.4782714844],"type":"Point"}
}