{
  "type": "Feature",
  "properties": {
    "addr:full":"108, Via Veneto 74100 Taranto Taranto Taranto 74100",
    "addr:housenumber":"108",
    "addr:postcode":"74100;74100",
    "addr:street":"Via Veneto",
    "iso:country":"IT",
    "sg:address":"108, Via Veneto 74100 Taranto",
    "sg:city":"Taranto",
    "sg:classifiers":[
        {
            "category":"Home & Garden",
            "subcategory":"Home Furnishings",
            "type":"Retail Goods"
        }
    ],
    "sg:phone":"+39 099 732 3430",
    "sg:postcode":"74100",
    "sg:province":"Taranto",
    "sg:tags":[
        "household"
    ],
    "wof:name":"Pellicoro Antonio",
    "wof:placetype":"venue"
},
  "geometry": {"coordinates":[17.261412,40.455315],"type":"Point"}
}