{
  "type": "Feature",
  "properties": {
    "iso:country":"IT",
    "sg:address":"00178 Roma",
    "sg:city":"Roma",
    "sg:orig_category":"Prodotti Alimentari",
    "sg:phone":"+39 06 718 8947",
    "sg:postcode":"00178",
    "sg:province":"Roma",
    "wof:name":"Imp.mar. Ortofrutticola Srl",
    "wof:placetype":"venue"
},
  "geometry": {"coordinates":[12.5445041656,41.8404655457],"type":"Point"}
}