{
  "type": "Feature",
  "properties": {
    "iso:country":"IT",
    "sg:address":"36065 Mussolente",
    "sg:city":"Mussolente",
    "sg:orig_category":"Macchine, Impianti Ed Attrezzature Per Agricoltura E Zootecnia. Macchine, Strumenti Ed Apparecchi Per Attivita' Industriali",
    "sg:phone":"+39 0424 8788",
    "sg:postcode":"36065",
    "sg:province":"Vicenza",
    "sg:website":"http://www.dimartino.it",
    "wof:name":"Di Martino Srl",
    "wof:placetype":"venue"
},
  "geometry": {"coordinates":[11.805497,45.765652],"type":"Point"}
}