{
  "type": "Feature",
  "properties": {
    "addr:full":"20, Via Monte Rosa 28040 Paruzzaro Paruzzaro Novara 28040",
    "addr:postcode":"28040;28040",
    "addr:street":"Via Monte Rosa",
    "iso:country":"IT",
    "sg:address":"20, Via Monte Rosa 28040 Paruzzaro",
    "sg:city":"Paruzzaro",
    "sg:classifiers":[
        {
            "category":"Shopping",
            "type":"Retail Goods"
        }
    ],
    "sg:phone":"+39 0322 230698",
    "sg:postcode":"28040",
    "sg:province":"Novara",
    "sg:tags":[
        "finished",
        "-",
        "metallic"
    ],
    "wof:name":"Europonteggi Srl",
    "wof:placetype":"venue"
},
  "geometry": {"coordinates":[8.5183134079,45.746219635],"type":"Point"}
}