{
  "type": "Feature",
  "properties": {
    "addr:full":"40138 Bologna Bologna Bologna 40138",
    "addr:postcode":"40138;40138",
    "iso:country":"IT",
    "sg:address":"40138 Bologna",
    "sg:city":"Bologna",
    "sg:orig_category":"Raccordi Per Tubi",
    "sg:phone":"+39 051 530371",
    "sg:postcode":"40138",
    "sg:province":"Bologna",
    "wof:name":"In.ra.bo Srl",
    "wof:placetype":"venue"
},
  "geometry": {"coordinates":[11.416885,44.500145],"type":"Point"}
}