{
  "type": "Feature",
  "properties": {
    "addr:full":"50063 Figline Valdarno Figline Valdarno Firenze 50063",
    "addr:postcode":"50063;50063",
    "addr:street":"Valdarno",
    "iso:country":"IT",
    "sg:address":"50063 Figline Valdarno",
    "sg:city":"Figline Valdarno",
    "sg:orig_category":"Sport And Leisure, Services. Tourism, Services. Motor Vehicles, Auxiliary Services. Transport, Auxiliary Services",
    "sg:phone":"+39 055 959596",
    "sg:postcode":"50063",
    "sg:province":"Firenze",
    "wof:name":"Valdarno Rent Sas",
    "wof:placetype":"venue"
},
  "geometry": {"coordinates":[11.463088,43.625492],"type":"Point"}
}