{
  "type": "Feature",
  "properties": {
    "addr:full":"80056 Ercolano Ercolano Napoli 80056",
    "addr:postcode":"80056;80056",
    "iso:country":"IT",
    "sg:address":"80056 Ercolano",
    "sg:city":"Ercolano",
    "sg:orig_category":"Prodotti Alimentari",
    "sg:phone":"+39 081 732 1631",
    "sg:postcode":"80056",
    "sg:province":"Napoli",
    "wof:name":"Maddaloni Francesco",
    "wof:placetype":"venue"
},
  "geometry": {"coordinates":[14.3567857742,40.8109779358],"type":"Point"}
}