{
  "type": "Feature",
  "properties": {
    "iso:country":"IT",
    "sg:address":"2, Via Jappelli 35020 Saonara",
    "sg:city":"Saonara",
    "sg:classifiers":[
        {
            "category":"Personal",
            "subcategory":"Shoe Repair & Shine",
            "type":"Services"
        }
    ],
    "sg:phone":"+39 39049640004",
    "sg:postcode":"35020",
    "sg:province":"Padova",
    "sg:tags":[
        "leather"
    ],
    "wof:name":"Maretto (s.r.l.)",
    "wof:placetype":"venue"
},
  "geometry": {"coordinates":[11.989075,45.365856],"type":"Point"}
}