{
  "type": "Feature",
  "properties": {
    "addr:full":"6, Via Industriale 25014 Castenedolo Castenedolo Brescia 25014",
    "addr:postcode":"25014;25014",
    "addr:street":"Via Industriale",
    "iso:country":"IT",
    "sg:address":"6, Via Industriale 25014 Castenedolo",
    "sg:city":"Castenedolo",
    "sg:classifiers":[
        {
            "category":"Shopping",
            "subcategory":"Computers & Home Electronics",
            "type":"Retail Goods"
        }
    ],
    "sg:phone":"+39 030 213 0566",
    "sg:postcode":"25014",
    "sg:province":"Brescia",
    "sg:tags":[
        "electronic",
        "electrical",
        "equipment"
    ],
    "wof:name":"Fkf (s.r.l.)",
    "wof:placetype":"venue"
},
  "geometry": {"coordinates":[10.285706,45.478466],"type":"Point"}
}