{
  "type": "Feature",
  "properties": {
    "iso:country":"IT",
    "sg:address":"70121 Bari",
    "sg:city":"Bari",
    "sg:classifiers":[
        {
            "category":"Health Services",
            "subcategory":"Health Practitioner",
            "type":"Services"
        }
    ],
    "sg:phone":"+39 080 521 4470",
    "sg:postcode":"70121",
    "sg:province":"Bari",
    "sg:tags":[
        "medici"
    ],
    "wof:name":"Tripoli Gaetano",
    "wof:placetype":"venue"
},
  "geometry": {"coordinates":[16.8747711182,41.1209449768],"type":"Point"}
}