{
  "type": "Feature",
  "properties": {
    "iso:country":"IT",
    "sg:address":"53, Via Ronchi 43010 Fontevivo",
    "sg:city":"Fontevivo",
    "sg:classifiers":[
        {
            "category":"Manufacturing",
            "subcategory":"Wood Products",
            "type":"Manufacturing & Wholesale Goods"
        }
    ],
    "sg:phone":"+39 0521 619721",
    "sg:postcode":"43010",
    "sg:province":"Parma",
    "sg:tags":[
        "furniture"
    ],
    "wof:name":"Eurosughero (s.p.a.)",
    "wof:placetype":"venue"
},
  "geometry": {"coordinates":[10.184378,44.841488],"type":"Point"}
}