{
  "type": "Feature",
  "properties": {
    "addr:full":"Viale Garibaldi 9; Cava Dei Tirreni; 84013 Salerno 84013",
    "addr:housenumber":"9",
    "addr:postcode":"84013;84013",
    "addr:street":"Viale Garibaldi;Cava Dei Tirreni",
    "iso:country":"IT",
    "sg:address":"Viale Garibaldi 9; Cava Dei Tirreni; 84013",
    "sg:classifiers":[
        {
            "category":"Banks & Credit Unions",
            "subcategory":"Bank",
            "type":"Services"
        }
    ],
    "sg:phone":"+39 089 344120",
    "sg:postcode":"84013",
    "sg:province":"Salerno",
    "wof:name":"Banca Di Credito Popolare Scarl",
    "wof:placetype":"venue"
},
  "geometry": {"coordinates":[14.706748,40.703045],"type":"Point"}
}