{
  "type": "Feature",
  "properties": {
    "addr:full":"15042 Bassignana Bassignana Alessandria 15042",
    "addr:housenumber":"15042",
    "addr:postcode":"15042",
    "addr:street":"Bassignana Bassignana",
    "iso:country":"IT",
    "sg:address":"15042 Bassignana",
    "sg:city":"Bassignana",
    "sg:orig_category":"Agenzie D'affari E Servizi Commerciali",
    "sg:phone":"+39 0131 926545",
    "sg:postcode":"15042",
    "sg:province":"Alessandria",
    "wof:name":"Heart Of Gem Di Cervari Alberto",
    "wof:placetype":"venue"
},
  "geometry": {"coordinates":[8.643981,44.953968],"type":"Point"}
}