{
  "type": "Feature",
  "properties": {
    "addr:full":"Via Conca D' Oro, 14/14/a 25070 Bione Bione Brescia 25070",
    "addr:housenumber":"14 / 14 / a",
    "addr:postcode":"25070;25070",
    "addr:street":"Via Conca D ' Oro",
    "iso:country":"IT",
    "sg:address":"Via Conca D' Oro, 14/14/a 25070 Bione",
    "sg:city":"Bione",
    "sg:classifiers":[
        {
            "category":"Manufacturing",
            "subcategory":"Metals",
            "type":"Manufacturing & Wholesale Goods"
        }
    ],
    "sg:phone":"+39 036 589 7043",
    "sg:postcode":"25070",
    "sg:province":"Brescia",
    "sg:tags":[
        "die",
        "aluminium",
        "casting"
    ],
    "sg:website":"www.fonpresmetal.it",
    "wof:name":"Fonpresmetal Gap Spa",
    "wof:placetype":"venue"
},
  "geometry": {"coordinates":[10.222958,45.539829],"type":"Point"}
}