{
  "type": "Feature",
  "properties": {
    "iso:country":"IT",
    "sg:address":"35028 Piove Di Sacco",
    "sg:city":"Corte",
    "sg:orig_category":"Forniture Per Abbigliamento E Pelletterie",
    "sg:phone":"+39 049 972 5450",
    "sg:postcode":"35028",
    "sg:province":"Padova",
    "wof:name":"Tacchificio 3 C (s.n.c.)",
    "wof:placetype":"venue"
},
  "geometry": {"coordinates":[12.047832489,45.2945976257],"type":"Point"}
}