{
  "type": "Feature",
  "properties": {
    "addr:full":"Zona Industriale Giammoro - Giammoro 98042 Pace Del Mela Giammoro Messina 98042",
    "addr:postcode":"98042;98042",
    "addr:street":"Zona Industriale Giammoro Giammoro",
    "iso:country":"IT",
    "sg:address":"Zona Industriale Giammoro - Giammoro 98042 Pace Del Mela",
    "sg:city":"Giammoro",
    "sg:classifiers":[
        {
            "category":"Food & Beverages",
            "subcategory":"Groceries & Convenience Stores",
            "type":"Retail Goods"
        }
    ],
    "sg:phone":"+39 090 938 4395",
    "sg:postcode":"98042",
    "sg:province":"Messina",
    "sg:tags":[
        "product",
        "related"
    ],
    "wof:name":"Puglisi N. & F. (s.p.a.)",
    "wof:placetype":"venue"
},
  "geometry": {"coordinates":[15.5555229187,38.1923332214],"type":"Point"}
}