{
  "type": "Feature",
  "properties": {
    "addr:full":"31053 Pieve Di Soligo Pieve di Soligo Treviso 31053",
    "addr:postcode":"31053;31053",
    "iso:country":"IT",
    "sg:address":"31053 Pieve Di Soligo",
    "sg:city":"Pieve di Soligo",
    "sg:orig_category":"Prodotti Alimentari",
    "sg:phone":"+39 0438 981083",
    "sg:postcode":"31053",
    "sg:province":"Treviso",
    "wof:name":"Deste Ortofrutta Srl",
    "wof:placetype":"venue"
},
  "geometry": {"coordinates":[12.1701421738,45.887638092],"type":"Point"}
}