{
  "type": "Feature",
  "properties": {
    "addr:full":"Via I Maggio 76 40026 Imola Imola Bologna 40026",
    "addr:housenumber":"76",
    "addr:postcode":"40026;40026",
    "addr:street":"Via I Maggio",
    "iso:country":"IT",
    "sg:address":"Via I Maggio 76 40026 Imola",
    "sg:city":"Imola",
    "sg:classifiers":[
        {
            "category":"Manufacturing",
            "subcategory":"Paper Products",
            "type":"Manufacturing & Wholesale Goods"
        }
    ],
    "sg:phone":"+39 0542 641111",
    "sg:postcode":"40026",
    "sg:province":"Bologna",
    "sg:tags":[
        "cardboard",
        "package"
    ],
    "wof:name":"Smurfit Sisa Spa",
    "wof:placetype":"venue"
},
  "geometry": {"coordinates":[11.346481,44.494221],"type":"Point"}
}