{
  "type": "Feature",
  "properties": {
    "iso:country":"IT",
    "sg:address":"18, Via Primo Maggio 40057 Granarolo Dell'emilia",
    "sg:classifiers":[
        {
            "category":"Manufacturing",
            "subcategory":"Textiles",
            "type":"Manufacturing & Wholesale Goods"
        }
    ],
    "sg:phone":"+39 39051768124",
    "sg:postcode":"40057",
    "sg:province":"Bologna",
    "sg:tags":[
        "leather",
        "raw",
        "material",
        "-"
    ],
    "wof:name":"Compel (s.a.s.)",
    "wof:placetype":"venue"
},
  "geometry": {"coordinates":[11.414498,44.532661],"type":"Point"}
}