{
  "type": "Feature",
  "properties": {
    "addr:full":"1, Via Varalli 20089 Rozzano Rozzano Milano 20089",
    "addr:postcode":"20089;20089",
    "addr:street":"Via Varalli",
    "iso:country":"IT",
    "sg:address":"1, Via Varalli 20089 Rozzano",
    "sg:city":"Rozzano",
    "sg:classifiers":[
        {
            "category":"Professional",
            "subcategory":"Engineering",
            "type":"Services"
        }
    ],
    "sg:phone":"+39 39028240355",
    "sg:postcode":"20089",
    "sg:province":"Milano",
    "sg:tags":[
        "machine",
        "-",
        "mechanical"
    ],
    "wof:name":"Multi Import Srl",
    "wof:placetype":"venue"
},
  "geometry": {"coordinates":[9.15911,45.398571],"type":"Point"}
}