{
  "type": "Feature",
  "properties": {
    "iso:country":"IT",
    "sg:address":"Via Puccini 17 22070 Carbonate",
    "sg:city":"Carbonate",
    "sg:classifiers":[
        {
            "category":"Retail",
            "subcategory":"Auto Rental",
            "type":"Services"
        }
    ],
    "sg:phone":"+39 0331 821555",
    "sg:postcode":"22070",
    "sg:province":"Como",
    "sg:tags":[
        "machine",
        "cardboard"
    ],
    "wof:name":"Astin Srl",
    "wof:placetype":"venue"
},
  "geometry": {"coordinates":[9.085456,45.811966],"type":"Point"}
}