{
  "type": "Feature",
  "properties": {
    "iso:country":"IT",
    "sg:address":"20025 Legnano",
    "sg:city":"Legnano",
    "sg:orig_category":"Servizi Ausiliari Di Sorveglianza, Manutenzione E Pulizia. Servizi Vari Di Interesse Pubblico",
    "sg:phone":"+39 0331 459633",
    "sg:postcode":"20025",
    "sg:province":"Milano",
    "sg:website":"http://www.paginegialle.it/piccolasociet\u00e0",
    "wof:name":"Santa Rosa Da Lima Piccola Soc. Coop. Arl",
    "wof:placetype":"venue"
},
  "geometry": {"coordinates":[9.193615,45.572269],"type":"Point"}
}