{
  "type": "Feature",
  "properties": {
    "iso:country":"IT",
    "sg:address":"80121 Napoli",
    "sg:city":"Napoli",
    "sg:classifiers":[
        {
            "category":"Health Services",
            "subcategory":"Health Practitioner",
            "type":"Services"
        }
    ],
    "sg:phone":"+39 081 251 2303",
    "sg:postcode":"80121",
    "sg:province":"Napoli",
    "sg:tags":[
        "medici"
    ],
    "wof:name":"Vetrone Dr. Orazio",
    "wof:placetype":"venue"
},
  "geometry": {"coordinates":[14.2392101288,40.8357810974],"type":"Point"}
}