{
  "type": "Feature",
  "properties": {
    "addr:full":"00124 Roma Roma Roma 00124",
    "addr:postcode":"00124;00124",
    "iso:country":"IT",
    "sg:address":"00124 Roma",
    "sg:city":"Roma",
    "sg:orig_category":"Forniture Per Agricoltura E Zootecnia",
    "sg:phone":"+39 06 5093 0455",
    "sg:postcode":"00124",
    "sg:province":"Roma",
    "wof:name":"Zoo Farm Roma Sas",
    "wof:placetype":"venue"
},
  "geometry": {"coordinates":[12.3495893478,41.7370262146],"type":"Point"}
}