{
  "type": "Feature",
  "properties": {
    "addr:full":"29, Via Garibaldi 80029 Sant'antimo Napoli 80029",
    "addr:postcode":"80029;80029",
    "addr:street":"Via Garibaldi",
    "iso:country":"IT",
    "sg:address":"29, Via Garibaldi 80029 Sant'antimo",
    "sg:classifiers":[
        {
            "category":"Manufacturing",
            "subcategory":"Metals",
            "type":"Manufacturing & Wholesale Goods"
        }
    ],
    "sg:phone":"+39 081 505 0307",
    "sg:postcode":"80029",
    "sg:province":"Napoli",
    "sg:tags":[
        "metallurgy",
        "metalworking"
    ],
    "wof:name":"Buonanno Spa",
    "wof:placetype":"venue"
},
  "geometry": {"coordinates":[14.2317285538,40.9411849976],"type":"Point"}
}