{
  "type": "Feature",
  "properties": {
    "iso:country":"IT",
    "sg:address":"2, Via Parenzo 20143 Milano",
    "sg:city":"Milano",
    "sg:classifiers":[
        {
            "category":"Professional",
            "subcategory":"Engineering",
            "type":"Services"
        }
    ],
    "sg:phone":"+39 02 8915 0335",
    "sg:postcode":"20143",
    "sg:province":"Milano",
    "sg:tags":[
        "machine",
        "-",
        "mechanical"
    ],
    "wof:name":"Clonwerk S.r.l.",
    "wof:placetype":"venue"
},
  "geometry": {"coordinates":[9.139654,45.442883],"type":"Point"}
}