{
  "type": "Feature",
  "properties": {
    "iso:country":"IT",
    "sg:address":"59100 Prato",
    "sg:city":"Prato",
    "sg:orig_category":"Tessuti E Stoffe",
    "sg:phone":"+39 0574 624101",
    "sg:postcode":"59100",
    "sg:province":"Prato",
    "wof:name":"Italfeltro S.r.l.",
    "wof:placetype":"venue"
},
  "geometry": {"coordinates":[11.075285,43.890678],"type":"Point"}
}