{
  "type": "Feature",
  "properties": {
    "iso:country":"IT",
    "sg:address":"36010 Carr\u00e8",
    "sg:classifiers":[
        {
            "category":"Manufacturing",
            "subcategory":"Rubber & Plastics",
            "type":"Manufacturing & Wholesale Goods"
        }
    ],
    "sg:phone":"+39 0445 314128",
    "sg:postcode":"36010",
    "sg:province":"Vicenza",
    "sg:tags":[
        "activities",
        "product",
        "industrial",
        "articles",
        "supply"
    ],
    "sg:website":"http://www.gimatec.com",
    "wof:name":"Gimatec Srl",
    "wof:placetype":"venue"
},
  "geometry": {"coordinates":[11.443399,45.737965],"type":"Point"}
}