{
  "type": "Feature",
  "properties": {
    "addr:full":"00053 Civitavecchia Civitavecchia Roma 00053",
    "addr:postcode":"00053;roma 00053",
    "iso:country":"IT",
    "sg:address":"00053 Civitavecchia",
    "sg:city":"Civitavecchia",
    "sg:orig_category":"Articoli Per Neonati E Bambini",
    "sg:phone":"+39 0766 32718",
    "sg:postcode":"00053",
    "sg:province":"Roma",
    "wof:name":"Saladini Cinzia",
    "wof:placetype":"venue"
},
  "geometry": {"coordinates":[12.467824,41.868855],"type":"Point"}
}