{
  "type": "Feature",
  "properties": {
    "addr:full":"22040 Brenna Brenna Como 22040",
    "addr:postcode":"22040;22040",
    "iso:country":"IT",
    "sg:address":"22040 Brenna",
    "sg:city":"Brenna",
    "sg:orig_category":"Servizi E Lavori Per Arredamento E Industria Del Legno. Arte Ed Artigianato Artistico",
    "sg:phone":"+39 031 797166",
    "sg:postcode":"22040",
    "sg:province":"Como",
    "wof:name":"Colombo Marco",
    "wof:placetype":"venue"
},
  "geometry": {"coordinates":[9.172931,45.70504],"type":"Point"}
}