{
  "type": "Feature",
  "properties": {
    "addr:full":"Cuneo, Cn",
    "iso:country":"IT",
    "sg:address":"Cuneo, Cn",
    "sg:classifiers":[
        {
            "category":"Banks & Credit Unions",
            "subcategory":"Bank",
            "type":"Services"
        }
    ],
    "wof:name":"Federazione Piemontese Banche Di Credito Cooperativeo",
    "wof:placetype":"venue"
},
  "geometry": {"coordinates":[7.547111,44.388798],"type":"Point"}
}