{
  "type": "Feature",
  "properties": {
    "iso:country":"IT",
    "sg:address":"180, Via Montalbano 51100 Pistoia",
    "sg:city":"Pistoia",
    "sg:classifiers":[
        {
            "category":"Professional",
            "subcategory":"Engineering",
            "type":"Services"
        }
    ],
    "sg:phone":"+39 0573 381731",
    "sg:postcode":"51100",
    "sg:province":"Pistoia",
    "sg:tags":[
        "machine",
        "-",
        "mechanical"
    ],
    "wof:name":"Meccaniche Pistoiesi Srl",
    "wof:placetype":"venue"
},
  "geometry": {"coordinates":[10.917787,43.896389],"type":"Point"}
}