{
  "type": "Feature",
  "properties": {
    "iso:country":"IT",
    "sg:address":"37, Viale Polo Marco 00154 Roma",
    "sg:city":"Roma",
    "sg:classifiers":[
        {
            "category":"Utilities",
            "subcategory":"Electric",
            "type":"Services"
        }
    ],
    "sg:phone":"+39 39065745793",
    "sg:postcode":"00154",
    "sg:province":"Roma",
    "sg:tags":[
        "energy"
    ],
    "wof:name":"Peal Petroleum Consultans S.n.c.",
    "wof:placetype":"venue"
},
  "geometry": {"coordinates":[12.482325,41.895466],"type":"Point"}
}