{
  "type": "Feature",
  "properties": {
    "iso:country":"IT",
    "sg:address":"24048 Curnasco",
    "sg:orig_category":"Macchine, Impianti Ed Attrezzature Per Abbigliamento E Pelletterie",
    "sg:phone":"+39 035 691666",
    "sg:postcode":"24048",
    "sg:province":"Bergamo",
    "wof:name":"Officine Fratelli Taiocchi (s.p.a.)",
    "wof:placetype":"venue"
},
  "geometry": {"coordinates":[9.627111,45.677559],"type":"Point"}
}