{
  "type": "Feature",
  "properties": {
    "iso:country":"IT",
    "sg:address":"26845 Codogno",
    "sg:city":"Codogno",
    "sg:orig_category":"Articoli Per Imballaggio E Confezionamento",
    "sg:phone":"+39 0377 33095",
    "sg:postcode":"26845",
    "sg:province":"Lodi",
    "wof:name":"Gallay Mauser Italia S.p.a.",
    "wof:placetype":"venue"
},
  "geometry": {"coordinates":[9.647596,45.173386],"type":"Point"}
}