{
  "type": "Feature",
  "properties": {
    "addr:full":"2, Via Vecchia Milanese 21040 Venegono Inferiore Venegono Inferiore Varese 21040",
    "addr:postcode":"21040;21040",
    "addr:street":"Via Vecchia Milanese;Inferiore",
    "iso:country":"IT",
    "sg:address":"2, Via Vecchia Milanese 21040 Venegono Inferiore",
    "sg:city":"Venegono Inferiore",
    "sg:classifiers":[
        {
            "category":"Manufacturing",
            "subcategory":"Rubber & Plastics",
            "type":"Manufacturing & Wholesale Goods"
        }
    ],
    "sg:phone":"+39 0331 865068",
    "sg:postcode":"21040",
    "sg:province":"Varese",
    "wof:name":"Andriolo S.n.c. Di Andriolo Antonio & C.",
    "wof:placetype":"venue"
},
  "geometry": {"coordinates":[8.8263845444,45.8176040649],"type":"Point"}
}