{
  "type": "Feature",
  "properties": {
    "addr:full":"124/e, Via Mulini 25039 Travagliato Travagliato Brescia 25039",
    "addr:housenumber":"124 / e",
    "addr:postcode":"25039;25039",
    "addr:street":"Via Mulini",
    "iso:country":"IT",
    "sg:address":"124/e, Via Mulini 25039 Travagliato",
    "sg:city":"Travagliato",
    "sg:classifiers":[
        {
            "category":"Shopping",
            "subcategory":"Computers & Home Electronics",
            "type":"Retail Goods"
        }
    ],
    "sg:phone":"+39 030 686 3260",
    "sg:postcode":"25039",
    "sg:province":"Brescia",
    "sg:tags":[
        "electronic",
        "electrical",
        "equipment"
    ],
    "wof:name":"E M B Di Lancini Luciano E C. S.n.c.",
    "wof:placetype":"venue"
},
  "geometry": {"coordinates":[10.076344,45.533791],"type":"Point"}
}