{
  "type": "Feature",
  "properties": {
    "iso:country":"IT",
    "sg:address":"10123 Torino",
    "sg:city":"Torino",
    "sg:classifiers":[
        {
            "category":"Wholesale",
            "subcategory":"Home Furnishings",
            "type":"Manufacturing & Wholesale Goods"
        }
    ],
    "sg:phone":"+39 011 817 2856",
    "sg:postcode":"10123",
    "sg:province":"Torino",
    "sg:tags":[
        "decorative",
        "objects",
        "furnishings",
        "gift"
    ],
    "sg:website":"http://www.ilgiardinoonline.com",
    "wof:name":"Il Giardino Di M. Sieg Sas",
    "wof:placetype":"venue"
},
  "geometry": {"coordinates":[7.6844244003,45.0684013367],"type":"Point"}
}