{
  "type": "Feature",
  "properties": {
    "addr:full":"06063 Magione Magione Perugia 06063",
    "addr:postcode":"06063;06063",
    "iso:country":"IT",
    "sg:address":"06063 Magione",
    "sg:city":"Magione",
    "sg:orig_category":"Non-classified Establishments",
    "sg:phone":"+39 075 843546",
    "sg:postcode":"06063",
    "sg:province":"Perugia",
    "wof:name":"Rondini F.lli Srl",
    "wof:placetype":"venue"
},
  "geometry": {"coordinates":[12.288794,43.158237],"type":"Point"}
}