{
  "type": "Feature",
  "properties": {
    "iso:country":"IT",
    "sg:address":"09047 Selargius",
    "sg:city":"Selargius",
    "sg:orig_category":"Carni, Salumi E Pesci. Zootecnia E Pesca, Allevamento Piccoli Animali",
    "sg:phone":"+39 070 573869",
    "sg:postcode":"09047",
    "sg:province":"Cagliari",
    "sg:website":"http://www.paginegialle.it/saccdipoddesuflli",
    "wof:name":"S.a.c.c. Snc Dei F.lli Poddesu",
    "wof:placetype":"venue"
},
  "geometry": {"coordinates":[9.14008,39.287392],"type":"Point"}
}