{
  "type": "Feature",
  "properties": {
    "iso:country":"IT",
    "sg:address":"Via Ofantina 8/10 71042 Cerignola",
    "sg:city":"Cerignola",
    "sg:classifiers":[
        {
            "category":"Food & Beverages",
            "subcategory":"Fruits & Vegetables",
            "type":"Retail Goods"
        }
    ],
    "sg:phone":"+39 0885 426124",
    "sg:postcode":"71042",
    "sg:province":"Foggia",
    "sg:tags":[
        "canned"
    ],
    "wof:name":"Iaculli Matteo & C. S.n.c.",
    "wof:placetype":"venue"
},
  "geometry": {"coordinates":[15.891696,41.250202],"type":"Point"}
}