{
  "type": "Feature",
  "properties": {
    "addr:full":"25020 Flero Flero Brescia 25020",
    "addr:postcode":"25020;25020",
    "iso:country":"IT",
    "sg:address":"25020 Flero",
    "sg:city":"Flero",
    "sg:orig_category":"Cartotecnica E Servizi. Composizione, Stampa E Confezione. Servizi E Lavori Industria Delle Materie Plastiche. Servizi Per Imballaggio E Confezionamento",
    "sg:phone":"+39 030 268 0961",
    "sg:postcode":"25020",
    "sg:province":"Brescia",
    "wof:name":"Tecno Carto Plast (s.r.l.)",
    "wof:placetype":"venue"
},
  "geometry": {"coordinates":[10.174537,45.483612],"type":"Point"}
}