{
  "type": "Feature",
  "properties": {
    "iso:country":"IT",
    "sg:address":"92024 Canicatt\u00ec",
    "sg:orig_category":"Prodotti Alimentari",
    "sg:phone":"+39 0922 735484",
    "sg:postcode":"92024",
    "sg:province":"Agrigento",
    "wof:name":"Traspomar Di Marino Vincenzo & C. Snc",
    "wof:placetype":"venue"
},
  "geometry": {"coordinates":[13.8573217392,37.3625602722],"type":"Point"}
}