{
  "type": "Feature",
  "properties": {
    "addr:full":"20050 Sulbiate Sulbiate Milano 20050",
    "addr:housenumber":"20050",
    "addr:postcode":"20050",
    "addr:street":"Sulbiate Sulbiate",
    "iso:country":"IT",
    "sg:address":"20050 Sulbiate",
    "sg:city":"Sulbiate",
    "sg:orig_category":"Forniture Per Edilizia E Lavori Pubblici",
    "sg:phone":"+39 039 688 3166",
    "sg:postcode":"20050",
    "sg:province":"Milano",
    "sg:website":"http://www.rinol.com",
    "wof:name":"Rinol Italia Srl",
    "wof:placetype":"venue"
},
  "geometry": {"coordinates":[9.4285440445,45.6250495911],"type":"Point"}
}