{
  "type": "Feature",
  "properties": {
    "iso:country":"IT",
    "sg:address":"34170 Gorizia",
    "sg:city":"Gorizia",
    "sg:orig_category":"Avvocati - Studi",
    "sg:phone":"+39 0481 532232",
    "sg:postcode":"34170",
    "sg:province":"Gorizia",
    "wof:name":"Terpin Avv. Damijan",
    "wof:placetype":"venue"
},
  "geometry": {"coordinates":[13.621899,45.941769],"type":"Point"}
}