{
  "type": "Feature",
  "properties": {
    "addr:full":"169, Via Dalmazia 17031 Albenga Albenga Savona 17031",
    "addr:housenumber":"169",
    "addr:postcode":"17031;17031",
    "addr:street":"Via Dalmazia",
    "iso:country":"IT",
    "sg:address":"169, Via Dalmazia 17031 Albenga",
    "sg:city":"Albenga",
    "sg:classifiers":[
        {
            "category":"Wholesale",
            "subcategory":"Machinery & Supplies",
            "type":"Manufacturing & Wholesale Goods"
        }
    ],
    "sg:phone":"+39 39018250374",
    "sg:postcode":"17031",
    "sg:province":"Savona",
    "sg:tags":[
        "-",
        "agriculture",
        "equipment"
    ],
    "wof:name":"Cooperativa L'ortofrutticola (s.r.l.)",
    "wof:placetype":"venue"
},
  "geometry": {"coordinates":[8.222549,44.050968],"type":"Point"}
}