{
  "type": "Feature",
  "properties": {
    "addr:full":"Via Tortona 105 47020 Pievesestina Forl\u00ec-Cesena 47020",
    "addr:housenumber":"105",
    "addr:postcode":"47020;47020",
    "addr:street":"Via Tortona",
    "iso:country":"IT",
    "sg:address":"Via Tortona 105 47020 Pievesestina",
    "sg:orig_category":"Repair Services For Truck Trailers",
    "sg:phone":"+39 0547 317271",
    "sg:postcode":"47020",
    "sg:province":"Forl\u00ec-Cesena",
    "sg:website":"www.officinecollini.it",
    "wof:name":"Collini Renzo & C. Snc",
    "wof:placetype":"venue"
},
  "geometry": {"coordinates":[11.980461,43.994766],"type":"Point"}
}