{
  "type": "Feature",
  "properties": {
    "iso:country":"IT",
    "sg:address":"31020 Carita'",
    "sg:orig_category":"Automazione E Macchine Per Ufficio. Servizi Ausiliari Di Certificati, Riproduzioni, Disegni E Foto",
    "sg:phone":"+39 0422 608880",
    "sg:postcode":"31020",
    "sg:province":"Treviso",
    "wof:name":"Divisione Sistemi Informativi (s.r.l.)",
    "wof:placetype":"venue"
},
  "geometry": {"coordinates":[12.290718,45.903358],"type":"Point"}
}