{
  "type": "Feature",
  "properties": {
    "addr:full":"27049 Stradella Stradella Pavia 27049",
    "addr:postcode":"27049;27049",
    "iso:country":"IT",
    "sg:address":"27049 Stradella",
    "sg:city":"Stradella",
    "sg:orig_category":"Macchine, Impianti Ed Attrezzature Per Industria Alimentare E Bevande",
    "sg:phone":"+39 0385 246076",
    "sg:postcode":"27049",
    "sg:province":"Pavia",
    "wof:name":"Sanna Francesco",
    "wof:placetype":"venue"
},
  "geometry": {"coordinates":[9.147802,45.170288],"type":"Point"}
}