{
  "type": "Feature",
  "properties": {
    "iso:country":"IT",
    "sg:address":"20049 Concorezzo",
    "sg:city":"Concorezzo",
    "sg:orig_category":"Tempo Libero - Articoli E Forniture. Automobili E Mezzi Di Trasporto",
    "sg:phone":"+39 039 648661",
    "sg:postcode":"20049",
    "sg:province":"Milano",
    "wof:name":"Mondonico G.m.c. (s.a.s.)",
    "wof:placetype":"venue"
},
  "geometry": {"coordinates":[9.336818,45.593395],"type":"Point"}
}