{
  "type": "Feature",
  "properties": {
    "addr:full":"Contra S. Corona, 25; Vicenza; 36100 Vicenza Vicenza 36100",
    "addr:housenumber":"25",
    "addr:postcode":"36100;36100",
    "addr:street":"Contra S. Corona",
    "iso:country":"IT",
    "sg:address":"Contra S. Corona, 25; Vicenza; 36100",
    "sg:city":"Vicenza",
    "sg:classifiers":[
        {
            "category":"Banks & Credit Unions",
            "subcategory":"Bank",
            "type":"Services"
        }
    ],
    "sg:phone":"+39 0444 519111",
    "sg:postcode":"36100",
    "sg:province":"Vicenza",
    "wof:name":"Banca Cattolica Del Veneto",
    "wof:placetype":"venue"
},
  "geometry": {"coordinates":[11.546902,45.550278],"type":"Point"}
}