{
  "type": "Feature",
  "properties": {
    "iso:country":"IT",
    "sg:address":"00119 Roma",
    "sg:city":"Roma",
    "sg:orig_category":"Bevande, Vini E Liquori",
    "sg:phone":"+39 06 5635 2624",
    "sg:postcode":"00119",
    "sg:province":"Roma",
    "wof:name":"Elrashid Ebrahiem",
    "wof:placetype":"venue"
},
  "geometry": {"coordinates":[12.31229,41.767509],"type":"Point"}
}