{
  "type": "Feature",
  "properties": {
    "addr:full":"20090 Assago Assago Milano 20090",
    "addr:postcode":"20090;20090",
    "addr:street":"Assago",
    "iso:country":"IT",
    "sg:address":"20090 Assago",
    "sg:city":"Assago",
    "sg:orig_category":"Cinematografia E Radiotelevisione. Pubblicita', Marketing E Comunicazione. Acqua, Luce, Gas E Societa' Di Esercizio Pubblico",
    "sg:phone":"+39 02 4570 1723",
    "sg:postcode":"20090",
    "sg:province":"Milano",
    "wof:name":"Teleradiocity Lombardia S.r.l.",
    "wof:placetype":"venue"
},
  "geometry": {"coordinates":[9.129325,45.399857],"type":"Point"}
}