{
  "type": "Feature",
  "properties": {
    "iso:country":"IT",
    "sg:address":"85018 Trivigno",
    "sg:city":"Trivigno",
    "sg:orig_category":"Box Prefabbricati",
    "sg:phone":"+39 0971 981059",
    "sg:postcode":"85018",
    "sg:province":"Potenza",
    "wof:name":"Edilmaggio",
    "wof:placetype":"venue"
},
  "geometry": {"coordinates":[15.981739,40.572071],"type":"Point"}
}