{
  "type": "Feature",
  "properties": {
    "iso:country":"IT",
    "sg:address":"1, Via Roma 80017 Melito Di Napoli",
    "sg:city":"Melito di Napoli",
    "sg:classifiers":[
        {
            "category":"Professional",
            "subcategory":"Engineering",
            "type":"Services"
        }
    ],
    "sg:phone":"+39 081 702 3622",
    "sg:postcode":"80017",
    "sg:province":"Napoli",
    "sg:tags":[
        "machine",
        "-",
        "mechanical"
    ],
    "wof:name":"D'amodio Gennaro S.r.l.",
    "wof:placetype":"venue"
},
  "geometry": {"coordinates":[14.237894,40.914093],"type":"Point"}
}