{
  "type": "Feature",
  "properties": {
    "iso:country":"IT",
    "sg:address":"32, Via Maggiore 35045 Ospedaletto Euganeo",
    "sg:city":"Ospedaletto Euganeo",
    "sg:classifiers":[
        {
            "category":"Sports & Exercise",
            "subcategory":"Playing Field",
            "type":"Entertainment"
        }
    ],
    "sg:phone":"+39 39042990390",
    "sg:postcode":"35045",
    "sg:province":"Padova",
    "sg:tags":[
        "game"
    ],
    "wof:name":"Montesin",
    "wof:placetype":"venue"
},
  "geometry": {"coordinates":[11.601667,45.223499],"type":"Point"}
}