{
  "type": "Feature",
  "properties": {
    "addr:full":"09039 Villacidro Villacidro Medio Campidano 09039",
    "addr:postcode":"09039;09039",
    "iso:country":"IT",
    "sg:address":"09039 Villacidro",
    "sg:city":"Villacidro",
    "sg:orig_category":"Cartotecnica E Servizi. Composizione, Stampa E Confezione. Servizi E Lavori Industria Delle Materie Plastiche. Servizi Per Imballaggio E Confezionamento",
    "sg:phone":"+39 070 931 1236",
    "sg:postcode":"09039",
    "sg:province":"Medio Campidano",
    "wof:name":"Forming Plast (s.n.c.)",
    "wof:placetype":"venue"
},
  "geometry": {"coordinates":[8.704075,39.531738],"type":"Point"}
}