{
  "type": "Feature",
  "properties": {
    "addr:full":"31030 Borso Del Grappa Borso del Grappa Treviso 31030",
    "addr:postcode":"31030;31030",
    "iso:country":"IT",
    "sg:address":"31030 Borso Del Grappa",
    "sg:city":"Borso del Grappa",
    "sg:orig_category":"Forniture E Materiali Per Imballaggio E Confezionamento",
    "sg:phone":"+39 0423 561578",
    "sg:postcode":"31030",
    "sg:province":"Treviso",
    "wof:name":"Europack Srl",
    "wof:placetype":"venue"
},
  "geometry": {"coordinates":[11.8008136749,45.815486908],"type":"Point"}
}