{
  "type": "Feature",
  "properties": {
    "addr:full":"52100 Arezzo Arezzo Arezzo 52100",
    "addr:postcode":"52100;52100",
    "iso:country":"IT",
    "sg:address":"52100 Arezzo",
    "sg:city":"Arezzo",
    "sg:classifiers":[
        {
            "category":"Shopping",
            "subcategory":"Clothing, Apparel, & Fashions",
            "type":"Retail Goods"
        }
    ],
    "sg:phone":"+39 0575 302246",
    "sg:postcode":"52100",
    "sg:province":"Arezzo",
    "sg:tags":[
        "clothing",
        "fur",
        "knitwear"
    ],
    "wof:name":"Uomo Pi\u00d9 Italia Srl",
    "wof:placetype":"venue"
},
  "geometry": {"coordinates":[11.934807,43.432545],"type":"Point"}
}