{
  "type": "Feature",
  "properties": {
    "addr:full":"Strada Consorziale Dei Crederi 24045 Fara Gera D'adda Bergamo 24045",
    "addr:postcode":"24045;24045",
    "addr:street":"Strada",
    "iso:country":"IT",
    "sg:address":"Strada Consorziale Dei Crederi 24045 Fara Gera D'adda",
    "sg:classifiers":[
        {
            "category":"Manufacturing",
            "subcategory":"Metals",
            "type":"Manufacturing & Wholesale Goods"
        }
    ],
    "sg:phone":"+39 036 339 8346",
    "sg:postcode":"24045",
    "sg:province":"Bergamo",
    "sg:tags":[
        "processing"
    ],
    "wof:name":"Mi - Metal Bramati (s.r.l.)",
    "wof:placetype":"venue"
},
  "geometry": {"coordinates":[9.6699523926,45.6949043274],"type":"Point"}
}