{
  "type": "Feature",
  "properties": {
    "iso:country":"IT",
    "sg:address":"33033 Codroipo",
    "sg:city":"Codroipo",
    "sg:orig_category":"Macchine, Impianti Ed Attrezzature Per Industria Alimentare E Bevande",
    "sg:phone":"+39 0432 900788",
    "sg:postcode":"33033",
    "sg:province":"Udine",
    "wof:name":"Agenzia Enologica",
    "wof:placetype":"venue"
},
  "geometry": {"coordinates":[12.976709,45.960175],"type":"Point"}
}