{
  "type": "Feature",
  "properties": {
    "addr:full":"90146 Palermo Palermo Palermo 90146",
    "addr:postcode":"90146;90146",
    "iso:country":"IT",
    "sg:address":"90146 Palermo",
    "sg:city":"Palermo",
    "sg:orig_category":"Climatizzazione E Condizionamento, Apparecchiature E Servizi. Elettrodomestici",
    "sg:phone":"+39 091 670 3819",
    "sg:postcode":"90146",
    "sg:province":"Palermo",
    "wof:name":"Albamonte Calcedonio",
    "wof:placetype":"venue"
},
  "geometry": {"coordinates":[13.328044,38.152657],"type":"Point"}
}