{
  "type": "Feature",
  "properties": {
    "iso:country":"IT",
    "sg:address":"6, Via Faiella F. 84018 Scafati",
    "sg:city":"Scafati",
    "sg:classifiers":[
        {
            "category":"Food & Beverages",
            "subcategory":"Groceries & Convenience Stores",
            "type":"Retail Goods"
        }
    ],
    "sg:phone":"+39 081 859 9692",
    "sg:postcode":"84018",
    "sg:province":"Salerno",
    "sg:tags":[
        "product",
        "related"
    ],
    "wof:name":"Faiella",
    "wof:placetype":"venue"
},
  "geometry": {"coordinates":[14.765912056,40.6779556274],"type":"Point"}
}