{
  "type": "Feature",
  "properties": {
    "addr:full":"Via Raffaello 2; Malo; 36034 Malo Vicenza 36034",
    "addr:housenumber":"2",
    "addr:postcode":"36034;36034",
    "addr:street":"Via Raffaello",
    "iso:country":"IT",
    "sg:address":"Via Raffaello 2; Malo; 36034",
    "sg:city":"Malo",
    "sg:classifiers":[
        {
            "category":"Banks & Credit Unions",
            "subcategory":"Bank",
            "type":"Services"
        }
    ],
    "sg:phone":"+39 0445 602021",
    "sg:postcode":"36034",
    "sg:province":"Vicenza",
    "wof:name":"Banca Popolare Vicentina Scparl",
    "wof:placetype":"venue"
},
  "geometry": {"coordinates":[11.401567,45.65873],"type":"Point"}
}