{
  "type": "Feature",
  "properties": {
    "addr:full":"60027 Osimo Osimo Ancona 60027",
    "addr:postcode":"60027;60027",
    "iso:country":"IT",
    "sg:address":"60027 Osimo",
    "sg:city":"Osimo",
    "sg:orig_category":"Prodotti E Manufatti In Materie Plastiche. Materiali Edili",
    "sg:phone":"+39 071 723 2219",
    "sg:postcode":"60027",
    "sg:province":"Ancona",
    "wof:name":"Sa.mo. Di Bruno Monika",
    "wof:placetype":"venue"
},
  "geometry": {"coordinates":[13.4263629913,43.6128883362],"type":"Point"}
}