{
  "type": "Feature",
  "properties": {
    "iso:country":"IT",
    "sg:address":"40056 Crespellano",
    "sg:city":"Crespellano",
    "sg:orig_category":"Macchine E Forniture Per Arredamento E Industria Del Legno",
    "sg:phone":"+39 051 969284",
    "sg:postcode":"40056",
    "sg:province":"Bologna",
    "wof:name":"Stamperia Marra Snc",
    "wof:placetype":"venue"
},
  "geometry": {"coordinates":[11.129846,44.521412],"type":"Point"}
}