{
  "type": "Feature",
  "properties": {
    "iso:country":"IT",
    "sg:address":"62014 Corridonia",
    "sg:city":"Corridonia",
    "sg:orig_category":"Arredamenti E Mobili Professionali. Arredi Ed Attrezzature Per Uffici",
    "sg:phone":"+39 0733 262049",
    "sg:postcode":"62014",
    "sg:province":"Macerata",
    "sg:website":"http://www.riganelli.it",
    "wof:name":"Riganelli Luigi",
    "wof:placetype":"venue"
},
  "geometry": {"coordinates":[13.488422,43.263237],"type":"Point"}
}