{
  "type": "Feature",
  "properties": {
    "iso:country":"IT",
    "sg:address":"258, Via Cappona Rurale I Tratto 47039 Savignano Sul Rubicone",
    "sg:city":"Savignano sul Rubicone",
    "sg:classifiers":[
        {
            "category":"Personal",
            "subcategory":"Shoe Repair & Shine",
            "type":"Services"
        }
    ],
    "sg:phone":"+39 0541 944519",
    "sg:postcode":"47039",
    "sg:province":"Forl\u00ec-Cesena",
    "sg:tags":[
        "leather"
    ],
    "wof:name":"Suolificio Viola Srl",
    "wof:placetype":"venue"
},
  "geometry": {"coordinates":[12.394245,44.093197],"type":"Point"}
}