{
  "type": "Feature",
  "properties": {
    "iso:country":"IT",
    "sg:address":"20, V. Leonardo Da Vinci 33010 Reana Del Rojale",
    "sg:classifiers":[
        {
            "category":"Professional",
            "subcategory":"Engineering",
            "type":"Services"
        }
    ],
    "sg:phone":"+39 0432 851455",
    "sg:postcode":"33010",
    "sg:province":"Udine",
    "sg:tags":[
        "machine",
        "-",
        "mechanical"
    ],
    "sg:website":"http://www.mepgroup.com:ws_end: :mark:ws:http://www.paginegialle.it/mepspa",
    "wof:name":"M.e.p. Spa",
    "wof:placetype":"venue"
},
  "geometry": {"coordinates":[13.224132,46.141624],"type":"Point"}
}