{
  "type": "Feature",
  "properties": {
    "iso:country":"IT",
    "sg:address":"00187 Roma",
    "sg:city":"Roma",
    "sg:orig_category":"Servizi Al Turismo. Trasporto Pubblico E Privato",
    "sg:phone":"+39 06 4201 4452",
    "sg:postcode":"00187",
    "sg:province":"Roma",
    "wof:name":"Epirotiki Cruises And Ferries",
    "wof:placetype":"venue"
},
  "geometry": {"coordinates":[12.491043,41.9044],"type":"Point"}
}