{
  "type": "Feature",
  "properties": {
    "iso:country":"IT",
    "sg:address":"30174 Venezia",
    "sg:city":"Venezia",
    "sg:orig_category":"Valvole E Apparecchiature Di Misura. Ricambi E Componenti Dei Mezzi Di Trasporto",
    "sg:phone":"+39 041 501 0109",
    "sg:postcode":"30174",
    "sg:province":"Venezia",
    "wof:name":"Belimo Servomotori (s.r.l.)",
    "wof:placetype":"venue"
},
  "geometry": {"coordinates":[12.970455,45.810093],"type":"Point"}
}