{
  "type": "Feature",
  "properties": {
    "iso:country":"IT",
    "sg:address":"20124 Milano",
    "sg:city":"Milano",
    "sg:orig_category":"Macchine, Impianti Ed Attrezzature Industria Chimica",
    "sg:phone":"+39 02 670 2882",
    "sg:postcode":"20124",
    "sg:province":"Milano",
    "wof:name":"Progetti Impianti Chimici Pic Srl",
    "wof:placetype":"venue"
},
  "geometry": {"coordinates":[9.197339,45.486568],"type":"Point"}
}