{
  "type": "Feature",
  "properties": {
    "addr:full":"7, Via Milano 20020 Lainate Lainate Milano 20020",
    "addr:postcode":"20020;20020",
    "addr:street":"Via Milano",
    "iso:country":"IT",
    "sg:address":"7, Via Milano 20020 Lainate",
    "sg:city":"Lainate",
    "sg:classifiers":[
        {
            "category":"Manufacturing",
            "subcategory":"Lumber",
            "type":"Manufacturing & Wholesale Goods"
        }
    ],
    "sg:phone":"+39 39029370228",
    "sg:postcode":"20020",
    "sg:province":"Milano",
    "sg:tags":[
        "wood"
    ],
    "wof:name":"Pavinlegno Di Parini (s.r.l.)",
    "wof:placetype":"venue"
},
  "geometry": {"coordinates":[9.045741,45.525681],"type":"Point"}
}