{
  "type": "Feature",
  "properties": {
    "iso:country":"IT",
    "sg:address":"Via Saluzzo 54/b 12022 Busca",
    "sg:city":"Busca",
    "sg:classifiers":[
        {
            "category":"Building & Trades",
            "subcategory":"Construction",
            "type":"Services"
        }
    ],
    "sg:phone":"+39 0171 945266",
    "sg:postcode":"12022",
    "sg:province":"Cuneo",
    "sg:tags":[
        "carpenter's",
        "work",
        "supraregional"
    ],
    "sg:website":"www.riberi.com",
    "wof:name":"Fratelli Riberi Snc",
    "wof:placetype":"venue"
},
  "geometry": {"coordinates":[7.517339,44.45668],"type":"Point"}
}