{
  "type": "Feature",
  "properties": {
    "addr:full":"Via Caselette Km 16,200 10091 Alpignano Alpignano Torino 10091",
    "addr:housenumber":"km 16,200",
    "addr:postcode":"10091;10091",
    "addr:street":"Via Caselette",
    "iso:country":"IT",
    "sg:address":"Via Caselette Km 16,200 10091 Alpignano",
    "sg:city":"Alpignano",
    "sg:orig_category":"Plastic Film Capacitors",
    "sg:phone":"+39 011 967 7969",
    "sg:postcode":"10091",
    "sg:province":"Torino",
    "sg:website":"www.temaitalia.it",
    "wof:name":"Nke Spa",
    "wof:placetype":"venue"
},
  "geometry": {"coordinates":[7.6866188049,45.0705604553],"type":"Point"}
}