{
  "type": "Feature",
  "properties": {
    "iso:country":"IT",
    "sg:address":"34121 Trieste",
    "sg:city":"Trieste",
    "sg:orig_category":"Servizi E Lavori Per Industria Alimentare E Bevande",
    "sg:phone":"+39 040 368052",
    "sg:postcode":"34121",
    "sg:province":"Trieste",
    "wof:name":"Mercati Comunali",
    "wof:placetype":"venue"
},
  "geometry": {"coordinates":[13.771276,45.651764],"type":"Point"}
}