{
  "type": "Feature",
  "properties": {
    "iso:country":"IT",
    "sg:address":"Via Xxv Aprile 304 21044 Cavaria Con Premezzo",
    "sg:city":"Cavaria con Premezzo",
    "sg:classifiers":[
        {
            "category":"Manufacturing",
            "subcategory":"Tools & Machinery",
            "type":"Manufacturing & Wholesale Goods"
        }
    ],
    "sg:phone":"+39 0331 217194",
    "sg:postcode":"21044",
    "sg:province":"Varese",
    "sg:tags":[
        "shutter",
        "shaft",
        "roller",
        "drive",
        "motor"
    ],
    "wof:name":"Nuova Mazzucchelli Srl",
    "wof:placetype":"venue"
},
  "geometry": {"coordinates":[8.8263845444,45.8176040649],"type":"Point"}
}