{
  "type": "Feature",
  "properties": {
    "iso:country":"IT",
    "sg:address":"15057 Tortona",
    "sg:city":"Tortona",
    "sg:orig_category":"Dottori Commercialisti - Studi",
    "sg:phone":"+39 0131 861241",
    "sg:postcode":"15057",
    "sg:province":"Alessandria",
    "wof:name":"Gavio Aldo & C. Sas",
    "wof:placetype":"venue"
},
  "geometry": {"coordinates":[8.616986,44.922077],"type":"Point"}
}