{
  "type": "Feature",
  "properties": {
    "addr:full":"9, Contrada Squillace 80022 Arzano Arzano Napoli 80022",
    "addr:postcode":"80022;80022",
    "addr:street":"Squillace",
    "iso:country":"IT",
    "sg:address":"9, Contrada Squillace 80022 Arzano",
    "sg:city":"Arzano",
    "sg:classifiers":[
        {
            "category":"Professional",
            "subcategory":"Engineering",
            "type":"Services"
        }
    ],
    "sg:phone":"+39 081 573 4215",
    "sg:postcode":"80022",
    "sg:province":"Napoli",
    "sg:tags":[
        "machine",
        "-",
        "mechanical"
    ],
    "wof:name":"Fra Man Srl",
    "wof:placetype":"venue"
},
  "geometry": {"coordinates":[14.251636,40.840096],"type":"Point"}
}