{
  "type": "Feature",
  "properties": {
    "iso:country":"IT",
    "sg:address":"29027 Podenzano",
    "sg:city":"Podenzano",
    "sg:orig_category":"Utensili Meccanici E Materiali",
    "sg:phone":"+39 0523 558357",
    "sg:postcode":"29027",
    "sg:province":"Piacenza",
    "wof:name":"Ala Plus Srl",
    "wof:placetype":"venue"
},
  "geometry": {"coordinates":[9.73336,44.988262],"type":"Point"}
}