{
  "type": "Feature",
  "properties": {
    "iso:country":"IT",
    "sg:address":"Viale Parioli 160/162; Roma; 00197",
    "sg:city":"Roma",
    "sg:classifiers":[
        {
            "category":"Banks & Credit Unions",
            "subcategory":"Bank",
            "type":"Services"
        }
    ],
    "sg:phone":"+39 06 858 7811",
    "sg:postcode":"00197",
    "sg:province":"Roma",
    "wof:name":"Banca Fideuram Spa",
    "wof:placetype":"venue"
},
  "geometry": {"coordinates":[12.486213,41.928577],"type":"Point"}
}