{
  "type": "Feature",
  "properties": {
    "iso:country":"IT",
    "sg:address":"Via Osmannoro 50019 Sesto Fiorentino",
    "sg:city":"Osmannoro",
    "sg:classifiers":[
        {
            "category":"Wholesale",
            "subcategory":"Drugs",
            "type":"Manufacturing & Wholesale Goods"
        }
    ],
    "sg:phone":"+39 390 554 2951",
    "sg:postcode":"50019",
    "sg:province":"Firenze",
    "sg:tags":[
        "chemical",
        "pharmaceutical"
    ],
    "wof:name":"Baxter Manufacturing S.p.a.",
    "wof:placetype":"venue"
},
  "geometry": {"coordinates":[11.190084,43.820202],"type":"Point"}
}