{
  "type": "Feature",
  "properties": {
    "addr:full":"12, Via Boldani 30034 Mira Mira Venezia 30034",
    "addr:postcode":"30034;30034",
    "addr:street":"Via Boldani;Mira Mira Venezia",
    "iso:country":"IT",
    "sg:address":"12, Via Boldani 30034 Mira",
    "sg:city":"Mira",
    "sg:classifiers":[
        {
            "category":"Real Estate",
            "subcategory":"Architect",
            "type":"Services"
        }
    ],
    "sg:phone":"+39 041 426 5862",
    "sg:postcode":"30034",
    "sg:province":"Venezia",
    "sg:tags":[
        "textile",
        "clothing"
    ],
    "wof:name":"Incotex (s.p.a.)",
    "wof:placetype":"venue"
},
  "geometry": {"coordinates":[12.142714,45.449112],"type":"Point"}
}