{
  "type": "Feature",
  "properties": {
    "iso:country":"IT",
    "sg:address":"46029 Suzzara",
    "sg:city":"Suzzara",
    "sg:orig_category":"Impiantistica E Prodotti Tecnologici Per Edilizia. Forniture Industriali Per Prevenzione, Controllo E Sicurezza",
    "sg:phone":"+39 0376 522159",
    "sg:postcode":"46029",
    "sg:province":"Mantova",
    "wof:name":"Messori Paolo",
    "wof:placetype":"venue"
},
  "geometry": {"coordinates":[10.750845,45.008492],"type":"Point"}
}