{
  "type": "Feature",
  "properties": {
    "iso:country":"IT",
    "sg:address":"85, Via Piave 80126 Napoli",
    "sg:city":"Napoli",
    "sg:classifiers":[
        {
            "category":"Communications",
            "subcategory":"Newspaper",
            "type":"Services"
        }
    ],
    "sg:phone":"+39 081 714 2539",
    "sg:postcode":"80126",
    "sg:province":"Napoli",
    "sg:tags":[
        "advertising"
    ],
    "wof:name":"Ragucci Advertising Di Ragucci P.le",
    "wof:placetype":"venue"
},
  "geometry": {"coordinates":[14.211364,40.839607],"type":"Point"}
}