{
  "type": "Feature",
  "properties": {
    "addr:full":"95127 Catania Catania Catania 95127",
    "addr:postcode":"95127;95127",
    "iso:country":"IT",
    "sg:address":"95127 Catania",
    "sg:city":"Catania",
    "sg:orig_category":"Minuterie Metalliche E Ferramenta",
    "sg:phone":"+39 095 388003",
    "sg:postcode":"95127",
    "sg:province":"Catania",
    "wof:name":"Spilt Sas Di Pepe Francesco",
    "wof:placetype":"venue"
},
  "geometry": {"coordinates":[15.1025590897,37.5176582336],"type":"Point"}
}