{
  "type": "Feature",
  "properties": {
    "addr:full":"50014 Fiesole Fiesole Firenze 50014",
    "addr:postcode":"50014;50014",
    "iso:country":"IT",
    "sg:address":"50014 Fiesole",
    "sg:city":"Fiesole",
    "sg:orig_category":"Macchine Utensili E Impianti",
    "sg:phone":"+39 055 659 3741",
    "sg:postcode":"50014",
    "sg:province":"Firenze",
    "wof:name":"Centro Galvanotecnico Toscano Srl",
    "wof:placetype":"venue"
},
  "geometry": {"coordinates":[11.357944,43.774986],"type":"Point"}
}