{
  "type": "Feature",
  "properties": {
    "iso:country":"IT",
    "sg:address":"50019 Sesto Fiorentino",
    "sg:city":"Sesto Fiorentino",
    "sg:orig_category":"Elettrotecnica Industriale, Prodotti E Apparecchiature. Ricambi E Componenti Dei Mezzi Di Trasporto",
    "sg:phone":"+39 055 302 4290",
    "sg:postcode":"50019",
    "sg:province":"Firenze",
    "wof:name":"Ener1 S.r.l.",
    "wof:placetype":"venue"
},
  "geometry": {"coordinates":[11.178112,43.81134],"type":"Point"}
}