{
  "type": "Feature",
  "properties": {
    "iso:country":"IT",
    "sg:address":"Via Del Lavoro 41 20030 Senago",
    "sg:city":"Senago",
    "sg:orig_category":"Analogue Indicators",
    "sg:phone":"+39 02 998 6557",
    "sg:postcode":"20030",
    "sg:province":"Milano",
    "sg:website":"www.fase.it",
    "wof:name":"Fase Srl",
    "wof:placetype":"venue"
},
  "geometry": {"coordinates":[9.157892,45.551891],"type":"Point"}
}