{
  "type": "Feature",
  "properties": {
    "iso:country":"IT",
    "sg:address":"20124 Milano",
    "sg:city":"Milano",
    "sg:orig_category":"Editoria",
    "sg:phone":"+39 0267171",
    "sg:postcode":"20124",
    "sg:province":"Milano",
    "wof:name":"Societa' Editoriale Quotidiani",
    "wof:placetype":"venue"
},
  "geometry": {"coordinates":[9.205235,45.483143],"type":"Point"}
}