{
  "type": "Feature",
  "properties": {
    "iso:country":"IT",
    "sg:address":"Via Venezia 28 30022 Ceggia",
    "sg:city":"Ceggia",
    "sg:classifiers":[
        {
            "category":"Wholesale",
            "subcategory":"Construction Materials",
            "type":"Manufacturing & Wholesale Goods"
        }
    ],
    "sg:phone":"+39 0421 322000",
    "sg:postcode":"30022",
    "sg:province":"Venezia",
    "sg:tags":[
        "sealing",
        "insulating",
        "insulant",
        "moisture"
    ],
    "sg:website":"www.generalmembrane.it",
    "wof:name":"General Membrane S.p.a.",
    "wof:placetype":"venue"
},
  "geometry": {"coordinates":[12.970455,45.810093],"type":"Point"}
}