{
  "type": "Feature",
  "properties": {
    "iso:country":"IT",
    "sg:address":"90121 Palermo",
    "sg:city":"Palermo",
    "sg:orig_category":"Autodemolizioni",
    "sg:phone":"+39 091 614 2670",
    "sg:postcode":"90121",
    "sg:province":"Palermo",
    "wof:name":"Palermo Star Di D'anna Gaetano",
    "wof:placetype":"venue"
},
  "geometry": {"coordinates":[13.430436,38.082901],"type":"Point"}
}