{
  "type": "Feature",
  "properties": {
    "addr:full":"20030 Senago Senago Milano 20030",
    "addr:postcode":"20030;20030",
    "iso:country":"IT",
    "sg:address":"20030 Senago",
    "sg:city":"Senago",
    "sg:orig_category":"Bevande, Vini E Liquori",
    "sg:phone":"+39 02 998 0009",
    "sg:postcode":"20030",
    "sg:province":"Milano",
    "wof:name":"Carraro Luigi",
    "wof:placetype":"venue"
},
  "geometry": {"coordinates":[9.107018,45.547775],"type":"Point"}
}