{
  "type": "Feature",
  "properties": {
    "iso:country":"IT",
    "sg:address":"18100 Imperia",
    "sg:city":"Imperia",
    "sg:orig_category":"Tempo Libero - Articoli E Forniture. Regalistica Aziendale",
    "sg:phone":"+39 0183 290870",
    "sg:postcode":"18100",
    "sg:province":"Imperia",
    "wof:name":"Giocattoli Garelli Sas",
    "wof:placetype":"venue"
},
  "geometry": {"coordinates":[8.064083,43.912491],"type":"Point"}
}