{
  "type": "Feature",
  "properties": {
    "iso:country":"IT",
    "sg:address":"33100 Udine",
    "sg:city":"Udine",
    "sg:orig_category":"Agenzie Investigative",
    "sg:phone":"+39 0432 531744",
    "sg:postcode":"33100",
    "sg:province":"Udine",
    "wof:name":"Aptel Snc Di Pulin Antonio & C.",
    "wof:placetype":"venue"
},
  "geometry": {"coordinates":[13.225008,46.063148],"type":"Point"}
}