{
  "type": "Feature",
  "properties": {
    "iso:country":"IT",
    "sg:address":"90126 Palermo",
    "sg:city":"Palermo",
    "sg:orig_category":"Trasporti E Spedizioni Merci",
    "sg:phone":"+39 091 668 7094",
    "sg:postcode":"90126",
    "sg:province":"Palermo",
    "wof:name":"Bartolini Spa",
    "wof:placetype":"venue"
},
  "geometry": {"coordinates":[13.314615,38.060795],"type":"Point"}
}