{
  "type": "Feature",
  "properties": {
    "addr:full":"10060 Rifugio Melano Torino 10060",
    "addr:postcode":"10060;10060",
    "iso:country":"IT",
    "sg:address":"10060 Rifugio Melano",
    "sg:orig_category":"Servizi Per Lo Sport E Il Tempo Libero. Alberghi E Strutture Extra Alberghiere",
    "sg:phone":"+39 0121 353160",
    "sg:postcode":"10060",
    "sg:province":"Torino",
    "wof:name":"Rifugio C.a.i.",
    "wof:placetype":"venue"
},
  "geometry": {"coordinates":[7.686619,45.07056],"type":"Point"}
}