{
  "type": "Feature",
  "properties": {
    "iso:country":"IT",
    "sg:address":"16043 Chiavari",
    "sg:city":"Chiavari",
    "sg:orig_category":"Servizi E Lavori Industria Della Gomma",
    "sg:phone":"+39 0185 382043",
    "sg:postcode":"16043",
    "sg:province":"Genova",
    "wof:name":"F.lli Scotto Gomme",
    "wof:placetype":"venue"
},
  "geometry": {"coordinates":[9.3465,44.335617],"type":"Point"}
}