{
  "type": "Feature",
  "properties": {
    "addr:full":"142, Via Roma 50063 Figline Valdarno Figline Valdarno Firenze 50063",
    "addr:housenumber":"142",
    "addr:postcode":"50063;50063",
    "addr:street":"Via Roma;Valdarno",
    "iso:country":"IT",
    "sg:address":"142, Via Roma 50063 Figline Valdarno",
    "sg:city":"Figline Valdarno",
    "sg:classifiers":[
        {
            "category":"Shopping",
            "subcategory":"Clothing, Apparel, & Fashions",
            "type":"Retail Goods"
        }
    ],
    "sg:phone":"+39 39055959368",
    "sg:postcode":"50063",
    "sg:province":"Firenze",
    "sg:tags":[
        "clothes"
    ],
    "wof:name":"Laba Srl",
    "wof:placetype":"venue"
},
  "geometry": {"coordinates":[11.463697,43.625587],"type":"Point"}
}