{
  "type": "Feature",
  "properties": {
    "iso:country":"IT",
    "sg:address":"00185 Roma",
    "sg:city":"Roma",
    "sg:orig_category":"Pubblica Amministrazione",
    "sg:phone":"+39 06 4620 3905",
    "sg:postcode":"00185",
    "sg:province":"Roma",
    "wof:name":"Commissariato Viminale",
    "wof:placetype":"venue"
},
  "geometry": {"coordinates":[12.4990987778,41.8985443115],"type":"Point"}
}