{
  "type": "Feature",
  "properties": {
    "iso:country":"IT",
    "sg:address":"40024 Castel San Pietro Terme",
    "sg:city":"Castel San Pietro Terme",
    "sg:orig_category":"Arredamenti - Vendita Al Dettaglio",
    "sg:phone":"+39 051 945216",
    "sg:postcode":"40024",
    "sg:province":"Bologna",
    "wof:name":"Mobili Baldazzi",
    "wof:placetype":"venue"
},
  "geometry": {"coordinates":[11.546265,44.418331],"type":"Point"}
}