{
  "type": "Feature",
  "properties": {
    "iso:country":"IT",
    "sg:address":"40057 Cadriano",
    "sg:orig_category":"Forniture Per Attivita' Industriali",
    "sg:phone":"+39 051 765028",
    "sg:postcode":"40057",
    "sg:province":"Bologna",
    "wof:name":"Cebora",
    "wof:placetype":"venue"
},
  "geometry": {"coordinates":[11.3908996582,44.552230835],"type":"Point"}
}