{
  "type": "Feature",
  "properties": {
    "iso:country":"IT",
    "sg:address":"20149 Milano",
    "sg:city":"Milano",
    "sg:orig_category":"Forniture Per Agricoltura E Zootecnia. Prodotti Chimici Secondari. Macchine E Forniture Per Ecologia E Smaltimento Rifiuti",
    "sg:phone":"+39 02 319131",
    "sg:postcode":"20149",
    "sg:province":"Milano",
    "wof:name":"Aventis Cropscience Italia Spa",
    "wof:placetype":"venue"
},
  "geometry": {"coordinates":[9.1524648666,45.4840507507],"type":"Point"}
}