{
  "type": "Feature",
  "properties": {
    "iso:country":"IT",
    "sg:address":"21059 Viggiu'",
    "sg:orig_category":"Macchine, Impianti Ed Attrezzature Industria Chimica",
    "sg:phone":"+39 0332 856909",
    "sg:postcode":"21059",
    "sg:province":"Varese",
    "wof:name":"O.m.g.m.",
    "wof:placetype":"venue"
},
  "geometry": {"coordinates":[8.891466,45.870556],"type":"Point"}
}