{
  "type": "Feature",
  "properties": {
    "iso:country":"IT",
    "sg:address":"20032 Cormano",
    "sg:city":"Cormano",
    "sg:orig_category":"Trattamenti Termici E Superficiali Metalli, Galvanotecnica",
    "sg:phone":"+39 02 615 1617",
    "sg:postcode":"20032",
    "sg:province":"Milano",
    "wof:name":"Annoscia Metallizzazioni Di Andrea E Danilo Snc",
    "wof:placetype":"venue"
},
  "geometry": {"coordinates":[9.16115,45.538113],"type":"Point"}
}