{
  "type": "Feature",
  "properties": {
    "iso:country":"IT",
    "sg:address":"42, Via Piave 62012 Civitanova Marche",
    "sg:city":"Civitanova Marche",
    "sg:classifiers":[
        {
            "category":"Manufacturing",
            "subcategory":"Metals",
            "type":"Manufacturing & Wholesale Goods"
        }
    ],
    "sg:phone":"+39 0733 815074",
    "sg:postcode":"62012",
    "sg:province":"Macerata",
    "sg:tags":[
        "metallurgy",
        "metalworking"
    ],
    "wof:name":"Quadri Umberto (s.p.a.)",
    "wof:placetype":"venue"
},
  "geometry": {"coordinates":[13.730682373,43.3036422729],"type":"Point"}
}