{
  "type": "Feature",
  "properties": {
    "addr:full":"37135 Verona Verona Verona 37135",
    "addr:postcode":"37135;37135",
    "iso:country":"IT",
    "sg:address":"37135 Verona",
    "sg:city":"Verona",
    "sg:orig_category":"Motori Ed Organi Di Trasmissione. Ricambi E Componenti Dei Mezzi Di Trasporto",
    "sg:phone":"+39 045 820 0435",
    "sg:postcode":"37135",
    "sg:province":"Verona",
    "wof:name":"La Marmitta Snc",
    "wof:placetype":"venue"
},
  "geometry": {"coordinates":[10.9747571945,45.4088096619],"type":"Point"}
}