{
  "type": "Feature",
  "properties": {
    "iso:country":"IT",
    "sg:address":"91026 Mazara Del Vallo",
    "sg:city":"Mazara del Vallo",
    "sg:orig_category":"Manufacturers: Prefabbricati",
    "sg:phone":"+39 0923 908296",
    "sg:postcode":"91026",
    "sg:province":"Trapani",
    "wof:name":"Trivelsicilia Di Castelli Domenico & C. Snc",
    "wof:placetype":"venue"
},
  "geometry": {"coordinates":[12.644587,37.738953],"type":"Point"}
}