{
  "type": "Feature",
  "properties": {
    "addr:full":"16137 Genova Genova Genova 16137",
    "addr:postcode":"16137;16137",
    "iso:country":"IT",
    "sg:address":"16137 Genova",
    "sg:city":"Genova",
    "sg:orig_category":"Prodotti Chimici Secondari. Servizi E Lavori Per Ecologia E Smaltimento Rifiuti. Macchine E Forniture Per Ecologia E Smaltimento Rifiuti",
    "sg:phone":"+39 010 839 1671",
    "sg:postcode":"16137",
    "sg:province":"Genova",
    "sg:website":"http://www.cattanizanelli.it",
    "wof:name":"Cattani E Zanelli Snc",
    "wof:placetype":"venue"
},
  "geometry": {"coordinates":[8.943854332,44.4322433472],"type":"Point"}
}