{
  "type": "Feature",
  "properties": {
    "iso:country":"IT",
    "sg:address":"93100 Caltanissetta",
    "sg:city":"Caltanissetta",
    "sg:orig_category":"Arredo Cucina Ed Elettrodomestici. Elettrodomestici",
    "sg:phone":"+39 0934 565608",
    "sg:postcode":"93100",
    "sg:province":"Caltanissetta",
    "wof:name":"Tecno Servizi Di F.sco Guccione",
    "wof:placetype":"venue"
},
  "geometry": {"coordinates":[14.030454,37.454559],"type":"Point"}
}