{
  "type": "Feature",
  "properties": {
    "addr:full":"87, Viale Crispi Francesco 36100 Vicenza Vicenza Vicenza 36100",
    "addr:housenumber":"87",
    "addr:postcode":"36100;36100",
    "addr:street":"Viale Crispi Francesco",
    "iso:country":"IT",
    "sg:address":"87, Viale Crispi Francesco 36100 Vicenza",
    "sg:city":"Vicenza",
    "sg:classifiers":[
        {
            "category":"Professional",
            "subcategory":"Engineering",
            "type":"Services"
        }
    ],
    "sg:phone":"+39 0444 569273",
    "sg:postcode":"36100",
    "sg:province":"Vicenza",
    "sg:tags":[
        "machine",
        "-",
        "mechanical"
    ],
    "wof:name":"Polazzo Grandimpianti S.r.l.- Soc. Uninominale",
    "wof:placetype":"venue"
},
  "geometry": {"coordinates":[11.526389,45.575279],"type":"Point"}
}