{
  "type": "Feature",
  "properties": {
    "iso:country":"IT",
    "sg:address":"34, Via Dei Vecchi 01100 Viterbo",
    "sg:city":"Viterbo",
    "sg:classifiers":[
        {
            "category":"Manufacturing",
            "subcategory":"Tools & Machinery",
            "type":"Manufacturing & Wholesale Goods"
        }
    ],
    "sg:phone":"+39 0761 227288",
    "sg:postcode":"01100",
    "sg:province":"Viterbo",
    "sg:tags":[
        "environment",
        "equipment",
        "-"
    ],
    "wof:name":"Com. Alberto Ciorba Srl",
    "wof:placetype":"venue"
},
  "geometry": {"coordinates":[12.064167,42.430279],"type":"Point"}
}