{
  "type": "Feature",
  "properties": {
    "iso:country":"IT",
    "sg:address":"10094 Giaveno",
    "sg:city":"Giaveno",
    "sg:orig_category":"Servizi E Lavori Per Industria Alimentare E Bevande. Servizi E Lavori Per Abbigliamento E Pelletterie. Servizi E Lavori Per Arredamento E Industria Del Legno. Servizi Vari Di Interesse Pubblico",
    "sg:phone":"+39 011 936 4991",
    "sg:postcode":"10094",
    "sg:province":"Torino",
    "wof:name":"Il Sognacose Di Cavallero Marina E C. Sas",
    "wof:placetype":"venue"
},
  "geometry": {"coordinates":[7.359146,45.040833],"type":"Point"}
}