{
  "type": "Feature",
  "properties": {
    "iso:country":"IT",
    "sg:address":"31058 Susegana",
    "sg:city":"Susegana",
    "sg:orig_category":"Macchine, Impianti Ed Attrezzature Industria Chimica. Macchine Ed Impianti Per Edilizia E Lavori Pubblici",
    "sg:phone":"+39 0438 738411",
    "sg:postcode":"31058",
    "sg:province":"Treviso",
    "sg:website":"http://www.cogefor.it",
    "wof:name":"Co.ge.for. Srl",
    "wof:placetype":"venue"
},
  "geometry": {"coordinates":[12.261415,45.842098],"type":"Point"}
}