{
  "type": "Feature",
  "properties": {
    "addr:full":"1, Via Tajani Filippo 20133 Milano Milano Milano 20133",
    "addr:postcode":"20133;20133",
    "addr:street":"Via Tajani Filippo",
    "iso:country":"IT",
    "sg:address":"1, Via Tajani Filippo 20133 Milano",
    "sg:city":"Milano",
    "sg:classifiers":[
        {
            "category":"Shopping",
            "subcategory":"Clothing, Apparel, & Fashions",
            "type":"Retail Goods"
        }
    ],
    "sg:phone":"+39 02 7104 0332",
    "sg:postcode":"20133",
    "sg:province":"Milano",
    "sg:tags":[
        "clothes"
    ],
    "wof:name":"Marni Srl",
    "wof:placetype":"venue"
},
  "geometry": {"coordinates":[9.23667,45.473137],"type":"Point"}
}