{
  "type": "Feature",
  "properties": {
    "addr:full":"36057 Arcugnano Arcugnano Vicenza 36057",
    "addr:postcode":"36057;36057",
    "iso:country":"IT",
    "sg:address":"36057 Arcugnano",
    "sg:city":"Arcugnano",
    "sg:orig_category":"Lavorazioni Metalli, Stampaggio E Saldatura",
    "sg:phone":"+39 0444 566466",
    "sg:postcode":"36057",
    "sg:province":"Vicenza",
    "wof:name":"Zaccaria Bruno Srl",
    "wof:placetype":"venue"
},
  "geometry": {"coordinates":[11.510608,45.509506],"type":"Point"}
}