{
  "type": "Feature",
  "properties": {
    "iso:country":"IT",
    "sg:address":"M.-pacher-str. 22; Pfalzen; 39030",
    "sg:classifiers":[
        {
            "category":"Banks & Credit Unions",
            "subcategory":"Bank",
            "type":"Services"
        }
    ],
    "sg:phone":"+39 0474 528119",
    "sg:postcode":"39030",
    "sg:province":"Bolzano/Bozen",
    "wof:name":"Raiffeisen Zentralkasse, Bruneck",
    "wof:placetype":"venue"
},
  "geometry": {"coordinates":[11.358005,46.496716],"type":"Point"}
}