{
  "type": "Feature",
  "properties": {
    "iso:country":"IT",
    "sg:address":"20124 Milano",
    "sg:city":"Milano",
    "sg:orig_category":"Servizi E Lavori Per Edilizia E Lavori Pubblici. Telecomunicazioni E Telefonia, Impianti, Apparecchi E Servizi. Acqua, Luce, Gas E Societa' Di Esercizio Pubblico",
    "sg:phone":"+39 02 202 0451",
    "sg:postcode":"20124",
    "sg:province":"Milano",
    "sg:website":"http://www.e-via.it",
    "wof:name":"E-via Spa",
    "wof:placetype":"venue"
},
  "geometry": {"coordinates":[9.204427,45.478378],"type":"Point"}
}