{
  "type": "Feature",
  "properties": {
    "iso:country":"IT",
    "sg:address":"17021 Alassio",
    "sg:city":"Alassio",
    "sg:classifiers":[
        {
            "category":"Restaurant",
            "type":"Food & Drink"
        }
    ],
    "sg:phone":"+39 0182 640821",
    "sg:postcode":"17021",
    "sg:province":"Savona",
    "sg:tags":[
        "auxiliary",
        "entertainment",
        "premises",
        "related",
        "catering",
        "similar",
        "public",
        "restaurants"
    ],
    "sg:website":"http://www.hotelrosa.it",
    "wof:name":"Hotel Rosa",
    "wof:placetype":"venue"
},
  "geometry": {"coordinates":[8.16117,44.017982],"type":"Point"}
}