{
  "type": "Feature",
  "properties": {
    "addr:full":"20034 Paina Paina Milano 20034",
    "addr:postcode":"20034;20034",
    "iso:country":"IT",
    "sg:address":"20034 Paina",
    "sg:city":"Paina",
    "sg:orig_category":"Forniture Per Abbigliamento E Pelletterie",
    "sg:phone":"+39 036 286 2501",
    "sg:postcode":"20034",
    "sg:province":"Milano",
    "wof:name":"Cit Piuma S.r.l",
    "wof:placetype":"venue"
},
  "geometry": {"coordinates":[9.1999540329,45.6718482971],"type":"Point"}
}