{
  "type": "Feature",
  "properties": {
    "addr:full":"43011 Busseto Busseto Parma 43011",
    "addr:postcode":"43011;43011",
    "iso:country":"IT",
    "sg:address":"43011 Busseto",
    "sg:city":"Busseto",
    "sg:orig_category":"Forniture Per Attivita' Industriali",
    "sg:phone":"+39 0524 930128",
    "sg:postcode":"43011",
    "sg:province":"Parma",
    "wof:name":"Lmpt Di Fava Bruno & Uccelli Luciana S.n.c.",
    "wof:placetype":"venue"
},
  "geometry": {"coordinates":[10.0504932404,44.9597320557],"type":"Point"}
}