{
  "type": "Feature",
  "properties": {
    "iso:country":"IT",
    "sg:address":"Corso Vittorio Emanuele 45, 63038 Ripatransone, Ap",
    "sg:city":"Ripatransone",
    "sg:classifiers":[
        {
            "category":"Banks & Credit Unions",
            "subcategory":"Bank",
            "type":"Services"
        }
    ],
    "sg:postcode":"63038",
    "sg:province":"Ascoli Piceno",
    "wof:name":"Banca Di Credito Cooperativo Di Ripatransone (provincia Di Ascoli Piceno)",
    "wof:placetype":"venue"
},
  "geometry": {"coordinates":[13.574977,42.8554],"type":"Point"}
}