{
  "type": "Feature",
  "properties": {
    "addr:full":"53036 Poggibonsi Poggibonsi Siena 53036",
    "addr:postcode":"53036;53036",
    "iso:country":"IT",
    "sg:address":"53036 Poggibonsi",
    "sg:city":"Poggibonsi",
    "sg:orig_category":"Macchine, Impianti Ed Attrezzature Per Industria Alimentare E Bevande",
    "sg:phone":"+39 0577 936507",
    "sg:postcode":"53036",
    "sg:province":"Siena",
    "wof:name":"Borghesi Fratelli",
    "wof:placetype":"venue"
},
  "geometry": {"coordinates":[11.145561,43.469612],"type":"Point"}
}