{
  "type": "Feature",
  "properties": {
    "iso:country":"IT",
    "sg:address":"00142 Roma",
    "sg:city":"Roma",
    "sg:orig_category":"Macchine E Forniture Per Ecologia E Smaltimento Rifiuti. Termotecnica E Riscaldamento, Apparecchiature E Servizi",
    "sg:phone":"+39 06 543 1214",
    "sg:postcode":"00142",
    "sg:province":"Roma",
    "wof:name":"Downstream Advanced Investigations Srl",
    "wof:placetype":"venue"
},
  "geometry": {"coordinates":[12.480938,41.845596],"type":"Point"}
}