{
  "type": "Feature",
  "properties": {
    "iso:country":"IT",
    "sg:address":"23, Via Scarfoglio Eduardo 80125 Napoli",
    "sg:city":"Napoli",
    "sg:classifiers":[
        {
            "category":"Shopping",
            "type":"Retail Goods"
        }
    ],
    "sg:phone":"+39 081 570 3768",
    "sg:postcode":"80125",
    "sg:province":"Napoli",
    "sg:tags":[
        "finished",
        "-",
        "metallic"
    ],
    "wof:name":"Carrannante S.r.l.",
    "wof:placetype":"venue"
},
  "geometry": {"coordinates":[14.2516355515,40.84009552],"type":"Point"}
}