{
  "type": "Feature",
  "properties": {
    "iso:country":"IT",
    "sg:address":"00188 Roma",
    "sg:city":"Roma",
    "sg:orig_category":"Servizi Per Lo Sport E Il Tempo Libero. Servizi Al Turismo",
    "sg:phone":"+39 06 3361 3375",
    "sg:postcode":"00188",
    "sg:province":"Roma",
    "wof:name":"Jolly Sporting Club Srl",
    "wof:placetype":"venue"
},
  "geometry": {"coordinates":[12.485881,42.003376],"type":"Point"}
}