{
  "type": "Feature",
  "properties": {
    "iso:country":"IT",
    "sg:address":"46019 Viadana",
    "sg:city":"Viadana",
    "sg:classifiers":[
        {
            "category":"Home & Garden",
            "subcategory":"Kitchen Supply",
            "type":"Retail Goods"
        }
    ],
    "sg:phone":"+39 0375 781089",
    "sg:postcode":"46019",
    "sg:province":"Mantova",
    "sg:tags":[
        "utensil",
        "houseware"
    ],
    "wof:name":"Borettini Giordano Srl",
    "wof:placetype":"venue"
},
  "geometry": {"coordinates":[10.525985,44.944809],"type":"Point"}
}