{
  "type": "Feature",
  "properties": {
    "iso:country":"IT",
    "sg:address":"10128 Torino",
    "sg:city":"Torino",
    "sg:orig_category":"Cine-foto-ottica. Articoli Medico-sanitari Ed Ortopedici",
    "sg:phone":"+39 011 538008",
    "sg:postcode":"10128",
    "sg:province":"Torino",
    "wof:name":"Ganio Di Bondi E Bertolino (s.n.c.)",
    "wof:placetype":"venue"
},
  "geometry": {"coordinates":[7.674986,45.061268],"type":"Point"}
}