{
  "type": "Feature",
  "properties": {
    "iso:country":"IT",
    "sg:address":"V. Fosso Rio - Torre Matigge Di Trevi 06039 Trevi",
    "sg:city":"Matigge",
    "sg:classifiers":[
        {
            "category":"Food & Beverages",
            "subcategory":"Groceries & Convenience Stores",
            "type":"Retail Goods"
        }
    ],
    "sg:phone":"+39 0742 391631",
    "sg:postcode":"06039",
    "sg:province":"Perugia",
    "sg:tags":[
        "product",
        "related"
    ],
    "sg:website":"http://www.oliotrevi.it",
    "wof:name":"Societ\u00c0 Agricola Trevi",
    "wof:placetype":"venue"
},
  "geometry": {"coordinates":[12.3891716003,43.1107025146],"type":"Point"}
}