{
  "type": "Feature",
  "properties": {
    "iso:country":"IT",
    "sg:address":"56/a, Via Beschi Costantino 00125 Roma",
    "sg:city":"Roma",
    "sg:classifiers":[
        {
            "category":"Manufacturing",
            "subcategory":"Chemicals & Compounds",
            "type":"Manufacturing & Wholesale Goods"
        }
    ],
    "sg:phone":"+39 06 5235 1933",
    "sg:postcode":"00125",
    "sg:province":"Roma",
    "sg:tags":[
        "chemistry"
    ],
    "wof:name":"Tecnotrasfer Di Raffaele De Bellis E C.snc",
    "wof:placetype":"venue"
},
  "geometry": {"coordinates":[12.482325,41.895466],"type":"Point"}
}