{
  "type": "Feature",
  "properties": {
    "iso:country":"IT",
    "sg:address":"Via Palestro,7/9 50013 Campi Bisenzio",
    "sg:city":"Campi Bisenzio",
    "sg:classifiers":[
        {
            "category":"Shopping",
            "subcategory":"Shoes",
            "type":"Retail Goods"
        }
    ],
    "sg:phone":"+39 055 895 3158",
    "sg:postcode":"50013",
    "sg:province":"Firenze",
    "sg:tags":[
        "ski-boots",
        "ski"
    ],
    "wof:name":"Calzaturificio San Bernardo Di Carlo Biagiotti S.n.c",
    "wof:placetype":"venue"
},
  "geometry": {"coordinates":[11.120631,43.824512],"type":"Point"}
}