{
  "type": "Feature",
  "properties": {
    "iso:country":"IT",
    "sg:address":"35123 Padova",
    "sg:city":"Padova",
    "sg:classifiers":[
        {
            "category":"Health Services",
            "subcategory":"Health Practitioner",
            "type":"Services"
        }
    ],
    "sg:phone":"+39 049 664484",
    "sg:postcode":"35123",
    "sg:province":"Padova",
    "sg:tags":[
        "medici"
    ],
    "wof:name":"Radiologia Specialistica Prof. Stelio Vio (s.a.s.)",
    "wof:placetype":"venue"
},
  "geometry": {"coordinates":[11.8782739639,45.397102356],"type":"Point"}
}