{
  "type": "Feature",
  "properties": {
    "iso:country":"IT",
    "sg:address":"Via Zona Industriale 84021 Buccino",
    "sg:city":"Buccino",
    "sg:classifiers":[
        {
            "category":"Food & Beverages",
            "subcategory":"Groceries & Convenience Stores",
            "type":"Retail Goods"
        }
    ],
    "sg:phone":"+39 0828 957065",
    "sg:postcode":"84021",
    "sg:province":"Salerno",
    "sg:tags":[
        "product",
        "related"
    ],
    "wof:name":"Consorzio Bioitalia Alimentare",
    "wof:placetype":"venue"
},
  "geometry": {"coordinates":[14.765912056,40.6779556274],"type":"Point"}
}