{
  "type": "Feature",
  "properties": {
    "iso:country":"IT",
    "sg:address":"40060 Osteria Grande",
    "sg:city":"Osteria Grande",
    "sg:orig_category":"Macchine Ed Impianti Per Edilizia E Lavori Pubblici",
    "sg:phone":"+39 051 945085",
    "sg:postcode":"40060",
    "sg:province":"Bologna",
    "wof:name":"Mecbo (s.r.l.)",
    "wof:placetype":"venue"
},
  "geometry": {"coordinates":[11.384359,44.475983],"type":"Point"}
}