{
  "type": "Feature",
  "properties": {
    "addr:full":"Piazza Roma 13; Stagno Lombardo",
    "addr:housenumber":"13",
    "addr:street":"Piazza Roma",
    "iso:country":"IT",
    "sg:address":"Piazza Roma 13; Stagno Lombardo",
    "sg:classifiers":[
        {
            "category":"Banks & Credit Unions",
            "subcategory":"Bank",
            "type":"Services"
        }
    ],
    "sg:phone":"+39 0372 57034",
    "wof:name":"Banca Popolare Di Cremona Scarl",
    "wof:placetype":"venue"
},
  "geometry": {"coordinates":[10.087814,45.073055],"type":"Point"}
}