{
  "type": "Feature",
  "properties": {
    "iso:country":"IT",
    "sg:address":"Via Di Vittorio 21 20060 Vignate",
    "sg:city":"Vignate",
    "sg:classifiers":[
        {
            "category":"Home & Garden",
            "subcategory":"Building Materials",
            "type":"Retail Goods"
        }
    ],
    "sg:phone":"+39 02 951271",
    "sg:postcode":"20060",
    "sg:province":"Milano",
    "sg:tags":[
        "plate",
        "lathe",
        "face"
    ],
    "sg:website":"www.igv1.com",
    "wof:name":"I.g.v. Spa",
    "wof:placetype":"venue"
},
  "geometry": {"coordinates":[9.3327007294,45.5030174255],"type":"Point"}
}