{
  "type": "Feature",
  "properties": {
    "iso:country":"IT",
    "sg:address":"249, Via Sempione 20016 Pero",
    "sg:city":"Pero",
    "sg:classifiers":[
        {
            "category":"Professional",
            "subcategory":"Engineering",
            "type":"Services"
        }
    ],
    "sg:phone":"+39 39023534024",
    "sg:postcode":"20016",
    "sg:province":"Milano",
    "sg:tags":[
        "machine",
        "-",
        "mechanical"
    ],
    "wof:name":"T.s.t. Trattamenti Termici Speciali (s.r.l.)",
    "wof:placetype":"venue"
},
  "geometry": {"coordinates":[9.082224,45.514225],"type":"Point"}
}