{
  "type": "Feature",
  "properties": {
    "iso:country":"IT",
    "sg:address":"41013 Castelfranco Emilia",
    "sg:city":"Castelfranco Emilia",
    "sg:orig_category":"Pompe. Macchine, Strumenti Ed Apparecchi Per Attivita' Industriali",
    "sg:phone":"+39 059 927676",
    "sg:postcode":"41013",
    "sg:province":"Modena",
    "wof:name":"Scova System Srl",
    "wof:placetype":"venue"
},
  "geometry": {"coordinates":[11.0349063873,44.6011390686],"type":"Point"}
}