{
  "type": "Feature",
  "properties": {
    "addr:full":"Localita Prataroni 01034 Civita Castellana Viterbo 01034",
    "addr:postcode":"01034;01034",
    "addr:street":"Localita Prataroni",
    "iso:country":"IT",
    "sg:address":"Localita Prataroni 01034 Civita Castellana",
    "sg:classifiers":[
        {
            "category":"Building & Trades",
            "subcategory":"Plumbing",
            "type":"Services"
        }
    ],
    "sg:phone":"+39 0761 542144",
    "sg:postcode":"01034",
    "sg:province":"Viterbo",
    "sg:tags":[
        "fixtures",
        "enamelled"
    ],
    "sg:website":"www.altheaceramica.com",
    "wof:name":"Ceramica Althea Srl",
    "wof:placetype":"venue"
},
  "geometry": {"coordinates":[12.1048536301,42.4173812866],"type":"Point"}
}