{
  "type": "Feature",
  "properties": {
    "iso:country":"IT",
    "sg:address":"89/93, Via Pitteri Riccardo 20134 Milano",
    "sg:city":"Milano",
    "sg:classifiers":[
        {
            "category":"Parking",
            "subcategory":"Lot",
            "type":"Transportation"
        }
    ],
    "sg:phone":"+39 39022152626",
    "sg:postcode":"20134",
    "sg:province":"Milano",
    "sg:tags":[
        "transport",
        "road"
    ],
    "wof:name":"Franzosini Luciano S.p.a.",
    "wof:placetype":"venue"
},
  "geometry": {"coordinates":[9.246046,45.479149],"type":"Point"}
}