{
  "type": "Feature",
  "properties": {
    "iso:country":"IT",
    "sg:address":"25125 Brescia",
    "sg:city":"Brescia",
    "sg:orig_category":"Macchine, Impianti Ed Attrezzature Industria Chimica. Attrezzature E Forniture Per Officine Riparazione E Servizi Ausiliari",
    "sg:phone":"+39 030 354 2068",
    "sg:postcode":"25125",
    "sg:province":"Brescia",
    "wof:name":"Fa & Spe Di Facchetti R. E Speriani D. S.n.c.",
    "wof:placetype":"venue"
},
  "geometry": {"coordinates":[10.199821,45.530464],"type":"Point"}
}