{
  "type": "Feature",
  "properties": {
    "iso:country":"IT",
    "sg:address":"Regione Caseppa 10090 Rivalba",
    "sg:city":"Rivalba",
    "sg:classifiers":[
        {
            "category":"Professional",
            "subcategory":"Engineering",
            "type":"Services"
        }
    ],
    "sg:phone":"+39 011 960 4525",
    "sg:postcode":"10090",
    "sg:province":"Torino",
    "sg:tags":[
        "machine",
        "-",
        "mechanical"
    ],
    "wof:name":"Officine Meccaniche Musso Di Musso Armando & C. S.a.s.",
    "wof:placetype":"venue"
},
  "geometry": {"coordinates":[7.894105,45.112316],"type":"Point"}
}