{
  "type": "Feature",
  "properties": {
    "addr:full":"18, Via Giaveno 10040 Rivalta Di Torino Rivalta di Torino Torino 10040",
    "addr:postcode":"10040;10040",
    "addr:street":"Via Giaveno",
    "iso:country":"IT",
    "sg:address":"18, Via Giaveno 10040 Rivalta Di Torino",
    "sg:city":"Rivalta di Torino",
    "sg:classifiers":[
        {
            "category":"Farming",
            "subcategory":"Livestock Farm",
            "type":"Manufacturing & Wholesale Goods"
        }
    ],
    "sg:phone":"+39 011 900 2092",
    "sg:postcode":"10040",
    "sg:province":"Torino",
    "sg:tags":[
        "agriculture"
    ],
    "wof:name":"S.v.b. (s.p.a.)",
    "wof:placetype":"venue"
},
  "geometry": {"coordinates":[7.504227,45.013271],"type":"Point"}
}