{
  "type": "Feature",
  "properties": {
    "addr:full":"1, Via Mons. Giulio Babolin 35024 Bovolenta Bovolenta Padova 35024",
    "addr:postcode":"35024;35024",
    "addr:street":"Via Mons. Giulio Babolin",
    "iso:country":"IT",
    "sg:address":"1, Via Mons. Giulio Babolin 35024 Bovolenta",
    "sg:city":"Bovolenta",
    "sg:classifiers":[
        {
            "category":"Shopping",
            "subcategory":"Crafts & Fabrics",
            "type":"Retail Goods"
        }
    ],
    "sg:phone":"+39 049 538 6614",
    "sg:postcode":"35024",
    "sg:province":"Padova",
    "wof:name":"Emmetre Tintolavanderie Industriali (s.r.l.)",
    "wof:placetype":"venue"
},
  "geometry": {"coordinates":[11.8765888214,45.4095687866],"type":"Point"}
}