{
  "type": "Feature",
  "properties": {
    "addr:full":"2, Via Matteotti 28070 Garbagna Novarese Garbagna Novarese Novara 28070",
    "addr:postcode":"28070;28070",
    "addr:street":"Via Matteotti;Novarese",
    "iso:country":"IT",
    "sg:address":"2, Via Matteotti 28070 Garbagna Novarese",
    "sg:city":"Garbagna Novarese",
    "sg:classifiers":[
        {
            "category":"Manufacturing",
            "subcategory":"Metals",
            "type":"Manufacturing & Wholesale Goods"
        }
    ],
    "sg:phone":"+39 0321 884966",
    "sg:postcode":"28070",
    "sg:province":"Novara",
    "sg:tags":[
        "processing"
    ],
    "wof:name":"Ferri (s.r.l.)",
    "wof:placetype":"venue"
},
  "geometry": {"coordinates":[8.6615028381,45.381652832],"type":"Point"}
}