{
  "type": "Feature",
  "properties": {
    "iso:country":"IT",
    "sg:address":"Ss Villagio Mose 115; Agrigento; 92100",
    "sg:city":"Agrigento",
    "sg:classifiers":[
        {
            "category":"Banks & Credit Unions",
            "subcategory":"Bank",
            "type":"Services"
        }
    ],
    "sg:phone":"+39 0922 607726",
    "sg:postcode":"92100",
    "sg:province":"Agrigento",
    "wof:name":"Credito Emiliano Spa",
    "wof:placetype":"venue"
},
  "geometry": {"coordinates":[13.578402,37.30899],"type":"Point"}
}