{
  "type": "Feature",
  "properties": {
    "addr:full":"26, Via Scalabrini Monsignor Gian Battista 25086 Rezzato Rezzato Brescia 25086",
    "addr:postcode":"25086;25086",
    "addr:street":"Via Scalabrini Monsignor Gian Battista",
    "iso:country":"IT",
    "sg:address":"26, Via Scalabrini Monsignor Gian Battista 25086 Rezzato",
    "sg:city":"Rezzato",
    "sg:classifiers":[
        {
            "category":"Professional",
            "subcategory":"Engineering",
            "type":"Services"
        }
    ],
    "sg:phone":"+39 030 279 1445",
    "sg:postcode":"25086",
    "sg:province":"Brescia",
    "sg:tags":[
        "machine",
        "-",
        "mechanical"
    ],
    "wof:name":"Arcom (s.r.l.)",
    "wof:placetype":"venue"
},
  "geometry": {"coordinates":[10.222958,45.539829],"type":"Point"}
}