{
  "type": "Feature",
  "properties": {
    "iso:country":"IT",
    "sg:address":"90143 Palermo",
    "sg:city":"Palermo",
    "sg:classifiers":[
        {
            "category":"Bars & Pubs",
            "subcategory":"Champagne Bar",
            "type":"Food & Drink"
        }
    ],
    "sg:phone":"+39 091 308236",
    "sg:postcode":"90143",
    "sg:province":"Palermo",
    "sg:tags":[
        "caffe'",
        "e"
    ],
    "wof:name":"Bar Alaimo Di Bonanno Francesco",
    "wof:placetype":"venue"
},
  "geometry": {"coordinates":[13.350065,38.141975],"type":"Point"}
}