{
  "type": "Feature",
  "properties": {
    "addr:full":"2 Largo Porta Nuova, 24122 Bergamo Bergamo Bergamo 24122",
    "addr:housenumber":"2",
    "addr:postcode":"24122;24122",
    "addr:street":"Largo Porta Nuova",
    "iso:country":"IT",
    "sg:address":"2 Largo Porta Nuova, 24122 Bergamo",
    "sg:city":"Bergamo",
    "sg:classifiers":[
        {
            "category":"Banks & Credit Unions",
            "subcategory":"Financial Services",
            "type":"Services"
        }
    ],
    "sg:phone":"+39 39035393111",
    "sg:postcode":"24122",
    "sg:province":"Bergamo",
    "sg:tags":[
        "banking",
        "finance",
        "insurance"
    ],
    "wof:name":"Credito Bergamasco",
    "wof:placetype":"venue"
},
  "geometry": {"coordinates":[9.6703023911,45.6940765381],"type":"Point"}
}