{
  "type": "Feature",
  "properties": {
    "addr:full":"1/d, Via Madonna Delle Grazie 31030 Cison Di Valmarino Cison di Valmarino Treviso 31030",
    "addr:housenumber":"1 / d;di valmarino",
    "addr:postcode":"31030;31030",
    "addr:street":"Via Madonna Delle Grazie;Di Valmarino",
    "iso:country":"IT",
    "sg:address":"1/d, Via Madonna Delle Grazie 31030 Cison Di Valmarino",
    "sg:city":"Cison di Valmarino",
    "sg:classifiers":[
        {
            "category":"Home & Garden",
            "subcategory":"Home Furnishings",
            "type":"Retail Goods"
        }
    ],
    "sg:phone":"+39 0438 975081",
    "sg:postcode":"31030",
    "sg:province":"Treviso",
    "sg:tags":[
        "household"
    ],
    "wof:name":"Mobil Linea Srl",
    "wof:placetype":"venue"
},
  "geometry": {"coordinates":[12.242072,45.666286],"type":"Point"}
}