{
  "type": "Feature",
  "properties": {
    "iso:country":"IT",
    "sg:address":"4, Via Oriani Alfredo 20122 Milano",
    "sg:city":"Milano",
    "sg:classifiers":[
        {
            "category":"Professional",
            "subcategory":"Advertising",
            "type":"Services"
        }
    ],
    "sg:phone":"+39 02 5830 9853",
    "sg:postcode":"20122",
    "sg:province":"Milano",
    "sg:tags":[
        "communication",
        "medium"
    ],
    "wof:name":"Strategia D'immagine (s.r.l.)",
    "wof:placetype":"venue"
},
  "geometry": {"coordinates":[9.194278,45.452492],"type":"Point"}
}