{
  "type": "Feature",
  "properties": {
    "addr:full":"10029 Villastellone Villastellone Torino 10029",
    "addr:housenumber":"10029",
    "addr:postcode":"10029",
    "addr:street":"Villastellone Villastellone",
    "iso:country":"IT",
    "sg:address":"10029 Villastellone",
    "sg:city":"Villastellone",
    "sg:classifiers":[
        {
            "category":"Manufacturing",
            "subcategory":"Tools & Machinery",
            "type":"Manufacturing & Wholesale Goods"
        }
    ],
    "sg:phone":"+39 011 969 6013",
    "sg:postcode":"10029",
    "sg:province":"Torino",
    "sg:tags":[
        "machining",
        "mechanical"
    ],
    "wof:name":"Ag Srl",
    "wof:placetype":"venue"
},
  "geometry": {"coordinates":[7.71664,44.950481],"type":"Point"}
}