{
  "type": "Feature",
  "properties": {
    "addr:full":"16030 Pieve Ligure Pieve Ligure Genova 16030",
    "addr:postcode":"16030;16030",
    "iso:country":"IT",
    "sg:address":"16030 Pieve Ligure",
    "sg:city":"Pieve Ligure",
    "sg:orig_category":"Nautica. Accessori Dei Mezzi Di Trasporto. Servizi Ausiliari Dei Mezzi Di Trasporto",
    "sg:phone":"+39 010 346 0428",
    "sg:postcode":"16030",
    "sg:province":"Genova",
    "wof:name":"Shipco S.a.s. Di Franco Francini E C.",
    "wof:placetype":"venue"
},
  "geometry": {"coordinates":[9.093884,44.374287],"type":"Point"}
}