{
  "type": "Feature",
  "properties": {
    "iso:country":"IT",
    "sg:address":"06084 Bettona",
    "sg:city":"Bettona",
    "sg:orig_category":"Macchine Ed Impianti Per Edilizia E Lavori Pubblici",
    "sg:phone":"+39 075 987028",
    "sg:postcode":"06084",
    "sg:province":"Perugia",
    "wof:name":"Rocchi Srl",
    "wof:placetype":"venue"
},
  "geometry": {"coordinates":[12.493149,43.022881],"type":"Point"}
}