{
  "type": "Feature",
  "properties": {
    "addr:full":"24035 Curno Curno Bergamo 24035",
    "addr:postcode":"24035;24035",
    "iso:country":"IT",
    "sg:address":"24035 Curno",
    "sg:city":"Curno",
    "sg:orig_category":"Forniture Per Edilizia E Lavori Pubblici",
    "sg:phone":"+39 035 615053",
    "sg:postcode":"24035",
    "sg:province":"Bergamo",
    "wof:name":"Beppe Visconti Srl",
    "wof:placetype":"venue"
},
  "geometry": {"coordinates":[9.6186170578,45.694152832],"type":"Point"}
}