{
  "type": "Feature",
  "properties": {
    "iso:country":"IT",
    "sg:address":"00155 Roma",
    "sg:city":"Roma",
    "sg:classifiers":[
        {
            "category":"Manufacturing",
            "subcategory":"Rubber & Plastics",
            "type":"Manufacturing & Wholesale Goods"
        }
    ],
    "sg:phone":"+39 06 229 4435",
    "sg:postcode":"00155",
    "sg:province":"Roma",
    "sg:tags":[
        "activities",
        "product",
        "industrial",
        "articles",
        "supply"
    ],
    "wof:name":"Stalg Di Pallotta Vincenzo",
    "wof:placetype":"venue"
},
  "geometry": {"coordinates":[12.603024,41.901905],"type":"Point"}
}