{
  "type": "Feature",
  "properties": {
    "addr:full":"14100 Asti Asti Asti 14100",
    "addr:postcode":"14100;14100",
    "iso:country":"IT",
    "sg:address":"14100 Asti",
    "sg:city":"Asti",
    "sg:orig_category":"Tessuti E Stoffe. Tessuti Arredamento, Tende E Tappeti. Shopping",
    "sg:phone":"+39 0141 215777",
    "sg:postcode":"14100",
    "sg:province":"Asti",
    "wof:name":"Dezzani G. & Paneati M. Sdf",
    "wof:placetype":"venue"
},
  "geometry": {"coordinates":[8.187995,44.904694],"type":"Point"}
}