{
  "type": "Feature",
  "properties": {
    "iso:country":"IT",
    "sg:address":"26, Via Marchi Vittorio 42100 Reggio Emilia",
    "sg:classifiers":[
        {
            "category":"Home & Garden",
            "subcategory":"Home Furnishings",
            "type":"Retail Goods"
        }
    ],
    "sg:phone":"+39 0522 553452",
    "sg:postcode":"42100",
    "sg:province":"Reggio Nell'Emilia",
    "sg:tags":[
        "household"
    ],
    "wof:name":"La Regginflex Di Fiaccadori Cav.sante & Figli S.n.c.",
    "wof:placetype":"venue"
},
  "geometry": {"coordinates":[10.658411,44.684826],"type":"Point"}
}