{
  "type": "Feature",
  "properties": {
    "iso:country":"IT",
    "sg:address":"97017 S. Croce Camerina",
    "sg:orig_category":"Agenzie Viaggi E Turismo",
    "sg:phone":"+39 0932 825288",
    "sg:postcode":"97017",
    "sg:province":"Ragusa",
    "wof:name":"Azzaro Viaggi Di Azzaro Maria Carmela",
    "wof:placetype":"venue"
},
  "geometry": {"coordinates":[14.524774,36.826206],"type":"Point"}
}