{
  "type": "Feature",
  "properties": {
    "iso:country":"IT",
    "sg:address":"91025 Marsala",
    "sg:city":"Marsala",
    "sg:orig_category":"Tessuti Arredamento, Tende E Tappeti. Forniture Per Edilizia E Lavori Pubblici",
    "sg:phone":"+39 0923 716071",
    "sg:postcode":"91025",
    "sg:province":"Trapani",
    "wof:name":"Tende E Tendaggi Di Ingrassia Caterina & C. Sas",
    "wof:placetype":"venue"
},
  "geometry": {"coordinates":[12.552751,37.832535],"type":"Point"}
}