{
  "type": "Feature",
  "properties": {
    "iso:country":"IT",
    "sg:address":"15100 Alessandria",
    "sg:city":"Alessandria",
    "sg:orig_category":"Internet, Telematica E Audiotex - Servizi",
    "sg:phone":"+39 0131 223435",
    "sg:postcode":"15100",
    "sg:province":"Alessandria",
    "sg:website":"http://www.millenniumgames.it",
    "wof:name":"Millennium Game Srl",
    "wof:placetype":"venue"
},
  "geometry": {"coordinates":[8.619092,44.924477],"type":"Point"}
}