{
  "type": "Feature",
  "properties": {
    "addr:full":"Via Volta 10 42024 Castelnovo Di Sotto Reggio Nell'Emilia 42024",
    "addr:housenumber":"10",
    "addr:postcode":"42024;42024",
    "addr:street":"Via Volta",
    "iso:country":"IT",
    "sg:address":"Via Volta 10 42024 Castelnovo Di Sotto",
    "sg:classifiers":[
        {
            "category":"Food & Beverages",
            "subcategory":"Supermarket",
            "type":"Retail Goods"
        }
    ],
    "sg:phone":"+39 0522 688443",
    "sg:postcode":"42024",
    "sg:province":"Reggio Nell'Emilia",
    "sg:tags":[
        "shop",
        "refrigerator"
    ],
    "sg:website":"www.coldmaser.com",
    "wof:name":"Cold Master Srl",
    "wof:placetype":"venue"
},
  "geometry": {"coordinates":[10.566279,44.799923],"type":"Point"}
}