{
  "type": "Feature",
  "properties": {
    "iso:country":"IT",
    "sg:address":"37122 Verona",
    "sg:city":"Verona",
    "sg:orig_category":"Ospedali E Servizi Sanitari",
    "sg:phone":"+39 045 594207",
    "sg:postcode":"37122",
    "sg:province":"Verona",
    "wof:name":"Centro Di Agopuntura",
    "wof:placetype":"venue"
},
  "geometry": {"coordinates":[10.95454,45.421432],"type":"Point"}
}