{
  "type": "Feature",
  "properties": {
    "addr:full":"90047 Partinico Partinico Palermo 90047",
    "addr:postcode":"90047;90047",
    "iso:country":"IT",
    "sg:address":"90047 Partinico",
    "sg:city":"Partinico",
    "sg:orig_category":"Scuole E Servizi Scolastici",
    "sg:phone":"+39 091 890 5326",
    "sg:postcode":"90047",
    "sg:province":"Palermo",
    "wof:name":"Scuola Magistrale M.d.m. - Crispi",
    "wof:placetype":"venue"
},
  "geometry": {"coordinates":[13.36384,38.116047],"type":"Point"}
}