{
  "type": "Feature",
  "properties": {
    "iso:country":"IT",
    "sg:address":"29, Via Monti Vincenzo 20016 Pero",
    "sg:city":"Pero",
    "sg:classifiers":[
        {
            "category":"Professional",
            "subcategory":"Business Services",
            "type":"Services"
        }
    ],
    "sg:phone":"+39 39023390241",
    "sg:postcode":"20016",
    "sg:province":"Milano",
    "sg:tags":[
        "advice"
    ],
    "wof:name":"Hhs Italia S.r.l.",
    "wof:placetype":"venue"
},
  "geometry": {"coordinates":[9.09427,45.513382],"type":"Point"}
}