{
  "type": "Feature",
  "properties": {
    "iso:country":"IT",
    "sg:address":"Via Simone Martini, 58/a; Napoli; 80100",
    "sg:classifiers":[
        {
            "category":"Banks & Credit Unions",
            "subcategory":"Bank",
            "type":"Services"
        }
    ],
    "sg:phone":"+39 081 242389",
    "wof:name":"Banca Della Provincia Di Napoli",
    "wof:placetype":"venue"
},
  "geometry": {"coordinates":[14.222362,40.85146],"type":"Point"}
}