{
  "type": "Feature",
  "properties": {
    "addr:full":"52011 Bibbiena Bibbiena Arezzo 52011",
    "addr:postcode":"52011;52011",
    "iso:country":"IT",
    "sg:address":"52011 Bibbiena",
    "sg:city":"Bibbiena",
    "sg:orig_category":"Macchine Tessili",
    "sg:phone":"+39 0575 561166",
    "sg:postcode":"52011",
    "sg:province":"Arezzo",
    "sg:website":"http://www.texmaitaly.com",
    "wof:name":"Tex-ma Srl",
    "wof:placetype":"venue"
},
  "geometry": {"coordinates":[11.81209,43.728065],"type":"Point"}
}