{
  "type": "Feature",
  "properties": {
    "addr:full":"73, Via Italia 25080 Paitone Paitone Brescia 25080",
    "addr:postcode":"25080;25080",
    "addr:street":"Via Italia",
    "iso:country":"IT",
    "sg:address":"73, Via Italia 25080 Paitone",
    "sg:city":"Paitone",
    "sg:classifiers":[
        {
            "category":"Manufacturing",
            "subcategory":"Rubber & Plastics",
            "type":"Manufacturing & Wholesale Goods"
        }
    ],
    "sg:phone":"+39 39030691113",
    "sg:postcode":"25080",
    "sg:province":"Brescia",
    "wof:name":"Massolini Componenti Plastica Spa",
    "wof:placetype":"venue"
},
  "geometry": {"coordinates":[10.404507637,45.5526695251],"type":"Point"}
}