{
  "type": "Feature",
  "properties": {
    "iso:country":"IT",
    "sg:address":"97013 Comiso",
    "sg:city":"Comiso",
    "sg:orig_category":"Onoranze E Pompe Funebri",
    "sg:phone":"+39 0932 721354",
    "sg:postcode":"97013",
    "sg:province":"Ragusa",
    "wof:name":"Agenzia Onoranze Funebri 'la Misericordia'",
    "wof:placetype":"venue"
},
  "geometry": {"coordinates":[14.603324,36.946751],"type":"Point"}
}