{
  "type": "Feature",
  "properties": {
    "addr:full":"1, Via Matteotti 18032 Perinaldo Perinaldo Imperia 18032",
    "addr:postcode":"18032;18032",
    "addr:street":"Via Matteotti",
    "iso:country":"IT",
    "sg:address":"1, Via Matteotti 18032 Perinaldo",
    "sg:city":"Perinaldo",
    "sg:classifiers":[
        {
            "category":"Travel",
            "subcategory":"Travel Agent",
            "type":"Entertainment"
        }
    ],
    "sg:phone":"+39 0184 672093",
    "sg:postcode":"18032",
    "sg:province":"Imperia",
    "sg:tags":[
        "business"
    ],
    "wof:name":"Ristorante I Pianeti Di Giove",
    "wof:placetype":"venue"
},
  "geometry": {"coordinates":[7.671091,43.867134],"type":"Point"}
}