{
  "type": "Feature",
  "properties": {
    "addr:full":"35127 Padova Padova Padova 35127",
    "addr:postcode":"35127;35127",
    "iso:country":"IT",
    "sg:address":"35127 Padova",
    "sg:city":"Padova",
    "sg:orig_category":"Arredamento Negozi E Supermercati",
    "sg:phone":"+39 049 870 2804",
    "sg:postcode":"35127",
    "sg:province":"Padova",
    "sg:website":"http://www.sgf.it",
    "wof:name":"S.g.f. Srl",
    "wof:placetype":"venue"
},
  "geometry": {"coordinates":[11.956322,45.387569],"type":"Point"}
}