{
  "type": "Feature",
  "properties": {
    "iso:country":"IT",
    "sg:address":"Strada Delle Brecce Bianche 60131 Ancona",
    "sg:city":"Ancona",
    "sg:classifiers":[
        {
            "category":"Utilities",
            "subcategory":"Telephone",
            "type":"Services"
        }
    ],
    "sg:phone":"+39 071 286 6410",
    "sg:postcode":"60131",
    "sg:province":"Ancona",
    "sg:tags":[
        "telecommunication"
    ],
    "wof:name":"Publineon Snc",
    "wof:placetype":"venue"
},
  "geometry": {"coordinates":[13.514432,43.576485],"type":"Point"}
}