{
  "type": "Feature",
  "properties": {
    "iso:country":"IT",
    "sg:address":"35029 Pontelongo",
    "sg:city":"Pontelongo",
    "sg:orig_category":"Forniture Per Edilizia E Lavori Pubblici",
    "sg:phone":"+39 049 977 6272",
    "sg:postcode":"35029",
    "sg:province":"Padova",
    "wof:name":"L.a.m.p. Snc",
    "wof:placetype":"venue"
},
  "geometry": {"coordinates":[12.0272188187,45.2516937256],"type":"Point"}
}