{
  "type": "Feature",
  "properties": {
    "iso:country":"IT",
    "sg:address":"1, Via Campo Boario 64100 Teramo",
    "sg:city":"Teramo",
    "sg:classifiers":[
        {
            "category":"Farming",
            "subcategory":"Livestock Farm",
            "type":"Manufacturing & Wholesale Goods"
        }
    ],
    "sg:phone":"+39 390 861 3321",
    "sg:postcode":"64100",
    "sg:province":"Teramo",
    "sg:tags":[
        "agriculture"
    ],
    "wof:name":"Istituto Zooprofilatico",
    "wof:placetype":"venue"
},
  "geometry": {"coordinates":[13.709419,42.656113],"type":"Point"}
}