{
  "type": "Feature",
  "properties": {
    "addr:full":"20092 Cinisello Balsamo Cinisello Balsamo Milano 20092",
    "addr:postcode":"20092;20092",
    "iso:country":"IT",
    "sg:address":"20092 Cinisello Balsamo",
    "sg:city":"Cinisello Balsamo",
    "sg:orig_category":"Forniture Per Attivita' Industriali",
    "sg:phone":"+39 02 6604 6282",
    "sg:postcode":"20092",
    "sg:province":"Milano",
    "wof:name":"Cipro (s.r.l.)",
    "wof:placetype":"venue"
},
  "geometry": {"coordinates":[9.1902723312,45.5515365601],"type":"Point"}
}