{
  "type": "Feature",
  "properties": {
    "addr:full":"Km. 5.700, Str. St. 114 Tremestieri 98100 Messina",
    "addr:housenumber":"114",
    "addr:postcode":"98100",
    "addr:street":"Km. 5.700 Str. St.;Tremestieri",
    "iso:country":"IT",
    "sg:address":"Km. 5.700, Str. St. 114 Tremestieri 98100 Messina",
    "sg:classifiers":[
        {
            "category":"Manufacturing",
            "subcategory":"Tools & Machinery",
            "type":"Manufacturing & Wholesale Goods"
        }
    ],
    "sg:phone":"+39 090 625 8939",
    "sg:tags":[
        "environment",
        "equipment",
        "-"
    ],
    "sg:website":"http://www.paginegialle.it/citinox",
    "wof:name":"C.i.t. Inox Popolo",
    "wof:placetype":"venue"
},
  "geometry": {"coordinates":[15.494688,38.197247],"type":"Point"}
}