{
  "type": "Feature",
  "properties": {
    "iso:country":"IT",
    "sg:address":"Via Caduti Di Amola 21/2 40132 Bologna",
    "sg:city":"Bologna",
    "sg:classifiers":[
        {
            "category":"Home & Garden",
            "subcategory":"Building Materials",
            "type":"Retail Goods"
        }
    ],
    "sg:phone":"+39 051 400374",
    "sg:postcode":"40132",
    "sg:province":"Bologna",
    "sg:tags":[
        "aluminium",
        "window"
    ],
    "sg:website":"www.scandellari.it",
    "wof:name":"Scandellari Infissi Srl",
    "wof:placetype":"venue"
},
  "geometry": {"coordinates":[11.280589,44.513123],"type":"Point"}
}