{
  "type": "Feature",
  "properties": {
    "iso:country":"IT",
    "sg:address":"20052 Monza",
    "sg:city":"Monza",
    "sg:orig_category":"Calzature, Pelletterie E Pelli. Shopping",
    "sg:phone":"+39 039 284 0136",
    "sg:postcode":"20052",
    "sg:province":"Milano",
    "wof:name":"Moscatelli Emilia",
    "wof:placetype":"venue"
},
  "geometry": {"coordinates":[9.126738,45.468761],"type":"Point"}
}