{
  "type": "Feature",
  "properties": {
    "addr:full":"Via Archimede 7 20041 Agrate Brianza Agrate Brianza Milano 20041",
    "addr:housenumber":"7",
    "addr:postcode":"20041;20041",
    "addr:street":"Via Archimede",
    "iso:country":"IT",
    "sg:address":"Via Archimede 7 20041 Agrate Brianza",
    "sg:city":"Agrate Brianza",
    "sg:classifiers":[
        {
            "category":"Military Area",
            "subcategory":"Restricted Area",
            "type":"Public Place"
        }
    ],
    "sg:phone":"+39 039 607461",
    "sg:postcode":"20041",
    "sg:province":"Milano",
    "sg:tags":[
        "magnet",
        "coil"
    ],
    "sg:website":"www.atam.it",
    "wof:name":"Atam Windings Srl",
    "wof:placetype":"venue"
},
  "geometry": {"coordinates":[9.343593,45.56876],"type":"Point"}
}