{
  "type": "Feature",
  "properties": {
    "addr:full":"48, Via Roppi 46033 Castel D'ario Mantova 46033",
    "addr:postcode":"46033;46033",
    "addr:street":"Via Roppi",
    "iso:country":"IT",
    "sg:address":"48, Via Roppi 46033 Castel D'ario",
    "sg:classifiers":[
        {
            "category":"Shopping",
            "subcategory":"Clothing, Apparel, & Fashions",
            "type":"Retail Goods"
        }
    ],
    "sg:phone":"+39 0376 660777",
    "sg:postcode":"46033",
    "sg:province":"Mantova",
    "sg:tags":[
        "clothes"
    ],
    "wof:name":"Moa Sport Mantovani Vincenzo Di Mantovani Claudio & C. S.a.s.",
    "wof:placetype":"venue"
},
  "geometry": {"coordinates":[10.977979,45.181267],"type":"Point"}
}