{
  "type": "Feature",
  "properties": {
    "addr:full":"30020 Noventa Di Piave Noventa di Piave Venezia 30020",
    "addr:postcode":"30020;30020",
    "iso:country":"IT",
    "sg:address":"30020 Noventa Di Piave",
    "sg:city":"Noventa di Piave",
    "sg:orig_category":"Forniture Alle Strutture Ricettive. Forniture Per Attivita' Commerciali Ed Artigianali",
    "sg:phone":"+39 0421 307274",
    "sg:postcode":"30020",
    "sg:province":"Venezia",
    "sg:website":"http://www.nordesttrade.com",
    "wof:name":"Nord Est Trade Srl",
    "wof:placetype":"venue"
},
  "geometry": {"coordinates":[12.5347032547,45.6607971191],"type":"Point"}
}