{
  "type": "Feature",
  "properties": {
    "iso:country":"IT",
    "sg:address":"90045 Cinisi",
    "sg:city":"Cinisi",
    "sg:classifiers":[
        {
            "category":"Bars & Pubs",
            "subcategory":"Champagne Bar",
            "type":"Food & Drink"
        }
    ],
    "sg:phone":"+39 091 866 4923",
    "sg:postcode":"90045",
    "sg:province":"Palermo",
    "sg:tags":[
        "caffe'",
        "e"
    ],
    "wof:name":"Biscottificio Cucinella Pietro S. & A. Snc",
    "wof:placetype":"venue"
},
  "geometry": {"coordinates":[13.116374,38.155689],"type":"Point"}
}