{
  "type": "Feature",
  "properties": {
    "addr:full":"214, Via Firenze 51039 Quarrata Quarrata Pistoia 51039",
    "addr:housenumber":"214",
    "addr:postcode":"51039;51039",
    "addr:street":"Via Firenze",
    "iso:country":"IT",
    "sg:address":"214, Via Firenze 51039 Quarrata",
    "sg:city":"Quarrata",
    "sg:classifiers":[
        {
            "category":"Shopping",
            "subcategory":"Stationery & Office Supplies",
            "type":"Retail Goods"
        }
    ],
    "sg:phone":"+39 39057372488",
    "sg:postcode":"51039",
    "sg:province":"Pistoia",
    "sg:tags":[
        "professional"
    ],
    "wof:name":"Ital Design Arredamenti Srl",
    "wof:placetype":"venue"
},
  "geometry": {"coordinates":[10.9945793152,43.8561935425],"type":"Point"}
}