{
  "type": "Feature",
  "properties": {
    "iso:country":"IT",
    "sg:address":"70051 Barletta",
    "sg:city":"Barletta",
    "sg:orig_category":"Metalli E Leghe",
    "sg:phone":"+39 0883 347497",
    "sg:postcode":"70051",
    "sg:province":"Bari",
    "wof:name":"Nts Di Cristofaro Nicola",
    "wof:placetype":"venue"
},
  "geometry": {"coordinates":[16.2950572968,41.3127593994],"type":"Point"}
}