{
  "type": "Feature",
  "properties": {
    "addr:full":"33044 Manzano Manzano Udine 33044",
    "addr:postcode":"33044;33044",
    "iso:country":"IT",
    "sg:address":"33044 Manzano",
    "sg:city":"Manzano",
    "sg:orig_category":"Salotti, Poltrone, Sedie E Tavoli",
    "sg:phone":"+39 0432 755469",
    "sg:postcode":"33044",
    "sg:province":"Udine",
    "sg:website":"http://www.callegariitalia.it",
    "wof:name":"Callegari Italia Di Callegari Laura & C. Sas",
    "wof:placetype":"venue"
},
  "geometry": {"coordinates":[13.379481,45.984085],"type":"Point"}
}