{
  "type": "Feature",
  "properties": {
    "iso:country":"IT",
    "sg:address":"20061 Carugate",
    "sg:city":"Carugate",
    "sg:orig_category":"Calzature, Pelletterie E Pelli. Servizi E Lavori Per Abbigliamento E Pelletterie",
    "sg:phone":"+39 02 9215 1254",
    "sg:postcode":"20061",
    "sg:province":"Milano",
    "wof:name":"Galante S.n.c",
    "wof:placetype":"venue"
},
  "geometry": {"coordinates":[9.336032,45.555378],"type":"Point"}
}