{
  "type": "Feature",
  "properties": {
    "addr:full":"80142 Napoli Napoli Napoli 80142",
    "addr:housenumber":"80142",
    "addr:postcode":"80142",
    "iso:country":"IT",
    "sg:address":"80142 Napoli",
    "sg:city":"Napoli",
    "sg:orig_category":"Trasporti E Spedizioni Merci",
    "sg:phone":"+39 081 734 0435",
    "sg:postcode":"80142",
    "sg:province":"Napoli",
    "sg:website":"http://www.gondrand.it",
    "wof:name":"Gondrand Spa - Filiale Napoli",
    "wof:placetype":"venue"
},
  "geometry": {"coordinates":[14.277389,40.847008],"type":"Point"}
}