{
  "type": "Feature",
  "properties": {
    "iso:country":"IT",
    "sg:address":"65016 Montesilvano",
    "sg:orig_category":"Antincendio - Impianti, Attrezzature E Materiali",
    "sg:phone":"+39 085 449 1488",
    "sg:province":"PE",
    "wof:name":"Ellegi' Estintori",
    "wof:placetype":"venue"
},
  "geometry": {"coordinates":[-91.91481,38.579685],"type":"Point"}
}