{
  "type": "Feature",
  "properties": {
    "iso:country":"IT",
    "sg:address":"Via Roma 54 23834 Premana",
    "sg:city":"Premana",
    "sg:classifiers":[
        {
            "category":"Bars & Pubs",
            "type":"Food & Drink"
        }
    ],
    "sg:phone":"+39 0341 819133",
    "sg:postcode":"23834",
    "sg:province":"Lecco",
    "sg:tags":[
        "knife",
        "bread"
    ],
    "wof:name":"Fiskars Montana Srl",
    "wof:placetype":"venue"
},
  "geometry": {"coordinates":[9.410014,46.055763],"type":"Point"}
}