{
  "type": "Feature",
  "properties": {
    "iso:country":"IT",
    "sg:address":"64023 Mosciano Sant'angelo",
    "sg:orig_category":"Servizi Ausiliari Di Analisi, Controllo E Ricerca. Acqua, Luce, Gas E Societa' Di Esercizio Pubblico",
    "sg:phone":"+39 085 806 1499",
    "sg:postcode":"64023",
    "sg:province":"Teramo",
    "wof:name":"Osservatorio Astronomico Colle Leone",
    "wof:placetype":"venue"
},
  "geometry": {"coordinates":[13.877944,42.753536],"type":"Point"}
}