{
  "type": "Feature",
  "properties": {
    "iso:country":"IT",
    "sg:address":"94018 Troina",
    "sg:city":"Troina",
    "sg:orig_category":"Abbigliamento - Vendita Al Dettaglio",
    "sg:phone":"+39 0935 657190",
    "sg:postcode":"94018",
    "sg:province":"Enna",
    "wof:name":"Millennium Wear Di Giamblanco Giuseppe",
    "wof:placetype":"venue"
},
  "geometry": {"coordinates":[14.635463,37.755424],"type":"Point"}
}