{
  "type": "Feature",
  "properties": {
    "addr:full":"80133 Napoli Napoli Napoli 80133",
    "addr:housenumber":"80133",
    "addr:postcode":"80133",
    "iso:country":"IT",
    "sg:address":"80133 Napoli",
    "sg:city":"Napoli",
    "sg:orig_category":"Servizi E Lavori Per Edilizia E Lavori Pubblici. Consulenze Tecniche, Amministrative E Perizie",
    "sg:phone":"+39 081 551 9268",
    "sg:postcode":"80133",
    "sg:province":"Napoli",
    "wof:name":"Anaci Sede Provinciale Napoli",
    "wof:placetype":"venue"
},
  "geometry": {"coordinates":[14.249927,40.84132],"type":"Point"}
}