{
  "type": "Feature",
  "properties": {
    "iso:country":"IT",
    "sg:address":"20125 Milano",
    "sg:city":"Milano",
    "sg:orig_category":"Non-classified Establishments",
    "sg:phone":"+39 02 6707 0562",
    "sg:postcode":"20125",
    "sg:province":"Milano",
    "wof:name":"Rosy Pelletterie (s.n.c.)",
    "wof:placetype":"venue"
},
  "geometry": {"coordinates":[9.20582,45.493797],"type":"Point"}
}