{
  "type": "Feature",
  "properties": {
    "iso:country":"IT",
    "sg:address":"23030 Villa Di Tirano",
    "sg:city":"Villa di Tirano",
    "sg:orig_category":"Ospedali E Servizi Sanitari",
    "sg:phone":"+39 0342 702375",
    "sg:postcode":"23030",
    "sg:province":"Sondrio",
    "wof:name":"Molinari Andreola Genni",
    "wof:placetype":"venue"
},
  "geometry": {"coordinates":[10.150562,46.214001],"type":"Point"}
}