{
  "type": "Feature",
  "properties": {
    "iso:country":"IT",
    "sg:address":"20060 Cassina De' Pecchi",
    "sg:orig_category":"Acciai Inossidabili - Lavorazione",
    "sg:phone":"+39 02 952 9307",
    "sg:postcode":"20060",
    "sg:province":"Milano",
    "sg:website":"http://www.rivestinox.it",
    "wof:name":"Rivestinox Snc",
    "wof:placetype":"venue"
},
  "geometry": {"coordinates":[9.356756,45.50877],"type":"Point"}
}