{
  "type": "Feature",
  "properties": {
    "iso:country":"IT",
    "sg:address":"00123 Roma",
    "sg:city":"Roma",
    "sg:orig_category":"Arredamenti E Mobili Professionali. Arredi Ed Attrezzature Per Attivita' Commerciali Ed Artigianali",
    "sg:phone":"+39 06 3362 4261",
    "sg:postcode":"00123",
    "sg:province":"Roma",
    "wof:name":"Pentarredo Srl",
    "wof:placetype":"venue"
},
  "geometry": {"coordinates":[12.397561,42.072693],"type":"Point"}
}