{
  "type": "Feature",
  "properties": {
    "addr:full":"63039 San. Benedetto Del Tronto Ascoli Piceno 63039",
    "addr:housenumber":"63039",
    "addr:postcode":"63039",
    "addr:street":"San. Benedetto Del Tronto;Piceno",
    "iso:country":"IT",
    "sg:address":"63039 San. Benedetto Del Tronto",
    "sg:orig_category":"Campeggio. Alberghi E Strutture Extra Alberghiere",
    "sg:phone":"+39 0735 587070",
    "sg:postcode":"63039",
    "sg:province":"Ascoli Piceno",
    "sg:website":"http://www.centro-vacanze.it",
    "wof:name":"Residence Azzurro",
    "wof:placetype":"venue"
},
  "geometry": {"coordinates":[13.881191,42.949596],"type":"Point"}
}