{
  "type": "Feature",
  "properties": {
    "iso:country":"IT",
    "sg:address":"Localita' La Baraggia 13040 Carisio",
    "sg:city":"Carisio",
    "sg:classifiers":[
        {
            "category":"Manufacturing",
            "subcategory":"Metals",
            "type":"Manufacturing & Wholesale Goods"
        }
    ],
    "sg:phone":"+39 0161 971119",
    "sg:postcode":"13040",
    "sg:province":"Vercelli",
    "sg:tags":[
        "metallurgy",
        "metalworking"
    ],
    "wof:name":"Sacal Societa' Alluminio Carisio S.p.a.",
    "wof:placetype":"venue"
},
  "geometry": {"coordinates":[8.4263935089,45.3210601807],"type":"Point"}
}