{
  "type": "Feature",
  "properties": {
    "iso:country":"IT",
    "sg:address":"36027 Rosa'",
    "sg:orig_category":"Serramenti Ed Infissi. Prodotti Vari In Metallo",
    "sg:phone":"+39 0424 532311",
    "sg:postcode":"36027",
    "sg:province":"Vicenza",
    "sg:website":"http://www.comunello.it",
    "wof:name":"Fratelli Comunello Spa",
    "wof:placetype":"venue"
},
  "geometry": {"coordinates":[11.792451,45.739792],"type":"Point"}
}