{
  "type": "Feature",
  "properties": {
    "iso:country":"IT",
    "sg:address":"30126 Venezia",
    "sg:city":"Alberoni",
    "sg:orig_category":"Alberghi E Strutture Extra Alberghiere. Ospedali E Servizi Sanitari",
    "sg:phone":"+39 041 731142",
    "sg:postcode":"30126",
    "sg:province":"Venezia",
    "wof:name":"Colonia Marina Enpas",
    "wof:placetype":"venue"
},
  "geometry": {"coordinates":[12.330564,45.358959],"type":"Point"}
}