{
  "type": "Feature",
  "properties": {
    "iso:country":"IT",
    "sg:address":"57125 Livorno",
    "sg:city":"Livorno",
    "sg:orig_category":"Campeggio, Tende, Attrezzature Ed Articoli - Vendita Al Dettaglio",
    "sg:phone":"+39 0586 894178",
    "sg:postcode":"57125",
    "sg:province":"Livorno",
    "wof:name":"Tosi Rossana",
    "wof:placetype":"venue"
},
  "geometry": {"coordinates":[10.316616,43.551373],"type":"Point"}
}