{
  "type": "Feature",
  "properties": {
    "iso:country":"IT",
    "sg:address":"65013 Citt\u00e0 Sant'angelo",
    "sg:classifiers":[
        {
            "category":"Utilities",
            "subcategory":"Refuse",
            "type":"Services"
        }
    ],
    "sg:phone":"+39 085 950523",
    "sg:postcode":"65013",
    "sg:province":"Pescara",
    "sg:tags":[
        "houseware",
        "utensil",
        "linen",
        "blankets",
        "drapery",
        "kitchen"
    ],
    "wof:name":"C.b. Distribution Srl",
    "wof:placetype":"venue"
},
  "geometry": {"coordinates":[14.21354,42.463902],"type":"Point"}
}