{
  "type": "Feature",
  "properties": {
    "iso:country":"IT",
    "sg:address":"5, Via Del Commercio 25039 Travagliato",
    "sg:city":"Travagliato",
    "sg:classifiers":[
        {
            "category":"Shopping",
            "subcategory":"Clothing, Apparel, & Fashions",
            "type":"Retail Goods"
        }
    ],
    "sg:phone":"+39 030 686 4379",
    "sg:postcode":"25039",
    "sg:province":"Brescia",
    "sg:tags":[
        "clothes"
    ],
    "wof:name":"Equipe 5 (s.r.l.)",
    "wof:placetype":"venue"
},
  "geometry": {"coordinates":[10.09693,45.532139],"type":"Point"}
}