{
  "type": "Feature",
  "properties": {
    "iso:country":"IT",
    "sg:address":"Via Flaminia 669 60015 Falconara Marittima",
    "sg:city":"Falconara Marittima",
    "sg:classifiers":[
        {
            "category":"Shopping",
            "subcategory":"Luggage & Leather Goods",
            "type":"Retail Goods"
        }
    ],
    "sg:phone":"+39 071 916691",
    "sg:postcode":"60015",
    "sg:province":"Ancona",
    "sg:tags":[
        "bag"
    ],
    "wof:name":"Carlo Filipponi Srl",
    "wof:placetype":"venue"
},
  "geometry": {"coordinates":[13.415611,43.622246],"type":"Point"}
}