{
  "type": "Feature",
  "properties": {
    "iso:country":"IT",
    "sg:address":"84010 Sant'egidio Del Monte Albino",
    "sg:orig_category":"Bevande, Vini E Liquori",
    "sg:phone":"+39 081 513 8872",
    "sg:postcode":"84010",
    "sg:province":"Salerno",
    "wof:name":"Casa D'amalfi Di D'ambrosio Aniello",
    "wof:placetype":"venue"
},
  "geometry": {"coordinates":[14.584896,40.742397],"type":"Point"}
}