{
  "type": "Feature",
  "properties": {
    "iso:country":"IT",
    "sg:address":"22075 Lurate Caccivio",
    "sg:city":"Lurate Caccivio",
    "sg:orig_category":"Tessuti E Stoffe",
    "sg:phone":"+39 031 390036",
    "sg:postcode":"22075",
    "sg:province":"Como",
    "sg:website":"http://www.trinca.it",
    "wof:name":"Trinca Colonel Silvio & Figlio Sergio Snc",
    "wof:placetype":"venue"
},
  "geometry": {"coordinates":[8.993656,45.764156],"type":"Point"}
}