{
  "type": "Feature",
  "properties": {
    "addr:full":"2, Via Europa 24034 Cisano Bergamasco Cisano Bergamasco Bergamo 24034",
    "addr:postcode":"24034;24034",
    "addr:street":"Via Europa",
    "iso:country":"IT",
    "sg:address":"2, Via Europa 24034 Cisano Bergamasco",
    "sg:city":"Cisano Bergamasco",
    "sg:classifiers":[
        {
            "category":"Manufacturing",
            "subcategory":"Food",
            "type":"Manufacturing & Wholesale Goods"
        }
    ],
    "sg:phone":"+39 39035787772",
    "sg:postcode":"24034",
    "sg:province":"Bergamo",
    "sg:tags":[
        "equipment",
        "processing",
        "-",
        "machinery"
    ],
    "wof:name":"Due Effe Componenti S.r.l.",
    "wof:placetype":"venue"
},
  "geometry": {"coordinates":[9.47265625,45.7402381897],"type":"Point"}
}