{
  "type": "Feature",
  "properties": {
    "addr:full":"80045 Pompei Pompei Napoli 80045",
    "addr:housenumber":"80045",
    "addr:postcode":"80045",
    "iso:country":"IT",
    "sg:address":"80045 Pompei",
    "sg:city":"Pompei",
    "sg:orig_category":"Gioielleria, Oreficeria E Argenteria. Shopping",
    "sg:phone":"+39 081 863 1083",
    "sg:postcode":"80045",
    "sg:province":"Napoli",
    "wof:name":"Somma Lucia",
    "wof:placetype":"venue"
},
  "geometry": {"coordinates":[14.540633,40.720078],"type":"Point"}
}