{
  "type": "Feature",
  "properties": {
    "iso:country":"IT",
    "sg:address":"Via Santa Maria Molgora 60 20059 Vimercate",
    "sg:city":"Vimercate",
    "sg:orig_category":"Temperature Transmitters",
    "sg:phone":"+39 039 667009",
    "sg:postcode":"20059",
    "sg:province":"Milano",
    "sg:website":"www.sigmacontrol.it",
    "wof:name":"Sigma Control Srl",
    "wof:placetype":"venue"
},
  "geometry": {"coordinates":[9.367733,45.598892],"type":"Point"}
}