{
  "type": "Feature",
  "properties": {
    "addr:full":"60022 Castelfidardo Castelfidardo Ancona 60022",
    "addr:postcode":"60022;60022",
    "iso:country":"IT",
    "sg:address":"60022 Castelfidardo",
    "sg:city":"Castelfidardo",
    "sg:orig_category":"Fisarmoniche",
    "sg:phone":"+39 071 782 0247",
    "sg:postcode":"60022",
    "sg:province":"Ancona",
    "sg:website":"http://www.accordions.com/mengascini",
    "wof:name":"Mengascini Nello",
    "wof:placetype":"venue"
},
  "geometry": {"coordinates":[13.5598306656,43.4915924072],"type":"Point"}
}