{
  "type": "Feature",
  "properties": {
    "iso:country":"IT",
    "sg:address":"Via 2 Giugno, 28/30 52020 Laterina",
    "sg:city":"Laterina",
    "sg:classifiers":[
        {
            "category":"Manufacturing",
            "subcategory":"Motor Vehicles & Parts",
            "type":"Manufacturing & Wholesale Goods"
        }
    ],
    "sg:phone":"+39 0575 89063",
    "sg:postcode":"52020",
    "sg:province":"Arezzo",
    "sg:tags":[
        "automotive",
        "chassis"
    ],
    "wof:name":"Chimetal Srl",
    "wof:placetype":"venue"
},
  "geometry": {"coordinates":[11.714366,43.502148],"type":"Point"}
}