{
  "type": "Feature",
  "properties": {
    "addr:full":"Via Altobelli 45 47900 Rimini Rimini Rimini 47900",
    "addr:housenumber":"45",
    "addr:postcode":"47900;47900",
    "addr:street":"Via Altobelli",
    "iso:country":"IT",
    "sg:address":"Via Altobelli 45 47900 Rimini",
    "sg:city":"Rimini",
    "sg:classifiers":[
        {
            "category":"Professional",
            "subcategory":"Advertising",
            "type":"Services"
        }
    ],
    "sg:phone":"+39 0541 380306",
    "sg:postcode":"47900",
    "sg:province":"Rimini",
    "sg:tags":[
        "postcard"
    ],
    "wof:name":"Graph Di Celli Ottavio & C. Snc",
    "wof:placetype":"venue"
},
  "geometry": {"coordinates":[12.575646,44.026981],"type":"Point"}
}