{
  "type": "Feature",
  "properties": {
    "iso:country":"IT",
    "sg:address":"20090 Trezzano Sul Naviglio",
    "sg:city":"Trezzano sul Naviglio",
    "sg:orig_category":"Arte Ed Artigianato Artistico",
    "sg:phone":"+39 02 4840 2771",
    "sg:postcode":"20090",
    "sg:province":"Milano",
    "wof:name":"Metal Art Di Della Torre Daniele",
    "wof:placetype":"venue"
},
  "geometry": {"coordinates":[9.060785,45.41634],"type":"Point"}
}