{
  "type": "Feature",
  "properties": {
    "iso:country":"IT",
    "sg:address":"36078 Valdagno",
    "sg:city":"Valdagno",
    "sg:orig_category":"Articoli Da Regalo. Forniture Per Attivita' Commerciali Ed Artigianali",
    "sg:phone":"+39 0445 401967",
    "sg:postcode":"36078",
    "sg:province":"Vicenza",
    "wof:name":"Fioreria Armando Di Ongaro Beniamino E C. Snc",
    "wof:placetype":"venue"
},
  "geometry": {"coordinates":[11.292549,45.662086],"type":"Point"}
}