{
  "type": "Feature",
  "properties": {
    "iso:country":"IT",
    "sg:address":"55011 Altopascio",
    "sg:city":"Altopascio",
    "sg:orig_category":"Gas Compressi E Liquefatti - Produzione E Ingrosso",
    "sg:phone":"+39 0583 28721",
    "sg:postcode":"55011",
    "sg:province":"Lucca",
    "wof:name":"Toscogas Spa",
    "wof:placetype":"venue"
},
  "geometry": {"coordinates":[10.691158,43.837185],"type":"Point"}
}