{
  "type": "Feature",
  "properties": {
    "iso:country":"IT",
    "sg:address":"21029 Vergiate",
    "sg:city":"Vergiate",
    "sg:orig_category":"Materiali Edili",
    "sg:phone":"+39 0331 948491",
    "sg:postcode":"21029",
    "sg:province":"Varese",
    "wof:name":"Torciere Angelo",
    "wof:placetype":"venue"
},
  "geometry": {"coordinates":[8.693928,45.725471],"type":"Point"}
}