{
  "type": "Feature",
  "properties": {
    "addr:full":"Via Mercatelli Maglio 77 31030 Colfosco Colfosco Treviso 31030",
    "addr:housenumber":"77",
    "addr:postcode":"31030;31030",
    "addr:street":"Via Mercatelli Maglio",
    "iso:country":"IT",
    "sg:address":"Via Mercatelli Maglio 77 31030 Colfosco",
    "sg:city":"Colfosco",
    "sg:orig_category":"Hoisiery Goods",
    "sg:phone":"+39 0438 758421",
    "sg:postcode":"31030",
    "sg:province":"Treviso",
    "wof:name":"Top Maglia Srl",
    "wof:placetype":"venue"
},
  "geometry": {"coordinates":[12.233025,45.829514],"type":"Point"}
}