{
  "type": "Feature",
  "properties": {
    "iso:country":"IT",
    "sg:address":"42046 Reggiolo",
    "sg:orig_category":"Abbigliamento Esterno, Maglierie E Pelliccerie. Forniture Per Abbigliamento E Pelletterie",
    "sg:phone":"+39 0522 971111",
    "sg:postcode":"42046",
    "sg:province":"Reggio Nell'Emilia",
    "wof:name":"Negri Gabriella",
    "wof:placetype":"venue"
},
  "geometry": {"coordinates":[10.810376,44.924847],"type":"Point"}
}