{
  "type": "Feature",
  "properties": {
    "addr:full":"80046 S. Giorgio A Cremano Napoli 80046",
    "addr:housenumber":"80046",
    "addr:postcode":"80046",
    "addr:street":"S. Giorgio A Cremano Napoli",
    "iso:country":"IT",
    "sg:address":"80046 S. Giorgio A Cremano",
    "sg:orig_category":"Elettrodomestici. Forniture Alle Strutture Ricettive",
    "sg:phone":"+39 081 481222",
    "sg:postcode":"80046",
    "sg:province":"Napoli",
    "sg:website":"http://www.cismet.com",
    "wof:name":"Cismet Srl",
    "wof:placetype":"venue"
},
  "geometry": {"coordinates":[14.320687,40.826527],"type":"Point"}
}