{
  "type": "Feature",
  "properties": {
    "addr:full":"Via Dell' Opificio 32 36100 Vicenza Vicenza Vicenza 36100",
    "addr:housenumber":"32",
    "addr:postcode":"36100;36100",
    "addr:street":"Via Dell ' Opificio",
    "iso:country":"IT",
    "sg:address":"Via Dell' Opificio 32 36100 Vicenza",
    "sg:city":"Vicenza",
    "sg:classifiers":[
        {
            "category":"Shopping",
            "subcategory":"Clothing, Apparel, & Fashions",
            "type":"Retail Goods"
        }
    ],
    "sg:phone":"+39 0444 246600",
    "sg:postcode":"36100",
    "sg:province":"Vicenza",
    "sg:tags":[
        "clothing",
        "fabric"
    ],
    "sg:website":"www.cotonificioveneto.it",
    "wof:name":"Cotonificio Veneto Spa",
    "wof:placetype":"venue"
},
  "geometry": {"coordinates":[11.526389,45.575279],"type":"Point"}
}