{
  "type": "Feature",
  "properties": {
    "iso:country":"IT",
    "sg:address":"20063 Cernusco Sul Naviglio",
    "sg:city":"Cernusco sul Naviglio",
    "sg:orig_category":"Macchine, Impianti E Forniture Per Industria Grafica, Cartaria E Cartotecnica",
    "sg:phone":"+39 02 9259 0187",
    "sg:postcode":"20063",
    "sg:province":"Milano",
    "wof:name":"Cargraf Srl",
    "wof:placetype":"venue"
},
  "geometry": {"coordinates":[9.338531,45.502674],"type":"Point"}
}