{
  "type": "Feature",
  "properties": {
    "iso:country":"IT",
    "sg:address":"20154 Milano",
    "sg:city":"Milano",
    "sg:classifiers":[
        {
            "category":"Health Services",
            "subcategory":"Health Practitioner",
            "type":"Services"
        }
    ],
    "sg:phone":"+39 02 349 0811",
    "sg:postcode":"20154",
    "sg:province":"Milano",
    "sg:tags":[
        "medici"
    ],
    "wof:name":"Di Paolo Paola",
    "wof:placetype":"venue"
},
  "geometry": {"coordinates":[9.166147,45.482689],"type":"Point"}
}