{
  "type": "Feature",
  "properties": {
    "iso:country":"IT",
    "sg:address":"59100 Prato",
    "sg:city":"Prato",
    "sg:orig_category":"Canapa Filati E Tessuti",
    "sg:phone":"+39 0574 606960",
    "sg:postcode":"59100",
    "sg:province":"Prato",
    "wof:name":"Mirola Di Biagioli A. & C. Sas",
    "wof:placetype":"venue"
},
  "geometry": {"coordinates":[11.093808,43.878033],"type":"Point"}
}