{
  "type": "Feature",
  "properties": {
    "addr:full":"03036 Isola Del Liri Isola del Liri Frosinone 03036",
    "addr:postcode":"03036;03036",
    "iso:country":"IT",
    "sg:address":"03036 Isola Del Liri",
    "sg:city":"Isola del Liri",
    "sg:orig_category":"Forniture Industriali Per Prevenzione, Controllo E Sicurezza",
    "sg:phone":"+39 0776 851060",
    "sg:postcode":"03036",
    "sg:province":"Frosinone",
    "wof:name":"Guanti Sole Srl",
    "wof:placetype":"venue"
},
  "geometry": {"coordinates":[13.5799283981,41.6881942749],"type":"Point"}
}