{
  "type": "Feature",
  "properties": {
    "addr:full":"7, Via Rezzara 24020 Ranica Ranica Bergamo 24020",
    "addr:postcode":"24020;24020",
    "addr:street":"Via Rezzara",
    "iso:country":"IT",
    "sg:address":"7, Via Rezzara 24020 Ranica",
    "sg:city":"Ranica",
    "sg:classifiers":[
        {
            "category":"Home & Garden",
            "subcategory":"Home Furnishings",
            "type":"Retail Goods"
        }
    ],
    "sg:phone":"+39 39035516660",
    "sg:postcode":"24020",
    "sg:province":"Bergamo",
    "sg:tags":[
        "household"
    ],
    "wof:name":"Modulor (s.n.c.)",
    "wof:placetype":"venue"
},
  "geometry": {"coordinates":[9.664046,45.693314],"type":"Point"}
}