{
  "type": "Feature",
  "properties": {
    "addr:full":"Via Ettore Majorana 16 20054 Nova Milanese Nova Milanese Milano 20054",
    "addr:housenumber":"16",
    "addr:postcode":"20054;20054",
    "addr:street":"Via Ettore Majorana",
    "iso:country":"IT",
    "sg:address":"Via Ettore Majorana 16 20054 Nova Milanese",
    "sg:city":"Nova Milanese",
    "sg:classifiers":[
        {
            "category":"Utilities",
            "subcategory":"Natural Gas",
            "type":"Services"
        }
    ],
    "sg:phone":"+39 036 237091",
    "sg:postcode":"20054",
    "sg:province":"Milano",
    "sg:tags":[
        "pump",
        "vacuum"
    ],
    "sg:website":"www.busch.it",
    "wof:name":"Busch Italia Srl",
    "wof:placetype":"venue"
},
  "geometry": {"coordinates":[9.188141,45.463688],"type":"Point"}
}