{
  "type": "Feature",
  "properties": {
    "addr:full":"30, Loc. Scaglioni 88049 Soveria Mannelli Soveria Mannelli Catanzaro 88049",
    "addr:postcode":"88049;88049",
    "addr:street":"Loc. Scaglioni;Mannelli;Mannelli",
    "iso:country":"IT",
    "sg:address":"30, Loc. Scaglioni 88049 Soveria Mannelli",
    "sg:city":"Soveria Mannelli",
    "sg:classifiers":[
        {
            "category":"Shopping",
            "subcategory":"Stationery & Office Supplies",
            "type":"Retail Goods"
        }
    ],
    "sg:phone":"+39 0968 662147",
    "sg:postcode":"88049",
    "sg:province":"Catanzaro",
    "sg:tags":[
        "professional"
    ],
    "sg:website":"http://www.sirianni.it:ws_end: :mark:ws:http://www.paginegialle.it/csirianni",
    "wof:name":"Camillo Sirianni Sas",
    "wof:placetype":"venue"
},
  "geometry": {"coordinates":[16.5876789093,38.9105987549],"type":"Point"}
}