{
  "type": "Feature",
  "properties": {
    "addr:full":"00055 Ladispoli Ladispoli Roma 00055",
    "addr:postcode":"00055;roma 00055",
    "iso:country":"IT",
    "sg:address":"00055 Ladispoli",
    "sg:city":"Ladispoli",
    "sg:orig_category":"Pneumatici - Commercio E Riparazione",
    "sg:phone":"+39 06 991 0237",
    "sg:postcode":"00055",
    "sg:province":"Roma",
    "wof:name":"Feroci Gomme",
    "wof:placetype":"venue"
},
  "geometry": {"coordinates":[12.504491806,41.9125328064],"type":"Point"}
}