{
  "type": "Feature",
  "properties": {
    "iso:country":"IT",
    "sg:address":"20151 Milano",
    "sg:city":"Milano",
    "sg:orig_category":"Servizi E Lavori Per Agricoltura E Zootecnia. Servizi E Lavori Per Ecologia E Smaltimento Rifiuti",
    "sg:phone":"+39 02 452 4601",
    "sg:postcode":"20151",
    "sg:province":"Milano",
    "sg:website":"http://www.bonificheamianto.com",
    "wof:name":"Eco Metal",
    "wof:placetype":"venue"
},
  "geometry": {"coordinates":[9.115582,45.487705],"type":"Point"}
}