{
  "type": "Feature",
  "properties": {
    "iso:country":"IT",
    "sg:address":"00133 Roma",
    "sg:city":"Roma",
    "sg:orig_category":"Macchine, Impianti E Forniture Per Industria Grafica, Cartaria E Cartotecnica",
    "sg:phone":"+39 06 201 5898",
    "sg:postcode":"00133",
    "sg:province":"Roma",
    "wof:name":"Cerniglia Sebastiano",
    "wof:placetype":"venue"
},
  "geometry": {"coordinates":[12.614849,41.870728],"type":"Point"}
}