{
  "type": "Feature",
  "properties": {
    "addr:full":"Piazza Garibaldi 9; Gemona; 33013 Udine 33013",
    "addr:housenumber":"9",
    "addr:postcode":"33013;33013",
    "addr:street":"Piazza Garibaldi",
    "iso:country":"IT",
    "sg:address":"Piazza Garibaldi 9; Gemona; 33013",
    "sg:classifiers":[
        {
            "category":"Banks & Credit Unions",
            "subcategory":"Bank",
            "type":"Services"
        }
    ],
    "sg:phone":"+39 0432 973706",
    "sg:postcode":"33013",
    "sg:province":"Udine",
    "wof:name":"Banca Antoniana, Popolare Veneta Scarl",
    "wof:placetype":"venue"
},
  "geometry": {"coordinates":[13.13961,46.278465],"type":"Point"}
}