{
  "type": "Feature",
  "properties": {
    "iso:country":"IT",
    "sg:address":"20099 Sesto San Giovanni",
    "sg:city":"Sesto San Giovanni",
    "sg:orig_category":"Prodotti Vari In Metallo",
    "sg:phone":"+39 02 2247 0817",
    "sg:postcode":"20099",
    "sg:province":"Milano",
    "wof:name":"Ronchi Luciano",
    "wof:placetype":"venue"
},
  "geometry": {"coordinates":[9.226817131,45.5366973877],"type":"Point"}
}