{
  "type": "Feature",
  "properties": {
    "addr:full":"21100 Varese Varese Varese 21100",
    "addr:postcode":"21100;21100",
    "iso:country":"IT",
    "sg:address":"21100 Varese",
    "sg:city":"Varese",
    "sg:orig_category":"Animali Domestici - Toeletta",
    "sg:phone":"+39 0332 813496",
    "sg:postcode":"21100",
    "sg:province":"Varese",
    "wof:name":"Fer\u00c8 Rosangela",
    "wof:placetype":"venue"
},
  "geometry": {"coordinates":[8.83653,45.810658],"type":"Point"}
}