{
  "type": "Feature",
  "properties": {
    "iso:country":"IT",
    "sg:address":"97015 Modica",
    "sg:city":"Modica",
    "sg:orig_category":"Ospedali E Servizi Sanitari. Centri Di Estetica E Cosmesi E Servizi",
    "sg:phone":"+39 0932 771158",
    "sg:postcode":"97015",
    "sg:province":"Ragusa",
    "wof:name":"Pisana Giorgio - Fisiotek",
    "wof:placetype":"venue"
},
  "geometry": {"coordinates":[14.76477,36.839523],"type":"Point"}
}