{
  "type": "Feature",
  "properties": {
    "iso:country":"IT",
    "sg:address":"49, Via Sempione 28831 Baveno",
    "sg:city":"Baveno",
    "sg:classifiers":[
        {
            "category":"Shopping",
            "subcategory":"Computers & Home Electronics",
            "type":"Retail Goods"
        }
    ],
    "sg:phone":"+39 0323 924638",
    "sg:postcode":"28831",
    "sg:province":"Verbano-Cusio-Ossola",
    "sg:tags":[
        "electronic",
        "electrical",
        "equipment"
    ],
    "wof:name":"Cave Marmi Vallestrona S.r.l.",
    "wof:placetype":"venue"
},
  "geometry": {"coordinates":[8.511597,45.899044],"type":"Point"}
}