{
  "type": "Feature",
  "properties": {
    "addr:full":"83, Via Appia 81040 Curti Curti Caserta 81040",
    "addr:postcode":"81040;81040",
    "addr:street":"Via Appia",
    "iso:country":"IT",
    "sg:address":"83, Via Appia 81040 Curti",
    "sg:city":"Curti",
    "sg:classifiers":[
        {
            "category":"Shopping",
            "type":"Retail Goods"
        }
    ],
    "sg:phone":"+39 0823 845333",
    "sg:postcode":"81040",
    "sg:province":"Caserta",
    "sg:tags":[
        "finished",
        "-",
        "metallic"
    ],
    "wof:name":"Aveta Arredo Bagno Spa",
    "wof:placetype":"venue"
},
  "geometry": {"coordinates":[14.2766647339,41.0787658691],"type":"Point"}
}