{
  "type": "Feature",
  "properties": {
    "addr:full":"26833 Comazzo Comazzo Lodi 26833",
    "addr:postcode":"26833;26833",
    "iso:country":"IT",
    "sg:address":"26833 Comazzo",
    "sg:city":"Comazzo",
    "sg:orig_category":"Pubblica Amministrazione",
    "sg:phone":"+39 02 906 1328",
    "sg:postcode":"26833",
    "sg:province":"Lodi",
    "wof:name":"Poste Italiane Spa",
    "wof:placetype":"venue"
},
  "geometry": {"coordinates":[9.4651794434,45.4426231384],"type":"Point"}
}