{
  "type": "Feature",
  "properties": {
    "addr:full":"14, Via Coccola 41057 Spilamberto Spilamberto Modena 41057",
    "addr:postcode":"41057;41057",
    "addr:street":"Via Coccola",
    "iso:country":"IT",
    "sg:address":"14, Via Coccola 41057 Spilamberto",
    "sg:city":"Spilamberto",
    "sg:classifiers":[
        {
            "category":"Sports & Exercise",
            "subcategory":"Playing Field",
            "type":"Entertainment"
        }
    ],
    "sg:phone":"+39 39059783378",
    "sg:postcode":"41057",
    "sg:province":"Modena",
    "sg:tags":[
        "game"
    ],
    "wof:name":"Emiliana Luna Park Di De Maria Gian Luigi",
    "wof:placetype":"venue"
},
  "geometry": {"coordinates":[11.015471,44.515503],"type":"Point"}
}