{
  "type": "Feature",
  "properties": {
    "iso:country":"IT",
    "sg:address":"21100 Varese",
    "sg:city":"Varese",
    "sg:orig_category":"Medici Specialisti - Andrologia",
    "sg:phone":"+39 0332 289533",
    "sg:postcode":"21100",
    "sg:province":"Varese",
    "wof:name":"Dott. Marconi Alberto Mario",
    "wof:placetype":"venue"
},
  "geometry": {"coordinates":[8.790376,45.887997],"type":"Point"}
}