{
  "type": "Feature",
  "properties": {
    "addr:full":"00166 Roma Roma Roma 00166",
    "addr:postcode":"00166;00166",
    "iso:country":"IT",
    "sg:address":"00166 Roma",
    "sg:city":"Roma",
    "sg:orig_category":"Chiese Ed Associazioni Religiose",
    "sg:phone":"+39 06 614 0262",
    "sg:postcode":"00166",
    "sg:province":"Roma",
    "wof:name":"Iglesia Ni Cristo",
    "wof:placetype":"venue"
},
  "geometry": {"coordinates":[12.383321,41.923008],"type":"Point"}
}