{
  "type": "Feature",
  "properties": {
    "iso:country":"IT",
    "sg:address":"06129 Perugia",
    "sg:city":"Perugia",
    "sg:orig_category":"Case Editrici",
    "sg:phone":"+39 075 528 7141",
    "sg:postcode":"06129",
    "sg:province":"Perugia",
    "wof:name":"G.p.r. Snc",
    "wof:placetype":"venue"
},
  "geometry": {"coordinates":[12.348722,43.068485],"type":"Point"}
}