{
  "type": "Feature",
  "properties": {
    "iso:country":"IT",
    "sg:address":"42, Via Leonardo Da Vinci 35018 San Martino Di Lupari",
    "sg:city":"San Martino di Lupari",
    "sg:classifiers":[
        {
            "category":"Shopping",
            "subcategory":"Stationery & Office Supplies",
            "type":"Retail Goods"
        }
    ],
    "sg:phone":"+39 049 595 2922",
    "sg:postcode":"35018",
    "sg:province":"Padova",
    "sg:tags":[
        "professional"
    ],
    "wof:name":"Bergamin Attilio",
    "wof:placetype":"venue"
},
  "geometry": {"coordinates":[11.866112709,45.6457252502],"type":"Point"}
}