{
  "type": "Feature",
  "properties": {
    "iso:country":"IT",
    "sg:address":"Corso Vittorio Emanuelle; Roma; 00186",
    "sg:city":"Roma",
    "sg:classifiers":[
        {
            "category":"Banks & Credit Unions",
            "subcategory":"Bank",
            "type":"Services"
        }
    ],
    "sg:phone":"+39 06 689 3240",
    "sg:postcode":"00186",
    "sg:province":"Roma",
    "wof:name":"Credito Varesino",
    "wof:placetype":"venue"
},
  "geometry": {"coordinates":[12.471713,41.897091],"type":"Point"}
}