{
  "type": "Feature",
  "properties": {
    "iso:country":"IT",
    "sg:address":"1, Strada Ii Zona Industriale 95121 Catania",
    "sg:city":"Catania",
    "sg:classifiers":[
        {
            "category":"Wholesale",
            "subcategory":"Machinery & Supplies",
            "type":"Manufacturing & Wholesale Goods"
        }
    ],
    "sg:phone":"+39 39095591133",
    "sg:postcode":"95121",
    "sg:province":"Catania",
    "sg:tags":[
        "-",
        "agriculture",
        "equipment"
    ],
    "wof:name":"Agris Srl",
    "wof:placetype":"venue"
},
  "geometry": {"coordinates":[15.0661678314,37.4674224854],"type":"Point"}
}