{
  "type": "Feature",
  "properties": {
    "iso:country":"IT",
    "sg:address":"73100 Lecce",
    "sg:city":"Lecce",
    "sg:orig_category":"Informatica - Consulenza E Software",
    "sg:phone":"+39 0832 317933",
    "sg:postcode":"73100",
    "sg:province":"Lecce",
    "wof:name":"Informatica E Tecnologia Srl",
    "wof:placetype":"venue"
},
  "geometry": {"coordinates":[18.187634,40.356071],"type":"Point"}
}