{
  "type": "Feature",
  "properties": {
    "iso:country":"IT",
    "sg:address":"00185 Roma",
    "sg:city":"Roma",
    "sg:orig_category":"Metalli E Leghe",
    "sg:phone":"+39 06 490754",
    "sg:postcode":"00185",
    "sg:province":"Roma",
    "wof:name":"Bruccola Giovanni",
    "wof:placetype":"venue"
},
  "geometry": {"coordinates":[13.1814661026,41.5230560303],"type":"Point"}
}