{
  "type": "Feature",
  "properties": {
    "iso:country":"IT",
    "sg:address":"04012 Cisterna Di Latina",
    "sg:city":"Cisterna di Latina",
    "sg:orig_category":"Trattamenti Termici E Superficiali Metalli, Galvanotecnica",
    "sg:phone":"+39 06 968 5426",
    "sg:postcode":"04012",
    "sg:province":"Latina",
    "wof:name":"Oxyver Teknik Srl",
    "wof:placetype":"venue"
},
  "geometry": {"coordinates":[12.814796,41.494957],"type":"Point"}
}