{
  "type": "Feature",
  "properties": {
    "addr:full":"25040 Corte Franca Corte Franca Brescia 25040",
    "addr:housenumber":"25040",
    "addr:postcode":"25040",
    "addr:street":"Corte",
    "iso:country":"IT",
    "sg:address":"25040 Corte Franca",
    "sg:city":"Corte Franca",
    "sg:orig_category":"Acciaierie E Fonderie",
    "sg:phone":"+39 030 988 4118",
    "sg:postcode":"25040",
    "sg:province":"Brescia",
    "wof:name":"Fonderia Di Cortefranca Srl",
    "wof:placetype":"venue"
},
  "geometry": {"coordinates":[10.000555,45.647438],"type":"Point"}
}