{
  "type": "Feature",
  "properties": {
    "iso:country":"IT",
    "sg:address":"13, Strada Bassa Nuova - Coloreto 43100 Parma",
    "sg:city":"Parma",
    "sg:classifiers":[
        {
            "category":"Building & Trades",
            "subcategory":"Construction",
            "type":"Services"
        }
    ],
    "sg:phone":"+39 0521 645195",
    "sg:postcode":"43100",
    "sg:province":"Parma",
    "sg:tags":[
        "work",
        "public"
    ],
    "wof:name":"Impresa Ferrari Renato Di Ferrari Gianni E C (s.n.c.)",
    "wof:placetype":"venue"
},
  "geometry": {"coordinates":[10.377016,44.767475],"type":"Point"}
}