{
  "type": "Feature",
  "properties": {
    "iso:country":"IT",
    "sg:address":"00041 Albano Laziale",
    "sg:city":"Albano Laziale",
    "sg:orig_category":"Macchine, Impianti Ed Attrezzature Per Industria Alimentare E Bevande",
    "sg:phone":"+39 06 934 5423",
    "sg:postcode":"00041",
    "sg:province":"Roma",
    "wof:name":"Alfatek S.r.l.",
    "wof:placetype":"venue"
},
  "geometry": {"coordinates":[12.622416,41.71077],"type":"Point"}
}