{
  "type": "Feature",
  "properties": {
    "addr:full":"20020 Vanzaghello Vanzaghello Milano 20020",
    "addr:postcode":"20020;20020",
    "iso:country":"IT",
    "sg:address":"20020 Vanzaghello",
    "sg:city":"Vanzaghello",
    "sg:orig_category":"Automatismi Elettrici, Elettronici E Pneumatici",
    "sg:phone":"+39 0331 307052",
    "sg:postcode":"20020",
    "sg:province":"Milano",
    "sg:website":"http://www.cogi.it",
    "wof:name":"Cogi Elettronica Srl",
    "wof:placetype":"venue"
},
  "geometry": {"coordinates":[9.055713,45.489727],"type":"Point"}
}