{
  "type": "Feature",
  "properties": {
    "addr:full":"Via Dei Mille 57021 Campiglia Marittima Campiglia Marittima Livorno 57021",
    "addr:postcode":"57021;57021",
    "addr:street":"Via Dei Mille",
    "iso:country":"IT",
    "sg:address":"Via Dei Mille 57021 Campiglia Marittima",
    "sg:city":"Campiglia Marittima",
    "sg:classifiers":[
        {
            "category":"Manufacturing",
            "subcategory":"Rubber & Plastics",
            "type":"Manufacturing & Wholesale Goods"
        }
    ],
    "sg:phone":"+39 39056585661",
    "sg:postcode":"57021",
    "sg:province":"Livorno",
    "wof:name":"Venplast Srl",
    "wof:placetype":"venue"
},
  "geometry": {"coordinates":[10.6059732437,43.0268745422],"type":"Point"}
}