{
  "type": "Feature",
  "properties": {
    "iso:country":"IT",
    "sg:address":"20121 Milano",
    "sg:city":"Milano",
    "sg:orig_category":"Servizi Editoriali. Professionisti - Studi E Servizi Ed Associazioni Di Interesse Aziendale",
    "sg:phone":"+39 02 780692",
    "sg:postcode":"20121",
    "sg:province":"Milano",
    "wof:name":"Azzini Clemente",
    "wof:placetype":"venue"
},
  "geometry": {"coordinates":[9.195242,45.471039],"type":"Point"}
}