{
  "type": "Feature",
  "properties": {
    "iso:country":"IT",
    "sg:address":"11, Via Raffaello 52035 Monterchi",
    "sg:city":"Monterchi",
    "sg:classifiers":[
        {
            "category":"Shopping",
            "subcategory":"Clothing, Apparel, & Fashions",
            "type":"Retail Goods"
        }
    ],
    "sg:phone":"+39 39057570359",
    "sg:postcode":"52035",
    "sg:province":"Arezzo",
    "sg:tags":[
        "clothes"
    ],
    "wof:name":"Confezioni Falcon (s.r.l.)",
    "wof:placetype":"venue"
},
  "geometry": {"coordinates":[12.079852,43.485756],"type":"Point"}
}