{
  "type": "Feature",
  "properties": {
    "iso:country":"IT",
    "sg:address":"80126 Napoli",
    "sg:city":"Napoli",
    "sg:orig_category":"Disinfezione, Disinfestazione E Derattizzazione",
    "sg:phone":"+39 081 728 0604",
    "sg:postcode":"80126",
    "sg:province":"Napoli",
    "sg:website":"http://www.anthiratcontrol.it",
    "wof:name":"Anthirat Control",
    "wof:placetype":"venue"
},
  "geometry": {"coordinates":[14.202069,40.84412],"type":"Point"}
}