{
  "type": "Feature",
  "properties": {
    "iso:country":"IT",
    "sg:address":"10, Via Cervi Fratelli 96016 Lentini",
    "sg:city":"Lentini",
    "sg:orig_category":"Miscellaneous Products",
    "sg:phone":"+39 095 783 5606",
    "sg:postcode":"96016",
    "sg:province":"Siracusa",
    "wof:name":"Max Srl",
    "wof:placetype":"venue"
},
  "geometry": {"coordinates":[15.2844400406,37.0664825439],"type":"Point"}
}