{
  "type": "Feature",
  "properties": {
    "iso:country":"IT",
    "sg:address":"48022 Lugo",
    "sg:city":"Lugo",
    "sg:orig_category":"Trasporto Pubblico E Privato",
    "sg:phone":"+39 0545 26423",
    "sg:postcode":"48022",
    "sg:province":"Ravenna",
    "wof:name":"Taxi Rosso Di Angelo Tabanelli",
    "wof:placetype":"venue"
},
  "geometry": {"coordinates":[11.856597,44.443882],"type":"Point"}
}