{
  "type": "Feature",
  "properties": {
    "iso:country":"IT",
    "sg:address":"07041 Alghero",
    "sg:city":"Alghero",
    "sg:orig_category":"Palificazioni, Fondazioni E Consolidamenti",
    "sg:phone":"+39 079 984320",
    "sg:postcode":"07041",
    "sg:province":"Sassari",
    "wof:name":"Sanna Mario & Venturi Bruno Snc",
    "wof:placetype":"venue"
},
  "geometry": {"coordinates":[8.286948204,40.641040802],"type":"Point"}
}