{
  "type": "Feature",
  "properties": {
    "iso:country":"IT",
    "sg:address":"5, Via Chiesa 37060 Erbe'",
    "sg:classifiers":[
        {
            "category":"Sports & Exercise",
            "subcategory":"Playing Field",
            "type":"Entertainment"
        }
    ],
    "sg:phone":"+39 045 732 5744",
    "sg:postcode":"37060",
    "sg:province":"Verona",
    "sg:tags":[
        "game"
    ],
    "wof:name":"Bercelli (s.r.l.)",
    "wof:placetype":"venue"
},
  "geometry": {"coordinates":[10.969256,45.240631],"type":"Point"}
}