{
  "type": "Feature",
  "properties": {
    "addr:full":"18038 Sanremo Imperia 18038",
    "addr:postcode":"18038;18038",
    "iso:country":"IT",
    "sg:address":"18038 Sanremo",
    "sg:orig_category":"Avvocati - Studi",
    "sg:phone":"+39 0184 500063",
    "sg:postcode":"18038",
    "sg:province":"Imperia",
    "wof:name":"Rovere Avv. Andrea",
    "wof:placetype":"venue"
},
  "geometry": {"coordinates":[7.781303,43.819618],"type":"Point"}
}