{
  "type": "Feature",
  "properties": {
    "iso:country":"IT",
    "sg:address":"20122 Milano",
    "sg:city":"Milano",
    "sg:orig_category":"Assicurazioni E Servizi Assicurativi. Consulenze Tecniche, Amministrative E Perizie",
    "sg:phone":"+39 02 778011",
    "sg:postcode":"20122",
    "sg:province":"Milano",
    "wof:name":"April Spa",
    "wof:placetype":"venue"
},
  "geometry": {"coordinates":[9.199107,45.466503],"type":"Point"}
}