{
  "type": "Feature",
  "properties": {
    "iso:country":"IT",
    "sg:address":"03043 Cassino",
    "sg:city":"Cappella Morrone",
    "sg:orig_category":"Marmo Ed Affini - Lavorazione",
    "sg:phone":"+39 0776 366793",
    "sg:postcode":"03043",
    "sg:province":"Frosinone",
    "wof:name":"Russo Angelo",
    "wof:placetype":"venue"
},
  "geometry": {"coordinates":[13.874233,41.484528],"type":"Point"}
}