{
  "type": "Feature",
  "properties": {
    "iso:country":"IT",
    "sg:address":"26, Via Artigianato 36057 Arcugnano",
    "sg:city":"Arcugnano",
    "sg:classifiers":[
        {
            "category":"Wholesale",
            "subcategory":"Drugs",
            "type":"Manufacturing & Wholesale Goods"
        }
    ],
    "sg:phone":"+39 0444 240460",
    "sg:postcode":"36057",
    "sg:province":"Vicenza",
    "sg:tags":[
        "chemical",
        "pharmaceutical"
    ],
    "wof:name":"Berica Hygiene (s.r.l.)",
    "wof:placetype":"venue"
},
  "geometry": {"coordinates":[11.517685,45.529453],"type":"Point"}
}