{
  "type": "Feature",
  "properties": {
    "iso:country":"IT",
    "sg:address":"20037 Paderno Dugnano",
    "sg:city":"Paderno Dugnano",
    "sg:orig_category":"Servizi E Lavori Per Edilizia E Lavori Pubblici",
    "sg:phone":"+39 02 9904 6550",
    "sg:postcode":"20037",
    "sg:province":"Milano",
    "wof:name":"Bezzetto Massimo",
    "wof:placetype":"venue"
},
  "geometry": {"coordinates":[9.174489,45.566357],"type":"Point"}
}