{
  "type": "Feature",
  "properties": {
    "addr:full":"95127 Catania Catania Catania 95127",
    "addr:postcode":"95127;95127",
    "iso:country":"IT",
    "sg:address":"95127 Catania",
    "sg:city":"Catania",
    "sg:orig_category":"Cine-foto-ottica. Shopping",
    "sg:phone":"+39 095 372944",
    "sg:postcode":"95127",
    "sg:province":"Catania",
    "wof:name":"Ali' Maria",
    "wof:placetype":"venue"
},
  "geometry": {"coordinates":[15.097395,37.51886],"type":"Point"}
}