{
  "type": "Feature",
  "properties": {
    "iso:country":"IT",
    "sg:address":"Voc. Case Sparse - Zona Artig. 05028 Penna In Teverina",
    "sg:city":"Penna in Teverina",
    "sg:classifiers":[
        {
            "category":"Wholesale",
            "subcategory":"Drugs",
            "type":"Manufacturing & Wholesale Goods"
        }
    ],
    "sg:phone":"+39 0744 993050",
    "sg:postcode":"05028",
    "sg:province":"Terni",
    "sg:tags":[
        "chemical",
        "pharmaceutical"
    ],
    "sg:website":"http://www.herbier.it",
    "wof:name":"Herbier",
    "wof:placetype":"venue"
},
  "geometry": {"coordinates":[12.363978,42.509415],"type":"Point"}
}