{
  "type": "Feature",
  "properties": {
    "iso:country":"IT",
    "sg:address":"35020 Albignasego",
    "sg:city":"Albignasego",
    "sg:orig_category":"Automazione E Macchine Per Ufficio",
    "sg:phone":"+39 049 711949",
    "sg:postcode":"35020",
    "sg:province":"Padova",
    "wof:name":"Euroffice Di Neodo Massimiliano",
    "wof:placetype":"venue"
},
  "geometry": {"coordinates":[11.849997,45.38546],"type":"Point"}
}