{
  "type": "Feature",
  "properties": {
    "iso:country":"IT",
    "sg:address":"20050 Sovico",
    "sg:city":"Sovico",
    "sg:orig_category":"Motori Ed Organi Di Trasmissione",
    "sg:phone":"+39 039 201 1904",
    "sg:postcode":"20050",
    "sg:province":"Milano",
    "sg:website":"http://www.comesrl.com",
    "wof:name":"Come Srl",
    "wof:placetype":"venue"
},
  "geometry": {"coordinates":[9.2607908249,45.6449050903],"type":"Point"}
}