{
  "type": "Feature",
  "properties": {
    "iso:country":"IT",
    "sg:address":"14, Via San Vincenzo 66010 Vacri",
    "sg:city":"Vacri",
    "sg:classifiers":[
        {
            "category":"Home & Garden",
            "subcategory":"Home Furnishings",
            "type":"Retail Goods"
        }
    ],
    "sg:phone":"+39 0871 718527",
    "sg:postcode":"66010",
    "sg:province":"Chieti",
    "sg:tags":[
        "household"
    ],
    "wof:name":"Orlando Srl",
    "wof:placetype":"venue"
},
  "geometry": {"coordinates":[14.231243,42.31105],"type":"Point"}
}