{
  "type": "Feature",
  "properties": {
    "iso:country":"IT",
    "sg:address":"00191 Roma",
    "sg:city":"Roma",
    "sg:classifiers":[
        {
            "category":"Restaurant",
            "type":"Food & Drink"
        }
    ],
    "sg:phone":"+39 06 4781 8451",
    "sg:postcode":"00191",
    "sg:province":"Roma",
    "sg:tags":[
        "auxiliary",
        "entertainment",
        "premises",
        "related",
        "catering",
        "similar",
        "public",
        "restaurants"
    ],
    "wof:name":"Foglietta Isabella",
    "wof:placetype":"venue"
},
  "geometry": {"coordinates":[12.466764,41.944519],"type":"Point"}
}