{
  "type": "Feature",
  "properties": {
    "iso:country":"IT",
    "sg:address":"86100 Campobasso",
    "sg:city":"Campobasso",
    "sg:orig_category":"Psicologi - Studi",
    "sg:phone":"+39 0874 411186",
    "sg:postcode":"86100",
    "sg:province":"Campobasso",
    "wof:name":"Di Nunzio Dr. Luigi",
    "wof:placetype":"venue"
},
  "geometry": {"coordinates":[14.6704425812,41.5770835876],"type":"Point"}
}