{
  "type": "Feature",
  "properties": {
    "iso:country":"IT",
    "sg:address":"40013 Castel Maggiore",
    "sg:city":"Castel Maggiore",
    "sg:orig_category":"Impianti, Attrezzature E Forniture Sanitarie Ed Ospedaliere",
    "sg:phone":"+39 051 700877",
    "sg:postcode":"40013",
    "sg:province":"Bologna",
    "sg:website":"http://www.castellini.com",
    "wof:name":"Castellini Spa",
    "wof:placetype":"venue"
},
  "geometry": {"coordinates":[11.373261,44.557774],"type":"Point"}
}