{
  "type": "Feature",
  "properties": {
    "iso:country":"IT",
    "sg:address":"31054 Possagno",
    "sg:city":"Possagno",
    "sg:orig_category":"Materiali Edili",
    "sg:phone":"+39 0423 544878",
    "sg:postcode":"31054",
    "sg:province":"Treviso",
    "wof:name":"Industrie Cotto Possagno S.p.a.",
    "wof:placetype":"venue"
},
  "geometry": {"coordinates":[12.249028,45.666534],"type":"Point"}
}