{
  "type": "Feature",
  "properties": {
    "iso:country":"IT",
    "sg:address":"34123 Trieste",
    "sg:city":"Trieste",
    "sg:orig_category":"Tempo Libero - Articoli E Forniture. Forniture Per Congressi, Fiere E Manifestazioni. Regalistica Aziendale",
    "sg:phone":"+39 040 301887",
    "sg:postcode":"34123",
    "sg:province":"Trieste",
    "wof:name":"Zadro R. Succ. Di A.zadro & C. (s.n.c.)",
    "wof:placetype":"venue"
},
  "geometry": {"coordinates":[13.761509,45.645775],"type":"Point"}
}