{
  "type": "Feature",
  "properties": {
    "iso:country":"IT",
    "sg:address":"20021 Baranzate",
    "sg:city":"Baranzate",
    "sg:orig_category":"Motori Ed Organi Di Trasmissione. Ricambi E Componenti Dei Mezzi Di Trasporto",
    "sg:phone":"+39 02 3820 3183",
    "sg:postcode":"20021",
    "sg:province":"Milano",
    "wof:name":"Carlo De Giorgi S.r.l.",
    "wof:placetype":"venue"
},
  "geometry": {"coordinates":[9.1050615311,45.5232124329],"type":"Point"}
}