{
  "type": "Feature",
  "properties": {
    "addr:full":"27, Viale Francia 20036 Meda Meda Milano 20036",
    "addr:housenumber":"27",
    "addr:postcode":"20036;20036",
    "addr:street":"Viale Francia",
    "iso:country":"IT",
    "sg:address":"27, Viale Francia 20036 Meda",
    "sg:city":"Meda",
    "sg:classifiers":[
        {
            "category":"Professional",
            "subcategory":"Engineering",
            "type":"Services"
        }
    ],
    "sg:phone":"+39 39036270877",
    "sg:postcode":"20036",
    "sg:province":"Milano",
    "sg:tags":[
        "machine",
        "-",
        "mechanical"
    ],
    "wof:name":"Meccanica Medese (s.r.l.)",
    "wof:placetype":"venue"
},
  "geometry": {"coordinates":[9.155654,45.660427],"type":"Point"}
}