{
  "type": "Feature",
  "properties": {
    "iso:country":"IT",
    "sg:address":"21040 Gerenzano",
    "sg:city":"Gerenzano",
    "sg:orig_category":"Macchine Utensili E Impianti",
    "sg:phone":"+39 02 968 0057",
    "sg:postcode":"21040",
    "sg:province":"Varese",
    "wof:name":"Isopresse Sas Di Cazzitti E C.",
    "wof:placetype":"venue"
},
  "geometry": {"coordinates":[9.00444,45.638321],"type":"Point"}
}