{
  "type": "Feature",
  "properties": {
    "iso:country":"IT",
    "sg:address":"9, Via Cocapanna 46026 Quistello",
    "sg:city":"Quistello",
    "sg:classifiers":[
        {
            "category":"Real Estate",
            "subcategory":"Architect",
            "type":"Services"
        }
    ],
    "sg:phone":"+39 0376 625369",
    "sg:postcode":"46026",
    "sg:province":"Mantova",
    "sg:tags":[
        "textile",
        "clothing"
    ],
    "wof:name":"M I R T A Snc",
    "wof:placetype":"venue"
},
  "geometry": {"coordinates":[10.982933,45.005325],"type":"Point"}
}