{
  "type": "Feature",
  "properties": {
    "addr:full":"28921 Biganzolo Verbano-Cusio-Ossola 28921",
    "addr:postcode":"28921;28921",
    "iso:country":"IT",
    "sg:address":"28921 Biganzolo",
    "sg:orig_category":"Macchine, Impianti Ed Attrezzature Per Abbigliamento E Pelletterie",
    "sg:phone":"+39 0323 53509",
    "sg:postcode":"28921",
    "sg:province":"Verbano-Cusio-Ossola",
    "wof:name":"Lomazzi Anna Maria",
    "wof:placetype":"venue"
},
  "geometry": {"coordinates":[8.584571,45.941742],"type":"Point"}
}