{
  "type": "Feature",
  "properties": {
    "addr:full":"04011 Aprilia Aprilia Latina 04011",
    "addr:postcode":"04011;04011",
    "iso:country":"IT",
    "sg:address":"04011 Aprilia",
    "sg:city":"Aprilia",
    "sg:orig_category":"Macchine E Forniture Per Industria Orafa E Per Orologeria",
    "sg:phone":"+39 06 9285 5046",
    "sg:postcode":"04011",
    "sg:province":"Latina",
    "wof:name":"Migliaccio Giuseppe",
    "wof:placetype":"venue"
},
  "geometry": {"coordinates":[12.886678,41.464447],"type":"Point"}
}