{
  "type": "Feature",
  "properties": {
    "iso:country":"IT",
    "sg:address":"20122 Milano",
    "sg:city":"Milano",
    "sg:orig_category":"Editoria",
    "sg:phone":"+39 02 7602 3769",
    "sg:postcode":"20122",
    "sg:province":"Milano",
    "wof:name":"Nazionalmusic Edizioni Musicali (s.a.s.)",
    "wof:placetype":"venue"
},
  "geometry": {"coordinates":[9.195943,45.463806],"type":"Point"}
}