{
  "type": "Feature",
  "properties": {
    "addr:full":"8, Via Dei Campi 23883 Brivio Brivio Lecco 23883",
    "addr:postcode":"23883;23883",
    "addr:street":"Via Dei Campi",
    "iso:country":"IT",
    "sg:address":"8, Via Dei Campi 23883 Brivio",
    "sg:city":"Brivio",
    "sg:classifiers":[
        {
            "category":"Professional",
            "subcategory":"Engineering",
            "type":"Services"
        }
    ],
    "sg:phone":"+39 039 532 0732",
    "sg:postcode":"23883",
    "sg:province":"Lecco",
    "sg:tags":[
        "machine",
        "-",
        "mechanical"
    ],
    "wof:name":"A.t.g. (s.r.l.)",
    "wof:placetype":"venue"
},
  "geometry": {"coordinates":[9.390071,45.852982],"type":"Point"}
}