{
  "type": "Feature",
  "properties": {
    "iso:country":"IT",
    "sg:address":"15040 Pecetto Di Valenza",
    "sg:city":"Pecetto di Valenza",
    "sg:orig_category":"Gioielleria, Oreficeria E Argenteria",
    "sg:phone":"+39 0131 940189",
    "sg:postcode":"15040",
    "sg:province":"Alessandria",
    "wof:name":"Marino Salvatore",
    "wof:placetype":"venue"
},
  "geometry": {"coordinates":[8.671669,44.989677],"type":"Point"}
}