{
  "type": "Feature",
  "properties": {
    "iso:country":"IT",
    "sg:address":"53047 Sarteano",
    "sg:city":"Sarteano",
    "sg:orig_category":"Campeggi, Ostelli E Villaggi Turistici",
    "sg:phone":"+39 0578 26971",
    "sg:postcode":"53047",
    "sg:province":"Siena",
    "sg:website":"http://www.parcodellepiscine.it",
    "wof:name":"Parco Campeggio Delle Piscine",
    "wof:placetype":"venue"
},
  "geometry": {"coordinates":[11.863642,42.988171],"type":"Point"}
}