{
  "type": "Feature",
  "properties": {
    "addr:full":"22, Via Ruffini Jacopo 20037 Paderno Dugnano Paderno Dugnano Milano 20037",
    "addr:postcode":"20037;20037",
    "addr:street":"Via Ruffini Jacopo",
    "iso:country":"IT",
    "sg:address":"22, Via Ruffini Jacopo 20037 Paderno Dugnano",
    "sg:city":"Paderno Dugnano",
    "sg:classifiers":[
        {
            "category":"Manufacturing",
            "subcategory":"Metals",
            "type":"Manufacturing & Wholesale Goods"
        }
    ],
    "sg:phone":"+39 39029101518",
    "sg:postcode":"20037",
    "sg:province":"Milano",
    "sg:tags":[
        "processing"
    ],
    "wof:name":"Stampinox (s.r.l.)",
    "wof:placetype":"venue"
},
  "geometry": {"coordinates":[9.1881408691,45.4636878967],"type":"Point"}
}