{
  "type": "Feature",
  "properties": {
    "addr:full":"25080 Prevalle Prevalle Brescia 25080",
    "addr:postcode":"25080;25080",
    "iso:country":"IT",
    "sg:address":"25080 Prevalle",
    "sg:city":"Prevalle",
    "sg:orig_category":"Metalli E Leghe",
    "sg:phone":"+39 030 603259",
    "sg:postcode":"25080",
    "sg:province":"Brescia",
    "wof:name":"Gnutti Virginio (s.p.a.)",
    "wof:placetype":"venue"
},
  "geometry": {"coordinates":[10.4150686264,45.5562782288],"type":"Point"}
}