{
  "type": "Feature",
  "properties": {
    "addr:full":"42/b, Frazione Borgo Grotta Gigante 34010 Sgonico Sgonico Trieste 34010",
    "addr:housenumber":"42 / b",
    "addr:postcode":"34010;34010",
    "addr:street":"Frazione Borgo Grotta Gigante",
    "iso:country":"IT",
    "sg:address":"42/b, Frazione Borgo Grotta Gigante 34010 Sgonico",
    "sg:city":"Sgonico",
    "sg:classifiers":[
        {
            "category":"Sports & Exercise",
            "subcategory":"Playing Field",
            "type":"Entertainment"
        }
    ],
    "sg:phone":"+39 39040327309",
    "sg:postcode":"34010",
    "sg:province":"Trieste",
    "sg:tags":[
        "game"
    ],
    "wof:name":"Tennis Campi Rossi S.n.c.",
    "wof:placetype":"venue"
},
  "geometry": {"coordinates":[13.778407,45.653629],"type":"Point"}
}