{
  "type": "Feature",
  "properties": {
    "addr:full":"10149 Torino Torino Torino 10149",
    "addr:postcode":"10149;10149",
    "iso:country":"IT",
    "sg:address":"10149 Torino",
    "sg:city":"Torino",
    "sg:orig_category":"Incisione Metalli E Plastica",
    "sg:phone":"+39 011 252276",
    "sg:postcode":"10149",
    "sg:province":"Torino",
    "wof:name":"Bocca Giovanni Snc",
    "wof:placetype":"venue"
},
  "geometry": {"coordinates":[7.66514,45.095795],"type":"Point"}
}