{
  "type": "Feature",
  "properties": {
    "iso:country":"IT",
    "sg:address":"Via De' Ruggiero 14 59100 Prato",
    "sg:city":"Prato",
    "sg:classifiers":[
        {
            "category":"Shopping",
            "subcategory":"Clothing, Apparel, & Fashions",
            "type":"Retail Goods"
        }
    ],
    "sg:phone":"+39 0574 632264",
    "sg:postcode":"59100",
    "sg:province":"Prato",
    "sg:tags":[
        "clothing",
        "fabric"
    ],
    "wof:name":"Il Cotonificio Srl",
    "wof:placetype":"venue"
},
  "geometry": {"coordinates":[11.067057,43.862644],"type":"Point"}
}