{
  "type": "Feature",
  "properties": {
    "iso:country":"IT",
    "sg:address":"09170 Oristano",
    "sg:city":"Oristano",
    "sg:orig_category":"Carpenterie Legno",
    "sg:phone":"+39 0783 350004",
    "sg:postcode":"09170",
    "sg:province":"Oristano",
    "wof:name":"Garau Legnami Snc",
    "wof:placetype":"venue"
},
  "geometry": {"coordinates":[8.592362,39.889839],"type":"Point"}
}