{
  "type": "Feature",
  "properties": {
    "addr:full":"36040 Brendola Brendola Vicenza 36040",
    "addr:postcode":"36040;36040",
    "iso:country":"IT",
    "sg:address":"36040 Brendola",
    "sg:city":"Brendola",
    "sg:orig_category":"Arredi Ed Attrezzature Per Uffici",
    "sg:phone":"+39 0444 401510",
    "sg:postcode":"36040",
    "sg:province":"Vicenza",
    "wof:name":"V.d.e. International S.r.l.",
    "wof:placetype":"venue"
},
  "geometry": {"coordinates":[11.450313,45.511791],"type":"Point"}
}