{
  "type": "Feature",
  "properties": {
    "iso:country":"IT",
    "sg:address":"17, Via V. Foppa 23876 Monticello Brianza",
    "sg:city":"Monticello Brianza",
    "sg:classifiers":[
        {
            "category":"Shopping",
            "subcategory":"Crafts & Fabrics",
            "type":"Retail Goods"
        }
    ],
    "sg:phone":"+39 039 920 5100",
    "sg:postcode":"23876",
    "sg:province":"Lecco",
    "wof:name":"Torcitura All'olmo (s.r.l.)",
    "wof:placetype":"venue"
},
  "geometry": {"coordinates":[9.3900709152,45.8529815674],"type":"Point"}
}