{
  "type": "Feature",
  "properties": {
    "iso:country":"IT",
    "sg:address":"53100 Siena",
    "sg:city":"Siena",
    "sg:orig_category":"Elettrotecnica Professionale E Di Consumo. Forniture Per Attivita' Commerciali Ed Artigianali",
    "sg:phone":"+39 0577 223616",
    "sg:postcode":"53100",
    "sg:province":"Siena",
    "wof:name":"Publineonart Snc",
    "wof:placetype":"venue"
},
  "geometry": {"coordinates":[11.365801,43.31971],"type":"Point"}
}