{
  "type": "Feature",
  "properties": {
    "addr:full":"31040 Volpago Del Montello Volpago del Montello Treviso 31040",
    "addr:housenumber":"del montello",
    "addr:postcode":"31040;31040",
    "addr:street":"Del Montello",
    "iso:country":"IT",
    "sg:address":"31040 Volpago Del Montello",
    "sg:city":"Volpago del Montello",
    "sg:orig_category":"Pubblicita', Marketing E Comunicazione",
    "sg:phone":"+39 0423 870385",
    "sg:postcode":"31040",
    "sg:province":"Treviso",
    "wof:name":"Direttorio",
    "wof:placetype":"venue"
},
  "geometry": {"coordinates":[12.1721696854,45.7282676697],"type":"Point"}
}