{
  "type": "Feature",
  "properties": {
    "iso:country":"IT",
    "sg:address":"00167 Roma",
    "sg:city":"Roma",
    "sg:orig_category":"Macchine E Forniture Per Industria Orafa E Per Orologeria",
    "sg:phone":"+39 06 3937 8046",
    "sg:postcode":"00167",
    "sg:province":"Roma",
    "wof:name":"Comezzi Ferruccio E Figli",
    "wof:placetype":"venue"
},
  "geometry": {"coordinates":[12.4396762848,41.9006080627],"type":"Point"}
}