{
  "type": "Feature",
  "properties": {
    "iso:country":"IT",
    "sg:address":"30, Corso Buenos Aires 20124 Milano",
    "sg:city":"Milano",
    "sg:orig_category":"Miscellaneous Products",
    "sg:phone":"+39 02 2940 3148",
    "sg:postcode":"20124",
    "sg:province":"Milano",
    "wof:name":"Te.m.i. (s.r.l.)",
    "wof:placetype":"venue"
},
  "geometry": {"coordinates":[9.2090940475,45.4784736633],"type":"Point"}
}