{
  "type": "Feature",
  "properties": {
    "iso:country":"IT",
    "sg:address":"61026 Piandimeleto",
    "sg:city":"Piandimeleto",
    "sg:orig_category":"Arredamenti - Produzione E Ingrosso",
    "sg:phone":"+39 0722 721321",
    "sg:postcode":"61026",
    "sg:province":"Pesaro E Urbino",
    "sg:website":"http://www.mercantini.it",
    "wof:name":"Mercantini Mobili Spa",
    "wof:placetype":"venue"
},
  "geometry": {"coordinates":[12.414024,43.727726],"type":"Point"}
}