{
  "type": "Feature",
  "properties": {
    "addr:full":"191, Via Dei Colli 50058 Signa Signa Firenze 50058",
    "addr:housenumber":"191",
    "addr:postcode":"50058;50058",
    "addr:street":"Via Dei Colli",
    "iso:country":"IT",
    "sg:address":"191, Via Dei Colli 50058 Signa",
    "sg:city":"Signa",
    "sg:classifiers":[
        {
            "category":"Shopping",
            "subcategory":"Clothing, Apparel, & Fashions",
            "type":"Retail Goods"
        }
    ],
    "sg:phone":"+39 055 899 7518",
    "sg:postcode":"50058",
    "sg:province":"Firenze",
    "sg:tags":[
        "clothing",
        "accessory"
    ],
    "wof:name":"Catarzi Filippo S.a.s.",
    "wof:placetype":"venue"
},
  "geometry": {"coordinates":[11.113518,43.802715],"type":"Point"}
}