{
  "type": "Feature",
  "properties": {
    "iso:country":"IT",
    "sg:address":"22060 Novedrate",
    "sg:city":"Novedrate",
    "sg:orig_category":"Servizi E Lavori Per Arredamento E Industria Del Legno. Arte Ed Artigianato Artistico",
    "sg:phone":"+39 031 791036",
    "sg:postcode":"22060",
    "sg:province":"Como",
    "wof:name":"Marelli Emilio E Marco",
    "wof:placetype":"venue"
},
  "geometry": {"coordinates":[9.120639,45.700275],"type":"Point"}
}