{
  "type": "Feature",
  "properties": {
    "iso:country":"IT",
    "sg:address":"00154 Roma",
    "sg:city":"Roma",
    "sg:orig_category":"Servizi E Lavori Per Edilizia E Lavori Pubblici. Servizi Ausiliari Di Sorveglianza, Manutenzione E Pulizia",
    "sg:phone":"+39 06 575 9454",
    "sg:postcode":"00154",
    "sg:province":"Roma",
    "wof:name":"C.l.c. Srl",
    "wof:placetype":"venue"
},
  "geometry": {"coordinates":[12.485743,41.867775],"type":"Point"}
}