{
  "type": "Feature",
  "properties": {
    "addr:full":"Via Don Luigi Pozzi 34 20020 Robecchetto Con Induno Robecchetto con Induno Milano 20020",
    "addr:housenumber":"34",
    "addr:postcode":"20020;20020",
    "addr:street":"Via Don Luigi Pozzi;Con Induno",
    "iso:country":"IT",
    "sg:address":"Via Don Luigi Pozzi 34 20020 Robecchetto Con Induno",
    "sg:city":"Robecchetto con Induno",
    "sg:classifiers":[
        {
            "category":"Home & Garden",
            "subcategory":"Household Appliances",
            "type":"Retail Goods"
        }
    ],
    "sg:phone":"+39 0331 875697",
    "sg:postcode":"20020",
    "sg:province":"Milano",
    "sg:tags":[
        "thermostat"
    ],
    "sg:website":"www.thermomess.com",
    "wof:name":"Thermomess Srl",
    "wof:placetype":"venue"
},
  "geometry": {"coordinates":[9.188141,45.463688],"type":"Point"}
}