{
  "type": "Feature",
  "properties": {
    "addr:full":"00145 Roma Roma Roma 00145",
    "addr:postcode":"00145;00145",
    "iso:country":"IT",
    "sg:address":"00145 Roma",
    "sg:city":"Roma",
    "sg:orig_category":"Palestre",
    "sg:phone":"+39 06 540 4663",
    "sg:postcode":"00145",
    "sg:province":"Roma",
    "wof:name":"Ass. Cult. E Sportiva La Piroetta",
    "wof:placetype":"venue"
},
  "geometry": {"coordinates":[12.4799051285,41.8513221741],"type":"Point"}
}