{
  "type": "Feature",
  "properties": {
    "iso:country":"IT",
    "sg:address":"00040 Pomezia",
    "sg:city":"Pomezia",
    "sg:orig_category":"Facchinaggio, Carico E Scarico Merci, Portabagagli - Servizio",
    "sg:phone":"+39 06 910 4412",
    "sg:postcode":"00040",
    "sg:province":"Roma",
    "wof:name":"Nuova Pomezia 90 Srl",
    "wof:placetype":"venue"
},
  "geometry": {"coordinates":[12.4956197739,41.6576957703],"type":"Point"}
}