{
  "type": "Feature",
  "properties": {
    "addr:full":"04011 Aprilia Aprilia Latina 04011",
    "addr:postcode":"04011;04011",
    "iso:country":"IT",
    "sg:address":"04011 Aprilia",
    "sg:city":"Aprilia",
    "sg:orig_category":"Manufacturers: Prefabbricati",
    "sg:phone":"+39 06 928 3234",
    "sg:postcode":"04011",
    "sg:province":"Latina",
    "wof:name":"Co.i.m.u. Di Melotti Ugo",
    "wof:placetype":"venue"
},
  "geometry": {"coordinates":[12.895775,41.4547],"type":"Point"}
}