{
  "type": "Feature",
  "properties": {
    "iso:country":"IT",
    "sg:address":"20066 Melzo",
    "sg:city":"Melzo",
    "sg:classifiers":[
        {
            "category":"Health Services",
            "subcategory":"Health Practitioner",
            "type":"Services"
        }
    ],
    "sg:phone":"+39 02 955 1842",
    "sg:postcode":"20066",
    "sg:province":"Milano",
    "sg:tags":[
        "medici"
    ],
    "wof:name":"Prandi Mauro Eugenio",
    "wof:placetype":"venue"
},
  "geometry": {"coordinates":[9.1015825272,45.5032119751],"type":"Point"}
}