{
  "type": "Feature",
  "properties": {
    "iso:country":"IT",
    "sg:address":"62019 Recanati",
    "sg:city":"Recanati",
    "sg:orig_category":"Musica",
    "sg:phone":"+39 071 757 4384",
    "sg:postcode":"62019",
    "sg:province":"Macerata",
    "wof:name":"Nibaldi F.lli Di Nibaldi Franco E Giancarlo Snc",
    "wof:placetype":"venue"
},
  "geometry": {"coordinates":[13.479300499,43.3569259644],"type":"Point"}
}