{
  "type": "Feature",
  "properties": {
    "iso:country":"IT",
    "sg:address":"Via Tito Speri 12 00040 Pomezia",
    "sg:city":"Pomezia",
    "sg:classifiers":[
        {
            "category":"Professional",
            "subcategory":"Research",
            "type":"Services"
        }
    ],
    "sg:phone":"+39 06 910951",
    "sg:postcode":"00040",
    "sg:province":"Roma",
    "sg:tags":[
        "opinion",
        "market"
    ],
    "sg:website":"www.rtc.it",
    "wof:name":"Research Toxicology Centre Spa",
    "wof:placetype":"venue"
},
  "geometry": {"coordinates":[12.487879,41.670609],"type":"Point"}
}