{
  "type": "Feature",
  "properties": {
    "iso:country":"IT",
    "sg:address":"41053 Maranello",
    "sg:city":"Maranello",
    "sg:classifiers":[
        {
            "category":"Manufacturing",
            "subcategory":"Tools & Machinery",
            "type":"Manufacturing & Wholesale Goods"
        }
    ],
    "sg:phone":"+39 0536 948317",
    "sg:postcode":"41053",
    "sg:province":"Modena",
    "sg:tags":[
        "machine",
        "system"
    ],
    "sg:website":"http://www.tecoma.it",
    "wof:name":"Tecoma Srl",
    "wof:placetype":"venue"
},
  "geometry": {"coordinates":[10.877491,44.531876],"type":"Point"}
}