{
  "type": "Feature",
  "properties": {
    "iso:country":"IT",
    "sg:address":"10/a, Via Faraci 95126 Catania",
    "sg:city":"Catania",
    "sg:classifiers":[
        {
            "category":"Professional",
            "subcategory":"Printing & Photocopies",
            "type":"Services"
        }
    ],
    "sg:phone":"+39 39095372478",
    "sg:postcode":"95126",
    "sg:province":"Catania",
    "wof:name":"Litografica Mediterranea Di Tringale Salvatrice E C",
    "wof:placetype":"venue"
},
  "geometry": {"coordinates":[15.0973100662,37.5273208618],"type":"Point"}
}