{
  "type": "Feature",
  "properties": {
    "iso:country":"IT",
    "sg:address":"03023 Ceccano",
    "sg:city":"Ceccano",
    "sg:orig_category":"Mobili - Vendita Al Dettaglio",
    "sg:phone":"+39 0775 600425",
    "sg:postcode":"03023",
    "sg:province":"Frosinone",
    "wof:name":"Fratelli Viola Snc",
    "wof:placetype":"venue"
},
  "geometry": {"coordinates":[13.337975502,41.6211013794],"type":"Point"}
}