{
  "type": "Feature",
  "properties": {
    "addr:full":"Via Rivolta 34/a 56029 Santa Croce Sull'arno Pisa 56029",
    "addr:housenumber":"34 / a",
    "addr:postcode":"56029;56029",
    "addr:street":"Via Rivolta",
    "iso:country":"IT",
    "sg:address":"Via Rivolta 34/a 56029 Santa Croce Sull'arno",
    "sg:classifiers":[
        {
            "category":"Manufacturing",
            "subcategory":"Tools & Machinery",
            "type":"Manufacturing & Wholesale Goods"
        }
    ],
    "sg:phone":"+39 0571 32258",
    "sg:postcode":"56029",
    "sg:province":"Pisa",
    "sg:tags":[
        "tannery"
    ],
    "sg:website":"www.soldani.it",
    "wof:name":"Officina Meccanica Soldani Srl",
    "wof:placetype":"venue"
},
  "geometry": {"coordinates":[10.396585,43.716137],"type":"Point"}
}