{
  "type": "Feature",
  "properties": {
    "addr:full":"Via Della Tecnica, 22/24 56024 Ponte A Egola Ponte a egola Pisa 56024",
    "addr:housenumber":"22 / 24",
    "addr:postcode":"56024;56024",
    "addr:street":"Via Della Tecnica;Egola Ponte A",
    "iso:country":"IT",
    "sg:address":"Via Della Tecnica, 22/24 56024 Ponte A Egola",
    "sg:city":"Ponte a egola",
    "sg:classifiers":[
        {
            "category":"Home & Garden",
            "subcategory":"Carpets & Floor Coverings",
            "type":"Retail Goods"
        }
    ],
    "sg:phone":"+39 0571 498355",
    "sg:postcode":"56024",
    "sg:province":"Pisa",
    "sg:tags":[
        "animal",
        "skin"
    ],
    "wof:name":"Conceria Italpel Spa",
    "wof:placetype":"venue"
},
  "geometry": {"coordinates":[10.784584,43.693356],"type":"Point"}
}