{
  "type": "Feature",
  "properties": {
    "iso:country":"IT",
    "sg:address":"Piazza Umberto I 26; Realmonte; 92010",
    "sg:city":"Realmonte",
    "sg:classifiers":[
        {
            "category":"Banks & Credit Unions",
            "subcategory":"Bank",
            "type":"Services"
        }
    ],
    "sg:phone":"+39 0922 816254",
    "sg:postcode":"92010",
    "sg:province":"Agrigento",
    "wof:name":"Istituto Bancario, San Paolo Di Torino Spa",
    "wof:placetype":"venue"
},
  "geometry": {"coordinates":[13.462439,37.306961],"type":"Point"}
}