{
  "type": "Feature",
  "properties": {
    "iso:country":"IT",
    "sg:address":"25064 Gussago",
    "sg:city":"Gussago",
    "sg:orig_category":"Spurgo Fognature E Pozzi Neri",
    "sg:phone":"+39 030 311509",
    "sg:postcode":"25064",
    "sg:province":"Brescia",
    "wof:name":"Tomasoni Giosue' Spurghi S.n.c. Di Frapporti Monia & C.",
    "wof:placetype":"venue"
},
  "geometry": {"coordinates":[10.151052,45.553432],"type":"Point"}
}