{
  "type": "Feature",
  "properties": {
    "addr:full":"11024 Chatillon Chatillon Aosta 11024",
    "addr:postcode":"11024;11024",
    "iso:country":"IT",
    "sg:address":"11024 Chatillon",
    "sg:city":"Chatillon",
    "sg:orig_category":"Termotecnica E Riscaldamento, Apparecchiature E Servizi",
    "sg:phone":"+39 0166 62265",
    "sg:postcode":"11024",
    "sg:province":"Aosta",
    "wof:name":"Elettrotermica Snc Di Dujany Ing. Livio",
    "wof:placetype":"venue"
},
  "geometry": {"coordinates":[7.623884,45.753639],"type":"Point"}
}