{
  "type": "Feature",
  "properties": {
    "iso:country":"IT",
    "sg:address":"Corso Giovanni; Montanao Antilla; 84060",
    "sg:classifiers":[
        {
            "category":"Banks & Credit Unions",
            "subcategory":"Bank",
            "type":"Services"
        }
    ],
    "sg:phone":"+39 0974 951537",
    "sg:postcode":"84060",
    "sg:province":"Salerno",
    "wof:name":"Banco Di Napoli Spa",
    "wof:placetype":"venue"
},
  "geometry": {"coordinates":[15.369808,40.163193],"type":"Point"}
}