{
  "type": "Feature",
  "properties": {
    "iso:country":"IT",
    "sg:address":"00015 Monterotondo",
    "sg:city":"Monterotondo",
    "sg:orig_category":"Abrasivi",
    "sg:phone":"+39 06 9008 5148",
    "sg:postcode":"00015",
    "sg:province":"Roma",
    "wof:name":"Italchimica Lazio Srl",
    "wof:placetype":"venue"
},
  "geometry": {"coordinates":[12.595741,42.076199],"type":"Point"}
}