{
  "type": "Feature",
  "properties": {
    "iso:country":"IT",
    "sg:address":"10070 Rocca Canavese",
    "sg:city":"Rocca Canavese",
    "sg:orig_category":"Legno E Semilavorati",
    "sg:phone":"+39 011 924 0303",
    "sg:postcode":"10070",
    "sg:province":"Torino",
    "wof:name":"Baima Besquet Domenico",
    "wof:placetype":"venue"
},
  "geometry": {"coordinates":[7.577352,45.310795],"type":"Point"}
}