{
  "type": "Feature",
  "properties": {
    "iso:country":"IT",
    "sg:address":"Via Michelangelo Buonarroti 59013 Montemurlo",
    "sg:city":"Montemurlo",
    "sg:classifiers":[
        {
            "category":"Shopping",
            "subcategory":"Crafts & Fabrics",
            "type":"Retail Goods"
        }
    ],
    "sg:phone":"+39 0574 720157",
    "sg:postcode":"59013",
    "sg:province":"Prato",
    "wof:name":"Manifattura Moderna Lane (s.n.c.)",
    "wof:placetype":"venue"
},
  "geometry": {"coordinates":[11.1213655472,43.9708518982],"type":"Point"}
}