{
  "type": "Feature",
  "properties": {
    "addr:full":"12, Via Cavour 41037 Mirandola Mirandola Modena 41037",
    "addr:postcode":"41037;41037",
    "addr:street":"Via Cavour",
    "iso:country":"IT",
    "sg:address":"12, Via Cavour 41037 Mirandola",
    "sg:city":"Mirandola",
    "sg:classifiers":[
        {
            "category":"Shopping",
            "subcategory":"Clothing, Apparel, & Fashions",
            "type":"Retail Goods"
        }
    ],
    "sg:phone":"+39 39053523606",
    "sg:postcode":"41037",
    "sg:province":"Modena",
    "sg:tags":[
        "clothes"
    ],
    "wof:name":"Bonini",
    "wof:placetype":"venue"
},
  "geometry": {"coordinates":[11.000317,44.826992],"type":"Point"}
}