{
  "type": "Feature",
  "properties": {
    "iso:country":"IT",
    "sg:address":"5, Via Dell' Industria 06065 Passignano Sul Trasimeno",
    "sg:city":"Passignano sul Trasimeno",
    "sg:classifiers":[
        {
            "category":"Autos & Motor Vehicles",
            "subcategory":"Automobile Sales",
            "type":"Retail Goods"
        }
    ],
    "sg:phone":"+39 39075829301",
    "sg:postcode":"06065",
    "sg:province":"Perugia",
    "sg:tags":[
        "motor-cars"
    ],
    "wof:name":"Coloni Motorsport Srl",
    "wof:placetype":"venue"
},
  "geometry": {"coordinates":[12.1165208817,43.1977844238],"type":"Point"}
}