{
  "type": "Feature",
  "properties": {
    "iso:country":"IT",
    "sg:address":"98070 Torrenova",
    "sg:city":"Torrenova",
    "sg:orig_category":"Bevande, Vini E Liquori",
    "sg:phone":"+39 0941 958086",
    "sg:postcode":"98070",
    "sg:province":"Messina",
    "wof:name":"Sicilbega Srl",
    "wof:placetype":"venue"
},
  "geometry": {"coordinates":[14.711705,38.100792],"type":"Point"}
}