{
  "type": "Feature",
  "properties": {
    "iso:country":"IT",
    "sg:address":"93012 Gela",
    "sg:city":"Gela",
    "sg:orig_category":"Engineering Societa'",
    "sg:phone":"+39 0933 844577",
    "sg:postcode":"93012",
    "sg:province":"Caltanissetta",
    "wof:name":"Sering Engineering Service",
    "wof:placetype":"venue"
},
  "geometry": {"coordinates":[14.063735,37.488335],"type":"Point"}
}