{
  "type": "Feature",
  "properties": {
    "iso:country":"IT",
    "sg:address":"95125 Tremestieri Etneo",
    "sg:orig_category":"Impianti, Attrezzature E Forniture Sanitarie Ed Ospedaliere",
    "sg:phone":"+39 095 338811",
    "sg:postcode":"95125",
    "sg:province":"Catania",
    "wof:name":"Arthos Srl",
    "wof:placetype":"venue"
},
  "geometry": {"coordinates":[15.106057,37.56324],"type":"Point"}
}