{
  "type": "Feature",
  "properties": {
    "iso:country":"IT",
    "sg:address":"89013 Gioia Tauro",
    "sg:city":"Gioia Tauro",
    "sg:orig_category":"Servizi E Lavori Per Arredamento E Industria Del Legno. Arte Ed Artigianato Artistico",
    "sg:phone":"+39 0966 500849",
    "sg:postcode":"89013",
    "sg:province":"Reggio Di Calabria",
    "wof:name":"Zara Domenico Antonio - Habitart",
    "wof:placetype":"venue"
},
  "geometry": {"coordinates":[15.890885,38.433399],"type":"Point"}
}