{
  "type": "Feature",
  "properties": {
    "iso:country":"IT",
    "sg:address":"Pl Xxvi Luglio 62; Udine; 33100",
    "sg:city":"Udine",
    "sg:classifiers":[
        {
            "category":"Banks & Credit Unions",
            "subcategory":"Bank",
            "type":"Services"
        }
    ],
    "sg:phone":"+39 0432 531632",
    "sg:postcode":"33100",
    "sg:province":"Udine",
    "wof:name":"Banco Ambrosiano Veneto Spa",
    "wof:placetype":"venue"
},
  "geometry": {"coordinates":[13.245426,46.06356],"type":"Point"}
}