{
  "type": "Feature",
  "properties": {
    "iso:country":"IT",
    "sg:address":"77, Via Boniperti 28015 Momo",
    "sg:city":"Momo",
    "sg:classifiers":[
        {
            "category":"Shopping",
            "subcategory":"Computers & Home Electronics",
            "type":"Retail Goods"
        }
    ],
    "sg:phone":"+39 0321 926308",
    "sg:postcode":"28015",
    "sg:province":"Novara",
    "sg:tags":[
        "electronic",
        "electrical",
        "equipment"
    ],
    "wof:name":"Aspex A R.l.",
    "wof:placetype":"venue"
},
  "geometry": {"coordinates":[8.564836,45.559593],"type":"Point"}
}