{
  "type": "Feature",
  "properties": {
    "iso:country":"IT",
    "sg:address":"20099 Sesto San Giovanni",
    "sg:city":"Sesto San Giovanni",
    "sg:orig_category":"Servizi Ausiliari Dei Mezzi Di Trasporto",
    "sg:phone":"+39 02 2247 0013",
    "sg:postcode":"20099",
    "sg:province":"Milano",
    "wof:name":"Beretta Camillo",
    "wof:placetype":"venue"
},
  "geometry": {"coordinates":[9.240488,45.534908],"type":"Point"}
}