{
  "type": "Feature",
  "properties": {
    "addr:full":"02013 Antrodoco Antrodoco Rieti 02013",
    "addr:postcode":"02013;02013",
    "iso:country":"IT",
    "sg:address":"02013 Antrodoco",
    "sg:city":"Antrodoco",
    "sg:orig_category":"Non-classified Establishments",
    "sg:phone":"+39 0746 586028",
    "sg:postcode":"02013",
    "sg:province":"Rieti",
    "wof:name":"Ciuffa Mobili Srl",
    "wof:placetype":"venue"
},
  "geometry": {"coordinates":[13.104845,42.401661],"type":"Point"}
}