{
  "type": "Feature",
  "properties": {
    "addr:full":"8, Via Degli Artigiani 12100 Cuneo Cuneo Cuneo 12100",
    "addr:postcode":"12100;12100",
    "addr:street":"Via Degli Artigiani",
    "iso:country":"IT",
    "sg:address":"8, Via Degli Artigiani 12100 Cuneo",
    "sg:city":"Cuneo",
    "sg:classifiers":[
        {
            "category":"Shopping",
            "subcategory":"Clothing, Apparel, & Fashions",
            "type":"Retail Goods"
        }
    ],
    "sg:phone":"+39 0171 698663",
    "sg:postcode":"12100",
    "sg:province":"Cuneo",
    "sg:tags":[
        "clothes"
    ],
    "wof:name":"Maglificio Iride",
    "wof:placetype":"venue"
},
  "geometry": {"coordinates":[7.521925,44.375748],"type":"Point"}
}