{
  "type": "Feature",
  "properties": {
    "addr:full":"Via Madonna 20/a 48010 Bagnara Di Romagna Bagnara di Romagna Ravenna 48010",
    "addr:housenumber":"20 / a",
    "addr:postcode":"48010;48010",
    "addr:street":"Via Madonna",
    "iso:country":"IT",
    "sg:address":"Via Madonna 20/a 48010 Bagnara Di Romagna",
    "sg:city":"Bagnara di Romagna",
    "sg:classifiers":[
        {
            "category":"Wholesale",
            "subcategory":"Durable Goods & Equipment",
            "type":"Manufacturing & Wholesale Goods"
        }
    ],
    "sg:phone":"+39 0545 31830",
    "sg:postcode":"48010",
    "sg:province":"Ravenna",
    "sg:tags":[
        "feeding"
    ],
    "wof:name":"C.e.m. Srl",
    "wof:placetype":"venue"
},
  "geometry": {"coordinates":[11.8369121552,44.395690918],"type":"Point"}
}