{
  "type": "Feature",
  "properties": {
    "iso:country":"IT",
    "sg:address":"58100 Grosseto",
    "sg:city":"Grosseto",
    "sg:orig_category":"Legno E Semilavorati. Apparecchiature E Sistemi Per Magazzinaggio E Movimentazione",
    "sg:phone":"+39 0564 450879",
    "sg:postcode":"58100",
    "sg:province":"Grosseto",
    "wof:name":"Cmb Ecologia Srl",
    "wof:placetype":"venue"
},
  "geometry": {"coordinates":[11.1028356552,42.784702301],"type":"Point"}
}