{
  "type": "Feature",
  "properties": {
    "addr:full":"17024 Finale Ligure Finale Ligure Savona 17024",
    "addr:postcode":"17024;17024",
    "iso:country":"IT",
    "sg:address":"17024 Finale Ligure",
    "sg:city":"Finale Ligure",
    "sg:orig_category":"Non-classified Establishments",
    "sg:phone":"+39 019 680008",
    "sg:postcode":"17024",
    "sg:province":"Savona",
    "wof:name":"L.m.d.",
    "wof:placetype":"venue"
},
  "geometry": {"coordinates":[8.326895,44.175301],"type":"Point"}
}