{
  "type": "Feature",
  "properties": {
    "iso:country":"IT",
    "sg:address":"133, Via Bentivogli 40062 Molinella",
    "sg:city":"Molinella",
    "sg:classifiers":[
        {
            "category":"Farming",
            "subcategory":"Livestock Farm",
            "type":"Manufacturing & Wholesale Goods"
        }
    ],
    "sg:phone":"+39 39051880251",
    "sg:postcode":"40062",
    "sg:province":"Bologna",
    "sg:tags":[
        "agriculture"
    ],
    "wof:name":"Patfrut - Produttori Patate Deltafrutta Soc. Coop. A R.l.",
    "wof:placetype":"venue"
},
  "geometry": {"coordinates":[11.671682,44.625313],"type":"Point"}
}