{
  "type": "Feature",
  "properties": {
    "iso:country":"IT",
    "sg:address":"42017 Novellara",
    "sg:orig_category":"Servizi Al Turismo. Trasporto Pubblico E Privato",
    "sg:phone":"+39 0522 651261",
    "sg:postcode":"42017",
    "sg:province":"Reggio Nell'Emilia",
    "wof:name":"Mundo Joven - Agenzia Viaggi E Turismo",
    "wof:placetype":"venue"
},
  "geometry": {"coordinates":[10.646409,44.718746],"type":"Point"}
}