{
  "type": "Feature",
  "properties": {
    "iso:country":"IT",
    "sg:address":"20010 Bareggio",
    "sg:city":"Bareggio",
    "sg:classifiers":[
        {
            "category":"Health Services",
            "subcategory":"Health Practitioner",
            "type":"Services"
        }
    ],
    "sg:phone":"+39 02 9036 1358",
    "sg:postcode":"20010",
    "sg:province":"Milano",
    "sg:tags":[
        "medici"
    ],
    "wof:name":"Centro Medicina Dello Sport Bareggio Srl",
    "wof:placetype":"venue"
},
  "geometry": {"coordinates":[9.188035,45.462608],"type":"Point"}
}