{
  "type": "Feature",
  "properties": {
    "iso:country":"IT",
    "sg:address":"61024 Mombaroccio",
    "sg:city":"Mombaroccio",
    "sg:orig_category":"Arredi Ed Attrezzature Per Uffici",
    "sg:phone":"+39 0721 471410",
    "sg:postcode":"61024",
    "sg:province":"Pesaro E Urbino",
    "wof:name":"Forum Sas Di Bonazzoli Roberto & C.",
    "wof:placetype":"venue"
},
  "geometry": {"coordinates":[12.864027,43.816936],"type":"Point"}
}