{
  "type": "Feature",
  "properties": {
    "iso:country":"IT",
    "sg:address":"8, Via Prati 35031 Abano Terme",
    "sg:city":"Abano Terme",
    "sg:classifiers":[
        {
            "category":"Professional",
            "subcategory":"Engineering",
            "type":"Services"
        }
    ],
    "sg:phone":"+39 049 860 0133",
    "sg:postcode":"35031",
    "sg:province":"Padova",
    "sg:tags":[
        "machine",
        "-",
        "mechanical"
    ],
    "wof:name":"Eco Edilizia Coordinata (s.r.l.)",
    "wof:placetype":"venue"
},
  "geometry": {"coordinates":[11.787095,45.356682],"type":"Point"}
}