{
  "type": "Feature",
  "properties": {
    "iso:country":"IT",
    "sg:address":"35031 Abano Terme",
    "sg:city":"Abano Terme",
    "sg:orig_category":"Alberghi E Strutture Extra Alberghiere. Ospedali E Servizi Sanitari",
    "sg:phone":"+39 049 866 9061",
    "sg:postcode":"35031",
    "sg:province":"Padova",
    "wof:name":"Albergo Termale Ariston Molino",
    "wof:placetype":"venue"
},
  "geometry": {"coordinates":[11.776321,45.352879],"type":"Point"}
}