{
  "type": "Feature",
  "properties": {
    "iso:country":"IT",
    "sg:address":"25010 Montirone",
    "sg:city":"Montirone",
    "sg:orig_category":"Trattamenti Termici E Superficiali Metalli, Galvanotecnica",
    "sg:phone":"+39 030 267438",
    "sg:postcode":"25010",
    "sg:province":"Brescia",
    "wof:name":"S.v.i.m. Snc Di Besacchi Giuseppe E C.",
    "wof:placetype":"venue"
},
  "geometry": {"coordinates":[10.219462,45.450691],"type":"Point"}
}