{
  "type": "Feature",
  "properties": {
    "iso:country":"IT",
    "sg:address":"37136 Verona",
    "sg:city":"Verona",
    "sg:orig_category":"Macchine Ed Impianti Per Edilizia E Lavori Pubblici",
    "sg:phone":"+39 045 502091",
    "sg:postcode":"37136",
    "sg:province":"Verona",
    "wof:name":"Forni E Impianti Srl",
    "wof:placetype":"venue"
},
  "geometry": {"coordinates":[10.966357,45.419361],"type":"Point"}
}