{
  "type": "Feature",
  "properties": {
    "iso:country":"IT",
    "sg:address":"04100 Latina",
    "sg:city":"Latina",
    "sg:orig_category":"Campeggio. Accessori Dei Mezzi Di Trasporto",
    "sg:phone":"+39 0773 486160",
    "sg:postcode":"04100",
    "sg:province":"Latina",
    "wof:name":"De Petris Giancarlo Latina Tendoni",
    "wof:placetype":"venue"
},
  "geometry": {"coordinates":[12.876109,41.477413],"type":"Point"}
}