{
  "type": "Feature",
  "properties": {
    "addr:full":"91026 Mazara Del Vallo Mazara del Vallo Trapani 91026",
    "addr:postcode":"91026;91026",
    "iso:country":"IT",
    "sg:address":"91026 Mazara Del Vallo",
    "sg:city":"Mazara del Vallo",
    "sg:orig_category":"Calzature, Pelletterie E Pelli. Shopping",
    "sg:phone":"+39 0923 948200",
    "sg:postcode":"91026",
    "sg:province":"Trapani",
    "wof:name":"Chamade Di Piccione Antonino",
    "wof:placetype":"venue"
},
  "geometry": {"coordinates":[12.644587,37.738953],"type":"Point"}
}