{
  "type": "Feature",
  "properties": {
    "addr:full":"40026 Imola Imola Bologna 40026",
    "addr:postcode":"40026;40026",
    "iso:country":"IT",
    "sg:address":"40026 Imola",
    "sg:city":"Imola",
    "sg:classifiers":[
        {
            "category":"Health Services",
            "subcategory":"Health Practitioner",
            "type":"Services"
        }
    ],
    "sg:phone":"+39 0542 22555",
    "sg:postcode":"40026",
    "sg:province":"Bologna",
    "sg:tags":[
        "medici"
    ],
    "wof:name":"Dal Monte Alberto",
    "wof:placetype":"venue"
},
  "geometry": {"coordinates":[11.620038,44.389988],"type":"Point"}
}