{
  "type": "Feature",
  "properties": {
    "addr:full":"55045 Pietrasanta Pietrasanta Lucca 55045",
    "addr:postcode":"55045;55045",
    "iso:country":"IT",
    "sg:address":"55045 Pietrasanta",
    "sg:city":"Pietrasanta",
    "sg:orig_category":"Musica",
    "sg:phone":"+39 0584 71733",
    "sg:postcode":"55045",
    "sg:province":"Lucca",
    "wof:name":"Jurmann Ennio",
    "wof:placetype":"venue"
},
  "geometry": {"coordinates":[10.2309236526,43.9590911865],"type":"Point"}
}