{
  "type": "Feature",
  "properties": {
    "iso:country":"IT",
    "sg:address":"20090 Segrate",
    "sg:city":"Segrate",
    "sg:orig_category":"Servizi Al Turismo. Servizi Ausiliari Per Il Trasporto",
    "sg:phone":"+39 02 269771",
    "sg:postcode":"20090",
    "sg:province":"Milano",
    "wof:name":"Cos- Cos Srl",
    "wof:placetype":"venue"
},
  "geometry": {"coordinates":[9.285573,45.495258],"type":"Point"}
}