{
  "type": "Feature",
  "properties": {
    "iso:country":"IT",
    "sg:address":"10044 Pianezza",
    "sg:city":"Pianezza",
    "sg:orig_category":"Abbigliamento Intimo, Calze E Costumi Da Bagno. Shopping",
    "sg:phone":"+39 011 966 3261",
    "sg:postcode":"10044",
    "sg:province":"Torino",
    "wof:name":"Genova Rosella",
    "wof:placetype":"venue"
},
  "geometry": {"coordinates":[7.579644,45.071239],"type":"Point"}
}