{
  "type": "Feature",
  "properties": {
    "iso:country":"IT",
    "sg:address":"Via I Maggio 50 50067 Rignano Sull'arno",
    "sg:classifiers":[
        {
            "category":"Structure",
            "subcategory":"Factory",
            "type":"Public Place"
        }
    ],
    "sg:phone":"+39 055 830 3450",
    "sg:postcode":"50067",
    "sg:province":"Firenze",
    "sg:tags":[
        "evaporators"
    ],
    "sg:website":"www.cgdepur.it",
    "wof:name":"C. & G. Depurazione Industriale Srl",
    "wof:placetype":"venue"
},
  "geometry": {"coordinates":[11.256902,43.768734],"type":"Point"}
}