{
  "type": "Feature",
  "properties": {
    "iso:country":"IT",
    "sg:address":"12012 Boves",
    "sg:city":"Boves",
    "sg:orig_category":"Autotrasporti",
    "sg:phone":"+39 0171 387700",
    "sg:postcode":"12012",
    "sg:province":"Cuneo",
    "sg:website":"http://www.agautvallestura.com",
    "wof:name":"Franza Sergio",
    "wof:placetype":"venue"
},
  "geometry": {"coordinates":[7.549334,44.333996],"type":"Point"}
}