{
  "type": "Feature",
  "properties": {
    "iso:country":"IT",
    "sg:address":"22070 Veniano",
    "sg:city":"Veniano",
    "sg:orig_category":"Materie Plastiche - Produzione E Lavorazione",
    "sg:phone":"+39 031 933620",
    "sg:postcode":"22070",
    "sg:province":"Como",
    "sg:website":"http://www.oltronaplast.it",
    "wof:name":"Oltrona Plast Srl",
    "wof:placetype":"venue"
},
  "geometry": {"coordinates":[8.990943,45.720772],"type":"Point"}
}