{
  "type": "Feature",
  "properties": {
    "addr:full":"73010 Lequile Lequile Lecce 73010",
    "addr:postcode":"73010;73010",
    "iso:country":"IT",
    "sg:address":"73010 Lequile",
    "sg:city":"Lequile",
    "sg:classifiers":[
        {
            "category":"Utilities",
            "subcategory":"Refuse",
            "type":"Services"
        }
    ],
    "sg:phone":"+39 0832 634400",
    "sg:postcode":"73010",
    "sg:province":"Lecce",
    "sg:tags":[
        "auxiliary",
        "disposal",
        "surveillance",
        "environmental",
        "protection",
        "cleaning",
        "maintenance",
        "works"
    ],
    "wof:name":"Ecotecnica Srl",
    "wof:placetype":"venue"
},
  "geometry": {"coordinates":[18.141111,40.306889],"type":"Point"}
}