{
  "type": "Feature",
  "properties": {
    "iso:country":"IT",
    "sg:address":"21050 Cairate",
    "sg:city":"Cairate",
    "sg:orig_category":"Apparecchiature E Sistemi Per Imballaggio E Confezionamento. Apparecchiature E Sistemi Per Magazzinaggio E Movimentazione",
    "sg:phone":"+39 0331 311534",
    "sg:postcode":"21050",
    "sg:province":"Varese",
    "wof:name":"Seghezzi Luigi",
    "wof:placetype":"venue"
},
  "geometry": {"coordinates":[8.870648,45.690334],"type":"Point"}
}