{
  "type": "Feature",
  "properties": {
    "iso:country":"IT",
    "sg:address":"44042 Cento",
    "sg:city":"Cento",
    "sg:orig_category":"Apparecchiature E Sistemi Per Magazzinaggio E Movimentazione. Macchine E Impianti Per Attivita' Commerciali Ed Artigianali. Macchine, Strumenti Ed Apparecchi Per Attivita' Industriali",
    "sg:phone":"+39 051 902134",
    "sg:postcode":"44042",
    "sg:province":"Ferrara",
    "wof:name":"Tassinari Bilance Srl",
    "wof:placetype":"venue"
},
  "geometry": {"coordinates":[11.291046,44.748875],"type":"Point"}
}