{
  "type": "Feature",
  "properties": {
    "addr:full":"20044 Bernareggio Bernareggio Milano 20044",
    "addr:postcode":"20044;20044",
    "iso:country":"IT",
    "sg:address":"20044 Bernareggio",
    "sg:city":"Bernareggio",
    "sg:orig_category":"Impiantistica E Prodotti Tecnologici Per Edilizia. Forniture Industriali Per Prevenzione, Controllo E Sicurezza",
    "sg:phone":"+39 039 688 4123",
    "sg:postcode":"20044",
    "sg:province":"Milano",
    "wof:name":"Antincendio Giemme Srl",
    "wof:placetype":"venue"
},
  "geometry": {"coordinates":[9.400828,45.648521],"type":"Point"}
}