{
  "type": "Feature",
  "properties": {
    "iso:country":"IT",
    "sg:address":"20060 Truccazzano",
    "sg:city":"Truccazzano",
    "sg:orig_category":"Ristorazione E Locali Pubblici Affini. Ristoranti Ed Esercizi Affini. Servizi Ausiliari Di Ristorazione E Di Intrattenimento",
    "sg:phone":"+39 02 958 3063",
    "sg:postcode":"20060",
    "sg:province":"Milano",
    "wof:name":"Osteria Del Castello",
    "wof:placetype":"venue"
},
  "geometry": {"coordinates":[9.476386,45.464249],"type":"Point"}
}