{
  "type": "Feature",
  "properties": {
    "iso:country":"IT",
    "sg:address":"20061 Carugate",
    "sg:city":"Carugate",
    "sg:orig_category":"Automobili E Mezzi Di Trasporto",
    "sg:phone":"+39 02 925 4202",
    "sg:postcode":"20061",
    "sg:province":"Milano",
    "wof:name":"Ribaltabili Giovanni Colombo Spa",
    "wof:placetype":"venue"
},
  "geometry": {"coordinates":[9.336032,45.555378],"type":"Point"}
}