{
  "type": "Feature",
  "properties": {
    "addr:full":"41100 Modena Modena Modena 41100",
    "addr:postcode":"41100;41100",
    "iso:country":"IT",
    "sg:address":"41100 Modena",
    "sg:city":"Modena",
    "sg:orig_category":"Forniture Per Abbigliamento E Pelletterie",
    "sg:phone":"+39 059 314568",
    "sg:postcode":"41100",
    "sg:province":"Modena",
    "wof:name":"Pizzochero Attilio (s.n.c.)",
    "wof:placetype":"venue"
},
  "geometry": {"coordinates":[10.9290409088,44.6569671631],"type":"Point"}
}