{
  "type": "Feature",
  "properties": {
    "iso:country":"IT",
    "sg:address":"00191 Roma",
    "sg:city":"Roma",
    "sg:orig_category":"Cinematografia E Radiotelevisione. Cine-foto-ottica",
    "sg:phone":"+39 06 333 2592",
    "sg:postcode":"00191",
    "sg:province":"Roma",
    "wof:name":"Video Doc",
    "wof:placetype":"venue"
},
  "geometry": {"coordinates":[12.471946,41.943352],"type":"Point"}
}