{
  "type": "Feature",
  "properties": {
    "iso:country":"IT",
    "sg:address":"61011 Gabicce Mare",
    "sg:city":"Gabicce Mare",
    "sg:orig_category":"Ospedali E Servizi Sanitari. Centri Di Estetica E Cosmesi E Servizi",
    "sg:phone":"+39 0541 831591",
    "sg:postcode":"61011",
    "sg:province":"Pesaro E Urbino",
    "wof:name":"Baldassarri Giuseppe",
    "wof:placetype":"venue"
},
  "geometry": {"coordinates":[12.529803,43.633556],"type":"Point"}
}