{
  "type": "Feature",
  "properties": {
    "iso:country":"IT",
    "sg:address":"35040 Boara Pisani",
    "sg:city":"Boara Pisani",
    "sg:orig_category":"Non-classified Establishments",
    "sg:phone":"+39 0425 485412",
    "sg:postcode":"35040",
    "sg:province":"Padova",
    "wof:name":"Toys Center",
    "wof:placetype":"venue"
},
  "geometry": {"coordinates":[11.771438,45.118206],"type":"Point"}
}