{
  "type": "Feature",
  "properties": {
    "iso:country":"IT",
    "sg:address":"04100 Latina",
    "sg:city":"Latina",
    "sg:orig_category":"Servizi Per Lo Sport E Il Tempo Libero. Servizi Vari Di Interesse Pubblico",
    "sg:phone":"+39 0773 695604",
    "sg:postcode":"04100",
    "sg:province":"Latina",
    "wof:name":"Punto Snai - Del Duca E Pierotti",
    "wof:placetype":"venue"
},
  "geometry": {"coordinates":[12.874495,41.452148],"type":"Point"}
}