{
  "type": "Feature",
  "properties": {
    "iso:country":"IT",
    "sg:address":"25/b, Via Colombo Cristoforo 41012 Carpi",
    "sg:city":"Carpi",
    "sg:classifiers":[
        {
            "category":"Shopping",
            "subcategory":"Clothing, Apparel, & Fashions",
            "type":"Retail Goods"
        }
    ],
    "sg:phone":"+39 39059694339",
    "sg:postcode":"41012",
    "sg:province":"Modena",
    "sg:tags":[
        "clothes"
    ],
    "wof:name":"Jeans Club S.r.l.",
    "wof:placetype":"venue"
},
  "geometry": {"coordinates":[10.913278,44.886204],"type":"Point"}
}