{
  "type": "Feature",
  "properties": {
    "addr:full":"45010 Villadose Villadose Rovigo 45010",
    "addr:postcode":"45010;45010",
    "iso:country":"IT",
    "sg:address":"45010 Villadose",
    "sg:city":"Villadose",
    "sg:orig_category":"Forniture Per Edilizia E Lavori Pubblici",
    "sg:phone":"+39 0425 409900",
    "sg:postcode":"45010",
    "sg:province":"Rovigo",
    "wof:name":"Na - Ma (s.n.c.)",
    "wof:placetype":"venue"
},
  "geometry": {"coordinates":[11.8872871399,45.0695991516],"type":"Point"}
}