{
  "type": "Feature",
  "properties": {
    "addr:full":"59100 Prato Prato Prato 59100",
    "addr:postcode":"59100;59100",
    "iso:country":"IT",
    "sg:address":"59100 Prato",
    "sg:city":"Prato",
    "sg:orig_category":"Scuole E Servizi Scolastici",
    "sg:phone":"+39 0574 401376",
    "sg:postcode":"59100",
    "sg:province":"Prato",
    "wof:name":"Terminale Soc. Cooperativa A R.l.",
    "wof:placetype":"venue"
},
  "geometry": {"coordinates":[11.096498,43.876984],"type":"Point"}
}