{
  "type": "Feature",
  "properties": {
    "iso:country":"IT",
    "sg:address":"Via Ferdinando Scala 62; S. Paolo Belsito; 80030",
    "sg:classifiers":[
        {
            "category":"Banks & Credit Unions",
            "subcategory":"Bank",
            "type":"Services"
        }
    ],
    "sg:phone":"+39 081 829 5461",
    "sg:postcode":"80030",
    "sg:province":"Napoli",
    "wof:name":"Banco Di Napoli Spa",
    "wof:placetype":"venue"
},
  "geometry": {"coordinates":[14.553874,40.982613],"type":"Point"}
}