{
  "type": "Feature",
  "properties": {
    "addr:full":"12062 Cherasco Cherasco Cuneo 12062",
    "addr:housenumber":"12062",
    "addr:postcode":"12062",
    "addr:street":"Cherasco Cherasco",
    "iso:country":"IT",
    "sg:address":"12062 Cherasco",
    "sg:city":"Cherasco",
    "sg:orig_category":"Falegnami",
    "sg:phone":"+39 0172 495967",
    "sg:postcode":"12062",
    "sg:province":"Cuneo",
    "wof:name":"Falegnameria Sg Di Sprovieri Giuseppe E Gianfranco Snc",
    "wof:placetype":"venue"
},
  "geometry": {"coordinates":[7.5312795639,44.4017524719],"type":"Point"}
}