{
  "type": "Feature",
  "properties": {
    "addr:full":"10, Via Savani 41057 Spilamberto Spilamberto Modena 41057",
    "addr:postcode":"41057;41057",
    "addr:street":"Via Savani",
    "iso:country":"IT",
    "sg:address":"10, Via Savani 41057 Spilamberto",
    "sg:city":"Spilamberto",
    "sg:classifiers":[
        {
            "category":"Manufacturing",
            "subcategory":"Textiles",
            "type":"Manufacturing & Wholesale Goods"
        }
    ],
    "sg:phone":"+39 39059785083",
    "sg:postcode":"41057",
    "sg:province":"Modena",
    "sg:tags":[
        "leather",
        "raw",
        "material",
        "-"
    ],
    "wof:name":"Tonelli Mauro",
    "wof:placetype":"venue"
},
  "geometry": {"coordinates":[11.026299,44.533272],"type":"Point"}
}