{
  "type": "Feature",
  "properties": {
    "iso:country":"IT",
    "sg:address":"21051 Arcisate",
    "sg:city":"Arcisate",
    "sg:orig_category":"Etichette",
    "sg:phone":"+39 0332 471075",
    "sg:postcode":"21051",
    "sg:province":"Varese",
    "wof:name":"Artes Srl",
    "wof:placetype":"venue"
},
  "geometry": {"coordinates":[8.86192,45.851158],"type":"Point"}
}