{
  "type": "Feature",
  "properties": {
    "addr:full":"41100 Modena Modena Modena 41100",
    "addr:postcode":"41100;41100",
    "iso:country":"IT",
    "sg:address":"41100 Modena",
    "sg:city":"Modena",
    "sg:orig_category":"Cine-foto-ottica",
    "sg:phone":"+39 059 351241",
    "sg:postcode":"41100",
    "sg:province":"Modena",
    "wof:name":"Foto Pugnaghi Di Pugnaghi Agostino",
    "wof:placetype":"venue"
},
  "geometry": {"coordinates":[10.914429,44.663944],"type":"Point"}
}