{
  "type": "Feature",
  "properties": {
    "iso:country":"IT",
    "sg:address":"4, Via Col Alt 33070 Caneva",
    "sg:city":"Caneva",
    "sg:classifiers":[
        {
            "category":"Farming",
            "subcategory":"Livestock Farm",
            "type":"Manufacturing & Wholesale Goods"
        }
    ],
    "sg:phone":"+39 39043479132",
    "sg:postcode":"33070",
    "sg:province":"Pordenone",
    "sg:tags":[
        "agriculture"
    ],
    "wof:name":"Friulfunghi P.s.c.r.l.",
    "wof:placetype":"venue"
},
  "geometry": {"coordinates":[12.423484,45.957283],"type":"Point"}
}