{
  "type": "Feature",
  "properties": {
    "iso:country":"IT",
    "sg:address":"Via Salvo D' Acquisto 4 42020 Albinea",
    "sg:classifiers":[
        {
            "category":"Government",
            "subcategory":"Fire Station",
            "type":"Public Place"
        }
    ],
    "sg:phone":"+39 0522 347266",
    "sg:postcode":"42020",
    "sg:province":"Reggio Nell'Emilia",
    "sg:tags":[
        "interior",
        "steel",
        "fitting",
        "stainless"
    ],
    "sg:website":"www.ramex.it",
    "wof:name":"Ramex S.r.l.",
    "wof:placetype":"venue"
},
  "geometry": {"coordinates":[10.574821,44.623238],"type":"Point"}
}