{
  "type": "Feature",
  "properties": {
    "iso:country":"IT",
    "sg:address":"25010 Isorella",
    "sg:city":"Isorella",
    "sg:orig_category":"Zootecnia E Pesca, Allevamento Piccoli Animali",
    "sg:phone":"+39 030 995 8252",
    "sg:postcode":"25010",
    "sg:province":"Brescia",
    "wof:name":"Regonaschi Amilcare",
    "wof:placetype":"venue"
},
  "geometry": {"coordinates":[10.323462,45.309223],"type":"Point"}
}