{
  "type": "Feature",
  "properties": {
    "iso:country":"IT",
    "sg:address":"66, Via Chieri 10022 Carmagnola",
    "sg:city":"Carmagnola",
    "sg:orig_category":"Miscellaneous Products",
    "sg:phone":"+39 011 977 1553",
    "sg:postcode":"10022",
    "sg:province":"Torino",
    "wof:name":"S.p.a.f. (s.a.s.)",
    "wof:placetype":"venue"
},
  "geometry": {"coordinates":[7.7227020264,44.8640708923],"type":"Point"}
}