{
  "type": "Feature",
  "properties": {
    "addr:full":"54, Via Reno Vecchio 44042 Cento Cento Ferrara 44042",
    "addr:postcode":"44042;44042",
    "addr:street":"Via Reno Vecchio",
    "iso:country":"IT",
    "sg:address":"54, Via Reno Vecchio 44042 Cento",
    "sg:city":"Cento",
    "sg:classifiers":[
        {
            "category":"Manufacturing",
            "subcategory":"Food",
            "type":"Manufacturing & Wholesale Goods"
        }
    ],
    "sg:phone":"+39 051 683 6647",
    "sg:postcode":"44042",
    "sg:province":"Ferrara",
    "sg:tags":[
        "equipment",
        "processing",
        "-",
        "machinery"
    ],
    "wof:name":"R.e.p. Di Magagnoli A. & C. (s.n.c.)",
    "wof:placetype":"venue"
},
  "geometry": {"coordinates":[11.2632818222,44.7159156799],"type":"Point"}
}