{
  "type": "Feature",
  "properties": {
    "iso:country":"IT",
    "sg:address":"216, V. I Maggio - Loc. Ponte A Egola56024 San Miniato",
    "sg:city":"Ponte a egola",
    "sg:classifiers":[
        {
            "category":"Manufacturing",
            "subcategory":"Textiles",
            "type":"Manufacturing & Wholesale Goods"
        }
    ],
    "sg:phone":"+39 0571 497195",
    "sg:postcode":"56024",
    "sg:province":"Pisa",
    "sg:tags":[
        "leather",
        "raw",
        "material",
        "-"
    ],
    "sg:website":"http://www.biemmecuoio.it:ws_end: :mark:ws:http://www.paginegialle.it/biemme04",
    "wof:name":"Conceria Biemme",
    "wof:placetype":"venue"
},
  "geometry": {"coordinates":[10.396585,43.716137],"type":"Point"}
}