{
  "type": "Feature",
  "properties": {
    "addr:full":"9, Via Delle Industrie 35010 Limena Limena Padova 35010",
    "addr:postcode":"35010;35010",
    "addr:street":"Via Delle Industrie",
    "iso:country":"IT",
    "sg:address":"9, Via Delle Industrie 35010 Limena",
    "sg:city":"Limena",
    "sg:classifiers":[
        {
            "category":"Shopping",
            "subcategory":"Clothing, Apparel, & Fashions",
            "type":"Retail Goods"
        }
    ],
    "sg:phone":"+39 049 884 0033",
    "sg:postcode":"35010",
    "sg:province":"Padova",
    "sg:tags":[
        "clothes"
    ],
    "wof:name":"Lesina (srl)",
    "wof:placetype":"venue"
},
  "geometry": {"coordinates":[11.845468,45.47472],"type":"Point"}
}