{
  "type": "Feature",
  "properties": {
    "addr:full":"74016 Massafra Massafra Taranto 74016",
    "addr:postcode":"74016;74016",
    "iso:country":"IT",
    "sg:address":"74016 Massafra",
    "sg:city":"Massafra",
    "sg:classifiers":[
        {
            "category":"Home & Garden",
            "subcategory":"Building Materials",
            "type":"Retail Goods"
        }
    ],
    "sg:phone":"+39 099 880 5819",
    "sg:postcode":"74016",
    "sg:province":"Taranto",
    "sg:tags":[
        "gas",
        "caldaie"
    ],
    "wof:name":"Itiesse Di Recchia Marino",
    "wof:placetype":"venue"
},
  "geometry": {"coordinates":[17.111645,40.589146],"type":"Point"}
}