{
  "type": "Feature",
  "properties": {
    "iso:country":"IT",
    "sg:address":"24060 Bagnatica",
    "sg:city":"Bagnatica",
    "sg:orig_category":"Macchine, Impianti Ed Attrezzature Industria Chimica. Macchine Ed Impianti Per Edilizia E Lavori Pubblici",
    "sg:phone":"+39 035 681209",
    "sg:postcode":"24060",
    "sg:province":"Bergamo",
    "sg:website":"http://www.preziosa.com",
    "wof:name":"Preziosa Francesco & C. Snc Di Preziosa Marco",
    "wof:placetype":"venue"
},
  "geometry": {"coordinates":[9.782194,45.661896],"type":"Point"}
}