{
  "type": "Feature",
  "properties": {
    "addr:full":"Via Galcianese 56/c 59100 Prato Prato Prato 59100",
    "addr:housenumber":"56 / c",
    "addr:postcode":"59100;59100",
    "addr:street":"Via Galcianese",
    "iso:country":"IT",
    "sg:address":"Via Galcianese 56/c 59100 Prato",
    "sg:city":"Prato",
    "sg:classifiers":[
        {
            "category":"Shopping",
            "subcategory":"Clothing, Apparel, & Fashions",
            "type":"Retail Goods"
        }
    ],
    "sg:phone":"+39 0574 30041",
    "sg:postcode":"59100",
    "sg:province":"Prato",
    "sg:tags":[
        "clothing",
        "fabric"
    ],
    "sg:website":"www.lanificiozanieri.it",
    "wof:name":"Lanificio Luigi Zanieri Spa",
    "wof:placetype":"venue"
},
  "geometry": {"coordinates":[11.078012,43.878429],"type":"Point"}
}