{
  "type": "Feature",
  "properties": {
    "addr:full":"Via Le Lame 7 03100 Frosinone Frosinone Frosinone 03100",
    "addr:housenumber":"7",
    "addr:postcode":"03100;03100",
    "addr:street":"Via Le Lame",
    "iso:country":"IT",
    "sg:address":"Via Le Lame 7 03100 Frosinone",
    "sg:city":"Frosinone",
    "sg:classifiers":[
        {
            "category":"Government",
            "subcategory":"Court House",
            "type":"Public Place"
        }
    ],
    "sg:phone":"+39 0775 200649",
    "sg:postcode":"03100",
    "sg:province":"Frosinone",
    "sg:tags":[
        "cable",
        "special-purpose"
    ],
    "sg:website":"www.ceatbolton.com",
    "wof:name":"Teleco Cavi Spa",
    "wof:placetype":"venue"
},
  "geometry": {"coordinates":[13.284445,41.622559],"type":"Point"}
}