{
  "type": "Feature",
  "properties": {
    "addr:full":"51016 Montecatini Terme Pistoia 51016",
    "addr:postcode":"51016;51016",
    "iso:country":"IT",
    "sg:address":"51016 Montecatini Terme",
    "sg:orig_category":"Scuole E Servizi Scolastici",
    "sg:postcode":"51016",
    "sg:province":"Pistoia",
    "wof:name":"Istituto Magistrale Parificato Don Bosco",
    "wof:placetype":"venue"
},
  "geometry": {"coordinates":[10.833727,43.905914],"type":"Point"}
}