{
  "type": "Feature",
  "properties": {
    "addr:full":"55100 Lucca Lucca Lucca 55100",
    "addr:postcode":"55100;55100",
    "iso:country":"IT",
    "sg:address":"55100 Lucca",
    "sg:city":"Lucca",
    "sg:orig_category":"Prodotti Chimici Secondari. Macchine E Forniture Per Ecologia E Smaltimento Rifiuti. Forniture Per Attivita' Industriali",
    "sg:phone":"+39 0583 469809",
    "sg:postcode":"55100",
    "sg:province":"Lucca",
    "wof:name":"Chimicart Srl",
    "wof:placetype":"venue"
},
  "geometry": {"coordinates":[10.4621362686,43.8625450134],"type":"Point"}
}