{
  "type": "Feature",
  "properties": {
    "iso:country":"IT",
    "sg:address":"45011 Adria",
    "sg:city":"Adria",
    "sg:orig_category":"Carrozzerie Automobili",
    "sg:phone":"+39 0426 21865",
    "sg:postcode":"45011",
    "sg:province":"Rovigo",
    "wof:name":"Nuova Carrozzeria Splendor",
    "wof:placetype":"venue"
},
  "geometry": {"coordinates":[12.065631,45.054302],"type":"Point"}
}