{
  "type": "Feature",
  "properties": {
    "addr:full":"9, Via Belvedere Fogliense 47836 Mondaino Mondaino Rimini 47836",
    "addr:postcode":"47836;47836",
    "addr:street":"Via Belvedere Fogliense",
    "iso:country":"IT",
    "sg:address":"9, Via Belvedere Fogliense 47836 Mondaino",
    "sg:city":"Mondaino",
    "sg:classifiers":[
        {
            "category":"Utilities",
            "subcategory":"Telephone",
            "type":"Services"
        }
    ],
    "sg:phone":"+39 0541 981140",
    "sg:postcode":"47836",
    "sg:province":"Rimini",
    "sg:tags":[
        "telecommunication"
    ],
    "wof:name":"Bicma S.r.l.",
    "wof:placetype":"venue"
},
  "geometry": {"coordinates":[12.68177,43.85384],"type":"Point"}
}