{
  "type": "Feature",
  "properties": {
    "iso:country":"IT",
    "sg:address":"98123 Messina",
    "sg:city":"Messina",
    "sg:orig_category":"Hobbistica",
    "sg:phone":"+39 090 771096",
    "sg:postcode":"98123",
    "sg:province":"Messina",
    "wof:name":"Casella Jolanda",
    "wof:placetype":"venue"
},
  "geometry": {"coordinates":[15.552062,38.183502],"type":"Point"}
}