{
  "type": "Feature",
  "properties": {
    "iso:country":"IT",
    "sg:address":"61020 Montecchio",
    "sg:city":"Montecchio",
    "sg:orig_category":"Servizi E Lavori Per Arredamento E Industria Del Legno",
    "sg:phone":"+39 0721 499114",
    "sg:postcode":"61020",
    "sg:province":"Pesaro E Urbino",
    "wof:name":"Tabu (s.p.a.)",
    "wof:placetype":"venue"
},
  "geometry": {"coordinates":[12.965963,43.608463],"type":"Point"}
}