{
  "type": "Feature",
  "properties": {
    "iso:country":"IT",
    "sg:address":"24030 Mapello",
    "sg:city":"Mapello",
    "sg:classifiers":[
        {
            "category":"Retail",
            "subcategory":"Storage",
            "type":"Services"
        }
    ],
    "sg:phone":"+39 035 494 5066",
    "sg:postcode":"24030",
    "sg:province":"Bergamo",
    "sg:tags":[
        "equipment",
        "handling",
        "system"
    ],
    "sg:website":"http://www.locatellicrane.com",
    "wof:name":"Fratelli Locatelli Spa",
    "wof:placetype":"venue"
},
  "geometry": {"coordinates":[9.5116,45.730881],"type":"Point"}
}