{
  "type": "Feature",
  "properties": {
    "iso:country":"IT",
    "sg:address":"80146 Napoli",
    "sg:city":"Napoli",
    "sg:orig_category":"Forniture Per Edilizia E Lavori Pubblici",
    "sg:phone":"+39 081 752 3477",
    "sg:postcode":"80146",
    "sg:province":"Napoli",
    "wof:name":"Mario Gallinoro & C. Sas Di Vittorio Gallinoro",
    "wof:placetype":"venue"
},
  "geometry": {"coordinates":[14.2663650513,40.8897514343],"type":"Point"}
}