{
  "type": "Feature",
  "properties": {
    "addr:full":"10131 Torino Torino Torino 10131",
    "addr:postcode":"10131;10131",
    "iso:country":"IT",
    "sg:address":"10131 Torino",
    "sg:city":"Torino",
    "sg:orig_category":"Alimenti Dietetici, Macrobiotici E Biologici - Produzione E Ingrosso",
    "sg:phone":"+39 011 660 3246",
    "sg:postcode":"10131",
    "sg:province":"Torino",
    "wof:name":"Sanitalia Snc Di Lavarra G. & C.",
    "wof:placetype":"venue"
},
  "geometry": {"coordinates":[7.72157,45.052528],"type":"Point"}
}