{
  "type": "Feature",
  "properties": {
    "addr:full":"20122 Milano Milano Milano 20122",
    "addr:postcode":"20122;20122",
    "iso:country":"IT",
    "sg:address":"20122 Milano",
    "sg:city":"Milano",
    "sg:orig_category":"Scuole E Servizi Scolastici. Ricerca, Selezione E Formazione Del Personale",
    "sg:phone":"+39 02 863273",
    "sg:postcode":"20122",
    "sg:province":"Milano",
    "wof:name":"Tecnitravel Srl",
    "wof:placetype":"venue"
},
  "geometry": {"coordinates":[9.192152,45.459244],"type":"Point"}
}