{
  "type": "Feature",
  "properties": {
    "addr:full":"33080 Prata Di Pordenone Prata di Pordenone Pordenone 33080",
    "addr:postcode":"33080;33080",
    "iso:country":"IT",
    "sg:address":"33080 Prata Di Pordenone",
    "sg:city":"Prata di Pordenone",
    "sg:orig_category":"Utensili Lavorazione Legno",
    "sg:phone":"+39 0434 621447",
    "sg:postcode":"33080",
    "sg:province":"Pordenone",
    "wof:name":"Mion Utensili Srl",
    "wof:placetype":"venue"
},
  "geometry": {"coordinates":[12.60257,45.896732],"type":"Point"}
}