{
  "type": "Feature",
  "properties": {
    "iso:country":"IT",
    "sg:address":"Via Altura 42 35045 Ospedaletto Euganeo",
    "sg:city":"Ospedaletto Euganeo",
    "sg:classifiers":[
        {
            "category":"Autos & Motor Vehicles",
            "subcategory":"Automobile Sales",
            "type":"Retail Goods"
        }
    ],
    "sg:phone":"+39 0429 90805",
    "sg:postcode":"35045",
    "sg:province":"Padova",
    "sg:tags":[
        "varnish",
        "lacquers"
    ],
    "wof:name":"Trivellato Srl",
    "wof:placetype":"venue"
},
  "geometry": {"coordinates":[11.619053,45.22509],"type":"Point"}
}