{
  "type": "Feature",
  "properties": {
    "iso:country":"IT",
    "sg:address":"25124 Brescia",
    "sg:city":"Brescia",
    "sg:orig_category":"Pianoforti",
    "sg:phone":"+39 030 230 1615",
    "sg:postcode":"25124",
    "sg:province":"Brescia",
    "wof:name":"Leonardi Andrea",
    "wof:placetype":"venue"
},
  "geometry": {"coordinates":[10.2417221069,45.5134086609],"type":"Point"}
}