{
  "type": "Feature",
  "properties": {
    "addr:full":"6, Localita' Madonna Di Loreto 31020 Tarzo Tarzo Treviso 31020",
    "addr:postcode":"31020;31020",
    "addr:street":"Localita ' Madonna Di Loreto",
    "iso:country":"IT",
    "sg:address":"6, Localita' Madonna Di Loreto 31020 Tarzo",
    "sg:city":"Tarzo",
    "sg:classifiers":[
        {
            "category":"Professional",
            "subcategory":"Engineering",
            "type":"Services"
        }
    ],
    "sg:phone":"+39 0438 933033",
    "sg:postcode":"31020",
    "sg:province":"Treviso",
    "sg:tags":[
        "machine",
        "-",
        "mechanical"
    ],
    "wof:name":"Irinox (s.r.l.)",
    "wof:placetype":"venue"
},
  "geometry": {"coordinates":[12.240701,45.943333],"type":"Point"}
}