{
  "type": "Feature",
  "properties": {
    "iso:country":"IT",
    "sg:address":"Via Salvo D'acquisto 49 20049 Concorezzo",
    "sg:city":"Concorezzo",
    "sg:classifiers":[
        {
            "category":"Wholesale",
            "subcategory":"Vending Machines",
            "type":"Manufacturing & Wholesale Goods"
        }
    ],
    "sg:phone":"+39 039 604 0893",
    "sg:postcode":"20049",
    "sg:province":"Milano",
    "sg:tags":[
        "bending",
        "profile",
        "iron",
        "structural"
    ],
    "sg:website":"www.imcar.it",
    "wof:name":"Imcar Srl",
    "wof:placetype":"venue"
},
  "geometry": {"coordinates":[9.330225,45.578484],"type":"Point"}
}