{
  "type": "Feature",
  "properties": {
    "addr:full":"04011 Aprilia Aprilia Latina 04011",
    "addr:postcode":"04011;04011",
    "iso:country":"IT",
    "sg:address":"04011 Aprilia",
    "sg:city":"Aprilia",
    "sg:orig_category":"Abbigliamento Esterno, Maglierie E Pelliccerie. Shopping",
    "sg:phone":"+39 06 9270 2472",
    "sg:postcode":"04011",
    "sg:province":"Latina",
    "wof:name":"Sartoria Cirillo Rosalia",
    "wof:placetype":"venue"
},
  "geometry": {"coordinates":[12.786899,41.42244],"type":"Point"}
}