{
  "type": "Feature",
  "properties": {
    "addr:full":"10046 Poirino Marocchi Torino 10046",
    "addr:postcode":"10046;10046",
    "iso:country":"IT",
    "sg:address":"10046 Poirino",
    "sg:city":"Marocchi",
    "sg:orig_category":"Prodotti Chimici Di Base",
    "sg:phone":"+39 011 943 0114",
    "sg:postcode":"10046",
    "sg:province":"Torino",
    "wof:name":"Culligan Piemonte Srl",
    "wof:placetype":"venue"
},
  "geometry": {"coordinates":[7.8396863937,44.9237213135],"type":"Point"}
}