{
  "type": "Feature",
  "properties": {
    "iso:country":"IT",
    "sg:address":"20060 Ornago",
    "sg:city":"Ornago",
    "sg:orig_category":"Materiali Semilavorati Metallici",
    "sg:phone":"+39 039 601 0373",
    "sg:postcode":"20060",
    "sg:province":"Milano",
    "wof:name":"Trafileria Monzese",
    "wof:placetype":"venue"
},
  "geometry": {"coordinates":[9.419566,45.596592],"type":"Point"}
}