{
  "type": "Feature",
  "properties": {
    "iso:country":"IT",
    "sg:address":"20010 Marcallo Con Casone",
    "sg:city":"Casone",
    "sg:orig_category":"Macchine, Impianti E Forniture Per Industria Grafica, Cartaria E Cartotecnica. Apparecchiature Ed Attrezzature Meccaniche. Automazione E Macchine Per Ufficio",
    "sg:phone":"+39 02 976 1748",
    "sg:postcode":"20010",
    "sg:province":"Milano",
    "wof:name":"Ghirlanda Spa",
    "wof:placetype":"venue"
},
  "geometry": {"coordinates":[8.39892,45.462345],"type":"Point"}
}