{
  "type": "Feature",
  "properties": {
    "iso:country":"IT",
    "sg:address":"10125 Torino",
    "sg:city":"Torino",
    "sg:classifiers":[
        {
            "category":"Health Services",
            "subcategory":"Health Practitioner",
            "type":"Services"
        }
    ],
    "sg:phone":"+39 011 650 7505",
    "sg:postcode":"10125",
    "sg:province":"Torino",
    "sg:tags":[
        "medici"
    ],
    "wof:name":"Girotto Dr. Gianfranco",
    "wof:placetype":"venue"
},
  "geometry": {"coordinates":[7.680298,45.052155],"type":"Point"}
}