{
  "type": "Feature",
  "properties": {
    "addr:full":"22078 Turate Turate Como 22078",
    "addr:postcode":"22078;22078",
    "iso:country":"IT",
    "sg:address":"22078 Turate",
    "sg:city":"Turate",
    "sg:orig_category":"Macchine Ed Impianti Per Edilizia E Lavori Pubblici. Forniture Per Edilizia E Lavori Pubblici",
    "sg:phone":"+39 02 969731",
    "sg:postcode":"22078",
    "sg:province":"Como",
    "sg:website":"http://www.huennebeck.it",
    "wof:name":"H\u00dcnnebeck Italia Spa",
    "wof:placetype":"venue"
},
  "geometry": {"coordinates":[9.031639,45.773991],"type":"Point"}
}