{
  "type": "Feature",
  "properties": {
    "addr:full":"37036 San Martino Buon Albergo San Martino Buon Albergo Verona 37036",
    "addr:housenumber":"37036",
    "addr:postcode":"buon albergo;37036",
    "iso:country":"IT",
    "sg:address":"37036 San Martino Buon Albergo",
    "sg:city":"San Martino Buon Albergo",
    "sg:orig_category":"Forniture Per Attivita' Commerciali Ed Artigianali. Pubblicita', Marketing E Comunicazione",
    "sg:phone":"+39 045 991666",
    "sg:postcode":"37036",
    "sg:province":"Verona",
    "sg:website":"http://www.emmedue.net",
    "wof:name":"Emmedue Minuterie Snc",
    "wof:placetype":"venue"
},
  "geometry": {"coordinates":[11.0865068436,45.418586731],"type":"Point"}
}