{
  "type": "Feature",
  "properties": {
    "iso:country":"IT",
    "sg:address":"01100 Viterbo",
    "sg:city":"Viterbo",
    "sg:orig_category":"Carrozzerie Automobili",
    "sg:phone":"+39 0761 250866",
    "sg:postcode":"01100",
    "sg:province":"Viterbo",
    "wof:name":"Carrozzeria Veicoli Industriali Fonti & Filippi Snc",
    "wof:placetype":"venue"
},
  "geometry": {"coordinates":[12.048979,42.441536],"type":"Point"}
}