{
  "type": "Feature",
  "properties": {
    "iso:country":"IT",
    "sg:address":"28921 Verbania",
    "sg:city":"Verbania",
    "sg:orig_category":"Servizi Ausiliari Di Certificati, Riproduzioni, Disegni E Foto",
    "sg:phone":"+39 0323 53375",
    "sg:postcode":"28921",
    "sg:province":"Verbano-Cusio-Ossola",
    "wof:name":"Laser 6 Srl",
    "wof:placetype":"venue"
},
  "geometry": {"coordinates":[8.574253,45.936543],"type":"Point"}
}