{
  "type": "Feature",
  "properties": {
    "iso:country":"IT",
    "sg:address":"20093 Cologno Monzese",
    "sg:city":"Cologno Monzese",
    "sg:orig_category":"Forniture Per Attivita' Commerciali Ed Artigianali",
    "sg:phone":"+39 02 2670 3003",
    "sg:postcode":"20093",
    "sg:province":"Milano",
    "wof:name":"L.m.c. Di Montanari L. E Cirelli M.",
    "wof:placetype":"venue"
},
  "geometry": {"coordinates":[9.2865180969,45.5287590027],"type":"Point"}
}