{
  "type": "Feature",
  "properties": {
    "iso:country":"IT",
    "sg:address":"1, Via Saturno 37059 Zevio",
    "sg:city":"Zevio",
    "sg:classifiers":[
        {
            "category":"Manufacturing",
            "subcategory":"Food",
            "type":"Manufacturing & Wholesale Goods"
        }
    ],
    "sg:phone":"+39 045 605 1428",
    "sg:postcode":"37059",
    "sg:province":"Verona",
    "sg:tags":[
        "equipment",
        "processing",
        "-",
        "machinery"
    ],
    "wof:name":"Laser S.r.l.",
    "wof:placetype":"venue"
},
  "geometry": {"coordinates":[11.0919084549,45.3699798584],"type":"Point"}
}