{
  "type": "Feature",
  "properties": {
    "addr:full":"25080 Moniga Del Garda Moniga del Garda Brescia 25080",
    "addr:postcode":"25080;25080",
    "iso:country":"IT",
    "sg:address":"25080 Moniga Del Garda",
    "sg:city":"Moniga del Garda",
    "sg:orig_category":"Materiali Semilavorati Metallici",
    "sg:phone":"+39 036 550 2073",
    "sg:postcode":"25080",
    "sg:province":"Brescia",
    "wof:name":"Cr Srl",
    "wof:placetype":"venue"
},
  "geometry": {"coordinates":[10.529067,45.52747],"type":"Point"}
}