{
  "type": "Feature",
  "properties": {
    "iso:country":"IT",
    "sg:address":"41100 Modena",
    "sg:city":"Modena",
    "sg:orig_category":"Prodotti Alimentari",
    "sg:phone":"+39 059 392446",
    "sg:postcode":"41100",
    "sg:province":"Modena",
    "wof:name":"Il Forno Di Jhonny & C. Snc",
    "wof:placetype":"venue"
},
  "geometry": {"coordinates":[10.93055439,44.650062561],"type":"Point"}
}