{
  "type": "Feature",
  "properties": {
    "iso:country":"IT",
    "sg:address":"21040 Caronno Varesino",
    "sg:city":"Caronno Varesino",
    "sg:orig_category":"Impermeabilizzazioni Edili - Lavori",
    "sg:phone":"+39 0331 980767",
    "sg:postcode":"21040",
    "sg:province":"Varese",
    "wof:name":"Co.im. Di Dalena Mario",
    "wof:placetype":"venue"
},
  "geometry": {"coordinates":[8.832245,45.730785],"type":"Point"}
}