{
  "type": "Feature",
  "properties": {
    "addr:full":"80041 Boscoreale Boscoreale Napoli 80041",
    "addr:postcode":"80041;80041",
    "iso:country":"IT",
    "sg:address":"80041 Boscoreale",
    "sg:city":"Boscoreale",
    "sg:orig_category":"Articoli Da Regalo. Regalistica Aziendale",
    "sg:phone":"+39 081 537 2571",
    "sg:postcode":"80041",
    "sg:province":"Napoli",
    "wof:name":"Filippone Carla",
    "wof:placetype":"venue"
},
  "geometry": {"coordinates":[14.496436,40.773331],"type":"Point"}
}