{
  "type": "Feature",
  "properties": {
    "addr:full":"51, Strada Padana Verso Verona 36100 Vicenza Vicenza Vicenza 36100",
    "addr:postcode":"36100;36100",
    "addr:street":"Strada Padana Verso",
    "iso:country":"IT",
    "sg:address":"51, Strada Padana Verso Verona 36100 Vicenza",
    "sg:city":"Vicenza",
    "sg:classifiers":[
        {
            "category":"Professional",
            "subcategory":"Engineering",
            "type":"Services"
        }
    ],
    "sg:phone":"+39 0444 563322",
    "sg:postcode":"36100",
    "sg:province":"Vicenza",
    "sg:tags":[
        "machine",
        "-",
        "mechanical"
    ],
    "wof:name":"Bdf Boscato & Dalla Fontana (s.p.a.)",
    "wof:placetype":"venue"
},
  "geometry": {"coordinates":[11.526389,45.575279],"type":"Point"}
}