{
  "type": "Feature",
  "properties": {
    "iso:country":"IT",
    "sg:address":"25050 Pian Camuno",
    "sg:city":"Pian Camuno",
    "sg:orig_category":"Forniture Per Attivita' Industriali",
    "sg:phone":"+39 036 459 0792",
    "sg:postcode":"25050",
    "sg:province":"Brescia",
    "sg:website":"http://www.abrabeta.it",
    "wof:name":"Abra-beta Srl",
    "wof:placetype":"venue"
},
  "geometry": {"coordinates":[10.1416864395,45.846446991],"type":"Point"}
}