{
  "type": "Feature",
  "properties": {
    "iso:country":"IT",
    "sg:address":"18038 Sanremo",
    "sg:orig_category":"Bagno - Accessori E Mobili",
    "sg:phone":"+39 0184 507822",
    "sg:postcode":"18038",
    "sg:province":"Imperia",
    "wof:name":"Ceramiche Spada",
    "wof:placetype":"venue"
},
  "geometry": {"coordinates":[7.77427,43.841179],"type":"Point"}
}