{
  "type": "Feature",
  "properties": {
    "iso:country":"IT",
    "sg:address":"20090 Pieve Emanuele",
    "sg:city":"Pieve Emanuele",
    "sg:orig_category":"Forniture Per Abbigliamento E Pelletterie",
    "sg:phone":"+39 02 9072 2283",
    "sg:postcode":"20090",
    "sg:province":"Milano",
    "wof:name":"Brio Di Giammona Ugo",
    "wof:placetype":"venue"
},
  "geometry": {"coordinates":[9.1863775253,45.3711433411],"type":"Point"}
}