{
  "type": "Feature",
  "properties": {
    "iso:country":"IT",
    "sg:address":"80050 Santa Maria La Carit\u00e0",
    "sg:orig_category":"Manufacturers: Prefabbricati. Impianti E Attrezzature Per Lo Sport E Il Tempo Libero",
    "sg:phone":"+39 081 871 3206",
    "sg:postcode":"80050",
    "sg:province":"Napoli",
    "sg:website":"http://www.arreditalia.net",
    "wof:name":"Arreditalia Srl",
    "wof:placetype":"venue"
},
  "geometry": {"coordinates":[14.501177,40.714504],"type":"Point"}
}