{
  "type": "Feature",
  "properties": {
    "iso:country":"IT",
    "sg:address":"41049 Sassuolo",
    "sg:city":"Sassuolo",
    "sg:classifiers":[
        {
            "category":"Home & Garden",
            "subcategory":"Building Materials",
            "type":"Retail Goods"
        }
    ],
    "sg:phone":"+39 0536 812132",
    "sg:postcode":"41049",
    "sg:province":"Modena",
    "sg:tags":[
        "stone",
        "similar",
        "marble"
    ],
    "wof:name":"Marmorex Srl",
    "wof:placetype":"venue"
},
  "geometry": {"coordinates":[10.783298,44.536282],"type":"Point"}
}