{
  "type": "Feature",
  "properties": {
    "iso:country":"IT",
    "sg:address":"20159 Milano",
    "sg:city":"Milano",
    "sg:orig_category":"Ristoranti",
    "sg:phone":"+39 02 606174",
    "sg:postcode":"20159",
    "sg:province":"Milano",
    "sg:website":"http://www.vecchia_trattoria.3000.it",
    "wof:name":"La Vecchia Trattoria Da Ugo",
    "wof:placetype":"venue"
},
  "geometry": {"coordinates":[9.2766666412,45.4483337402],"type":"Point"}
}