{
  "type": "Feature",
  "properties": {
    "addr:full":"46030 Bigarello Bigarello Mantova 46030",
    "addr:postcode":"46030;46030",
    "iso:country":"IT",
    "sg:address":"46030 Bigarello",
    "sg:city":"Bigarello",
    "sg:orig_category":"Forniture Per Edilizia E Lavori Pubblici. Arredi Ed Attrezzature Per Attivita' Commerciali Ed Artigianali. Forniture Per Attivita' Industriali",
    "sg:phone":"+39 0376 457020",
    "sg:postcode":"46030",
    "sg:province":"Mantova",
    "wof:name":"C.m.s. Inox Infissi Di Malacarne Luca & C. Snc",
    "wof:placetype":"venue"
},
  "geometry": {"coordinates":[10.8720369339,45.1749992371],"type":"Point"}
}