{
  "type": "Feature",
  "properties": {
    "iso:country":"IT",
    "sg:address":"1, V. Ticino 20030 Limbiate",
    "sg:classifiers":[
        {
            "category":"Autos & Motor Vehicles",
            "subcategory":"Automobile Sales",
            "type":"Retail Goods"
        }
    ],
    "sg:phone":"+39 036 256 2059",
    "sg:postcode":"20030",
    "sg:province":"Milano",
    "sg:tags":[
        "motor-cars"
    ],
    "wof:name":"Rally Car",
    "wof:placetype":"venue"
},
  "geometry": {"coordinates":[9.1881408691,45.4636878967],"type":"Point"}
}