{
  "type": "Feature",
  "properties": {
    "iso:country":"IT",
    "sg:address":"26831 Casalmaiocco",
    "sg:city":"Casalmaiocco",
    "sg:orig_category":"Pannelli Prefabbricati",
    "sg:phone":"+39 02 9826 0275",
    "sg:postcode":"26831",
    "sg:province":"Lodi",
    "wof:name":"Unipre Srl",
    "wof:placetype":"venue"
},
  "geometry": {"coordinates":[9.3716859818,45.3519592285],"type":"Point"}
}