{
  "type": "Feature",
  "properties": {
    "iso:country":"IT",
    "sg:address":"41058 Vignola",
    "sg:city":"Vignola",
    "sg:orig_category":"Caminetti, Forni Da Giardino E Barbecues",
    "sg:phone":"+39 059 762434",
    "sg:postcode":"41058",
    "sg:province":"Modena",
    "wof:name":"B.z. Di Boni Umberto & C. Snc",
    "wof:placetype":"venue"
},
  "geometry": {"coordinates":[11.002486,44.496532],"type":"Point"}
}