{
  "type": "Feature",
  "properties": {
    "addr:full":"Via Rango 18 25065 Lumezzane Lumezzane Brescia 25065",
    "addr:housenumber":"18",
    "addr:postcode":"25065;25065",
    "addr:street":"Via Rango",
    "iso:country":"IT",
    "sg:address":"Via Rango 18 25065 Lumezzane",
    "sg:city":"Lumezzane",
    "sg:classifiers":[
        {
            "category":"Government",
            "subcategory":"Fire Station",
            "type":"Public Place"
        }
    ],
    "sg:phone":"+39 030 892 8511",
    "sg:postcode":"25065",
    "sg:province":"Brescia",
    "sg:tags":[
        "brass",
        "working"
    ],
    "sg:website":"www.gnutticirillo.it",
    "wof:name":"Gnutti Cirillo S.p.a.",
    "wof:placetype":"venue"
},
  "geometry": {"coordinates":[10.262872,45.647301],"type":"Point"}
}