{
  "type": "Feature",
  "properties": {
    "iso:country":"IT",
    "sg:address":"Via Firenze 1 21057 Olgiate Olona",
    "sg:city":"Olgiate Olona",
    "sg:classifiers":[
        {
            "category":"Manufacturing",
            "subcategory":"Furniture",
            "type":"Manufacturing & Wholesale Goods"
        }
    ],
    "sg:phone":"+39 0331 629111",
    "sg:postcode":"21057",
    "sg:province":"Varese",
    "sg:tags":[
        "fabric"
    ],
    "sg:website":"www.marnmarnate.it",
    "wof:name":"Manifattura Di Marnate Spa",
    "wof:placetype":"venue"
},
  "geometry": {"coordinates":[8.8751602173,45.6188964844],"type":"Point"}
}