{
  "type": "Feature",
  "properties": {
    "iso:country":"IT",
    "sg:address":"00184 Roma",
    "sg:city":"Roma",
    "sg:orig_category":"Campeggio. Alberghi E Strutture Extra Alberghiere",
    "sg:phone":"+39 06 4782 4275",
    "sg:postcode":"00184",
    "sg:province":"Roma",
    "sg:website":"http://www.romainn.com",
    "wof:name":"Roma Inn Youth Hostel",
    "wof:placetype":"venue"
},
  "geometry": {"coordinates":[12.49365,41.895779],"type":"Point"}
}