{
  "type": "Feature",
  "properties": {
    "addr:full":"20090 Pieve Emanuele Pieve Emanuele Milano 20090",
    "addr:postcode":"20090;20090",
    "iso:country":"IT",
    "sg:address":"20090 Pieve Emanuele",
    "sg:city":"Pieve Emanuele",
    "sg:orig_category":"Minuterie Metalliche E Ferramenta",
    "sg:phone":"+39 02 9042 9080",
    "sg:postcode":"20090",
    "sg:province":"Milano",
    "wof:name":"Leyvit Srl",
    "wof:placetype":"venue"
},
  "geometry": {"coordinates":[9.1754198074,45.375541687],"type":"Point"}
}