{
  "type": "Feature",
  "properties": {
    "iso:country":"IT",
    "sg:address":"10026 Torino",
    "sg:city":"Santena",
    "sg:orig_category":"Frigotecnica, Apparecchiature E Servizi",
    "sg:phone":"+39 011 949 3742",
    "sg:postcode":"10026",
    "sg:province":"Torino",
    "wof:name":"Delta Refrigerazioni",
    "wof:placetype":"venue"
},
  "geometry": {"coordinates":[7.7727541924,44.9490242004],"type":"Point"}
}