{
  "type": "Feature",
  "properties": {
    "iso:country":"IT",
    "sg:address":"67100 L'aquila",
    "sg:orig_category":"Macchine, Impianti E Forniture Per Industria Grafica, Cartaria E Cartotecnica",
    "sg:phone":"+39 0862 315787",
    "sg:postcode":"67100",
    "sg:province":"L'Aquila",
    "wof:name":"Start Snc",
    "wof:placetype":"venue"
},
  "geometry": {"coordinates":[13.497426,42.413437],"type":"Point"}
}