{
  "type": "Feature",
  "properties": {
    "iso:country":"IT",
    "sg:address":"42100 Reggio Emilia",
    "sg:orig_category":"Servizi E Lavori Per Industria Alimentare E Bevande",
    "sg:phone":"+39 0522 520121",
    "sg:postcode":"42100",
    "sg:province":"Reggio Nell'Emilia",
    "wof:name":"Braglia Alfredo Spa",
    "wof:placetype":"venue"
},
  "geometry": {"coordinates":[10.64668,44.647469],"type":"Point"}
}