{
  "type": "Feature",
  "properties": {
    "iso:country":"IT",
    "sg:address":"20090 Segrate",
    "sg:city":"Segrate",
    "sg:orig_category":"Agenzie D'affari E Servizi Commerciali",
    "sg:phone":"+39 02 2692 9282",
    "sg:postcode":"20090",
    "sg:province":"Milano",
    "wof:name":"Micronex Srl",
    "wof:placetype":"venue"
},
  "geometry": {"coordinates":[9.303998,45.497738],"type":"Point"}
}