{
  "type": "Feature",
  "properties": {
    "addr:full":"13100 Vercelli Vercelli Vercelli 13100",
    "addr:postcode":"13100;13100",
    "iso:country":"IT",
    "sg:address":"13100 Vercelli",
    "sg:city":"Vercelli",
    "sg:orig_category":"Automobili E Mezzi Di Trasporto",
    "sg:phone":"+39 0161 56461",
    "sg:postcode":"13100",
    "sg:province":"Vercelli",
    "wof:name":"Benini Moto Srl",
    "wof:placetype":"venue"
},
  "geometry": {"coordinates":[8.417936,45.326893],"type":"Point"}
}