{
  "type": "Feature",
  "properties": {
    "addr:full":"20125 Milano Milano Milano 20125",
    "addr:postcode":"20125;20125",
    "iso:country":"IT",
    "sg:address":"20125 Milano",
    "sg:city":"Milano",
    "sg:orig_category":"Macchine Ed Impianti Per Edilizia E Lavori Pubblici. Forniture Per Edilizia E Lavori Pubblici",
    "sg:phone":"+39 02 6747 9331",
    "sg:postcode":"20125",
    "sg:province":"Milano",
    "sg:website":"http://www.vibroget.net",
    "wof:name":"Vibroget Srl",
    "wof:placetype":"venue"
},
  "geometry": {"coordinates":[9.246177,45.510338],"type":"Point"}
}