{
  "type": "Feature",
  "properties": {
    "iso:country":"IT",
    "sg:address":"26867 Somaglia",
    "sg:city":"Somaglia",
    "sg:orig_category":"Radiografia E Radiologia - Impianti, Apparecchi E Forniture",
    "sg:phone":"+39 0377 57685",
    "sg:postcode":"26867",
    "sg:province":"Lodi",
    "sg:website":"http://www.pierotti.it",
    "wof:name":"Pierotti Maria Pia Srl",
    "wof:placetype":"venue"
},
  "geometry": {"coordinates":[9.633295,45.144779],"type":"Point"}
}