{
  "type": "Feature",
  "properties": {
    "iso:country":"IT",
    "sg:address":"00184 Roma",
    "sg:city":"Roma",
    "sg:orig_category":"Calzature, Pelletterie E Pelli. Servizi E Lavori Per Abbigliamento E Pelletterie",
    "sg:phone":"+39 06 474 3834",
    "sg:postcode":"00184",
    "sg:province":"Roma",
    "wof:name":"C.c.t. Calzature Cine Teatrali Srl",
    "wof:placetype":"venue"
},
  "geometry": {"coordinates":[12.485175,41.821686],"type":"Point"}
}