{
  "type": "Feature",
  "properties": {
    "addr:full":"6, Via Postioma 31040 Trevignano Trevignano Treviso 31040",
    "addr:postcode":"31040;31040",
    "addr:street":"Via Postioma",
    "iso:country":"IT",
    "sg:address":"6, Via Postioma 31040 Trevignano",
    "sg:city":"Trevignano",
    "sg:classifiers":[
        {
            "category":"Food & Beverages",
            "subcategory":"Dairy",
            "type":"Retail Goods"
        }
    ],
    "sg:phone":"+39 0423 819571",
    "sg:postcode":"31040",
    "sg:province":"Treviso",
    "sg:tags":[
        "product"
    ],
    "wof:name":"Formai (s.r.l.)",
    "wof:placetype":"venue"
},
  "geometry": {"coordinates":[12.078691,45.709911],"type":"Point"}
}