{
  "type": "Feature",
  "properties": {
    "iso:country":"IT",
    "sg:address":"24035 Curno",
    "sg:city":"Curno",
    "sg:orig_category":"Salotti, Poltrone, Sedie E Tavoli",
    "sg:phone":"+39 035 460637",
    "sg:postcode":"24035",
    "sg:province":"Bergamo",
    "wof:name":"Mauri Ferruccio",
    "wof:placetype":"venue"
},
  "geometry": {"coordinates":[9.609666,45.68362],"type":"Point"}
}