{
  "type": "Feature",
  "properties": {
    "addr:full":"21030 Rancio Valcuvia Rancio Valcuvia Varese 21030",
    "addr:postcode":"21030;21030",
    "addr:street":"Valcuvia;Valcuvia",
    "iso:country":"IT",
    "sg:address":"21030 Rancio Valcuvia",
    "sg:city":"Rancio Valcuvia",
    "sg:orig_category":"Prodotti Alimentari",
    "sg:phone":"+39 0332 994019",
    "sg:postcode":"21030",
    "sg:province":"Varese",
    "wof:name":"Molino Stalletti Luigi & C. Snc",
    "wof:placetype":"venue"
},
  "geometry": {"coordinates":[8.7689666748,45.9300689697],"type":"Point"}
}