{
  "type": "Feature",
  "properties": {
    "addr:full":"20092 Cinisello Balsamo Cinisello Balsamo Milano 20092",
    "addr:postcode":"20092;20092",
    "iso:country":"IT",
    "sg:address":"20092 Cinisello Balsamo",
    "sg:city":"Cinisello Balsamo",
    "sg:classifiers":[
        {
            "category":"Home & Garden",
            "subcategory":"Building Materials",
            "type":"Retail Goods"
        }
    ],
    "sg:phone":"+39 02 617 0348",
    "sg:postcode":"20092",
    "sg:province":"Milano",
    "sg:tags":[
        "window",
        "door",
        "frame"
    ],
    "wof:name":"Myfer Snc",
    "wof:placetype":"venue"
},
  "geometry": {"coordinates":[9.24383,45.560753],"type":"Point"}
}