{
  "type": "Feature",
  "properties": {
    "iso:country":"IT",
    "sg:address":"21013 Gallarate",
    "sg:city":"Gallarate",
    "sg:orig_category":"Trasportatori Meccanici E Pneumatici",
    "sg:phone":"+39 0331 776170",
    "sg:postcode":"21013",
    "sg:province":"Varese",
    "wof:name":"Bimac Srl",
    "wof:placetype":"venue"
},
  "geometry": {"coordinates":[8.870221,45.646473],"type":"Point"}
}