{
  "type": "Feature",
  "properties": {
    "addr:full":"19, Viale Delle Scienze 20082 Binasco Binasco Milano 20082",
    "addr:housenumber":"19",
    "addr:postcode":"20082;20082",
    "addr:street":"Viale Delle Scienze",
    "iso:country":"IT",
    "sg:address":"19, Viale Delle Scienze 20082 Binasco",
    "sg:city":"Binasco",
    "sg:classifiers":[
        {
            "category":"Manufacturing",
            "subcategory":"Printing",
            "type":"Manufacturing & Wholesale Goods"
        }
    ],
    "sg:phone":"+39 39029055169",
    "sg:postcode":"20082",
    "sg:province":"Milano",
    "sg:tags":[
        "publishing"
    ],
    "wof:name":"Cartograf S.n.c.",
    "wof:placetype":"venue"
},
  "geometry": {"coordinates":[9.0937395096,45.3360824585],"type":"Point"}
}