{
  "type": "Feature",
  "properties": {
    "addr:full":"20090 Cesano Boscone Cesano Boscone Milano 20090",
    "addr:postcode":"20090;20090",
    "iso:country":"IT",
    "sg:address":"20090 Cesano Boscone",
    "sg:city":"Cesano Boscone",
    "sg:orig_category":"Servizi E Lavori Per Arredamento E Industria Del Legno. Servizi E Lavori Per Edilizia E Lavori Pubblici",
    "sg:phone":"+39 02 458 2602",
    "sg:postcode":"20090",
    "sg:province":"Milano",
    "wof:name":"Notaro Felice",
    "wof:placetype":"venue"
},
  "geometry": {"coordinates":[9.090227,45.438042],"type":"Point"}
}