{
  "type": "Feature",
  "properties": {
    "addr:full":"81030 Sant'arpino Caserta 81030",
    "addr:postcode":"81030;81030",
    "iso:country":"IT",
    "sg:address":"81030 Sant'arpino",
    "sg:orig_category":"Forniture Per Abbigliamento E Pelletterie",
    "sg:phone":"+39 081 501 1056",
    "sg:postcode":"81030",
    "sg:province":"Caserta",
    "wof:name":"Liberti E C.srl",
    "wof:placetype":"venue"
},
  "geometry": {"coordinates":[14.2605724335,40.9663696289],"type":"Point"}
}