{
  "type": "Feature",
  "properties": {
    "addr:full":"80040 Cercola Cercola Napoli 80040",
    "addr:postcode":"80040;80040",
    "iso:country":"IT",
    "sg:address":"80040 Cercola",
    "sg:city":"Cercola",
    "sg:orig_category":"Minuterie Metalliche E Ferramenta",
    "sg:phone":"+39 081 555 1864",
    "sg:postcode":"80040",
    "sg:province":"Napoli",
    "wof:name":"Punzo Gabriele",
    "wof:placetype":"venue"
},
  "geometry": {"coordinates":[14.3537731171,40.8510971069],"type":"Point"}
}