{
  "type": "Feature",
  "properties": {
    "iso:country":"IT",
    "sg:address":"25015 Desenzano Del Garda",
    "sg:city":"Desenzano del Garda",
    "sg:orig_category":"Serramenti Ed Infissi. Prodotti Vari In Metallo",
    "sg:phone":"+39 030 912 0048",
    "sg:postcode":"25015",
    "sg:province":"Brescia",
    "wof:name":"Cvd Di Corain Vinicio E Alberto & C. S.a.s.",
    "wof:placetype":"venue"
},
  "geometry": {"coordinates":[10.530111,45.463306],"type":"Point"}
}