{
  "type": "Feature",
  "properties": {
    "iso:country":"IT",
    "sg:address":"00179 Roma",
    "sg:city":"Roma",
    "sg:orig_category":"Elettronica Professionale E Di Consumo. Tempo Libero - Articoli E Forniture",
    "sg:phone":"+39 06 789736",
    "sg:postcode":"00179",
    "sg:province":"Roma",
    "wof:name":"L.d.m. Giochi Di Luciano Pascucci E C. Snc",
    "wof:placetype":"venue"
},
  "geometry": {"coordinates":[12.526054,41.868885],"type":"Point"}
}