{
  "type": "Feature",
  "properties": {
    "iso:country":"IT",
    "sg:address":"25070 Sabbio Chiese",
    "sg:city":"Sabbio Chiese",
    "sg:orig_category":"Idrosanitari - Produzione",
    "sg:phone":"+39 036 589 5714",
    "sg:postcode":"25070",
    "sg:province":"Brescia",
    "wof:name":"Essebi Snc Di Savoldi Silvio Giovita & C",
    "wof:placetype":"venue"
},
  "geometry": {"coordinates":[10.419286,45.662575],"type":"Point"}
}