{
  "type": "Feature",
  "properties": {
    "iso:country":"IT",
    "sg:address":"20, Via Dello Stadio 56022 Castelfranco Di Sotto",
    "sg:city":"Castelfranco di Sotto",
    "sg:classifiers":[
        {
            "category":"Personal",
            "subcategory":"Shoe Repair & Shine",
            "type":"Services"
        }
    ],
    "sg:phone":"+39 0571 480586",
    "sg:postcode":"56022",
    "sg:province":"Pisa",
    "sg:tags":[
        "leather"
    ],
    "wof:name":"Calzaturificio Noemi Srl",
    "wof:placetype":"venue"
},
  "geometry": {"coordinates":[10.749887,43.701015],"type":"Point"}
}