{
  "type": "Feature",
  "properties": {
    "addr:full":"Via Ilaria Alpi ,26/28 56028 San Miniato Basso San Miniato Pisa 56028",
    "addr:housenumber":"26 / 28",
    "addr:postcode":"56028;56028",
    "addr:street":"Via Ilaria Alpi;Basso",
    "iso:country":"IT",
    "sg:address":"Via Ilaria Alpi ,26/28 56028 San Miniato Basso",
    "sg:city":"San Miniato",
    "sg:classifiers":[
        {
            "category":"Shopping",
            "subcategory":"Bicycles & Sporting Goods",
            "type":"Retail Goods"
        }
    ],
    "sg:phone":"+39 0571 401447",
    "sg:postcode":"56028",
    "sg:province":"Pisa",
    "sg:website":"www.daccordi-cicli.com",
    "wof:name":"Luigi Daccordi Impresa Individuale",
    "wof:placetype":"venue"
},
  "geometry": {"coordinates":[10.828933,43.694096],"type":"Point"}
}