{
  "type": "Feature",
  "properties": {
    "addr:full":"2, Via Oberdan Guglielmo 25128 Brescia Brescia Brescia 25128",
    "addr:postcode":"25128;25128",
    "addr:street":"Via Oberdan Guglielmo",
    "iso:country":"IT",
    "sg:address":"2, Via Oberdan Guglielmo 25128 Brescia",
    "sg:city":"Brescia",
    "sg:classifiers":[
        {
            "category":"Manufacturing",
            "subcategory":"Tools & Machinery",
            "type":"Manufacturing & Wholesale Goods"
        }
    ],
    "sg:phone":"+39 39030380246",
    "sg:postcode":"25128",
    "sg:province":"Brescia",
    "sg:tags":[
        "environment",
        "equipment",
        "-"
    ],
    "wof:name":"Ata Engineering Alta Tecnologia Ambientale S.r.l.",
    "wof:placetype":"venue"
},
  "geometry": {"coordinates":[10.222958,45.539829],"type":"Point"}
}