{
  "type": "Feature",
  "properties": {
    "iso:country":"IT",
    "sg:address":"Via Trani 174 70051 Barletta",
    "sg:city":"Barletta",
    "sg:classifiers":[
        {
            "category":"Banks & Credit Unions",
            "subcategory":"Atm",
            "type":"Services"
        }
    ],
    "sg:phone":"+39 0883 533062",
    "sg:postcode":"70051",
    "sg:province":"Bari",
    "sg:tags":[
        "lock",
        "high-security",
        "fitting"
    ],
    "sg:website":"www.smal.it",
    "wof:name":"Smal Di Losappio Antonio & C. S.a.s .",
    "wof:placetype":"venue"
},
  "geometry": {"coordinates":[16.310165,41.309456],"type":"Point"}
}