{
  "type": "Feature",
  "properties": {
    "iso:country":"IT",
    "sg:address":"19/21, V. Rombiolo 00178 Roma",
    "sg:city":"Roma",
    "sg:classifiers":[
        {
            "category":"Professional",
            "subcategory":"Engineering",
            "type":"Services"
        }
    ],
    "sg:phone":"+39 39067183111",
    "sg:postcode":"00178",
    "sg:province":"Roma",
    "sg:tags":[
        "machine",
        "-",
        "mechanical"
    ],
    "sg:website":"http://www.paginegialle.it/colonebelts",
    "wof:name":"Colone-belt Srl",
    "wof:placetype":"venue"
},
  "geometry": {"coordinates":[12.557537,41.840889],"type":"Point"}
}