{
  "type": "Feature",
  "properties": {
    "iso:country":"IT",
    "sg:address":"20124 Milano",
    "sg:city":"Milano",
    "sg:orig_category":"Agenzie Ed Enti Turistici",
    "sg:phone":"+39 02 2953 6541",
    "sg:postcode":"20124",
    "sg:province":"Milano",
    "sg:website":"http://www.nonsolomare.org",
    "wof:name":"Agenzia Viaggi Nonsolomare",
    "wof:placetype":"venue"
},
  "geometry": {"coordinates":[9.206673,45.482372],"type":"Point"}
}