{
  "type": "Feature",
  "properties": {
    "iso:country":"IT",
    "sg:address":"80030 Castel Cisterna",
    "sg:orig_category":"Arredamenti - Vendita Al Dettaglio",
    "sg:phone":"+39 081 886 3171",
    "sg:postcode":"80030",
    "sg:province":"Napoli",
    "wof:name":"Centro Camerette",
    "wof:placetype":"venue"
},
  "geometry": {"coordinates":[15.170838,41.089676],"type":"Point"}
}