{
  "type": "Feature",
  "properties": {
    "iso:country":"IT",
    "sg:address":"41057 Spilamberto",
    "sg:city":"Spilamberto",
    "sg:classifiers":[
        {
            "category":"Farming",
            "subcategory":"Livestock Farm",
            "type":"Manufacturing & Wholesale Goods"
        }
    ],
    "sg:phone":"+39 059 784392",
    "sg:postcode":"41057",
    "sg:province":"Modena",
    "sg:tags":[
        "equipment",
        "breeding",
        "agriculture",
        "machinery"
    ],
    "sg:website":"http://www.thema.it/lam",
    "wof:name":"L.a.m. Srl",
    "wof:placetype":"venue"
},
  "geometry": {"coordinates":[11.00487,44.547569],"type":"Point"}
}