{
  "type": "Feature",
  "properties": {
    "iso:country":"IT",
    "sg:address":"Sda Nuova Padovana 37040 San Gregorio Di Veronella",
    "sg:city":"San Gregorio",
    "sg:orig_category":"Underwear, Woven",
    "sg:phone":"+39 0442 47688",
    "sg:postcode":"37040",
    "sg:province":"Verona",
    "sg:website":"www.antonella.it",
    "wof:name":"Maglificio Antonella Spa",
    "wof:placetype":"venue"
},
  "geometry": {"coordinates":[10.991748,45.438366],"type":"Point"}
}