{
  "type": "Feature",
  "properties": {
    "addr:full":"18, Via Lisonino 26866 Sant'angelo Lodigiano Lodi 26866",
    "addr:postcode":"26866;26866",
    "addr:street":"Via Lisonino",
    "iso:country":"IT",
    "sg:address":"18, Via Lisonino 26866 Sant'angelo Lodigiano",
    "sg:classifiers":[
        {
            "category":"Wholesale",
            "subcategory":"Machinery & Supplies",
            "type":"Manufacturing & Wholesale Goods"
        }
    ],
    "sg:phone":"+39 39037190445",
    "sg:postcode":"26866",
    "sg:province":"Lodi",
    "sg:tags":[
        "-",
        "agriculture",
        "equipment"
    ],
    "wof:name":"Savare' Domenico Di Savare' A. & C. (s.n.c.)",
    "wof:placetype":"venue"
},
  "geometry": {"coordinates":[9.407216,45.243847],"type":"Point"}
}