{
  "type": "Feature",
  "properties": {
    "addr:full":"23880 Casatenovo Casatenovo Lecco 23880",
    "addr:postcode":"23880;23880",
    "iso:country":"IT",
    "sg:address":"23880 Casatenovo",
    "sg:city":"Casatenovo",
    "sg:orig_category":"Tessuti E Stoffe",
    "sg:phone":"+39 039 920 8011",
    "sg:postcode":"23880",
    "sg:province":"Lecco",
    "wof:name":"C B Blades S.n.c. Di Bonfanti Luca & C.",
    "wof:placetype":"venue"
},
  "geometry": {"coordinates":[9.304247,45.701851],"type":"Point"}
}