{
  "type": "Feature",
  "properties": {
    "addr:full":"91025 Marsala Marsala Trapani 91025",
    "addr:postcode":"91025;91025",
    "iso:country":"IT",
    "sg:address":"91025 Marsala",
    "sg:city":"Marsala",
    "sg:orig_category":"Pompe. Macchine, Strumenti Ed Apparecchi Per Attivita' Industriali",
    "sg:phone":"+39 0923 735008",
    "sg:postcode":"91025",
    "sg:province":"Trapani",
    "wof:name":"Omac Commerciale Srl",
    "wof:placetype":"venue"
},
  "geometry": {"coordinates":[12.5527505875,37.83253479],"type":"Point"}
}