{
  "type": "Feature",
  "properties": {
    "addr:full":"Via Antonio Locatelli 133 24019 Zogno Zogno Bergamo 24019",
    "addr:housenumber":"133",
    "addr:postcode":"24019;24019",
    "addr:street":"Via Antonio Locatelli",
    "iso:country":"IT",
    "sg:address":"Via Antonio Locatelli 133 24019 Zogno",
    "sg:city":"Zogno",
    "sg:classifiers":[
        {
            "category":"Manufacturing",
            "subcategory":"Rubber & Plastics",
            "type":"Manufacturing & Wholesale Goods"
        }
    ],
    "sg:phone":"+39 0345 94333",
    "sg:postcode":"24019",
    "sg:province":"Bergamo",
    "sg:tags":[
        "wood",
        "tool",
        "processing",
        "cnc"
    ],
    "sg:website":"www.rinaldi.it",
    "wof:name":"Rinaldi Srl",
    "wof:placetype":"venue"
},
  "geometry": {"coordinates":[9.662219,45.746342],"type":"Point"}
}