{
  "type": "Feature",
  "properties": {
    "iso:country":"IT",
    "sg:address":"5, Via Zona Industriale 26814 Livraga",
    "sg:city":"Livraga",
    "sg:classifiers":[
        {
            "category":"Wholesale",
            "subcategory":"Medical Equipment & Supplies",
            "type":"Manufacturing & Wholesale Goods"
        }
    ],
    "sg:phone":"+39 0377 987201",
    "sg:postcode":"26814",
    "sg:province":"Lodi",
    "sg:tags":[
        "-",
        "health",
        "instrument"
    ],
    "wof:name":"C.g.d.b. (s.p.a.)",
    "wof:placetype":"venue"
},
  "geometry": {"coordinates":[9.49785,45.312878],"type":"Point"}
}