{
  "type": "Feature",
  "properties": {
    "iso:country":"IT",
    "sg:address":"33057 Palmanova",
    "sg:city":"Palmanova",
    "sg:orig_category":"Edilizia - Materiali",
    "sg:phone":"+39 0432 929792",
    "sg:postcode":"33057",
    "sg:province":"Udine",
    "sg:website":"http://www.ilcanguro.net",
    "wof:name":"Il Canguro Soc. Coop. A R.l.",
    "wof:placetype":"venue"
},
  "geometry": {"coordinates":[13.317671,45.904892],"type":"Point"}
}