{
  "type": "Feature",
  "properties": {
    "iso:country":"IT",
    "sg:address":"27/29, Via Comunale Pelo 55012 Capannori",
    "sg:city":"Capannori",
    "sg:classifiers":[
        {
            "category":"Manufacturing",
            "subcategory":"Paper Products",
            "type":"Manufacturing & Wholesale Goods"
        }
    ],
    "sg:phone":"+39 0583 936696",
    "sg:postcode":"55012",
    "sg:province":"Lucca",
    "sg:tags":[
        "cardboard"
    ],
    "wof:name":"Im.c.on Di Cipriani Francesco E Stefano Snc",
    "wof:placetype":"venue"
},
  "geometry": {"coordinates":[10.5833330154,43.8333320618],"type":"Point"}
}