{
  "type": "Feature",
  "properties": {
    "iso:country":"IT",
    "sg:address":"10156 Torino",
    "sg:city":"Torino",
    "sg:orig_category":"Verniciatura A Spruzzo",
    "sg:phone":"+39 011 262 4172",
    "sg:postcode":"10156",
    "sg:province":"Torino",
    "wof:name":"Guglielmi Verniciatura Srl",
    "wof:placetype":"venue"
},
  "geometry": {"coordinates":[7.70615,45.119347],"type":"Point"}
}