{
  "type": "Feature",
  "properties": {
    "iso:country":"IT",
    "sg:address":"41, Via Pascoli Giovanni 20090 Segrate",
    "sg:city":"Segrate",
    "sg:classifiers":[
        {
            "category":"Professional",
            "subcategory":"Printing & Photocopies",
            "type":"Services"
        }
    ],
    "sg:phone":"+39 39027560159",
    "sg:postcode":"20090",
    "sg:province":"Milano",
    "wof:name":"Arti Grafiche M. & G.pirovano S.r.l.",
    "wof:placetype":"venue"
},
  "geometry": {"coordinates":[9.2793521881,45.4682044983],"type":"Point"}
}