{
  "type": "Feature",
  "properties": {
    "iso:country":"IT",
    "sg:address":"16134 Genova",
    "sg:city":"Genova",
    "sg:orig_category":"Apparecchiature E Sistemi Per Imballaggio E Confezionamento. Apparecchiature E Sistemi Per Magazzinaggio E Movimentazione",
    "sg:phone":"+39 010 275 8579",
    "sg:postcode":"16134",
    "sg:province":"Genova",
    "wof:name":"Ligure Containers Services (s.r.l.)",
    "wof:placetype":"venue"
},
  "geometry": {"coordinates":[8.919224,44.419098],"type":"Point"}
}