{
  "type": "Feature",
  "properties": {
    "iso:country":"IT",
    "sg:address":"31040 Salgareda",
    "sg:city":"Salgareda",
    "sg:orig_category":"Asfalti, Bitumi Ed Affini",
    "sg:phone":"+39 0422 747069",
    "sg:postcode":"31040",
    "sg:province":"Treviso",
    "wof:name":"G.e.p.",
    "wof:placetype":"venue"
},
  "geometry": {"coordinates":[12.510858,45.694069],"type":"Point"}
}