{
  "type": "Feature",
  "properties": {
    "iso:country":"IT",
    "sg:address":"74026 Pulsano",
    "sg:city":"Pulsano",
    "sg:orig_category":"Imprese Di Costruzioni Civili Ed Industriali. Servizi E Lavori Per Ecologia E Smaltimento Rifiuti",
    "sg:phone":"+39 099 533 0603",
    "sg:postcode":"74026",
    "sg:province":"Taranto",
    "wof:name":"De.pu.edil. Di Giovanni Scardino & C. Snc",
    "wof:placetype":"venue"
},
  "geometry": {"coordinates":[17.355614,40.385311],"type":"Point"}
}