{
  "type": "Feature",
  "properties": {
    "iso:country":"IT",
    "sg:address":"Via Foligno 97/12 10149 Torino",
    "sg:city":"Torino",
    "sg:classifiers":[
        {
            "category":"Manufacturing",
            "subcategory":"Motor Vehicles & Parts",
            "type":"Manufacturing & Wholesale Goods"
        }
    ],
    "sg:phone":"+39 011 455 0131",
    "sg:postcode":"10149",
    "sg:province":"Torino",
    "sg:tags":[
        "industry",
        "metallurgical",
        "spare"
    ],
    "sg:website":"www.errebisider.it",
    "wof:name":"Errebi Siderurgica Srl",
    "wof:placetype":"venue"
},
  "geometry": {"coordinates":[7.658952,45.100079],"type":"Point"}
}