{
  "type": "Feature",
  "properties": {
    "iso:country":"IT",
    "sg:address":"09170 Oristano",
    "sg:city":"Oristano",
    "sg:orig_category":"Autogru - Noleggio",
    "sg:phone":"+39 0783 73281",
    "sg:postcode":"09170",
    "sg:province":"Oristano",
    "wof:name":"Veica Srl",
    "wof:placetype":"venue"
},
  "geometry": {"coordinates":[8.605074,39.917812],"type":"Point"}
}