{
  "type": "Feature",
  "properties": {
    "addr:full":"10, Via Martinelli 34015 Muggia Muggia Trieste 34015",
    "addr:postcode":"34015;34015",
    "addr:street":"Via Martinelli",
    "iso:country":"IT",
    "sg:address":"10, Via Martinelli 34015 Muggia",
    "sg:city":"Muggia",
    "sg:classifiers":[
        {
            "category":"Autos & Motor Vehicles",
            "subcategory":"Automobile Sales",
            "type":"Retail Goods"
        }
    ],
    "sg:phone":"+39 39040232277",
    "sg:postcode":"34015",
    "sg:province":"Trieste",
    "sg:tags":[
        "motor-cars"
    ],
    "wof:name":"Nascimben Fratelli (s.p.a.)",
    "wof:placetype":"venue"
},
  "geometry": {"coordinates":[13.8055028915,45.5925865173],"type":"Point"}
}