{
  "type": "Feature",
  "properties": {
    "iso:country":"IT",
    "sg:address":"Via D. Alighieri 21 21019 Somma Lombardo",
    "sg:city":"Somma Lombardo",
    "sg:classifiers":[
        {
            "category":"Banks & Credit Unions",
            "subcategory":"Financial Services",
            "type":"Services"
        }
    ],
    "sg:phone":"+39 0331 256593",
    "sg:postcode":"21019",
    "sg:province":"Varese",
    "sg:tags":[
        "knitwear",
        "industry",
        "lace"
    ],
    "wof:name":"Vemarpiz Srl",
    "wof:placetype":"venue"
},
  "geometry": {"coordinates":[8.826385,45.817604],"type":"Point"}
}