{
  "type": "Feature",
  "properties": {
    "iso:country":"IT",
    "sg:address":"21038 Sangiano",
    "sg:city":"Sangiano",
    "sg:orig_category":"Agenzie Ed Uffici Commerciali",
    "sg:phone":"+39 0332 647305",
    "sg:postcode":"21038",
    "sg:province":"Varese",
    "wof:name":"Tecnomel Snc",
    "wof:placetype":"venue"
},
  "geometry": {"coordinates":[8.632618,45.875858],"type":"Point"}
}