{
  "type": "Feature",
  "properties": {
    "addr:full":"4, Via Pezzotti Giovanni 20141 Milano Milano Milano 20141",
    "addr:postcode":"20141;20141",
    "addr:street":"Via Pezzotti Giovanni",
    "iso:country":"IT",
    "sg:address":"4, Via Pezzotti Giovanni 20141 Milano",
    "sg:city":"Milano",
    "sg:classifiers":[
        {
            "category":"Manufacturing",
            "subcategory":"Printing",
            "type":"Manufacturing & Wholesale Goods"
        }
    ],
    "sg:phone":"+39 02 5810 3891",
    "sg:postcode":"20141",
    "sg:province":"Milano",
    "sg:tags":[
        "publishing"
    ],
    "wof:name":"Collins S.r.l.",
    "wof:placetype":"venue"
},
  "geometry": {"coordinates":[9.1828517914,45.4432258606],"type":"Point"}
}