{
  "type": "Feature",
  "properties": {
    "iso:country":"IT",
    "sg:address":"88, V. Copernico 41015 Nonantola",
    "sg:city":"Nonantola",
    "sg:classifiers":[
        {
            "category":"Shopping",
            "subcategory":"Computers & Home Electronics",
            "type":"Retail Goods"
        }
    ],
    "sg:phone":"+39 39059548655",
    "sg:postcode":"41015",
    "sg:province":"Modena",
    "sg:tags":[
        "electronic",
        "electrical",
        "equipment"
    ],
    "sg:website":"http://www.aliceclub.it",
    "wof:name":"Alice Club Sas",
    "wof:placetype":"venue"
},
  "geometry": {"coordinates":[11.017054,44.676064],"type":"Point"}
}