{
  "type": "Feature",
  "properties": {
    "addr:full":"00152 Roma Roma Roma 00152",
    "addr:postcode":"00152;00152",
    "iso:country":"IT",
    "sg:address":"00152 Roma",
    "sg:city":"Roma",
    "sg:orig_category":"Scuole E Servizi Scolastici",
    "sg:phone":"+39 06 582 6107",
    "sg:postcode":"00152",
    "sg:province":"Roma",
    "wof:name":"Scuola Parificata Anna Micheli",
    "wof:placetype":"venue"
},
  "geometry": {"coordinates":[12.422956,41.855946],"type":"Point"}
}