{
  "type": "Feature",
  "properties": {
    "addr:full":"21047 Saronno Saronno Varese 21047",
    "addr:postcode":"21047;21047",
    "iso:country":"IT",
    "sg:address":"21047 Saronno",
    "sg:city":"Saronno",
    "sg:orig_category":"Servizi Editoriali. Professionisti - Studi E Servizi Ed Associazioni Di Interesse Aziendale",
    "sg:phone":"+39 02 962 2874",
    "sg:postcode":"21047",
    "sg:province":"Varese",
    "wof:name":"Saiz Saez Jesus",
    "wof:placetype":"venue"
},
  "geometry": {"coordinates":[9.02705,45.629539],"type":"Point"}
}