{
  "type": "Feature",
  "properties": {
    "addr:full":"49, Via Cirignano 80069 Vico Equense Vico Equense Napoli 80069",
    "addr:postcode":"80069;80069",
    "addr:street":"Via Cirignano;Vico",
    "iso:country":"IT",
    "sg:address":"49, Via Cirignano 80069 Vico Equense",
    "sg:city":"Vico Equense",
    "sg:classifiers":[
        {
            "category":"Manufacturing",
            "subcategory":"Lumber",
            "type":"Manufacturing & Wholesale Goods"
        }
    ],
    "sg:phone":"+39 081 802 3101",
    "sg:postcode":"80069",
    "sg:province":"Napoli",
    "sg:tags":[
        "wood"
    ],
    "wof:name":"De Martino Antonino",
    "wof:placetype":"venue"
},
  "geometry": {"coordinates":[14.463052,40.650887],"type":"Point"}
}