{
  "type": "Feature",
  "properties": {
    "iso:country":"IT",
    "sg:address":"20090 Pieve Emanuele",
    "sg:city":"Pieve Emanuele",
    "sg:orig_category":"Serramenti Ed Infissi. Prodotti Vari In Metallo",
    "sg:phone":"+39 02 9040 0244",
    "sg:postcode":"20090",
    "sg:province":"Milano",
    "sg:website":"http://www.fbpserramenti.it",
    "wof:name":"F.b.p. Sas Di Boni",
    "wof:placetype":"venue"
},
  "geometry": {"coordinates":[9.185315,45.36985],"type":"Point"}
}