{
  "type": "Feature",
  "properties": {
    "iso:country":"IT",
    "sg:address":"13011 Borgosesia",
    "sg:city":"Borgosesia",
    "sg:orig_category":"Cartotecnica E Servizi. Articoli Per Imballaggio E Confezionamento",
    "sg:phone":"+39 0163 20050",
    "sg:postcode":"13011",
    "sg:province":"Vercelli",
    "wof:name":"Kartec Sas Di Casagrande Paolo, Michele & C.",
    "wof:placetype":"venue"
},
  "geometry": {"coordinates":[8.277605,45.716988],"type":"Point"}
}