{
  "type": "Feature",
  "properties": {
    "iso:country":"IT",
    "sg:address":"15/2, Via Empoli 50142 Firenze",
    "sg:city":"Firenze",
    "sg:classifiers":[
        {
            "category":"Shopping",
            "subcategory":"Jewelry",
            "type":"Retail Goods"
        }
    ],
    "sg:phone":"+39 055 732 1317",
    "sg:postcode":"50142",
    "sg:province":"Firenze",
    "sg:tags":[
        "jewellery"
    ],
    "wof:name":"Minozzi (s.r.l.)",
    "wof:placetype":"venue"
},
  "geometry": {"coordinates":[11.2048,43.772537],"type":"Point"}
}