{
  "type": "Feature",
  "properties": {
    "iso:country":"IT",
    "sg:address":"00153 Roma",
    "sg:city":"Roma",
    "sg:orig_category":"Associazioni Ed Organismi Di Interesse Pubblico",
    "sg:phone":"+39 06 574 2981",
    "sg:postcode":"00153",
    "sg:province":"Roma",
    "wof:name":"Associazione Italiana Utenti E Consumatori",
    "wof:placetype":"venue"
},
  "geometry": {"coordinates":[12.472164,41.877304],"type":"Point"}
}