{
  "type": "Feature",
  "properties": {
    "addr:full":"Via Delle Industrie 1 17012 Albissola Marina Albissola Marina Savona 17012",
    "addr:housenumber":"1",
    "addr:postcode":"17012;17012",
    "addr:street":"Via Delle Industrie",
    "iso:country":"IT",
    "sg:address":"Via Delle Industrie 1 17012 Albissola Marina",
    "sg:city":"Albissola Marina",
    "sg:classifiers":[
        {
            "category":"Food & Beverages",
            "subcategory":"Groceries & Convenience Stores",
            "type":"Retail Goods"
        }
    ],
    "sg:phone":"+39 019 486923",
    "sg:postcode":"17012",
    "sg:province":"Savona",
    "sg:tags":[
        "dietetic",
        "foodstuff"
    ],
    "sg:website":"www.esitalia.com",
    "wof:name":"Esi S.p.a.",
    "wof:placetype":"venue"
},
  "geometry": {"coordinates":[8.502196,44.337574],"type":"Point"}
}