{
  "type": "Feature",
  "properties": {
    "iso:country":"IT",
    "sg:address":"58100 Grosseto",
    "sg:city":"Grosseto",
    "sg:orig_category":"Assicurazioni E Servizi Assicurativi. Consulenze Tecniche, Amministrative E Perizie",
    "sg:phone":"+39 0564 413655",
    "sg:postcode":"58100",
    "sg:province":"Grosseto",
    "wof:name":"Studio Biemme Sas",
    "wof:placetype":"venue"
},
  "geometry": {"coordinates":[11.122659,42.765236],"type":"Point"}
}