{
  "type": "Feature",
  "properties": {
    "iso:country":"IT",
    "sg:address":"31, Via Crosera 33082 Azzano Decimo",
    "sg:city":"Azzano Decimo",
    "sg:classifiers":[
        {
            "category":"Manufacturing",
            "subcategory":"Printing",
            "type":"Manufacturing & Wholesale Goods"
        }
    ],
    "sg:phone":"+39 0434 632089",
    "sg:postcode":"33082",
    "sg:province":"Pordenone",
    "sg:tags":[
        "publishing"
    ],
    "wof:name":"Cartotecnica Friulana S.n.c.",
    "wof:placetype":"venue"
},
  "geometry": {"coordinates":[12.6886405945,45.8928947449],"type":"Point"}
}