{
  "type": "Feature",
  "properties": {
    "iso:country":"IT",
    "sg:address":"35013 Cittadella",
    "sg:city":"Cittadella",
    "sg:orig_category":"Articoli Medico-sanitari Ed Ortopedici. Impianti, Attrezzature E Forniture Sanitarie Ed Ospedaliere",
    "sg:phone":"+39 049 940 1093",
    "sg:postcode":"35013",
    "sg:province":"Padova",
    "wof:name":"Strumentazione Elettronica Industriale Di Didone' Ing. Giorgio & C. (s.n.c.)",
    "wof:placetype":"venue"
},
  "geometry": {"coordinates":[11.786617,45.666035],"type":"Point"}
}