{
  "type": "Feature",
  "properties": {
    "addr:full":"11, Via Antica Cava 41042 Fiorano Modenese Fiorano Modenese Modena 41042",
    "addr:postcode":"41042;41042",
    "addr:street":"Via Antica Cava",
    "iso:country":"IT",
    "sg:address":"11, Via Antica Cava 41042 Fiorano Modenese",
    "sg:city":"Fiorano Modenese",
    "sg:classifiers":[
        {
            "category":"Shopping",
            "subcategory":"Crafts & Fabrics",
            "type":"Retail Goods"
        }
    ],
    "sg:phone":"+39 0536 921553",
    "sg:postcode":"41042",
    "sg:province":"Modena",
    "sg:tags":[
        "ceramic"
    ],
    "wof:name":"Labo-cer Srl",
    "wof:placetype":"venue"
},
  "geometry": {"coordinates":[10.848972,44.541252],"type":"Point"}
}