{
  "type": "Feature",
  "properties": {
    "addr:full":"50018 Scandicci Scandicci Firenze 50018",
    "addr:postcode":"50018;50018",
    "iso:country":"IT",
    "sg:address":"50018 Scandicci",
    "sg:city":"Scandicci",
    "sg:orig_category":"Musica",
    "sg:phone":"+39 055 754 2214",
    "sg:postcode":"50018",
    "sg:province":"Firenze",
    "sg:website":"http://www.harmonymusic.it",
    "wof:name":"Harmony Music Srl",
    "wof:placetype":"venue"
},
  "geometry": {"coordinates":[11.1661043167,43.7634887695],"type":"Point"}
}