{
  "type": "Feature",
  "properties": {
    "iso:country":"IT",
    "sg:address":"58046 Grosseto",
    "sg:orig_category":"Agenzie Immobiliari",
    "sg:phone":"+39 0564 37223",
    "sg:province":"GR",
    "sg:website":"http://www.marinadigrosseto.it/biancotti",
    "wof:name":"Agenzia Immobiliare Biancotti",
    "wof:placetype":"venue"
},
  "geometry": {"coordinates":[11.112782,42.762859],"type":"Point"}
}