{
  "type": "Feature",
  "properties": {
    "iso:country":"IT",
    "sg:address":"00187 Roma",
    "sg:city":"Roma",
    "sg:orig_category":"Servizi E Lavori Per Ecologia E Smaltimento Rifiuti. Servizi Ausiliari Di Sorveglianza, Manutenzione E Pulizia",
    "sg:phone":"+39 06 4201 4429",
    "sg:postcode":"00187",
    "sg:province":"Roma",
    "wof:name":"Centro Italia Eco Ambiente Srl",
    "wof:placetype":"venue"
},
  "geometry": {"coordinates":[12.496984,41.909306],"type":"Point"}
}