{
  "type": "Feature",
  "properties": {
    "iso:country":"IT",
    "sg:address":"38066 Riva Del Garda",
    "sg:city":"Riva del Garda",
    "sg:orig_category":"Agenzie Immobiliari",
    "sg:phone":"+39 0464 520499",
    "sg:postcode":"38066",
    "sg:province":"Trento",
    "sg:website":"http://www.quadrifoglioimm.it",
    "wof:name":"Agenzia Immobiliare Quadrifoglio",
    "wof:placetype":"venue"
},
  "geometry": {"coordinates":[10.857544,45.906029],"type":"Point"}
}