{
  "type": "Feature",
  "properties": {
    "iso:country":"IT",
    "sg:address":"66020 S. Giovanni Teatino",
    "sg:orig_category":"Materiali E Componenti Elettrotecnici",
    "sg:phone":"+39 085 446 3759",
    "sg:postcode":"66020",
    "sg:province":"Chieti",
    "wof:name":"Dime Srl",
    "wof:placetype":"venue"
},
  "geometry": {"coordinates":[14.163328,42.401901],"type":"Point"}
}