{
  "type": "Feature",
  "properties": {
    "iso:country":"IT",
    "sg:address":"35016 Piazzola Sul Brenta",
    "sg:city":"Piazzola sul Brenta",
    "sg:classifiers":[
        {
            "category":"Wholesale",
            "subcategory":"Chemicals & Plastics",
            "type":"Manufacturing & Wholesale Goods"
        }
    ],
    "sg:phone":"+39 049 559 8446",
    "sg:postcode":"35016",
    "sg:province":"Padova",
    "sg:tags":[
        "article",
        "product",
        "plastics"
    ],
    "wof:name":"De.mi.plast Di Mion Giannina",
    "wof:placetype":"venue"
},
  "geometry": {"coordinates":[11.8280096054,45.5084381104],"type":"Point"}
}