{
  "type": "Feature",
  "properties": {
    "iso:country":"IT",
    "sg:address":"06031 Bevagna",
    "sg:city":"Bevagna",
    "sg:orig_category":"Arredamento Ospedali, Ambulatori E Studi Medici",
    "sg:phone":"+39 0742 361947",
    "sg:postcode":"06031",
    "sg:province":"Perugia",
    "wof:name":"Ksp Italia Srl",
    "wof:placetype":"venue"
},
  "geometry": {"coordinates":[12.680844,42.828106],"type":"Point"}
}