{
  "type": "Feature",
  "properties": {
    "addr:full":"Ctr San Gaetano 1200 91011 Alcamo Alcamo Trapani 91011",
    "addr:housenumber":"1200",
    "addr:postcode":"91011;91011",
    "addr:street":"Ctr San Gaetano",
    "iso:country":"IT",
    "sg:address":"Ctr San Gaetano 1200 91011 Alcamo",
    "sg:city":"Alcamo",
    "sg:classifiers":[
        {
            "category":"Transit Center",
            "subcategory":"Freight",
            "type":"Transportation"
        }
    ],
    "sg:phone":"+39 0924 503846",
    "sg:postcode":"91011",
    "sg:province":"Trapani",
    "sg:tags":[
        "shipyard",
        "crane"
    ],
    "sg:website":"www.sormec.net",
    "wof:name":"Sormec S.r.l.",
    "wof:placetype":"venue"
},
  "geometry": {"coordinates":[12.514634,38.018589],"type":"Point"}
}