{
  "type": "Feature",
  "properties": {
    "addr:full":"65, Via S. Protaso 21017 Samarate Samarate Varese 21017",
    "addr:postcode":"21017;21017",
    "addr:street":"Via S. Protaso",
    "iso:country":"IT",
    "sg:address":"65, Via S. Protaso 21017 Samarate",
    "sg:city":"Samarate",
    "sg:classifiers":[
        {
            "category":"Professional",
            "subcategory":"Engineering",
            "type":"Services"
        }
    ],
    "sg:phone":"+39 0331 222302",
    "sg:postcode":"21017",
    "sg:province":"Varese",
    "sg:tags":[
        "machine",
        "-",
        "mechanical"
    ],
    "wof:name":"Omf Di Fortunato Giuseppe & C. (s.n.c.)",
    "wof:placetype":"venue"
},
  "geometry": {"coordinates":[8.826385,45.817604],"type":"Point"}
}