{
  "type": "Feature",
  "properties": {
    "iso:country":"IT",
    "sg:address":"37057 San Giovanni Lupatoto",
    "sg:city":"San Giovanni Lupatoto",
    "sg:orig_category":"Autodemolizioni",
    "sg:phone":"+39 045 8730 9909",
    "sg:postcode":"37057",
    "sg:province":"Verona",
    "wof:name":"Autodemolizioni 2000 Di Ferrari Vera & C. Snc",
    "wof:placetype":"venue"
},
  "geometry": {"coordinates":[11.034973,45.349831],"type":"Point"}
}