{
  "type": "Feature",
  "properties": {
    "iso:country":"IT",
    "sg:address":"Via Don Innocenzo; Ponte Stazzemes; 55040",
    "sg:classifiers":[
        {
            "category":"Banks & Credit Unions",
            "subcategory":"Bank",
            "type":"Services"
        }
    ],
    "sg:phone":"+39 0584 777223",
    "sg:postcode":"55040",
    "sg:province":"Lucca",
    "wof:name":"Banca Toscana Spa",
    "wof:placetype":"venue"
},
  "geometry": {"coordinates":[10.293669,44.000698],"type":"Point"}
}