{
  "type": "Feature",
  "properties": {
    "addr:full":"1, Via Bisbino 22070 Grandate Grandate Como 22070",
    "addr:postcode":"22070;22070",
    "addr:street":"Via Bisbino",
    "iso:country":"IT",
    "sg:address":"1, Via Bisbino 22070 Grandate",
    "sg:city":"Grandate",
    "sg:classifiers":[
        {
            "category":"Manufacturing",
            "subcategory":"Food",
            "type":"Manufacturing & Wholesale Goods"
        }
    ],
    "sg:phone":"+39 39031564621",
    "sg:postcode":"22070",
    "sg:province":"Como",
    "sg:tags":[
        "equipment",
        "processing",
        "-",
        "machinery"
    ],
    "wof:name":"Capitanio Camillo (s.n.c.)",
    "wof:placetype":"venue"
},
  "geometry": {"coordinates":[9.0649290085,45.7759780884],"type":"Point"}
}