{
  "type": "Feature",
  "properties": {
    "addr:full":"6, Via La Torre Pio 42015 Correggio Reggio Nell'Emilia 42015",
    "addr:postcode":"42015;42015",
    "addr:street":"Via La Torre Pio",
    "iso:country":"IT",
    "sg:address":"6, Via La Torre Pio 42015 Correggio",
    "sg:classifiers":[
        {
            "category":"Autos & Motor Vehicles",
            "subcategory":"Automobile Sales",
            "type":"Retail Goods"
        }
    ],
    "sg:phone":"+39 0522 637583",
    "sg:postcode":"42015",
    "sg:province":"Reggio Nell'Emilia",
    "sg:tags":[
        "motor-cars"
    ],
    "wof:name":"Prima (s.r.l.)",
    "wof:placetype":"venue"
},
  "geometry": {"coordinates":[10.6277942657,44.6962280273],"type":"Point"}
}