{
  "type": "Feature",
  "properties": {
    "iso:country":"IT",
    "sg:address":"42010 Rio Saliceto",
    "sg:orig_category":"Manufacturers: Prefabbricati",
    "sg:phone":"+39 0522 649346",
    "sg:postcode":"42010",
    "sg:province":"Reggio Nell'Emilia",
    "wof:name":"Venturelli Gemmo",
    "wof:placetype":"venue"
},
  "geometry": {"coordinates":[10.793002,44.768887],"type":"Point"}
}