{
  "type": "Feature",
  "properties": {
    "iso:country":"IT",
    "sg:address":"6, V. Roma 98047 Saponara",
    "sg:city":"Saponara",
    "sg:classifiers":[
        {
            "category":"Personal",
            "subcategory":"Shoe Repair & Shine",
            "type":"Services"
        }
    ],
    "sg:phone":"+39 39090337534",
    "sg:postcode":"98047",
    "sg:province":"Messina",
    "sg:tags":[
        "leather"
    ],
    "sg:website":"http://www.leartipelletterie.com",
    "wof:name":"Le Arti Srl",
    "wof:placetype":"venue"
},
  "geometry": {"coordinates":[15.432614,38.19529],"type":"Point"}
}