{
  "type": "Feature",
  "properties": {
    "iso:country":"IT",
    "sg:address":"Zona Industriale 73044 Galatone",
    "sg:city":"Galatone",
    "sg:classifiers":[
        {
            "category":"Real Estate",
            "subcategory":"Surveying",
            "type":"Services"
        }
    ],
    "sg:phone":"+39 0833 832300",
    "sg:postcode":"73044",
    "sg:province":"Lecce",
    "sg:tags":[
        "equipment",
        "material",
        "good",
        "-",
        "handling"
    ],
    "wof:name":"Falco Srl",
    "wof:placetype":"venue"
},
  "geometry": {"coordinates":[18.174015,40.353291],"type":"Point"}
}