{
  "type": "Feature",
  "properties": {
    "addr:full":"Via Nuova Delle Brecce 324 80147 Napoli Napoli Napoli 80147",
    "addr:housenumber":"324",
    "addr:postcode":"80147;80147",
    "addr:street":"Via Nuova Delle Brecce",
    "iso:country":"IT",
    "sg:address":"Via Nuova Delle Brecce 324 80147 Napoli",
    "sg:city":"Napoli",
    "sg:classifiers":[
        {
            "category":"Home & Garden",
            "subcategory":"Garden Supply",
            "type":"Retail Goods"
        }
    ],
    "sg:phone":"+39 081 752 3222",
    "sg:postcode":"80147",
    "sg:province":"Napoli",
    "sg:tags":[
        "plant",
        "power"
    ],
    "sg:website":"www.concavi.it",
    "wof:name":"Com.cavi Spa",
    "wof:placetype":"venue"
},
  "geometry": {"coordinates":[14.3110103607,40.8542366028],"type":"Point"}
}