{
  "type": "Feature",
  "properties": {
    "addr:full":"37057 San Giovanni Lupatoto San Giovanni Lupatoto Verona 37057",
    "addr:housenumber":"37057",
    "addr:postcode":"37057",
    "addr:street":"San;Verona",
    "iso:country":"IT",
    "sg:address":"37057 San Giovanni Lupatoto",
    "sg:city":"San Giovanni Lupatoto",
    "sg:orig_category":"Macchine, Impianti E Forniture Per Industria Grafica, Cartaria E Cartotecnica",
    "sg:phone":"+39 045 545674",
    "sg:postcode":"37057",
    "sg:province":"Verona",
    "wof:name":"Airaghi (s.r.l.)",
    "wof:placetype":"venue"
},
  "geometry": {"coordinates":[11.027088,45.395805],"type":"Point"}
}