{
  "type": "Feature",
  "properties": {
    "iso:country":"IT",
    "sg:address":"19, Via Borgo Aragno 12084 Mondovi'",
    "sg:classifiers":[
        {
            "category":"Shopping",
            "subcategory":"Clothing, Apparel, & Fashions",
            "type":"Retail Goods"
        }
    ],
    "sg:phone":"+39 0174 551666",
    "sg:postcode":"12084",
    "sg:province":"Cuneo",
    "sg:tags":[
        "clothes"
    ],
    "wof:name":"Linea Donna (s.r.l.)",
    "wof:placetype":"venue"
},
  "geometry": {"coordinates":[7.814023,44.401913],"type":"Point"}
}