{
  "type": "Feature",
  "properties": {
    "addr:full":"38039 Vigo Di Fassa Vigo di Fassa Trento 38039",
    "addr:postcode":"38039;38039",
    "iso:country":"IT",
    "sg:address":"38039 Vigo Di Fassa",
    "sg:city":"Vigo di Fassa",
    "sg:orig_category":"Pubblica Amministrazione",
    "sg:phone":"+39 0462 760240",
    "sg:postcode":"38039",
    "sg:province":"Trento",
    "wof:name":"Comprensorio Ladino Di Fassa - C 11 -",
    "wof:placetype":"venue"
},
  "geometry": {"coordinates":[11.6778278351,46.422454834],"type":"Point"}
}