{
  "type": "Feature",
  "properties": {
    "addr:full":"Via Saul Banfi 1 21047 Saronno Saronno Varese 21047",
    "addr:housenumber":"1",
    "addr:postcode":"21047;21047",
    "addr:street":"Via Saul Banfi",
    "iso:country":"IT",
    "sg:address":"Via Saul Banfi 1 21047 Saronno",
    "sg:city":"Saronno",
    "sg:classifiers":[
        {
            "category":"Communications",
            "subcategory":"Television Station",
            "type":"Services"
        }
    ],
    "sg:phone":"+39 02 961751",
    "sg:postcode":"21047",
    "sg:province":"Varese",
    "sg:tags":[
        "monitor"
    ],
    "sg:website":"www.fimi.philips.com",
    "wof:name":"Fimi Srl",
    "wof:placetype":"venue"
},
  "geometry": {"coordinates":[8.8263845444,45.8176040649],"type":"Point"}
}