{
  "type": "Feature",
  "properties": {
    "iso:country":"IT",
    "sg:address":"20093 Cologno Monzese",
    "sg:city":"Cologno Monzese",
    "sg:orig_category":"Bevande, Vini E Liquori",
    "sg:phone":"+39 02 253 2288",
    "sg:postcode":"20093",
    "sg:province":"Milano",
    "wof:name":"Smaldone Francesco",
    "wof:placetype":"venue"
},
  "geometry": {"coordinates":[9.285564,45.53754],"type":"Point"}
}