{
  "type": "Feature",
  "properties": {
    "iso:country":"IT",
    "sg:address":"80028 Grumo Nevano",
    "sg:city":"Grumo Nevano",
    "sg:orig_category":"Macchine, Impianti Ed Attrezzature Per Abbigliamento E Pelletterie",
    "sg:phone":"+39 081 505 4738",
    "sg:postcode":"80028",
    "sg:province":"Napoli",
    "wof:name":"A.t.c. Srl",
    "wof:placetype":"venue"
},
  "geometry": {"coordinates":[14.259658,40.932735],"type":"Point"}
}