{
  "type": "Feature",
  "properties": {
    "iso:country":"IT",
    "sg:address":"10127 Torino",
    "sg:city":"Torino",
    "sg:orig_category":"Studi E Consulenze Tecniche E Industriali. Consulenze Tecniche, Amministrative E Perizie. Servizi Ausiliari Di Analisi, Controllo E Ricerca",
    "sg:phone":"+39 011 663 6285",
    "sg:postcode":"10127",
    "sg:province":"Torino",
    "sg:website":"http://www.essecicar.com",
    "wof:name":"Esseci Car Design Srl",
    "wof:placetype":"venue"
},
  "geometry": {"coordinates":[7.654738,45.021843],"type":"Point"}
}