{
  "type": "Feature",
  "properties": {
    "iso:country":"IT",
    "sg:address":"27, Via Copernico Nicolo' 41015 Nonantola",
    "sg:city":"Nonantola",
    "sg:classifiers":[
        {
            "category":"Manufacturing",
            "subcategory":"Metals",
            "type":"Manufacturing & Wholesale Goods"
        }
    ],
    "sg:phone":"+39 39059549740",
    "sg:postcode":"41015",
    "sg:province":"Modena",
    "sg:tags":[
        "metallurgy",
        "metalworking"
    ],
    "wof:name":"Simoni Pressofusioni (s.r.l.)",
    "wof:placetype":"venue"
},
  "geometry": {"coordinates":[11.0123806,44.674533844],"type":"Point"}
}