{
  "type": "Feature",
  "properties": {
    "addr:full":"Via Domodossola 11 28016 Orta San Giulio Orta San Giulio Novara 28016",
    "addr:housenumber":"11",
    "addr:postcode":"28016;28016",
    "addr:street":"Via Domodossola",
    "iso:country":"IT",
    "sg:address":"Via Domodossola 11 28016 Orta San Giulio",
    "sg:city":"Orta San Giulio",
    "sg:classifiers":[
        {
            "category":"Food & Beverages",
            "subcategory":"Groceries & Convenience Stores",
            "type":"Retail Goods"
        }
    ],
    "sg:phone":"+39 0322 911910",
    "sg:postcode":"28016",
    "sg:province":"Novara",
    "sg:tags":[
        "fresh"
    ],
    "wof:name":"La Commerciale San Giulio Negri & C Spa",
    "wof:placetype":"venue"
},
  "geometry": {"coordinates":[8.4192276001,45.7996025085],"type":"Point"}
}