{
  "type": "Feature",
  "properties": {
    "iso:country":"IT",
    "sg:address":"24030 Brembate Di Sopra",
    "sg:city":"Brembate di Sopra",
    "sg:orig_category":"Macchine, Impianti Ed Attrezzature Industria Chimica",
    "sg:phone":"+39 035 621534",
    "sg:postcode":"24030",
    "sg:province":"Bergamo",
    "wof:name":"Carpenteria Metallica Se.i.t. Dei F.lli Tironi Srl",
    "wof:placetype":"venue"
},
  "geometry": {"coordinates":[9.575905,45.708847],"type":"Point"}
}