{
  "type": "Feature",
  "properties": {
    "iso:country":"IT",
    "sg:address":"00144 Roma",
    "sg:city":"Roma",
    "sg:classifiers":[
        {
            "category":"Government",
            "subcategory":"Post Office",
            "type":"Public Place"
        }
    ],
    "sg:phone":"+39 06 520 1369",
    "sg:postcode":"00144",
    "sg:province":"Roma",
    "sg:tags":[
        "activities",
        "commercial",
        "automation",
        "equipment",
        "artisan",
        "machines",
        "furnishing"
    ],
    "wof:name":"Sir",
    "wof:placetype":"venue"
},
  "geometry": {"coordinates":[12.448885,41.817692],"type":"Point"}
}