{
  "type": "Feature",
  "properties": {
    "addr:full":"24022 Nese Nese Bergamo 24022",
    "addr:postcode":"24022;24022",
    "iso:country":"IT",
    "sg:address":"24022 Nese",
    "sg:city":"Nese",
    "sg:orig_category":"Prodotti Chimici Secondari. Materiali Edili",
    "sg:phone":"+39 035 412 3028",
    "sg:postcode":"24022",
    "sg:province":"Bergamo",
    "wof:name":"Imbalcart Fiorano Snc",
    "wof:placetype":"venue"
},
  "geometry": {"coordinates":[9.7158546448,45.7496566772],"type":"Point"}
}