{
  "type": "Feature",
  "properties": {
    "addr:full":"16153 Genova Genova Genova 16153",
    "addr:housenumber":"16153",
    "addr:postcode":"16153",
    "iso:country":"IT",
    "sg:address":"16153 Genova",
    "sg:city":"Genova",
    "sg:orig_category":"Scuole E Servizi Scolastici. Ospedali E Servizi Sanitari",
    "sg:phone":"+39 010 600 1902",
    "sg:postcode":"16153",
    "sg:province":"Genova",
    "wof:name":"Azienda Usl 3 Genovese",
    "wof:placetype":"venue"
},
  "geometry": {"coordinates":[8.852817,44.455761],"type":"Point"}
}