{
  "type": "Feature",
  "properties": {
    "iso:country":"IT",
    "sg:address":"53011 Castellina Chianti",
    "sg:orig_category":"Animali Domestici - Allevamento E Addestramento",
    "sg:phone":"+39 0577 740916",
    "sg:postcode":"53011",
    "sg:province":"Siena",
    "wof:name":"Allevamento Del Chianti Di Pianigiani Stefano",
    "wof:placetype":"venue"
},
  "geometry": {"coordinates":[11.250018,43.489223],"type":"Point"}
}