{
  "type": "Feature",
  "properties": {
    "iso:country":"IT",
    "sg:address":"16010 Savignone",
    "sg:city":"Savignone",
    "sg:orig_category":"Banche E Servizi Finanziari. Acqua, Luce, Gas E Societa' Di Esercizio Pubblico",
    "sg:phone":"+39 010 936616",
    "sg:postcode":"16010",
    "sg:province":"Genova",
    "wof:name":"Esattoria Consorziale Imposte Dirette",
    "wof:placetype":"venue"
},
  "geometry": {"coordinates":[8.97072,44.4147],"type":"Point"}
}