{
  "type": "Feature",
  "properties": {
    "iso:country":"IT",
    "sg:address":"20, Via Riva Carlo 00157 Roma",
    "sg:city":"Roma",
    "sg:classifiers":[
        {
            "category":"Bars & Pubs",
            "subcategory":"Nightclub",
            "type":"Food & Drink"
        }
    ],
    "sg:phone":"+39 39064506265",
    "sg:postcode":"00157",
    "sg:province":"Roma",
    "sg:tags":[
        "cake",
        "bread"
    ],
    "wof:name":"Giolly Pancarre' Srl",
    "wof:placetype":"venue"
},
  "geometry": {"coordinates":[12.482325,41.895466],"type":"Point"}
}