{
  "type": "Feature",
  "properties": {
    "addr:full":"6, Via Provinciale 13883 Roppolo Roppolo Biella 13883",
    "addr:postcode":"13883;roppolo;13883",
    "addr:street":"Via Provinciale",
    "iso:country":"IT",
    "sg:address":"6, Via Provinciale 13883 Roppolo",
    "sg:city":"Roppolo",
    "sg:classifiers":[
        {
            "category":"Communications",
            "subcategory":"Television Station",
            "type":"Services"
        }
    ],
    "sg:phone":"+39 0161 989511",
    "sg:postcode":"13883",
    "sg:province":"Biella",
    "sg:tags":[
        "audio-visual"
    ],
    "wof:name":"Farp Elettronica S.r.l.",
    "wof:placetype":"venue"
},
  "geometry": {"coordinates":[8.05827,45.562836],"type":"Point"}
}