{
  "type": "Feature",
  "properties": {
    "addr:full":"23864 Malgrate Malgrate Lecco 23864",
    "addr:postcode":"23864;23864",
    "iso:country":"IT",
    "sg:address":"23864 Malgrate",
    "sg:city":"Malgrate",
    "sg:orig_category":"Prodotti Vari In Metallo",
    "sg:phone":"+39 0341 581563",
    "sg:postcode":"23864",
    "sg:province":"Lecco",
    "wof:name":"Anghileri Francesco",
    "wof:placetype":"venue"
},
  "geometry": {"coordinates":[9.3720378876,45.8498535156],"type":"Point"}
}