{
  "type": "Feature",
  "properties": {
    "iso:country":"IT",
    "sg:address":"161, Via Benaco 25081 Bedizzole",
    "sg:city":"Bedizzole",
    "sg:classifiers":[
        {
            "category":"Manufacturing",
            "subcategory":"Paper Products",
            "type":"Manufacturing & Wholesale Goods"
        }
    ],
    "sg:phone":"+39 030 687 2002",
    "sg:postcode":"25081",
    "sg:province":"Brescia",
    "sg:tags":[
        "cardboard"
    ],
    "wof:name":"Onda 3 (s.r.l.)",
    "wof:placetype":"venue"
},
  "geometry": {"coordinates":[10.4484624863,45.5058822632],"type":"Point"}
}