{
  "type": "Feature",
  "properties": {
    "addr:full":"12062 Lequio Tanaro Cuneo 12062",
    "addr:postcode":"12062;12062",
    "iso:country":"IT",
    "sg:address":"12062 Lequio Tanaro",
    "sg:orig_category":"Professionisti - Studi E Servizi Ed Associazioni Di Interesse Aziendale. Servizi Sociali. Associazioni Ed Organismi Di Interesse Pubblico",
    "sg:phone":"+39 0172 696018",
    "sg:postcode":"12062",
    "sg:province":"Cuneo",
    "wof:name":"Senior Service - Residenza Don Comino",
    "wof:placetype":"venue"
},
  "geometry": {"coordinates":[7.5471105576,44.38879776],"type":"Point"}
}