{
  "type": "Feature",
  "properties": {
    "addr:full":"20056 Grezzago Grezzago Milano 20056",
    "addr:postcode":"20056;20056",
    "iso:country":"IT",
    "sg:address":"20056 Grezzago",
    "sg:city":"Grezzago",
    "sg:orig_category":"Carni, Salumi E Pesci. Zootecnia E Pesca, Allevamento Piccoli Animali",
    "sg:phone":"+39 02 9096 7580",
    "sg:postcode":"20056",
    "sg:province":"Milano",
    "wof:name":"La Macchia Salvatore Massimo",
    "wof:placetype":"venue"
},
  "geometry": {"coordinates":[9.549175,45.606129],"type":"Point"}
}