{
  "type": "Feature",
  "properties": {
    "addr:full":"12400, Via Appia 74100 Taranto Taranto Taranto 74100",
    "addr:housenumber":"12400",
    "addr:postcode":"74100;74100",
    "addr:street":"Via Appia",
    "iso:country":"IT",
    "sg:address":"12400, Via Appia 74100 Taranto",
    "sg:city":"Taranto",
    "sg:classifiers":[
        {
            "category":"Food & Beverages",
            "subcategory":"Groceries & Convenience Stores",
            "type":"Retail Goods"
        }
    ],
    "sg:phone":"+39 099 470 0160",
    "sg:postcode":"74100",
    "sg:province":"Taranto",
    "sg:tags":[
        "product",
        "related"
    ],
    "wof:name":"Euroinvest S.r.l.",
    "wof:placetype":"venue"
},
  "geometry": {"coordinates":[17.1985340118,40.5024986267],"type":"Point"}
}