{
  "type": "Feature",
  "properties": {
    "addr:full":"Via Bogino, 8; Torino; 10123 Torino Torino 10123",
    "addr:housenumber":"8",
    "addr:postcode":"10123;10123",
    "addr:street":"Via Bogino",
    "iso:country":"IT",
    "sg:address":"Via Bogino, 8; Torino; 10123",
    "sg:city":"Torino",
    "sg:classifiers":[
        {
            "category":"Travel",
            "subcategory":"Travel Agent",
            "type":"Entertainment"
        }
    ],
    "sg:phone":"+39 390 118 1850",
    "sg:postcode":"10123",
    "sg:province":"Torino",
    "sg:website":"turismotorino.org",
    "wof:name":"Turismo Torino",
    "wof:placetype":"venue"
},
  "geometry": {"coordinates":[7.687011,45.067711],"type":"Point"}
}