{
  "type": "Feature",
  "properties": {
    "iso:country":"IT",
    "sg:address":"15, Via Portogallo 63015 Monte Urano",
    "sg:city":"Monte Urano",
    "sg:classifiers":[
        {
            "category":"Personal",
            "subcategory":"Shoe Repair & Shine",
            "type":"Services"
        }
    ],
    "sg:phone":"+39 0734 841993",
    "sg:postcode":"63015",
    "sg:province":"Ascoli Piceno",
    "sg:tags":[
        "leather"
    ],
    "wof:name":"Calzaturificio Fiorita S.r.l.",
    "wof:placetype":"venue"
},
  "geometry": {"coordinates":[13.659901,43.187992],"type":"Point"}
}