{
  "type": "Feature",
  "properties": {
    "iso:country":"IT",
    "sg:address":"Via Pola 23 20034 Giussano",
    "sg:city":"Giussano",
    "sg:classifiers":[
        {
            "category":"Government",
            "subcategory":"Court House",
            "type":"Public Place"
        }
    ],
    "sg:phone":"+39 036 231 1316",
    "sg:postcode":"20034",
    "sg:province":"Milano",
    "sg:tags":[
        "residential",
        "intercom"
    ],
    "sg:website":"www.ctaitalia.it",
    "wof:name":"Cta Italia Srl",
    "wof:placetype":"venue"
},
  "geometry": {"coordinates":[9.209275,45.678112],"type":"Point"}
}