{
  "type": "Feature",
  "properties": {
    "addr:full":"27029 Vigevano Vigevano Pavia 27029",
    "addr:postcode":"27029;27029",
    "iso:country":"IT",
    "sg:address":"27029 Vigevano",
    "sg:city":"Vigevano",
    "sg:orig_category":"Servizi Di Magazzinaggio E Movimentazione. Servizi Ausiliari Di Sorveglianza, Manutenzione E Pulizia. Servizi Per Aziende, Manifestazioni E Supporto Agli Scambi Commerciali",
    "sg:phone":"+39 0381 325000",
    "sg:postcode":"27029",
    "sg:province":"Pavia",
    "wof:name":"Cooperativa Sociale Oikos",
    "wof:placetype":"venue"
},
  "geometry": {"coordinates":[8.847061,45.311398],"type":"Point"}
}