{
  "type": "Feature",
  "properties": {
    "iso:country":"IT",
    "sg:address":"00124 Roma",
    "sg:city":"Roma",
    "sg:orig_category":"Zootecnia E Pesca, Allevamento Piccoli Animali. Animali Domestici",
    "sg:phone":"+39 06 521 4522",
    "sg:postcode":"00124",
    "sg:province":"Roma",
    "sg:website":"http://www.masterdog.it/villaandreina",
    "wof:name":"Villa Andreina",
    "wof:placetype":"venue"
},
  "geometry": {"coordinates":[12.335577,41.770657],"type":"Point"}
}