{
  "type": "Feature",
  "properties": {
    "addr:full":"41, Via Copernico 41043 Formigine Formigine Modena 41043",
    "addr:postcode":"41043;41043",
    "addr:street":"Via Copernico",
    "iso:country":"IT",
    "sg:address":"41, Via Copernico 41043 Formigine",
    "sg:city":"Formigine",
    "sg:classifiers":[
        {
            "category":"Autos & Motor Vehicles",
            "subcategory":"Automobile Sales",
            "type":"Retail Goods"
        }
    ],
    "sg:phone":"+39 39059573363",
    "sg:postcode":"41043",
    "sg:province":"Modena",
    "sg:tags":[
        "motor-cars"
    ],
    "wof:name":"Sitcar (s.p.a.)",
    "wof:placetype":"venue"
},
  "geometry": {"coordinates":[10.8491544724,44.5884399414],"type":"Point"}
}