{
  "type": "Feature",
  "properties": {
    "iso:country":"IT",
    "sg:address":"20090 Segrate",
    "sg:city":"Segrate",
    "sg:orig_category":"Materiali Semilavorati Metallici",
    "sg:phone":"+39 02 213 9867",
    "sg:postcode":"20090",
    "sg:province":"Milano",
    "wof:name":"N.e.f.f.a.s. Srl",
    "wof:placetype":"venue"
},
  "geometry": {"coordinates":[9.281686,45.493496],"type":"Point"}
}