{
  "type": "Feature",
  "properties": {
    "iso:country":"IT",
    "sg:address":"Via Nazionale 18 33010 Magnano In Riviera",
    "sg:city":"Magnano in Riviera",
    "sg:classifiers":[
        {
            "category":"Building & Trades",
            "subcategory":"Construction",
            "type":"Services"
        }
    ],
    "sg:phone":"+39 0432 785262",
    "sg:postcode":"33010",
    "sg:province":"Udine",
    "sg:tags":[
        "work",
        "public"
    ],
    "wof:name":"Holz Haus Di Franceschinis Clara & C. (s.n.c.)",
    "wof:placetype":"venue"
},
  "geometry": {"coordinates":[13.169717,46.229504],"type":"Point"}
}