{
  "type": "Feature",
  "properties": {
    "iso:country":"IT",
    "sg:address":"10024 Moncalieri",
    "sg:city":"Moncalieri",
    "sg:orig_category":"Studi E Consulenze Amministrative, Commerciali E Aziendali. Banche E Servizi Finanziari. Agenzie D'affari E Servizi Commerciali. Consulenze Tecniche, Amministrative E Perizie",
    "sg:phone":"+39 011 640 8142",
    "sg:postcode":"10024",
    "sg:province":"Torino",
    "wof:name":"Asc Servizi Commerciali Srl",
    "wof:placetype":"venue"
},
  "geometry": {"coordinates":[7.68381,45.001053],"type":"Point"}
}