{
  "type": "Feature",
  "properties": {
    "addr:full":"00054 Fiumicino Fiumicino Roma 00054",
    "addr:postcode":"00054;roma 00054",
    "iso:country":"IT",
    "sg:address":"00054 Fiumicino",
    "sg:city":"Fiumicino",
    "sg:orig_category":"Servizi Per Lo Sport E Il Tempo Libero. Alberghi E Strutture Extra Alberghiere",
    "sg:phone":"+39 06 667 2047",
    "sg:postcode":"00054",
    "sg:province":"Roma",
    "wof:name":"Stabilimento Balneare Marina Piccola",
    "wof:placetype":"venue"
},
  "geometry": {"coordinates":[12.200747,41.911003],"type":"Point"}
}