{
  "type": "Feature",
  "properties": {
    "addr:full":"00155 Roma Roma Roma 00155",
    "addr:postcode":"00155;00155",
    "iso:country":"IT",
    "sg:address":"00155 Roma",
    "sg:city":"Roma",
    "sg:orig_category":"Coperture Edili E Tetti",
    "sg:phone":"+39 06 229 4404",
    "sg:postcode":"00155",
    "sg:province":"Roma",
    "wof:name":"C.i.s.e.d. Srl",
    "wof:placetype":"venue"
},
  "geometry": {"coordinates":[12.603024,41.901905],"type":"Point"}
}