{
  "type": "Feature",
  "properties": {
    "addr:full":"10, Corso Genova 27029 Vigevano Vigevano Pavia 27029",
    "addr:postcode":"27029;27029",
    "addr:street":"Corso Genova",
    "iso:country":"IT",
    "sg:address":"10, Corso Genova 27029 Vigevano",
    "sg:city":"Vigevano",
    "sg:classifiers":[
        {
            "category":"Personal",
            "subcategory":"Shoe Repair & Shine",
            "type":"Services"
        }
    ],
    "sg:phone":"+39 39038170734",
    "sg:postcode":"27029",
    "sg:province":"Pavia",
    "sg:tags":[
        "leather"
    ],
    "wof:name":"Guardolificio Universale (s.r.l.)",
    "wof:placetype":"venue"
},
  "geometry": {"coordinates":[8.852715,45.313351],"type":"Point"}
}