{
  "type": "Feature",
  "properties": {
    "addr:full":"Piazza Roma, 5/11; Oristano; 09170 Oristano Oristano 09170",
    "addr:housenumber":"5 / 11",
    "addr:postcode":"09170;09170",
    "addr:street":"Piazza Roma",
    "iso:country":"IT",
    "sg:address":"Piazza Roma, 5/11; Oristano; 09170",
    "sg:city":"Oristano",
    "sg:classifiers":[
        {
            "category":"Banks & Credit Unions",
            "subcategory":"Bank",
            "type":"Services"
        }
    ],
    "sg:phone":"+39 0783 74281",
    "sg:postcode":"09170",
    "sg:province":"Oristano",
    "wof:name":"Banca Nazionale Del Lavoro Spa",
    "wof:placetype":"venue"
},
  "geometry": {"coordinates":[8.591431,39.906036],"type":"Point"}
}