{
  "type": "Feature",
  "properties": {
    "addr:full":"40012 Calderara Di Reno Calderara di Reno Bologna 40012",
    "addr:postcode":"40012;40012",
    "iso:country":"IT",
    "sg:address":"40012 Calderara Di Reno",
    "sg:city":"Calderara di Reno",
    "sg:orig_category":"Biciclette - Accessori E Parti",
    "sg:phone":"+39 051 727701",
    "sg:postcode":"40012",
    "sg:province":"Bologna",
    "wof:name":"Amici Centro Ciclistico Srl",
    "wof:placetype":"venue"
},
  "geometry": {"coordinates":[11.269792,44.539646],"type":"Point"}
}