{
  "type": "Feature",
  "properties": {
    "iso:country":"IT",
    "sg:address":"60127 Ancona",
    "sg:city":"Ancona",
    "sg:orig_category":"Termotecnica E Riscaldamento, Apparecchiature E Servizi",
    "sg:phone":"+39 071 280 2551",
    "sg:postcode":"60127",
    "sg:province":"Ancona",
    "wof:name":"S.p.i.l.t. Srl",
    "wof:placetype":"venue"
},
  "geometry": {"coordinates":[13.505359,43.595776],"type":"Point"}
}