{
  "type": "Feature",
  "properties": {
    "addr:full":"Via Dell' Artigianato 4 12042 Bra Bra Cuneo 12042",
    "addr:housenumber":"4",
    "addr:postcode":"12042;12042",
    "addr:street":"Via Dell ' Artigianato",
    "iso:country":"IT",
    "sg:address":"Via Dell' Artigianato 4 12042 Bra",
    "sg:city":"Bra",
    "sg:classifiers":[
        {
            "category":"Restaurant",
            "type":"Food & Drink"
        }
    ],
    "sg:phone":"+39 0172 415565",
    "sg:postcode":"12042",
    "sg:province":"Cuneo",
    "sg:tags":[
        "pasta"
    ],
    "wof:name":"Pastificio Artigianale Bordone Daniele & C. S.a.s.",
    "wof:placetype":"venue"
},
  "geometry": {"coordinates":[7.8375959396,44.6879119873],"type":"Point"}
}