{
  "type": "Feature",
  "properties": {
    "addr:full":"4, Via Torino 80024 Cardito Cardito Napoli 80024",
    "addr:postcode":"80024;80024",
    "addr:street":"Via Torino",
    "iso:country":"IT",
    "sg:address":"4, Via Torino 80024 Cardito",
    "sg:city":"Cardito",
    "sg:classifiers":[
        {
            "category":"Shopping",
            "subcategory":"Computers & Home Electronics",
            "type":"Retail Goods"
        }
    ],
    "sg:phone":"+39 081 835 3809",
    "sg:postcode":"80024",
    "sg:province":"Napoli",
    "sg:tags":[
        "electronic",
        "electrical",
        "equipment"
    ],
    "wof:name":"Simec Sistemi Srl",
    "wof:placetype":"venue"
},
  "geometry": {"coordinates":[14.308354,40.916805],"type":"Point"}
}