{
  "type": "Feature",
  "properties": {
    "addr:full":"Via Vittorio Emanuele; Pieve Vergonte; 28020",
    "addr:postcode":"28020",
    "addr:street":"Via Vittorio Emanuele Pieve",
    "iso:country":"IT",
    "sg:address":"Via Vittorio Emanuele; Pieve Vergonte; 28020",
    "sg:classifiers":[
        {
            "category":"Banks & Credit Unions",
            "subcategory":"Bank",
            "type":"Services"
        }
    ],
    "sg:phone":"+39 0324 86140",
    "wof:name":"Banca Popolare Di Intra",
    "wof:placetype":"venue"
},
  "geometry": {"coordinates":[8.268683,46.007053],"type":"Point"}
}