{
  "type": "Feature",
  "properties": {
    "iso:country":"IT",
    "sg:address":"17031 Albenga",
    "sg:city":"Albenga",
    "sg:orig_category":"Dischi, Musicassette E Compact Disc - Vendita Al Dettaglio",
    "sg:phone":"+39 0182 50392",
    "sg:postcode":"17031",
    "sg:province":"Savona",
    "wof:name":"B.m. Di Zunino Anna Maria Sas",
    "wof:placetype":"venue"
},
  "geometry": {"coordinates":[8.188495,44.058578],"type":"Point"}
}