{
  "type": "Feature",
  "properties": {
    "iso:country":"IT",
    "sg:address":"10078 Venaria",
    "sg:orig_category":"Antivibranti",
    "sg:phone":"+39 011 455 3408",
    "sg:postcode":"10078",
    "sg:province":"Torino",
    "wof:name":"Sicat Snc",
    "wof:placetype":"venue"
},
  "geometry": {"coordinates":[7.648118,45.113834],"type":"Point"}
}