{
  "type": "Feature",
  "properties": {
    "iso:country":"IT",
    "sg:address":"4376, Via Elpidiense 63019 Sant'elpidio A Mare",
    "sg:classifiers":[
        {
            "category":"Personal",
            "subcategory":"Shoe Repair & Shine",
            "type":"Services"
        }
    ],
    "sg:phone":"+39 0734 909672",
    "sg:postcode":"63019",
    "sg:province":"Ascoli Piceno",
    "sg:tags":[
        "leather"
    ],
    "wof:name":"Monaldi Carla",
    "wof:placetype":"venue"
},
  "geometry": {"coordinates":[13.696618,43.223923],"type":"Point"}
}