{
  "type": "Feature",
  "properties": {
    "addr:full":"47838 Riccione Riccione Rimini 47838",
    "addr:postcode":"47838;47838",
    "iso:country":"IT",
    "sg:address":"47838 Riccione",
    "sg:city":"Riccione",
    "sg:orig_category":"Metalli E Leghe",
    "sg:phone":"+39 0541 607321",
    "sg:postcode":"47838",
    "sg:province":"Rimini",
    "wof:name":"Greenmac Srl",
    "wof:placetype":"venue"
},
  "geometry": {"coordinates":[12.6503295898,44.0014877319],"type":"Point"}
}