{
  "type": "Feature",
  "properties": {
    "addr:full":"Via Montalbano 3/b 51030 Serravalle Pistoiese Serravalle Pistoiese Pistoia 51030",
    "addr:housenumber":"3 / b",
    "addr:postcode":"51030;51030",
    "addr:street":"Via Montalbano",
    "iso:country":"IT",
    "sg:address":"Via Montalbano 3/b 51030 Serravalle Pistoiese",
    "sg:city":"Serravalle Pistoiese",
    "sg:orig_category":"Hoisiery Goods",
    "sg:phone":"+39 0573 929144",
    "sg:postcode":"51030",
    "sg:province":"Pistoia",
    "wof:name":"Manifatture Tessili Riunite Srl",
    "wof:placetype":"venue"
},
  "geometry": {"coordinates":[10.91798,43.907955],"type":"Point"}
}