{
  "type": "Feature",
  "properties": {
    "iso:country":"IT",
    "sg:address":"95, Via Di Nanni Dante 10141 Torino",
    "sg:city":"Torino",
    "sg:classifiers":[
        {
            "category":"Shopping",
            "subcategory":"Clothing, Apparel, & Fashions",
            "type":"Retail Goods"
        }
    ],
    "sg:phone":"+39 39011331993",
    "sg:postcode":"10141",
    "sg:province":"Torino",
    "sg:tags":[
        "clothes"
    ],
    "wof:name":"Vestidello Di Vestidello Antonio & C. (s.n.c.)",
    "wof:placetype":"venue"
},
  "geometry": {"coordinates":[7.567663,45.063061],"type":"Point"}
}