{
  "type": "Feature",
  "properties": {
    "iso:country":"IT",
    "sg:address":"Via Roma 28885 Piedimulera",
    "sg:city":"Piedimulera",
    "sg:classifiers":[
        {
            "category":"Professional",
            "subcategory":"Engineering",
            "type":"Services"
        }
    ],
    "sg:phone":"+39 0324 842502",
    "sg:postcode":"28885",
    "sg:province":"Verbano-Cusio-Ossola",
    "sg:tags":[
        "machine",
        "-",
        "mechanical"
    ],
    "wof:name":"Erreemme S.r.l.",
    "wof:placetype":"venue"
},
  "geometry": {"coordinates":[8.272465,46.139969],"type":"Point"}
}