{
  "type": "Feature",
  "properties": {
    "iso:country":"IT",
    "sg:address":"48015 Cervia",
    "sg:city":"Cervia",
    "sg:orig_category":"Servizi Per Lo Sport E Il Tempo Libero. Alberghi E Strutture Extra Alberghiere",
    "sg:phone":"+39 0544 973014",
    "sg:postcode":"48015",
    "sg:province":"Ravenna",
    "wof:name":"Bagno Emilio",
    "wof:placetype":"venue"
},
  "geometry": {"coordinates":[12.323482,44.238918],"type":"Point"}
}