{
  "type": "Feature",
  "properties": {
    "iso:country":"IT",
    "sg:address":"36075 Montecchio Maggiore",
    "sg:city":"Montecchio Maggiore",
    "sg:classifiers":[
        {
            "category":"Wholesale",
            "subcategory":"Hardware",
            "type":"Manufacturing & Wholesale Goods"
        }
    ],
    "sg:phone":"+39 0444 695811",
    "sg:postcode":"36075",
    "sg:province":"Vicenza",
    "sg:tags":[
        "activities",
        "industrial",
        "supply",
        "valve",
        "equipment",
        "measurement"
    ],
    "sg:website":"http://www.mondeovalves.com",
    "wof:name":"Mondeo Srl",
    "wof:placetype":"venue"
},
  "geometry": {"coordinates":[11.448024,45.526798],"type":"Point"}
}