{
  "type": "Feature",
  "properties": {
    "addr:full":"48012 Bagnacavallo Bagnacavallo Ravenna 48012",
    "addr:postcode":"48012;48012",
    "iso:country":"IT",
    "sg:address":"48012 Bagnacavallo",
    "sg:city":"Bagnacavallo",
    "sg:orig_category":"Zootecnia E Pesca, Allevamento Piccoli Animali. Animali Domestici",
    "sg:phone":"+39 0545 40385",
    "sg:postcode":"48012",
    "sg:province":"Ravenna",
    "wof:name":"Allevamento Della Pioppa Di Marangoni Primo",
    "wof:placetype":"venue"
},
  "geometry": {"coordinates":[12.036406,44.477669],"type":"Point"}
}