{
  "type": "Feature",
  "properties": {
    "iso:country":"IT",
    "sg:address":"29, Ctr. Selvole 46042 Castel Goffredo",
    "sg:city":"Castel Goffredo",
    "sg:classifiers":[
        {
            "category":"Communications",
            "subcategory":"Television Station",
            "type":"Services"
        }
    ],
    "sg:phone":"+39 0376 781094",
    "sg:postcode":"46042",
    "sg:province":"Mantova",
    "sg:tags":[
        "equipment",
        "optical",
        "instrument"
    ],
    "sg:website":"http://www.amlux.it",
    "wof:name":"Amlux Srl",
    "wof:placetype":"venue"
},
  "geometry": {"coordinates":[10.797698,45.160366],"type":"Point"}
}