{
  "type": "Feature",
  "properties": {
    "iso:country":"IT",
    "sg:address":"Via Volturno 119/a 41032 Cavezzo",
    "sg:city":"Cavezzo",
    "sg:classifiers":[
        {
            "category":"Manufacturing",
            "subcategory":"Building Materials",
            "type":"Manufacturing & Wholesale Goods"
        }
    ],
    "sg:phone":"+39 0535 46577",
    "sg:postcode":"41032",
    "sg:province":"Modena",
    "sg:tags":[
        "filter",
        "dust",
        "separation",
        "air"
    ],
    "sg:website":"www.mixsrl.it",
    "wof:name":"Mix Srl",
    "wof:placetype":"venue"
},
  "geometry": {"coordinates":[10.92522,44.647079],"type":"Point"}
}