{
  "type": "Feature",
  "properties": {
    "iso:country":"IT",
    "sg:address":"Via Galileo 8 10070 Mappano",
    "sg:classifiers":[
        {
            "category":"Shopping",
            "subcategory":"Stationery & Office Supplies",
            "type":"Retail Goods"
        }
    ],
    "sg:phone":"+39 011 222 2275",
    "sg:postcode":"10070",
    "sg:province":"Torino",
    "sg:tags":[
        "pen",
        "ball",
        "ink",
        "point"
    ],
    "sg:website":"www.dobell.it",
    "wof:name":"Dobell Spa",
    "wof:placetype":"venue"
},
  "geometry": {"coordinates":[7.704031,45.139641],"type":"Point"}
}