{
  "type": "Feature",
  "properties": {
    "addr:full":"Via Giardino 3, 83035 Grottaminarda, Av Grottaminarda Avellino 83035",
    "addr:housenumber":"3",
    "addr:postcode":"83035;83035",
    "addr:street":"Via Giardino;Av",
    "iso:country":"IT",
    "sg:address":"Via Giardino 3, 83035 Grottaminarda, Av",
    "sg:city":"Grottaminarda",
    "sg:classifiers":[
        {
            "category":"Banks & Credit Unions",
            "subcategory":"Bank",
            "type":"Services"
        }
    ],
    "sg:postcode":"83035",
    "sg:province":"Avellino",
    "wof:name":"Banca Popolare Meridionale",
    "wof:placetype":"venue"
},
  "geometry": {"coordinates":[15.032551,41.074383],"type":"Point"}
}