{
  "type": "Feature",
  "properties": {
    "iso:country":"IT",
    "sg:address":"00141 Roma",
    "sg:city":"Roma",
    "sg:orig_category":"Servizi E Lavori Per Agricoltura E Zootecnia. Servizi Ausiliari Di Analisi, Controllo E Ricerca",
    "sg:phone":"+39 06 8864 0081",
    "sg:postcode":"00141",
    "sg:province":"Roma",
    "wof:name":"Panta S.r.l.",
    "wof:placetype":"venue"
},
  "geometry": {"coordinates":[12.524306,41.941875],"type":"Point"}
}