{
  "type": "Feature",
  "properties": {
    "addr:full":"80121 Napoli Napoli Napoli 80121",
    "addr:housenumber":"80121",
    "addr:postcode":"80121",
    "iso:country":"IT",
    "sg:address":"80121 Napoli",
    "sg:city":"Napoli",
    "sg:classifiers":[
        {
            "category":"Health Services",
            "subcategory":"Health Practitioner",
            "type":"Services"
        }
    ],
    "sg:phone":"+39 081 417345",
    "sg:postcode":"80121",
    "sg:province":"Napoli",
    "sg:tags":[
        "medici"
    ],
    "wof:name":"D'antonio Mario",
    "wof:placetype":"venue"
},
  "geometry": {"coordinates":[14.243191,40.835773],"type":"Point"}
}