{
  "type": "Feature",
  "properties": {
    "addr:full":"10153 Torino Torino Torino 10153",
    "addr:postcode":"10153;10153",
    "iso:country":"IT",
    "sg:address":"10153 Torino",
    "sg:city":"Torino",
    "sg:classifiers":[
        {
            "category":"Health Services",
            "subcategory":"Health Practitioner",
            "type":"Services"
        }
    ],
    "sg:phone":"+39 011 836655",
    "sg:postcode":"10153",
    "sg:province":"Torino",
    "sg:tags":[
        "medici"
    ],
    "wof:name":"Orlandi Fabio",
    "wof:placetype":"venue"
},
  "geometry": {"coordinates":[7.7077217102,45.0700950623],"type":"Point"}
}