{
  "type": "Feature",
  "properties": {
    "iso:country":"IT",
    "sg:address":"35020 Albignasego",
    "sg:city":"Albignasego",
    "sg:orig_category":"Impiantistica E Prodotti Tecnologici Per Edilizia. Elettrotecnica Industriale, Prodotti E Apparecchiature",
    "sg:phone":"+39 049 862 5400",
    "sg:postcode":"35020",
    "sg:province":"Padova",
    "sg:website":"http://www.bestlight.com",
    "wof:name":"Bestlight Snc",
    "wof:placetype":"venue"
},
  "geometry": {"coordinates":[11.831878,45.343536],"type":"Point"}
}