{
  "type": "Feature",
  "properties": {
    "iso:country":"IT",
    "sg:address":"70123 Bari",
    "sg:city":"Bari",
    "sg:orig_category":"Servizi E Lavori Per Industria Alimentare E Bevande",
    "sg:phone":"+39 080 527 8563",
    "sg:postcode":"70123",
    "sg:province":"Bari",
    "wof:name":"Calabrese Giovanni",
    "wof:placetype":"venue"
},
  "geometry": {"coordinates":[16.847757,41.128742],"type":"Point"}
}