{
  "type": "Feature",
  "properties": {
    "iso:country":"IT",
    "sg:address":"00015 Monterotondo",
    "sg:city":"Monterotondo",
    "sg:orig_category":"Legno E Semilavorati",
    "sg:phone":"+39 06 900 4941",
    "sg:postcode":"00015",
    "sg:province":"Roma",
    "wof:name":"Persia Legnami Di Persia Gabriele",
    "wof:placetype":"venue"
},
  "geometry": {"coordinates":[12.606717,42.079819],"type":"Point"}
}