{
  "type": "Feature",
  "properties": {
    "iso:country":"IT",
    "sg:address":"50032 Borgo San Lorenzo",
    "sg:city":"Borgo San Lorenzo",
    "sg:orig_category":"Servizi Di Magazzinaggio E Movimentazione",
    "sg:phone":"+39 055 845 9403",
    "sg:postcode":"50032",
    "sg:province":"Firenze",
    "wof:name":"Ferrero M. Di A. Lisi & Figli S.r.l.",
    "wof:placetype":"venue"
},
  "geometry": {"coordinates":[11.370298,43.95739],"type":"Point"}
}