{
  "type": "Feature",
  "properties": {
    "addr:full":"20149 Milano Milano Milano 20149",
    "addr:postcode":"20149;20149",
    "iso:country":"IT",
    "sg:address":"20149 Milano",
    "sg:city":"Milano",
    "sg:orig_category":"Abbigliamento Esterno, Maglierie E Pelliccerie. Forniture Per Abbigliamento E Pelletterie",
    "sg:phone":"+39 02 313590",
    "sg:postcode":"20149",
    "sg:province":"Milano",
    "wof:name":"Il Triciclo Di Cereghini Anna Francesca",
    "wof:placetype":"venue"
},
  "geometry": {"coordinates":[9.153866,45.486023],"type":"Point"}
}