{
  "type": "Feature",
  "properties": {
    "addr:full":"40057 Granarolo Emilia Bologna 40057",
    "addr:postcode":"40057;40057",
    "addr:street":"Emilia Bologna",
    "iso:country":"IT",
    "sg:address":"40057 Granarolo Emilia",
    "sg:orig_category":"Serramenti Ed Infissi",
    "sg:phone":"+39 051 767358",
    "sg:postcode":"40057",
    "sg:province":"Bologna",
    "wof:name":"Arvieri Stefano",
    "wof:placetype":"venue"
},
  "geometry": {"coordinates":[11.417401,44.53389],"type":"Point"}
}