{
  "type": "Feature",
  "properties": {
    "iso:country":"IT",
    "sg:address":"20127 Milano",
    "sg:city":"Milano",
    "sg:orig_category":"Telecomunicazioni E Telefonia, Impianti, Apparecchi E Servizi. Acqua, Luce, Gas E Societa' Di Esercizio Pubblico. Servizi Vari Di Interesse Pubblico",
    "sg:phone":"+39 02 2614 9318",
    "sg:postcode":"20127",
    "sg:province":"Milano",
    "wof:name":"Vasquez Villar Carlos Henry",
    "wof:placetype":"venue"
},
  "geometry": {"coordinates":[9.221626,45.501003],"type":"Point"}
}