{
  "type": "Feature",
  "properties": {
    "iso:country":"IT",
    "sg:address":"160, Via Cossa Pietro 10146 Torino",
    "sg:city":"Torino",
    "sg:classifiers":[
        {
            "category":"Utilities",
            "subcategory":"Telephone",
            "type":"Services"
        }
    ],
    "sg:phone":"+39 39011724729",
    "sg:postcode":"10146",
    "sg:province":"Torino",
    "sg:tags":[
        "telecommunication"
    ],
    "wof:name":"Neon Bergui S.r.l.",
    "wof:placetype":"venue"
},
  "geometry": {"coordinates":[7.62608,45.086502],"type":"Point"}
}