{
  "type": "Feature",
  "properties": {
    "iso:country":"IT",
    "sg:address":"20081 Abbiategrasso",
    "sg:city":"Abbiategrasso",
    "sg:orig_category":"Cartotecnica E Servizi. Forniture Per Uffici",
    "sg:phone":"+39 02 946 2919",
    "sg:postcode":"20081",
    "sg:province":"Milano",
    "wof:name":"Cor.alb. Di Garavaglia Teresio",
    "wof:placetype":"venue"
},
  "geometry": {"coordinates":[8.908846,45.391895],"type":"Point"}
}