{
  "type": "Feature",
  "properties": {
    "addr:full":"2, Via Bainsizza 25128 Brescia Brescia Brescia 25128",
    "addr:postcode":"25128;25128",
    "addr:street":"Via Bainsizza",
    "iso:country":"IT",
    "sg:address":"2, Via Bainsizza 25128 Brescia",
    "sg:city":"Brescia",
    "sg:classifiers":[
        {
            "category":"Communications",
            "subcategory":"Television Station",
            "type":"Services"
        }
    ],
    "sg:phone":"+39 39030380572",
    "sg:postcode":"25128",
    "sg:province":"Brescia",
    "sg:tags":[
        "equipment",
        "optical",
        "instrument"
    ],
    "wof:name":"Photo G 2 (s.r.l.)",
    "wof:placetype":"venue"
},
  "geometry": {"coordinates":[10.212846,45.557011],"type":"Point"}
}