{
  "type": "Feature",
  "properties": {
    "iso:country":"IT",
    "sg:address":"35010 San Pietro In Gu",
    "sg:city":"San Pietro in Gu",
    "sg:orig_category":"Termotecnica E Riscaldamento, Apparecchiature E Servizi",
    "sg:phone":"+39 049 945 5618",
    "sg:postcode":"35010",
    "sg:province":"Padova",
    "wof:name":"Dest Sistemi S.r.l.",
    "wof:placetype":"venue"
},
  "geometry": {"coordinates":[11.659801,45.590443],"type":"Point"}
}