{
  "type": "Feature",
  "properties": {
    "iso:country":"IT",
    "sg:address":"28, Via Morgagni Gianbattista 37135 Verona",
    "sg:city":"Verona",
    "sg:classifiers":[
        {
            "category":"Professional",
            "subcategory":"Printing & Photocopies",
            "type":"Services"
        }
    ],
    "sg:phone":"+39 045 820 0021",
    "sg:postcode":"37135",
    "sg:province":"Verona",
    "wof:name":"Grafiscan S.r.l.",
    "wof:placetype":"venue"
},
  "geometry": {"coordinates":[10.9658870697,45.4025268555],"type":"Point"}
}