{
  "type": "Feature",
  "properties": {
    "iso:country":"IT",
    "sg:address":"41100 Modena",
    "sg:city":"Modena",
    "sg:orig_category":"Pelletterie - Produzione E Ingrosso",
    "sg:phone":"+39 059 370035",
    "sg:postcode":"41100",
    "sg:province":"Modena",
    "wof:name":"Molinari Bruno Sas",
    "wof:placetype":"venue"
},
  "geometry": {"coordinates":[10.9365940094,44.6419792175],"type":"Point"}
}