{
  "type": "Feature",
  "properties": {
    "addr:full":"00015 Monterotondo Monterotondo Roma 00015",
    "addr:postcode":"00015;roma 00015",
    "iso:country":"IT",
    "sg:address":"00015 Monterotondo",
    "sg:city":"Monterotondo",
    "sg:orig_category":"Abbigliamento Esterno, Maglierie E Pelliccerie. Calzature, Pelletterie E Pelli",
    "sg:phone":"+39 06 906 4189",
    "sg:postcode":"00015",
    "sg:province":"Roma",
    "wof:name":"Tecnica A.v.s. Di Seri Carla E C. Sas",
    "wof:placetype":"venue"
},
  "geometry": {"coordinates":[12.620311,42.048344],"type":"Point"}
}