{
  "type": "Feature",
  "properties": {
    "addr:full":"13, Via Aurelia - Rugginosa 58100 Grosseto Grosseto Grosseto 58100",
    "addr:postcode":"58100;58100",
    "addr:street":"Via Aurelia Rugginosa",
    "iso:country":"IT",
    "sg:address":"13, Via Aurelia - Rugginosa 58100 Grosseto",
    "sg:city":"Grosseto",
    "sg:classifiers":[
        {
            "category":"Food & Beverages",
            "subcategory":"Groceries & Convenience Stores",
            "type":"Retail Goods"
        }
    ],
    "sg:phone":"+39 0564 451093",
    "sg:postcode":"58100",
    "sg:province":"Grosseto",
    "sg:tags":[
        "product",
        "related"
    ],
    "wof:name":"I.c.e.d. (s.p.a.)",
    "wof:placetype":"venue"
},
  "geometry": {"coordinates":[11.1127824783,42.7628593445],"type":"Point"}
}