{
  "type": "Feature",
  "properties": {
    "addr:full":"Via Senigallia 29 61100 Pesaro Pesaro Pesaro E Urbino 61100",
    "addr:housenumber":"29",
    "addr:postcode":"61100;61100",
    "addr:street":"Via Senigallia",
    "iso:country":"IT",
    "sg:address":"Via Senigallia 29 61100 Pesaro",
    "sg:city":"Pesaro",
    "sg:classifiers":[
        {
            "category":"Juice Bar",
            "subcategory":"None",
            "type":"Food & Drink"
        }
    ],
    "sg:phone":"+39 0721 40871",
    "sg:postcode":"61100",
    "sg:province":"Pesaro E Urbino",
    "sg:tags":[
        "liquid",
        "paraffin"
    ],
    "sg:website":"www.foxpetroli.com",
    "wof:name":"Fox Petroli Spa",
    "wof:placetype":"venue"
},
  "geometry": {"coordinates":[12.885578,43.904594],"type":"Point"}
}