{
  "type": "Feature",
  "properties": {
    "iso:country":"IT",
    "sg:address":"13011 Borgosesia",
    "sg:city":"Borgosesia",
    "sg:classifiers":[
        {
            "category":"Home & Garden",
            "subcategory":"Home Furnishings",
            "type":"Retail Goods"
        }
    ],
    "sg:phone":"+39 0163 21998",
    "sg:postcode":"13011",
    "sg:province":"Vercelli",
    "sg:tags":[
        "hardware",
        "plumbing",
        "bathroom",
        "accessories",
        "fitting"
    ],
    "wof:name":"Rubinetterie Beta Srl",
    "wof:placetype":"venue"
},
  "geometry": {"coordinates":[8.2574167252,45.7293128967],"type":"Point"}
}