{
  "type": "Feature",
  "properties": {
    "addr:full":"Via Antoniana 100 35011 Campodarsego Campodarsego Padova 35011",
    "addr:housenumber":"100",
    "addr:postcode":"35011;35011",
    "addr:street":"Via Antoniana",
    "iso:country":"IT",
    "sg:address":"Via Antoniana 100 35011 Campodarsego",
    "sg:city":"Campodarsego",
    "sg:classifiers":[
        {
            "category":"Banks & Credit Unions",
            "subcategory":"Bureau De Change",
            "type":"Services"
        }
    ],
    "sg:phone":"+39 049 920 0990",
    "sg:postcode":"35011",
    "sg:province":"Padova",
    "sg:tags":[
        "stove",
        "gas"
    ],
    "sg:website":"www.ilve.com",
    "wof:name":"I.l.v.e. Spa",
    "wof:placetype":"venue"
},
  "geometry": {"coordinates":[11.907006,45.50288],"type":"Point"}
}