{
  "type": "Feature",
  "properties": {
    "iso:country":"IT",
    "sg:address":"10144 Torino",
    "sg:city":"Torino",
    "sg:orig_category":"Non-classified Establishments",
    "sg:phone":"+39 011 487763",
    "sg:postcode":"10144",
    "sg:province":"Torino",
    "wof:name":"Trinca & Branca Sas",
    "wof:placetype":"venue"
},
  "geometry": {"coordinates":[7.553993,44.999767],"type":"Point"}
}