{
  "type": "Feature",
  "properties": {
    "iso:country":"IT",
    "sg:address":"25030 Roncadelle",
    "sg:city":"Roncadelle",
    "sg:orig_category":"Macchine E Forniture Per Ecologia E Smaltimento Rifiuti. Forniture Per Attivita' Industriali",
    "sg:phone":"+39 030 258 3678",
    "sg:postcode":"25030",
    "sg:province":"Brescia",
    "wof:name":"Jolly Doc Snc",
    "wof:placetype":"venue"
},
  "geometry": {"coordinates":[10.156334,45.511234],"type":"Point"}
}