{
  "type": "Feature",
  "properties": {
    "iso:country":"IT",
    "sg:address":"120, Vl. Africa00144 Roma",
    "sg:city":"Roma",
    "sg:classifiers":[
        {
            "category":"Wholesale",
            "subcategory":"Drugs",
            "type":"Manufacturing & Wholesale Goods"
        }
    ],
    "sg:phone":"+39 39065123946",
    "sg:postcode":"00144",
    "sg:province":"Roma",
    "sg:tags":[
        "chemical",
        "pharmaceutical"
    ],
    "sg:website":"http://www.herbsforhealth.it",
    "wof:name":"Herbs & Health Srl",
    "wof:placetype":"venue"
},
  "geometry": {"coordinates":[12.472614,41.825352],"type":"Point"}
}