{
  "type": "Feature",
  "properties": {
    "addr:full":"71100 Foggia Foggia Foggia 71100",
    "addr:postcode":"71100;71100",
    "iso:country":"IT",
    "sg:address":"71100 Foggia",
    "sg:city":"Foggia",
    "sg:orig_category":"Arredamento Negozi E Supermercati",
    "sg:phone":"+39 0881 665341",
    "sg:postcode":"71100",
    "sg:province":"Foggia",
    "wof:name":"Marredi Sud",
    "wof:placetype":"venue"
},
  "geometry": {"coordinates":[15.55457,41.458286],"type":"Point"}
}