{
  "type": "Feature",
  "properties": {
    "iso:country":"IT",
    "sg:address":"16, Via Variante 84091 Battipaglia",
    "sg:city":"Battipaglia",
    "sg:classifiers":[
        {
            "category":"Real Estate",
            "subcategory":"Architect",
            "type":"Services"
        }
    ],
    "sg:phone":"+39 0828 370131",
    "sg:postcode":"84091",
    "sg:province":"Salerno",
    "sg:tags":[
        "textile",
        "clothing"
    ],
    "wof:name":"Confezione Abbigliamento Europa - S.r.l.",
    "wof:placetype":"venue"
},
  "geometry": {"coordinates":[14.765912,40.677956],"type":"Point"}
}