{
  "type": "Feature",
  "properties": {
    "iso:country":"IT",
    "sg:address":"25050 Rodengo Saiano",
    "sg:orig_category":"Articoli Da Regalo. Tempo Libero - Articoli E Forniture. Regalistica Aziendale",
    "sg:phone":"+39 030 681 0706",
    "sg:postcode":"25050",
    "sg:province":"Brescia",
    "wof:name":"Eurocoppe S.r.l.",
    "wof:placetype":"venue"
},
  "geometry": {"coordinates":[10.117466,45.576298],"type":"Point"}
}