{
  "type": "Feature",
  "properties": {
    "iso:country":"IT",
    "sg:address":"18027 Pontedassio",
    "sg:city":"Pontedassio",
    "sg:orig_category":"Alimentari - Produzione E Ingrosso",
    "sg:phone":"+39 0183 279760",
    "sg:postcode":"18027",
    "sg:province":"Imperia",
    "wof:name":"Frantoio Bianco Snc",
    "wof:placetype":"venue"
},
  "geometry": {"coordinates":[8.045254,43.8895],"type":"Point"}
}