{
  "type": "Feature",
  "properties": {
    "addr:full":"37069 Villafranca Di Verona Villafranca di Verona Verona 37069",
    "addr:postcode":"37069;37069",
    "addr:street":"Verona",
    "iso:country":"IT",
    "sg:address":"37069 Villafranca Di Verona",
    "sg:city":"Villafranca di Verona",
    "sg:orig_category":"Escavatori E Draghe",
    "sg:phone":"+39 045 630 1323",
    "sg:postcode":"37069",
    "sg:province":"Verona",
    "wof:name":"Mai Verona Srl",
    "wof:placetype":"venue"
},
  "geometry": {"coordinates":[10.97745,45.409954],"type":"Point"}
}