{
  "type": "Feature",
  "properties": {
    "addr:full":"06029 Valfabbrica Valfabbrica Perugia 06029",
    "addr:postcode":"06029;06029",
    "iso:country":"IT",
    "sg:address":"06029 Valfabbrica",
    "sg:city":"Valfabbrica",
    "sg:orig_category":"Manufacturers: Prefabbricati",
    "sg:phone":"+39 075 901321",
    "sg:postcode":"06029",
    "sg:province":"Perugia",
    "sg:website":"http://www.profilumbra.it",
    "wof:name":"Profilumbra Spa",
    "wof:placetype":"venue"
},
  "geometry": {"coordinates":[12.680844,42.828106],"type":"Point"}
}