{
  "type": "Feature",
  "properties": {
    "iso:country":"IT",
    "sg:address":"20024 Garbagnate Milanese",
    "sg:city":"Garbagnate Milanese",
    "sg:classifiers":[
        {
            "category":"Health Services",
            "subcategory":"Health Practitioner",
            "type":"Services"
        }
    ],
    "sg:phone":"+39 02 995 3265",
    "sg:postcode":"20024",
    "sg:province":"Milano",
    "sg:tags":[
        "medici"
    ],
    "wof:name":"Fuccilo Michele",
    "wof:placetype":"venue"
},
  "geometry": {"coordinates":[9.080532,45.561466],"type":"Point"}
}