{
  "type": "Feature",
  "properties": {
    "addr:full":"2 Via Pascoli, 47030 Gatteo Forl\u00ec-Cesena 47030",
    "addr:postcode":"47030;47030",
    "addr:street":"Via Pascoli",
    "iso:country":"IT",
    "sg:address":"2 Via Pascoli, 47030 Gatteo",
    "sg:classifiers":[
        {
            "category":"Banks & Credit Unions",
            "subcategory":"Financial Services",
            "type":"Services"
        }
    ],
    "sg:phone":"+39 0541 930161",
    "sg:postcode":"47030",
    "sg:province":"Forl\u00ec-Cesena",
    "sg:tags":[
        "banking",
        "finance",
        "insurance"
    ],
    "wof:name":"Banca Di Credito Cooperativo Di Gatteo (soccooprl)",
    "wof:placetype":"venue"
},
  "geometry": {"coordinates":[11.9804611206,43.9947662354],"type":"Point"}
}