{
  "type": "Feature",
  "properties": {
    "addr:full":"20122 Milano Milano Milano 20122",
    "addr:postcode":"20122;20122",
    "iso:country":"IT",
    "sg:address":"20122 Milano",
    "sg:city":"Milano",
    "sg:orig_category":"Pubblicita', Marketing E Comunicazione",
    "sg:phone":"+39 02 5519 2002",
    "sg:postcode":"20122",
    "sg:province":"Milano",
    "wof:name":"Studio Simonetti - T. Marketing",
    "wof:placetype":"venue"
},
  "geometry": {"coordinates":[9.1994533539,45.4566421509],"type":"Point"}
}