{
  "type": "Feature",
  "properties": {
    "addr:full":"24050 Grassobbio Grassobbio Bergamo 24050",
    "addr:postcode":"24050;24050",
    "iso:country":"IT",
    "sg:address":"24050 Grassobbio",
    "sg:city":"Grassobbio",
    "sg:orig_category":"Macchine E Forniture Per Ecologia E Smaltimento Rifiuti. Termotecnica E Riscaldamento, Apparecchiature E Servizi",
    "sg:phone":"+39 035 335645",
    "sg:postcode":"24050",
    "sg:province":"Bergamo",
    "wof:name":"Impelsol Srl",
    "wof:placetype":"venue"
},
  "geometry": {"coordinates":[9.726836,45.659176],"type":"Point"}
}