{
  "type": "Feature",
  "properties": {
    "iso:country":"IT",
    "sg:address":"Via Statale Nocerina 84083 Castel San Giorgio",
    "sg:city":"Castel San Giorgio",
    "sg:classifiers":[
        {
            "category":"Manufacturing",
            "subcategory":"Paper Products",
            "type":"Manufacturing & Wholesale Goods"
        }
    ],
    "sg:phone":"+39 081 517 3646",
    "sg:postcode":"84083",
    "sg:province":"Salerno",
    "sg:tags":[
        "cardboard"
    ],
    "wof:name":"Gianni De Falco & C. Srl",
    "wof:placetype":"venue"
},
  "geometry": {"coordinates":[14.6653614044,40.7724304199],"type":"Point"}
}