{
  "type": "Feature",
  "properties": {
    "addr:full":"16, Via Partini Umberto 00159 Roma Roma Roma 00159",
    "addr:postcode":"00159;00159",
    "addr:street":"Via Partini Umberto",
    "iso:country":"IT",
    "sg:address":"16, Via Partini Umberto 00159 Roma",
    "sg:city":"Roma",
    "sg:classifiers":[
        {
            "category":"Autos & Motor Vehicles",
            "subcategory":"Automobile Sales",
            "type":"Retail Goods"
        }
    ],
    "sg:phone":"+39 06 4353 4242",
    "sg:postcode":"00159",
    "sg:province":"Roma",
    "sg:tags":[
        "industrial"
    ],
    "wof:name":"Cooperativa Benzinai (s.r.l.)",
    "wof:placetype":"venue"
},
  "geometry": {"coordinates":[12.482325,41.895466],"type":"Point"}
}