{
  "type": "Feature",
  "properties": {
    "addr:full":"47100 Forli' Forl\u00ec-Cesena 47100",
    "addr:postcode":"47100;47100",
    "addr:street":"Forli ' Forli\u0300-Cesena",
    "iso:country":"IT",
    "sg:address":"47100 Forli'",
    "sg:orig_category":"Forniture Per Agricoltura E Zootecnia. Animali Domestici",
    "sg:phone":"+39 0543 403004",
    "sg:postcode":"47100",
    "sg:province":"Forl\u00ec-Cesena",
    "wof:name":"Zooveterin Di Casali Miranda & C. S.a.s.",
    "wof:placetype":"venue"
},
  "geometry": {"coordinates":[12.0487136841,44.2054176331],"type":"Point"}
}