{
  "type": "Feature",
  "properties": {
    "iso:country":"IT",
    "sg:address":"87100 Cosenza",
    "sg:city":"Cosenza",
    "sg:orig_category":"Condizionamento Aria Impianti - Installazione E Manutenzione",
    "sg:phone":"+39 0984 795486",
    "sg:postcode":"87100",
    "sg:province":"Cosenza",
    "wof:name":"Rte Service Snc Di Pasqua G. & Squillace V.",
    "wof:placetype":"venue"
},
  "geometry": {"coordinates":[16.252357,39.293888],"type":"Point"}
}