{
  "type": "Feature",
  "properties": {
    "iso:country":"IT",
    "sg:address":"50/d, Via Brendole 30174 Venezia",
    "sg:city":"Venezia",
    "sg:classifiers":[
        {
            "category":"Manufacturing",
            "subcategory":"Metals",
            "type":"Manufacturing & Wholesale Goods"
        }
    ],
    "sg:phone":"+39 041 544 1255",
    "sg:postcode":"30174",
    "sg:province":"Venezia",
    "sg:tags":[
        "metallurgy",
        "metalworking"
    ],
    "wof:name":"F.lli De Rossi Roberto E Luciano (s.n.c.)",
    "wof:placetype":"venue"
},
  "geometry": {"coordinates":[12.3266267776,45.4408950806],"type":"Point"}
}