{
  "type": "Feature",
  "properties": {
    "addr:full":"20063 Cernusco Sul Naviglio Cernusco sul Naviglio Milano 20063",
    "addr:postcode":"20063;20063",
    "iso:country":"IT",
    "sg:address":"20063 Cernusco Sul Naviglio",
    "sg:city":"Cernusco sul Naviglio",
    "sg:orig_category":"Pubblicita', Marketing E Comunicazione",
    "sg:phone":"+39 02 924 3123",
    "sg:postcode":"20063",
    "sg:province":"Milano",
    "wof:name":"Grafomania Srl",
    "wof:placetype":"venue"
},
  "geometry": {"coordinates":[9.3381586075,45.5376396179],"type":"Point"}
}