{
  "type": "Feature",
  "properties": {
    "addr:full":"84083 Castel San Giorgio Castel San Giorgio Salerno 84083",
    "addr:postcode":"84083;giorgio;84083",
    "addr:street":"San",
    "iso:country":"IT",
    "sg:address":"84083 Castel San Giorgio",
    "sg:city":"Castel San Giorgio",
    "sg:orig_category":"Termotecnica E Riscaldamento, Apparecchiature E Servizi",
    "sg:phone":"+39 081 951125",
    "sg:postcode":"84083",
    "sg:province":"Salerno",
    "wof:name":"Lanzara Antonio",
    "wof:placetype":"venue"
},
  "geometry": {"coordinates":[14.680284,40.776333],"type":"Point"}
}