{
  "type": "Feature",
  "properties": {
    "iso:country":"IT",
    "sg:address":"21013 Gallarate",
    "sg:city":"Gallarate",
    "sg:orig_category":"Ospedali E Servizi Sanitari",
    "sg:phone":"+39 0331 773939",
    "sg:postcode":"21013",
    "sg:province":"Varese",
    "wof:name":"Sirianni Dr. Franco",
    "wof:placetype":"venue"
},
  "geometry": {"coordinates":[8.7992763519,45.6648635864],"type":"Point"}
}