{
  "type": "Feature",
  "properties": {
    "addr:full":"Via Ilaria Alpi, 13/15 56028 San Miniato Basso San Miniato Pisa 56028",
    "addr:housenumber":"13 / 15",
    "addr:postcode":"56028;56028",
    "addr:street":"Via Ilaria Alpi;Basso",
    "iso:country":"IT",
    "sg:address":"Via Ilaria Alpi, 13/15 56028 San Miniato Basso",
    "sg:city":"San Miniato",
    "sg:classifiers":[
        {
            "category":"Manufacturing",
            "subcategory":"Tools & Machinery",
            "type":"Manufacturing & Wholesale Goods"
        }
    ],
    "sg:phone":"+39 0571 400701",
    "sg:postcode":"56028",
    "sg:province":"Pisa",
    "sg:tags":[
        "making",
        "shoe"
    ],
    "sg:website":"www.tepal.it",
    "wof:name":"Tepal Group Srl",
    "wof:placetype":"venue"
},
  "geometry": {"coordinates":[10.829452,43.693882],"type":"Point"}
}