{
  "type": "Feature",
  "properties": {
    "addr:full":"Via Ss 275 73035 Miggiano Miggiano Lecce 73035",
    "addr:housenumber":"275",
    "addr:postcode":"73035;73035",
    "addr:street":"Via Ss",
    "iso:country":"IT",
    "sg:address":"Via Ss 275 73035 Miggiano",
    "sg:city":"Miggiano",
    "sg:classifiers":[
        {
            "category":"Home & Garden",
            "subcategory":"Home Furnishings",
            "type":"Retail Goods"
        }
    ],
    "sg:phone":"+39 0833 761292",
    "sg:postcode":"73035",
    "sg:province":"Lecce",
    "sg:tags":[
        "household"
    ],
    "wof:name":"Cafiero Cucine S.n.c.",
    "wof:placetype":"venue"
},
  "geometry": {"coordinates":[18.174015,40.353291],"type":"Point"}
}