{
  "type": "Feature",
  "properties": {
    "addr:full":"56127 Pisa Pisa Pisa 56127",
    "addr:postcode":"56127;56127",
    "iso:country":"IT",
    "sg:address":"56127 Pisa",
    "sg:city":"Pisa",
    "sg:orig_category":"Hobbistica",
    "sg:phone":"+39 050 574015",
    "sg:postcode":"56127",
    "sg:province":"Pisa",
    "wof:name":"Circolo Il Collezionismo",
    "wof:placetype":"venue"
},
  "geometry": {"coordinates":[10.408754,43.718346],"type":"Point"}
}