{
  "type": "Feature",
  "properties": {
    "addr:full":"12042 Bra Bra Cuneo 12042",
    "addr:postcode":"12042;12042",
    "iso:country":"IT",
    "sg:address":"12042 Bra",
    "sg:city":"Bra",
    "sg:orig_category":"Prodotti Finiti Stampati. Forniture Per Uffici",
    "sg:phone":"+39 0172 412355",
    "sg:postcode":"12042",
    "sg:province":"Cuneo",
    "wof:name":"Tipografia Grosso",
    "wof:placetype":"venue"
},
  "geometry": {"coordinates":[7.8491282463,44.692276001],"type":"Point"}
}