{
  "type": "Feature",
  "properties": {
    "addr:full":"5, Via Alberti Leon Battista 20149 Milano Milano Milano 20149",
    "addr:postcode":"20149;20149",
    "addr:street":"Via Alberti;Battista",
    "iso:country":"IT",
    "sg:address":"5, Via Alberti Leon Battista 20149 Milano",
    "sg:city":"Milano",
    "sg:classifiers":[
        {
            "category":"Wholesale",
            "subcategory":"Machinery & Supplies",
            "type":"Manufacturing & Wholesale Goods"
        }
    ],
    "sg:phone":"+39 39023491141",
    "sg:postcode":"20149",
    "sg:province":"Milano",
    "sg:tags":[
        "equipment",
        "-",
        "instrument",
        "measurement"
    ],
    "wof:name":"Nuova Fima (s.p.a.)",
    "wof:placetype":"venue"
},
  "geometry": {"coordinates":[9.157866,45.483799],"type":"Point"}
}