{
  "type": "Feature",
  "properties": {
    "addr:full":"38100 Trento Trento Trento 38100",
    "addr:postcode":"38100;38100",
    "iso:country":"IT",
    "sg:address":"38100 Trento",
    "sg:city":"Trento",
    "sg:orig_category":"Elettrotecnica Industriale, Prodotti E Apparecchiature",
    "sg:phone":"+39 0461 991994",
    "sg:postcode":"38100",
    "sg:province":"Trento",
    "sg:website":"http://elettromeccanicatrentina.it",
    "wof:name":"Elettromeccanica Trentina Snc",
    "wof:placetype":"venue"
},
  "geometry": {"coordinates":[11.11063,46.124554],"type":"Point"}
}