{
  "type": "Feature",
  "properties": {
    "iso:country":"IT",
    "sg:address":"12, V. Ho Chi Min 60022 Castelfidardo",
    "sg:city":"Castelfidardo",
    "sg:classifiers":[
        {
            "category":"Manufacturing",
            "subcategory":"Tools & Machinery",
            "type":"Manufacturing & Wholesale Goods"
        }
    ],
    "sg:phone":"+39 071 780 8176",
    "sg:postcode":"60022",
    "sg:province":"Ancona",
    "sg:tags":[
        "environment",
        "equipment",
        "-"
    ],
    "sg:website":"http://www.gel.it",
    "wof:name":"Gel Srl",
    "wof:placetype":"venue"
},
  "geometry": {"coordinates":[13.539552,43.451794],"type":"Point"}
}