{
  "type": "Feature",
  "properties": {
    "addr:full":"31033 Castelfranco Veneto Castelfranco Veneto Treviso 31033",
    "addr:postcode":"31033;31033",
    "iso:country":"IT",
    "sg:address":"31033 Castelfranco Veneto",
    "sg:city":"Castelfranco Veneto",
    "sg:orig_category":"Lavorazioni Meccaniche E Servizi",
    "sg:phone":"+39 0423 472433",
    "sg:postcode":"31033",
    "sg:province":"Treviso",
    "wof:name":"Antonello Angelo E Figlio Snc",
    "wof:placetype":"venue"
},
  "geometry": {"coordinates":[11.951897,45.67329],"type":"Point"}
}