{
  "type": "Feature",
  "properties": {
    "iso:country":"IT",
    "sg:address":"124, Via Provinciale Carrara Avenza 54033 Carrara",
    "sg:city":"Avenza",
    "sg:classifiers":[
        {
            "category":"Shopping",
            "subcategory":"Clothing, Apparel, & Fashions",
            "type":"Retail Goods"
        }
    ],
    "sg:phone":"+39 39058552052",
    "sg:postcode":"54033",
    "sg:province":"Massa-Carrara",
    "sg:tags":[
        "clothes"
    ],
    "wof:name":"Foster (s.p.a.)",
    "wof:placetype":"venue"
},
  "geometry": {"coordinates":[10.07264,44.053429],"type":"Point"}
}