{
  "type": "Feature",
  "properties": {
    "iso:country":"IT",
    "sg:address":"56121 Pisa",
    "sg:city":"Pisa",
    "sg:orig_category":"Pubblica Amministrazione",
    "sg:phone":"+39 050 503590",
    "sg:postcode":"56121",
    "sg:province":"Pisa",
    "wof:name":"Corpo Forestale Dello Stato",
    "wof:placetype":"venue"
},
  "geometry": {"coordinates":[10.3834791183,43.6518669128],"type":"Point"}
}