{
  "type": "Feature",
  "properties": {
    "addr:full":"24, Via Dell' Artigianato 33048 San Giovanni Al Natisone San Giovanni al Natisone Udine 33048",
    "addr:postcode":"33048;33048",
    "addr:street":"Via Dell ' Artigianato",
    "iso:country":"IT",
    "sg:address":"24, Via Dell' Artigianato 33048 San Giovanni Al Natisone",
    "sg:city":"San Giovanni al Natisone",
    "sg:classifiers":[
        {
            "category":"Home & Garden",
            "subcategory":"Home Furnishings",
            "type":"Retail Goods"
        }
    ],
    "sg:phone":"+39 0432 756624",
    "sg:postcode":"33048",
    "sg:province":"Udine",
    "sg:tags":[
        "household"
    ],
    "wof:name":"Frava Srl",
    "wof:placetype":"venue"
},
  "geometry": {"coordinates":[13.406726,45.954983],"type":"Point"}
}