{
  "type": "Feature",
  "properties": {
    "iso:country":"IT",
    "sg:address":"53047 Sarteano",
    "sg:city":"Sarteano",
    "sg:orig_category":"Macchine, Impianti E Forniture Per Industria Grafica, Cartaria E Cartotecnica. Apparecchiature Ed Attrezzature Meccaniche. Automazione E Macchine Per Ufficio",
    "sg:phone":"+39 0578 266584",
    "sg:postcode":"53047",
    "sg:province":"Siena",
    "wof:name":"Publivit Snc",
    "wof:placetype":"venue"
},
  "geometry": {"coordinates":[11.880386,42.983814],"type":"Point"}
}