{
  "type": "Feature",
  "properties": {
    "addr:full":"24050 Palosco Palosco Bergamo 24050",
    "addr:postcode":"24050;24050",
    "iso:country":"IT",
    "sg:address":"24050 Palosco",
    "sg:city":"Palosco",
    "sg:orig_category":"Non-classified Establishments",
    "sg:phone":"+39 035 846222",
    "sg:postcode":"24050",
    "sg:province":"Bergamo",
    "wof:name":"Aceti Arredamenti",
    "wof:placetype":"venue"
},
  "geometry": {"coordinates":[9.832516,45.582001],"type":"Point"}
}