{
  "type": "Feature",
  "properties": {
    "addr:full":"1, Via Divisione Julia 33013 Gemona Del Friuli Gemona del Friuli Udine 33013",
    "addr:postcode":"33013;33013",
    "addr:street":"Via Divisione Julia",
    "iso:country":"IT",
    "sg:address":"1, Via Divisione Julia 33013 Gemona Del Friuli",
    "sg:city":"Gemona del Friuli",
    "sg:classifiers":[
        {
            "category":"Professional",
            "subcategory":"Engineering",
            "type":"Services"
        }
    ],
    "sg:phone":"+39 0432 973511",
    "sg:postcode":"33013",
    "sg:province":"Udine",
    "sg:tags":[
        "machine",
        "-",
        "mechanical"
    ],
    "wof:name":"More S.r.l.",
    "wof:placetype":"venue"
},
  "geometry": {"coordinates":[13.230724,46.064941],"type":"Point"}
}