{
  "type": "Feature",
  "properties": {
    "iso:country":"IT",
    "sg:address":"00061 Anguillara Sabazia",
    "sg:city":"Anguillara Sabazia",
    "sg:orig_category":"Accessori Dei Mezzi Di Trasporto",
    "sg:phone":"+39 06 999 4078",
    "sg:postcode":"00061",
    "sg:province":"Roma",
    "wof:name":"Leader Car Di Pasqualucci Marco E C Snc",
    "wof:placetype":"venue"
},
  "geometry": {"coordinates":[12.283628,42.082283],"type":"Point"}
}