{
  "type": "Feature",
  "properties": {
    "iso:country":"IT",
    "sg:address":"61, Via Alpi 63014 Montegranaro",
    "sg:city":"Montegranaro",
    "sg:classifiers":[
        {
            "category":"Personal",
            "subcategory":"Shoe Repair & Shine",
            "type":"Services"
        }
    ],
    "sg:phone":"+39 0734 892435",
    "sg:postcode":"63014",
    "sg:province":"Ascoli Piceno",
    "sg:tags":[
        "leather"
    ],
    "wof:name":"Calzaturificio Fenis (s.r.l.)",
    "wof:placetype":"venue"
},
  "geometry": {"coordinates":[13.646888,43.258656],"type":"Point"}
}