{
  "type": "Feature",
  "properties": {
    "iso:country":"IT",
    "sg:address":"59, Via Pagano Mario Francesco 80020 Casavatore",
    "sg:city":"Casavatore",
    "sg:classifiers":[
        {
            "category":"Shopping",
            "subcategory":"Clothing, Apparel, & Fashions",
            "type":"Retail Goods"
        }
    ],
    "sg:phone":"+39 081 736 7118",
    "sg:postcode":"80020",
    "sg:province":"Napoli",
    "sg:tags":[
        "clothes"
    ],
    "wof:name":"Cardam S.n.c. Di Cardamone & D'ambrosio",
    "wof:placetype":"venue"
},
  "geometry": {"coordinates":[14.281137,40.898266],"type":"Point"}
}