{
  "type": "Feature",
  "properties": {
    "iso:country":"IT",
    "sg:address":"20022 Castano Primo",
    "sg:city":"Castano Primo",
    "sg:orig_category":"Macchine E Forniture Per Ecologia E Smaltimento Rifiuti. Elettrodomestici. Forniture Alle Strutture Ricettive. Macchine, Strumenti Ed Apparecchi Per Attivita' Industriali",
    "sg:phone":"+39 0331 877858",
    "sg:postcode":"20022",
    "sg:province":"Milano",
    "wof:name":"Trezeta Di Zito G.",
    "wof:placetype":"venue"
},
  "geometry": {"coordinates":[8.783273,45.557846],"type":"Point"}
}