{
  "type": "Feature",
  "properties": {
    "addr:full":"47011 Castrocaro Terme Terra del sole Forl\u00ec-Cesena 47011",
    "addr:postcode":"47011;47011",
    "iso:country":"IT",
    "sg:address":"47011 Castrocaro Terme",
    "sg:city":"Terra del sole",
    "sg:orig_category":"Officine Meccaniche Di Precisione",
    "sg:phone":"+39 0543 766990",
    "sg:postcode":"47011",
    "sg:province":"Forl\u00ec-Cesena",
    "sg:website":"http://www.fllimarzocchi.com",
    "wof:name":"Fratelli Marzocchi Srl",
    "wof:placetype":"venue"
},
  "geometry": {"coordinates":[11.950328,44.182137],"type":"Point"}
}