{
  "type": "Feature",
  "properties": {
    "addr:full":"7, Via Brescia 24040 Ciserano Ciserano Bergamo 24040",
    "addr:postcode":"24040;24040",
    "addr:street":"Via Brescia",
    "iso:country":"IT",
    "sg:address":"7, Via Brescia 24040 Ciserano",
    "sg:city":"Ciserano",
    "sg:classifiers":[
        {
            "category":"Manufacturing",
            "subcategory":"Metals",
            "type":"Manufacturing & Wholesale Goods"
        }
    ],
    "sg:phone":"+39 39035882390",
    "sg:postcode":"24040",
    "sg:province":"Bergamo",
    "sg:tags":[
        "metallurgy",
        "metalworking"
    ],
    "wof:name":"Fonderia Pz (s.r.l.)",
    "wof:placetype":"venue"
},
  "geometry": {"coordinates":[9.5999479294,45.6326179504],"type":"Point"}
}