{
  "type": "Feature",
  "properties": {
    "addr:full":"65013 Citta'santangelo Pescara 65013",
    "addr:postcode":"65013;65013",
    "iso:country":"IT",
    "sg:address":"65013 Citta'santangelo",
    "sg:orig_category":"Arredamenti E Mobili Professionali. Forniture Alle Strutture Ricettive. Arredi Ed Attrezzature Per Attivita' Commerciali Ed Artigianali",
    "sg:phone":"+39 085 950266",
    "sg:postcode":"65013",
    "sg:province":"Pescara",
    "wof:name":"Tecnomet Italia Spa",
    "wof:placetype":"venue"
},
  "geometry": {"coordinates":[14.129369,42.521191],"type":"Point"}
}