{
  "type": "Feature",
  "properties": {
    "iso:country":"IT",
    "sg:address":"20010 Inveruno",
    "sg:city":"Inveruno",
    "sg:orig_category":"Termotecnica E Riscaldamento, Apparecchiature E Servizi",
    "sg:phone":"+39 02 978 7024",
    "sg:postcode":"20010",
    "sg:province":"Milano",
    "wof:name":"Recuperator Srl",
    "wof:placetype":"venue"
},
  "geometry": {"coordinates":[8.853754,45.515686],"type":"Point"}
}