{
  "type": "Feature",
  "properties": {
    "addr:full":"20146 Milano Milano Milano 20146",
    "addr:postcode":"20146;20146",
    "iso:country":"IT",
    "sg:address":"20146 Milano",
    "sg:city":"Milano",
    "sg:orig_category":"Elettronica Professionale E Di Consumo. Forniture Per Il Settore Dello Spettacolo. Automazione E Macchine Per Ufficio. Forniture Per Congressi, Fiere E Manifestazioni",
    "sg:phone":"+39 02 481 6312",
    "sg:postcode":"20146",
    "sg:province":"Milano",
    "wof:name":"Gls Di Giovanni Conti",
    "wof:placetype":"venue"
},
  "geometry": {"coordinates":[9.155313,45.459835],"type":"Point"}
}