{
  "type": "Feature",
  "properties": {
    "addr:full":"Via Castruccio 21 59100 Prato Prato Prato 59100",
    "addr:housenumber":"21",
    "addr:postcode":"59100;59100",
    "addr:street":"Via Castruccio",
    "iso:country":"IT",
    "sg:address":"Via Castruccio 21 59100 Prato",
    "sg:city":"Prato",
    "sg:orig_category":"Preparations For Textile Fibres",
    "sg:phone":"+39 0574 623383",
    "sg:postcode":"59100",
    "sg:province":"Prato",
    "wof:name":"P.m.d. Fibre S.a.s. Di Paolieri Mauro Impero E C.",
    "wof:placetype":"venue"
},
  "geometry": {"coordinates":[11.0354156494,43.865146637],"type":"Point"}
}