{
  "type": "Feature",
  "properties": {
    "iso:country":"IT",
    "sg:address":"Localita' Cattagnina 29010 Rottofreno",
    "sg:city":"Rottofreno",
    "sg:classifiers":[
        {
            "category":"Real Estate",
            "subcategory":"Architect",
            "type":"Services"
        }
    ],
    "sg:phone":"+39 0523 782711",
    "sg:postcode":"29010",
    "sg:province":"Piacenza",
    "sg:tags":[
        "textile",
        "clothing"
    ],
    "wof:name":"Red S.r.l.",
    "wof:placetype":"venue"
},
  "geometry": {"coordinates":[9.695142,45.053772],"type":"Point"}
}