{
  "type": "Feature",
  "properties": {
    "iso:country":"IT",
    "sg:address":"16122 Genova",
    "sg:city":"Genova",
    "sg:orig_category":"Agenzie Marittime",
    "sg:phone":"+39 010 251 8426",
    "sg:postcode":"16122",
    "sg:province":"Genova",
    "wof:name":"Goliath Italia Srl",
    "wof:placetype":"venue"
},
  "geometry": {"coordinates":[8.939375,44.411648],"type":"Point"}
}