{
  "type": "Feature",
  "properties": {
    "addr:full":"5, Via Garibaldi 28076 Pogno Pogno Novara 28076",
    "addr:postcode":"28076;28076",
    "addr:street":"Via Garibaldi",
    "iso:country":"IT",
    "sg:address":"5, Via Garibaldi 28076 Pogno",
    "sg:city":"Pogno",
    "sg:classifiers":[
        {
            "category":"Shopping",
            "type":"Retail Goods"
        }
    ],
    "sg:phone":"+39 39032297360",
    "sg:postcode":"28076",
    "sg:province":"Novara",
    "sg:tags":[
        "finished",
        "-",
        "metallic"
    ],
    "wof:name":"Rubinetteria Gaboli Luigi & C. (s.n.c.)",
    "wof:placetype":"venue"
},
  "geometry": {"coordinates":[8.3831558228,45.7571678162],"type":"Point"}
}