{
  "type": "Feature",
  "properties": {
    "addr:full":"12, Via Dell' Artigianato 47814 Bellaria Igea Marina Bellaria Rimini 47814",
    "addr:postcode":"47814;47814",
    "addr:street":"Via Dell ' Artigianato",
    "iso:country":"IT",
    "sg:address":"12, Via Dell' Artigianato 47814 Bellaria Igea Marina",
    "sg:city":"Bellaria",
    "sg:classifiers":[
        {
            "category":"Bars & Pubs",
            "subcategory":"Nightclub",
            "type":"Food & Drink"
        }
    ],
    "sg:phone":"+39 0541 330184",
    "sg:postcode":"47814",
    "sg:province":"Rimini",
    "sg:tags":[
        "cake",
        "bread"
    ],
    "wof:name":"Forno Romagnolo Di Muccioli Mirko Mulazzani Roberto E Rocchi Alessandro Snc",
    "wof:placetype":"venue"
},
  "geometry": {"coordinates":[12.469237,44.129238],"type":"Point"}
}