{
  "type": "Feature",
  "properties": {
    "addr:full":"Via Della Canonica 06012 Citta' Di Castello Perugia 06012",
    "addr:postcode":"06012 citta;06012",
    "addr:street":"Via Della Canonica",
    "iso:country":"IT",
    "sg:address":"Via Della Canonica 06012 Citta' Di Castello",
    "sg:classifiers":[
        {
            "category":"Home & Garden",
            "subcategory":"Home Furnishings",
            "type":"Retail Goods"
        }
    ],
    "sg:phone":"+39 075 852 1577",
    "sg:postcode":"06012",
    "sg:province":"Perugia",
    "sg:tags":[
        "household"
    ],
    "wof:name":"Old House Di Milli E Antonelli S.r.l.",
    "wof:placetype":"venue"
},
  "geometry": {"coordinates":[12.24544,43.447231],"type":"Point"}
}