{
  "type": "Feature",
  "properties": {
    "iso:country":"IT",
    "sg:address":"89029 Taurianova",
    "sg:city":"Taurianova",
    "sg:orig_category":"Macchine Ed Impianti Per Edilizia E Lavori Pubblici",
    "sg:phone":"+39 0966 611771",
    "sg:postcode":"89029",
    "sg:province":"Reggio Di Calabria",
    "wof:name":"Zavaglia Salvatore",
    "wof:placetype":"venue"
},
  "geometry": {"coordinates":[15.650137,38.114689],"type":"Point"}
}