{
  "type": "Feature",
  "properties": {
    "iso:country":"IT",
    "sg:address":"85100 Potenza",
    "sg:city":"Potenza",
    "sg:orig_category":"Servizi Ausiliari Di Analisi, Controllo E Ricerca",
    "sg:phone":"+39 0971 411717",
    "sg:postcode":"85100",
    "sg:province":"Potenza",
    "wof:name":"Istat - Istituto Nazionale Di Statistica",
    "wof:placetype":"venue"
},
  "geometry": {"coordinates":[15.800895,40.637169],"type":"Point"}
}