{
  "type": "Feature",
  "properties": {
    "iso:country":"IT",
    "sg:address":"20099 Sesto San Giovanni",
    "sg:city":"Sesto San Giovanni",
    "sg:orig_category":"Abbigliamento Esterno, Maglierie E Pelliccerie. Servizi E Lavori Per Abbigliamento E Pelletterie",
    "sg:phone":"+39 02 262 1041",
    "sg:postcode":"20099",
    "sg:province":"Milano",
    "wof:name":"M - By Margherita Di Di Mauro Margherita",
    "wof:placetype":"venue"
},
  "geometry": {"coordinates":[9.238032,45.535614],"type":"Point"}
}