{
  "type": "Feature",
  "properties": {
    "iso:country":"IT",
    "sg:address":"00040 Pomezia",
    "sg:city":"Pomezia",
    "sg:orig_category":"Arredamenti - Vendita Al Dettaglio",
    "sg:phone":"+39 330 544 893",
    "sg:postcode":"00040",
    "sg:province":"Roma",
    "wof:name":"D'alessandro Michele",
    "wof:placetype":"venue"
},
  "geometry": {"coordinates":[12.508023,41.66748],"type":"Point"}
}