{
  "type": "Feature",
  "properties": {
    "iso:country":"IT",
    "sg:address":"Via Agostino Berenini 57; Fidenza; 43036",
    "sg:city":"Fidenza",
    "sg:classifiers":[
        {
            "category":"Banks & Credit Unions",
            "subcategory":"Bank",
            "type":"Services"
        }
    ],
    "sg:phone":"+39 0524 528482",
    "sg:postcode":"43036",
    "sg:province":"Parma",
    "wof:name":"Credito Italiano Spa",
    "wof:placetype":"venue"
},
  "geometry": {"coordinates":[10.065513,44.865089],"type":"Point"}
}