{
  "type": "Feature",
  "properties": {
    "addr:full":"10/b, Via Barbacini Francesco 43100 Parma Parma Parma 43100",
    "addr:housenumber":"10 / b",
    "addr:postcode":"43100;43100",
    "addr:street":"Via Barbacini Francesco",
    "iso:country":"IT",
    "sg:address":"10/b, Via Barbacini Francesco 43100 Parma",
    "sg:city":"Parma",
    "sg:classifiers":[
        {
            "category":"Professional",
            "subcategory":"Printing & Photocopies",
            "type":"Services"
        }
    ],
    "sg:phone":"+39 0521 783268",
    "sg:postcode":"43100",
    "sg:province":"Parma",
    "wof:name":"Grafiche Step Coop. (s.r.l.)",
    "wof:placetype":"venue"
},
  "geometry": {"coordinates":[10.2949199677,44.8232078552],"type":"Point"}
}