{
  "type": "Feature",
  "properties": {
    "addr:full":"30100 Venezia VE",
    "addr:postcode":"30100",
    "addr:street":"Ve",
    "iso:country":"IT",
    "sg:address":"30100 Venezia",
    "sg:orig_category":"Ristorazione E Locali Pubblici Affini. Ristoranti Ed Esercizi Affini. Servizi Ausiliari Di Ristorazione E Di Intrattenimento",
    "sg:phone":"+39 041 275 0418",
    "sg:province":"VE",
    "sg:website":"http://www.venice2000.it",
    "wof:name":"Venice 2000 Soc.coop.r.l.",
    "wof:placetype":"venue"
},
  "geometry": {"coordinates":[12.290899,45.373199],"type":"Point"}
}