{
  "type": "Feature",
  "properties": {
    "iso:country":"IT",
    "sg:address":"64024 Notaresco",
    "sg:city":"Notaresco",
    "sg:orig_category":"Trasporti E Spedizioni Merci",
    "sg:phone":"+39 085 898121",
    "sg:postcode":"64024",
    "sg:province":"Teramo",
    "wof:name":"Italsoviet Lines Sas",
    "wof:placetype":"venue"
},
  "geometry": {"coordinates":[13.981002,42.5802],"type":"Point"}
}