{
  "type": "Feature",
  "properties": {
    "addr:full":"97019 Vittoria Scoglitti Ragusa 97019",
    "addr:postcode":"97019;97019",
    "iso:country":"IT",
    "sg:address":"97019 Vittoria",
    "sg:city":"Scoglitti",
    "sg:orig_category":"Pompe. Ricambi E Componenti Dei Mezzi Di Trasporto",
    "sg:phone":"+39 0932 980666",
    "sg:postcode":"97019",
    "sg:province":"Ragusa",
    "wof:name":"Lombardo Salvatore",
    "wof:placetype":"venue"
},
  "geometry": {"coordinates":[14.4331445694,36.8941612244],"type":"Point"}
}