{
  "type": "Feature",
  "properties": {
    "iso:country":"IT",
    "sg:address":"Corso Torino 87/d 10090 Buttigliera Alta",
    "sg:city":"Buttigliera Alta",
    "sg:classifiers":[
        {
            "category":"Home & Garden",
            "subcategory":"Hardware",
            "type":"Retail Goods"
        }
    ],
    "sg:phone":"+39 011 936 7757",
    "sg:postcode":"10090",
    "sg:province":"Torino",
    "sg:tags":[
        "component",
        "electronic"
    ],
    "sg:website":"www.comelec.it",
    "wof:name":"Comelec Srl",
    "wof:placetype":"venue"
},
  "geometry": {"coordinates":[7.397664,45.086906],"type":"Point"}
}