{
  "type": "Feature",
  "properties": {
    "iso:country":"IT",
    "sg:address":"15057 Tortona",
    "sg:city":"Tortona",
    "sg:orig_category":"Metalli E Leghe",
    "sg:phone":"+39 0131 867159",
    "sg:postcode":"15057",
    "sg:province":"Alessandria",
    "sg:website":"http://www.stooss.com",
    "wof:name":"Schmiedewerk Stooss Ag - Co.i.r. Sas",
    "wof:placetype":"venue"
},
  "geometry": {"coordinates":[8.8437108994,44.9004821777],"type":"Point"}
}