{
  "type": "Feature",
  "properties": {
    "iso:country":"IT",
    "sg:address":"15067 Novi Ligure",
    "sg:city":"Novi Ligure",
    "sg:orig_category":"Ospedali E Servizi Sanitari",
    "sg:phone":"+39 0143 2564",
    "sg:postcode":"15067",
    "sg:province":"Alessandria",
    "wof:name":"Studio Radiologico Dott. Foco Di Maria Teresa Foco Sas",
    "wof:placetype":"venue"
},
  "geometry": {"coordinates":[8.789277,44.780621],"type":"Point"}
}