{
  "type": "Feature",
  "properties": {
    "iso:country":"IT",
    "sg:address":"28060 Vicolungo",
    "sg:city":"Vicolungo",
    "sg:orig_category":"Impiantistica E Prodotti Tecnologici Per Edilizia",
    "sg:phone":"+39 0321 835801",
    "sg:postcode":"28060",
    "sg:province":"Novara",
    "wof:name":"Euroelevator Snc",
    "wof:placetype":"venue"
},
  "geometry": {"coordinates":[8.468402,45.435612],"type":"Point"}
}