{
  "type": "Feature",
  "properties": {
    "iso:country":"IT",
    "sg:address":"20091 Bresso",
    "sg:city":"Bresso",
    "sg:orig_category":"Materiali E Componenti Elettrotecnici",
    "sg:phone":"+39 02 610 1341",
    "sg:postcode":"20091",
    "sg:province":"Milano",
    "wof:name":"Thermowatt Spa",
    "wof:placetype":"venue"
},
  "geometry": {"coordinates":[9.188227,45.539879],"type":"Point"}
}