{
  "type": "Feature",
  "properties": {
    "iso:country":"IT",
    "sg:address":"12, Via Pravinera 31010 Fregona",
    "sg:city":"Fregona",
    "sg:classifiers":[
        {
            "category":"Sports & Exercise",
            "subcategory":"Playing Field",
            "type":"Entertainment"
        }
    ],
    "sg:phone":"+39 0438 581924",
    "sg:postcode":"31010",
    "sg:province":"Treviso",
    "sg:tags":[
        "game"
    ],
    "wof:name":"Dal Pos Romano",
    "wof:placetype":"venue"
},
  "geometry": {"coordinates":[12.348525,46.01582],"type":"Point"}
}