{
  "type": "Feature",
  "properties": {
    "iso:country":"IT",
    "sg:address":"21, Via Battisti Cesare 26100 Cremona",
    "sg:city":"Cremona",
    "sg:classifiers":[
        {
            "category":"Farming",
            "subcategory":"Livestock Farm",
            "type":"Manufacturing & Wholesale Goods"
        }
    ],
    "sg:phone":"+39 39037222308",
    "sg:postcode":"26100",
    "sg:province":"Cremona",
    "sg:tags":[
        "agriculture"
    ],
    "wof:name":"Consorzio Incremento Irrigazione Territorio Cremonese",
    "wof:placetype":"venue"
},
  "geometry": {"coordinates":[10.026135,45.133499],"type":"Point"}
}