{
  "type": "Feature",
  "properties": {
    "iso:country":"IT",
    "sg:address":"26853 Caselle Lurani",
    "sg:city":"Caselle Lurani",
    "sg:orig_category":"Disegno, Grafica E Belle Arti - Articoli",
    "sg:phone":"+39 0371 96043",
    "sg:postcode":"26853",
    "sg:province":"Lodi",
    "wof:name":"Micron Snc",
    "wof:placetype":"venue"
},
  "geometry": {"coordinates":[9.357668,45.280376],"type":"Point"}
}