{
  "type": "Feature",
  "properties": {
    "addr:full":"93014 Mussomeli Mussomeli Caltanissetta 93014",
    "addr:postcode":"93014;93014",
    "iso:country":"IT",
    "sg:address":"93014 Mussomeli",
    "sg:city":"Mussomeli",
    "sg:orig_category":"Prodotti Di Base E Forniture Per Industria Alimentare E Bevande. Macchine, Impianti Ed Attrezzature Per Industria Alimentare E Bevande. Frigotecnica, Apparecchiature E Servizi. Macchine E Impianti Per",
    "sg:phone":"+39 0934 951793",
    "sg:postcode":"93014",
    "sg:province":"Caltanissetta",
    "wof:name":"Russo Antonino",
    "wof:placetype":"venue"
},
  "geometry": {"coordinates":[13.9177846909,37.5994987488],"type":"Point"}
}