{
  "type": "Feature",
  "properties": {
    "iso:country":"IT",
    "sg:address":"Via Castello 98 31020 Sernaglia Della Battaglia",
    "sg:city":"Sernaglia della Battaglia",
    "sg:classifiers":[
        {
            "category":"Manufacturing",
            "subcategory":"Furniture",
            "type":"Manufacturing & Wholesale Goods"
        }
    ],
    "sg:phone":"+39 0438 966222",
    "sg:postcode":"31020",
    "sg:province":"Treviso",
    "sg:tags":[
        "bedroom"
    ],
    "sg:website":"www.faveromobili.it",
    "wof:name":"Cig Srl",
    "wof:placetype":"venue"
},
  "geometry": {"coordinates":[12.139961,45.877014],"type":"Point"}
}