{
  "type": "Feature",
  "properties": {
    "iso:country":"IT",
    "sg:address":"20, Via Scaldasole 27020 Dorno",
    "sg:city":"Dorno",
    "sg:classifiers":[
        {
            "category":"Shopping",
            "subcategory":"Crafts & Fabrics",
            "type":"Retail Goods"
        }
    ],
    "sg:phone":"+39 39038284019",
    "sg:postcode":"27020",
    "sg:province":"Pavia",
    "sg:tags":[
        "ceramic"
    ],
    "wof:name":"Keraplan S.r.l.",
    "wof:placetype":"venue"
},
  "geometry": {"coordinates":[8.947366,45.147381],"type":"Point"}
}