{
  "type": "Feature",
  "properties": {
    "iso:country":"IT",
    "sg:address":"22100 Como",
    "sg:city":"Como",
    "sg:orig_category":"Studi E Consulenze Tecniche E Industriali. Consulenze Tecniche, Amministrative E Perizie. Professionisti - Studi E Servizi Ed Associazioni Di Interesse Aziendale",
    "sg:phone":"+39 031 242653",
    "sg:postcode":"22100",
    "sg:province":"Como",
    "wof:name":"Bissolotti Alessandro",
    "wof:placetype":"venue"
},
  "geometry": {"coordinates":[9.082616,45.808128],"type":"Point"}
}