{
  "type": "Feature",
  "properties": {
    "iso:country":"IT",
    "sg:address":"26010 Chieve",
    "sg:city":"Chieve",
    "sg:orig_category":"Servizi Di Magazzinaggio E Movimentazione",
    "sg:phone":"+39 0373 234303",
    "sg:postcode":"26010",
    "sg:province":"Cremona",
    "wof:name":"Autex Snc Di Aquilia A. & Co.",
    "wof:placetype":"venue"
},
  "geometry": {"coordinates":[9.620738,45.349056],"type":"Point"}
}