{
  "type": "Feature",
  "properties": {
    "iso:country":"IT",
    "sg:address":"19038 Sarzana",
    "sg:city":"Sarzana",
    "sg:orig_category":"Automazione E Macchine Per Ufficio. Arredi Ed Attrezzature Per Attivita' Commerciali Ed Artigianali",
    "sg:phone":"+39 0187 620026",
    "sg:postcode":"19038",
    "sg:province":"La Spezia",
    "wof:name":"Cargioli Giancarlo & C.",
    "wof:placetype":"venue"
},
  "geometry": {"coordinates":[9.819501,44.104362],"type":"Point"}
}