{
  "type": "Feature",
  "properties": {
    "addr:full":"80035 Nola Nola Napoli 80035",
    "addr:housenumber":"80035",
    "addr:postcode":"80035",
    "addr:street":"Nola",
    "iso:country":"IT",
    "sg:address":"80035 Nola",
    "sg:city":"Nola",
    "sg:orig_category":"Prodotti Chimici Di Base. Forniture Per Attivita' Industriali",
    "sg:phone":"+39 081 823 1439",
    "sg:postcode":"80035",
    "sg:province":"Napoli",
    "wof:name":"Industrie Riunite Meridionali (s.p.a.)",
    "wof:placetype":"venue"
},
  "geometry": {"coordinates":[14.5130968094,40.9334526062],"type":"Point"}
}