{
  "type": "Feature",
  "properties": {
    "addr:full":"10153 Torino Torino Torino 10153",
    "addr:postcode":"10153;10153",
    "iso:country":"IT",
    "sg:address":"10153 Torino",
    "sg:city":"Torino",
    "sg:classifiers":[
        {
            "category":"Communications",
            "subcategory":"Film & Video Production",
            "type":"Services"
        }
    ],
    "sg:phone":"+39 011 248 2149",
    "sg:postcode":"10153",
    "sg:province":"Torino",
    "sg:tags":[
        "cracker",
        "e",
        "biscotti"
    ],
    "sg:website":"http://www.gattodolcione.it",
    "wof:name":"Gatto Dolcione Srl",
    "wof:placetype":"venue"
},
  "geometry": {"coordinates":[7.713487,45.074207],"type":"Point"}
}