{
  "type": "Feature",
  "properties": {
    "iso:country":"IT",
    "sg:address":"30038 Spinea",
    "sg:city":"Spinea",
    "sg:orig_category":"Fotolito",
    "sg:phone":"+39 041 990718",
    "sg:postcode":"30038",
    "sg:province":"Venezia",
    "wof:name":"Quattrifoglio Snc",
    "wof:placetype":"venue"
},
  "geometry": {"coordinates":[12.1674833298,45.4901275635],"type":"Point"}
}