{
  "type": "Feature",
  "properties": {
    "iso:country":"IT",
    "sg:address":"35/a, Via Renon 39100 Bolzano",
    "sg:city":"Bolzano",
    "sg:classifiers":[
        {
            "category":"Food & Beverages",
            "subcategory":"Groceries & Convenience Stores",
            "type":"Retail Goods"
        }
    ],
    "sg:phone":"+39 0471 977218",
    "sg:postcode":"39100",
    "sg:province":"Bolzano/Bozen",
    "sg:tags":[
        "drink"
    ],
    "wof:name":"Vintrade (s.r.l. - G.m.b.h.)",
    "wof:placetype":"venue"
},
  "geometry": {"coordinates":[11.328239,46.461643],"type":"Point"}
}