{
  "type": "Feature",
  "properties": {
    "addr:full":"35020 Albignasego Albignasego Padova 35020",
    "addr:postcode":"35020;35020",
    "iso:country":"IT",
    "sg:address":"35020 Albignasego",
    "sg:city":"Albignasego",
    "sg:orig_category":"Macchine, Impianti Ed Attrezzature Per Abbigliamento E Pelletterie",
    "sg:phone":"+39 049 880 6149",
    "sg:postcode":"35020",
    "sg:province":"Padova",
    "sg:website":"http://www.tecnomain.com",
    "wof:name":"Tecnomain Srl",
    "wof:placetype":"venue"
},
  "geometry": {"coordinates":[11.852051,45.377914],"type":"Point"}
}