{
  "type": "Feature",
  "properties": {
    "addr:full":"38068 Rovereto Rovereto Trento 38068",
    "addr:postcode":"38068;38068",
    "iso:country":"IT",
    "sg:address":"38068 Rovereto",
    "sg:city":"Rovereto",
    "sg:orig_category":"Frigotecnica, Apparecchiature E Servizi. Forniture Alle Strutture Ricettive",
    "sg:phone":"+39 0464 439178",
    "sg:postcode":"38068",
    "sg:province":"Trento",
    "wof:name":"Viemme Di Marchiori Romeo & C. Snc",
    "wof:placetype":"venue"
},
  "geometry": {"coordinates":[11.0321512222,45.8955917358],"type":"Point"}
}