{
  "type": "Feature",
  "properties": {
    "iso:country":"IT",
    "sg:address":"20019 Settimo Milanese",
    "sg:city":"Settimo Milanese",
    "sg:orig_category":"Ospedali E Servizi Sanitari",
    "sg:phone":"+39 02 3350 0850",
    "sg:postcode":"20019",
    "sg:province":"Milano",
    "wof:name":"Croce Rossa Italiana",
    "wof:placetype":"venue"
},
  "geometry": {"coordinates":[9.053775,45.482407],"type":"Point"}
}