{
  "type": "Feature",
  "properties": {
    "iso:country":"IT",
    "sg:address":"35123 Padova",
    "sg:city":"Padova",
    "sg:orig_category":"Accessori Moda D'abbigliamento. Forniture Per Abbigliamento E Pelletterie. Shopping",
    "sg:phone":"+39 049 875 1521",
    "sg:postcode":"35123",
    "sg:province":"Padova",
    "wof:name":"Marchioro Anna Maria",
    "wof:placetype":"venue"
},
  "geometry": {"coordinates":[11.879743,45.402027],"type":"Point"}
}