{
  "type": "Feature",
  "properties": {
    "addr:full":"2, Via S. Martino 33087 Pasiano Di Pordenone Pasiano Pordenone 33087",
    "addr:postcode":"33087;33087",
    "addr:street":"Via S. Martino",
    "iso:country":"IT",
    "sg:address":"2, Via S. Martino 33087 Pasiano Di Pordenone",
    "sg:city":"Pasiano",
    "sg:classifiers":[
        {
            "category":"Home & Garden",
            "subcategory":"Home Furnishings",
            "type":"Retail Goods"
        }
    ],
    "sg:phone":"+39 0434 626421",
    "sg:postcode":"33087",
    "sg:province":"Pordenone",
    "sg:tags":[
        "household"
    ],
    "wof:name":"Dacia S.r.l.",
    "wof:placetype":"venue"
},
  "geometry": {"coordinates":[12.580357,45.831383],"type":"Point"}
}