{
  "type": "Feature",
  "properties": {
    "iso:country":"IT",
    "sg:address":"78, Via Alfieri Vittorio 63018 Porto Sant'elpidio",
    "sg:classifiers":[
        {
            "category":"Personal",
            "subcategory":"Shoe Repair & Shine",
            "type":"Services"
        }
    ],
    "sg:phone":"+39 0734 991050",
    "sg:postcode":"63018",
    "sg:province":"Ascoli Piceno",
    "sg:tags":[
        "leather"
    ],
    "wof:name":"Calzaturificio Alex Moda (s.a.s.)",
    "wof:placetype":"venue"
},
  "geometry": {"coordinates":[13.574977,42.8554],"type":"Point"}
}