{
  "type": "Feature",
  "properties": {
    "iso:country":"IT",
    "sg:address":"Via Ripe 35 25069 Villa Carcina",
    "sg:city":"Carcina",
    "sg:classifiers":[
        {
            "category":"Building & Trades",
            "subcategory":"Construction",
            "type":"Services"
        }
    ],
    "sg:phone":"+39 030 898 1693",
    "sg:postcode":"25069",
    "sg:province":"Brescia",
    "sg:tags":[
        "cutter",
        "milling",
        "side"
    ],
    "sg:website":"www.rime.net",
    "wof:name":"Rime Srl",
    "wof:placetype":"venue"
},
  "geometry": {"coordinates":[10.20103,45.630913],"type":"Point"}
}