{
  "type": "Feature",
  "properties": {
    "iso:country":"IT",
    "sg:address":"48, Strada Tra I Due Porti 61100 Pesaro",
    "sg:city":"Pesaro",
    "sg:classifiers":[
        {
            "category":"Autos & Motor Vehicles",
            "subcategory":"Boat Sales",
            "type":"Retail Goods"
        }
    ],
    "sg:phone":"+39 39072142581",
    "sg:postcode":"61100",
    "sg:province":"Pesaro E Urbino",
    "wof:name":"Cantiere Navale Pesaro Srl",
    "wof:placetype":"venue"
},
  "geometry": {"coordinates":[12.903887,43.919392],"type":"Point"}
}