{
  "type": "Feature",
  "properties": {
    "iso:country":"IT",
    "sg:address":"04018 Sezze",
    "sg:city":"Sezze",
    "sg:orig_category":"Engineering Societa'",
    "sg:phone":"+39 0773 877461",
    "sg:postcode":"04018",
    "sg:province":"Latina",
    "sg:website":"http://www.francisbacon.it",
    "wof:name":"Francis Bacon Srl",
    "wof:placetype":"venue"
},
  "geometry": {"coordinates":[13.070265,41.498653],"type":"Point"}
}