{
  "type": "Feature",
  "properties": {
    "iso:country":"IT",
    "sg:address":"06021 Costacciaro",
    "sg:city":"Costacciaro",
    "sg:orig_category":"Restaurants And Related Public Premises. Sport And Leisure, Services. Hotels And Hotel Facilities. Restaurants And Similar",
    "sg:phone":"+39 075 917 0770",
    "sg:postcode":"06021",
    "sg:province":"Perugia",
    "wof:name":"Villa Pascolo Di Santinelli & C. Snc",
    "wof:placetype":"venue"
},
  "geometry": {"coordinates":[12.344562,43.04583],"type":"Point"}
}