{
  "type": "Feature",
  "properties": {
    "addr:full":"Contrada Cisterna 62029 Tolentino Tolentino Macerata 62029",
    "addr:postcode":"62029;62029",
    "addr:street":"Contrada Cisterna",
    "iso:country":"IT",
    "sg:address":"Contrada Cisterna 62029 Tolentino",
    "sg:city":"Tolentino",
    "sg:classifiers":[
        {
            "category":"Personal",
            "subcategory":"Shoe Repair & Shine",
            "type":"Services"
        }
    ],
    "sg:phone":"+39 0733 971485",
    "sg:postcode":"62029",
    "sg:province":"Macerata",
    "sg:tags":[
        "leather"
    ],
    "wof:name":"Calzaturificio Montebove (s.p.a.)",
    "wof:placetype":"venue"
},
  "geometry": {"coordinates":[13.324789,43.222443],"type":"Point"}
}