{
  "type": "Feature",
  "properties": {
    "iso:country":"IT",
    "sg:address":"16128 Genova",
    "sg:city":"Genova",
    "sg:orig_category":"Riparazione Dei Mezzi Di Trasporto. Servizi Ausiliari Dei Mezzi Di Trasporto",
    "sg:phone":"+39 010 246 1127",
    "sg:postcode":"16128",
    "sg:province":"Genova",
    "wof:name":"Pizzorno & Lini (s.r.l.)",
    "wof:placetype":"venue"
},
  "geometry": {"coordinates":[8.938192,44.397606],"type":"Point"}
}