{
  "type": "Feature",
  "properties": {
    "addr:full":"Km. 9.750, Viale Monastir 09028 Sestu Sestu Cagliari 09028",
    "addr:postcode":"09028;09028",
    "addr:street":"Km. 9.750 Viale Monastir",
    "iso:country":"IT",
    "sg:address":"Km. 9.750, Viale Monastir 09028 Sestu",
    "sg:city":"Sestu",
    "sg:classifiers":[
        {
            "category":"Parking",
            "subcategory":"Lot",
            "type":"Transportation"
        }
    ],
    "sg:phone":"+39 390 702 2181",
    "sg:postcode":"09028",
    "sg:province":"Cagliari",
    "sg:tags":[
        "transport",
        "road"
    ],
    "wof:name":"Trasporti Isolani Srl",
    "wof:placetype":"venue"
},
  "geometry": {"coordinates":[9.109228,39.215458],"type":"Point"}
}