{
  "type": "Feature",
  "properties": {
    "addr:full":"54, Via Principessa Iolanda 10090 Foglizzo Foglizzo Torino 10090",
    "addr:postcode":"10090;10090",
    "addr:street":"Via Principessa Iolanda",
    "iso:country":"IT",
    "sg:address":"54, Via Principessa Iolanda 10090 Foglizzo",
    "sg:city":"Foglizzo",
    "sg:classifiers":[
        {
            "category":"Building & Trades",
            "subcategory":"Construction",
            "type":"Services"
        }
    ],
    "sg:phone":"+39 011 970 1834",
    "sg:postcode":"10090",
    "sg:province":"Torino",
    "sg:tags":[
        "work",
        "public"
    ],
    "wof:name":"Bitux S.r.l.",
    "wof:placetype":"venue"
},
  "geometry": {"coordinates":[7.686619,45.07056],"type":"Point"}
}