{
  "type": "Feature",
  "properties": {
    "iso:country":"IT",
    "sg:address":"33080 Porcia",
    "sg:city":"Porcia",
    "sg:orig_category":"Ristorazione E Locali Pubblici Affini. Servizi Ausiliari Di Ristorazione E Di Intrattenimento",
    "sg:phone":"+39 0434 361035",
    "sg:postcode":"33080",
    "sg:province":"Pordenone",
    "wof:name":"Coquina Floreani Di Floreani Annarosa",
    "wof:placetype":"venue"
},
  "geometry": {"coordinates":[12.620641,45.962475],"type":"Point"}
}