{
  "type": "Feature",
  "properties": {
    "iso:country":"IT",
    "sg:address":"49, Via Pontarola 35011 Campodarsego",
    "sg:city":"Campodarsego",
    "sg:classifiers":[
        {
            "category":"Home & Garden",
            "subcategory":"Home Furnishings",
            "type":"Retail Goods"
        }
    ],
    "sg:phone":"+39 049 920 0982",
    "sg:postcode":"35011",
    "sg:province":"Padova",
    "sg:tags":[
        "household"
    ],
    "wof:name":"Nuova Linea Valentini (s.r.l.)",
    "wof:placetype":"venue"
},
  "geometry": {"coordinates":[11.916875,45.480293],"type":"Point"}
}