{
  "type": "Feature",
  "properties": {
    "addr:full":"65013 Citta's.angelo Pescara 65013",
    "addr:postcode":"65013;65013",
    "iso:country":"IT",
    "sg:address":"65013 Citta's.angelo",
    "sg:orig_category":"Agricoltura, Orticoltura E Floricoltura. Articoli Da Regalo",
    "sg:phone":"+39 085 95387",
    "sg:postcode":"65013",
    "sg:province":"Pescara",
    "wof:name":"Martinelli Giancarlo",
    "wof:placetype":"venue"
},
  "geometry": {"coordinates":[14.140759,42.523209],"type":"Point"}
}