{
  "type": "Feature",
  "properties": {
    "iso:country":"IT",
    "sg:address":"16, Via Cantarane 25030 Barbariga",
    "sg:city":"Barbariga",
    "sg:classifiers":[
        {
            "category":"Real Estate",
            "subcategory":"Architect",
            "type":"Services"
        }
    ],
    "sg:phone":"+39 030 971 9276",
    "sg:postcode":"25030",
    "sg:province":"Brescia",
    "sg:tags":[
        "textile",
        "clothing"
    ],
    "wof:name":"Prestige Di Potieri Monica & C. S.n.c.",
    "wof:placetype":"venue"
},
  "geometry": {"coordinates":[10.050035,45.403122],"type":"Point"}
}