{
  "type": "Feature",
  "properties": {
    "addr:full":"Corso Mazzini 84; Marostica; 36063 Marostica Vicenza 36063",
    "addr:housenumber":"84",
    "addr:postcode":"36063;36063",
    "addr:street":"Corso Mazzini",
    "iso:country":"IT",
    "sg:address":"Corso Mazzini 84; Marostica; 36063",
    "sg:city":"Marostica",
    "sg:classifiers":[
        {
            "category":"Banks & Credit Unions",
            "subcategory":"Bank",
            "type":"Services"
        }
    ],
    "sg:phone":"+39 0424 488811",
    "sg:postcode":"36063",
    "sg:province":"Vicenza",
    "wof:name":"Banca Popolare Di Marostica",
    "wof:placetype":"venue"
},
  "geometry": {"coordinates":[11.654986,45.746353],"type":"Point"}
}