{
  "type": "Feature",
  "properties": {
    "addr:full":"07100 Sassari Sassari Sassari 07100",
    "addr:postcode":"07100;07100",
    "iso:country":"IT",
    "sg:address":"07100 Sassari",
    "sg:city":"Sassari",
    "sg:orig_category":"Prodotti Chimici Di Base",
    "sg:phone":"+39 079 260092",
    "sg:postcode":"07100",
    "sg:province":"Sassari",
    "wof:name":"Macciocu Giuseppe & C. S.n.c.",
    "wof:placetype":"venue"
},
  "geometry": {"coordinates":[8.3745718002,40.7555809021],"type":"Point"}
}