{
  "type": "Feature",
  "properties": {
    "iso:country":"IT",
    "sg:address":"Via Gavazzeni 68a 23018 Talamona",
    "sg:city":"Talamona",
    "sg:classifiers":[
        {
            "category":"Shopping",
            "subcategory":"Computers & Home Electronics",
            "type":"Retail Goods"
        }
    ],
    "sg:phone":"+39 0342 670670",
    "sg:postcode":"23018",
    "sg:province":"Sondrio",
    "sg:tags":[
        "industrial",
        "power"
    ],
    "wof:name":"Em Elettrotecnica Srl",
    "wof:placetype":"venue"
},
  "geometry": {"coordinates":[9.6157712936,46.1401023865],"type":"Point"}
}