{
  "type": "Feature",
  "properties": {
    "iso:country":"IT",
    "sg:address":"22070 Appiano Gentile",
    "sg:city":"Appiano Gentile",
    "sg:orig_category":"Servizi E Lavori Per Edilizia E Lavori Pubblici. Servizi Ausiliari Di Sorveglianza, Manutenzione E Pulizia",
    "sg:phone":"+39 031 933947",
    "sg:postcode":"22070",
    "sg:province":"Como",
    "wof:name":"Arrigoni Flavio Termoidraulica",
    "wof:placetype":"venue"
},
  "geometry": {"coordinates":[8.979852,45.738609],"type":"Point"}
}