{
  "type": "Feature",
  "properties": {
    "iso:country":"IT",
    "sg:address":"19, Via Ca' Dell' Orbo 40055 Castenaso",
    "sg:city":"Castenaso",
    "sg:classifiers":[
        {
            "category":"Manufacturing",
            "subcategory":"Metals",
            "type":"Manufacturing & Wholesale Goods"
        }
    ],
    "sg:phone":"+39 39051780019",
    "sg:postcode":"40055",
    "sg:province":"Bologna",
    "sg:tags":[
        "processing"
    ],
    "wof:name":"Tim Processi Termici (s.r.l.)",
    "wof:placetype":"venue"
},
  "geometry": {"coordinates":[11.4415025711,44.51197052],"type":"Point"}
}