{
  "type": "Feature",
  "properties": {
    "addr:full":"34121 Trieste Trieste Trieste 34121",
    "addr:postcode":"34121;34121",
    "iso:country":"IT",
    "sg:address":"34121 Trieste",
    "sg:city":"Trieste",
    "sg:orig_category":"Servizi Per Aziende, Manifestazioni E Supporto Agli Scambi Commerciali",
    "sg:phone":"+39 040 372 4638",
    "sg:postcode":"34121",
    "sg:province":"Trieste",
    "wof:name":"Monte Investigazioni Sas",
    "wof:placetype":"venue"
},
  "geometry": {"coordinates":[13.771352,45.648792],"type":"Point"}
}