{
  "type": "Feature",
  "properties": {
    "iso:country":"IT",
    "sg:address":"61032 Fano",
    "sg:city":"Bellocchi",
    "sg:orig_category":"Box Prefabbricati",
    "sg:phone":"+39 0721 855650",
    "sg:postcode":"61032",
    "sg:province":"Pesaro E Urbino",
    "sg:website":"http://www.mdue.it",
    "wof:name":"Emmedue Srl",
    "wof:placetype":"venue"
},
  "geometry": {"coordinates":[13.004723,43.78616],"type":"Point"}
}