{
  "type": "Feature",
  "properties": {
    "iso:country":"IT",
    "sg:address":"49, Strada Padana Superiore 20063 Cernusco Sul Naviglio",
    "sg:city":"Cernusco sul Naviglio",
    "sg:classifiers":[
        {
            "category":"Manufacturing",
            "subcategory":"Rubber & Plastics",
            "type":"Manufacturing & Wholesale Goods"
        }
    ],
    "sg:phone":"+39 02 9210 6853",
    "sg:postcode":"20063",
    "sg:province":"Milano",
    "wof:name":"Rapisarda Antonio & C. (s.p.a.)",
    "wof:placetype":"venue"
},
  "geometry": {"coordinates":[9.2936563492,45.5129852295],"type":"Point"}
}