{
  "type": "Feature",
  "properties": {
    "iso:country":"IT",
    "sg:address":"95121 Catania",
    "sg:city":"Catania",
    "sg:orig_category":"Elettrotecnica Industriale, Prodotti E Apparecchiature",
    "sg:phone":"+39 095 456972",
    "sg:postcode":"95121",
    "sg:province":"Catania",
    "wof:name":"S.i.e.m. Di Tabita Giuseppe",
    "wof:placetype":"venue"
},
  "geometry": {"coordinates":[15.062243,37.495735],"type":"Point"}
}