{
  "type": "Feature",
  "properties": {
    "iso:country":"IT",
    "sg:address":"20091 Bresso",
    "sg:city":"Bresso",
    "sg:orig_category":"Bombole Metalliche",
    "sg:phone":"+39 02 240 4370",
    "sg:postcode":"20091",
    "sg:province":"Milano",
    "wof:name":"Fina Cosimo Srl",
    "wof:placetype":"venue"
},
  "geometry": {"coordinates":[9.20419,45.532909],"type":"Point"}
}