{
  "type": "Feature",
  "properties": {
    "iso:country":"IT",
    "sg:address":"9, Via Noalese Sud 30033 Noale",
    "sg:city":"Noale",
    "sg:classifiers":[
        {
            "category":"Shopping",
            "subcategory":"Clothing, Apparel, & Fashions",
            "type":"Retail Goods"
        }
    ],
    "sg:phone":"+39 39041442140",
    "sg:postcode":"30033",
    "sg:province":"Venezia",
    "sg:tags":[
        "clothes"
    ],
    "wof:name":"Vallese Romolo",
    "wof:placetype":"venue"
},
  "geometry": {"coordinates":[12.059041,45.537525],"type":"Point"}
}