{
  "type": "Feature",
  "properties": {
    "iso:country":"IT",
    "sg:address":"20121 Milano",
    "sg:city":"Milano",
    "sg:orig_category":"Banche E Servizi Finanziari",
    "sg:phone":"+39 02 880 0091",
    "sg:postcode":"20121",
    "sg:province":"Milano",
    "sg:website":"http://www.axa-im.it",
    "wof:name":"Axa Im Italia Spa",
    "wof:placetype":"venue"
},
  "geometry": {"coordinates":[9.184167,45.468521],"type":"Point"}
}