{
  "type": "Feature",
  "properties": {
    "iso:country":"IT",
    "sg:address":"25123 Brescia",
    "sg:city":"Brescia",
    "sg:orig_category":"Calzature, Pelletterie E Pelli",
    "sg:phone":"+39 030 336 7474",
    "sg:postcode":"25123",
    "sg:province":"Brescia",
    "wof:name":"Ragni Romualdo",
    "wof:placetype":"venue"
},
  "geometry": {"coordinates":[10.253435,45.54287],"type":"Point"}
}