{
  "type": "Feature",
  "properties": {
    "iso:country":"IT",
    "sg:address":"Via Brescia 25020 Gambara",
    "sg:city":"Gambara",
    "sg:classifiers":[
        {
            "category":"Manufacturing",
            "subcategory":"Rubber & Plastics",
            "type":"Manufacturing & Wholesale Goods"
        }
    ],
    "sg:phone":"+39 030 995 6079",
    "sg:postcode":"25020",
    "sg:province":"Brescia",
    "wof:name":"Garden (s.r.l.)",
    "wof:placetype":"venue"
},
  "geometry": {"coordinates":[10.2853403091,45.2649154663],"type":"Point"}
}