{
  "type": "Feature",
  "properties": {
    "iso:country":"IT",
    "sg:address":"98121 Messina",
    "sg:city":"Messina",
    "sg:orig_category":"Forniture Per Agricoltura E Zootecnia. Animali Domestici",
    "sg:phone":"+39 090 40251",
    "sg:postcode":"98121",
    "sg:province":"Messina",
    "wof:name":"Geni S.a.s.",
    "wof:placetype":"venue"
},
  "geometry": {"coordinates":[15.5589933395,38.2027893066],"type":"Point"}
}