{
  "type": "Feature",
  "properties": {
    "addr:full":"23900 Lecco Lecco Lecco 23900",
    "addr:postcode":"23900;23900",
    "iso:country":"IT",
    "sg:address":"23900 Lecco",
    "sg:city":"Lecco",
    "sg:orig_category":"Ortopedia - Articoli",
    "sg:phone":"+39 0341 362266",
    "sg:postcode":"23900",
    "sg:province":"Lecco",
    "wof:name":"Di Martino Snc Di Mariano & Giovanni Di Martino",
    "wof:placetype":"venue"
},
  "geometry": {"coordinates":[9.392384,45.853287],"type":"Point"}
}