{
  "type": "Feature",
  "properties": {
    "addr:full":"05100 Terni Terni Terni 05100",
    "addr:postcode":"05100;05100",
    "iso:country":"IT",
    "sg:address":"05100 Terni",
    "sg:city":"Terni",
    "sg:orig_category":"Agenzie D'affari E Servizi Commerciali",
    "sg:phone":"+39 800 117 766",
    "sg:postcode":"05100",
    "sg:province":"Terni",
    "wof:name":"Pec - Pronto Emergenza Casa Srl",
    "wof:placetype":"venue"
},
  "geometry": {"coordinates":[12.644587,42.569992],"type":"Point"}
}