{
  "type": "Feature",
  "properties": {
    "iso:country":"IT",
    "sg:address":"70123 Bari",
    "sg:city":"Bari",
    "sg:orig_category":"Trattamenti Termici E Superficiali Metalli, Galvanotecnica",
    "sg:phone":"+39 080 506 1805",
    "sg:postcode":"70123",
    "sg:province":"Bari",
    "wof:name":"De Lena M. Di Vittorio De Lena",
    "wof:placetype":"venue"
},
  "geometry": {"coordinates":[16.821033,41.110607],"type":"Point"}
}