{
  "type": "Feature",
  "properties": {
    "iso:country":"IT",
    "sg:address":"66030 Filetto",
    "sg:city":"Filetto",
    "sg:orig_category":"Elettrotecnica Industriale, Prodotti E Apparecchiature. Ricambi E Componenti Dei Mezzi Di Trasporto",
    "sg:phone":"+39 0871 86403",
    "sg:postcode":"66030",
    "sg:province":"Chieti",
    "wof:name":"Faba Batterie",
    "wof:placetype":"venue"
},
  "geometry": {"coordinates":[14.246111,42.229221],"type":"Point"}
}