{
  "type": "Feature",
  "properties": {
    "addr:full":"25010 Borgosatollo Borgosatollo Brescia 25010",
    "addr:postcode":"25010;25010",
    "iso:country":"IT",
    "sg:address":"25010 Borgosatollo",
    "sg:city":"Borgosatollo",
    "sg:orig_category":"Materiali Edili",
    "sg:phone":"+39 030 250 0254",
    "sg:postcode":"25010",
    "sg:province":"Brescia",
    "wof:name":"S.i.r. Impianti (s.r.l.)",
    "wof:placetype":"venue"
},
  "geometry": {"coordinates":[10.252937,45.477104],"type":"Point"}
}