{
  "type": "Feature",
  "properties": {
    "iso:country":"IT",
    "sg:address":"46040 Soave",
    "sg:orig_category":"Macchine, Impianti Ed Attrezzature Per Industria Alimentare E Bevande. Apparecchiature E Sistemi Per Imballaggio E Confezionamento",
    "sg:phone":"+39 0376 300525",
    "sg:postcode":"46040",
    "sg:province":"Mantova",
    "wof:name":"Mutti Alberto",
    "wof:placetype":"venue"
},
  "geometry": {"coordinates":[10.722226,45.194637],"type":"Point"}
}