{
  "type": "Feature",
  "properties": {
    "iso:country":"IT",
    "sg:address":"90146 Palermo",
    "sg:city":"Palermo",
    "sg:orig_category":"Telecomunicazioni E Telefonia, Impianti, Apparecchi E Servizi",
    "sg:phone":"+39 091 671 0715",
    "sg:postcode":"90146",
    "sg:province":"Palermo",
    "sg:website":"http://www.sicilianatel.it",
    "wof:name":"Si.tel. Srl Siciliana Telecomunicazioni",
    "wof:placetype":"venue"
},
  "geometry": {"coordinates":[13.31193,38.17141],"type":"Point"}
}