{
  "type": "Feature",
  "properties": {
    "iso:country":"IT",
    "sg:address":"Via Vignazzola 125/a 20036 Meda",
    "sg:city":"Meda",
    "sg:orig_category":"Heat Exchanger Manufacturing Machines",
    "sg:phone":"+39 036 233 8020",
    "sg:postcode":"20036",
    "sg:province":"Milano",
    "wof:name":"Cms Costruzione Macchine Speciali S.r.l.",
    "wof:placetype":"venue"
},
  "geometry": {"coordinates":[9.188141,45.463688],"type":"Point"}
}