{
  "type": "Feature",
  "properties": {
    "iso:country":"IT",
    "sg:address":"00145 Roma",
    "sg:city":"Roma",
    "sg:orig_category":"Prodotti Finiti Stampati. Servizi Editoriali. Tempo Libero - Articoli E Forniture",
    "sg:phone":"+39 06 541 7291",
    "sg:postcode":"00145",
    "sg:province":"Roma",
    "wof:name":"Italtop S.r.l.",
    "wof:placetype":"venue"
},
  "geometry": {"coordinates":[12.4809789658,41.8570594788],"type":"Point"}
}