{
  "type": "Feature",
  "properties": {
    "iso:country":"IT",
    "sg:address":"00045 Genzano Di Roma",
    "sg:city":"Genzano di Roma",
    "sg:orig_category":"Ricambi E Componenti Dei Mezzi Di Trasporto",
    "sg:phone":"+39 06 939 8426",
    "sg:postcode":"00045",
    "sg:province":"Roma",
    "wof:name":"Mancini Fausto",
    "wof:placetype":"venue"
},
  "geometry": {"coordinates":[12.696568,41.698734],"type":"Point"}
}