{
  "type": "Feature",
  "properties": {
    "iso:country":"IT",
    "sg:address":"25060 Polaveno",
    "sg:city":"Polaveno",
    "sg:orig_category":"Metalli E Leghe",
    "sg:phone":"+39 030 84026",
    "sg:postcode":"25060",
    "sg:province":"Brescia",
    "wof:name":"Eredi Bonomini",
    "wof:placetype":"venue"
},
  "geometry": {"coordinates":[10.2256002426,45.5868492126],"type":"Point"}
}