{
  "type": "Feature",
  "properties": {
    "addr:full":"Via San Donato 21/b 50127 Firenze Firenze Firenze 50127",
    "addr:housenumber":"21 / b",
    "addr:postcode":"50127;50127",
    "addr:street":"Via San Donato",
    "iso:country":"IT",
    "sg:address":"Via San Donato 21/b 50127 Firenze",
    "sg:city":"Firenze",
    "sg:classifiers":[
        {
            "category":"Retail",
            "subcategory":"Laundry & Dry Cleaning",
            "type":"Services"
        }
    ],
    "sg:phone":"+39 055 360014",
    "sg:postcode":"50127",
    "sg:province":"Firenze",
    "sg:tags":[
        "felt",
        "clothing"
    ],
    "wof:name":"Buonriposi Feltri Sas",
    "wof:placetype":"venue"
},
  "geometry": {"coordinates":[11.2205896378,43.5380554199],"type":"Point"}
}