{
  "type": "Feature",
  "properties": {
    "iso:country":"IT",
    "sg:address":"20141 Milano",
    "sg:city":"Milano",
    "sg:orig_category":"Affilatrici",
    "sg:phone":"+39 02 843 9425",
    "sg:postcode":"20141",
    "sg:province":"Milano",
    "wof:name":"A.g.m. Sas Di Andini A. & C.",
    "wof:placetype":"venue"
},
  "geometry": {"coordinates":[9.181416,45.441975],"type":"Point"}
}