{
  "type": "Feature",
  "properties": {
    "addr:full":"10156 Torino Torino Torino 10156",
    "addr:postcode":"10156;10156",
    "iso:country":"IT",
    "sg:address":"10156 Torino",
    "sg:city":"Torino",
    "sg:orig_category":"Macchine Utensili E Impianti. Apparecchiature Ed Attrezzature Meccaniche",
    "sg:phone":"+39 011 470 4615",
    "sg:postcode":"10156",
    "sg:province":"Torino",
    "sg:website":"http://www.siaforni.com",
    "wof:name":"Sia Forni Srl",
    "wof:placetype":"venue"
},
  "geometry": {"coordinates":[7.70615,45.119347],"type":"Point"}
}