{
  "type": "Feature",
  "properties": {
    "iso:country":"IT",
    "sg:address":"28010 Gargallo",
    "sg:city":"Gargallo",
    "sg:orig_category":"Metalli E Leghe",
    "sg:phone":"+39 0322 955100",
    "sg:postcode":"28010",
    "sg:province":"Novara",
    "wof:name":"Surace Massimiliano",
    "wof:placetype":"venue"
},
  "geometry": {"coordinates":[8.4269714355,45.7314910889],"type":"Point"}
}