{
  "type": "Feature",
  "properties": {
    "addr:full":"80026 Casoria Casoria Napoli 80026",
    "addr:postcode":"80026;80026",
    "iso:country":"IT",
    "sg:address":"80026 Casoria",
    "sg:city":"Casoria",
    "sg:orig_category":"Elettronica Professionale E Di Consumo. Tempo Libero - Articoli E Forniture",
    "sg:phone":"+39 081 774 6892",
    "sg:postcode":"80026",
    "sg:province":"Napoli",
    "wof:name":"Arca Giochi Sas",
    "wof:placetype":"venue"
},
  "geometry": {"coordinates":[14.335067,40.886471],"type":"Point"}
}