{
  "type": "Feature",
  "properties": {
    "addr:full":"12, Via Del Ponte 48100 Ravenna Ravenna Ravenna 48100",
    "addr:postcode":"48100;48100",
    "addr:street":"Via Del Ponte",
    "iso:country":"IT",
    "sg:address":"12, Via Del Ponte 48100 Ravenna",
    "sg:city":"Ravenna",
    "sg:classifiers":[
        {
            "category":"Building & Trades",
            "subcategory":"Construction",
            "type":"Services"
        }
    ],
    "sg:phone":"+39 0544 450307",
    "sg:postcode":"48100",
    "sg:province":"Ravenna",
    "sg:tags":[
        "work",
        "public"
    ],
    "wof:name":"Societa' Industriale Lavori Marittimi (s.r.l.)",
    "wof:placetype":"venue"
},
  "geometry": {"coordinates":[12.21884,44.275204],"type":"Point"}
}