{
  "type": "Feature",
  "properties": {
    "iso:country":"IT",
    "sg:address":"Via Puccini 1; Vigonovo Di Fontanafredda",
    "sg:classifiers":[
        {
            "category":"Banks & Credit Unions",
            "subcategory":"Bank",
            "type":"Services"
        }
    ],
    "sg:phone":"+39 0434 565024",
    "wof:name":"Banca Popolare Friuladria",
    "wof:placetype":"venue"
},
  "geometry": {"coordinates":[12.547318,45.989082],"type":"Point"}
}