{
  "type": "Feature",
  "properties": {
    "addr:full":"39, Via Ungaretti 20090 Opera Opera Milano 20090",
    "addr:postcode":"20090;20090",
    "addr:street":"Via Ungaretti",
    "iso:country":"IT",
    "sg:address":"39, Via Ungaretti 20090 Opera",
    "sg:city":"Opera",
    "sg:classifiers":[
        {
            "category":"Shopping",
            "subcategory":"Stationery & Office Supplies",
            "type":"Retail Goods"
        }
    ],
    "sg:phone":"+39 02 5760 6520",
    "sg:postcode":"20090",
    "sg:province":"Milano",
    "sg:tags":[
        "professional"
    ],
    "wof:name":"Euroscaff (s.r.l.)",
    "wof:placetype":"venue"
},
  "geometry": {"coordinates":[9.2227373123,45.3796768188],"type":"Point"}
}