{
  "type": "Feature",
  "properties": {
    "iso:country":"IT",
    "sg:address":"83047 Lioni",
    "sg:city":"Lioni",
    "sg:orig_category":"Vetro: Prodotti E Lavorazioni. Forniture Industriali Per Prevenzione, Controllo E Sicurezza",
    "sg:phone":"+39 0827 270187",
    "sg:postcode":"83047",
    "sg:province":"Avellino",
    "wof:name":"Lettieri Rocco",
    "wof:placetype":"venue"
},
  "geometry": {"coordinates":[15.184381,40.860214],"type":"Point"}
}