{
  "type": "Feature",
  "properties": {
    "iso:country":"IT",
    "sg:address":"161, Via Mazzini Giuseppe 15067 Novi Ligure",
    "sg:city":"Novi Ligure",
    "sg:classifiers":[
        {
            "category":"Wholesale",
            "subcategory":"Medical Equipment & Supplies",
            "type":"Manufacturing & Wholesale Goods"
        }
    ],
    "sg:phone":"+39 390 143 2148",
    "sg:postcode":"15067",
    "sg:province":"Alessandria",
    "sg:tags":[
        "-",
        "health",
        "instrument"
    ],
    "wof:name":"Industria Zingardi (s.r.l.)",
    "wof:placetype":"venue"
},
  "geometry": {"coordinates":[8.789386,44.770988],"type":"Point"}
}