{
  "type": "Feature",
  "properties": {
    "iso:country":"IT",
    "sg:address":"Via Vandalino 10 10095 Grugliasco",
    "sg:city":"Grugliasco",
    "sg:classifiers":[
        {
            "category":"Manufacturing",
            "subcategory":"Tools & Machinery",
            "type":"Manufacturing & Wholesale Goods"
        }
    ],
    "sg:phone":"+39 011 411 8078",
    "sg:postcode":"10095",
    "sg:province":"Torino",
    "sg:tags":[
        "machine"
    ],
    "wof:name":"Le.mac Sas Di Cecconi G. & C.",
    "wof:placetype":"venue"
},
  "geometry": {"coordinates":[7.607072,45.071232],"type":"Point"}
}