{
  "type": "Feature",
  "properties": {
    "iso:country":"IT",
    "sg:address":"30124 Venezia",
    "sg:city":"San Marco",
    "sg:orig_category":"Tappeti Persiani Ed Orientali",
    "sg:phone":"+39 041 522 4736",
    "sg:postcode":"30124",
    "sg:province":"Venezia",
    "wof:name":"Rascid Rahaim & C.",
    "wof:placetype":"venue"
},
  "geometry": {"coordinates":[12.333602,45.434242],"type":"Point"}
}