{
  "type": "Feature",
  "properties": {
    "iso:country":"IT",
    "sg:address":"Strada Vigevanese Barbattola 20083 Gaggiano",
    "sg:city":"Gaggiano",
    "sg:classifiers":[
        {
            "category":"Sports & Exercise",
            "subcategory":"Playing Field",
            "type":"Entertainment"
        }
    ],
    "sg:phone":"+39 39029086545",
    "sg:postcode":"20083",
    "sg:province":"Milano",
    "sg:tags":[
        "game"
    ],
    "wof:name":"Hamer Line S.r.l.",
    "wof:placetype":"venue"
},
  "geometry": {"coordinates":[9.188141,45.463688],"type":"Point"}
}