{
  "type": "Feature",
  "properties": {
    "iso:country":"IT",
    "sg:address":"20024 Garbagnate Milanese",
    "sg:city":"Garbagnate Milanese",
    "sg:orig_category":"Ospedali E Servizi Sanitari",
    "sg:phone":"+39 02 9902 7211",
    "sg:postcode":"20024",
    "sg:province":"Milano",
    "wof:name":"Squadra Emergenza Operativa",
    "wof:placetype":"venue"
},
  "geometry": {"coordinates":[9.087238,45.580246],"type":"Point"}
}