{
  "type": "Feature",
  "properties": {
    "addr:full":"Via Podgora 7 21049 Tradate Tradate Varese 21049",
    "addr:housenumber":"7",
    "addr:postcode":"21049;21049",
    "addr:street":"Via Podgora",
    "iso:country":"IT",
    "sg:address":"Via Podgora 7 21049 Tradate",
    "sg:city":"Tradate",
    "sg:orig_category":"Motor-actuated Cylinders",
    "sg:phone":"+39 0331 849149",
    "sg:postcode":"21049",
    "sg:province":"Varese",
    "sg:website":"www.cortellezziprimo.it",
    "wof:name":"Primo Cortellezzi & C. Srl",
    "wof:placetype":"venue"
},
  "geometry": {"coordinates":[8.9151754379,45.7036247253],"type":"Point"}
}