{
  "type": "Feature",
  "properties": {
    "iso:country":"IT",
    "sg:address":"Via Fidelina 53 20061 Carugate",
    "sg:city":"Carugate",
    "sg:classifiers":[
        {
            "category":"Home & Garden",
            "subcategory":"Home Furnishings",
            "type":"Retail Goods"
        }
    ],
    "sg:phone":"+39 02 9215 0107",
    "sg:postcode":"20061",
    "sg:province":"Milano",
    "sg:tags":[
        "interior",
        "decoration"
    ],
    "wof:name":"Ac 3 Arredamenti S.r.l.",
    "wof:placetype":"venue"
},
  "geometry": {"coordinates":[9.345357,45.556648],"type":"Point"}
}