{
  "type": "Feature",
  "properties": {
    "iso:country":"IT",
    "sg:address":"60123 Ancona",
    "sg:city":"Ancona",
    "sg:orig_category":"Scuole Di Lingue",
    "sg:phone":"+39 071 207 1289",
    "sg:postcode":"60123",
    "sg:province":"Ancona",
    "sg:website":"http://www.sspiov-an.net",
    "wof:name":"Centro Linguistico Kompass",
    "wof:placetype":"venue"
},
  "geometry": {"coordinates":[13.527785,43.618553],"type":"Point"}
}