{
  "type": "Feature",
  "properties": {
    "iso:country":"IT",
    "sg:address":"9, Via Dell' Acqua 20050 Triuggio",
    "sg:city":"Triuggio",
    "sg:classifiers":[
        {
            "category":"Professional",
            "subcategory":"Business Services",
            "type":"Services"
        }
    ],
    "sg:phone":"+39 036 299 7752",
    "sg:postcode":"20050",
    "sg:province":"Milano",
    "sg:tags":[
        "advice"
    ],
    "wof:name":"Solaris Societa' Lavoro E Riabilitazione A.r.l.",
    "wof:placetype":"venue"
},
  "geometry": {"coordinates":[9.268272,45.655617],"type":"Point"}
}