{
  "type": "Feature",
  "properties": {
    "iso:country":"IT",
    "sg:address":"12, V. Friuli Venezia Giulia59014 Prato",
    "sg:classifiers":[
        {
            "category":"Real Estate",
            "subcategory":"Surveying",
            "type":"Services"
        }
    ],
    "sg:phone":"+39 0574 624322",
    "sg:tags":[
        "equipment",
        "material",
        "good",
        "-",
        "handling"
    ],
    "sg:website":"http://www.simi-srl.it",
    "wof:name":"S.i.m.i. Srl",
    "wof:placetype":"venue"
},
  "geometry": {"coordinates":[11.051665,43.859509],"type":"Point"}
}