{
  "type": "Feature",
  "properties": {
    "iso:country":"IT",
    "sg:address":"19021 Arcola",
    "sg:city":"Arcola",
    "sg:orig_category":"Carpenterie Ferro",
    "sg:phone":"+39 0187 955069",
    "sg:postcode":"19021",
    "sg:province":"La Spezia",
    "wof:name":"Metalmac Srl",
    "wof:placetype":"venue"
},
  "geometry": {"coordinates":[9.919858,44.115673],"type":"Point"}
}