{
  "type": "Feature",
  "properties": {
    "addr:full":"35028 Piove Di Sacco Piove di Sacco Padova 35028",
    "addr:postcode":"35028;35028",
    "iso:country":"IT",
    "sg:address":"35028 Piove Di Sacco",
    "sg:city":"Piove di Sacco",
    "sg:orig_category":"Forniture Per Abbigliamento E Pelletterie",
    "sg:phone":"+39 049 972 5464",
    "sg:postcode":"35028",
    "sg:province":"Padova",
    "wof:name":"Tacchificio 3 C (s.n.c.)",
    "wof:placetype":"venue"
},
  "geometry": {"coordinates":[12.0777330399,45.3232269287],"type":"Point"}
}