{
  "type": "Feature",
  "properties": {
    "addr:full":"Via Moro A. 70018 Rutigliano Rutigliano Bari 70018",
    "addr:postcode":"70018;70018",
    "addr:street":"Via Moro A.",
    "iso:country":"IT",
    "sg:address":"Via Moro A. 70018 Rutigliano",
    "sg:city":"Rutigliano",
    "sg:classifiers":[
        {
            "category":"Farming",
            "subcategory":"Livestock Farm",
            "type":"Manufacturing & Wholesale Goods"
        }
    ],
    "sg:phone":"+39 080 476 8730",
    "sg:postcode":"70018",
    "sg:province":"Bari",
    "sg:tags":[
        "agriculture"
    ],
    "wof:name":"Iko Hydro (s.r.l.)",
    "wof:placetype":"venue"
},
  "geometry": {"coordinates":[17.009438,41.009766],"type":"Point"}
}