{
  "type": "Feature",
  "properties": {
    "iso:country":"IT",
    "sg:address":"21011 Casorate Sempione",
    "sg:city":"Casorate Sempione",
    "sg:orig_category":"Tessuti Arredamento, Tende E Tappeti",
    "sg:phone":"+39 0331 296545",
    "sg:postcode":"21011",
    "sg:province":"Varese",
    "wof:name":"D.g. Di Dettoni Giuseppe",
    "wof:placetype":"venue"
},
  "geometry": {"coordinates":[8.739934,45.675858],"type":"Point"}
}