{
  "type": "Feature",
  "properties": {
    "iso:country":"IT",
    "sg:address":"73100 Lecce",
    "sg:city":"Lecce",
    "sg:orig_category":"Amianto - Bonifica E Smantellamento",
    "sg:phone":"+39 0832 240735",
    "sg:postcode":"73100",
    "sg:province":"Lecce",
    "wof:name":"Central Service Srl",
    "wof:placetype":"venue"
},
  "geometry": {"coordinates":[18.175745,40.351318],"type":"Point"}
}