{
  "type": "Feature",
  "properties": {
    "iso:country":"IT",
    "sg:address":"36078 Valdagno",
    "sg:city":"Piana",
    "sg:orig_category":"Abbigliamento Esterno, Maglierie E Pelliccerie. Calzature, Pelletterie E Pelli. Sport - Articoli E Forniture",
    "sg:phone":"+39 0445 430370",
    "sg:postcode":"36078",
    "sg:province":"Vicenza",
    "wof:name":"Emmepi",
    "wof:placetype":"venue"
},
  "geometry": {"coordinates":[11.311114,45.623646],"type":"Point"}
}