{
  "type": "Feature",
  "properties": {
    "addr:full":"Via Repubblica 29019 San Giorgio Piacentino San Giorgio Piacentino Piacenza 29019",
    "addr:postcode":"29019;piacentino;29019",
    "addr:street":"Via Repubblica",
    "iso:country":"IT",
    "sg:address":"Via Repubblica 29019 San Giorgio Piacentino",
    "sg:city":"San Giorgio Piacentino",
    "sg:classifiers":[
        {
            "category":"Real Estate",
            "subcategory":"Architect",
            "type":"Services"
        }
    ],
    "sg:phone":"+39 0523 370811",
    "sg:postcode":"29019",
    "sg:province":"Piacenza",
    "sg:tags":[
        "textile",
        "clothing"
    ],
    "wof:name":"Maggi Group S.r.l.",
    "wof:placetype":"venue"
},
  "geometry": {"coordinates":[9.723333,44.913055],"type":"Point"}
}