{
  "type": "Feature",
  "properties": {
    "iso:country":"IT",
    "sg:address":"98, Vl. Della Vittoria 92024 Canicatti'",
    "sg:classifiers":[
        {
            "category":"Food & Beverages",
            "subcategory":"Groceries & Convenience Stores",
            "type":"Retail Goods"
        }
    ],
    "sg:phone":"+39 0922 851104",
    "sg:postcode":"92024",
    "sg:province":"Agrigento",
    "sg:tags":[
        "drink"
    ],
    "sg:website":"http://www.paginegialle.it/enotecalabotte",
    "wof:name":"Enoteca La Botte Import Export",
    "wof:placetype":"venue"
},
  "geometry": {"coordinates":[13.843911,37.352833],"type":"Point"}
}