{
  "type": "Feature",
  "properties": {
    "iso:country":"IT",
    "sg:address":"50041 Calenzano",
    "sg:city":"Calenzano",
    "sg:orig_category":"Serigrafia",
    "sg:phone":"+39 055 887 6198",
    "sg:postcode":"50041",
    "sg:province":"Firenze",
    "sg:website":"http://www.gmcompanies.com",
    "wof:name":"Monzoni Alessandro",
    "wof:placetype":"venue"
},
  "geometry": {"coordinates":[11.1618,43.848099],"type":"Point"}
}