{
  "type": "Feature",
  "properties": {
    "iso:country":"IT",
    "sg:address":"00043 Ciampino",
    "sg:city":"Ciampino",
    "sg:orig_category":"Macchine Utensili E Impianti",
    "sg:phone":"+39 06 791 9243",
    "sg:postcode":"00043",
    "sg:province":"Roma",
    "wof:name":"Fiums (s.r.l.)",
    "wof:placetype":"venue"
},
  "geometry": {"coordinates":[12.599219,41.79874],"type":"Point"}
}