{
  "type": "Feature",
  "properties": {
    "iso:country":"IT",
    "sg:address":"6, Via Dei Lanzi 57123 Livorno",
    "sg:city":"Livorno",
    "sg:classifiers":[
        {
            "category":"Banks & Credit Unions",
            "subcategory":"Investment Brokerage",
            "type":"Services"
        }
    ],
    "sg:phone":"+39 0586 899144",
    "sg:postcode":"57123",
    "sg:province":"Livorno",
    "sg:tags":[
        "-",
        "transport",
        "related"
    ],
    "wof:name":"Bartolini Fratelli (s.n.c.)",
    "wof:placetype":"venue"
},
  "geometry": {"coordinates":[10.30987,43.548237],"type":"Point"}
}