{
  "type": "Feature",
  "properties": {
    "addr:full":"20043 Arcore Arcore Milano 20043",
    "addr:postcode":"20043;20043",
    "iso:country":"IT",
    "sg:address":"20043 Arcore",
    "sg:city":"Arcore",
    "sg:orig_category":"Elettrotecnica Industriale, Prodotti E Apparecchiature. Elettronica Industriale, Prodotti E Apparecchiature",
    "sg:phone":"+39 039 601 4821",
    "sg:postcode":"20043",
    "sg:province":"Milano",
    "sg:website":"http://www.visionsys.it",
    "wof:name":"Vision Srl",
    "wof:placetype":"venue"
},
  "geometry": {"coordinates":[9.326173,45.632385],"type":"Point"}
}