{
  "type": "Feature",
  "properties": {
    "iso:country":"IT",
    "sg:address":"Via Monte Bisbino 56 20021 Bollate",
    "sg:city":"Bollate",
    "sg:classifiers":[
        {
            "category":"Wholesale",
            "subcategory":"Vending Machines",
            "type":"Manufacturing & Wholesale Goods"
        }
    ],
    "sg:phone":"+39 02 356961",
    "sg:postcode":"20021",
    "sg:province":"Milano",
    "sg:tags":[
        "aluminium",
        "working"
    ],
    "sg:website":"www.tekna.it",
    "wof:name":"Tekna Srl",
    "wof:placetype":"venue"
},
  "geometry": {"coordinates":[9.106105,45.524544],"type":"Point"}
}