{
  "type": "Feature",
  "properties": {
    "addr:full":"80024 Cardito Cardito Napoli 80024",
    "addr:postcode":"80024;80024",
    "iso:country":"IT",
    "sg:address":"80024 Cardito",
    "sg:city":"Cardito",
    "sg:orig_category":"Prodotti Alimentari",
    "sg:phone":"+39 081 831 7707",
    "sg:postcode":"80024",
    "sg:province":"Napoli",
    "wof:name":"Caseificio Delle Rose Di Salvatore Corso",
    "wof:placetype":"venue"
},
  "geometry": {"coordinates":[14.2844409943,40.9373130798],"type":"Point"}
}