{
  "type": "Feature",
  "properties": {
    "addr:full":"93100 Terrapelata Caltanissetta 93100",
    "addr:postcode":"93100;93100",
    "iso:country":"IT",
    "sg:address":"93100 Terrapelata",
    "sg:orig_category":"Trasporti E Spedizioni Merci",
    "sg:phone":"+39 0934 566283",
    "sg:postcode":"93100",
    "sg:province":"Caltanissetta",
    "wof:name":"Bartolini Spa",
    "wof:placetype":"venue"
},
  "geometry": {"coordinates":[14.06329,37.48991],"type":"Point"}
}