{
  "type": "Feature",
  "properties": {
    "iso:country":"IT",
    "sg:address":"24066 Pedrengo",
    "sg:city":"Pedrengo",
    "sg:orig_category":"Antifurto",
    "sg:phone":"+39 035 656252",
    "sg:postcode":"24066",
    "sg:province":"Bergamo",
    "sg:website":"http://www.albaelettronic.it",
    "wof:name":"Alba Elettronic Srl",
    "wof:placetype":"venue"
},
  "geometry": {"coordinates":[9.747564,45.693436],"type":"Point"}
}