{
  "type": "Feature",
  "properties": {
    "addr:full":"00175 Roma Roma Roma 00175",
    "addr:postcode":"00175;00175",
    "iso:country":"IT",
    "sg:address":"00175 Roma",
    "sg:city":"Roma",
    "sg:orig_category":"Cooperative Produzione, Lavoro E Servizi",
    "sg:phone":"+39 06 764213",
    "sg:postcode":"00175",
    "sg:province":"Roma",
    "wof:name":"Futuroma Cooperativa Facchinaggio E Trasporto",
    "wof:placetype":"venue"
},
  "geometry": {"coordinates":[12.547618,41.864182],"type":"Point"}
}