{
  "type": "Feature",
  "properties": {
    "addr:full":"22070 Bregnano Bregnano Como 22070",
    "addr:postcode":"22070;22070",
    "iso:country":"IT",
    "sg:address":"22070 Bregnano",
    "sg:city":"Bregnano",
    "sg:orig_category":"Non-classified Establishments",
    "sg:phone":"+39 031 773442",
    "sg:postcode":"22070",
    "sg:province":"Como",
    "wof:name":"V.m. Arredamenti Nautici S.n.c.",
    "wof:placetype":"venue"
},
  "geometry": {"coordinates":[9.050431,45.743263],"type":"Point"}
}