{
  "type": "Feature",
  "properties": {
    "iso:country":"IT",
    "sg:address":"95100 Catania",
    "sg:orig_category":"Articoli Medico-sanitari Ed Ortopedici",
    "sg:phone":"+39 095 316914",
    "sg:province":"CT",
    "wof:name":"Officina Tecnica Ortopedica Catanese Srl",
    "wof:placetype":"venue"
},
  "geometry": {"coordinates":[15.080064,37.511063],"type":"Point"}
}