{
  "type": "Feature",
  "properties": {
    "iso:country":"IT",
    "sg:address":"10, Via Careno 21040 Vedano Olona",
    "sg:city":"Vedano Olona",
    "sg:classifiers":[
        {
            "category":"Shopping",
            "subcategory":"Computers & Home Electronics",
            "type":"Retail Goods"
        }
    ],
    "sg:phone":"+39 0332 867011",
    "sg:postcode":"21040",
    "sg:province":"Varese",
    "sg:tags":[
        "electronic",
        "electrical",
        "equipment"
    ],
    "wof:name":"Solidarieta' Cooperativa Sociale A R.l.",
    "wof:placetype":"venue"
},
  "geometry": {"coordinates":[8.871966,45.766296],"type":"Point"}
}