{
  "type": "Feature",
  "properties": {
    "iso:country":"IT",
    "sg:address":"Via Provinciale, 16/b/c; Piano Di Sorrento; 95045",
    "sg:classifiers":[
        {
            "category":"Banks & Credit Unions",
            "subcategory":"Bank",
            "type":"Services"
        }
    ],
    "sg:phone":"+39 095 391520",
    "sg:postcode":"95045",
    "sg:province":"Catania",
    "wof:name":"Banca Popolare Di Belpasso",
    "wof:placetype":"venue"
},
  "geometry": {"coordinates":[15.020676,37.529091],"type":"Point"}
}