{
  "type": "Feature",
  "properties": {
    "iso:country":"IT",
    "sg:address":"23881 Airuno",
    "sg:city":"Airuno",
    "sg:orig_category":"Macchine, Impianti Ed Attrezzature Per Agricoltura E Zootecnia",
    "sg:phone":"+39 039 994 3936",
    "sg:postcode":"23881",
    "sg:province":"Lecco",
    "wof:name":"Minotti Walter",
    "wof:placetype":"venue"
},
  "geometry": {"coordinates":[9.407584,45.80254],"type":"Point"}
}