{
  "type": "Feature",
  "properties": {
    "iso:country":"IT",
    "sg:address":"16149 Genova",
    "sg:city":"Genova",
    "sg:orig_category":"Motori Ed Organi Di Trasmissione",
    "sg:phone":"+39 010 645 9954",
    "sg:postcode":"16149",
    "sg:province":"Genova",
    "wof:name":"Forniture Industriali Dellacasa S.r.l.",
    "wof:placetype":"venue"
},
  "geometry": {"coordinates":[8.8964471817,44.4215545654],"type":"Point"}
}