{
  "type": "Feature",
  "properties": {
    "addr:full":"Via Montecatini 14 20144 Milano Milano Milano 20144",
    "addr:housenumber":"14",
    "addr:postcode":"20144;20144",
    "addr:street":"Via Montecatini",
    "iso:country":"IT",
    "sg:address":"Via Montecatini 14 20144 Milano",
    "sg:city":"Milano",
    "sg:classifiers":[
        {
            "category":"Wholesale",
            "subcategory":"Metals & Minerals",
            "type":"Manufacturing & Wholesale Goods"
        }
    ],
    "sg:phone":"+39 02 474504",
    "sg:postcode":"20144",
    "sg:province":"Milano",
    "sg:tags":[
        "non-ferrous"
    ],
    "sg:website":"www.clamatrade.it",
    "wof:name":"Clama Trade Srl",
    "wof:placetype":"venue"
},
  "geometry": {"coordinates":[9.156385,45.453274],"type":"Point"}
}