{
  "type": "Feature",
  "properties": {
    "addr:full":"00185 Roma Roma Roma 00185",
    "addr:postcode":"00185;00185",
    "iso:country":"IT",
    "sg:address":"00185 Roma",
    "sg:city":"Roma",
    "sg:orig_category":"Servizi Al Turismo. Ambasciate Ed Enti Internazionali",
    "sg:phone":"+39 06 488 8211",
    "sg:postcode":"00185",
    "sg:province":"Roma",
    "wof:name":"Ambasciata Presso Lo Stato Italiano Stati Uniti D'america",
    "wof:placetype":"venue"
},
  "geometry": {"coordinates":[12.499439,41.907715],"type":"Point"}
}