{
  "type": "Feature",
  "properties": {
    "iso:country":"IT",
    "sg:address":"31100 Treviso",
    "sg:city":"Treviso",
    "sg:orig_category":"Alberghi",
    "sg:phone":"+39 0422 432550",
    "sg:postcode":"31100",
    "sg:province":"Treviso",
    "sg:website":"http://www.sevenonline.it/cadelgalletto",
    "wof:name":"Hotel Ca' Del Galletto Spa",
    "wof:placetype":"venue"
},
  "geometry": {"coordinates":[12.226585,45.687344],"type":"Point"}
}