{
  "type": "Feature",
  "properties": {
    "iso:country":"IT",
    "sg:address":"50013 Campi Bisenzio",
    "sg:city":"Campi Bisenzio",
    "sg:orig_category":"Prodotti Alimentari",
    "sg:phone":"+39 055 898 6228",
    "sg:postcode":"50013",
    "sg:province":"Firenze",
    "wof:name":"Dream Fruits Srl",
    "wof:placetype":"venue"
},
  "geometry": {"coordinates":[11.1467542648,43.8444023132],"type":"Point"}
}