{
  "type": "Feature",
  "properties": {
    "addr:full":"Via Tre Novembre, 58 - Tombelle 35020 Saonara Saonara Padova 35020",
    "addr:housenumber":"58",
    "addr:postcode":"35020;35020",
    "addr:street":"Via Tre Novembre",
    "iso:country":"IT",
    "sg:address":"Via Tre Novembre, 58 - Tombelle 35020 Saonara",
    "sg:city":"Saonara",
    "sg:orig_category":"Ladies' Shoes",
    "sg:phone":"+39 049 879 0848",
    "sg:postcode":"35020",
    "sg:province":"Padova",
    "wof:name":"Mitica S.r.l.",
    "wof:placetype":"venue"
},
  "geometry": {"coordinates":[11.876589,45.409569],"type":"Point"}
}