{
  "type": "Feature",
  "properties": {
    "iso:country":"IT",
    "sg:address":"28040 Paruzzaro",
    "sg:city":"Oleggio Castello",
    "sg:orig_category":"Trattamenti Termici E Superficiali Metalli, Galvanotecnica",
    "sg:phone":"+39 0322 53260",
    "sg:postcode":"28040",
    "sg:province":"Novara",
    "wof:name":"Zanini Spa",
    "wof:placetype":"venue"
},
  "geometry": {"coordinates":[8.522325,45.745594],"type":"Point"}
}