{
  "type": "Feature",
  "properties": {
    "addr:full":"Viale G. Marconi 1; Assisi; 06081 Assisi Perugia 06081",
    "addr:housenumber":"1",
    "addr:postcode":"06081;06081",
    "addr:street":"Viale G. Marconi",
    "iso:country":"IT",
    "sg:address":"Viale G. Marconi 1; Assisi; 06081",
    "sg:city":"Assisi",
    "sg:classifiers":[
        {
            "category":"Banks & Credit Unions",
            "subcategory":"Bank",
            "type":"Services"
        }
    ],
    "sg:phone":"+39 075 813200",
    "sg:postcode":"06081",
    "sg:province":"Perugia",
    "wof:name":"Cassa Di Risparmio Di Foligno Spa",
    "wof:placetype":"venue"
},
  "geometry": {"coordinates":[12.607059,43.072716],"type":"Point"}
}