{
  "type": "Feature",
  "properties": {
    "addr:full":"12010 Bernezzo Bernezzo Cuneo 12010",
    "addr:postcode":"12010;12010",
    "iso:country":"IT",
    "sg:address":"12010 Bernezzo",
    "sg:city":"Bernezzo",
    "sg:orig_category":"Illuminazione - Impianti E Materiali",
    "sg:phone":"+39 0171 85581",
    "sg:postcode":"12010",
    "sg:province":"Cuneo",
    "wof:name":"Il Triangolo Lampadari Sas",
    "wof:placetype":"venue"
},
  "geometry": {"coordinates":[7.486408,44.388184],"type":"Point"}
}