{
  "type": "Feature",
  "properties": {
    "iso:country":"IT",
    "sg:address":"16149 Genova",
    "sg:city":"Genova",
    "sg:orig_category":"Legno E Semilavorati. Macchine E Forniture Per Arredamento E Industria Del Legno. Hobbistica",
    "sg:phone":"+39 010 412717",
    "sg:postcode":"16149",
    "sg:province":"Genova",
    "wof:name":"Fai Da Te La Casa Del Legno",
    "wof:placetype":"venue"
},
  "geometry": {"coordinates":[8.899701,44.412285],"type":"Point"}
}