{
  "type": "Feature",
  "properties": {
    "addr:full":"31020 Revine Lago Lago Treviso 31020",
    "addr:postcode":"31020;31020",
    "addr:street":"Lago Lago Treviso",
    "iso:country":"IT",
    "sg:address":"31020 Revine Lago",
    "sg:city":"Lago",
    "sg:orig_category":"Macchine, Impianti Ed Attrezzature Per Agricoltura E Zootecnia",
    "sg:phone":"+39 0438 562066",
    "sg:postcode":"31020",
    "sg:province":"Treviso",
    "wof:name":"Officine Fava",
    "wof:placetype":"venue"
},
  "geometry": {"coordinates":[12.228759,45.991425],"type":"Point"}
}