{
  "type": "Feature",
  "properties": {
    "iso:country":"IT",
    "sg:address":"20128 Milano",
    "sg:city":"Milano",
    "sg:orig_category":"Metalli E Leghe",
    "sg:phone":"+39 02 255 1335",
    "sg:postcode":"20128",
    "sg:province":"Milano",
    "wof:name":"Mas Metal Srl",
    "wof:placetype":"venue"
},
  "geometry": {"coordinates":[9.2311449051,45.5072555542],"type":"Point"}
}