{
  "type": "Feature",
  "properties": {
    "iso:country":"IT",
    "sg:address":"6, Via Leonardo Da Vinci 25080 Mazzano",
    "sg:city":"Mazzano",
    "sg:classifiers":[
        {
            "category":"Wholesale",
            "subcategory":"Machinery & Supplies",
            "type":"Manufacturing & Wholesale Goods"
        }
    ],
    "sg:phone":"+39 39030212151",
    "sg:postcode":"25080",
    "sg:province":"Brescia",
    "sg:tags":[
        "equipment",
        "-",
        "instrument",
        "measurement"
    ],
    "wof:name":"Siccet Srl",
    "wof:placetype":"venue"
},
  "geometry": {"coordinates":[10.316347,45.512974],"type":"Point"}
}