{
  "type": "Feature",
  "properties": {
    "addr:full":"10155 Torino Torino Torino 10155",
    "addr:postcode":"10155;10155",
    "iso:country":"IT",
    "sg:address":"10155 Torino",
    "sg:city":"Torino",
    "sg:orig_category":"Macchine, Impianti Ed Attrezzature Industria Chimica. Attrezzature E Forniture Per Officine Riparazione E Servizi Ausiliari",
    "sg:phone":"+39 011 205 3828",
    "sg:postcode":"10155",
    "sg:province":"Torino",
    "wof:name":"Antonicelli Giuseppe",
    "wof:placetype":"venue"
},
  "geometry": {"coordinates":[7.683727,45.089481],"type":"Point"}
}