{
  "type": "Feature",
  "properties": {
    "addr:full":"34, Via Marigonda 31040 Gorgo Al Monticano Gorgo al Monticano Treviso 31040",
    "addr:housenumber":"monticano",
    "addr:postcode":"31040;al;31040",
    "addr:street":"Via Marigonda",
    "iso:country":"IT",
    "sg:address":"34, Via Marigonda 31040 Gorgo Al Monticano",
    "sg:city":"Gorgo al Monticano",
    "sg:classifiers":[
        {
            "category":"Manufacturing",
            "subcategory":"Rubber & Plastics",
            "type":"Manufacturing & Wholesale Goods"
        }
    ],
    "sg:phone":"+39 0422 742026",
    "sg:postcode":"31040",
    "sg:province":"Treviso",
    "wof:name":"T.m.p. (s.r.l.)",
    "wof:placetype":"venue"
},
  "geometry": {"coordinates":[12.5926332474,45.8075485229],"type":"Point"}
}