{
  "type": "Feature",
  "properties": {
    "iso:country":"IT",
    "sg:address":"00186 Roma",
    "sg:city":"Roma",
    "sg:classifiers":[
        {
            "category":"Manufacturing",
            "subcategory":"Food",
            "type":"Manufacturing & Wholesale Goods"
        }
    ],
    "sg:phone":"+39 06 6880 6264",
    "sg:postcode":"00186",
    "sg:province":"Roma",
    "sg:tags":[
        "product"
    ],
    "wof:name":"Bernasconi",
    "wof:placetype":"venue"
},
  "geometry": {"coordinates":[12.4890213013,41.8578071594],"type":"Point"}
}