{
  "type": "Feature",
  "properties": {
    "iso:country":"IT",
    "sg:address":"00062 Bracciano",
    "sg:city":"Bracciano",
    "sg:orig_category":"Amministrazioni Immobiliari",
    "sg:phone":"+39 06 9980 9071",
    "sg:postcode":"00062",
    "sg:province":"Roma",
    "wof:name":"A. & G. Manutenzioni E Servizi Di Antonio Orlando",
    "wof:placetype":"venue"
},
  "geometry": {"coordinates":[12.676808,41.80888],"type":"Point"}
}