{
  "type": "Feature",
  "properties": {
    "addr:full":"47, Via Volpiano 10040 Leini' Torino 10040",
    "addr:postcode":"10040 leini;10040",
    "addr:street":"Via Volpiano",
    "iso:country":"IT",
    "sg:address":"47, Via Volpiano 10040 Leini'",
    "sg:classifiers":[
        {
            "category":"Banks & Credit Unions",
            "subcategory":"Investment Brokerage",
            "type":"Services"
        }
    ],
    "sg:phone":"+39 011 997 3374",
    "sg:postcode":"10040",
    "sg:province":"Torino",
    "sg:tags":[
        "-",
        "transport",
        "related"
    ],
    "wof:name":"L.i.s.a. (s.r.l.)",
    "wof:placetype":"venue"
},
  "geometry": {"coordinates":[7.770323,45.175739],"type":"Point"}
}