{
  "type": "Feature",
  "properties": {
    "addr:full":"14, Via Marconi 21015 Lonate Pozzolo Lonate Pozzolo Varese 21015",
    "addr:postcode":"21015;21015",
    "addr:street":"Via Marconi",
    "iso:country":"IT",
    "sg:address":"14, Via Marconi 21015 Lonate Pozzolo",
    "sg:city":"Lonate Pozzolo",
    "sg:classifiers":[
        {
            "category":"Real Estate",
            "subcategory":"Architect",
            "type":"Services"
        }
    ],
    "sg:phone":"+39 0331 302112",
    "sg:postcode":"21015",
    "sg:province":"Varese",
    "sg:tags":[
        "textile",
        "clothing"
    ],
    "wof:name":"Creazioni Lisa Sas Di Francica Francesco E C.",
    "wof:placetype":"venue"
},
  "geometry": {"coordinates":[8.826385,45.817604],"type":"Point"}
}