{
  "type": "Feature",
  "properties": {
    "iso:country":"IT",
    "sg:address":"00187 Roma",
    "sg:city":"Roma",
    "sg:orig_category":"Servizi Culturali E Per Lo Spettacolo. Servizi Al Turismo. Acqua, Luce, Gas E Societa' Di Esercizio Pubblico",
    "sg:phone":"+39 06 3211 0702",
    "sg:postcode":"00187",
    "sg:province":"Roma",
    "wof:name":"Museo Canova Tadolini Srl",
    "wof:placetype":"venue"
},
  "geometry": {"coordinates":[12.479856,41.9077],"type":"Point"}
}