{
  "type": "Feature",
  "properties": {
    "iso:country":"IT",
    "sg:address":"Loc Capanne 56020 Montopoli In Val D'arno",
    "sg:city":"Capanne",
    "sg:classifiers":[
        {
            "category":"Home & Garden",
            "subcategory":"Carpets & Floor Coverings",
            "type":"Retail Goods"
        }
    ],
    "sg:phone":"+39 0571 467666",
    "sg:postcode":"56020",
    "sg:province":"Pisa",
    "sg:tags":[
        "animal",
        "skin"
    ],
    "sg:website":"www.reberpell.it",
    "wof:name":"Mondialsplit Srl",
    "wof:placetype":"venue"
},
  "geometry": {"coordinates":[10.3965845108,43.7161369324],"type":"Point"}
}