{
  "type": "Feature",
  "properties": {
    "iso:country":"IT",
    "sg:address":"20099 Sesto San Giovanni",
    "sg:city":"Sesto San Giovanni",
    "sg:orig_category":"Servizi E Lavori Per Ecologia E Smaltimento Rifiuti. Acqua, Luce, Gas E Societa' Di Esercizio Pubblico",
    "sg:phone":"+39 02 2622 2972",
    "sg:postcode":"20099",
    "sg:province":"Milano",
    "wof:name":"Waste Management Italia Spa",
    "wof:placetype":"venue"
},
  "geometry": {"coordinates":[9.259248,45.52346],"type":"Point"}
}