{
  "type": "Feature",
  "properties": {
    "iso:country":"IT",
    "sg:address":"30141 Murano",
    "sg:city":"Murano",
    "sg:orig_category":"Non-classified Establishments",
    "sg:phone":"+39 041 739695",
    "sg:postcode":"30141",
    "sg:province":"Venezia",
    "sg:website":"http://www.promovetro.com",
    "wof:name":"La Perla Veneziana Snc",
    "wof:placetype":"venue"
},
  "geometry": {"coordinates":[12.354397,45.456192],"type":"Point"}
}