{
  "type": "Feature",
  "properties": {
    "iso:country":"IT",
    "sg:address":"31031 Caerano Di San Marco",
    "sg:city":"Caerano di San Marco",
    "sg:orig_category":"Detergenti Industriali",
    "sg:phone":"+39 0423 85444",
    "sg:postcode":"31031",
    "sg:province":"Treviso",
    "wof:name":"P.h. Srl",
    "wof:placetype":"venue"
},
  "geometry": {"coordinates":[12.002752,45.782501],"type":"Point"}
}