{
  "type": "Feature",
  "properties": {
    "addr:full":"Via Faletti , 33/35 25031 Capriolo Capriolo Brescia 25031",
    "addr:housenumber":"33 / 35",
    "addr:postcode":"25031;25031",
    "addr:street":"Via Faletti",
    "iso:country":"IT",
    "sg:address":"Via Faletti , 33/35 25031 Capriolo",
    "sg:city":"Capriolo",
    "sg:classifiers":[
        {
            "category":"Professional",
            "subcategory":"Engineering",
            "type":"Services"
        }
    ],
    "sg:phone":"+39 030 746 1171",
    "sg:postcode":"25031",
    "sg:province":"Brescia",
    "sg:tags":[
        "technical",
        "thread"
    ],
    "sg:website":"www.filtes.it",
    "wof:name":"Filtes International Srl",
    "wof:placetype":"venue"
},
  "geometry": {"coordinates":[9.926611,45.62561],"type":"Point"}
}