{
  "type": "Feature",
  "properties": {
    "iso:country":"IT",
    "sg:address":"20144 Milano",
    "sg:city":"Milano",
    "sg:orig_category":"Caldaie - Produzione E Commercio",
    "sg:phone":"+39 02 4860 1485",
    "sg:postcode":"20144",
    "sg:province":"Milano",
    "wof:name":"Artigiancasa Petrillo Nicola",
    "wof:placetype":"venue"
},
  "geometry": {"coordinates":[9.153463,45.450779],"type":"Point"}
}