{
  "type": "Feature",
  "properties": {
    "addr:full":"Piazza Costadura 13, 73044 Galatone, Le Galatone Lecce 73044",
    "addr:housenumber":"13",
    "addr:postcode":"73044;73044",
    "addr:street":"Piazza Costadura",
    "iso:country":"IT",
    "sg:address":"Piazza Costadura 13, 73044 Galatone, Le",
    "sg:city":"Galatone",
    "sg:classifiers":[
        {
            "category":"Banks & Credit Unions",
            "subcategory":"Bank",
            "type":"Services"
        }
    ],
    "sg:postcode":"73044",
    "sg:province":"Lecce",
    "wof:name":"Banca Leuzzi & Megha",
    "wof:placetype":"venue"
},
  "geometry": {"coordinates":[18.004467,40.148861],"type":"Point"}
}