{
  "type": "Feature",
  "properties": {
    "addr:full":"21052 Busto Arsizio Busto Arsizio Varese 21052",
    "addr:postcode":"21052;21052",
    "iso:country":"IT",
    "sg:address":"21052 Busto Arsizio",
    "sg:city":"Busto Arsizio",
    "sg:orig_category":"Servizi E Lavori Per Arredamento E Industria Del Legno. Forniture Per Congressi, Fiere E Manifestazioni. Servizi Per Aziende, Manifestazioni E Supporto Agli Scambi Commerciali",
    "sg:phone":"+39 0331 623343",
    "sg:postcode":"21052",
    "sg:province":"Varese",
    "wof:name":"Bustese Pompe Funebri Di Monti Angelo",
    "wof:placetype":"venue"
},
  "geometry": {"coordinates":[8.833518,45.609245],"type":"Point"}
}