{
  "type": "Feature",
  "properties": {
    "addr:full":"Via Scavata Case Rosse 84131 Salerno Salerno Salerno 84131",
    "addr:postcode":"84131;84131",
    "addr:street":"Via Scavata Case Rosse",
    "iso:country":"IT",
    "sg:address":"Via Scavata Case Rosse 84131 Salerno",
    "sg:city":"Salerno",
    "sg:classifiers":[
        {
            "category":"Parking",
            "subcategory":"Lot",
            "type":"Transportation"
        }
    ],
    "sg:phone":"+39 39089771411",
    "sg:postcode":"84131",
    "sg:province":"Salerno",
    "sg:tags":[
        "transport",
        "road"
    ],
    "wof:name":"S.m.e.t. Srl",
    "wof:placetype":"venue"
},
  "geometry": {"coordinates":[14.765912,40.677956],"type":"Point"}
}