{
  "type": "Feature",
  "properties": {
    "iso:country":"IT",
    "sg:address":"61020 Sant'angelo In Lizzola",
    "sg:city":"Montecchio",
    "sg:orig_category":"Accessori Moda D'abbigliamento. Forniture Per Abbigliamento E Pelletterie",
    "sg:phone":"+39 0721 491953",
    "sg:postcode":"61020",
    "sg:province":"Pesaro E Urbino",
    "wof:name":"Stile Ricamo Di Occhialini Roberto",
    "wof:placetype":"venue"
},
  "geometry": {"coordinates":[12.77234,43.851006],"type":"Point"}
}