{
  "type": "Feature",
  "properties": {
    "addr:full":"1, Borgata Ramello 13822 Mosso Mosso Biella 13822",
    "addr:housenumber":"1",
    "addr:postcode":"13822;13822",
    "addr:street":"Borgata Ramello;Mosso",
    "iso:country":"IT",
    "sg:address":"1, Borgata Ramello 13822 Mosso",
    "sg:city":"Mosso",
    "sg:classifiers":[
        {
            "category":"Shopping",
            "subcategory":"Crafts & Fabrics",
            "type":"Retail Goods"
        }
    ],
    "sg:phone":"+39 015 714 2060",
    "sg:postcode":"13822",
    "sg:province":"Biella",
    "wof:name":"Palmatex S.n.c.",
    "wof:placetype":"venue"
},
  "geometry": {"coordinates":[8.13697052,45.6428146362],"type":"Point"}
}