{
  "type": "Feature",
  "properties": {
    "iso:country":"IT",
    "sg:address":"35127 Padova",
    "sg:city":"Padova",
    "sg:orig_category":"Studi E Consulenze Tecniche E Industriali. Consulenze Tecniche, Amministrative E Perizie. Servizi Ausiliari Di Analisi, Controllo E Ricerca",
    "sg:phone":"+39 049 806 4111",
    "sg:postcode":"35127",
    "sg:province":"Padova",
    "sg:website":"http://www.idroesse.it",
    "wof:name":"Studio Di Ingegneria Idroesse S.s.",
    "wof:placetype":"venue"
},
  "geometry": {"coordinates":[11.934061,45.387646],"type":"Point"}
}