{
  "type": "Feature",
  "properties": {
    "addr:full":"06080 Perugia PG",
    "addr:postcode":"06080",
    "addr:street":"Pg",
    "iso:country":"IT",
    "sg:address":"06080 Perugia",
    "sg:orig_category":"Depurazione E Trattamento Delle Acque - Impianti Ed Apparecchi",
    "sg:phone":"+39 075 396278",
    "sg:province":"PG",
    "wof:name":"Tecnoacque Srl",
    "wof:placetype":"venue"
},
  "geometry": {"coordinates":[12.479795,43.086018],"type":"Point"}
}