{
  "type": "Feature",
  "properties": {
    "iso:country":"IT",
    "sg:address":"53, Via Roma 33040 Chiopris Viscone",
    "sg:city":"Visco",
    "sg:classifiers":[
        {
            "category":"Home & Garden",
            "subcategory":"Home Furnishings",
            "type":"Retail Goods"
        }
    ],
    "sg:phone":"+39 0432 991161",
    "sg:postcode":"33040",
    "sg:province":"Udine",
    "sg:tags":[
        "household"
    ],
    "wof:name":"Friulbaby (s.r.l.)",
    "wof:placetype":"venue"
},
  "geometry": {"coordinates":[13.340637,45.944145],"type":"Point"}
}