{
  "type": "Feature",
  "properties": {
    "addr:full":"20094 Corsico Corsico Milano 20094",
    "addr:postcode":"20094;20094",
    "iso:country":"IT",
    "sg:address":"20094 Corsico",
    "sg:city":"Corsico",
    "sg:orig_category":"Biancheria Intima Ed Abbigliamento Intimo - Produzione E Ingrosso",
    "sg:phone":"+39 02 4860 1530",
    "sg:postcode":"20094",
    "sg:province":"Milano",
    "wof:name":"Suardi Industria Confezioni Sas",
    "wof:placetype":"venue"
},
  "geometry": {"coordinates":[9.109643,45.449394],"type":"Point"}
}