{
  "type": "Feature",
  "properties": {
    "iso:country":"IT",
    "sg:address":"16, Frazione Prato All'isarco 39050 Fie' Allo Sciliar",
    "sg:classifiers":[
        {
            "category":"Wholesale",
            "subcategory":"Drugs",
            "type":"Manufacturing & Wholesale Goods"
        }
    ],
    "sg:phone":"+39 0471 353355",
    "sg:postcode":"39050",
    "sg:province":"Bolzano/Bozen",
    "sg:tags":[
        "chemical",
        "pharmaceutical"
    ],
    "wof:name":"Loacker Remedia S.r.l.",
    "wof:placetype":"venue"
},
  "geometry": {"coordinates":[11.449594,46.495747],"type":"Point"}
}