{
  "type": "Feature",
  "properties": {
    "addr:full":"44100 Ferrara Ferrara Ferrara 44100",
    "addr:postcode":"44100;44100",
    "iso:country":"IT",
    "sg:address":"44100 Ferrara",
    "sg:city":"Ferrara",
    "sg:orig_category":"Pozzi Neri",
    "sg:phone":"+39 0532 62990",
    "sg:postcode":"44100",
    "sg:province":"Ferrara",
    "wof:name":"Guidi F.lli Snc",
    "wof:placetype":"venue"
},
  "geometry": {"coordinates":[11.6217603683,44.8134613037],"type":"Point"}
}