{
  "type": "Feature",
  "properties": {
    "addr:full":"41100 Modena Modena Modena 41100",
    "addr:postcode":"41100;41100",
    "iso:country":"IT",
    "sg:address":"41100 Modena",
    "sg:city":"Modena",
    "sg:classifiers":[
        {
            "category":"Restaurant",
            "type":"Food & Drink"
        }
    ],
    "sg:phone":"+39 059 313528",
    "sg:postcode":"41100",
    "sg:province":"Modena",
    "sg:tags":[
        "equipment",
        "industry",
        "machinery"
    ],
    "wof:name":"Gel.bar Forniture Srl",
    "wof:placetype":"venue"
},
  "geometry": {"coordinates":[10.9387159348,44.5485191345],"type":"Point"}
}