{
  "type": "Feature",
  "properties": {
    "addr:full":"15, Piazza Verdi 39100 Bolzano Bolzano Bolzano/Bozen 39100",
    "addr:postcode":"39100;39100",
    "addr:street":"Piazza Verdi",
    "iso:country":"IT",
    "sg:address":"15, Piazza Verdi 39100 Bolzano",
    "sg:city":"Bolzano",
    "sg:classifiers":[
        {
            "category":"Parking",
            "subcategory":"Lot",
            "type":"Transportation"
        }
    ],
    "sg:phone":"+39 0471 970406",
    "sg:postcode":"39100",
    "sg:province":"Bolzano/Bozen",
    "sg:tags":[
        "transport",
        "road"
    ],
    "wof:name":"Trasporti Indian (s.n.c. - O.h.g.)",
    "wof:placetype":"venue"
},
  "geometry": {"coordinates":[11.328239,46.461643],"type":"Point"}
}