{
  "type": "Feature",
  "properties": {
    "iso:country":"IT",
    "sg:address":"Via Madonna Di Rosa 7; San Vito Al Tagliamento",
    "sg:classifiers":[
        {
            "category":"Banks & Credit Unions",
            "subcategory":"Bank",
            "type":"Services"
        }
    ],
    "sg:phone":"+39 0434 81514",
    "wof:name":"Banca Popolare Friuladria",
    "wof:placetype":"venue"
},
  "geometry": {"coordinates":[12.84019,45.924492],"type":"Point"}
}