{
  "type": "Feature",
  "properties": {
    "addr:full":"32020 Voltago Agordino Voltago Agordino Belluno 32020",
    "addr:postcode":"32020;32020",
    "addr:street":"Agordino;Agordino",
    "iso:country":"IT",
    "sg:address":"32020 Voltago Agordino",
    "sg:city":"Voltago Agordino",
    "sg:orig_category":"Servizi E Lavori Per Arredamento E Industria Del Legno. Servizi E Lavori Per Edilizia E Lavori Pubblici",
    "sg:phone":"+39 0437 67040",
    "sg:postcode":"32020",
    "sg:province":"Belluno",
    "wof:name":"Carpenteria Agordina Srl",
    "wof:placetype":"venue"
},
  "geometry": {"coordinates":[11.983373,46.253551],"type":"Point"}
}