{
  "type": "Feature",
  "properties": {
    "iso:country":"IT",
    "sg:address":"61038 Orciano Di Pesaro",
    "sg:city":"Orciano di Pesaro",
    "sg:orig_category":"Edilizia - Materiali",
    "sg:phone":"+39 0721 97208",
    "sg:postcode":"61038",
    "sg:province":"Pesaro E Urbino",
    "sg:website":"http://www.grupposecchiaroli.com",
    "wof:name":"Gruppo Fratelli Secchiaroli Srl",
    "wof:placetype":"venue"
},
  "geometry": {"coordinates":[12.969805,43.690605],"type":"Point"}
}