{
  "type": "Feature",
  "properties": {
    "addr:full":"20091 Bresso Bresso Milano 20091",
    "addr:postcode":"20091;20091",
    "iso:country":"IT",
    "sg:address":"20091 Bresso",
    "sg:city":"Bresso",
    "sg:orig_category":"Servizi E Lavori Per Agricoltura E Zootecnia. Servizi E Lavori Industria Chimica. Servizi Ausiliari Di Analisi, Controllo E Ricerca",
    "sg:phone":"+39 02 6650 2227",
    "sg:postcode":"20091",
    "sg:province":"Milano",
    "wof:name":"Pe Italia Filiale Della Pe Europe B.v.",
    "wof:placetype":"venue"
},
  "geometry": {"coordinates":[9.198076,45.535713],"type":"Point"}
}