{
  "type": "Feature",
  "properties": {
    "iso:country":"IT",
    "sg:address":"2, Strada Provinciale Per S. Nazzaro Sesia 28061 Biandrate",
    "sg:city":"Biandrate",
    "sg:classifiers":[
        {
            "category":"Food & Beverages",
            "subcategory":"Dairy",
            "type":"Retail Goods"
        }
    ],
    "sg:phone":"+39 39032183012",
    "sg:postcode":"28061",
    "sg:province":"Novara",
    "sg:tags":[
        "product"
    ],
    "wof:name":"Ticozzelli Giuseppe E C. Srl",
    "wof:placetype":"venue"
},
  "geometry": {"coordinates":[8.618671,45.445084],"type":"Point"}
}