{
  "type": "Feature",
  "properties": {
    "iso:country":"IT",
    "sg:address":"15012 Bistagno",
    "sg:city":"Bistagno",
    "sg:orig_category":"Macchine, Impianti Ed Attrezzature Per Agricoltura E Zootecnia. Macchine Ed Impianti Per Edilizia E Lavori Pubblici",
    "sg:phone":"+39 0144 79634",
    "sg:postcode":"15012",
    "sg:province":"Alessandria",
    "wof:name":"Comat Srl",
    "wof:placetype":"venue"
},
  "geometry": {"coordinates":[8.369092,44.669979],"type":"Point"}
}