{
  "type": "Feature",
  "properties": {
    "addr:full":"Via Brera 3; Milano; 20121 Milano Milano 20121",
    "addr:housenumber":"3",
    "addr:postcode":"20121;20121",
    "addr:street":"Via Brera",
    "iso:country":"IT",
    "sg:address":"Via Brera 3; Milano; 20121",
    "sg:city":"Milano",
    "sg:classifiers":[
        {
            "category":"Banks & Credit Unions",
            "subcategory":"Bank",
            "type":"Services"
        }
    ],
    "sg:phone":"+39 02 863262",
    "sg:postcode":"20121",
    "sg:province":"Milano",
    "wof:name":"The Sanwa Bank Ltd",
    "wof:placetype":"venue"
},
  "geometry": {"coordinates":[9.188032,45.469559],"type":"Point"}
}