{
  "type": "Feature",
  "properties": {
    "iso:country":"IT",
    "sg:address":"Via Pacinotti 52 60021 Camerano",
    "sg:city":"Camerano",
    "sg:classifiers":[
        {
            "category":"Manufacturing",
            "subcategory":"Furniture",
            "type":"Manufacturing & Wholesale Goods"
        }
    ],
    "sg:phone":"+39 071 95208",
    "sg:postcode":"60021",
    "sg:province":"Ancona",
    "sg:tags":[
        "children's"
    ],
    "sg:website":"www.fram.it",
    "wof:name":"Fram Srl",
    "wof:placetype":"venue"
},
  "geometry": {"coordinates":[13.551714,43.527245],"type":"Point"}
}