{
  "type": "Feature",
  "properties": {
    "iso:country":"IT",
    "sg:address":"10125 Torino",
    "sg:city":"Torino",
    "sg:orig_category":"Arredamenti - Vendita Al Dettaglio",
    "sg:phone":"+39 011 669 6879",
    "sg:postcode":"10125",
    "sg:province":"Torino",
    "sg:website":"http://www.tanto.it",
    "wof:name":"Tanto.it Srl",
    "wof:placetype":"venue"
},
  "geometry": {"coordinates":[7.679143,45.053272],"type":"Point"}
}