{
  "type": "Feature",
  "properties": {
    "iso:country":"IT",
    "sg:address":"20090 Assago",
    "sg:city":"Assago",
    "sg:orig_category":"Macchine, Impianti Ed Attrezzature Industria Chimica",
    "sg:phone":"+39 02 488 2987",
    "sg:postcode":"20090",
    "sg:province":"Milano",
    "wof:name":"Studio Tecnico Emme Effe Sas Di Murtinu F. E C.",
    "wof:placetype":"venue"
},
  "geometry": {"coordinates":[9.130575,45.404739],"type":"Point"}
}