{
  "type": "Feature",
  "properties": {
    "iso:country":"IT",
    "sg:address":"16043 Chiavari",
    "sg:city":"Chiavari",
    "sg:orig_category":"Hobbistica",
    "sg:phone":"+39 0185 307144",
    "sg:postcode":"16043",
    "sg:province":"Genova",
    "wof:name":"Ghio Giovanni",
    "wof:placetype":"venue"
},
  "geometry": {"coordinates":[9.317374,44.324886],"type":"Point"}
}