{
  "type": "Feature",
  "properties": {
    "iso:country":"IT",
    "sg:address":"22060 Carimate",
    "sg:city":"Carimate",
    "sg:orig_category":"Servizi E Lavori Per Arredamento E Industria Del Legno. Arte Ed Artigianato Artistico",
    "sg:phone":"+39 031 790202",
    "sg:postcode":"22060",
    "sg:province":"Como",
    "wof:name":"Grassi Michelino",
    "wof:placetype":"venue"
},
  "geometry": {"coordinates":[9.128355,45.738541],"type":"Point"}
}