{
  "type": "Feature",
  "properties": {
    "addr:full":"52, Via Piemonte 26026 Pizzighettone Pizzighettone Cremona 26026",
    "addr:postcode":"26026;26026",
    "addr:street":"Via Piemonte",
    "iso:country":"IT",
    "sg:address":"52, Via Piemonte 26026 Pizzighettone",
    "sg:city":"Pizzighettone",
    "sg:classifiers":[
        {
            "category":"Shopping",
            "type":"Retail Goods"
        }
    ],
    "sg:phone":"+39 0372 743076",
    "sg:postcode":"26026",
    "sg:province":"Cremona",
    "sg:tags":[
        "finished",
        "-",
        "metallic"
    ],
    "wof:name":"Massari",
    "wof:placetype":"venue"
},
  "geometry": {"coordinates":[9.7946300507,45.1934204102],"type":"Point"}
}