{
  "type": "Feature",
  "properties": {
    "addr:full":"10129 Torino Torino Torino 10129",
    "addr:postcode":"10129;10129",
    "iso:country":"IT",
    "sg:address":"10129 Torino",
    "sg:city":"Torino",
    "sg:classifiers":[
        {
            "category":"Health Services",
            "subcategory":"Health Practitioner",
            "type":"Services"
        }
    ],
    "sg:phone":"+39 335 628 2225",
    "sg:postcode":"10129",
    "sg:province":"Torino",
    "sg:tags":[
        "medici"
    ],
    "sg:website":"http://www.furioferrari.com",
    "wof:name":"Ferrari Dott. Furio",
    "wof:placetype":"venue"
},
  "geometry": {"coordinates":[7.65794,45.054478],"type":"Point"}
}