{
  "type": "Feature",
  "properties": {
    "iso:country":"IT",
    "sg:address":"00146 Roma",
    "sg:city":"Roma",
    "sg:orig_category":"Forniture Per Agricoltura E Zootecnia. Animali Domestici",
    "sg:phone":"+39 06 556 1331",
    "sg:postcode":"00146",
    "sg:province":"Roma",
    "wof:name":"Farmacia Magliana Antica",
    "wof:placetype":"venue"
},
  "geometry": {"coordinates":[12.4649248123,41.8646621704],"type":"Point"}
}