{
  "type": "Feature",
  "properties": {
    "iso:country":"IT",
    "sg:address":"41100 Modena",
    "sg:city":"Modena",
    "sg:orig_category":"Automobili E Mezzi Di Trasporto",
    "sg:phone":"+39 059 281821",
    "sg:postcode":"41100",
    "sg:province":"Modena",
    "wof:name":"Merkeryshima Spa",
    "wof:placetype":"venue"
},
  "geometry": {"coordinates":[10.966105,44.632629],"type":"Point"}
}