{
  "type": "Feature",
  "properties": {
    "addr:full":"26013 Crema Crema Cremona 26013",
    "addr:postcode":"26013;26013",
    "iso:country":"IT",
    "sg:address":"26013 Crema",
    "sg:city":"Crema",
    "sg:orig_category":"Pubblicita', Marketing E Comunicazione",
    "sg:phone":"+39 0373 200738",
    "sg:postcode":"26013",
    "sg:province":"Cremona",
    "wof:name":"Beltrame Vittorio & C. Snc",
    "wof:placetype":"venue"
},
  "geometry": {"coordinates":[9.6782627106,45.3699569702],"type":"Point"}
}