{
  "type": "Feature",
  "properties": {
    "iso:country":"IT",
    "sg:address":"Via Luca Giordano 85 A; Napoli; 80127",
    "sg:city":"Napoli",
    "sg:classifiers":[
        {
            "category":"Banks & Credit Unions",
            "subcategory":"Bank",
            "type":"Services"
        }
    ],
    "sg:phone":"+39 081 377644",
    "sg:postcode":"80127",
    "sg:province":"Napoli",
    "wof:name":"Banco Di Roma",
    "wof:placetype":"venue"
},
  "geometry": {"coordinates":[14.227809,40.846016],"type":"Point"}
}