{
  "type": "Feature",
  "properties": {
    "addr:full":"87036 Rende Rende Cosenza 87036",
    "addr:postcode":"87036;87036",
    "iso:country":"IT",
    "sg:address":"87036 Rende",
    "sg:city":"Rende",
    "sg:classifiers":[
        {
            "category":"Health Services",
            "subcategory":"Health Practitioner",
            "type":"Services"
        }
    ],
    "sg:phone":"+39 338 960 5975",
    "sg:postcode":"87036",
    "sg:province":"Cosenza",
    "sg:tags":[
        "medici"
    ],
    "wof:name":"Orrico Dott.ssa Antonella",
    "wof:placetype":"venue"
},
  "geometry": {"coordinates":[16.2444076538,39.351348877],"type":"Point"}
}