{
  "type": "Feature",
  "properties": {
    "addr:full":"Piazza Roma 1; Giussano",
    "addr:housenumber":"1",
    "addr:street":"Piazza Roma",
    "iso:country":"IT",
    "sg:address":"Piazza Roma 1; Giussano",
    "sg:classifiers":[
        {
            "category":"Banks & Credit Unions",
            "subcategory":"Bank",
            "type":"Services"
        }
    ],
    "sg:phone":"+39 036 285 0449",
    "wof:name":"Banca Di Roma",
    "wof:placetype":"venue"
},
  "geometry": {"coordinates":[9.210068,45.699139],"type":"Point"}
}