{
  "type": "Feature",
  "properties": {
    "addr:full":"25, Via Torino 22063 Cantu' Como 22063",
    "addr:postcode":"22063;22063",
    "addr:street":"Via Torino;Cantu ' Como",
    "iso:country":"IT",
    "sg:address":"25, Via Torino 22063 Cantu'",
    "sg:classifiers":[
        {
            "category":"Manufacturing",
            "subcategory":"Glass & Minerals",
            "type":"Manufacturing & Wholesale Goods"
        }
    ],
    "sg:phone":"+39 39031714973",
    "sg:postcode":"22063",
    "sg:province":"Como",
    "wof:name":"Mi.ro. Glass",
    "wof:placetype":"venue"
},
  "geometry": {"coordinates":[9.133175,45.728283],"type":"Point"}
}