{
  "type": "Feature",
  "properties": {
    "addr:full":"Loc Cabianchino 61021 Carpegna Carpegna Pesaro E Urbino 61021",
    "addr:postcode":"61021;61021",
    "addr:street":"Loc Cabianchino",
    "iso:country":"IT",
    "sg:address":"Loc Cabianchino 61021 Carpegna",
    "sg:city":"Carpegna",
    "sg:classifiers":[
        {
            "category":"Real Estate",
            "subcategory":"Surveying",
            "type":"Services"
        }
    ],
    "sg:phone":"+39 39072272721",
    "sg:postcode":"61021",
    "sg:province":"Pesaro E Urbino",
    "sg:tags":[
        "equipment",
        "material",
        "good",
        "-",
        "handling"
    ],
    "wof:name":"Mo.ri.na T Srl",
    "wof:placetype":"venue"
},
  "geometry": {"coordinates":[12.529803,43.633556],"type":"Point"}
}