{
  "type": "Feature",
  "properties": {
    "addr:full":"Via Castel Morrone, 1 Milan 20129",
    "addr:housenumber":"1",
    "addr:postcode":"20129",
    "addr:street":"Via Castel Morrone",
    "iso:country":"IT",
    "sg:address":"Via Castel Morrone, 1",
    "sg:city":"Milan",
    "sg:classifiers":[
        {
            "category":"Professional",
            "subcategory":"Management & Consulting",
            "type":"Services"
        }
    ],
    "sg:postcode":"20129",
    "sg:tags":[
        "web-application",
        "backend-tasks",
        "web-design"
    ],
    "sg:website":"http://wonsys.net",
    "wof:name":"Wonsys",
    "wof:placetype":"venue"
},
  "geometry": {"coordinates":[9.214761,45.468399],"type":"Point"}
}