{
  "type": "Feature",
  "properties": {
    "addr:full":"23, V. Garibaldi 50031 Barberino Di Mugello Barberino di Mugello Firenze 50031",
    "addr:housenumber":"23",
    "addr:postcode":"50031;50031",
    "addr:street":"V. Garibaldi",
    "iso:country":"IT",
    "sg:address":"23, V. Garibaldi 50031 Barberino Di Mugello",
    "sg:city":"Barberino di Mugello",
    "sg:classifiers":[
        {
            "category":"Professional",
            "subcategory":"Engineering",
            "type":"Services"
        }
    ],
    "sg:phone":"+39 055 847 9065",
    "sg:postcode":"50031",
    "sg:province":"Firenze",
    "sg:tags":[
        "machine",
        "-",
        "mechanical"
    ],
    "sg:website":"http://www.paginegialle.it/sipem-01",
    "wof:name":"Sipem Srl",
    "wof:placetype":"venue"
},
  "geometry": {"coordinates":[11.256902,43.768734],"type":"Point"}
}