{
  "type": "Feature",
  "properties": {
    "iso:country":"IT",
    "sg:address":"145, V. Candia 00192 Roma",
    "sg:city":"Roma",
    "sg:classifiers":[
        {
            "category":"Parking",
            "subcategory":"Lot",
            "type":"Transportation"
        }
    ],
    "sg:phone":"+39 06 3972 3972",
    "sg:postcode":"00192",
    "sg:province":"Roma",
    "sg:tags":[
        "transport",
        "road"
    ],
    "sg:website":"http://www.mottasrl.it",
    "wof:name":"M.o.t.t.a.",
    "wof:placetype":"venue"
},
  "geometry": {"coordinates":[12.450313,41.907475],"type":"Point"}
}