{
  "type": "Feature",
  "properties": {
    "iso:country":"IT",
    "sg:address":"20090 Settala",
    "sg:city":"Caleppio",
    "sg:orig_category":"Tessuti Arredamento, Tende E Tappeti",
    "sg:phone":"+39 02 958 9410",
    "sg:postcode":"20090",
    "sg:province":"Milano",
    "wof:name":"Arten Snc",
    "wof:placetype":"venue"
},
  "geometry": {"coordinates":[9.382722,45.429424],"type":"Point"}
}