{
  "type": "Feature",
  "properties": {
    "addr:full":"145, Via Di Fioranello 00134 Roma Roma Roma 00134",
    "addr:housenumber":"145",
    "addr:postcode":"00134;00134",
    "addr:street":"Via Di Fioranello",
    "iso:country":"IT",
    "sg:address":"145, Via Di Fioranello 00134 Roma",
    "sg:city":"Roma",
    "sg:classifiers":[
        {
            "category":"Shopping",
            "subcategory":"Computers & Home Electronics",
            "type":"Retail Goods"
        }
    ],
    "sg:phone":"+39 06 7135 5525",
    "sg:postcode":"00134",
    "sg:province":"Roma",
    "sg:tags":[
        "electronic",
        "electrical",
        "equipment"
    ],
    "wof:name":"Euroiset (s.r.l.)",
    "wof:placetype":"venue"
},
  "geometry": {"coordinates":[12.434388,41.831562],"type":"Point"}
}