{
  "type": "Feature",
  "properties": {
    "iso:country":"IT",
    "sg:address":"10064 Pinerolo",
    "sg:city":"Pinerolo",
    "sg:orig_category":"Gioielleria, Oreficeria E Argenteria. Shopping",
    "sg:phone":"+39 0121 322568",
    "sg:postcode":"10064",
    "sg:province":"Torino",
    "wof:name":"Bresso Angelo",
    "wof:placetype":"venue"
},
  "geometry": {"coordinates":[7.371718,44.893055],"type":"Point"}
}