{
  "type": "Feature",
  "properties": {
    "addr:full":"31, V. Pertini - Zona Industriale 62012 Civitanova Marche Civitanova Marche Macerata 62012",
    "addr:housenumber":"31",
    "addr:postcode":"62012;62012",
    "addr:street":"V. Pertini Zona Industriale",
    "iso:country":"IT",
    "sg:address":"31, V. Pertini - Zona Industriale 62012 Civitanova Marche",
    "sg:city":"Civitanova Marche",
    "sg:classifiers":[
        {
            "category":"Personal",
            "subcategory":"Shoe Repair & Shine",
            "type":"Services"
        }
    ],
    "sg:phone":"+39 0733 800811",
    "sg:postcode":"62012",
    "sg:province":"Macerata",
    "sg:tags":[
        "leather"
    ],
    "sg:website":"http://www.paginegialle.it/margom-01",
    "wof:name":"Margom Srl",
    "wof:placetype":"venue"
},
  "geometry": {"coordinates":[13.456262,43.300747],"type":"Point"}
}