{
  "type": "Feature",
  "properties": {
    "iso:country":"IT",
    "sg:address":"9, Via Canaletto 60019 Senigallia",
    "sg:city":"Senigallia",
    "sg:classifiers":[
        {
            "category":"Shopping",
            "subcategory":"Clothing, Apparel, & Fashions",
            "type":"Retail Goods"
        }
    ],
    "sg:phone":"+39 39071668049",
    "sg:postcode":"60019",
    "sg:province":"Ancona",
    "sg:tags":[
        "clothes"
    ],
    "wof:name":"Confezioni Pierre Di Rossini Mariella & C.",
    "wof:placetype":"venue"
},
  "geometry": {"coordinates":[13.195403,43.728912],"type":"Point"}
}