{
  "type": "Feature",
  "properties": {
    "addr:full":"20037 Paderno Dugnano Paderno Dugnano Milano 20037",
    "addr:postcode":"20037;20037",
    "iso:country":"IT",
    "sg:address":"20037 Paderno Dugnano",
    "sg:city":"Paderno Dugnano",
    "sg:orig_category":"Articoli Pulizia. Carta, Cartone E Prodotti Primari. Prodotti Cosmetici E Da Toeletta",
    "sg:phone":"+39 02 918 1355",
    "sg:postcode":"20037",
    "sg:province":"Milano",
    "wof:name":"Am.to (s.n.c.)",
    "wof:placetype":"venue"
},
  "geometry": {"coordinates":[9.165154,45.56929],"type":"Point"}
}