{
  "type": "Feature",
  "properties": {
    "addr:full":"43100 Parma Baganzola Parma 43100",
    "addr:postcode":"43100;43100",
    "iso:country":"IT",
    "sg:address":"43100 Parma",
    "sg:city":"Baganzola",
    "sg:orig_category":"Macchine Ed Impianti Per Edilizia E Lavori Pubblici. Forniture Per Edilizia E Lavori Pubblici",
    "sg:phone":"+39 0521 987396",
    "sg:postcode":"43100",
    "sg:province":"Parma",
    "wof:name":"Carelia Srl",
    "wof:placetype":"venue"
},
  "geometry": {"coordinates":[10.309288,44.857605],"type":"Point"}
}