{
  "type": "Feature",
  "properties": {
    "iso:country":"IT",
    "sg:address":"02100 Rieti",
    "sg:city":"Rieti",
    "sg:orig_category":"Automazione E Macchine Per Ufficio. Servizi Ausiliari Di Certificati, Riproduzioni, Disegni E Foto",
    "sg:phone":"+39 0746 251282",
    "sg:postcode":"02100",
    "sg:province":"Rieti",
    "wof:name":"Gemprint Societa' A Responsabilita' Limitata",
    "wof:placetype":"venue"
},
  "geometry": {"coordinates":[12.883499,42.408981],"type":"Point"}
}