{
  "type": "Feature",
  "properties": {
    "iso:country":"IT",
    "sg:address":"82, Via Battisti Cesare 36045 Lonigo",
    "sg:city":"Lonigo",
    "sg:classifiers":[
        {
            "category":"Food & Beverages",
            "subcategory":"Groceries & Convenience Stores",
            "type":"Retail Goods"
        }
    ],
    "sg:phone":"+39 0444 436466",
    "sg:postcode":"36045",
    "sg:province":"Vicenza",
    "sg:tags":[
        "product",
        "related"
    ],
    "wof:name":"Brendolan Prosciutti (s.p.a.)",
    "wof:placetype":"venue"
},
  "geometry": {"coordinates":[11.540307045,45.5459060669],"type":"Point"}
}