{
  "type": "Feature",
  "properties": {
    "iso:country":"IT",
    "sg:address":"74/b, Via Emilia Ovest 43100 Parma",
    "sg:city":"Parma",
    "sg:classifiers":[
        {
            "category":"Manufacturing",
            "subcategory":"Metals",
            "type":"Manufacturing & Wholesale Goods"
        }
    ],
    "sg:phone":"+39 0521 277611",
    "sg:postcode":"43100",
    "sg:province":"Parma",
    "sg:tags":[
        "metallurgy",
        "metalworking"
    ],
    "wof:name":"Commercial Dado Spa",
    "wof:placetype":"venue"
},
  "geometry": {"coordinates":[10.2949199677,44.8232078552],"type":"Point"}
}