{
  "type": "Feature",
  "properties": {
    "iso:country":"IT",
    "sg:address":"20121 Milano",
    "sg:city":"Milano",
    "sg:orig_category":"Servizi Vari Di Interesse Pubblico",
    "sg:phone":"+39 02 801111",
    "sg:postcode":"20121",
    "sg:province":"Milano",
    "wof:name":"Astropony Srl",
    "wof:placetype":"venue"
},
  "geometry": {"coordinates":[9.186421,45.475124],"type":"Point"}
}