{
  "type": "Feature",
  "properties": {
    "iso:country":"IT",
    "sg:address":"46047 Porto Mantovano",
    "sg:city":"Porto Mantovano",
    "sg:orig_category":"Macchine, Impianti E Forniture Per Industria Grafica, Cartaria E Cartotecnica. Automazione E Macchine Per Ufficio",
    "sg:phone":"+39 0376 386371",
    "sg:postcode":"46047",
    "sg:province":"Mantova",
    "sg:website":"http://www.mainoldieturcato.it",
    "wof:name":"Mainoldi E Turcato",
    "wof:placetype":"venue"
},
  "geometry": {"coordinates":[10.77345,45.192951],"type":"Point"}
}