{
  "type": "Feature",
  "properties": {
    "iso:country":"IT",
    "sg:address":"00054 Fiumicino",
    "sg:city":"Fiumicino",
    "sg:orig_category":"Alberghi",
    "sg:phone":"+39 06 658 3839",
    "sg:postcode":"00054",
    "sg:province":"Roma",
    "wof:name":"Michisanti Giovanni",
    "wof:placetype":"venue"
},
  "geometry": {"coordinates":[12.254793,41.767517],"type":"Point"}
}