{
  "type": "Feature",
  "properties": {
    "addr:full":"20135 Milano Milano Milano 20135",
    "addr:postcode":"20135;20135",
    "iso:country":"IT",
    "sg:address":"20135 Milano",
    "sg:city":"Milano",
    "sg:orig_category":"Stampe Artistiche",
    "sg:phone":"+39 02 5830 0822",
    "sg:postcode":"20135",
    "sg:province":"Milano",
    "wof:name":"Egim. Srl",
    "wof:placetype":"venue"
},
  "geometry": {"coordinates":[9.199273,45.446667],"type":"Point"}
}