{
  "type": "Feature",
  "properties": {
    "iso:country":"IT",
    "sg:address":"Piazza Garibaldi, 9; Volta; 46049",
    "sg:classifiers":[
        {
            "category":"Banks & Credit Unions",
            "subcategory":"Bank",
            "type":"Services"
        }
    ],
    "sg:phone":"+39 0376 801332",
    "sg:postcode":"46049",
    "sg:province":"Mantova",
    "wof:name":"Banca Agricola Mantovana",
    "wof:placetype":"venue"
},
  "geometry": {"coordinates":[10.735342,45.352367],"type":"Point"}
}