{
  "type": "Feature",
  "properties": {
    "iso:country":"IT",
    "sg:address":"51039 Quarrata",
    "sg:city":"Quarrata",
    "sg:orig_category":"Macchine E Forniture Per Arredamento E Industria Del Legno",
    "sg:phone":"+39 0573 738703",
    "sg:postcode":"51039",
    "sg:province":"Pistoia",
    "wof:name":"F.i.d.a. Di Innocenti Daniele",
    "wof:placetype":"venue"
},
  "geometry": {"coordinates":[11.005282,43.904789],"type":"Point"}
}