{
  "type": "Feature",
  "properties": {
    "iso:country":"IT",
    "sg:address":"Via Sant' Antonino 6 R; Florence; 50123",
    "sg:classifiers":[
        {
            "category":"Travel",
            "subcategory":"Travel Agent",
            "type":"Entertainment"
        }
    ],
    "sg:phone":"+39 390 552 8320",
    "sg:postcode":"50123",
    "sg:province":"Firenze",
    "sg:website":"www.caftours.com",
    "wof:name":"Caf Tour & Travel",
    "wof:placetype":"venue"
},
  "geometry": {"coordinates":[11.251118,43.775288],"type":"Point"}
}