{
  "type": "Feature",
  "properties": {
    "iso:country":"IT",
    "sg:address":"10126 Torino",
    "sg:city":"Torino",
    "sg:orig_category":"Termotecnica E Riscaldamento, Apparecchiature E Servizi. Prodotti Vari In Metallo",
    "sg:phone":"+39 011 669 9911",
    "sg:postcode":"10126",
    "sg:province":"Torino",
    "wof:name":"Ucav-to Snc",
    "wof:placetype":"venue"
},
  "geometry": {"coordinates":[7.673777,45.050827],"type":"Point"}
}