{
  "type": "Feature",
  "properties": {
    "addr:full":"47023 Cesena Cesena Forl\u00ec-Cesena 47023",
    "addr:postcode":"47023;47023",
    "iso:country":"IT",
    "sg:address":"47023 Cesena",
    "sg:city":"Cesena",
    "sg:orig_category":"Pelli Per Pellicceria",
    "sg:phone":"+39 0547 610722",
    "sg:postcode":"47023",
    "sg:province":"Forl\u00ec-Cesena",
    "wof:name":"Pellicceria U. Biagini Eredi Snc",
    "wof:placetype":"venue"
},
  "geometry": {"coordinates":[11.9804611206,43.9947662354],"type":"Point"}
}