{
  "type": "Feature",
  "properties": {
    "iso:country":"IT",
    "sg:address":"31058 Susegana",
    "sg:city":"Susegana",
    "sg:orig_category":"Elettricita' Materiali - Produzione",
    "sg:phone":"+39 0438 60583",
    "sg:postcode":"31058",
    "sg:province":"Treviso",
    "wof:name":"Ht Spa",
    "wof:placetype":"venue"
},
  "geometry": {"coordinates":[12.277253,45.872833],"type":"Point"}
}