{
  "type": "Feature",
  "properties": {
    "iso:country":"IT",
    "sg:address":"20063 Cernusco Sul Naviglio",
    "sg:city":"Cernusco sul Naviglio",
    "sg:orig_category":"Scuole E Servizi Scolastici",
    "sg:phone":"+39 02 923 5916",
    "sg:postcode":"20063",
    "sg:province":"Milano",
    "wof:name":"Scuola Elementare L'aurora",
    "wof:placetype":"venue"
},
  "geometry": {"coordinates":[9.324529,45.523693],"type":"Point"}
}