{
  "type": "Feature",
  "properties": {
    "iso:country":"IT",
    "sg:address":"33100 Udine",
    "sg:city":"Udine",
    "sg:classifiers":[
        {
            "category":"Professional",
            "subcategory":"Art Services",
            "type":"Services"
        }
    ],
    "sg:phone":"+39 0432 512528",
    "sg:postcode":"33100",
    "sg:province":"Udine",
    "sg:tags":[
        "studi",
        "designer",
        "-"
    ],
    "wof:name":"Friul Giotto A. V. Distribuzioni",
    "wof:placetype":"venue"
},
  "geometry": {"coordinates":[13.238148,46.055527],"type":"Point"}
}