{
  "type": "Feature",
  "properties": {
    "iso:country":"IT",
    "sg:address":"64018 Tortoreto",
    "sg:city":"Salino",
    "sg:classifiers":[
        {
            "category":"Home & Garden",
            "subcategory":"Home Furnishings",
            "type":"Retail Goods"
        }
    ],
    "sg:phone":"+39 0861 786222",
    "sg:postcode":"64018",
    "sg:province":"Teramo",
    "sg:tags":[
        "activities",
        "commercial",
        "equipment",
        "artisan",
        "professional",
        "furniture"
    ],
    "sg:website":"http://www.frigomeccanica.com",
    "wof:name":"Frigomeccanica Srl",
    "wof:placetype":"venue"
},
  "geometry": {"coordinates":[13.9134807587,42.7864952087],"type":"Point"}
}