{
  "type": "Feature",
  "properties": {
    "addr:full":"V Dismano 4902; Cesena; 47023 Cesena Forl\u00ec-Cesena 47023",
    "addr:housenumber":"4902",
    "addr:postcode":"47023;47023",
    "addr:street":"V Dismano",
    "iso:country":"IT",
    "sg:address":"V Dismano 4902; Cesena; 47023",
    "sg:city":"Cesena",
    "sg:classifiers":[
        {
            "category":"Banks & Credit Unions",
            "subcategory":"Bank",
            "type":"Services"
        }
    ],
    "sg:phone":"+39 0544 4902",
    "sg:postcode":"47023",
    "sg:province":"Forl\u00ec-Cesena",
    "wof:name":"Credito Romagnolo",
    "wof:placetype":"venue"
},
  "geometry": {"coordinates":[12.217715,44.188881],"type":"Point"}
}