{
  "type": "Feature",
  "properties": {
    "addr:full":"20068 Peschiera Borromeo Peschiera Borromeo Milano 20068",
    "addr:postcode":"20068;20068",
    "iso:country":"IT",
    "sg:address":"20068 Peschiera Borromeo",
    "sg:city":"Peschiera Borromeo",
    "sg:orig_category":"Accessori Moda D'abbigliamento. Forniture Per Abbigliamento E Pelletterie. Shopping",
    "sg:phone":"+39 02 5530 5786",
    "sg:postcode":"20068",
    "sg:province":"Milano",
    "wof:name":"Viceversa Srl",
    "wof:placetype":"venue"
},
  "geometry": {"coordinates":[9.302252,45.430054],"type":"Point"}
}