{
  "type": "Feature",
  "properties": {
    "addr:full":"20013 Magenta Magenta Milano 20013",
    "addr:postcode":"20013;20013",
    "iso:country":"IT",
    "sg:address":"20013 Magenta",
    "sg:city":"Magenta",
    "sg:orig_category":"Minuterie Metalliche E Ferramenta",
    "sg:phone":"+39 02 9729 2228",
    "sg:postcode":"20013",
    "sg:province":"Milano",
    "wof:name":"Nobex Srl",
    "wof:placetype":"venue"
},
  "geometry": {"coordinates":[9.1509017944,45.4929122925],"type":"Point"}
}