{
  "type": "Feature",
  "properties": {
    "iso:country":"IT",
    "sg:address":"31, Via I Maggio 75100 Matera",
    "sg:city":"Matera",
    "sg:classifiers":[
        {
            "category":"Home & Garden",
            "subcategory":"Home Furnishings",
            "type":"Retail Goods"
        }
    ],
    "sg:phone":"+39 0835 259415",
    "sg:postcode":"75100",
    "sg:province":"Matera",
    "sg:tags":[
        "household"
    ],
    "wof:name":"Soft Sofa' Di Andrisani Spera Maria",
    "wof:placetype":"venue"
},
  "geometry": {"coordinates":[16.606087,40.668652],"type":"Point"}
}