{
  "type": "Feature",
  "properties": {
    "iso:country":"IT",
    "sg:address":"22, Via Di Gabbiano 50026 San Casciano In Val Di Pesa",
    "sg:city":"San Casciano in Val di Pesa",
    "sg:classifiers":[
        {
            "category":"Food & Beverages",
            "subcategory":"Groceries & Convenience Stores",
            "type":"Retail Goods"
        }
    ],
    "sg:phone":"+39 39055821053",
    "sg:postcode":"50026",
    "sg:province":"Firenze",
    "sg:tags":[
        "drink"
    ],
    "wof:name":"Icaro - S.p.a.",
    "wof:placetype":"venue"
},
  "geometry": {"coordinates":[11.256902,43.768734],"type":"Point"}
}