{
  "type": "Feature",
  "properties": {
    "addr:full":"19, Via Valdirivo 34132 Trieste Trieste Trieste 34132",
    "addr:postcode":"34132;34132",
    "addr:street":"Via Valdirivo",
    "iso:country":"IT",
    "sg:address":"19, Via Valdirivo 34132 Trieste",
    "sg:city":"Trieste",
    "sg:orig_category":"Miscellaneous Products",
    "sg:phone":"+39 39040632091",
    "sg:postcode":"34132",
    "sg:province":"Trieste",
    "wof:name":"La Distributrice (s.p.a.)",
    "wof:placetype":"venue"
},
  "geometry": {"coordinates":[13.7742118835,45.653213501],"type":"Point"}
}