{
  "type": "Feature",
  "properties": {
    "addr:full":"20129 Milano Milano Milano 20129",
    "addr:postcode":"20129;20129",
    "iso:country":"IT",
    "sg:address":"20129 Milano",
    "sg:city":"Milano",
    "sg:orig_category":"Medici Specialisti - Oculistica",
    "sg:phone":"+39 02 7631 8174",
    "sg:postcode":"20129",
    "sg:province":"Milano",
    "sg:website":"http://www.carones.com",
    "wof:name":"Centro Oftalmo Chirurgico Carones",
    "wof:placetype":"venue"
},
  "geometry": {"coordinates":[9.203575,45.46632],"type":"Point"}
}