{
  "type": "Feature",
  "properties": {
    "iso:country":"IT",
    "sg:address":"22030 Lipomo",
    "sg:city":"Lipomo",
    "sg:orig_category":"Arredamenti - Vendita Al Dettaglio",
    "sg:phone":"+39 031 555474",
    "sg:postcode":"22030",
    "sg:province":"Como",
    "wof:name":"Arredamenti Vastalegna",
    "wof:placetype":"venue"
},
  "geometry": {"coordinates":[9.121426,45.793926],"type":"Point"}
}