{
  "type": "Feature",
  "properties": {
    "addr:full":"00148 Roma Roma Roma 00148",
    "addr:postcode":"00148;00148",
    "iso:country":"IT",
    "sg:address":"00148 Roma",
    "sg:city":"Roma",
    "sg:orig_category":"Impiantistica E Prodotti Tecnologici Per Edilizia. Elettrotecnica Industriale, Prodotti E Apparecchiature",
    "sg:phone":"+39 06 657 0634",
    "sg:postcode":"00148",
    "sg:province":"Roma",
    "wof:name":"Romana Cantieri Costruzioni Srl",
    "wof:placetype":"venue"
},
  "geometry": {"coordinates":[12.431009,41.833794],"type":"Point"}
}