{
  "type": "Feature",
  "properties": {
    "addr:full":"Via N. Tartaglia, 30/32 25064 Gussago Gussago Brescia 25064",
    "addr:housenumber":"30 / 32",
    "addr:postcode":"25064;25064",
    "addr:street":"Via N. Tartaglia",
    "iso:country":"IT",
    "sg:address":"Via N. Tartaglia, 30/32 25064 Gussago",
    "sg:city":"Gussago",
    "sg:classifiers":[
        {
            "category":"Home & Garden",
            "subcategory":"Building Materials",
            "type":"Retail Goods"
        }
    ],
    "sg:phone":"+39 030 241 1449",
    "sg:postcode":"25064",
    "sg:province":"Brescia",
    "sg:tags":[
        "fire-proof"
    ],
    "sg:website":"www.vrl.it",
    "wof:name":"Veneta Lombarda Refrattari Srl",
    "wof:placetype":"venue"
},
  "geometry": {"coordinates":[10.1589164734,45.554561615],"type":"Point"}
}