{
  "type": "Feature",
  "properties": {
    "iso:country":"IT",
    "sg:address":"50142 Firenze",
    "sg:city":"Firenze",
    "sg:orig_category":"Accessori Dei Mezzi Di Trasporto",
    "sg:phone":"+39 055 732446",
    "sg:postcode":"50142",
    "sg:province":"Firenze",
    "sg:website":"http://www.harleydavidsonfirenze.com",
    "wof:name":"Grandi Motori Srl",
    "wof:placetype":"venue"
},
  "geometry": {"coordinates":[11.190053,43.778824],"type":"Point"}
}