{
  "type": "Feature",
  "properties": {
    "addr:full":"Via Juker 28 20025 Legnano Legnano Milano 20025",
    "addr:housenumber":"28",
    "addr:postcode":"20025;20025",
    "addr:street":"Via Juker",
    "iso:country":"IT",
    "sg:address":"Via Juker 28 20025 Legnano",
    "sg:city":"Legnano",
    "sg:classifiers":[
        {
            "category":"Wholesale",
            "subcategory":"Chemicals & Plastics",
            "type":"Manufacturing & Wholesale Goods"
        }
    ],
    "sg:phone":"+39 0331 464097",
    "sg:postcode":"20025",
    "sg:province":"Milano",
    "sg:tags":[
        "processing",
        "machinery",
        "accessory"
    ],
    "wof:name":"Decatex S.r.l.",
    "wof:placetype":"venue"
},
  "geometry": {"coordinates":[8.925611,45.616169],"type":"Point"}
}