{
  "type": "Feature",
  "properties": {
    "addr:full":"11, Via Vivaldi Antonio 20020 Lainate Lainate Milano 20020",
    "addr:postcode":"20020;20020",
    "addr:street":"Via Vivaldi Antonio",
    "iso:country":"IT",
    "sg:address":"11, Via Vivaldi Antonio 20020 Lainate",
    "sg:city":"Lainate",
    "sg:classifiers":[
        {
            "category":"Professional",
            "subcategory":"Engineering",
            "type":"Services"
        }
    ],
    "sg:phone":"+39 39029370779",
    "sg:postcode":"20020",
    "sg:province":"Milano",
    "sg:tags":[
        "machine",
        "-",
        "mechanical"
    ],
    "wof:name":"Bazzi Carlo (s.r.l.)",
    "wof:placetype":"venue"
},
  "geometry": {"coordinates":[9.188141,45.463688],"type":"Point"}
}