{
  "type": "Feature",
  "properties": {
    "addr:full":"10020 Cambiano Cambiano Torino 10020",
    "addr:postcode":"10020;10020",
    "iso:country":"IT",
    "sg:address":"10020 Cambiano",
    "sg:city":"Cambiano",
    "sg:orig_category":"Elettrotecnica Industriale, Prodotti E Apparecchiature",
    "sg:phone":"+39 011 944 1641",
    "sg:postcode":"10020",
    "sg:province":"Torino",
    "wof:name":"Kab-lem Srl",
    "wof:placetype":"venue"
},
  "geometry": {"coordinates":[7.772493,44.965199],"type":"Point"}
}