{
  "type": "Feature",
  "properties": {
    "addr:full":"19020 Vezzano Ligure Vezzano Ligure La Spezia 19020",
    "addr:postcode":"19020;19020",
    "iso:country":"IT",
    "sg:address":"19020 Vezzano Ligure",
    "sg:city":"Vezzano Ligure",
    "sg:orig_category":"Videogiochi, Flippers E Biliardini - Produzione E Ingrosso",
    "sg:phone":"+39 0187 558529",
    "sg:postcode":"19020",
    "sg:province":"La Spezia",
    "wof:name":"Spezia Games",
    "wof:placetype":"venue"
},
  "geometry": {"coordinates":[9.894104,44.132164],"type":"Point"}
}