{
  "type": "Feature",
  "properties": {
    "iso:country":"IT",
    "sg:address":"22073 Fino Mornasco",
    "sg:city":"Fino Mornasco",
    "sg:orig_category":"Tessuti E Stoffe. Forniture Per Attivita' Industriali",
    "sg:phone":"+39 031 881151",
    "sg:postcode":"22073",
    "sg:province":"Como",
    "wof:name":"New Technik Company (s.r.l.)",
    "wof:placetype":"venue"
},
  "geometry": {"coordinates":[9.054928,45.733921],"type":"Point"}
}