{
  "type": "Feature",
  "properties": {
    "iso:country":"IT",
    "sg:address":"212, Corso Venticinque Aprile 14100 Asti",
    "sg:city":"Asti",
    "sg:classifiers":[
        {
            "category":"Shopping",
            "subcategory":"Computers & Home Electronics",
            "type":"Retail Goods"
        }
    ],
    "sg:phone":"+39 0141 219187",
    "sg:postcode":"14100",
    "sg:province":"Asti",
    "sg:tags":[
        "electronic",
        "electrical",
        "equipment"
    ],
    "wof:name":"Elettroforniture C.d.t. Spa",
    "wof:placetype":"venue"
},
  "geometry": {"coordinates":[8.206813,44.900864],"type":"Point"}
}