{
  "type": "Feature",
  "properties": {
    "iso:country":"IT",
    "sg:address":"Via Zoboli 10 42100 Reggio Emilia",
    "sg:orig_category":"Pumps Made Of Stainless Steel",
    "sg:phone":"+39 0522 513941",
    "sg:postcode":"42100",
    "sg:province":"Reggio Nell'Emilia",
    "sg:website":"www.hidrotecnik.it",
    "wof:name":"Hidrotecnik S.r.l.",
    "wof:placetype":"venue"
},
  "geometry": {"coordinates":[10.6570672989,44.7382392883],"type":"Point"}
}