{
  "type": "Feature",
  "properties": {
    "addr:full":"Via Raccordo Autostradale 8 12041 Bene Vagienna Bene Vagienna Cuneo 12041",
    "addr:housenumber":"8",
    "addr:postcode":"12041;12041",
    "addr:street":"Via Raccordo Autostradale",
    "iso:country":"IT",
    "sg:address":"Via Raccordo Autostradale 8 12041 Bene Vagienna",
    "sg:city":"Bene Vagienna",
    "sg:classifiers":[
        {
            "category":"Shopping",
            "subcategory":"Stationery & Office Supplies",
            "type":"Retail Goods"
        }
    ],
    "sg:phone":"+39 0172 651811",
    "sg:postcode":"12041",
    "sg:province":"Cuneo",
    "sg:tags":[
        "adhesive",
        "label"
    ],
    "sg:website":"www.eurostampa.com",
    "wof:name":"Industria Grafica Eurostampa Spa",
    "wof:placetype":"venue"
},
  "geometry": {"coordinates":[7.547111,44.388798],"type":"Point"}
}