{
  "type": "Feature",
  "properties": {
    "addr:full":"20027 Rescaldina Rescaldina Milano 20027",
    "addr:postcode":"20027;20027",
    "iso:country":"IT",
    "sg:address":"20027 Rescaldina",
    "sg:city":"Rescaldina",
    "sg:orig_category":"Macchine Utensili E Impianti",
    "sg:phone":"+39 0331 576280",
    "sg:postcode":"20027",
    "sg:province":"Milano",
    "wof:name":"Rosa Ermando (s.p.a.)",
    "wof:placetype":"venue"
},
  "geometry": {"coordinates":[9.218322,45.500504],"type":"Point"}
}