{
  "type": "Feature",
  "properties": {
    "iso:country":"IT",
    "sg:address":"25038 Rovato",
    "sg:city":"Rovato",
    "sg:orig_category":"Attrezzature E Forniture Per Officine Riparazione E Servizi Ausiliari",
    "sg:phone":"+39 030 772 2410",
    "sg:postcode":"25038",
    "sg:province":"Brescia",
    "wof:name":"Zani Alfredo Zani Gomme",
    "wof:placetype":"venue"
},
  "geometry": {"coordinates":[10.012017,45.557022],"type":"Point"}
}