{
  "type": "Feature",
  "properties": {
    "iso:country":"IT",
    "sg:address":"50056 Montelupo Fiorentino",
    "sg:city":"Montelupo Fiorentino",
    "sg:orig_category":"Prodotti E Manufatti In Materie Plastiche. Articoli Per Imballaggio E Confezionamento",
    "sg:phone":"+39 0571 541034",
    "sg:postcode":"50056",
    "sg:province":"Firenze",
    "wof:name":"Gori Pasquale E Antonio",
    "wof:placetype":"venue"
},
  "geometry": {"coordinates":[10.9939527512,43.7275123596],"type":"Point"}
}