{
  "type": "Feature",
  "properties": {
    "iso:country":"IT",
    "sg:address":"1, Contrada Terzi 66052 Gissi",
    "sg:city":"Gissi",
    "sg:classifiers":[
        {
            "category":"Wholesale",
            "subcategory":"Drugs",
            "type":"Manufacturing & Wholesale Goods"
        }
    ],
    "sg:phone":"+39 39087394521",
    "sg:postcode":"66052",
    "sg:province":"Chieti",
    "sg:tags":[
        "chemical",
        "pharmaceutical"
    ],
    "wof:name":"Cray Valley Italia S.r.l.",
    "wof:placetype":"venue"
},
  "geometry": {"coordinates":[14.596083,42.069969],"type":"Point"}
}