{
  "type": "Feature",
  "properties": {
    "iso:country":"IT",
    "sg:address":"30172 Venezia",
    "sg:city":"Venezia",
    "sg:orig_category":"Imprese Pulizia",
    "sg:phone":"+39 041 920011",
    "sg:postcode":"30172",
    "sg:province":"Venezia",
    "wof:name":"Astrocoop Universale - Pulizie, Manutenzioni E Trasporti Soc. Coop. A R.l.",
    "wof:placetype":"venue"
},
  "geometry": {"coordinates":[12.23123,45.480984],"type":"Point"}
}