{
  "type": "Feature",
  "properties": {
    "addr:full":"00182 Roma Roma Roma 00182",
    "addr:postcode":"00182;00182",
    "iso:country":"IT",
    "sg:address":"00182 Roma",
    "sg:city":"Roma",
    "sg:orig_category":"Professionisti - Studi E Servizi Ed Associazioni Di Interesse Aziendale. Associazioni Ed Organismi Di Interesse Pubblico",
    "sg:phone":"+39 06 7030 5707",
    "sg:postcode":"00182",
    "sg:province":"Roma",
    "wof:name":"Collegio Amministrativo Ferroviario Italiano",
    "wof:placetype":"venue"
},
  "geometry": {"coordinates":[12.5208730698,41.8791847229],"type":"Point"}
}