{
  "type": "Feature",
  "properties": {
    "iso:country":"IT",
    "sg:address":"31020 San Fior",
    "sg:city":"San Fior",
    "sg:orig_category":"Servizi Per Lo Sport E Il Tempo Libero. Servizi Al Turismo",
    "sg:phone":"+39 0438 402396",
    "sg:postcode":"31020",
    "sg:province":"Treviso",
    "wof:name":"C.a.v.s. Di Citron Angelo & C. Snc",
    "wof:placetype":"venue"
},
  "geometry": {"coordinates":[12.34208,45.908951],"type":"Point"}
}