{
  "type": "Feature",
  "properties": {
    "iso:country":"IT",
    "sg:address":"09122 Cagliari",
    "sg:city":"Cagliari",
    "sg:orig_category":"Prodotti E Manufatti In Materie Plastiche. Materiali Edili",
    "sg:phone":"+39 070 208 6057",
    "sg:postcode":"09122",
    "sg:province":"Cagliari",
    "wof:name":"Politec Srl",
    "wof:placetype":"venue"
},
  "geometry": {"coordinates":[9.1018285751,39.2456932068],"type":"Point"}
}