{
  "type": "Feature",
  "properties": {
    "addr:full":"Viale Aldo Moro N. 18; Bologna; 40127 Bologna Bologna 40127",
    "addr:housenumber":"18",
    "addr:postcode":"40127;40127",
    "addr:street":"Viale Aldo Moro N.",
    "iso:country":"IT",
    "sg:address":"Viale Aldo Moro N. 18; Bologna; 40127",
    "sg:city":"Bologna",
    "sg:classifiers":[
        {
            "category":"Banks & Credit Unions",
            "subcategory":"Bank",
            "type":"Services"
        }
    ],
    "sg:phone":"+39 051 298111",
    "sg:postcode":"40127",
    "sg:province":"Bologna",
    "wof:name":"Banca Del Monte",
    "wof:placetype":"venue"
},
  "geometry": {"coordinates":[11.362365,44.509109],"type":"Point"}
}