{
  "type": "Feature",
  "properties": {
    "iso:country":"IT",
    "sg:address":"63015 Monte Urano",
    "sg:city":"Monte Urano",
    "sg:orig_category":"Forniture Per Edilizia E Lavori Pubblici",
    "sg:phone":"+39 0734 841294",
    "sg:postcode":"63015",
    "sg:province":"Ascoli Piceno",
    "sg:website":"http://www.opuspavimenti.it",
    "wof:name":"Opus Snc Di Leva & Buccolini",
    "wof:placetype":"venue"
},
  "geometry": {"coordinates":[13.6804208755,43.1759414673],"type":"Point"}
}