{
  "type": "Feature",
  "properties": {
    "iso:country":"IT",
    "sg:address":"25080 Mazzano",
    "sg:city":"Mazzano",
    "sg:orig_category":"Macchine, Impianti Ed Attrezzature Per Industria Alimentare E Bevande",
    "sg:phone":"+39 030 259 0755",
    "sg:postcode":"25080",
    "sg:province":"Brescia",
    "wof:name":"Tecnopan",
    "wof:placetype":"venue"
},
  "geometry": {"coordinates":[10.215549,45.535877],"type":"Point"}
}