{
  "type": "Feature",
  "properties": {
    "iso:country":"IT",
    "sg:address":"Via Cavour, 11/13; Montodine; 26010",
    "sg:city":"Montodine",
    "sg:classifiers":[
        {
            "category":"Banks & Credit Unions",
            "subcategory":"Bank",
            "type":"Services"
        }
    ],
    "sg:phone":"+39 0373 66102",
    "sg:postcode":"26010",
    "sg:province":"Cremona",
    "wof:name":"Casse Rurali Ed Artigiane",
    "wof:placetype":"venue"
},
  "geometry": {"coordinates":[9.711144,45.286163],"type":"Point"}
}