{
  "type": "Feature",
  "properties": {
    "addr:full":"21040 Carnago Carnago Varese 21040",
    "addr:postcode":"21040;21040",
    "iso:country":"IT",
    "sg:address":"21040 Carnago",
    "sg:city":"Carnago",
    "sg:orig_category":"Audiovisivi Filmati, Spot E Multimediali - Realizzazione E Duplicazione",
    "sg:phone":"+39 0331 985545",
    "sg:postcode":"21040",
    "sg:province":"Varese",
    "wof:name":"Studio Millennium Di Bassani Davide",
    "wof:placetype":"venue"
},
  "geometry": {"coordinates":[8.874603,45.755814],"type":"Point"}
}