{
  "type": "Feature",
  "properties": {
    "iso:country":"IT",
    "sg:address":"91/5, Via Bisceglie 20152 Milano",
    "sg:city":"Milano",
    "sg:classifiers":[
        {
            "category":"Wholesale",
            "subcategory":"Drugs",
            "type":"Manufacturing & Wholesale Goods"
        }
    ],
    "sg:phone":"+39 02 4830 0027",
    "sg:postcode":"20152",
    "sg:province":"Milano",
    "sg:tags":[
        "chemical",
        "pharmaceutical"
    ],
    "wof:name":"Repico (s.r.l.)",
    "wof:placetype":"venue"
},
  "geometry": {"coordinates":[9.120055,45.449001],"type":"Point"}
}