{
  "type": "Feature",
  "properties": {
    "iso:country":"IT",
    "sg:address":"09129 Cagliari",
    "sg:city":"Cagliari",
    "sg:orig_category":"Scuole E Servizi Scolastici",
    "sg:phone":"+39 070 403655",
    "sg:postcode":"09129",
    "sg:province":"Cagliari",
    "sg:website":"http://www.cambosu.com",
    "wof:name":"Istituto Cambosu",
    "wof:placetype":"venue"
},
  "geometry": {"coordinates":[9.125978,39.217064],"type":"Point"}
}