{
  "type": "Feature",
  "properties": {
    "addr:full":"46100 Mantova Mantova Mantova 46100",
    "addr:postcode":"46100;46100",
    "iso:country":"IT",
    "sg:address":"46100 Mantova",
    "sg:city":"Mantova",
    "sg:orig_category":"Disegno, Grafica E Belle Arti - Articoli",
    "sg:phone":"+39 0376 326630",
    "sg:postcode":"46100",
    "sg:province":"Mantova",
    "sg:website":"http://www.eliograf.it",
    "wof:name":"Eliograf Di Previti Giovanni & Figlio Snc",
    "wof:placetype":"venue"
},
  "geometry": {"coordinates":[10.790153,45.156052],"type":"Point"}
}