{
  "type": "Feature",
  "properties": {
    "iso:country":"IT",
    "sg:address":"30, Via Guglielmo Marconi 37030 Badia Calavena",
    "sg:city":"Badia Calavena",
    "sg:classifiers":[
        {
            "category":"Parking",
            "subcategory":"Lot",
            "type":"Transportation"
        }
    ],
    "sg:phone":"+39 045 781 0526",
    "sg:postcode":"37030",
    "sg:province":"Verona",
    "sg:tags":[
        "transport",
        "road"
    ],
    "wof:name":"Anselmi S.r.l.",
    "wof:placetype":"venue"
},
  "geometry": {"coordinates":[11.153433,45.567005],"type":"Point"}
}