{
  "type": "Feature",
  "properties": {
    "iso:country":"IT",
    "sg:address":"Via Ermete Zacconi 5/a 43100 Parma",
    "sg:city":"Parma",
    "sg:orig_category":"Hardening Furnaces For Glass",
    "sg:phone":"+39 0521 780749",
    "sg:postcode":"43100",
    "sg:province":"Parma",
    "wof:name":"Lema Srl",
    "wof:placetype":"venue"
},
  "geometry": {"coordinates":[10.29492,44.823208],"type":"Point"}
}