{
  "type": "Feature",
  "properties": {
    "iso:country":"IT",
    "sg:address":"16/d, V. Chiavari 43100 Parma",
    "sg:city":"Parma",
    "sg:classifiers":[
        {
            "category":"Autos & Motor Vehicles",
            "subcategory":"Automobile Sales",
            "type":"Retail Goods"
        }
    ],
    "sg:phone":"+39 0521 992847",
    "sg:postcode":"43100",
    "sg:province":"Parma",
    "sg:tags":[
        "industrial"
    ],
    "sg:website":"http://www.vezzoniricambi.com",
    "wof:name":"Tino Vezzoni Srl",
    "wof:placetype":"venue"
},
  "geometry": {"coordinates":[10.30772,44.785767],"type":"Point"}
}