{
  "type": "Feature",
  "properties": {
    "iso:country":"IT",
    "sg:address":"39, Via Leonardo Da Vinci 20094 Corsico",
    "sg:city":"Corsico",
    "sg:classifiers":[
        {
            "category":"Manufacturing",
            "subcategory":"Metals",
            "type":"Manufacturing & Wholesale Goods"
        }
    ],
    "sg:phone":"+39 39024505121",
    "sg:postcode":"20094",
    "sg:province":"Milano",
    "sg:tags":[
        "metallurgy",
        "metalworking"
    ],
    "wof:name":"Invitea Spa",
    "wof:placetype":"venue"
},
  "geometry": {"coordinates":[9.1078901291,45.4481201172],"type":"Point"}
}