{
  "type": "Feature",
  "properties": {
    "iso:country":"IT",
    "sg:address":"20047 Brugherio",
    "sg:city":"Brugherio",
    "sg:orig_category":"Macchine Ed Impianti Per Edilizia E Lavori Pubblici",
    "sg:phone":"+39 039 870003",
    "sg:postcode":"20047",
    "sg:province":"Milano",
    "wof:name":"Cave Rocca Srl",
    "wof:placetype":"venue"
},
  "geometry": {"coordinates":[9.232317,45.541328],"type":"Point"}
}