{
  "type": "Feature",
  "properties": {
    "addr:full":"43100 San Prospero Parmense San prospero parmense Parma 43100",
    "addr:housenumber":"43100",
    "addr:postcode":"43100",
    "addr:street":"San;Parmense",
    "iso:country":"IT",
    "sg:address":"43100 San Prospero Parmense",
    "sg:city":"San prospero parmense",
    "sg:orig_category":"Macchine, Impianti Ed Attrezzature Per Industria Alimentare E Bevande",
    "sg:phone":"+39 0521 242852",
    "sg:postcode":"43100",
    "sg:province":"Parma",
    "wof:name":"C.m.a. (s.r.l.)",
    "wof:placetype":"venue"
},
  "geometry": {"coordinates":[10.329548,44.807865],"type":"Point"}
}