{
  "type": "Feature",
  "properties": {
    "addr:full":"Via Don L. Meroni 56 22060 Figino Serenza Figino Serenza Como 22060",
    "addr:housenumber":"56;serenza",
    "addr:postcode":"22060;22060",
    "addr:street":"Via Don L. Meroni;Como",
    "iso:country":"IT",
    "sg:address":"Via Don L. Meroni 56 22060 Figino Serenza",
    "sg:city":"Figino Serenza",
    "sg:classifiers":[
        {
            "category":"Manufacturing",
            "subcategory":"Wood Products",
            "type":"Manufacturing & Wholesale Goods"
        }
    ],
    "sg:phone":"+39 031 780150",
    "sg:postcode":"22060",
    "sg:province":"Como",
    "sg:tags":[
        "solid",
        "panel"
    ],
    "sg:website":"www.paniforti.com",
    "wof:name":"Paniforti Multistrati Jolando Eliseo Molteni Spa",
    "wof:placetype":"venue"
},
  "geometry": {"coordinates":[9.1297521591,45.7139053345],"type":"Point"}
}