{
  "type": "Feature",
  "properties": {
    "iso:country":"IT",
    "sg:address":"Corso Levi 35/f 10098 Rivoli",
    "sg:city":"Rivoli",
    "sg:classifiers":[
        {
            "category":"Autos & Motor Vehicles",
            "subcategory":"Auto Supplies",
            "type":"Retail Goods"
        }
    ],
    "sg:phone":"+39 011 959 1841",
    "sg:postcode":"10098",
    "sg:province":"Torino",
    "sg:tags":[
        "automobile",
        "part",
        "spare"
    ],
    "wof:name":"Miraglio Spa",
    "wof:placetype":"venue"
},
  "geometry": {"coordinates":[7.535861,45.066311],"type":"Point"}
}