{
  "type": "Feature",
  "properties": {
    "iso:country":"IT",
    "sg:address":"21100 Varese",
    "sg:city":"Varese",
    "sg:orig_category":"Parafulmini",
    "sg:phone":"+39 0332 280041",
    "sg:postcode":"21100",
    "sg:province":"Varese",
    "sg:website":"http://www.ingelva.it",
    "wof:name":"Ingelva Parafulmini Srl",
    "wof:placetype":"venue"
},
  "geometry": {"coordinates":[8.8290519714,45.8156204224],"type":"Point"}
}