{
  "type": "Feature",
  "properties": {
    "addr:full":"Viale Regina Margherita 37; Supino",
    "addr:housenumber":"37",
    "addr:street":"Viale Regina Margherita",
    "iso:country":"IT",
    "sg:address":"Viale Regina Margherita 37; Supino",
    "sg:classifiers":[
        {
            "category":"Banks & Credit Unions",
            "subcategory":"Bank",
            "type":"Services"
        }
    ],
    "sg:phone":"+39 0775 226002",
    "wof:name":"Banca Di Roma",
    "wof:placetype":"venue"
},
  "geometry": {"coordinates":[13.226213,41.610054],"type":"Point"}
}