{
  "type": "Feature",
  "properties": {
    "iso:country":"IT",
    "sg:address":"Via Stazione 72017 Ostuni",
    "sg:city":"Ostuni",
    "sg:classifiers":[
        {
            "category":"Home & Garden",
            "subcategory":"Home Furnishings",
            "type":"Retail Goods"
        }
    ],
    "sg:phone":"+39 0831 304562",
    "sg:postcode":"72017",
    "sg:province":"Brindisi",
    "sg:tags":[
        "household"
    ],
    "wof:name":"Mv Srl",
    "wof:placetype":"venue"
},
  "geometry": {"coordinates":[17.600458,40.720798],"type":"Point"}
}