{
  "type": "Feature",
  "properties": {
    "addr:full":"9, Via Polo Marco 62024 Matelica Matelica Macerata 62024",
    "addr:postcode":"62024;62024",
    "addr:street":"Via Polo Marco",
    "iso:country":"IT",
    "sg:address":"9, Via Polo Marco 62024 Matelica",
    "sg:city":"Matelica",
    "sg:classifiers":[
        {
            "category":"Shopping",
            "type":"Retail Goods"
        }
    ],
    "sg:phone":"+39 0737 784011",
    "sg:postcode":"62024",
    "sg:province":"Macerata",
    "sg:tags":[
        "finished",
        "-",
        "metallic"
    ],
    "wof:name":"Mag Metal Srl",
    "wof:placetype":"venue"
},
  "geometry": {"coordinates":[13.4562616348,43.3007469177],"type":"Point"}
}