{
  "type": "Feature",
  "properties": {
    "iso:country":"IT",
    "sg:address":"Piazza S. Ciro 34/35; Portici; 80055",
    "sg:city":"Portici",
    "sg:classifiers":[
        {
            "category":"Banks & Credit Unions",
            "subcategory":"Bank",
            "type":"Services"
        }
    ],
    "sg:phone":"+39 081 472200",
    "sg:postcode":"80055",
    "sg:province":"Napoli",
    "wof:name":"Banca Della Provincia Di Napoli",
    "wof:placetype":"venue"
},
  "geometry": {"coordinates":[14.33907,40.814079],"type":"Point"}
}