{
  "type": "Feature",
  "properties": {
    "addr:full":"80, Via Sinistra Guerro 41014 Castelvetro Modena 41014",
    "addr:postcode":"41014;41014",
    "addr:street":"Via Sinistra Guerro",
    "iso:country":"IT",
    "sg:address":"80, Via Sinistra Guerro 41014 Castelvetro",
    "sg:classifiers":[
        {
            "category":"Sports & Exercise",
            "subcategory":"Playing Field",
            "type":"Entertainment"
        }
    ],
    "sg:phone":"+39 39059790549",
    "sg:postcode":"41014",
    "sg:province":"Modena",
    "sg:tags":[
        "game"
    ],
    "wof:name":"New Day Srl",
    "wof:placetype":"venue"
},
  "geometry": {"coordinates":[10.941051,44.491711],"type":"Point"}
}