{
  "type": "Feature",
  "properties": {
    "iso:country":"IT",
    "sg:address":"36, Via Merano 33045 Nimis",
    "sg:city":"Nimis",
    "sg:classifiers":[
        {
            "category":"Home & Garden",
            "subcategory":"Home Furnishings",
            "type":"Retail Goods"
        }
    ],
    "sg:phone":"+39 0432 790241",
    "sg:postcode":"33045",
    "sg:province":"Udine",
    "sg:tags":[
        "household"
    ],
    "wof:name":"Nuova Friularredi Soc.coop A R.l.",
    "wof:placetype":"venue"
},
  "geometry": {"coordinates":[13.255482,46.191757],"type":"Point"}
}