{
  "type": "Feature",
  "properties": {
    "iso:country":"IT",
    "sg:address":"10134 Torino",
    "sg:city":"Torino",
    "sg:orig_category":"Sport - Articoli E Forniture",
    "sg:phone":"+39 011 319 7940",
    "sg:postcode":"10134",
    "sg:province":"Torino",
    "wof:name":"Armeria Enria",
    "wof:placetype":"venue"
},
  "geometry": {"coordinates":[7.661375,45.047363],"type":"Point"}
}