{
  "type": "Feature",
  "properties": {
    "addr:full":"27, Via Ravanas Pietro 70037 Ruvo Di Puglia Ruvo di Puglia Bari 70037",
    "addr:postcode":"70037;70037",
    "addr:street":"Via Ravanas Pietro",
    "iso:country":"IT",
    "sg:address":"27, Via Ravanas Pietro 70037 Ruvo Di Puglia",
    "sg:city":"Ruvo di Puglia",
    "sg:classifiers":[
        {
            "category":"Real Estate",
            "subcategory":"Architect",
            "type":"Services"
        }
    ],
    "sg:phone":"+39 080 362 8998",
    "sg:postcode":"70037",
    "sg:province":"Bari",
    "sg:tags":[
        "textile",
        "clothing"
    ],
    "wof:name":"Ital Sud Confezioni",
    "wof:placetype":"venue"
},
  "geometry": {"coordinates":[16.503553,41.112465],"type":"Point"}
}