{
  "type": "Feature",
  "properties": {
    "addr:full":"Via Canepa Luigi 09170 Oristano Oristano Oristano 09170",
    "addr:postcode":"09170;09170",
    "addr:street":"Via Canepa Luigi",
    "iso:country":"IT",
    "sg:address":"Via Canepa Luigi 09170 Oristano",
    "sg:city":"Oristano",
    "sg:classifiers":[
        {
            "category":"Banks & Credit Unions",
            "subcategory":"Financial Services",
            "type":"Services"
        }
    ],
    "sg:phone":"+39 0783 212193",
    "sg:postcode":"09170",
    "sg:province":"Oristano",
    "sg:tags":[
        "banking",
        "finance",
        "insurance"
    ],
    "wof:name":"Scanu Giulia",
    "wof:placetype":"venue"
},
  "geometry": {"coordinates":[8.596333,39.905273],"type":"Point"}
}