{
  "type": "Feature",
  "properties": {
    "addr:full":"00196 Roma Roma Roma 00196",
    "addr:postcode":"00196;00196",
    "iso:country":"IT",
    "sg:address":"00196 Roma",
    "sg:city":"Roma",
    "sg:orig_category":"Prodotti Chimici Secondari",
    "sg:phone":"+39 06 3600 3197",
    "sg:postcode":"00196",
    "sg:province":"Roma",
    "wof:name":"Nobelsport",
    "wof:placetype":"venue"
},
  "geometry": {"coordinates":[12.46879673,41.9292373657],"type":"Point"}
}