{
  "type": "Feature",
  "properties": {
    "iso:country":"IT",
    "sg:address":"37012 Bussolengo",
    "sg:city":"Bussolengo",
    "sg:orig_category":"Gas, Metano E Gpl In Bombole E Per Serbatoi - Vendita Al Dettaglio",
    "sg:phone":"+39 045 715 6421",
    "sg:postcode":"37012",
    "sg:province":"Verona",
    "wof:name":"Melotto Dario",
    "wof:placetype":"venue"
},
  "geometry": {"coordinates":[10.858655,45.465469],"type":"Point"}
}