{
  "type": "Feature",
  "properties": {
    "addr:full":"87058 Spezzano Della Sila Spezzano della Sila Cosenza 87058",
    "addr:postcode":"87058;87058",
    "iso:country":"IT",
    "sg:address":"87058 Spezzano Della Sila",
    "sg:city":"Spezzano della Sila",
    "sg:classifiers":[
        {
            "category":"Restaurant",
            "type":"Food & Drink"
        }
    ],
    "sg:phone":"+39 0984 578034",
    "sg:postcode":"87058",
    "sg:province":"Cosenza",
    "sg:tags":[
        "auxiliary",
        "entertainment",
        "premises",
        "related",
        "catering",
        "similar",
        "public",
        "restaurants"
    ],
    "wof:name":"Hotel Cozza",
    "wof:placetype":"venue"
},
  "geometry": {"coordinates":[16.338722,39.301132],"type":"Point"}
}