{
  "type": "Feature",
  "properties": {
    "iso:country":"IT",
    "sg:address":"25028 Verolanuova",
    "sg:city":"Verolanuova",
    "sg:orig_category":"Agricoltura, Orticoltura E Floricoltura",
    "sg:phone":"+39 030 931144",
    "sg:postcode":"25028",
    "sg:province":"Brescia",
    "wof:name":"Lo' Domenico",
    "wof:placetype":"venue"
},
  "geometry": {"coordinates":[10.084085,45.324875],"type":"Point"}
}