{
  "type": "Feature",
  "properties": {
    "iso:country":"IT",
    "sg:address":"5, Via Bertoni 95030 Tremestieri Etneo",
    "sg:city":"Tremestieri Etneo",
    "sg:classifiers":[
        {
            "category":"Manufacturing",
            "subcategory":"Wood Products",
            "type":"Manufacturing & Wholesale Goods"
        }
    ],
    "sg:phone":"+39 39095496267",
    "sg:postcode":"95030",
    "sg:province":"Catania",
    "sg:tags":[
        "furniture"
    ],
    "wof:name":"S.i.r.a.r. S.r.l",
    "wof:placetype":"venue"
},
  "geometry": {"coordinates":[15.099065,37.543446],"type":"Point"}
}