{
  "type": "Feature",
  "properties": {
    "iso:country":"IT",
    "sg:address":"Via Rossini 6a 24129 Bergamo",
    "sg:city":"Bergamo",
    "sg:classifiers":[
        {
            "category":"Professional",
            "subcategory":"Accounting & Tax Preparation",
            "type":"Services"
        }
    ],
    "sg:phone":"+39 035 260360",
    "sg:postcode":"24129",
    "sg:province":"Bergamo",
    "sg:tags":[
        "additive",
        "baking"
    ],
    "sg:website":"www.puntogel.com",
    "wof:name":"Puntogel Srl",
    "wof:placetype":"venue"
},
  "geometry": {"coordinates":[9.669952,45.694904],"type":"Point"}
}