{
  "type": "Feature",
  "properties": {
    "addr:full":"20153 Milano Milano Milano 20153",
    "addr:postcode":"20153;20153",
    "iso:country":"IT",
    "sg:address":"20153 Milano",
    "sg:city":"Milano",
    "sg:orig_category":"Termotecnica E Riscaldamento, Apparecchiature E Servizi",
    "sg:phone":"+39 02 456 8314",
    "sg:postcode":"20153",
    "sg:province":"Milano",
    "wof:name":"Arensi Massimo",
    "wof:placetype":"venue"
},
  "geometry": {"coordinates":[9.080491,45.450813],"type":"Point"}
}