{
  "type": "Feature",
  "properties": {
    "addr:full":"14049 Nizza Monferrato Nizza Monferrato Asti 14049",
    "addr:postcode":"14049;14049",
    "iso:country":"IT",
    "sg:address":"14049 Nizza Monferrato",
    "sg:city":"Nizza Monferrato",
    "sg:orig_category":"Motori Ed Organi Di Trasmissione",
    "sg:phone":"+39 0141 702508",
    "sg:postcode":"14049",
    "sg:province":"Asti",
    "wof:name":"Gear Snc Di Giuso Laura & C.",
    "wof:placetype":"venue"
},
  "geometry": {"coordinates":[8.3644237518,44.7701568604],"type":"Point"}
}