{
  "type": "Feature",
  "properties": {
    "iso:country":"IT",
    "sg:address":"66034 Lanciano",
    "sg:city":"Lanciano",
    "sg:orig_category":"Arredo Cucina Ed Elettrodomestici. Elettrodomestici",
    "sg:phone":"+39 0872 43556",
    "sg:postcode":"66034",
    "sg:province":"Chieti",
    "wof:name":"Di Nucci Lanciano Srl",
    "wof:placetype":"venue"
},
  "geometry": {"coordinates":[14.39462,42.229694],"type":"Point"}
}