{
  "type": "Feature",
  "properties": {
    "iso:country":"IT",
    "sg:address":"00145 Roma",
    "sg:city":"Roma",
    "sg:orig_category":"Scuole E Servizi Scolastici. Servizi Vari Di Interesse Pubblico",
    "sg:phone":"+39 06 594 3017",
    "sg:postcode":"00145",
    "sg:province":"Roma",
    "sg:website":"http://www.paginegialle.it/gardenbimbo",
    "wof:name":"Scuola Materna Garden Bimbo Snc",
    "wof:placetype":"venue"
},
  "geometry": {"coordinates":[12.481492,41.850643],"type":"Point"}
}