{
  "type": "Feature",
  "properties": {
    "addr:full":"06127 Perugia Perugia Perugia 06127",
    "addr:postcode":"06127;06127",
    "iso:country":"IT",
    "sg:address":"06127 Perugia",
    "sg:city":"Perugia",
    "sg:orig_category":"Riparazione Dei Mezzi Di Trasporto",
    "sg:phone":"+39 075 505 1741",
    "sg:postcode":"06127",
    "sg:province":"Perugia",
    "sg:website":"http://www.fratellipalomba.it",
    "wof:name":"Fratelli Palomba Di Palomba Giorgio Srl",
    "wof:placetype":"venue"
},
  "geometry": {"coordinates":[12.371949,43.105637],"type":"Point"}
}