{
  "type": "Feature",
  "properties": {
    "addr:full":"37057 San Giovanni Lupatoto San Giovanni Lupatoto Verona 37057",
    "addr:housenumber":"37057",
    "addr:postcode":"37057",
    "addr:street":"San;Verona",
    "iso:country":"IT",
    "sg:address":"37057 San Giovanni Lupatoto",
    "sg:city":"San Giovanni Lupatoto",
    "sg:orig_category":"Salotti, Poltrone, Sedie E Tavoli",
    "sg:phone":"+39 045 875 0098",
    "sg:postcode":"37057",
    "sg:province":"Verona",
    "wof:name":"Tappezzeria Piubel Paolo",
    "wof:placetype":"venue"
},
  "geometry": {"coordinates":[11.05417,45.37841],"type":"Point"}
}