{
  "type": "Feature",
  "properties": {
    "iso:country":"IT",
    "sg:address":"20162 Milano",
    "sg:city":"Milano",
    "sg:classifiers":[
        {
            "category":"Professional",
            "subcategory":"Advertising",
            "type":"Services"
        }
    ],
    "sg:phone":"+39 02 6610 6753",
    "sg:postcode":"20162",
    "sg:province":"Milano",
    "sg:tags":[
        "marketing",
        "communication"
    ],
    "wof:name":"Computer Grafic",
    "wof:placetype":"venue"
},
  "geometry": {"coordinates":[9.195667,45.519268],"type":"Point"}
}