{
  "type": "Feature",
  "properties": {
    "addr:full":"12, Via Portobuffole' 31040 Mansue' Treviso 31040",
    "addr:postcode":"31040;31040",
    "addr:street":"Via Portobuffole '",
    "iso:country":"IT",
    "sg:address":"12, Via Portobuffole' 31040 Mansue'",
    "sg:classifiers":[
        {
            "category":"Home & Garden",
            "subcategory":"Home Furnishings",
            "type":"Retail Goods"
        }
    ],
    "sg:phone":"+39 0422 801835",
    "sg:postcode":"31040",
    "sg:province":"Treviso",
    "sg:tags":[
        "household"
    ],
    "wof:name":"Diesse Componenti Mobili (s.r.l.)",
    "wof:placetype":"venue"
},
  "geometry": {"coordinates":[12.53839,45.824497],"type":"Point"}
}