{
  "type": "Feature",
  "properties": {
    "iso:country":"IT",
    "sg:address":"4, Via Enrico De Nicola 33080 Prata Di Pordenone",
    "sg:city":"Prata di Pordenone",
    "sg:classifiers":[
        {
            "category":"Home & Garden",
            "subcategory":"Home Furnishings",
            "type":"Retail Goods"
        }
    ],
    "sg:phone":"+39 0434 610230",
    "sg:postcode":"33080",
    "sg:province":"Pordenone",
    "sg:tags":[
        "household"
    ],
    "wof:name":"Ar - Tre (s.r.l.)",
    "wof:placetype":"venue"
},
  "geometry": {"coordinates":[12.575418,45.889244],"type":"Point"}
}