{
  "type": "Feature",
  "properties": {
    "iso:country":"IT",
    "sg:address":"56030 Perignano",
    "sg:orig_category":"Prodotti Chimici Secondari",
    "sg:phone":"+39 0587 618313",
    "sg:postcode":"56030",
    "sg:province":"Pisa",
    "wof:name":"Toscana Cubic Center",
    "wof:placetype":"venue"
},
  "geometry": {"coordinates":[10.3970136642,43.7248153687],"type":"Point"}
}