{
  "type": "Feature",
  "properties": {
    "iso:country":"IT",
    "sg:address":"00193 Roma",
    "sg:city":"Roma",
    "sg:orig_category":"Studi E Consulenze Legali E Notarili. Avvocati, Notai E Servizi Legali. Professionisti - Studi E Servizi Ed Associazioni Di Interesse Aziendale",
    "sg:phone":"+39 06 323 4646",
    "sg:postcode":"00193",
    "sg:province":"Roma",
    "wof:name":"Bartolomucci Prof. Dr. Franco",
    "wof:placetype":"venue"
},
  "geometry": {"coordinates":[12.468385,41.907932],"type":"Point"}
}