{
  "type": "Feature",
  "properties": {
    "addr:full":"16129 Genova Genova Genova 16129",
    "addr:postcode":"16129;16129",
    "iso:country":"IT",
    "sg:address":"16129 Genova",
    "sg:city":"Genova",
    "sg:orig_category":"Professionisti - Studi E Servizi Ed Associazioni Di Interesse Aziendale. Associazioni Ed Organismi Di Interesse Pubblico",
    "sg:phone":"+39 010 591452",
    "sg:postcode":"16129",
    "sg:province":"Genova",
    "wof:name":"Collegio Provinciale Infermieri Professionali Assistenti Sanitari E Vigilatrici D'infanzia",
    "wof:placetype":"venue"
},
  "geometry": {"coordinates":[8.9473867416,44.3977584839],"type":"Point"}
}