{
  "type": "Feature",
  "properties": {
    "addr:full":"31032 Lughignano Lughignano Treviso 31032",
    "addr:postcode":"31032;31032",
    "addr:street":"Lughignano Treviso",
    "iso:country":"IT",
    "sg:address":"31032 Lughignano",
    "sg:city":"Lughignano",
    "sg:orig_category":"Tempo Libero - Articoli E Forniture. Regalistica Aziendale",
    "sg:phone":"+39 0422 822621",
    "sg:postcode":"31032",
    "sg:province":"Treviso",
    "wof:name":"Paper Dream S.r.l.",
    "wof:placetype":"venue"
},
  "geometry": {"coordinates":[12.242232,45.640446],"type":"Point"}
}