{
  "type": "Feature",
  "properties": {
    "iso:country":"IT",
    "sg:address":"29017 Fiorenzuola D'arda",
    "sg:orig_category":"Autoaccessori - Commercio",
    "sg:phone":"+39 0523 983296",
    "sg:postcode":"29017",
    "sg:province":"Piacenza",
    "wof:name":"Teloni Torrigiani Sas",
    "wof:placetype":"venue"
},
  "geometry": {"coordinates":[9.906591,44.920273],"type":"Point"}
}