{
  "type": "Feature",
  "properties": {
    "iso:country":"IT",
    "sg:address":"21040 Gornate Olona",
    "sg:orig_category":"Stampaggio Materie Plastiche",
    "sg:phone":"+39 0331 858334",
    "sg:postcode":"21040",
    "sg:province":"Varese",
    "wof:name":"D.m. Sas Di Mombelli S. & C.",
    "wof:placetype":"venue"
},
  "geometry": {"coordinates":[8.861111,45.7425],"type":"Point"}
}