{
  "type": "Feature",
  "properties": {
    "addr:full":"56125 Pisa Pisa Pisa 56125",
    "addr:postcode":"56125;56125",
    "iso:country":"IT",
    "sg:address":"56125 Pisa",
    "sg:city":"Pisa",
    "sg:orig_category":"Scuole E Servizi Scolastici. Ricerca, Selezione E Formazione Del Personale",
    "sg:phone":"+39 800 441 538",
    "sg:postcode":"56125",
    "sg:province":"Pisa",
    "wof:name":"Cepu Srl",
    "wof:placetype":"venue"
},
  "geometry": {"coordinates":[10.399333,43.71022],"type":"Point"}
}