{
  "type": "Feature",
  "properties": {
    "iso:country":"IT",
    "sg:address":"88034 Nicotera",
    "sg:orig_category":"Agriturismo",
    "sg:phone":"+39 0966 712113",
    "sg:province":"VV",
    "wof:name":"Agriturismo Cally Cally Di Mancuso Giuseppina",
    "wof:placetype":"venue"
},
  "geometry": {"coordinates":[-107.99490400000001,32.505501],"type":"Point"}
}