{
  "type": "Feature",
  "properties": {
    "iso:country":"IT",
    "sg:address":"24040 Castel Rozzone",
    "sg:city":"Castel Rozzone",
    "sg:orig_category":"Materiali E Componenti Elettrotecnici",
    "sg:phone":"+39 036 338 1262",
    "sg:postcode":"24040",
    "sg:province":"Bergamo",
    "wof:name":"Bosco Ottica Srl",
    "wof:placetype":"venue"
},
  "geometry": {"coordinates":[9.620944,45.553295],"type":"Point"}
}