{
  "type": "Feature",
  "properties": {
    "iso:country":"IT",
    "sg:address":"25040 Corte Franca",
    "sg:city":"Corte Franca",
    "sg:orig_category":"Servizi Editoriali",
    "sg:phone":"+39 030 984407",
    "sg:postcode":"25040",
    "sg:province":"Brescia",
    "wof:name":"Bellandi & Marini Di Bellandi Guido E Marini Luciano (s.n.c.)",
    "wof:placetype":"venue"
},
  "geometry": {"coordinates":[10.011921,45.636131],"type":"Point"}
}