{
  "type": "Feature",
  "properties": {
    "iso:country":"IT",
    "sg:address":"6, Via Marina Garibaldi 98057 Milazzo",
    "sg:city":"Milazzo",
    "sg:classifiers":[
        {
            "category":"Professional",
            "subcategory":"Engineering",
            "type":"Services"
        }
    ],
    "sg:phone":"+39 090 924 0272",
    "sg:postcode":"98057",
    "sg:province":"Messina",
    "sg:tags":[
        "machine",
        "-",
        "mechanical"
    ],
    "wof:name":"Simoco Impianti Srl",
    "wof:placetype":"venue"
},
  "geometry": {"coordinates":[15.555523,38.192333],"type":"Point"}
}