{
  "type": "Feature",
  "properties": {
    "iso:country":"IT",
    "sg:address":"48, V. Mazzini 80027 Frattamaggiore",
    "sg:city":"Frattamaggiore",
    "sg:classifiers":[
        {
            "category":"Sports & Exercise",
            "subcategory":"Playing Field",
            "type":"Entertainment"
        }
    ],
    "sg:phone":"+39 081 835 1754",
    "sg:postcode":"80027",
    "sg:province":"Napoli",
    "sg:tags":[
        "game"
    ],
    "sg:website":"http://www.cereriacimmino.it",
    "wof:name":"Cereria Cimmino",
    "wof:placetype":"venue"
},
  "geometry": {"coordinates":[14.274323,40.905941],"type":"Point"}
}