{
  "type": "Feature",
  "properties": {
    "addr:full":"28028 Pettenasco Pettenasco Novara 28028",
    "addr:postcode":"28028;28028",
    "iso:country":"IT",
    "sg:address":"28028 Pettenasco",
    "sg:city":"Pettenasco",
    "sg:orig_category":"Bagno - Accessori E Mobili",
    "sg:phone":"+39 0323 89128",
    "sg:postcode":"28028",
    "sg:province":"Novara",
    "wof:name":"Oioli Rubinetterie Sas",
    "wof:placetype":"venue"
},
  "geometry": {"coordinates":[8.407639,45.816578],"type":"Point"}
}