{
  "type": "Feature",
  "properties": {
    "addr:full":"33080 Roveredo In Piano Roveredo in Piano Pordenone 33080",
    "addr:postcode":"33080;33080",
    "iso:country":"IT",
    "sg:address":"33080 Roveredo In Piano",
    "sg:city":"Roveredo in Piano",
    "sg:orig_category":"Arredo Bagno Ed Idrosanitari. Idrosanitari E Accessori",
    "sg:phone":"+39 0434 949470",
    "sg:postcode":"33080",
    "sg:province":"Pordenone",
    "wof:name":"Astrea Srl",
    "wof:placetype":"venue"
},
  "geometry": {"coordinates":[12.623463,46.009853],"type":"Point"}
}