{
  "type": "Feature",
  "properties": {
    "addr:full":"36015 Schio Schio Vicenza 36015",
    "addr:postcode":"36015;36015",
    "iso:country":"IT",
    "sg:address":"36015 Schio",
    "sg:city":"Schio",
    "sg:orig_category":"Utensili Meccanici E Materiali",
    "sg:phone":"+39 0445 576337",
    "sg:postcode":"36015",
    "sg:province":"Vicenza",
    "wof:name":"Modelmec Snc Di Ciscato S. & C.",
    "wof:placetype":"venue"
},
  "geometry": {"coordinates":[11.543027,45.575569],"type":"Point"}
}