{
  "type": "Feature",
  "properties": {
    "iso:country":"IT",
    "sg:address":"20081 Abbiategrasso",
    "sg:city":"Abbiategrasso",
    "sg:orig_category":"Automobili - Elaborazioni",
    "sg:phone":"+39 02 9496 9958",
    "sg:postcode":"20081",
    "sg:province":"Milano",
    "wof:name":"No Limits The Next Generation",
    "wof:placetype":"venue"
},
  "geometry": {"coordinates":[9.195965,45.48019],"type":"Point"}
}