{
  "type": "Feature",
  "properties": {
    "addr:full":"21030 Cuveglio Cuveglio Varese 21030",
    "addr:postcode":"21030;21030",
    "iso:country":"IT",
    "sg:address":"21030 Cuveglio",
    "sg:city":"Cuveglio",
    "sg:orig_category":"Gruppi Elettrogeni E Di Continuita'",
    "sg:phone":"+39 0332 651045",
    "sg:postcode":"21030",
    "sg:province":"Varese",
    "sg:website":"http://www.rocoma.it",
    "wof:name":"Rocoma Snc",
    "wof:placetype":"venue"
},
  "geometry": {"coordinates":[8.735456,45.905075],"type":"Point"}
}