{
  "type": "Feature",
  "properties": {
    "iso:country":"IT",
    "sg:address":"70027 Palo Del Colle",
    "sg:city":"Palo del Colle",
    "sg:orig_category":"Servizi E Lavori Per Industria Alimentare E Bevande",
    "sg:phone":"+39 080 629373",
    "sg:postcode":"70027",
    "sg:province":"Bari",
    "wof:name":"Somma Biagio",
    "wof:placetype":"venue"
},
  "geometry": {"coordinates":[16.742117,41.037796],"type":"Point"}
}