{
  "type": "Feature",
  "properties": {
    "addr:full":"Via Del Molino, 106/108 50041 Calenzano Calenzano Firenze 50041",
    "addr:housenumber":"106 / 108",
    "addr:postcode":"50041;50041",
    "addr:street":"Via Del Molino",
    "iso:country":"IT",
    "sg:address":"Via Del Molino, 106/108 50041 Calenzano",
    "sg:city":"Calenzano",
    "sg:classifiers":[
        {
            "category":"Shopping",
            "subcategory":"Crafts & Fabrics",
            "type":"Retail Goods"
        }
    ],
    "sg:phone":"+39 055 887 8086",
    "sg:postcode":"50041",
    "sg:province":"Firenze",
    "sg:tags":[
        "ladies'",
        "wear"
    ],
    "sg:website":"www.erion.it",
    "wof:name":"Erion Di Bigagli E Carpeggiani Spa",
    "wof:placetype":"venue"
},
  "geometry": {"coordinates":[10.7479085922,43.8607368469],"type":"Point"}
}