{
  "type": "Feature",
  "properties": {
    "addr:full":"Via Provinciale Fondi 04022 Fondi Fondi Latina 04022",
    "addr:postcode":"04022;04022",
    "addr:street":"Via Provinciale Fondi",
    "iso:country":"IT",
    "sg:address":"Via Provinciale Fondi 04022 Fondi",
    "sg:city":"Fondi",
    "sg:classifiers":[
        {
            "category":"Food & Beverages",
            "subcategory":"Groceries & Convenience Stores",
            "type":"Retail Goods"
        }
    ],
    "sg:phone":"+39 0771 502127",
    "sg:postcode":"04022",
    "sg:province":"Latina",
    "sg:tags":[
        "product",
        "related"
    ],
    "wof:name":"La Rezzola Srl",
    "wof:placetype":"venue"
},
  "geometry": {"coordinates":[12.9036998749,41.4675979614],"type":"Point"}
}