{
  "type": "Feature",
  "properties": {
    "iso:country":"IT",
    "sg:address":"09016 Iglesias",
    "sg:city":"Iglesias",
    "sg:orig_category":"Bagno - Accessori E Mobili",
    "sg:phone":"+39 0781 22363",
    "sg:postcode":"09016",
    "sg:province":"Carbonia-Iglesias",
    "wof:name":"Era Angela",
    "wof:placetype":"venue"
},
  "geometry": {"coordinates":[8.646503,39.325909],"type":"Point"}
}