{
  "type": "Feature",
  "properties": {
    "addr:full":"1, Via Palazzi 21016 Luino Luino Varese 21016",
    "addr:postcode":"21016;21016",
    "addr:street":"Via Palazzi",
    "iso:country":"IT",
    "sg:address":"1, Via Palazzi 21016 Luino",
    "sg:city":"Luino",
    "sg:classifiers":[
        {
            "category":"Travel",
            "subcategory":"Travel Agent",
            "type":"Entertainment"
        }
    ],
    "sg:phone":"+39 0332 510855",
    "sg:postcode":"21016",
    "sg:province":"Varese",
    "sg:tags":[
        "business"
    ],
    "wof:name":"Albergo Camin Colmegna S.a.s.",
    "wof:placetype":"venue"
},
  "geometry": {"coordinates":[8.750574,46.025681],"type":"Point"}
}