{
  "type": "Feature",
  "properties": {
    "iso:country":"IT",
    "sg:address":"24040 Canonica D'adda",
    "sg:orig_category":"Sport - Articoli E Forniture",
    "sg:phone":"+39 02 9096 5403",
    "sg:postcode":"24040",
    "sg:province":"Bergamo",
    "wof:name":"Adda Pesca Sport Di Ronchi Davide",
    "wof:placetype":"venue"
},
  "geometry": {"coordinates":[9.546778,45.577866],"type":"Point"}
}