{
  "type": "Feature",
  "properties": {
    "iso:country":"IT",
    "sg:address":"17, Via Contarella 42019 Scandiano",
    "sg:classifiers":[
        {
            "category":"Wholesale",
            "subcategory":"Medical Equipment & Supplies",
            "type":"Manufacturing & Wholesale Goods"
        }
    ],
    "sg:phone":"+39 0522 856185",
    "sg:postcode":"42019",
    "sg:province":"Reggio Nell'Emilia",
    "sg:tags":[
        "-",
        "health",
        "instrument"
    ],
    "wof:name":"Artem Giorgio Vezzosi S.r.l.",
    "wof:placetype":"venue"
},
  "geometry": {"coordinates":[10.699446,44.59956],"type":"Point"}
}