{
  "type": "Feature",
  "properties": {
    "iso:country":"IT",
    "sg:address":"18, Strada Del Crocifisso 04100 Latina",
    "sg:city":"Latina",
    "sg:classifiers":[
        {
            "category":"Shopping",
            "subcategory":"Computers & Home Electronics",
            "type":"Retail Goods"
        }
    ],
    "sg:phone":"+39 390 773 6871",
    "sg:postcode":"04100",
    "sg:province":"Latina",
    "sg:tags":[
        "electronic",
        "electrical",
        "equipment"
    ],
    "wof:name":"Alcanet International Italia S.p.a.",
    "wof:placetype":"venue"
},
  "geometry": {"coordinates":[12.909445,41.543056],"type":"Point"}
}