{
  "type": "Feature",
  "properties": {
    "addr:full":"00043 Ciampino Ciampino Roma 00043",
    "addr:postcode":"00043;roma 00043",
    "iso:country":"IT",
    "sg:address":"00043 Ciampino",
    "sg:city":"Ciampino",
    "sg:orig_category":"Articoli Sportivi - Vendita Al Dettaglio",
    "sg:phone":"+39 06 791 9584",
    "sg:postcode":"00043",
    "sg:province":"Roma",
    "wof:name":"V. M. Di Vangelisti Marco",
    "wof:placetype":"venue"
},
  "geometry": {"coordinates":[12.596179,41.807194],"type":"Point"}
}