{
  "type": "Feature",
  "properties": {
    "iso:country":"IT",
    "sg:address":"3, Via A.malignani 33058 San Giorgio Di Nogaro",
    "sg:city":"San Giorgio di Nogaro",
    "sg:classifiers":[
        {
            "category":"Manufacturing",
            "subcategory":"Wood Products",
            "type":"Manufacturing & Wholesale Goods"
        }
    ],
    "sg:phone":"+39 0431 621198",
    "sg:postcode":"33058",
    "sg:province":"Udine",
    "sg:tags":[
        "furniture"
    ],
    "wof:name":"Friulparchet (s.r.l.)",
    "wof:placetype":"venue"
},
  "geometry": {"coordinates":[13.222426,45.799038],"type":"Point"}
}