{
  "type": "Feature",
  "properties": {
    "iso:country":"IT",
    "sg:address":"80122 Casavatore",
    "sg:orig_category":"Termotecnica E Riscaldamento, Apparecchiature E Servizi. Prodotti Vari In Metallo",
    "sg:phone":"+39 081 738 5311",
    "sg:postcode":"80122",
    "sg:province":"Napoli",
    "wof:name":"Ceramiche Russo Snc",
    "wof:placetype":"venue"
},
  "geometry": {"coordinates":[14.280914,40.894356],"type":"Point"}
}