{
  "type": "Feature",
  "properties": {
    "addr:full":"50058 Signa Signa Firenze 50058",
    "addr:postcode":"50058;50058",
    "iso:country":"IT",
    "sg:address":"50058 Signa",
    "sg:city":"Signa",
    "sg:orig_category":"Forniture Per Abbigliamento E Pelletterie",
    "sg:phone":"+39 055 899 7228",
    "sg:postcode":"50058",
    "sg:province":"Firenze",
    "wof:name":"Bastoni Lucia",
    "wof:placetype":"venue"
},
  "geometry": {"coordinates":[11.1287794113,43.7959823608],"type":"Point"}
}