{
  "type": "Feature",
  "properties": {
    "iso:country":"IT",
    "sg:address":"36060 Longare",
    "sg:city":"Longa",
    "sg:orig_category":"Marmo, Pietre Ed Affini",
    "sg:phone":"+39 0444 555259",
    "sg:postcode":"36060",
    "sg:province":"Vicenza",
    "wof:name":"Lazzari Commerciale Srl",
    "wof:placetype":"venue"
},
  "geometry": {"coordinates":[11.610999,45.474842],"type":"Point"}
}