{
  "type": "Feature",
  "properties": {
    "iso:country":"IT",
    "sg:address":"40132 Bologna",
    "sg:city":"Bologna",
    "sg:orig_category":"Automazione E Macchine Per Ufficio. Servizi Ausiliari Di Certificati, Riproduzioni, Disegni E Foto",
    "sg:phone":"+39 051 641 4946",
    "sg:postcode":"40132",
    "sg:province":"Bologna",
    "wof:name":"A.m. Automazione Microfilm (s.r.l.)",
    "wof:placetype":"venue"
},
  "geometry": {"coordinates":[11.275328,44.527374],"type":"Point"}
}