{
  "type": "Feature",
  "properties": {
    "iso:country":"IT",
    "sg:address":"Via Sg Emiliani 5/c; Merone; 22046",
    "sg:city":"Merone",
    "sg:classifiers":[
        {
            "category":"Banks & Credit Unions",
            "subcategory":"Bank",
            "type":"Services"
        }
    ],
    "sg:phone":"+39 031 650817",
    "sg:postcode":"22046",
    "sg:province":"Como",
    "wof:name":"Banca Popolare Di Sondrio Scarl",
    "wof:placetype":"venue"
},
  "geometry": {"coordinates":[9.243779,45.784706],"type":"Point"}
}