{
  "type": "Feature",
  "properties": {
    "iso:country":"IT",
    "sg:address":"Via M. Bercilli 64 50050 Stabbia",
    "sg:city":"Stabbia",
    "sg:orig_category":"Ladies' Stockings",
    "sg:phone":"+39 0571 586095",
    "sg:postcode":"50050",
    "sg:province":"Firenze",
    "wof:name":"Nuova Iside Srl",
    "wof:placetype":"venue"
},
  "geometry": {"coordinates":[10.835866,43.78299],"type":"Point"}
}