{
  "type": "Feature",
  "properties": {
    "iso:country":"IT",
    "sg:address":"16164 Genova",
    "sg:city":"Genova",
    "sg:classifiers":[
        {
            "category":"Professional",
            "subcategory":"Art Services",
            "type":"Services"
        }
    ],
    "sg:phone":"+39 010 714541",
    "sg:postcode":"16164",
    "sg:province":"Genova",
    "sg:tags":[
        "gifts",
        "craft",
        "artistic"
    ],
    "wof:name":"A. Barabino E Betti Sas",
    "wof:placetype":"venue"
},
  "geometry": {"coordinates":[8.899701,44.505917],"type":"Point"}
}