{
  "type": "Feature",
  "properties": {
    "addr:full":"20144 Milano Milano Milano 20144",
    "addr:postcode":"20144;20144",
    "iso:country":"IT",
    "sg:address":"20144 Milano",
    "sg:city":"Milano",
    "sg:orig_category":"Tessuti E Stoffe. Tessuti Arredamento, Tende E Tappeti. Shopping",
    "sg:phone":"+39 02 437942",
    "sg:postcode":"20144",
    "sg:province":"Milano",
    "sg:website":"http://www.omnitex.it",
    "wof:name":"Omnitex Srl",
    "wof:placetype":"venue"
},
  "geometry": {"coordinates":[9.163937,45.466187],"type":"Point"}
}