{
  "type": "Feature",
  "properties": {
    "iso:country":"IT",
    "sg:address":"50129 Firenze",
    "sg:city":"Firenze",
    "sg:orig_category":"Cine-foto-ottica. Shopping",
    "sg:phone":"+39 055 212840",
    "sg:postcode":"50129",
    "sg:province":"Firenze",
    "wof:name":"Sex World",
    "wof:placetype":"venue"
},
  "geometry": {"coordinates":[11.254278,43.777863],"type":"Point"}
}