{
  "type": "Feature",
  "properties": {
    "iso:country":"IT",
    "sg:address":"62100 Macerata",
    "sg:city":"Macerata",
    "sg:orig_category":"Dolciumi E Gelati",
    "sg:phone":"+39 0733 283164",
    "sg:postcode":"62100",
    "sg:province":"Macerata",
    "wof:name":"Azienda Agricola Si.gi Sas",
    "wof:placetype":"venue"
},
  "geometry": {"coordinates":[13.428059,43.28381],"type":"Point"}
}