{
  "type": "Feature",
  "properties": {
    "iso:country":"IT",
    "sg:address":"10139 Torino",
    "sg:city":"Torino",
    "sg:orig_category":"Forniture Per Abbigliamento E Pelletterie",
    "sg:phone":"+39 011 447 1657",
    "sg:postcode":"10139",
    "sg:province":"Torino",
    "wof:name":"Ordasso Ada",
    "wof:placetype":"venue"
},
  "geometry": {"coordinates":[7.6503753662,45.0672302246],"type":"Point"}
}