{
  "type": "Feature",
  "properties": {
    "iso:country":"IT",
    "sg:address":"00191 Roma",
    "sg:city":"Roma",
    "sg:orig_category":"Cinematografia E Radiotelevisione. Cine-foto-ottica",
    "sg:phone":"+39 06 330831",
    "sg:postcode":"00191",
    "sg:province":"Roma",
    "wof:name":"Buena Vista International",
    "wof:placetype":"venue"
},
  "geometry": {"coordinates":[12.485605,41.954735],"type":"Point"}
}