{
  "type": "Feature",
  "properties": {
    "iso:country":"IT",
    "sg:address":"46/a, Via Togliatti 42020 Quattro Castella",
    "sg:classifiers":[
        {
            "category":"Communications",
            "subcategory":"Television Station",
            "type":"Services"
        }
    ],
    "sg:phone":"+39 0522 880808",
    "sg:postcode":"42020",
    "sg:province":"Reggio Nell'Emilia",
    "sg:tags":[
        "audio-visual"
    ],
    "wof:name":"Zendar (s.p.a.)",
    "wof:placetype":"venue"
},
  "geometry": {"coordinates":[10.567183,44.642696],"type":"Point"}
}