{
  "type": "Feature",
  "properties": {
    "iso:country":"IT",
    "sg:address":"37024 Negrar",
    "sg:city":"Negrar",
    "sg:orig_category":"Forniture Per Abbigliamento E Pelletterie",
    "sg:phone":"+39 045 600 0630",
    "sg:postcode":"37024",
    "sg:province":"Verona",
    "wof:name":"Adami Amelia",
    "wof:placetype":"venue"
},
  "geometry": {"coordinates":[10.9543609619,45.5392608643],"type":"Point"}
}