{
  "type": "Feature",
  "properties": {
    "iso:country":"IT",
    "sg:address":"25062 Concesio",
    "sg:city":"Concesio",
    "sg:orig_category":"Ingranaggi",
    "sg:phone":"+39 030 275 2356",
    "sg:postcode":"25062",
    "sg:province":"Brescia",
    "wof:name":"Nuova Dean Ingranaggi",
    "wof:placetype":"venue"
},
  "geometry": {"coordinates":[10.15818,45.578335],"type":"Point"}
}