{
  "type": "Feature",
  "properties": {
    "iso:country":"IT",
    "sg:address":"88, Via Grotte Di Penseroni 00128 Roma",
    "sg:city":"Roma",
    "sg:classifiers":[
        {
            "category":"Professional",
            "subcategory":"Engineering",
            "type":"Services"
        }
    ],
    "sg:phone":"+39 39065060400",
    "sg:postcode":"00128",
    "sg:province":"Roma",
    "sg:tags":[
        "machine",
        "-",
        "mechanical"
    ],
    "wof:name":"Trend Oil Srl",
    "wof:placetype":"venue"
},
  "geometry": {"coordinates":[12.483235,41.754002],"type":"Point"}
}