{
  "type": "Feature",
  "properties": {
    "iso:country":"IT",
    "sg:address":"40133 Bologna",
    "sg:city":"Bologna",
    "sg:orig_category":"Materiali E Componenti Elettrotecnici",
    "sg:phone":"+39 051 383474",
    "sg:postcode":"40133",
    "sg:province":"Bologna",
    "wof:name":"Cembre (s.p.a.)",
    "wof:placetype":"venue"
},
  "geometry": {"coordinates":[11.299254,44.509571],"type":"Point"}
}