{
  "type": "Feature",
  "properties": {
    "iso:country":"IT",
    "sg:address":"10136 Torino",
    "sg:city":"Torino",
    "sg:orig_category":"Forniture Per Abbigliamento E Pelletterie",
    "sg:phone":"+39 011 390007",
    "sg:postcode":"10136",
    "sg:province":"Torino",
    "wof:name":"Filati Tre Sfere Srl",
    "wof:placetype":"venue"
},
  "geometry": {"coordinates":[7.6376643181,45.0492782593],"type":"Point"}
}