{
  "type": "Feature",
  "properties": {
    "addr:full":"38032 Canazei Canazei Trento 38032",
    "addr:postcode":"38032;38032",
    "iso:country":"IT",
    "sg:address":"38032 Canazei",
    "sg:city":"Canazei",
    "sg:orig_category":"Alberghi E Strutture Extra Alberghiere",
    "sg:phone":"+39 0462 602086",
    "sg:postcode":"38032",
    "sg:province":"Trento",
    "sg:website":"http://www.cirelle.it",
    "wof:name":"Cirelle Garni - Appartamenti Snc Di Dantone Luciano & C.",
    "wof:placetype":"venue"
},
  "geometry": {"coordinates":[11.783897,46.460728],"type":"Point"}
}