{
  "type": "Feature",
  "properties": {
    "iso:country":"IT",
    "sg:address":"10036 Settimo Torinese",
    "sg:city":"Settimo Torinese",
    "sg:orig_category":"Prodotti E Manufatti In Materie Plastiche. Servizi E Lavori Industria Delle Materie Plastiche",
    "sg:phone":"+39 011 895 7024",
    "sg:postcode":"10036",
    "sg:province":"Torino",
    "sg:website":"http://www.gieffetermoformati.com",
    "wof:name":"Gi-effe Snc",
    "wof:placetype":"venue"
},
  "geometry": {"coordinates":[7.7308034897,45.1354827881],"type":"Point"}
}