{
  "type": "Feature",
  "properties": {
    "addr:full":"3, Viale Commercio 41012 Carpi Carpi Modena 41012",
    "addr:postcode":"41012;41012",
    "addr:street":"Viale Commercio",
    "iso:country":"IT",
    "sg:address":"3, Viale Commercio 41012 Carpi",
    "sg:city":"Carpi",
    "sg:classifiers":[
        {
            "category":"Autos & Motor Vehicles",
            "subcategory":"Automobile Sales",
            "type":"Retail Goods"
        }
    ],
    "sg:phone":"+39 39059641550",
    "sg:postcode":"41012",
    "sg:province":"Modena",
    "sg:tags":[
        "motor-cars"
    ],
    "wof:name":"Schiatti Motors (s.r.l.)",
    "wof:placetype":"venue"
},
  "geometry": {"coordinates":[10.8607435226,44.7863502502],"type":"Point"}
}