{
  "type": "Feature",
  "properties": {
    "addr:full":"77, Corso Battaglione Aosta 11100 Aosta Aosta Aosta 11100",
    "addr:postcode":"11100;11100",
    "addr:street":"Corso Battaglione Aosta",
    "iso:country":"IT",
    "sg:address":"77, Corso Battaglione Aosta 11100 Aosta",
    "sg:city":"Aosta",
    "sg:orig_category":"Miscellaneous Products",
    "sg:phone":"+39 39016534934",
    "sg:postcode":"11100",
    "sg:province":"Aosta",
    "wof:name":"Magazzini Vagnino S.p.a.",
    "wof:placetype":"venue"
},
  "geometry": {"coordinates":[7.3100581169,45.7339553833],"type":"Point"}
}