{
  "type": "Feature",
  "properties": {
    "iso:country":"IT",
    "sg:address":"70123 Bari",
    "sg:city":"Bari",
    "sg:orig_category":"Officine Meccaniche",
    "sg:phone":"+39 080 574 0783",
    "sg:postcode":"70123",
    "sg:province":"Bari",
    "wof:name":"Centro Rettifiche Traversa Srl",
    "wof:placetype":"venue"
},
  "geometry": {"coordinates":[16.835537,41.122498],"type":"Point"}
}