{
  "type": "Feature",
  "properties": {
    "addr:full":"143, Via Della Repubblica 50050 Cerreto Guidi Cerreto Guidi Firenze 50050",
    "addr:housenumber":"143",
    "addr:postcode":"50050;50050",
    "addr:street":"Via Della Repubblica",
    "iso:country":"IT",
    "sg:address":"143, Via Della Repubblica 50050 Cerreto Guidi",
    "sg:city":"Cerreto Guidi",
    "sg:classifiers":[
        {
            "category":"Shopping",
            "subcategory":"Clothing, Apparel, & Fashions",
            "type":"Retail Goods"
        }
    ],
    "sg:phone":"+39 0571 586707",
    "sg:postcode":"50050",
    "sg:province":"Firenze",
    "sg:tags":[
        "clothes"
    ],
    "wof:name":"Calzificio M.c.s.",
    "wof:placetype":"venue"
},
  "geometry": {"coordinates":[10.845674,43.78318],"type":"Point"}
}