{
  "type": "Feature",
  "properties": {
    "iso:country":"IT",
    "sg:address":"41046 Palagano",
    "sg:city":"Palagano",
    "sg:orig_category":"Ceramiche: Prodotti E Lavorazioni. Forniture Per Attivita' Industriali",
    "sg:phone":"+39 0536 961656",
    "sg:postcode":"41046",
    "sg:province":"Modena",
    "wof:name":"P.f.m. S.r.l.",
    "wof:placetype":"venue"
},
  "geometry": {"coordinates":[10.653444,44.324436],"type":"Point"}
}