{
  "type": "Feature",
  "properties": {
    "iso:country":"IT",
    "sg:address":"Via Canova 38/40; Milano; 20145",
    "sg:city":"Milano",
    "sg:classifiers":[
        {
            "category":"Banks & Credit Unions",
            "subcategory":"Bank",
            "type":"Services"
        }
    ],
    "sg:phone":"+39 02 3453 0389",
    "sg:postcode":"20145",
    "sg:province":"Milano",
    "wof:name":"West Merchant Bank Ltd",
    "wof:placetype":"venue"
},
  "geometry": {"coordinates":[9.168756,45.477268],"type":"Point"}
}