{
  "type": "Feature",
  "properties": {
    "iso:country":"IT",
    "sg:address":"41100 Modena",
    "sg:city":"Modena",
    "sg:orig_category":"Cartiere - Macchine",
    "sg:phone":"+39 059 250481",
    "sg:postcode":"41100",
    "sg:province":"Modena",
    "wof:name":"Malagoli Alessandro",
    "wof:placetype":"venue"
},
  "geometry": {"coordinates":[10.924488,44.547882],"type":"Point"}
}