{
  "type": "Feature",
  "properties": {
    "addr:full":"Via G. La Spina 7, 98042 Pace Del Mela, Me Pace del Mela Messina 98042",
    "addr:housenumber":"7",
    "addr:postcode":"98042;98042",
    "addr:street":"Via G. La Spina",
    "iso:country":"IT",
    "sg:address":"Via G. La Spina 7, 98042 Pace Del Mela, Me",
    "sg:city":"Pace del Mela",
    "sg:classifiers":[
        {
            "category":"Banks & Credit Unions",
            "subcategory":"Bank",
            "type":"Services"
        }
    ],
    "sg:postcode":"98042",
    "sg:province":"Messina",
    "wof:name":"Banca Di Credito Cooperativo Di Pace Del Mela",
    "wof:placetype":"venue"
},
  "geometry": {"coordinates":[15.307973,38.180962],"type":"Point"}
}