{
  "type": "Feature",
  "properties": {
    "iso:country":"IT",
    "sg:address":"20123 Milano",
    "sg:city":"Milano",
    "sg:orig_category":"Assicurazioni E Servizi Assicurativi",
    "sg:phone":"+39 02 860000",
    "sg:postcode":"20123",
    "sg:province":"Milano",
    "wof:name":"Servizi Assicurativi De Micheli Srl",
    "wof:placetype":"venue"
},
  "geometry": {"coordinates":[9.181848,45.462959],"type":"Point"}
}