{
  "type": "Feature",
  "properties": {
    "iso:country":"IT",
    "sg:address":"7/4, Localita' Vaccheria 12051 Alba",
    "sg:city":"Alba",
    "sg:classifiers":[
        {
            "category":"Manufacturing",
            "subcategory":"Metals",
            "type":"Manufacturing & Wholesale Goods"
        }
    ],
    "sg:phone":"+39 0173 442088",
    "sg:postcode":"12051",
    "sg:province":"Cuneo",
    "sg:tags":[
        "processing"
    ],
    "wof:name":"Battaglino Elio E C. S.a.s.",
    "wof:placetype":"venue"
},
  "geometry": {"coordinates":[8.0748872757,44.7454223633],"type":"Point"}
}