{
  "type": "Feature",
  "properties": {
    "addr:full":"50124 Firenze Firenze Firenze 50124",
    "addr:postcode":"50124;50124",
    "iso:country":"IT",
    "sg:address":"50124 Firenze",
    "sg:city":"Firenze",
    "sg:orig_category":"Arte Ed Artigianato Artistico. Scuole E Servizi Scolastici. Servizi Ausiliari Di Analisi, Controllo E Ricerca",
    "sg:phone":"+39 055 221646",
    "sg:postcode":"50124",
    "sg:province":"Firenze",
    "wof:name":"Accademia Bartolomeo Cristofori Amici Del Fortepiano",
    "wof:placetype":"venue"
},
  "geometry": {"coordinates":[11.241155,43.768509],"type":"Point"}
}