{
  "type": "Feature",
  "properties": {
    "addr:full":"4, Via Cantarane 25030 Erbusco Erbusco Brescia 25030",
    "addr:postcode":"25030;25030",
    "addr:street":"Via Cantarane",
    "iso:country":"IT",
    "sg:address":"4, Via Cantarane 25030 Erbusco",
    "sg:city":"Erbusco",
    "sg:classifiers":[
        {
            "category":"Shopping",
            "subcategory":"Stationery & Office Supplies",
            "type":"Retail Goods"
        }
    ],
    "sg:phone":"+39 390 307 7101",
    "sg:postcode":"25030",
    "sg:province":"Brescia",
    "sg:tags":[
        "professional"
    ],
    "wof:name":"Semeraro Casa E Famiglia Sp",
    "wof:placetype":"venue"
},
  "geometry": {"coordinates":[9.9979476929,45.5810165405],"type":"Point"}
}