{
  "type": "Feature",
  "properties": {
    "iso:country":"IT",
    "sg:address":"2, Via Levi Carlo 81030 Lusciano",
    "sg:city":"Lusciano",
    "sg:classifiers":[
        {
            "category":"Food & Beverages",
            "subcategory":"Dairy",
            "type":"Retail Goods"
        }
    ],
    "sg:phone":"+39 081 814 4747",
    "sg:postcode":"81030",
    "sg:province":"Caserta",
    "sg:tags":[
        "product"
    ],
    "wof:name":"Casearia Olimpica Srl",
    "wof:placetype":"venue"
},
  "geometry": {"coordinates":[14.332194,41.075417],"type":"Point"}
}