{
  "type": "Feature",
  "properties": {
    "addr:full":"53034 Colle Di Val D'elsa Siena 53034",
    "addr:postcode":"53034;53034",
    "iso:country":"IT",
    "sg:address":"53034 Colle Di Val D'elsa",
    "sg:orig_category":"Prodotti E Manufatti In Gomma",
    "sg:phone":"+39 0577 909048",
    "sg:postcode":"53034",
    "sg:province":"Siena",
    "wof:name":"Pizzirani Srl",
    "wof:placetype":"venue"
},
  "geometry": {"coordinates":[11.0938081741,43.3848114014],"type":"Point"}
}