{
  "type": "Feature",
  "properties": {
    "iso:country":"IT",
    "sg:address":"09040 Donori",
    "sg:orig_category":"Dolciumi E Gelati",
    "sg:phone":"+39 070 981065",
    "sg:postcode":"09040",
    "sg:province":"Cagliari",
    "wof:name":"L'ape Sarda Di Aresu Maria",
    "wof:placetype":"venue"
},
  "geometry": {"coordinates":[9.17104,39.47435],"type":"Point"}
}