{
  "type": "Feature",
  "properties": {
    "iso:country":"IT",
    "sg:address":"19, Strada Cascina Baroggi 20064 Gorgonzola",
    "sg:city":"Gorgonzola",
    "sg:classifiers":[
        {
            "category":"Manufacturing",
            "subcategory":"Chemicals & Compounds",
            "type":"Manufacturing & Wholesale Goods"
        }
    ],
    "sg:phone":"+39 39029510690",
    "sg:postcode":"20064",
    "sg:province":"Milano",
    "sg:tags":[
        "chemistry"
    ],
    "wof:name":"Ba.do. Termoidrovacuum (s.r.l.)",
    "wof:placetype":"venue"
},
  "geometry": {"coordinates":[9.385477,45.52623],"type":"Point"}
}