{
  "type": "Feature",
  "properties": {
    "addr:full":"Via Statale 22040 Alzate Brianza Alzate Brianza Como 22040",
    "addr:postcode":"22040;22040",
    "addr:street":"Via Statale",
    "iso:country":"IT",
    "sg:address":"Via Statale 22040 Alzate Brianza",
    "sg:city":"Alzate Brianza",
    "sg:classifiers":[
        {
            "category":"Shopping",
            "subcategory":"Crafts & Fabrics",
            "type":"Retail Goods"
        }
    ],
    "sg:phone":"+39 39031631735",
    "sg:postcode":"22040",
    "sg:province":"Como",
    "wof:name":"Tessitura Di Lurago D'erba Srl",
    "wof:placetype":"venue"
},
  "geometry": {"coordinates":[9.1556997299,45.7902870178],"type":"Point"}
}