{
  "type": "Feature",
  "properties": {
    "iso:country":"IT",
    "sg:address":"24040 Madone",
    "sg:city":"Madone",
    "sg:classifiers":[
        {
            "category":"Social Services",
            "subcategory":"Job Training",
            "type":"Services"
        }
    ],
    "sg:phone":"+39 035 994420",
    "sg:postcode":"24040",
    "sg:province":"Bergamo",
    "sg:tags":[
        "flange"
    ],
    "wof:name":"S.i.t.i.m. Di Facchinetti Antonio & C. Sas",
    "wof:placetype":"venue"
},
  "geometry": {"coordinates":[9.5494623184,45.650680542],"type":"Point"}
}