{
  "type": "Feature",
  "properties": {
    "addr:full":"Via Valcunsat 1 33072 Casarsa Della Delizia Casarsa della Delizia Pordenone 33072",
    "addr:housenumber":"1",
    "addr:postcode":"33072;33072",
    "addr:street":"Via Valcunsat",
    "iso:country":"IT",
    "sg:address":"Via Valcunsat 1 33072 Casarsa Della Delizia",
    "sg:city":"Casarsa della Delizia",
    "sg:classifiers":[
        {
            "category":"Autos & Motor Vehicles",
            "subcategory":"Fuel & Gas Station",
            "type":"Retail Goods"
        }
    ],
    "sg:phone":"+39 0434 870830",
    "sg:postcode":"33072",
    "sg:province":"Pordenone",
    "sg:tags":[
        "submersible",
        "pump"
    ],
    "sg:website":"www.sublime.com",
    "wof:name":"Sublime Srl",
    "wof:placetype":"venue"
},
  "geometry": {"coordinates":[12.860218,45.96006],"type":"Point"}
}