{
  "type": "Feature",
  "properties": {
    "addr:full":"31020 Villorba Villorba Treviso 31020",
    "addr:postcode":"31020;31020",
    "iso:country":"IT",
    "sg:address":"31020 Villorba",
    "sg:city":"Villorba",
    "sg:orig_category":"Climatizzazione E Condizionamento, Apparecchiature E Servizi. Elettrotecnica Professionale E Di Consumo",
    "sg:phone":"+39 0422 918121",
    "sg:postcode":"31020",
    "sg:province":"Treviso",
    "sg:website":"http://www.tvm-termoventilmec.com",
    "wof:name":"Tvm Termoventilmec Spa",
    "wof:placetype":"venue"
},
  "geometry": {"coordinates":[12.260084,45.713669],"type":"Point"}
}