{
  "type": "Feature",
  "properties": {
    "iso:country":"IT",
    "sg:address":"33010 Tavagnacco",
    "sg:city":"Tavagnacco",
    "sg:orig_category":"Saldatura E Taglio - Impianti Ed Attrezzature",
    "sg:phone":"+39 0432 573602",
    "sg:postcode":"33010",
    "sg:province":"Udine",
    "wof:name":"S.i.c. Srl",
    "wof:placetype":"venue"
},
  "geometry": {"coordinates":[13.221408,46.113461],"type":"Point"}
}