{
  "type": "Feature",
  "properties": {
    "iso:country":"IT",
    "sg:address":"52033 Caprese Michelangelo",
    "sg:city":"Caprese Michelangelo",
    "sg:orig_category":"Non-classified Establishments",
    "sg:phone":"+39 0575 793984",
    "sg:postcode":"52033",
    "sg:province":"Arezzo",
    "sg:website":"http://www.fontanaarreda.it",
    "wof:name":"Mobilificio Fontana & Agostini Srl",
    "wof:placetype":"venue"
},
  "geometry": {"coordinates":[11.998445,43.647499],"type":"Point"}
}