{
  "type": "Feature",
  "properties": {
    "iso:country":"IT",
    "sg:address":"80059 Torre Del Greco",
    "sg:city":"Torre del Greco",
    "sg:classifiers":[
        {
            "category":"Home & Garden",
            "subcategory":"Building Materials",
            "type":"Retail Goods"
        }
    ],
    "sg:phone":"+39 081 847 3480",
    "sg:postcode":"80059",
    "sg:province":"Napoli",
    "sg:tags":[
        "window",
        "door",
        "frame"
    ],
    "sg:website":"http://www.profilcomarin.it",
    "wof:name":"Profil Comarin Sas",
    "wof:placetype":"venue"
},
  "geometry": {"coordinates":[14.399472,40.7812],"type":"Point"}
}