{
  "type": "Feature",
  "properties": {
    "addr:full":"22070 Montano Lucino Lucino Como 22070",
    "addr:postcode":"22070;22070",
    "addr:street":"Lucino Lucino",
    "iso:country":"IT",
    "sg:address":"22070 Montano Lucino",
    "sg:city":"Lucino",
    "sg:orig_category":"Studi E Consulenze Tecniche E Industriali. Consulenze Tecniche, Amministrative E Perizie. Professionisti - Studi E Servizi Ed Associazioni Di Interesse Aziendale",
    "sg:phone":"+39 031 470403",
    "sg:postcode":"22070",
    "sg:province":"Como",
    "wof:name":"Pizzelli Franco S.a.s.",
    "wof:placetype":"venue"
},
  "geometry": {"coordinates":[9.044027,45.784744],"type":"Point"}
}