{
  "type": "Feature",
  "properties": {
    "iso:country":"IT",
    "sg:address":"84015 Nocera Superiore",
    "sg:city":"Nocera Superiore",
    "sg:orig_category":"Servizi E Lavori Per Edilizia E Lavori Pubblici. Servizi Ausiliari Di Sorveglianza, Manutenzione E Pulizia",
    "sg:phone":"+39 081 514 3353",
    "sg:postcode":"84015",
    "sg:province":"Salerno",
    "wof:name":"Antonio Cimino",
    "wof:placetype":"venue"
},
  "geometry": {"coordinates":[14.676273,40.73407],"type":"Point"}
}