{
  "type": "Feature",
  "properties": {
    "iso:country":"IT",
    "sg:address":"10070 San Francesco Al Campo",
    "sg:city":"Barbania",
    "sg:orig_category":"Servizi E Lavori Industria Della Gomma",
    "sg:phone":"+39 011 927 9422",
    "sg:postcode":"10070",
    "sg:province":"Torino",
    "wof:name":"Tecnogomma Srl",
    "wof:placetype":"venue"
},
  "geometry": {"coordinates":[7.653266,45.229504],"type":"Point"}
}