{
  "type": "Feature",
  "properties": {
    "addr:full":"90124 Palermo Palermo Palermo 90124",
    "addr:postcode":"90124;90124",
    "iso:country":"IT",
    "sg:address":"90124 Palermo",
    "sg:city":"Palermo",
    "sg:orig_category":"Parrucche E Toupets - Produzione E Ingrosso",
    "sg:phone":"+39 091 630 5368",
    "sg:postcode":"90124",
    "sg:province":"Palermo",
    "wof:name":"Saieva Vincenzo",
    "wof:placetype":"venue"
},
  "geometry": {"coordinates":[13.3667402267,38.1067047119],"type":"Point"}
}