{
  "type": "Feature",
  "properties": {
    "addr:full":"84010 Sant'egidio Del Monte Albino Salerno 84010",
    "addr:postcode":"84010;84010",
    "iso:country":"IT",
    "sg:address":"84010 Sant'egidio Del Monte Albino",
    "sg:orig_category":"Analisi Chimiche, Industriali E Merceologiche",
    "sg:phone":"+39 081 515 4989",
    "sg:postcode":"84010",
    "sg:province":"Salerno",
    "wof:name":"Ecoscreening Srl",
    "wof:placetype":"venue"
},
  "geometry": {"coordinates":[14.60234,40.741364],"type":"Point"}
}