{
  "type": "Feature",
  "properties": {
    "addr:full":"00183 Roma Roma Roma 00183",
    "addr:postcode":"00183;00183",
    "iso:country":"IT",
    "sg:address":"00183 Roma",
    "sg:city":"Roma",
    "sg:orig_category":"Armi E Munizioni - Vendita Al Dettaglio",
    "sg:phone":"+39 06 7047 6281",
    "sg:postcode":"00183",
    "sg:province":"Roma",
    "wof:name":"Maxarmi Srl",
    "wof:placetype":"venue"
},
  "geometry": {"coordinates":[12.507749,41.875332],"type":"Point"}
}