{
  "type": "Feature",
  "properties": {
    "iso:country":"IT",
    "sg:address":"3, Via Zona Industriale 74020 Montemesola",
    "sg:city":"Montemesola",
    "sg:classifiers":[
        {
            "category":"Personal",
            "subcategory":"Shoe Repair & Shine",
            "type":"Services"
        }
    ],
    "sg:phone":"+39 099 566 4834",
    "sg:postcode":"74020",
    "sg:province":"Taranto",
    "sg:tags":[
        "leather"
    ],
    "wof:name":"Solettificio M.p. Di Mare Patrizia",
    "wof:placetype":"venue"
},
  "geometry": {"coordinates":[17.240009,40.469238],"type":"Point"}
}