{
  "type": "Feature",
  "properties": {
    "iso:country":"IT",
    "sg:address":"20068 Peschiera Borromeo",
    "sg:city":"Peschiera Borromeo",
    "sg:orig_category":"Cartotecnica E Servizi. Articoli Per Imballaggio E Confezionamento",
    "sg:phone":"+39 02 547 1276",
    "sg:postcode":"20068",
    "sg:province":"Milano",
    "wof:name":"Cartotecnica Tds Srl",
    "wof:placetype":"venue"
},
  "geometry": {"coordinates":[9.288423,45.429073],"type":"Point"}
}