{
  "type": "Feature",
  "properties": {
    "iso:country":"IT",
    "sg:address":"27, Via Giorgione 51039 Quarrata",
    "sg:city":"Quarrata",
    "sg:classifiers":[
        {
            "category":"Manufacturing",
            "subcategory":"Rubber & Plastics",
            "type":"Manufacturing & Wholesale Goods"
        }
    ],
    "sg:phone":"+39 0573 775453",
    "sg:postcode":"51039",
    "sg:province":"Pistoia",
    "wof:name":"Sofa' 2001 Srl Unipersonale",
    "wof:placetype":"venue"
},
  "geometry": {"coordinates":[10.98802948,43.8587226868],"type":"Point"}
}