{
  "type": "Feature",
  "properties": {
    "addr:full":"16163 Genova Genova Genova 16163",
    "addr:postcode":"16163;16163",
    "iso:country":"IT",
    "sg:address":"16163 Genova",
    "sg:city":"Genova",
    "sg:orig_category":"Forniture Per Agricoltura E Zootecnia",
    "sg:phone":"+39 010 726 1160",
    "sg:postcode":"16163",
    "sg:province":"Genova",
    "wof:name":"Agrifarma S.a.s. Di Foppiani Michele & C.",
    "wof:placetype":"venue"
},
  "geometry": {"coordinates":[8.8993215561,44.4905014038],"type":"Point"}
}