{
  "type": "Feature",
  "properties": {
    "addr:full":"47900 Rimini Rimini Rimini 47900",
    "addr:postcode":"47900;47900",
    "iso:country":"IT",
    "sg:address":"47900 Rimini",
    "sg:city":"Rimini",
    "sg:orig_category":"Ceramiche: Prodotti E Lavorazioni. Articoli Da Regalo. Arte Ed Artigianato Artistico. Shopping",
    "sg:phone":"+39 0541 743698",
    "sg:postcode":"47900",
    "sg:province":"Rimini",
    "wof:name":"Bardelli Srl",
    "wof:placetype":"venue"
},
  "geometry": {"coordinates":[12.531578,44.064083],"type":"Point"}
}