{
  "type": "Feature",
  "properties": {
    "iso:country":"IT",
    "sg:address":"20099 Sesto San Giovanni",
    "sg:city":"Sesto San Giovanni",
    "sg:orig_category":"Materiali E Componenti Elettronici",
    "sg:phone":"+39 02 248 4578",
    "sg:postcode":"20099",
    "sg:province":"Milano",
    "wof:name":"Secom Srl",
    "wof:placetype":"venue"
},
  "geometry": {"coordinates":[9.239779,45.532341],"type":"Point"}
}