{
  "type": "Feature",
  "properties": {
    "iso:country":"IT",
    "sg:address":"20038 Seregno",
    "sg:city":"Seregno",
    "sg:orig_category":"Non-classified Establishments",
    "sg:phone":"+39 036 232 5382",
    "sg:postcode":"20038",
    "sg:province":"Milano",
    "sg:website":"http://www.fgm-giambellini.com",
    "wof:name":"Fgm Giambellini Srl",
    "wof:placetype":"venue"
},
  "geometry": {"coordinates":[9.203573,45.651917],"type":"Point"}
}