{
  "type": "Feature",
  "properties": {
    "iso:country":"IT",
    "sg:address":"00198 Roma",
    "sg:city":"Roma",
    "sg:classifiers":[
        {
            "category":"Communications",
            "subcategory":"Film & Video Production",
            "type":"Services"
        }
    ],
    "sg:phone":"+39 06 841 9605",
    "sg:postcode":"00198",
    "sg:province":"Roma",
    "sg:tags":[
        "certificates",
        "photo",
        "auxiliary",
        "reproduction",
        "drawing"
    ],
    "wof:name":"Agenzia Salaria Srl",
    "wof:placetype":"venue"
},
  "geometry": {"coordinates":[12.590537,42.063171],"type":"Point"}
}