{
  "type": "Feature",
  "properties": {
    "iso:country":"IT",
    "sg:address":"22020 San Fermo Della Battaglia",
    "sg:city":"San Fermo della Battaglia",
    "sg:orig_category":"Frigoriferi Industriali E Commerciali - Commercio",
    "sg:phone":"+39 031 210034",
    "sg:postcode":"22020",
    "sg:province":"Como",
    "wof:name":"Comofrigor Snc Dei F.lli Beccari",
    "wof:placetype":"venue"
},
  "geometry": {"coordinates":[9.049577713,45.802986145],"type":"Point"}
}