{
  "type": "Feature",
  "properties": {
    "addr:full":"20122 Milano Milano Milano 20122",
    "addr:postcode":"20122;20122",
    "iso:country":"IT",
    "sg:address":"20122 Milano",
    "sg:city":"Milano",
    "sg:orig_category":"Pubblicita', Marketing E Comunicazione",
    "sg:phone":"+39 02 8645 1029",
    "sg:postcode":"20122",
    "sg:province":"Milano",
    "wof:name":"Ab Service Soc Coop A R L",
    "wof:placetype":"venue"
},
  "geometry": {"coordinates":[9.18978405,45.4585456848],"type":"Point"}
}