{
  "type": "Feature",
  "properties": {
    "addr:full":"7, V. Provaglia 40138 Bologna Bologna Bologna 40138",
    "addr:housenumber":"7",
    "addr:postcode":"40138;40138",
    "addr:street":"V. Provaglia",
    "iso:country":"IT",
    "sg:address":"7, V. Provaglia 40138 Bologna",
    "sg:city":"Bologna",
    "sg:classifiers":[
        {
            "category":"Professional",
            "subcategory":"Engineering",
            "type":"Services"
        }
    ],
    "sg:phone":"+39 39051532145",
    "sg:postcode":"40138",
    "sg:province":"Bologna",
    "sg:tags":[
        "machine",
        "-",
        "mechanical"
    ],
    "sg:website":"http://www.mcncaldaie.com",
    "wof:name":"M.c.n. Srl",
    "wof:placetype":"venue"
},
  "geometry": {"coordinates":[11.398512,44.495522],"type":"Point"}
}