{
  "type": "Feature",
  "properties": {
    "iso:country":"IT",
    "sg:address":"98124 Messina",
    "sg:city":"Messina",
    "sg:orig_category":"Arredo Cucina Ed Elettrodomestici. Elettrodomestici",
    "sg:phone":"+39 090 292 1007",
    "sg:postcode":"98124",
    "sg:province":"Messina",
    "wof:name":"Electronic Brain",
    "wof:placetype":"venue"
},
  "geometry": {"coordinates":[15.541151,38.172119],"type":"Point"}
}