{
  "type": "Feature",
  "properties": {
    "iso:country":"IT",
    "sg:address":"00040 Pomezia",
    "sg:city":"Pomezia",
    "sg:orig_category":"Ristorazione E Locali Pubblici Affini. Ristoranti Ed Esercizi Affini. Servizi Ausiliari Di Ristorazione E Di Intrattenimento",
    "sg:phone":"+39 06 911481",
    "sg:postcode":"00040",
    "sg:province":"Roma",
    "wof:name":"Hotel Antonella Srl",
    "wof:placetype":"venue"
},
  "geometry": {"coordinates":[12.499561,41.676605],"type":"Point"}
}