{
  "type": "Feature",
  "properties": {
    "addr:full":"60, Via Morsella 27036 Mortara Mortara Pavia 27036",
    "addr:postcode":"27036;27036",
    "addr:street":"Via Morsella",
    "iso:country":"IT",
    "sg:address":"60, Via Morsella 27036 Mortara",
    "sg:city":"Mortara",
    "sg:classifiers":[
        {
            "category":"Professional",
            "subcategory":"Engineering",
            "type":"Services"
        }
    ],
    "sg:phone":"+39 39038493381",
    "sg:postcode":"27036",
    "sg:province":"Pavia",
    "sg:tags":[
        "machine",
        "-",
        "mechanical"
    ],
    "wof:name":"Unitech S.r.l.",
    "wof:placetype":"venue"
},
  "geometry": {"coordinates":[8.790738,45.268208],"type":"Point"}
}