{
  "type": "Feature",
  "properties": {
    "iso:country":"IT",
    "sg:address":"06049 Spoleto",
    "sg:city":"Spoleto",
    "sg:orig_category":"Materiali Edili",
    "sg:phone":"+39 0573 229975",
    "sg:postcode":"06049",
    "sg:province":"Perugia",
    "wof:name":"Tecnocal Spa",
    "wof:placetype":"venue"
},
  "geometry": {"coordinates":[12.690533,42.719028],"type":"Point"}
}