{
  "type": "Feature",
  "properties": {
    "addr:full":"10121 Torino Torino Torino 10121",
    "addr:postcode":"10121;10121",
    "iso:country":"IT",
    "sg:address":"10121 Torino",
    "sg:city":"Torino",
    "sg:orig_category":"Ospedali E Servizi Sanitari. Servizi Sociali. Associazioni Ed Organismi Di Interesse Pubblico",
    "sg:phone":"+39 011 537542",
    "sg:postcode":"10121",
    "sg:province":"Torino",
    "wof:name":"Fidas Federazione Italiana Associazioni Donatori Sangue",
    "wof:placetype":"venue"
},
  "geometry": {"coordinates":[7.675093,45.066814],"type":"Point"}
}