{
  "type": "Feature",
  "properties": {
    "addr:full":"07041 Alghero Alghero Sassari 07041",
    "addr:postcode":"07041;07041",
    "iso:country":"IT",
    "sg:address":"07041 Alghero",
    "sg:city":"Alghero",
    "sg:orig_category":"Autodemolizioni",
    "sg:phone":"+39 079 986328",
    "sg:postcode":"07041",
    "sg:province":"Sassari",
    "wof:name":"Oleosistem Di G.luca Pastrovicchio & C. Snc",
    "wof:placetype":"venue"
},
  "geometry": {"coordinates":[8.286948,40.641041],"type":"Point"}
}