{
  "type": "Feature",
  "properties": {
    "addr:full":"19, Contrada Cona 87030 Belsito Belsito Cosenza 87030",
    "addr:postcode":"87030;87030",
    "addr:street":"Contrada Cona",
    "iso:country":"IT",
    "sg:address":"19, Contrada Cona 87030 Belsito",
    "sg:city":"Belsito",
    "sg:classifiers":[
        {
            "category":"Shopping",
            "type":"Retail Goods"
        }
    ],
    "sg:phone":"+39 0984 983425",
    "sg:postcode":"87030",
    "sg:province":"Cosenza",
    "sg:tags":[
        "finished",
        "-",
        "metallic"
    ],
    "wof:name":"M.c. S.d.f. Di Macchione E Cicchelli",
    "wof:placetype":"venue"
},
  "geometry": {"coordinates":[16.2861747742,39.1792373657],"type":"Point"}
}