{
  "type": "Feature",
  "properties": {
    "iso:country":"IT",
    "sg:address":"80133 Napoli",
    "sg:city":"Napoli",
    "sg:orig_category":"Macchine, Impianti Ed Attrezzature Industria Chimica. Macchine E Impianti Per Attivita' Commerciali Ed Artigianali",
    "sg:phone":"+39 081 284123",
    "sg:postcode":"80133",
    "sg:province":"Napoli",
    "wof:name":"Genovesi Gaetano",
    "wof:placetype":"venue"
},
  "geometry": {"coordinates":[14.255583,40.841072],"type":"Point"}
}