{
  "type": "Feature",
  "properties": {
    "iso:country":"IT",
    "sg:address":"50145 Firenze",
    "sg:city":"Firenze",
    "sg:classifiers":[
        {
            "category":"Cinema",
            "subcategory":"Drive-in Theater",
            "type":"Entertainment"
        }
    ],
    "sg:phone":"+39 055 317976",
    "sg:postcode":"50145",
    "sg:province":"Firenze",
    "sg:tags":[
        "sector",
        "radio-television",
        "supply"
    ],
    "wof:name":"Cinemec Snc",
    "wof:placetype":"venue"
},
  "geometry": {"coordinates":[11.187502,43.799576],"type":"Point"}
}