{
  "type": "Feature",
  "properties": {
    "iso:country":"IT",
    "sg:address":"37/a, Via Monte Grugnanello 00067 Morlupo",
    "sg:city":"Morlupo",
    "sg:classifiers":[
        {
            "category":"Personal",
            "subcategory":"Shoe Repair & Shine",
            "type":"Services"
        }
    ],
    "sg:phone":"+39 39069072304",
    "sg:postcode":"00067",
    "sg:province":"Roma",
    "sg:tags":[
        "leather"
    ],
    "wof:name":"Biemme Pelletterie S.n.c.",
    "wof:placetype":"venue"
},
  "geometry": {"coordinates":[12.482325,41.895466],"type":"Point"}
}