{
  "type": "Feature",
  "properties": {
    "iso:country":"IT",
    "sg:address":"51013 Chiesina Uzzanese",
    "sg:city":"Chiesina Uzzanese",
    "sg:orig_category":"Agenzie Immobiliari",
    "sg:phone":"+39 0572 411492",
    "sg:postcode":"51013",
    "sg:province":"Pistoia",
    "sg:website":"http://www.lucaimmobiliare.com",
    "wof:name":"Luca Immobiliare",
    "wof:placetype":"venue"
},
  "geometry": {"coordinates":[10.719529,43.839405],"type":"Point"}
}