{
  "type": "Feature",
  "properties": {
    "addr:full":"V.le Del Lavoro 128 62014 Corridonia Corridonia Macerata 62014",
    "addr:housenumber":"128",
    "addr:postcode":"62014;62014",
    "addr:street":"V.Le Del Lavoro",
    "iso:country":"IT",
    "sg:address":"V.le Del Lavoro 128 62014 Corridonia",
    "sg:city":"Corridonia",
    "sg:classifiers":[
        {
            "category":"Shopping",
            "subcategory":"Stationery & Office Supplies",
            "type":"Retail Goods"
        }
    ],
    "sg:phone":"+39 0733 283020",
    "sg:postcode":"62014",
    "sg:province":"Macerata",
    "sg:tags":[
        "furniture"
    ],
    "wof:name":"Efar Arredamenti Srl",
    "wof:placetype":"venue"
},
  "geometry": {"coordinates":[13.487377,43.264011],"type":"Point"}
}