{
  "type": "Feature",
  "properties": {
    "iso:country":"IT",
    "sg:address":"33100 Udine",
    "sg:city":"Udine",
    "sg:orig_category":"Agenzie D'affari E Servizi Commerciali. Acqua, Luce, Gas E Societa' Di Esercizio Pubblico",
    "sg:phone":"+39 0432 299947",
    "sg:postcode":"33100",
    "sg:province":"Udine",
    "wof:name":"Coveg Srl",
    "wof:placetype":"venue"
},
  "geometry": {"coordinates":[13.230629,46.061047],"type":"Point"}
}