{
  "type": "Feature",
  "properties": {
    "iso:country":"IT",
    "sg:address":"04015 Priverno",
    "sg:city":"Priverno",
    "sg:orig_category":"Prodotti Di Base E Forniture Per Industria Alimentare E Bevande. Carta, Cartone E Prodotti Primari. Forniture Per Attivita' Commerciali Ed Artigianali",
    "sg:phone":"+39 0773 903878",
    "sg:postcode":"04015",
    "sg:province":"Latina",
    "wof:name":"Co.dis.s.n.c. Dei Colabono Ascenzo",
    "wof:placetype":"venue"
},
  "geometry": {"coordinates":[13.1625003815,41.4683189392],"type":"Point"}
}