{
  "type": "Feature",
  "properties": {
    "iso:country":"IT",
    "sg:address":"Via Monte Asolon 39 36022 San Zeno",
    "sg:city":"San Zeno",
    "sg:classifiers":[
        {
            "category":"Manufacturing",
            "subcategory":"Metals",
            "type":"Manufacturing & Wholesale Goods"
        }
    ],
    "sg:phone":"+39 0424 570269",
    "sg:postcode":"36022",
    "sg:province":"Vicenza",
    "sg:tags":[
        "precious",
        "furnace",
        "heating"
    ],
    "wof:name":"Costruzioni Generali Grafiti Srl",
    "wof:placetype":"venue"
},
  "geometry": {"coordinates":[11.540307,45.545906],"type":"Point"}
}