{
  "type": "Feature",
  "properties": {
    "iso:country":"IT",
    "sg:address":"90046 Monreale",
    "sg:city":"Monreale",
    "sg:orig_category":"Gelaterie",
    "sg:phone":"+39 091 640 9004",
    "sg:postcode":"90046",
    "sg:province":"Palermo",
    "wof:name":"Gelateria Pink Panther",
    "wof:placetype":"venue"
},
  "geometry": {"coordinates":[13.292022,38.082748],"type":"Point"}
}