{
  "type": "Feature",
  "properties": {
    "iso:country":"IT",
    "sg:address":"81, Via Dei Ribes 00172 Roma",
    "sg:city":"Roma",
    "sg:classifiers":[
        {
            "category":"Food & Beverages",
            "subcategory":"Groceries & Convenience Stores",
            "type":"Retail Goods"
        }
    ],
    "sg:phone":"+39 39062572843",
    "sg:postcode":"00172",
    "sg:province":"Roma",
    "sg:tags":[
        "drink"
    ],
    "wof:name":"Delmar Srl",
    "wof:placetype":"venue"
},
  "geometry": {"coordinates":[12.577966,41.886745],"type":"Point"}
}