{
  "type": "Feature",
  "properties": {
    "iso:country":"IT",
    "sg:address":"16167 Genova",
    "sg:city":"Genova",
    "sg:orig_category":"Forniture Per Abbigliamento E Pelletterie",
    "sg:phone":"+39 010 323869",
    "sg:postcode":"16167",
    "sg:province":"Genova",
    "wof:name":"Areltex Srl",
    "wof:placetype":"venue"
},
  "geometry": {"coordinates":[9.0348157883,44.3878250122],"type":"Point"}
}