{
  "type": "Feature",
  "properties": {
    "addr:full":"28076 Pogno Pogno Novara 28076",
    "addr:postcode":"28076;28076",
    "iso:country":"IT",
    "sg:address":"28076 Pogno",
    "sg:city":"Pogno",
    "sg:orig_category":"Fonderie Bronzo, Ottone E Rame",
    "sg:phone":"+39 0322 97275",
    "sg:postcode":"28076",
    "sg:province":"Novara",
    "wof:name":"Peretti Srl",
    "wof:placetype":"venue"
},
  "geometry": {"coordinates":[8.3890609741,45.7557258606],"type":"Point"}
}