{
  "type": "Feature",
  "properties": {
    "iso:country":"IT",
    "sg:address":"Borgo Santi Apostoli 15 50123 Firenze",
    "sg:city":"Firenze",
    "sg:classifiers":[
        {
            "category":"Shopping",
            "subcategory":"Jewelry",
            "type":"Retail Goods"
        }
    ],
    "sg:phone":"+39 055 287304",
    "sg:postcode":"50123",
    "sg:province":"Firenze",
    "sg:tags":[
        "gemstone",
        "jewellery"
    ],
    "wof:name":"Gold Alley Srl",
    "wof:placetype":"venue"
},
  "geometry": {"coordinates":[11.252688,43.769295],"type":"Point"}
}