{
  "type": "Feature",
  "properties": {
    "addr:full":"50019 Sesto Fiorentino Sesto Fiorentino Firenze 50019",
    "addr:postcode":"50019;50019",
    "iso:country":"IT",
    "sg:address":"50019 Sesto Fiorentino",
    "sg:city":"Sesto Fiorentino",
    "sg:orig_category":"Fotografia Apparecchi E Materiali - Vendita Al Dettaglio",
    "sg:phone":"+39 055 340825",
    "sg:postcode":"50019",
    "sg:province":"Firenze",
    "wof:name":"New S.a.r. Srl",
    "wof:placetype":"venue"
},
  "geometry": {"coordinates":[11.17811203,43.811340332],"type":"Point"}
}