{
  "type": "Feature",
  "properties": {
    "iso:country":"IT",
    "sg:address":"12100 Cuneo",
    "sg:city":"Cuneo",
    "sg:orig_category":"Macchine Ed Impianti Per Edilizia E Lavori Pubblici. Macchine, Strumenti Ed Apparecchi Per Attivita' Industriali",
    "sg:phone":"+39 0171 692370",
    "sg:postcode":"12100",
    "sg:province":"Cuneo",
    "wof:name":"Granata Service Di Granata Cristiano",
    "wof:placetype":"venue"
},
  "geometry": {"coordinates":[7.539258,44.386208],"type":"Point"}
}