{
  "type": "Feature",
  "properties": {
    "iso:country":"IT",
    "sg:address":"14100 Asti",
    "sg:city":"Asti",
    "sg:orig_category":"Ricambi E Componenti Dei Mezzi Di Trasporto. Riparazione Dei Mezzi Di Trasporto",
    "sg:phone":"+39 0141 208774",
    "sg:postcode":"14100",
    "sg:province":"Asti",
    "wof:name":"Fratelli Nonanta Snc",
    "wof:placetype":"venue"
},
  "geometry": {"coordinates":[8.192273,44.883762],"type":"Point"}
}