{
  "type": "Feature",
  "properties": {
    "iso:country":"IT",
    "sg:address":"5, Largo Po 21052 Busto Arsizio",
    "sg:city":"Busto Arsizio",
    "sg:classifiers":[
        {
            "category":"Shopping",
            "subcategory":"Crafts & Fabrics",
            "type":"Retail Goods"
        }
    ],
    "sg:phone":"+39 0331 632977",
    "sg:postcode":"21052",
    "sg:province":"Varese",
    "wof:name":"Iniziativa Cerana Srl",
    "wof:placetype":"venue"
},
  "geometry": {"coordinates":[8.8557424545,45.6205940247],"type":"Point"}
}