{
  "type": "Feature",
  "properties": {
    "iso:country":"IT",
    "sg:address":"Via Longobarda 6 54100 Massa",
    "sg:city":"Massa",
    "sg:classifiers":[
        {
            "category":"Banks & Credit Unions",
            "subcategory":"Investment Brokerage",
            "type":"Services"
        }
    ],
    "sg:phone":"+39 0585 830941",
    "sg:postcode":"54100",
    "sg:province":"Massa-Carrara",
    "sg:tags":[
        "work",
        "marble"
    ],
    "sg:website":"www.contri-marmi.com",
    "wof:name":"Cav. Dino Contri & Figli Srl",
    "wof:placetype":"venue"
},
  "geometry": {"coordinates":[10.035966,44.221401],"type":"Point"}
}