{
  "type": "Feature",
  "properties": {
    "addr:full":"00159 Roma Roma Roma 00159",
    "addr:postcode":"00159;00159",
    "iso:country":"IT",
    "sg:address":"00159 Roma",
    "sg:city":"Roma",
    "sg:orig_category":"Lavorazioni Meccaniche E Servizi. Riparazione Dei Mezzi Di Trasporto",
    "sg:phone":"+39 06 438 5791",
    "sg:postcode":"00159",
    "sg:province":"Roma",
    "wof:name":"Bruno Vincenzo",
    "wof:placetype":"venue"
},
  "geometry": {"coordinates":[12.537294,41.89703],"type":"Point"}
}