{
  "type": "Feature",
  "properties": {
    "iso:country":"IT",
    "sg:address":"20136 Milano",
    "sg:city":"Milano",
    "sg:orig_category":"Servizi Vari Di Interesse Pubblico",
    "sg:phone":"+39 02 8940 2583",
    "sg:postcode":"20136",
    "sg:province":"Milano",
    "wof:name":"Bar Baby Snc",
    "wof:placetype":"venue"
},
  "geometry": {"coordinates":[9.178369,45.443447],"type":"Point"}
}