{
  "type": "Feature",
  "properties": {
    "addr:full":"63023 Fermo Campiglione Ascoli Piceno 63023",
    "addr:postcode":"63023;63023",
    "iso:country":"IT",
    "sg:address":"63023 Fermo",
    "sg:city":"Campiglione",
    "sg:orig_category":"Serramenti Ed Infissi",
    "sg:phone":"+39 0734 628303",
    "sg:postcode":"63023",
    "sg:province":"Ascoli Piceno",
    "sg:website":"http://www.royalpat.it",
    "wof:name":"Royal Pat Srl",
    "wof:placetype":"venue"
},
  "geometry": {"coordinates":[13.670963,43.178444],"type":"Point"}
}