{
  "type": "Feature",
  "properties": {
    "addr:full":"18/20, Via Enrico Mattei 20010 Mesero Mesero Milano 20010",
    "addr:housenumber":"18 / 20",
    "addr:postcode":"20010;20010",
    "addr:street":"Via Enrico Mattei",
    "iso:country":"IT",
    "sg:address":"18/20, Via Enrico Mattei 20010 Mesero",
    "sg:city":"Mesero",
    "sg:classifiers":[
        {
            "category":"Professional",
            "subcategory":"Engineering",
            "type":"Services"
        }
    ],
    "sg:phone":"+39 02 9728 9696",
    "sg:postcode":"20010",
    "sg:province":"Milano",
    "sg:tags":[
        "machine",
        "-",
        "mechanical"
    ],
    "wof:name":"I.t.f. Srl Impianti Trattamenti Finitura",
    "wof:placetype":"venue"
},
  "geometry": {"coordinates":[9.188141,45.463688],"type":"Point"}
}