{
  "type": "Feature",
  "properties": {
    "iso:country":"IT",
    "sg:address":"35010 Limena",
    "sg:city":"Limena",
    "sg:orig_category":"Macchine, Impianti E Forniture Per Industria Grafica, Cartaria E Cartotecnica",
    "sg:phone":"+39 049 767166",
    "sg:postcode":"35010",
    "sg:province":"Padova",
    "wof:name":"Camporese Macchine Grafiche S.r.l.",
    "wof:placetype":"venue"
},
  "geometry": {"coordinates":[11.857602,45.457825],"type":"Point"}
}