{
  "type": "Feature",
  "properties": {
    "iso:country":"IT",
    "sg:address":"56, Via Torino 13900 Biella",
    "sg:city":"Biella",
    "sg:classifiers":[
        {
            "category":"Travel",
            "subcategory":"Travel Agent",
            "type":"Entertainment"
        }
    ],
    "sg:phone":"+39 015 849 5606",
    "sg:postcode":"13900",
    "sg:province":"Biella",
    "sg:tags":[
        "business"
    ],
    "wof:name":"Associazione Ideabiella",
    "wof:placetype":"venue"
},
  "geometry": {"coordinates":[8.060537,45.559265],"type":"Point"}
}