{
  "type": "Feature",
  "properties": {
    "addr:full":"9, Via Dell' Industria 33098 Valvasone Valvasone Pordenone 33098",
    "addr:postcode":"33098;33098",
    "addr:street":"Via Dell ' Industria",
    "iso:country":"IT",
    "sg:address":"9, Via Dell' Industria 33098 Valvasone",
    "sg:city":"Valvasone",
    "sg:classifiers":[
        {
            "category":"Professional",
            "subcategory":"Engineering",
            "type":"Services"
        }
    ],
    "sg:phone":"+39 39043485440",
    "sg:postcode":"33098",
    "sg:province":"Pordenone",
    "sg:tags":[
        "machine",
        "-",
        "mechanical"
    ],
    "wof:name":"Dimac S.r.l.",
    "wof:placetype":"venue"
},
  "geometry": {"coordinates":[12.655044,45.96265],"type":"Point"}
}