{
  "type": "Feature",
  "properties": {
    "iso:country":"IT",
    "sg:address":"15011 Acqui Terme",
    "sg:city":"Acqui Terme",
    "sg:orig_category":"Forniture Per Edilizia E Lavori Pubblici",
    "sg:phone":"+39 0144 322215",
    "sg:postcode":"15011",
    "sg:province":"Alessandria",
    "wof:name":"Leoncino Enzo",
    "wof:placetype":"venue"
},
  "geometry": {"coordinates":[8.4713659286,44.6774864197],"type":"Point"}
}