{
  "type": "Feature",
  "properties": {
    "iso:country":"IT",
    "sg:address":"16152 Genova",
    "sg:city":"Genova",
    "sg:orig_category":"Telecomunicazioni E Telefonia, Impianti, Apparecchi E Servizi",
    "sg:phone":"+39 010 651 2653",
    "sg:postcode":"16152",
    "sg:province":"Genova",
    "sg:website":"http://www.sea-impianti.it",
    "wof:name":"S.e.a. Srl",
    "wof:placetype":"venue"
},
  "geometry": {"coordinates":[8.887343,44.426205],"type":"Point"}
}