{
  "type": "Feature",
  "properties": {
    "iso:country":"IT",
    "sg:address":"40034 Castel D'aiano",
    "sg:orig_category":"Zootecnia E Pesca, Allevamento Piccoli Animali. Servizi Per Lo Sport E Il Tempo Libero",
    "sg:phone":"+39 051 919272",
    "sg:postcode":"40034",
    "sg:province":"Bologna",
    "wof:name":"Azienda Agricola La Fenice",
    "wof:placetype":"venue"
},
  "geometry": {"coordinates":[11.014619,44.271164],"type":"Point"}
}