{
  "type": "Feature",
  "properties": {
    "addr:full":"50127 Firenze Firenze Firenze 50127",
    "addr:postcode":"50127;50127",
    "iso:country":"IT",
    "sg:address":"50127 Firenze",
    "sg:city":"Firenze",
    "sg:orig_category":"Informatica - Consulenza E Servizi. Editoria",
    "sg:phone":"+39 055 436 8525",
    "sg:postcode":"50127",
    "sg:province":"Firenze",
    "sg:website":"http://www.plangroup.it",
    "wof:name":"Plan Group",
    "wof:placetype":"venue"
},
  "geometry": {"coordinates":[11.216192,43.708786],"type":"Point"}
}