{
  "type": "Feature",
  "properties": {
    "iso:country":"IT",
    "sg:address":"Piazza Municipio 35/37; Vicari; 90020",
    "sg:city":"Vicari",
    "sg:classifiers":[
        {
            "category":"Banks & Credit Unions",
            "subcategory":"Bank",
            "type":"Services"
        }
    ],
    "sg:phone":"+39 091 821 6012",
    "sg:postcode":"90020",
    "sg:province":"Palermo",
    "wof:name":"Banco Di Sicilia Spa",
    "wof:placetype":"venue"
},
  "geometry": {"coordinates":[13.566579,37.822853],"type":"Point"}
}