{
  "type": "Feature",
  "properties": {
    "iso:country":"IT",
    "sg:address":"01010 Gradoli",
    "sg:city":"Gradoli",
    "sg:orig_category":"Ristorazione E Locali Pubblici Affini. Servizi Ausiliari Di Ristorazione E Di Intrattenimento",
    "sg:phone":"+39 0761 456100",
    "sg:postcode":"01010",
    "sg:province":"Viterbo",
    "sg:website":"http://www.laripetta.it",
    "wof:name":"Ristorante-albergo 'la Ripetta'",
    "wof:placetype":"venue"
},
  "geometry": {"coordinates":[12.135119,42.55761],"type":"Point"}
}