{
  "type": "Feature",
  "properties": {
    "iso:country":"IT",
    "sg:address":"10, Via Tulipani 20020 Vanzaghello",
    "sg:city":"Vanzaghello",
    "sg:classifiers":[
        {
            "category":"Manufacturing",
            "subcategory":"Printing",
            "type":"Manufacturing & Wholesale Goods"
        }
    ],
    "sg:phone":"+39 0331 305047",
    "sg:postcode":"20020",
    "sg:province":"Milano",
    "sg:tags":[
        "publishing"
    ],
    "wof:name":"Lualdi Mario (s.p.a.)",
    "wof:placetype":"venue"
},
  "geometry": {"coordinates":[8.793888092,45.5959320068],"type":"Point"}
}