{
  "type": "Feature",
  "properties": {
    "iso:country":"IT",
    "sg:address":"22030 Barni",
    "sg:city":"Barni",
    "sg:orig_category":"Bevande, Vini E Liquori",
    "sg:phone":"+39 031 965174",
    "sg:postcode":"22030",
    "sg:province":"Como",
    "wof:name":"Fonti Di Barni (s.r.l.)",
    "wof:placetype":"venue"
},
  "geometry": {"coordinates":[9.266264,45.912361],"type":"Point"}
}