{
  "type": "Feature",
  "properties": {
    "iso:country":"IT",
    "sg:address":"07020 Cannigione",
    "sg:classifiers":[
        {
            "category":"Professional",
            "subcategory":"Employment Agencies",
            "type":"Services"
        }
    ],
    "sg:phone":"+39 0789 86003",
    "sg:postcode":"07020",
    "sg:province":"Olbia-Tempio",
    "sg:tags":[
        "services",
        "school",
        "sport",
        "educational",
        "leisure"
    ],
    "sg:website":"http://www.isuledda.it",
    "wof:name":"Villaggio Turistico Camping Isuledda",
    "wof:placetype":"venue"
},
  "geometry": {"coordinates":[9.43919,41.123909],"type":"Point"}
}