{
  "type": "Feature",
  "properties": {
    "iso:country":"IT",
    "sg:address":"64010 Torricella Sicura",
    "sg:city":"Torricella Sicura",
    "sg:orig_category":"Vetrate Isolanti",
    "sg:phone":"+39 0861 554821",
    "sg:postcode":"64010",
    "sg:province":"Teramo",
    "wof:name":"Btt Srl",
    "wof:placetype":"venue"
},
  "geometry": {"coordinates":[13.649884,42.648624],"type":"Point"}
}