{
  "type": "Feature",
  "properties": {
    "iso:country":"IT",
    "sg:address":"41019 Soliera",
    "sg:city":"Soliera",
    "sg:orig_category":"Prodotti Alimentari",
    "sg:phone":"+39 059 567359",
    "sg:postcode":"41019",
    "sg:province":"Modena",
    "wof:name":"Malagoli Davide",
    "wof:placetype":"venue"
},
  "geometry": {"coordinates":[10.9294528961,44.7351646423],"type":"Point"}
}