{
  "type": "Feature",
  "properties": {
    "iso:country":"IT",
    "sg:address":"6, Via Bartlm\u00e4 Von Guggenberg 39030 Vandoies",
    "sg:city":"Vandoies",
    "sg:classifiers":[
        {
            "category":"Food & Beverages",
            "subcategory":"Bakery",
            "type":"Retail Goods"
        }
    ],
    "sg:phone":"+39 0472 867900",
    "sg:postcode":"39030",
    "sg:province":"Bolzano/Bozen",
    "sg:tags":[
        "grain",
        "cereal"
    ],
    "wof:name":"Rieper A. S.p.a.",
    "wof:placetype":"venue"
},
  "geometry": {"coordinates":[11.719586,46.815971],"type":"Point"}
}