{
  "type": "Feature",
  "properties": {
    "iso:country":"IT",
    "sg:address":"Via Pasquale Vena 75015 Pisticci",
    "sg:city":"Pisticci",
    "sg:classifiers":[
        {
            "category":"Food & Beverages",
            "subcategory":"Liquor & Beverages",
            "type":"Retail Goods"
        }
    ],
    "sg:phone":"+39 0835 4691",
    "sg:postcode":"75015",
    "sg:province":"Matera",
    "sg:tags":[
        "liqueur"
    ],
    "sg:website":"www.amarolucano.it",
    "wof:name":"Cav. Pasquale Vena & Figli Amaro Lu Cano Spa",
    "wof:placetype":"venue"
},
  "geometry": {"coordinates":[16.547556,40.417908],"type":"Point"}
}