{
  "type": "Feature",
  "properties": {
    "iso:country":"IT",
    "sg:address":"20010 Bareggio",
    "sg:city":"Bareggio",
    "sg:orig_category":"Apparecchiature Ed Attrezzature Meccaniche",
    "sg:phone":"+39 02 9036 0500",
    "sg:postcode":"20010",
    "sg:province":"Milano",
    "wof:name":"Idrogas Di Pancotti Edmondo E C. S.a.s.",
    "wof:placetype":"venue"
},
  "geometry": {"coordinates":[9.058317,45.486641],"type":"Point"}
}