{
  "type": "Feature",
  "properties": {
    "iso:country":"IT",
    "sg:address":"46019 Viadana",
    "sg:city":"Viadana",
    "sg:orig_category":"Servizi E Lavori Per Agricoltura E Zootecnia",
    "sg:phone":"+39 0375 85138",
    "sg:postcode":"46019",
    "sg:province":"Mantova",
    "wof:name":"Bologni Angiolino",
    "wof:placetype":"venue"
},
  "geometry": {"coordinates":[10.562857,44.968651],"type":"Point"}
}