{
  "type": "Feature",
  "properties": {
    "addr:full":"31, Viale Prealpi 22036 Erba Erba Como 22036",
    "addr:housenumber":"31",
    "addr:postcode":"22036;22036",
    "addr:street":"Viale Prealpi",
    "iso:country":"IT",
    "sg:address":"31, Viale Prealpi 22036 Erba",
    "sg:city":"Erba",
    "sg:classifiers":[
        {
            "category":"Shopping",
            "subcategory":"Computers & Home Electronics",
            "type":"Retail Goods"
        }
    ],
    "sg:phone":"+39 39031614111",
    "sg:postcode":"22036",
    "sg:province":"Como",
    "sg:tags":[
        "electronic",
        "electrical",
        "equipment"
    ],
    "wof:name":"Elettromeccanica Galli Italo S.p.a.",
    "wof:placetype":"venue"
},
  "geometry": {"coordinates":[9.226079,45.803806],"type":"Point"}
}