{
  "type": "Feature",
  "properties": {
    "addr:full":"Via Verga 12 20088 Rosate Rosate Milano 20088",
    "addr:housenumber":"12",
    "addr:postcode":"20088;20088",
    "addr:street":"Via Verga",
    "iso:country":"IT",
    "sg:address":"Via Verga 12 20088 Rosate",
    "sg:city":"Rosate",
    "sg:classifiers":[
        {
            "category":"Home & Garden",
            "subcategory":"Hardware",
            "type":"Retail Goods"
        }
    ],
    "sg:phone":"+39 02 9084 9026",
    "sg:postcode":"20088",
    "sg:province":"Milano",
    "sg:tags":[
        "small",
        "ironware",
        "item"
    ],
    "sg:website":"www.omasrosati.it",
    "wof:name":"Omas S.r.l.",
    "wof:placetype":"venue"
},
  "geometry": {"coordinates":[9.188141,45.463688],"type":"Point"}
}