{
  "type": "Feature",
  "properties": {
    "iso:country":"IT",
    "sg:address":"20068 Peschiera Borromeo",
    "sg:city":"Peschiera Borromeo",
    "sg:orig_category":"Metalli E Leghe. Gioielleria, Oreficeria E Argenteria",
    "sg:phone":"+39 02 547 0512",
    "sg:postcode":"20068",
    "sg:province":"Milano",
    "wof:name":"C.m.p. S.r.l.",
    "wof:placetype":"venue"
},
  "geometry": {"coordinates":[9.2683038712,45.4128494263],"type":"Point"}
}