{
  "type": "Feature",
  "properties": {
    "iso:country":"IT",
    "sg:address":"20132 Milano",
    "sg:city":"Milano",
    "sg:orig_category":"Servizi E Lavori Per Ecologia E Smaltimento Rifiuti. Forniture Industriali Per Prevenzione, Controllo E Sicurezza",
    "sg:phone":"+39 02 2720 7063",
    "sg:postcode":"20132",
    "sg:province":"Milano",
    "sg:website":"http://www.hermesitalia.it",
    "wof:name":"Hermes Italia Srl",
    "wof:placetype":"venue"
},
  "geometry": {"coordinates":[9.245543,45.50383],"type":"Point"}
}