{
  "type": "Feature",
  "properties": {
    "addr:full":"9, Via Delle Arnasche 20023 Cerro Maggiore Cerro Maggiore Milano 20023",
    "addr:postcode":"20023;20023",
    "addr:street":"Via Delle Arnasche",
    "iso:country":"IT",
    "sg:address":"9, Via Delle Arnasche 20023 Cerro Maggiore",
    "sg:city":"Cerro Maggiore",
    "sg:classifiers":[
        {
            "category":"Professional",
            "subcategory":"Business Services",
            "type":"Services"
        }
    ],
    "sg:phone":"+39 0331 514977",
    "sg:postcode":"20023",
    "sg:province":"Milano",
    "sg:tags":[
        "advice"
    ],
    "wof:name":"Audis S.r.l.",
    "wof:placetype":"venue"
},
  "geometry": {"coordinates":[8.953925,45.586464],"type":"Point"}
}