{
  "type": "Feature",
  "properties": {
    "addr:full":"16031 Bogliasco Bogliasco Genova 16031",
    "addr:housenumber":"16031",
    "addr:postcode":"16031",
    "addr:street":"Bogliasco Bogliasco Genova",
    "iso:country":"IT",
    "sg:address":"16031 Bogliasco",
    "sg:city":"Bogliasco",
    "sg:orig_category":"Forniture E Prodotti Informatici. Forniture Per Uffici",
    "sg:phone":"+39 010 347 0190",
    "sg:postcode":"16031",
    "sg:province":"Genova",
    "sg:website":"http://www.lucesa.com",
    "wof:name":"Cartotecnica Lucesa Srl",
    "wof:placetype":"venue"
},
  "geometry": {"coordinates":[9.0708780289,44.377784729],"type":"Point"}
}