{
  "type": "Feature",
  "properties": {
    "addr:full":"20066 Melzo Melzo Milano 20066",
    "addr:postcode":"20066;20066",
    "iso:country":"IT",
    "sg:address":"20066 Melzo",
    "sg:city":"Melzo",
    "sg:classifiers":[
        {
            "category":"Organizations",
            "subcategory":"Community Association",
            "type":"Services"
        }
    ],
    "sg:phone":"+39 02 9573 9700",
    "sg:postcode":"20066",
    "sg:province":"Milano",
    "sg:tags":[
        "handling",
        "storage",
        "system",
        "packaging",
        "equipment",
        "packing",
        "systems"
    ],
    "sg:website":"http://www.comunilombardia.com/idramel.html",
    "wof:name":"Gestione Manutenzione Containers Srl",
    "wof:placetype":"venue"
},
  "geometry": {"coordinates":[9.4233474731,45.5006065369],"type":"Point"}
}