{
  "type": "Feature",
  "properties": {
    "iso:country":"IT",
    "sg:address":"Via Dell' Industria 7 37040 Veronella",
    "sg:city":"Veronella",
    "sg:classifiers":[
        {
            "category":"Manufacturing",
            "subcategory":"Tools & Machinery",
            "type":"Manufacturing & Wholesale Goods"
        }
    ],
    "sg:phone":"+39 0442 47555",
    "sg:postcode":"37040",
    "sg:province":"Verona",
    "sg:tags":[
        "machine"
    ],
    "sg:website":"www.robbimac.com",
    "wof:name":"Robbi Spa Di Robbi Roberto & C.",
    "wof:placetype":"venue"
},
  "geometry": {"coordinates":[11.336726,45.335155],"type":"Point"}
}