{
  "type": "Feature",
  "properties": {
    "iso:country":"IT",
    "sg:address":"25125 Brescia",
    "sg:city":"Brescia",
    "sg:orig_category":"Consulenza Commerciale E Finanziaria",
    "sg:phone":"+39 030 221134",
    "sg:postcode":"25125",
    "sg:province":"Brescia",
    "wof:name":"Fidimpresa Soc.coop.r.l.",
    "wof:placetype":"venue"
},
  "geometry": {"coordinates":[10.185771,45.520386],"type":"Point"}
}