{
  "type": "Feature",
  "properties": {
    "iso:country":"IT",
    "sg:address":"35135 Padova",
    "sg:city":"Padova",
    "sg:orig_category":"Petroli, Gas E Combustibili",
    "sg:phone":"+39 049 864 5101",
    "sg:postcode":"35135",
    "sg:province":"Padova",
    "wof:name":"Morganite Italiana S.r.l.",
    "wof:placetype":"venue"
},
  "geometry": {"coordinates":[11.8691091537,45.444568634],"type":"Point"}
}