{
  "type": "Feature",
  "properties": {
    "iso:country":"IT",
    "sg:address":"20089 Rozzano",
    "sg:city":"Rozzano",
    "sg:classifiers":[
        {
            "category":"Banks & Credit Unions",
            "subcategory":"Investment Brokerage",
            "type":"Services"
        }
    ],
    "sg:phone":"+39 02 825 0468",
    "sg:postcode":"20089",
    "sg:province":"Milano",
    "sg:tags":[
        "parrucchieri",
        "per",
        "donna"
    ],
    "wof:name":"Majori Snc",
    "wof:placetype":"venue"
},
  "geometry": {"coordinates":[9.1543903351,45.381477356],"type":"Point"}
}