{
  "type": "Feature",
  "properties": {
    "iso:country":"IT",
    "sg:address":"26837 Mulazzano",
    "sg:city":"Mulazzano",
    "sg:classifiers":[
        {
            "category":"Health Services",
            "subcategory":"Health Practitioner",
            "type":"Services"
        }
    ],
    "sg:phone":"+39 02 9885 0090",
    "sg:postcode":"26837",
    "sg:province":"Lodi",
    "sg:tags":[
        "medici"
    ],
    "wof:name":"Centro Prevenzione Donna",
    "wof:placetype":"venue"
},
  "geometry": {"coordinates":[9.403203,45.369366],"type":"Point"}
}