{
  "type": "Feature",
  "properties": {
    "iso:country":"IT",
    "sg:address":"40139 Bologna",
    "sg:city":"Bologna",
    "sg:orig_category":"Tessuti Arredamento, Tende E Tappeti",
    "sg:phone":"+39 051 548762",
    "sg:postcode":"40139",
    "sg:province":"Bologna",
    "wof:name":"Flexatende Di Morsetti Graziella",
    "wof:placetype":"venue"
},
  "geometry": {"coordinates":[11.381944,44.478165],"type":"Point"}
}