{
  "type": "Feature",
  "properties": {
    "iso:country":"IT",
    "sg:address":"56, V. Arturo Graf00141 Roma",
    "sg:city":"Roma",
    "sg:classifiers":[
        {
            "category":"Wholesale",
            "subcategory":"Medical Equipment & Supplies",
            "type":"Manufacturing & Wholesale Goods"
        }
    ],
    "sg:phone":"+39 06 8680 2202",
    "sg:postcode":"00141",
    "sg:province":"Roma",
    "sg:tags":[
        "-",
        "health",
        "instrument"
    ],
    "sg:website":"http://www.sofarco.com",
    "wof:name":"Salvaven",
    "wof:placetype":"venue"
},
  "geometry": {"coordinates":[12.552722,41.943207],"type":"Point"}
}