{
  "type": "Feature",
  "properties": {
    "iso:country":"IT",
    "sg:address":"24050 Grassobbio",
    "sg:city":"Grassobbio",
    "sg:orig_category":"Termotecnica E Riscaldamento, Apparecchiature E Servizi. Prodotti Vari In Metallo",
    "sg:phone":"+39 035 525069",
    "sg:postcode":"24050",
    "sg:province":"Bergamo",
    "wof:name":"Carival Srl",
    "wof:placetype":"venue"
},
  "geometry": {"coordinates":[9.659751,45.625496],"type":"Point"}
}