{
  "type": "Feature",
  "properties": {
    "iso:country":"IT",
    "sg:address":"Via Del Sesto 55016 Porcari",
    "sg:city":"Porcari",
    "sg:classifiers":[
        {
            "category":"Wholesale",
            "subcategory":"Machinery & Supplies",
            "type":"Manufacturing & Wholesale Goods"
        }
    ],
    "sg:phone":"+39 0583 211070",
    "sg:postcode":"55016",
    "sg:province":"Lucca",
    "sg:tags":[
        "-",
        "agriculture",
        "equipment"
    ],
    "wof:name":"Cooperativa L'unitaria",
    "wof:placetype":"venue"
},
  "geometry": {"coordinates":[10.629207,43.823471],"type":"Point"}
}