{
  "type": "Feature",
  "properties": {
    "iso:country":"IT",
    "sg:address":"61, Via Cavour Camillo Benso 20026 Novate Milanese",
    "sg:city":"Novate Milanese",
    "sg:classifiers":[
        {
            "category":"Communications",
            "subcategory":"Newspaper",
            "type":"Services"
        }
    ],
    "sg:phone":"+39 39023548518",
    "sg:postcode":"20026",
    "sg:province":"Milano",
    "sg:tags":[
        "advertising"
    ],
    "wof:name":"Studio Baldus (s.r.l.)",
    "wof:placetype":"venue"
},
  "geometry": {"coordinates":[9.115809,45.542862],"type":"Point"}
}