{
  "type": "Feature",
  "properties": {
    "addr:full":"15, Via Indipendenza 10095 Grugliasco Grugliasco Torino 10095",
    "addr:postcode":"10095;10095",
    "addr:street":"Via Indipendenza",
    "iso:country":"IT",
    "sg:address":"15, Via Indipendenza 10095 Grugliasco",
    "sg:city":"Grugliasco",
    "sg:classifiers":[
        {
            "category":"Shopping",
            "type":"Retail Goods"
        }
    ],
    "sg:phone":"+39 39011784343",
    "sg:postcode":"10095",
    "sg:province":"Torino",
    "sg:tags":[
        "finished",
        "-",
        "metallic"
    ],
    "wof:name":"Simat Abrasivi S.p.a.",
    "wof:placetype":"venue"
},
  "geometry": {"coordinates":[7.5973329544,45.0502243042],"type":"Point"}
}