{
  "type": "Feature",
  "properties": {
    "iso:country":"IT",
    "sg:address":"6, Via Campanini Alfredo 20124 Milano",
    "sg:city":"Milano",
    "sg:classifiers":[
        {
            "category":"Wholesale",
            "subcategory":"Drugs",
            "type":"Manufacturing & Wholesale Goods"
        }
    ],
    "sg:phone":"+39 390 267 1951",
    "sg:postcode":"20124",
    "sg:province":"Milano",
    "sg:tags":[
        "chemical",
        "pharmaceutical"
    ],
    "wof:name":"Totalfina Italia Spa",
    "wof:placetype":"venue"
},
  "geometry": {"coordinates":[9.1984500885,45.4864807129],"type":"Point"}
}