{
  "type": "Feature",
  "properties": {
    "addr:full":"Via San Cristoforo 78 20090 Trezzano Sul Naviglio Trezzano sul Naviglio Milano 20090",
    "addr:housenumber":"78",
    "addr:postcode":"20090;20090",
    "addr:street":"Via San Cristoforo",
    "iso:country":"IT",
    "sg:address":"Via San Cristoforo 78 20090 Trezzano Sul Naviglio",
    "sg:city":"Trezzano sul Naviglio",
    "sg:classifiers":[
        {
            "category":"Manufacturing",
            "subcategory":"Rubber & Plastics",
            "type":"Manufacturing & Wholesale Goods"
        }
    ],
    "sg:phone":"+39 02 4840 1749",
    "sg:postcode":"20090",
    "sg:province":"Milano",
    "sg:tags":[
        "rigid",
        "sheet"
    ],
    "sg:website":"www.mohwinckel.it",
    "wof:name":"Mohwinckel Spa",
    "wof:placetype":"venue"
},
  "geometry": {"coordinates":[9.0788354874,45.4175109863],"type":"Point"}
}