{
  "type": "Feature",
  "properties": {
    "iso:country":"IT",
    "sg:address":"20129 Milano",
    "sg:city":"Milano",
    "sg:orig_category":"Studi E Consulenze Amministrative, Commerciali E Aziendali. Consulenze Tecniche, Amministrative E Perizie",
    "sg:phone":"+39 0277161",
    "sg:postcode":"20129",
    "sg:province":"Milano",
    "sg:website":"http://www.haygroup.com",
    "wof:name":"Hay Management Consultants Srl",
    "wof:placetype":"venue"
},
  "geometry": {"coordinates":[9.205812,45.469368],"type":"Point"}
}