{
  "type": "Feature",
  "properties": {
    "addr:full":"20147 Milano Milano Milano 20147",
    "addr:postcode":"20147;20147",
    "iso:country":"IT",
    "sg:address":"20147 Milano",
    "sg:city":"Milano",
    "sg:orig_category":"Professionisti - Studi E Servizi Ed Associazioni Di Interesse Aziendale. Associazioni Ed Organismi Di Interesse Pubblico. Chiese Ed Associazioni Religiose",
    "sg:phone":"+39 02 4870 5429",
    "sg:postcode":"20147",
    "sg:province":"Milano",
    "wof:name":"Fondazione Vita Nova-progetto Gemma",
    "wof:placetype":"venue"
},
  "geometry": {"coordinates":[9.1257658005,45.4560241699],"type":"Point"}
}