{
  "type": "Feature",
  "properties": {
    "addr:full":"Via Campo Romano 24050 Spirano Spirano Bergamo 24050",
    "addr:postcode":"24050;24050",
    "addr:street":"Via Campo Romano",
    "iso:country":"IT",
    "sg:address":"Via Campo Romano 24050 Spirano",
    "sg:city":"Spirano",
    "sg:classifiers":[
        {
            "category":"Farming",
            "subcategory":"Livestock Farm",
            "type":"Manufacturing & Wholesale Goods"
        }
    ],
    "sg:phone":"+39 39035876597",
    "sg:postcode":"24050",
    "sg:province":"Bergamo",
    "sg:tags":[
        "agriculture"
    ],
    "wof:name":"Cascina Italia (s.p.a.)",
    "wof:placetype":"venue"
},
  "geometry": {"coordinates":[9.662219,45.595497],"type":"Point"}
}