{
  "type": "Feature",
  "properties": {
    "iso:country":"IT",
    "sg:address":"18, Via Lombardia 40024 Castel San Pietro Terme",
    "sg:city":"Castel San Pietro Terme",
    "sg:classifiers":[
        {
            "category":"Shopping",
            "subcategory":"Stationery & Office Supplies",
            "type":"Retail Goods"
        }
    ],
    "sg:phone":"+39 051 695 8430",
    "sg:postcode":"40024",
    "sg:province":"Bologna",
    "sg:tags":[
        "professional"
    ],
    "wof:name":"L.f. International",
    "wof:placetype":"venue"
},
  "geometry": {"coordinates":[11.5259866714,44.4288673401],"type":"Point"}
}