{
  "type": "Feature",
  "properties": {
    "addr:full":"Via Trinita 65; Sala Consilina",
    "addr:housenumber":"65 sala",
    "addr:street":"Via Trinita",
    "iso:country":"IT",
    "sg:address":"Via Trinita 65; Sala Consilina",
    "sg:classifiers":[
        {
            "category":"Banks & Credit Unions",
            "subcategory":"Bank",
            "type":"Services"
        }
    ],
    "sg:phone":"+39 0975 45560",
    "wof:name":"Banca Di Roma",
    "wof:placetype":"venue"
},
  "geometry": {"coordinates":[15.6111,40.371559],"type":"Point"}
}