{
  "type": "Feature",
  "properties": {
    "addr:full":"73100 Lecce Lecce Lecce 73100",
    "addr:postcode":"73100;73100",
    "iso:country":"IT",
    "sg:address":"73100 Lecce",
    "sg:city":"Lecce",
    "sg:orig_category":"Articoli Per Imballaggio E Confezionamento",
    "sg:phone":"+39 0832 352341",
    "sg:postcode":"73100",
    "sg:province":"Lecce",
    "wof:name":"Scorrano Rag. Antonio",
    "wof:placetype":"venue"
},
  "geometry": {"coordinates":[18.162109,40.339153],"type":"Point"}
}