{
  "type": "Feature",
  "properties": {
    "addr:full":"00158 Roma Roma Roma 00158",
    "addr:postcode":"00158;00158",
    "iso:country":"IT",
    "sg:address":"00158 Roma",
    "sg:city":"Roma",
    "sg:orig_category":"Macchine, Impianti Ed Attrezzature Industria Chimica. Attrezzature E Forniture Per Officine Riparazione E Servizi Ausiliari",
    "sg:postcode":"00158",
    "sg:province":"Roma",
    "wof:name":"Unitek Srl",
    "wof:placetype":"venue"
},
  "geometry": {"coordinates":[12.544326,41.923508],"type":"Point"}
}