{
  "type": "Feature",
  "properties": {
    "addr:full":"Via L. Da Vinci 4/8 30020 Cinto Caomaggiore Cinto Caomaggiore Venezia 30020",
    "addr:housenumber":"4 / 8",
    "addr:postcode":"30020;30020",
    "addr:street":"Via L. Da Vinci",
    "iso:country":"IT",
    "sg:address":"Via L. Da Vinci 4/8 30020 Cinto Caomaggiore",
    "sg:city":"Cinto Caomaggiore",
    "sg:classifiers":[
        {
            "category":"Utilities",
            "subcategory":"Electric",
            "type":"Services"
        }
    ],
    "sg:phone":"+39 0421 241243",
    "sg:postcode":"30020",
    "sg:province":"Venezia",
    "sg:tags":[
        "sheet-metal",
        "precision",
        "working"
    ],
    "wof:name":"Rubert Dino E C. S.n.c.",
    "wof:placetype":"venue"
},
  "geometry": {"coordinates":[12.7753925323,45.8307151794],"type":"Point"}
}