{
  "type": "Feature",
  "properties": {
    "iso:country":"IT",
    "sg:address":"Viale Leonardo Da Vinci 185; Roma; 00145",
    "sg:city":"Roma",
    "sg:classifiers":[
        {
            "category":"Banks & Credit Unions",
            "subcategory":"Bank",
            "type":"Services"
        }
    ],
    "sg:phone":"+39 06 540 0386",
    "sg:postcode":"00145",
    "sg:province":"Roma",
    "wof:name":"Credito Artigiano",
    "wof:placetype":"venue"
},
  "geometry": {"coordinates":[12.480509,41.854099],"type":"Point"}
}