{
  "type": "Feature",
  "properties": {
    "addr:full":"15/a, Corso Sempione 20145 Milano Milano Milano 20145",
    "addr:housenumber":"15 / a",
    "addr:postcode":"20145;20145",
    "addr:street":"Corso Sempione",
    "iso:country":"IT",
    "sg:address":"15/a, Corso Sempione 20145 Milano",
    "sg:city":"Milano",
    "sg:classifiers":[
        {
            "category":"Professional",
            "subcategory":"Engineering",
            "type":"Services"
        }
    ],
    "sg:phone":"+39 390 233 1221",
    "sg:postcode":"20145",
    "sg:province":"Milano",
    "sg:tags":[
        "machine",
        "-",
        "mechanical"
    ],
    "wof:name":"Dott. Bonapace & C. Srl",
    "wof:placetype":"venue"
},
  "geometry": {"coordinates":[9.169501,45.477821],"type":"Point"}
}