{
  "type": "Feature",
  "properties": {
    "iso:country":"IT",
    "sg:address":"36034 Malo",
    "sg:city":"Malo",
    "sg:orig_category":"Macchine, Impianti E Forniture Per Industria Grafica, Cartaria E Cartotecnica",
    "sg:phone":"+39 0445 606519",
    "sg:postcode":"36034",
    "sg:province":"Vicenza",
    "wof:name":"Berica Engineering Srl",
    "wof:placetype":"venue"
},
  "geometry": {"coordinates":[11.392198,45.666569],"type":"Point"}
}