{
  "type": "Feature",
  "properties": {
    "iso:country":"IT",
    "sg:address":"16016 Cogoleto",
    "sg:city":"Cogoleto",
    "sg:classifiers":[
        {
            "category":"Shopping",
            "subcategory":"Bicycles & Sporting Goods",
            "type":"Retail Goods"
        }
    ],
    "sg:phone":"+39 010 918 2891",
    "sg:postcode":"16016",
    "sg:province":"Genova",
    "sg:tags":[
        "tempo",
        "lo",
        "-",
        "libero",
        "per",
        "servizi",
        "forniture",
        "articoli",
        "e",
        "sport",
        "il"
    ],
    "wof:name":"Vanni Orlando Pesca Sport Orlando",
    "wof:placetype":"venue"
},
  "geometry": {"coordinates":[8.685621,44.404625],"type":"Point"}
}