{
  "type": "Feature",
  "properties": {
    "iso:country":"IT",
    "sg:address":"22060 Cabiate",
    "sg:city":"Cabiate",
    "sg:orig_category":"Scatole - Produzione E Commercio",
    "sg:phone":"+39 031 767721",
    "sg:postcode":"22060",
    "sg:province":"Como",
    "wof:name":"Scatolificio C4 Srl",
    "wof:placetype":"venue"
},
  "geometry": {"coordinates":[9.060228,45.81813],"type":"Point"}
}