{
  "type": "Feature",
  "properties": {
    "iso:country":"IT",
    "sg:address":"Via Cilea 33 59100 Prato",
    "sg:city":"Prato",
    "sg:classifiers":[
        {
            "category":"Shopping",
            "subcategory":"Crafts & Fabrics",
            "type":"Retail Goods"
        }
    ],
    "sg:phone":"+39 0574 22127",
    "sg:postcode":"59100",
    "sg:province":"Prato",
    "sg:tags":[
        "high-fashion"
    ],
    "wof:name":"L'agenzia Italiana Import-export Di Gabuzzini Luca & C. Sas",
    "wof:placetype":"venue"
},
  "geometry": {"coordinates":[11.074087,43.884861],"type":"Point"}
}