{
  "type": "Feature",
  "properties": {
    "addr:full":"38, Via Cristo 35028 Piove Di Sacco Piove di Sacco Padova 35028",
    "addr:postcode":"35028;35028",
    "addr:street":"Via Cristo",
    "iso:country":"IT",
    "sg:address":"38, Via Cristo 35028 Piove Di Sacco",
    "sg:city":"Piove di Sacco",
    "sg:classifiers":[
        {
            "category":"Manufacturing",
            "subcategory":"Rubber & Plastics",
            "type":"Manufacturing & Wholesale Goods"
        }
    ],
    "sg:phone":"+39 049 970 0463",
    "sg:postcode":"35028",
    "sg:province":"Padova",
    "wof:name":"Clima-bend S.n.c. Di Ferrara Cristiano & C.",
    "wof:placetype":"venue"
},
  "geometry": {"coordinates":[12.0215349197,45.2770614624],"type":"Point"}
}