{
  "type": "Feature",
  "properties": {
    "iso:country":"IT",
    "sg:address":"05018 Orvieto",
    "sg:city":"Orvieto",
    "sg:orig_category":"Birra - Produzione E Commercio",
    "sg:phone":"+39 0763 316224",
    "sg:postcode":"05018",
    "sg:province":"Terni",
    "wof:name":"Gruppo Italiano Vini Soc.coop.r.l.",
    "wof:placetype":"venue"
},
  "geometry": {"coordinates":[12.064555,42.759537],"type":"Point"}
}