{
  "type": "Feature",
  "properties": {
    "iso:country":"IT",
    "sg:address":"91022 Castelvetrano",
    "sg:city":"Castelvetrano",
    "sg:orig_category":"Arredamenti E Mobili Professionali. Forniture Alle Strutture Ricettive. Arredi Ed Attrezzature Per Attivita' Commerciali Ed Artigianali",
    "sg:phone":"+39 0924 902351",
    "sg:postcode":"91022",
    "sg:province":"Trapani",
    "wof:name":"Gmc Di Mario Gucciardo & C. Snc",
    "wof:placetype":"venue"
},
  "geometry": {"coordinates":[12.810007,37.673267],"type":"Point"}
}