{
  "type": "Feature",
  "properties": {
    "addr:full":"16, Via Milano 20060 Liscate Liscate Milano 20060",
    "addr:postcode":"20060;20060",
    "addr:street":"Via Milano",
    "iso:country":"IT",
    "sg:address":"16, Via Milano 20060 Liscate",
    "sg:city":"Liscate",
    "sg:classifiers":[
        {
            "category":"Manufacturing",
            "subcategory":"Glass & Minerals",
            "type":"Manufacturing & Wholesale Goods"
        }
    ],
    "sg:phone":"+39 02 9535 0356",
    "sg:postcode":"20060",
    "sg:province":"Milano",
    "wof:name":"Global Glass S.r.l.",
    "wof:placetype":"venue"
},
  "geometry": {"coordinates":[9.393945,45.486294],"type":"Point"}
}