{
  "type": "Feature",
  "properties": {
    "iso:country":"IT",
    "sg:address":"04019 Terracina",
    "sg:city":"Terracina",
    "sg:classifiers":[
        {
            "category":"Autos & Motor Vehicles",
            "subcategory":"Fuel & Gas Station",
            "type":"Retail Goods"
        }
    ],
    "sg:phone":"+39 0773 704751",
    "sg:postcode":"04019",
    "sg:province":"Latina",
    "sg:tags":[
        "car",
        "camping"
    ],
    "wof:name":"M. Auto Di Mirabelli Rita & C. Snc",
    "wof:placetype":"venue"
},
  "geometry": {"coordinates":[13.243098,41.29356],"type":"Point"}
}