{
  "type": "Feature",
  "properties": {
    "addr:full":"24040 Misano Di Gera D'adda Bergamo 24040",
    "addr:postcode":"24040;24040",
    "iso:country":"IT",
    "sg:address":"24040 Misano Di Gera D'adda",
    "sg:orig_category":"Abbigliamento In Pelle - Produzione E Ingrosso",
    "sg:phone":"+39 036 384 8412",
    "sg:postcode":"24040",
    "sg:province":"Bergamo",
    "wof:name":"De.ma. Srl",
    "wof:placetype":"venue"
},
  "geometry": {"coordinates":[9.623007,45.466438],"type":"Point"}
}