{
  "type": "Feature",
  "properties": {
    "iso:country":"IT",
    "sg:address":"Sda Gabannone 8 15030 Terruggia",
    "sg:city":"Terruggia",
    "sg:classifiers":[
        {
            "category":"Structure",
            "subcategory":"Office Building",
            "type":"Public Place"
        }
    ],
    "sg:phone":"+39 0142 403223",
    "sg:postcode":"15030",
    "sg:province":"Alessandria",
    "sg:tags":[
        "door",
        "automatic",
        "actuator"
    ],
    "sg:website":"www.sesamo.org",
    "wof:name":"Sesamo Srl",
    "wof:placetype":"venue"
},
  "geometry": {"coordinates":[8.458582,45.060722],"type":"Point"}
}