{
  "type": "Feature",
  "properties": {
    "addr:full":"Contrada Campomaggio 62032 Morrovalle Morro Macerata 62032",
    "addr:postcode":"62032;62032",
    "addr:street":"Contrada Campomaggio",
    "iso:country":"IT",
    "sg:address":"Contrada Campomaggio 62032 Morrovalle",
    "sg:city":"Morro",
    "sg:classifiers":[
        {
            "category":"Personal",
            "subcategory":"Shoe Repair & Shine",
            "type":"Services"
        }
    ],
    "sg:phone":"+39 390 733 8671",
    "sg:postcode":"62032",
    "sg:province":"Macerata",
    "sg:tags":[
        "leather"
    ],
    "wof:name":"Finproject S.p.a.",
    "wof:placetype":"venue"
},
  "geometry": {"coordinates":[13.575701,43.275723],"type":"Point"}
}