{
  "type": "Feature",
  "properties": {
    "iso:country":"IT",
    "sg:address":"36033 Isola Vicentina",
    "sg:city":"Isola Vicentina",
    "sg:orig_category":"Materiali Edili",
    "sg:phone":"+39 0444 976780",
    "sg:postcode":"36033",
    "sg:province":"Vicenza",
    "wof:name":"Gruppo Stabila Stabilimenti Italiani Laterizi S.p.a.",
    "wof:placetype":"venue"
},
  "geometry": {"coordinates":[11.467641,45.634182],"type":"Point"}
}