{
  "type": "Feature",
  "properties": {
    "iso:country":"IT",
    "sg:address":"56125 Pisa",
    "sg:city":"Pisa",
    "sg:orig_category":"Universita' Ed Istituti Superiori E Liberi",
    "sg:phone":"+39 050 21111",
    "sg:postcode":"56125",
    "sg:province":"Pisa",
    "wof:name":"Cepu Srl",
    "wof:placetype":"venue"
},
  "geometry": {"coordinates":[10.401732,43.71069],"type":"Point"}
}