{
  "type": "Feature",
  "properties": {
    "addr:full":"84, Via G. Marconi 42023 Cadelbosco Di Sopra Reggio Nell'Emilia 42023",
    "addr:postcode":"42023;42023",
    "addr:street":"Via G. Marconi",
    "iso:country":"IT",
    "sg:address":"84, Via G. Marconi 42023 Cadelbosco Di Sopra",
    "sg:classifiers":[
        {
            "category":"Wholesale",
            "subcategory":"Machinery & Supplies",
            "type":"Manufacturing & Wholesale Goods"
        }
    ],
    "sg:phone":"+39 0522 911052",
    "sg:postcode":"42023",
    "sg:province":"Reggio Nell'Emilia",
    "sg:tags":[
        "-",
        "agriculture",
        "equipment"
    ],
    "wof:name":"O.m.a.i. (s.r.l.)",
    "wof:placetype":"venue"
},
  "geometry": {"coordinates":[10.612203,44.794445],"type":"Point"}
}