{
  "type": "Feature",
  "properties": {
    "addr:full":"00145 Roma Roma Roma 00145",
    "addr:postcode":"00145;00145",
    "iso:country":"IT",
    "sg:address":"00145 Roma",
    "sg:city":"Roma",
    "sg:orig_category":"Prodotti Chimici Di Base. Forniture Per Attivita' Industriali",
    "sg:phone":"+39 06 541 2951",
    "sg:postcode":"00145",
    "sg:province":"Roma",
    "wof:name":"Sace (s.r.l.)",
    "wof:placetype":"venue"
},
  "geometry": {"coordinates":[12.4860076904,41.8514328003],"type":"Point"}
}