{
  "type": "Feature",
  "properties": {
    "iso:country":"IT",
    "sg:address":"6, Via Pietro Porro 22031 Albavilla",
    "sg:city":"Albavilla",
    "sg:classifiers":[
        {
            "category":"Shopping",
            "subcategory":"Clothing, Apparel, & Fashions",
            "type":"Retail Goods"
        }
    ],
    "sg:phone":"+39 39031628961",
    "sg:postcode":"22031",
    "sg:province":"Como",
    "sg:tags":[
        "clothing",
        "accessory"
    ],
    "wof:name":"Creazioni Cravatte (s.n.c.)",
    "wof:placetype":"venue"
},
  "geometry": {"coordinates":[9.085456,45.811966],"type":"Point"}
}