{
  "type": "Feature",
  "properties": {
    "iso:country":"IT",
    "sg:address":"96100 Siracusa",
    "sg:city":"Siracusa",
    "sg:orig_category":"Servizi Per Lo Sport E Il Tempo Libero. Alberghi E Strutture Extra Alberghiere",
    "sg:phone":"+39 0931 790345",
    "sg:postcode":"96100",
    "sg:province":"Siracusa",
    "wof:name":"Lido Sayonara Di Ierna Aldo & C. Snc",
    "wof:placetype":"venue"
},
  "geometry": {"coordinates":[15.222188,36.968273],"type":"Point"}
}