{
  "type": "Feature",
  "properties": {
    "iso:country":"IT",
    "sg:address":"20132 Milano",
    "sg:city":"Milano",
    "sg:orig_category":"Forniture E Materiali Per Imballaggio E Confezionamento. Forniture Per Uffici. Forniture Per Attivita' Commerciali Ed Artigianali",
    "sg:phone":"+39 02 215 4591",
    "sg:postcode":"20132",
    "sg:province":"Milano",
    "wof:name":"Maiocchi Srl",
    "wof:placetype":"venue"
},
  "geometry": {"coordinates":[9.2392215729,45.4911727905],"type":"Point"}
}