{
  "type": "Feature",
  "properties": {
    "iso:country":"IT",
    "sg:address":"07026 Olbia",
    "sg:city":"Olbia",
    "sg:classifiers":[
        {
            "category":"Shopping",
            "subcategory":"Crafts & Fabrics",
            "type":"Retail Goods"
        }
    ],
    "sg:phone":"+39 348 548 0060",
    "sg:postcode":"07026",
    "sg:province":"Olbia-Tempio",
    "sg:tags":[
        "gifts",
        "art",
        "artistic",
        "crafts"
    ],
    "sg:website":"http://www.solosardegna.com",
    "wof:name":"Careddu Salvatore Solo Sardegna",
    "wof:placetype":"venue"
},
  "geometry": {"coordinates":[9.278559,40.826839],"type":"Point"}
}