{
  "type": "Feature",
  "properties": {
    "iso:country":"IT",
    "sg:address":"126, Via Vallonto 31043 Fontanelle",
    "sg:city":"Fontanelle",
    "sg:classifiers":[
        {
            "category":"Manufacturing",
            "subcategory":"Wood Products",
            "type":"Manufacturing & Wholesale Goods"
        }
    ],
    "sg:phone":"+39 0422 818903",
    "sg:postcode":"31043",
    "sg:province":"Treviso",
    "sg:tags":[
        "furniture"
    ],
    "wof:name":"Aqua (s.r.l.)",
    "wof:placetype":"venue"
},
  "geometry": {"coordinates":[12.476646,45.854633],"type":"Point"}
}