{
  "type": "Feature",
  "properties": {
    "iso:country":"IT",
    "sg:address":"00195 Roma",
    "sg:city":"Roma",
    "sg:orig_category":"Fiere, Mostre E Saloni - Allestimento E Servizi",
    "sg:phone":"+39 06 3735 3588",
    "sg:postcode":"00195",
    "sg:province":"Roma",
    "wof:name":"G.v. Sas Di Viggiano Giuseppe",
    "wof:placetype":"venue"
},
  "geometry": {"coordinates":[12.4625854492,41.9220085144],"type":"Point"}
}