{
  "type": "Feature",
  "properties": {
    "iso:country":"IT",
    "sg:address":"81055 Santa Maria Capua Vetere",
    "sg:city":"Santa Maria Capua Vetere",
    "sg:orig_category":"Estetiste",
    "sg:phone":"+39 0823 794652",
    "sg:postcode":"81055",
    "sg:province":"Caserta",
    "sg:website":"http://www.studens.it",
    "wof:name":"Scuola Di Estetica Associazione 'studens Formazione'",
    "wof:placetype":"venue"
},
  "geometry": {"coordinates":[14.25636,41.080658],"type":"Point"}
}