{
  "type": "Feature",
  "properties": {
    "iso:country":"IT",
    "sg:address":"47814 Bellaria Igea Marina",
    "sg:city":"Bellaria",
    "sg:orig_category":"Ricami - Produzione E Ingrosso",
    "sg:phone":"+39 0541 346339",
    "sg:postcode":"47814",
    "sg:province":"Rimini",
    "wof:name":"Ricami Creazioni Ed Idee Di Franca Pironi & C. Snc",
    "wof:placetype":"venue"
},
  "geometry": {"coordinates":[12.453465,44.151733],"type":"Point"}
}