{
  "type": "Feature",
  "properties": {
    "iso:country":"IT",
    "sg:address":"20132 Milano",
    "sg:city":"Milano",
    "sg:orig_category":"Servizi E Lavori Industria Chimica",
    "sg:phone":"+39 02 2720 9016",
    "sg:postcode":"20132",
    "sg:province":"Milano",
    "wof:name":"Coppola Salvatore Di Coppola Roberto & C. (s.n.c.)",
    "wof:placetype":"venue"
},
  "geometry": {"coordinates":[9.251816,45.510262],"type":"Point"}
}