{
  "type": "Feature",
  "properties": {
    "iso:country":"IT",
    "sg:address":"72, Via Palermo 59013 Montemurlo",
    "sg:city":"Montemurlo",
    "sg:classifiers":[
        {
            "category":"Shopping",
            "subcategory":"Crafts & Fabrics",
            "type":"Retail Goods"
        }
    ],
    "sg:phone":"+39 0574 791768",
    "sg:postcode":"59013",
    "sg:province":"Prato",
    "wof:name":"Gipidue S.r.l.",
    "wof:placetype":"venue"
},
  "geometry": {"coordinates":[11.0258760452,43.9216766357],"type":"Point"}
}