{
  "type": "Feature",
  "properties": {
    "addr:full":"00155 Roma Roma Roma 00155",
    "addr:postcode":"00155;00155",
    "iso:country":"IT",
    "sg:address":"00155 Roma",
    "sg:city":"Roma",
    "sg:orig_category":"Scuole E Servizi Scolastici. Ricerca, Selezione E Formazione Del Personale",
    "sg:phone":"+39 06 225411",
    "sg:postcode":"00155",
    "sg:province":"Roma",
    "sg:website":"http://www.unicampus.it",
    "wof:name":"Universita' 'campus Bio Medico' Di Roma",
    "wof:placetype":"venue"
},
  "geometry": {"coordinates":[12.603024,41.901905],"type":"Point"}
}