{
  "type": "Feature",
  "properties": {
    "addr:full":"00192 Roma Roma Roma 00192",
    "addr:postcode":"00192;00192",
    "iso:country":"IT",
    "sg:address":"00192 Roma",
    "sg:city":"Roma",
    "sg:orig_category":"Sport - Articoli E Forniture",
    "sg:phone":"+39 06 3735 0762",
    "sg:postcode":"00192",
    "sg:province":"Roma",
    "wof:name":"Fonomaster Sas Di Riccardo Giampaoletti",
    "wof:placetype":"venue"
},
  "geometry": {"coordinates":[12.459212,41.912228],"type":"Point"}
}