{
  "type": "Feature",
  "properties": {
    "addr:full":"10042 Nichelino Nichelino Torino 10042",
    "addr:postcode":"10042;10042",
    "iso:country":"IT",
    "sg:address":"10042 Nichelino",
    "sg:city":"Nichelino",
    "sg:orig_category":"Istituti Di Bellezza",
    "sg:phone":"+39 011 680 1611",
    "sg:postcode":"10042",
    "sg:province":"Torino",
    "wof:name":"Papasso Ermanno S. Divamania",
    "wof:placetype":"venue"
},
  "geometry": {"coordinates":[7.654806,45.001461],"type":"Point"}
}