{
  "type": "Feature",
  "properties": {
    "iso:country":"IT",
    "sg:address":"59100 Prato",
    "sg:city":"Prato",
    "sg:classifiers":[
        {
            "category":"Health Services",
            "subcategory":"Nursing And Care Facility",
            "type":"Services"
        }
    ],
    "sg:phone":"+39 0574 440114",
    "sg:postcode":"59100",
    "sg:province":"Prato",
    "sg:tags":[
        "case",
        "riposo",
        "di"
    ],
    "wof:name":"Sanital Service Sas",
    "wof:placetype":"venue"
},
  "geometry": {"coordinates":[11.105757,43.898823],"type":"Point"}
}