{
  "type": "Feature",
  "properties": {
    "iso:country":"IT",
    "sg:address":"20095 Cusano Milanino",
    "sg:city":"Cusano Milanino",
    "sg:orig_category":"Servizi E Lavori Per Industria Alimentare E Bevande",
    "sg:phone":"+39 02 619 2367",
    "sg:postcode":"20095",
    "sg:province":"Milano",
    "wof:name":"Circolo Familiare =achille Grandi=",
    "wof:placetype":"venue"
},
  "geometry": {"coordinates":[9.177178,45.549728],"type":"Point"}
}