{
  "type": "Feature",
  "properties": {
    "iso:country":"IT",
    "sg:address":"27, Via Del Marzocco 57123 Livorno",
    "sg:city":"Livorno",
    "sg:classifiers":[
        {
            "category":"Banks & Credit Unions",
            "subcategory":"Investment Brokerage",
            "type":"Services"
        }
    ],
    "sg:phone":"+39 0586 886061",
    "sg:postcode":"57123",
    "sg:province":"Livorno",
    "sg:tags":[
        "-",
        "transport",
        "related"
    ],
    "wof:name":"Unisped (s.r.l.)",
    "wof:placetype":"venue"
},
  "geometry": {"coordinates":[10.307262,43.562546],"type":"Point"}
}