{
  "type": "Feature",
  "properties": {
    "iso:country":"IT",
    "sg:address":"Contrada Settimo 87036 Rende",
    "sg:city":"Rende",
    "sg:classifiers":[
        {
            "category":"Building & Trades",
            "subcategory":"Construction",
            "type":"Services"
        }
    ],
    "sg:phone":"+39 0984 839727",
    "sg:postcode":"87036",
    "sg:province":"Cosenza",
    "sg:tags":[
        "work",
        "public"
    ],
    "wof:name":"Nigro Acque S.r.l.",
    "wof:placetype":"venue"
},
  "geometry": {"coordinates":[16.214554,39.348446],"type":"Point"}
}