{
  "type": "Feature",
  "properties": {
    "iso:country":"IT",
    "sg:address":"37019 Peschiera Del Garda",
    "sg:city":"Peschiera del Garda",
    "sg:classifiers":[
        {
            "category":"Autos & Motor Vehicles",
            "subcategory":"Auto Supplies",
            "type":"Retail Goods"
        }
    ],
    "sg:phone":"+39 045 640 1837",
    "sg:postcode":"37019",
    "sg:province":"Verona",
    "sg:tags":[
        "article",
        "supplies",
        "vehicles",
        "leisure",
        "accessory"
    ],
    "wof:name":"World Bike Di Businaro Andrea & C. Snc",
    "wof:placetype":"venue"
},
  "geometry": {"coordinates":[10.696488,45.439896],"type":"Point"}
}