{
  "type": "Feature",
  "properties": {
    "iso:country":"IT",
    "sg:address":"31030 Carbonera",
    "sg:city":"Carbonera",
    "sg:orig_category":"Esportatori Ed Importatori",
    "sg:phone":"+39 0422 398059",
    "sg:postcode":"31030",
    "sg:province":"Treviso",
    "sg:website":"http://www.wineorchestra.it",
    "wof:name":"Orchestra Srl",
    "wof:placetype":"venue"
},
  "geometry": {"coordinates":[12.28253,45.68737],"type":"Point"}
}