{
  "type": "Feature",
  "properties": {
    "iso:country":"IT",
    "sg:address":"60127 Ancona",
    "sg:city":"Ancona",
    "sg:orig_category":"Autofficine E Centri Assistenza",
    "sg:phone":"+39 071 82766",
    "sg:postcode":"60127",
    "sg:province":"Ancona",
    "wof:name":"Autocarrozzeria Barbini Di Barbini Giacomo & Simone Snc",
    "wof:placetype":"venue"
},
  "geometry": {"coordinates":[13.502876,43.596775],"type":"Point"}
}