{
  "type": "Feature",
  "properties": {
    "addr:full":"19, Via Sanzio 20030 Barlassina Barlassina Milano 20030",
    "addr:postcode":"20030;20030",
    "addr:street":"Via Sanzio",
    "iso:country":"IT",
    "sg:address":"19, Via Sanzio 20030 Barlassina",
    "sg:city":"Barlassina",
    "sg:classifiers":[
        {
            "category":"Shopping",
            "subcategory":"Stationery & Office Supplies",
            "type":"Retail Goods"
        }
    ],
    "sg:phone":"+39 036 256 0555",
    "sg:postcode":"20030",
    "sg:province":"Milano",
    "sg:tags":[
        "professional"
    ],
    "wof:name":"Pellegatta Snc Di Pellegatta Enrico E C.",
    "wof:placetype":"venue"
},
  "geometry": {"coordinates":[9.1881408691,45.4636878967],"type":"Point"}
}