{
  "type": "Feature",
  "properties": {
    "iso:country":"IT",
    "sg:address":"24060 Bagnatica",
    "sg:city":"Bagnatica",
    "sg:orig_category":"Non-classified Establishments",
    "sg:phone":"+39 035 689411",
    "sg:postcode":"24060",
    "sg:province":"Bergamo",
    "wof:name":"Tre P Spa",
    "wof:placetype":"venue"
},
  "geometry": {"coordinates":[9.740073,45.687954],"type":"Point"}
}