{
  "type": "Feature",
  "properties": {
    "addr:full":"26100 Cremona Cremona Cremona 26100",
    "addr:postcode":"26100;26100",
    "iso:country":"IT",
    "sg:address":"26100 Cremona",
    "sg:city":"Cremona",
    "sg:orig_category":"Serramenti Ed Infissi",
    "sg:phone":"+39 0372 452749",
    "sg:postcode":"26100",
    "sg:province":"Cremona",
    "sg:website":"http://www.cremonaautomazioni.com",
    "wof:name":"Cremona Automazioni",
    "wof:placetype":"venue"
},
  "geometry": {"coordinates":[10.03482,45.134155],"type":"Point"}
}