{
  "type": "Feature",
  "properties": {
    "iso:country":"IT",
    "sg:address":"48100 Ravenna",
    "sg:city":"Ravenna",
    "sg:orig_category":"Abbigliamento Esterno, Maglierie E Pelliccerie",
    "sg:phone":"+39 0544 407655",
    "sg:postcode":"48100",
    "sg:province":"Ravenna",
    "wof:name":"3r Ricami Di Melandri Roberta Snc",
    "wof:placetype":"venue"
},
  "geometry": {"coordinates":[12.193419,44.419983],"type":"Point"}
}