{
  "type": "Feature",
  "properties": {
    "addr:full":"66034 Lanciano Lanciano Chieti 66034",
    "addr:postcode":"66034;66034",
    "iso:country":"IT",
    "sg:address":"66034 Lanciano",
    "sg:city":"Lanciano",
    "sg:orig_category":"Prodotti Chimici Secondari",
    "sg:phone":"+39 0872 40019",
    "sg:postcode":"66034",
    "sg:province":"Chieti",
    "wof:name":"Esplodenti Sabino S.r.l.",
    "wof:placetype":"venue"
},
  "geometry": {"coordinates":[14.3996944427,42.2281532288],"type":"Point"}
}