{
  "type": "Feature",
  "properties": {
    "addr:full":"10045 Piossasco Piossasco Torino 10045",
    "addr:postcode":"10045;10045",
    "iso:country":"IT",
    "sg:address":"10045 Piossasco",
    "sg:city":"Piossasco",
    "sg:orig_category":"Serbatoi - Produzione E Commercio",
    "sg:phone":"+39 0121 570588",
    "sg:postcode":"10045",
    "sg:province":"Torino",
    "sg:website":"http://www.paginegialle.it/latalpasnc",
    "wof:name":"La Talpa Snc",
    "wof:placetype":"venue"
},
  "geometry": {"coordinates":[7.623147,45.060375],"type":"Point"}
}