{
  "type": "Feature",
  "properties": {
    "iso:country":"IT",
    "sg:address":"20020 Arese",
    "sg:city":"Arese",
    "sg:orig_category":"Servizi E Lavori Per Industria Alimentare E Bevande",
    "sg:phone":"+39 02 938 0812",
    "sg:postcode":"20020",
    "sg:province":"Milano",
    "wof:name":"Cooperativa Agricola Edificatrice Di Arese",
    "wof:placetype":"venue"
},
  "geometry": {"coordinates":[9.078461,45.548351],"type":"Point"}
}