{
  "type": "Feature",
  "properties": {
    "iso:country":"IT",
    "sg:address":"17100 Savona",
    "sg:city":"Savona",
    "sg:orig_category":"Servizi Ausiliari Dei Mezzi Di Trasporto. Servizi Ausiliari Per Il Trasporto. Acqua, Luce, Gas E Societa' Di Esercizio Pubblico",
    "sg:phone":"+39 019 848 5291",
    "sg:postcode":"17100",
    "sg:province":"Savona",
    "wof:name":"Autostrada Dei Fiori Spa",
    "wof:placetype":"venue"
},
  "geometry": {"coordinates":[8.429389,44.342548],"type":"Point"}
}