{
  "type": "Feature",
  "properties": {
    "addr:full":"30027 San Dona'dipiave Venezia 30027",
    "addr:housenumber":"30027",
    "addr:postcode":"30027",
    "addr:street":"San Dona'Dipiave Venezia",
    "iso:country":"IT",
    "sg:address":"30027 San Dona'dipiave",
    "sg:orig_category":"Agenzie D'affari E Servizi Commerciali. Servizi Per Aziende, Manifestazioni E Supporto Agli Scambi Commerciali",
    "sg:phone":"+39 0421 330743",
    "sg:postcode":"30027",
    "sg:province":"Venezia",
    "wof:name":"Rozzino Carlo",
    "wof:placetype":"venue"
},
  "geometry": {"coordinates":[12.593511,45.636463],"type":"Point"}
}