{
  "type": "Feature",
  "properties": {
    "addr:full":"41100 Modena Modena Modena 41100",
    "addr:postcode":"41100;41100",
    "iso:country":"IT",
    "sg:address":"41100 Modena",
    "sg:city":"Modena",
    "sg:orig_category":"Forniture Per Attivita' Industriali",
    "sg:phone":"+39 059 280605",
    "sg:postcode":"41100",
    "sg:province":"Modena",
    "wof:name":"Cri.mo (s.r.l.)",
    "wof:placetype":"venue"
},
  "geometry": {"coordinates":[10.9691896439,44.6381912231],"type":"Point"}
}