{
  "type": "Feature",
  "properties": {
    "iso:country":"IT",
    "sg:address":"496, V. Tosco Romagnola 56021 Cascina",
    "sg:city":"Cascina",
    "sg:classifiers":[
        {
            "category":"Parking",
            "subcategory":"Lot",
            "type":"Transportation"
        }
    ],
    "sg:phone":"+39 39050740984",
    "sg:postcode":"56021",
    "sg:province":"Pisa",
    "sg:tags":[
        "transport",
        "road"
    ],
    "sg:website":"http://www.paginegialle.it/",
    "wof:name":"Autotrasporti I Cognati Sas",
    "wof:placetype":"venue"
},
  "geometry": {"coordinates":[10.470207,43.689842],"type":"Point"}
}