{
  "type": "Feature",
  "properties": {
    "addr:full":"98100 Messina ME",
    "addr:postcode":"98100",
    "iso:country":"IT",
    "sg:address":"98100 Messina",
    "sg:orig_category":"Prodotti Vari In Metallo. Articoli Per Imballaggio E Confezionamento",
    "sg:phone":"+39 090 632740",
    "sg:province":"ME",
    "wof:name":"Sergi Salvatore",
    "wof:placetype":"venue"
},
  "geometry": {"coordinates":[15.523018837,38.140663147],"type":"Point"}
}