{
  "type": "Feature",
  "properties": {
    "iso:country":"IT",
    "sg:address":"89866 Ricadi",
    "sg:city":"Ricadi",
    "sg:orig_category":"Servizi Per Lo Sport E Il Tempo Libero. Servizi Ausiliari Dei Mezzi Di Trasporto",
    "sg:phone":"+39 0963 669470",
    "sg:postcode":"89866",
    "sg:province":"Vibo Valentia",
    "wof:name":"Russo Maria",
    "wof:placetype":"venue"
},
  "geometry": {"coordinates":[16.09766,38.67561],"type":"Point"}
}