{
  "type": "Feature",
  "properties": {
    "addr:full":"20154 Milano Milano Milano 20154",
    "addr:postcode":"20154;20154",
    "iso:country":"IT",
    "sg:address":"20154 Milano",
    "sg:city":"Milano",
    "sg:orig_category":"Servizi Ausiliari Dei Mezzi Di Trasporto",
    "sg:phone":"+39 02 311336",
    "sg:postcode":"20154",
    "sg:province":"Milano",
    "wof:name":"Garage Gran S. Bernardo Di Colombo & Balconi",
    "wof:placetype":"venue"
},
  "geometry": {"coordinates":[9.168293,45.48901],"type":"Point"}
}