{
  "type": "Feature",
  "properties": {
    "addr:full":"18, Localita' Sponda Trentina 38100 Trento Trento Trento 38100",
    "addr:postcode":"38100;38100",
    "addr:street":"Localita ' Sponda Trentina",
    "iso:country":"IT",
    "sg:address":"18, Localita' Sponda Trentina 38100 Trento",
    "sg:city":"Trento",
    "sg:classifiers":[
        {
            "category":"Manufacturing",
            "subcategory":"Tools & Machinery",
            "type":"Manufacturing & Wholesale Goods"
        }
    ],
    "sg:phone":"+39 0461 242366",
    "sg:postcode":"38100",
    "sg:province":"Trento",
    "sg:tags":[
        "environment",
        "equipment",
        "-"
    ],
    "wof:name":"Cooperativa Ecologica Trentina S.c.a R.l.",
    "wof:placetype":"venue"
},
  "geometry": {"coordinates":[11.111519,46.134373],"type":"Point"}
}