{
  "type": "Feature",
  "properties": {
    "iso:country":"IT",
    "sg:address":"23885 Calco",
    "sg:city":"Calco",
    "sg:orig_category":"Dottori Commercialisti - Studi",
    "sg:phone":"+39 039 508319",
    "sg:postcode":"23885",
    "sg:province":"Lecco",
    "wof:name":"Ripamonti Dr. Francesco",
    "wof:placetype":"venue"
},
  "geometry": {"coordinates":[9.425004,45.72681],"type":"Point"}
}