{
  "type": "Feature",
  "properties": {
    "iso:country":"IT",
    "sg:address":"167, V. Garibaldi10068 Venaria",
    "sg:classifiers":[
        {
            "category":"Shopping",
            "subcategory":"Computers & Home Electronics",
            "type":"Retail Goods"
        }
    ],
    "sg:phone":"+39 011 453 0700",
    "sg:postcode":"10068",
    "sg:province":"Torino",
    "sg:tags":[
        "electronic",
        "electrical",
        "equipment"
    ],
    "sg:website":"http://www.aliceclub.it",
    "wof:name":"Incontri In The World",
    "wof:placetype":"venue"
},
  "geometry": {"coordinates":[7.644157,45.118992],"type":"Point"}
}