{
  "type": "Feature",
  "properties": {
    "iso:country":"IT",
    "sg:address":"3, Via King Martin Luther 24127 Bergamo",
    "sg:city":"Bergamo",
    "sg:classifiers":[
        {
            "category":"Real Estate",
            "subcategory":"Surveying",
            "type":"Services"
        }
    ],
    "sg:phone":"+39 39035252214",
    "sg:postcode":"24127",
    "sg:province":"Bergamo",
    "sg:tags":[
        "equipment",
        "material",
        "good",
        "-",
        "handling"
    ],
    "wof:name":"Segheria Legnami Beretta Ferruccio Felice & C. (s.a.s.)",
    "wof:placetype":"venue"
},
  "geometry": {"coordinates":[9.669952,45.694904],"type":"Point"}
}