{
  "type": "Feature",
  "properties": {
    "iso:country":"IT",
    "sg:address":"Corso Vittorio Emanuele Iii 9, 67068 Scurcola Marsicana, Aq",
    "sg:classifiers":[
        {
            "category":"Banks & Credit Unions",
            "subcategory":"Bank",
            "type":"Services"
        }
    ],
    "sg:postcode":"67068",
    "sg:province":"L'Aquila",
    "wof:name":"Banca Di Credito Cooperativo Di Scurcola Marsicana",
    "wof:placetype":"venue"
},
  "geometry": {"coordinates":[13.431372,42.039116],"type":"Point"}
}