{
  "type": "Feature",
  "properties": {
    "iso:country":"IT",
    "sg:address":"36027 Rosa'",
    "sg:orig_category":"Forniture Per Abbigliamento E Pelletterie",
    "sg:phone":"+39 0424 533150",
    "sg:postcode":"36027",
    "sg:province":"Vicenza",
    "wof:name":"Toniolo Michele Di Toniolo Roberto & C. (s.a.s.)",
    "wof:placetype":"venue"
},
  "geometry": {"coordinates":[11.7933397293,45.7398300171],"type":"Point"}
}