{
  "type": "Feature",
  "properties": {
    "iso:country":"IT",
    "sg:address":"10/12, Via Ravello 20080 Vermezzo",
    "sg:city":"Vermezzo",
    "sg:classifiers":[
        {
            "category":"Shopping",
            "type":"Retail Goods"
        }
    ],
    "sg:phone":"+39 39029440430",
    "sg:postcode":"20080",
    "sg:province":"Milano",
    "sg:tags":[
        "finished",
        "-",
        "metallic"
    ],
    "wof:name":"Sisa Mould Systems Srl",
    "wof:placetype":"venue"
},
  "geometry": {"coordinates":[8.9632320404,45.4037475586],"type":"Point"}
}