{
  "type": "Feature",
  "properties": {
    "addr:full":"35010 Vigonza Vigonza Padova 35010",
    "addr:postcode":"35010;35010",
    "iso:country":"IT",
    "sg:address":"35010 Vigonza",
    "sg:city":"Vigonza",
    "sg:orig_category":"Frigotecnica, Apparecchiature E Servizi",
    "sg:phone":"+39 049 893 1555",
    "sg:postcode":"35010",
    "sg:province":"Padova",
    "wof:name":"Vi.ri. Srl",
    "wof:placetype":"venue"
},
  "geometry": {"coordinates":[11.9566879272,45.43309021],"type":"Point"}
}