{
  "type": "Feature",
  "properties": {
    "addr:full":"84010 San Marzano Sul Sarno San Marzano sul Sarno Salerno 84010",
    "addr:housenumber":"84010;marzano",
    "addr:postcode":"marzano;84010",
    "addr:street":"San",
    "iso:country":"IT",
    "sg:address":"84010 San Marzano Sul Sarno",
    "sg:city":"San Marzano sul Sarno",
    "sg:orig_category":"Macchine, Impianti Ed Attrezzature Per Agricoltura E Zootecnia",
    "sg:phone":"+39 081 518 6195",
    "sg:postcode":"84010",
    "sg:province":"Salerno",
    "wof:name":"Schiavone S.r.l.",
    "wof:placetype":"venue"
},
  "geometry": {"coordinates":[14.516899,40.745766],"type":"Point"}
}