{
  "type": "Feature",
  "properties": {
    "iso:country":"IT",
    "sg:address":"Via Fabriani, 1/3; Modena; 41100",
    "sg:city":"Modena",
    "sg:classifiers":[
        {
            "category":"Banks & Credit Unions",
            "subcategory":"Bank",
            "type":"Services"
        }
    ],
    "sg:phone":"+39 059 220909",
    "sg:postcode":"41100",
    "sg:province":"Modena",
    "wof:name":"Banca Di Roma",
    "wof:placetype":"venue"
},
  "geometry": {"coordinates":[10.919714,44.649757],"type":"Point"}
}