{
  "type": "Feature",
  "properties": {
    "addr:full":"14034 Castello Di Annone Castello di Annone Asti 14034",
    "addr:housenumber":"14034",
    "addr:postcode":"14034",
    "addr:street":"Castello",
    "iso:country":"IT",
    "sg:address":"14034 Castello Di Annone",
    "sg:city":"Castello di Annone",
    "sg:orig_category":"Motori Ed Organi Di Trasmissione. Ricambi E Componenti Dei Mezzi Di Trasporto",
    "sg:phone":"+39 0141 401766",
    "sg:postcode":"14034",
    "sg:province":"Asti",
    "wof:name":"Fad Spa",
    "wof:placetype":"venue"
},
  "geometry": {"coordinates":[8.3120918274,44.8805961609],"type":"Point"}
}