{
  "type": "Feature",
  "properties": {
    "addr:full":"96100 Siracusa Siracusa Siracusa 96100",
    "addr:postcode":"96100;96100",
    "iso:country":"IT",
    "sg:address":"96100 Siracusa",
    "sg:city":"Siracusa",
    "sg:classifiers":[
        {
            "category":"Home & Garden",
            "subcategory":"Carpets & Floor Coverings",
            "type":"Retail Goods"
        }
    ],
    "sg:phone":"+39 0931 462771",
    "sg:postcode":"96100",
    "sg:province":"Siracusa",
    "sg:tags":[
        "curtain",
        "material",
        "fabric",
        "fabrics",
        "furnishing"
    ],
    "wof:name":"Ars Domus Di Randazzo Giancarlo",
    "wof:placetype":"venue"
},
  "geometry": {"coordinates":[15.1960792542,37.0567092896],"type":"Point"}
}