{
  "type": "Feature",
  "properties": {
    "iso:country":"IT",
    "sg:address":"60027 Osimo",
    "sg:city":"Osimo",
    "sg:orig_category":"Serigrafia",
    "sg:phone":"+39 071 721 1163",
    "sg:postcode":"60027",
    "sg:province":"Ancona",
    "wof:name":"Plastopaint Srl",
    "wof:placetype":"venue"
},
  "geometry": {"coordinates":[13.474299,43.467899],"type":"Point"}
}