{
  "type": "Feature",
  "properties": {
    "addr:full":"50, Via Buonarroti Michelangelo 20093 Cologno Monzese Cologno Monzese Milano 20093",
    "addr:postcode":"20093;20093",
    "addr:street":"Via Buonarroti Michelangelo",
    "iso:country":"IT",
    "sg:address":"50, Via Buonarroti Michelangelo 20093 Cologno Monzese",
    "sg:city":"Cologno Monzese",
    "sg:classifiers":[
        {
            "category":"Shopping",
            "subcategory":"Crafts & Fabrics",
            "type":"Retail Goods"
        }
    ],
    "sg:phone":"+39 02 2539 0631",
    "sg:postcode":"20093",
    "sg:province":"Milano",
    "wof:name":"Silence Snc",
    "wof:placetype":"venue"
},
  "geometry": {"coordinates":[9.2697916031,45.5331573486],"type":"Point"}
}