{
  "type": "Feature",
  "properties": {
    "iso:country":"IT",
    "sg:address":"52025 Montevarchi",
    "sg:city":"Montevarchi",
    "sg:orig_category":"Macchine, Impianti Ed Attrezzature Per Abbigliamento E Pelletterie",
    "sg:phone":"+39 055 984082",
    "sg:postcode":"52025",
    "sg:province":"Arezzo",
    "wof:name":"Canestri Gaspero",
    "wof:placetype":"venue"
},
  "geometry": {"coordinates":[11.877016,43.458649],"type":"Point"}
}