{
  "type": "Feature",
  "properties": {
    "addr:full":"644, Corso Italia 44043 Mirabello Mirabello Ferrara 44043",
    "addr:postcode":"44043;44043",
    "addr:street":"Corso Italia",
    "iso:country":"IT",
    "sg:address":"644, Corso Italia 44043 Mirabello",
    "sg:city":"Mirabello",
    "sg:classifiers":[
        {
            "category":"Shopping",
            "type":"Retail Goods"
        }
    ],
    "sg:phone":"+39 0532 846200",
    "sg:postcode":"44043",
    "sg:province":"Ferrara",
    "sg:tags":[
        "finished",
        "-",
        "metallic"
    ],
    "wof:name":"Vega (s.r.l.)",
    "wof:placetype":"venue"
},
  "geometry": {"coordinates":[11.4598999023,44.8249778748],"type":"Point"}
}