{
  "type": "Feature",
  "properties": {
    "iso:country":"IT",
    "sg:address":"7, V. Domenico Millelire 00136 Roma",
    "sg:city":"Roma",
    "sg:classifiers":[
        {
            "category":"Shopping",
            "subcategory":"Stationery & Office Supplies",
            "type":"Retail Goods"
        }
    ],
    "sg:phone":"+39 06 3974 2730",
    "sg:postcode":"00136",
    "sg:province":"Roma",
    "sg:tags":[
        "professional"
    ],
    "sg:website":"http://www.paginegialle.it/arcdonofrio",
    "wof:name":"Architetture D'onofrio Srl",
    "wof:placetype":"venue"
},
  "geometry": {"coordinates":[12.4468193054,41.9049949646],"type":"Point"}
}