{
  "type": "Feature",
  "properties": {
    "iso:country":"IT",
    "sg:address":"P. Dei Giudici 3; Firenze; 50122",
    "sg:city":"Firenze",
    "sg:classifiers":[
        {
            "category":"Shopping",
            "subcategory":"Computers & Home Electronics",
            "type":"Retail Goods"
        }
    ],
    "sg:phone":"+39 390 552 7951",
    "sg:postcode":"50122",
    "sg:province":"Firenze",
    "sg:tags":[
        "chamber",
        "commerce"
    ],
    "sg:website":"www.fi.camcom.it",
    "wof:name":"Firenze Chamber Of Commerce And Industry",
    "wof:placetype":"venue"
},
  "geometry": {"coordinates":[11.256271,43.767826],"type":"Point"}
}