{
  "type": "Feature",
  "properties": {
    "addr:full":"8, Via Donatori Di Sangue 22100 Como Como Como 22100",
    "addr:postcode":"22100;22100",
    "addr:street":"Via Donatori Di Sangue",
    "iso:country":"IT",
    "sg:address":"8, Via Donatori Di Sangue 22100 Como",
    "sg:city":"Como",
    "sg:classifiers":[
        {
            "category":"Real Estate",
            "subcategory":"Architect",
            "type":"Services"
        }
    ],
    "sg:phone":"+39 031 338 8311",
    "sg:postcode":"22100",
    "sg:province":"Como",
    "sg:tags":[
        "textile",
        "clothing"
    ],
    "wof:name":"Tintoria Lariana Spa",
    "wof:placetype":"venue"
},
  "geometry": {"coordinates":[9.089283,45.788567],"type":"Point"}
}