{
  "type": "Feature",
  "properties": {
    "iso:country":"IT",
    "sg:address":"2, Via Ponte Della Regina 24031 Almenno San Salvatore",
    "sg:city":"Almenno San Salvatore",
    "sg:classifiers":[
        {
            "category":"Building & Trades",
            "subcategory":"Construction",
            "type":"Services"
        }
    ],
    "sg:phone":"+39 39035640120",
    "sg:postcode":"24031",
    "sg:province":"Bergamo",
    "sg:tags":[
        "work",
        "public"
    ],
    "wof:name":"Zanardi Luigi (s.r.l.)",
    "wof:placetype":"venue"
},
  "geometry": {"coordinates":[9.603419,45.745548],"type":"Point"}
}