{
  "type": "Feature",
  "properties": {
    "iso:country":"IT",
    "sg:address":"Strada Statale, 415 Km 45,400 26012 Castelleone",
    "sg:city":"Castelleone",
    "sg:classifiers":[
        {
            "category":"Bars & Pubs",
            "subcategory":"Champagne Bar",
            "type":"Food & Drink"
        }
    ],
    "sg:phone":"+39 0374 357511",
    "sg:postcode":"26012",
    "sg:province":"Cremona",
    "sg:tags":[
        "grippers",
        "cnc-lathes"
    ],
    "sg:website":"www.saco.it",
    "wof:name":"Saco Spa",
    "wof:placetype":"venue"
},
  "geometry": {"coordinates":[10.026135,45.133499],"type":"Point"}
}