{
  "type": "Feature",
  "properties": {
    "addr:full":"6, Via P. Borsellino 43055 Mezzani Mezzani Parma 43055",
    "addr:postcode":"43055;43055",
    "addr:street":"Via P. Borsellino",
    "iso:country":"IT",
    "sg:address":"6, Via P. Borsellino 43055 Mezzani",
    "sg:city":"Mezzani",
    "sg:classifiers":[
        {
            "category":"Manufacturing",
            "subcategory":"Rubber & Plastics",
            "type":"Manufacturing & Wholesale Goods"
        }
    ],
    "sg:phone":"+39 0521 818601",
    "sg:postcode":"43055",
    "sg:province":"Parma",
    "wof:name":"S.i.l.p. (s.n.c.)",
    "wof:placetype":"venue"
},
  "geometry": {"coordinates":[10.3295478821,44.8078651428],"type":"Point"}
}