{
  "type": "Feature",
  "properties": {
    "iso:country":"IT",
    "sg:address":"20132 Milano",
    "sg:city":"Milano",
    "sg:classifiers":[
        {
            "category":"Health Services",
            "subcategory":"Health Practitioner",
            "type":"Services"
        }
    ],
    "sg:phone":"+39 02 215 5636",
    "sg:postcode":"20132",
    "sg:province":"Milano",
    "sg:tags":[
        "medici"
    ],
    "wof:name":"Salomoni Fernando",
    "wof:placetype":"venue"
},
  "geometry": {"coordinates":[9.2531099319,45.5074729919],"type":"Point"}
}