{
  "type": "Feature",
  "properties": {
    "iso:country":"IT",
    "sg:address":"20094 Corsico",
    "sg:city":"Corsico",
    "sg:orig_category":"Forniture Per Edilizia E Lavori Pubblici",
    "sg:phone":"+39 02 4510 0103",
    "sg:postcode":"20094",
    "sg:province":"Milano",
    "wof:name":"Covering Carpet Company 3c Srl",
    "wof:placetype":"venue"
},
  "geometry": {"coordinates":[9.1140146255,45.4355049133],"type":"Point"}
}