{
  "type": "Feature",
  "properties": {
    "addr:full":"90047 Partinico Partinico Palermo 90047",
    "addr:postcode":"90047;90047",
    "iso:country":"IT",
    "sg:address":"90047 Partinico",
    "sg:city":"Partinico",
    "sg:orig_category":"Forniture Per Agricoltura E Zootecnia. Animali Domestici",
    "sg:phone":"+39 091 890 6845",
    "sg:postcode":"90047",
    "sg:province":"Palermo",
    "wof:name":"Piccolo Zoo Mediterraneo - Lo Grasso Giuseppa",
    "wof:placetype":"venue"
},
  "geometry": {"coordinates":[13.1163787842,38.0486869812],"type":"Point"}
}