{
  "type": "Feature",
  "properties": {
    "iso:country":"IT",
    "sg:address":"50051 Castelfiorentino",
    "sg:city":"Castelfiorentino",
    "sg:orig_category":"Abbigliamento Esterno, Maglierie E Pelliccerie. Shopping",
    "sg:phone":"+39 0571 64126",
    "sg:postcode":"50051",
    "sg:province":"Firenze",
    "wof:name":"Springmode Srl",
    "wof:placetype":"venue"
},
  "geometry": {"coordinates":[10.958095,43.62627],"type":"Point"}
}