{
  "type": "Feature",
  "properties": {
    "iso:country":"IT",
    "sg:address":"Via Rosellini 16/18; Milano; 20124",
    "sg:city":"Milano",
    "sg:classifiers":[
        {
            "category":"Banks & Credit Unions",
            "subcategory":"Bank",
            "type":"Services"
        }
    ],
    "sg:phone":"+39 02 6970 5506",
    "sg:postcode":"20124",
    "sg:province":"Milano",
    "wof:name":"Banca Monte Dei Paschi, Di Siena Spa",
    "wof:placetype":"venue"
},
  "geometry": {"coordinates":[9.195043,45.490425],"type":"Point"}
}