{
  "type": "Feature",
  "properties": {
    "iso:country":"IT",
    "sg:address":"Piazza Vittorio; Costabissara; 36030",
    "sg:city":"Costabissara",
    "sg:classifiers":[
        {
            "category":"Banks & Credit Unions",
            "subcategory":"Bank",
            "type":"Services"
        }
    ],
    "sg:phone":"+39 0444 970711",
    "sg:postcode":"36030",
    "sg:province":"Vicenza",
    "wof:name":"Cariverona Banca Spa",
    "wof:placetype":"venue"
},
  "geometry": {"coordinates":[11.487684,45.585445],"type":"Point"}
}