{
  "type": "Feature",
  "properties": {
    "iso:country":"IT",
    "sg:address":"10093 Collegno",
    "sg:city":"Collegno",
    "sg:orig_category":"Materiali E Componenti Elettrotecnici",
    "sg:phone":"+39 011 401 2111",
    "sg:postcode":"10093",
    "sg:province":"Torino",
    "sg:website":"http://www.tycoelectronics.com",
    "wof:name":"Tyco Electronics Amp Italia Spa",
    "wof:placetype":"venue"
},
  "geometry": {"coordinates":[7.586564,45.089779],"type":"Point"}
}