{
  "type": "Feature",
  "properties": {
    "iso:country":"IT",
    "sg:address":"35129 Padova",
    "sg:city":"Padova",
    "sg:orig_category":"Coperte E Copriletti",
    "sg:phone":"+39 049 625321",
    "sg:postcode":"35129",
    "sg:province":"Padova",
    "wof:name":"Carraro Casa Snc",
    "wof:placetype":"venue"
},
  "geometry": {"coordinates":[11.925999,45.426647],"type":"Point"}
}