{
  "type": "Feature",
  "properties": {
    "addr:full":"Via Piave Ang; Sumirago; 21040 Sumirago Varese 21040",
    "addr:postcode":"21040;21040",
    "addr:street":"Via Piave Ang",
    "iso:country":"IT",
    "sg:address":"Via Piave Ang; Sumirago; 21040",
    "sg:city":"Sumirago",
    "sg:classifiers":[
        {
            "category":"Banks & Credit Unions",
            "subcategory":"Bank",
            "type":"Services"
        }
    ],
    "sg:phone":"+39 0331 905151",
    "sg:postcode":"21040",
    "sg:province":"Varese",
    "wof:name":"Istitutuo Bancario, San Paolo Di Torino Spa",
    "wof:placetype":"venue"
},
  "geometry": {"coordinates":[8.782833,45.738777],"type":"Point"}
}