{
  "type": "Feature",
  "properties": {
    "iso:country":"IT",
    "sg:address":"11, Via Righi Augusto 80125 Napoli",
    "sg:city":"Napoli",
    "sg:classifiers":[
        {
            "category":"Professional",
            "subcategory":"Engineering",
            "type":"Services"
        }
    ],
    "sg:phone":"+39 081 617 1896",
    "sg:postcode":"80125",
    "sg:province":"Napoli",
    "sg:tags":[
        "machine",
        "-",
        "mechanical"
    ],
    "wof:name":"Edil Montaggi Service S.r.l.",
    "wof:placetype":"venue"
},
  "geometry": {"coordinates":[14.236499,40.918873],"type":"Point"}
}