{
  "type": "Feature",
  "properties": {
    "addr:full":"26, Via Marzabotto 20059 Vimercate Vimercate Milano 20059",
    "addr:postcode":"20059;20059",
    "addr:street":"Via Marzabotto",
    "iso:country":"IT",
    "sg:address":"26, Via Marzabotto 20059 Vimercate",
    "sg:city":"Vimercate",
    "sg:classifiers":[
        {
            "category":"Professional",
            "subcategory":"Engineering",
            "type":"Services"
        }
    ],
    "sg:phone":"+39 039 608 2914",
    "sg:postcode":"20059",
    "sg:province":"Milano",
    "sg:tags":[
        "machine",
        "-",
        "mechanical"
    ],
    "wof:name":"Egi Di Brambilla Sergio & C. (s.n.c.)",
    "wof:placetype":"venue"
},
  "geometry": {"coordinates":[9.360072,45.595528],"type":"Point"}
}