{
  "type": "Feature",
  "properties": {
    "addr:full":"00040 Pomezia Pomezia Roma 00040",
    "addr:postcode":"00040;roma 00040",
    "iso:country":"IT",
    "sg:address":"00040 Pomezia",
    "sg:city":"Pomezia",
    "sg:orig_category":"Pubblica Amministrazione",
    "sg:phone":"+39 06 917 3178",
    "sg:postcode":"00040",
    "sg:province":"Roma",
    "wof:name":"Provincia Di Roma",
    "wof:placetype":"venue"
},
  "geometry": {"coordinates":[12.4552087784,41.627696991],"type":"Point"}
}