{
  "type": "Feature",
  "properties": {
    "iso:country":"IT",
    "sg:address":"20146 Milano",
    "sg:city":"Milano",
    "sg:classifiers":[
        {
            "category":"Health Services",
            "subcategory":"Health Practitioner",
            "type":"Services"
        }
    ],
    "sg:phone":"+39 02 427178",
    "sg:postcode":"20146",
    "sg:province":"Milano",
    "sg:tags":[
        "medici"
    ],
    "wof:name":"Semplici Sacchi Tiziana",
    "wof:placetype":"venue"
},
  "geometry": {"coordinates":[9.1498317719,45.4511413574],"type":"Point"}
}