{
  "type": "Feature",
  "properties": {
    "addr:full":"40, Via S.ubaldo 60030 Monsano Monsano Ancona 60030",
    "addr:postcode":"60030;60030",
    "addr:street":"Via S.Ubaldo",
    "iso:country":"IT",
    "sg:address":"40, Via S.ubaldo 60030 Monsano",
    "sg:city":"Monsano",
    "sg:classifiers":[
        {
            "category":"Wholesale",
            "subcategory":"Drugs",
            "type":"Manufacturing & Wholesale Goods"
        }
    ],
    "sg:phone":"+39 39073160032",
    "sg:postcode":"60030",
    "sg:province":"Ancona",
    "sg:tags":[
        "chemical",
        "pharmaceutical"
    ],
    "wof:name":"Canadian Plaster (s.r.l.)",
    "wof:placetype":"venue"
},
  "geometry": {"coordinates":[13.518757,43.615856],"type":"Point"}
}