{
  "type": "Feature",
  "properties": {
    "addr:full":"00189 Roma Roma Roma 00189",
    "addr:postcode":"00189;00189",
    "iso:country":"IT",
    "sg:address":"00189 Roma",
    "sg:city":"Roma",
    "sg:orig_category":"Giocattoli E Giochi - Vendita Al Dettaglio",
    "sg:phone":"+39 06 3324 8356",
    "sg:postcode":"00189",
    "sg:province":"Roma",
    "sg:website":"http://www.dollshouseitalia.com",
    "wof:name":"Dolls House Italia",
    "wof:placetype":"venue"
},
  "geometry": {"coordinates":[12.435351,41.967575],"type":"Point"}
}