{
  "type": "Feature",
  "properties": {
    "iso:country":"IT",
    "sg:address":"36015 Schio",
    "sg:city":"Schio",
    "sg:orig_category":"Affettatrici E Tritacarne",
    "sg:phone":"+39 0445 521387",
    "sg:postcode":"36015",
    "sg:province":"Vicenza",
    "wof:name":"Moro Federico & Co. Snc",
    "wof:placetype":"venue"
},
  "geometry": {"coordinates":[11.584785,45.541496],"type":"Point"}
}