{
  "type": "Feature",
  "properties": {
    "iso:country":"IT",
    "sg:address":"46100 Mantova",
    "sg:city":"Mantova",
    "sg:orig_category":"Disinfezione, Disinfestazione E Derattizzazione",
    "sg:phone":"+39 0376 223126",
    "sg:postcode":"46100",
    "sg:province":"Mantova",
    "wof:name":"Mantova Service Di Raffaele La Marca",
    "wof:placetype":"venue"
},
  "geometry": {"coordinates":[10.791612,45.161064],"type":"Point"}
}