{
  "type": "Feature",
  "properties": {
    "addr:full":"10092 Beinasco Beinasco Torino 10092",
    "addr:postcode":"10092;10092",
    "iso:country":"IT",
    "sg:address":"10092 Beinasco",
    "sg:city":"Beinasco",
    "sg:orig_category":"Prodotti E Manufatti In Materie Plastiche",
    "sg:phone":"+39 011 398 9565",
    "sg:postcode":"10092",
    "sg:province":"Torino",
    "wof:name":"L.a.s.a. Holding Srl",
    "wof:placetype":"venue"
},
  "geometry": {"coordinates":[7.5810685158,45.0219535828],"type":"Point"}
}