{
  "type": "Feature",
  "properties": {
    "iso:country":"IT",
    "sg:address":"13, Via Predda Niedda 07100 Sassari",
    "sg:city":"Sassari",
    "sg:classifiers":[
        {
            "category":"Autos & Motor Vehicles",
            "subcategory":"Automobile Sales",
            "type":"Retail Goods"
        }
    ],
    "sg:phone":"+39 39079261818",
    "sg:postcode":"07100",
    "sg:province":"Sassari",
    "sg:tags":[
        "motor-cars"
    ],
    "wof:name":"U.p.a.s. Srl",
    "wof:placetype":"venue"
},
  "geometry": {"coordinates":[8.5538892746,40.7294425964],"type":"Point"}
}