{
  "type": "Feature",
  "properties": {
    "addr:full":"Via Provinciale Cremona 57 - San Qu 43010 Trecasali Trecasali Parma 43010",
    "addr:housenumber":"57",
    "addr:postcode":"43010;43010",
    "addr:street":"Via Provinciale Cremona;San Qu",
    "iso:country":"IT",
    "sg:address":"Via Provinciale Cremona 57 - San Qu 43010 Trecasali",
    "sg:city":"Trecasali",
    "sg:classifiers":[
        {
            "category":"Banks & Credit Unions",
            "subcategory":"Investment Brokerage",
            "type":"Services"
        }
    ],
    "sg:phone":"+39 0521 872321",
    "sg:postcode":"43010",
    "sg:province":"Parma",
    "sg:tags":[
        "irrigation",
        "pump",
        "system"
    ],
    "sg:website":"www.rmirriga.it",
    "wof:name":"Rm Spa",
    "wof:placetype":"venue"
},
  "geometry": {"coordinates":[10.329548,44.807865],"type":"Point"}
}