{
  "type": "Feature",
  "properties": {
    "addr:full":"14100 Asti Asti Asti 14100",
    "addr:postcode":"14100;14100",
    "iso:country":"IT",
    "sg:address":"14100 Asti",
    "sg:city":"Asti",
    "sg:orig_category":"Automazione E Macchine Per Ufficio. Forniture Industriali Per Prevenzione, Controllo E Sicurezza",
    "sg:phone":"+39 0141 595646",
    "sg:postcode":"14100",
    "sg:province":"Asti",
    "wof:name":"Mp Di Rabbione Giovanna",
    "wof:placetype":"venue"
},
  "geometry": {"coordinates":[8.214156,44.897858],"type":"Point"}
}