{
  "type": "Feature",
  "properties": {
    "addr:full":"Corso Cavour 2; Vigevano; 27029 Vigevano Pavia 27029",
    "addr:housenumber":"2",
    "addr:postcode":"27029;27029",
    "addr:street":"Corso Cavour",
    "iso:country":"IT",
    "sg:address":"Corso Cavour 2; Vigevano; 27029",
    "sg:city":"Vigevano",
    "sg:classifiers":[
        {
            "category":"Banks & Credit Unions",
            "subcategory":"Bank",
            "type":"Services"
        }
    ],
    "sg:phone":"+39 0381 88122",
    "sg:postcode":"27029",
    "sg:province":"Pavia",
    "wof:name":"Istituto Bancario, San Paolo Di Torino Spa",
    "wof:placetype":"venue"
},
  "geometry": {"coordinates":[8.856419,45.320183],"type":"Point"}
}