{
  "type": "Feature",
  "properties": {
    "iso:country":"IT",
    "sg:address":"11, Pl. Po 44039 Tresigallo",
    "sg:city":"Tresigallo",
    "sg:classifiers":[
        {
            "category":"Shopping",
            "subcategory":"Computers & Home Electronics",
            "type":"Retail Goods"
        }
    ],
    "sg:phone":"+39 0533 602170",
    "sg:postcode":"44039",
    "sg:province":"Ferrara",
    "sg:tags":[
        "electronic",
        "electrical",
        "equipment"
    ],
    "wof:name":"S.a.f. Italy Srl",
    "wof:placetype":"venue"
},
  "geometry": {"coordinates":[11.888281,44.817001],"type":"Point"}
}