{
  "type": "Feature",
  "properties": {
    "iso:country":"IT",
    "sg:address":"Via Del Seprio 54 22074 Lomazzo",
    "sg:city":"Lomazzo",
    "sg:orig_category":"Ladies' Shoes",
    "sg:phone":"+39 02 9677 9393",
    "sg:postcode":"22074",
    "sg:province":"Como",
    "sg:website":"www.brunate.it",
    "wof:name":"Calzaturificio Brunate S.p.a.",
    "wof:placetype":"venue"
},
  "geometry": {"coordinates":[9.018997,45.699829],"type":"Point"}
}