{
  "type": "Feature",
  "properties": {
    "iso:country":"IT",
    "sg:address":"90133 Palermo",
    "sg:city":"Palermo",
    "sg:orig_category":"Articoli Da Regalo. Arte Ed Artigianato Artistico. Shopping",
    "sg:phone":"+39 091 616 4101",
    "sg:postcode":"90133",
    "sg:province":"Palermo",
    "wof:name":"Glorioso Giuseppe",
    "wof:placetype":"venue"
},
  "geometry": {"coordinates":[13.371076,38.112778],"type":"Point"}
}