{
  "type": "Feature",
  "properties": {
    "iso:country":"IT",
    "sg:address":"Via Dell' Agricoltura 36040 Sarego",
    "sg:city":"Sarego",
    "sg:orig_category":"Current Limiting Reactors, Choke Coils, Reactance Coils, Power Chokes",
    "sg:phone":"+39 0444 822000",
    "sg:postcode":"36040",
    "sg:province":"Vicenza",
    "sg:website":"www.euroelettro.com",
    "wof:name":"Euroelettro Srl",
    "wof:placetype":"venue"
},
  "geometry": {"coordinates":[11.426064,45.442963],"type":"Point"}
}