{
  "type": "Feature",
  "properties": {
    "iso:country":"IT",
    "sg:address":"50028 Tavarnelle Val Di Pesa",
    "sg:city":"Tavarnelle Val di Pesa",
    "sg:orig_category":"Termotecnica E Riscaldamento, Apparecchiature E Servizi",
    "sg:phone":"+39 055 807 1799",
    "sg:postcode":"50028",
    "sg:province":"Firenze",
    "wof:name":"Guattioli & Martinelli",
    "wof:placetype":"venue"
},
  "geometry": {"coordinates":[11.204958,43.581558],"type":"Point"}
}