{
  "type": "Feature",
  "properties": {
    "iso:country":"IT",
    "sg:address":"59011 Seano",
    "sg:city":"Seano",
    "sg:orig_category":"Macchine, Impianti Ed Attrezzature Per Abbigliamento E Pelletterie",
    "sg:phone":"+39 055 870 6406",
    "sg:postcode":"59011",
    "sg:province":"Prato",
    "wof:name":"Bennati E Bennati Snc Giuseppe",
    "wof:placetype":"venue"
},
  "geometry": {"coordinates":[11.005391,43.824017],"type":"Point"}
}