{
  "type": "Feature",
  "properties": {
    "iso:country":"IT",
    "sg:address":"55100 Lucca",
    "sg:city":"Lucca",
    "sg:orig_category":"Nautica. Ricambi E Componenti Dei Mezzi Di Trasporto",
    "sg:phone":"+39 0583 418784",
    "sg:postcode":"55100",
    "sg:province":"Lucca",
    "wof:name":"Expo Moto Di Giovacchini Mario Luigi",
    "wof:placetype":"venue"
},
  "geometry": {"coordinates":[10.493017,43.844315],"type":"Point"}
}