{
  "type": "Feature",
  "properties": {
    "iso:country":"IT",
    "sg:address":"Via G. Matteotti 60; S. Mauro Pascoli; 47030",
    "sg:classifiers":[
        {
            "category":"Banks & Credit Unions",
            "subcategory":"Bank",
            "type":"Services"
        }
    ],
    "sg:phone":"+39 0541 931790",
    "sg:postcode":"47030",
    "sg:province":"Forl\u00ec-Cesena",
    "wof:name":"Cassa Di Risparmio Di Cesena Spa",
    "wof:placetype":"venue"
},
  "geometry": {"coordinates":[12.414165,44.106327],"type":"Point"}
}