{
  "type": "Feature",
  "properties": {
    "iso:country":"IT",
    "sg:address":"20129 Milano",
    "sg:city":"Milano",
    "sg:orig_category":"Pubblicita' - Articoli Ed Oggetti",
    "sg:phone":"+39 02 7600 8327",
    "sg:postcode":"20129",
    "sg:province":"Milano",
    "sg:website":"http://www.cmpep.com",
    "wof:name":"C.m.p. & P. Srl",
    "wof:placetype":"venue"
},
  "geometry": {"coordinates":[9.2053775787,45.4704818726],"type":"Point"}
}