{
  "type": "Feature",
  "properties": {
    "addr:full":"40127 Bologna Bologna Bologna 40127",
    "addr:postcode":"40127;40127",
    "iso:country":"IT",
    "sg:address":"40127 Bologna",
    "sg:city":"Bologna",
    "sg:orig_category":"Servizi E Lavori Per Abbigliamento E Pelletterie",
    "sg:phone":"+39 051 500052",
    "sg:postcode":"40127",
    "sg:province":"Bologna",
    "wof:name":"Pasvens Srl",
    "wof:placetype":"venue"
},
  "geometry": {"coordinates":[11.371506,44.504265],"type":"Point"}
}