{
  "type": "Feature",
  "properties": {
    "iso:country":"IT",
    "sg:address":"10122 Torino",
    "sg:city":"Torino",
    "sg:orig_category":"Forniture Per Abbigliamento E Pelletterie",
    "sg:phone":"+39 011 542952",
    "sg:postcode":"10122",
    "sg:province":"Torino",
    "wof:name":"Antica Fabbrica Passamanerie Massia Vittorio Snc Di Massia G. L. & C.",
    "wof:placetype":"venue"
},
  "geometry": {"coordinates":[7.6807546616,45.0718536377],"type":"Point"}
}