{
  "type": "Feature",
  "properties": {
    "addr:full":"34, Via Milazzo 21052 Busto Arsizio Busto Arsizio Varese 21052",
    "addr:postcode":"21052;21052",
    "addr:street":"Via Milazzo",
    "iso:country":"IT",
    "sg:address":"34, Via Milazzo 21052 Busto Arsizio",
    "sg:city":"Busto Arsizio",
    "sg:classifiers":[
        {
            "category":"Professional",
            "subcategory":"Business Services",
            "type":"Services"
        }
    ],
    "sg:phone":"+39 0331 679787",
    "sg:postcode":"21052",
    "sg:province":"Varese",
    "sg:tags":[
        "advice"
    ],
    "wof:name":"Adage (s.r.l.)",
    "wof:placetype":"venue"
},
  "geometry": {"coordinates":[8.857169,45.601624],"type":"Point"}
}