{
  "type": "Feature",
  "properties": {
    "addr:full":"Via Cavour 40; Casalmaggiore; 26041 Casalmaggiore Cremona 26041",
    "addr:housenumber":"40",
    "addr:postcode":"26041;26041",
    "addr:street":"Via Cavour",
    "iso:country":"IT",
    "sg:address":"Via Cavour 40; Casalmaggiore; 26041",
    "sg:city":"Casalmaggiore",
    "sg:classifiers":[
        {
            "category":"Banks & Credit Unions",
            "subcategory":"Bank",
            "type":"Services"
        }
    ],
    "sg:phone":"+39 0375 40521",
    "sg:postcode":"26041",
    "sg:province":"Cremona",
    "wof:name":"Credito Commerciale",
    "wof:placetype":"venue"
},
  "geometry": {"coordinates":[10.417533,44.987217],"type":"Point"}
}