{
  "type": "Feature",
  "properties": {
    "addr:full":"35019 Tombolo Tombolo Padova 35019",
    "addr:postcode":"35019;35019",
    "iso:country":"IT",
    "sg:address":"35019 Tombolo",
    "sg:city":"Tombolo",
    "sg:orig_category":"Prodotti E Manufatti In Materie Plastiche. Forniture Per Edilizia E Lavori Pubblici. Forniture E Materiali Per Imballaggio E Confezionamento",
    "sg:phone":"+39 049 947 1292",
    "sg:postcode":"35019",
    "sg:province":"Padova",
    "wof:name":"Zulian Giorgio",
    "wof:placetype":"venue"
},
  "geometry": {"coordinates":[11.8177776337,45.6370124817],"type":"Point"}
}