{
  "type": "Feature",
  "properties": {
    "addr:full":"Km. 18, V. Appia Sud Str. St. 7/bis 80029 Sant'antimo Napoli 80029",
    "addr:housenumber":"7 / bis",
    "addr:postcode":"80029;80029",
    "addr:street":"Km. 18 V. Appia Sud Str. St.",
    "iso:country":"IT",
    "sg:address":"Km. 18, V. Appia Sud Str. St. 7/bis 80029 Sant'antimo",
    "sg:classifiers":[
        {
            "category":"Farming",
            "subcategory":"Livestock Farm",
            "type":"Manufacturing & Wholesale Goods"
        }
    ],
    "sg:phone":"+39 081 505 9392",
    "sg:postcode":"80029",
    "sg:province":"Napoli",
    "sg:tags":[
        "agriculture"
    ],
    "sg:website":"http://www.paginegialle.it/montanaroernesto",
    "wof:name":"Montanaro Ernesto Spa",
    "wof:placetype":"venue"
},
  "geometry": {"coordinates":[14.251636,40.840096],"type":"Point"}
}