{
  "type": "Feature",
  "properties": {
    "addr:full":"Via S. Vitalino, 19 - Lippo 40012 Calderara Di Reno Calderara di Reno Bologna 40012",
    "addr:housenumber":"19",
    "addr:postcode":"40012;40012",
    "addr:street":"Via S. Vitalino",
    "iso:country":"IT",
    "sg:address":"Via S. Vitalino, 19 - Lippo 40012 Calderara Di Reno",
    "sg:city":"Calderara di Reno",
    "sg:classifiers":[
        {
            "category":"Home & Garden",
            "subcategory":"Household Appliances",
            "type":"Retail Goods"
        }
    ],
    "sg:phone":"+39 051 726553",
    "sg:postcode":"40012",
    "sg:province":"Bologna",
    "sg:tags":[
        "implement",
        "gardening",
        "tool"
    ],
    "wof:name":"Motori Minarelli Spa",
    "wof:placetype":"venue"
},
  "geometry": {"coordinates":[11.304271,44.551262],"type":"Point"}
}