{
  "type": "Feature",
  "properties": {
    "iso:country":"IT",
    "sg:address":"21026 Gavirate",
    "sg:city":"Gavirate",
    "sg:classifiers":[
        {
            "category":"Manufacturing",
            "subcategory":"Wood Products",
            "type":"Manufacturing & Wholesale Goods"
        }
    ],
    "sg:phone":"+39 0332 743454",
    "sg:postcode":"21026",
    "sg:province":"Varese",
    "sg:tags":[
        "semi-finished"
    ],
    "wof:name":"Fratelli Rovera Massimo & Maurizio Snc",
    "wof:placetype":"venue"
},
  "geometry": {"coordinates":[8.739281,45.832336],"type":"Point"}
}