{
  "type": "Feature",
  "properties": {
    "iso:country":"IT",
    "sg:address":"31, Viale S. Eufemia 25135 Brescia",
    "sg:city":"Brescia",
    "sg:classifiers":[
        {
            "category":"Home & Garden",
            "subcategory":"Home Furnishings",
            "type":"Retail Goods"
        }
    ],
    "sg:phone":"+39 39030360283",
    "sg:postcode":"25135",
    "sg:province":"Brescia",
    "sg:tags":[
        "household"
    ],
    "wof:name":"Silini Srl",
    "wof:placetype":"venue"
},
  "geometry": {"coordinates":[10.280519,45.49324],"type":"Point"}
}