{
  "type": "Feature",
  "properties": {
    "addr:full":"70033 Corato Corato Bari 70033",
    "addr:postcode":"70033;70033",
    "iso:country":"IT",
    "sg:address":"70033 Corato",
    "sg:city":"Corato",
    "sg:orig_category":"Abiti Da Sposa E Cerimonia",
    "sg:phone":"+39 080 898 5521",
    "sg:postcode":"70033",
    "sg:province":"Bari",
    "wof:name":"Campana Riccardo",
    "wof:placetype":"venue"
},
  "geometry": {"coordinates":[16.412176,41.14513],"type":"Point"}
}