{
  "type": "Feature",
  "properties": {
    "addr:full":"Via G. Marconi 35 26034 Piadena Piadena Cremona 26034",
    "addr:housenumber":"35",
    "addr:postcode":"26034;26034",
    "addr:street":"Via G. Marconi",
    "iso:country":"IT",
    "sg:address":"Via G. Marconi 35 26034 Piadena",
    "sg:city":"Piadena",
    "sg:classifiers":[
        {
            "category":"Restaurant",
            "type":"Food & Drink"
        }
    ],
    "sg:phone":"+39 0375 98220",
    "sg:postcode":"26034",
    "sg:province":"Cremona",
    "sg:tags":[
        "pasta"
    ],
    "sg:website":"www.pastanosari.it",
    "wof:name":"Pasta Nosari Srl",
    "wof:placetype":"venue"
},
  "geometry": {"coordinates":[10.0261354446,45.1334991455],"type":"Point"}
}