{
  "type": "Feature",
  "properties": {
    "addr:full":"40057 Granarolo Dell'emilia Bologna 40057",
    "addr:postcode":"40057;40057",
    "iso:country":"IT",
    "sg:address":"40057 Granarolo Dell'emilia",
    "sg:orig_category":"Macchine Utensili E Impianti",
    "sg:phone":"+39 051 761480",
    "sg:postcode":"40057",
    "sg:province":"Bologna",
    "wof:name":"Pigreco Progettazioni Meccaniche Srl",
    "wof:placetype":"venue"
},
  "geometry": {"coordinates":[11.447671,44.552177],"type":"Point"}
}