{
  "type": "Feature",
  "properties": {
    "addr:full":"80014 Giugliano In Campania Giugliano in Campania Napoli 80014",
    "addr:postcode":"80014;80014",
    "iso:country":"IT",
    "sg:address":"80014 Giugliano In Campania",
    "sg:city":"Giugliano in Campania",
    "sg:orig_category":"Filtri Acqua",
    "sg:phone":"+39 081 818 6758",
    "sg:postcode":"80014",
    "sg:province":"Napoli",
    "wof:name":"Di.ma. Piscine",
    "wof:placetype":"venue"
},
  "geometry": {"coordinates":[14.1434659958,40.931224823],"type":"Point"}
}