{
  "type": "Feature",
  "properties": {
    "addr:full":"10154 Torino Torino Torino 10154",
    "addr:postcode":"10154;10154",
    "iso:country":"IT",
    "sg:address":"10154 Torino",
    "sg:city":"Torino",
    "sg:orig_category":"Fissaggio Articoli",
    "sg:phone":"+39 011 285361",
    "sg:postcode":"10154",
    "sg:province":"Torino",
    "wof:name":"Stop Block Di Casamassima G.",
    "wof:placetype":"venue"
},
  "geometry": {"coordinates":[7.7494606972,45.0921707153],"type":"Point"}
}