{
  "type": "Feature",
  "properties": {
    "addr:full":"Strada Statale N. 11 24040 Isso Isso Bergamo 24040",
    "addr:housenumber":"11",
    "addr:postcode":"24040;24040",
    "addr:street":"Strada Statale N.",
    "iso:country":"IT",
    "sg:address":"Strada Statale N. 11 24040 Isso",
    "sg:city":"Isso",
    "sg:classifiers":[
        {
            "category":"Wholesale",
            "subcategory":"Drugs",
            "type":"Manufacturing & Wholesale Goods"
        }
    ],
    "sg:phone":"+39 036 399 8902",
    "sg:postcode":"24040",
    "sg:province":"Bergamo",
    "sg:tags":[
        "chemical",
        "pharmaceutical"
    ],
    "wof:name":"Archimica S.p.a.",
    "wof:placetype":"venue"
},
  "geometry": {"coordinates":[9.669952,45.694904],"type":"Point"}
}