{
  "type": "Feature",
  "properties": {
    "iso:country":"IT",
    "sg:address":"20123 Milano",
    "sg:city":"Milano",
    "sg:orig_category":"Forniture Per Abbigliamento E Pelletterie. Forniture Per Attivita' Commerciali Ed Artigianali",
    "sg:phone":"+39 02 835 8458",
    "sg:postcode":"20123",
    "sg:province":"Milano",
    "wof:name":"Po.sa. Di Porro Umberto",
    "wof:placetype":"venue"
},
  "geometry": {"coordinates":[9.1719341278,45.4582138062],"type":"Point"}
}