{
  "type": "Feature",
  "properties": {
    "addr:full":"40123 Bologna Bologna Bologna 40123",
    "addr:postcode":"40123;40123",
    "iso:country":"IT",
    "sg:address":"40123 Bologna",
    "sg:city":"Bologna",
    "sg:orig_category":"Abbigliamento Esterno, Maglierie E Pelliccerie. Shopping",
    "sg:phone":"+39 051 333150",
    "sg:postcode":"40123",
    "sg:province":"Bologna",
    "wof:name":"Serge Le Pat Snc",
    "wof:placetype":"venue"
},
  "geometry": {"coordinates":[11.334988,44.49165],"type":"Point"}
}