{
  "type": "Feature",
  "properties": {
    "iso:country":"IT",
    "sg:address":"52100 Arezzo",
    "sg:city":"Arezzo",
    "sg:orig_category":"Scuole E Servizi Scolastici. Servizi Ausiliari Dei Mezzi Di Trasporto. Ricerca, Selezione E Formazione Del Personale",
    "sg:phone":"+39 0575 24672",
    "sg:postcode":"52100",
    "sg:province":"Arezzo",
    "wof:name":"Autoscuola Margaritone Snc",
    "wof:placetype":"venue"
},
  "geometry": {"coordinates":[11.879835,43.461037],"type":"Point"}
}