{
  "type": "Feature",
  "properties": {
    "iso:country":"IT",
    "sg:address":"Via Alessandro Farnese 1, 00196 Rome, Rm",
    "sg:classifiers":[
        {
            "category":"Banks & Credit Unions",
            "subcategory":"Bank",
            "type":"Services"
        }
    ],
    "sg:postcode":"00196",
    "sg:province":"Roma",
    "wof:name":"Istituto Per Il Credito Sportivo",
    "wof:placetype":"venue"
},
  "geometry": {"coordinates":[12.468781,41.909023],"type":"Point"}
}