{
  "type": "Feature",
  "properties": {
    "iso:country":"IT",
    "sg:address":"13835 Trivero",
    "sg:city":"Ponzone",
    "sg:orig_category":"Servizi E Lavori Per Abbigliamento E Pelletterie",
    "sg:phone":"+39 015 779390",
    "sg:postcode":"13835",
    "sg:province":"Biella",
    "wof:name":"Rammendo Valentino",
    "wof:placetype":"venue"
},
  "geometry": {"coordinates":[8.135619,45.685669],"type":"Point"}
}