{
  "type": "Feature",
  "properties": {
    "addr:full":"73, Via Quattro Novembre 38030 Rovere' Della Luna Trento 38030",
    "addr:postcode":"38030 rovere;38030",
    "addr:street":"Via Quattro Novembre;' Della Luna",
    "iso:country":"IT",
    "sg:address":"73, Via Quattro Novembre 38030 Rovere' Della Luna",
    "sg:classifiers":[
        {
            "category":"Manufacturing",
            "subcategory":"Lumber",
            "type":"Manufacturing & Wholesale Goods"
        }
    ],
    "sg:phone":"+39 0461 658553",
    "sg:postcode":"38030",
    "sg:province":"Trento",
    "sg:tags":[
        "wood"
    ],
    "wof:name":"Segna Legnami S.n.c.",
    "wof:placetype":"venue"
},
  "geometry": {"coordinates":[11.119053,46.066738],"type":"Point"}
}