{
  "type": "Feature",
  "properties": {
    "iso:country":"IT",
    "sg:address":"20123 Milano",
    "sg:city":"Milano",
    "sg:orig_category":"Bigiotteria - Produzione E Ingrosso",
    "sg:phone":"+39 02 7201 0199",
    "sg:postcode":"20123",
    "sg:province":"Milano",
    "wof:name":"Pellini Srl",
    "wof:placetype":"venue"
},
  "geometry": {"coordinates":[9.180923,45.463356],"type":"Point"}
}