{
  "type": "Feature",
  "properties": {
    "addr:full":"Viale Belforte 199 21100 Varese Varese Varese 21100",
    "addr:housenumber":"199",
    "addr:postcode":"21100;21100",
    "addr:street":"Viale Belforte",
    "iso:country":"IT",
    "sg:address":"Viale Belforte 199 21100 Varese",
    "sg:city":"Varese",
    "sg:classifiers":[
        {
            "category":"Home & Garden",
            "subcategory":"Hardware",
            "type":"Retail Goods"
        }
    ],
    "sg:phone":"+39 0332 333109",
    "sg:postcode":"21100",
    "sg:province":"Varese",
    "sg:tags":[
        "small",
        "ironware",
        "item"
    ],
    "sg:website":"www.castiglionispa.it",
    "wof:name":"Giovanni Castiglioni Spa",
    "wof:placetype":"venue"
},
  "geometry": {"coordinates":[8.847424,45.815987],"type":"Point"}
}