{
  "type": "Feature",
  "properties": {
    "iso:country":"IT",
    "sg:address":"10022 Carmagnola",
    "sg:city":"Carmagnola",
    "sg:orig_category":"Forniture Per Agricoltura E Zootecnia. Prodotti Chimici Secondari",
    "sg:phone":"+39 011 977 3053",
    "sg:postcode":"10022",
    "sg:province":"Torino",
    "wof:name":"Mosso Rubinetto Maria",
    "wof:placetype":"venue"
},
  "geometry": {"coordinates":[7.7166419029,44.845741272],"type":"Point"}
}