{
  "type": "Feature",
  "properties": {
    "iso:country":"IT",
    "sg:address":"883/a, Via Cappuccini 45021 Badia Polesine",
    "sg:city":"Badia Polesine",
    "sg:classifiers":[
        {
            "category":"Manufacturing",
            "subcategory":"Rubber & Plastics",
            "type":"Manufacturing & Wholesale Goods"
        }
    ],
    "sg:phone":"+39 39042551417",
    "sg:postcode":"45021",
    "sg:province":"Rovigo",
    "wof:name":"Montini",
    "wof:placetype":"venue"
},
  "geometry": {"coordinates":[11.7897968292,45.0707359314],"type":"Point"}
}