{
  "type": "Feature",
  "properties": {
    "addr:full":"00146 Roma Roma Roma 00146",
    "addr:postcode":"00146;00146",
    "iso:country":"IT",
    "sg:address":"00146 Roma",
    "sg:city":"Roma",
    "sg:orig_category":"Prodotti E Manufatti In Gomma. Servizi E Lavori Industria Della Gomma. Ricambi E Componenti Dei Mezzi Di Trasporto. Riparazione Dei Mezzi Di Trasporto",
    "sg:phone":"+39 06 557 2394",
    "sg:postcode":"00146",
    "sg:province":"Roma",
    "sg:website":"http://www.piergentilityre.it",
    "wof:name":"Piergentili Tyre 2000 Srl",
    "wof:placetype":"venue"
},
  "geometry": {"coordinates":[12.469587326,41.8581047058],"type":"Point"}
}