{
  "type": "Feature",
  "properties": {
    "iso:country":"IT",
    "sg:address":"47039 Savignano Sul Rubicone",
    "sg:city":"Savignano sul Rubicone",
    "sg:orig_category":"Autofficine, Gommisti E Autolavaggi - Attrezzature",
    "sg:phone":"+39 0541 944752",
    "sg:postcode":"47039",
    "sg:province":"Forl\u00ec-Cesena",
    "wof:name":"Zammarchi Spa",
    "wof:placetype":"venue"
},
  "geometry": {"coordinates":[12.374441,44.091255],"type":"Point"}
}