{
  "type": "Feature",
  "properties": {
    "iso:country":"IT",
    "sg:address":"50123 Firenze",
    "sg:city":"Firenze",
    "sg:orig_category":"Abbigliamento Esterno, Maglierie E Pelliccerie. Shopping",
    "sg:phone":"+39 055 293041",
    "sg:postcode":"50123",
    "sg:province":"Firenze",
    "wof:name":"Replay",
    "wof:placetype":"venue"
},
  "geometry": {"coordinates":[11.253628,43.772743],"type":"Point"}
}