{
  "type": "Feature",
  "properties": {
    "iso:country":"IT",
    "sg:address":"00187 Roma",
    "sg:city":"Roma",
    "sg:orig_category":"Servizi Editoriali. Servizi Per Aziende, Manifestazioni E Supporto Agli Scambi Commerciali",
    "sg:phone":"+39 0667741",
    "sg:postcode":"00187",
    "sg:province":"Roma",
    "wof:name":"Agenzia Stampa Agenzia Nazionale Stampa Associata",
    "wof:placetype":"venue"
},
  "geometry": {"coordinates":[12.484715,41.899952],"type":"Point"}
}