{
  "type": "Feature",
  "properties": {
    "iso:country":"IT",
    "sg:address":"16, Via Favara 96016 Lentini",
    "sg:city":"Lentini",
    "sg:classifiers":[
        {
            "category":"Farming",
            "subcategory":"Livestock Farm",
            "type":"Manufacturing & Wholesale Goods"
        }
    ],
    "sg:phone":"+39 39095905308",
    "sg:postcode":"96016",
    "sg:province":"Siracusa",
    "sg:tags":[
        "agriculture"
    ],
    "wof:name":"Blanco Alfio",
    "wof:placetype":"venue"
},
  "geometry": {"coordinates":[14.995445,37.301029],"type":"Point"}
}