{
  "type": "Feature",
  "properties": {
    "iso:country":"IT",
    "sg:address":"90, V. Don Bosco 62010 Montecosaro",
    "sg:city":"Montecosaro",
    "sg:classifiers":[
        {
            "category":"Banks & Credit Unions",
            "subcategory":"Investment Brokerage",
            "type":"Services"
        }
    ],
    "sg:phone":"+39 0733 564828",
    "sg:postcode":"62010",
    "sg:province":"Macerata",
    "sg:tags":[
        "-",
        "transport",
        "related"
    ],
    "sg:website":"http://www.paginegialle.it/autotrasportirenzi",
    "wof:name":"Autotrasporti Renzi",
    "wof:placetype":"venue"
},
  "geometry": {"coordinates":[13.652304,43.282898],"type":"Point"}
}