{
  "type": "Feature",
  "properties": {
    "iso:country":"IT",
    "sg:address":"00174 Roma",
    "sg:city":"Roma",
    "sg:orig_category":"Impiantistica E Prodotti Tecnologici Per Edilizia. Termotecnica E Riscaldamento, Apparecchiature E Servizi",
    "sg:phone":"+39 06 714 0114",
    "sg:postcode":"00174",
    "sg:province":"Roma",
    "wof:name":"De Pascoli Vincenzo & C. S.n.c",
    "wof:placetype":"venue"
},
  "geometry": {"coordinates":[12.553553,41.860886],"type":"Point"}
}