{
  "type": "Feature",
  "properties": {
    "iso:country":"IT",
    "sg:address":"10090 Rosta",
    "sg:city":"Rosta",
    "sg:orig_category":"Petroli, Gas E Combustibili",
    "sg:phone":"+39 011 956 7900",
    "sg:postcode":"10090",
    "sg:province":"Torino",
    "wof:name":"Lipitalia 2000 Spa",
    "wof:placetype":"venue"
},
  "geometry": {"coordinates":[7.4662590027,45.0689086914],"type":"Point"}
}