{
  "type": "Feature",
  "properties": {
    "addr:full":"11, Via Gavirate 20148 Milano Milano Milano 20148",
    "addr:postcode":"20148;20148",
    "addr:street":"Via Gavirate",
    "iso:country":"IT",
    "sg:address":"11, Via Gavirate 20148 Milano",
    "sg:city":"Milano",
    "sg:classifiers":[
        {
            "category":"Communications",
            "subcategory":"Newspaper",
            "type":"Services"
        }
    ],
    "sg:phone":"+39 39024041626",
    "sg:postcode":"20148",
    "sg:province":"Milano",
    "sg:tags":[
        "advertising"
    ],
    "wof:name":"Matt Promotion Di Roberto Gatti",
    "wof:placetype":"venue"
},
  "geometry": {"coordinates":[9.141633,45.47821],"type":"Point"}
}