{
  "type": "Feature",
  "properties": {
    "iso:country":"IT",
    "sg:address":"26845 Codogno",
    "sg:city":"Codogno",
    "sg:classifiers":[
        {
            "category":"Professional",
            "subcategory":"Business Services",
            "type":"Services"
        }
    ],
    "sg:phone":"+39 0377 435019",
    "sg:postcode":"26845",
    "sg:province":"Lodi",
    "sg:tags":[
        "support",
        "companies",
        "events",
        "trade"
    ],
    "sg:website":"http://www.prismatetrart.it",
    "wof:name":"Prisma Srl",
    "wof:placetype":"venue"
},
  "geometry": {"coordinates":[9.67469,45.1544],"type":"Point"}
}