{
  "type": "Feature",
  "properties": {
    "addr:full":"51, Via Volvera 10045 Piossasco Piossasco Torino 10045",
    "addr:postcode":"10045;10045",
    "addr:street":"Via Volvera",
    "iso:country":"IT",
    "sg:address":"51, Via Volvera 10045 Piossasco",
    "sg:city":"Piossasco",
    "sg:classifiers":[
        {
            "category":"Manufacturing",
            "subcategory":"Motor Vehicles & Parts",
            "type":"Manufacturing & Wholesale Goods"
        }
    ],
    "sg:phone":"+39 390 119 0441",
    "sg:postcode":"10045",
    "sg:province":"Torino",
    "sg:tags":[
        "engine"
    ],
    "wof:name":"Sab Wabco",
    "wof:placetype":"venue"
},
  "geometry": {"coordinates":[7.477654,44.975693],"type":"Point"}
}