{
  "type": "Feature",
  "properties": {
    "iso:country":"IT",
    "sg:address":"25064 Gussago",
    "sg:city":"Gussago",
    "sg:orig_category":"Bevande, Vini E Liquori. Servizi E Lavori Per Industria Alimentare E Bevande",
    "sg:phone":"+39 030 277 0640",
    "sg:postcode":"25064",
    "sg:province":"Brescia",
    "wof:name":"Peroni Maddalena",
    "wof:placetype":"venue"
},
  "geometry": {"coordinates":[10.161293,45.583023],"type":"Point"}
}