{
  "type": "Feature",
  "properties": {
    "iso:country":"IT",
    "sg:address":"38066 Riva Del Garda",
    "sg:city":"Riva del Garda",
    "sg:orig_category":"Servizi E Lavori Per Edilizia E Lavori Pubblici. Consulenze Tecniche, Amministrative E Perizie",
    "sg:phone":"+39 0464 557444",
    "sg:postcode":"38066",
    "sg:province":"Trento",
    "sg:website":"http://www.rivadelgarda.com/gardadomus",
    "wof:name":"Agenzia Garda Domus",
    "wof:placetype":"venue"
},
  "geometry": {"coordinates":[10.880648,45.915699],"type":"Point"}
}