{
  "type": "Feature",
  "properties": {
    "iso:country":"IT",
    "sg:address":"20094 Corsico",
    "sg:city":"Corsico",
    "sg:orig_category":"Bagno - Accessori E Mobili",
    "sg:phone":"+39 02 4586 9781",
    "sg:postcode":"20094",
    "sg:province":"Milano",
    "wof:name":"Idrotermoarredo Snc",
    "wof:placetype":"venue"
},
  "geometry": {"coordinates":[9.084466,45.430813],"type":"Point"}
}