{
  "type": "Feature",
  "properties": {
    "addr:full":"06074 Perugia PG",
    "addr:postcode":"06074",
    "addr:street":"Pg",
    "iso:country":"IT",
    "sg:address":"06074 Perugia",
    "sg:classifiers":[
        {
            "category":"Personal",
            "subcategory":"Beauty Salon",
            "type":"Services"
        }
    ],
    "sg:phone":"+39 075 527 2090",
    "sg:province":"PG",
    "sg:tags":[
        "salons",
        "activities",
        "commercial",
        "equipment",
        "artisan",
        "supplies",
        "professional",
        "furniture",
        "furnishing"
    ],
    "wof:name":"Settonce Nello Arredamenti Sas",
    "wof:placetype":"venue"
},
  "geometry": {"coordinates":[-72.57963562010001,41.8445320129],"type":"Point"}
}