{
  "type": "Feature",
  "properties": {
    "iso:country":"IT",
    "sg:address":"4/d, Via Manifattura 50058 Signa",
    "sg:city":"Signa",
    "sg:classifiers":[
        {
            "category":"Shopping",
            "subcategory":"Clothing, Apparel, & Fashions",
            "type":"Retail Goods"
        }
    ],
    "sg:phone":"+39 055 873 4081",
    "sg:postcode":"50058",
    "sg:province":"Firenze",
    "sg:tags":[
        "clothing",
        "accessory"
    ],
    "wof:name":"Grevi Mode Sas Di Giuseppe Grevi & C.",
    "wof:placetype":"venue"
},
  "geometry": {"coordinates":[11.256902,43.768734],"type":"Point"}
}