{
  "type": "Feature",
  "properties": {
    "addr:full":"1, Via Comugne 33058 San Giorgio Di Nogaro San Giorgio di Nogaro Udine 33058",
    "addr:postcode":"33058;33058",
    "addr:street":"Via Comugne",
    "iso:country":"IT",
    "sg:address":"1, Via Comugne 33058 San Giorgio Di Nogaro",
    "sg:city":"San Giorgio di Nogaro",
    "sg:classifiers":[
        {
            "category":"Shopping",
            "type":"Retail Goods"
        }
    ],
    "sg:phone":"+39 39043165486",
    "sg:postcode":"33058",
    "sg:province":"Udine",
    "sg:tags":[
        "finished",
        "-",
        "metallic"
    ],
    "wof:name":"Officina Zanon Di Gianni E Barbara Zanon S.n.c.",
    "wof:placetype":"venue"
},
  "geometry": {"coordinates":[13.2307243347,46.0649414062],"type":"Point"}
}