{
  "type": "Feature",
  "properties": {
    "iso:country":"IT",
    "sg:address":"52037 Sansepolcro",
    "sg:city":"Sansepolcro",
    "sg:orig_category":"Universita' Ed Istituti Superiori E Liberi",
    "sg:phone":"+39 0575 7381",
    "sg:postcode":"52037",
    "sg:province":"Arezzo",
    "sg:website":"http://www.cepu.it",
    "wof:name":"Cepu Srl",
    "wof:placetype":"venue"
},
  "geometry": {"coordinates":[12.082436,43.493744],"type":"Point"}
}