{
  "type": "Feature",
  "properties": {
    "iso:country":"IT",
    "sg:address":"7/a, Via Lungargine Brenta 35010 Vigodarzere",
    "sg:city":"Vigodarzere",
    "sg:classifiers":[
        {
            "category":"Manufacturing",
            "subcategory":"Tools & Machinery",
            "type":"Manufacturing & Wholesale Goods"
        }
    ],
    "sg:phone":"+39 39049700428",
    "sg:postcode":"35010",
    "sg:province":"Padova",
    "sg:tags":[
        "environment",
        "equipment",
        "-"
    ],
    "wof:name":"Aircontrol Di Zatta Valentino & C. S.n.c.",
    "wof:placetype":"venue"
},
  "geometry": {"coordinates":[11.878875,45.45451],"type":"Point"}
}