{
  "type": "Feature",
  "properties": {
    "iso:country":"IT",
    "sg:address":"00151 Roma",
    "sg:city":"Roma",
    "sg:orig_category":"Servizi E Lavori Per Edilizia E Lavori Pubblici. Servizi E Lavori Per Ecologia E Smaltimento Rifiuti. Macchine E Forniture Per Ecologia E Smaltimento Rifiuti. Acqua, Luce, Gas E Societa' Di Esercizio ",
    "sg:phone":"+39 06 653 8972",
    "sg:postcode":"00151",
    "sg:province":"Roma",
    "wof:name":"S.t.i.a.m.s. S.r.l.",
    "wof:placetype":"venue"
},
  "geometry": {"coordinates":[12.438348,41.857262],"type":"Point"}
}