{
  "type": "Feature",
  "properties": {
    "iso:country":"IT",
    "sg:address":"13852 Cerreto Castello",
    "sg:city":"Cerreto Castello",
    "sg:orig_category":"Servizi E Lavori Per Arredamento E Industria Del Legno. Servizi E Lavori Per Edilizia E Lavori Pubblici",
    "sg:phone":"+39 015 882270",
    "sg:postcode":"13852",
    "sg:province":"Biella",
    "wof:name":"Bernardi Ciano Srl",
    "wof:placetype":"venue"
},
  "geometry": {"coordinates":[8.129254,45.563591],"type":"Point"}
}