{
  "type": "Feature",
  "properties": {
    "iso:country":"IT",
    "sg:address":"7, Via Adamello 28066 Galliate",
    "sg:city":"Galliate",
    "sg:classifiers":[
        {
            "category":"Manufacturing",
            "subcategory":"Metals",
            "type":"Manufacturing & Wholesale Goods"
        }
    ],
    "sg:phone":"+39 0321 806160",
    "sg:postcode":"28066",
    "sg:province":"Novara",
    "sg:tags":[
        "metallurgy",
        "metalworking"
    ],
    "wof:name":"Commerciale Alfa (s.p.a.)",
    "wof:placetype":"venue"
},
  "geometry": {"coordinates":[8.6976232529,45.4849739075],"type":"Point"}
}