{
  "type": "Feature",
  "properties": {
    "addr:full":"803, V. Appia Nuova 00178 Roma Roma Roma 00178",
    "addr:housenumber":"803",
    "addr:postcode":"00178;00178",
    "addr:street":"V. Appia Nuova",
    "iso:country":"IT",
    "sg:address":"803, V. Appia Nuova 00178 Roma",
    "sg:city":"Roma",
    "sg:classifiers":[
        {
            "category":"Autos & Motor Vehicles",
            "subcategory":"Automobile Sales",
            "type":"Retail Goods"
        }
    ],
    "sg:phone":"+39 390 678 4611",
    "sg:postcode":"00178",
    "sg:province":"Roma",
    "sg:tags":[
        "motor-cars"
    ],
    "sg:website":"http://www.autocentribalduina.it",
    "wof:name":"Autocentri Balduina",
    "wof:placetype":"venue"
},
  "geometry": {"coordinates":[12.5435295105,41.8538970947],"type":"Point"}
}