{
  "type": "Feature",
  "properties": {
    "addr:full":"24121 Bergamo Bergamo Bergamo 24121",
    "addr:postcode":"24121;24121",
    "iso:country":"IT",
    "sg:address":"24121 Bergamo",
    "sg:city":"Bergamo",
    "sg:orig_category":"Elaborazione Dati - Servizio Conto Terzi",
    "sg:phone":"+39 035 217453",
    "sg:postcode":"24121",
    "sg:province":"Bergamo",
    "wof:name":"Ice Srl",
    "wof:placetype":"venue"
},
  "geometry": {"coordinates":[9.669227,45.698311],"type":"Point"}
}