{
  "type": "Feature",
  "properties": {
    "addr:full":"4495, Via Metaponto 74100 Taranto Taranto Taranto 74100",
    "addr:housenumber":"4495",
    "addr:postcode":"74100;74100",
    "addr:street":"Via Metaponto",
    "iso:country":"IT",
    "sg:address":"4495, Via Metaponto 74100 Taranto",
    "sg:city":"Taranto",
    "sg:classifiers":[
        {
            "category":"Manufacturing",
            "subcategory":"Metals",
            "type":"Manufacturing & Wholesale Goods"
        }
    ],
    "sg:phone":"+39 099 475 2509",
    "sg:postcode":"74100",
    "sg:province":"Taranto",
    "sg:tags":[
        "processing"
    ],
    "wof:name":"Welding S.r.l.",
    "wof:placetype":"venue"
},
  "geometry": {"coordinates":[17.2346668243,40.4749984741],"type":"Point"}
}