{
  "type": "Feature",
  "properties": {
    "addr:full":"82, Regione Case Sparse 14034 Castello Di Annone Castello di Annone Asti 14034",
    "addr:housenumber":"82",
    "addr:postcode":"14034;14034",
    "addr:street":"Regione Case Sparse",
    "iso:country":"IT",
    "sg:address":"82, Regione Case Sparse 14034 Castello Di Annone",
    "sg:city":"Castello di Annone",
    "sg:classifiers":[
        {
            "category":"Autos & Motor Vehicles",
            "subcategory":"Automobile Sales",
            "type":"Retail Goods"
        }
    ],
    "sg:phone":"+39 0141 401766",
    "sg:postcode":"14034",
    "sg:province":"Asti",
    "sg:tags":[
        "industrial"
    ],
    "wof:name":"F.a.d. S.p.a.",
    "wof:placetype":"venue"
},
  "geometry": {"coordinates":[8.263794,44.879395],"type":"Point"}
}