{
  "type": "Feature",
  "properties": {
    "addr:full":"00128 Roma Roma Roma 00128",
    "addr:postcode":"00128;00128",
    "iso:country":"IT",
    "sg:address":"00128 Roma",
    "sg:city":"Roma",
    "sg:classifiers":[
        {
            "category":"Health Services",
            "subcategory":"Health Practitioner",
            "type":"Services"
        }
    ],
    "sg:phone":"+39 06 506 0619",
    "sg:postcode":"00128",
    "sg:province":"Roma",
    "sg:tags":[
        "medici"
    ],
    "wof:name":"Arnaboldi Lorenza",
    "wof:placetype":"venue"
},
  "geometry": {"coordinates":[12.477912,41.773289],"type":"Point"}
}