{
  "type": "Feature",
  "properties": {
    "iso:country":"IT",
    "sg:address":"Corso Bucci 3; Campobasso; 86100",
    "sg:city":"Campobasso",
    "sg:classifiers":[
        {
            "category":"Banks & Credit Unions",
            "subcategory":"Bank",
            "type":"Services"
        }
    ],
    "sg:phone":"+39 0874 4251",
    "sg:postcode":"86100",
    "sg:province":"Campobasso",
    "wof:name":"Banco Di Napoli Spa",
    "wof:placetype":"venue"
},
  "geometry": {"coordinates":[14.660398,41.55954],"type":"Point"}
}