{
  "type": "Feature",
  "properties": {
    "iso:country":"IT",
    "sg:address":"18, Via Arnaldo Fraccaroli 28831 Baveno",
    "sg:city":"Baveno",
    "sg:classifiers":[
        {
            "category":"Manufacturing",
            "subcategory":"Wood Products",
            "type":"Manufacturing & Wholesale Goods"
        }
    ],
    "sg:phone":"+39 0323 923482",
    "sg:postcode":"28831",
    "sg:province":"Verbano-Cusio-Ossola",
    "sg:tags":[
        "furniture"
    ],
    "wof:name":"Ragazzi",
    "wof:placetype":"venue"
},
  "geometry": {"coordinates":[8.493151,45.907097],"type":"Point"}
}