{
  "type": "Feature",
  "properties": {
    "addr:full":"51036 Larciano Larciano Pistoia 51036",
    "addr:postcode":"51036;51036",
    "iso:country":"IT",
    "sg:address":"51036 Larciano",
    "sg:city":"Larciano",
    "sg:orig_category":"Macchine Agricole - Commercio E Riparazione",
    "sg:phone":"+39 0573 849150",
    "sg:postcode":"51036",
    "sg:province":"Pistoia",
    "wof:name":"Carli Snc Di Carli Giuseppe & C.",
    "wof:placetype":"venue"
},
  "geometry": {"coordinates":[10.917109,43.92445],"type":"Point"}
}