{
  "type": "Feature",
  "properties": {
    "addr:full":"29100 Piacenza Piacenza Piacenza 29100",
    "addr:postcode":"29100;29100",
    "iso:country":"IT",
    "sg:address":"29100 Piacenza",
    "sg:city":"Piacenza",
    "sg:orig_category":"Prodotti E Manufatti In Gomma",
    "sg:phone":"+39 0523 606628",
    "sg:postcode":"29100",
    "sg:province":"Piacenza",
    "wof:name":"C.m.f. Piu' Nuova Tecno Piacenza Srl",
    "wof:placetype":"venue"
},
  "geometry": {"coordinates":[9.7545871735,45.040397644],"type":"Point"}
}