{
  "type": "Feature",
  "properties": {
    "addr:full":"1139, Via Emilia Est 41100 Modena Modena Modena 41100",
    "addr:housenumber":"1139",
    "addr:postcode":"41100;41100",
    "addr:street":"Via Emilia Est",
    "iso:country":"IT",
    "sg:address":"1139, Via Emilia Est 41100 Modena",
    "sg:city":"Modena",
    "sg:classifiers":[
        {
            "category":"Manufacturing",
            "subcategory":"Metals",
            "type":"Manufacturing & Wholesale Goods"
        }
    ],
    "sg:phone":"+39 39059362012",
    "sg:postcode":"41100",
    "sg:province":"Modena",
    "sg:tags":[
        "processing"
    ],
    "wof:name":"Carrara S.r.l.",
    "wof:placetype":"venue"
},
  "geometry": {"coordinates":[10.9365940094,44.6419792175],"type":"Point"}
}