{
  "type": "Feature",
  "properties": {
    "iso:country":"IT",
    "sg:address":"24, Via A. Avogadro 62010 Montelupone",
    "sg:city":"Montelupone",
    "sg:classifiers":[
        {
            "category":"Professional",
            "subcategory":"Engineering",
            "type":"Services"
        }
    ],
    "sg:phone":"+39 0733 228339",
    "sg:postcode":"62010",
    "sg:province":"Macerata",
    "sg:tags":[
        "machine",
        "-",
        "mechanical"
    ],
    "wof:name":"S.g.a. Assemblaggi Di Lioi Salvatore",
    "wof:placetype":"venue"
},
  "geometry": {"coordinates":[13.456262,43.300747],"type":"Point"}
}