{
  "type": "Feature",
  "properties": {
    "addr:full":"Via Lodovico Borsari 33/a 43100 Parma Parma Parma 43100",
    "addr:housenumber":"33 / a",
    "addr:postcode":"43100;43100",
    "addr:street":"Via Lodovico Borsari",
    "iso:country":"IT",
    "sg:address":"Via Lodovico Borsari 33/a 43100 Parma",
    "sg:city":"Parma",
    "sg:classifiers":[
        {
            "category":"Bus Stop",
            "subcategory":"None",
            "type":"Transportation"
        }
    ],
    "sg:phone":"+39 0521 909711",
    "sg:postcode":"43100",
    "sg:province":"Parma",
    "sg:tags":[
        "trucks",
        "buses",
        "cars",
        "system",
        "driver's",
        "air-conditioning",
        "cab",
        "crane"
    ],
    "wof:name":"Skg Italia Spa",
    "wof:placetype":"venue"
},
  "geometry": {"coordinates":[10.29492,44.823208],"type":"Point"}
}