{
  "type": "Feature",
  "properties": {
    "iso:country":"IT",
    "sg:address":"65126 Pescara",
    "sg:city":"Pescara",
    "sg:orig_category":"Climatizzazione E Condizionamento, Apparecchiature E Servizi. Elettrodomestici",
    "sg:phone":"+39 085 60233",
    "sg:postcode":"65126",
    "sg:province":"Pescara",
    "wof:name":"Mec. Terni",
    "wof:placetype":"venue"
},
  "geometry": {"coordinates":[14.22506,42.461456],"type":"Point"}
}