{
  "type": "Feature",
  "properties": {
    "iso:country":"IT",
    "sg:address":"43011 Busseto",
    "sg:city":"Busseto",
    "sg:orig_category":"Macchine, Impianti Ed Attrezzature Industria Chimica. Macchine Ed Impianti Per Edilizia E Lavori Pubblici",
    "sg:phone":"+39 0524 91844",
    "sg:postcode":"43011",
    "sg:province":"Parma",
    "sg:website":"http://www.laurini.com",
    "wof:name":"Laurini Lodovico & C. Snc",
    "wof:placetype":"venue"
},
  "geometry": {"coordinates":[10.050493,44.959732],"type":"Point"}
}