{
  "type": "Feature",
  "properties": {
    "addr:full":"38100 Roncafort Trento 38100",
    "addr:postcode":"38100;38100",
    "addr:street":"Roncafort Trento",
    "iso:country":"IT",
    "sg:address":"38100 Roncafort",
    "sg:orig_category":"Valvole E Apparecchiature Di Misura. Ricambi E Componenti Dei Mezzi Di Trasporto",
    "sg:phone":"+39 0461 822654",
    "sg:postcode":"38100",
    "sg:province":"Trento",
    "wof:name":"Casa Del Contachilometri",
    "wof:placetype":"venue"
},
  "geometry": {"coordinates":[11.103128,46.099243],"type":"Point"}
}