{
  "type": "Feature",
  "properties": {
    "addr:full":"5, Corso Europa 20020 Lainate Lainate Milano 20020",
    "addr:postcode":"20020;20020",
    "addr:street":"Corso Europa",
    "iso:country":"IT",
    "sg:address":"5, Corso Europa 20020 Lainate",
    "sg:city":"Lainate",
    "sg:classifiers":[
        {
            "category":"Real Estate",
            "subcategory":"Surveying",
            "type":"Services"
        }
    ],
    "sg:phone":"+39 390 293 5761",
    "sg:postcode":"20020",
    "sg:province":"Milano",
    "sg:tags":[
        "equipment",
        "material",
        "good",
        "-",
        "handling"
    ],
    "wof:name":"Still Italia S.p.a.",
    "wof:placetype":"venue"
},
  "geometry": {"coordinates":[9.05262,45.525738],"type":"Point"}
}