{
  "type": "Feature",
  "properties": {
    "iso:country":"IT",
    "sg:address":"Via Del Lavoro 56 20060 Vignate",
    "sg:city":"Vignate",
    "sg:classifiers":[
        {
            "category":"Building & Trades",
            "subcategory":"Landscaping Services",
            "type":"Services"
        }
    ],
    "sg:phone":"+39 02 956 0245",
    "sg:postcode":"20060",
    "sg:province":"Milano",
    "sg:tags":[
        "tool"
    ],
    "sg:website":"www.mabertools.com",
    "wof:name":"Maber Srl",
    "wof:placetype":"venue"
},
  "geometry": {"coordinates":[9.188141,45.463688],"type":"Point"}
}