{
  "type": "Feature",
  "properties": {
    "iso:country":"IT",
    "sg:address":"31, Via Europa Unita 22038 Tavernerio",
    "sg:city":"Tavernerio",
    "sg:classifiers":[
        {
            "category":"Utilities",
            "subcategory":"Telephone",
            "type":"Services"
        }
    ],
    "sg:phone":"+39 39031360444",
    "sg:postcode":"22038",
    "sg:province":"Como",
    "sg:tags":[
        "telecommunication"
    ],
    "wof:name":"Suardi Como (s.r.l.)",
    "wof:placetype":"venue"
},
  "geometry": {"coordinates":[9.135359,45.794182],"type":"Point"}
}