{
  "type": "Feature",
  "properties": {
    "iso:country":"IT",
    "sg:address":"10088 Volpiano",
    "sg:city":"Volpiano",
    "sg:orig_category":"Accoppiatura E Spalmatura",
    "sg:phone":"+39 011 995 3776",
    "sg:postcode":"10088",
    "sg:province":"Torino",
    "wof:name":"Tr.a.e. Spa",
    "wof:placetype":"venue"
},
  "geometry": {"coordinates":[7.6933999062,45.0764961243],"type":"Point"}
}