{
  "type": "Feature",
  "properties": {
    "iso:country":"IT",
    "sg:address":"Via Bosco 25 31028 Vazzola",
    "sg:city":"Vazzola",
    "sg:classifiers":[
        {
            "category":"Coffee & Tea",
            "type":"Food & Drink"
        }
    ],
    "sg:phone":"+39 0438 794103",
    "sg:postcode":"31028",
    "sg:province":"Treviso",
    "sg:tags":[
        "aquavit"
    ],
    "sg:website":"www.acquavite.it",
    "wof:name":"Acquavite Spa",
    "wof:placetype":"venue"
},
  "geometry": {"coordinates":[12.423085,45.847313],"type":"Point"}
}