{
  "type": "Feature",
  "properties": {
    "addr:full":"73048 Nardo' Lecce 73048",
    "addr:postcode":"73048;73048",
    "addr:street":"Nardo ' Lecce",
    "iso:country":"IT",
    "sg:address":"73048 Nardo'",
    "sg:classifiers":[
        {
            "category":"Health Services",
            "subcategory":"Health Practitioner",
            "type":"Services"
        }
    ],
    "sg:phone":"+39 0833 570573",
    "sg:postcode":"73048",
    "sg:province":"Lecce",
    "sg:tags":[
        "medici"
    ],
    "wof:name":"Mellone Giuseppe",
    "wof:placetype":"venue"
},
  "geometry": {"coordinates":[18.027281,40.183998],"type":"Point"}
}