{
  "type": "Feature",
  "properties": {
    "iso:country":"IT",
    "sg:address":"Via Battisti 2 20090 Settala",
    "sg:city":"Settala",
    "sg:orig_category":"Washing Equipment For Small Parts Of Metal",
    "sg:phone":"+39 02 9577 0024",
    "sg:postcode":"20090",
    "sg:province":"Milano",
    "sg:website":"www.ceever.com",
    "wof:name":"Ceever Srl",
    "wof:placetype":"venue"
},
  "geometry": {"coordinates":[9.350938,45.431107],"type":"Point"}
}