{
  "type": "Feature",
  "properties": {
    "iso:country":"IT",
    "sg:address":"73, V. Siepelunga 40141 Bologna",
    "sg:city":"Bologna",
    "sg:classifiers":[
        {
            "category":"Personal",
            "subcategory":"Shoe Repair & Shine",
            "type":"Services"
        }
    ],
    "sg:phone":"+39 051 623 9411",
    "sg:postcode":"40141",
    "sg:province":"Bologna",
    "sg:tags":[
        "leather"
    ],
    "sg:website":"http://www.disandro.it:ws_end: :mark:ws:http://www.paginegialle.it/disandro",
    "wof:name":"Calzaturificio Sandro Magli & C. Sas",
    "wof:placetype":"venue"
},
  "geometry": {"coordinates":[11.362048,44.468876],"type":"Point"}
}