{
  "type": "Feature",
  "properties": {
    "iso:country":"IT",
    "sg:address":"30038 Spinea",
    "sg:city":"Spinea",
    "sg:orig_category":"Antifurto",
    "sg:phone":"+39 041 998800",
    "sg:postcode":"30038",
    "sg:province":"Venezia",
    "wof:name":"E.s.a. Elettronica Sas",
    "wof:placetype":"venue"
},
  "geometry": {"coordinates":[12.152692,45.491676],"type":"Point"}
}