{
  "type": "Feature",
  "properties": {
    "iso:country":"IT",
    "sg:address":"224, V. Sediari 80036 Palma Campania",
    "sg:city":"Palma Campania",
    "sg:classifiers":[
        {
            "category":"Shopping",
            "subcategory":"Clothing, Apparel, & Fashions",
            "type":"Retail Goods"
        }
    ],
    "sg:phone":"+39 081 824 1504",
    "sg:postcode":"80036",
    "sg:province":"Napoli",
    "sg:tags":[
        "clothing",
        "accessory"
    ],
    "sg:website":"http://www.ca-group.net",
    "wof:name":"C.a. Sas Di Vecchione Pietro & C.",
    "wof:placetype":"venue"
},
  "geometry": {"coordinates":[14.545662,40.872349],"type":"Point"}
}