{
  "type": "Feature",
  "properties": {
    "iso:country":"IT",
    "sg:address":"33/22, Via Di Vittorio Giuseppe 20068 Peschiera Borromeo",
    "sg:city":"Peschiera Borromeo",
    "sg:classifiers":[
        {
            "category":"Professional",
            "subcategory":"Printing & Photocopies",
            "type":"Services"
        }
    ],
    "sg:phone":"+39 02 5530 2468",
    "sg:postcode":"20068",
    "sg:province":"Milano",
    "wof:name":"Grafiche Lito-express (s.r.l.)",
    "wof:placetype":"venue"
},
  "geometry": {"coordinates":[9.2657194138,45.4064407349],"type":"Point"}
}