{
  "type": "Feature",
  "properties": {
    "addr:full":"20032 Cormano Cormano Milano 20032",
    "addr:postcode":"20032;20032",
    "iso:country":"IT",
    "sg:address":"20032 Cormano",
    "sg:city":"Cormano",
    "sg:orig_category":"Cartotecnica E Servizi. Composizione, Stampa E Confezione. Forniture E Prodotti Informatici. Forniture Per Congressi, Fiere E Manifestazioni",
    "sg:phone":"+39 02 6630 4864",
    "sg:postcode":"20032",
    "sg:province":"Milano",
    "sg:website":"http://www.magiccard.it",
    "wof:name":"Magic Card Srl",
    "wof:placetype":"venue"
},
  "geometry": {"coordinates":[9.172073,45.538139],"type":"Point"}
}