{
  "type": "Feature",
  "properties": {
    "addr:full":"00100 Roma RM",
    "addr:postcode":"00100",
    "iso:country":"IT",
    "sg:address":"00100 Roma",
    "sg:orig_category":"Minuterie Metalliche E Ferramenta",
    "sg:phone":"+39 06 614 4466",
    "sg:province":"RM",
    "wof:name":"Castoro",
    "wof:placetype":"venue"
},
  "geometry": {"coordinates":[12.4199428558,41.9316368103],"type":"Point"}
}