{
  "type": "Feature",
  "properties": {
    "iso:country":"IT",
    "sg:address":"27, Via Matteotti 37032 Monteforte D'alpone",
    "sg:classifiers":[
        {
            "category":"Farming",
            "subcategory":"Livestock Farm",
            "type":"Manufacturing & Wholesale Goods"
        }
    ],
    "sg:phone":"+39 045 761 0723",
    "sg:postcode":"37032",
    "sg:province":"Verona",
    "sg:tags":[
        "agriculture"
    ],
    "wof:name":"Praja Export Srl",
    "wof:placetype":"venue"
},
  "geometry": {"coordinates":[10.98313,45.359241],"type":"Point"}
}