{
  "type": "Feature",
  "properties": {
    "iso:country":"IT",
    "sg:address":"70125 Bari",
    "sg:city":"Bari",
    "sg:orig_category":"Servizi E Lavori Per Abbigliamento E Pelletterie. Scuole E Servizi Scolastici. Ricerca, Selezione E Formazione Del Personale",
    "sg:phone":"+39 080 542 4824",
    "sg:postcode":"70125",
    "sg:province":"Bari",
    "sg:website":"http://www.istituticallegari.com",
    "wof:name":"Istituto Callegari Snc Di Colaianni A.&c. Affiliato Per Puglia E Basilicata",
    "wof:placetype":"venue"
},
  "geometry": {"coordinates":[16.798628,41.000782],"type":"Point"}
}