{
  "type": "Feature",
  "properties": {
    "iso:country":"IT",
    "sg:address":"80131 Napoli",
    "sg:city":"Napoli",
    "sg:orig_category":"Servizi E Lavori Per Arredamento E Industria Del Legno. Servizi Di Magazzinaggio E Movimentazione",
    "sg:phone":"+39 081 587 3400",
    "sg:postcode":"80131",
    "sg:province":"Napoli",
    "wof:name":"La Vomerese Traslochi Di D'aria Giovanni",
    "wof:placetype":"venue"
},
  "geometry": {"coordinates":[14.192903,40.867626],"type":"Point"}
}