{
  "type": "Feature",
  "properties": {
    "addr:full":"53019 Castelnuovo Berardenga Castelnuovo Berardenga Siena 53019",
    "addr:postcode":"53019;53019",
    "iso:country":"IT",
    "sg:address":"53019 Castelnuovo Berardenga",
    "sg:city":"Castelnuovo Berardenga",
    "sg:orig_category":"Carni, Salumi E Pesci",
    "sg:phone":"+39 0577 352022",
    "sg:postcode":"53019",
    "sg:province":"Siena",
    "wof:name":"Antica Etruria",
    "wof:placetype":"venue"
},
  "geometry": {"coordinates":[11.32827,43.323936],"type":"Point"}
}