{
  "type": "Feature",
  "properties": {
    "iso:country":"IT",
    "sg:address":"40026 Imola",
    "sg:city":"Imola",
    "sg:orig_category":"Forniture Per Uffici",
    "sg:phone":"+39 0542 681400",
    "sg:postcode":"40026",
    "sg:province":"Bologna",
    "sg:website":"http://www.maggioliufficio.it",
    "wof:name":"Imola Ufficio",
    "wof:placetype":"venue"
},
  "geometry": {"coordinates":[11.7296047211,44.3768310547],"type":"Point"}
}