{
  "type": "Feature",
  "properties": {
    "addr:full":"36016 Thiene Thiene Vicenza 36016",
    "addr:postcode":"36016;36016",
    "iso:country":"IT",
    "sg:address":"36016 Thiene",
    "sg:city":"Thiene",
    "sg:orig_category":"Macchine, Impianti Ed Attrezzature Per Industria Alimentare E Bevande",
    "sg:phone":"+39 0445 382182",
    "sg:postcode":"36016",
    "sg:province":"Vicenza",
    "wof:name":"Frautech S.r.l.",
    "wof:placetype":"venue"
},
  "geometry": {"coordinates":[11.511514,45.529568],"type":"Point"}
}