{
  "type": "Feature",
  "properties": {
    "iso:country":"IT",
    "sg:address":"Via Margherita 16; Taranto; 74100",
    "sg:city":"Taranto",
    "sg:classifiers":[
        {
            "category":"Banks & Credit Unions",
            "subcategory":"Bank",
            "type":"Services"
        }
    ],
    "sg:phone":"+39 099 47021",
    "sg:postcode":"74100",
    "sg:province":"Taranto",
    "wof:name":"Credito Italiano Spa",
    "wof:placetype":"venue"
},
  "geometry": {"coordinates":[17.237242,40.473381],"type":"Point"}
}