{
  "type": "Feature",
  "properties": {
    "iso:country":"IT",
    "sg:address":"20129 Milano",
    "sg:city":"Milano",
    "sg:orig_category":"Automazione E Macchine Per Ufficio",
    "sg:phone":"+39 02 718506",
    "sg:postcode":"20129",
    "sg:province":"Milano",
    "wof:name":"S.i.m.i. Societa'italiana Macchine Indirizzi Di Paolo Cioni E C. Sas",
    "wof:placetype":"venue"
},
  "geometry": {"coordinates":[9.272895,45.445187],"type":"Point"}
}