{
  "type": "Feature",
  "properties": {
    "iso:country":"IT",
    "sg:address":"81022 Casagiove",
    "sg:city":"Casagiove",
    "sg:orig_category":"Ricambi E Componenti Dei Mezzi Di Trasporto. Riparazione Dei Mezzi Di Trasporto",
    "sg:phone":"+39 0823 466999",
    "sg:postcode":"81022",
    "sg:province":"Caserta",
    "wof:name":"Emmecci Srl",
    "wof:placetype":"venue"
},
  "geometry": {"coordinates":[14.295203,41.049862],"type":"Point"}
}