{
  "type": "Feature",
  "properties": {
    "iso:country":"IT",
    "sg:address":"16131 Genova",
    "sg:city":"Genova",
    "sg:classifiers":[
        {
            "category":"Health Services",
            "subcategory":"Health Practitioner",
            "type":"Services"
        }
    ],
    "sg:phone":"+39 010 358206",
    "sg:postcode":"16131",
    "sg:province":"Genova",
    "sg:tags":[
        "medici"
    ],
    "wof:name":"Trombetta Carlo",
    "wof:placetype":"venue"
},
  "geometry": {"coordinates":[8.9749135971,44.4034423828],"type":"Point"}
}