{
  "type": "Feature",
  "properties": {
    "iso:country":"IT",
    "sg:address":"10040 Villar Dora",
    "sg:city":"Villar Dora",
    "sg:orig_category":"Macchine E Forniture Per Arredamento E Industria Del Legno. Colori, Vernici E Smalti",
    "sg:phone":"+39 011 935 0260",
    "sg:postcode":"10040",
    "sg:province":"Torino",
    "wof:name":"Colore Amico Sas Di Ferrero Marzio & C.",
    "wof:placetype":"venue"
},
  "geometry": {"coordinates":[7.384704,45.115631],"type":"Point"}
}