{
  "type": "Feature",
  "properties": {
    "iso:country":"IT",
    "sg:address":"50127 Firenze",
    "sg:city":"Firenze",
    "sg:orig_category":"Servizi E Lavori Per Agricoltura E Zootecnia. Consulenze Tecniche, Amministrative E Perizie",
    "sg:phone":"+39 055 659 9007",
    "sg:postcode":"50127",
    "sg:province":"Firenze",
    "wof:name":"Peter Furler",
    "wof:placetype":"venue"
},
  "geometry": {"coordinates":[11.237197,43.79319],"type":"Point"}
}