{
  "type": "Feature",
  "properties": {
    "iso:country":"IT",
    "sg:address":"41058 Vignola",
    "sg:city":"Vignola",
    "sg:classifiers":[
        {
            "category":"Government",
            "subcategory":"Department Of Motor Vehicles",
            "type":"Public Place"
        }
    ],
    "sg:phone":"+39 059 773354",
    "sg:postcode":"41058",
    "sg:province":"Modena",
    "sg:tags":[
        "refuse",
        "disposal",
        "vehicles",
        "component",
        "environmental",
        "protection",
        "spare",
        "machinery",
        "supplies",
        "part"
    ],
    "sg:website":"http://www.springprotezione.it",
    "wof:name":"Spring Protezione Srl",
    "wof:placetype":"venue"
},
  "geometry": {"coordinates":[11.015047,44.479362],"type":"Point"}
}