{
  "type": "Feature",
  "properties": {
    "iso:country":"IT",
    "sg:address":"2/a, Vicolo Goldoni Carlo 45100 Rovigo",
    "sg:city":"Rovigo",
    "sg:classifiers":[
        {
            "category":"Parking",
            "subcategory":"Lot",
            "type":"Transportation"
        }
    ],
    "sg:phone":"+39 0425 361039",
    "sg:postcode":"45100",
    "sg:province":"Rovigo",
    "sg:tags":[
        "transport",
        "road"
    ],
    "wof:name":"Centro Servizi Trasporti (s.r.l.)",
    "wof:placetype":"venue"
},
  "geometry": {"coordinates":[11.789797,45.070736],"type":"Point"}
}