{
  "type": "Feature",
  "properties": {
    "iso:country":"IT",
    "sg:address":"20124 Milano",
    "sg:city":"Milano",
    "sg:orig_category":"Petroli, Gas E Combustibili",
    "sg:phone":"+39 02 6698 5893",
    "sg:postcode":"20124",
    "sg:province":"Milano",
    "wof:name":"Luigi Florio E C. (s.p.a.)",
    "wof:placetype":"venue"
},
  "geometry": {"coordinates":[9.1986236572,45.4833869934],"type":"Point"}
}