{
  "type": "Feature",
  "properties": {
    "iso:country":"IT",
    "sg:address":"00193 Roma",
    "sg:city":"Roma",
    "sg:orig_category":"Calzature, Pelletterie E Pelli",
    "sg:phone":"+39 06 687 4800",
    "sg:postcode":"00193",
    "sg:province":"Roma",
    "wof:name":"Linx S.r.l.",
    "wof:placetype":"venue"
},
  "geometry": {"coordinates":[12.465301,41.906143],"type":"Point"}
}