{
  "type": "Feature",
  "properties": {
    "iso:country":"IT",
    "sg:address":"95021 Aci Castello",
    "sg:city":"Aci Castello",
    "sg:orig_category":"Macchine, Impianti Ed Attrezzature Per Agricoltura E Zootecnia. Macchine E Forniture Per Arredamento E Industria Del Legno",
    "sg:phone":"+39 095 712 5398",
    "sg:postcode":"95021",
    "sg:province":"Catania",
    "wof:name":"Mar Sicilia Di Manueli Giovanni",
    "wof:placetype":"venue"
},
  "geometry": {"coordinates":[15.123455,37.543682],"type":"Point"}
}