{
  "type": "Feature",
  "properties": {
    "iso:country":"IT",
    "sg:address":"36, Via Quattroventi 33040 Corno Di Rosazzo",
    "sg:city":"Corno di Rosazzo",
    "sg:classifiers":[
        {
            "category":"Home & Garden",
            "subcategory":"Home Furnishings",
            "type":"Retail Goods"
        }
    ],
    "sg:phone":"+39 0432 759069",
    "sg:postcode":"33040",
    "sg:province":"Udine",
    "sg:tags":[
        "household"
    ],
    "wof:name":"Bergamasco & Vosca S.r.l.",
    "wof:placetype":"venue"
},
  "geometry": {"coordinates":[13.443022,45.987972],"type":"Point"}
}