{
  "type": "Feature",
  "properties": {
    "iso:country":"IT",
    "sg:address":"1, Via Rio Rocca 42013 Casalgrande",
    "sg:classifiers":[
        {
            "category":"Professional",
            "subcategory":"Engineering",
            "type":"Services"
        }
    ],
    "sg:phone":"+39 0536 823156",
    "sg:postcode":"42013",
    "sg:province":"Reggio Nell'Emilia",
    "sg:tags":[
        "machine",
        "-",
        "mechanical"
    ],
    "wof:name":"Progeco (s.r.l.)",
    "wof:placetype":"venue"
},
  "geometry": {"coordinates":[10.763596,44.551582],"type":"Point"}
}