{
  "type": "Feature",
  "properties": {
    "addr:full":"Via Provinciale Per Carpi 33 42015 Correggio Reggio Nell'Emilia 42015",
    "addr:housenumber":"33",
    "addr:postcode":"42015;42015",
    "addr:street":"Via Provinciale Per Carpi",
    "iso:country":"IT",
    "sg:address":"Via Provinciale Per Carpi 33 42015 Correggio",
    "sg:classifiers":[
        {
            "category":"Wholesale",
            "subcategory":"Vending Machines",
            "type":"Manufacturing & Wholesale Goods"
        }
    ],
    "sg:phone":"+39 0522 631777",
    "sg:postcode":"42015",
    "sg:province":"Reggio Nell'Emilia",
    "sg:tags":[
        "balancing"
    ],
    "wof:name":"Snap On Equipment Srl",
    "wof:placetype":"venue"
},
  "geometry": {"coordinates":[10.773781,44.728115],"type":"Point"}
}