{
  "type": "Feature",
  "properties": {
    "iso:country":"IT",
    "sg:address":"52015 Pratovecchio",
    "sg:city":"Pratovecchio",
    "sg:orig_category":"Servizi E Lavori Per Abbigliamento E Pelletterie. Arte Ed Artigianato Artistico. Shopping",
    "sg:phone":"+39 0575 504344",
    "sg:postcode":"52015",
    "sg:province":"Arezzo",
    "wof:name":"Arte Del Cuoio Fantechi",
    "wof:placetype":"venue"
},
  "geometry": {"coordinates":[11.740994,43.784416],"type":"Point"}
}