{
  "type": "Feature",
  "properties": {
    "iso:country":"IT",
    "sg:address":"70051 Barletta",
    "sg:city":"Barletta",
    "sg:orig_category":"Medici Specialisti - Dermatologia E Malattie Veneree",
    "sg:phone":"+39 0883 520681",
    "sg:postcode":"70051",
    "sg:province":"Bari",
    "wof:name":"Vena Prof. Gino Antonio",
    "wof:placetype":"venue"
},
  "geometry": {"coordinates":[16.22868,41.294952],"type":"Point"}
}