{
  "type": "Feature",
  "properties": {
    "addr:full":"Via Mecenate 84/a; Milano",
    "addr:housenumber":"84 / a",
    "addr:street":"Via Mecenate",
    "iso:country":"IT",
    "sg:address":"Via Mecenate 84/a; Milano",
    "sg:classifiers":[
        {
            "category":"Banks & Credit Unions",
            "subcategory":"Bank",
            "type":"Services"
        }
    ],
    "sg:phone":"+39 02 580 1011",
    "wof:name":"Banca Popolare Di Crema",
    "wof:placetype":"venue"
},
  "geometry": {"coordinates":[9.24947,45.451714],"type":"Point"}
}