{
  "type": "Feature",
  "properties": {
    "iso:country":"IT",
    "sg:address":"31050 Ponzano Veneto",
    "sg:city":"Ponzano Veneto",
    "sg:orig_category":"Manufacturers: Prefabbricati",
    "sg:phone":"+39 0422 441698",
    "sg:postcode":"31050",
    "sg:province":"Treviso",
    "wof:name":"Multiform S.r.l.",
    "wof:placetype":"venue"
},
  "geometry": {"coordinates":[12.216647,45.729523],"type":"Point"}
}