{
  "type": "Feature",
  "properties": {
    "iso:country":"IT",
    "sg:address":"37135 Verona",
    "sg:city":"Verona",
    "sg:orig_category":"Macchine Ed Impianti Per Edilizia E Lavori Pubblici. Elettronica Industriale, Prodotti E Apparecchiature",
    "sg:phone":"+39 045 820 3166",
    "sg:postcode":"37135",
    "sg:province":"Verona",
    "wof:name":"Sicontraf (s.r.l.)",
    "wof:placetype":"venue"
},
  "geometry": {"coordinates":[10.974001,45.401073],"type":"Point"}
}