{
  "type": "Feature",
  "properties": {
    "addr:full":"02100 Rieti Rieti Rieti 02100",
    "addr:postcode":"02100;02100",
    "iso:country":"IT",
    "sg:address":"02100 Rieti",
    "sg:city":"Rieti",
    "sg:orig_category":"Onoranze E Pompe Funebri",
    "sg:phone":"+39 0746 202727",
    "sg:postcode":"02100",
    "sg:province":"Rieti",
    "wof:name":"La Funeraria Snc Dei F.lli Biscetti Roberto E Alessandra",
    "wof:placetype":"venue"
},
  "geometry": {"coordinates":[12.828477,42.39465],"type":"Point"}
}