{
  "type": "Feature",
  "properties": {
    "iso:country":"IT",
    "sg:address":"63018 Porto Sant'elpidio",
    "sg:orig_category":"Forniture Per Abbigliamento E Pelletterie",
    "sg:phone":"+39 0734 992490",
    "sg:postcode":"63018",
    "sg:province":"Ascoli Piceno",
    "wof:name":"Ruggeri",
    "wof:placetype":"venue"
},
  "geometry": {"coordinates":[13.7613563538,43.2511825562],"type":"Point"}
}