{
  "type": "Feature",
  "properties": {
    "iso:country":"IT",
    "sg:address":"Via Roma, 25; Bene Vagienna; 12041",
    "sg:city":"Bene Vagienna",
    "sg:classifiers":[
        {
            "category":"Banks & Credit Unions",
            "subcategory":"Bank",
            "type":"Services"
        }
    ],
    "sg:phone":"+39 0172 654164",
    "sg:postcode":"12041",
    "sg:province":"Cuneo",
    "wof:name":"Banca Popolare Di Novara",
    "wof:placetype":"venue"
},
  "geometry": {"coordinates":[7.831384,44.544231],"type":"Point"}
}