{
  "type": "Feature",
  "properties": {
    "iso:country":"IT",
    "sg:address":"2, Via Della Resistenza 06012 Citta' Di Castello",
    "sg:classifiers":[
        {
            "category":"Building & Trades",
            "subcategory":"Construction",
            "type":"Services"
        }
    ],
    "sg:phone":"+39 075 857 8626",
    "sg:postcode":"06012",
    "sg:province":"Perugia",
    "sg:tags":[
        "work",
        "public"
    ],
    "wof:name":"Lepri F.lli S.r.l.",
    "wof:placetype":"venue"
},
  "geometry": {"coordinates":[12.235503,43.398178],"type":"Point"}
}