{
  "type": "Feature",
  "properties": {
    "addr:full":"50127 Firenze Firenze Firenze 50127",
    "addr:postcode":"50127;50127",
    "iso:country":"IT",
    "sg:address":"50127 Firenze",
    "sg:city":"Firenze",
    "sg:orig_category":"Accessori Moda D'abbigliamento",
    "sg:phone":"+39 055 430765",
    "sg:postcode":"50127",
    "sg:province":"Firenze",
    "wof:name":"Noferini Loredana",
    "wof:placetype":"venue"
},
  "geometry": {"coordinates":[10.747925,43.67762],"type":"Point"}
}