{
  "type": "Feature",
  "properties": {
    "iso:country":"IT",
    "sg:address":"39040 Naz Sciaves",
    "sg:city":"Naz",
    "sg:orig_category":"Macchine Utensili E Impianti",
    "sg:phone":"+39 0472 412035",
    "sg:postcode":"39040",
    "sg:province":"Bolzano/Bozen",
    "wof:name":"Zingerle Metal Srl",
    "wof:placetype":"venue"
},
  "geometry": {"coordinates":[11.66674,46.769871],"type":"Point"}
}