{
  "type": "Feature",
  "properties": {
    "addr:full":"20123 Milano Milano Milano 20123",
    "addr:postcode":"20123;20123",
    "iso:country":"IT",
    "sg:address":"20123 Milano",
    "sg:city":"Milano",
    "sg:orig_category":"Metalli E Leghe. Gioielleria, Oreficeria E Argenteria",
    "sg:phone":"+39 02 8645 4578",
    "sg:postcode":"20123",
    "sg:province":"Milano",
    "wof:name":"La Meridiana Snc Di Mirta Visconti E C.",
    "wof:placetype":"venue"
},
  "geometry": {"coordinates":[9.1846904755,45.4610176086],"type":"Point"}
}