{
  "type": "Feature",
  "properties": {
    "addr:full":"6, Via Zanica 24050 Grassobbio Grassobbio Bergamo 24050",
    "addr:postcode":"24050;24050",
    "addr:street":"Via Zanica",
    "iso:country":"IT",
    "sg:address":"6, Via Zanica 24050 Grassobbio",
    "sg:city":"Grassobbio",
    "sg:classifiers":[
        {
            "category":"Professional",
            "subcategory":"Printing & Photocopies",
            "type":"Services"
        }
    ],
    "sg:phone":"+39 39035335219",
    "sg:postcode":"24050",
    "sg:province":"Bergamo",
    "wof:name":"Distriberg (s.r.l.)",
    "wof:placetype":"venue"
},
  "geometry": {"coordinates":[9.7131681442,45.6516532898],"type":"Point"}
}