{
  "type": "Feature",
  "properties": {
    "addr:full":"09126 Cagliari Cagliari Cagliari 09126",
    "addr:postcode":"09126;09126",
    "iso:country":"IT",
    "sg:address":"09126 Cagliari",
    "sg:city":"Cagliari",
    "sg:orig_category":"Scuole E Servizi Scolastici. Servizi Per Lo Sport E Il Tempo Libero",
    "sg:phone":"+39 070 304711",
    "sg:postcode":"09126",
    "sg:province":"Cagliari",
    "wof:name":"Associazione Culturale I.s.m. Roland Piano",
    "wof:placetype":"venue"
},
  "geometry": {"coordinates":[9.15115,39.193771],"type":"Point"}
}