{
  "type": "Feature",
  "properties": {
    "iso:country":"IT",
    "sg:address":"00167 Roma",
    "sg:city":"Roma",
    "sg:orig_category":"Non-classified Establishments",
    "sg:phone":"+39 06 638 2695",
    "sg:postcode":"00167",
    "sg:province":"Roma",
    "wof:name":"Salvini Lorenzo",
    "wof:placetype":"venue"
},
  "geometry": {"coordinates":[12.429461,41.911411],"type":"Point"}
}