{
  "type": "Feature",
  "properties": {
    "iso:country":"IT",
    "sg:address":"12042 Bra",
    "sg:city":"Bra",
    "sg:orig_category":"Prodotti Vari In Metallo",
    "sg:phone":"+39 0172 457246",
    "sg:postcode":"12042",
    "sg:province":"Cuneo",
    "wof:name":"Bracord",
    "wof:placetype":"venue"
},
  "geometry": {"coordinates":[7.820807457,44.7257423401],"type":"Point"}
}