{
  "type": "Feature",
  "properties": {
    "iso:country":"IT",
    "sg:address":"09028 Sestu",
    "sg:city":"Sestu",
    "sg:orig_category":"Imprese Di Costruzioni Civili Ed Industriali",
    "sg:phone":"+39 070 22049",
    "sg:postcode":"09028",
    "sg:province":"Cagliari",
    "sg:website":"http://www.ecosilam.it",
    "wof:name":"Eco Silam Srl",
    "wof:placetype":"venue"
},
  "geometry": {"coordinates":[9.090287,39.306751],"type":"Point"}
}