{
  "type": "Feature",
  "properties": {
    "addr:full":"20060 Trezzano Rosa Trezzano Rosa Milano 20060",
    "addr:postcode":"20060;20060",
    "iso:country":"IT",
    "sg:address":"20060 Trezzano Rosa",
    "sg:city":"Trezzano Rosa",
    "sg:orig_category":"Agenzie D'affari E Servizi Commerciali",
    "sg:phone":"+39 02 909 3171",
    "sg:postcode":"20060",
    "sg:province":"Milano",
    "wof:name":"Bomi 2000",
    "wof:placetype":"venue"
},
  "geometry": {"coordinates":[9.472111,45.5872],"type":"Point"}
}