{
  "type": "Feature",
  "properties": {
    "iso:country":"IT",
    "sg:address":"Via Roma 20 34170 Gorizia",
    "sg:city":"Gorizia",
    "sg:classifiers":[
        {
            "category":"Shopping",
            "subcategory":"Stationery & Office Supplies",
            "type":"Retail Goods"
        }
    ],
    "sg:phone":"+39 0481 530332",
    "sg:postcode":"34170",
    "sg:province":"Gorizia",
    "sg:tags":[
        "cardboard"
    ],
    "sg:website":"www.fimpaper.com",
    "wof:name":"Fimpaper Spa",
    "wof:placetype":"venue"
},
  "geometry": {"coordinates":[13.623756,45.944012],"type":"Point"}
}