{
  "type": "Feature",
  "properties": {
    "addr:full":"8, Via G. Reich 24020 Torre Boldone Torre Boldone Bergamo 24020",
    "addr:postcode":"24020;24020",
    "addr:street":"Via G. Reich",
    "iso:country":"IT",
    "sg:address":"8, Via G. Reich 24020 Torre Boldone",
    "sg:city":"Torre Boldone",
    "sg:classifiers":[
        {
            "category":"Shopping",
            "subcategory":"Crafts & Fabrics",
            "type":"Retail Goods"
        }
    ],
    "sg:phone":"+39 39035347092",
    "sg:postcode":"24020",
    "sg:province":"Bergamo",
    "wof:name":"Precifil (s.r.l.)",
    "wof:placetype":"venue"
},
  "geometry": {"coordinates":[9.7063827515,45.7161331177],"type":"Point"}
}