{
  "type": "Feature",
  "properties": {
    "addr:full":"107, Viale Porta Po 45100 Rovigo Rovigo Rovigo 45100",
    "addr:postcode":"45100;45100",
    "addr:street":"Viale Porta Po",
    "iso:country":"IT",
    "sg:address":"107, Viale Porta Po 45100 Rovigo",
    "sg:city":"Rovigo",
    "sg:classifiers":[
        {
            "category":"Shopping",
            "subcategory":"Clothing, Apparel, & Fashions",
            "type":"Retail Goods"
        }
    ],
    "sg:phone":"+39 0425 471208",
    "sg:postcode":"45100",
    "sg:province":"Rovigo",
    "sg:tags":[
        "clothes"
    ],
    "wof:name":"3 M S.r.l.",
    "wof:placetype":"venue"
},
  "geometry": {"coordinates":[11.786964,45.049957],"type":"Point"}
}