{
  "type": "Feature",
  "properties": {
    "addr:full":"22032 Albese Con Cassano Albese con Cassano Como 22032",
    "addr:postcode":"22032;22032",
    "iso:country":"IT",
    "sg:address":"22032 Albese Con Cassano",
    "sg:city":"Albese con Cassano",
    "sg:classifiers":[
        {
            "category":"Communications",
            "subcategory":"Newspaper",
            "type":"Services"
        }
    ],
    "sg:phone":"+39 031 428025",
    "sg:postcode":"22032",
    "sg:province":"Como",
    "sg:tags":[
        "publishing"
    ],
    "wof:name":"Logipak Snc",
    "wof:placetype":"venue"
},
  "geometry": {"coordinates":[9.1530151367,45.7876205444],"type":"Point"}
}