{
  "type": "Feature",
  "properties": {
    "addr:full":"15, Via Delle Colombaie 59013 Montemurlo Montemurlo Prato 59013",
    "addr:postcode":"59013;59013",
    "addr:street":"Via Delle Colombaie",
    "iso:country":"IT",
    "sg:address":"15, Via Delle Colombaie 59013 Montemurlo",
    "sg:city":"Montemurlo",
    "sg:classifiers":[
        {
            "category":"Shopping",
            "subcategory":"Crafts & Fabrics",
            "type":"Retail Goods"
        }
    ],
    "sg:phone":"+39 0574 720789",
    "sg:postcode":"59013",
    "sg:province":"Prato",
    "wof:name":"Boomerang Fil Srl",
    "wof:placetype":"venue"
},
  "geometry": {"coordinates":[11.0473632812,43.9102859497],"type":"Point"}
}