{
  "type": "Feature",
  "properties": {
    "addr:full":"9, Via Per Camaiore 55100 Lucca Lucca Lucca 55100",
    "addr:postcode":"55100;55100",
    "addr:street":"Via Per Camaiore",
    "iso:country":"IT",
    "sg:address":"9, Via Per Camaiore 55100 Lucca",
    "sg:city":"Lucca",
    "sg:classifiers":[
        {
            "category":"Professional",
            "subcategory":"Engineering",
            "type":"Services"
        }
    ],
    "sg:phone":"+39 39058333231",
    "sg:postcode":"55100",
    "sg:province":"Lucca",
    "sg:tags":[
        "machine",
        "-",
        "mechanical"
    ],
    "wof:name":"Faper S.r.l.",
    "wof:placetype":"venue"
},
  "geometry": {"coordinates":[10.484478,43.881546],"type":"Point"}
}