{
  "type": "Feature",
  "properties": {
    "iso:country":"IT",
    "sg:address":"20149 Milano",
    "sg:city":"Milano",
    "sg:orig_category":"Macchine, Impianti Ed Attrezzature Industria Chimica. Vetro: Prodotti E Lavorazioni",
    "sg:phone":"+39 02 327 0907",
    "sg:postcode":"20149",
    "sg:province":"Milano",
    "wof:name":"Soffieria Bertolini S.p.a.",
    "wof:placetype":"venue"
},
  "geometry": {"coordinates":[9.155182,45.487427],"type":"Point"}
}