{
  "type": "Feature",
  "properties": {
    "addr:full":"Via Per Turbigo 20022 Castano Primo Castano Primo Milano 20022",
    "addr:postcode":"20022;20022",
    "addr:street":"Via Per Turbigo",
    "iso:country":"IT",
    "sg:address":"Via Per Turbigo 20022 Castano Primo",
    "sg:city":"Castano Primo",
    "sg:classifiers":[
        {
            "category":"Real Estate",
            "subcategory":"Architect",
            "type":"Services"
        }
    ],
    "sg:phone":"+39 0331 881554",
    "sg:postcode":"20022",
    "sg:province":"Milano",
    "sg:tags":[
        "textile",
        "clothing"
    ],
    "wof:name":"International Fashion System (s.r.l.)",
    "wof:placetype":"venue"
},
  "geometry": {"coordinates":[8.760369,45.543549],"type":"Point"}
}