{
  "type": "Feature",
  "properties": {
    "iso:country":"IT",
    "sg:address":"17, Corso Sempione 21013 Gallarate",
    "sg:city":"Gallarate",
    "sg:classifiers":[
        {
            "category":"Communications",
            "subcategory":"Newspaper",
            "type":"Services"
        }
    ],
    "sg:phone":"+39 0331 785104",
    "sg:postcode":"21013",
    "sg:province":"Varese",
    "sg:tags":[
        "advertising"
    ],
    "wof:name":"Uniservice Piccola Societa' Cooperativa A R.l.",
    "wof:placetype":"venue"
},
  "geometry": {"coordinates":[8.785411,45.66259],"type":"Point"}
}