{
  "type": "Feature",
  "properties": {
    "addr:full":"45, Via Camurati Carlo 15048 Valenza Valenza Alessandria 15048",
    "addr:postcode":"15048;15048",
    "addr:street":"Via Camurati Carlo",
    "iso:country":"IT",
    "sg:address":"45, Via Camurati Carlo 15048 Valenza",
    "sg:city":"Valenza",
    "sg:classifiers":[
        {
            "category":"Shopping",
            "subcategory":"Jewelry",
            "type":"Retail Goods"
        }
    ],
    "sg:phone":"+39 0131 952815",
    "sg:postcode":"15048",
    "sg:province":"Alessandria",
    "sg:tags":[
        "jewellery"
    ],
    "wof:name":"R.c.m. Ricci Corbellini Manfrinati (s.n.c.)",
    "wof:placetype":"venue"
},
  "geometry": {"coordinates":[8.637957,45.013962],"type":"Point"}
}