{
  "type": "Feature",
  "properties": {
    "addr:full":"90129 Palermo Palermo Palermo 90129",
    "addr:postcode":"90129;90129",
    "iso:country":"IT",
    "sg:address":"90129 Palermo",
    "sg:city":"Palermo",
    "sg:orig_category":"Articoli Funerari",
    "sg:phone":"+39 091 211911",
    "sg:postcode":"90129",
    "sg:province":"Palermo",
    "wof:name":"F.lli Vitale Fedele E Armando & C. Snc",
    "wof:placetype":"venue"
},
  "geometry": {"coordinates":[13.339916,38.111809],"type":"Point"}
}