{
  "type": "Feature",
  "properties": {
    "iso:country":"IT",
    "sg:address":"35135 Padova",
    "sg:city":"Padova",
    "sg:orig_category":"Antifurto",
    "sg:phone":"+39 049 864 3635",
    "sg:postcode":"35135",
    "sg:province":"Padova",
    "wof:name":"Securtecnica Snc",
    "wof:placetype":"venue"
},
  "geometry": {"coordinates":[11.869109,45.444569],"type":"Point"}
}