{
  "type": "Feature",
  "properties": {
    "iso:country":"IT",
    "sg:address":"62010 Montecassiano",
    "sg:city":"Montecassiano",
    "sg:orig_category":"Arredo Cucina Ed Elettrodomestici",
    "sg:phone":"+39 0733 290561",
    "sg:postcode":"62010",
    "sg:province":"Macerata",
    "wof:name":"Delta S.r.l.",
    "wof:placetype":"venue"
},
  "geometry": {"coordinates":[13.457635,43.354885],"type":"Point"}
}