{
  "type": "Feature",
  "properties": {
    "iso:country":"IT",
    "sg:address":"25037 Pontoglio",
    "sg:city":"Pontoglio",
    "sg:orig_category":"Carni, Salumi E Pesci. Zootecnia E Pesca, Allevamento Piccoli Animali",
    "sg:phone":"+39 030 747 0350",
    "sg:postcode":"25037",
    "sg:province":"Brescia",
    "wof:name":"Bertoli Tomaso Di Bertoli Tomaso & C. Snc",
    "wof:placetype":"venue"
},
  "geometry": {"coordinates":[10.225477,45.548649],"type":"Point"}
}