{
  "type": "Feature",
  "properties": {
    "iso:country":"IT",
    "sg:address":"00193 Roma",
    "sg:city":"Roma",
    "sg:orig_category":"Articoli Religiosi",
    "sg:phone":"+39 06 687 5079",
    "sg:postcode":"00193",
    "sg:province":"Roma",
    "sg:website":"http://www.comandini.it",
    "wof:name":"Comandini S. Srl",
    "wof:placetype":"venue"
},
  "geometry": {"coordinates":[12.497056,41.85984],"type":"Point"}
}