{
  "type": "Feature",
  "properties": {
    "iso:country":"IT",
    "sg:address":"15, Via Campagna 31020 San Polo Di Piave",
    "sg:city":"San Polo di Piave",
    "sg:classifiers":[
        {
            "category":"Manufacturing",
            "subcategory":"Metals",
            "type":"Manufacturing & Wholesale Goods"
        }
    ],
    "sg:phone":"+39 0422 855548",
    "sg:postcode":"31020",
    "sg:province":"Treviso",
    "sg:tags":[
        "processing"
    ],
    "wof:name":"Stampiave S.r.l.",
    "wof:placetype":"venue"
},
  "geometry": {"coordinates":[12.3859329224,45.7982444763],"type":"Point"}
}