{
  "type": "Feature",
  "properties": {
    "iso:country":"IT",
    "sg:address":"25032 Chiari",
    "sg:city":"Chiari",
    "sg:orig_category":"Servizi E Lavori Per Edilizia E Lavori Pubblici",
    "sg:phone":"+39 030 712348",
    "sg:postcode":"25032",
    "sg:province":"Brescia",
    "wof:name":"Mazzotti Giovanni Rino",
    "wof:placetype":"venue"
},
  "geometry": {"coordinates":[9.938583,45.535408],"type":"Point"}
}