{
  "type": "Feature",
  "properties": {
    "iso:country":"IT",
    "sg:address":"20124 Milano",
    "sg:city":"Milano",
    "sg:orig_category":"Elettricita' Materiali - Ingrosso",
    "sg:phone":"+39 02 2952 2245",
    "sg:postcode":"20124",
    "sg:province":"Milano",
    "sg:website":"http://www.2mdmandotti.it",
    "wof:name":"2 Md Mandotti Srl",
    "wof:placetype":"venue"
},
  "geometry": {"coordinates":[9.207749,45.477108],"type":"Point"}
}