{
  "type": "Feature",
  "properties": {
    "addr:full":"47, Via Maria Cristina 10025 Pino Torinese Pino Torinese Torino 10025",
    "addr:postcode":"10025;10025",
    "addr:street":"Via Maria Cristina",
    "iso:country":"IT",
    "sg:address":"47, Via Maria Cristina 10025 Pino Torinese",
    "sg:city":"Pino Torinese",
    "sg:classifiers":[
        {
            "category":"Food & Beverages",
            "subcategory":"Groceries & Convenience Stores",
            "type":"Retail Goods"
        }
    ],
    "sg:phone":"+39 011 815 2111",
    "sg:postcode":"10025",
    "sg:province":"Torino",
    "sg:tags":[
        "product",
        "related"
    ],
    "wof:name":"Ferrero (s.p.a.)",
    "wof:placetype":"venue"
},
  "geometry": {"coordinates":[7.7753295898,45.0452613831],"type":"Point"}
}