{
  "type": "Feature",
  "properties": {
    "iso:country":"IT",
    "sg:address":"Via Brigata Osoppo 178 33074 Fontanafredda",
    "sg:city":"Fontanafredda",
    "sg:classifiers":[
        {
            "category":"Banks & Credit Unions",
            "subcategory":"Investment Brokerage",
            "type":"Services"
        }
    ],
    "sg:phone":"+39 0434 565056",
    "sg:postcode":"33074",
    "sg:province":"Pordenone",
    "sg:tags":[
        "work",
        "marble"
    ],
    "sg:website":"www.systemarble.com",
    "wof:name":"Trevisan System Srl",
    "wof:placetype":"venue"
},
  "geometry": {"coordinates":[12.531343,45.978977],"type":"Point"}
}