{
  "type": "Feature",
  "properties": {
    "iso:country":"IT",
    "sg:address":"7/a, Via Volta Alessandro 20121 Milano",
    "sg:city":"Milano",
    "sg:classifiers":[
        {
            "category":"Manufacturing",
            "subcategory":"Rubber & Plastics",
            "type":"Manufacturing & Wholesale Goods"
        }
    ],
    "sg:phone":"+39 39026555151",
    "sg:postcode":"20121",
    "sg:province":"Milano",
    "wof:name":"Azienda Posatori Linoleum E Moquettes (s.n.c.)",
    "wof:placetype":"venue"
},
  "geometry": {"coordinates":[9.1839666367,45.4791374207],"type":"Point"}
}