{
  "type": "Feature",
  "properties": {
    "addr:full":"52/54, Via Delle Groane 20024 Garbagnate Milanese Garbagnate Milanese Milano 20024",
    "addr:housenumber":"52 / 54",
    "addr:postcode":"20024;20024",
    "addr:street":"Via Delle Groane",
    "iso:country":"IT",
    "sg:address":"52/54, Via Delle Groane 20024 Garbagnate Milanese",
    "sg:city":"Garbagnate Milanese",
    "sg:classifiers":[
        {
            "category":"Manufacturing",
            "subcategory":"Metals",
            "type":"Manufacturing & Wholesale Goods"
        }
    ],
    "sg:phone":"+39 02 9902 5065",
    "sg:postcode":"20024",
    "sg:province":"Milano",
    "sg:tags":[
        "processing"
    ],
    "wof:name":"Sintec (s.r.l.)",
    "wof:placetype":"venue"
},
  "geometry": {"coordinates":[9.0851011276,45.5830612183],"type":"Point"}
}