{
  "type": "Feature",
  "properties": {
    "iso:country":"IT",
    "sg:address":"Via Newton 34 50018 Scandicci",
    "sg:city":"Scandicci",
    "sg:classifiers":[
        {
            "category":"Shopping",
            "subcategory":"Clothing, Apparel, & Fashions",
            "type":"Retail Goods"
        }
    ],
    "sg:phone":"+39 055 753186",
    "sg:postcode":"50018",
    "sg:province":"Firenze",
    "sg:tags":[
        "blouse",
        "ladies'",
        "dress"
    ],
    "sg:website":"www.atelierevento.com",
    "wof:name":"Evento Srl",
    "wof:placetype":"venue"
},
  "geometry": {"coordinates":[11.165927,43.761204],"type":"Point"}
}