{
  "type": "Feature",
  "properties": {
    "iso:country":"IT",
    "sg:address":"10128 Torino",
    "sg:city":"Torino",
    "sg:orig_category":"Materiali E Componenti Elettrotecnici",
    "sg:phone":"+39 011 596215",
    "sg:postcode":"10128",
    "sg:province":"Torino",
    "wof:name":"Carbonari Aldo E C. Snc",
    "wof:placetype":"venue"
},
  "geometry": {"coordinates":[7.67263,45.05621],"type":"Point"}
}