{
  "type": "Feature",
  "properties": {
    "iso:country":"IT",
    "sg:address":"20128 Milano",
    "sg:city":"Milano",
    "sg:orig_category":"Gioielleria E Oreficeria - Lavorazione E Ingrosso",
    "sg:phone":"+39 02 256 4668",
    "sg:postcode":"20128",
    "sg:province":"Milano",
    "wof:name":"Taglio E Lavorazione Pietre Di Biasioli",
    "wof:placetype":"venue"
},
  "geometry": {"coordinates":[9.236152,45.508373],"type":"Point"}
}