{
  "type": "Feature",
  "properties": {
    "iso:country":"IT",
    "sg:address":"82020 Pago Veiano",
    "sg:city":"Pago Veiano",
    "sg:classifiers":[
        {
            "category":"Manufacturing",
            "subcategory":"Food",
            "type":"Manufacturing & Wholesale Goods"
        }
    ],
    "sg:phone":"+39 0824 997500",
    "sg:postcode":"82020",
    "sg:province":"Benevento",
    "sg:tags":[
        "product"
    ],
    "wof:name":"Pago Bur Chease Spa",
    "wof:placetype":"venue"
},
  "geometry": {"coordinates":[14.8723707199,41.2489089966],"type":"Point"}
}