{
  "type": "Feature",
  "properties": {
    "iso:country":"IT",
    "sg:address":"59100 Prato",
    "sg:city":"Prato",
    "sg:classifiers":[
        {
            "category":"Shopping",
            "subcategory":"Clothing, Apparel, & Fashions",
            "type":"Retail Goods"
        }
    ],
    "sg:phone":"+39 0574 624107",
    "sg:postcode":"59100",
    "sg:province":"Prato",
    "sg:tags":[
        "clothing",
        "fur",
        "knitwear"
    ],
    "wof:name":"Nuova Creazioni Luela",
    "wof:placetype":"venue"
},
  "geometry": {"coordinates":[11.082459,43.894394],"type":"Point"}
}