{
  "type": "Feature",
  "properties": {
    "addr:full":"84081 Acquamela Di Baronissi Acquamela Salerno 84081",
    "addr:postcode":"84081;84081",
    "addr:street":"Acquamela",
    "iso:country":"IT",
    "sg:address":"84081 Acquamela Di Baronissi",
    "sg:city":"Acquamela",
    "sg:orig_category":"Prodotti E Manufatti In Materie Plastiche. Articoli Per Imballaggio E Confezionamento",
    "sg:phone":"+39 089 956222",
    "sg:postcode":"84081",
    "sg:province":"Salerno",
    "sg:website":"http://www.generalpacking.it",
    "wof:name":"General Packing Srl",
    "wof:placetype":"venue"
},
  "geometry": {"coordinates":[14.7734413147,40.7318840027],"type":"Point"}
}