{
  "type": "Feature",
  "properties": {
    "addr:full":"Zona Industriale S. Sabina - S. Sisto06132 Perugia Perugia Perugia 06132",
    "addr:postcode":"sisto06132;06132",
    "addr:street":"Zona Industriale S. Sabina S.",
    "iso:country":"IT",
    "sg:address":"Zona Industriale S. Sabina - S. Sisto06132 Perugia",
    "sg:city":"Perugia",
    "sg:classifiers":[
        {
            "category":"Shopping",
            "type":"Retail Goods"
        }
    ],
    "sg:phone":"+39 075 527 2405",
    "sg:postcode":"06132",
    "sg:province":"Perugia",
    "sg:tags":[
        "finished",
        "-",
        "metallic"
    ],
    "sg:website":"http://www.3g.italy.com:ws_end: :mark:ws:http://www.paginegialle.it/3g",
    "wof:name":"3 G Srl",
    "wof:placetype":"venue"
},
  "geometry": {"coordinates":[12.3891716003,43.1107025146],"type":"Point"}
}