{
  "type": "Feature",
  "properties": {
    "addr:full":"Via Gramsci 3 37010 Palazzolo Verona 37010",
    "addr:housenumber":"3",
    "addr:postcode":"37010;37010",
    "addr:street":"Via Gramsci",
    "iso:country":"IT",
    "sg:address":"Via Gramsci 3 37010 Palazzolo",
    "sg:classifiers":[
        {
            "category":"Shopping",
            "subcategory":"Shoes",
            "type":"Retail Goods"
        }
    ],
    "sg:phone":"+39 045 608 1088",
    "sg:postcode":"37010",
    "sg:province":"Verona",
    "sg:tags":[
        "men's",
        "boot"
    ],
    "wof:name":"Calzaturificio Maxi Srl",
    "wof:placetype":"venue"
},
  "geometry": {"coordinates":[10.9917478561,45.4383659363],"type":"Point"}
}