{
  "type": "Feature",
  "properties": {
    "iso:country":"IT",
    "sg:address":"20121 Milano",
    "sg:city":"Milano",
    "sg:orig_category":"Servizi Editoriali. Servizi Per Aziende, Manifestazioni E Supporto Agli Scambi Commerciali",
    "sg:phone":"+39 02 725451",
    "sg:postcode":"20121",
    "sg:province":"Milano",
    "wof:name":"Telerate Italia Spa",
    "wof:placetype":"venue"
},
  "geometry": {"coordinates":[9.184875,45.47253],"type":"Point"}
}