{
  "type": "Feature",
  "properties": {
    "addr:full":"25, P. Dante 00185 Roma Roma Roma 00185",
    "addr:housenumber":"25",
    "addr:postcode":"00185;00185",
    "addr:street":"P. Dante",
    "iso:country":"IT",
    "sg:address":"25, P. Dante 00185 Roma",
    "sg:city":"Roma",
    "sg:classifiers":[
        {
            "category":"Manufacturing",
            "subcategory":"Printing",
            "type":"Manufacturing & Wholesale Goods"
        }
    ],
    "sg:phone":"+39 06 7710 4209",
    "sg:postcode":"00185",
    "sg:province":"Roma",
    "sg:tags":[
        "publishing"
    ],
    "sg:website":"http://www.poste.it",
    "wof:name":"Poste Italiane Spa",
    "wof:placetype":"venue"
},
  "geometry": {"coordinates":[12.5041513443,41.8917121887],"type":"Point"}
}