{
  "type": "Feature",
  "properties": {
    "addr:full":"15057 Tortona Tortona Alessandria 15057",
    "addr:postcode":"15057;15057",
    "iso:country":"IT",
    "sg:address":"15057 Tortona",
    "sg:city":"Tortona",
    "sg:orig_category":"Materiali Semilavorati Metallici",
    "sg:phone":"+39 0131 813418",
    "sg:postcode":"15057",
    "sg:province":"Alessandria",
    "wof:name":"L.l.t.",
    "wof:placetype":"venue"
},
  "geometry": {"coordinates":[8.843711,44.900482],"type":"Point"}
}