{
  "type": "Feature",
  "properties": {
    "addr:full":"Via Guido Rossa 39 44012 Bondeno Bondeno Ferrara 44012",
    "addr:housenumber":"39",
    "addr:postcode":"44012;44012",
    "addr:street":"Via Guido Rossa",
    "iso:country":"IT",
    "sg:address":"Via Guido Rossa 39 44012 Bondeno",
    "sg:city":"Bondeno",
    "sg:classifiers":[
        {
            "category":"Military Area",
            "subcategory":"Armory",
            "type":"Public Place"
        }
    ],
    "sg:phone":"+39 0532 896176",
    "sg:postcode":"44012",
    "sg:province":"Ferrara",
    "sg:tags":[
        "net",
        "mosquito"
    ],
    "sg:website":"www.geniusgroup.it",
    "wof:name":"Stiltende Genius S.r.l.",
    "wof:placetype":"venue"
},
  "geometry": {"coordinates":[11.6204395294,44.8378944397],"type":"Point"}
}