{
  "type": "Feature",
  "properties": {
    "iso:country":"IT",
    "sg:address":"37030 Verona",
    "sg:classifiers":[
        {
            "category":"Home & Garden",
            "subcategory":"Home Furnishings",
            "type":"Retail Goods"
        }
    ],
    "sg:phone":"+39 045 550244",
    "sg:postcode":"37030",
    "sg:province":"Verona",
    "sg:tags":[
        "varnish",
        "enamel",
        "paints",
        "industry",
        "wood",
        "machinery",
        "supplies"
    ],
    "sg:website":"http://www.casati.it",
    "wof:name":"Colorificio A. & B. Casati Spa",
    "wof:placetype":"venue"
},
  "geometry": {"coordinates":[11.0187473297,45.4867553711],"type":"Point"}
}