{
  "type": "Feature",
  "properties": {
    "iso:country":"IT",
    "sg:address":"10092 Beinasco",
    "sg:city":"Beinasco",
    "sg:orig_category":"Elettrotecnica Professionale E Di Consumo. Forniture Alle Strutture Ricettive. Arredi Ed Attrezzature Per Attivita' Commerciali Ed Artigianali",
    "sg:phone":"+39 011 358 3455",
    "sg:postcode":"10092",
    "sg:province":"Torino",
    "wof:name":"Golmar Italia (s.p.a.)",
    "wof:placetype":"venue"
},
  "geometry": {"coordinates":[7.597255,45.006294],"type":"Point"}
}