{
  "type": "Feature",
  "properties": {
    "iso:country":"IT",
    "sg:address":"39055 Laives",
    "sg:city":"Laives",
    "sg:classifiers":[
        {
            "category":"Sports & Exercise",
            "subcategory":"Tennis Court",
            "type":"Entertainment"
        }
    ],
    "sg:phone":"+39 0471 954430",
    "sg:postcode":"39055",
    "sg:province":"Bolzano/Bozen",
    "sg:tags":[
        "e",
        "lo",
        "tempo",
        "libero",
        "per",
        "impianti",
        "il",
        "attrezzature"
    ],
    "wof:name":"Bolzano Impianti A Fune S.a.s.",
    "wof:placetype":"venue"
},
  "geometry": {"coordinates":[11.33835,46.418751],"type":"Point"}
}