{
  "type": "Feature",
  "properties": {
    "addr:full":"12100 Cuneo Cuneo Cuneo 12100",
    "addr:postcode":"12100;12100",
    "iso:country":"IT",
    "sg:address":"12100 Cuneo",
    "sg:city":"Cuneo",
    "sg:orig_category":"Servizi Vari Di Interesse Pubblico",
    "sg:phone":"+39 0171 698565",
    "sg:postcode":"12100",
    "sg:province":"Cuneo",
    "wof:name":"Lanzone Alessandro Altair Signore Dell'occulto",
    "wof:placetype":"venue"
},
  "geometry": {"coordinates":[8.162781,44.12582],"type":"Point"}
}