{
  "type": "Feature",
  "properties": {
    "iso:country":"IT",
    "sg:address":"15, Via Pirandello Luigi 10024 Moncalieri",
    "sg:city":"Moncalieri",
    "sg:classifiers":[
        {
            "category":"Professional",
            "subcategory":"Engineering",
            "type":"Services"
        }
    ],
    "sg:phone":"+39 011 627 1895",
    "sg:postcode":"10024",
    "sg:province":"Torino",
    "sg:tags":[
        "machine",
        "-",
        "mechanical"
    ],
    "wof:name":"Nuova Alfa Di Nicastri Francesco",
    "wof:placetype":"venue"
},
  "geometry": {"coordinates":[7.663428,45.001148],"type":"Point"}
}