{
  "type": "Feature",
  "properties": {
    "iso:country":"IT",
    "sg:address":"36040 Torri Di Quartesolo",
    "sg:city":"Torri di Quartesolo",
    "sg:orig_category":"Banche E Servizi Finanziari",
    "sg:phone":"+39 0444 301695",
    "sg:postcode":"36040",
    "sg:province":"Vicenza",
    "wof:name":"Mediofactoring Spa",
    "wof:placetype":"venue"
},
  "geometry": {"coordinates":[11.606951,45.524563],"type":"Point"}
}