{
  "type": "Feature",
  "properties": {
    "iso:country":"IT",
    "sg:address":"20090 Cusago",
    "sg:city":"Cusago",
    "sg:orig_category":"Materiali Semilavorati Metallici",
    "sg:phone":"+39 02 903 9221",
    "sg:postcode":"20090",
    "sg:province":"Milano",
    "sg:website":"http://www.mtinox.com",
    "wof:name":"Emme-ti Srl",
    "wof:placetype":"venue"
},
  "geometry": {"coordinates":[9.04367,45.440315],"type":"Point"}
}