{
  "type": "Feature",
  "properties": {
    "iso:country":"IT",
    "sg:address":"Via Casa Bianca 10 26037 San Giovanni In Croce",
    "sg:city":"San Giovanni in Croce",
    "sg:classifiers":[
        {
            "category":"Military Area",
            "subcategory":"Army Base",
            "type":"Public Place"
        }
    ],
    "sg:phone":"+39 0375 310281",
    "sg:postcode":"26037",
    "sg:province":"Cremona",
    "sg:tags":[
        "safes",
        "room",
        "strong"
    ],
    "sg:website":"www.technomax.it",
    "wof:name":"Technomax Srl",
    "wof:placetype":"venue"
},
  "geometry": {"coordinates":[10.034898,45.138],"type":"Point"}
}