{
  "type": "Feature",
  "properties": {
    "iso:country":"IT",
    "sg:address":"35020 Codevigo",
    "sg:city":"Codevigo",
    "sg:orig_category":"Edilizia - Materiali",
    "sg:phone":"+39 041 554 2280",
    "sg:postcode":"35020",
    "sg:province":"Padova",
    "sg:website":"http://www.tiozzoscavi.com",
    "wof:name":"Tiozzo Fratelli & Nipote Srl",
    "wof:placetype":"venue"
},
  "geometry": {"coordinates":[12.113196,45.263462],"type":"Point"}
}