{
  "type": "Feature",
  "properties": {
    "iso:country":"IT",
    "sg:address":"27036 Mortara",
    "sg:city":"Mortara",
    "sg:orig_category":"Prodotti E Manufatti In Materie Plastiche. Forniture Per Edilizia E Lavori Pubblici",
    "sg:phone":"+39 0384 98306",
    "sg:postcode":"27036",
    "sg:province":"Pavia",
    "wof:name":"Ferro Edile F. Lli Bertani Srl",
    "wof:placetype":"venue"
},
  "geometry": {"coordinates":[8.7593431473,45.2552108765],"type":"Point"}
}