{
  "type": "Feature",
  "properties": {
    "iso:country":"IT",
    "sg:address":"10, Via Cairoli Fratelli 58100 Grosseto",
    "sg:city":"Grosseto",
    "sg:classifiers":[
        {
            "category":"Manufacturing",
            "subcategory":"Printing",
            "type":"Manufacturing & Wholesale Goods"
        }
    ],
    "sg:phone":"+39 0564 415426",
    "sg:postcode":"58100",
    "sg:province":"Grosseto",
    "sg:tags":[
        "publishing"
    ],
    "wof:name":"Associazione Provinciale Per La Nautica Da Diporto",
    "wof:placetype":"venue"
},
  "geometry": {"coordinates":[11.1135044098,42.761554718],"type":"Point"}
}