{
  "type": "Feature",
  "properties": {
    "iso:country":"IT",
    "sg:address":"Via Resia 130; Bolzano; 39100",
    "sg:city":"Bolzano",
    "sg:classifiers":[
        {
            "category":"Banks & Credit Unions",
            "subcategory":"Bank",
            "type":"Services"
        }
    ],
    "sg:phone":"+39 0471 204311",
    "sg:postcode":"39100",
    "sg:province":"Bolzano/Bozen",
    "wof:name":"S\u00fcdtiroler Volksbank",
    "wof:placetype":"venue"
},
  "geometry": {"coordinates":[11.319983,46.484921],"type":"Point"}
}