{
  "type": "Feature",
  "properties": {
    "addr:full":"249/a, Via Guglielmo Marconi 51018 Pieve A Nievole Pieve a Nievole Pistoia 51018",
    "addr:housenumber":"249 / a",
    "addr:postcode":"51018;51018",
    "addr:street":"Via Guglielmo Marconi;A Nievole",
    "iso:country":"IT",
    "sg:address":"249/a, Via Guglielmo Marconi 51018 Pieve A Nievole",
    "sg:city":"Pieve a Nievole",
    "sg:classifiers":[
        {
            "category":"Building & Trades",
            "subcategory":"Construction",
            "type":"Services"
        }
    ],
    "sg:phone":"+39 0572 951509",
    "sg:postcode":"51018",
    "sg:province":"Pistoia",
    "sg:tags":[
        "work",
        "public"
    ],
    "wof:name":"Az Idrovie S.r.l.",
    "wof:placetype":"venue"
},
  "geometry": {"coordinates":[10.918524,43.932156],"type":"Point"}
}