{
  "type": "Feature",
  "properties": {
    "iso:country":"IT",
    "sg:address":"28100 Novara",
    "sg:city":"Novara",
    "sg:orig_category":"Articoli Per Imballaggio E Confezionamento",
    "sg:phone":"+39 0321 620270",
    "sg:postcode":"28100",
    "sg:province":"Novara",
    "wof:name":"Eco Medit Srl",
    "wof:placetype":"venue"
},
  "geometry": {"coordinates":[8.615502,45.442333],"type":"Point"}
}