{
  "type": "Feature",
  "properties": {
    "iso:country":"IT",
    "sg:address":"19038 Sarzana",
    "sg:city":"Sarzana",
    "sg:orig_category":"Pietre Preziose",
    "sg:phone":"+39 338 808 0756",
    "sg:postcode":"19038",
    "sg:province":"La Spezia",
    "wof:name":"Ambramania Sas",
    "wof:placetype":"venue"
},
  "geometry": {"coordinates":[9.7678689957,44.2447929382],"type":"Point"}
}