{
  "type": "Feature",
  "properties": {
    "iso:country":"IT",
    "sg:address":"63035 Offida",
    "sg:city":"Offida",
    "sg:orig_category":"Manufacturers: Prefabbricati",
    "sg:phone":"+39 0736 880011",
    "sg:postcode":"63035",
    "sg:province":"Ascoli Piceno",
    "wof:name":"Ophyplast Di Massicci Tonino",
    "wof:placetype":"venue"
},
  "geometry": {"coordinates":[13.730734,42.868805],"type":"Point"}
}