{
  "type": "Feature",
  "properties": {
    "addr:full":"Via San Mauro 122 10036 Settimo Torinese Settimo Torinese Torino 10036",
    "addr:housenumber":"122",
    "addr:postcode":"10036;10036",
    "addr:street":"Via San Mauro",
    "iso:country":"IT",
    "sg:address":"Via San Mauro 122 10036 Settimo Torinese",
    "sg:city":"Settimo Torinese",
    "sg:orig_category":"Plates, Worked",
    "sg:phone":"+39 011 895 0930",
    "sg:postcode":"10036",
    "sg:province":"Torino",
    "wof:name":"Nuova Accornero S.p.a.",
    "wof:placetype":"venue"
},
  "geometry": {"coordinates":[7.7531552315,45.1206512451],"type":"Point"}
}