{
  "type": "Feature",
  "properties": {
    "iso:country":"IT",
    "sg:address":"Via Trento 28 24035 Curno",
    "sg:city":"Curno",
    "sg:classifiers":[
        {
            "category":"Home & Garden",
            "subcategory":"Home Furnishings",
            "type":"Retail Goods"
        }
    ],
    "sg:phone":"+39 035 612249",
    "sg:postcode":"24035",
    "sg:province":"Bergamo",
    "sg:tags":[
        "candle"
    ],
    "sg:website":"www.deber.com",
    "wof:name":"Cereria Luigi Bertoncini S.r.l.",
    "wof:placetype":"venue"
},
  "geometry": {"coordinates":[9.617111,45.695026],"type":"Point"}
}