{
  "type": "Feature",
  "properties": {
    "addr:full":"Contrada Lama Di Cervo 70022 Altamura Altamura Bari 70022",
    "addr:postcode":"70022;70022",
    "addr:street":"Contrada Lama Di Cervo",
    "iso:country":"IT",
    "sg:address":"Contrada Lama Di Cervo 70022 Altamura",
    "sg:city":"Altamura",
    "sg:classifiers":[
        {
            "category":"Building & Trades",
            "subcategory":"Construction",
            "type":"Services"
        }
    ],
    "sg:phone":"+39 080 311 3445",
    "sg:postcode":"70022",
    "sg:province":"Bari",
    "sg:tags":[
        "work",
        "public"
    ],
    "wof:name":"Costruzioni Di Leo Srl",
    "wof:placetype":"venue"
},
  "geometry": {"coordinates":[16.869291,41.126053],"type":"Point"}
}