{
  "type": "Feature",
  "properties": {
    "iso:country":"IT",
    "sg:address":"40132 Bologna",
    "sg:city":"Bologna",
    "sg:orig_category":"Macchine Utensili E Impianti",
    "sg:phone":"+39 051 565400",
    "sg:postcode":"40132",
    "sg:province":"Bologna",
    "sg:website":"http://www.morara.it",
    "wof:name":"Morara Spa",
    "wof:placetype":"venue"
},
  "geometry": {"coordinates":[11.281042,44.510159],"type":"Point"}
}