{
  "type": "Feature",
  "properties": {
    "addr:full":"38066 Riva Del Garda Riva del Garda Trento 38066",
    "addr:postcode":"38066;38066",
    "iso:country":"IT",
    "sg:address":"38066 Riva Del Garda",
    "sg:city":"Riva del Garda",
    "sg:orig_category":"Persiane Ed Avvolgibili",
    "sg:phone":"+39 0464 552384",
    "sg:postcode":"38066",
    "sg:province":"Trento",
    "wof:name":"Sintelux Di Polidoro R. & C. Snc",
    "wof:placetype":"venue"
},
  "geometry": {"coordinates":[10.8617153168,45.8814201355],"type":"Point"}
}