{
  "type": "Feature",
  "properties": {
    "addr:full":"9, Via Ii Giugno 20051 Limbiate Limbiate Milano 20051",
    "addr:postcode":"20051;20051",
    "addr:street":"Via Ii Giugno",
    "iso:country":"IT",
    "sg:address":"9, Via Ii Giugno 20051 Limbiate",
    "sg:city":"Limbiate",
    "sg:classifiers":[
        {
            "category":"Wholesale",
            "subcategory":"Drugs",
            "type":"Manufacturing & Wholesale Goods"
        }
    ],
    "sg:phone":"+39 390 299 0961",
    "sg:postcode":"20051",
    "sg:province":"Milano",
    "sg:tags":[
        "chemical",
        "pharmaceutical"
    ],
    "wof:name":"Gruppo Chimico Dalton S.p.a.",
    "wof:placetype":"venue"
},
  "geometry": {"coordinates":[9.188141,45.463688],"type":"Point"}
}