{
  "type": "Feature",
  "properties": {
    "iso:country":"IT",
    "sg:address":"42100 Reggio Emilia",
    "sg:orig_category":"Trasporti E Spedizioni Merci",
    "sg:phone":"+39 0522 369111",
    "sg:postcode":"42100",
    "sg:province":"Reggio Nell'Emilia",
    "sg:website":"http://www.artoni.com",
    "wof:name":"Artoni Trasporti Spa",
    "wof:placetype":"venue"
},
  "geometry": {"coordinates":[10.575814,44.713871],"type":"Point"}
}