{
  "type": "Feature",
  "properties": {
    "iso:country":"IT",
    "sg:address":"98076 S. Agata Di Militello",
    "sg:orig_category":"Biancheria Intima Ed Abbigliamento Intimo - Vendita Al Dettaglio",
    "sg:phone":"+39 0941 722222",
    "sg:postcode":"98076",
    "sg:province":"Messina",
    "sg:website":"http://www.casadellino.it",
    "wof:name":"Morello Nitto - Casa Del Lino",
    "wof:placetype":"venue"
},
  "geometry": {"coordinates":[14.634133,38.069588],"type":"Point"}
}