{
  "type": "Feature",
  "properties": {
    "iso:country":"IT",
    "sg:address":"Contrada Serritiello La Valle 75100 Matera",
    "sg:city":"Matera",
    "sg:classifiers":[
        {
            "category":"Home & Garden",
            "subcategory":"Home Furnishings",
            "type":"Retail Goods"
        }
    ],
    "sg:phone":"+39 390 835 3031",
    "sg:postcode":"75100",
    "sg:province":"Matera",
    "sg:tags":[
        "household"
    ],
    "wof:name":"Calia Salotti S.p.a.",
    "wof:placetype":"venue"
},
  "geometry": {"coordinates":[16.592236,40.687038],"type":"Point"}
}