{
  "type": "Feature",
  "properties": {
    "iso:country":"IT",
    "sg:address":"62100 Macerata",
    "sg:city":"Macerata",
    "sg:orig_category":"Campeggio. Automobili E Mezzi Di Trasporto",
    "sg:phone":"+39 0733 233787",
    "sg:postcode":"62100",
    "sg:province":"Macerata",
    "wof:name":"R.a.a.m. Sas Di Riccobelli M. E C.",
    "wof:placetype":"venue"
},
  "geometry": {"coordinates":[13.438415,43.30529],"type":"Point"}
}