{
  "type": "Feature",
  "properties": {
    "addr:full":"10, Via Gnutti Cav. Lavoro Umberto 25065 Lumezzane Lumezzane Brescia 25065",
    "addr:postcode":"25065;25065",
    "addr:street":"Via Gnutti",
    "iso:country":"IT",
    "sg:address":"10, Via Gnutti Cav. Lavoro Umberto 25065 Lumezzane",
    "sg:city":"Lumezzane",
    "sg:classifiers":[
        {
            "category":"Shopping",
            "subcategory":"Crafts & Fabrics",
            "type":"Retail Goods"
        }
    ],
    "sg:phone":"+39 39030828958",
    "sg:postcode":"25065",
    "sg:province":"Brescia",
    "wof:name":"La Fontana Coop. Sociale A R.l. - Garden Serra Rosa Blu",
    "wof:placetype":"venue"
},
  "geometry": {"coordinates":[10.2229576111,45.5398292542],"type":"Point"}
}