{
  "type": "Feature",
  "properties": {
    "iso:country":"IT",
    "sg:address":"70125 Bari",
    "sg:city":"Bari",
    "sg:orig_category":"Elettronica Professionale E Di Consumo. Musica",
    "sg:phone":"+39 080 501 9521",
    "sg:postcode":"70125",
    "sg:province":"Bari",
    "wof:name":"Music House Di Vanni Claudia",
    "wof:placetype":"venue"
},
  "geometry": {"coordinates":[16.875771,41.10091],"type":"Point"}
}