{
  "type": "Feature",
  "properties": {
    "iso:country":"IT",
    "sg:address":"20090 Opera",
    "sg:city":"Opera",
    "sg:orig_category":"Autonoleggio",
    "sg:phone":"+39 02 5760 6651",
    "sg:postcode":"20090",
    "sg:province":"Milano",
    "wof:name":"Blue Car By Ceresa Fulvio",
    "wof:placetype":"venue"
},
  "geometry": {"coordinates":[9.21857,45.379105],"type":"Point"}
}