{
  "type": "Feature",
  "properties": {
    "iso:country":"IT",
    "sg:address":"20090 Trezzano Sul Naviglio",
    "sg:city":"Trezzano sul Naviglio",
    "sg:orig_category":"Cosmetici, Prodotti Di Bellezza E Di Igiene",
    "sg:phone":"+39 02 445 3191",
    "sg:postcode":"20090",
    "sg:province":"Milano",
    "wof:name":"Gandino Luca",
    "wof:placetype":"venue"
},
  "geometry": {"coordinates":[9.052341,45.427673],"type":"Point"}
}