{
  "type": "Feature",
  "properties": {
    "iso:country":"IT",
    "sg:address":"V. Provinciale Per Nardo' 73043 Copertino",
    "sg:city":"Copertino",
    "sg:classifiers":[
        {
            "category":"Farming",
            "subcategory":"Livestock Farm",
            "type":"Manufacturing & Wholesale Goods"
        }
    ],
    "sg:postcode":"73043",
    "sg:province":"Lecce",
    "sg:tags":[
        "agriculture"
    ],
    "sg:website":"http://www.paginegialle.it/edengreen",
    "wof:name":"Edengreen Vivai",
    "wof:placetype":"venue"
},
  "geometry": {"coordinates":[18.174015,40.353291],"type":"Point"}
}