{
  "type": "Feature",
  "properties": {
    "addr:full":"Viale G Matteotti 31; Forli",
    "addr:housenumber":"31",
    "addr:street":"Viale G Matteotti",
    "iso:country":"IT",
    "sg:address":"Viale G Matteotti 31; Forli",
    "sg:classifiers":[
        {
            "category":"Banks & Credit Unions",
            "subcategory":"Bank",
            "type":"Services"
        }
    ],
    "sg:phone":"+39 0543 28243",
    "wof:name":"Banca Di Roma",
    "wof:placetype":"venue"
},
  "geometry": {"coordinates":[12.048234,44.221405],"type":"Point"}
}