{
  "type": "Feature",
  "properties": {
    "iso:country":"IT",
    "sg:address":"10095 Grugliasco",
    "sg:city":"Grugliasco",
    "sg:orig_category":"Utensili Meccanici E Materiali",
    "sg:phone":"+39 011 403 1812",
    "sg:postcode":"10095",
    "sg:province":"Torino",
    "wof:name":"M.t.u. S.r.l.",
    "wof:placetype":"venue"
},
  "geometry": {"coordinates":[7.601918,45.06588],"type":"Point"}
}