{
  "type": "Feature",
  "properties": {
    "addr:full":"8/e, Via Della Consortia 37127 Verona Verona Verona 37127",
    "addr:housenumber":"8 / e",
    "addr:postcode":"37127;37127",
    "addr:street":"Via Della Consortia",
    "iso:country":"IT",
    "sg:address":"8/e, Via Della Consortia 37127 Verona",
    "sg:city":"Verona",
    "sg:classifiers":[
        {
            "category":"Shopping",
            "subcategory":"Crafts & Fabrics",
            "type":"Retail Goods"
        }
    ],
    "sg:phone":"+39 045 830 1366",
    "sg:postcode":"37127",
    "sg:province":"Verona",
    "sg:tags":[
        "linen"
    ],
    "wof:name":"Lavanderia Pigozzi E Lunardi (s.n.c.)",
    "wof:placetype":"venue"
},
  "geometry": {"coordinates":[10.9845991135,45.4673118591],"type":"Point"}
}