{
  "type": "Feature",
  "properties": {
    "iso:country":"IT",
    "sg:address":"Via Roma, 84; Rubiana; 10040",
    "sg:city":"Rubiana",
    "sg:classifiers":[
        {
            "category":"Banks & Credit Unions",
            "subcategory":"Bank",
            "type":"Services"
        }
    ],
    "sg:phone":"+39 011 935 8673",
    "sg:postcode":"10040",
    "sg:province":"Torino",
    "wof:name":"Banca Sella",
    "wof:placetype":"venue"
},
  "geometry": {"coordinates":[7.386682,45.135094],"type":"Point"}
}