{
  "type": "Feature",
  "properties": {
    "addr:full":"33, Via Carpaccio 20090 Trezzano Sul Naviglio Trezzano sul Naviglio Milano 20090",
    "addr:postcode":"20090;20090",
    "addr:street":"Via Carpaccio",
    "iso:country":"IT",
    "sg:address":"33, Via Carpaccio 20090 Trezzano Sul Naviglio",
    "sg:city":"Trezzano sul Naviglio",
    "sg:classifiers":[
        {
            "category":"Wholesale",
            "subcategory":"Medical Equipment & Supplies",
            "type":"Manufacturing & Wholesale Goods"
        }
    ],
    "sg:phone":"+39 39024844231",
    "sg:postcode":"20090",
    "sg:province":"Milano",
    "sg:tags":[
        "-",
        "health",
        "instrument"
    ],
    "wof:name":"Vti Srl",
    "wof:placetype":"venue"
},
  "geometry": {"coordinates":[9.06145,45.419014],"type":"Point"}
}