{
  "type": "Feature",
  "properties": {
    "iso:country":"IT",
    "sg:address":"20125 Milano",
    "sg:city":"Milano",
    "sg:orig_category":"Manufacturers: Prefabbricati",
    "sg:phone":"+39 02 670 4304",
    "sg:postcode":"20125",
    "sg:province":"Milano",
    "wof:name":"Crippa Renato",
    "wof:placetype":"venue"
},
  "geometry": {"coordinates":[9.193342,45.474182],"type":"Point"}
}