{
  "type": "Feature",
  "properties": {
    "iso:country":"IT",
    "sg:address":"31028 Vazzola",
    "sg:city":"Vazzola",
    "sg:classifiers":[
        {
            "category":"Home & Garden",
            "subcategory":"Household Appliances",
            "type":"Retail Goods"
        }
    ],
    "sg:phone":"+39 0438 740832",
    "sg:postcode":"31028",
    "sg:province":"Treviso",
    "sg:tags":[
        "accommodation",
        "appliances",
        "supply"
    ],
    "wof:name":"Metalplast Srl",
    "wof:placetype":"venue"
},
  "geometry": {"coordinates":[12.38415,45.82793],"type":"Point"}
}