{
  "type": "Feature",
  "properties": {
    "iso:country":"IT",
    "sg:address":"5/a, Via Caorsana Fossadello 29012 Caorso",
    "sg:city":"Caorso",
    "sg:classifiers":[
        {
            "category":"Manufacturing",
            "subcategory":"Lumber",
            "type":"Manufacturing & Wholesale Goods"
        }
    ],
    "sg:phone":"+39 0523 813003",
    "sg:postcode":"29012",
    "sg:province":"Piacenza",
    "sg:tags":[
        "wood"
    ],
    "wof:name":"S.a.i.b. (s.p.a.)",
    "wof:placetype":"venue"
},
  "geometry": {"coordinates":[9.816184,45.043312],"type":"Point"}
}