{
  "type": "Feature",
  "properties": {
    "addr:full":"41012 Carpi Carpi Modena 41012",
    "addr:postcode":"41012;41012",
    "iso:country":"IT",
    "sg:address":"41012 Carpi",
    "sg:city":"Carpi",
    "sg:orig_category":"Prodotti E Manufatti In Gomma",
    "sg:phone":"+39 059 641700",
    "sg:postcode":"41012",
    "sg:province":"Modena",
    "wof:name":"Mantovani Enzo & Paolo Srl",
    "wof:placetype":"venue"
},
  "geometry": {"coordinates":[10.8632650375,44.8377151489],"type":"Point"}
}