{
  "type": "Feature",
  "properties": {
    "iso:country":"IT",
    "sg:address":"Via Cinelli, 10/12 25063 Gardone Val Trompia",
    "sg:city":"Gardone Val Trompia",
    "sg:classifiers":[
        {
            "category":"Personal",
            "subcategory":"Skin Care",
            "type":"Services"
        }
    ],
    "sg:phone":"+39 030 891 2578",
    "sg:postcode":"25063",
    "sg:province":"Brescia",
    "sg:tags":[
        "rifles",
        "closed-season",
        "hunting",
        "rifle"
    ],
    "sg:website":"www.piotti.com",
    "wof:name":"Fratelli Piotti Snc",
    "wof:placetype":"venue"
},
  "geometry": {"coordinates":[10.188894,45.699978],"type":"Point"}
}