{
  "type": "Feature",
  "properties": {
    "iso:country":"IT",
    "sg:address":"23, Via Castellana 31038 Paese",
    "sg:city":"Paese",
    "sg:classifiers":[
        {
            "category":"Real Estate",
            "subcategory":"Surveying",
            "type":"Services"
        }
    ],
    "sg:phone":"+39 0422 959872",
    "sg:postcode":"31038",
    "sg:province":"Treviso",
    "sg:tags":[
        "equipment",
        "material",
        "good",
        "-",
        "handling"
    ],
    "wof:name":"Miozzo S.r.l.",
    "wof:placetype":"venue"
},
  "geometry": {"coordinates":[12.131664,45.67886],"type":"Point"}
}