{
  "type": "Feature",
  "properties": {
    "iso:country":"IT",
    "sg:address":"41012 Carpi",
    "sg:city":"Carpi",
    "sg:orig_category":"Materiali Edili",
    "sg:phone":"+39 059 687233",
    "sg:postcode":"41012",
    "sg:province":"Modena",
    "wof:name":"Fabbrica Laterizi Carpi (s.r.l.)",
    "wof:placetype":"venue"
},
  "geometry": {"coordinates":[10.895595,44.797421],"type":"Point"}
}