{
  "type": "Feature",
  "properties": {
    "iso:country":"IT",
    "sg:address":"15, Via Pralongo 31050 Vedelago",
    "sg:city":"Vedelago",
    "sg:classifiers":[
        {
            "category":"Professional",
            "subcategory":"Engineering",
            "type":"Services"
        }
    ],
    "sg:phone":"+39 0423 401929",
    "sg:postcode":"31050",
    "sg:province":"Treviso",
    "sg:tags":[
        "machine",
        "-",
        "mechanical"
    ],
    "wof:name":"Techmek S.r.l",
    "wof:placetype":"venue"
},
  "geometry": {"coordinates":[12.019404,45.695004],"type":"Point"}
}