{
  "type": "Feature",
  "properties": {
    "addr:full":"21, Corso Dei Tintori 50122 Firenze Firenze Firenze 50122",
    "addr:postcode":"50122;50122",
    "addr:street":"Corso Dei Tintori",
    "iso:country":"IT",
    "sg:address":"21, Corso Dei Tintori 50122 Firenze",
    "sg:city":"Firenze",
    "sg:classifiers":[
        {
            "category":"Shopping",
            "subcategory":"Jewelry",
            "type":"Retail Goods"
        }
    ],
    "sg:phone":"+39 39055244911",
    "sg:postcode":"50122",
    "sg:province":"Firenze",
    "sg:tags":[
        "jewellery"
    ],
    "wof:name":"La Nouvelle Bague Spa",
    "wof:placetype":"venue"
},
  "geometry": {"coordinates":[11.260391,43.767395],"type":"Point"}
}