{
  "type": "Feature",
  "properties": {
    "iso:country":"IT",
    "sg:address":"23020 Piateda",
    "sg:city":"Piateda",
    "sg:orig_category":"Acciaierie E Fonderie",
    "sg:phone":"+39 0342 484200",
    "sg:postcode":"23020",
    "sg:province":"Sondrio",
    "wof:name":"Societa' Nordelettrica Sondel (s.p.a.)",
    "wof:placetype":"venue"
},
  "geometry": {"coordinates":[9.936111,46.160648],"type":"Point"}
}