{
  "type": "Feature",
  "properties": {
    "addr:full":"39012 Merano Merano Bolzano/Bozen 39012",
    "addr:postcode":"39012;39012",
    "iso:country":"IT",
    "sg:address":"39012 Merano",
    "sg:city":"Merano",
    "sg:orig_category":"Servizi E Lavori Per Edilizia E Lavori Pubblici. Servizi Ausiliari Di Sorveglianza, Manutenzione E Pulizia",
    "sg:phone":"+39 0473 231644",
    "sg:postcode":"39012",
    "sg:province":"Bolzano/Bozen",
    "wof:name":"Lanzendorfer Klaus",
    "wof:placetype":"venue"
},
  "geometry": {"coordinates":[11.183267,46.665592],"type":"Point"}
}