{
  "type": "Feature",
  "properties": {
    "iso:country":"IT",
    "sg:address":"00196 Roma",
    "sg:city":"Roma",
    "sg:orig_category":"Arredo Cucina Ed Elettrodomestici. Elettrodomestici",
    "sg:phone":"+39 06 3600 4677",
    "sg:postcode":"00196",
    "sg:province":"Roma",
    "wof:name":"Le Due Emme Sas",
    "wof:placetype":"venue"
},
  "geometry": {"coordinates":[12.463854,41.927189],"type":"Point"}
}