{
  "type": "Feature",
  "properties": {
    "addr:full":"20143 Milano Milano Milano 20143",
    "addr:postcode":"20143;20143",
    "iso:country":"IT",
    "sg:address":"20143 Milano",
    "sg:city":"Milano",
    "sg:orig_category":"Telecomunicazioni E Telefonia, Impianti, Apparecchi E Servizi. Acqua, Luce, Gas E Societa' Di Esercizio Pubblico. Servizi Vari Di Interesse Pubblico",
    "sg:phone":"+39 02 832 3454",
    "sg:postcode":"20143",
    "sg:province":"Milano",
    "wof:name":"Ramsis Phone Di El Habbal Mostafa",
    "wof:placetype":"venue"
},
  "geometry": {"coordinates":[9.16254,45.44846],"type":"Point"}
}