{
  "type": "Feature",
  "properties": {
    "iso:country":"IT",
    "sg:address":"20161 Milano",
    "sg:city":"Milano",
    "sg:orig_category":"Chiese Ed Associazioni Religiose",
    "sg:phone":"+39 02 646 9891",
    "sg:postcode":"20161",
    "sg:province":"Milano",
    "wof:name":"Oratorio Centro Giovanile San Luigi",
    "wof:placetype":"venue"
},
  "geometry": {"coordinates":[9.189205,45.460072],"type":"Point"}
}