{
  "type": "Feature",
  "properties": {
    "iso:country":"IT",
    "sg:address":"90143 Palermo",
    "sg:city":"Palermo",
    "sg:orig_category":"Banche E Servizi Finanziari",
    "sg:phone":"+39 091 348036",
    "sg:postcode":"90143",
    "sg:province":"Palermo",
    "wof:name":"Ferrara Calogero",
    "wof:placetype":"venue"
},
  "geometry": {"coordinates":[13.348673,38.135403],"type":"Point"}
}