{
  "type": "Feature",
  "properties": {
    "addr:full":"35025 Cartura Cartura Padova 35025",
    "addr:postcode":"35025;35025",
    "iso:country":"IT",
    "sg:address":"35025 Cartura",
    "sg:city":"Cartura",
    "sg:orig_category":"Servizi E Lavori Industria Chimica",
    "sg:phone":"+39 049 955 6190",
    "sg:postcode":"35025",
    "sg:province":"Padova",
    "wof:name":"Bi.sma. (s.n.c.)",
    "wof:placetype":"venue"
},
  "geometry": {"coordinates":[11.852488,45.299473],"type":"Point"}
}