{
  "type": "Feature",
  "properties": {
    "addr:full":"10151 Torino Torino Torino 10151",
    "addr:housenumber":"10151",
    "addr:postcode":"10151",
    "iso:country":"IT",
    "sg:address":"10151 Torino",
    "sg:city":"Torino",
    "sg:orig_category":"Carni, Salumi E Pesci. Zootecnia E Pesca, Allevamento Piccoli Animali",
    "sg:phone":"+39 011 739 5003",
    "sg:postcode":"10151",
    "sg:province":"Torino",
    "sg:website":"http://farfish.it",
    "wof:name":"Fa.r.fish Srl",
    "wof:placetype":"venue"
},
  "geometry": {"coordinates":[7.627122,45.107552],"type":"Point"}
}