{
  "type": "Feature",
  "properties": {
    "addr:full":"23900 Lecco Lecco Lecco 23900",
    "addr:postcode":"23900;23900",
    "iso:country":"IT",
    "sg:address":"23900 Lecco",
    "sg:city":"Lecco",
    "sg:orig_category":"Materiali Semilavorati Metallici",
    "sg:phone":"+39 0341 285595",
    "sg:postcode":"23900",
    "sg:province":"Lecco",
    "wof:name":"Metallurgica G. Berera (s.p.a.)",
    "wof:placetype":"venue"
},
  "geometry": {"coordinates":[9.403128,45.854862],"type":"Point"}
}