{
  "type": "Feature",
  "properties": {
    "iso:country":"IT",
    "sg:address":"15033 Casale Monferrato",
    "sg:city":"Casale Monferrato",
    "sg:orig_category":"Forniture Per Edilizia E Lavori Pubblici",
    "sg:phone":"+39 0142 76161",
    "sg:postcode":"15033",
    "sg:province":"Alessandria",
    "sg:website":"http://www.comedil.net",
    "wof:name":"Comedil Di Defrancisci & C. Snc",
    "wof:placetype":"venue"
},
  "geometry": {"coordinates":[8.4668769836,45.131816864],"type":"Point"}
}