{
  "type": "Feature",
  "properties": {
    "addr:full":"80022 Arzano Arzano Napoli 80022",
    "addr:postcode":"80022;80022",
    "iso:country":"IT",
    "sg:address":"80022 Arzano",
    "sg:city":"Arzano",
    "sg:orig_category":"Medicinali E Prodotti Parafarmaceutici. Prodotti Cosmetici E Da Toeletta",
    "sg:phone":"+39 081 573 8016",
    "sg:postcode":"80022",
    "sg:province":"Napoli",
    "wof:name":"Gipafarm Sas",
    "wof:placetype":"venue"
},
  "geometry": {"coordinates":[14.2686662674,40.9149971008],"type":"Point"}
}