{
  "type": "Feature",
  "properties": {
    "iso:country":"IT",
    "sg:address":"12042 Bra",
    "sg:city":"Bra",
    "sg:orig_category":"Automazione E Macchine Per Ufficio. Arredi Ed Attrezzature Per Attivita' Commerciali Ed Artigianali",
    "sg:phone":"+39 0172 412997",
    "sg:postcode":"12042",
    "sg:province":"Cuneo",
    "wof:name":"Biemme Ufficio Di Balocco E C. Snc",
    "wof:placetype":"venue"
},
  "geometry": {"coordinates":[7.496734,44.339779],"type":"Point"}
}