{
  "type": "Feature",
  "properties": {
    "iso:country":"IT",
    "sg:address":"40057 Cadriano",
    "sg:orig_category":"Forniture Per Attivita' Industriali",
    "sg:phone":"+39 051 765267",
    "sg:postcode":"40057",
    "sg:province":"Bologna",
    "wof:name":"Ferri Silvia",
    "wof:placetype":"venue"
},
  "geometry": {"coordinates":[11.3887643814,44.5498313904],"type":"Point"}
}