{
  "type": "Feature",
  "properties": {
    "iso:country":"IT",
    "sg:address":"V.le Passionisti 25 62019 Recanati",
    "sg:city":"Recanati",
    "sg:orig_category":"Energy Retention Screens, Textile",
    "sg:phone":"+39 071 75891",
    "sg:postcode":"62019",
    "sg:province":"Macerata",
    "sg:website":"www.acrilux.com",
    "wof:name":"Acrilux Spa",
    "wof:placetype":"venue"
},
  "geometry": {"coordinates":[13.534736,43.401249],"type":"Point"}
}