{
  "type": "Feature",
  "properties": {
    "iso:country":"IT",
    "sg:address":"37136 Verona",
    "sg:city":"Verona",
    "sg:orig_category":"Condizionamento Aria Impianti - Installazione E Manutenzione",
    "sg:phone":"+39 045 820 3950",
    "sg:postcode":"37136",
    "sg:province":"Verona",
    "sg:website":"http://albafrigor.com",
    "wof:name":"Albafrigor Srl",
    "wof:placetype":"venue"
},
  "geometry": {"coordinates":[10.955135,45.405033],"type":"Point"}
}