{
  "type": "Feature",
  "properties": {
    "iso:country":"IT",
    "sg:address":"80075 Forio",
    "sg:city":"Forio",
    "sg:orig_category":"Impiantistica E Prodotti Tecnologici Per Edilizia. Telecomunicazioni E Telefonia, Impianti, Apparecchi E Servizi",
    "sg:phone":"+39 081 507 1374",
    "sg:postcode":"80075",
    "sg:province":"Napoli",
    "sg:website":"http://www.geginformatica.it",
    "wof:name":"G. & G. Informatica",
    "wof:placetype":"venue"
},
  "geometry": {"coordinates":[13.865878,40.736115],"type":"Point"}
}