{
  "type": "Feature",
  "properties": {
    "iso:country":"IT",
    "sg:address":"25063 Gardone Val Trompia",
    "sg:city":"Gardone Val Trompia",
    "sg:orig_category":"Sport - Articoli E Forniture",
    "sg:phone":"+39 030 831109",
    "sg:postcode":"25063",
    "sg:province":"Brescia",
    "wof:name":"Telo' Renato",
    "wof:placetype":"venue"
},
  "geometry": {"coordinates":[10.183864,45.681904],"type":"Point"}
}