{
  "type": "Feature",
  "properties": {
    "addr:full":"51017 Pescia Pescia Pistoia 51017",
    "addr:postcode":"51017;51017",
    "iso:country":"IT",
    "sg:address":"51017 Pescia",
    "sg:city":"Pescia",
    "sg:orig_category":"Agricoltura, Orticoltura E Floricoltura. Articoli Da Regalo",
    "sg:phone":"+39 0572 451824",
    "sg:postcode":"51017",
    "sg:province":"Pistoia",
    "sg:website":"http://www.vivaifranchi.it",
    "wof:name":"Vivai Franchi S.s. Di Malucchi, Lavorini & Papini",
    "wof:placetype":"venue"
},
  "geometry": {"coordinates":[10.698516,43.944355],"type":"Point"}
}