{
  "type": "Feature",
  "properties": {
    "iso:country":"IT",
    "sg:address":"95041 Caltagirone",
    "sg:city":"Caltagirone",
    "sg:orig_category":"Articoli Da Regalo. Arte Ed Artigianato Artistico",
    "sg:phone":"+39 0933 57729",
    "sg:postcode":"95041",
    "sg:province":"Catania",
    "wof:name":"Ceramiche Artistiche Di Martino",
    "wof:placetype":"venue"
},
  "geometry": {"coordinates":[15.082664,37.563705],"type":"Point"}
}