{
  "type": "Feature",
  "properties": {
    "iso:country":"IT",
    "sg:address":"82100 Benevento",
    "sg:city":"Benevento",
    "sg:orig_category":"Ospedali E Servizi Sanitari",
    "sg:phone":"+39 0824 54780",
    "sg:postcode":"82100",
    "sg:province":"Benevento",
    "sg:website":"http://www.sanniotac.it",
    "wof:name":"Sannio Tac Srl",
    "wof:placetype":"venue"
},
  "geometry": {"coordinates":[14.775431,41.141388],"type":"Point"}
}