{
  "type": "Feature",
  "properties": {
    "iso:country":"IT",
    "sg:address":"25013 Carpenedolo",
    "sg:city":"Carpenedolo",
    "sg:classifiers":[
        {
            "category":"Manufacturing",
            "subcategory":"Leather Goods",
            "type":"Manufacturing & Wholesale Goods"
        }
    ],
    "sg:phone":"+39 030 996 5454",
    "sg:postcode":"25013",
    "sg:province":"Brescia",
    "sg:tags":[
        "goods",
        "clothing",
        "supply"
    ],
    "sg:website":"http://www.pbssoles.it",
    "wof:name":"P.b.s. Srl",
    "wof:placetype":"venue"
},
  "geometry": {"coordinates":[10.424191,45.341812],"type":"Point"}
}