{
  "type": "Feature",
  "properties": {
    "addr:full":"73020 Cutrofiano Cutrofiano Lecce 73020",
    "addr:postcode":"73020;73020",
    "iso:country":"IT",
    "sg:address":"73020 Cutrofiano",
    "sg:city":"Cutrofiano",
    "sg:orig_category":"Non-classified Establishments",
    "sg:phone":"+39 0836 544383",
    "sg:postcode":"73020",
    "sg:province":"Lecce",
    "wof:name":"Coli' Fratelli Snc",
    "wof:placetype":"venue"
},
  "geometry": {"coordinates":[18.256605,40.160469],"type":"Point"}
}