{
  "type": "Feature",
  "properties": {
    "addr:full":"28100 Novara Novara Novara 28100",
    "addr:postcode":"28100;28100",
    "iso:country":"IT",
    "sg:address":"28100 Novara",
    "sg:city":"Novara",
    "sg:orig_category":"Prodotti Finiti Stampati. Servizi Editoriali. Tempo Libero - Articoli E Forniture",
    "sg:phone":"+39 0321 628662",
    "sg:postcode":"28100",
    "sg:province":"Novara",
    "wof:name":"Carrera Rossella",
    "wof:placetype":"venue"
},
  "geometry": {"coordinates":[8.6066837311,45.4445457458],"type":"Point"}
}