{
  "type": "Feature",
  "properties": {
    "addr:full":"40138 Bologna Bologna Bologna 40138",
    "addr:postcode":"40138;40138",
    "iso:country":"IT",
    "sg:address":"40138 Bologna",
    "sg:city":"Bologna",
    "sg:orig_category":"Trattamenti Termici E Superficiali Metalli, Galvanotecnica",
    "sg:phone":"+39 051 533550",
    "sg:postcode":"40138",
    "sg:province":"Bologna",
    "sg:website":"http://www.rivit.it",
    "wof:name":"Peen Service",
    "wof:placetype":"venue"
},
  "geometry": {"coordinates":[11.421345,44.504715],"type":"Point"}
}