{
  "type": "Feature",
  "properties": {
    "addr:full":"20143 Milano Milano Milano 20143",
    "addr:postcode":"20143;20143",
    "iso:country":"IT",
    "sg:address":"20143 Milano",
    "sg:city":"Milano",
    "sg:orig_category":"Articoli Da Regalo. Forniture Per Uffici. Regalistica Aziendale",
    "sg:phone":"+39 02 813 6790",
    "sg:postcode":"20143",
    "sg:province":"Milano",
    "wof:name":"Fulker Srl",
    "wof:placetype":"venue"
},
  "geometry": {"coordinates":[9.1561,45.44252],"type":"Point"}
}