{
  "type": "Feature",
  "properties": {
    "addr:full":"106, Via Gramsci Antonio 96011 Augusta Augusta Siracusa 96011",
    "addr:housenumber":"106;96011",
    "addr:postcode":"96011",
    "addr:street":"Via Gramsci Antonio",
    "iso:country":"IT",
    "sg:address":"106, Via Gramsci Antonio 96011 Augusta",
    "sg:city":"Augusta",
    "sg:classifiers":[
        {
            "category":"Building & Trades",
            "subcategory":"Construction",
            "type":"Services"
        }
    ],
    "sg:phone":"+39 0931 511790",
    "sg:postcode":"96011",
    "sg:province":"Siracusa",
    "sg:tags":[
        "work",
        "public"
    ],
    "wof:name":"Augusta Impre. Con. - Imprese Consorziate",
    "wof:placetype":"venue"
},
  "geometry": {"coordinates":[15.28444,37.066483],"type":"Point"}
}