{
  "type": "Feature",
  "properties": {
    "iso:country":"IT",
    "sg:address":"41037 Mirandola",
    "sg:city":"Mirandola",
    "sg:orig_category":"Cartotecnica E Servizi. Forniture Per Uffici",
    "sg:phone":"+39 0535 26589",
    "sg:postcode":"41037",
    "sg:province":"Modena",
    "wof:name":"Duebi Di Baldini Silvia & C. Snc",
    "wof:placetype":"venue"
},
  "geometry": {"coordinates":[11.067537,44.871052],"type":"Point"}
}