{
  "type": "Feature",
  "properties": {
    "iso:country":"IT",
    "sg:address":"31038 Paese",
    "sg:city":"Padernello",
    "sg:orig_category":"Apparecchiature E Sistemi Per Magazzinaggio E Movimentazione",
    "sg:phone":"+39 0422 450721",
    "sg:postcode":"31038",
    "sg:province":"Treviso",
    "sg:website":"http://www.teknoimpianti.it",
    "wof:name":"Tekno Impianti Srl",
    "wof:placetype":"venue"
},
  "geometry": {"coordinates":[12.129053,45.676456],"type":"Point"}
}