{
  "type": "Feature",
  "properties": {
    "iso:country":"IT",
    "sg:address":"20124 Milano",
    "sg:city":"Milano",
    "sg:orig_category":"Articoli Da Regalo. Arte Ed Artigianato Artistico. Shopping. Regalistica Aziendale",
    "sg:phone":"+39 02 655 4440",
    "sg:postcode":"20124",
    "sg:province":"Milano",
    "wof:name":"Elleti (s.r.l.)",
    "wof:placetype":"venue"
},
  "geometry": {"coordinates":[9.198624,45.483387],"type":"Point"}
}