{
  "type": "Feature",
  "properties": {
    "addr:full":"Via Boccardo Gerolamo 1 16121 Genova Genova Genova 16121",
    "addr:housenumber":"1",
    "addr:postcode":"16121;16121",
    "addr:street":"Via Boccardo Gerolamo",
    "iso:country":"IT",
    "sg:address":"Via Boccardo Gerolamo 1 16121 Genova",
    "sg:city":"Genova",
    "sg:classifiers":[
        {
            "category":"Manufacturing",
            "subcategory":"Paper Products",
            "type":"Manufacturing & Wholesale Goods"
        }
    ],
    "sg:phone":"+39 010 55411",
    "sg:postcode":"16121",
    "sg:province":"Genova",
    "sg:tags":[
        "reel"
    ],
    "sg:website":"www.gapac.com",
    "wof:name":"Georgia Pacific Italia Srl",
    "wof:placetype":"venue"
},
  "geometry": {"coordinates":[8.9339885712,44.4070625305],"type":"Point"}
}