{
  "type": "Feature",
  "properties": {
    "iso:country":"IT",
    "sg:address":"Via Liguria, 4/6 42100 Reggio Emilia",
    "sg:classifiers":[
        {
            "category":"Utilities",
            "subcategory":"Telephone",
            "type":"Services"
        }
    ],
    "sg:phone":"+39 0522 518556",
    "sg:postcode":"42100",
    "sg:province":"Reggio Nell'Emilia",
    "sg:tags":[
        "accessory"
    ],
    "wof:name":"New Cell Top S.r.l.",
    "wof:placetype":"venue"
},
  "geometry": {"coordinates":[10.632305,44.71109],"type":"Point"}
}