{
  "type": "Feature",
  "properties": {
    "iso:country":"IT",
    "sg:address":"V Adige 6; Rubano; 35030",
    "sg:city":"Rubano",
    "sg:classifiers":[
        {
            "category":"Banks & Credit Unions",
            "subcategory":"Bank",
            "type":"Services"
        }
    ],
    "sg:phone":"+39 049 897 5162",
    "sg:postcode":"35030",
    "sg:province":"Padova",
    "wof:name":"Cassa Di Risparmio Di Padova & Rovi",
    "wof:placetype":"venue"
},
  "geometry": {"coordinates":[11.816498,45.424511],"type":"Point"}
}