{
  "type": "Feature",
  "properties": {
    "iso:country":"IT",
    "sg:address":"10127 Torino",
    "sg:city":"Torino",
    "sg:orig_category":"Macchine, Impianti Ed Attrezzature Industria Chimica. Attrezzature E Forniture Per Officine Riparazione E Servizi Ausiliari",
    "sg:phone":"+39 011 316 0140",
    "sg:postcode":"10127",
    "sg:province":"Torino",
    "wof:name":"Ati (s.r.l.)",
    "wof:placetype":"venue"
},
  "geometry": {"coordinates":[7.646509,45.019337],"type":"Point"}
}