{
  "type": "Feature",
  "properties": {
    "iso:country":"IT",
    "sg:address":"24050 Spirano",
    "sg:city":"Spirano",
    "sg:orig_category":"Imprese Edili",
    "sg:phone":"+39 035 877143",
    "sg:postcode":"24050",
    "sg:province":"Bergamo",
    "wof:name":"Edile Asperianum Srl",
    "wof:placetype":"venue"
},
  "geometry": {"coordinates":[9.669994,45.580616],"type":"Point"}
}