{
  "type": "Feature",
  "properties": {
    "iso:country":"IT",
    "sg:address":"73043 Copertino",
    "sg:city":"Copertino",
    "sg:orig_category":"Prodotti Finiti Stampati. Forniture E Materiali Per Imballaggio E Confezionamento. Forniture Per Attivita' Commerciali Ed Artigianali",
    "sg:phone":"+39 0832 948298",
    "sg:postcode":"73043",
    "sg:province":"Lecce",
    "wof:name":"Cairo Vincenzo Graficart",
    "wof:placetype":"venue"
},
  "geometry": {"coordinates":[18.0598659515,40.277797699],"type":"Point"}
}