{
  "type": "Feature",
  "properties": {
    "iso:country":"IT",
    "sg:address":"12012 Boves",
    "sg:city":"Boves",
    "sg:classifiers":[
        {
            "category":"Professional",
            "subcategory":"Printing & Photocopies",
            "type":"Services"
        }
    ],
    "sg:phone":"+39 0171 388931",
    "sg:postcode":"12012",
    "sg:province":"Cuneo",
    "sg:tags":[
        "packaging",
        "setting"
    ],
    "wof:name":"Fotolito Ponti Snc Di Ponti Luigi & C.",
    "wof:placetype":"venue"
},
  "geometry": {"coordinates":[7.533549,44.336967],"type":"Point"}
}