{
  "type": "Feature",
  "properties": {
    "iso:country":"IT",
    "sg:address":"Piazzle De Agostini 8; Milano",
    "sg:classifiers":[
        {
            "category":"Banks & Credit Unions",
            "subcategory":"Bank",
            "type":"Services"
        }
    ],
    "sg:phone":"+39 02 4895 4182",
    "wof:name":"Banca Popolare Commercio, E Industria Scarl",
    "wof:placetype":"venue"
},
  "geometry": {"coordinates":[9.155819,45.458023],"type":"Point"}
}