{
  "type": "Feature",
  "properties": {
    "iso:country":"IT",
    "sg:address":"00139 Roma",
    "sg:city":"Roma",
    "sg:orig_category":"Elettrodomestici. Forniture Alle Strutture Ricettive",
    "sg:phone":"+39 06 8864 1190",
    "sg:postcode":"00139",
    "sg:province":"Roma",
    "wof:name":"G.i.r.a.l.c. Sas",
    "wof:placetype":"venue"
},
  "geometry": {"coordinates":[12.564226,41.986916],"type":"Point"}
}