{
  "type": "Feature",
  "properties": {
    "addr:full":"44100 Ferrara Ferrara Ferrara 44100",
    "addr:postcode":"44100;44100",
    "iso:country":"IT",
    "sg:address":"44100 Ferrara",
    "sg:city":"Ferrara",
    "sg:classifiers":[
        {
            "category":"Health Services",
            "subcategory":"Health Practitioner",
            "type":"Services"
        }
    ],
    "sg:phone":"+39 0532 207823",
    "sg:postcode":"44100",
    "sg:province":"Ferrara",
    "sg:tags":[
        "medici"
    ],
    "wof:name":"Altieri Ermete",
    "wof:placetype":"venue"
},
  "geometry": {"coordinates":[11.635376,44.794403],"type":"Point"}
}