{
  "type": "Feature",
  "properties": {
    "addr:full":"1/c, Via Statale N.12 41036 Medolla Medolla Modena 41036",
    "addr:housenumber":"1 / c",
    "addr:postcode":"41036;41036",
    "addr:street":"Via Statale N.12",
    "iso:country":"IT",
    "sg:address":"1/c, Via Statale N.12 41036 Medolla",
    "sg:city":"Medolla",
    "sg:classifiers":[
        {
            "category":"Communications",
            "subcategory":"Television Station",
            "type":"Services"
        }
    ],
    "sg:phone":"+39 0535 611465",
    "sg:postcode":"41036",
    "sg:province":"Modena",
    "sg:tags":[
        "audio-visual"
    ],
    "wof:name":"Damitec Srl",
    "wof:placetype":"venue"
},
  "geometry": {"coordinates":[10.92522,44.647079],"type":"Point"}
}