{
  "type": "Feature",
  "properties": {
    "iso:country":"IT",
    "sg:address":"23, Via Serenza 22070 Capiago Intimiano",
    "sg:city":"Capiago",
    "sg:classifiers":[
        {
            "category":"Manufacturing",
            "subcategory":"Lumber",
            "type":"Manufacturing & Wholesale Goods"
        }
    ],
    "sg:phone":"+39 39031460184",
    "sg:postcode":"22070",
    "sg:province":"Como",
    "sg:tags":[
        "wood"
    ],
    "wof:name":"Bergna & Colombo (s.n.c.)",
    "wof:placetype":"venue"
},
  "geometry": {"coordinates":[9.126648,45.770004],"type":"Point"}
}