{
  "type": "Feature",
  "properties": {
    "iso:country":"IT",
    "sg:address":"Via Brancaleta 58100 Grosseto",
    "sg:city":"Grosseto",
    "sg:classifiers":[
        {
            "category":"Real Estate",
            "subcategory":"Architect",
            "type":"Services"
        }
    ],
    "sg:phone":"+39 0564 402707",
    "sg:postcode":"58100",
    "sg:province":"Grosseto",
    "sg:tags":[
        "textile",
        "clothing"
    ],
    "wof:name":"Tecnoprodotti Srl",
    "wof:placetype":"venue"
},
  "geometry": {"coordinates":[11.129478,42.805168],"type":"Point"}
}