{
  "type": "Feature",
  "properties": {
    "iso:country":"IT",
    "sg:address":"31033 Castelfranco Veneto",
    "sg:city":"Castelfranco Veneto",
    "sg:orig_category":"Macchine E Forniture Per Ecologia E Smaltimento Rifiuti",
    "sg:phone":"+39 0423 490722",
    "sg:postcode":"31033",
    "sg:province":"Treviso",
    "wof:name":"Bru.impianti Srl",
    "wof:placetype":"venue"
},
  "geometry": {"coordinates":[11.957829,45.676781],"type":"Point"}
}