{
  "type": "Feature",
  "properties": {
    "iso:country":"IT",
    "sg:address":"31033 Castelfranco Veneto",
    "sg:city":"Castelfranco Veneto",
    "sg:orig_category":"Ristorazione E Locali Pubblici Affini. Servizi Ausiliari Di Ristorazione E Di Intrattenimento",
    "sg:phone":"+39 0423 487101",
    "sg:postcode":"31033",
    "sg:province":"Treviso",
    "sg:website":"http://www.iltamburello.it",
    "wof:name":"Ristorante Tamburello",
    "wof:placetype":"venue"
},
  "geometry": {"coordinates":[11.974838,45.68837],"type":"Point"}
}