{
  "type": "Feature",
  "properties": {
    "addr:full":"Via Faverzani 13a 26046 San Daniele Po San Daniele Po Cremona 26046",
    "addr:housenumber":"13a",
    "addr:postcode":"26046;daniele;26046",
    "addr:street":"Via Faverzani;Po",
    "iso:country":"IT",
    "sg:address":"Via Faverzani 13a 26046 San Daniele Po",
    "sg:city":"San Daniele Po",
    "sg:classifiers":[
        {
            "category":"Manufacturing",
            "subcategory":"Food",
            "type":"Manufacturing & Wholesale Goods"
        }
    ],
    "sg:phone":"+39 0372 65544",
    "sg:postcode":"26046",
    "sg:province":"Cremona",
    "sg:tags":[
        "vinegar"
    ],
    "sg:website":"www.gallettisnc.it",
    "wof:name":"Galletti Di Galletti Aurelio & C Snc",
    "wof:placetype":"venue"
},
  "geometry": {"coordinates":[10.174338,45.067558],"type":"Point"}
}