{
  "type": "Feature",
  "properties": {
    "iso:country":"IT",
    "sg:address":"20136 Milano",
    "sg:city":"Milano",
    "sg:orig_category":"Agenzie Ippiche",
    "sg:phone":"+39 02 8942 2206",
    "sg:postcode":"20136",
    "sg:province":"Milano",
    "sg:website":"http://www.giocopiu.it",
    "wof:name":"Gioco Piu'",
    "wof:placetype":"venue"
},
  "geometry": {"coordinates":[9.182438,45.445236],"type":"Point"}
}