{
  "type": "Feature",
  "properties": {
    "iso:country":"IT",
    "sg:address":"Contrada Pantano 95032 Belpasso",
    "sg:city":"Belpasso",
    "sg:classifiers":[
        {
            "category":"Autos & Motor Vehicles",
            "subcategory":"Automobile Sales",
            "type":"Retail Goods"
        }
    ],
    "sg:phone":"+39 39095391813",
    "sg:postcode":"95032",
    "sg:province":"Catania",
    "sg:tags":[
        "industrial"
    ],
    "wof:name":"Comina Srl",
    "wof:placetype":"venue"
},
  "geometry": {"coordinates":[14.927204,37.520317],"type":"Point"}
}