{
  "type": "Feature",
  "properties": {
    "addr:full":"37139 Verona Verona Verona 37139",
    "addr:postcode":"37139;37139",
    "iso:country":"IT",
    "sg:address":"37139 Verona",
    "sg:city":"Verona",
    "sg:orig_category":"Gruppi Elettrogeni E Di Continuita'",
    "sg:phone":"+39 045 851 0988",
    "sg:postcode":"37139",
    "sg:province":"Verona",
    "wof:name":"Piccoli S. & C. Srl",
    "wof:placetype":"venue"
},
  "geometry": {"coordinates":[10.901408,45.438122],"type":"Point"}
}