{
  "type": "Feature",
  "properties": {
    "iso:country":"IT",
    "sg:address":"09040 Senorb\u00ec",
    "sg:orig_category":"Articoli Funerari",
    "sg:phone":"+39 070 980 9271",
    "sg:postcode":"09040",
    "sg:province":"Cagliari",
    "wof:name":"Alesir Color",
    "wof:placetype":"venue"
},
  "geometry": {"coordinates":[9.131278,39.536278],"type":"Point"}
}