{
  "type": "Feature",
  "properties": {
    "iso:country":"IT",
    "sg:address":"Piazza Amendola 1; Nocera",
    "sg:classifiers":[
        {
            "category":"Banks & Credit Unions",
            "subcategory":"Bank",
            "type":"Services"
        }
    ],
    "sg:phone":"+39 081 923766",
    "wof:name":"Banca Popolare Dell'irpinia Scarl",
    "wof:placetype":"venue"
},
  "geometry": {"coordinates":[14.641726,40.742947],"type":"Point"}
}