{
  "type": "Feature",
  "properties": {
    "addr:full":"3, Strada Val Nure 29100 Piacenza Piacenza Piacenza 29100",
    "addr:postcode":"29100;29100",
    "addr:street":"Strada Val Nure",
    "iso:country":"IT",
    "sg:address":"3, Strada Val Nure 29100 Piacenza",
    "sg:city":"Piacenza",
    "sg:classifiers":[
        {
            "category":"Manufacturing",
            "subcategory":"Metals",
            "type":"Manufacturing & Wholesale Goods"
        }
    ],
    "sg:phone":"+39 0523 454352",
    "sg:postcode":"29100",
    "sg:province":"Piacenza",
    "sg:tags":[
        "processing"
    ],
    "wof:name":"Zincatura E Metalli (s.p.a.)",
    "wof:placetype":"venue"
},
  "geometry": {"coordinates":[9.6864204407,45.029296875],"type":"Point"}
}