{
  "type": "Feature",
  "properties": {
    "iso:country":"IT",
    "sg:address":"17100 Savona",
    "sg:city":"Savona",
    "sg:orig_category":"Macchine, Impianti Ed Attrezzature Per Industria Alimentare E Bevande",
    "sg:phone":"+39 019 824925",
    "sg:postcode":"17100",
    "sg:province":"Savona",
    "wof:name":"Comadira",
    "wof:placetype":"venue"
},
  "geometry": {"coordinates":[7.779292,44.641384],"type":"Point"}
}