{
  "type": "Feature",
  "properties": {
    "iso:country":"IT",
    "sg:address":"38, Via Portobuffole' 31040 Mansue'",
    "sg:classifiers":[
        {
            "category":"Home & Garden",
            "subcategory":"Home Furnishings",
            "type":"Retail Goods"
        }
    ],
    "sg:phone":"+39 0422 801080",
    "sg:postcode":"31040",
    "sg:province":"Treviso",
    "sg:tags":[
        "household"
    ],
    "wof:name":"La Torniveneta Srl",
    "wof:placetype":"venue"
},
  "geometry": {"coordinates":[12.53703,45.824066],"type":"Point"}
}