{
  "type": "Feature",
  "properties": {
    "iso:country":"IT",
    "sg:address":"Loc San Faustino 28 43036 Fidenza",
    "sg:city":"Fidenza",
    "sg:orig_category":"Loading Equipment For Gases",
    "sg:phone":"+39 0524 82341",
    "sg:postcode":"43036",
    "sg:province":"Parma",
    "sg:website":"www.sgig.com",
    "wof:name":"Societa' Generale Impianti Gas Gasimpianti S.r.l.",
    "wof:placetype":"venue"
},
  "geometry": {"coordinates":[10.329548,44.807865],"type":"Point"}
}