{
  "type": "Feature",
  "properties": {
    "addr:full":"24048 Treviolo Treviolo Bergamo 24048",
    "addr:postcode":"24048;24048",
    "iso:country":"IT",
    "sg:address":"24048 Treviolo",
    "sg:city":"Treviolo",
    "sg:orig_category":"Agricoltura, Orticoltura E Floricoltura. Articoli Da Regalo. Shopping",
    "sg:phone":"+39 035 203440",
    "sg:postcode":"24048",
    "sg:province":"Bergamo",
    "wof:name":"Azienda Floricola Giulio Bombardieri Di Bombardieri Giorgio",
    "wof:placetype":"venue"
},
  "geometry": {"coordinates":[9.618894,45.676514],"type":"Point"}
}