{
  "type": "Feature",
  "properties": {
    "iso:country":"IT",
    "sg:address":"Via Mandrizzo 84084 Fisciano",
    "sg:city":"Fisciano",
    "sg:classifiers":[
        {
            "category":"Professional",
            "subcategory":"Engineering",
            "type":"Services"
        }
    ],
    "sg:phone":"+39 39089821931",
    "sg:postcode":"84084",
    "sg:province":"Salerno",
    "sg:tags":[
        "machine",
        "-",
        "mechanical"
    ],
    "wof:name":"C.m.p. Di D'auria R & C Snc",
    "wof:placetype":"venue"
},
  "geometry": {"coordinates":[14.868673,40.716183],"type":"Point"}
}