{
  "type": "Feature",
  "properties": {
    "iso:country":"IT",
    "sg:address":"15057 Tortona",
    "sg:city":"Tortona",
    "sg:orig_category":"Elettrotecnica Industriale, Prodotti E Apparecchiature",
    "sg:phone":"+39 0131 820102",
    "sg:postcode":"15057",
    "sg:province":"Alessandria",
    "wof:name":"Eurorent Italia Srl",
    "wof:placetype":"venue"
},
  "geometry": {"coordinates":[8.843711,44.900482],"type":"Point"}
}