{
  "type": "Feature",
  "properties": {
    "iso:country":"IT",
    "sg:address":"24035 Curno",
    "sg:city":"Curno",
    "sg:orig_category":"Forniture Per Attivita' Commerciali Ed Artigianali",
    "sg:phone":"+39 035 612023",
    "sg:postcode":"24035",
    "sg:province":"Bergamo",
    "wof:name":"Morgantina Di Puccio & Pesenti Snc",
    "wof:placetype":"venue"
},
  "geometry": {"coordinates":[9.6187801361,45.6937789917],"type":"Point"}
}