{
  "type": "Feature",
  "properties": {
    "iso:country":"IT",
    "sg:address":"00040 Rocca Priora",
    "sg:city":"Rocca Priora",
    "sg:orig_category":"Frigotecnica, Apparecchiature E Servizi. Climatizzazione E Condizionamento, Apparecchiature E Servizi",
    "sg:phone":"+39 06 940 6685",
    "sg:postcode":"00040",
    "sg:province":"Roma",
    "sg:website":"http://www.pmeparts.it",
    "wof:name":"P.m.e. Srl",
    "wof:placetype":"venue"
},
  "geometry": {"coordinates":[12.7473430634,41.7881813049],"type":"Point"}
}