{
  "type": "Feature",
  "properties": {
    "addr:full":"61, Via Fornace 13825 Valle Mosso Valle Mosso Biella 13825",
    "addr:postcode":"13825;13825",
    "addr:street":"Via Fornace;Mosso",
    "iso:country":"IT",
    "sg:address":"61, Via Fornace 13825 Valle Mosso",
    "sg:city":"Valle Mosso",
    "sg:classifiers":[
        {
            "category":"Shopping",
            "subcategory":"Crafts & Fabrics",
            "type":"Retail Goods"
        }
    ],
    "sg:phone":"+39 39015737608",
    "sg:postcode":"13825",
    "sg:province":"Biella",
    "wof:name":"Filatura Rivetti (s.r.l.)",
    "wof:placetype":"venue"
},
  "geometry": {"coordinates":[8.0856895447,45.6295585632],"type":"Point"}
}