{
  "type": "Feature",
  "properties": {
    "iso:country":"IT",
    "sg:address":"50, Via Di Rivale 30030 Pianiga",
    "sg:city":"Pianiga",
    "sg:classifiers":[
        {
            "category":"Shopping",
            "subcategory":"Computers & Home Electronics",
            "type":"Retail Goods"
        }
    ],
    "sg:phone":"+39 39041469222",
    "sg:postcode":"30030",
    "sg:province":"Venezia",
    "sg:tags":[
        "electronic",
        "electrical",
        "equipment"
    ],
    "wof:name":"Neon Stefanello (s.r.l.)",
    "wof:placetype":"venue"
},
  "geometry": {"coordinates":[12.029387,45.455723],"type":"Point"}
}