{
  "type": "Feature",
  "properties": {
    "addr:full":"83, Frazione Valtreara 60040 Genga Genga Ancona 60040",
    "addr:postcode":"60040;60040",
    "addr:street":"Frazione Valtreara",
    "iso:country":"IT",
    "sg:address":"83, Frazione Valtreara 60040 Genga",
    "sg:city":"Genga",
    "sg:classifiers":[
        {
            "category":"Wholesale",
            "subcategory":"Drugs",
            "type":"Manufacturing & Wholesale Goods"
        }
    ],
    "sg:phone":"+39 39073290348",
    "sg:postcode":"60040",
    "sg:province":"Ancona",
    "sg:tags":[
        "chemical",
        "pharmaceutical"
    ],
    "wof:name":"Nuova Sima S.r.l.",
    "wof:placetype":"venue"
},
  "geometry": {"coordinates":[12.9827270508,43.3906822205],"type":"Point"}
}