{
  "type": "Feature",
  "properties": {
    "iso:country":"IT",
    "sg:address":"40023 Castel Guelfo Di Bologna",
    "sg:city":"Castel Guelfo di Bologna",
    "sg:orig_category":"Macchine Utensili E Impianti",
    "sg:phone":"+39 0542 670427",
    "sg:postcode":"40023",
    "sg:province":"Bologna",
    "wof:name":"A.t.s. S.n.c.",
    "wof:placetype":"venue"
},
  "geometry": {"coordinates":[11.612316,44.435837],"type":"Point"}
}