{
  "type": "Feature",
  "properties": {
    "addr:full":"Via Allende, 11/19 50058 Signa Signa Firenze 50058",
    "addr:housenumber":"11 / 19",
    "addr:postcode":"50058;50058",
    "addr:street":"Via Allende",
    "iso:country":"IT",
    "sg:address":"Via Allende, 11/19 50058 Signa",
    "sg:city":"Signa",
    "sg:orig_category":"Hoisiery Goods",
    "sg:phone":"+39 055 879 1501",
    "sg:postcode":"50058",
    "sg:province":"Firenze",
    "wof:name":"Le Noir S.r.l",
    "wof:placetype":"venue"
},
  "geometry": {"coordinates":[11.149037,43.829517],"type":"Point"}
}