{
  "type": "Feature",
  "properties": {
    "addr:full":"Via Piave 12 06034 Foligno Foligno Perugia 06034",
    "addr:housenumber":"12",
    "addr:postcode":"06034;06034",
    "addr:street":"Via Piave",
    "iso:country":"IT",
    "sg:address":"Via Piave 12 06034 Foligno",
    "sg:city":"Foligno",
    "sg:classifiers":[
        {
            "category":"Banks & Credit Unions",
            "subcategory":"Investment Brokerage",
            "type":"Services"
        }
    ],
    "sg:phone":"+39 0742 348167",
    "sg:postcode":"06034",
    "sg:province":"Perugia",
    "sg:tags":[
        "bearing",
        "ball"
    ],
    "sg:website":"www.umbracus.com",
    "wof:name":"Umbra Cuscinetti Spa",
    "wof:placetype":"venue"
},
  "geometry": {"coordinates":[12.711814,42.958427],"type":"Point"}
}