{
  "type": "Feature",
  "properties": {
    "iso:country":"IT",
    "sg:address":"73100 Lecce",
    "sg:city":"Lecce",
    "sg:orig_category":"Servizi Per Aziende, Manifestazioni E Supporto Agli Scambi Commerciali",
    "sg:phone":"+39 0832 396293",
    "sg:postcode":"73100",
    "sg:province":"Lecce",
    "wof:name":"Studio Ipotecario Taurino",
    "wof:placetype":"venue"
},
  "geometry": {"coordinates":[18.186651,40.354172],"type":"Point"}
}