{
  "type": "Feature",
  "properties": {
    "iso:country":"IT",
    "sg:address":"00181 Roma",
    "sg:city":"Roma",
    "sg:orig_category":"Prodotti Di Base E Forniture Per Industria Alimentare E Bevande. Carta, Cartone E Prodotti Primari. Forniture Per Attivita' Commerciali Ed Artigianali",
    "sg:phone":"+39 06 780 4783",
    "sg:postcode":"00181",
    "sg:province":"Roma",
    "wof:name":"Zappia Antonio",
    "wof:placetype":"venue"
},
  "geometry": {"coordinates":[12.445930481,41.8621482849],"type":"Point"}
}