{
  "type": "Feature",
  "properties": {
    "iso:country":"IT",
    "sg:address":"Via Roma 96 35010 Carmignano Di Brenta",
    "sg:city":"Carmignano di Brenta",
    "sg:orig_category":"Bonbon Wrapping Paper",
    "sg:phone":"+39 049 942 3600",
    "sg:postcode":"35010",
    "sg:province":"Padova",
    "wof:name":"Cartiera Di Carmignano Spa",
    "wof:placetype":"venue"
},
  "geometry": {"coordinates":[11.711038,45.630974],"type":"Point"}
}