{
  "type": "Feature",
  "properties": {
    "addr:full":"41034 Finale Emilia Finale Emilia Modena 41034",
    "addr:postcode":"41034;41034",
    "iso:country":"IT",
    "sg:address":"41034 Finale Emilia",
    "sg:city":"Finale Emilia",
    "sg:classifiers":[
        {
            "category":"Manufacturing",
            "subcategory":"Motor Vehicles & Parts",
            "type":"Manufacturing & Wholesale Goods"
        }
    ],
    "sg:phone":"+39 0535 98372",
    "sg:postcode":"41034",
    "sg:province":"Modena",
    "sg:tags":[
        "spare",
        "vehicles",
        "component"
    ],
    "wof:name":"Unifer Srl",
    "wof:placetype":"venue"
},
  "geometry": {"coordinates":[11.2450876236,44.8258895874],"type":"Point"}
}