{
  "type": "Feature",
  "properties": {
    "addr:full":"10144 Torino Torino Torino 10144",
    "addr:postcode":"10144;10144",
    "iso:country":"IT",
    "sg:address":"10144 Torino",
    "sg:city":"Torino",
    "sg:orig_category":"Motori Ed Organi Di Trasmissione",
    "sg:phone":"+39 011 437 1553",
    "sg:postcode":"10144",
    "sg:province":"Torino",
    "sg:website":"http://www.idorossi.it",
    "wof:name":"Dott. Ido Rossi Snc Di Ferdinando Rossi & C.",
    "wof:placetype":"venue"
},
  "geometry": {"coordinates":[7.6644835472,45.4054107666],"type":"Point"}
}