{
  "type": "Feature",
  "properties": {
    "iso:country":"IT",
    "sg:address":"Via Coriano, 58 - Blocco 23/b 47900 Rimini",
    "sg:city":"Rimini",
    "sg:classifiers":[
        {
            "category":"Professional",
            "subcategory":"Employment Agencies",
            "type":"Services"
        }
    ],
    "sg:phone":"+39 0541 391001",
    "sg:postcode":"47900",
    "sg:province":"Rimini",
    "sg:tags":[
        "import"
    ],
    "sg:website":"www.exel.com",
    "wof:name":"Exel (italy) Spa",
    "wof:placetype":"venue"
},
  "geometry": {"coordinates":[12.566257,44.06078],"type":"Point"}
}