{
  "type": "Feature",
  "properties": {
    "iso:country":"IT",
    "sg:address":"20010 Pogliano Milanese",
    "sg:city":"Pogliano Milanese",
    "sg:orig_category":"Banche E Servizi Finanziari. Acqua, Luce, Gas E Societa' Di Esercizio Pubblico",
    "sg:phone":"+39 02 934 7901",
    "sg:postcode":"20010",
    "sg:province":"Milano",
    "wof:name":"Banca Di Legnano S.p.a.",
    "wof:placetype":"venue"
},
  "geometry": {"coordinates":[8.990255,45.5368],"type":"Point"}
}