{
  "type": "Feature",
  "properties": {
    "iso:country":"IT",
    "sg:address":"22100 Como",
    "sg:city":"Como",
    "sg:orig_category":"Automazione E Macchine Per Ufficio",
    "sg:phone":"+39 02 9645 0815",
    "sg:postcode":"22100",
    "sg:province":"Como",
    "wof:name":"Copying Srl",
    "wof:placetype":"venue"
},
  "geometry": {"coordinates":[9.092748,45.799282],"type":"Point"}
}