{
  "type": "Feature",
  "properties": {
    "iso:country":"IT",
    "sg:address":"98147 Messina",
    "sg:city":"Messina",
    "sg:orig_category":"Prodotti Alimentari",
    "sg:phone":"+39 090 371 7103",
    "sg:postcode":"98147",
    "sg:province":"Messina",
    "wof:name":"La Cucinotta Snc Di Raso Maria & Filippo",
    "wof:placetype":"venue"
},
  "geometry": {"coordinates":[15.5313177109,38.1703987122],"type":"Point"}
}