{
  "type": "Feature",
  "properties": {
    "iso:country":"IT",
    "sg:address":"31020 San Polo Di Piave",
    "sg:city":"San Polo di Piave",
    "sg:orig_category":"Prodotti Di Base E Forniture Per Industria Alimentare E Bevande. Vetro: Prodotti E Lavorazioni. Articoli Per Imballaggio E Confezionamento",
    "sg:phone":"+39 0422 805060",
    "sg:postcode":"31020",
    "sg:province":"Treviso",
    "wof:name":"Vetro Commerciale S.r.l.",
    "wof:placetype":"venue"
},
  "geometry": {"coordinates":[12.4146652222,45.7140274048],"type":"Point"}
}