{
  "type": "Feature",
  "properties": {
    "iso:country":"IT",
    "sg:address":"Via Martiri Della Romania 7 42010 Borzano",
    "sg:orig_category":"Castings Of Ductile Cast Iron",
    "sg:phone":"+39 0522 349017",
    "sg:postcode":"42010",
    "sg:province":"Reggio Nell'Emilia",
    "sg:website":"www.eurofluid.it",
    "wof:name":"Eurofluid Hydraulic S.r.l.",
    "wof:placetype":"venue"
},
  "geometry": {"coordinates":[10.627794,44.696228],"type":"Point"}
}