{
  "type": "Feature",
  "properties": {
    "iso:country":"IT",
    "sg:address":"Piazza Cavour, 33; Rimini; 47037",
    "sg:classifiers":[
        {
            "category":"Banks & Credit Unions",
            "subcategory":"Bank",
            "type":"Services"
        }
    ],
    "sg:phone":"+39 0541 52220",
    "wof:name":"Banca Nazionale Dell'agricoltura",
    "wof:placetype":"venue"
},
  "geometry": {"coordinates":[12.566544,44.060963],"type":"Point"}
}