{
  "type": "Feature",
  "properties": {
    "iso:country":"IT",
    "sg:address":"21, Via Arluno 20010 Casorezzo",
    "sg:city":"Arluno",
    "sg:classifiers":[
        {
            "category":"Wholesale",
            "subcategory":"Drugs",
            "type":"Manufacturing & Wholesale Goods"
        }
    ],
    "sg:phone":"+39 02 9029 6086",
    "sg:postcode":"20010",
    "sg:province":"Milano",
    "sg:tags":[
        "chemical",
        "pharmaceutical"
    ],
    "wof:name":"I.r.s.e.a. (s.p.a.)",
    "wof:placetype":"venue"
},
  "geometry": {"coordinates":[8.920108,45.498699],"type":"Point"}
}