{
  "type": "Feature",
  "properties": {
    "iso:country":"IT",
    "sg:address":"31055 Quinto Di Treviso",
    "sg:city":"Quinto di Treviso",
    "sg:orig_category":"Apparecchiature E Sistemi Per Magazzinaggio E Movimentazione",
    "sg:phone":"+39 0422 470326",
    "sg:postcode":"31055",
    "sg:province":"Treviso",
    "wof:name":"Puppinato Srl",
    "wof:placetype":"venue"
},
  "geometry": {"coordinates":[12.180581,45.669182],"type":"Point"}
}