{
  "type": "Feature",
  "properties": {
    "addr:full":"80133 Napoli Napoli Napoli 80133",
    "addr:housenumber":"80133",
    "addr:postcode":"80133",
    "iso:country":"IT",
    "sg:address":"80133 Napoli",
    "sg:city":"Napoli",
    "sg:orig_category":"Gioielleria, Oreficeria E Argenteria",
    "sg:phone":"+39 081 264388",
    "sg:postcode":"80133",
    "sg:province":"Napoli",
    "wof:name":"Ca.ma",
    "wof:placetype":"venue"
},
  "geometry": {"coordinates":[14.260309,40.845978],"type":"Point"}
}