{
  "type": "Feature",
  "properties": {
    "iso:country":"IT",
    "sg:address":"11, Via Fantoli Gaudenzio 20138 Milano",
    "sg:city":"Milano",
    "sg:classifiers":[
        {
            "category":"Shopping",
            "type":"Retail Goods"
        }
    ],
    "sg:phone":"+39 02 5801 8532",
    "sg:postcode":"20138",
    "sg:province":"Milano",
    "sg:tags":[
        "finished",
        "-",
        "metallic"
    ],
    "wof:name":"Meccanostamp Srl",
    "wof:placetype":"venue"
},
  "geometry": {"coordinates":[9.2519712448,45.4543190002],"type":"Point"}
}