{
  "type": "Feature",
  "properties": {
    "iso:country":"IT",
    "sg:address":"10144 Torino",
    "sg:city":"Torino",
    "sg:orig_category":"Spazzole Industriali",
    "sg:phone":"+39 011 437 5038",
    "sg:postcode":"10144",
    "sg:province":"Torino",
    "wof:name":"Martina Di Cassone L.",
    "wof:placetype":"venue"
},
  "geometry": {"coordinates":[7.661304,45.084644],"type":"Point"}
}