{
  "type": "Feature",
  "properties": {
    "addr:full":"40061 Minerbio Minerbio Bologna 40061",
    "addr:postcode":"40061;minerbio bologna 40061",
    "iso:country":"IT",
    "sg:address":"40061 Minerbio",
    "sg:city":"Minerbio",
    "sg:orig_category":"Autotrasporti",
    "sg:phone":"+39 051 6619 0011",
    "sg:postcode":"40061",
    "sg:province":"Bologna",
    "sg:website":"http://www.paginegialle.it/leduetorri-03",
    "wof:name":"Due Torri Spa",
    "wof:placetype":"venue"
},
  "geometry": {"coordinates":[11.498995,44.615402],"type":"Point"}
}