{
  "type": "Feature",
  "properties": {
    "iso:country":"IT",
    "sg:address":"Via P. Costa 33 48100 Ravenna",
    "sg:city":"Ravenna",
    "sg:classifiers":[
        {
            "category":"Shopping",
            "subcategory":"Books",
            "type":"Retail Goods"
        }
    ],
    "sg:phone":"+39 0544 217026",
    "sg:postcode":"48100",
    "sg:province":"Ravenna",
    "sg:website":"www.longo-editore.it",
    "wof:name":"Longo Angelo Editore Snc",
    "wof:placetype":"venue"
},
  "geometry": {"coordinates":[12.225,44.363888],"type":"Point"}
}