{
  "type": "Feature",
  "properties": {
    "addr:full":"80056 Ercolano Ercolano Napoli 80056",
    "addr:postcode":"80056;80056",
    "iso:country":"IT",
    "sg:address":"80056 Ercolano",
    "sg:city":"Ercolano",
    "sg:orig_category":"Sport - Articoli E Forniture",
    "sg:phone":"+39 081 739 0102",
    "sg:postcode":"80056",
    "sg:province":"Napoli",
    "wof:name":"Di Cicco Daniele",
    "wof:placetype":"venue"
},
  "geometry": {"coordinates":[14.349765,40.809799],"type":"Point"}
}