{
  "type": "Feature",
  "properties": {
    "iso:country":"IT",
    "sg:address":"00154 Roma",
    "sg:city":"Roma",
    "sg:orig_category":"Orologi Di Controllo E Sistemi Di Rilevazione Presenze",
    "sg:phone":"+39 06 575 5981",
    "sg:postcode":"00154",
    "sg:province":"Roma",
    "wof:name":"M.b. Sistemi Srl",
    "wof:placetype":"venue"
},
  "geometry": {"coordinates":[12.481548,41.871407],"type":"Point"}
}