{
  "type": "Feature",
  "properties": {
    "iso:country":"IT",
    "sg:address":"50059 Vinci",
    "sg:city":"Sovigliana",
    "sg:orig_category":"Articoli Da Regalo. Regalistica Aziendale",
    "sg:phone":"+39 0571 402131",
    "sg:postcode":"50059",
    "sg:province":"Firenze",
    "sg:website":"http://www.colorobbia.it",
    "wof:name":"Bitossi Diffusione Spa",
    "wof:placetype":"venue"
},
  "geometry": {"coordinates":[10.931823,43.72974],"type":"Point"}
}