{
  "type": "Feature",
  "properties": {
    "iso:country":"IT",
    "sg:address":"25077 Roe'volciano",
    "sg:orig_category":"Carni, Salumi E Pesci",
    "sg:phone":"+39 036 563225",
    "sg:postcode":"25077",
    "sg:province":"Brescia",
    "wof:name":"Biondo Carni Di Biondo Alberto & C. Snc",
    "wof:placetype":"venue"
},
  "geometry": {"coordinates":[10.495611,45.616112],"type":"Point"}
}