{
  "type": "Feature",
  "properties": {
    "iso:country":"IT",
    "sg:address":"43, Via Vecchia Madonna Sterpeto 70051 Barletta",
    "sg:city":"Barletta",
    "sg:classifiers":[
        {
            "category":"Personal",
            "subcategory":"Shoe Repair & Shine",
            "type":"Services"
        }
    ],
    "sg:phone":"+39 0883 331081",
    "sg:postcode":"70051",
    "sg:province":"Bari",
    "sg:tags":[
        "leather"
    ],
    "wof:name":"Calzaturificio Dima Shoes (s.n.c.)",
    "wof:placetype":"venue"
},
  "geometry": {"coordinates":[16.299006,41.31179],"type":"Point"}
}