{
  "type": "Feature",
  "properties": {
    "iso:country":"IT",
    "sg:address":"Via Canelli 104/106 10127 Torino",
    "sg:city":"Torino",
    "sg:orig_category":"Shears And Scissors",
    "sg:phone":"+39 011 663 5656",
    "sg:postcode":"10127",
    "sg:province":"Torino",
    "sg:website":"www.oscam.com",
    "wof:name":"Oscam Spa",
    "wof:placetype":"venue"
},
  "geometry": {"coordinates":[7.660756,45.020229],"type":"Point"}
}