{
  "type": "Feature",
  "properties": {
    "iso:country":"IT",
    "sg:address":"Via Gramsci 7 21050 Gorla Maggiore",
    "sg:city":"Gorla Maggiore",
    "sg:classifiers":[
        {
            "category":"Manufacturing",
            "subcategory":"Glass & Minerals",
            "type":"Manufacturing & Wholesale Goods"
        }
    ],
    "sg:phone":"+39 0331 604700",
    "sg:postcode":"21050",
    "sg:province":"Varese",
    "sg:tags":[
        "machine",
        "tool",
        "working"
    ],
    "wof:name":"Glass Progetti Di Mari Giorgio",
    "wof:placetype":"venue"
},
  "geometry": {"coordinates":[8.826385,45.817604],"type":"Point"}
}