{
  "type": "Feature",
  "properties": {
    "addr:full":"30175 Mestre Mestre Venezia 30175",
    "addr:postcode":"30175;30175",
    "addr:street":"Mestre Mestre Venezia",
    "iso:country":"IT",
    "sg:address":"30175 Mestre",
    "sg:city":"Mestre",
    "sg:orig_category":"Automazione E Macchine Per Ufficio",
    "sg:phone":"+39 041 531 4543",
    "sg:postcode":"30175",
    "sg:province":"Venezia",
    "wof:name":"Duplimatic Italiana (s.r.l.)",
    "wof:placetype":"venue"
},
  "geometry": {"coordinates":[12.23798,45.486485],"type":"Point"}
}