{
  "type": "Feature",
  "properties": {
    "addr:full":"47900 Rimini Rimini Rimini 47900",
    "addr:postcode":"47900;47900",
    "iso:country":"IT",
    "sg:address":"47900 Rimini",
    "sg:city":"Rimini",
    "sg:orig_category":"Tende Alla Veneziana E Verticali",
    "sg:phone":"+39 0541 740641",
    "sg:postcode":"47900",
    "sg:province":"Rimini",
    "wof:name":"F.lli Ghinelli Di Ghinelli Roberto & C. Sas",
    "wof:placetype":"venue"
},
  "geometry": {"coordinates":[12.550586,44.06802],"type":"Point"}
}