{
  "type": "Feature",
  "properties": {
    "iso:country":"IT",
    "sg:address":"21016 Luino",
    "sg:city":"Luino",
    "sg:classifiers":[
        {
            "category":"Home & Garden",
            "subcategory":"Furniture",
            "type":"Retail Goods"
        }
    ],
    "sg:phone":"+39 0332 530615",
    "sg:postcode":"21016",
    "sg:province":"Varese",
    "sg:tags":[
        "furnishing"
    ],
    "sg:website":"http://www.gognasas.it",
    "wof:name":"Studio Dell'arredamento Gogna Sas",
    "wof:placetype":"venue"
},
  "geometry": {"coordinates":[8.7773351669,45.9485244751],"type":"Point"}
}