{
  "type": "Feature",
  "properties": {
    "iso:country":"IT",
    "sg:address":"60031 Castelplanio",
    "sg:city":"Castelplanio",
    "sg:orig_category":"Carni, Salumi E Pesci. Zootecnia E Pesca, Allevamento Piccoli Animali",
    "sg:phone":"+39 0731 8101",
    "sg:postcode":"60031",
    "sg:province":"Ancona",
    "wof:name":"Co.dis.al. (s.r.l.)",
    "wof:placetype":"venue"
},
  "geometry": {"coordinates":[13.097695,43.493279],"type":"Point"}
}