{
  "type": "Feature",
  "properties": {
    "iso:country":"IT",
    "sg:address":"06059 Todi",
    "sg:city":"Todi",
    "sg:classifiers":[
        {
            "category":"Shopping",
            "subcategory":"Pets & Pet Supplies",
            "type":"Retail Goods"
        }
    ],
    "sg:phone":"+39 075 898 7128",
    "sg:postcode":"06059",
    "sg:province":"Perugia",
    "sg:tags":[
        "supplies",
        "breeding",
        "agriculture",
        "livestock"
    ],
    "wof:name":"Tecnoverde Servizi Srl",
    "wof:placetype":"venue"
},
  "geometry": {"coordinates":[12.415133,42.788071],"type":"Point"}
}