{
  "type": "Feature",
  "properties": {
    "iso:country":"IT",
    "sg:address":"89043 Grotteria",
    "sg:city":"Grotteria",
    "sg:orig_category":"Elettronica Professionale E Di Consumo. Automazione E Macchine Per Ufficio. Forniture Per Congressi, Fiere E Manifestazioni",
    "sg:phone":"+39 0964 419586",
    "sg:postcode":"89043",
    "sg:province":"Reggio Di Calabria",
    "wof:name":"Ocam Di Nigro Natale",
    "wof:placetype":"venue"
},
  "geometry": {"coordinates":[15.650137,38.114689],"type":"Point"}
}