{
  "type": "Feature",
  "properties": {
    "iso:country":"IT",
    "sg:address":"Via Tosco Romagnola 101/a, Fornacette, 56012 Calcinaia, Pi",
    "sg:city":"Calcinaia",
    "sg:classifiers":[
        {
            "category":"Banks & Credit Unions",
            "subcategory":"Bank",
            "type":"Services"
        }
    ],
    "sg:postcode":"56012",
    "sg:province":"Pisa",
    "wof:name":"Banca Di Credito Cooperativo Di Fornacette",
    "wof:placetype":"venue"
},
  "geometry": {"coordinates":[10.527763,43.678822],"type":"Point"}
}