{
  "type": "Feature",
  "properties": {
    "iso:country":"IT",
    "sg:address":"80142 Napoli",
    "sg:city":"Napoli",
    "sg:orig_category":"Automobili E Mezzi Di Trasporto",
    "sg:phone":"+39 081 554 3969",
    "sg:postcode":"80142",
    "sg:province":"Napoli",
    "wof:name":"Seatva S.p.a.",
    "wof:placetype":"venue"
},
  "geometry": {"coordinates":[14.201646,40.922722],"type":"Point"}
}