{
  "type": "Feature",
  "properties": {
    "iso:country":"IT",
    "sg:address":"79, Via Arona 28021 Borgomanero",
    "sg:city":"Borgomanero",
    "sg:classifiers":[
        {
            "category":"Professional",
            "subcategory":"Engineering",
            "type":"Services"
        }
    ],
    "sg:phone":"+39 39032281853",
    "sg:postcode":"28021",
    "sg:province":"Novara",
    "sg:tags":[
        "machine",
        "-",
        "mechanical"
    ],
    "wof:name":"Officina Meccanica Di Precisione Prandi G. (s.a.s.)",
    "wof:placetype":"venue"
},
  "geometry": {"coordinates":[8.468894,45.705292],"type":"Point"}
}