{
  "type": "Feature",
  "properties": {
    "addr:full":"20154 Milano Milano Milano 20154",
    "addr:postcode":"20154;20154",
    "iso:country":"IT",
    "sg:address":"20154 Milano",
    "sg:city":"Milano",
    "sg:orig_category":"Forniture Per Uffici",
    "sg:phone":"+39 02 3453 6252",
    "sg:postcode":"20154",
    "sg:province":"Milano",
    "wof:name":"Cartoleria Colombo Di Angelo Colombo & C. Snc",
    "wof:placetype":"venue"
},
  "geometry": {"coordinates":[9.173913002,45.479133606],"type":"Point"}
}