{
  "type": "Feature",
  "properties": {
    "iso:country":"IT",
    "sg:address":"11100 Aosta",
    "sg:city":"Aosta",
    "sg:orig_category":"Arredo Camera Letto E Complementi",
    "sg:phone":"+39 0165 368273",
    "sg:postcode":"11100",
    "sg:province":"Aosta",
    "wof:name":"I.n. Sas Di Dabroi Igor & C.",
    "wof:placetype":"venue"
},
  "geometry": {"coordinates":[7.339442,45.740784],"type":"Point"}
}