{
  "type": "Feature",
  "properties": {
    "addr:full":"Via Incerti 1/a 10069 Villar Perosa Villar Perosa Torino 10069",
    "addr:housenumber":"1 / a",
    "addr:postcode":"10069;10069",
    "addr:street":"Via Incerti",
    "iso:country":"IT",
    "sg:address":"Via Incerti 1/a 10069 Villar Perosa",
    "sg:city":"Villar Perosa",
    "sg:classifiers":[
        {
            "category":"Wholesale",
            "subcategory":"Construction Materials",
            "type":"Manufacturing & Wholesale Goods"
        }
    ],
    "sg:phone":"+39 0121 515840",
    "sg:postcode":"10069",
    "sg:province":"Torino",
    "sg:tags":[
        "fibre",
        "insulating",
        "ceramic",
        "refractory"
    ],
    "wof:name":"Iso-talco Societa' Cooperativa A R.l.",
    "wof:placetype":"venue"
},
  "geometry": {"coordinates":[7.686619,45.07056],"type":"Point"}
}