{
  "type": "Feature",
  "properties": {
    "iso:country":"IT",
    "sg:address":"84, Via Indipendenza 31030 Arcade",
    "sg:city":"Arcade",
    "sg:classifiers":[
        {
            "category":"Manufacturing",
            "subcategory":"Tools & Machinery",
            "type":"Manufacturing & Wholesale Goods"
        }
    ],
    "sg:phone":"+39 0422 874122",
    "sg:postcode":"31030",
    "sg:province":"Treviso",
    "sg:tags":[
        "environment",
        "equipment",
        "-"
    ],
    "wof:name":"Mion Costruzioni Meccaniche (s.r.l.)",
    "wof:placetype":"venue"
},
  "geometry": {"coordinates":[12.217218,45.777344],"type":"Point"}
}