{
  "type": "Feature",
  "properties": {
    "iso:country":"IT",
    "sg:address":"7, Via Rossa Guido 40069 Zola Predosa",
    "sg:city":"Zola",
    "sg:classifiers":[
        {
            "category":"Professional",
            "subcategory":"Engineering",
            "type":"Services"
        }
    ],
    "sg:phone":"+39 39051758268",
    "sg:postcode":"40069",
    "sg:province":"Bologna",
    "sg:tags":[
        "machine",
        "-",
        "mechanical"
    ],
    "wof:name":"Bavieri Alfeo S.r.l.",
    "wof:placetype":"venue"
},
  "geometry": {"coordinates":[11.245131,44.497417],"type":"Point"}
}