{
  "type": "Feature",
  "properties": {
    "iso:country":"IT",
    "sg:address":"Piazzale Aldo Moro; Bari; 70123",
    "sg:city":"Bari",
    "sg:classifiers":[
        {
            "category":"Banks & Credit Unions",
            "subcategory":"Bank",
            "type":"Services"
        }
    ],
    "sg:phone":"+39 080 521 0633",
    "sg:postcode":"70123",
    "sg:province":"Bari",
    "wof:name":"Istituto Bancario, San Paolo Di Torino Spa",
    "wof:placetype":"venue"
},
  "geometry": {"coordinates":[16.870197,41.118534],"type":"Point"}
}