{
  "type": "Feature",
  "properties": {
    "iso:country":"IT",
    "sg:address":"Via Locatelli 10; Verona",
    "sg:classifiers":[
        {
            "category":"Banks & Credit Unions",
            "subcategory":"Bank",
            "type":"Services"
        }
    ],
    "sg:phone":"+39 045 801 1077",
    "wof:name":"Banca San Paolo, Di Brescia Spa",
    "wof:placetype":"venue"
},
  "geometry": {"coordinates":[10.987279,45.432571],"type":"Point"}
}