{
  "type": "Feature",
  "properties": {
    "iso:country":"IT",
    "sg:address":"Via Gandino Giovanni Battista 60/37 10148 Torino",
    "sg:city":"Torino",
    "sg:classifiers":[
        {
            "category":"Shopping",
            "subcategory":"Hobbies, Toys, & Games",
            "type":"Retail Goods"
        }
    ],
    "sg:phone":"+39 011 220 2347",
    "sg:postcode":"10148",
    "sg:province":"Torino",
    "sg:tags":[
        "equipment",
        "machining",
        "mechanical"
    ],
    "wof:name":"Lamit Srl",
    "wof:placetype":"venue"
},
  "geometry": {"coordinates":[7.686619,45.07056],"type":"Point"}
}