{
  "type": "Feature",
  "properties": {
    "iso:country":"IT",
    "sg:address":"6, Via Buonarroti Michelangelo 20016 Pero",
    "sg:city":"Pero",
    "sg:classifiers":[
        {
            "category":"Manufacturing",
            "subcategory":"Textiles",
            "type":"Manufacturing & Wholesale Goods"
        }
    ],
    "sg:phone":"+39 39023535153",
    "sg:postcode":"20016",
    "sg:province":"Milano",
    "sg:tags":[
        "leather",
        "raw",
        "material",
        "-"
    ],
    "wof:name":"Portolano Pelli Snc",
    "wof:placetype":"venue"
},
  "geometry": {"coordinates":[9.078519,45.502506],"type":"Point"}
}