{
  "type": "Feature",
  "properties": {
    "iso:country":"IT",
    "sg:address":"98, Via Pace 36072 Chiampo",
    "sg:city":"Chiampo",
    "sg:classifiers":[
        {
            "category":"Manufacturing",
            "subcategory":"Textiles",
            "type":"Manufacturing & Wholesale Goods"
        }
    ],
    "sg:phone":"+39 0444 625050",
    "sg:postcode":"36072",
    "sg:province":"Vicenza",
    "sg:tags":[
        "leather",
        "raw",
        "material",
        "-"
    ],
    "wof:name":"Lavorazione Pelli Lomar Srl",
    "wof:placetype":"venue"
},
  "geometry": {"coordinates":[11.291324,45.538982],"type":"Point"}
}