{
  "type": "Feature",
  "properties": {
    "addr:full":"1, Via Flaminia 06023 Gualdo Tadino Gualdo Tadino Perugia 06023",
    "addr:postcode":"06023;06023",
    "addr:street":"Via Flaminia",
    "iso:country":"IT",
    "sg:address":"1, Via Flaminia 06023 Gualdo Tadino",
    "sg:city":"Gualdo Tadino",
    "sg:classifiers":[
        {
            "category":"Shopping",
            "subcategory":"Crafts & Fabrics",
            "type":"Retail Goods"
        }
    ],
    "sg:phone":"+39 390 759 1471",
    "sg:postcode":"06023",
    "sg:province":"Perugia",
    "sg:tags":[
        "ceramic"
    ],
    "wof:name":"Tagina Ceramiche D'arte S.p.a.",
    "wof:placetype":"venue"
},
  "geometry": {"coordinates":[12.786714,43.209297],"type":"Point"}
}