{
  "type": "Feature",
  "properties": {
    "iso:country":"IT",
    "sg:address":"Via Goggetta 60024 Filottrano",
    "sg:city":"Filottrano",
    "sg:classifiers":[
        {
            "category":"Shopping",
            "subcategory":"Clothing, Apparel, & Fashions",
            "type":"Retail Goods"
        }
    ],
    "sg:phone":"+39 071 722 0925",
    "sg:postcode":"60024",
    "sg:province":"Ancona",
    "sg:tags":[
        "clothes"
    ],
    "wof:name":"Lardini Srl",
    "wof:placetype":"venue"
},
  "geometry": {"coordinates":[13.352367,43.440117],"type":"Point"}
}