{
  "type": "Feature",
  "properties": {
    "addr:full":"25023 Gottolengo Gottolengo Brescia 25023",
    "addr:postcode":"25023;25023",
    "iso:country":"IT",
    "sg:address":"25023 Gottolengo",
    "sg:city":"Gottolengo",
    "sg:orig_category":"Non-classified Establishments",
    "sg:phone":"+39 030 951 7586",
    "sg:postcode":"25023",
    "sg:province":"Brescia",
    "wof:name":"Gottinghen (s.p.a.)",
    "wof:placetype":"venue"
},
  "geometry": {"coordinates":[10.256757,45.30563],"type":"Point"}
}