{
  "type": "Feature",
  "properties": {
    "iso:country":"IT",
    "sg:address":"20124 Milano",
    "sg:city":"Milano",
    "sg:orig_category":"Servizi Al Turismo. Servizi Ausiliari Per Il Trasporto",
    "sg:phone":"+39 02 676471",
    "sg:postcode":"20124",
    "sg:province":"Milano",
    "wof:name":"Canmar - Contship Agencies Srl",
    "wof:placetype":"venue"
},
  "geometry": {"coordinates":[9.20004,45.48394],"type":"Point"}
}