{
  "type": "Feature",
  "properties": {
    "iso:country":"IT",
    "sg:address":"09128 Cagliari",
    "sg:city":"Cagliari",
    "sg:orig_category":"Tessuti E Stoffe. Filati E Materie Prime Tessili",
    "sg:phone":"+39 070 654542",
    "sg:postcode":"09128",
    "sg:province":"Cagliari",
    "wof:name":"Bioshop Di Trogu K. E Birocchi R. Snc",
    "wof:placetype":"venue"
},
  "geometry": {"coordinates":[9.1222810745,39.2177047729],"type":"Point"}
}