{
  "type": "Feature",
  "properties": {
    "iso:country":"IT",
    "sg:address":"Piazza C.battisti 35; Traversetolo; 43029",
    "sg:city":"Traversetolo",
    "sg:classifiers":[
        {
            "category":"Banks & Credit Unions",
            "subcategory":"Bank",
            "type":"Services"
        }
    ],
    "sg:phone":"+39 0521 341250",
    "sg:postcode":"43029",
    "sg:province":"Parma",
    "wof:name":"Banca Popolare Di Verona",
    "wof:placetype":"venue"
},
  "geometry": {"coordinates":[10.381138,44.641651],"type":"Point"}
}