{
  "type": "Feature",
  "properties": {
    "addr:full":"Via Friuli 19 24044 Dalmine Dalmine Bergamo 24044",
    "addr:housenumber":"19",
    "addr:postcode":"24044;24044",
    "addr:street":"Via Friuli",
    "iso:country":"IT",
    "sg:address":"Via Friuli 19 24044 Dalmine",
    "sg:city":"Dalmine",
    "sg:classifiers":[
        {
            "category":"Military Area",
            "subcategory":"Army Base",
            "type":"Public Place"
        }
    ],
    "sg:phone":"+39 035 416 5607",
    "sg:postcode":"24044",
    "sg:province":"Bergamo",
    "sg:tags":[
        "filter",
        "analysis"
    ],
    "sg:website":"www.3vcogeim.com",
    "wof:name":"3v Cogeim Spa",
    "wof:placetype":"venue"
},
  "geometry": {"coordinates":[9.629004,45.64996],"type":"Point"}
}