{
  "type": "Feature",
  "properties": {
    "iso:country":"IT",
    "sg:address":"34125 Trieste",
    "sg:city":"Trieste",
    "sg:classifiers":[
        {
            "category":"Utilities",
            "subcategory":"Mobile Phone",
            "type":"Services"
        }
    ],
    "sg:phone":"+39 040 760 6159",
    "sg:postcode":"34125",
    "sg:province":"Trieste",
    "sg:tags":[
        "equipment",
        "telecommunication",
        "systems",
        "telephony"
    ],
    "wof:name":"Alex Trade Srl",
    "wof:placetype":"venue"
},
  "geometry": {"coordinates":[13.781603,45.651749],"type":"Point"}
}