{
  "type": "Feature",
  "properties": {
    "iso:country":"IT",
    "sg:address":"80122 Napoli",
    "sg:city":"Napoli",
    "sg:classifiers":[
        {
            "category":"Health Services",
            "subcategory":"Health Practitioner",
            "type":"Services"
        }
    ],
    "sg:phone":"+39 081 664659",
    "sg:postcode":"80122",
    "sg:province":"Napoli",
    "sg:tags":[
        "medici"
    ],
    "wof:name":"Sodano Antonio",
    "wof:placetype":"venue"
},
  "geometry": {"coordinates":[14.2267723083,40.8348846436],"type":"Point"}
}