{
  "type": "Feature",
  "properties": {
    "iso:country":"IT",
    "sg:address":"Via Cavatorta 8-z. I. Cavatorta 48010 Cotignola",
    "sg:city":"Cotignola",
    "sg:classifiers":[
        {
            "category":"Utilities",
            "subcategory":"Sewage",
            "type":"Services"
        }
    ],
    "sg:phone":"+39 0545 288401",
    "sg:postcode":"48010",
    "sg:province":"Ravenna",
    "sg:tags":[
        "plant",
        "digestion",
        "tank",
        "equipment",
        "treatment",
        "sludge"
    ],
    "sg:website":"www.inditel.com",
    "wof:name":"Tecofil Srl",
    "wof:placetype":"venue"
},
  "geometry": {"coordinates":[12.196571,44.41573],"type":"Point"}
}