{
  "type": "Feature",
  "properties": {
    "addr:full":"25060 Lodrino Lodrino Brescia 25060",
    "addr:postcode":"25060;25060",
    "iso:country":"IT",
    "sg:address":"25060 Lodrino",
    "sg:city":"Lodrino",
    "sg:orig_category":"Cromatura E Nichelatura",
    "sg:phone":"+39 030 850059",
    "sg:postcode":"25060",
    "sg:province":"Brescia",
    "wof:name":"Baston Nord Di Morabito Nicola & C. Snc",
    "wof:placetype":"venue"
},
  "geometry": {"coordinates":[10.276831,45.719738],"type":"Point"}
}