{
  "type": "Feature",
  "properties": {
    "iso:country":"IT",
    "sg:address":"58, Via Billo' Erri 41043 Formigine",
    "sg:city":"Formigine",
    "sg:classifiers":[
        {
            "category":"Food & Beverages",
            "subcategory":"Groceries & Convenience Stores",
            "type":"Retail Goods"
        }
    ],
    "sg:phone":"+39 39059550069",
    "sg:postcode":"41043",
    "sg:province":"Modena",
    "sg:tags":[
        "product",
        "related"
    ],
    "wof:name":"Cavazzuti G. & Figli (s.p.a.)",
    "wof:placetype":"venue"
},
  "geometry": {"coordinates":[10.8604831696,44.5893325806],"type":"Point"}
}