{
  "type": "Feature",
  "properties": {
    "addr:full":"Via Degli Olmi 16/5, 61100 Pesaro, Pu Pesaro Pesaro E Urbino 61100",
    "addr:housenumber":"16 / 5",
    "addr:postcode":"61100;pu;61100",
    "addr:street":"Via Degli Olmi",
    "iso:country":"IT",
    "sg:address":"Via Degli Olmi 16/5, 61100 Pesaro, Pu",
    "sg:city":"Pesaro",
    "sg:classifiers":[
        {
            "category":"Banks & Credit Unions",
            "subcategory":"Bank",
            "type":"Services"
        }
    ],
    "sg:postcode":"61100",
    "sg:province":"Pesaro E Urbino",
    "wof:name":"Centrale Spa",
    "wof:placetype":"venue"
},
  "geometry": {"coordinates":[12.857252,43.901241],"type":"Point"}
}