{
  "type": "Feature",
  "properties": {
    "iso:country":"IT",
    "sg:address":"20063 Cernusco Sul Naviglio",
    "sg:city":"Cernusco sul Naviglio",
    "sg:orig_category":"Articoli Medico-sanitari Ed Ortopedici",
    "sg:phone":"+39 02 923 2380",
    "sg:postcode":"20063",
    "sg:province":"Milano",
    "wof:name":"Amplifon (s.p.a.)",
    "wof:placetype":"venue"
},
  "geometry": {"coordinates":[9.329873,45.488522],"type":"Point"}
}