{
  "type": "Feature",
  "properties": {
    "iso:country":"IT",
    "sg:address":"46019 Viadana",
    "sg:city":"Viadana",
    "sg:orig_category":"Macchine, Impianti Ed Attrezzature Per Abbigliamento E Pelletterie",
    "sg:phone":"+39 0375 781910",
    "sg:postcode":"46019",
    "sg:province":"Mantova",
    "wof:name":"Paglia Luigi",
    "wof:placetype":"venue"
},
  "geometry": {"coordinates":[10.529956,44.930599],"type":"Point"}
}