{
  "type": "Feature",
  "properties": {
    "iso:country":"IT",
    "sg:address":"Via Fonda Di Mezzana 59100 Prato",
    "sg:city":"Mezzana",
    "sg:classifiers":[
        {
            "category":"Shopping",
            "subcategory":"Crafts & Fabrics",
            "type":"Retail Goods"
        }
    ],
    "sg:phone":"+39 0574 592251",
    "sg:postcode":"59100",
    "sg:province":"Prato",
    "wof:name":"Spinning (s.r.l.)",
    "wof:placetype":"venue"
},
  "geometry": {"coordinates":[11.1001787186,43.8483543396],"type":"Point"}
}