{
  "type": "Feature",
  "properties": {
    "iso:country":"IT",
    "sg:address":"98124 Messina",
    "sg:city":"Messina",
    "sg:orig_category":"Legno E Semilavorati. Materiali Edili",
    "sg:phone":"+39 090 635313",
    "sg:postcode":"98124",
    "sg:province":"Messina",
    "wof:name":"Millo Salvatore Sas",
    "wof:placetype":"venue"
},
  "geometry": {"coordinates":[15.292408,37.858902],"type":"Point"}
}