{
  "type": "Feature",
  "properties": {
    "addr:full":"50013 Campi Bisenzio Campi Bisenzio Firenze 50013",
    "addr:postcode":"50013;50013",
    "addr:street":"Bisenzio",
    "iso:country":"IT",
    "sg:address":"50013 Campi Bisenzio",
    "sg:city":"Campi Bisenzio",
    "sg:orig_category":"Filati E Materie Prime Tessili",
    "sg:phone":"+39 055 895 3060",
    "sg:postcode":"50013",
    "sg:province":"Firenze",
    "wof:name":"Myfil (s.r.l.)",
    "wof:placetype":"venue"
},
  "geometry": {"coordinates":[11.1227388382,43.8308639526],"type":"Point"}
}