{
  "type": "Feature",
  "properties": {
    "iso:country":"IT",
    "sg:address":"04011 Aprilia",
    "sg:city":"Aprilia",
    "sg:orig_category":"Manufacturers: Prefabbricati",
    "sg:phone":"+39 06 925 8218",
    "sg:postcode":"04011",
    "sg:province":"Latina",
    "wof:name":"La Pontina Impianti Sas Di Campo Luciano",
    "wof:placetype":"venue"
},
  "geometry": {"coordinates":[12.690533,41.551586],"type":"Point"}
}