{
  "type": "Feature",
  "properties": {
    "iso:country":"IT",
    "sg:address":"13, Via Industria 23037 Tirano",
    "sg:city":"Tirano",
    "sg:classifiers":[
        {
            "category":"Manufacturing",
            "subcategory":"Motor Vehicles & Parts",
            "type":"Manufacturing & Wholesale Goods"
        }
    ],
    "sg:phone":"+39 0342 702451",
    "sg:postcode":"23037",
    "sg:province":"Sondrio",
    "sg:tags":[
        "engine"
    ],
    "wof:name":"Selva (s.p.a.)",
    "wof:placetype":"venue"
},
  "geometry": {"coordinates":[10.16081,46.213226],"type":"Point"}
}