{
  "type": "Feature",
  "properties": {
    "addr:full":"55012 Capannori Capannori Lucca 55012",
    "addr:postcode":"55012;55012",
    "iso:country":"IT",
    "sg:address":"55012 Capannori",
    "sg:city":"Capannori",
    "sg:orig_category":"Prodotti Vari In Metallo. Articoli Per Imballaggio E Confezionamento",
    "sg:phone":"+39 0583 935395",
    "sg:postcode":"55012",
    "sg:province":"Lucca",
    "sg:website":"http://www.fenili.it",
    "wof:name":"Officine Meccaniche Fenili Snc",
    "wof:placetype":"venue"
},
  "geometry": {"coordinates":[10.5739765167,43.8586578369],"type":"Point"}
}