{
  "type": "Feature",
  "properties": {
    "iso:country":"IT",
    "sg:address":"61022 Colbordolo",
    "sg:city":"Colbordolo",
    "sg:orig_category":"Vetri, Cristalli E Specchi - Lavorazione E Trattamenti",
    "sg:phone":"+39 0721 49441",
    "sg:postcode":"61022",
    "sg:province":"Pesaro E Urbino",
    "sg:website":"http://www.curvet.it",
    "wof:name":"Curvet Spa",
    "wof:placetype":"venue"
},
  "geometry": {"coordinates":[12.753956,43.850807],"type":"Point"}
}