{
  "type": "Feature",
  "properties": {
    "iso:country":"IT",
    "sg:address":"10024 Moncalieri",
    "sg:city":"Moncalieri",
    "sg:orig_category":"Cartotecnica E Servizi. Composizione, Stampa E Confezione. Forniture E Prodotti Informatici. Forniture Per Congressi, Fiere E Manifestazioni",
    "sg:phone":"+39 011 682 9591",
    "sg:postcode":"10024",
    "sg:province":"Torino",
    "wof:name":"Card & Label Snc Di Besusso Luca E Fabris Fabio",
    "wof:placetype":"venue"
},
  "geometry": {"coordinates":[7.671287,45.002331],"type":"Point"}
}