{
  "type": "Feature",
  "properties": {
    "addr:full":"15067 Novi Ligure Novi Ligure Alessandria 15067",
    "addr:postcode":"15067;15067",
    "iso:country":"IT",
    "sg:address":"15067 Novi Ligure",
    "sg:city":"Novi Ligure",
    "sg:orig_category":"Pulizia Caldaie E Spazzacamini",
    "sg:phone":"+39 0143 73495",
    "sg:postcode":"15067",
    "sg:province":"Alessandria",
    "wof:name":"Lorito Luciano",
    "wof:placetype":"venue"
},
  "geometry": {"coordinates":[8.7907409668,44.7670783997],"type":"Point"}
}