{
  "type": "Feature",
  "properties": {
    "iso:country":"IT",
    "sg:address":"34, Via Calessani 31027 Spresiano",
    "sg:city":"Spresiano",
    "sg:orig_category":"Miscellaneous Products",
    "sg:phone":"+39 0422 725231",
    "sg:postcode":"31027",
    "sg:province":"Treviso",
    "wof:name":"Illcof Industria Lavorazione Legno E Cofani Funebr",
    "wof:placetype":"venue"
},
  "geometry": {"coordinates":[12.2652873993,45.7868347168],"type":"Point"}
}