{
  "type": "Feature",
  "properties": {
    "iso:country":"IT",
    "sg:address":"16043 Chiavari",
    "sg:city":"Chiavari",
    "sg:orig_category":"Abbigliamento Alta Moda E Stilisti - Boutiques",
    "sg:phone":"+39 0185 301011",
    "sg:postcode":"16043",
    "sg:province":"Genova",
    "wof:name":"A.m.r. Snc",
    "wof:placetype":"venue"
},
  "geometry": {"coordinates":[9.322735,44.318352],"type":"Point"}
}