{
  "type": "Feature",
  "properties": {
    "addr:full":"41100 Modena Modena Modena 41100",
    "addr:postcode":"41100;41100",
    "iso:country":"IT",
    "sg:address":"41100 Modena",
    "sg:city":"Modena",
    "sg:orig_category":"Vigilanza E Sorveglianza",
    "sg:phone":"+39 059 211122",
    "sg:postcode":"41100",
    "sg:province":"Modena",
    "sg:website":"http://www.sistemi-integrati.com",
    "wof:name":"Istituto Di Vigilanza Colli",
    "wof:placetype":"venue"
},
  "geometry": {"coordinates":[10.93236,44.653511],"type":"Point"}
}