{
  "type": "Feature",
  "properties": {
    "addr:full":"Via Anzalone 95024 Acireale Acireale Catania 95024",
    "addr:postcode":"95024;95024",
    "addr:street":"Via Anzalone",
    "iso:country":"IT",
    "sg:address":"Via Anzalone 95024 Acireale",
    "sg:city":"Acireale",
    "sg:classifiers":[
        {
            "category":"Farming",
            "subcategory":"Livestock Farm",
            "type":"Manufacturing & Wholesale Goods"
        }
    ],
    "sg:phone":"+39 39095877272",
    "sg:postcode":"95024",
    "sg:province":"Catania",
    "sg:tags":[
        "agriculture"
    ],
    "wof:name":"A.catanzaro E C. (s.r.l.)",
    "wof:placetype":"venue"
},
  "geometry": {"coordinates":[15.163268,37.584244],"type":"Point"}
}