{
  "type": "Feature",
  "properties": {
    "iso:country":"IT",
    "sg:address":"Via Provinciale 31 23867 Suello",
    "sg:city":"Suello",
    "sg:orig_category":"Hot Presses",
    "sg:phone":"+39 031 655881",
    "sg:postcode":"23867",
    "sg:province":"Lecco",
    "wof:name":"Farina Presse Spa",
    "wof:placetype":"venue"
},
  "geometry": {"coordinates":[9.351871,45.829845],"type":"Point"}
}