{
  "type": "Feature",
  "properties": {
    "addr:full":"48017 Conselice Conselice Ravenna 48017",
    "addr:postcode":"48017;48017",
    "iso:country":"IT",
    "sg:address":"48017 Conselice",
    "sg:city":"Conselice",
    "sg:orig_category":"Sementi E Bulbi",
    "sg:phone":"+39 0545 980381",
    "sg:postcode":"48017",
    "sg:province":"Ravenna",
    "wof:name":"Co.na.se. Soc.coop.r.l.",
    "wof:placetype":"venue"
},
  "geometry": {"coordinates":[11.835147,44.526783],"type":"Point"}
}