{
  "type": "Feature",
  "properties": {
    "iso:country":"IT",
    "sg:address":"74023 Grottaglie",
    "sg:city":"Grottaglie",
    "sg:orig_category":"Abiti Da Sposa E Cerimonia",
    "sg:phone":"+39 099 561 2520",
    "sg:postcode":"74023",
    "sg:province":"Taranto",
    "wof:name":"Carant Di Caramia Antonia",
    "wof:placetype":"venue"
},
  "geometry": {"coordinates":[17.470675,40.430367],"type":"Point"}
}