{
  "type": "Feature",
  "properties": {
    "addr:full":"80126 Napoli Napoli Napoli 80126",
    "addr:housenumber":"80126",
    "addr:postcode":"80126",
    "iso:country":"IT",
    "sg:address":"80126 Napoli",
    "sg:city":"Napoli",
    "sg:orig_category":"Elettricita' Materiali - Ingrosso",
    "sg:phone":"+39 081 588 6540",
    "sg:postcode":"80126",
    "sg:province":"Napoli",
    "wof:name":"Salfin Srl",
    "wof:placetype":"venue"
},
  "geometry": {"coordinates":[14.180327,40.856228],"type":"Point"}
}