{
  "type": "Feature",
  "properties": {
    "addr:full":"Via Caduti Di Russia 26 35010 Curtarolo Curtarolo Padova 35010",
    "addr:housenumber":"26",
    "addr:postcode":"35010;35010",
    "addr:street":"Via Caduti Di Russia",
    "iso:country":"IT",
    "sg:address":"Via Caduti Di Russia 26 35010 Curtarolo",
    "sg:city":"Curtarolo",
    "sg:orig_category":"Lacquer, Varnishes, Industrial Lacquer",
    "sg:phone":"+39 049 962 0333",
    "sg:postcode":"35010",
    "sg:province":"Padova",
    "wof:name":"S.d. Color Srl",
    "wof:placetype":"venue"
},
  "geometry": {"coordinates":[11.832061,45.537865],"type":"Point"}
}