{
  "type": "Feature",
  "properties": {
    "iso:country":"IT",
    "sg:address":"96010 Solarino",
    "sg:city":"Solarino",
    "sg:classifiers":[
        {
            "category":"Building & Trades",
            "subcategory":"Construction",
            "type":"Services"
        }
    ],
    "sg:phone":"+39 0931 922735",
    "sg:postcode":"96010",
    "sg:province":"Siracusa",
    "sg:tags":[
        "equipment",
        "heat",
        "heating",
        "engineering"
    ],
    "wof:name":"Elteknica Di Magnano Letizia",
    "wof:placetype":"venue"
},
  "geometry": {"coordinates":[15.122952,37.102192],"type":"Point"}
}