{
  "type": "Feature",
  "properties": {
    "iso:country":"IT",
    "sg:address":"Via Monte Rosa 27 20051 Limbiate",
    "sg:city":"Limbiate",
    "sg:orig_category":"Diamond Tools For The Glass Industry",
    "sg:phone":"+39 02 996 2935",
    "sg:postcode":"20051",
    "sg:province":"Milano",
    "wof:name":"Diamond-drills Di Colombo Maria Michela",
    "wof:placetype":"venue"
},
  "geometry": {"coordinates":[9.116521,45.614288],"type":"Point"}
}