{
  "type": "Feature",
  "properties": {
    "iso:country":"IT",
    "sg:address":"10, V. Degli Artigiani 31035 Crocetta Del Montello",
    "sg:city":"Crocetta del Montello",
    "sg:classifiers":[
        {
            "category":"Shopping",
            "type":"Retail Goods"
        }
    ],
    "sg:phone":"+39 0423 839990",
    "sg:postcode":"31035",
    "sg:province":"Treviso",
    "sg:tags":[
        "finished",
        "-",
        "metallic"
    ],
    "sg:website":"http://www.paginegialle.it/stm-03",
    "wof:name":"Meccanica S.t.m. Srl",
    "wof:placetype":"venue"
},
  "geometry": {"coordinates":[12.0260410309,45.8118743896],"type":"Point"}
}