{
  "type": "Feature",
  "properties": {
    "iso:country":"IT",
    "sg:address":"Via Battisti 3; S. Dona Di Piave",
    "sg:classifiers":[
        {
            "category":"Banks & Credit Unions",
            "subcategory":"Bank",
            "type":"Services"
        }
    ],
    "sg:phone":"+39 0421 52621",
    "wof:name":"Cassa Di Risparmio Di Venezia Spa",
    "wof:placetype":"venue"
},
  "geometry": {"coordinates":[12.565157,45.628914],"type":"Point"}
}