{
  "type": "Feature",
  "properties": {
    "iso:country":"IT",
    "sg:address":"20127 Milano",
    "sg:city":"Milano",
    "sg:orig_category":"Servizi Editoriali. Servizi Per Aziende, Manifestazioni E Supporto Agli Scambi Commerciali",
    "sg:phone":"+39 02 261 0147",
    "sg:postcode":"20127",
    "sg:province":"Milano",
    "wof:name":"Antinea Press Srl",
    "wof:placetype":"venue"
},
  "geometry": {"coordinates":[9.215158,45.489532],"type":"Point"}
}