{
  "type": "Feature",
  "properties": {
    "iso:country":"IT",
    "sg:address":"40055 Castenaso",
    "sg:city":"Castenaso",
    "sg:orig_category":"Macchine, Impianti Ed Attrezzature Per Agricoltura E Zootecnia",
    "sg:phone":"+39 051 782013",
    "sg:postcode":"40055",
    "sg:province":"Bologna",
    "sg:website":"http://www.irrigarden-bo.it",
    "wof:name":"Irrigarden Snc",
    "wof:placetype":"venue"
},
  "geometry": {"coordinates":[11.439313,44.509758],"type":"Point"}
}