{
  "type": "Feature",
  "properties": {
    "iso:country":"IT",
    "sg:address":"Via Selva Piana - Localit\u00e0 Arcotorr 83029 Solofra",
    "sg:city":"Solofra",
    "sg:classifiers":[
        {
            "category":"Home & Garden",
            "subcategory":"Carpets & Floor Coverings",
            "type":"Retail Goods"
        }
    ],
    "sg:phone":"+39 0825 583671",
    "sg:postcode":"83029",
    "sg:province":"Avellino",
    "sg:tags":[
        "animal",
        "skin"
    ],
    "wof:name":"F.lli Buongiorno S.p.a.",
    "wof:placetype":"venue"
},
  "geometry": {"coordinates":[14.792723,40.914749],"type":"Point"}
}