{
  "type": "Feature",
  "properties": {
    "addr:full":"Via Brennero 10 37029 San Pietro In Cariano San Pietro in Cariano Verona 37029",
    "addr:housenumber":"10",
    "addr:postcode":"37029;37029",
    "addr:street":"Via Brennero",
    "iso:country":"IT",
    "sg:address":"Via Brennero 10 37029 San Pietro In Cariano",
    "sg:city":"San Pietro in Cariano",
    "sg:classifiers":[
        {
            "category":"Home & Garden",
            "subcategory":"Carpets & Floor Coverings",
            "type":"Retail Goods"
        }
    ],
    "sg:phone":"+39 045 772 5018",
    "sg:postcode":"37029",
    "sg:province":"Verona",
    "sg:tags":[
        "marble",
        "flooring"
    ],
    "wof:name":"Delmar Srl",
    "wof:placetype":"venue"
},
  "geometry": {"coordinates":[10.877016,45.494171],"type":"Point"}
}