{
  "type": "Feature",
  "properties": {
    "addr:full":"20041 Agrate Brianza Agrate Brianza Milano 20041",
    "addr:postcode":"20041;20041",
    "iso:country":"IT",
    "sg:address":"20041 Agrate Brianza",
    "sg:city":"Agrate Brianza",
    "sg:orig_category":"Valigerie Ed Articoli Da Viaggio - Produzione E Ingrosso",
    "sg:phone":"+39 039 60701",
    "sg:postcode":"20041",
    "sg:province":"Milano",
    "wof:name":"Delsey Italia Spa",
    "wof:placetype":"venue"
},
  "geometry": {"coordinates":[9.3535413742,45.5729751587],"type":"Point"}
}