{
  "type": "Feature",
  "properties": {
    "iso:country":"IT",
    "sg:address":"33010 Magnano In Riviera",
    "sg:city":"Magnano in Riviera",
    "sg:orig_category":"Motori Ed Organi Di Trasmissione",
    "sg:phone":"+39 0432 780811",
    "sg:postcode":"33010",
    "sg:province":"Udine",
    "wof:name":"Acciaierie Weissenfels S.p.a.",
    "wof:placetype":"venue"
},
  "geometry": {"coordinates":[13.1831569672,46.2122154236],"type":"Point"}
}