{
  "type": "Feature",
  "properties": {
    "iso:country":"IT",
    "sg:address":"52023 Levane",
    "sg:orig_category":"Forniture Per Abbigliamento E Pelletterie",
    "sg:phone":"+39 055 978 9655",
    "sg:province":"AR",
    "wof:name":"Etruria Tacchi (s.n.c.)",
    "wof:placetype":"venue"
},
  "geometry": {"coordinates":[11.6131505966,43.4991950989],"type":"Point"}
}