{
  "type": "Feature",
  "properties": {
    "iso:country":"IT",
    "sg:address":"60025 Loreto",
    "sg:city":"Loreto",
    "sg:orig_category":"Strumenti Musicali Ed Accessori - Produzione E Ingrosso",
    "sg:phone":"+39 071 750 1554",
    "sg:postcode":"60025",
    "sg:province":"Ancona",
    "sg:website":"http://www.euromet.it",
    "wof:name":"C.s.s.g. Consorzio Sociale Servizi Generali Soc.coop.r.l.",
    "wof:placetype":"venue"
},
  "geometry": {"coordinates":[13.659943,43.43425],"type":"Point"}
}