{
  "type": "Feature",
  "properties": {
    "iso:country":"IT",
    "sg:address":"20141 Milano",
    "sg:city":"Milano",
    "sg:orig_category":"Motori Ed Organi Di Trasmissione",
    "sg:phone":"+39 02 8950 6801",
    "sg:postcode":"20141",
    "sg:province":"Milano",
    "wof:name":"Colnago E.c. (s.r.l.)",
    "wof:placetype":"venue"
},
  "geometry": {"coordinates":[9.1887197495,45.4423027039],"type":"Point"}
}