{
  "type": "Feature",
  "properties": {
    "iso:country":"IT",
    "sg:address":"41051 Castelnuovo Rangone",
    "sg:city":"Castelnuovo Rangone",
    "sg:orig_category":"Macchine, Impianti Ed Attrezzature Per Abbigliamento E Pelletterie",
    "sg:phone":"+39 059 531325",
    "sg:postcode":"41051",
    "sg:province":"Modena",
    "wof:name":"Commercialfina S.r.l.",
    "wof:placetype":"venue"
},
  "geometry": {"coordinates":[10.897016,44.567101],"type":"Point"}
}