{
  "type": "Feature",
  "properties": {
    "iso:country":"IT",
    "sg:address":"78, Via Camillo Cavour 13894 Gaglianico",
    "sg:city":"Gaglianico",
    "sg:classifiers":[
        {
            "category":"Shopping",
            "subcategory":"Computers & Home Electronics",
            "type":"Retail Goods"
        }
    ],
    "sg:phone":"+39 015 254 3078",
    "sg:postcode":"13894",
    "sg:province":"Biella",
    "sg:tags":[
        "electronic",
        "electrical",
        "equipment"
    ],
    "wof:name":"Sabib S.r.l.",
    "wof:placetype":"venue"
},
  "geometry": {"coordinates":[8.050406,45.569847],"type":"Point"}
}