{
  "type": "Feature",
  "properties": {
    "addr:full":"47016 Predappio Fiumana Forl\u00ec-Cesena 47016",
    "addr:postcode":"47016;47016",
    "iso:country":"IT",
    "sg:address":"47016 Predappio",
    "sg:city":"Fiumana",
    "sg:orig_category":"Box Prefabbricati",
    "sg:phone":"+39 0543 940133",
    "sg:postcode":"47016",
    "sg:province":"Forl\u00ec-Cesena",
    "wof:name":"Fabbri Giovanni",
    "wof:placetype":"venue"
},
  "geometry": {"coordinates":[11.987204,44.145313],"type":"Point"}
}