{
  "type": "Feature",
  "properties": {
    "iso:country":"IT",
    "sg:address":"10024 Moncalieri",
    "sg:city":"Moncalieri",
    "sg:orig_category":"Ricambi E Componenti Dei Mezzi Di Trasporto",
    "sg:phone":"+39 011 682 2197",
    "sg:postcode":"10024",
    "sg:province":"Torino",
    "wof:name":"Gioachin Maurizio",
    "wof:placetype":"venue"
},
  "geometry": {"coordinates":[7.659132,45.013905],"type":"Point"}
}