{
  "type": "Feature",
  "properties": {
    "iso:country":"IT",
    "sg:address":"Km. 18, Strada Statale 229 28010 Vaprio D'agogna",
    "sg:classifiers":[
        {
            "category":"Professional",
            "subcategory":"Engineering",
            "type":"Services"
        }
    ],
    "sg:phone":"+39 0321 996387",
    "sg:postcode":"28010",
    "sg:province":"Novara",
    "sg:tags":[
        "machine",
        "-",
        "mechanical"
    ],
    "wof:name":"Automation System S.r.l.",
    "wof:placetype":"venue"
},
  "geometry": {"coordinates":[8.618671,45.445084],"type":"Point"}
}