{
  "type": "Feature",
  "properties": {
    "iso:country":"IT",
    "sg:address":"58, Viale Matteotti Giacomo 50052 Certaldo",
    "sg:city":"Certaldo",
    "sg:classifiers":[
        {
            "category":"Shopping",
            "subcategory":"Clothing, Apparel, & Fashions",
            "type":"Retail Goods"
        }
    ],
    "sg:phone":"+39 0571 668233",
    "sg:postcode":"50052",
    "sg:province":"Firenze",
    "sg:tags":[
        "clothes"
    ],
    "wof:name":"Roberta",
    "wof:placetype":"venue"
},
  "geometry": {"coordinates":[11.256902,43.768734],"type":"Point"}
}