{
  "type": "Feature",
  "properties": {
    "iso:country":"IT",
    "sg:address":"37018 Malcesine",
    "sg:city":"Malcesine",
    "sg:orig_category":"Non-classified Establishments",
    "sg:phone":"+39 045 657 0768",
    "sg:postcode":"37018",
    "sg:province":"Verona",
    "wof:name":"La Grotta Delle Candele",
    "wof:placetype":"venue"
},
  "geometry": {"coordinates":[10.809759,45.765724],"type":"Point"}
}