{
  "type": "Feature",
  "properties": {
    "addr:full":"05100 Terni Terni Terni 05100",
    "addr:postcode":"05100;05100",
    "iso:country":"IT",
    "sg:address":"05100 Terni",
    "sg:city":"Terni",
    "sg:orig_category":"Ristorazione E Locali Pubblici Affini. Ristoranti Ed Esercizi Affini",
    "sg:phone":"+39 0744 62199",
    "sg:postcode":"05100",
    "sg:province":"Terni",
    "wof:name":"Ristoranti Le Marmore Srl",
    "wof:placetype":"venue"
},
  "geometry": {"coordinates":[12.76188,42.58601],"type":"Point"}
}