{
  "type": "Feature",
  "properties": {
    "addr:full":"20143 Milano Milano Milano 20143",
    "addr:postcode":"20143;20143",
    "iso:country":"IT",
    "sg:address":"20143 Milano",
    "sg:city":"Milano",
    "sg:orig_category":"Informatica - Consulenza E Servizi. Editoria",
    "sg:phone":"+39 02 8940 4661",
    "sg:postcode":"20143",
    "sg:province":"Milano",
    "sg:website":"http://www.duplicazionecd.com",
    "wof:name":"Marinimedia Srl",
    "wof:placetype":"venue"
},
  "geometry": {"coordinates":[9.167386,45.444851],"type":"Point"}
}