{
  "type": "Feature",
  "properties": {
    "iso:country":"IT",
    "sg:address":"Piazza Della Vittoria 25; Cordenons",
    "sg:classifiers":[
        {
            "category":"Banks & Credit Unions",
            "subcategory":"Bank",
            "type":"Services"
        }
    ],
    "sg:phone":"+39 0434 932491",
    "wof:name":"Banca Popolare Friuladria",
    "wof:placetype":"venue"
},
  "geometry": {"coordinates":[12.706398,45.987865],"type":"Point"}
}