{
  "type": "Feature",
  "properties": {
    "iso:country":"IT",
    "sg:address":"33080 Prata Di Pordenone",
    "sg:city":"Prata di Pordenone",
    "sg:classifiers":[
        {
            "category":"Government",
            "subcategory":"Office",
            "type":"Public Place"
        }
    ],
    "sg:phone":"+39 0434 610680",
    "sg:postcode":"33080",
    "sg:province":"Pordenone",
    "sg:tags":[
        "e",
        "lo",
        "tempo",
        "libero",
        "per",
        "spettacolo",
        "servizi",
        "culturali",
        "sport",
        "il"
    ],
    "wof:name":"Banda Musicale Gruppo Majorette",
    "wof:placetype":"venue"
},
  "geometry": {"coordinates":[12.593361,45.892181],"type":"Point"}
}