{
  "type": "Feature",
  "properties": {
    "iso:country":"IT",
    "sg:address":"73048 Nard\u00f2",
    "sg:orig_category":"Ecologia - Studi Consulenza E Servizi",
    "sg:phone":"+39 0833 561185",
    "sg:postcode":"73048",
    "sg:province":"Lecce",
    "wof:name":"A.d.eco Srl",
    "wof:placetype":"venue"
},
  "geometry": {"coordinates":[17.976887,40.202019],"type":"Point"}
}