{
  "type": "Feature",
  "properties": {
    "iso:country":"IT",
    "sg:address":"25, Via Maestri Del Lavoro 24020 Gorle",
    "sg:city":"Gorle",
    "sg:classifiers":[
        {
            "category":"Shopping",
            "subcategory":"Computers & Home Electronics",
            "type":"Retail Goods"
        }
    ],
    "sg:phone":"+39 035 412 3153",
    "sg:postcode":"24020",
    "sg:province":"Bergamo",
    "sg:tags":[
        "electronic",
        "electrical",
        "equipment"
    ],
    "wof:name":"Milesi Sistemi Srl",
    "wof:placetype":"venue"
},
  "geometry": {"coordinates":[9.720261,45.710987],"type":"Point"}
}