{
  "type": "Feature",
  "properties": {
    "iso:country":"IT",
    "sg:address":"43050 Mezzano Rondani",
    "sg:orig_category":"Forniture Per Attivita' Industriali",
    "sg:phone":"+39 0521 814345",
    "sg:postcode":"43050",
    "sg:province":"Parma",
    "wof:name":"Pennellificio Anversa Viller",
    "wof:placetype":"venue"
},
  "geometry": {"coordinates":[10.3295478821,44.8078651428],"type":"Point"}
}