{
  "type": "Feature",
  "properties": {
    "addr:full":"00187 Roma Roma Roma 00187",
    "addr:postcode":"00187;00187",
    "iso:country":"IT",
    "sg:address":"00187 Roma",
    "sg:city":"Roma",
    "sg:orig_category":"Centri Di Estetica E Cosmesi E Servizi",
    "sg:phone":"+39 06 4274 5809",
    "sg:postcode":"00187",
    "sg:province":"Roma",
    "wof:name":"G.d.g. Di G. Di Giovanni",
    "wof:placetype":"venue"
},
  "geometry": {"coordinates":[12.497256,41.909611],"type":"Point"}
}