{
  "type": "Feature",
  "properties": {
    "iso:country":"IT",
    "sg:address":"31016 Cordignano",
    "sg:city":"Cordignano",
    "sg:orig_category":"Arredamento Alberghi",
    "sg:phone":"+39 0438 995246",
    "sg:postcode":"31016",
    "sg:province":"Treviso",
    "sg:website":"http://www.casaitalia.it/ortolan",
    "wof:name":"Mobilificio Ortolan Spa",
    "wof:placetype":"venue"
},
  "geometry": {"coordinates":[12.257602,45.673748],"type":"Point"}
}