{
  "type": "Feature",
  "properties": {
    "addr:full":"Piazza Sabbato 11-14; Pontecagnano; 84098 Pontecagnano Salerno 84098",
    "addr:housenumber":"11-14",
    "addr:postcode":"84098;84098",
    "addr:street":"Piazza Sabbato",
    "iso:country":"IT",
    "sg:address":"Piazza Sabbato 11-14; Pontecagnano; 84098",
    "sg:city":"Pontecagnano",
    "sg:classifiers":[
        {
            "category":"Banks & Credit Unions",
            "subcategory":"Bank",
            "type":"Services"
        }
    ],
    "sg:phone":"+39 089 382726",
    "sg:postcode":"84098",
    "sg:province":"Salerno",
    "wof:name":"Banco Di Napoli Spa",
    "wof:placetype":"venue"
},
  "geometry": {"coordinates":[14.873856,40.645092],"type":"Point"}
}