{
  "type": "Feature",
  "properties": {
    "iso:country":"IT",
    "sg:address":"64018 Tortoreto",
    "sg:city":"Tortoreto",
    "sg:orig_category":"Articoli Per Imballaggio E Confezionamento",
    "sg:phone":"+39 0861 786463",
    "sg:postcode":"64018",
    "sg:province":"Teramo",
    "wof:name":"Alma S.r.l.",
    "wof:placetype":"venue"
},
  "geometry": {"coordinates":[13.902799,42.797012],"type":"Point"}
}