{
  "type": "Feature",
  "properties": {
    "iso:country":"IT",
    "sg:address":"20062 Cassano D'adda",
    "sg:orig_category":"Elettrotecnica Industriale, Prodotti E Apparecchiature. Ricambi E Componenti Dei Mezzi Di Trasporto",
    "sg:phone":"+39 036 360528",
    "sg:postcode":"20062",
    "sg:province":"Milano",
    "sg:website":"http://www.labatteria.com",
    "wof:name":"La Batteria Industriale Ricerca Tecnologia Srl",
    "wof:placetype":"venue"
},
  "geometry": {"coordinates":[9.53238,45.576324],"type":"Point"}
}