{
  "type": "Feature",
  "properties": {
    "iso:country":"IT",
    "sg:address":"15100 Alessandria",
    "sg:city":"Alessandria",
    "sg:orig_category":"Scuole E Servizi Scolastici. Centri Di Estetica E Cosmesi E Servizi. Ricerca, Selezione E Formazione Del Personale",
    "sg:postcode":"15100",
    "sg:province":"Alessandria",
    "wof:name":"S.i.d.e.p. Srl",
    "wof:placetype":"venue"
},
  "geometry": {"coordinates":[8.71055,44.910763],"type":"Point"}
}