{
  "type": "Feature",
  "properties": {
    "addr:full":"31032 Casale Sul Sile Casale sul Sile Treviso 31032",
    "addr:postcode":"31032;31032",
    "iso:country":"IT",
    "sg:address":"31032 Casale Sul Sile",
    "sg:city":"Casale sul Sile",
    "sg:orig_category":"Motori Ed Organi Di Trasmissione. Ricambi E Componenti Dei Mezzi Di Trasporto",
    "sg:phone":"+39 0422 821546",
    "sg:postcode":"31032",
    "sg:province":"Treviso",
    "wof:name":"Euro Motori Srl",
    "wof:placetype":"venue"
},
  "geometry": {"coordinates":[12.251748085,45.6415061951],"type":"Point"}
}