{
  "type": "Feature",
  "properties": {
    "addr:full":"10141 Torino Torino Torino 10141",
    "addr:postcode":"10141;10141",
    "iso:country":"IT",
    "sg:address":"10141 Torino",
    "sg:city":"Torino",
    "sg:orig_category":"Macchine, Impianti Ed Attrezzature Per Abbigliamento E Pelletterie",
    "sg:phone":"+39 011 707 3263",
    "sg:postcode":"10141",
    "sg:province":"Torino",
    "wof:name":"Guarraci Silvio",
    "wof:placetype":"venue"
},
  "geometry": {"coordinates":[7.621639,45.068146],"type":"Point"}
}