{
  "type": "Feature",
  "properties": {
    "iso:country":"IT",
    "sg:address":"Localit\u00e0 Puisle 4 38051 Borgo Valsugana",
    "sg:city":"Borgo",
    "sg:classifiers":[
        {
            "category":"Wholesale",
            "subcategory":"Hardware",
            "type":"Manufacturing & Wholesale Goods"
        }
    ],
    "sg:phone":"+39 0461 753517",
    "sg:postcode":"38051",
    "sg:province":"Trento",
    "sg:tags":[
        "steel",
        "rod"
    ],
    "wof:name":"Siderurgica Trentina Spa",
    "wof:placetype":"venue"
},
  "geometry": {"coordinates":[11.448579,46.050262],"type":"Point"}
}