{
  "type": "Feature",
  "properties": {
    "iso:country":"IT",
    "sg:address":"13, Via Guglielmo Marconi 61046 Piobbico",
    "sg:city":"Piobbico",
    "sg:classifiers":[
        {
            "category":"Professional",
            "subcategory":"Engineering",
            "type":"Services"
        }
    ],
    "sg:phone":"+39 0722 986229",
    "sg:postcode":"61046",
    "sg:province":"Pesaro E Urbino",
    "sg:tags":[
        "machine",
        "-",
        "mechanical"
    ],
    "wof:name":"Catani Domenico",
    "wof:placetype":"venue"
},
  "geometry": {"coordinates":[12.511341,43.589672],"type":"Point"}
}