{
  "type": "Feature",
  "properties": {
    "iso:country":"IT",
    "sg:address":"00147 Roma",
    "sg:city":"Roma",
    "sg:orig_category":"Pubblica Amministrazione",
    "sg:phone":"+39 06 5160 9972",
    "sg:postcode":"00147",
    "sg:province":"Roma",
    "wof:name":"Regione Lazio",
    "wof:placetype":"venue"
},
  "geometry": {"coordinates":[12.495639801,41.8512687683],"type":"Point"}
}