{
  "type": "Feature",
  "properties": {
    "iso:country":"IT",
    "sg:address":"35129 Padova",
    "sg:city":"Padova",
    "sg:orig_category":"Metalli E Leghe",
    "sg:phone":"+39 049 807 8738",
    "sg:postcode":"35129",
    "sg:province":"Padova",
    "sg:website":"http://www.metalb.com",
    "wof:name":"Metal B Srl",
    "wof:placetype":"venue"
},
  "geometry": {"coordinates":[11.8630666733,45.3212738037],"type":"Point"}
}