{
  "type": "Feature",
  "properties": {
    "iso:country":"IT",
    "sg:address":"43013 Langhirano",
    "sg:city":"Langhirano",
    "sg:classifiers":[
        {
            "category":"Home & Garden",
            "subcategory":"Building Materials",
            "type":"Retail Goods"
        }
    ],
    "sg:phone":"+39 0521 857592",
    "sg:postcode":"43013",
    "sg:province":"Parma",
    "sg:tags":[
        "articles",
        "product",
        "plastics",
        "supply",
        "packaging",
        "packing"
    ],
    "sg:website":"http://www.gammapack.com",
    "wof:name":"Gammapack Spa",
    "wof:placetype":"venue"
},
  "geometry": {"coordinates":[10.2739601135,44.6205558777],"type":"Point"}
}