{
  "type": "Feature",
  "properties": {
    "iso:country":"IT",
    "sg:address":"66020 San Giovanni Teatino",
    "sg:city":"San Giovanni Teatino",
    "sg:orig_category":"Carta, Cartone E Prodotti Primari. Forniture E Materiali Per Imballaggio E Confezionamento",
    "sg:phone":"+39 085 444481",
    "sg:postcode":"66020",
    "sg:province":"Chieti",
    "sg:website":"http://www.ico.it",
    "wof:name":"Ico Srl",
    "wof:placetype":"venue"
},
  "geometry": {"coordinates":[14.173457,42.405289],"type":"Point"}
}