{
  "type": "Feature",
  "properties": {
    "addr:full":"Via Ancona 25 29010 Calendasco Calendasco Piacenza 29010",
    "addr:housenumber":"25",
    "addr:postcode":"29010;29010",
    "addr:street":"Via Ancona",
    "iso:country":"IT",
    "sg:address":"Via Ancona 25 29010 Calendasco",
    "sg:city":"Calendasco",
    "sg:classifiers":[
        {
            "category":"Manufacturing",
            "subcategory":"Chemicals & Compounds",
            "type":"Manufacturing & Wholesale Goods"
        }
    ],
    "sg:phone":"+39 0523 760841",
    "sg:postcode":"29010",
    "sg:province":"Piacenza",
    "sg:tags":[
        "industry",
        "fitting",
        "high-pressure"
    ],
    "wof:name":"Omc Raccordi Srl",
    "wof:placetype":"venue"
},
  "geometry": {"coordinates":[9.631399,45.058933],"type":"Point"}
}