{
  "type": "Feature",
  "properties": {
    "iso:country":"IT",
    "sg:address":"15, V. Del Gerolo 20017 Rho",
    "sg:city":"Rho",
    "sg:classifiers":[
        {
            "category":"Shopping",
            "subcategory":"Computers & Home Electronics",
            "type":"Retail Goods"
        }
    ],
    "sg:phone":"+39 02 9350 1860",
    "sg:postcode":"20017",
    "sg:province":"Milano",
    "sg:tags":[
        "electronic",
        "electrical",
        "equipment"
    ],
    "sg:website":"http://www.paginegialle.it/olearivirginio",
    "wof:name":"Oleari Virginio",
    "wof:placetype":"venue"
},
  "geometry": {"coordinates":[9.024836,45.528091],"type":"Point"}
}