{
  "type": "Feature",
  "properties": {
    "addr:full":"00159 Roma Roma Roma 00159",
    "addr:postcode":"00159;00159",
    "iso:country":"IT",
    "sg:address":"00159 Roma",
    "sg:city":"Roma",
    "sg:orig_category":"Termotecnica E Riscaldamento, Apparecchiature E Servizi",
    "sg:phone":"+39 06 439 6469",
    "sg:postcode":"00159",
    "sg:province":"Roma",
    "wof:name":"Siram Spa",
    "wof:placetype":"venue"
},
  "geometry": {"coordinates":[12.57191,41.907539],"type":"Point"}
}