{
  "type": "Feature",
  "properties": {
    "iso:country":"IT",
    "sg:address":"90135 Palermo",
    "sg:city":"Palermo",
    "sg:orig_category":"Prodotti Chimici Di Base",
    "sg:phone":"+39 091 408062",
    "sg:postcode":"90135",
    "sg:province":"Palermo",
    "wof:name":"Avila Salvatore",
    "wof:placetype":"venue"
},
  "geometry": {"coordinates":[13.3262138367,38.1170539856],"type":"Point"}
}