{
  "type": "Feature",
  "properties": {
    "iso:country":"IT",
    "sg:address":"20065 Inzago",
    "sg:city":"Inzago",
    "sg:orig_category":"Prodotti Di Base E Forniture Per Industria Alimentare E Bevande. Forniture Per Attivita' Commerciali Ed Artigianali",
    "sg:phone":"+39 02 9531 0707",
    "sg:postcode":"20065",
    "sg:province":"Milano",
    "wof:name":"Nembri Oreste",
    "wof:placetype":"venue"
},
  "geometry": {"coordinates":[9.5367088318,45.5764732361],"type":"Point"}
}