{
  "type": "Feature",
  "properties": {
    "addr:full":"Via Fonte Giugliano 15 63014 Montegranaro Montegranaro Ascoli Piceno 63014",
    "addr:housenumber":"15",
    "addr:postcode":"63014;63014",
    "addr:street":"Via Fonte Giugliano",
    "iso:country":"IT",
    "sg:address":"Via Fonte Giugliano 15 63014 Montegranaro",
    "sg:city":"Montegranaro",
    "sg:orig_category":"Ladies' Shoes",
    "sg:phone":"+39 0734 891437",
    "sg:postcode":"63014",
    "sg:province":"Ascoli Piceno",
    "wof:name":"Calzaturificio Medori & C. Srl",
    "wof:placetype":"venue"
},
  "geometry": {"coordinates":[13.648611,43.238579],"type":"Point"}
}