{
  "type": "Feature",
  "properties": {
    "addr:full":"32032 Villabruna Villabruna Belluno 32032",
    "addr:postcode":"32032;32032",
    "iso:country":"IT",
    "sg:address":"32032 Villabruna",
    "sg:city":"Villabruna",
    "sg:orig_category":"Materiali Edili",
    "sg:phone":"+39 0439 42702",
    "sg:postcode":"32032",
    "sg:province":"Belluno",
    "wof:name":"Wienerberger Brunori S.r.l.",
    "wof:placetype":"venue"
},
  "geometry": {"coordinates":[11.919808,46.049152],"type":"Point"}
}