{
  "type": "Feature",
  "properties": {
    "iso:country":"IT",
    "sg:address":"25086 Brescia",
    "sg:orig_category":"Macchine E Forniture Per Ecologia E Smaltimento Rifiuti. Elettrodomestici. Forniture Alle Strutture Ricettive. Macchine, Strumenti Ed Apparecchi Per Attivita' Industriali",
    "sg:phone":"+39 030 220177",
    "sg:postcode":"25086",
    "sg:province":"Brescia",
    "wof:name":"Formula 1 Center",
    "wof:placetype":"venue"
},
  "geometry": {"coordinates":[10.219798,45.52433],"type":"Point"}
}