{
  "type": "Feature",
  "properties": {
    "addr:full":"42030 Minozzo Reggio Nell'Emilia 42030",
    "addr:postcode":"42030;42030",
    "iso:country":"IT",
    "sg:address":"42030 Minozzo",
    "sg:orig_category":"Materiali Edili",
    "sg:phone":"+39 0522 801515",
    "sg:postcode":"42030",
    "sg:province":"Reggio Nell'Emilia",
    "wof:name":"Rubertelli Pietro & Francesco (s.n.c.)",
    "wof:placetype":"venue"
},
  "geometry": {"coordinates":[10.627794,44.696228],"type":"Point"}
}