{
  "type": "Feature",
  "properties": {
    "addr:full":"3, Via Croce Rossa 29100 Piacenza Piacenza Piacenza 29100",
    "addr:postcode":"29100;29100",
    "addr:street":"Via Croce Rossa",
    "iso:country":"IT",
    "sg:address":"3, Via Croce Rossa 29100 Piacenza",
    "sg:city":"Piacenza",
    "sg:classifiers":[
        {
            "category":"Professional",
            "subcategory":"Engineering",
            "type":"Services"
        }
    ],
    "sg:phone":"+39 0523 578220",
    "sg:postcode":"29100",
    "sg:province":"Piacenza",
    "sg:tags":[
        "machine",
        "-",
        "mechanical"
    ],
    "wof:name":"Flexit Srl",
    "wof:placetype":"venue"
},
  "geometry": {"coordinates":[8.705935,44.923347],"type":"Point"}
}