{
  "type": "Feature",
  "properties": {
    "iso:country":"IT",
    "sg:address":"30174 Venezia",
    "sg:city":"Venezia",
    "sg:classifiers":[
        {
            "category":"Travel",
            "subcategory":"Hotels & Motels",
            "type":"Entertainment"
        }
    ],
    "sg:phone":"+39 041 968027",
    "sg:postcode":"30174",
    "sg:province":"Venezia",
    "sg:tags":[
        "camping",
        "facility"
    ],
    "sg:website":"http://www.marconinet.it/cavallino/residenc",
    "wof:name":"Residence Gestioni Turistiche Srl",
    "wof:placetype":"venue"
},
  "geometry": {"coordinates":[12.555243,45.477039],"type":"Point"}
}