{
  "type": "Feature",
  "properties": {
    "addr:full":"21, Via Degli Artigiani 22040 Lurago D'erba Como 22040",
    "addr:postcode":"22040;22040",
    "addr:street":"Via Degli Artigiani",
    "iso:country":"IT",
    "sg:address":"21, Via Degli Artigiani 22040 Lurago D'erba",
    "sg:classifiers":[
        {
            "category":"Autos & Motor Vehicles",
            "subcategory":"Automobile Sales",
            "type":"Retail Goods"
        }
    ],
    "sg:phone":"+39 39031698311",
    "sg:postcode":"22040",
    "sg:province":"Como",
    "sg:tags":[
        "industrial"
    ],
    "wof:name":"R.c. S.r.l.",
    "wof:placetype":"venue"
},
  "geometry": {"coordinates":[9.222903,45.763859],"type":"Point"}
}