{
  "type": "Feature",
  "properties": {
    "addr:full":"50136 Firenze Firenze Firenze 50136",
    "addr:postcode":"50136;50136",
    "iso:country":"IT",
    "sg:address":"50136 Firenze",
    "sg:city":"Firenze",
    "sg:orig_category":"Servizi Di Magazzinaggio E Movimentazione. Servizi Ausiliari Di Sorveglianza, Manutenzione E Pulizia. Servizi Per Aziende, Manifestazioni E Supporto Agli Scambi Commerciali",
    "sg:phone":"+39 055 652 7601",
    "sg:postcode":"50136",
    "sg:province":"Firenze",
    "sg:website":"http://www.divittorio.it",
    "wof:name":"Cooperativa Di Vittorio Sociale Srl",
    "wof:placetype":"venue"
},
  "geometry": {"coordinates":[11.305856,43.767117],"type":"Point"}
}