{
  "type": "Feature",
  "properties": {
    "iso:country":"IT",
    "sg:address":"59025 Cantagallo",
    "sg:city":"Cantagallo",
    "sg:orig_category":"Servizi E Lavori Per Abbigliamento E Pelletterie",
    "sg:phone":"+39 0574 982079",
    "sg:postcode":"59025",
    "sg:province":"Prato",
    "wof:name":"Tintoria Carbonizzo 'colle' S.r.l.",
    "wof:placetype":"venue"
},
  "geometry": {"coordinates":[11.122839,43.969322],"type":"Point"}
}