{
  "type": "Feature",
  "properties": {
    "addr:full":"98121 Messina Messina Messina 98121",
    "addr:postcode":"98121;98121",
    "iso:country":"IT",
    "sg:address":"98121 Messina",
    "sg:city":"Messina",
    "sg:classifiers":[
        {
            "category":"Banks & Credit Unions",
            "subcategory":"Investment Brokerage",
            "type":"Services"
        }
    ],
    "sg:phone":"+39 090 52839",
    "sg:postcode":"98121",
    "sg:province":"Messina",
    "sg:tags":[
        "packaging",
        "packing"
    ],
    "wof:name":"Gentile Traslochi",
    "wof:placetype":"venue"
},
  "geometry": {"coordinates":[15.5587348938,38.2034797668],"type":"Point"}
}