{
  "type": "Feature",
  "properties": {
    "addr:full":"324, Via Roma 35030 Cervarese Santa Croce Cervarese Santa Croce Padova 35030",
    "addr:housenumber":"324",
    "addr:postcode":"35030;35030",
    "addr:street":"Via Roma",
    "iso:country":"IT",
    "sg:address":"324, Via Roma 35030 Cervarese Santa Croce",
    "sg:city":"Cervarese Santa Croce",
    "sg:classifiers":[
        {
            "category":"Professional",
            "subcategory":"Engineering",
            "type":"Services"
        }
    ],
    "sg:phone":"+39 049 990 3830",
    "sg:postcode":"35030",
    "sg:province":"Padova",
    "sg:tags":[
        "machine",
        "-",
        "mechanical"
    ],
    "wof:name":"Cold Line Srl",
    "wof:placetype":"venue"
},
  "geometry": {"coordinates":[11.705222,45.381004],"type":"Point"}
}