{
  "type": "Feature",
  "properties": {
    "iso:country":"IT",
    "sg:address":"20132 Milano",
    "sg:city":"Milano",
    "sg:orig_category":"Hobbistica",
    "sg:phone":"+39 02 259 0965",
    "sg:postcode":"20132",
    "sg:province":"Milano",
    "wof:name":"Ripa S.r.l.",
    "wof:placetype":"venue"
},
  "geometry": {"coordinates":[9.241715,45.503323],"type":"Point"}
}