{
  "type": "Feature",
  "properties": {
    "iso:country":"IT",
    "sg:address":"81, Strada Statale Adriatica 61100 Pesaro",
    "sg:city":"Pesaro",
    "sg:classifiers":[
        {
            "category":"Wholesale",
            "subcategory":"Drugs",
            "type":"Manufacturing & Wholesale Goods"
        }
    ],
    "sg:phone":"+39 0721 403633",
    "sg:postcode":"61100",
    "sg:province":"Pesaro E Urbino",
    "sg:tags":[
        "chemical",
        "pharmaceutical"
    ],
    "wof:name":"A C E M A (s.p.a.)",
    "wof:placetype":"venue"
},
  "geometry": {"coordinates":[12.529803,43.633556],"type":"Point"}
}