{
  "type": "Feature",
  "properties": {
    "addr:full":"Via Bronzino 19 20133 Milano Milano Milano 20133",
    "addr:housenumber":"19",
    "addr:postcode":"20133;20133",
    "addr:street":"Via Bronzino",
    "iso:country":"IT",
    "sg:address":"Via Bronzino 19 20133 Milano",
    "sg:city":"Milano",
    "sg:orig_category":"Fertilizers, Organo-chemical",
    "sg:phone":"+39 02 2951 8305",
    "sg:postcode":"20133",
    "sg:province":"Milano",
    "wof:name":"Tecniterra Srl",
    "wof:placetype":"venue"
},
  "geometry": {"coordinates":[9.2194042206,45.4777488708],"type":"Point"}
}