{
  "type": "Feature",
  "properties": {
    "addr:full":"Viale Dell'industria 5 24030 Villa D'adda Bergamo 24030",
    "addr:housenumber":"5",
    "addr:postcode":"24030;24030",
    "addr:street":"Viale Dell'Industria",
    "iso:country":"IT",
    "sg:address":"Viale Dell'industria 5 24030 Villa D'adda",
    "sg:classifiers":[
        {
            "category":"Sports & Exercise",
            "subcategory":"Swimming Pool",
            "type":"Entertainment"
        }
    ],
    "sg:phone":"+39 035 784141",
    "sg:postcode":"24030",
    "sg:province":"Bergamo",
    "sg:tags":[
        "facilities",
        "recreational"
    ],
    "sg:website":"www.biffisport.it",
    "wof:name":"Biffi Spa",
    "wof:placetype":"venue"
},
  "geometry": {"coordinates":[9.669952,45.694904],"type":"Point"}
}