{
  "type": "Feature",
  "properties": {
    "addr:full":"40, Via Valverde 25086 Rezzato Rezzato Brescia 25086",
    "addr:postcode":"25086;25086",
    "addr:street":"Via Valverde",
    "iso:country":"IT",
    "sg:address":"40, Via Valverde 25086 Rezzato",
    "sg:city":"Rezzato",
    "sg:classifiers":[
        {
            "category":"Manufacturing",
            "subcategory":"Metals",
            "type":"Manufacturing & Wholesale Goods"
        }
    ],
    "sg:phone":"+39 030 279 1369",
    "sg:postcode":"25086",
    "sg:province":"Brescia",
    "sg:tags":[
        "processing"
    ],
    "wof:name":"S.a.r.o.m. (s.r.l.)",
    "wof:placetype":"venue"
},
  "geometry": {"coordinates":[10.3088264465,45.5245628357],"type":"Point"}
}