{
  "type": "Feature",
  "properties": {
    "iso:country":"IT",
    "sg:address":"24010 Sorisole",
    "sg:city":"Sorisole",
    "sg:orig_category":"Frigotecnica, Apparecchiature E Servizi. Forniture Alle Strutture Ricettive",
    "sg:phone":"+39 035 575554",
    "sg:postcode":"24010",
    "sg:province":"Bergamo",
    "wof:name":"Nordfrigor Snc Di Angeli Busi Francesco & C.",
    "wof:placetype":"venue"
},
  "geometry": {"coordinates":[9.6485424042,45.7347335815],"type":"Point"}
}