{
  "type": "Feature",
  "properties": {
    "iso:country":"IT",
    "sg:address":"Via Zona Industriale 64025 Pineto",
    "sg:city":"Pineto",
    "sg:classifiers":[
        {
            "category":"Food & Beverages",
            "subcategory":"Groceries & Convenience Stores",
            "type":"Retail Goods"
        }
    ],
    "sg:phone":"+39 085 946 1140",
    "sg:postcode":"64025",
    "sg:province":"Teramo",
    "sg:tags":[
        "product",
        "related"
    ],
    "wof:name":"Rossi Tascioni",
    "wof:placetype":"venue"
},
  "geometry": {"coordinates":[13.6985311508,42.6612701416],"type":"Point"}
}