{
  "type": "Feature",
  "properties": {
    "addr:full":"20144 Milano Milano Milano 20144",
    "addr:postcode":"20144;20144",
    "iso:country":"IT",
    "sg:address":"20144 Milano",
    "sg:city":"Milano",
    "sg:orig_category":"Servizi E Lavori Per Abbigliamento E Pelletterie",
    "sg:phone":"+39 02 428280",
    "sg:postcode":"20144",
    "sg:province":"Milano",
    "wof:name":"Cellamare Grazia",
    "wof:placetype":"venue"
},
  "geometry": {"coordinates":[9.156224,45.453083],"type":"Point"}
}