{
  "type": "Feature",
  "properties": {
    "addr:full":"37069 Villafranca Verona Verona 37069",
    "addr:postcode":"37069;37069",
    "iso:country":"IT",
    "sg:address":"37069 Villafranca Verona",
    "sg:classifiers":[
        {
            "category":"Autos & Motor Vehicles",
            "subcategory":"Boat Sales",
            "type":"Retail Goods"
        }
    ],
    "sg:phone":"+39 045 860 0739",
    "sg:postcode":"37069",
    "sg:province":"Verona",
    "sg:tags":[
        "repair",
        "vehicles"
    ],
    "wof:name":"Friscar Srl",
    "wof:placetype":"venue"
},
  "geometry": {"coordinates":[10.9050893784,45.3889198303],"type":"Point"}
}