{
  "type": "Feature",
  "properties": {
    "iso:country":"IT",
    "sg:address":"11, Via Larga 24050 Calcinate",
    "sg:city":"Calcinate",
    "sg:classifiers":[
        {
            "category":"Shopping",
            "type":"Retail Goods"
        }
    ],
    "sg:phone":"+39 035 442 3055",
    "sg:postcode":"24050",
    "sg:province":"Bergamo",
    "sg:tags":[
        "finished",
        "-",
        "metallic"
    ],
    "wof:name":"Asperti F.lli S.r.l.",
    "wof:placetype":"venue"
},
  "geometry": {"coordinates":[9.790017128,45.6161956787],"type":"Point"}
}