{
  "type": "Feature",
  "properties": {
    "iso:country":"IT",
    "sg:address":"70052 Bisceglie",
    "sg:city":"Bisceglie",
    "sg:classifiers":[
        {
            "category":"Community Center",
            "subcategory":"Youth",
            "type":"Public Place"
        }
    ],
    "sg:phone":"+39 080 396 0046",
    "sg:postcode":"70052",
    "sg:province":"Bari",
    "sg:tags":[
        "underwear",
        "bathing",
        "stocking",
        "costume"
    ],
    "sg:website":"http://www.telematicaitalia.it/labirba",
    "wof:name":"La Birba Di Brescia Daniele & C. Snc",
    "wof:placetype":"venue"
},
  "geometry": {"coordinates":[16.505079,41.230209],"type":"Point"}
}