{
  "type": "Feature",
  "properties": {
    "addr:full":"4, Zona D. Artigiani 39030 Terento Terento Bolzano/Bozen 39030",
    "addr:housenumber":"4",
    "addr:postcode":"39030;39030",
    "addr:street":"Zona D. Artigiani",
    "iso:country":"IT",
    "sg:address":"4, Zona D. Artigiani 39030 Terento",
    "sg:city":"Terento",
    "sg:classifiers":[
        {
            "category":"Building & Trades",
            "subcategory":"Construction",
            "type":"Services"
        }
    ],
    "sg:phone":"+39 0472 546193",
    "sg:postcode":"39030",
    "sg:province":"Bolzano/Bozen",
    "sg:tags":[
        "work",
        "public"
    ],
    "wof:name":"Alpenbau (s.n.c.)",
    "wof:placetype":"venue"
},
  "geometry": {"coordinates":[11.35800457,46.4967155457],"type":"Point"}
}