{
  "type": "Feature",
  "properties": {
    "iso:country":"IT",
    "sg:address":"90129 Palermo",
    "sg:city":"Palermo",
    "sg:orig_category":"Materiali Edili",
    "sg:phone":"+39 091 488413",
    "sg:postcode":"90129",
    "sg:province":"Palermo",
    "wof:name":"Arreditalia Di Siragusa Maurizio Snc",
    "wof:placetype":"venue"
},
  "geometry": {"coordinates":[13.340207,38.108788],"type":"Point"}
}