{
  "type": "Feature",
  "properties": {
    "addr:full":"13011 Borgosesia Borgosesia Vercelli 13011",
    "addr:postcode":"13011;13011",
    "iso:country":"IT",
    "sg:address":"13011 Borgosesia",
    "sg:city":"Borgosesia",
    "sg:orig_category":"Pubblica Amministrazione",
    "sg:phone":"+39 0163 23321",
    "sg:postcode":"13011",
    "sg:province":"Vercelli",
    "wof:name":"Guardia Di Finanza",
    "wof:placetype":"venue"
},
  "geometry": {"coordinates":[8.2574167252,45.7293128967],"type":"Point"}
}