{
  "type": "Feature",
  "properties": {
    "iso:country":"IT",
    "sg:address":"80129 Napoli",
    "sg:city":"Napoli",
    "sg:orig_category":"Automazione E Macchine Per Ufficio. Servizi Ausiliari Di Certificati, Riproduzioni, Disegni E Foto",
    "sg:phone":"+39 081 578 3723",
    "sg:postcode":"80129",
    "sg:province":"Napoli",
    "wof:name":"Jechel E. (s.r.l.)",
    "wof:placetype":"venue"
},
  "geometry": {"coordinates":[14.27348,40.892498],"type":"Point"}
}