{
  "type": "Feature",
  "properties": {
    "addr:full":"13853 Lessona Lessona Biella 13853",
    "addr:postcode":"13853;13853",
    "iso:country":"IT",
    "sg:address":"13853 Lessona",
    "sg:city":"Lessona",
    "sg:orig_category":"Motori Ed Organi Di Trasmissione",
    "sg:phone":"+39 015 982192",
    "sg:postcode":"13853",
    "sg:province":"Biella",
    "wof:name":"A.r.c.a. Di Rinaldo Furno & C. Snc",
    "wof:placetype":"venue"
},
  "geometry": {"coordinates":[8.1923704147,45.647518158],"type":"Point"}
}