{
  "type": "Feature",
  "properties": {
    "addr:full":"24030 Ambivere Ambivere Bergamo 24030",
    "addr:postcode":"24030;24030",
    "iso:country":"IT",
    "sg:address":"24030 Ambivere",
    "sg:city":"Ambivere",
    "sg:orig_category":"Servizi E Lavori Per Edilizia E Lavori Pubblici. Acqua, Luce, Gas E Societa' Di Esercizio Pubblico",
    "sg:phone":"+39 035 494 5462",
    "sg:postcode":"24030",
    "sg:province":"Bergamo",
    "wof:name":"Consorzio Acquedotto Dell'isola",
    "wof:placetype":"venue"
},
  "geometry": {"coordinates":[9.636486,45.689686],"type":"Point"}
}