{
  "type": "Feature",
  "properties": {
    "iso:country":"IT",
    "sg:address":"16167 Genova",
    "sg:city":"Genova",
    "sg:orig_category":"Calzature, Pelletterie E Pelli. Shopping",
    "sg:phone":"+39 010 372 6751",
    "sg:postcode":"16167",
    "sg:province":"Genova",
    "wof:name":"Center Bag 2000 Di Cardace Antonio & C. S.a.s.",
    "wof:placetype":"venue"
},
  "geometry": {"coordinates":[9.035509,44.387989],"type":"Point"}
}