{
  "type": "Feature",
  "properties": {
    "iso:country":"IT",
    "sg:address":"39012 Merano",
    "sg:city":"Merano",
    "sg:orig_category":"Apparecchiature Ed Attrezzature Meccaniche. Macchine, Strumenti Ed Apparecchi Per Attivita' Industriali",
    "sg:phone":"+39 0473 449099",
    "sg:postcode":"39012",
    "sg:province":"Bolzano/Bozen",
    "wof:name":"Pressol (s.r.l.)",
    "wof:placetype":"venue"
},
  "geometry": {"coordinates":[11.151839,46.653919],"type":"Point"}
}