{
  "type": "Feature",
  "properties": {
    "addr:full":"Via Longarone 20080 Zibido San Giacomo Zibido San Giacomo Milano 20080",
    "addr:postcode":"20080;20080",
    "addr:street":"Via Longarone;San",
    "iso:country":"IT",
    "sg:address":"Via Longarone 20080 Zibido San Giacomo",
    "sg:city":"Zibido San Giacomo",
    "sg:classifiers":[
        {
            "category":"Real Estate",
            "subcategory":"Real Estate Agent",
            "type":"Services"
        }
    ],
    "sg:phone":"+39 02 9000 5075",
    "sg:postcode":"20080",
    "sg:province":"Milano",
    "sg:tags":[
        "lacquer"
    ],
    "sg:website":"www.ilgabbianosas.it",
    "wof:name":"Il Gabbiano Sas Di Chisena A & C",
    "wof:placetype":"venue"
},
  "geometry": {"coordinates":[9.123543,45.367592],"type":"Point"}
}