{
  "type": "Feature",
  "properties": {
    "iso:country":"IT",
    "sg:address":"14, Via Villa Sotto 38011 Don",
    "sg:city":"Don",
    "sg:orig_category":"Miscellaneous Products",
    "sg:phone":"+39 0463 875186",
    "sg:postcode":"38011",
    "sg:province":"Trento",
    "wof:name":"Endricci",
    "wof:placetype":"venue"
},
  "geometry": {"coordinates":[11.1352491379,46.3906822205],"type":"Point"}
}