{
  "type": "Feature",
  "properties": {
    "iso:country":"IT",
    "sg:address":"31036 Istrana",
    "sg:city":"Istrana",
    "sg:orig_category":"Materie Plastiche - Produzione E Lavorazione",
    "sg:phone":"+39 0422 832223",
    "sg:postcode":"31036",
    "sg:province":"Treviso",
    "sg:website":"http://www.ellediplast.it",
    "wof:name":"Elledi Plast Srl",
    "wof:placetype":"venue"
},
  "geometry": {"coordinates":[12.09647,45.692131],"type":"Point"}
}