{
  "type": "Feature",
  "properties": {
    "iso:country":"IT",
    "sg:address":"34, Via Cristoforo Colombo 35011 Campodarsego",
    "sg:city":"Campodarsego",
    "sg:classifiers":[
        {
            "category":"Food & Beverages",
            "subcategory":"Groceries & Convenience Stores",
            "type":"Retail Goods"
        }
    ],
    "sg:phone":"+39 049 920 1496",
    "sg:postcode":"35011",
    "sg:province":"Padova",
    "sg:tags":[
        "drink"
    ],
    "wof:name":"Chimab S.p.a.",
    "wof:placetype":"venue"
},
  "geometry": {"coordinates":[11.904157,45.48521],"type":"Point"}
}