{
  "type": "Feature",
  "properties": {
    "addr:full":"Via Brandizzo 145 10088 Volpiano Volpiano Torino 10088",
    "addr:housenumber":"145",
    "addr:postcode":"10088;10088",
    "addr:street":"Via Brandizzo",
    "iso:country":"IT",
    "sg:address":"Via Brandizzo 145 10088 Volpiano",
    "sg:city":"Volpiano",
    "sg:classifiers":[
        {
            "category":"Government",
            "subcategory":"Post Office",
            "type":"Public Place"
        }
    ],
    "sg:phone":"+39 011 988 2352",
    "sg:postcode":"10088",
    "sg:province":"Torino",
    "sg:tags":[
        "blade",
        "saw",
        "circular"
    ],
    "sg:website":"www.isap.it",
    "wof:name":"Isap Srl",
    "wof:placetype":"venue"
},
  "geometry": {"coordinates":[7.813622,45.174004],"type":"Point"}
}