{
  "type": "Feature",
  "properties": {
    "iso:country":"IT",
    "sg:address":"20133 Milano",
    "sg:city":"Milano",
    "sg:orig_category":"Tessuti E Stoffe",
    "sg:phone":"+39 02 7010 8311",
    "sg:postcode":"20133",
    "sg:province":"Milano",
    "wof:name":"Ortel S.p.a.",
    "wof:placetype":"venue"
},
  "geometry": {"coordinates":[9.229692,45.471371],"type":"Point"}
}