{
  "type": "Feature",
  "properties": {
    "iso:country":"IT",
    "sg:address":"20040 Cavenago Di Brianza",
    "sg:city":"Cavenago di Brianza",
    "sg:orig_category":"Bilance, Bilici E Bascule",
    "sg:phone":"+39 02 9533 9165",
    "sg:postcode":"20040",
    "sg:province":"Milano",
    "sg:website":"http://www.pavonesistemi.it",
    "wof:name":"Pavone Sistemi Srl",
    "wof:placetype":"venue"
},
  "geometry": {"coordinates":[9.412702,45.579376],"type":"Point"}
}