{
  "type": "Feature",
  "properties": {
    "addr:full":"20149 Milano Milano Milano 20149",
    "addr:postcode":"20149;20149",
    "iso:country":"IT",
    "sg:address":"20149 Milano",
    "sg:city":"Milano",
    "sg:orig_category":"Ospedali E Servizi Sanitari",
    "sg:phone":"+39 02 462257",
    "sg:postcode":"20149",
    "sg:province":"Milano",
    "wof:name":"D.g. Dental Di D'ambrosio Giuseppe",
    "wof:placetype":"venue"
},
  "geometry": {"coordinates":[9.155252,45.468075],"type":"Point"}
}