{
  "type": "Feature",
  "properties": {
    "iso:country":"IT",
    "sg:address":"75, Via Roma 24030 Medolago",
    "sg:city":"Medolago",
    "sg:classifiers":[
        {
            "category":"Professional",
            "subcategory":"Engineering",
            "type":"Services"
        }
    ],
    "sg:phone":"+39 39035901717",
    "sg:postcode":"24030",
    "sg:province":"Bergamo",
    "sg:tags":[
        "machine",
        "-",
        "mechanical"
    ],
    "wof:name":"Co.ma.l.l. F.lli Pesavento Dipesavento Fausto & C. S.n.c.",
    "wof:placetype":"venue"
},
  "geometry": {"coordinates":[9.486482,45.679646],"type":"Point"}
}