{
  "type": "Feature",
  "properties": {
    "addr:full":"05034 Ferentillo Ferentillo Terni 05034",
    "addr:postcode":"05034;05034",
    "iso:country":"IT",
    "sg:address":"05034 Ferentillo",
    "sg:city":"Ferentillo",
    "sg:classifiers":[
        {
            "category":"Manufacturing",
            "subcategory":"Tools & Machinery",
            "type":"Manufacturing & Wholesale Goods"
        }
    ],
    "sg:phone":"+39 0744 780727",
    "sg:postcode":"05034",
    "sg:province":"Terni",
    "sg:tags":[
        "material",
        "mechanical"
    ],
    "wof:name":"Vipal Spa",
    "wof:placetype":"venue"
},
  "geometry": {"coordinates":[12.828477,42.626431],"type":"Point"}
}