{
  "type": "Feature",
  "properties": {
    "addr:full":"90146 Palermo Palermo Palermo 90146",
    "addr:postcode":"90146;90146",
    "iso:country":"IT",
    "sg:address":"90146 Palermo",
    "sg:city":"Palermo",
    "sg:orig_category":"Elettronica Professionale E Di Consumo. Tempo Libero - Articoli E Forniture",
    "sg:phone":"+39 091 630 6054",
    "sg:postcode":"90146",
    "sg:province":"Palermo",
    "wof:name":"American Giochi",
    "wof:placetype":"venue"
},
  "geometry": {"coordinates":[13.376877,38.091934],"type":"Point"}
}