{
  "type": "Feature",
  "properties": {
    "iso:country":"IT",
    "sg:address":"Via Pirelli 20 20124 Milano",
    "sg:city":"Milano",
    "sg:orig_category":"Karl-fischer Reagents",
    "sg:phone":"+39 02 678 7711",
    "sg:postcode":"20124",
    "sg:province":"Milano",
    "sg:website":"www.icnbiomed.com",
    "wof:name":"Icn Farmaceuticas Italy S.r.l.",
    "wof:placetype":"venue"
},
  "geometry": {"coordinates":[9.198696,45.483936],"type":"Point"}
}