{
  "type": "Feature",
  "properties": {
    "iso:country":"IT",
    "sg:address":"60, Via Fondo Ausa 47031 Repubblica Di San Marino",
    "sg:classifiers":[
        {
            "category":"Wholesale",
            "subcategory":"Drugs",
            "type":"Manufacturing & Wholesale Goods"
        }
    ],
    "sg:phone":"+39 0549 909025",
    "sg:province":"SM",
    "sg:tags":[
        "chemical",
        "pharmaceutical"
    ],
    "wof:name":"Difass S.a.",
    "wof:placetype":"venue"
},
  "geometry": {"coordinates":[12.4994,43.985458],"type":"Point"}
}