{
  "type": "Feature",
  "properties": {
    "iso:country":"IT",
    "sg:address":"20121 Milano",
    "sg:city":"Milano",
    "sg:orig_category":"Abbigliamento Intimo, Calze E Costumi Da Bagno. Sport - Articoli E Forniture. Shopping",
    "sg:phone":"+39 02 860423",
    "sg:postcode":"20121",
    "sg:province":"Milano",
    "wof:name":"Parah Boutique",
    "wof:placetype":"venue"
},
  "geometry": {"coordinates":[9.185846,45.472031],"type":"Point"}
}