{
  "type": "Feature",
  "properties": {
    "iso:country":"IT",
    "sg:address":"97, Via Bellini Vincenzo 50041 Calenzano",
    "sg:city":"Calenzano",
    "sg:classifiers":[
        {
            "category":"Professional",
            "subcategory":"Engineering",
            "type":"Services"
        }
    ],
    "sg:phone":"+39 055 881 9915",
    "sg:postcode":"50041",
    "sg:province":"Firenze",
    "sg:tags":[
        "machine",
        "-",
        "mechanical"
    ],
    "wof:name":"Co.me.ca",
    "wof:placetype":"venue"
},
  "geometry": {"coordinates":[11.207866,43.827423],"type":"Point"}
}