{
  "type": "Feature",
  "properties": {
    "iso:country":"IT",
    "sg:address":"Piazza Vi Dicembre Ang; Enna; 94100",
    "sg:city":"Enna",
    "sg:classifiers":[
        {
            "category":"Banks & Credit Unions",
            "subcategory":"Bank",
            "type":"Services"
        }
    ],
    "sg:phone":"+39 0935 24444",
    "sg:postcode":"94100",
    "sg:province":"Enna",
    "wof:name":"Istituto Bancario, San Paolo Di Torino Spa",
    "wof:placetype":"venue"
},
  "geometry": {"coordinates":[14.262851,37.509933],"type":"Point"}
}