{
  "type": "Feature",
  "properties": {
    "iso:country":"IT",
    "sg:address":"Via Stoppani 22032 Albese",
    "sg:classifiers":[
        {
            "category":"Manufacturing",
            "subcategory":"Textiles",
            "type":"Manufacturing & Wholesale Goods"
        }
    ],
    "sg:phone":"+39 031 360110",
    "sg:postcode":"22032",
    "sg:province":"Como",
    "sg:tags":[
        "blended",
        "yarn"
    ],
    "wof:name":"Trel Di Locati Marco & C. Snc",
    "wof:placetype":"venue"
},
  "geometry": {"coordinates":[9.173972,45.79287],"type":"Point"}
}