{
  "type": "Feature",
  "properties": {
    "iso:country":"IT",
    "sg:address":"Via G. Di Vittorio 1 20063 Cernusco Sul Naviglio",
    "sg:city":"Cernusco sul Naviglio",
    "sg:classifiers":[
        {
            "category":"Manufacturing",
            "subcategory":"Motor Vehicles & Parts",
            "type":"Manufacturing & Wholesale Goods"
        }
    ],
    "sg:phone":"+39 02 923651",
    "sg:postcode":"20063",
    "sg:province":"Milano",
    "sg:tags":[
        "electromechanical"
    ],
    "sg:website":"www.boshrexroth.it",
    "wof:name":"Gruppo Bosch Rexroth S.p.a.",
    "wof:placetype":"venue"
},
  "geometry": {"coordinates":[9.284911,45.513279],"type":"Point"}
}