{
  "type": "Feature",
  "properties": {
    "addr:full":"Piazza Roma 3; Giulianova; 64022",
    "addr:housenumber":"3",
    "addr:postcode":"64022",
    "addr:street":"Piazza Roma",
    "iso:country":"IT",
    "sg:address":"Piazza Roma 3; Giulianova; 64022",
    "sg:classifiers":[
        {
            "category":"Banks & Credit Unions",
            "subcategory":"Bank",
            "type":"Services"
        }
    ],
    "sg:phone":"+39 085 800 3318",
    "wof:name":"Banco Di Napoli Spa",
    "wof:placetype":"venue"
},
  "geometry": {"coordinates":[13.964945,42.751534],"type":"Point"}
}