{
  "type": "Feature",
  "properties": {
    "addr:full":"41/43, V. Consolare 25030 Zocco Di Erbusco Erbusco Brescia 25030",
    "addr:housenumber":"41 / 43 v.",
    "addr:postcode":"25030;25030",
    "addr:street":"Consolare",
    "iso:country":"IT",
    "sg:address":"41/43, V. Consolare 25030 Zocco Di Erbusco",
    "sg:city":"Erbusco",
    "sg:classifiers":[
        {
            "category":"Shopping",
            "type":"Retail Goods"
        }
    ],
    "sg:phone":"+39 030 776 0257",
    "sg:postcode":"25030",
    "sg:province":"Brescia",
    "sg:tags":[
        "finished",
        "-",
        "metallic"
    ],
    "sg:website":"http://www.farbel.com",
    "wof:name":"Farbel Srl",
    "wof:placetype":"venue"
},
  "geometry": {"coordinates":[9.9377250671,45.6016845703],"type":"Point"}
}