{
  "type": "Feature",
  "properties": {
    "iso:country":"IT",
    "sg:address":"41049 Sassuolo",
    "sg:city":"Sassuolo",
    "sg:classifiers":[
        {
            "category":"Professional",
            "subcategory":"Art Services",
            "type":"Services"
        }
    ],
    "sg:phone":"+39 0536 811081",
    "sg:postcode":"41049",
    "sg:province":"Modena",
    "sg:tags":[
        "studi",
        "designer",
        "-"
    ],
    "sg:website":"http://www.exprimo.it",
    "wof:name":"Exprimo Srl",
    "wof:placetype":"venue"
},
  "geometry": {"coordinates":[10.783298,44.536282],"type":"Point"}
}