{
  "type": "Feature",
  "properties": {
    "iso:country":"IT",
    "sg:address":"73024 Maglie",
    "sg:city":"Maglie",
    "sg:orig_category":"Carrozzerie - Forniture",
    "sg:phone":"+39 0836 427888",
    "sg:postcode":"73024",
    "sg:province":"Lecce",
    "wof:name":"Valerio G. & C. Snc",
    "wof:placetype":"venue"
},
  "geometry": {"coordinates":[18.29707,40.120602],"type":"Point"}
}