{
  "type": "Feature",
  "properties": {
    "iso:country":"IT",
    "sg:address":"Via Roma 315 31043 Fontanelle",
    "sg:city":"Fontanelle",
    "sg:classifiers":[
        {
            "category":"Manufacturing",
            "subcategory":"Furniture",
            "type":"Manufacturing & Wholesale Goods"
        }
    ],
    "sg:phone":"+39 0422 8183",
    "sg:postcode":"31043",
    "sg:province":"Treviso",
    "sg:tags":[
        "bedroom"
    ],
    "wof:name":"Mobil Record - S.r.l.",
    "wof:placetype":"venue"
},
  "geometry": {"coordinates":[12.209793,45.715496],"type":"Point"}
}