{
  "type": "Feature",
  "properties": {
    "iso:country":"IT",
    "sg:address":"25064 Gussago",
    "sg:city":"Gussago",
    "sg:orig_category":"Materiali Semilavorati Metallici",
    "sg:phone":"+39 030 320850",
    "sg:postcode":"25064",
    "sg:province":"Brescia",
    "wof:name":"T.f.e. (s.r.l.)",
    "wof:placetype":"venue"
},
  "geometry": {"coordinates":[10.15785,45.555443],"type":"Point"}
}