{
  "type": "Feature",
  "properties": {
    "iso:country":"IT",
    "sg:address":"00182 Roma",
    "sg:city":"Roma",
    "sg:orig_category":"Servizi Per Lo Sport E Il Tempo Libero. Servizi Al Turismo",
    "sg:phone":"+39 06 7030 5210",
    "sg:postcode":"00182",
    "sg:province":"Roma",
    "wof:name":"Digital Demo S.n.c.",
    "wof:placetype":"venue"
},
  "geometry": {"coordinates":[12.522349,41.888611],"type":"Point"}
}