{
  "type": "Feature",
  "properties": {
    "addr:full":"87/19, Strada Del Francese 10156 Torino Torino Torino 10156",
    "addr:housenumber":"87 / 19",
    "addr:postcode":"10156;10156",
    "addr:street":"Strada Del Francese",
    "iso:country":"IT",
    "sg:address":"87/19, Strada Del Francese 10156 Torino",
    "sg:city":"Torino",
    "sg:classifiers":[
        {
            "category":"Shopping",
            "type":"Retail Goods"
        }
    ],
    "sg:phone":"+39 011 450 0333",
    "sg:postcode":"10156",
    "sg:province":"Torino",
    "sg:tags":[
        "finished",
        "-",
        "metallic"
    ],
    "wof:name":"Nuova Omege S.p.a.",
    "wof:placetype":"venue"
},
  "geometry": {"coordinates":[7.672460556,45.1347351074],"type":"Point"}
}