{
  "type": "Feature",
  "properties": {
    "addr:full":"Vle Amendola Costa Dei Barbari 55049 Viareggio Viareggio Lucca 55049",
    "addr:postcode":"55049;55049",
    "addr:street":"Vle Amendola Costa Dei Barbari",
    "iso:country":"IT",
    "sg:address":"Vle Amendola Costa Dei Barbari 55049 Viareggio",
    "sg:city":"Viareggio",
    "sg:classifiers":[
        {
            "category":"Metro Station",
            "type":"Transportation"
        }
    ],
    "sg:phone":"+39 0584 383221",
    "sg:postcode":"55049",
    "sg:province":"Lucca",
    "sg:tags":[
        "ship",
        "boat",
        "special-purpose"
    ],
    "sg:website":"www.codecasayachts.com",
    "wof:name":"Cantieri Navali Ugo Codecasa Spa",
    "wof:placetype":"venue"
},
  "geometry": {"coordinates":[10.507994,43.843014],"type":"Point"}
}