{
  "type": "Feature",
  "properties": {
    "addr:full":"90133 Palermo Palermo Palermo 90133",
    "addr:postcode":"90133;90133",
    "iso:country":"IT",
    "sg:address":"90133 Palermo",
    "sg:city":"Palermo",
    "sg:orig_category":"Calzature, Pelletterie E Pelli. Shopping",
    "sg:phone":"+39 091 617 5794",
    "sg:postcode":"90133",
    "sg:province":"Palermo",
    "wof:name":"Patorno Giuseppe",
    "wof:placetype":"venue"
},
  "geometry": {"coordinates":[13.365949,38.115482],"type":"Point"}
}