{
  "type": "Feature",
  "properties": {
    "addr:full":"Via Marsala 19 58100 Grosseto Grosseto Grosseto 58100",
    "addr:housenumber":"19",
    "addr:postcode":"58100;58100",
    "addr:street":"Via Marsala",
    "iso:country":"IT",
    "sg:address":"Via Marsala 19 58100 Grosseto",
    "sg:city":"Grosseto",
    "sg:orig_category":"Hotels: Equipment",
    "sg:phone":"+39 0564 25577",
    "sg:postcode":"58100",
    "sg:province":"Grosseto",
    "wof:name":"Piersanti E C Srl",
    "wof:placetype":"venue"
},
  "geometry": {"coordinates":[11.1318569183,42.7627372742],"type":"Point"}
}