{
  "type": "Feature",
  "properties": {
    "iso:country":"IT",
    "sg:address":"120/124, Via Colloredo 33037 Pasian Di Prato",
    "sg:city":"Pasian di Prato",
    "sg:classifiers":[
        {
            "category":"Home & Garden",
            "subcategory":"Home Furnishings",
            "type":"Retail Goods"
        }
    ],
    "sg:phone":"+39 0432 690623",
    "sg:postcode":"33037",
    "sg:province":"Udine",
    "sg:tags":[
        "household"
    ],
    "wof:name":"Friulana Accessori (s.r.l.)",
    "wof:placetype":"venue"
},
  "geometry": {"coordinates":[13.173676,46.051403],"type":"Point"}
}