{
  "type": "Feature",
  "properties": {
    "addr:full":"23, Via Milano 25037 Pontoglio Pontoglio Brescia 25037",
    "addr:postcode":"25037;25037",
    "addr:street":"Via Milano",
    "iso:country":"IT",
    "sg:address":"23, Via Milano 25037 Pontoglio",
    "sg:city":"Pontoglio",
    "sg:classifiers":[
        {
            "category":"Manufacturing",
            "subcategory":"Motor Vehicles & Parts",
            "type":"Manufacturing & Wholesale Goods"
        }
    ],
    "sg:phone":"+39 030 737 6853",
    "sg:postcode":"25037",
    "sg:province":"Brescia",
    "sg:tags":[
        "engine"
    ],
    "wof:name":"V.b. Di Belotti Alessandro E C. S.n.c.",
    "wof:placetype":"venue"
},
  "geometry": {"coordinates":[9.857085,45.579849],"type":"Point"}
}