{
  "type": "Feature",
  "properties": {
    "iso:country":"IT",
    "sg:address":"Km. 266,300, S.s. 115 - Zona Industriale 93012 Gela",
    "sg:city":"Gela",
    "sg:classifiers":[
        {
            "category":"Parking",
            "subcategory":"Lot",
            "type":"Transportation"
        }
    ],
    "sg:phone":"+39 0933 921478",
    "sg:postcode":"93012",
    "sg:province":"Caltanissetta",
    "sg:tags":[
        "transport",
        "road"
    ],
    "sg:website":"http://www.paginegialle.it/biundotrasporti",
    "wof:name":"Eredi Biundo R. A. Snc",
    "wof:placetype":"venue"
},
  "geometry": {"coordinates":[14.06329,37.48991],"type":"Point"}
}