{
  "type": "Feature",
  "properties": {
    "iso:country":"IT",
    "sg:address":"25064 Gussago",
    "sg:city":"Gussago",
    "sg:orig_category":"Macchine Ed Impianti Per Edilizia E Lavori Pubblici",
    "sg:phone":"+39 030 373 0977",
    "sg:postcode":"25064",
    "sg:province":"Brescia",
    "wof:name":"La Casa Del Martello",
    "wof:placetype":"venue"
},
  "geometry": {"coordinates":[10.152153,45.550667],"type":"Point"}
}