{
  "type": "Feature",
  "properties": {
    "addr:full":"32014 Ponte Nelle Alpi Ponte nelle Alpi Belluno 32014",
    "addr:postcode":"32014;32014",
    "iso:country":"IT",
    "sg:address":"32014 Ponte Nelle Alpi",
    "sg:city":"Ponte nelle Alpi",
    "sg:orig_category":"Apparecchiature Elettriche Civili Ed Industriali",
    "sg:phone":"+39 0437 989171",
    "sg:postcode":"32014",
    "sg:province":"Belluno",
    "wof:name":"Misure Srl",
    "wof:placetype":"venue"
},
  "geometry": {"coordinates":[12.283276,46.174549],"type":"Point"}
}