{
  "type": "Feature",
  "properties": {
    "iso:country":"IT",
    "sg:address":"20019 Settimo Milanese",
    "sg:city":"Settimo Milanese",
    "sg:orig_category":"Arredamenti - Produzione E Ingrosso",
    "sg:phone":"+39 02 3351 2552",
    "sg:postcode":"20019",
    "sg:province":"Milano",
    "wof:name":"Officina Picca Srl",
    "wof:placetype":"venue"
},
  "geometry": {"coordinates":[9.06477,45.480404],"type":"Point"}
}