{
  "type": "Feature",
  "properties": {
    "iso:country":"IT",
    "sg:address":"95032 Belpasso",
    "sg:city":"Belpasso",
    "sg:orig_category":"Biancheria Intima Ed Abbigliamento Intimo - Vendita Al Dettaglio",
    "sg:phone":"+39 095 391570",
    "sg:postcode":"95032",
    "sg:province":"Catania",
    "wof:name":"Loleancot Srl",
    "wof:placetype":"venue"
},
  "geometry": {"coordinates":[14.927204,37.520317],"type":"Point"}
}