{
  "type": "Feature",
  "properties": {
    "addr:full":"20132 Milano Milano Milano 20132",
    "addr:postcode":"20132;20132",
    "iso:country":"IT",
    "sg:address":"20132 Milano",
    "sg:city":"Milano",
    "sg:orig_category":"Utensili Meccanici E Materiali",
    "sg:phone":"+39 02 2851 0153",
    "sg:postcode":"20132",
    "sg:province":"Milano",
    "wof:name":"Diama Sas Di Mariani Adolfo E C",
    "wof:placetype":"venue"
},
  "geometry": {"coordinates":[9.238126,45.499062],"type":"Point"}
}