{
  "type": "Feature",
  "properties": {
    "iso:country":"IT",
    "sg:address":"16128 Genova",
    "sg:city":"Genova",
    "sg:classifiers":[
        {
            "category":"Health Services",
            "subcategory":"Health Practitioner",
            "type":"Services"
        }
    ],
    "sg:phone":"+39 010 584685",
    "sg:postcode":"16128",
    "sg:province":"Genova",
    "sg:tags":[
        "medici"
    ],
    "wof:name":"Brughera Gino",
    "wof:placetype":"venue"
},
  "geometry": {"coordinates":[8.939987,44.397831],"type":"Point"}
}