{
  "type": "Feature",
  "properties": {
    "iso:country":"IT",
    "sg:address":"24126 Bergamo",
    "sg:city":"Bergamo",
    "sg:orig_category":"Agenzie D'affari E Servizi Commerciali",
    "sg:phone":"+39 800 117 766",
    "sg:postcode":"24126",
    "sg:province":"Bergamo",
    "wof:name":"Pec - Pronto Emergenza Casa Srl",
    "wof:placetype":"venue"
},
  "geometry": {"coordinates":[9.664414,45.6842],"type":"Point"}
}