{
  "type": "Feature",
  "properties": {
    "addr:full":"67061 Carsoli L'Aquila 67061",
    "addr:postcode":"67061;l'aquila 67061",
    "iso:country":"IT",
    "sg:address":"67061 Carsoli",
    "sg:orig_category":"Ospedali E Servizi Sanitari. Centri Di Estetica E Cosmesi E Servizi",
    "sg:phone":"+39 0863 909048",
    "sg:postcode":"67061",
    "sg:province":"L'Aquila",
    "wof:name":"Podologo - Greco Maria Giovanna Maria Giovanna",
    "wof:placetype":"venue"
},
  "geometry": {"coordinates":[13.094582,42.101284],"type":"Point"}
}