{
  "type": "Feature",
  "properties": {
    "addr:full":"16, Via Redipuglia 34070 San Pier D'isonzo Redipuglia Gorizia 34070",
    "addr:postcode":"34070;34070",
    "addr:street":"Via Redipuglia",
    "iso:country":"IT",
    "sg:address":"16, Via Redipuglia 34070 San Pier D'isonzo",
    "sg:city":"Redipuglia",
    "sg:classifiers":[
        {
            "category":"Professional",
            "subcategory":"Engineering",
            "type":"Services"
        }
    ],
    "sg:phone":"+39 39048170297",
    "sg:postcode":"34070",
    "sg:province":"Gorizia",
    "sg:tags":[
        "machine",
        "-",
        "mechanical"
    ],
    "wof:name":"N.e.m. S.n.c.",
    "wof:placetype":"venue"
},
  "geometry": {"coordinates":[13.411222,45.842445],"type":"Point"}
}