{
  "type": "Feature",
  "properties": {
    "iso:country":"IT",
    "sg:address":"20094 Corsico",
    "sg:city":"Corsico",
    "sg:orig_category":"Macchine, Impianti E Forniture Per Industria Grafica, Cartaria E Cartotecnica",
    "sg:phone":"+39 02 440 6294",
    "sg:postcode":"20094",
    "sg:province":"Milano",
    "wof:name":"Globograf Di Grossi Enrico",
    "wof:placetype":"venue"
},
  "geometry": {"coordinates":[9.081244,45.425957],"type":"Point"}
}