{
  "type": "Feature",
  "properties": {
    "iso:country":"IT",
    "sg:address":"44028 Poggio Renatico",
    "sg:city":"Gallo",
    "sg:orig_category":"Macchine, Impianti Ed Attrezzature Per Agricoltura E Zootecnia",
    "sg:phone":"+39 0532 820017",
    "sg:postcode":"44028",
    "sg:province":"Ferrara",
    "wof:name":"F. Lli Festi Di Festi Roberto & C. Snc",
    "wof:placetype":"venue"
},
  "geometry": {"coordinates":[11.504056,44.774368],"type":"Point"}
}