{
  "type": "Feature",
  "properties": {
    "iso:country":"IT",
    "sg:address":"01038 Soriano Nel Cimino",
    "sg:city":"Soriano nel Cimino",
    "sg:orig_category":"Arredo Cucina Ed Elettrodomestici",
    "sg:phone":"+39 0761 749336",
    "sg:postcode":"01038",
    "sg:province":"Viterbo",
    "wof:name":"Cucine & Cucine Srl",
    "wof:placetype":"venue"
},
  "geometry": {"coordinates":[12.234416,42.427074],"type":"Point"}
}