{
  "type": "Feature",
  "properties": {
    "iso:country":"IT",
    "sg:address":"00175 Roma",
    "sg:city":"Roma",
    "sg:orig_category":"Abbigliamento Esterno, Maglierie E Pelliccerie. Shopping",
    "sg:phone":"+39 06 765124",
    "sg:postcode":"00175",
    "sg:province":"Roma",
    "wof:name":"Cgm 90 Srl",
    "wof:placetype":"venue"
},
  "geometry": {"coordinates":[12.558596,41.859623],"type":"Point"}
}