{
  "type": "Feature",
  "properties": {
    "iso:country":"IT",
    "sg:address":"20127 Milano",
    "sg:city":"Milano",
    "sg:orig_category":"Servizi Al Turismo. Ambasciate Ed Enti Internazionali",
    "sg:phone":"+39 02 2682 1752",
    "sg:postcode":"20127",
    "sg:province":"Milano",
    "wof:name":"Consolato Peru'",
    "wof:placetype":"venue"
},
  "geometry": {"coordinates":[9.22226,45.493233],"type":"Point"}
}