{
  "type": "Feature",
  "properties": {
    "iso:country":"IT",
    "sg:address":"33170 Pordenone",
    "sg:city":"Pordenone",
    "sg:classifiers":[
        {
            "category":"Banks & Credit Unions",
            "subcategory":"Investment Brokerage",
            "type":"Services"
        }
    ],
    "sg:phone":"+39 0434 573369",
    "sg:postcode":"33170",
    "sg:province":"Pordenone",
    "sg:tags":[
        "activities",
        "refuse",
        "industrial",
        "environmental",
        "disposal",
        "household",
        "equipment",
        "instrument",
        "protection",
        "machinery",
        "appliances",
        "supplies",
        "accommodation",
        "machines"
    ],
    "wof:name":"Idrosystem Snc",
    "wof:placetype":"venue"
},
  "geometry": {"coordinates":[12.656448,45.922134],"type":"Point"}
}