{
  "type": "Feature",
  "properties": {
    "iso:country":"IT",
    "sg:address":"95030 San Pietro Clarenza",
    "sg:city":"San Pietro Clarenza",
    "sg:orig_category":"Prodotti Di Base E Forniture Per Industria Alimentare E Bevande",
    "sg:phone":"+39 095 520636",
    "sg:postcode":"95030",
    "sg:province":"Catania",
    "wof:name":"Garozzo Augusto",
    "wof:placetype":"venue"
},
  "geometry": {"coordinates":[15.0178308487,37.5704612732],"type":"Point"}
}