{
  "type": "Feature",
  "properties": {
    "iso:country":"IT",
    "sg:address":"Km. 1.400, Via Foggia 71016 San Severo",
    "sg:city":"San Severo",
    "sg:orig_category":"Miscellaneous Products",
    "sg:phone":"+39 0882 331421",
    "sg:postcode":"71016",
    "sg:province":"Foggia",
    "wof:name":"Vetreria D'amico (s.r.l.)",
    "wof:placetype":"venue"
},
  "geometry": {"coordinates":[15.5446996689,41.4623336792],"type":"Point"}
}