{
  "type": "Feature",
  "properties": {
    "iso:country":"IT",
    "sg:address":"25, Via Provinciale Per Lecco 22030 Lipomo",
    "sg:city":"Lipomo",
    "sg:classifiers":[
        {
            "category":"Shopping",
            "subcategory":"Crafts & Fabrics",
            "type":"Retail Goods"
        }
    ],
    "sg:phone":"+39 39031557888",
    "sg:postcode":"22030",
    "sg:province":"Como",
    "wof:name":"Christian Fischbacher Spa",
    "wof:placetype":"venue"
},
  "geometry": {"coordinates":[9.1207990646,45.7972297668],"type":"Point"}
}