{
  "type": "Feature",
  "properties": {
    "iso:country":"IT",
    "sg:address":"6 Via Piacenza, 00184 Roma",
    "sg:city":"Roma",
    "sg:classifiers":[
        {
            "category":"Banks & Credit Unions",
            "subcategory":"Financial Services",
            "type":"Services"
        }
    ],
    "sg:phone":"+39 390 647 971",
    "sg:postcode":"00184",
    "sg:province":"Roma",
    "sg:tags":[
        "banking",
        "finance",
        "insurance"
    ],
    "wof:name":"Banca Istituto Italiano Di Credito Fondiario (spa)",
    "wof:placetype":"venue"
},
  "geometry": {"coordinates":[12.5044755936,41.834651947],"type":"Point"}
}