{
  "type": "Feature",
  "properties": {
    "addr:full":"Via I Maggio 4 59013 Montemurlo Montemurlo Prato 59013",
    "addr:housenumber":"4",
    "addr:postcode":"59013;59013",
    "addr:street":"Via I Maggio",
    "iso:country":"IT",
    "sg:address":"Via I Maggio 4 59013 Montemurlo",
    "sg:city":"Montemurlo",
    "sg:classifiers":[
        {
            "category":"Manufacturing",
            "subcategory":"Textiles",
            "type":"Manufacturing & Wholesale Goods"
        }
    ],
    "sg:phone":"+39 0574 680906",
    "sg:postcode":"59013",
    "sg:province":"Prato",
    "sg:tags":[
        "thread",
        "yarn",
        "fancy"
    ],
    "sg:website":"www.filatiriccio.it",
    "wof:name":"Filati Riccio Srl",
    "wof:placetype":"venue"
},
  "geometry": {"coordinates":[11.0347671509,43.903213501],"type":"Point"}
}