{
  "type": "Feature",
  "properties": {
    "iso:country":"IT",
    "sg:address":"14, V. Provinciale 24040 Lallio",
    "sg:city":"Lallio",
    "sg:classifiers":[
        {
            "category":"Shopping",
            "subcategory":"Clothing, Apparel, & Fashions",
            "type":"Retail Goods"
        }
    ],
    "sg:phone":"+39 39035690566",
    "sg:postcode":"24040",
    "sg:province":"Bergamo",
    "sg:tags":[
        "clothes"
    ],
    "sg:website":"http://www.santinisms.it:ws_end: :mark:ws:http://www.paginegialle.it/santini-01",
    "wof:name":"Santini Maglificio Sportivo",
    "wof:placetype":"venue"
},
  "geometry": {"coordinates":[9.612682,45.641319],"type":"Point"}
}