{
  "type": "Feature",
  "properties": {
    "addr:full":"Via S. Pietro A Trisaia 75025 Policoro Policoro Matera 75025",
    "addr:postcode":"75025;75025",
    "addr:street":"Via S. Pietro A Trisaia",
    "iso:country":"IT",
    "sg:address":"Via S. Pietro A Trisaia 75025 Policoro",
    "sg:city":"Policoro",
    "sg:classifiers":[
        {
            "category":"Food & Beverages",
            "subcategory":"Groceries & Convenience Stores",
            "type":"Retail Goods"
        }
    ],
    "sg:phone":"+39 0835 902961",
    "sg:postcode":"75025",
    "sg:province":"Matera",
    "sg:tags":[
        "product",
        "related"
    ],
    "wof:name":"Agrifela S.r.l.",
    "wof:placetype":"venue"
},
  "geometry": {"coordinates":[16.606086731,40.6686515808],"type":"Point"}
}