{
  "type": "Feature",
  "properties": {
    "iso:country":"IT",
    "sg:address":"24040 Ciserano",
    "sg:city":"Ciserano",
    "sg:orig_category":"Forniture Per Abbigliamento E Pelletterie. Forniture E Materiali Per Imballaggio E Confezionamento",
    "sg:phone":"+39 035 882282",
    "sg:postcode":"24040",
    "sg:province":"Bergamo",
    "wof:name":"Nastrificio Zingonia (s.r.l.)",
    "wof:placetype":"venue"
},
  "geometry": {"coordinates":[9.608953476,45.5917816162],"type":"Point"}
}