{
  "type": "Feature",
  "properties": {
    "addr:full":"86, Viale Castellammare 00054 Fiumicino Fiumicino Roma 00054",
    "addr:housenumber":"86",
    "addr:postcode":"00054;roma 00054",
    "addr:street":"Viale Castellammare",
    "iso:country":"IT",
    "sg:address":"86, Viale Castellammare 00054 Fiumicino",
    "sg:city":"Fiumicino",
    "sg:classifiers":[
        {
            "category":"Travel",
            "subcategory":"Travel Agent",
            "type":"Entertainment"
        }
    ],
    "sg:phone":"+39 06 6656 4590",
    "sg:postcode":"00054",
    "sg:province":"Roma",
    "sg:tags":[
        "business"
    ],
    "wof:name":"Hotel Hotel Villa Fiorita",
    "wof:placetype":"venue"
},
  "geometry": {"coordinates":[12.200776,41.85191],"type":"Point"}
}