{
  "type": "Feature",
  "properties": {
    "iso:country":"IT",
    "sg:address":"40/42, Via Tasso Torquato 20089 Rozzano",
    "sg:city":"Rozzano",
    "sg:classifiers":[
        {
            "category":"Shopping",
            "subcategory":"Computers & Home Electronics",
            "type":"Retail Goods"
        }
    ],
    "sg:phone":"+39 39028257852",
    "sg:postcode":"20089",
    "sg:province":"Milano",
    "sg:tags":[
        "electronic",
        "electrical",
        "equipment"
    ],
    "wof:name":"Metal Spot Spa",
    "wof:placetype":"venue"
},
  "geometry": {"coordinates":[9.174992,45.378784],"type":"Point"}
}