{
  "type": "Feature",
  "properties": {
    "addr:full":"01020 Celleno Celleno Viterbo 01020",
    "addr:postcode":"01020;01020",
    "iso:country":"IT",
    "sg:address":"01020 Celleno",
    "sg:city":"Celleno",
    "sg:orig_category":"Imprese Di Costruzioni Civili Ed Industriali",
    "sg:phone":"+39 0761 912720",
    "sg:postcode":"01020",
    "sg:province":"Viterbo",
    "wof:name":"Chiavarino D. Srl",
    "wof:placetype":"venue"
},
  "geometry": {"coordinates":[12.120454,42.573551],"type":"Point"}
}