{
  "type": "Feature",
  "properties": {
    "addr:full":"Corso Garibaldi 35; Villafranca Di Verona; 37069 Villafranca di Verona Verona 37069",
    "addr:housenumber":"35",
    "addr:postcode":"37069;37069",
    "addr:street":"Corso Garibaldi",
    "iso:country":"IT",
    "sg:address":"Corso Garibaldi 35; Villafranca Di Verona; 37069",
    "sg:city":"Villafranca di Verona",
    "sg:classifiers":[
        {
            "category":"Banks & Credit Unions",
            "subcategory":"Bank",
            "type":"Services"
        }
    ],
    "sg:phone":"+39 045 790 0616",
    "sg:postcode":"37069",
    "sg:province":"Verona",
    "wof:name":"Banco Ambrosiano Veneto Spa",
    "wof:placetype":"venue"
},
  "geometry": {"coordinates":[10.84584,45.351185],"type":"Point"}
}