{
  "type": "Feature",
  "properties": {
    "iso:country":"IT",
    "sg:address":"21013 Gallarate",
    "sg:city":"Gallarate",
    "sg:orig_category":"Scuole E Servizi Scolastici",
    "sg:postcode":"21013",
    "sg:province":"Varese",
    "wof:name":"Istituto Magistrale Parificato Sacro Cuore",
    "wof:placetype":"venue"
},
  "geometry": {"coordinates":[8.791742,45.657661],"type":"Point"}
}