{
  "type": "Feature",
  "properties": {
    "addr:full":"1, Via Gadda Carlo Emilio 52027 San Giovanni Valdarno San Giovanni Valdarno Arezzo 52027",
    "addr:housenumber":"52027",
    "addr:postcode":"52027",
    "addr:street":"Via Gadda Carlo Emilio",
    "iso:country":"IT",
    "sg:address":"1, Via Gadda Carlo Emilio 52027 San Giovanni Valdarno",
    "sg:city":"San Giovanni Valdarno",
    "sg:classifiers":[
        {
            "category":"Wholesale",
            "subcategory":"Medical Equipment & Supplies",
            "type":"Manufacturing & Wholesale Goods"
        }
    ],
    "sg:phone":"+39 055 912 0404",
    "sg:postcode":"52027",
    "sg:province":"Arezzo",
    "sg:tags":[
        "-",
        "health",
        "instrument"
    ],
    "wof:name":"Moretti S.r.l.",
    "wof:placetype":"venue"
},
  "geometry": {"coordinates":[11.863062,43.471203],"type":"Point"}
}