{
  "type": "Feature",
  "properties": {
    "iso:country":"IT",
    "sg:address":"Via Toscana 148 50052 Certaldo",
    "sg:city":"Certaldo",
    "sg:classifiers":[
        {
            "category":"Manufacturing",
            "subcategory":"Motor Vehicles & Parts",
            "type":"Manufacturing & Wholesale Goods"
        }
    ],
    "sg:phone":"+39 0571 662474",
    "sg:postcode":"50052",
    "sg:province":"Firenze",
    "sg:tags":[
        "superstructure",
        "special"
    ],
    "wof:name":"Faboc Due Srl",
    "wof:placetype":"venue"
},
  "geometry": {"coordinates":[11.0267133713,43.5607223511],"type":"Point"}
}