{
  "type": "Feature",
  "properties": {
    "addr:full":"20089 Rozzano Rozzano Milano 20089",
    "addr:postcode":"20089;20089",
    "iso:country":"IT",
    "sg:address":"20089 Rozzano",
    "sg:city":"Rozzano",
    "sg:orig_category":"Articoli Da Regalo. Arte Ed Artigianato Artistico. Shopping",
    "sg:phone":"+39 02 825 5282",
    "sg:postcode":"20089",
    "sg:province":"Milano",
    "wof:name":"Garofalo Emidio",
    "wof:placetype":"venue"
},
  "geometry": {"coordinates":[9.144563,45.376411],"type":"Point"}
}