{
  "type": "Feature",
  "properties": {
    "addr:full":"52015 Pratovecchio Pratovecchio Arezzo 52015",
    "addr:postcode":"52015;52015",
    "iso:country":"IT",
    "sg:address":"52015 Pratovecchio",
    "sg:city":"Pratovecchio",
    "sg:orig_category":"Metalli E Leghe. Gioielleria, Oreficeria E Argenteria",
    "sg:phone":"+39 0575 582212",
    "sg:postcode":"52015",
    "sg:province":"Arezzo",
    "wof:name":"Vezzosi Argenterie Srl",
    "wof:placetype":"venue"
},
  "geometry": {"coordinates":[11.7409944534,43.7844161987],"type":"Point"}
}