{
  "type": "Feature",
  "properties": {
    "addr:full":"11, Via Petrarca 35020 Casalserugo Casalserugo Padova 35020",
    "addr:postcode":"35020;35020",
    "addr:street":"Via Petrarca",
    "iso:country":"IT",
    "sg:address":"11, Via Petrarca 35020 Casalserugo",
    "sg:city":"Casalserugo",
    "sg:classifiers":[
        {
            "category":"Shopping",
            "subcategory":"Crafts & Fabrics",
            "type":"Retail Goods"
        }
    ],
    "sg:phone":"+39 39049643064",
    "sg:postcode":"35020",
    "sg:province":"Padova",
    "wof:name":"Maglificio Vitt Di Agnoletti A. E C. S.a.s.",
    "wof:placetype":"venue"
},
  "geometry": {"coordinates":[11.9024181366,45.3118782043],"type":"Point"}
}