{
  "type": "Feature",
  "properties": {
    "addr:full":"323, Via Pasitea 84017 Positano Positano Salerno 84017",
    "addr:housenumber":"323",
    "addr:postcode":"84017;84017",
    "addr:street":"Via Pasitea",
    "iso:country":"IT",
    "sg:address":"323, Via Pasitea 84017 Positano",
    "sg:city":"Positano",
    "sg:classifiers":[
        {
            "category":"Shopping",
            "subcategory":"Clothing, Apparel, & Fashions",
            "type":"Retail Goods"
        }
    ],
    "sg:phone":"+39 39089811229",
    "sg:postcode":"84017",
    "sg:province":"Salerno",
    "sg:tags":[
        "clothes"
    ],
    "wof:name":"Ca.lu.' S.r.l.",
    "wof:placetype":"venue"
},
  "geometry": {"coordinates":[14.482939,40.629292],"type":"Point"}
}