{
  "type": "Feature",
  "properties": {
    "iso:country":"IT",
    "sg:address":"20121 Milano",
    "sg:city":"Milano",
    "sg:orig_category":"Gioielleria, Oreficeria E Argenteria. Shopping",
    "sg:phone":"+39 02 7600 1293",
    "sg:postcode":"20121",
    "sg:province":"Milano",
    "wof:name":"Calderoni Gioielli Spa",
    "wof:placetype":"venue"
},
  "geometry": {"coordinates":[9.194212,45.469097],"type":"Point"}
}