{
  "type": "Feature",
  "properties": {
    "iso:country":"IT",
    "sg:address":"Via Bologna 45/47, 89026 San Ferdinando, Rc",
    "sg:city":"San Ferdinando",
    "sg:classifiers":[
        {
            "category":"Banks & Credit Unions",
            "subcategory":"Bank",
            "type":"Services"
        }
    ],
    "sg:postcode":"89026",
    "sg:province":"Reggio Di Calabria",
    "wof:name":"Banca Di Credito Cooperativo Del Tirreno-san Ferdinando Scrl",
    "wof:placetype":"venue"
},
  "geometry": {"coordinates":[15.917535,38.484589],"type":"Point"}
}