{
  "type": "Feature",
  "properties": {
    "iso:country":"IT",
    "sg:address":"95121 Catania",
    "sg:city":"Catania",
    "sg:orig_category":"Prodotti E Manufatti In Materie Plastiche",
    "sg:phone":"+39 095 341101",
    "sg:postcode":"95121",
    "sg:province":"Catania",
    "wof:name":"Leocata Tiziana",
    "wof:placetype":"venue"
},
  "geometry": {"coordinates":[15.0833711624,37.4917640686],"type":"Point"}
}