{
  "type": "Feature",
  "properties": {
    "iso:country":"IT",
    "sg:address":"141, Via Gregorio Xi 00166 Roma",
    "sg:city":"Roma",
    "sg:classifiers":[
        {
            "category":"Travel",
            "subcategory":"Travel Agent",
            "type":"Entertainment"
        }
    ],
    "sg:phone":"+39 39066637630",
    "sg:postcode":"00166",
    "sg:province":"Roma",
    "sg:tags":[
        "business"
    ],
    "wof:name":"Hotel Marc'aurelio S.r.l.",
    "wof:placetype":"venue"
},
  "geometry": {"coordinates":[12.419189,41.899612],"type":"Point"}
}