{
  "type": "Feature",
  "properties": {
    "addr:full":"43100 Parma Parma Parma 43100",
    "addr:postcode":"43100;43100",
    "iso:country":"IT",
    "sg:address":"43100 Parma",
    "sg:city":"Parma",
    "sg:classifiers":[
        {
            "category":"Professional",
            "subcategory":"Advertising",
            "type":"Services"
        }
    ],
    "sg:phone":"+39 0521 290215",
    "sg:postcode":"43100",
    "sg:province":"Parma",
    "sg:tags":[
        "services",
        "shopping",
        "publishing"
    ],
    "wof:name":"Libreria Santa Croce",
    "wof:placetype":"venue"
},
  "geometry": {"coordinates":[10.3229598999,44.7756004333],"type":"Point"}
}