{
  "type": "Feature",
  "properties": {
    "iso:country":"IT",
    "sg:address":"50022 Greve In Chianti",
    "sg:city":"Greve in Chianti",
    "sg:orig_category":"Forniture Per Edilizia E Lavori Pubblici",
    "sg:phone":"+39 055 852730",
    "sg:postcode":"50022",
    "sg:province":"Firenze",
    "wof:name":"Apotema S.n.c. Di M. Cristofani",
    "wof:placetype":"venue"
},
  "geometry": {"coordinates":[11.2920093536,43.7162437439],"type":"Point"}
}