{
  "type": "Feature",
  "properties": {
    "addr:full":"25010 Tremosine Tremosine Brescia 25010",
    "addr:postcode":"25010;25010",
    "iso:country":"IT",
    "sg:address":"25010 Tremosine",
    "sg:city":"Tremosine",
    "sg:classifiers":[
        {
            "category":"Travel",
            "subcategory":"Hotels & Motels",
            "type":"Entertainment"
        }
    ],
    "sg:phone":"+39 036 595 1236",
    "sg:postcode":"25010",
    "sg:province":"Brescia",
    "sg:tags":[
        "hotels",
        "facility"
    ],
    "sg:website":"http://www.hotellafenice.it",
    "wof:name":"Hotel La Fenice Srl",
    "wof:placetype":"venue"
},
  "geometry": {"coordinates":[10.760198,45.771557],"type":"Point"}
}