{
  "type": "Feature",
  "properties": {
    "iso:country":"IT",
    "sg:address":"Via E. Fermi 7 20090 Assago",
    "sg:city":"Assago",
    "sg:classifiers":[
        {
            "category":"Home & Garden",
            "subcategory":"Building Materials",
            "type":"Retail Goods"
        }
    ],
    "sg:phone":"+39 02 488 0082",
    "sg:postcode":"20090",
    "sg:province":"Milano",
    "sg:tags":[
        "handle",
        "door"
    ],
    "sg:website":"www.poggimariani.com",
    "wof:name":"Poggi E Mariani S.r.l.",
    "wof:placetype":"venue"
},
  "geometry": {"coordinates":[9.127594,45.403202],"type":"Point"}
}