{
  "type": "Feature",
  "properties": {
    "addr:full":"1, Via Bentivoglio Cornelio 42100 Reggio Emilia Reggio Nell'Emilia 42100",
    "addr:postcode":"42100;42100",
    "addr:street":"Via Bentivoglio Cornelio",
    "iso:country":"IT",
    "sg:address":"1, Via Bentivoglio Cornelio 42100 Reggio Emilia",
    "sg:classifiers":[
        {
            "category":"Banks & Credit Unions",
            "subcategory":"Investment Brokerage",
            "type":"Services"
        }
    ],
    "sg:phone":"+39 0522 308641",
    "sg:postcode":"42100",
    "sg:province":"Reggio Nell'Emilia",
    "sg:tags":[
        "-",
        "transport",
        "related"
    ],
    "wof:name":"General Cargo (s.r.l.)",
    "wof:placetype":"venue"
},
  "geometry": {"coordinates":[10.610163,44.710274],"type":"Point"}
}