{
  "type": "Feature",
  "properties": {
    "addr:full":"26, Via Massaua 13100 Vercelli Vercelli Vercelli 13100",
    "addr:postcode":"13100;13100",
    "addr:street":"Via Massaua",
    "iso:country":"IT",
    "sg:address":"26, Via Massaua 13100 Vercelli",
    "sg:city":"Vercelli",
    "sg:classifiers":[
        {
            "category":"Manufacturing",
            "subcategory":"Printing",
            "type":"Manufacturing & Wholesale Goods"
        }
    ],
    "sg:phone":"+39 0161 259500",
    "sg:postcode":"13100",
    "sg:province":"Vercelli",
    "sg:tags":[
        "publishing"
    ],
    "wof:name":"Edoardo Roy & Figli S.r.l.",
    "wof:placetype":"venue"
},
  "geometry": {"coordinates":[8.4208498001,45.3193435669],"type":"Point"}
}