{
  "type": "Feature",
  "properties": {
    "addr:full":"18039 Ventimiglia Bevera Imperia 18039",
    "addr:postcode":"18039;18039",
    "iso:country":"IT",
    "sg:address":"18039 Ventimiglia",
    "sg:city":"Bevera",
    "sg:orig_category":"Pubblicita' - Agenzie Studi",
    "sg:phone":"+39 0184 211542",
    "sg:postcode":"18039",
    "sg:province":"Imperia",
    "wof:name":"Euroview Advertising Sas",
    "wof:placetype":"venue"
},
  "geometry": {"coordinates":[7.5778393745,43.8274536133],"type":"Point"}
}