{
  "type": "Feature",
  "properties": {
    "iso:country":"IT",
    "sg:address":"Strada Di Cortemaggiore 25 29100 Piacenza",
    "sg:city":"Piacenza",
    "sg:classifiers":[
        {
            "category":"Military Area",
            "subcategory":"Air Force Base",
            "type":"Public Place"
        }
    ],
    "sg:phone":"+39 0523 599611",
    "sg:postcode":"29100",
    "sg:province":"Piacenza",
    "sg:tags":[
        "precast",
        "component",
        "concrete"
    ],
    "sg:website":"www.paver.it",
    "wof:name":"Paver Costruzioni Spa",
    "wof:placetype":"venue"
},
  "geometry": {"coordinates":[9.8469686508,45.0466079712],"type":"Point"}
}