{
  "type": "Feature",
  "properties": {
    "iso:country":"IT",
    "sg:address":"20123 Milano",
    "sg:city":"Milano",
    "sg:orig_category":"Prodotti Alimentari. Shopping",
    "sg:phone":"+39 02 839 4080",
    "sg:postcode":"20123",
    "sg:province":"Milano",
    "wof:name":"Cimatra (s.r.l.)",
    "wof:placetype":"venue"
},
  "geometry": {"coordinates":[9.1741113663,45.4616279602],"type":"Point"}
}