{
  "type": "Feature",
  "properties": {
    "iso:country":"IT",
    "sg:address":"121, Via Mantova 37053 Cerea",
    "sg:city":"Cerea",
    "sg:classifiers":[
        {
            "category":"Professional",
            "subcategory":"Engineering",
            "type":"Services"
        }
    ],
    "sg:phone":"+39 0442 330422",
    "sg:postcode":"37053",
    "sg:province":"Verona",
    "sg:tags":[
        "machine",
        "-",
        "mechanical"
    ],
    "wof:name":"Meccanica Fadini Di Luigi Gaetano E Carlo (s.n.c.)",
    "wof:placetype":"venue"
},
  "geometry": {"coordinates":[11.200756,45.188324],"type":"Point"}
}