{
  "type": "Feature",
  "properties": {
    "iso:country":"IT",
    "sg:address":"1, Corso Unione Sovietica 37038 Soave",
    "sg:city":"Soave",
    "sg:classifiers":[
        {
            "category":"Shopping",
            "subcategory":"Computers & Home Electronics",
            "type":"Retail Goods"
        }
    ],
    "sg:phone":"+39 045 617 3411",
    "sg:postcode":"37038",
    "sg:province":"Verona",
    "sg:tags":[
        "electronic",
        "electrical",
        "equipment"
    ],
    "wof:name":"Eurogen S.r.l.",
    "wof:placetype":"venue"
},
  "geometry": {"coordinates":[11.242423,45.408482],"type":"Point"}
}