{
  "type": "Feature",
  "properties": {
    "addr:full":"90010 Ficarazzi Ficarazzi Palermo 90010",
    "addr:postcode":"90010;90010",
    "iso:country":"IT",
    "sg:address":"90010 Ficarazzi",
    "sg:city":"Ficarazzi",
    "sg:orig_category":"Serramenti Ed Infissi. Prodotti Vari In Metallo",
    "sg:phone":"+39 091 636 0740",
    "sg:postcode":"90010",
    "sg:province":"Palermo",
    "wof:name":"F. Lli Miosi Snc",
    "wof:placetype":"venue"
},
  "geometry": {"coordinates":[13.466847,38.087467],"type":"Point"}
}