{
  "type": "Feature",
  "properties": {
    "iso:country":"IT",
    "sg:address":"35, Strada Macerata 62015 Monte San Giusto",
    "sg:city":"Monte San Giusto",
    "sg:classifiers":[
        {
            "category":"Manufacturing",
            "subcategory":"Textiles",
            "type":"Manufacturing & Wholesale Goods"
        }
    ],
    "sg:phone":"+39 0733 539798",
    "sg:postcode":"62015",
    "sg:province":"Macerata",
    "sg:tags":[
        "leather",
        "raw",
        "material",
        "-"
    ],
    "wof:name":"Italven Pelli (s.r.l.)",
    "wof:placetype":"venue"
},
  "geometry": {"coordinates":[13.592091,43.237431],"type":"Point"}
}