{
  "type": "Feature",
  "properties": {
    "iso:country":"IT",
    "sg:address":"6, Via Buonarroti Michelangelo 67051 Avezzano",
    "sg:classifiers":[
        {
            "category":"Professional",
            "subcategory":"Advertising",
            "type":"Services"
        }
    ],
    "sg:phone":"+39 39086326985",
    "sg:postcode":"67051",
    "sg:province":"L'Aquila",
    "sg:tags":[
        "communication",
        "medium"
    ],
    "wof:name":"Del Pretaro",
    "wof:placetype":"venue"
},
  "geometry": {"coordinates":[13.431372,42.039116],"type":"Point"}
}