{
  "type": "Feature",
  "properties": {
    "addr:full":"16047 Ferrada Ferrada Genova 16047",
    "addr:postcode":"16047;16047",
    "iso:country":"IT",
    "sg:address":"16047 Ferrada",
    "sg:city":"Ferrada",
    "sg:orig_category":"Marmo, Pietre Ed Affini",
    "sg:phone":"+39 0185 939739",
    "sg:postcode":"16047",
    "sg:province":"Genova",
    "wof:name":"Dondero Gian Luigi",
    "wof:placetype":"venue"
},
  "geometry": {"coordinates":[8.941254,44.402462],"type":"Point"}
}