{
  "type": "Feature",
  "properties": {
    "iso:country":"IT",
    "sg:address":"11, Via S. Spirito 50125 Firenze",
    "sg:city":"Firenze",
    "sg:classifiers":[
        {
            "category":"Real Estate",
            "subcategory":"Architect",
            "type":"Services"
        }
    ],
    "sg:phone":"+39 39055211423",
    "sg:postcode":"50125",
    "sg:province":"Firenze",
    "sg:tags":[
        "textile",
        "clothing"
    ],
    "wof:name":"Boralevi",
    "wof:placetype":"venue"
},
  "geometry": {"coordinates":[11.256902,43.768734],"type":"Point"}
}