{
  "type": "Feature",
  "properties": {
    "addr:full":"1, V. Grandi 43045 Fornovo Di Taro Fornovo di Taro Parma 43045",
    "addr:housenumber":"1;di taro",
    "addr:postcode":"43045;43045",
    "addr:street":"V. Grandi",
    "iso:country":"IT",
    "sg:address":"1, V. Grandi 43045 Fornovo Di Taro",
    "sg:city":"Fornovo di Taro",
    "sg:classifiers":[
        {
            "category":"Manufacturing",
            "subcategory":"Food",
            "type":"Manufacturing & Wholesale Goods"
        }
    ],
    "sg:phone":"+39 0525 400303",
    "sg:postcode":"43045",
    "sg:province":"Parma",
    "sg:tags":[
        "equipment",
        "processing",
        "-",
        "machinery"
    ],
    "sg:website":"http://www.paginegialle.it/valforsrl",
    "wof:name":"Valfor Srl",
    "wof:placetype":"venue"
},
  "geometry": {"coordinates":[10.0970869064,44.6950912476],"type":"Point"}
}