{
  "type": "Feature",
  "properties": {
    "iso:country":"IT",
    "sg:address":"20148 Milano",
    "sg:city":"Milano",
    "sg:orig_category":"Cinematografia E Radiotelevisione",
    "sg:phone":"+39 02 3921 6377",
    "sg:postcode":"20148",
    "sg:province":"Milano",
    "wof:name":"Some Of Vs Di Anzalone Michele & C. Sas",
    "wof:placetype":"venue"
},
  "geometry": {"coordinates":[9.145488,45.481579],"type":"Point"}
}