{
  "type": "Feature",
  "properties": {
    "iso:country":"IT",
    "sg:address":"7, Via Castel Rozzone 24050 Lurano",
    "sg:city":"Lurano",
    "sg:classifiers":[
        {
            "category":"Manufacturing",
            "subcategory":"Metals",
            "type":"Manufacturing & Wholesale Goods"
        }
    ],
    "sg:phone":"+39 035 487 9011",
    "sg:postcode":"24050",
    "sg:province":"Bergamo",
    "sg:tags":[
        "processing"
    ],
    "wof:name":"Olvan S.p.a.",
    "wof:placetype":"venue"
},
  "geometry": {"coordinates":[9.6401185989,45.5475845337],"type":"Point"}
}