{
  "type": "Feature",
  "properties": {
    "iso:country":"IT",
    "sg:address":"00197 Roma",
    "sg:city":"Roma",
    "sg:orig_category":"Ambasciate Ed Enti Internazionali",
    "sg:phone":"+39 06 321 8017",
    "sg:postcode":"00197",
    "sg:province":"Roma",
    "wof:name":"Ambasciata Presso La S. Sede Uruguay",
    "wof:placetype":"venue"
},
  "geometry": {"coordinates":[12.652259,41.748497],"type":"Point"}
}