{
  "type": "Feature",
  "properties": {
    "iso:country":"IT",
    "sg:address":"Frazione Failungo Inf. 13020 Pila",
    "sg:city":"Pila",
    "sg:classifiers":[
        {
            "category":"Shopping",
            "type":"Retail Goods"
        }
    ],
    "sg:phone":"+39 39016371530",
    "sg:postcode":"13020",
    "sg:province":"Vercelli",
    "sg:tags":[
        "finished",
        "-",
        "metallic"
    ],
    "wof:name":"Copra (s.n.c.)",
    "wof:placetype":"venue"
},
  "geometry": {"coordinates":[8.4263935089,45.3210601807],"type":"Point"}
}