{
  "type": "Feature",
  "properties": {
    "iso:country":"IT",
    "sg:address":"Piazza Duomo 13; Tortona; 15057",
    "sg:city":"Tortona",
    "sg:classifiers":[
        {
            "category":"Banks & Credit Unions",
            "subcategory":"Bank",
            "type":"Services"
        }
    ],
    "sg:phone":"+39 0131 8191",
    "sg:postcode":"15057",
    "sg:province":"Alessandria",
    "wof:name":"Cassa Di Risparmio Di Tortona Spa",
    "wof:placetype":"venue"
},
  "geometry": {"coordinates":[8.865677,44.897278],"type":"Point"}
}