{
  "type": "Feature",
  "properties": {
    "iso:country":"IT",
    "sg:address":"37063 Isola Della Scala",
    "sg:city":"Isola della Scala",
    "sg:orig_category":"Prodotti Alimentari. Agricoltura, Orticoltura E Floricoltura",
    "sg:phone":"+39 045 730 2592",
    "sg:postcode":"37063",
    "sg:province":"Verona",
    "wof:name":"Azienda Agricola Paolo Olivieri",
    "wof:placetype":"venue"
},
  "geometry": {"coordinates":[10.9503288269,45.3565406799],"type":"Point"}
}