{
  "type": "Feature",
  "properties": {
    "iso:country":"IT",
    "sg:address":"59100 Prato",
    "sg:city":"Prato",
    "sg:orig_category":"Lana Tessuti",
    "sg:phone":"+39 0574 59821",
    "sg:postcode":"59100",
    "sg:province":"Prato",
    "wof:name":"Picchi Spa",
    "wof:placetype":"venue"
},
  "geometry": {"coordinates":[11.085596,43.865623],"type":"Point"}
}