{
  "type": "Feature",
  "properties": {
    "addr:full":"20060 Pozzuolo Martesana Pozzuolo Martesana Milano 20060",
    "addr:postcode":"20060;20060",
    "iso:country":"IT",
    "sg:address":"20060 Pozzuolo Martesana",
    "sg:city":"Pozzuolo Martesana",
    "sg:orig_category":"Valvole E Apparecchiature Di Misura. Forniture Per Attivita' Industriali",
    "sg:phone":"+39 02 9535 6075",
    "sg:postcode":"20060",
    "sg:province":"Milano",
    "wof:name":"S.m.e.g. Sas Di Spinetta & C.",
    "wof:placetype":"venue"
},
  "geometry": {"coordinates":[9.480043,45.520153],"type":"Point"}
}