{
  "type": "Feature",
  "properties": {
    "iso:country":"IT",
    "sg:address":"Via Pascatti 19; S. Vito Al Tagliamento; 33078",
    "sg:classifiers":[
        {
            "category":"Banks & Credit Unions",
            "subcategory":"Bank",
            "type":"Services"
        }
    ],
    "sg:phone":"+39 0434 875833",
    "sg:postcode":"33078",
    "sg:province":"Pordenone",
    "wof:name":"Cassa Di Risparmio Di Gorizia Spa",
    "wof:placetype":"venue"
},
  "geometry": {"coordinates":[12.854345,45.915756],"type":"Point"}
}