{
  "type": "Feature",
  "properties": {
    "addr:full":"Via De Gasperi 22; S. Vendemiano; 31020 Treviso 31020",
    "addr:housenumber":"22 s.",
    "addr:postcode":"31020;31020",
    "addr:street":"Via De Gasperi;Vendemiano",
    "iso:country":"IT",
    "sg:address":"Via De Gasperi 22; S. Vendemiano; 31020",
    "sg:classifiers":[
        {
            "category":"Banks & Credit Unions",
            "subcategory":"Bank",
            "type":"Services"
        }
    ],
    "sg:phone":"+39 0438 400741",
    "sg:postcode":"31020",
    "sg:province":"Treviso",
    "wof:name":"Cassa Marca",
    "wof:placetype":"venue"
},
  "geometry": {"coordinates":[12.336214,45.893032],"type":"Point"}
}