{
  "type": "Feature",
  "properties": {
    "addr:full":"90036 Misilmeri Misilmeri Palermo 90036",
    "addr:postcode":"90036;90036",
    "iso:country":"IT",
    "sg:address":"90036 Misilmeri",
    "sg:city":"Misilmeri",
    "sg:orig_category":"Macchine, Impianti Ed Attrezzature Industria Chimica. Prodotti Vari In Metallo. Articoli Per Imballaggio E Confezionamento",
    "sg:phone":"+39 091 872 3901",
    "sg:postcode":"90036",
    "sg:province":"Palermo",
    "wof:name":"Sciarabba Mario",
    "wof:placetype":"venue"
},
  "geometry": {"coordinates":[13.447765,38.031754],"type":"Point"}
}