{
  "type": "Feature",
  "properties": {
    "iso:country":"IT",
    "sg:address":"20148 Milano",
    "sg:city":"Milano",
    "sg:orig_category":"Rettificatrici",
    "sg:phone":"+39 02 4870 1858",
    "sg:postcode":"20148",
    "sg:province":"Milano",
    "wof:name":"Officine Meccaniche Giuseppe Rastelli Spa",
    "wof:placetype":"venue"
},
  "geometry": {"coordinates":[9.140984,45.468388],"type":"Point"}
}