{
  "type": "Feature",
  "properties": {
    "iso:country":"IT",
    "sg:address":"7, Via S. Francesco Di Sales 31100 Treviso",
    "sg:city":"Treviso",
    "sg:classifiers":[
        {
            "category":"Sports & Exercise",
            "subcategory":"Playing Field",
            "type":"Entertainment"
        }
    ],
    "sg:phone":"+39 0422 432484",
    "sg:postcode":"31100",
    "sg:province":"Treviso",
    "sg:tags":[
        "game"
    ],
    "wof:name":"Calleri & C. (s.a.s.)",
    "wof:placetype":"venue"
},
  "geometry": {"coordinates":[12.20272,45.651211],"type":"Point"}
}