{
  "type": "Feature",
  "properties": {
    "iso:country":"IT",
    "sg:address":"95014 Giarre",
    "sg:city":"Giarre",
    "sg:classifiers":[
        {
            "category":"Banks & Credit Unions",
            "subcategory":"Investment Brokerage",
            "type":"Services"
        }
    ],
    "sg:phone":"+39 095 933644",
    "sg:postcode":"95014",
    "sg:province":"Catania",
    "sg:tags":[
        "parrucchieri",
        "per",
        "donna"
    ],
    "wof:name":"Inzerilli Piero",
    "wof:placetype":"venue"
},
  "geometry": {"coordinates":[15.184261322,37.7281227112],"type":"Point"}
}