{
  "type": "Feature",
  "properties": {
    "iso:country":"IT",
    "sg:address":"Via Martini 36055 Nove",
    "sg:city":"Nove",
    "sg:classifiers":[
        {
            "category":"Sports & Exercise",
            "subcategory":"Playing Field",
            "type":"Entertainment"
        }
    ],
    "sg:phone":"+39 0424 827286",
    "sg:postcode":"36055",
    "sg:province":"Vicenza",
    "sg:tags":[
        "game"
    ],
    "wof:name":"Vittorio Carraro Di Ferruccio Mario Carraro",
    "wof:placetype":"venue"
},
  "geometry": {"coordinates":[11.677138,45.711964],"type":"Point"}
}