{
  "type": "Feature",
  "properties": {
    "iso:country":"IT",
    "sg:address":"60022 Castelfidardo",
    "sg:city":"Castelfidardo",
    "sg:classifiers":[
        {
            "category":"Farming",
            "subcategory":"Fish & Marine Products",
            "type":"Manufacturing & Wholesale Goods"
        }
    ],
    "sg:phone":"+39 071 782491",
    "sg:postcode":"60022",
    "sg:province":"Ancona",
    "sg:tags":[
        "industrial",
        "material",
        "equipment",
        "engineering",
        "electrical",
        "components"
    ],
    "sg:website":"http://www.comelit.it",
    "wof:name":"Comelit Srl",
    "wof:placetype":"venue"
},
  "geometry": {"coordinates":[13.519364,43.575863],"type":"Point"}
}