{
  "type": "Feature",
  "properties": {
    "addr:full":"21, V. Dell'industria Vittorio Veneto Treviso 31029",
    "addr:housenumber":"21",
    "addr:postcode":"31029",
    "addr:street":"V. Dell'Industria",
    "iso:country":"IT",
    "sg:address":"21, V. Dell'industria",
    "sg:city":"Vittorio Veneto",
    "sg:classifiers":[
        {
            "category":"Manufacturing",
            "subcategory":"Rubber & Plastics",
            "type":"Manufacturing & Wholesale Goods"
        }
    ],
    "sg:phone":"+39 390 438 5031",
    "sg:postcode":"31029",
    "sg:province":"Treviso",
    "sg:website":"http://www.paginegialle.it/temasrl-tv",
    "wof:name":"Tema Srl",
    "wof:placetype":"venue"
},
  "geometry": {"coordinates":[12.2420721054,45.6662864685],"type":"Point"}
}