{
  "type": "Feature",
  "properties": {
    "addr:full":"53026 Pienza Pienza Siena 53026",
    "addr:postcode":"53026;53026",
    "iso:country":"IT",
    "sg:address":"53026 Pienza",
    "sg:city":"Pienza",
    "sg:orig_category":"Prodotti Alimentari",
    "sg:phone":"+39 0578 748350",
    "sg:postcode":"53026",
    "sg:province":"Siena",
    "sg:website":"http://www.fattoriabucanuova.com",
    "wof:name":"Fattoria Buca Nuova Srl",
    "wof:placetype":"venue"
},
  "geometry": {"coordinates":[11.6868772507,43.0942420959],"type":"Point"}
}