{
  "type": "Feature",
  "properties": {
    "addr:full":"95127 Catania Catania Catania 95127",
    "addr:postcode":"95127;95127",
    "iso:country":"IT",
    "sg:address":"95127 Catania",
    "sg:city":"Catania",
    "sg:orig_category":"Automazione E Macchine Per Ufficio. Servizi Ausiliari Di Certificati, Riproduzioni, Disegni E Foto",
    "sg:phone":"+39 095 437186",
    "sg:postcode":"95127",
    "sg:province":"Catania",
    "sg:website":"http://www.paginegialle.it/tecnocadservice2000",
    "wof:name":"Tecno Cad Service 2000 Di Calcagno Lucia",
    "wof:placetype":"venue"
},
  "geometry": {"coordinates":[15.094099,37.519459],"type":"Point"}
}