{
  "type": "Feature",
  "properties": {
    "iso:country":"IT",
    "sg:address":"75022 Irsina",
    "sg:city":"Irsina",
    "sg:orig_category":"Manufacturers: Prefabbricati. Forniture Per Edilizia E Lavori Pubblici",
    "sg:phone":"+39 0835 518977",
    "sg:postcode":"75022",
    "sg:province":"Matera",
    "wof:name":"Lo Russo Antonio",
    "wof:placetype":"venue"
},
  "geometry": {"coordinates":[16.22868,40.744595],"type":"Point"}
}