{
  "type": "Feature",
  "properties": {
    "iso:country":"IT",
    "sg:address":"21021 Angera",
    "sg:city":"Angera",
    "sg:orig_category":"Studi E Consulenze Tecniche E Industriali. Consulenze Tecniche, Amministrative E Perizie",
    "sg:phone":"+39 0331 931163",
    "sg:postcode":"21021",
    "sg:province":"Varese",
    "wof:name":"Digierre Consulting Sas",
    "wof:placetype":"venue"
},
  "geometry": {"coordinates":[8.585088,45.774414],"type":"Point"}
}