{
  "type": "Feature",
  "properties": {
    "addr:full":"Ctr. S. Stefano87030 Rende Cosenza 87030",
    "addr:postcode":"stefano87030;87030",
    "addr:street":"Ctr. S.",
    "iso:country":"IT",
    "sg:address":"Ctr. S. Stefano87030 Rende",
    "sg:classifiers":[
        {
            "category":"Real Estate",
            "subcategory":"Architect",
            "type":"Services"
        }
    ],
    "sg:phone":"+39 0984 446561",
    "sg:postcode":"87030",
    "sg:province":"Cosenza",
    "sg:tags":[
        "textile",
        "clothing"
    ],
    "sg:website":"http://www.paginegialle.it/prontomodardv",
    "wof:name":"Pronto Moda Rdv",
    "wof:placetype":"venue"
},
  "geometry": {"coordinates":[16.253809,39.298264],"type":"Point"}
}