{
  "type": "Feature",
  "properties": {
    "addr:full":"09032 Macchiareddu Macchiareddu Cagliari 09032",
    "addr:postcode":"09032;09032",
    "addr:street":"Macchiareddu Cagliari",
    "iso:country":"IT",
    "sg:address":"09032 Macchiareddu",
    "sg:city":"Macchiareddu",
    "sg:orig_category":"Bevande, Vini E Liquori. Servizi E Lavori Per Industria Alimentare E Bevande",
    "sg:phone":"+39 070 247090",
    "sg:postcode":"09032",
    "sg:province":"Cagliari",
    "wof:name":"Distilleria Cooperativa Viticoltori Sardi (s.r.l.)",
    "wof:placetype":"venue"
},
  "geometry": {"coordinates":[9.024555,39.226257],"type":"Point"}
}