{
  "type": "Feature",
  "properties": {
    "iso:country":"IT",
    "sg:address":"43100 Parma",
    "sg:city":"Parma",
    "sg:orig_category":"Utensili Meccanici E Materiali. Elettrotecnica Industriale, Prodotti E Apparecchiature",
    "sg:phone":"+39 0521 786778",
    "sg:postcode":"43100",
    "sg:province":"Parma",
    "wof:name":"A. Minozzi E C. Snc",
    "wof:placetype":"venue"
},
  "geometry": {"coordinates":[10.332787,44.810909],"type":"Point"}
}