{
  "type": "Feature",
  "properties": {
    "addr:full":"24010 Sorisole Sorisole Bergamo 24010",
    "addr:postcode":"24010;24010",
    "iso:country":"IT",
    "sg:address":"24010 Sorisole",
    "sg:city":"Sorisole",
    "sg:orig_category":"Utensili Meccanici E Materiali",
    "sg:phone":"+39 035 571321",
    "sg:postcode":"24010",
    "sg:province":"Bergamo",
    "wof:name":"Brugnetti Serafino",
    "wof:placetype":"venue"
},
  "geometry": {"coordinates":[9.646112,45.73798],"type":"Point"}
}