{
  "type": "Feature",
  "properties": {
    "iso:country":"IT",
    "sg:address":"31, Via Averolda 25039 Travagliato",
    "sg:city":"Travagliato",
    "sg:classifiers":[
        {
            "category":"Sports & Exercise",
            "subcategory":"Playing Field",
            "type":"Entertainment"
        }
    ],
    "sg:phone":"+39 030 686 3629",
    "sg:postcode":"25039",
    "sg:province":"Brescia",
    "sg:tags":[
        "game"
    ],
    "wof:name":"Fabarm-fabbrica Bresciana Armi (s.p.a.)",
    "wof:placetype":"venue"
},
  "geometry": {"coordinates":[10.101091,45.536377],"type":"Point"}
}