{
  "type": "Feature",
  "properties": {
    "addr:full":"42028 Poviglio Reggio Nell'Emilia 42028",
    "addr:postcode":"42028;42028",
    "iso:country":"IT",
    "sg:address":"42028 Poviglio",
    "sg:orig_category":"Apparecchiature E Sistemi Per Magazzinaggio E Movimentazione",
    "sg:phone":"+39 0522 960563",
    "sg:postcode":"42028",
    "sg:province":"Reggio Nell'Emilia",
    "wof:name":"Heila Gru Srl",
    "wof:placetype":"venue"
},
  "geometry": {"coordinates":[10.621229,44.705502],"type":"Point"}
}