{
  "type": "Feature",
  "properties": {
    "iso:country":"IT",
    "sg:address":"Via Degli Schiavetti 11 34074 Monfalcone",
    "sg:city":"Monfalcone",
    "sg:classifiers":[
        {
            "category":"Retail",
            "subcategory":"Auto Rental",
            "type":"Services"
        }
    ],
    "sg:phone":"+39 0481 496949",
    "sg:postcode":"34074",
    "sg:province":"Gorizia",
    "sg:tags":[
        "cranes",
        "automobile",
        "crane",
        "salvage",
        "wrecking"
    ],
    "sg:website":"www.liebherr-italia.com",
    "wof:name":"Liebherr Italia Spa",
    "wof:placetype":"venue"
},
  "geometry": {"coordinates":[13.522777,45.79464],"type":"Point"}
}