{
  "type": "Feature",
  "properties": {
    "iso:country":"IT",
    "sg:address":"95030 Tremestieri Etneo",
    "sg:city":"Tremestieri Etneo",
    "sg:orig_category":"Carni, Salumi E Pesci. Zootecnia E Pesca, Allevamento Piccoli Animali",
    "sg:phone":"+39 095 754 5013",
    "sg:postcode":"95030",
    "sg:province":"Catania",
    "wof:name":"Del Campo Ag. Di Ct Ce.d.al. Srl",
    "wof:placetype":"venue"
},
  "geometry": {"coordinates":[15.065545,37.575241],"type":"Point"}
}