{
  "type": "Feature",
  "properties": {
    "iso:country":"IT",
    "sg:address":"73028 Otranto",
    "sg:city":"Otranto",
    "sg:orig_category":"Servizi Al Turismo. Servizi Ausiliari Per Il Trasporto",
    "sg:phone":"+39 0836 802375",
    "sg:postcode":"73028",
    "sg:province":"Lecce",
    "wof:name":"Agenzia Marittima Sari & Co Sas",
    "wof:placetype":"venue"
},
  "geometry": {"coordinates":[18.485754,40.148029],"type":"Point"}
}