{
  "type": "Feature",
  "properties": {
    "iso:country":"IT",
    "sg:address":"25038 Rovato",
    "sg:city":"Rovato",
    "sg:orig_category":"Servizi Culturali E Per Lo Spettacolo. Servizi Al Turismo. Acqua, Luce, Gas E Societa' Di Esercizio Pubblico",
    "sg:phone":"+39 030 772 2525",
    "sg:postcode":"25038",
    "sg:province":"Brescia",
    "wof:name":"Biblioteca Comunale",
    "wof:placetype":"venue"
},
  "geometry": {"coordinates":[10.20752,45.523041],"type":"Point"}
}