{
  "type": "Feature",
  "properties": {
    "addr:full":"50136 Firenze Firenze Firenze 50136",
    "addr:postcode":"50136;50136",
    "iso:country":"IT",
    "sg:address":"50136 Firenze",
    "sg:city":"Firenze",
    "sg:orig_category":"Forniture Ospedaliere",
    "sg:phone":"+39 055 650 5145",
    "sg:postcode":"50136",
    "sg:province":"Firenze",
    "wof:name":"Medilab Sas",
    "wof:placetype":"venue"
},
  "geometry": {"coordinates":[11.3268995285,43.7289009094],"type":"Point"}
}