{
  "type": "Feature",
  "properties": {
    "iso:country":"IT",
    "sg:address":"20123 Milano",
    "sg:city":"Milano",
    "sg:orig_category":"Centri Di Estetica E Cosmesi E Servizi",
    "sg:phone":"+39 02 877155",
    "sg:postcode":"20123",
    "sg:province":"Milano",
    "wof:name":"Di Bella Giuseppe",
    "wof:placetype":"venue"
},
  "geometry": {"coordinates":[9.1770467758,45.4675064087],"type":"Point"}
}