{
  "type": "Feature",
  "properties": {
    "iso:country":"IT",
    "sg:address":"86012 Cercemaggiore",
    "sg:city":"Cercemaggiore",
    "sg:orig_category":"Marmo, Pietre Ed Affini",
    "sg:phone":"+39 0874 799442",
    "sg:postcode":"86012",
    "sg:province":"Campobasso",
    "wof:name":"Petraroia Gianvincenzo",
    "wof:placetype":"venue"
},
  "geometry": {"coordinates":[14.740427,41.450516],"type":"Point"}
}