{
  "type": "Feature",
  "properties": {
    "iso:country":"IT",
    "sg:address":"00187 Roma",
    "sg:city":"Roma",
    "sg:orig_category":"Servizi Culturali E Per Lo Spettacolo. Servizi Al Turismo. Acqua, Luce, Gas E Societa' Di Esercizio Pubblico",
    "sg:phone":"+39 06 4201 3123",
    "sg:postcode":"00187",
    "sg:province":"Roma",
    "wof:name":"Museo Boncompagni Ludovisi Per Le Arti Decorative",
    "wof:placetype":"venue"
},
  "geometry": {"coordinates":[12.495148,41.908802],"type":"Point"}
}