{
  "type": "Feature",
  "properties": {
    "addr:full":"20080 Basiglio Basiglio Milano 20080",
    "addr:postcode":"20080;20080",
    "iso:country":"IT",
    "sg:address":"20080 Basiglio",
    "sg:city":"Basiglio",
    "sg:orig_category":"Ospedali E Servizi Sanitari. Pubblica Amministrazione. Servizi Sociali",
    "sg:phone":"+39 02 9075 4658",
    "sg:postcode":"20080",
    "sg:province":"Milano",
    "wof:name":"Asl Provincia Di Milano 2",
    "wof:placetype":"venue"
},
  "geometry": {"coordinates":[9.147522,45.399651],"type":"Point"}
}