{
  "type": "Feature",
  "properties": {
    "addr:full":"34135 Trieste Trieste Trieste 34135",
    "addr:postcode":"34135;34135",
    "iso:country":"IT",
    "sg:address":"34135 Trieste",
    "sg:city":"Trieste",
    "sg:orig_category":"Dolciumi E Gelati. Shopping",
    "sg:phone":"+39 040 421128",
    "sg:postcode":"34135",
    "sg:province":"Trieste",
    "sg:website":"http://www.alberodelpane.net",
    "wof:name":"L'albero Del Pane Di Giorgi Giorgio",
    "wof:placetype":"venue"
},
  "geometry": {"coordinates":[13.770081,45.662243],"type":"Point"}
}