{
  "type": "Feature",
  "properties": {
    "addr:full":"00049 Velletri Velletri Roma 00049",
    "addr:postcode":"00049;roma 00049",
    "iso:country":"IT",
    "sg:address":"00049 Velletri",
    "sg:city":"Velletri",
    "sg:classifiers":[
        {
            "category":"Banks & Credit Unions",
            "subcategory":"Investment Brokerage",
            "type":"Services"
        }
    ],
    "sg:phone":"+39 06 964 0736",
    "sg:postcode":"00049",
    "sg:province":"Roma",
    "sg:tags":[
        "parrucchieri",
        "per",
        "donna"
    ],
    "wof:name":"Ass. G.a.v. Scuola Acconciatori",
    "wof:placetype":"venue"
},
  "geometry": {"coordinates":[12.7725343704,41.6926307678],"type":"Point"}
}