{
  "type": "Feature",
  "properties": {
    "iso:country":"IT",
    "sg:address":"53044 Chiusi Scalo",
    "sg:orig_category":"Accessori Dei Mezzi Di Trasporto",
    "sg:phone":"+39 0578 21437",
    "sg:province":"SI",
    "wof:name":"Bacci Motors Snc Di Bacci S. & C.",
    "wof:placetype":"venue"
},
  "geometry": {"coordinates":[-87.78125,43.745457],"type":"Point"}
}