{
  "type": "Feature",
  "properties": {
    "addr:full":"60, Via S. Pietro 25077 Roe' Volciano Brescia 25077",
    "addr:postcode":"25077;25077",
    "addr:street":"Via S. Pietro;Roe ' Volciano",
    "iso:country":"IT",
    "sg:address":"60, Via S. Pietro 25077 Roe' Volciano",
    "sg:classifiers":[
        {
            "category":"Manufacturing",
            "subcategory":"Motor Vehicles & Parts",
            "type":"Manufacturing & Wholesale Goods"
        }
    ],
    "sg:phone":"+39 036 555 6182",
    "sg:postcode":"25077",
    "sg:province":"Brescia",
    "sg:tags":[
        "engine"
    ],
    "wof:name":"O.m.s.i. Trasmissioni (s.p.a.)",
    "wof:placetype":"venue"
},
  "geometry": {"coordinates":[10.222958,45.539829],"type":"Point"}
}