{
  "type": "Feature",
  "properties": {
    "iso:country":"IT",
    "sg:address":"25020 Seniga",
    "sg:city":"Seniga",
    "sg:orig_category":"Materiali Edili",
    "sg:phone":"+39 030 995 5038",
    "sg:postcode":"25020",
    "sg:province":"Brescia",
    "wof:name":"Grandi F.lli Di Grandi Francesco & C. (s.n.c.)",
    "wof:placetype":"venue"
},
  "geometry": {"coordinates":[10.121168,45.247398],"type":"Point"}
}