{
  "type": "Feature",
  "properties": {
    "iso:country":"IT",
    "sg:address":"30, Via Ligonto 31051 Follina",
    "sg:city":"Follina",
    "sg:classifiers":[
        {
            "category":"Shopping",
            "subcategory":"Crafts & Fabrics",
            "type":"Retail Goods"
        }
    ],
    "sg:phone":"+39 0438 970249",
    "sg:postcode":"31051",
    "sg:province":"Treviso",
    "wof:name":"Cesca",
    "wof:placetype":"venue"
},
  "geometry": {"coordinates":[12.1395053864,45.9366378784],"type":"Point"}
}