{
  "type": "Feature",
  "properties": {
    "addr:full":"20032 Cormano Cormano Milano 20032",
    "addr:postcode":"20032;20032",
    "iso:country":"IT",
    "sg:address":"20032 Cormano",
    "sg:city":"Cormano",
    "sg:orig_category":"Forniture Per Attivita' Industriali",
    "sg:phone":"+39 02 615 1511",
    "sg:postcode":"20032",
    "sg:province":"Milano",
    "wof:name":"Lionetti Antonio",
    "wof:placetype":"venue"
},
  "geometry": {"coordinates":[9.1586122513,45.5413856506],"type":"Point"}
}