{
  "type": "Feature",
  "properties": {
    "iso:country":"IT",
    "sg:address":"20145 Milano",
    "sg:city":"Milano",
    "sg:orig_category":"Motori Ed Organi Di Trasmissione. Ricambi E Componenti Dei Mezzi Di Trasporto",
    "sg:phone":"+39 02 4391 1572",
    "sg:postcode":"20145",
    "sg:province":"Milano",
    "wof:name":"Opel Italia Spa",
    "wof:placetype":"venue"
},
  "geometry": {"coordinates":[9.1563072205,45.4751091003],"type":"Point"}
}