{
  "type": "Feature",
  "properties": {
    "iso:country":"IT",
    "sg:address":"33100 Udine",
    "sg:city":"Udine",
    "sg:orig_category":"Minuterie Metalliche E Ferramenta",
    "sg:phone":"+39 0432 600071",
    "sg:postcode":"33100",
    "sg:province":"Udine",
    "wof:name":"Sami Tecnica Srl",
    "wof:placetype":"venue"
},
  "geometry": {"coordinates":[13.2596645355,46.0260124207],"type":"Point"}
}