{
  "type": "Feature",
  "properties": {
    "addr:full":"Via Tevere 64020 Castellalto Castellalto Teramo 64020",
    "addr:postcode":"64020;64020",
    "addr:street":"Via Tevere",
    "iso:country":"IT",
    "sg:address":"Via Tevere 64020 Castellalto",
    "sg:city":"Castellalto",
    "sg:classifiers":[
        {
            "category":"Shopping",
            "subcategory":"Stationery & Office Supplies",
            "type":"Retail Goods"
        }
    ],
    "sg:phone":"+39 0861 570221",
    "sg:postcode":"64020",
    "sg:province":"Teramo",
    "sg:tags":[
        "professional"
    ],
    "wof:name":"Arcadia Componibili S.r.l.",
    "wof:placetype":"venue"
},
  "geometry": {"coordinates":[13.8572034836,42.6236190796],"type":"Point"}
}