{
  "type": "Feature",
  "properties": {
    "iso:country":"IT",
    "sg:address":"10135 Torino",
    "sg:city":"Torino",
    "sg:orig_category":"Carta E Cartone - Produzione E Commercio",
    "sg:phone":"+39 011 397 8197",
    "sg:postcode":"10135",
    "sg:province":"Torino",
    "wof:name":"Desogus Cartotecnica",
    "wof:placetype":"venue"
},
  "geometry": {"coordinates":[7.623632,45.020302],"type":"Point"}
}