{
  "type": "Feature",
  "properties": {
    "addr:full":"85, Corso Casale 14100 Asti Asti Asti 14100",
    "addr:postcode":"14100;14100",
    "addr:street":"Corso Casale",
    "iso:country":"IT",
    "sg:address":"85, Corso Casale 14100 Asti",
    "sg:city":"Asti",
    "sg:classifiers":[
        {
            "category":"Food & Beverages",
            "subcategory":"Groceries & Convenience Stores",
            "type":"Retail Goods"
        }
    ],
    "sg:phone":"+39 0141 272518",
    "sg:postcode":"14100",
    "sg:province":"Asti",
    "sg:tags":[
        "product",
        "related"
    ],
    "wof:name":"Salumificio Nebiolo (s.r.l.)",
    "wof:placetype":"venue"
},
  "geometry": {"coordinates":[8.2191352844,44.9070053101],"type":"Point"}
}