{
  "type": "Feature",
  "properties": {
    "iso:country":"IT",
    "sg:address":"70043 Monopoli",
    "sg:city":"Monopoli",
    "sg:orig_category":"Automazione E Macchine Per Ufficio. Servizi Ausiliari Di Certificati, Riproduzioni, Disegni E Foto",
    "sg:phone":"+39 080 413 6090",
    "sg:postcode":"70043",
    "sg:province":"Bari",
    "wof:name":"Arkivia Di Meo Dr. Ivan",
    "wof:placetype":"venue"
},
  "geometry": {"coordinates":[16.866993,41.073784],"type":"Point"}
}