{
  "type": "Feature",
  "properties": {
    "iso:country":"IT",
    "sg:address":"74100 Taranto",
    "sg:city":"Taranto",
    "sg:orig_category":"Editoria",
    "sg:phone":"+39 099 732 5059",
    "sg:postcode":"74100",
    "sg:province":"Taranto",
    "sg:website":"http://www.informannunci.it",
    "wof:name":"Informannunci Periodico D'informazione",
    "wof:placetype":"venue"
},
  "geometry": {"coordinates":[17.250986,40.46257],"type":"Point"}
}