{
  "type": "Feature",
  "properties": {
    "iso:country":"IT",
    "sg:address":"67, Frazione Lizzona 32014 Ponte Nelle Alpi",
    "sg:city":"Ponte nelle Alpi",
    "sg:classifiers":[
        {
            "category":"Building & Trades",
            "subcategory":"Construction",
            "type":"Services"
        }
    ],
    "sg:phone":"+39 0437 989010",
    "sg:postcode":"32014",
    "sg:province":"Belluno",
    "sg:tags":[
        "work",
        "public"
    ],
    "wof:name":"Dolomiti Rocce Srl",
    "wof:placetype":"venue"
},
  "geometry": {"coordinates":[12.323375,46.156158],"type":"Point"}
}