{
  "type": "Feature",
  "properties": {
    "addr:full":"10123 Torino Torino Torino 10123",
    "addr:postcode":"10123;10123",
    "iso:country":"IT",
    "sg:address":"10123 Torino",
    "sg:city":"Torino",
    "sg:classifiers":[
        {
            "category":"Shopping",
            "subcategory":"Clothing, Apparel, & Fashions",
            "type":"Retail Goods"
        }
    ],
    "sg:phone":"+39 011 839 5839",
    "sg:postcode":"10123",
    "sg:province":"Torino",
    "sg:tags":[
        "knitwear",
        "furs",
        "clothing"
    ],
    "sg:website":"http://www.andreamaugeri.com",
    "wof:name":"Andrea Sas Di Stefania Montanino E C.",
    "wof:placetype":"venue"
},
  "geometry": {"coordinates":[8.39892,45.462345],"type":"Point"}
}