{
  "type": "Feature",
  "properties": {
    "iso:country":"IT",
    "sg:address":"24059 Urgnano",
    "sg:city":"Urgnano",
    "sg:orig_category":"Servizi E Lavori Per Abbigliamento E Pelletterie",
    "sg:postcode":"24059",
    "sg:province":"Bergamo",
    "wof:name":"Conceria Bergamasca Di Provenzi Luigino & C. (s.a.s.)",
    "wof:placetype":"venue"
},
  "geometry": {"coordinates":[9.704788,45.584267],"type":"Point"}
}