{
  "type": "Feature",
  "properties": {
    "addr:full":"16, Via Case Sparse 26041 Casalmaggiore Casalmaggiore Cremona 26041",
    "addr:postcode":"26041;26041",
    "addr:street":"Via Case Sparse",
    "iso:country":"IT",
    "sg:address":"16, Via Case Sparse 26041 Casalmaggiore",
    "sg:city":"Casalmaggiore",
    "sg:classifiers":[
        {
            "category":"Manufacturing",
            "subcategory":"Paper Products",
            "type":"Manufacturing & Wholesale Goods"
        }
    ],
    "sg:phone":"+39 39800518166",
    "sg:postcode":"26041",
    "sg:province":"Cremona",
    "sg:tags":[
        "cardboard"
    ],
    "wof:name":"Industrie Emiliana Parati Spa",
    "wof:placetype":"venue"
},
  "geometry": {"coordinates":[10.0261354446,45.1334991455],"type":"Point"}
}