{
  "type": "Feature",
  "properties": {
    "iso:country":"IT",
    "sg:address":"41057 Spilamberto",
    "sg:city":"Spilamberto",
    "sg:orig_category":"Prodotti Di Base E Forniture Per Industria Alimentare E Bevande",
    "sg:phone":"+39 059 781818",
    "sg:postcode":"41057",
    "sg:province":"Modena",
    "wof:name":"Poggi S.n.c.",
    "wof:placetype":"venue"
},
  "geometry": {"coordinates":[11.0096979141,44.5427398682],"type":"Point"}
}