{
  "type": "Feature",
  "properties": {
    "addr:full":"44047 Sant'agostino Ferrara 44047",
    "addr:postcode":"44047;44047",
    "iso:country":"IT",
    "sg:address":"44047 Sant'agostino",
    "sg:classifiers":[
        {
            "category":"Retail",
            "subcategory":"Storage",
            "type":"Services"
        }
    ],
    "sg:phone":"+39 0532 848348",
    "sg:postcode":"44047",
    "sg:province":"Ferrara",
    "sg:tags":[
        "equipment",
        "handling",
        "system"
    ],
    "sg:website":"http://www.comav-srl.com",
    "wof:name":"Comav Srl",
    "wof:placetype":"venue"
},
  "geometry": {"coordinates":[11.381498,44.796173],"type":"Point"}
}