{
  "type": "Feature",
  "properties": {
    "iso:country":"IT",
    "sg:address":"15, Via Ix Agosto 34170 Gorizia",
    "sg:city":"Gorizia",
    "sg:classifiers":[
        {
            "category":"Utilities",
            "subcategory":"Electric",
            "type":"Services"
        }
    ],
    "sg:phone":"+39 0481 593111",
    "sg:postcode":"34170",
    "sg:province":"Gorizia",
    "sg:tags":[
        "electricity"
    ],
    "wof:name":"Azienda Multiservizi Goriziana A.m.g. S.p.a.",
    "wof:placetype":"venue"
},
  "geometry": {"coordinates":[13.621546,45.941303],"type":"Point"}
}