{
  "type": "Feature",
  "properties": {
    "iso:country":"IT",
    "sg:address":"Via Marzabotto 12 41030 Bomporto",
    "sg:city":"Bomporto",
    "sg:classifiers":[
        {
            "category":"Building & Trades",
            "subcategory":"Construction",
            "type":"Services"
        }
    ],
    "sg:phone":"+39 059 818406",
    "sg:postcode":"41030",
    "sg:province":"Modena",
    "sg:tags":[
        "carpenter's",
        "work",
        "supraregional"
    ],
    "wof:name":"Carpenfer Snc",
    "wof:placetype":"venue"
},
  "geometry": {"coordinates":[11.004882,44.692844],"type":"Point"}
}