{
  "type": "Feature",
  "properties": {
    "iso:country":"IT",
    "sg:address":"32032 Feltre",
    "sg:city":"Feltre",
    "sg:orig_category":"Arredo Cucina Ed Elettrodomestici. Elettrodomestici",
    "sg:phone":"+39 0439 302222",
    "sg:postcode":"32032",
    "sg:province":"Belluno",
    "wof:name":"Centa (s.n.c.)",
    "wof:placetype":"venue"
},
  "geometry": {"coordinates":[11.898079,46.022766],"type":"Point"}
}