{
  "type": "Feature",
  "properties": {
    "iso:country":"IT",
    "sg:address":"00047 Marino",
    "sg:city":"Marino",
    "sg:orig_category":"Pompe. Ricambi E Componenti Dei Mezzi Di Trasporto",
    "sg:phone":"+39 06 931 1493",
    "sg:postcode":"00047",
    "sg:province":"Roma",
    "wof:name":"Albrizio Angelo",
    "wof:placetype":"venue"
},
  "geometry": {"coordinates":[12.6160993576,41.7619552612],"type":"Point"}
}