{
  "type": "Feature",
  "properties": {
    "iso:country":"IT",
    "sg:address":"20011 Corbetta",
    "sg:city":"Corbetta",
    "sg:orig_category":"Servizi Editoriali. Servizi Ausiliari Per Il Trasporto",
    "sg:phone":"+39 02 9727 2209",
    "sg:postcode":"20011",
    "sg:province":"Milano",
    "wof:name":"A & G Marco S.p.a.",
    "wof:placetype":"venue"
},
  "geometry": {"coordinates":[9.209378,45.69976],"type":"Point"}
}