{
  "type": "Feature",
  "properties": {
    "iso:country":"IT",
    "sg:address":"Via Giuseppe Del Papa 10; Empoli; 50053",
    "sg:city":"Empoli",
    "sg:classifiers":[
        {
            "category":"Banks & Credit Unions",
            "subcategory":"Bank",
            "type":"Services"
        }
    ],
    "sg:phone":"+39 0571 711332",
    "sg:postcode":"50053",
    "sg:province":"Firenze",
    "wof:name":"Banca Nazionale Del Lavoro Spa",
    "wof:placetype":"venue"
},
  "geometry": {"coordinates":[10.946881,43.719173],"type":"Point"}
}