{
  "type": "Feature",
  "properties": {
    "addr:full":"00045 Genzano Di Roma Genzano di Roma Roma 00045",
    "addr:postcode":"00045;00045",
    "iso:country":"IT",
    "sg:address":"00045 Genzano Di Roma",
    "sg:city":"Genzano di Roma",
    "sg:orig_category":"Forniture Uffici",
    "sg:phone":"+39 06 936 4384",
    "sg:postcode":"00045",
    "sg:province":"Roma",
    "wof:name":"L'istantanea Sud Srl",
    "wof:placetype":"venue"
},
  "geometry": {"coordinates":[12.6846923828,41.7017707825],"type":"Point"}
}