{
  "type": "Feature",
  "properties": {
    "addr:full":"Via Dell'industria 39 42025 Cavriago Reggio Nell'Emilia 42025",
    "addr:housenumber":"39",
    "addr:postcode":"42025;42025",
    "addr:street":"Via Dell'Industria",
    "iso:country":"IT",
    "sg:address":"Via Dell'industria 39 42025 Cavriago",
    "sg:classifiers":[
        {
            "category":"Manufacturing",
            "subcategory":"Motor Vehicles & Parts",
            "type":"Manufacturing & Wholesale Goods"
        }
    ],
    "sg:phone":"+39 0522 941266",
    "sg:postcode":"42025",
    "sg:province":"Reggio Nell'Emilia",
    "sg:tags":[
        "electromechanical"
    ],
    "wof:name":"A.r.c.e. Elettropompe Impresa Individuale",
    "wof:placetype":"venue"
},
  "geometry": {"coordinates":[10.551993,44.718601],"type":"Point"}
}