{
  "type": "Feature",
  "properties": {
    "addr:full":"Via Crescenzio 42, 00193 Rome, Rm Roma 00193",
    "addr:housenumber":"42",
    "addr:postcode":"00193;rm;00193",
    "addr:street":"Via Crescenzio",
    "iso:country":"IT",
    "sg:address":"Via Crescenzio 42, 00193 Rome, Rm",
    "sg:classifiers":[
        {
            "category":"Banks & Credit Unions",
            "subcategory":"Bank",
            "type":"Services"
        }
    ],
    "sg:postcode":"00193",
    "sg:province":"Roma",
    "wof:name":"Centro Agro Alimentare Roma",
    "wof:placetype":"venue"
},
  "geometry": {"coordinates":[12.464396,41.905674],"type":"Point"}
}