{
  "type": "Feature",
  "properties": {
    "addr:full":"44, Via Po 20015 Parabiago Parabiago Milano 20015",
    "addr:postcode":"20015;20015",
    "addr:street":"Via Po",
    "iso:country":"IT",
    "sg:address":"44, Via Po 20015 Parabiago",
    "sg:city":"Parabiago",
    "sg:classifiers":[
        {
            "category":"Shopping",
            "subcategory":"Crafts & Fabrics",
            "type":"Retail Goods"
        }
    ],
    "sg:phone":"+39 0331 557594",
    "sg:postcode":"20015",
    "sg:province":"Milano",
    "wof:name":"Zucchetti Tessitura Srl",
    "wof:placetype":"venue"
},
  "geometry": {"coordinates":[8.3989200592,45.4623451233],"type":"Point"}
}