{
  "type": "Feature",
  "properties": {
    "iso:country":"IT",
    "sg:address":"17, Via Oberdan Guglielmo 25065 Lumezzane",
    "sg:city":"Lumezzane",
    "sg:classifiers":[
        {
            "category":"Shopping",
            "type":"Retail Goods"
        }
    ],
    "sg:phone":"+39 39030827229",
    "sg:postcode":"25065",
    "sg:province":"Brescia",
    "sg:tags":[
        "finished",
        "-",
        "metallic"
    ],
    "wof:name":"Coltelleria Valgobbia Di Gnutti Pierino & C. S.n.c.",
    "wof:placetype":"venue"
},
  "geometry": {"coordinates":[10.2155694962,45.6077384949],"type":"Point"}
}