{
  "type": "Feature",
  "properties": {
    "iso:country":"IT",
    "sg:address":"123, Via Rossini 60022 Castelfidardo",
    "sg:city":"Castelfidardo",
    "sg:classifiers":[
        {
            "category":"Sports & Exercise",
            "subcategory":"Playing Field",
            "type":"Entertainment"
        }
    ],
    "sg:phone":"+39 39071780092",
    "sg:postcode":"60022",
    "sg:province":"Ancona",
    "sg:tags":[
        "game"
    ],
    "wof:name":"Salpa Di Breccia & C. Srl",
    "wof:placetype":"venue"
},
  "geometry": {"coordinates":[13.548714,43.529442],"type":"Point"}
}