{
  "type": "Feature",
  "properties": {
    "iso:country":"IT",
    "sg:address":"29100 Piacenza",
    "sg:city":"Piacenza",
    "sg:orig_category":"Automobili E Mezzi Di Trasporto",
    "sg:phone":"+39 0523 594005",
    "sg:postcode":"29100",
    "sg:province":"Piacenza",
    "wof:name":"Perazzi Massimo",
    "wof:placetype":"venue"
},
  "geometry": {"coordinates":[9.749136,45.02528],"type":"Point"}
}