{
  "type": "Feature",
  "properties": {
    "addr:full":"10/12 Via Pellico Silvio, 20121 Milano Milano Milano 20121",
    "addr:housenumber":"10 / 12",
    "addr:postcode":"20121;20121",
    "addr:street":"Via Pellico Silvio",
    "iso:country":"IT",
    "sg:address":"10/12 Via Pellico Silvio, 20121 Milano",
    "sg:city":"Milano",
    "sg:classifiers":[
        {
            "category":"Banks & Credit Unions",
            "subcategory":"Financial Services",
            "type":"Services"
        }
    ],
    "sg:phone":"+39 390 288 171",
    "sg:postcode":"20121",
    "sg:province":"Milano",
    "sg:tags":[
        "banking",
        "finance",
        "insurance"
    ],
    "wof:name":"Banco Di Brescia",
    "wof:placetype":"venue"
},
  "geometry": {"coordinates":[9.189289093,45.4659347534],"type":"Point"}
}