{
  "type": "Feature",
  "properties": {
    "addr:full":"25020 Cigole Cigole Brescia 25020",
    "addr:postcode":"25020;25020",
    "iso:country":"IT",
    "sg:address":"25020 Cigole",
    "sg:city":"Cigole",
    "sg:orig_category":"Forniture Per Agricoltura E Zootecnia",
    "sg:phone":"+39 030 995 9940",
    "sg:postcode":"25020",
    "sg:province":"Brescia",
    "wof:name":"Agrifort Di Anelli M. & R. (s.n.c.)",
    "wof:placetype":"venue"
},
  "geometry": {"coordinates":[10.129611969,45.3344726562],"type":"Point"}
}