{
  "type": "Feature",
  "properties": {
    "iso:country":"IT",
    "sg:address":"16036 Recco",
    "sg:city":"Recco",
    "sg:orig_category":"Non-classified Establishments",
    "sg:phone":"+39 0185 75250",
    "sg:postcode":"16036",
    "sg:province":"Genova",
    "wof:name":"Bacigalupo Mario",
    "wof:placetype":"venue"
},
  "geometry": {"coordinates":[9.141026,44.36245],"type":"Point"}
}