{
  "type": "Feature",
  "properties": {
    "iso:country":"IT",
    "sg:address":"13, Via A.mazzocchi 44033 Berra",
    "sg:city":"Berra",
    "sg:classifiers":[
        {
            "category":"Shopping",
            "subcategory":"Computers & Home Electronics",
            "type":"Retail Goods"
        }
    ],
    "sg:phone":"+39 0532 832270",
    "sg:postcode":"44033",
    "sg:province":"Ferrara",
    "sg:tags":[
        "electronic",
        "electrical",
        "equipment"
    ],
    "wof:name":"Elettromecber",
    "wof:placetype":"venue"
},
  "geometry": {"coordinates":[11.62044,44.837894],"type":"Point"}
}