{
  "type": "Feature",
  "properties": {
    "iso:country":"IT",
    "sg:address":"25125 Brescia",
    "sg:city":"Brescia",
    "sg:orig_category":"Apparecchiature Ed Attrezzature Meccaniche",
    "sg:phone":"+39 030 353 2439",
    "sg:postcode":"25125",
    "sg:province":"Brescia",
    "wof:name":"Hilti Italia Spa",
    "wof:placetype":"venue"
},
  "geometry": {"coordinates":[10.182327,45.530933],"type":"Point"}
}