{
  "type": "Feature",
  "properties": {
    "iso:country":"IT",
    "sg:address":"119 Corso Martiri Della Liberazione, 23900 Lecco",
    "sg:city":"Lecco",
    "sg:classifiers":[
        {
            "category":"Banks & Credit Unions",
            "subcategory":"Financial Services",
            "type":"Services"
        }
    ],
    "sg:phone":"+39 0341 369479",
    "sg:postcode":"23900",
    "sg:province":"Lecco",
    "sg:tags":[
        "banking",
        "finance",
        "insurance"
    ],
    "wof:name":"Cofile (srl)",
    "wof:placetype":"venue"
},
  "geometry": {"coordinates":[9.3979043961,45.8464126587],"type":"Point"}
}