{
  "type": "Feature",
  "properties": {
    "iso:country":"IT",
    "sg:address":"20/a/1, V. Staffora 20090 Opera",
    "sg:city":"Opera",
    "sg:classifiers":[
        {
            "category":"Shopping",
            "type":"Retail Goods"
        }
    ],
    "sg:phone":"+39 02 5760 4617",
    "sg:postcode":"20090",
    "sg:province":"Milano",
    "sg:tags":[
        "finished",
        "-",
        "metallic"
    ],
    "sg:website":"http://www.bombole.it",
    "wof:name":"Saca Unit Tek Srl",
    "wof:placetype":"venue"
},
  "geometry": {"coordinates":[9.2046842575,45.3661460876],"type":"Point"}
}