{
  "type": "Feature",
  "properties": {
    "iso:country":"IT",
    "sg:address":"1, Via Del Lavoro 40057 Granarolo Dell'emilia",
    "sg:classifiers":[
        {
            "category":"Wholesale",
            "subcategory":"Medical Equipment & Supplies",
            "type":"Manufacturing & Wholesale Goods"
        }
    ],
    "sg:phone":"+39 39051767211",
    "sg:postcode":"40057",
    "sg:province":"Bologna",
    "sg:tags":[
        "-",
        "health",
        "instrument"
    ],
    "wof:name":"Autovanti (s.p.a.)",
    "wof:placetype":"venue"
},
  "geometry": {"coordinates":[11.414116,44.527466],"type":"Point"}
}