{
  "type": "Feature",
  "properties": {
    "iso:country":"IT",
    "sg:address":"Via Scalo Ferroviario 75012 Bernalda",
    "sg:city":"Bernalda",
    "sg:classifiers":[
        {
            "category":"Personal",
            "subcategory":"Shoe Repair & Shine",
            "type":"Services"
        }
    ],
    "sg:phone":"+39 0835 542410",
    "sg:postcode":"75012",
    "sg:province":"Matera",
    "sg:tags":[
        "leather"
    ],
    "wof:name":"Calzaturificio Del Basento (s.r.l.)",
    "wof:placetype":"venue"
},
  "geometry": {"coordinates":[16.606087,40.668652],"type":"Point"}
}