{
  "type": "Feature",
  "properties": {
    "iso:country":"IT",
    "sg:address":"20147 Milano",
    "sg:city":"Milano",
    "sg:orig_category":"Servizi Ausiliari Dei Mezzi Di Trasporto",
    "sg:phone":"+39 02 415 8277",
    "sg:postcode":"20147",
    "sg:province":"Milano",
    "wof:name":"Speriani & Viggiano Snc Di Paola Speriani E Daniele Viggiano",
    "wof:placetype":"venue"
},
  "geometry": {"coordinates":[9.141659,45.451706],"type":"Point"}
}