{
  "type": "Feature",
  "properties": {
    "iso:country":"IT",
    "sg:address":"16129 Genova",
    "sg:city":"Genova",
    "sg:orig_category":"Ospedali E Servizi Sanitari",
    "sg:phone":"+39 010 588952",
    "sg:postcode":"16129",
    "sg:province":"Genova",
    "wof:name":"Studio Gazzerro Di Gazzerro & C. Snc",
    "wof:placetype":"venue"
},
  "geometry": {"coordinates":[8.950755,44.400074],"type":"Point"}
}