{
  "type": "Feature",
  "properties": {
    "addr:full":"3, Via Piero Della Francesca 74100 Taranto Taranto Taranto 74100",
    "addr:postcode":"74100;74100",
    "addr:street":"Via Piero Della Francesca",
    "iso:country":"IT",
    "sg:address":"3, Via Piero Della Francesca 74100 Taranto",
    "sg:city":"Taranto",
    "sg:classifiers":[
        {
            "category":"Manufacturing",
            "subcategory":"Rubber & Plastics",
            "type":"Manufacturing & Wholesale Goods"
        }
    ],
    "sg:phone":"+39 099 470 9002",
    "sg:postcode":"74100",
    "sg:province":"Taranto",
    "wof:name":"Templa Tecnologie Materie Plastiche S.r.l",
    "wof:placetype":"venue"
},
  "geometry": {"coordinates":[17.2259044647,40.5045928955],"type":"Point"}
}