{
  "type": "Feature",
  "properties": {
    "addr:full":"98163 Messina Messina Messina 98163",
    "addr:postcode":"98163;98163",
    "iso:country":"IT",
    "sg:address":"98163 Messina",
    "sg:city":"Messina",
    "sg:orig_category":"Carni, Salumi E Pesci. Ristorazione E Locali Pubblici Affini. Shopping",
    "sg:phone":"+39 090 293 9461",
    "sg:postcode":"98163",
    "sg:province":"Messina",
    "wof:name":"Ceraolo Snc",
    "wof:placetype":"venue"
},
  "geometry": {"coordinates":[15.53897,38.165207],"type":"Point"}
}