{
  "type": "Feature",
  "properties": {
    "iso:country":"IT",
    "sg:address":"92014 Porto Empedocle",
    "sg:city":"Porto Empedocle",
    "sg:orig_category":"Impiantistica E Prodotti Tecnologici Per Edilizia. Termotecnica E Riscaldamento, Apparecchiature E Servizi",
    "sg:phone":"+39 0922 635706",
    "sg:postcode":"92014",
    "sg:province":"Agrigento",
    "wof:name":"Mediterranea Impianti Snc Di Gino Grillo Alberto & C.",
    "wof:placetype":"venue"
},
  "geometry": {"coordinates":[13.524106,37.291077],"type":"Point"}
}