{
  "type": "Feature",
  "properties": {
    "iso:country":"IT",
    "sg:address":"Via Garibaldi, 5 Int. 5; Portovenere; 19025",
    "sg:city":"Portovenere",
    "sg:classifiers":[
        {
            "category":"Banks & Credit Unions",
            "subcategory":"Bank",
            "type":"Services"
        }
    ],
    "sg:phone":"+39 0187 900633",
    "sg:postcode":"19025",
    "sg:province":"La Spezia",
    "wof:name":"Cassa Di Risparmio Della Spezia",
    "wof:placetype":"venue"
},
  "geometry": {"coordinates":[9.83709,44.054867],"type":"Point"}
}