{
  "type": "Feature",
  "properties": {
    "iso:country":"IT",
    "sg:address":"10134 Torino",
    "sg:city":"Torino",
    "sg:orig_category":"Non-classified Establishments",
    "sg:phone":"+39 011 304 2478",
    "sg:postcode":"10134",
    "sg:province":"Torino",
    "wof:name":"Opportunity Shop",
    "wof:placetype":"venue"
},
  "geometry": {"coordinates":[7.651949,45.03458],"type":"Point"}
}