{
  "type": "Feature",
  "properties": {
    "iso:country":"IT",
    "sg:address":"62, Via Morosetti 15048 Valenza",
    "sg:city":"Valenza",
    "sg:classifiers":[
        {
            "category":"Shopping",
            "subcategory":"Jewelry",
            "type":"Retail Goods"
        }
    ],
    "sg:phone":"+39 0131 946542",
    "sg:postcode":"15048",
    "sg:province":"Alessandria",
    "sg:tags":[
        "jewellery"
    ],
    "wof:name":"Linea Oro Sas Gioielleria In Montatura Di Mangolini Patrizia E C.",
    "wof:placetype":"venue"
},
  "geometry": {"coordinates":[8.64427,45.006832],"type":"Point"}
}