{
  "type": "Feature",
  "properties": {
    "iso:country":"IT",
    "sg:address":"41012 Carpi",
    "sg:city":"Carpi",
    "sg:orig_category":"Apparecchiature E Sistemi Per Magazzinaggio E Movimentazione",
    "sg:phone":"+39 059 644290",
    "sg:postcode":"41012",
    "sg:province":"Modena",
    "sg:website":"http://www.carrmm.com",
    "wof:name":"Carrozzeria M. M. Snc",
    "wof:placetype":"venue"
},
  "geometry": {"coordinates":[10.863265,44.837715],"type":"Point"}
}