{
  "type": "Feature",
  "properties": {
    "addr:full":"50018 Scandicci Scandicci Firenze 50018",
    "addr:postcode":"50018;50018",
    "iso:country":"IT",
    "sg:address":"50018 Scandicci",
    "sg:city":"Scandicci",
    "sg:orig_category":"Prodotti E Manufatti In Materie Plastiche. Forniture Per Attivita' Industriali",
    "sg:phone":"+39 055 722 1449",
    "sg:postcode":"50018",
    "sg:province":"Firenze",
    "wof:name":"L.p.m. Snc",
    "wof:placetype":"venue"
},
  "geometry": {"coordinates":[11.1567001343,43.7640800476],"type":"Point"}
}