{
  "type": "Feature",
  "properties": {
    "addr:full":"Via Vittorio; Partanna; 91028 Partanna Trapani 91028",
    "addr:postcode":"91028;91028",
    "addr:street":"Via Vittorio Partanna",
    "iso:country":"IT",
    "sg:address":"Via Vittorio; Partanna; 91028",
    "sg:city":"Partanna",
    "sg:classifiers":[
        {
            "category":"Banks & Credit Unions",
            "subcategory":"Bank",
            "type":"Services"
        }
    ],
    "sg:phone":"+39 0924 49152",
    "sg:postcode":"91028",
    "sg:province":"Trapani",
    "wof:name":"Banco Di Sicilia Spa",
    "wof:placetype":"venue"
},
  "geometry": {"coordinates":[12.890744,37.723927],"type":"Point"}
}