{
  "type": "Feature",
  "properties": {
    "addr:full":"9, Via Delle Brughiere 20024 Garbagnate Milanese Garbagnate Milanese Milano 20024",
    "addr:postcode":"20024;20024",
    "addr:street":"Via Delle Brughiere",
    "iso:country":"IT",
    "sg:address":"9, Via Delle Brughiere 20024 Garbagnate Milanese",
    "sg:city":"Garbagnate Milanese",
    "sg:classifiers":[
        {
            "category":"Shopping",
            "subcategory":"Crafts & Fabrics",
            "type":"Retail Goods"
        }
    ],
    "sg:phone":"+39 02 9902 2155",
    "sg:postcode":"20024",
    "sg:province":"Milano",
    "wof:name":"Nuova Er.me Stampa Srl",
    "wof:placetype":"venue"
},
  "geometry": {"coordinates":[9.0845746994,45.5830497742],"type":"Point"}
}