{
  "type": "Feature",
  "properties": {
    "addr:full":"19, Via Vittorio Veneto 20010 Bernate Ticino Bernate Ticino Milano 20010",
    "addr:postcode":"20010;20010",
    "addr:street":"Via Vittorio Veneto",
    "iso:country":"IT",
    "sg:address":"19, Via Vittorio Veneto 20010 Bernate Ticino",
    "sg:city":"Bernate Ticino",
    "sg:classifiers":[
        {
            "category":"Professional",
            "subcategory":"Printing & Photocopies",
            "type":"Services"
        }
    ],
    "sg:phone":"+39 02 9725 5281",
    "sg:postcode":"20010",
    "sg:province":"Milano",
    "wof:name":"Gasa S.r.l.",
    "wof:placetype":"venue"
},
  "geometry": {"coordinates":[8.8486976624,45.5175170898],"type":"Point"}
}