{
  "type": "Feature",
  "properties": {
    "iso:country":"IT",
    "sg:address":"205, Via Barberinese 50013 Campi Bisenzio",
    "sg:city":"Campi Bisenzio",
    "sg:classifiers":[
        {
            "category":"Shopping",
            "subcategory":"Clothing, Apparel, & Fashions",
            "type":"Retail Goods"
        }
    ],
    "sg:phone":"+39 055 895 4472",
    "sg:postcode":"50013",
    "sg:province":"Firenze",
    "sg:tags":[
        "clothes"
    ],
    "wof:name":"La Florens (s.p.a.)",
    "wof:placetype":"venue"
},
  "geometry": {"coordinates":[11.129261,43.827839],"type":"Point"}
}