{
  "type": "Feature",
  "properties": {
    "addr:full":"47, Viale L. Scarfiotti 62017 Porto Recanati Porto Recanati Macerata 62017",
    "addr:housenumber":"47",
    "addr:postcode":"62017;62017",
    "addr:street":"Viale L. Scarfiotti",
    "iso:country":"IT",
    "sg:address":"47, Viale L. Scarfiotti 62017 Porto Recanati",
    "sg:city":"Porto Recanati",
    "sg:classifiers":[
        {
            "category":"Sports & Exercise",
            "subcategory":"Playing Field",
            "type":"Entertainment"
        }
    ],
    "sg:phone":"+39 071 979 8302",
    "sg:postcode":"62017",
    "sg:province":"Macerata",
    "sg:tags":[
        "game"
    ],
    "wof:name":"Lola Happening",
    "wof:placetype":"venue"
},
  "geometry": {"coordinates":[13.456262,43.300747],"type":"Point"}
}