{
  "type": "Feature",
  "properties": {
    "iso:country":"IT",
    "sg:address":"39012 Sinigo",
    "sg:city":"Sinigo",
    "sg:orig_category":"Macchine, Impianti Ed Attrezzature Per Agricoltura E Zootecnia. Macchine, Strumenti Ed Apparecchi Per Attivita' Industriali",
    "sg:postcode":"39012",
    "sg:province":"Bolzano/Bozen",
    "wof:name":"Waibl Diethart",
    "wof:placetype":"venue"
},
  "geometry": {"coordinates":[11.184671,46.625195],"type":"Point"}
}