{
  "type": "Feature",
  "properties": {
    "addr:full":"20034 Giussano Giussano Milano 20034",
    "addr:postcode":"20034;20034",
    "iso:country":"IT",
    "sg:address":"20034 Giussano",
    "sg:city":"Giussano",
    "sg:orig_category":"Manufacturers: Prefabbricati",
    "sg:phone":"+39 036 231 2020",
    "sg:postcode":"20034",
    "sg:province":"Milano",
    "wof:name":"Sidea Srl",
    "wof:placetype":"venue"
},
  "geometry": {"coordinates":[9.211144,45.681065],"type":"Point"}
}