{
  "type": "Feature",
  "properties": {
    "addr:full":"89, V. Delle Industrie 20040 Cambiago Cambiago Milano 20040",
    "addr:housenumber":"89",
    "addr:postcode":"20040;20040",
    "addr:street":"V. Delle Industrie",
    "iso:country":"IT",
    "sg:address":"89, V. Delle Industrie 20040 Cambiago",
    "sg:city":"Cambiago",
    "sg:classifiers":[
        {
            "category":"Manufacturing",
            "subcategory":"Rubber & Plastics",
            "type":"Manufacturing & Wholesale Goods"
        }
    ],
    "sg:phone":"+39 02 9530 8330",
    "sg:postcode":"20040",
    "sg:province":"Milano",
    "sg:tags":[
        "packaging",
        "material",
        "-"
    ],
    "sg:website":"http://www.bmp-tappi.it",
    "wof:name":"B.m.p. Srl",
    "wof:placetype":"venue"
},
  "geometry": {"coordinates":[9.4343070984,45.5796432495],"type":"Point"}
}