{
  "type": "Feature",
  "properties": {
    "iso:country":"IT",
    "sg:address":"20154 Milano",
    "sg:city":"Milano",
    "sg:orig_category":"Ingranaggi",
    "sg:phone":"+39 02 331 1898",
    "sg:postcode":"20154",
    "sg:province":"Milano",
    "wof:name":"Micromeccanica R.m. Di Paolo Metzger & D. Manelli Snc",
    "wof:placetype":"venue"
},
  "geometry": {"coordinates":[9.176217,45.480717],"type":"Point"}
}