{
  "type": "Feature",
  "properties": {
    "iso:country":"IT",
    "sg:address":"17028 Spotorno",
    "sg:city":"Spotorno",
    "sg:orig_category":"Elettronica Professionale E Di Consumo. Automazione E Macchine Per Ufficio",
    "sg:phone":"+39 019 747486",
    "sg:postcode":"17028",
    "sg:province":"Savona",
    "wof:name":"Abs",
    "wof:placetype":"venue"
},
  "geometry": {"coordinates":[8.41149,44.228367],"type":"Point"}
}