{
  "type": "Feature",
  "properties": {
    "addr:full":"21, Via Milano 59013 Montemurlo Montemurlo Prato 59013",
    "addr:postcode":"59013;59013",
    "addr:street":"Via Milano",
    "iso:country":"IT",
    "sg:address":"21, Via Milano 59013 Montemurlo",
    "sg:city":"Montemurlo",
    "sg:classifiers":[
        {
            "category":"Shopping",
            "subcategory":"Crafts & Fabrics",
            "type":"Retail Goods"
        }
    ],
    "sg:phone":"+39 0574 798421",
    "sg:postcode":"59013",
    "sg:province":"Prato",
    "wof:name":"I.te.sa. (s.r.l.)",
    "wof:placetype":"venue"
},
  "geometry": {"coordinates":[11.0300884247,43.9115982056],"type":"Point"}
}