{
  "type": "Feature",
  "properties": {
    "iso:country":"IT",
    "sg:address":"22071 Cadorago",
    "sg:city":"Bulgorello",
    "sg:classifiers":[
        {
            "category":"Shopping",
            "subcategory":"Crafts & Fabrics",
            "type":"Retail Goods"
        }
    ],
    "sg:phone":"+39 031 900106",
    "sg:postcode":"22071",
    "sg:province":"Como",
    "sg:tags":[
        "material"
    ],
    "wof:name":"Tessitura Di Bulgorello Sas Di Armando Gabaglio",
    "wof:placetype":"venue"
},
  "geometry": {"coordinates":[9.0535345078,45.7223091125],"type":"Point"}
}