{
  "type": "Feature",
  "properties": {
    "iso:country":"IT",
    "sg:address":"41100 Modena",
    "sg:city":"Modena",
    "sg:classifiers":[
        {
            "category":"Retail",
            "subcategory":"Storage",
            "type":"Services"
        }
    ],
    "sg:phone":"+39 059 310236",
    "sg:postcode":"41100",
    "sg:province":"Modena",
    "sg:tags":[
        "equipment",
        "handling",
        "system"
    ],
    "wof:name":"Off. Meccanica Amadei Di Amadei Lino & C. Snc",
    "wof:placetype":"venue"
},
  "geometry": {"coordinates":[10.937602,44.672443],"type":"Point"}
}