{
  "type": "Feature",
  "properties": {
    "iso:country":"IT",
    "sg:address":"48100 Ravenna",
    "sg:city":"Ravenna",
    "sg:orig_category":"Servizi Per Lo Sport E Il Tempo Libero. Servizi Al Turismo. Servizi Ausiliari Dei Mezzi Di Trasporto. Servizi Ausiliari Per Il Trasporto",
    "sg:phone":"+39 0544 422985",
    "sg:postcode":"48100",
    "sg:province":"Ravenna",
    "wof:name":"T.rent Autonoleggi Sas",
    "wof:placetype":"venue"
},
  "geometry": {"coordinates":[12.274966,44.486099],"type":"Point"}
}