{
  "type": "Feature",
  "properties": {
    "iso:country":"IT",
    "sg:address":"50123 Firenze",
    "sg:city":"Firenze",
    "sg:orig_category":"Articoli Da Regalo. Tempo Libero - Articoli E Forniture. Regalistica Aziendale",
    "sg:phone":"+39 055 282035",
    "sg:postcode":"50123",
    "sg:province":"Firenze",
    "sg:website":"http://www.citti-firenze.com",
    "wof:name":"C.i.t.t.i.",
    "wof:placetype":"venue"
},
  "geometry": {"coordinates":[11.2465,43.776299],"type":"Point"}
}