{
  "type": "Feature",
  "properties": {
    "iso:country":"IT",
    "sg:address":"Via Bruno Rizzi 6/8 37012 Bussolengo",
    "sg:city":"Bussolengo",
    "sg:classifiers":[
        {
            "category":"Shopping",
            "subcategory":"Clothing, Apparel, & Fashions",
            "type":"Retail Goods"
        }
    ],
    "sg:phone":"+39 045 676 6306",
    "sg:postcode":"37012",
    "sg:province":"Verona",
    "sg:tags":[
        "sportswear"
    ],
    "sg:website":"www.speed-power.com",
    "wof:name":"Primo Piano Srl",
    "wof:placetype":"venue"
},
  "geometry": {"coordinates":[10.848567,45.444965],"type":"Point"}
}