{
  "type": "Feature",
  "properties": {
    "iso:country":"IT",
    "sg:address":"16129 Genova",
    "sg:city":"Genova",
    "sg:orig_category":"Non-classified Establishments",
    "sg:phone":"+39 010 318816",
    "sg:postcode":"16129",
    "sg:province":"Genova",
    "wof:name":"Idrovo Herrera Priscilla",
    "wof:placetype":"venue"
},
  "geometry": {"coordinates":[8.956008,44.403545],"type":"Point"}
}