{
  "type": "Feature",
  "properties": {
    "iso:country":"IT",
    "sg:address":"2, Via Tiziano 65124 Pescara",
    "sg:city":"Pescara",
    "sg:classifiers":[
        {
            "category":"Banks & Credit Unions",
            "subcategory":"Financial Services",
            "type":"Services"
        }
    ],
    "sg:phone":"+39 085 422 5480",
    "sg:postcode":"65124",
    "sg:province":"Pescara",
    "sg:tags":[
        "banking",
        "finance",
        "insurance"
    ],
    "wof:name":"Il Duomo Assicurazioni E Riassicurazioni Spa",
    "wof:placetype":"venue"
},
  "geometry": {"coordinates":[14.214094,42.464825],"type":"Point"}
}