{
  "type": "Feature",
  "properties": {
    "addr:full":"20016 Pero Pero Milano 20016",
    "addr:postcode":"20016;20016",
    "iso:country":"IT",
    "sg:address":"20016 Pero",
    "sg:city":"Pero",
    "sg:orig_category":"Macchine, Impianti Ed Attrezzature Industria Chimica",
    "sg:phone":"+39 02 3391 0880",
    "sg:postcode":"20016",
    "sg:province":"Milano",
    "wof:name":"Imf (s.r.l.)",
    "wof:placetype":"venue"
},
  "geometry": {"coordinates":[9.095313,45.512547],"type":"Point"}
}