{
  "type": "Feature",
  "properties": {
    "iso:country":"IT",
    "sg:address":"18038 Sanremo",
    "sg:orig_category":"Motori Fuoribordo",
    "sg:phone":"+39 0184 507405",
    "sg:postcode":"18038",
    "sg:province":"Imperia",
    "wof:name":"Nautiservice Srl",
    "wof:placetype":"venue"
},
  "geometry": {"coordinates":[7.7742700577,43.841178894],"type":"Point"}
}