{
  "type": "Feature",
  "properties": {
    "iso:country":"IT",
    "sg:address":"95127 Catania",
    "sg:city":"Catania",
    "sg:orig_category":"Abbigliamento Esterno, Maglierie E Pelliccerie. Shopping",
    "sg:phone":"+39 095 388042",
    "sg:postcode":"95127",
    "sg:province":"Catania",
    "sg:website":"http://www.valentinaspose.it",
    "wof:name":"Valentina Spose Srl",
    "wof:placetype":"venue"
},
  "geometry": {"coordinates":[15.101163,37.51783],"type":"Point"}
}