{
  "type": "Feature",
  "properties": {
    "addr:full":"10073 Cirie' Torino 10073",
    "addr:housenumber":"10073",
    "addr:postcode":"10073",
    "addr:street":"Cirie ' Torino",
    "iso:country":"IT",
    "sg:address":"10073 Cirie'",
    "sg:orig_category":"Automobili E Mezzi Di Trasporto",
    "sg:phone":"+39 011 921 1793",
    "sg:postcode":"10073",
    "sg:province":"Torino",
    "wof:name":"Boero Autoveicoli",
    "wof:placetype":"venue"
},
  "geometry": {"coordinates":[7.655625,45.002319],"type":"Point"}
}