{
  "type": "Feature",
  "properties": {
    "addr:full":"00166 Roma Roma Roma 00166",
    "addr:postcode":"00166;00166",
    "iso:country":"IT",
    "sg:address":"00166 Roma",
    "sg:city":"Roma",
    "sg:orig_category":"Non-classified Establishments",
    "sg:phone":"+39 06 624 2889",
    "sg:postcode":"00166",
    "sg:province":"Roma",
    "wof:name":"Giusti Gianni",
    "wof:placetype":"venue"
},
  "geometry": {"coordinates":[12.375854,42.134258],"type":"Point"}
}