{
  "type": "Feature",
  "properties": {
    "iso:country":"IT",
    "sg:address":"249/251, Via Cisa 42041 Brescello",
    "sg:classifiers":[
        {
            "category":"Autos & Motor Vehicles",
            "subcategory":"Automobile Sales",
            "type":"Retail Goods"
        }
    ],
    "sg:phone":"+39 0522 680505",
    "sg:postcode":"42041",
    "sg:province":"Reggio Nell'Emilia",
    "sg:tags":[
        "motor-cars"
    ],
    "wof:name":"Fair S.r.l.",
    "wof:placetype":"venue"
},
  "geometry": {"coordinates":[10.4812459946,44.8637695312],"type":"Point"}
}