{
  "type": "Feature",
  "properties": {
    "addr:full":"00131 Roma Roma Roma 00131",
    "addr:postcode":"00131;00131",
    "iso:country":"IT",
    "sg:address":"00131 Roma",
    "sg:city":"Roma",
    "sg:orig_category":"Forniture Per Edilizia E Lavori Pubblici. Prodotti Vari In Metallo",
    "sg:phone":"+39 06 4129 4749",
    "sg:postcode":"00131",
    "sg:province":"Roma",
    "wof:name":"Ponteggi Chece Srl",
    "wof:placetype":"venue"
},
  "geometry": {"coordinates":[12.6240930557,41.9402923584],"type":"Point"}
}