{
  "type": "Feature",
  "properties": {
    "addr:full":"22/23, Via Delle Confina 50054 Fucecchio Fucecchio Firenze 50054",
    "addr:housenumber":"22 / 23",
    "addr:postcode":"50054;50054",
    "addr:street":"Via Delle Confina",
    "iso:country":"IT",
    "sg:address":"22/23, Via Delle Confina 50054 Fucecchio",
    "sg:city":"Fucecchio",
    "sg:classifiers":[
        {
            "category":"Manufacturing",
            "subcategory":"Textiles",
            "type":"Manufacturing & Wholesale Goods"
        }
    ],
    "sg:phone":"+39 39057120343",
    "sg:postcode":"50054",
    "sg:province":"Firenze",
    "sg:tags":[
        "leather",
        "raw",
        "material",
        "-"
    ],
    "wof:name":"Conceria Gange Srl",
    "wof:placetype":"venue"
},
  "geometry": {"coordinates":[10.789012,43.724926],"type":"Point"}
}