{
  "type": "Feature",
  "properties": {
    "iso:country":"IT",
    "sg:address":"27, Via Vittuone 20152 Milano",
    "sg:city":"Milano",
    "sg:classifiers":[
        {
            "category":"Manufacturing",
            "subcategory":"Metals",
            "type":"Manufacturing & Wholesale Goods"
        }
    ],
    "sg:phone":"+39 02 4892 9194",
    "sg:postcode":"20152",
    "sg:province":"Milano",
    "sg:tags":[
        "processing"
    ],
    "wof:name":"Lazzerini Argenteria Sas Di Emilio E Stefano Lazzerini",
    "wof:placetype":"venue"
},
  "geometry": {"coordinates":[9.018248558,45.5077362061],"type":"Point"}
}