{
  "type": "Feature",
  "properties": {
    "addr:full":"Strada Paniate 1 15040 Occimiano Occimiano Alessandria 15040",
    "addr:housenumber":"1",
    "addr:postcode":"15040;15040",
    "addr:street":"Strada Paniate",
    "iso:country":"IT",
    "sg:address":"Strada Paniate 1 15040 Occimiano",
    "sg:city":"Occimiano",
    "sg:classifiers":[
        {
            "category":"Ice Cream",
            "type":"Food & Drink"
        }
    ],
    "sg:phone":"+39 0142 400611",
    "sg:postcode":"15040",
    "sg:province":"Alessandria",
    "sg:tags":[
        "freezers",
        "chest",
        "deep",
        "freezer"
    ],
    "sg:website":"www.coldcar.it",
    "wof:name":"Cold Car Srl",
    "wof:placetype":"venue"
},
  "geometry": {"coordinates":[8.490181,45.067097],"type":"Point"}
}