{
  "type": "Feature",
  "properties": {
    "addr:full":"80139 Napoli Napoli Napoli 80139",
    "addr:housenumber":"80139",
    "addr:postcode":"80139",
    "iso:country":"IT",
    "sg:address":"80139 Napoli",
    "sg:city":"Napoli",
    "sg:orig_category":"Macchine, Impianti Ed Attrezzature Per Abbigliamento E Pelletterie",
    "sg:phone":"+39 081 441018",
    "sg:postcode":"80139",
    "sg:province":"Napoli",
    "wof:name":"Pa.mi.tex 2000 S.r.l.",
    "wof:placetype":"venue"
},
  "geometry": {"coordinates":[14.316091,40.923588],"type":"Point"}
}