{
  "type": "Feature",
  "properties": {
    "iso:country":"IT",
    "sg:address":"Corso Di Porta Nuova 1; Milano; 20121",
    "sg:city":"Milano",
    "sg:classifiers":[
        {
            "category":"Banks & Credit Unions",
            "subcategory":"Bank",
            "type":"Services"
        }
    ],
    "sg:phone":"+39 02 655 4854",
    "sg:postcode":"20121",
    "sg:province":"Milano",
    "wof:name":"Istituto Bancario, San Paolo Di Tori Spa",
    "wof:placetype":"venue"
},
  "geometry": {"coordinates":[9.191268,45.473366],"type":"Point"}
}