{
  "type": "Feature",
  "properties": {
    "iso:country":"IT",
    "sg:address":"20017 Rho",
    "sg:city":"Rho",
    "sg:orig_category":"Valvole E Apparecchiature Di Misura",
    "sg:phone":"+39 02 933331",
    "sg:postcode":"20017",
    "sg:province":"Milano",
    "wof:name":"Klinger Spa",
    "wof:placetype":"venue"
},
  "geometry": {"coordinates":[9.080031,45.52861],"type":"Point"}
}