{
  "type": "Feature",
  "properties": {
    "iso:country":"IT",
    "sg:address":"25, Via Piamarta Padre Giovanni 25021 Bagnolo Mella",
    "sg:city":"Bagnolo Mella",
    "sg:classifiers":[
        {
            "category":"Wholesale",
            "subcategory":"Machinery & Supplies",
            "type":"Manufacturing & Wholesale Goods"
        }
    ],
    "sg:phone":"+39 030 682 1391",
    "sg:postcode":"25021",
    "sg:province":"Brescia",
    "sg:tags":[
        "-",
        "agriculture",
        "equipment"
    ],
    "wof:name":"Agrorama Di Ermici A. E Pietrobelli E. S.n.c.",
    "wof:placetype":"venue"
},
  "geometry": {"coordinates":[10.222958,45.539829],"type":"Point"}
}