{
  "type": "Feature",
  "properties": {
    "iso:country":"IT",
    "sg:address":"00, Via Alessandro Volta 35030 Veggiano",
    "sg:city":"Veggiano",
    "sg:orig_category":"Miscellaneous Products",
    "sg:phone":"+39 049 900 3097",
    "sg:postcode":"35030",
    "sg:province":"Padova",
    "wof:name":"Sport Service S.a.s.",
    "wof:placetype":"venue"
},
  "geometry": {"coordinates":[11.8765888214,45.4095687866],"type":"Point"}
}