{
  "type": "Feature",
  "properties": {
    "iso:country":"IT",
    "sg:address":"17031 Albenga",
    "sg:city":"Albenga",
    "sg:orig_category":"Abbigliamento Esterno, Maglierie E Pelliccerie. Calzature, Pelletterie E Pelli",
    "sg:phone":"+39 0182 545044",
    "sg:postcode":"17031",
    "sg:province":"Savona",
    "wof:name":"American Magazines",
    "wof:placetype":"venue"
},
  "geometry": {"coordinates":[8.188495,44.058578],"type":"Point"}
}