{
  "type": "Feature",
  "properties": {
    "addr:full":"39, Via Respighi Ottorino 44100 Ferrara Ferrara Ferrara 44100",
    "addr:postcode":"44100;44100",
    "addr:street":"Via Respighi Ottorino",
    "iso:country":"IT",
    "sg:address":"39, Via Respighi Ottorino 44100 Ferrara",
    "sg:city":"Ferrara",
    "sg:classifiers":[
        {
            "category":"Shopping",
            "type":"Retail Goods"
        }
    ],
    "sg:phone":"+39 39053292892",
    "sg:postcode":"44100",
    "sg:province":"Ferrara",
    "sg:tags":[
        "finished",
        "-",
        "metallic"
    ],
    "wof:name":"Baruffaldi (s.r.l.)",
    "wof:placetype":"venue"
},
  "geometry": {"coordinates":[11.6204395294,44.8378944397],"type":"Point"}
}