{
  "type": "Feature",
  "properties": {
    "iso:country":"IT",
    "sg:address":"4, Via Ariosto Ludovico 41012 Carpi",
    "sg:city":"Carpi",
    "sg:classifiers":[
        {
            "category":"Farming",
            "subcategory":"Livestock Farm",
            "type":"Manufacturing & Wholesale Goods"
        }
    ],
    "sg:phone":"+39 39059653099",
    "sg:postcode":"41012",
    "sg:province":"Modena",
    "sg:tags":[
        "agriculture"
    ],
    "wof:name":"Allegretti",
    "wof:placetype":"venue"
},
  "geometry": {"coordinates":[10.921858,44.740463],"type":"Point"}
}