{
  "type": "Feature",
  "properties": {
    "iso:country":"IT",
    "sg:address":"21052 Busto Arsizio",
    "sg:city":"Busto Arsizio",
    "sg:orig_category":"Audiovisivi Apparecchi Ed Impianti - Produzione, Commercio E Noleggio",
    "sg:phone":"+39 0331 323089",
    "sg:postcode":"21052",
    "sg:province":"Varese",
    "wof:name":"Telesistem Sas",
    "wof:placetype":"venue"
},
  "geometry": {"coordinates":[8.862947,45.623512],"type":"Point"}
}