{
  "type": "Feature",
  "properties": {
    "iso:country":"IT",
    "sg:address":"40012 Calderara Di Reno",
    "sg:city":"Calderara di Reno",
    "sg:orig_category":"Ingranaggi",
    "sg:phone":"+39 051 726207",
    "sg:postcode":"40012",
    "sg:province":"Bologna",
    "sg:website":"http://www.molinati.com",
    "wof:name":"Molinati Orlando & C. Sas",
    "wof:placetype":"venue"
},
  "geometry": {"coordinates":[11.296104,44.543179],"type":"Point"}
}