{
  "type": "Feature",
  "properties": {
    "addr:full":"Via S. Girolamo 13 25055 Pisogne Pisogne Brescia 25055",
    "addr:housenumber":"13",
    "addr:postcode":"25055;25055",
    "addr:street":"Via S. Girolamo",
    "iso:country":"IT",
    "sg:address":"Via S. Girolamo 13 25055 Pisogne",
    "sg:city":"Pisogne",
    "sg:orig_category":"Bolt Locks",
    "sg:phone":"+39 036 48821",
    "sg:postcode":"25055",
    "sg:province":"Brescia",
    "sg:website":"www.iseoserrature.it",
    "wof:name":"Iseo Serrature Spa",
    "wof:placetype":"venue"
},
  "geometry": {"coordinates":[10.222958,45.539829],"type":"Point"}
}