{
  "type": "Feature",
  "properties": {
    "addr:full":"12, Via Repubblica 24035 Curno Curno Bergamo 24035",
    "addr:postcode":"24035;24035",
    "addr:street":"Via Repubblica",
    "iso:country":"IT",
    "sg:address":"12, Via Repubblica 24035 Curno",
    "sg:city":"Curno",
    "sg:classifiers":[
        {
            "category":"Shopping",
            "type":"Retail Goods"
        }
    ],
    "sg:phone":"+39 39035612081",
    "sg:postcode":"24035",
    "sg:province":"Bergamo",
    "sg:tags":[
        "finished",
        "-",
        "metallic"
    ],
    "wof:name":"Caliberg (s.p.a.)",
    "wof:placetype":"venue"
},
  "geometry": {"coordinates":[9.6067581177,45.6917266846],"type":"Point"}
}