{
  "type": "Feature",
  "properties": {
    "addr:full":"49, Traversa Ii Spiana' 37138 Verona Verona Verona 37138",
    "addr:housenumber":"49",
    "addr:postcode":"37138;37138",
    "addr:street":"Traversa Ii Spiana '",
    "iso:country":"IT",
    "sg:address":"49, Traversa Ii Spiana' 37138 Verona",
    "sg:city":"Verona",
    "sg:classifiers":[
        {
            "category":"Manufacturing",
            "subcategory":"Rubber & Plastics",
            "type":"Manufacturing & Wholesale Goods"
        }
    ],
    "sg:phone":"+39 045 862 1421",
    "sg:postcode":"37138",
    "sg:province":"Verona",
    "wof:name":"Il Gommista S.a.s. Di Luigi Argentino & C.",
    "wof:placetype":"venue"
},
  "geometry": {"coordinates":[10.991748,45.438366],"type":"Point"}
}