{
  "type": "Feature",
  "properties": {
    "iso:country":"IT",
    "sg:address":"20142 Milano",
    "sg:city":"Milano",
    "sg:orig_category":"Servizi Editoriali. Professionisti - Studi E Servizi Ed Associazioni Di Interesse Aziendale",
    "sg:phone":"+39 02 8951 7340",
    "sg:postcode":"20142",
    "sg:province":"Milano",
    "wof:name":"Munari Andrea",
    "wof:placetype":"venue"
},
  "geometry": {"coordinates":[9.158861,45.418152],"type":"Point"}
}