{
  "type": "Feature",
  "properties": {
    "addr:full":"65010 Spoltore Spoltore Pescara 65010",
    "addr:postcode":"65010;65010",
    "iso:country":"IT",
    "sg:address":"65010 Spoltore",
    "sg:city":"Spoltore",
    "sg:orig_category":"Abiti Da Lavoro Ed Indumenti Protettivi",
    "sg:phone":"+39 085 497 3056",
    "sg:postcode":"65010",
    "sg:province":"Pescara",
    "wof:name":"Eurosap Snc Di Pompa Enrico & Antonio",
    "wof:placetype":"venue"
},
  "geometry": {"coordinates":[14.175814,42.444458],"type":"Point"}
}