{
  "type": "Feature",
  "properties": {
    "iso:country":"IT",
    "sg:address":"00054 Fiumicino",
    "sg:city":"Fiumicino",
    "sg:orig_category":"Arredo Cucina Ed Elettrodomestici. Elettrodomestici",
    "sg:phone":"+39 06 6502 5641",
    "sg:postcode":"00054",
    "sg:province":"Roma",
    "wof:name":"Simen Srl",
    "wof:placetype":"venue"
},
  "geometry": {"coordinates":[12.223774,41.769535],"type":"Point"}
}