{
  "type": "Feature",
  "properties": {
    "iso:country":"IT",
    "sg:address":"2, V. Ferrovia - Veggia 42013 Casalgrande",
    "sg:classifiers":[
        {
            "category":"Shopping",
            "subcategory":"Clothing, Apparel, & Fashions",
            "type":"Retail Goods"
        }
    ],
    "sg:phone":"+39 0536 823360",
    "sg:postcode":"42013",
    "sg:province":"Reggio Nell'Emilia",
    "sg:tags":[
        "clothes"
    ],
    "sg:website":"http://www.paginegialle.it/maglificiomedici",
    "wof:name":"Maglificio Medici Maria Srl",
    "wof:placetype":"venue"
},
  "geometry": {"coordinates":[10.763755,44.554337],"type":"Point"}
}