{
  "type": "Feature",
  "properties": {
    "iso:country":"IT",
    "sg:address":"30, Via Toscanini Arturo 44100 Ferrara",
    "sg:city":"Ferrara",
    "sg:classifiers":[
        {
            "category":"Manufacturing",
            "subcategory":"Metals",
            "type":"Manufacturing & Wholesale Goods"
        }
    ],
    "sg:phone":"+39 39053293272",
    "sg:postcode":"44100",
    "sg:province":"Ferrara",
    "sg:tags":[
        "metallurgy",
        "metalworking"
    ],
    "wof:name":"Morelli Riccardo E Antonio S P A",
    "wof:placetype":"venue"
},
  "geometry": {"coordinates":[11.6204395294,44.8378944397],"type":"Point"}
}