{
  "type": "Feature",
  "properties": {
    "iso:country":"IT",
    "sg:address":"00192 Roma",
    "sg:city":"Roma",
    "sg:orig_category":"Abbigliamento Esterno, Maglierie E Pelliccerie. Shopping",
    "sg:phone":"+39 06 321 8254",
    "sg:postcode":"00192",
    "sg:province":"Roma",
    "wof:name":"Stile Di Sara",
    "wof:placetype":"venue"
},
  "geometry": {"coordinates":[12.470063,41.911472],"type":"Point"}
}