{
  "type": "Feature",
  "properties": {
    "addr:full":"07046 Porto Torres Cala reale Sassari 07046",
    "addr:housenumber":"07046",
    "addr:postcode":"07046",
    "addr:street":"Porto Torres",
    "iso:country":"IT",
    "sg:address":"07046 Porto Torres",
    "sg:city":"Cala reale",
    "sg:orig_category":"Pubblica Amministrazione",
    "sg:phone":"+39 079 409408",
    "sg:postcode":"07046",
    "sg:province":"Sassari",
    "wof:name":"Comando Carabinieri",
    "wof:placetype":"venue"
},
  "geometry": {"coordinates":[8.3417005539,40.8283729553],"type":"Point"}
}