{
  "type": "Feature",
  "properties": {
    "addr:full":"Regione Pietra Fornaci 12060 Novello Novello Cuneo 12060",
    "addr:postcode":"12060;12060",
    "addr:street":"Regione Pietra Fornaci",
    "iso:country":"IT",
    "sg:address":"Regione Pietra Fornaci 12060 Novello",
    "sg:city":"Novello",
    "sg:classifiers":[
        {
            "category":"Manufacturing",
            "subcategory":"Metals",
            "type":"Manufacturing & Wholesale Goods"
        }
    ],
    "sg:phone":"+39 0173 792132",
    "sg:postcode":"12060",
    "sg:province":"Cuneo",
    "sg:tags":[
        "metallurgy",
        "metalworking"
    ],
    "wof:name":"Fissore Domenico (s.r.l.)",
    "wof:placetype":"venue"
},
  "geometry": {"coordinates":[7.5471105576,44.38879776],"type":"Point"}
}