{
  "type": "Feature",
  "properties": {
    "iso:country":"IT",
    "sg:address":"20146 Milano",
    "sg:city":"Milano",
    "sg:orig_category":"Elettrotecnica Industriale, Prodotti E Apparecchiature",
    "sg:phone":"+39 02 422 4450",
    "sg:postcode":"20146",
    "sg:province":"Milano",
    "sg:website":"http://www.giansoldati.it",
    "wof:name":"Giansoldati Gilberto",
    "wof:placetype":"venue"
},
  "geometry": {"coordinates":[9.142998,45.44894],"type":"Point"}
}