{
  "type": "Feature",
  "properties": {
    "addr:full":"Localita' Antiche Saline 57037 Portoferraio Portoferraio Livorno 57037",
    "addr:postcode":"57037;57037",
    "addr:street":"Localita ' Antiche",
    "iso:country":"IT",
    "sg:address":"Localita' Antiche Saline 57037 Portoferraio",
    "sg:city":"Portoferraio",
    "sg:classifiers":[
        {
            "category":"Bars & Pubs",
            "subcategory":"Nightclub",
            "type":"Food & Drink"
        }
    ],
    "sg:phone":"+39 0565 917142",
    "sg:postcode":"57037",
    "sg:province":"Livorno",
    "sg:tags":[
        "cake",
        "bread"
    ],
    "wof:name":"Panelba Gestioni Srl",
    "wof:placetype":"venue"
},
  "geometry": {"coordinates":[10.3117,42.805008],"type":"Point"}
}