{
  "type": "Feature",
  "properties": {
    "iso:country":"IT",
    "sg:address":"12084 Mondovi'",
    "sg:orig_category":"Prodotti E Manufatti In Materie Plastiche",
    "sg:phone":"+39 0174 44401",
    "sg:postcode":"12084",
    "sg:province":"Cuneo",
    "wof:name":"Balbo Gian Piero",
    "wof:placetype":"venue"
},
  "geometry": {"coordinates":[7.697078228,44.3763809204],"type":"Point"}
}