{
  "type": "Feature",
  "properties": {
    "iso:country":"IT",
    "sg:address":"20126 Milano",
    "sg:city":"Milano",
    "sg:orig_category":"Servizi Ausiliari Dei Mezzi Di Trasporto",
    "sg:phone":"+39 02 257 4112",
    "sg:postcode":"20126",
    "sg:province":"Milano",
    "wof:name":"Schirone Vito",
    "wof:placetype":"venue"
},
  "geometry": {"coordinates":[9.225767,45.516582],"type":"Point"}
}