{
  "type": "Feature",
  "properties": {
    "addr:full":"66100 Chieti Chieti Chieti 66100",
    "addr:postcode":"66100;66100",
    "iso:country":"IT",
    "sg:address":"66100 Chieti",
    "sg:city":"Chieti",
    "sg:orig_category":"Prodotti E Manufatti In Materie Plastiche",
    "sg:phone":"+39 0871 540246",
    "sg:postcode":"66100",
    "sg:province":"Chieti",
    "wof:name":"Mag.ma. Srl",
    "wof:placetype":"venue"
},
  "geometry": {"coordinates":[14.1582250595,42.3614120483],"type":"Point"}
}