{
  "type": "Feature",
  "properties": {
    "addr:full":"10078 Venaria Torino 10078",
    "addr:postcode":"10078;10078",
    "iso:country":"IT",
    "sg:address":"10078 Venaria",
    "sg:orig_category":"Minuterie Metalliche E Ferramenta. Ricambi E Componenti Dei Mezzi Di Trasporto",
    "sg:phone":"+39 011 220 1766",
    "sg:postcode":"10078",
    "sg:province":"Torino",
    "wof:name":"Mollebalestra S.p.a.",
    "wof:placetype":"venue"
},
  "geometry": {"coordinates":[7.6533989906,45.1158828735],"type":"Point"}
}