{
  "type": "Feature",
  "properties": {
    "iso:country":"IT",
    "sg:address":"20132 Milano",
    "sg:city":"Milano",
    "sg:orig_category":"Macchine E Forniture Per Arredamento E Industria Del Legno. Macchine Utensili E Impianti",
    "sg:phone":"+39 02 256 3897",
    "sg:postcode":"20132",
    "sg:province":"Milano",
    "wof:name":"Isap Srl",
    "wof:placetype":"venue"
},
  "geometry": {"coordinates":[9.243441,45.502117],"type":"Point"}
}