{
  "type": "Feature",
  "properties": {
    "iso:country":"IT",
    "sg:address":"80147 Napoli",
    "sg:city":"Napoli",
    "sg:orig_category":"Bevande, Vini E Liquori",
    "sg:phone":"+39 081 255 1955",
    "sg:postcode":"80147",
    "sg:province":"Napoli",
    "wof:name":"Dock Distribuzione Sas",
    "wof:placetype":"venue"
},
  "geometry": {"coordinates":[15.170838,41.089676],"type":"Point"}
}