{
  "type": "Feature",
  "properties": {
    "iso:country":"IT",
    "sg:address":"80141 Napoli",
    "sg:city":"Napoli",
    "sg:orig_category":"Calzature, Pelletterie E Pelli",
    "sg:phone":"+39 081 599 1385",
    "sg:postcode":"80141",
    "sg:province":"Napoli",
    "wof:name":"Esposito Giuseppe",
    "wof:placetype":"venue"
},
  "geometry": {"coordinates":[14.263508,40.871174],"type":"Point"}
}