{
  "type": "Feature",
  "properties": {
    "iso:country":"IT",
    "sg:address":"50125 Firenze",
    "sg:city":"Firenze",
    "sg:orig_category":"Macchine E Forniture Per Ecologia E Smaltimento Rifiuti",
    "sg:phone":"+39 055 234 6899",
    "sg:postcode":"50125",
    "sg:province":"Firenze",
    "sg:website":"http://chemieco.com",
    "wof:name":"Chemieco Srl",
    "wof:placetype":"venue"
},
  "geometry": {"coordinates":[11.261018,43.759022],"type":"Point"}
}