{
  "type": "Feature",
  "properties": {
    "iso:country":"IT",
    "sg:address":"90040 Capaci",
    "sg:city":"Capaci",
    "sg:classifiers":[
        {
            "category":"Shopping",
            "subcategory":"Beauty & Cosmetics",
            "type":"Retail Goods"
        }
    ],
    "sg:phone":"+39 091 869 7973",
    "sg:postcode":"90040",
    "sg:province":"Palermo",
    "sg:tags":[
        "salons",
        "activities",
        "supply",
        "commercial",
        "equipment",
        "artisan",
        "supplies"
    ],
    "wof:name":"Ri.vi. Picc. Soc. Coop. Arl",
    "wof:placetype":"venue"
},
  "geometry": {"coordinates":[13.238652,38.173302],"type":"Point"}
}