{
  "type": "Feature",
  "properties": {
    "addr:full":"20123 Milano Milano Milano 20123",
    "addr:postcode":"20123;20123",
    "iso:country":"IT",
    "sg:address":"20123 Milano",
    "sg:city":"Milano",
    "sg:orig_category":"Hobbistica",
    "sg:phone":"+39 02 805 6493",
    "sg:postcode":"20123",
    "sg:province":"Milano",
    "wof:name":"Di Loreto Antonio",
    "wof:placetype":"venue"
},
  "geometry": {"coordinates":[9.182626,45.465805],"type":"Point"}
}