{
  "type": "Feature",
  "properties": {
    "iso:country":"IT",
    "sg:address":"24025 Gazzaniga",
    "sg:city":"Gazzaniga",
    "sg:orig_category":"Apparecchiature Elettroniche",
    "sg:phone":"+39 035 712091",
    "sg:postcode":"24025",
    "sg:province":"Bergamo",
    "sg:website":"http://www.acmrs.com",
    "wof:name":"M.r.s. Srl",
    "wof:placetype":"venue"
},
  "geometry": {"coordinates":[9.824736,45.789436],"type":"Point"}
}