{
  "type": "Feature",
  "properties": {
    "iso:country":"IT",
    "sg:address":"73100 Lecce",
    "sg:city":"Lecce",
    "sg:orig_category":"Pubblicita', Marketing E Comunicazione",
    "sg:phone":"+39 0832 398268",
    "sg:postcode":"73100",
    "sg:province":"Lecce",
    "wof:name":"S.al.com. Piccola Soc.coop.r.l.",
    "wof:placetype":"venue"
},
  "geometry": {"coordinates":[18.1790161133,40.3636741638],"type":"Point"}
}