{
  "type": "Feature",
  "properties": {
    "iso:country":"IT",
    "sg:address":"20127 Milano",
    "sg:city":"Milano",
    "sg:classifiers":[
        {
            "category":"Professional",
            "subcategory":"Management & Consulting",
            "type":"Services"
        }
    ],
    "sg:phone":"+39 02 282 7402",
    "sg:postcode":"20127",
    "sg:province":"Milano",
    "sg:tags":[
        "industrial",
        "technical",
        "consultant",
        "consultants",
        "administrative",
        "appraiser"
    ],
    "sg:website":"http://www.enproject.it",
    "wof:name":"En Project Srl",
    "wof:placetype":"venue"
},
  "geometry": {"coordinates":[9.217259,45.487762],"type":"Point"}
}