{
  "type": "Feature",
  "properties": {
    "iso:country":"IT",
    "sg:address":"Via Nazionale 28; Codisotto",
    "sg:classifiers":[
        {
            "category":"Banks & Credit Unions",
            "subcategory":"Bank",
            "type":"Services"
        }
    ],
    "sg:phone":"+39 0522 976555",
    "wof:name":"Banca Agricola Mantovana Scarl",
    "wof:placetype":"venue"
},
  "geometry": {"coordinates":[10.728652,44.989811],"type":"Point"}
}