{
  "type": "Feature",
  "properties": {
    "iso:country":"IT",
    "sg:address":"35129 Padova",
    "sg:city":"Padova",
    "sg:orig_category":"Cartotecnica E Servizi. Forniture Per Uffici",
    "sg:phone":"+39 049 864 2110",
    "sg:postcode":"35129",
    "sg:province":"Padova",
    "wof:name":"Letter Service Snc",
    "wof:placetype":"venue"
},
  "geometry": {"coordinates":[11.911836,45.428856],"type":"Point"}
}