{
  "type": "Feature",
  "properties": {
    "iso:country":"IT",
    "sg:address":"60015 Falconara Marittima",
    "sg:city":"Falconara Marittima",
    "sg:orig_category":"Banche E Servizi Finanziari",
    "sg:phone":"+39 071 91691",
    "sg:postcode":"60015",
    "sg:province":"Ancona",
    "sg:website":"http://www.falconara.bcc.it",
    "wof:name":"Banca Di Credito Cooperativo Di Falconara Marittima",
    "wof:placetype":"venue"
},
  "geometry": {"coordinates":[13.392738,43.631657],"type":"Point"}
}