{
  "type": "Feature",
  "properties": {
    "iso:country":"IT",
    "sg:address":"Via G. Di Vittorio 29 40057 Granarolo Dell'emilia",
    "sg:classifiers":[
        {
            "category":"Building & Trades",
            "subcategory":"Construction",
            "type":"Services"
        }
    ],
    "sg:phone":"+39 051 765488",
    "sg:postcode":"40057",
    "sg:province":"Bologna",
    "sg:tags":[
        "carpenter's",
        "work",
        "supraregional"
    ],
    "sg:website":"www.molinariarredi.it",
    "wof:name":"Molinari Srl",
    "wof:placetype":"venue"
},
  "geometry": {"coordinates":[11.390239,44.544342],"type":"Point"}
}