{
  "type": "Feature",
  "properties": {
    "addr:full":"41, Via Proventa Ai Pioppi 48018 Faenza Faenza Ravenna 48018",
    "addr:postcode":"48018;48018",
    "addr:street":"Via Proventa Ai Pioppi",
    "iso:country":"IT",
    "sg:address":"41, Via Proventa Ai Pioppi 48018 Faenza",
    "sg:city":"Faenza",
    "sg:classifiers":[
        {
            "category":"Wholesale",
            "subcategory":"Machinery & Supplies",
            "type":"Manufacturing & Wholesale Goods"
        }
    ],
    "sg:phone":"+39 39054629050",
    "sg:postcode":"48018",
    "sg:province":"Ravenna",
    "sg:tags":[
        "-",
        "agriculture",
        "equipment"
    ],
    "wof:name":"Falc (s.r.l.)",
    "wof:placetype":"venue"
},
  "geometry": {"coordinates":[12.196571,44.41573],"type":"Point"}
}