{
  "type": "Feature",
  "properties": {
    "addr:full":"10098 Rivoli Rivoli Torino 10098",
    "addr:postcode":"10098;10098",
    "iso:country":"IT",
    "sg:address":"10098 Rivoli",
    "sg:city":"Rivoli",
    "sg:orig_category":"Scuole E Servizi Scolastici. Centri Di Estetica E Cosmesi E Servizi. Ricerca, Selezione E Formazione Del Personale",
    "sg:phone":"+39 011 953 5139",
    "sg:postcode":"10098",
    "sg:province":"Torino",
    "wof:name":"C.f.p.e Sirena Snc",
    "wof:placetype":"venue"
},
  "geometry": {"coordinates":[7.519322,45.067471],"type":"Point"}
}