{
  "type": "Feature",
  "properties": {
    "addr:full":"20098 San Giuliano Milanese San Giuliano Milanese Milano 20098",
    "addr:housenumber":"20098",
    "addr:postcode":"20098",
    "addr:street":"San",
    "iso:country":"IT",
    "sg:address":"20098 San Giuliano Milanese",
    "sg:city":"San Giuliano Milanese",
    "sg:orig_category":"Argentatura, Doratura, Platinatura E Rodiatura",
    "sg:phone":"+39 02 988 1026",
    "sg:postcode":"20098",
    "sg:province":"Milano",
    "wof:name":"P.f.g. Snc",
    "wof:placetype":"venue"
},
  "geometry": {"coordinates":[9.251337,45.401028],"type":"Point"}
}