{
  "type": "Feature",
  "properties": {
    "addr:full":"38045 Mochena Trento 38045",
    "addr:postcode":"38045;38045",
    "addr:street":"Mochena Trento",
    "iso:country":"IT",
    "sg:address":"38045 Mochena",
    "sg:orig_category":"Forniture Per Agricoltura E Zootecnia. Animali Domestici",
    "sg:phone":"+39 0461 858541",
    "sg:postcode":"38045",
    "sg:province":"Trento",
    "wof:name":"Molino Pontalti Di Pontalti Claudio & C. S.a.s.",
    "wof:placetype":"venue"
},
  "geometry": {"coordinates":[11.1930198669,46.0839080811],"type":"Point"}
}