{
  "type": "Feature",
  "properties": {
    "addr:full":"40050 Argelato Argelato Bologna 40050",
    "addr:postcode":"40050;40050",
    "iso:country":"IT",
    "sg:address":"40050 Argelato",
    "sg:city":"Argelato",
    "sg:orig_category":"Apparecchiature Ed Attrezzature Meccaniche",
    "sg:phone":"+39 051 862010",
    "sg:postcode":"40050",
    "sg:province":"Bologna",
    "sg:website":"http://www.stima.it",
    "wof:name":"Stima Srl",
    "wof:placetype":"venue"
},
  "geometry": {"coordinates":[11.367825,44.609711],"type":"Point"}
}