{
  "type": "Feature",
  "properties": {
    "iso:country":"IT",
    "sg:address":"Via Fornaci 61 25040 Artogne",
    "sg:city":"Artogne",
    "sg:classifiers":[
        {
            "category":"Home & Garden",
            "subcategory":"Carpets & Floor Coverings",
            "type":"Retail Goods"
        }
    ],
    "sg:phone":"+39 036 459 8841",
    "sg:postcode":"25040",
    "sg:province":"Brescia",
    "sg:tags":[
        "wall",
        "interior",
        "decoration"
    ],
    "sg:website":"www.evoluzione2000.com",
    "wof:name":"Evoluzione 2000 Spa",
    "wof:placetype":"venue"
},
  "geometry": {"coordinates":[10.163315,45.859543],"type":"Point"}
}