{
  "type": "Feature",
  "properties": {
    "addr:full":"Via Formenti 1; Seregno; 20038 Seregno Milano 20038",
    "addr:housenumber":"1",
    "addr:postcode":"20038;20038",
    "addr:street":"Via Formenti",
    "iso:country":"IT",
    "sg:address":"Via Formenti 1; Seregno; 20038",
    "sg:city":"Seregno",
    "sg:classifiers":[
        {
            "category":"Banks & Credit Unions",
            "subcategory":"Bank",
            "type":"Services"
        }
    ],
    "sg:phone":"+39 036 223 8034",
    "sg:postcode":"20038",
    "sg:province":"Milano",
    "wof:name":"Banca Popolare Di Sondrio Scarl",
    "wof:placetype":"venue"
},
  "geometry": {"coordinates":[9.205687,45.652431],"type":"Point"}
}