{
  "type": "Feature",
  "properties": {
    "iso:country":"IT",
    "sg:address":"48, Via Padana Inferiore 10023 Chieri",
    "sg:city":"Chieri",
    "sg:classifiers":[
        {
            "category":"Shopping",
            "subcategory":"Crafts & Fabrics",
            "type":"Retail Goods"
        }
    ],
    "sg:phone":"+39 011 942 7904",
    "sg:postcode":"10023",
    "sg:province":"Torino",
    "wof:name":"Tessitura Enzo Stella Di Stella Vincenzo & C. Sas",
    "wof:placetype":"venue"
},
  "geometry": {"coordinates":[7.862912178,44.9928474426],"type":"Point"}
}