{
  "type": "Feature",
  "properties": {
    "iso:country":"IT",
    "sg:address":"84015 Nocera Superiore",
    "sg:city":"Nocera Superiore",
    "sg:orig_category":"Prodotti Chimici Di Base",
    "sg:phone":"+39 081 517 9195",
    "sg:postcode":"84015",
    "sg:province":"Salerno",
    "wof:name":"Tecnoimball Sas Di A. Migliorini & C.",
    "wof:placetype":"venue"
},
  "geometry": {"coordinates":[14.6762733459,40.7340698242],"type":"Point"}
}