{
  "type": "Feature",
  "properties": {
    "addr:full":"44100 Ferrara Ferrara Ferrara 44100",
    "addr:postcode":"44100;44100",
    "iso:country":"IT",
    "sg:address":"44100 Ferrara",
    "sg:city":"Ferrara",
    "sg:orig_category":"Cartotecnica E Servizi. Articoli Per Imballaggio E Confezionamento",
    "sg:phone":"+39 0532 462212",
    "sg:postcode":"44100",
    "sg:province":"Ferrara",
    "wof:name":"I.l.p.a.c. Srl",
    "wof:placetype":"venue"
},
  "geometry": {"coordinates":[11.603573,44.870842],"type":"Point"}
}