{
  "type": "Feature",
  "properties": {
    "addr:full":"Contrada Gidora 87040 Luzzi Luzzi Cosenza 87040",
    "addr:postcode":"87040;87040",
    "addr:street":"Contrada Gidora",
    "iso:country":"IT",
    "sg:address":"Contrada Gidora 87040 Luzzi",
    "sg:city":"Luzzi",
    "sg:classifiers":[
        {
            "category":"Manufacturing",
            "subcategory":"Rubber & Plastics",
            "type":"Manufacturing & Wholesale Goods"
        }
    ],
    "sg:phone":"+39 0984 543855",
    "sg:postcode":"87040",
    "sg:province":"Cosenza",
    "wof:name":"Profilati Plastici (s.r.l.)",
    "wof:placetype":"venue"
},
  "geometry": {"coordinates":[16.2665176392,39.4410934448],"type":"Point"}
}