{
  "type": "Feature",
  "properties": {
    "iso:country":"IT",
    "sg:address":"55012 Capannori",
    "sg:city":"Capannori",
    "sg:orig_category":"Macchine, Impianti Ed Attrezzature Per Abbigliamento E Pelletterie",
    "sg:phone":"+39 0583 927372",
    "sg:postcode":"55012",
    "sg:province":"Lucca",
    "sg:website":"http://www.tredf.com",
    "wof:name":"Zoccolificio 3df",
    "wof:placetype":"venue"
},
  "geometry": {"coordinates":[10.596397,43.885216],"type":"Point"}
}