{
  "type": "Feature",
  "properties": {
    "iso:country":"IT",
    "sg:address":"00043 Ciampino",
    "sg:city":"Ciampino",
    "sg:orig_category":"Climatizzazione E Condizionamento, Apparecchiature E Servizi. Elettrodomestici",
    "sg:phone":"+39 06 7932 0078",
    "sg:postcode":"00043",
    "sg:province":"Roma",
    "wof:name":"E.v. Condizionamento (s.r.l.)",
    "wof:placetype":"venue"
},
  "geometry": {"coordinates":[12.589404,41.820904],"type":"Point"}
}