{
  "type": "Feature",
  "properties": {
    "addr:full":"28040 Borgo Ticino Borgo Ticino Novara 28040",
    "addr:postcode":"28040;28040",
    "iso:country":"IT",
    "sg:address":"28040 Borgo Ticino",
    "sg:city":"Borgo Ticino",
    "sg:orig_category":"Carni Fresche E Congelate - Lavorazione E Commercio",
    "sg:phone":"+39 0321 908036",
    "sg:postcode":"28040",
    "sg:province":"Novara",
    "sg:website":"http://www.fratellisibilia.com",
    "wof:name":"Sibilia Fratelli Srl",
    "wof:placetype":"venue"
},
  "geometry": {"coordinates":[8.60938,45.692699],"type":"Point"}
}