{
  "type": "Feature",
  "properties": {
    "addr:full":"56125 Pisa Pisa Pisa 56125",
    "addr:postcode":"56125;56125",
    "iso:country":"IT",
    "sg:address":"56125 Pisa",
    "sg:city":"Pisa",
    "sg:classifiers":[
        {
            "category":"Professional",
            "subcategory":"Management & Consulting",
            "type":"Services"
        }
    ],
    "sg:phone":"+39 050 49372",
    "sg:postcode":"56125",
    "sg:province":"Pisa",
    "sg:tags":[
        "building",
        "industrial",
        "business",
        "consultants",
        "technical",
        "worker",
        "industry",
        "-",
        "civil",
        "consultant",
        "works"
    ],
    "sg:website":"http://www.studiobaldini.it",
    "wof:name":"Studio Baldini Srl",
    "wof:placetype":"venue"
},
  "geometry": {"coordinates":[10.399333,43.71022],"type":"Point"}
}