{
  "type": "Feature",
  "properties": {
    "iso:country":"IT",
    "sg:address":"16149 Genova",
    "sg:city":"Genova",
    "sg:orig_category":"Motori Ed Organi Di Trasmissione. Ricambi E Componenti Dei Mezzi Di Trasporto",
    "sg:postcode":"16149",
    "sg:province":"Genova",
    "wof:name":"Italdiesel Genova (s.r.l.)",
    "wof:placetype":"venue"
},
  "geometry": {"coordinates":[8.9003343582,44.4122619629],"type":"Point"}
}