{
  "type": "Feature",
  "properties": {
    "iso:country":"IT",
    "sg:address":"Via Don Ettore Gaia 19 10043 Orbassano",
    "sg:city":"Orbassano",
    "sg:classifiers":[
        {
            "category":"Transit Center",
            "subcategory":"Freight",
            "type":"Transportation"
        }
    ],
    "sg:phone":"+39 011 903 5885",
    "sg:postcode":"10043",
    "sg:province":"Torino",
    "sg:tags":[
        "alloy",
        "light",
        "tanks",
        "boiler",
        "apparatus"
    ],
    "wof:name":"Prato Angelo E C. Srl",
    "wof:placetype":"venue"
},
  "geometry": {"coordinates":[7.565155,45.015438],"type":"Point"}
}