{
  "type": "Feature",
  "properties": {
    "iso:country":"IT",
    "sg:address":"37036 San Martino Buon Albergo",
    "sg:city":"San Martino Buon Albergo",
    "sg:classifiers":[
        {
            "category":"Manufacturing",
            "subcategory":"Tools & Machinery",
            "type":"Manufacturing & Wholesale Goods"
        }
    ],
    "sg:phone":"+39 045 994644",
    "sg:postcode":"37036",
    "sg:province":"Verona",
    "sg:tags":[
        "machining",
        "mechanical"
    ],
    "wof:name":"Gasparella Giuseppe",
    "wof:placetype":"venue"
},
  "geometry": {"coordinates":[11.11,45.420105],"type":"Point"}
}