{
  "type": "Feature",
  "properties": {
    "iso:country":"IT",
    "sg:address":"Corso Garibaldi 48; Melito Di Porto Salvo; 89063",
    "sg:city":"Melito di Porto Salvo",
    "sg:classifiers":[
        {
            "category":"Banks & Credit Unions",
            "subcategory":"Bank",
            "type":"Services"
        }
    ],
    "sg:phone":"+39 0965 771791",
    "sg:postcode":"89063",
    "sg:province":"Reggio Di Calabria",
    "wof:name":"Banco Di Napoli Spa",
    "wof:placetype":"venue"
},
  "geometry": {"coordinates":[15.781119,37.918949],"type":"Point"}
}