{
  "type": "Feature",
  "properties": {
    "iso:country":"IT",
    "sg:address":"11, Via Tomba 48022 Lugo",
    "sg:city":"Lugo",
    "sg:classifiers":[
        {
            "category":"Shopping",
            "subcategory":"Crafts & Fabrics",
            "type":"Retail Goods"
        }
    ],
    "sg:phone":"+39 0545 900714",
    "sg:postcode":"48022",
    "sg:province":"Ravenna",
    "sg:tags":[
        "linen"
    ],
    "wof:name":"Minardi Commerciale Srl",
    "wof:placetype":"venue"
},
  "geometry": {"coordinates":[11.9100322723,44.4328117371],"type":"Point"}
}