{
  "type": "Feature",
  "properties": {
    "iso:country":"IT",
    "sg:address":"40134 Bologna",
    "sg:city":"Bologna",
    "sg:orig_category":"Ospedali E Servizi Sanitari",
    "sg:phone":"+39 051 615 3716",
    "sg:postcode":"40134",
    "sg:province":"Bologna",
    "wof:name":"Maitri Sas Di Fornari Vittoria E C.",
    "wof:placetype":"venue"
},
  "geometry": {"coordinates":[11.3176240921,44.4957237244],"type":"Point"}
}