{
  "type": "Feature",
  "properties": {
    "iso:country":"IT",
    "sg:address":"33, Via Pioppi 20090 Opera",
    "sg:city":"Opera",
    "sg:classifiers":[
        {
            "category":"Shopping",
            "subcategory":"Computers & Home Electronics",
            "type":"Retail Goods"
        }
    ],
    "sg:phone":"+39 39025768071",
    "sg:postcode":"20090",
    "sg:province":"Milano",
    "sg:tags":[
        "electronic",
        "electrical",
        "equipment"
    ],
    "wof:name":"Bras Internazionale (s.p.a.)",
    "wof:placetype":"venue"
},
  "geometry": {"coordinates":[9.224173,45.376759],"type":"Point"}
}