{
  "type": "Feature",
  "properties": {
    "addr:full":"1, Via Monte Ortigara 24121 Bergamo Bergamo Bergamo 24121",
    "addr:postcode":"24121;24121",
    "addr:street":"Via Monte Ortigara",
    "iso:country":"IT",
    "sg:address":"1, Via Monte Ortigara 24121 Bergamo",
    "sg:city":"Bergamo",
    "sg:classifiers":[
        {
            "category":"Professional",
            "subcategory":"Advertising",
            "type":"Services"
        }
    ],
    "sg:phone":"+39 39035233350",
    "sg:postcode":"24121",
    "sg:province":"Bergamo",
    "sg:tags":[
        "communication",
        "medium"
    ],
    "wof:name":"Multi-consult (s.r.l.)",
    "wof:placetype":"venue"
},
  "geometry": {"coordinates":[9.667985,45.6992],"type":"Point"}
}