{
  "type": "Feature",
  "properties": {
    "iso:country":"IT",
    "sg:address":"Via Scorrano 5; Maglie; 73024",
    "sg:city":"Maglie",
    "sg:classifiers":[
        {
            "category":"Banks & Credit Unions",
            "subcategory":"Bank",
            "type":"Services"
        }
    ],
    "sg:phone":"+39 0836 21031",
    "sg:postcode":"73024",
    "sg:province":"Lecce",
    "wof:name":"Banco Di Napoli Spa",
    "wof:placetype":"venue"
},
  "geometry": {"coordinates":[18.299772,40.111187],"type":"Point"}
}