{
  "type": "Feature",
  "properties": {
    "addr:full":"46010 Curtatone Curtatone Mantova 46010",
    "addr:postcode":"46010;46010",
    "iso:country":"IT",
    "sg:address":"46010 Curtatone",
    "sg:city":"Curtatone",
    "sg:orig_category":"Forniture Per Attivita' Industriali",
    "sg:phone":"+39 0376 478871",
    "sg:postcode":"46010",
    "sg:province":"Mantova",
    "wof:name":"Ferramenta 2000 Spa",
    "wof:placetype":"venue"
},
  "geometry": {"coordinates":[10.7726736069,45.1307563782],"type":"Point"}
}