{
  "type": "Feature",
  "properties": {
    "iso:country":"IT",
    "sg:address":"Corso Garibaldi 1, 48018 Faenza, Ra",
    "sg:city":"Faenza",
    "sg:classifiers":[
        {
            "category":"Banks & Credit Unions",
            "subcategory":"Bank",
            "type":"Services"
        }
    ],
    "sg:postcode":"48018",
    "sg:province":"Ravenna",
    "wof:name":"Banca Del Monte E Cassa Di Risparmio Faenza Spa",
    "wof:placetype":"venue"
},
  "geometry": {"coordinates":[11.906044,44.414391],"type":"Point"}
}