{
  "type": "Feature",
  "properties": {
    "iso:country":"IT",
    "sg:address":"Piazza Cantore 2; Ala; 38061",
    "sg:city":"Ala",
    "sg:classifiers":[
        {
            "category":"Banks & Credit Unions",
            "subcategory":"Bank",
            "type":"Services"
        }
    ],
    "sg:phone":"+39 0464 671068",
    "sg:postcode":"38061",
    "sg:province":"Trento",
    "wof:name":"Banca Di Trento, E Bolzano Spa",
    "wof:placetype":"venue"
},
  "geometry": {"coordinates":[11.005389,45.75779],"type":"Point"}
}