{
  "type": "Feature",
  "properties": {
    "iso:country":"IT",
    "sg:address":"Via La Cona 1/c; Paliano",
    "sg:classifiers":[
        {
            "category":"Banks & Credit Unions",
            "subcategory":"Bank",
            "type":"Services"
        }
    ],
    "sg:phone":"+39 0775 578117",
    "wof:name":"Banca Di Roma",
    "wof:placetype":"venue"
},
  "geometry": {"coordinates":[13.060688,41.803837],"type":"Point"}
}