{
  "type": "Feature",
  "properties": {
    "iso:country":"IT",
    "sg:address":"10, Via Einaudi Luigi 45011 Adria",
    "sg:city":"Adria",
    "sg:classifiers":[
        {
            "category":"Home & Garden",
            "subcategory":"Home Furnishings",
            "type":"Retail Goods"
        }
    ],
    "sg:phone":"+39 39042646533",
    "sg:postcode":"45011",
    "sg:province":"Rovigo",
    "sg:tags":[
        "household"
    ],
    "wof:name":"M.m.",
    "wof:placetype":"venue"
},
  "geometry": {"coordinates":[11.789797,45.070736],"type":"Point"}
}