{
  "type": "Feature",
  "properties": {
    "iso:country":"IT",
    "sg:address":"62012 Civitanova Marche",
    "sg:city":"Civitanova Marche",
    "sg:classifiers":[
        {
            "category":"Shopping",
            "subcategory":"Clothing, Apparel, & Fashions",
            "type":"Retail Goods"
        }
    ],
    "sg:phone":"+39 0733 800111",
    "sg:postcode":"62012",
    "sg:province":"Macerata",
    "sg:tags":[
        "activities",
        "goods",
        "supply",
        "leather",
        "commercial",
        "artisan",
        "supplies",
        "clothing"
    ],
    "sg:website":"http://www.eurosuole.com",
    "wof:name":"Eurosuole Spa",
    "wof:placetype":"venue"
},
  "geometry": {"coordinates":[13.694167,43.318214],"type":"Point"}
}