{
  "type": "Feature",
  "properties": {
    "iso:country":"IT",
    "sg:address":"34071 Cormons",
    "sg:city":"Cormons",
    "sg:orig_category":"Prodotti Vari In Metallo. Articoli Per Imballaggio E Confezionamento",
    "sg:phone":"+39 0481 639290",
    "sg:postcode":"34071",
    "sg:province":"Gorizia",
    "wof:name":"Eurocalor S.r.l.",
    "wof:placetype":"venue"
},
  "geometry": {"coordinates":[13.460981369,45.9491043091],"type":"Point"}
}