{
  "type": "Feature",
  "properties": {
    "addr:full":"27/29, Via Nenni Pietro 10036 Settimo Torinese Settimo Torinese Torino 10036",
    "addr:housenumber":"27 / 29",
    "addr:postcode":"10036;10036",
    "addr:street":"Via Nenni Pietro",
    "iso:country":"IT",
    "sg:address":"27/29, Via Nenni Pietro 10036 Settimo Torinese",
    "sg:city":"Settimo Torinese",
    "sg:classifiers":[
        {
            "category":"Manufacturing",
            "subcategory":"Rubber & Plastics",
            "type":"Manufacturing & Wholesale Goods"
        }
    ],
    "sg:phone":"+39 011 800 2238",
    "sg:postcode":"10036",
    "sg:province":"Torino",
    "wof:name":"Comset (s.p.a.)",
    "wof:placetype":"venue"
},
  "geometry": {"coordinates":[7.7542719841,45.1523170471],"type":"Point"}
}