{
  "type": "Feature",
  "properties": {
    "iso:country":"IT",
    "sg:address":"40024 Castel San Pietro Terme",
    "sg:city":"Castel San Pietro Terme",
    "sg:orig_category":"Utensili Meccanici E Materiali",
    "sg:phone":"+39 051 943649",
    "sg:postcode":"40024",
    "sg:province":"Bologna",
    "wof:name":"Rifimpress Srl",
    "wof:placetype":"venue"
},
  "geometry": {"coordinates":[11.547541,44.395576],"type":"Point"}
}