{
  "type": "Feature",
  "properties": {
    "iso:country":"IT",
    "sg:address":"1, Via Francavilla 72024 Oria",
    "sg:city":"Oria",
    "sg:classifiers":[
        {
            "category":"Utilities",
            "subcategory":"Electric",
            "type":"Services"
        }
    ],
    "sg:phone":"+39 0831 845932",
    "sg:postcode":"72024",
    "sg:province":"Brindisi",
    "sg:tags":[
        "component",
        "electronic"
    ],
    "wof:name":"Mec Energia S.r.l.",
    "wof:placetype":"venue"
},
  "geometry": {"coordinates":[17.716543,40.551189],"type":"Point"}
}