{
  "type": "Feature",
  "properties": {
    "iso:country":"IT",
    "sg:address":"20135 Milano",
    "sg:city":"Milano",
    "sg:classifiers":[
        {
            "category":"Restaurant",
            "type":"Food & Drink"
        }
    ],
    "sg:phone":"+39 02 5519 4974",
    "sg:postcode":"20135",
    "sg:province":"Milano",
    "sg:tags":[
        "auxiliary",
        "entertainment",
        "premises",
        "related",
        "catering",
        "similar",
        "public",
        "restaurants"
    ],
    "sg:website":"http://www.cerroardente.it",
    "wof:name":"Cerro Ardente",
    "wof:placetype":"venue"
},
  "geometry": {"coordinates":[9.203932,45.454742],"type":"Point"}
}