{
  "type": "Feature",
  "properties": {
    "iso:country":"IT",
    "sg:address":"9, V. Del Lavoro 63039 San Benedetto Del Tronto",
    "sg:city":"San Benedetto del Tronto",
    "sg:classifiers":[
        {
            "category":"Wholesale",
            "subcategory":"Medical Equipment & Supplies",
            "type":"Manufacturing & Wholesale Goods"
        }
    ],
    "sg:phone":"+39 0735 751730",
    "sg:postcode":"63039",
    "sg:province":"Ascoli Piceno",
    "sg:tags":[
        "-",
        "health",
        "instrument"
    ],
    "sg:website":"http://www.biodis.it",
    "wof:name":"Biodis Srl",
    "wof:placetype":"venue"
},
  "geometry": {"coordinates":[13.890766,42.903797],"type":"Point"}
}