{
  "type": "Feature",
  "properties": {
    "iso:country":"IT",
    "sg:address":"41100 Modena",
    "sg:city":"Modena",
    "sg:orig_category":"Elettronica Professionale E Di Consumo. Musica",
    "sg:phone":"+39 059 331016",
    "sg:postcode":"41100",
    "sg:province":"Modena",
    "wof:name":"R.g. Elettronica Snc",
    "wof:placetype":"venue"
},
  "geometry": {"coordinates":[10.898548,44.656849],"type":"Point"}
}