{
  "type": "Feature",
  "properties": {
    "iso:country":"IT",
    "sg:address":"Via E. Fermi, 11/b; Verona; 37135",
    "sg:city":"Verona",
    "sg:classifiers":[
        {
            "category":"Industrial Area",
            "type":"Public Place"
        }
    ],
    "sg:phone":"+39 045 921 5100",
    "sg:postcode":"37135",
    "sg:province":"Verona",
    "sg:tags":[
        "large",
        "private"
    ],
    "sg:website":"www.marangoni.com",
    "wof:name":"Marangoni S.p.a.",
    "wof:placetype":"venue"
},
  "geometry": {"coordinates":[10.9712181091,45.4016418457],"type":"Point"}
}