{
  "type": "Feature",
  "properties": {
    "iso:country":"IT",
    "sg:address":"39012 Merano",
    "sg:city":"Merano",
    "sg:orig_category":"Arredo Urbano",
    "sg:phone":"+39 0473 221300",
    "sg:postcode":"39012",
    "sg:province":"Bolzano/Bozen",
    "sg:website":"http://www.mobilgarden.it",
    "wof:name":"Mobilgarden Sas Di Pircali Diego",
    "wof:placetype":"venue"
},
  "geometry": {"coordinates":[11.156925,46.653172],"type":"Point"}
}