{
  "type": "Feature",
  "properties": {
    "iso:country":"IT",
    "sg:address":"29, V. Bergolo 12074 Cortemilia",
    "sg:city":"Bergolo",
    "sg:classifiers":[
        {
            "category":"Farming",
            "subcategory":"Livestock Farm",
            "type":"Manufacturing & Wholesale Goods"
        }
    ],
    "sg:phone":"+39 39017381105",
    "sg:postcode":"12074",
    "sg:province":"Cuneo",
    "sg:tags":[
        "agriculture"
    ],
    "sg:website":"http://www.lagentile.com",
    "wof:name":"La Gentile Srl",
    "wof:placetype":"venue"
},
  "geometry": {"coordinates":[7.547111,44.388798],"type":"Point"}
}