{
  "type": "Feature",
  "properties": {
    "addr:full":"5, Via Bellenghi Alberto 47100 Forli' Forl\u00ec-Cesena 47100",
    "addr:postcode":"47100;47100",
    "addr:street":"Via Bellenghi Alberto;Forli ' Forli\u0300-Cesena",
    "iso:country":"IT",
    "sg:address":"5, Via Bellenghi Alberto 47100 Forli'",
    "sg:classifiers":[
        {
            "category":"Shopping",
            "subcategory":"Computers & Home Electronics",
            "type":"Retail Goods"
        }
    ],
    "sg:phone":"+39 0543 724068",
    "sg:postcode":"47100",
    "sg:province":"Forl\u00ec-Cesena",
    "sg:tags":[
        "electronic",
        "electrical",
        "equipment"
    ],
    "wof:name":"S.a.i.i.e. (s.n.c.)",
    "wof:placetype":"venue"
},
  "geometry": {"coordinates":[11.980461,43.994766],"type":"Point"}
}