{
  "type": "Feature",
  "properties": {
    "iso:country":"IT",
    "sg:address":"Via Del Lavoro 9 47838 Riccione",
    "sg:city":"Riccione",
    "sg:classifiers":[
        {
            "category":"Autos & Motor Vehicles",
            "subcategory":"Recreational Vehicle Sales",
            "type":"Retail Goods"
        }
    ],
    "sg:phone":"+39 0541 600320",
    "sg:postcode":"47838",
    "sg:province":"Rimini",
    "sg:tags":[
        "conversion"
    ],
    "sg:website":"www.rossioleodinamica.com",
    "wof:name":"Rossi Oleodinamica Srl",
    "wof:placetype":"venue"
},
  "geometry": {"coordinates":[12.642333,43.989658],"type":"Point"}
}