{
  "type": "Feature",
  "properties": {
    "addr:full":"50136 Firenze Firenze Firenze 50136",
    "addr:postcode":"50136;50136",
    "iso:country":"IT",
    "sg:address":"50136 Firenze",
    "sg:city":"Firenze",
    "sg:orig_category":"Buste E Sacchetti",
    "sg:phone":"+39 055 666735",
    "sg:postcode":"50136",
    "sg:province":"Firenze",
    "wof:name":"Corsini Cesare Di Patrizia Corsini & Elena Colombini Snc",
    "wof:placetype":"venue"
},
  "geometry": {"coordinates":[11.280924,43.76606],"type":"Point"}
}