{
  "type": "Feature",
  "properties": {
    "iso:country":"IT",
    "sg:address":"52, Via Statale 25011 Calcinato",
    "sg:city":"Calcinato",
    "sg:classifiers":[
        {
            "category":"Autos & Motor Vehicles",
            "subcategory":"Automobile Sales",
            "type":"Retail Goods"
        }
    ],
    "sg:phone":"+39 030 996 4229",
    "sg:postcode":"25011",
    "sg:province":"Brescia",
    "sg:tags":[
        "equipment",
        "transport"
    ],
    "wof:name":"Podium S.r.l.",
    "wof:placetype":"venue"
},
  "geometry": {"coordinates":[10.378597,45.48344],"type":"Point"}
}