{
  "type": "Feature",
  "properties": {
    "iso:country":"IT",
    "sg:address":"104, Contrada S. Giovanni 64010 Colonnella",
    "sg:city":"Colonnella",
    "sg:classifiers":[
        {
            "category":"Shopping",
            "type":"Retail Goods"
        }
    ],
    "sg:phone":"+39 0861 760382",
    "sg:postcode":"64010",
    "sg:province":"Teramo",
    "sg:tags":[
        "finished",
        "-",
        "metallic"
    ],
    "wof:name":"Aitec (s.r.l.)",
    "wof:placetype":"venue"
},
  "geometry": {"coordinates":[13.6985311508,42.6612701416],"type":"Point"}
}