{
  "type": "Feature",
  "properties": {
    "addr:full":"Via Ernesto Caorsi 49 16030 Sori Sori Genova 16030",
    "addr:housenumber":"49",
    "addr:postcode":"16030;16030",
    "addr:street":"Via Ernesto Caorsi",
    "iso:country":"IT",
    "sg:address":"Via Ernesto Caorsi 49 16030 Sori",
    "sg:city":"Sori",
    "sg:orig_category":"Transportation Equipment For Ships And Ship Components",
    "sg:phone":"+39 0185 700425",
    "sg:postcode":"16030",
    "sg:province":"Genova",
    "sg:website":"www.olcesricci.com",
    "wof:name":"Olcese Ricci Srl",
    "wof:placetype":"venue"
},
  "geometry": {"coordinates":[9.10913,44.379646],"type":"Point"}
}