{
  "type": "Feature",
  "properties": {
    "addr:full":"111, Via Carso 16137 Genova Genova Genova 16137",
    "addr:housenumber":"111",
    "addr:postcode":"16137;16137",
    "addr:street":"Via Carso",
    "iso:country":"IT",
    "sg:address":"111, Via Carso 16137 Genova",
    "sg:city":"Genova",
    "sg:classifiers":[
        {
            "category":"Bars & Pubs",
            "subcategory":"Nightclub",
            "type":"Food & Drink"
        }
    ],
    "sg:phone":"+39 010 831 0660",
    "sg:postcode":"16137",
    "sg:province":"Genova",
    "sg:tags":[
        "cake",
        "bread"
    ],
    "wof:name":"C.i.d.a.g. (s.r.l.)",
    "wof:placetype":"venue"
},
  "geometry": {"coordinates":[8.937298,44.425751],"type":"Point"}
}