{
  "type": "Feature",
  "properties": {
    "iso:country":"IT",
    "sg:address":"10135 Torino",
    "sg:city":"Torino",
    "sg:orig_category":"Banche E Servizi Finanziari",
    "sg:phone":"+39 011 347 1826",
    "sg:postcode":"10135",
    "sg:province":"Torino",
    "wof:name":"Tecnos Srl",
    "wof:placetype":"venue"
},
  "geometry": {"coordinates":[7.621897,45.017937],"type":"Point"}
}