{
  "type": "Feature",
  "properties": {
    "iso:country":"IT",
    "sg:address":"28/19, Via Marconi Guglielmo 20020 Arese",
    "sg:city":"Arese",
    "sg:classifiers":[
        {
            "category":"Manufacturing",
            "subcategory":"Printing",
            "type":"Manufacturing & Wholesale Goods"
        }
    ],
    "sg:phone":"+39 39029383515",
    "sg:postcode":"20020",
    "sg:province":"Milano",
    "sg:tags":[
        "publishing"
    ],
    "wof:name":"Biesse (s.r.l.)",
    "wof:placetype":"venue"
},
  "geometry": {"coordinates":[9.0872793198,45.5387611389],"type":"Point"}
}