{
  "type": "Feature",
  "properties": {
    "iso:country":"IT",
    "sg:address":"25018 Montichiari",
    "sg:city":"Montichiari",
    "sg:orig_category":"Impiantistica E Prodotti Tecnologici Per Edilizia. Elettrotecnica Industriale, Prodotti E Apparecchiature. Elettrotecnica Professionale E Di Consumo",
    "sg:phone":"+39 030 962149",
    "sg:postcode":"25018",
    "sg:province":"Brescia",
    "wof:name":"Soldi Impianti Elettrici Snc Di Soldi Sergio & C.",
    "wof:placetype":"venue"
},
  "geometry": {"coordinates":[10.358705,45.431847],"type":"Point"}
}