{
  "type": "Feature",
  "properties": {
    "iso:country":"IT",
    "sg:address":"20143 Milano",
    "sg:city":"Milano",
    "sg:orig_category":"Elettrotecnica Industriale, Prodotti E Apparecchiature. Elettronica Industriale, Prodotti E Apparecchiature. Macchine, Strumenti Ed Apparecchi Per Attivita' Industriali",
    "sg:phone":"+39 02 891 0142",
    "sg:postcode":"20143",
    "sg:province":"Milano",
    "wof:name":"An.na (s.a.s.)",
    "wof:placetype":"venue"
},
  "geometry": {"coordinates":[9.165786,45.44228],"type":"Point"}
}