{
  "type": "Feature",
  "properties": {
    "addr:full":"23037 Tirano Tirano Sondrio 23037",
    "addr:postcode":"23037;23037",
    "iso:country":"IT",
    "sg:address":"23037 Tirano",
    "sg:city":"Tirano",
    "sg:orig_category":"Arti Grafiche",
    "sg:phone":"+39 0342 701294",
    "sg:postcode":"23037",
    "sg:province":"Sondrio",
    "wof:name":"Petruzio Srl",
    "wof:placetype":"venue"
},
  "geometry": {"coordinates":[10.162838,46.217113],"type":"Point"}
}