{
  "type": "Feature",
  "properties": {
    "addr:full":"20022 Castano Primo Castano Primo Milano 20022",
    "addr:postcode":"20022;20022",
    "iso:country":"IT",
    "sg:address":"20022 Castano Primo",
    "sg:city":"Castano Primo",
    "sg:orig_category":"Pompe",
    "sg:phone":"+39 0331 877504",
    "sg:postcode":"20022",
    "sg:province":"Milano",
    "wof:name":"Oldani Pompe Di Claudio Oldani",
    "wof:placetype":"venue"
},
  "geometry": {"coordinates":[8.7396259308,45.5375099182],"type":"Point"}
}