{
  "type": "Feature",
  "properties": {
    "iso:country":"IT",
    "sg:address":"41019 Sozzigalli",
    "sg:city":"Sozzigalli",
    "sg:orig_category":"Nautica. Forniture Per Attivita' Commerciali Ed Artigianali",
    "sg:phone":"+39 059 563824",
    "sg:postcode":"41019",
    "sg:province":"Modena",
    "wof:name":"Righi Nino",
    "wof:placetype":"venue"
},
  "geometry": {"coordinates":[10.975664,44.748234],"type":"Point"}
}