{
  "type": "Feature",
  "properties": {
    "addr:full":"21028 Travedona Monate Varese 21028",
    "addr:postcode":"21028;21028",
    "iso:country":"IT",
    "sg:address":"21028 Travedona Monate",
    "sg:classifiers":[
        {
            "category":"Sports & Exercise",
            "subcategory":"Tennis Court",
            "type":"Entertainment"
        }
    ],
    "sg:phone":"+39 0332 977523",
    "sg:postcode":"21028",
    "sg:province":"Varese",
    "sg:tags":[
        "e",
        "lo",
        "tempo",
        "libero",
        "per",
        "impianti",
        "il",
        "attrezzature"
    ],
    "sg:website":"http://www.monatepiscine.com",
    "wof:name":"Marsetti Ivano",
    "wof:placetype":"venue"
},
  "geometry": {"coordinates":[8.733723,45.835083],"type":"Point"}
}