{
  "type": "Feature",
  "properties": {
    "iso:country":"IT",
    "sg:address":"60125 Ancona",
    "sg:city":"Ancona",
    "sg:orig_category":"Automobili E Mezzi Di Trasporto",
    "sg:phone":"+39 071 280871",
    "sg:postcode":"60125",
    "sg:province":"Ancona",
    "wof:name":"Mariotti Srl",
    "wof:placetype":"venue"
},
  "geometry": {"coordinates":[13.501762,43.609886],"type":"Point"}
}