{
  "type": "Feature",
  "properties": {
    "addr:full":"30173 Mestre Mestre Venezia 30173",
    "addr:postcode":"30173;30173",
    "addr:street":"Mestre Mestre Venezia",
    "iso:country":"IT",
    "sg:address":"30173 Mestre",
    "sg:city":"Mestre",
    "sg:orig_category":"Chiese Ed Associazioni Religiose",
    "sg:phone":"+39 041 534 7930",
    "sg:postcode":"30173",
    "sg:province":"Venezia",
    "wof:name":"Chiesa Di Altri Culti Cristiana Evangelica Asseblee Di Dio In Italia",
    "wof:placetype":"venue"
},
  "geometry": {"coordinates":[12.24931,45.494873],"type":"Point"}
}