{
  "type": "Feature",
  "properties": {
    "iso:country":"IT",
    "sg:address":"90123 Palermo",
    "sg:city":"Palermo",
    "sg:orig_category":"Non-classified Establishments",
    "sg:phone":"+39 091 441145",
    "sg:postcode":"90123",
    "sg:province":"Palermo",
    "wof:name":"Adelfio Tiziana",
    "wof:placetype":"venue"
},
  "geometry": {"coordinates":[13.387272,38.103085],"type":"Point"}
}