{
  "type": "Feature",
  "properties": {
    "addr:full":"Via Francia 20 41100 Modena Modena Modena 41100",
    "addr:housenumber":"20",
    "addr:postcode":"41100;41100",
    "addr:street":"Via Francia",
    "iso:country":"IT",
    "sg:address":"Via Francia 20 41100 Modena",
    "sg:city":"Modena",
    "sg:classifiers":[
        {
            "category":"Manufacturing",
            "subcategory":"Tools & Machinery",
            "type":"Manufacturing & Wholesale Goods"
        }
    ],
    "sg:phone":"+39 059 316 2911",
    "sg:postcode":"41100",
    "sg:province":"Modena",
    "sg:tags":[
        "tannery"
    ],
    "sg:website":"www.rizzi.it",
    "wof:name":"Rizzi 1857 Spa",
    "wof:placetype":"venue"
},
  "geometry": {"coordinates":[10.937694,44.66774],"type":"Point"}
}