{
  "type": "Feature",
  "properties": {
    "iso:country":"IT",
    "sg:address":"24040 Stezzano",
    "sg:city":"Stezzano",
    "sg:orig_category":"Cartotecnica E Servizi. Prodotti E Manufatti In Materie Plastiche. Articoli Per Imballaggio E Confezionamento",
    "sg:phone":"+39 035 592500",
    "sg:postcode":"24040",
    "sg:province":"Bergamo",
    "wof:name":"Idra Srl",
    "wof:placetype":"venue"
},
  "geometry": {"coordinates":[9.652866,45.655827],"type":"Point"}
}