{
  "type": "Feature",
  "properties": {
    "iso:country":"IT",
    "sg:address":"Via Cuneo 36 12012 Boves",
    "sg:city":"Boves",
    "sg:classifiers":[
        {
            "category":"Manufacturing",
            "subcategory":"Wood Products",
            "type":"Manufacturing & Wholesale Goods"
        }
    ],
    "sg:phone":"+39 0171 380103",
    "sg:postcode":"12012",
    "sg:province":"Cuneo",
    "sg:tags":[
        "high-quality",
        "board",
        "veneered"
    ],
    "wof:name":"Fratelli Ansaldi Srl",
    "wof:placetype":"venue"
},
  "geometry": {"coordinates":[7.554339,44.332699],"type":"Point"}
}