{
  "type": "Feature",
  "properties": {
    "addr:full":"66100 Chieti Chieti Chieti 66100",
    "addr:postcode":"66100;66100",
    "iso:country":"IT",
    "sg:address":"66100 Chieti",
    "sg:city":"Chieti",
    "sg:orig_category":"Musica",
    "sg:phone":"+39 0871 346647",
    "sg:postcode":"66100",
    "sg:province":"Chieti",
    "wof:name":"Di Paolo Perseo",
    "wof:placetype":"venue"
},
  "geometry": {"coordinates":[14.1698083878,42.3644943237],"type":"Point"}
}