{
  "type": "Feature",
  "properties": {
    "iso:country":"IT",
    "sg:address":"00148 Roma",
    "sg:city":"Roma",
    "sg:orig_category":"Arredo Bagno Ed Idrosanitari",
    "sg:phone":"+39 06 655901",
    "sg:postcode":"00148",
    "sg:province":"Roma",
    "wof:name":"Pischiutta Renato Spa",
    "wof:placetype":"venue"
},
  "geometry": {"coordinates":[12.445129,41.832371],"type":"Point"}
}