{
  "type": "Feature",
  "properties": {
    "iso:country":"IT",
    "sg:address":"20152 Milano",
    "sg:city":"Milano",
    "sg:orig_category":"Apparecchiature Ed Attrezzature Meccaniche. Forniture E Materiali Per Imballaggio E Confezionamento. Apparecchiature E Sistemi Per Imballaggio E Confezionamento",
    "sg:phone":"+39 02 410818",
    "sg:postcode":"20152",
    "sg:province":"Milano",
    "wof:name":"Kris (s.r.l.)",
    "wof:placetype":"venue"
},
  "geometry": {"coordinates":[9.066766,45.444138],"type":"Point"}
}