{
  "type": "Feature",
  "properties": {
    "iso:country":"IT",
    "sg:address":"37057 S. Giovanni Lupatoto",
    "sg:classifiers":[
        {
            "category":"Ice Cream",
            "type":"Food & Drink"
        }
    ],
    "sg:phone":"+39 045 877 8521",
    "sg:postcode":"37057",
    "sg:province":"Verona",
    "sg:tags":[
        "confectionery",
        "candy"
    ],
    "wof:name":"Rigodanza Serafino & C. Spa",
    "wof:placetype":"venue"
},
  "geometry": {"coordinates":[11.02931,45.377617],"type":"Point"}
}