{
  "type": "Feature",
  "properties": {
    "iso:country":"IT",
    "sg:address":"Via Artigani 17/19 35042 Este",
    "sg:city":"Este",
    "sg:orig_category":"In-mould Injection Moulded Parts",
    "sg:phone":"+39 0429 4005",
    "sg:postcode":"35042",
    "sg:province":"Padova",
    "sg:website":"www.maf3.com",
    "wof:name":"Maf 3 S.r.l.",
    "wof:placetype":"venue"
},
  "geometry": {"coordinates":[11.876589,45.409569],"type":"Point"}
}