{
  "type": "Feature",
  "properties": {
    "addr:full":"1, Via Assab 20132 Milano Milano Milano 20132",
    "addr:postcode":"20132;20132",
    "addr:street":"Via Assab",
    "iso:country":"IT",
    "sg:address":"1, Via Assab 20132 Milano",
    "sg:city":"Milano",
    "sg:classifiers":[
        {
            "category":"Professional",
            "subcategory":"Printing & Photocopies",
            "type":"Services"
        }
    ],
    "sg:phone":"+39 39022828546",
    "sg:postcode":"20132",
    "sg:province":"Milano",
    "wof:name":"Gruppo A.g.i. Srl",
    "wof:placetype":"venue"
},
  "geometry": {"coordinates":[9.2376594543,45.498714447],"type":"Point"}
}