{
  "type": "Feature",
  "properties": {
    "iso:country":"IT",
    "sg:address":"Corso Matteotti; Seregno; 20038",
    "sg:city":"Seregno",
    "sg:classifiers":[
        {
            "category":"Banks & Credit Unions",
            "subcategory":"Bank",
            "type":"Services"
        }
    ],
    "sg:phone":"+39 036 232 5525",
    "sg:postcode":"20038",
    "sg:province":"Milano",
    "wof:name":"Istituto Bancario, San Paolo Di Torino Spa",
    "wof:placetype":"venue"
},
  "geometry": {"coordinates":[9.208631,45.651043],"type":"Point"}
}