{
  "type": "Feature",
  "properties": {
    "iso:country":"IT",
    "sg:address":"30175 Venezia",
    "sg:city":"Marghera",
    "sg:orig_category":"Trattamenti Termici E Superficiali Metalli, Galvanotecnica",
    "sg:phone":"+39 041 924516",
    "sg:postcode":"30175",
    "sg:province":"Venezia",
    "wof:name":"Galvanomec Srl",
    "wof:placetype":"venue"
},
  "geometry": {"coordinates":[12.211958,45.462753],"type":"Point"}
}