{
  "type": "Feature",
  "properties": {
    "iso:country":"IT",
    "sg:address":"09038 Serramanna",
    "sg:city":"Serramanna",
    "sg:orig_category":"Macchine, Impianti Ed Attrezzature Industria Chimica. Apparecchiature Ed Attrezzature Meccaniche",
    "sg:phone":"+39 070 913 0473",
    "sg:postcode":"09038",
    "sg:province":"Medio Campidano",
    "wof:name":"Prima Di Murgia & C.snc",
    "wof:placetype":"venue"
},
  "geometry": {"coordinates":[8.925822,39.420986],"type":"Point"}
}