{
  "type": "Feature",
  "properties": {
    "iso:country":"IT",
    "sg:address":"84091 Battipaglia",
    "sg:city":"Battipaglia",
    "sg:orig_category":"Motori Ed Organi Di Trasmissione",
    "sg:phone":"+39 0828 301790",
    "sg:postcode":"84091",
    "sg:province":"Salerno",
    "wof:name":"Simer Srl",
    "wof:placetype":"venue"
},
  "geometry": {"coordinates":[14.9893188477,40.5953941345],"type":"Point"}
}