{
  "type": "Feature",
  "properties": {
    "iso:country":"IT",
    "sg:address":"06077 Perugia",
    "sg:orig_category":"Servizi E Lavori Per Edilizia E Lavori Pubblici",
    "sg:phone":"+39 075 591 7336",
    "sg:province":"PG",
    "sg:website":"http://www.lamimosasnc.it",
    "wof:name":"La Mimosa Snc Di Marri Rosella & C.",
    "wof:placetype":"venue"
},
  "geometry": {"coordinates":[12.430315,43.17548],"type":"Point"}
}