{
  "type": "Feature",
  "properties": {
    "iso:country":"IT",
    "sg:address":"10125 Torino",
    "sg:city":"Torino",
    "sg:classifiers":[
        {
            "category":"Shopping",
            "subcategory":"Crafts & Fabrics",
            "type":"Retail Goods"
        }
    ],
    "sg:phone":"+39 011 669 8643",
    "sg:postcode":"10125",
    "sg:province":"Torino",
    "sg:tags":[
        "material"
    ],
    "wof:name":"Sales Agency",
    "wof:placetype":"venue"
},
  "geometry": {"coordinates":[7.6810922623,45.0576133728],"type":"Point"}
}