{
  "type": "Feature",
  "properties": {
    "addr:full":"30016 Jesolo Venezia 30016",
    "addr:postcode":"30016;30016",
    "iso:country":"IT",
    "sg:address":"30016 Jesolo",
    "sg:orig_category":"Marmo, Pietre Ed Affini",
    "sg:phone":"+39 0421 363111",
    "sg:postcode":"30016",
    "sg:province":"Venezia",
    "sg:website":"http://www.capeletomarmi.it",
    "wof:name":"Capeleto Marmi Di Capeleto Silvio & C Snc",
    "wof:placetype":"venue"
},
  "geometry": {"coordinates":[12.33823,45.433655],"type":"Point"}
}