{
  "type": "Feature",
  "properties": {
    "iso:country":"IT",
    "sg:address":"Localit\u00e0 S.giorgio, 2 - Frazione Fe 25020 Capriano Del Colle",
    "sg:city":"Capriano del Colle",
    "sg:orig_category":"Hire Of Generators",
    "sg:phone":"+39 030 974 7921",
    "sg:postcode":"25020",
    "sg:province":"Brescia",
    "sg:website":"www.lanmar.it",
    "wof:name":"Lanmar Spa",
    "wof:placetype":"venue"
},
  "geometry": {"coordinates":[10.222958,45.539829],"type":"Point"}
}