{
  "type": "Feature",
  "properties": {
    "iso:country":"IT",
    "sg:address":"10072 Caselle Torinese",
    "sg:city":"Caselle Torinese",
    "sg:orig_category":"Forniture Per Abbigliamento E Pelletterie. Forniture Per Attivita' Commerciali Ed Artigianali",
    "sg:phone":"+39 011 996 1941",
    "sg:postcode":"10072",
    "sg:province":"Torino",
    "wof:name":"Manifer (s.n.c.)",
    "wof:placetype":"venue"
},
  "geometry": {"coordinates":[7.6509232521,45.1842308044],"type":"Point"}
}