{
  "type": "Feature",
  "properties": {
    "iso:country":"IT",
    "sg:address":"20050 Ronco Briantino",
    "sg:city":"Ronco Briantino",
    "sg:orig_category":"Apparecchiature E Sistemi Per Magazzinaggio E Movimentazione",
    "sg:phone":"+39 039 607 9061",
    "sg:postcode":"20050",
    "sg:province":"Milano",
    "wof:name":"2sg Srl",
    "wof:placetype":"venue"
},
  "geometry": {"coordinates":[9.403911,45.666603],"type":"Point"}
}