{
  "type": "Feature",
  "properties": {
    "addr:full":"37138 Verona Verona Verona 37138",
    "addr:postcode":"37138;37138",
    "iso:country":"IT",
    "sg:address":"37138 Verona",
    "sg:city":"Verona",
    "sg:orig_category":"Musica",
    "sg:phone":"+39 045 564325",
    "sg:postcode":"37138",
    "sg:province":"Verona",
    "wof:name":"Fiorentini Fratelli",
    "wof:placetype":"venue"
},
  "geometry": {"coordinates":[10.9706783295,45.4370498657],"type":"Point"}
}