{
  "type": "Feature",
  "properties": {
    "iso:country":"IT",
    "sg:address":"32043 Cortina D'ampezzo",
    "sg:orig_category":"Funivie, Sciovie E Impianti Di Risalita - Societa' Di Esercizio",
    "sg:phone":"+39 0436 862171",
    "sg:postcode":"32043",
    "sg:province":"Belluno",
    "wof:name":"Consorzio Esercenti Impianti A Fune Cortina",
    "wof:placetype":"venue"
},
  "geometry": {"coordinates":[11.9873304367,46.5034790039],"type":"Point"}
}