{
  "type": "Feature",
  "properties": {
    "iso:country":"IT",
    "sg:address":"20136 Milano",
    "sg:city":"Milano",
    "sg:classifiers":[
        {
            "category":"Manufacturing",
            "subcategory":"Leather Goods",
            "type":"Manufacturing & Wholesale Goods"
        }
    ],
    "sg:phone":"+39 02 5810 0412",
    "sg:postcode":"20136",
    "sg:province":"Milano",
    "sg:tags":[
        "goods",
        "clothing",
        "supply"
    ],
    "wof:name":"Nuova Cairati Srl",
    "wof:placetype":"venue"
},
  "geometry": {"coordinates":[9.182496,45.444973],"type":"Point"}
}