{
  "type": "Feature",
  "properties": {
    "iso:country":"IT",
    "sg:address":"20062 Cassano D'adda",
    "sg:orig_category":"Termotecnica E Riscaldamento, Apparecchiature E Servizi",
    "sg:phone":"+39 036 336 4511",
    "sg:postcode":"20062",
    "sg:province":"Milano",
    "wof:name":"Emmegi Alluminium Division Srl",
    "wof:placetype":"venue"
},
  "geometry": {"coordinates":[9.515581,45.53096],"type":"Point"}
}