{
  "type": "Feature",
  "properties": {
    "addr:full":"Via Eroi D' Italia 73056 Taurisano Taurisano Lecce 73056",
    "addr:postcode":"73056;73056",
    "addr:street":"Via Eroi D ' Italia",
    "iso:country":"IT",
    "sg:address":"Via Eroi D' Italia 73056 Taurisano",
    "sg:city":"Taurisano",
    "sg:classifiers":[
        {
            "category":"Shopping",
            "subcategory":"Clothing, Apparel, & Fashions",
            "type":"Retail Goods"
        }
    ],
    "sg:phone":"+39 0833 622495",
    "sg:postcode":"73056",
    "sg:province":"Lecce",
    "sg:tags":[
        "image",
        "clothing",
        "basic"
    ],
    "wof:name":"Forever S.r.l.",
    "wof:placetype":"venue"
},
  "geometry": {"coordinates":[18.219065,39.958019],"type":"Point"}
}