{
  "type": "Feature",
  "properties": {
    "addr:full":"47, Via Asiago 36030 Sarcedo Sarcedo Vicenza 36030",
    "addr:postcode":"36030;36030",
    "addr:street":"Via Asiago",
    "iso:country":"IT",
    "sg:address":"47, Via Asiago 36030 Sarcedo",
    "sg:city":"Sarcedo",
    "sg:classifiers":[
        {
            "category":"Professional",
            "subcategory":"Engineering",
            "type":"Services"
        }
    ],
    "sg:phone":"+39 0445 365666",
    "sg:postcode":"36030",
    "sg:province":"Vicenza",
    "sg:tags":[
        "machine",
        "-",
        "mechanical"
    ],
    "wof:name":"Tecnosald Vicentina S.a.s. Di Simonato Diego & C.",
    "wof:placetype":"venue"
},
  "geometry": {"coordinates":[11.508554,45.705029],"type":"Point"}
}