{
  "type": "Feature",
  "properties": {
    "addr:full":"Via Del Lavoro 20040 Usmate Velate Usmate Velate Milano 20040",
    "addr:postcode":"20040;20040",
    "addr:street":"Via Del Lavoro",
    "iso:country":"IT",
    "sg:address":"Via Del Lavoro 20040 Usmate Velate",
    "sg:city":"Usmate Velate",
    "sg:classifiers":[
        {
            "category":"Professional",
            "subcategory":"Engineering",
            "type":"Services"
        }
    ],
    "sg:phone":"+39 039 607 6900",
    "sg:postcode":"20040",
    "sg:province":"Milano",
    "sg:tags":[
        "machine",
        "-",
        "mechanical"
    ],
    "wof:name":"Unimec S.p.a.",
    "wof:placetype":"venue"
},
  "geometry": {"coordinates":[9.34302,45.642284],"type":"Point"}
}