{
  "type": "Feature",
  "properties": {
    "addr:full":"25, Vicolo Contex 28021 Borgomanero Borgomanero Novara 28021",
    "addr:housenumber":"25",
    "addr:postcode":"28021;28021",
    "addr:street":"Vicolo Contex",
    "iso:country":"IT",
    "sg:address":"25, Vicolo Contex 28021 Borgomanero",
    "sg:city":"Borgomanero",
    "sg:classifiers":[
        {
            "category":"Shopping",
            "type":"Retail Goods"
        }
    ],
    "sg:phone":"+39 39032281688",
    "sg:postcode":"28021",
    "sg:province":"Novara",
    "sg:tags":[
        "finished",
        "-",
        "metallic"
    ],
    "wof:name":"Tesa (s.r.l.)",
    "wof:placetype":"venue"
},
  "geometry": {"coordinates":[8.4724931717,45.6974487305],"type":"Point"}
}