{
  "type": "Feature",
  "properties": {
    "iso:country":"IT",
    "sg:address":"Via Buttici 66010 Tollo",
    "sg:city":"Tollo",
    "sg:classifiers":[
        {
            "category":"Manufacturing",
            "subcategory":"Lumber",
            "type":"Manufacturing & Wholesale Goods"
        }
    ],
    "sg:phone":"+39 0871 961442",
    "sg:postcode":"66010",
    "sg:province":"Chieti",
    "sg:tags":[
        "wood"
    ],
    "wof:name":"Civitarese Cesare & C. Snc",
    "wof:placetype":"venue"
},
  "geometry": {"coordinates":[14.322098,42.346924],"type":"Point"}
}