{
  "type": "Feature",
  "properties": {
    "iso:country":"IT",
    "sg:address":"20133 Milano",
    "sg:city":"Milano",
    "sg:orig_category":"Macchine, Impianti E Forniture Per Industria Grafica, Cartaria E Cartotecnica",
    "sg:phone":"+39 02 236 0004",
    "sg:postcode":"20133",
    "sg:province":"Milano",
    "wof:name":"Scitex Wide Format Italia Srl",
    "wof:placetype":"venue"
},
  "geometry": {"coordinates":[9.224896,45.476482],"type":"Point"}
}