{
  "type": "Feature",
  "properties": {
    "addr:full":"25020 Dello Dello Brescia 25020",
    "addr:postcode":"25020;25020",
    "iso:country":"IT",
    "sg:address":"25020 Dello",
    "sg:city":"Dello",
    "sg:orig_category":"Elettrotecnica Industriale, Prodotti E Apparecchiature",
    "sg:phone":"+39 030 977 1114",
    "sg:postcode":"25020",
    "sg:province":"Brescia",
    "wof:name":"Zanetti Giovanni",
    "wof:placetype":"venue"
},
  "geometry": {"coordinates":[10.13198,45.474712],"type":"Point"}
}