{
  "type": "Feature",
  "properties": {
    "iso:country":"IT",
    "sg:address":"8, Via Della Madonnina 31044 Montebelluna",
    "sg:city":"Montebelluna",
    "sg:classifiers":[
        {
            "category":"Manufacturing",
            "subcategory":"Metals",
            "type":"Manufacturing & Wholesale Goods"
        }
    ],
    "sg:phone":"+39 0423 603633",
    "sg:postcode":"31044",
    "sg:province":"Treviso",
    "sg:tags":[
        "processing"
    ],
    "wof:name":"Scat Convex Bottoms Srl",
    "wof:placetype":"venue"
},
  "geometry": {"coordinates":[12.0792951584,45.7644538879],"type":"Point"}
}