{
  "type": "Feature",
  "properties": {
    "iso:country":"IT",
    "sg:address":"00186 Roma",
    "sg:city":"Roma",
    "sg:orig_category":"Servizi Culturali E Per Lo Spettacolo. Servizi Al Turismo. Acqua, Luce, Gas E Societa' Di Esercizio Pubblico",
    "sg:phone":"+39 06 687 9629",
    "sg:postcode":"00186",
    "sg:province":"Roma",
    "wof:name":"Biblioteca Di Storia Moderna E Contemporanea",
    "wof:placetype":"venue"
},
  "geometry": {"coordinates":[12.478371,41.89386],"type":"Point"}
}