{
  "type": "Feature",
  "properties": {
    "addr:full":"20090 Rodano Rodano Milano 20090",
    "addr:postcode":"20090;20090",
    "iso:country":"IT",
    "sg:address":"20090 Rodano",
    "sg:city":"Rodano",
    "sg:orig_category":"Servizi E Lavori Per Edilizia E Lavori Pubblici",
    "sg:phone":"+39 02 950 0171",
    "sg:postcode":"20090",
    "sg:province":"Milano",
    "sg:website":"http://www.carver.it",
    "wof:name":"Carver Srl",
    "wof:placetype":"venue"
},
  "geometry": {"coordinates":[9.334034,45.472107],"type":"Point"}
}