{
  "type": "Feature",
  "properties": {
    "iso:country":"IT",
    "sg:address":"45018 Porto Tolle",
    "sg:city":"Porto Tolle",
    "sg:orig_category":"Imprese Di Costruzioni Civili Ed Industriali",
    "sg:phone":"+39 0426 380800",
    "sg:postcode":"45018",
    "sg:province":"Rovigo",
    "wof:name":"Metamauco Marine S.r.l.",
    "wof:placetype":"venue"
},
  "geometry": {"coordinates":[12.42849,44.902519],"type":"Point"}
}