{
  "type": "Feature",
  "properties": {
    "addr:full":"95019 Zafferana Etnea Zafferana Etnea Catania 95019",
    "addr:postcode":"95019;95019",
    "iso:country":"IT",
    "sg:address":"95019 Zafferana Etnea",
    "sg:city":"Zafferana Etnea",
    "sg:orig_category":"Legname Da Lavoro",
    "sg:phone":"+39 095 708 2165",
    "sg:postcode":"95019",
    "sg:province":"Catania",
    "wof:name":"Airone Legnami Di Di Re Vera",
    "wof:placetype":"venue"
},
  "geometry": {"coordinates":[15.128321,37.731571],"type":"Point"}
}