{
  "type": "Feature",
  "properties": {
    "addr:full":"57, Localita' Migliana 59025 Cantagallo Cantagallo Prato 59025",
    "addr:postcode":"59025;59025",
    "addr:street":"Localita ' Migliana",
    "iso:country":"IT",
    "sg:address":"57, Localita' Migliana 59025 Cantagallo",
    "sg:city":"Cantagallo",
    "sg:classifiers":[
        {
            "category":"Real Estate",
            "subcategory":"Architect",
            "type":"Services"
        }
    ],
    "sg:phone":"+39 0574 988328",
    "sg:postcode":"59025",
    "sg:province":"Prato",
    "sg:tags":[
        "textile",
        "clothing"
    ],
    "wof:name":"Tintoria 3 Monti (s.a.s.)",
    "wof:placetype":"venue"
},
  "geometry": {"coordinates":[11.108716,43.987125],"type":"Point"}
}