{
  "type": "Feature",
  "properties": {
    "iso:country":"IT",
    "sg:address":"Via Fara Gustavo 28 20124 Milano",
    "sg:city":"Milano",
    "sg:classifiers":[
        {
            "category":"Manufacturing",
            "subcategory":"Chemicals & Compounds",
            "type":"Manufacturing & Wholesale Goods"
        }
    ],
    "sg:phone":"+39 02 677 1681",
    "sg:postcode":"20124",
    "sg:province":"Milano",
    "sg:tags":[
        "industrial"
    ],
    "sg:website":"www.scl.it",
    "wof:name":"Societa' Chimica Larderello Spa",
    "wof:placetype":"venue"
},
  "geometry": {"coordinates":[9.198387,45.483883],"type":"Point"}
}