{
  "type": "Feature",
  "properties": {
    "addr:full":"52, Via Torricelli Evangelista 37136 Verona Verona Verona 37136",
    "addr:postcode":"37136;37136",
    "addr:street":"Via Torricelli Evangelista",
    "iso:country":"IT",
    "sg:address":"52, Via Torricelli Evangelista 37136 Verona",
    "sg:city":"Verona",
    "sg:classifiers":[
        {
            "category":"Farming",
            "subcategory":"Livestock Farm",
            "type":"Manufacturing & Wholesale Goods"
        }
    ],
    "sg:phone":"+39 045 862 0020",
    "sg:postcode":"37136",
    "sg:province":"Verona",
    "sg:tags":[
        "agriculture"
    ],
    "wof:name":"Perusi S.r.l.",
    "wof:placetype":"venue"
},
  "geometry": {"coordinates":[10.954658,45.411942],"type":"Point"}
}