{
  "type": "Feature",
  "properties": {
    "addr:full":"25046 Cazzago San Martino Cazzago San Martino Brescia 25046",
    "addr:postcode":"25046;25046",
    "iso:country":"IT",
    "sg:address":"25046 Cazzago San Martino",
    "sg:city":"Cazzago San Martino",
    "sg:orig_category":"Materiali E Componenti Elettrotecnici",
    "sg:phone":"+39 030 725333",
    "sg:postcode":"25046",
    "sg:province":"Brescia",
    "wof:name":"Caffi Fiorella Maria",
    "wof:placetype":"venue"
},
  "geometry": {"coordinates":[10.025928,45.576015],"type":"Point"}
}