{
  "type": "Feature",
  "properties": {
    "iso:country":"IT",
    "sg:address":"00122 Lido Di Ostia",
    "sg:orig_category":"Non-classified Establishments",
    "sg:phone":"+39 06 562 3646",
    "sg:postcode":"00122",
    "sg:province":"Roma",
    "wof:name":"Cosmopel S.r.l.",
    "wof:placetype":"venue"
},
  "geometry": {"coordinates":[12.284619,41.731243],"type":"Point"}
}