{
  "type": "Feature",
  "properties": {
    "iso:country":"IT",
    "sg:address":"Strada Provinciale Bressana Salice 27050 Retorbido",
    "sg:city":"Retorbido",
    "sg:classifiers":[
        {
            "category":"Wholesale",
            "subcategory":"Medical Equipment & Supplies",
            "type":"Manufacturing & Wholesale Goods"
        }
    ],
    "sg:phone":"+39 0383 372011",
    "sg:postcode":"27050",
    "sg:province":"Pavia",
    "sg:tags":[
        "cafeteria"
    ],
    "sg:website":"www.brasilia.it",
    "wof:name":"Brasilia Spa",
    "wof:placetype":"venue"
},
  "geometry": {"coordinates":[9.034039,44.953518],"type":"Point"}
}