{
  "type": "Feature",
  "properties": {
    "iso:country":"IT",
    "sg:address":"50012 Bagno A Ripoli",
    "sg:city":"Bagno a Ripoli",
    "sg:orig_category":"Motori Ed Organi Di Trasmissione",
    "sg:phone":"+39 055 696257",
    "sg:postcode":"50012",
    "sg:province":"Firenze",
    "sg:website":"http://www.frmitalia.com",
    "wof:name":"Frm Srl",
    "wof:placetype":"venue"
},
  "geometry": {"coordinates":[11.3317604065,43.7316246033],"type":"Point"}
}