{
  "type": "Feature",
  "properties": {
    "iso:country":"IT",
    "sg:address":"36015 Schio",
    "sg:city":"Schio",
    "sg:orig_category":"Macchine E Forniture Per Ecologia E Smaltimento Rifiuti. Elettrodomestici. Forniture Alle Strutture Ricettive. Macchine, Strumenti Ed Apparecchi Per Attivita' Industriali",
    "sg:phone":"+39 0445 575342",
    "sg:postcode":"36015",
    "sg:province":"Vicenza",
    "wof:name":"Dbr Di Balasso & C. Snc",
    "wof:placetype":"venue"
},
  "geometry": {"coordinates":[11.548257,45.577412],"type":"Point"}
}