{
  "type": "Feature",
  "properties": {
    "iso:country":"IT",
    "sg:address":"20064 Gorgonzola",
    "sg:city":"Gorgonzola",
    "sg:orig_category":"Macchine Ed Impianti Per Edilizia E Lavori Pubblici",
    "sg:phone":"+39 02 9530 5033",
    "sg:postcode":"20064",
    "sg:province":"Milano",
    "wof:name":"S.i.m. Spa",
    "wof:placetype":"venue"
},
  "geometry": {"coordinates":[9.202549,45.478348],"type":"Point"}
}