{
  "type": "Feature",
  "properties": {
    "iso:country":"IT",
    "sg:address":"00060 Roma",
    "sg:orig_category":"Macchine, Impianti Ed Attrezzature Per Agricoltura E Zootecnia",
    "sg:phone":"+39 06 3085 9411",
    "sg:postcode":"00060",
    "sg:province":"Roma",
    "wof:name":"Rimac Di Devi Amato",
    "wof:placetype":"venue"
},
  "geometry": {"coordinates":[12.246763,42.012676],"type":"Point"}
}