{
  "type": "Feature",
  "properties": {
    "iso:country":"IT",
    "sg:address":"80124 Napoli",
    "sg:city":"Napoli",
    "sg:orig_category":"Sport - Articoli E Forniture",
    "sg:phone":"+39 081 230 3293",
    "sg:postcode":"80124",
    "sg:province":"Napoli",
    "wof:name":"Local Emotion Di Romaniello Domenico",
    "wof:placetype":"venue"
},
  "geometry": {"coordinates":[14.163612,40.817547],"type":"Point"}
}