{
  "type": "Feature",
  "properties": {
    "iso:country":"IT",
    "sg:address":"90141 Palermo",
    "sg:city":"Palermo",
    "sg:classifiers":[
        {
            "category":"Health Services",
            "subcategory":"Health Practitioner",
            "type":"Services"
        }
    ],
    "sg:phone":"+39 091 730 0465",
    "sg:postcode":"90141",
    "sg:province":"Palermo",
    "sg:tags":[
        "medici"
    ],
    "wof:name":"Cemed Studio Medico Associato",
    "wof:placetype":"venue"
},
  "geometry": {"coordinates":[13.351336,38.129646],"type":"Point"}
}