{
  "type": "Feature",
  "properties": {
    "iso:country":"IT",
    "sg:address":"40127 Bologna",
    "sg:city":"Bologna",
    "sg:orig_category":"Associazioni Ed Organismi Di Interesse Pubblico",
    "sg:phone":"+39 051 421 1624",
    "sg:postcode":"40127",
    "sg:province":"Bologna",
    "wof:name":"Forum Metropolitano Delle Associazioni Di Cittadini Non Comunitari Di Bologn",
    "wof:placetype":"venue"
},
  "geometry": {"coordinates":[11.361051,44.501991],"type":"Point"}
}