{
  "type": "Feature",
  "properties": {
    "iso:country":"IT",
    "sg:address":"89, Via Della Vittoria 26837 Mulazzano",
    "sg:city":"Mulazzano",
    "sg:classifiers":[
        {
            "category":"Wholesale",
            "subcategory":"Drugs",
            "type":"Manufacturing & Wholesale Goods"
        }
    ],
    "sg:phone":"+39 39029888921",
    "sg:postcode":"26837",
    "sg:province":"Lodi",
    "sg:tags":[
        "chemical",
        "pharmaceutical"
    ],
    "wof:name":"Solchem Italiana S.p.a.",
    "wof:placetype":"venue"
},
  "geometry": {"coordinates":[9.385393,45.394718],"type":"Point"}
}