{
  "type": "Feature",
  "properties": {
    "iso:country":"IT",
    "sg:address":"16127 Genova",
    "sg:city":"Genova",
    "sg:orig_category":"Arredo Cucina Ed Elettrodomestici. Elettrodomestici",
    "sg:phone":"+39 010 242 6236",
    "sg:postcode":"16127",
    "sg:province":"Genova",
    "wof:name":"Tel & Tronic Snc",
    "wof:placetype":"venue"
},
  "geometry": {"coordinates":[8.910737,44.425476],"type":"Point"}
}