{
  "type": "Feature",
  "properties": {
    "iso:country":"IT",
    "sg:address":"20123 Milano",
    "sg:city":"Milano",
    "sg:orig_category":"Hobbistica",
    "sg:phone":"+39 02 806 6191",
    "sg:postcode":"20123",
    "sg:province":"Milano",
    "wof:name":"De Rosa S.p.a.",
    "wof:placetype":"venue"
},
  "geometry": {"coordinates":[9.181157,45.463299],"type":"Point"}
}