{
  "type": "Feature",
  "properties": {
    "iso:country":"IT",
    "sg:address":"00161 Roma",
    "sg:city":"Roma",
    "sg:orig_category":"Calzature - Produzione E Ingrosso",
    "sg:phone":"+39 06 4424 1808",
    "sg:postcode":"00161",
    "sg:province":"Roma",
    "wof:name":"Calzarium Snc",
    "wof:placetype":"venue"
},
  "geometry": {"coordinates":[12.518289,41.907658],"type":"Point"}
}