{
  "type": "Feature",
  "properties": {
    "iso:country":"IT",
    "sg:address":"24030 Mozzo",
    "sg:city":"Mozzo",
    "sg:orig_category":"Impiantistica E Prodotti Tecnologici Per Edilizia. Climatizzazione E Condizionamento, Apparecchiature E Servizi",
    "sg:phone":"+39 035 617444",
    "sg:postcode":"24030",
    "sg:province":"Bergamo",
    "sg:website":"http://www.rebba.it",
    "wof:name":"Rebba Srl",
    "wof:placetype":"venue"
},
  "geometry": {"coordinates":[9.609816,45.702415],"type":"Point"}
}