{
  "type": "Feature",
  "properties": {
    "addr:full":"3, Via Micca Pietro 36075 Montecchio Maggiore Montecchio Maggiore Vicenza 36075",
    "addr:postcode":"36075;36075",
    "addr:street":"Via Micca Pietro",
    "iso:country":"IT",
    "sg:address":"3, Via Micca Pietro 36075 Montecchio Maggiore",
    "sg:city":"Montecchio Maggiore",
    "sg:classifiers":[
        {
            "category":"Manufacturing",
            "subcategory":"Metals",
            "type":"Manufacturing & Wholesale Goods"
        }
    ],
    "sg:phone":"+39 0444 694777",
    "sg:postcode":"36075",
    "sg:province":"Vicenza",
    "sg:tags":[
        "processing"
    ],
    "wof:name":"Marangon Danilo & C. (s.r.l.)",
    "wof:placetype":"venue"
},
  "geometry": {"coordinates":[11.4034137726,45.4930496216],"type":"Point"}
}