{
  "type": "Feature",
  "properties": {
    "iso:country":"IT",
    "sg:address":"28921 Verbania",
    "sg:city":"Verbania",
    "sg:classifiers":[
        {
            "category":"Health Services",
            "subcategory":"Health Practitioner",
            "type":"Services"
        }
    ],
    "sg:phone":"+39 0323 401579",
    "sg:postcode":"28921",
    "sg:province":"Verbano-Cusio-Ossola",
    "sg:tags":[
        "medici"
    ],
    "wof:name":"Bernascone Giovanni",
    "wof:placetype":"venue"
},
  "geometry": {"coordinates":[8.568576,45.935078],"type":"Point"}
}