{
  "type": "Feature",
  "properties": {
    "iso:country":"IT",
    "sg:address":"Via Novara 20022 Castano Primo",
    "sg:city":"Castano Primo",
    "sg:classifiers":[
        {
            "category":"Shopping",
            "subcategory":"Clothing, Apparel, & Fashions",
            "type":"Retail Goods"
        }
    ],
    "sg:phone":"+39 0331 877310",
    "sg:postcode":"20022",
    "sg:province":"Milano",
    "sg:tags":[
        "clothes"
    ],
    "wof:name":"Erlivia (s.r.l.)",
    "wof:placetype":"venue"
},
  "geometry": {"coordinates":[8.767016,45.544594],"type":"Point"}
}