{
  "type": "Feature",
  "properties": {
    "addr:full":"20026 Novate Milanese Novate Milanese Milano 20026",
    "addr:postcode":"20026;20026",
    "iso:country":"IT",
    "sg:address":"20026 Novate Milanese",
    "sg:city":"Novate Milanese",
    "sg:orig_category":"Servizi E Lavori Per Ecologia E Smaltimento Rifiuti. Forniture Industriali Per Prevenzione, Controllo E Sicurezza",
    "sg:postcode":"20026",
    "sg:province":"Milano",
    "wof:name":"Db Progetti (s.r.l.)",
    "wof:placetype":"venue"
},
  "geometry": {"coordinates":[9.144377,45.531624],"type":"Point"}
}