{
  "type": "Feature",
  "properties": {
    "iso:country":"IT",
    "sg:address":"92016 Ribera",
    "sg:city":"Ribera",
    "sg:orig_category":"Carrozzelle E Poltrone Per Infermi",
    "sg:phone":"+39 0925 61054",
    "sg:postcode":"92016",
    "sg:province":"Agrigento",
    "sg:website":"http://www.ortopediacaruana.it",
    "wof:name":"Ortopedia Caruana",
    "wof:placetype":"venue"
},
  "geometry": {"coordinates":[13.390055,37.441006],"type":"Point"}
}