{
  "type": "Feature",
  "properties": {
    "addr:full":"37023 Grezzana Grezzana Verona 37023",
    "addr:postcode":"37023;37023",
    "iso:country":"IT",
    "sg:address":"37023 Grezzana",
    "sg:city":"Grezzana",
    "sg:orig_category":"Marmo, Pietre Ed Affini",
    "sg:phone":"+39 045 907336",
    "sg:postcode":"37023",
    "sg:province":"Verona",
    "sg:website":"http://www.cedalgraniti.com",
    "wof:name":"Cedal Graniti",
    "wof:placetype":"venue"
},
  "geometry": {"coordinates":[11.006146,45.533752],"type":"Point"}
}