{
  "type": "Feature",
  "properties": {
    "iso:country":"IT",
    "sg:address":"48010 Bagnara Di Romagna",
    "sg:city":"Bagnara di Romagna",
    "sg:orig_category":"Serramenti Ed Infissi",
    "sg:phone":"+39 0545 76009",
    "sg:postcode":"48010",
    "sg:province":"Ravenna",
    "sg:website":"http://www.ponzi-in.it",
    "wof:name":"Ponzi Ingressi Automatici Infissi Metallici",
    "wof:placetype":"venue"
},
  "geometry": {"coordinates":[11.820231,44.391563],"type":"Point"}
}