{
  "type": "Feature",
  "properties": {
    "addr:full":"82, Via Ventuno Aprile 29100 Piacenza Piacenza Piacenza 29100",
    "addr:postcode":"29100;29100",
    "addr:street":"Via Ventuno Aprile",
    "iso:country":"IT",
    "sg:address":"82, Via Ventuno Aprile 29100 Piacenza",
    "sg:city":"Piacenza",
    "sg:classifiers":[
        {
            "category":"Autos & Motor Vehicles",
            "subcategory":"Automobile Sales",
            "type":"Retail Goods"
        }
    ],
    "sg:phone":"+39 0523 331648",
    "sg:postcode":"29100",
    "sg:province":"Piacenza",
    "sg:tags":[
        "motor-cars"
    ],
    "wof:name":"Ponginibbi Gian Giacomo & Figli S.r.l.",
    "wof:placetype":"venue"
},
  "geometry": {"coordinates":[9.6951417923,45.0537719727],"type":"Point"}
}