{
  "type": "Feature",
  "properties": {
    "addr:full":"80126 Napoli Napoli Napoli 80126",
    "addr:housenumber":"80126",
    "addr:postcode":"80126",
    "iso:country":"IT",
    "sg:address":"80126 Napoli",
    "sg:city":"Napoli",
    "sg:orig_category":"Arte Ed Artigianato Artistico",
    "sg:phone":"+39 081 726 6128",
    "sg:postcode":"80126",
    "sg:province":"Napoli",
    "sg:website":"http://www.fonderiaruocco.com",
    "wof:name":"Lavorazione In Bronzo Di Ruocco Giuseppe & C. Snc",
    "wof:placetype":"venue"
},
  "geometry": {"coordinates":[14.175657,40.857288],"type":"Point"}
}