{
  "type": "Feature",
  "properties": {
    "iso:country":"IT",
    "sg:address":"Via Roma 290 35030 Monteortone",
    "sg:classifiers":[
        {
            "category":"Shopping",
            "subcategory":"Clothing, Apparel, & Fashions",
            "type":"Retail Goods"
        }
    ],
    "sg:phone":"+39 049 999 9911",
    "sg:postcode":"35030",
    "sg:province":"Padova",
    "sg:tags":[
        "shirt"
    ],
    "wof:name":"Camiceria Montegrappa Srl",
    "wof:placetype":"venue"
},
  "geometry": {"coordinates":[11.876589,45.409569],"type":"Point"}
}