{
  "type": "Feature",
  "properties": {
    "iso:country":"IT",
    "sg:address":"35011 Campodarsego",
    "sg:city":"Campodarsego",
    "sg:orig_category":"Arredo Camera Letto E Complementi",
    "sg:phone":"+39 049 556 4246",
    "sg:postcode":"35011",
    "sg:province":"Padova",
    "wof:name":"Zordan Teri",
    "wof:placetype":"venue"
},
  "geometry": {"coordinates":[11.954615,45.506519],"type":"Point"}
}