{
  "type": "Feature",
  "properties": {
    "iso:country":"IT",
    "sg:address":"00165 Roma",
    "sg:city":"Roma",
    "sg:orig_category":"Impiantistica E Prodotti Tecnologici Per Edilizia. Elettronica Professionale E Di Consumo",
    "sg:phone":"+39 06 638 1514",
    "sg:postcode":"00165",
    "sg:province":"Roma",
    "wof:name":"Pada Srl Progetti Appalti Per L'antincendio",
    "wof:placetype":"venue"
},
  "geometry": {"coordinates":[12.438639,41.893139],"type":"Point"}
}