{
  "type": "Feature",
  "properties": {
    "addr:full":"34142 Trieste Trieste Trieste 34142",
    "addr:postcode":"34142;34142",
    "iso:country":"IT",
    "sg:address":"34142 Trieste",
    "sg:city":"Trieste",
    "sg:orig_category":"Ricerca E Selezione Del Personale",
    "sg:phone":"+39 040 918 8111",
    "sg:postcode":"34142",
    "sg:province":"Trieste",
    "wof:name":"Mib School Of Management",
    "wof:placetype":"venue"
},
  "geometry": {"coordinates":[13.809735,45.645405],"type":"Point"}
}