{
  "type": "Feature",
  "properties": {
    "addr:full":"00047 Marino Marino Roma 00047",
    "addr:postcode":"00047;00047",
    "addr:street":"Marino Roma",
    "iso:country":"IT",
    "sg:address":"00047 Marino",
    "sg:city":"Marino",
    "sg:orig_category":"Macchine, Impianti Ed Attrezzature Industria Chimica. Attrezzature E Forniture Per Officine Riparazione E Servizi Ausiliari",
    "sg:phone":"+39 06 9354 8580",
    "sg:postcode":"00047",
    "sg:province":"Roma",
    "wof:name":"C.a.m.a.s. Snc",
    "wof:placetype":"venue"
},
  "geometry": {"coordinates":[12.616099,41.761955],"type":"Point"}
}