{
  "type": "Feature",
  "properties": {
    "iso:country":"IT",
    "sg:address":"95013 Fiumefreddo Di Sicilia",
    "sg:city":"Fiumefreddo di Sicilia",
    "sg:orig_category":"Salotti, Poltrone, Sedie E Tavoli",
    "sg:phone":"+39 095 642125",
    "sg:postcode":"95013",
    "sg:province":"Catania",
    "wof:name":"Mobili Casa Bella Di Santamaria Isabella",
    "wof:placetype":"venue"
},
  "geometry": {"coordinates":[15.201929,37.791451],"type":"Point"}
}