{
  "type": "Feature",
  "properties": {
    "iso:country":"IT",
    "sg:address":"Via Dei Cantieri 3 90142 Palermo",
    "sg:city":"Palermo",
    "sg:classifiers":[
        {
            "category":"Shopping",
            "subcategory":"Bridal",
            "type":"Retail Goods"
        }
    ],
    "sg:phone":"+39 091 541618",
    "sg:postcode":"90142",
    "sg:province":"Palermo",
    "sg:tags":[
        "veil"
    ],
    "wof:name":"Creazioni Francesca Di Vitellaro",
    "wof:placetype":"venue"
},
  "geometry": {"coordinates":[13.359068,38.136002],"type":"Point"}
}