{
  "type": "Feature",
  "properties": {
    "addr:full":"24044 Dalmine Dalmine Bergamo 24044",
    "addr:postcode":"24044;24044",
    "iso:country":"IT",
    "sg:address":"24044 Dalmine",
    "sg:city":"Dalmine",
    "sg:orig_category":"Biancheria, Telerie E Coperte. Arredo Camera Letto E Complementi",
    "sg:phone":"+39 035 373325",
    "sg:postcode":"24044",
    "sg:province":"Bergamo",
    "sg:website":"http://www.mondoflex.it",
    "wof:name":"Mondoflex Di Brena Bernardo",
    "wof:placetype":"venue"
},
  "geometry": {"coordinates":[9.615493,45.655453],"type":"Point"}
}