{
  "type": "Feature",
  "properties": {
    "iso:country":"IT",
    "sg:address":"09033 Decimomannu",
    "sg:city":"Decimomannu",
    "sg:orig_category":"Materiali Edili",
    "sg:phone":"+39 070 961583",
    "sg:postcode":"09033",
    "sg:province":"Cagliari",
    "wof:name":"Calcestruzzi Sarda (s.r.l.)",
    "wof:placetype":"venue"
},
  "geometry": {"coordinates":[8.957657,39.317078],"type":"Point"}
}