{
  "type": "Feature",
  "properties": {
    "addr:full":"22070 Rovello Porro Rovello Porro Como 22070",
    "addr:postcode":"22070;22070",
    "iso:country":"IT",
    "sg:address":"22070 Rovello Porro",
    "sg:city":"Rovello Porro",
    "sg:orig_category":"Macchine, Impianti Ed Attrezzature Per Abbigliamento E Pelletterie. Apparecchiature Ed Attrezzature Meccaniche. Elettrotecnica Industriale, Prodotti E Apparecchiature",
    "sg:phone":"+39 02 9675 0122",
    "sg:postcode":"22070",
    "sg:province":"Como",
    "wof:name":"Magnaghi Macchine Motori Srl",
    "wof:placetype":"venue"
},
  "geometry": {"coordinates":[9.041574,45.656113],"type":"Point"}
}