{
  "type": "Feature",
  "properties": {
    "iso:country":"IT",
    "sg:address":"6, Via Canturina 22070 Capiago Intimiano",
    "sg:city":"Capiago",
    "sg:classifiers":[
        {
            "category":"Shopping",
            "subcategory":"Crafts & Fabrics",
            "type":"Retail Goods"
        }
    ],
    "sg:phone":"+39 031 463 0211",
    "sg:postcode":"22070",
    "sg:province":"Como",
    "wof:name":"Olmetex Spa",
    "wof:placetype":"venue"
},
  "geometry": {"coordinates":[9.084397316,45.7898292542],"type":"Point"}
}