{
  "type": "Feature",
  "properties": {
    "iso:country":"IT",
    "sg:address":"49, Via Del Tabacco 70022 Altamura",
    "sg:city":"Altamura",
    "sg:classifiers":[
        {
            "category":"Home & Garden",
            "subcategory":"Home Furnishings",
            "type":"Retail Goods"
        }
    ],
    "sg:phone":"+39 080 314 9628",
    "sg:postcode":"70022",
    "sg:province":"Bari",
    "sg:tags":[
        "household"
    ],
    "wof:name":"Calia & Calia Di Calia A. & Calia A. Snc",
    "wof:placetype":"venue"
},
  "geometry": {"coordinates":[16.524399,40.822628],"type":"Point"}
}