{
  "type": "Feature",
  "properties": {
    "iso:country":"IT",
    "sg:address":"34123 Trieste",
    "sg:city":"Trieste",
    "sg:orig_category":"Ricambi E Componenti Dei Mezzi Di Trasporto",
    "sg:phone":"+39 040 311610",
    "sg:postcode":"34123",
    "sg:province":"Trieste",
    "wof:name":"Vigna Officina Meccanica",
    "wof:placetype":"venue"
},
  "geometry": {"coordinates":[13.755237,45.644485],"type":"Point"}
}