{
  "type": "Feature",
  "properties": {
    "iso:country":"IT",
    "sg:address":"74015 Martina Franca",
    "sg:city":"Martina Franca",
    "sg:orig_category":"Lavorazioni Metalli, Stampaggio E Saldatura",
    "sg:phone":"+39 080 483 9196",
    "sg:postcode":"74015",
    "sg:province":"Taranto",
    "wof:name":"Alfa Infissi Snc",
    "wof:placetype":"venue"
},
  "geometry": {"coordinates":[17.313931,40.701206],"type":"Point"}
}