{
  "type": "Feature",
  "properties": {
    "iso:country":"IT",
    "sg:address":"42100 Reggio Emilia",
    "sg:orig_category":"Pubblicita', Marketing E Comunicazione",
    "sg:phone":"+39 0522 292725",
    "sg:postcode":"42100",
    "sg:province":"Reggio Nell'Emilia",
    "wof:name":"New Communication Di Iori Gian Marco",
    "wof:placetype":"venue"
},
  "geometry": {"coordinates":[10.6349172592,44.6803970337],"type":"Point"}
}