{
  "type": "Feature",
  "properties": {
    "iso:country":"IT",
    "sg:address":"Via M. Gonzaga 7; Milano; 20123",
    "sg:city":"Milano",
    "sg:classifiers":[
        {
            "category":"Banks & Credit Unions",
            "subcategory":"Bank",
            "type":"Services"
        }
    ],
    "sg:phone":"+39 02 7200 1144",
    "sg:postcode":"20123",
    "sg:province":"Milano",
    "wof:name":"Skandinaviska Enskilda Bank",
    "wof:placetype":"venue"
},
  "geometry": {"coordinates":[9.188895,45.461395],"type":"Point"}
}