{
  "type": "Feature",
  "properties": {
    "addr:full":"15, Piazza Napoli 20146 Milano Milano Milano 20146",
    "addr:postcode":"20146;20146",
    "addr:street":"Piazza Napoli",
    "iso:country":"IT",
    "sg:address":"15, Piazza Napoli 20146 Milano",
    "sg:city":"Milano",
    "sg:classifiers":[
        {
            "category":"Shopping",
            "subcategory":"Crafts & Fabrics",
            "type":"Retail Goods"
        }
    ],
    "sg:phone":"+39 02 4895 2283",
    "sg:postcode":"20146",
    "sg:province":"Milano",
    "sg:tags":[
        "linen"
    ],
    "wof:name":"Gm Selezione (s.a.s.)",
    "wof:placetype":"venue"
},
  "geometry": {"coordinates":[9.1549816132,45.4532546997],"type":"Point"}
}