{
  "type": "Feature",
  "properties": {
    "iso:country":"IT",
    "sg:address":"43038 Sala Baganza",
    "sg:city":"Sala Baganza",
    "sg:orig_category":"Ristorazione E Locali Pubblici Affini. Ristoranti Ed Esercizi Affini. Servizi Ausiliari Di Ristorazione E Di Intrattenimento",
    "sg:phone":"+39 0521 833105",
    "sg:postcode":"43038",
    "sg:province":"Parma",
    "sg:website":"http://www.space.tin.it/cucina/angsch/",
    "wof:name":"Schiroli Angela Vecchia Osteria Di Talignano",
    "wof:placetype":"venue"
},
  "geometry": {"coordinates":[10.214409,44.701138],"type":"Point"}
}