{
  "type": "Feature",
  "properties": {
    "addr:full":"88046 Lamezia Terme Lamezia Terme Catanzaro 88046",
    "addr:postcode":"88046;88046",
    "iso:country":"IT",
    "sg:address":"88046 Lamezia Terme",
    "sg:city":"Lamezia Terme",
    "sg:orig_category":"Pubblica Amministrazione",
    "sg:phone":"+39 0968 2071",
    "sg:postcode":"88046",
    "sg:province":"Catanzaro",
    "wof:name":"Comune Di Lamezia Terme",
    "wof:placetype":"venue"
},
  "geometry": {"coordinates":[16.2977809906,38.9598121643],"type":"Point"}
}