{
  "type": "Feature",
  "properties": {
    "iso:country":"IT",
    "sg:address":"00165 Roma",
    "sg:city":"Roma",
    "sg:orig_category":"Macchine, Impianti Ed Attrezzature Per Abbigliamento E Pelletterie",
    "sg:phone":"+39 06 662 6857",
    "sg:postcode":"00165",
    "sg:province":"Roma",
    "wof:name":"D'ingiullo Gilberto",
    "wof:placetype":"venue"
},
  "geometry": {"coordinates":[12.430214,41.89872],"type":"Point"}
}