{
  "type": "Feature",
  "properties": {
    "addr:full":"21015 Lonate Pozzolo Lonate Pozzolo Varese 21015",
    "addr:postcode":"21015;21015",
    "iso:country":"IT",
    "sg:address":"21015 Lonate Pozzolo",
    "sg:city":"Lonate Pozzolo",
    "sg:classifiers":[
        {
            "category":"Health Services",
            "subcategory":"Health Practitioner",
            "type":"Services"
        }
    ],
    "sg:phone":"+39 0331 669199",
    "sg:postcode":"21015",
    "sg:province":"Varese",
    "sg:tags":[
        "medici"
    ],
    "wof:name":"Pedrali Patrick",
    "wof:placetype":"venue"
},
  "geometry": {"coordinates":[8.7632608414,45.5903663635],"type":"Point"}
}