{
  "type": "Feature",
  "properties": {
    "iso:country":"IT",
    "sg:address":"10060 None",
    "sg:city":"None",
    "sg:orig_category":"Servizi E Lavori Industria Chimica",
    "sg:phone":"+39 011 986 5272",
    "sg:postcode":"10060",
    "sg:province":"Torino",
    "wof:name":"I.v.p Di Gibellino G. & C. S.a.s.",
    "wof:placetype":"venue"
},
  "geometry": {"coordinates":[7.655646,45.158272],"type":"Point"}
}