{
  "type": "Feature",
  "properties": {
    "addr:full":"71042 Cerignola Cerignola Foggia 71042",
    "addr:postcode":"71042;71042",
    "iso:country":"IT",
    "sg:address":"71042 Cerignola",
    "sg:city":"Cerignola",
    "sg:orig_category":"Arredo Urbano",
    "sg:phone":"+39 0885 429972",
    "sg:postcode":"71042",
    "sg:province":"Foggia",
    "wof:name":"Arredo Tecnica & C. Sas Di Saverio Contino",
    "wof:placetype":"venue"
},
  "geometry": {"coordinates":[15.898499,41.260349],"type":"Point"}
}