{
  "type": "Feature",
  "properties": {
    "addr:full":"Via Brembo, 25; Curno; Bergamo; 24035 Curno Bergamo 24035",
    "addr:housenumber":"25",
    "addr:postcode":"24035;24035",
    "addr:street":"Via Brembo",
    "iso:country":"IT",
    "sg:address":"Via Brembo, 25; Curno; Bergamo; 24035",
    "sg:city":"Curno",
    "sg:classifiers":[
        {
            "category":"Industrial Area",
            "type":"Public Place"
        }
    ],
    "sg:phone":"+39 39035605111",
    "sg:postcode":"24035",
    "sg:province":"Bergamo",
    "sg:tags":[
        "large",
        "private"
    ],
    "sg:website":"www.brembo.it",
    "wof:name":"Brembo S.p.a.",
    "wof:placetype":"venue"
},
  "geometry": {"coordinates":[9.5999565125,45.6877670288],"type":"Point"}
}