{
  "type": "Feature",
  "properties": {
    "iso:country":"IT",
    "sg:address":"09044 Quartucciu",
    "sg:city":"Quartucciu",
    "sg:orig_category":"Impiantistica E Prodotti Tecnologici Per Edilizia. Elettrotecnica Professionale E Di Consumo. Telecomunicazioni E Telefonia, Impianti, Apparecchi E Servizi",
    "sg:phone":"+39 070 884178",
    "sg:postcode":"09044",
    "sg:province":"Cagliari",
    "sg:website":"http://www.elettricaservice.it",
    "wof:name":"Elettrica Service Snc",
    "wof:placetype":"venue"
},
  "geometry": {"coordinates":[9.149879,39.258656],"type":"Point"}
}