{
  "type": "Feature",
  "properties": {
    "addr:full":"24127 Bergamo Bergamo Bergamo 24127",
    "addr:postcode":"24127;24127",
    "iso:country":"IT",
    "sg:address":"24127 Bergamo",
    "sg:city":"Bergamo",
    "sg:orig_category":"Elettrodomestici. Forniture Alle Strutture Ricettive",
    "sg:phone":"+39 035 454 8111",
    "sg:postcode":"24127",
    "sg:province":"Bergamo",
    "sg:website":"http://www.elframo.it",
    "wof:name":"Nuova Elframo Srl",
    "wof:placetype":"venue"
},
  "geometry": {"coordinates":[9.645346,45.679661],"type":"Point"}
}