{
  "type": "Feature",
  "properties": {
    "iso:country":"IT",
    "sg:address":"Corso Romita 67 15100 Alessandria",
    "sg:city":"Alessandria",
    "sg:classifiers":[
        {
            "category":"Manufacturing",
            "subcategory":"Rubber & Plastics",
            "type":"Manufacturing & Wholesale Goods"
        }
    ],
    "sg:phone":"+39 0131 253235",
    "sg:postcode":"15100",
    "sg:province":"Alessandria",
    "sg:tags":[
        "injection",
        "part",
        "moulded"
    ],
    "sg:website":"www.reta.it",
    "wof:name":"Reta Rebora E Taverna Snc",
    "wof:placetype":"venue"
},
  "geometry": {"coordinates":[8.621263,44.902214],"type":"Point"}
}