{
  "type": "Feature",
  "properties": {
    "iso:country":"IT",
    "sg:address":"20146 Milano",
    "sg:city":"Milano",
    "sg:orig_category":"Servizi Per Aziende, Manifestazioni E Supporto Agli Scambi Commerciali",
    "sg:phone":"+39 02 422 2192",
    "sg:postcode":"20146",
    "sg:province":"Milano",
    "wof:name":"Aallestire S.r.l.",
    "wof:placetype":"venue"
},
  "geometry": {"coordinates":[9.151677,45.458256],"type":"Point"}
}