{
  "type": "Feature",
  "properties": {
    "addr:full":"84010 San Valentino Torio San Valentino Torio Salerno 84010",
    "addr:housenumber":"84010;valentino torio",
    "addr:postcode":"valentino torio;84010",
    "addr:street":"San;Salerno",
    "iso:country":"IT",
    "sg:address":"84010 San Valentino Torio",
    "sg:city":"San Valentino Torio",
    "sg:orig_category":"Prodotti Alimentari. Agricoltura, Orticoltura E Floricoltura",
    "sg:phone":"+39 081 939195",
    "sg:postcode":"84010",
    "sg:province":"Salerno",
    "wof:name":"Ferrara Giuseppe",
    "wof:placetype":"venue"
},
  "geometry": {"coordinates":[14.6141815186,40.7892570496],"type":"Point"}
}