{
  "type": "Feature",
  "properties": {
    "addr:full":"20066 Melzo Melzo Milano 20066",
    "addr:postcode":"20066;20066",
    "iso:country":"IT",
    "sg:address":"20066 Melzo",
    "sg:city":"Melzo",
    "sg:classifiers":[
        {
            "category":"Manufacturing",
            "subcategory":"Tools & Machinery",
            "type":"Manufacturing & Wholesale Goods"
        }
    ],
    "sg:phone":"+39 02 9573 9700",
    "sg:postcode":"20066",
    "sg:province":"Milano",
    "sg:tags":[
        "machining",
        "mechanical"
    ],
    "sg:website":"http://www.comunilombardia.com/idramel.html",
    "wof:name":"Gestione Manutenzione Containers Srl",
    "wof:placetype":"venue"
},
  "geometry": {"coordinates":[9.423347,45.500607],"type":"Point"}
}