{
  "type": "Feature",
  "properties": {
    "iso:country":"IT",
    "sg:address":"Via Trieste 26 20059 Vimercate",
    "sg:city":"Vimercate",
    "sg:orig_category":"Special Roller Bearings",
    "sg:phone":"+39 039 62591",
    "sg:postcode":"20059",
    "sg:province":"Milano",
    "sg:website":"www.rollon.com",
    "wof:name":"Rollon Spa",
    "wof:placetype":"venue"
},
  "geometry": {"coordinates":[9.359634,45.611057],"type":"Point"}
}