{
  "type": "Feature",
  "properties": {
    "iso:country":"IT",
    "sg:address":"38086 Pinzolo",
    "sg:city":"Pinzolo",
    "sg:orig_category":"Pubblica Amministrazione",
    "sg:phone":"+39 0465 502549",
    "sg:postcode":"38086",
    "sg:province":"Trento",
    "wof:name":"Comprensorio Delle Giudicarie",
    "wof:placetype":"venue"
},
  "geometry": {"coordinates":[10.7664461136,46.1599998474],"type":"Point"}
}