{
  "type": "Feature",
  "properties": {
    "iso:country":"IT",
    "sg:address":"83100 Avellino",
    "sg:city":"Avellino",
    "sg:orig_category":"Servizi Per Aziende, Manifestazioni E Supporto Agli Scambi Commerciali",
    "sg:phone":"+39 0825 760908",
    "sg:postcode":"83100",
    "sg:province":"Avellino",
    "wof:name":"Grossi Gerardo",
    "wof:placetype":"venue"
},
  "geometry": {"coordinates":[14.804785,40.821457],"type":"Point"}
}