{
  "type": "Feature",
  "properties": {
    "iso:country":"IT",
    "sg:address":"12100 Cuneo",
    "sg:city":"Cuneo",
    "sg:orig_category":"Macchine Ed Impianti Per Edilizia E Lavori Pubblici",
    "sg:phone":"+39 0171 412766",
    "sg:postcode":"12100",
    "sg:province":"Cuneo",
    "wof:name":"Miglioranza Amanzio",
    "wof:placetype":"venue"
},
  "geometry": {"coordinates":[7.568029,44.424561],"type":"Point"}
}