{
  "type": "Feature",
  "properties": {
    "iso:country":"IT",
    "sg:address":"20124 Milano",
    "sg:city":"Milano",
    "sg:orig_category":"Prodotti E Manufatti In Gomma",
    "sg:phone":"+39 02 669 1536",
    "sg:postcode":"20124",
    "sg:province":"Milano",
    "wof:name":"West Pharmaceutical Services Italia Srl",
    "wof:placetype":"venue"
},
  "geometry": {"coordinates":[9.2036180496,45.4839477539],"type":"Point"}
}