{
  "type": "Feature",
  "properties": {
    "addr:full":"20154 Milano Milano Milano 20154",
    "addr:postcode":"20154;20154",
    "iso:country":"IT",
    "sg:address":"20154 Milano",
    "sg:city":"Milano",
    "sg:orig_category":"Accessori Moda D'abbigliamento. Forniture Per Abbigliamento E Pelletterie. Shopping",
    "sg:phone":"+39 02 341953",
    "sg:postcode":"20154",
    "sg:province":"Milano",
    "wof:name":"Ricami Pibierre",
    "wof:placetype":"venue"
},
  "geometry": {"coordinates":[9.171398,45.480255],"type":"Point"}
}