{
  "type": "Feature",
  "properties": {
    "iso:country":"IT",
    "sg:address":"61025 Montelabbate",
    "sg:city":"Montelabbate",
    "sg:orig_category":"Macchine Utensili E Impianti. Elettrotecnica Industriale, Prodotti E Apparecchiature",
    "sg:phone":"+39 0721 491212",
    "sg:postcode":"61025",
    "sg:province":"Pesaro E Urbino",
    "wof:name":"Tornati Forni (s.r.l.)",
    "wof:placetype":"venue"
},
  "geometry": {"coordinates":[12.791903,43.861118],"type":"Point"}
}