{
  "type": "Feature",
  "properties": {
    "iso:country":"IT",
    "sg:address":"35010 Massanzago",
    "sg:city":"Massanzago",
    "sg:orig_category":"Zootecnia E Pesca, Allevamento Piccoli Animali",
    "sg:phone":"+39 049 572 0354",
    "sg:postcode":"35010",
    "sg:province":"Padova",
    "wof:name":"Azzurra (s.r.l.)",
    "wof:placetype":"venue"
},
  "geometry": {"coordinates":[12.016195,45.54324],"type":"Point"}
}