{
  "type": "Feature",
  "properties": {
    "iso:country":"IT",
    "sg:address":"20030 Lentate Sul Seveso",
    "sg:city":"Lentate sul Seveso",
    "sg:orig_category":"Vetro: Prodotti E Lavorazioni. Forniture Industriali Per Prevenzione, Controllo E Sicurezza",
    "sg:phone":"+39 036 256 0874",
    "sg:postcode":"20030",
    "sg:province":"Milano",
    "wof:name":"Fascetta Riccardo",
    "wof:placetype":"venue"
},
  "geometry": {"coordinates":[9.103204,45.686512],"type":"Point"}
}