{
  "type": "Feature",
  "properties": {
    "addr:full":"06053 Deruta Deruta Perugia 06053",
    "addr:postcode":"06053;06053",
    "iso:country":"IT",
    "sg:address":"06053 Deruta",
    "sg:city":"Deruta",
    "sg:classifiers":[
        {
            "category":"Building & Trades",
            "subcategory":"Construction",
            "type":"Services"
        }
    ],
    "sg:phone":"+39 075 972109",
    "sg:postcode":"06053",
    "sg:province":"Perugia",
    "sg:tags":[
        "fair",
        "industry",
        "support",
        "companies",
        "wood",
        "congresses",
        "furnishing",
        "supplies",
        "works",
        "events"
    ],
    "wof:name":"Ceramiche Vania Di Preziotti Vania E C. Sas",
    "wof:placetype":"venue"
},
  "geometry": {"coordinates":[12.4132919312,42.9814300537],"type":"Point"}
}