{
  "type": "Feature",
  "properties": {
    "addr:full":"470, Via Caduti Di Via Fani 47032 Bertinoro Bertinoro Forl\u00ec-Cesena 47032",
    "addr:housenumber":"470",
    "addr:postcode":"47032;47032",
    "addr:street":"Via Caduti Di Via Fani",
    "iso:country":"IT",
    "sg:address":"470, Via Caduti Di Via Fani 47032 Bertinoro",
    "sg:city":"Bertinoro",
    "sg:classifiers":[
        {
            "category":"Autos & Motor Vehicles",
            "subcategory":"Automobile Sales",
            "type":"Retail Goods"
        }
    ],
    "sg:phone":"+39 0543 448128",
    "sg:postcode":"47032",
    "sg:province":"Forl\u00ec-Cesena",
    "sg:tags":[
        "motor-cars"
    ],
    "wof:name":"A.s.t.a. - Car S.r.l.",
    "wof:placetype":"venue"
},
  "geometry": {"coordinates":[12.1657762527,44.1731948853],"type":"Point"}
}