{
  "type": "Feature",
  "properties": {
    "iso:country":"IT",
    "sg:address":"16151 Genova",
    "sg:city":"Genova",
    "sg:orig_category":"Non-classified Establishments",
    "sg:phone":"+39 010 468532",
    "sg:postcode":"16151",
    "sg:province":"Genova",
    "wof:name":"Gambino Lorenzo",
    "wof:placetype":"venue"
},
  "geometry": {"coordinates":[8.889144,44.414143],"type":"Point"}
}