{
  "type": "Feature",
  "properties": {
    "iso:country":"IT",
    "sg:address":"90036 Villabate",
    "sg:orig_category":"Segnaletica Aziendale, Cantieristica Ed Antinfortunistica",
    "sg:phone":"+39 091 614 4616",
    "sg:postcode":"90036",
    "sg:province":"Palermo",
    "wof:name":"Segnaletica Sud",
    "wof:placetype":"venue"
},
  "geometry": {"coordinates":[13.456762,38.075294],"type":"Point"}
}