{
  "type": "Feature",
  "properties": {
    "addr:full":"20098 San Giuliano Milanese San Giuliano Milanese Milano 20098",
    "addr:housenumber":"20098",
    "addr:postcode":"20098",
    "addr:street":"San",
    "iso:country":"IT",
    "sg:address":"20098 San Giuliano Milanese",
    "sg:city":"San Giuliano Milanese",
    "sg:orig_category":"Lavanderie - Impianti E Macchine",
    "sg:phone":"+39 02 9824 0600",
    "sg:postcode":"20098",
    "sg:province":"Milano",
    "wof:name":"Ghidini Benvenuto Srl",
    "wof:placetype":"venue"
},
  "geometry": {"coordinates":[9.150958,45.45208],"type":"Point"}
}