{
  "type": "Feature",
  "properties": {
    "addr:full":"Via Preyer 10, 26020 Casalmorano, Cr Casalmorano Cremona 26020",
    "addr:housenumber":"10",
    "addr:postcode":"26020;26020",
    "addr:street":"Via Preyer;Cr",
    "iso:country":"IT",
    "sg:address":"Via Preyer 10, 26020 Casalmorano, Cr",
    "sg:city":"Casalmorano",
    "sg:classifiers":[
        {
            "category":"Banks & Credit Unions",
            "subcategory":"Bank",
            "type":"Services"
        }
    ],
    "sg:postcode":"26020",
    "sg:province":"Cremona",
    "wof:name":"Banca Di Credito Cooperativo Del Cremonese-casalmorano (cremona) Scrl",
    "wof:placetype":"venue"
},
  "geometry": {"coordinates":[10.026135,45.133499],"type":"Point"}
}