{
  "type": "Feature",
  "properties": {
    "iso:country":"IT",
    "sg:address":"06012 Citt\u00e0 Di Castello",
    "sg:orig_category":"Arredo Camera Letto E Complementi",
    "sg:phone":"+39 075 855 8477",
    "sg:postcode":"06012",
    "sg:province":"Perugia",
    "wof:name":"Emiliani Emanuele",
    "wof:placetype":"venue"
},
  "geometry": {"coordinates":[12.224502,43.477341],"type":"Point"}
}