{
  "type": "Feature",
  "properties": {
    "addr:full":"40033 Casalecchio Di Reno Casalecchio di Reno Bologna 40033",
    "addr:postcode":"40033;40033",
    "addr:street":"Di Reno",
    "iso:country":"IT",
    "sg:address":"40033 Casalecchio Di Reno",
    "sg:city":"Casalecchio di Reno",
    "sg:orig_category":"Utensili Meccanici E Materiali",
    "sg:phone":"+39 051 573000",
    "sg:postcode":"40033",
    "sg:province":"Bologna",
    "wof:name":"Italpneumatica (s.a.s.)",
    "wof:placetype":"venue"
},
  "geometry": {"coordinates":[11.260859,44.487095],"type":"Point"}
}