{
  "type": "Feature",
  "properties": {
    "iso:country":"IT",
    "sg:address":"26039 Vescovato",
    "sg:city":"Vescovato",
    "sg:orig_category":"Carni, Salumi E Pesci",
    "sg:phone":"+39 0372 819211",
    "sg:postcode":"26039",
    "sg:province":"Cremona",
    "wof:name":"Gardenia - Pro Sus",
    "wof:placetype":"venue"
},
  "geometry": {"coordinates":[10.047606,45.130787],"type":"Point"}
}