{
  "type": "Feature",
  "properties": {
    "iso:country":"IT",
    "sg:address":"12, Via Del Lavoro 31016 Cordignano",
    "sg:city":"Cordignano",
    "sg:classifiers":[
        {
            "category":"Manufacturing",
            "subcategory":"Metals",
            "type":"Manufacturing & Wholesale Goods"
        }
    ],
    "sg:phone":"+39 0438 995350",
    "sg:postcode":"31016",
    "sg:province":"Treviso",
    "sg:tags":[
        "metallurgy",
        "metalworking"
    ],
    "wof:name":"Eurotravi (s.r.l.)",
    "wof:placetype":"venue"
},
  "geometry": {"coordinates":[12.4078598022,45.9418869019],"type":"Point"}
}