{
  "type": "Feature",
  "properties": {
    "iso:country":"IT",
    "sg:address":"22066 Mariano Comense",
    "sg:city":"Mariano Comense",
    "sg:orig_category":"Legno E Semilavorati",
    "sg:phone":"+39 031 746588",
    "sg:postcode":"22066",
    "sg:province":"Como",
    "wof:name":"Interplac Srl",
    "wof:placetype":"venue"
},
  "geometry": {"coordinates":[9.172934,45.702087],"type":"Point"}
}