{
  "type": "Feature",
  "properties": {
    "iso:country":"IT",
    "sg:address":"10098 Rivoli",
    "sg:city":"Rivoli",
    "sg:orig_category":"Arredi Ed Attrezzature Per Attivita' Commerciali Ed Artigianali",
    "sg:phone":"+39 011 959 6630",
    "sg:postcode":"10098",
    "sg:province":"Torino",
    "wof:name":"L.p.t. Snc Di Zanna & C.",
    "wof:placetype":"venue"
},
  "geometry": {"coordinates":[7.553561,45.064114],"type":"Point"}
}