{
  "type": "Feature",
  "properties": {
    "iso:country":"IT",
    "sg:address":"60021 Camerano",
    "sg:city":"Camerano",
    "sg:orig_category":"Carta, Cartone E Prodotti Primari. Forniture E Materiali Per Imballaggio E Confezionamento",
    "sg:phone":"+39 071 95342",
    "sg:postcode":"60021",
    "sg:province":"Ancona",
    "wof:name":"Ondulato Adriatico Srl",
    "wof:placetype":"venue"
},
  "geometry": {"coordinates":[13.540136,43.514297],"type":"Point"}
}