{
  "type": "Feature",
  "properties": {
    "addr:full":"Via C. Zucchi 21/a; Modena",
    "addr:housenumber":"21 / a",
    "addr:street":"Via C. Zucchi",
    "iso:country":"IT",
    "sg:address":"Via C. Zucchi 21/a; Modena",
    "sg:classifiers":[
        {
            "category":"Banks & Credit Unions",
            "subcategory":"Bank",
            "type":"Services"
        }
    ],
    "sg:phone":"+39 059 333933",
    "wof:name":"Cooperbanca Spa",
    "wof:placetype":"venue"
},
  "geometry": {"coordinates":[10.912754,44.652447],"type":"Point"}
}