{
  "type": "Feature",
  "properties": {
    "iso:country":"IT",
    "sg:address":"12, Strada Bussolino 12030 Caramagna Piemonte",
    "sg:city":"Caramagna Piemonte",
    "sg:classifiers":[
        {
            "category":"Food & Beverages",
            "subcategory":"Dairy",
            "type":"Retail Goods"
        }
    ],
    "sg:phone":"+39 39017289581",
    "sg:postcode":"12030",
    "sg:province":"Cuneo",
    "sg:tags":[
        "product"
    ],
    "wof:name":"Fattorie Osella (s.p.a.)",
    "wof:placetype":"venue"
},
  "geometry": {"coordinates":[7.735644,44.775997],"type":"Point"}
}