{
  "type": "Feature",
  "properties": {
    "iso:country":"IT",
    "sg:address":"38100 Trento",
    "sg:city":"Trento",
    "sg:orig_category":"Imprese Di Costruzioni Civili Ed Industriali",
    "sg:phone":"+39 0461 826611",
    "sg:postcode":"38100",
    "sg:province":"Trento",
    "wof:name":"Isoltrento Snc",
    "wof:placetype":"venue"
},
  "geometry": {"coordinates":[11.118841,46.07494],"type":"Point"}
}