{
  "type": "Feature",
  "properties": {
    "iso:country":"IT",
    "sg:address":"20127 Milano",
    "sg:city":"Milano",
    "sg:orig_category":"Impiantistica E Prodotti Tecnologici Per Edilizia",
    "sg:phone":"+39 02 261 5182",
    "sg:postcode":"20127",
    "sg:province":"Milano",
    "wof:name":"Casa Proget Snc Di Alfredo Murgia & C.",
    "wof:placetype":"venue"
},
  "geometry": {"coordinates":[9.213493,45.487514],"type":"Point"}
}