{
  "type": "Feature",
  "properties": {
    "iso:country":"IT",
    "sg:address":"24, Via Monte Sabotino 22044 Inverigo",
    "sg:city":"Inverigo",
    "sg:classifiers":[
        {
            "category":"Shopping",
            "subcategory":"Clothing, Apparel, & Fashions",
            "type":"Retail Goods"
        }
    ],
    "sg:phone":"+39 39031698241",
    "sg:postcode":"22044",
    "sg:province":"Como",
    "sg:tags":[
        "clothing",
        "accessory"
    ],
    "wof:name":"Tessitura Bosisio Umberto (s.a.s)",
    "wof:placetype":"venue"
},
  "geometry": {"coordinates":[9.205158,45.742985],"type":"Point"}
}