{
  "type": "Feature",
  "properties": {
    "iso:country":"IT",
    "sg:address":"43100 Parma",
    "sg:city":"Moletolo",
    "sg:orig_category":"Acciaierie E Fonderie",
    "sg:phone":"+39 0521 782200",
    "sg:postcode":"43100",
    "sg:province":"Parma",
    "wof:name":"Gardoni Enea Snc",
    "wof:placetype":"venue"
},
  "geometry": {"coordinates":[10.309977,44.808224],"type":"Point"}
}