{
  "type": "Feature",
  "properties": {
    "addr:full":"23891 Barzano' Lecco 23891",
    "addr:postcode":"23891;23891",
    "addr:street":"Barzano ' Lecco",
    "iso:country":"IT",
    "sg:address":"23891 Barzano'",
    "sg:orig_category":"Macchine E Forniture Per Arredamento E Industria Del Legno. Utensili Meccanici E Materiali",
    "sg:phone":"+39 039 956468",
    "sg:postcode":"23891",
    "sg:province":"Lecco",
    "wof:name":"Panzeri Carlo",
    "wof:placetype":"venue"
},
  "geometry": {"coordinates":[9.411667,45.865608],"type":"Point"}
}