{
  "type": "Feature",
  "properties": {
    "iso:country":"IT",
    "sg:address":"50032 Borgo San Lorenzo",
    "sg:city":"Borgo San Lorenzo",
    "sg:classifiers":[
        {
            "category":"Health Services",
            "subcategory":"Health Practitioner",
            "type":"Services"
        }
    ],
    "sg:phone":"+39 055 849 4566",
    "sg:postcode":"50032",
    "sg:province":"Firenze",
    "sg:tags":[
        "medici"
    ],
    "wof:name":"Boco Maitani Dott.ssa Giosiana",
    "wof:placetype":"venue"
},
  "geometry": {"coordinates":[11.411205,43.997242],"type":"Point"}
}