{
  "type": "Feature",
  "properties": {
    "addr:full":"80071 Anacapri Anacapri Napoli 80071",
    "addr:postcode":"80071;80071",
    "iso:country":"IT",
    "sg:address":"80071 Anacapri",
    "sg:city":"Anacapri",
    "sg:orig_category":"Ospedali E Servizi Sanitari",
    "sg:phone":"+39 081 837 1364",
    "sg:postcode":"80071",
    "sg:province":"Napoli",
    "wof:name":"Porta Lucia",
    "wof:placetype":"venue"
},
  "geometry": {"coordinates":[14.213687,40.551464],"type":"Point"}
}