{
  "type": "Feature",
  "properties": {
    "iso:country":"IT",
    "sg:address":"Via Borgogna 3; Milano; 20122",
    "sg:city":"Milano",
    "sg:classifiers":[
        {
            "category":"Banks & Credit Unions",
            "subcategory":"Bank",
            "type":"Services"
        }
    ],
    "sg:phone":"+39 02 7601 2435",
    "sg:postcode":"20122",
    "sg:province":"Milano",
    "wof:name":"Cassamarca Spa",
    "wof:placetype":"venue"
},
  "geometry": {"coordinates":[9.19846,45.465824],"type":"Point"}
}