{
  "type": "Feature",
  "properties": {
    "addr:full":"Via Val Tiberina, 105 - Porto D'asc 63039 San Benedetto Del Tronto San Benedetto del Tronto Ascoli Piceno 63039",
    "addr:housenumber":"105",
    "addr:postcode":"63039;63039",
    "addr:street":"Via Val Tiberina;Piceno",
    "iso:country":"IT",
    "sg:address":"Via Val Tiberina, 105 - Porto D'asc 63039 San Benedetto Del Tronto",
    "sg:city":"San Benedetto del Tronto",
    "sg:classifiers":[
        {
            "category":"Manufacturing",
            "subcategory":"Wood Products",
            "type":"Manufacturing & Wholesale Goods"
        }
    ],
    "sg:phone":"+39 0735 657344",
    "sg:postcode":"63039",
    "sg:province":"Ascoli Piceno",
    "sg:tags":[
        "cnc",
        "working"
    ],
    "wof:name":"Trancitalia Srl",
    "wof:placetype":"venue"
},
  "geometry": {"coordinates":[13.574977,42.8554],"type":"Point"}
}