{
  "type": "Feature",
  "properties": {
    "iso:country":"IT",
    "sg:address":"37020 Volargne",
    "sg:city":"Volargne",
    "sg:orig_category":"Arredamenti - Produzione E Ingrosso",
    "sg:phone":"+39 045 686 1800",
    "sg:postcode":"37020",
    "sg:province":"Verona",
    "wof:name":"Bettinazzi Renzo & C. Snc",
    "wof:placetype":"venue"
},
  "geometry": {"coordinates":[10.82313,45.547371],"type":"Point"}
}