{
  "type": "Feature",
  "properties": {
    "iso:country":"IT",
    "sg:address":"Via Rigosa 55/57 40069 Zola Predosa",
    "sg:city":"Zola",
    "sg:classifiers":[
        {
            "category":"Food & Beverages",
            "subcategory":"Liquor & Beverages",
            "type":"Retail Goods"
        }
    ],
    "sg:phone":"+39 051 753489",
    "sg:postcode":"40069",
    "sg:province":"Bologna",
    "sg:tags":[
        "wine",
        "italian"
    ],
    "sg:website":"www.gaggiolivini.it",
    "wof:name":"Gaggioli Azienda Agricola Vigneto Bagazzana",
    "wof:placetype":"venue"
},
  "geometry": {"coordinates":[11.235023,44.507614],"type":"Point"}
}