{
  "type": "Feature",
  "properties": {
    "addr:full":"52, Via Cortemilia 17014 Cairo Montenotte Cairo Montenotte Savona 17014",
    "addr:postcode":"17014;17014",
    "addr:street":"Via Cortemilia",
    "iso:country":"IT",
    "sg:address":"52, Via Cortemilia 17014 Cairo Montenotte",
    "sg:city":"Cairo Montenotte",
    "sg:classifiers":[
        {
            "category":"Shopping",
            "subcategory":"Crafts & Fabrics",
            "type":"Retail Goods"
        }
    ],
    "sg:phone":"+39 39019503750",
    "sg:postcode":"17014",
    "sg:province":"Savona",
    "sg:tags":[
        "ceramic"
    ],
    "wof:name":"Studio Vega S.r.l.",
    "wof:placetype":"venue"
},
  "geometry": {"coordinates":[8.275712,44.412956],"type":"Point"}
}