{
  "type": "Feature",
  "properties": {
    "addr:full":"Via Piave, 167 - Borgata Mare 32040 San Pietro Di Cadore San Pietro di Cadore Belluno 32040",
    "addr:housenumber":"167",
    "addr:postcode":"32040;32040",
    "addr:street":"Via Piave;Borgata Mare",
    "iso:country":"IT",
    "sg:address":"Via Piave, 167 - Borgata Mare 32040 San Pietro Di Cadore",
    "sg:city":"San Pietro di Cadore",
    "sg:classifiers":[
        {
            "category":"Manufacturing",
            "subcategory":"Glass & Minerals",
            "type":"Manufacturing & Wholesale Goods"
        }
    ],
    "sg:phone":"+39 0435 460008",
    "sg:postcode":"32040",
    "sg:province":"Belluno",
    "sg:tags":[
        "frame"
    ],
    "wof:name":"Esse 4 Di De Zolt Lisabetta & Erminio Sas",
    "wof:placetype":"venue"
},
  "geometry": {"coordinates":[12.21759,46.139965],"type":"Point"}
}