{
  "type": "Feature",
  "properties": {
    "iso:country":"IT",
    "sg:address":"22079 Villa Guardia",
    "sg:city":"Villa Guardia",
    "sg:classifiers":[
        {
            "category":"Manufacturing",
            "subcategory":"Textiles",
            "type":"Manufacturing & Wholesale Goods"
        }
    ],
    "sg:phone":"+39 031 563733",
    "sg:postcode":"22079",
    "sg:province":"Como",
    "sg:tags":[
        "textiles",
        "raw",
        "material",
        "fabric",
        "yarn"
    ],
    "sg:website":"http://www.giussanitessuti.com",
    "wof:name":"Giussani Tessuti",
    "wof:placetype":"venue"
},
  "geometry": {"coordinates":[9.0327234268,45.77734375],"type":"Point"}
}