{
  "type": "Feature",
  "properties": {
    "addr:full":"Via Giacomo Matteotti 1992 51036 Larciano Larciano Pistoia 51036",
    "addr:housenumber":"1992",
    "addr:postcode":"51036;51036",
    "addr:street":"Via Giacomo Matteotti",
    "iso:country":"IT",
    "sg:address":"Via Giacomo Matteotti 1992 51036 Larciano",
    "sg:city":"Larciano",
    "sg:classifiers":[
        {
            "category":"Wholesale",
            "subcategory":"Chemicals & Plastics",
            "type":"Manufacturing & Wholesale Goods"
        }
    ],
    "sg:phone":"+39 0573 83355",
    "sg:postcode":"51036",
    "sg:province":"Pistoia",
    "sg:tags":[
        "planter"
    ],
    "sg:website":"www.idel.it",
    "wof:name":"I.de.l. Srl",
    "wof:placetype":"venue"
},
  "geometry": {"coordinates":[10.9151849747,43.8689804077],"type":"Point"}
}