{
  "type": "Feature",
  "properties": {
    "addr:full":"41011 Campogalliano Campogalliano Modena 41011",
    "addr:postcode":"41011;41011",
    "iso:country":"IT",
    "sg:address":"41011 Campogalliano",
    "sg:city":"Campogalliano",
    "sg:classifiers":[
        {
            "category":"Train Station",
            "subcategory":"Light Rail",
            "type":"Transportation"
        }
    ],
    "sg:phone":"+39 059 527951",
    "sg:postcode":"41011",
    "sg:province":"Modena",
    "sg:tags":[
        "plating",
        "treatments",
        "metals",
        "heat",
        "electroforming",
        "surface"
    ],
    "wof:name":"General Sab Srl",
    "wof:placetype":"venue"
},
  "geometry": {"coordinates":[10.8468484879,44.6954193115],"type":"Point"}
}