{
  "type": "Feature",
  "properties": {
    "addr:full":"9, Via Artigianato 60027 Osimo Osimo Ancona 60027",
    "addr:postcode":"60027;60027",
    "addr:street":"Via Artigianato",
    "iso:country":"IT",
    "sg:address":"9, Via Artigianato 60027 Osimo",
    "sg:city":"Osimo",
    "sg:orig_category":"Miscellaneous Products",
    "sg:phone":"+39 39071716971",
    "sg:postcode":"60027",
    "sg:province":"Ancona",
    "wof:name":"Vetro Marche (s.n.c.)",
    "wof:placetype":"venue"
},
  "geometry": {"coordinates":[13.495308876,43.5010375977],"type":"Point"}
}