{
  "type": "Feature",
  "properties": {
    "iso:country":"IT",
    "sg:address":"491, Via Lavoro E Industria 25030 Rudiano",
    "sg:city":"Rudiano",
    "sg:classifiers":[
        {
            "category":"Shopping",
            "subcategory":"Clothing, Apparel, & Fashions",
            "type":"Retail Goods"
        }
    ],
    "sg:phone":"+39 030 706 0342",
    "sg:postcode":"25030",
    "sg:province":"Brescia",
    "sg:tags":[
        "clothes"
    ],
    "wof:name":"Gum Studio's (s.r.l.)",
    "wof:placetype":"venue"
},
  "geometry": {"coordinates":[9.881401,45.495926],"type":"Point"}
}