{
  "type": "Feature",
  "properties": {
    "iso:country":"IT",
    "sg:address":"50124 Firenze",
    "sg:city":"Firenze",
    "sg:orig_category":"Non-classified Establishments",
    "sg:phone":"+39 055 229 8371",
    "sg:postcode":"50124",
    "sg:province":"Firenze",
    "wof:name":"Locchi Snc",
    "wof:placetype":"venue"
},
  "geometry": {"coordinates":[11.238433,43.766788],"type":"Point"}
}