{
  "type": "Feature",
  "properties": {
    "iso:country":"IT",
    "sg:address":"65122 Pescara",
    "sg:city":"Pescara",
    "sg:orig_category":"Ristorazione E Locali Pubblici Affini. Ristoranti Ed Esercizi Affini. Servizi Ausiliari Di Ristorazione E Di Intrattenimento",
    "sg:phone":"+39 085 421 2911",
    "sg:postcode":"65122",
    "sg:province":"Pescara",
    "wof:name":"Bar Camplone",
    "wof:placetype":"venue"
},
  "geometry": {"coordinates":[14.210713,42.473167],"type":"Point"}
}