{
  "type": "Feature",
  "properties": {
    "iso:country":"IT",
    "sg:address":"56021 Cascina",
    "sg:city":"Cascina",
    "sg:orig_category":"Antifurto",
    "sg:phone":"+39 050 779042",
    "sg:postcode":"56021",
    "sg:province":"Pisa",
    "wof:name":"Idea Auto Di Bellucci Marco",
    "wof:placetype":"venue"
},
  "geometry": {"coordinates":[10.470207,43.689842],"type":"Point"}
}