{
  "type": "Feature",
  "properties": {
    "addr:full":"24126 Bergamo Bergamo Bergamo 24126",
    "addr:postcode":"24126;24126",
    "iso:country":"IT",
    "sg:address":"24126 Bergamo",
    "sg:city":"Bergamo",
    "sg:orig_category":"Macchine, Impianti Ed Attrezzature Per Abbigliamento E Pelletterie. Macchine E Impianti Per Attivita' Commerciali Ed Artigianali",
    "sg:phone":"+39 035 311277",
    "sg:postcode":"24126",
    "sg:province":"Bergamo",
    "wof:name":"Fasoli Ermanno",
    "wof:placetype":"venue"
},
  "geometry": {"coordinates":[9.657347,45.671482],"type":"Point"}
}