{
  "type": "Feature",
  "properties": {
    "iso:country":"IT",
    "sg:address":"73010 Surbo",
    "sg:city":"Surbo",
    "sg:orig_category":"Gas Auto Impianti - Produzione, Commercio E Installazione",
    "sg:phone":"+39 0832 362024",
    "sg:postcode":"73010",
    "sg:province":"Lecce",
    "wof:name":"Salento Autogas Snc",
    "wof:placetype":"venue"
},
  "geometry": {"coordinates":[18.127518,40.391724],"type":"Point"}
}