{
  "type": "Feature",
  "properties": {
    "iso:country":"IT",
    "sg:address":"70121 Bari",
    "sg:city":"Bari",
    "sg:orig_category":"Tessuti Arredamento, Tende E Tappeti. Forniture Per Edilizia E Lavori Pubblici",
    "sg:phone":"+39 080 523 1685",
    "sg:postcode":"70121",
    "sg:province":"Bari",
    "wof:name":"Angil Srl Casa & Casa",
    "wof:placetype":"venue"
},
  "geometry": {"coordinates":[16.869724,41.121742],"type":"Point"}
}