{
  "type": "Feature",
  "properties": {
    "addr:full":"10060 Scalenghe Scalenghe Torino 10060",
    "addr:postcode":"10060;10060",
    "iso:country":"IT",
    "sg:address":"10060 Scalenghe",
    "sg:city":"Scalenghe",
    "sg:orig_category":"Motori Ed Organi Di Trasmissione. Ricambi E Componenti Dei Mezzi Di Trasporto",
    "sg:phone":"+39 011 986 6229",
    "sg:postcode":"10060",
    "sg:province":"Torino",
    "wof:name":"Industria Volventi Srl",
    "wof:placetype":"venue"
},
  "geometry": {"coordinates":[7.4299879074,44.903503418],"type":"Point"}
}