{
  "type": "Feature",
  "properties": {
    "addr:full":"Via Gonzaga 4/h; Guastalla; 42016 Reggio Nell'Emilia 42016",
    "addr:housenumber":"4 / h",
    "addr:postcode":"42016;42016",
    "addr:street":"Via Gonzaga",
    "iso:country":"IT",
    "sg:address":"Via Gonzaga 4/h; Guastalla; 42016",
    "sg:classifiers":[
        {
            "category":"Banks & Credit Unions",
            "subcategory":"Bank",
            "type":"Services"
        }
    ],
    "sg:phone":"+39 0522 826997",
    "sg:postcode":"42016",
    "sg:province":"Reggio Nell'Emilia",
    "wof:name":"Cassa Di Risparmio, Di Reggio Emilia Spa",
    "wof:placetype":"venue"
},
  "geometry": {"coordinates":[10.654313,44.920124],"type":"Point"}
}