{
  "type": "Feature",
  "properties": {
    "addr:full":"Via Lioni. 2/4 92019 Sciacca Sciacca Agrigento 92019",
    "addr:housenumber":"2 / 4",
    "addr:postcode":"92019;92019",
    "addr:street":"Via Lioni.",
    "iso:country":"IT",
    "sg:address":"Via Lioni. 2/4 92019 Sciacca",
    "sg:city":"Sciacca",
    "sg:classifiers":[
        {
            "category":"Food & Beverages",
            "subcategory":"Liquor & Beverages",
            "type":"Retail Goods"
        }
    ],
    "sg:phone":"+39 0925 21992",
    "sg:postcode":"92019",
    "sg:province":"Agrigento",
    "sg:tags":[
        "wine",
        "italian"
    ],
    "wof:name":"Enocarboy S..r.l .",
    "wof:placetype":"venue"
},
  "geometry": {"coordinates":[13.077539,37.519821],"type":"Point"}
}