{
  "type": "Feature",
  "properties": {
    "iso:country":"IT",
    "sg:address":"56021 Cascina",
    "sg:city":"Cascina",
    "sg:orig_category":"Alimenti Dietetici, Macrobiotici E Biologici - Vendita Al Dettaglio",
    "sg:phone":"+39 050 742018",
    "sg:postcode":"56021",
    "sg:province":"Pisa",
    "wof:name":"Tenace Marina Eleonora - Nardini Danila",
    "wof:placetype":"venue"
},
  "geometry": {"coordinates":[10.747925,43.67762],"type":"Point"}
}