{
  "type": "Feature",
  "properties": {
    "addr:full":"25075 Nave Nave Brescia 25075",
    "addr:postcode":"25075;25075",
    "iso:country":"IT",
    "sg:address":"25075 Nave",
    "sg:city":"Nave",
    "sg:orig_category":"Arte Ed Artigianato Artistico",
    "sg:phone":"+39 030 253 0082",
    "sg:postcode":"25075",
    "sg:province":"Brescia",
    "wof:name":"Fonderia Fusart F. Lli Loda Srl",
    "wof:placetype":"venue"
},
  "geometry": {"coordinates":[10.251467,45.587399],"type":"Point"}
}