{
  "type": "Feature",
  "properties": {
    "addr:full":"2, Via Piemonte 61020 Petriano Petriano Pesaro E Urbino 61020",
    "addr:postcode":"61020;61020",
    "addr:street":"Via Piemonte",
    "iso:country":"IT",
    "sg:address":"2, Via Piemonte 61020 Petriano",
    "sg:city":"Petriano",
    "sg:classifiers":[
        {
            "category":"Shopping",
            "type":"Retail Goods"
        }
    ],
    "sg:phone":"+39 39072252382",
    "sg:postcode":"61020",
    "sg:province":"Pesaro E Urbino",
    "sg:tags":[
        "finished",
        "-",
        "metallic"
    ],
    "wof:name":"Olimar & C. (s.n.c.)",
    "wof:placetype":"venue"
},
  "geometry": {"coordinates":[12.6953706741,43.7831573486],"type":"Point"}
}