{
  "type": "Feature",
  "properties": {
    "addr:full":"65128 Pescara Pescara Pescara 65128",
    "addr:postcode":"65128;65128",
    "iso:country":"IT",
    "sg:address":"65128 Pescara",
    "sg:city":"Pescara",
    "sg:orig_category":"Valvole E Apparecchiature Di Misura",
    "sg:phone":"+39 085 52889",
    "sg:postcode":"65128",
    "sg:province":"Pescara",
    "wof:name":"Grannonio S.r.l.",
    "wof:placetype":"venue"
},
  "geometry": {"coordinates":[14.205555,42.451401],"type":"Point"}
}