{
  "type": "Feature",
  "properties": {
    "addr:full":"27036 Mortara Mortara Pavia 27036",
    "addr:postcode":"27036;27036",
    "iso:country":"IT",
    "sg:address":"27036 Mortara",
    "sg:city":"Mortara",
    "sg:orig_category":"Prodotti E Manufatti In Materie Plastiche",
    "sg:phone":"+39 0384 99662",
    "sg:postcode":"27036",
    "sg:province":"Pavia",
    "wof:name":"Casa Della Plastica",
    "wof:placetype":"venue"
},
  "geometry": {"coordinates":[9.1557044983,45.1868553162],"type":"Point"}
}