{
  "type": "Feature",
  "properties": {
    "addr:full":"20090 Vimodrone Vimodrone Milano 20090",
    "addr:postcode":"20090;20090",
    "iso:country":"IT",
    "sg:address":"20090 Vimodrone",
    "sg:city":"Vimodrone",
    "sg:orig_category":"Macchine Ed Impianti Per Edilizia E Lavori Pubblici. Macchine, Strumenti Ed Apparecchi Per Attivita' Industriali",
    "sg:phone":"+39 02 250 4784",
    "sg:postcode":"20090",
    "sg:province":"Milano",
    "wof:name":"Cologna Dino & C. (s.a.s.)",
    "wof:placetype":"venue"
},
  "geometry": {"coordinates":[9.299103,45.517197],"type":"Point"}
}