{
  "type": "Feature",
  "properties": {
    "addr:full":"Via Del Lavoro 9 36020 Castegnero Castegnero Vicenza 36020",
    "addr:housenumber":"9",
    "addr:postcode":"36020;36020",
    "addr:street":"Via Del Lavoro",
    "iso:country":"IT",
    "sg:address":"Via Del Lavoro 9 36020 Castegnero",
    "sg:city":"Castegnero",
    "sg:classifiers":[
        {
            "category":"Manufacturing",
            "subcategory":"Rubber & Plastics",
            "type":"Manufacturing & Wholesale Goods"
        }
    ],
    "sg:phone":"+39 0444 730011",
    "sg:postcode":"36020",
    "sg:province":"Vicenza",
    "sg:tags":[
        "household",
        "component",
        "kitchen"
    ],
    "sg:website":"www.plastime.it",
    "wof:name":"Plastime S.p.a.",
    "wof:placetype":"venue"
},
  "geometry": {"coordinates":[11.5966873169,45.4409065247],"type":"Point"}
}