{
  "type": "Feature",
  "properties": {
    "addr:full":"200, Via Ortolani Enrico 00125 Roma Roma Roma 00125",
    "addr:housenumber":"200",
    "addr:postcode":"00125;00125",
    "addr:street":"Via Ortolani Enrico",
    "iso:country":"IT",
    "sg:address":"200, Via Ortolani Enrico 00125 Roma",
    "sg:city":"Roma",
    "sg:classifiers":[
        {
            "category":"Wholesale",
            "subcategory":"Drugs",
            "type":"Manufacturing & Wholesale Goods"
        }
    ],
    "sg:phone":"+39 39065211707",
    "sg:postcode":"00125",
    "sg:province":"Roma",
    "sg:tags":[
        "chemical",
        "pharmaceutical"
    ],
    "wof:name":"Twente Paints Srl",
    "wof:placetype":"venue"
},
  "geometry": {"coordinates":[12.482325,41.895466],"type":"Point"}
}