{
  "type": "Feature",
  "properties": {
    "addr:full":"10128 Torino Torino Torino 10128",
    "addr:postcode":"10128;10128",
    "iso:country":"IT",
    "sg:address":"10128 Torino",
    "sg:city":"Torino",
    "sg:orig_category":"Elettrotecnica Industriale, Prodotti E Apparecchiature. Elettronica Industriale, Prodotti E Apparecchiature. Macchine, Strumenti Ed Apparecchi Per Attivita' Industriali",
    "sg:phone":"+39 011 562 9950",
    "sg:postcode":"10128",
    "sg:province":"Torino",
    "wof:name":"Bosco Marco Eredi Srl",
    "wof:placetype":"venue"
},
  "geometry": {"coordinates":[7.675663,45.060429],"type":"Point"}
}