{
  "type": "Feature",
  "properties": {
    "iso:country":"IT",
    "sg:address":"25080 Manerba Del Garda",
    "sg:city":"Manerba del Garda",
    "sg:classifiers":[
        {
            "category":"Arts & Performance",
            "subcategory":"Dance",
            "type":"Entertainment"
        }
    ],
    "sg:phone":"+39 036 565 4204",
    "sg:postcode":"25080",
    "sg:province":"Brescia",
    "sg:tags":[
        "decorative",
        "craft",
        "objects",
        "furnishings",
        "artistic"
    ],
    "wof:name":"Gardamad Snc",
    "wof:placetype":"venue"
},
  "geometry": {"coordinates":[10.5528535843,45.5495262146],"type":"Point"}
}