{
  "type": "Feature",
  "properties": {
    "iso:country":"IT",
    "sg:address":"06085 Perugia",
    "sg:orig_category":"Macchine Ed Impianti Per Edilizia E Lavori Pubblici. Forniture Per Edilizia E Lavori Pubblici",
    "sg:phone":"+39 075 594 1312",
    "sg:province":"PG",
    "wof:name":"Commoter C. Monni & C. Sas",
    "wof:placetype":"venue"
},
  "geometry": {"coordinates":[-72.892899,41.752853],"type":"Point"}
}