{
  "type": "Feature",
  "properties": {
    "addr:full":"20127 Milano Milano Milano 20127",
    "addr:postcode":"20127;20127",
    "iso:country":"IT",
    "sg:address":"20127 Milano",
    "sg:city":"Milano",
    "sg:orig_category":"Servizi Culturali E Per Lo Spettacolo. Servizi Al Turismo. Acqua, Luce, Gas E Societa' Di Esercizio Pubblico",
    "sg:phone":"+39 02 259 3751",
    "sg:postcode":"20127",
    "sg:province":"Milano",
    "wof:name":"Ditta Gioco Fiaba Di Ciancia Luca E Pizzo Luna",
    "wof:placetype":"venue"
},
  "geometry": {"coordinates":[9.236937,45.502632],"type":"Point"}
}