{
  "type": "Feature",
  "properties": {
    "iso:country":"IT",
    "sg:address":"20127 Milano",
    "sg:city":"Milano",
    "sg:orig_category":"Servizi Editoriali",
    "sg:phone":"+39 02 282 7523",
    "sg:postcode":"20127",
    "sg:province":"Milano",
    "wof:name":"Vranicich Roberto",
    "wof:placetype":"venue"
},
  "geometry": {"coordinates":[9.221231,45.5009],"type":"Point"}
}