{
  "type": "Feature",
  "properties": {
    "addr:full":"31020 Vidor Vidor Treviso 31020",
    "addr:postcode":"31020;31020",
    "iso:country":"IT",
    "sg:address":"31020 Vidor",
    "sg:city":"Vidor",
    "sg:orig_category":"Motori Ed Organi Di Trasmissione. Ricambi E Componenti Dei Mezzi Di Trasporto",
    "sg:phone":"+39 0423 986079",
    "sg:postcode":"31020",
    "sg:province":"Treviso",
    "wof:name":"Piemme Electric Motors S.r.l. - Unipersonale",
    "wof:placetype":"venue"
},
  "geometry": {"coordinates":[12.2509040833,45.733795166],"type":"Point"}
}