{
  "type": "Feature",
  "properties": {
    "iso:country":"IT",
    "sg:address":"70013 Castellana Grotte",
    "sg:city":"Castellana Grotte",
    "sg:orig_category":"Abbigliamento Esterno, Maglierie E Pelliccerie. Shopping",
    "sg:phone":"+39 080 496 5202",
    "sg:postcode":"70013",
    "sg:province":"Bari",
    "wof:name":"L'uomottanta",
    "wof:placetype":"venue"
},
  "geometry": {"coordinates":[17.167664,40.88372],"type":"Point"}
}