{
  "type": "Feature",
  "properties": {
    "addr:full":"20090 Trezzano Sul Naviglio Trezzano sul Naviglio Milano 20090",
    "addr:postcode":"20090;20090",
    "iso:country":"IT",
    "sg:address":"20090 Trezzano Sul Naviglio",
    "sg:city":"Trezzano sul Naviglio",
    "sg:orig_category":"Essenze, Estratti E Prodotti Aromatici Per Alimentari",
    "sg:phone":"+39 02 445 9162",
    "sg:postcode":"20090",
    "sg:province":"Milano",
    "wof:name":"Selvania Srl",
    "wof:placetype":"venue"
},
  "geometry": {"coordinates":[9.073258,45.424034],"type":"Point"}
}