{
  "type": "Feature",
  "properties": {
    "iso:country":"IT",
    "sg:address":"23, Via E. Mattei 29010 Villanova Sull'arda",
    "sg:city":"Villanova",
    "sg:classifiers":[
        {
            "category":"Shopping",
            "type":"Retail Goods"
        }
    ],
    "sg:phone":"+39 0523 837138",
    "sg:postcode":"29010",
    "sg:province":"Piacenza",
    "sg:tags":[
        "finished",
        "-",
        "metallic"
    ],
    "wof:name":"Achilli & Zerbini",
    "wof:placetype":"venue"
},
  "geometry": {"coordinates":[9.6951417923,45.0537719727],"type":"Point"}
}