{
  "type": "Feature",
  "properties": {
    "iso:country":"IT",
    "sg:address":"25080 Padenghe Sul Garda",
    "sg:city":"Padenghe sul Garda",
    "sg:orig_category":"Elettronica Industriale, Prodotti E Apparecchiature",
    "sg:phone":"+39 030 990 8800",
    "sg:postcode":"25080",
    "sg:province":"Brescia",
    "sg:website":"http://www.spazioitalia.it",
    "wof:name":"Spazio Italia Srl",
    "wof:placetype":"venue"
},
  "geometry": {"coordinates":[10.507519,45.510647],"type":"Point"}
}