{
  "type": "Feature",
  "properties": {
    "addr:full":"82030 Limatola Limatola Benevento 82030",
    "addr:postcode":"82030;82030",
    "iso:country":"IT",
    "sg:address":"82030 Limatola",
    "sg:city":"Limatola",
    "sg:orig_category":"Apparecchiature Ed Attrezzature Meccaniche. Ricambi E Componenti Dei Mezzi Di Trasporto",
    "sg:phone":"+39 0823 481124",
    "sg:postcode":"82030",
    "sg:province":"Benevento",
    "wof:name":"Powerflex Srl",
    "wof:placetype":"venue"
},
  "geometry": {"coordinates":[14.412056,41.128357],"type":"Point"}
}