{
  "type": "Feature",
  "properties": {
    "addr:full":"Via Vandalino 12 10095 Grugliasco Grugliasco Torino 10095",
    "addr:housenumber":"12",
    "addr:postcode":"10095;10095",
    "addr:street":"Via Vandalino",
    "iso:country":"IT",
    "sg:address":"Via Vandalino 12 10095 Grugliasco",
    "sg:city":"Grugliasco",
    "sg:classifiers":[
        {
            "category":"Bars & Pubs",
            "subcategory":"Sports Bar",
            "type":"Food & Drink"
        }
    ],
    "sg:phone":"+39 011 411 1866",
    "sg:postcode":"10095",
    "sg:province":"Torino",
    "sg:tags":[
        "dy",
        "forging"
    ],
    "wof:name":"Ready S.r.l.",
    "wof:placetype":"venue"
},
  "geometry": {"coordinates":[7.6070718765,45.071231842],"type":"Point"}
}