{
  "type": "Feature",
  "properties": {
    "addr:full":"21, Via Martiri Della Liberta' 50054 Fucecchio Fucecchio Firenze 50054",
    "addr:postcode":"50054;50054",
    "addr:street":"Via Martiri Della Liberta '",
    "iso:country":"IT",
    "sg:address":"21, Via Martiri Della Liberta' 50054 Fucecchio",
    "sg:city":"Fucecchio",
    "sg:classifiers":[
        {
            "category":"Manufacturing",
            "subcategory":"Rubber & Plastics",
            "type":"Manufacturing & Wholesale Goods"
        }
    ],
    "sg:phone":"+39 39057124731",
    "sg:postcode":"50054",
    "sg:province":"Firenze",
    "wof:name":"Solera Materie Plastiche Srl",
    "wof:placetype":"venue"
},
  "geometry": {"coordinates":[10.8024587631,43.7362136841],"type":"Point"}
}