{
  "type": "Feature",
  "properties": {
    "iso:country":"IT",
    "sg:address":"51031 Agliana",
    "sg:city":"Agliana",
    "sg:orig_category":"Servizi E Lavori Per Abbigliamento E Pelletterie",
    "sg:phone":"+39 0574 750218",
    "sg:postcode":"51031",
    "sg:province":"Pistoia",
    "wof:name":"Centro Rammendo Tessuti (s.n.c.)",
    "wof:placetype":"venue"
},
  "geometry": {"coordinates":[10.986428,43.909512],"type":"Point"}
}