{
  "type": "Feature",
  "properties": {
    "addr:full":"10098 Rivoli Rivoli Torino 10098",
    "addr:postcode":"10098;10098",
    "iso:country":"IT",
    "sg:address":"10098 Rivoli",
    "sg:city":"Rivoli",
    "sg:orig_category":"Motori Ed Organi Di Trasmissione",
    "sg:phone":"+39 011 957 4395",
    "sg:postcode":"10098",
    "sg:province":"Torino",
    "wof:name":"F.b. Di Francesco Bottiglieri",
    "wof:placetype":"venue"
},
  "geometry": {"coordinates":[7.549041748,45.0600662231],"type":"Point"}
}