{
  "type": "Feature",
  "properties": {
    "iso:country":"IT",
    "sg:address":"Via Colonnello Vita 5; Caltabellotta; 92010",
    "sg:city":"Caltabellotta",
    "sg:classifiers":[
        {
            "category":"Banks & Credit Unions",
            "subcategory":"Bank",
            "type":"Services"
        }
    ],
    "sg:phone":"+39 0925 51102",
    "sg:postcode":"92010",
    "sg:province":"Agrigento",
    "wof:name":"Banco Di Sicilia Spa",
    "wof:placetype":"venue"
},
  "geometry": {"coordinates":[13.214078,37.5774],"type":"Point"}
}