{
  "type": "Feature",
  "properties": {
    "addr:full":"74100 Taranto Taranto Taranto 74100",
    "addr:postcode":"74100;74100",
    "iso:country":"IT",
    "sg:address":"74100 Taranto",
    "sg:city":"Taranto",
    "sg:orig_category":"Prodotti E Manufatti In Materie Plastiche. Forniture Per Edilizia E Lavori Pubblici",
    "sg:phone":"+39 099 735 3863",
    "sg:postcode":"74100",
    "sg:province":"Taranto",
    "wof:name":"S.j.m.a.t. Srl",
    "wof:placetype":"venue"
},
  "geometry": {"coordinates":[17.2649517059,40.4602394104],"type":"Point"}
}