{
  "type": "Feature",
  "properties": {
    "iso:country":"IT",
    "sg:address":"59100 Prato",
    "sg:city":"Prato",
    "sg:orig_category":"Servizi Editoriali. Pubblicita', Marketing E Comunicazione",
    "sg:phone":"+39 0574 635774",
    "sg:postcode":"59100",
    "sg:province":"Prato",
    "wof:name":"Eurolegatoria Srl",
    "wof:placetype":"venue"
},
  "geometry": {"coordinates":[11.089884,43.861187],"type":"Point"}
}