{
  "type": "Feature",
  "properties": {
    "iso:country":"IT",
    "sg:address":"Circ Ovest Co In Or Lotto 14b 15048 Valenza",
    "sg:city":"Valenza",
    "sg:classifiers":[
        {
            "category":"Manufacturing",
            "subcategory":"Jewelry",
            "type":"Manufacturing & Wholesale Goods"
        }
    ],
    "sg:phone":"+39 0131 955102",
    "sg:postcode":"15048",
    "sg:province":"Alessandria",
    "sg:tags":[
        "jewel"
    ],
    "sg:website":"www.leopizzo.it",
    "wof:name":"Leo Pizzo Spa",
    "wof:placetype":"venue"
},
  "geometry": {"coordinates":[8.616951,44.913216],"type":"Point"}
}