{
  "type": "Feature",
  "properties": {
    "addr:full":"26010 Pianengo Pianengo Cremona 26010",
    "addr:postcode":"26010;26010",
    "iso:country":"IT",
    "sg:address":"26010 Pianengo",
    "sg:city":"Pianengo",
    "sg:orig_category":"Elettronica Professionale E Di Consumo. Musica",
    "sg:phone":"+39 0373 74264",
    "sg:postcode":"26010",
    "sg:province":"Cremona",
    "wof:name":"Denti Fratelli S.n.c.",
    "wof:placetype":"venue"
},
  "geometry": {"coordinates":[9.695683,45.399666],"type":"Point"}
}