{
  "type": "Feature",
  "properties": {
    "iso:country":"IT",
    "sg:address":"28100 Novara",
    "sg:city":"Novara",
    "sg:orig_category":"Condizionamento Aria Impianti - Installazione E Manutenzione",
    "sg:phone":"+39 0321 622330",
    "sg:postcode":"28100",
    "sg:province":"Novara",
    "sg:website":"http://www.aureliagroup.com",
    "wof:name":"Aurelia Group",
    "wof:placetype":"venue"
},
  "geometry": {"coordinates":[8.611785,45.478645],"type":"Point"}
}