{
  "type": "Feature",
  "properties": {
    "addr:full":"11/a, Via Buonriposo 90124 Palermo Palermo Palermo 90124",
    "addr:housenumber":"11 / a",
    "addr:postcode":"90124;90124",
    "addr:street":"Via Buonriposo",
    "iso:country":"IT",
    "sg:address":"11/a, Via Buonriposo 90124 Palermo",
    "sg:city":"Palermo",
    "sg:classifiers":[
        {
            "category":"Wholesale",
            "subcategory":"Machinery & Supplies",
            "type":"Manufacturing & Wholesale Goods"
        }
    ],
    "sg:phone":"+39 091 647 9904",
    "sg:postcode":"90124",
    "sg:province":"Palermo",
    "sg:tags":[
        "-",
        "agriculture",
        "equipment"
    ],
    "wof:name":"Fratelli Guardi' Officina Ricambi Veicoli Industriali (s.r.l.)",
    "wof:placetype":"venue"
},
  "geometry": {"coordinates":[13.361376,38.11562],"type":"Point"}
}