{
  "type": "Feature",
  "properties": {
    "iso:country":"IT",
    "sg:address":"36, Via Podgora 20030 Bovisio Masciago",
    "sg:city":"Bovisio",
    "sg:classifiers":[
        {
            "category":"Professional",
            "subcategory":"Engineering",
            "type":"Services"
        }
    ],
    "sg:phone":"+39 036 259 1532",
    "sg:postcode":"20030",
    "sg:province":"Milano",
    "sg:tags":[
        "machine",
        "-",
        "mechanical"
    ],
    "wof:name":"Coni - Press S.r.l.",
    "wof:placetype":"venue"
},
  "geometry": {"coordinates":[9.163544,45.610889],"type":"Point"}
}