{
  "type": "Feature",
  "properties": {
    "iso:country":"IT",
    "sg:address":"35012 Camposampiero",
    "sg:city":"Camposampiero",
    "sg:orig_category":"Carni, Salumi E Pesci",
    "sg:phone":"+39 049 579 0030",
    "sg:postcode":"35012",
    "sg:province":"Padova",
    "wof:name":"Rio Carni Di Riosa Michele & C. S.a.s.",
    "wof:placetype":"venue"
},
  "geometry": {"coordinates":[11.944629,45.469551],"type":"Point"}
}