{
  "type": "Feature",
  "properties": {
    "iso:country":"IT",
    "sg:address":"50023 Impruneta",
    "sg:city":"Impruneta",
    "sg:orig_category":"Abbigliamento Esterno, Maglierie E Pelliccerie. Shopping",
    "sg:phone":"+39 055 237 4141",
    "sg:postcode":"50023",
    "sg:province":"Firenze",
    "wof:name":"Gibo' Co. Spa",
    "wof:placetype":"venue"
},
  "geometry": {"coordinates":[11.225126,43.723923],"type":"Point"}
}