{
  "type": "Feature",
  "properties": {
    "iso:country":"IT",
    "sg:address":"3/5, Via Gorizia 35010 Vigonza",
    "sg:city":"Vigonza",
    "sg:classifiers":[
        {
            "category":"Personal",
            "subcategory":"Shoe Repair & Shine",
            "type":"Services"
        }
    ],
    "sg:phone":"+39 39049502354",
    "sg:postcode":"35010",
    "sg:province":"Padova",
    "sg:tags":[
        "leather"
    ],
    "wof:name":"Calzaturificio Padana Snc",
    "wof:placetype":"venue"
},
  "geometry": {"coordinates":[11.992149,45.416271],"type":"Point"}
}