{
  "type": "Feature",
  "properties": {
    "addr:full":"15028 Quattordio Quattordio Alessandria 15028",
    "addr:postcode":"15028;15028",
    "iso:country":"IT",
    "sg:address":"15028 Quattordio",
    "sg:city":"Quattordio",
    "sg:orig_category":"Materiali Semilavorati Metallici",
    "sg:phone":"+39 0131 7751",
    "sg:postcode":"15028",
    "sg:province":"Alessandria",
    "wof:name":"Pirelli Cavi E Sistemi Spa",
    "wof:placetype":"venue"
},
  "geometry": {"coordinates":[8.34432,44.935993],"type":"Point"}
}