{
  "type": "Feature",
  "properties": {
    "iso:country":"IT",
    "sg:address":"Via Bertini 51/a; Forli; 47100",
    "sg:classifiers":[
        {
            "category":"Banks & Credit Unions",
            "subcategory":"Bank",
            "type":"Services"
        }
    ],
    "sg:phone":"+39 0543 795101",
    "sg:postcode":"47100",
    "sg:province":"Forl\u00ec-Cesena",
    "wof:name":"Banca Popolare Di Ravenna Spa",
    "wof:placetype":"venue"
},
  "geometry": {"coordinates":[12.064042,44.225315],"type":"Point"}
}