{
  "type": "Feature",
  "properties": {
    "iso:country":"IT",
    "sg:address":"Piazza Cairoli, Ang.; Velletri; 00049",
    "sg:city":"Velletri",
    "sg:classifiers":[
        {
            "category":"Banks & Credit Unions",
            "subcategory":"Bank",
            "type":"Services"
        }
    ],
    "sg:phone":"+39 06 963 0006",
    "sg:postcode":"00049",
    "sg:province":"Roma",
    "wof:name":"Banco Di Roma",
    "wof:placetype":"venue"
},
  "geometry": {"coordinates":[12.782477,41.659153],"type":"Point"}
}