{
  "type": "Feature",
  "properties": {
    "iso:country":"IT",
    "sg:address":"54033 Carrara",
    "sg:city":"Carrara",
    "sg:orig_category":"Studi E Consulenze Amministrative, Commerciali E Aziendali. Consulenze Tecniche, Amministrative E Perizie. Professionisti - Studi E Servizi Ed Associazioni Di Interesse Aziendale",
    "sg:phone":"+39 0585 776742",
    "sg:postcode":"54033",
    "sg:province":"Massa-Carrara",
    "wof:name":"Studio Associato Conti E Giovannetti",
    "wof:placetype":"venue"
},
  "geometry": {"coordinates":[10.103053,44.077034],"type":"Point"}
}