{
  "type": "Feature",
  "properties": {
    "iso:country":"IT",
    "sg:address":"Via Turati F. 953 47020 Pievesestina",
    "sg:orig_category":"Liquid Manure Tank Trucks",
    "sg:phone":"+39 0547 318378",
    "sg:postcode":"47020",
    "sg:province":"Forl\u00ec-Cesena",
    "wof:name":"Nuova Sosma Srl",
    "wof:placetype":"venue"
},
  "geometry": {"coordinates":[12.32827,44.075146],"type":"Point"}
}