{
  "type": "Feature",
  "properties": {
    "addr:full":"48, Via Rigla 24010 Ponteranica Ponteranica Bergamo 24010",
    "addr:postcode":"24010;24010",
    "addr:street":"Via Rigla",
    "iso:country":"IT",
    "sg:address":"48, Via Rigla 24010 Ponteranica",
    "sg:city":"Ponteranica",
    "sg:classifiers":[
        {
            "category":"Manufacturing",
            "subcategory":"Rubber & Plastics",
            "type":"Manufacturing & Wholesale Goods"
        }
    ],
    "sg:phone":"+39 39035574244",
    "sg:postcode":"24010",
    "sg:province":"Bergamo",
    "wof:name":"T.p.e. (s.r.l.)",
    "wof:placetype":"venue"
},
  "geometry": {"coordinates":[9.6479825974,45.7343063354],"type":"Point"}
}