{
  "type": "Feature",
  "properties": {
    "addr:full":"4, Via Della Laguna 30010 Venezia Venezia 30010",
    "addr:postcode":"30010;30010",
    "addr:street":"Via Della Laguna",
    "iso:country":"IT",
    "sg:address":"4, Via Della Laguna 30010 Venezia",
    "sg:classifiers":[
        {
            "category":"Farming",
            "subcategory":"Livestock Farm",
            "type":"Manufacturing & Wholesale Goods"
        }
    ],
    "sg:phone":"+39 041 527 9355",
    "sg:postcode":"30010",
    "sg:province":"Venezia",
    "sg:tags":[
        "agriculture"
    ],
    "wof:name":"C.a.m.e.l. (s.r.l.)",
    "wof:placetype":"venue"
},
  "geometry": {"coordinates":[13.0883798599,45.7766532898],"type":"Point"}
}