{
  "type": "Feature",
  "properties": {
    "iso:country":"IT",
    "sg:address":"Via Cividina 9, 33035 Martignacco, Ud",
    "sg:city":"Martignacco",
    "sg:classifiers":[
        {
            "category":"Banks & Credit Unions",
            "subcategory":"Bank",
            "type":"Services"
        }
    ],
    "sg:postcode":"33035",
    "sg:province":"Udine",
    "wof:name":"Banca Di Credito Cooperativo Del Friuli Centrale Scrl",
    "wof:placetype":"venue"
},
  "geometry": {"coordinates":[13.167036,46.094769],"type":"Point"}
}