{
  "type": "Feature",
  "properties": {
    "iso:country":"IT",
    "sg:address":"00015 Monterotondo",
    "sg:city":"Monterotondo",
    "sg:orig_category":"Servizi Per Lo Sport E Il Tempo Libero. Servizi Al Turismo",
    "sg:phone":"+39 06 906 8137",
    "sg:postcode":"00015",
    "sg:province":"Roma",
    "wof:name":"As. Linea Club Fitness Studio",
    "wof:placetype":"venue"
},
  "geometry": {"coordinates":[12.616412,42.061214],"type":"Point"}
}