{
  "type": "Feature",
  "properties": {
    "addr:full":"36060 Pianezze Pianezze Vicenza 36060",
    "addr:postcode":"36060;36060",
    "iso:country":"IT",
    "sg:address":"36060 Pianezze",
    "sg:city":"Pianezze",
    "sg:orig_category":"Prodotti E Manufatti In Materie Plastiche. Forniture Per Edilizia E Lavori Pubblici",
    "sg:phone":"+39 0424 470660",
    "sg:postcode":"36060",
    "sg:province":"Vicenza",
    "sg:website":"http://www.caronaed.it",
    "wof:name":"Caron A&d",
    "wof:placetype":"venue"
},
  "geometry": {"coordinates":[11.6279811859,45.7407951355],"type":"Point"}
}