{
  "type": "Feature",
  "properties": {
    "iso:country":"IT",
    "sg:address":"32/3, Via Ca' Dell' Orbo 40055 Castenaso",
    "sg:city":"Castenaso",
    "sg:classifiers":[
        {
            "category":"Manufacturing",
            "subcategory":"Motor Vehicles & Parts",
            "type":"Manufacturing & Wholesale Goods"
        }
    ],
    "sg:phone":"+39 39051780384",
    "sg:postcode":"40055",
    "sg:province":"Bologna",
    "sg:tags":[
        "engine"
    ],
    "wof:name":"Pinna Pietro",
    "wof:placetype":"venue"
},
  "geometry": {"coordinates":[11.435254,44.502064],"type":"Point"}
}