{
  "type": "Feature",
  "properties": {
    "addr:full":"20131 Milano Milano Milano 20131",
    "addr:postcode":"20131;20131",
    "iso:country":"IT",
    "sg:address":"20131 Milano",
    "sg:city":"Milano",
    "sg:orig_category":"Case Editrici",
    "sg:phone":"+39 02 277961",
    "sg:postcode":"20131",
    "sg:province":"Milano",
    "sg:website":"http://www.e-duesse.it",
    "wof:name":"Editoriale Duesse Spa",
    "wof:placetype":"venue"
},
  "geometry": {"coordinates":[9.218117,45.480297],"type":"Point"}
}