{
  "type": "Feature",
  "properties": {
    "iso:country":"IT",
    "sg:address":"00146 Roma",
    "sg:city":"Roma",
    "sg:orig_category":"Centri Di Estetica E Cosmesi E Servizi",
    "sg:phone":"+39 06 541 3222",
    "sg:postcode":"00146",
    "sg:province":"Roma",
    "wof:name":"Senso Unico - Gruppo Artistico Parrucchieri",
    "wof:placetype":"venue"
},
  "geometry": {"coordinates":[12.468766,41.852795],"type":"Point"}
}