{
  "type": "Feature",
  "properties": {
    "iso:country":"IT",
    "sg:address":"18, Via Falzes Stegona 39031 Brunico",
    "sg:city":"Brunico",
    "sg:classifiers":[
        {
            "category":"Manufacturing",
            "subcategory":"Tools & Machinery",
            "type":"Manufacturing & Wholesale Goods"
        }
    ],
    "sg:phone":"+39 0474 552201",
    "sg:postcode":"39031",
    "sg:province":"Bolzano/Bozen",
    "sg:tags":[
        "environment",
        "equipment",
        "-"
    ],
    "wof:name":"\u00d6koline S.r.l.",
    "wof:placetype":"venue"
},
  "geometry": {"coordinates":[11.921534,46.792114],"type":"Point"}
}