{
  "type": "Feature",
  "properties": {
    "iso:country":"IT",
    "sg:address":"42025 Cavriago",
    "sg:orig_category":"Prodotti E Manufatti In Materie Plastiche",
    "sg:phone":"+39 0522 942434",
    "sg:postcode":"42025",
    "sg:province":"Reggio Nell'Emilia",
    "wof:name":"Abet Laminati (s.p.a.)",
    "wof:placetype":"venue"
},
  "geometry": {"coordinates":[10.5515327454,44.7148170471],"type":"Point"}
}