{
  "type": "Feature",
  "properties": {
    "iso:country":"IT",
    "sg:address":"98125 Messina",
    "sg:city":"Contesse",
    "sg:orig_category":"Prodotti Alimentari",
    "sg:phone":"+39 090 625 5112",
    "sg:postcode":"98125",
    "sg:province":"Messina",
    "wof:name":"Lagan\u00c0 Rag. Michele",
    "wof:placetype":"venue"
},
  "geometry": {"coordinates":[15.535197258,38.1671257019],"type":"Point"}
}