{
  "type": "Feature",
  "properties": {
    "iso:country":"IT",
    "sg:address":"85016 Pietragalla",
    "sg:city":"Pietragalla",
    "sg:orig_category":"Prodotti Chimici Secondari. Materiali Edili",
    "sg:phone":"+39 0971 944195",
    "sg:postcode":"85016",
    "sg:province":"Potenza",
    "wof:name":"De.da. Edil Di Gruosso Giuseppe",
    "wof:placetype":"venue"
},
  "geometry": {"coordinates":[15.8525152206,40.758556366],"type":"Point"}
}