{
  "type": "Feature",
  "properties": {
    "addr:full":"Via Radici 31/c; Cerredolo; 42010 Reggio Nell'Emilia 42010",
    "addr:housenumber":"31 / c",
    "addr:postcode":"42010;42010",
    "addr:street":"Via Radici;Cerredolo",
    "iso:country":"IT",
    "sg:address":"Via Radici 31/c; Cerredolo; 42010",
    "sg:classifiers":[
        {
            "category":"Banks & Credit Unions",
            "subcategory":"Bank",
            "type":"Services"
        }
    ],
    "sg:phone":"+39 0522 809221",
    "sg:postcode":"42010",
    "sg:province":"Reggio Nell'Emilia",
    "wof:name":"Banca Popolare Di Verona",
    "wof:placetype":"venue"
},
  "geometry": {"coordinates":[10.618174,44.402832],"type":"Point"}
}