{
  "type": "Feature",
  "properties": {
    "addr:full":"Via Postumia, 28/1 31045 Motta Di Livenza Motta di Livenza Treviso 31045",
    "addr:housenumber":"28 / 1",
    "addr:postcode":"31045;31045",
    "addr:street":"Via Postumia",
    "iso:country":"IT",
    "sg:address":"Via Postumia, 28/1 31045 Motta Di Livenza",
    "sg:city":"Motta di Livenza",
    "sg:classifiers":[
        {
            "category":"Food & Beverages",
            "subcategory":"Dairy",
            "type":"Retail Goods"
        }
    ],
    "sg:phone":"+39 0422 768734",
    "sg:postcode":"31045",
    "sg:province":"Treviso",
    "sg:tags":[
        "product",
        "milk"
    ],
    "wof:name":"Latteria E Caseificio Moro Srl",
    "wof:placetype":"venue"
},
  "geometry": {"coordinates":[12.6097106934,45.779132843],"type":"Point"}
}