{
  "type": "Feature",
  "properties": {
    "addr:full":"12033 Moretta Moretta Cuneo 12033",
    "addr:housenumber":"12033",
    "addr:postcode":"12033",
    "addr:street":"Moretta Moretta",
    "iso:country":"IT",
    "sg:address":"12033 Moretta",
    "sg:city":"Moretta",
    "sg:orig_category":"Contenitori In Plastica E Cartone",
    "sg:phone":"+39 0172 94877",
    "sg:postcode":"12033",
    "sg:province":"Cuneo",
    "sg:website":"http://www.neograf.it",
    "wof:name":"Neograf Srl",
    "wof:placetype":"venue"
},
  "geometry": {"coordinates":[8.114513,44.781071],"type":"Point"}
}