{
  "type": "Feature",
  "properties": {
    "iso:country":"IT",
    "sg:address":"Piazza Paracchini 8; Dongo; 22014",
    "sg:city":"Dongo",
    "sg:classifiers":[
        {
            "category":"Banks & Credit Unions",
            "subcategory":"Bank",
            "type":"Services"
        }
    ],
    "sg:phone":"+39 0344 81317",
    "sg:postcode":"22014",
    "sg:province":"Como",
    "wof:name":"Banca Popolare Di Lecco",
    "wof:placetype":"venue"
},
  "geometry": {"coordinates":[9.279579,46.122684],"type":"Point"}
}