{
  "type": "Feature",
  "properties": {
    "iso:country":"IT",
    "sg:address":"Via Don M. Ferrario 14 20010 Buscate",
    "sg:city":"Buscate",
    "sg:classifiers":[
        {
            "category":"Education",
            "subcategory":"College",
            "type":"Public Place"
        }
    ],
    "sg:phone":"+39 0331 803003",
    "sg:postcode":"20010",
    "sg:province":"Milano",
    "sg:tags":[
        "additive"
    ],
    "sg:website":"www.misachem.com",
    "wof:name":"Misachem Srl",
    "wof:placetype":"venue"
},
  "geometry": {"coordinates":[8.813766,45.542252],"type":"Point"}
}