{
  "type": "Feature",
  "properties": {
    "iso:country":"IT",
    "sg:address":"21029 Vergiate",
    "sg:city":"Vergiate",
    "sg:orig_category":"Servizi E Lavori Per Arredamento E Industria Del Legno. Servizi E Lavori Per Edilizia E Lavori Pubblici",
    "sg:phone":"+39 0331 946437",
    "sg:postcode":"21029",
    "sg:province":"Varese",
    "wof:name":"Bressan Erasmo",
    "wof:placetype":"venue"
},
  "geometry": {"coordinates":[8.698695,45.734589],"type":"Point"}
}