{
  "type": "Feature",
  "properties": {
    "iso:country":"IT",
    "sg:address":"00040 Ardea",
    "sg:city":"Ardea",
    "sg:orig_category":"Servizi E Lavori Per Edilizia E Lavori Pubblici. Servizi E Lavori Per Ecologia E Smaltimento Rifiuti",
    "sg:phone":"+39 06 927 8592",
    "sg:postcode":"00040",
    "sg:province":"Roma",
    "sg:website":"http://www.romanambiente.it",
    "wof:name":"Romana Ambiente Srl",
    "wof:placetype":"venue"
},
  "geometry": {"coordinates":[12.642649,41.670456],"type":"Point"}
}