{
  "type": "Feature",
  "properties": {
    "iso:country":"IT",
    "sg:address":"53045 Montepulciano",
    "sg:city":"Montepulciano",
    "sg:orig_category":"Agriturismo",
    "sg:phone":"+39 0578 716905",
    "sg:postcode":"53045",
    "sg:province":"Siena",
    "sg:website":"http://www.martiena.it",
    "wof:name":"Fattoria Martiena Di Paolo Raddi",
    "wof:placetype":"venue"
},
  "geometry": {"coordinates":[11.789631,43.094952],"type":"Point"}
}