{
  "type": "Feature",
  "properties": {
    "addr:full":"23900 Lecco Lecco Lecco 23900",
    "addr:postcode":"23900;23900",
    "iso:country":"IT",
    "sg:address":"23900 Lecco",
    "sg:city":"Lecco",
    "sg:orig_category":"Autoaccessori - Commercio",
    "sg:phone":"+39 0341 360385",
    "sg:postcode":"23900",
    "sg:province":"Lecco",
    "wof:name":"F.l.a.c. Di Gaviraghi Angelo & C. Snc",
    "wof:placetype":"venue"
},
  "geometry": {"coordinates":[9.404644,45.853718],"type":"Point"}
}