{
  "type": "Feature",
  "properties": {
    "addr:full":"37016 Garda Garda Verona 37016",
    "addr:postcode":"37016;37016",
    "iso:country":"IT",
    "sg:address":"37016 Garda",
    "sg:city":"Garda",
    "sg:classifiers":[
        {
            "category":"Restaurant",
            "type":"Food & Drink"
        }
    ],
    "sg:phone":"+39 045 725 5693",
    "sg:postcode":"37016",
    "sg:province":"Verona",
    "sg:tags":[
        "auxiliary",
        "entertainment",
        "premises",
        "related",
        "catering",
        "similar",
        "public",
        "restaurants"
    ],
    "wof:name":"Trattoria Pilleria Bar Affitta Camere Lady",
    "wof:placetype":"venue"
},
  "geometry": {"coordinates":[10.671072,45.571083],"type":"Point"}
}