{
  "type": "Feature",
  "properties": {
    "iso:country":"IT",
    "sg:address":"8, Via Alberogrosso 16044 Cicagna",
    "sg:city":"Cicagna",
    "sg:classifiers":[
        {
            "category":"Professional",
            "subcategory":"Engineering",
            "type":"Services"
        }
    ],
    "sg:phone":"+39 0185 971005",
    "sg:postcode":"16044",
    "sg:province":"Genova",
    "sg:tags":[
        "machine",
        "-",
        "mechanical"
    ],
    "wof:name":"O.m.p. Srl",
    "wof:placetype":"venue"
},
  "geometry": {"coordinates":[9.251446,44.402142],"type":"Point"}
}