{
  "type": "Feature",
  "properties": {
    "iso:country":"IT",
    "sg:address":"125, V. Alpi 63014 Montegranaro",
    "sg:city":"Montegranaro",
    "sg:classifiers":[
        {
            "category":"Personal",
            "subcategory":"Shoe Repair & Shine",
            "type":"Services"
        }
    ],
    "sg:phone":"+39 0734 890951",
    "sg:postcode":"63014",
    "sg:province":"Ascoli Piceno",
    "sg:tags":[
        "leather"
    ],
    "sg:website":"http://www.greatbear.it:ws_end: :mark:ws:http://www.paginegialle.it/greatbear-01",
    "wof:name":"Calzaturificio Great Bear Srl",
    "wof:placetype":"venue"
},
  "geometry": {"coordinates":[13.646888,43.258656],"type":"Point"}
}