{
  "type": "Feature",
  "properties": {
    "iso:country":"IT",
    "sg:address":"Via Todeschini 8 24030 Mozzo",
    "sg:city":"Mozzo",
    "sg:classifiers":[
        {
            "category":"Manufacturing",
            "subcategory":"Rubber & Plastics",
            "type":"Manufacturing & Wholesale Goods"
        }
    ],
    "sg:phone":"+39 035 611211",
    "sg:postcode":"24030",
    "sg:province":"Bergamo",
    "sg:tags":[
        "made",
        "drawing",
        "supply"
    ],
    "sg:website":"www.bergamoexport.it",
    "wof:name":"Arta Sas",
    "wof:placetype":"venue"
},
  "geometry": {"coordinates":[9.608298,45.703091],"type":"Point"}
}