{
  "type": "Feature",
  "properties": {
    "iso:country":"IT",
    "sg:address":"00126 Acilia",
    "sg:orig_category":"Alberghi E Strutture Extra Alberghiere. Ospedali E Servizi Sanitari",
    "sg:phone":"+39 06 5235 2914",
    "sg:postcode":"00126",
    "sg:province":"Roma",
    "wof:name":"Casa Di Riposo Giovanni Xxiii",
    "wof:placetype":"venue"
},
  "geometry": {"coordinates":[12.365297,41.788307],"type":"Point"}
}