{
  "type": "Feature",
  "properties": {
    "iso:country":"IT",
    "sg:address":"00034 Colleferro",
    "sg:city":"Colleferro",
    "sg:orig_category":"Forniture Per Agricoltura E Zootecnia",
    "sg:phone":"+39 06 9730 5029",
    "sg:postcode":"00034",
    "sg:province":"Roma",
    "wof:name":"Marcoccia Andrea",
    "wof:placetype":"venue"
},
  "geometry": {"coordinates":[13.0074672699,41.7316665649],"type":"Point"}
}