{
  "type": "Feature",
  "properties": {
    "iso:country":"IT",
    "sg:address":"20026 Novate Milanese",
    "sg:city":"Novate Milanese",
    "sg:orig_category":"Lavorazioni Meccaniche E Servizi",
    "sg:phone":"+39 02 354 8899",
    "sg:postcode":"20026",
    "sg:province":"Milano",
    "wof:name":"Ambrosio Raffaele",
    "wof:placetype":"venue"
},
  "geometry": {"coordinates":[9.134357,45.534813],"type":"Point"}
}