{
  "type": "Feature",
  "properties": {
    "addr:full":"00199 Roma Roma Roma 00199",
    "addr:postcode":"00199;00199",
    "iso:country":"IT",
    "sg:address":"00199 Roma",
    "sg:city":"Roma",
    "sg:orig_category":"Scuole E Servizi Scolastici. Ospedali E Servizi Sanitari",
    "sg:phone":"+39 06 8620 2449",
    "sg:postcode":"00199",
    "sg:province":"Roma",
    "wof:name":"Centro Di Audiofonologopedia Srl",
    "wof:placetype":"venue"
},
  "geometry": {"coordinates":[12.508831,41.928925],"type":"Point"}
}