{
  "type": "Feature",
  "properties": {
    "iso:country":"IT",
    "sg:address":"13894 Gaglianico",
    "sg:city":"Gaglianico",
    "sg:orig_category":"Servizi E Lavori Per Abbigliamento E Pelletterie",
    "sg:phone":"+39 015 542056",
    "sg:postcode":"13894",
    "sg:province":"Biella",
    "wof:name":"Gomitolatura Mariella",
    "wof:placetype":"venue"
},
  "geometry": {"coordinates":[8.080592,45.542389],"type":"Point"}
}