{
  "type": "Feature",
  "properties": {
    "iso:country":"IT",
    "sg:address":"V F De Stefano 84; Solofra; 83029",
    "sg:city":"Solofra",
    "sg:classifiers":[
        {
            "category":"Banks & Credit Unions",
            "subcategory":"Bank",
            "type":"Services"
        }
    ],
    "sg:phone":"+39 0825 581374",
    "sg:postcode":"83029",
    "sg:province":"Avellino",
    "wof:name":"Banca Popolare Dell'irpinia",
    "wof:placetype":"venue"
},
  "geometry": {"coordinates":[14.848747,40.831005],"type":"Point"}
}