{
  "type": "Feature",
  "properties": {
    "iso:country":"IT",
    "sg:address":"28845 Domodossola",
    "sg:city":"Domodossola",
    "sg:classifiers":[
        {
            "category":"Professional",
            "subcategory":"Business Services",
            "type":"Services"
        }
    ],
    "sg:phone":"+39 0324 248534",
    "sg:postcode":"28845",
    "sg:province":"Verbano-Cusio-Ossola",
    "sg:tags":[
        "support",
        "companies",
        "events",
        "trade"
    ],
    "wof:name":"Elena Cristian - Ristorante Biglia",
    "wof:placetype":"venue"
},
  "geometry": {"coordinates":[8.272465,46.139969],"type":"Point"}
}