{
  "type": "Feature",
  "properties": {
    "addr:full":"99, Via Xi Febbraio 20090 Vimodrone Vimodrone Milano 20090",
    "addr:postcode":"20090;20090",
    "addr:street":"Via Xi Febbraio",
    "iso:country":"IT",
    "sg:address":"99, Via Xi Febbraio 20090 Vimodrone",
    "sg:city":"Vimodrone",
    "sg:classifiers":[
        {
            "category":"Professional",
            "subcategory":"Engineering",
            "type":"Services"
        }
    ],
    "sg:phone":"+39 390 225 0781",
    "sg:postcode":"20090",
    "sg:province":"Milano",
    "sg:tags":[
        "machine",
        "-",
        "mechanical"
    ],
    "wof:name":"Millipore (s.p.a.)",
    "wof:placetype":"venue"
},
  "geometry": {"coordinates":[9.188141,45.463688],"type":"Point"}
}