{
  "type": "Feature",
  "properties": {
    "addr:full":"20020 Lainate Lainate Milano 20020",
    "addr:postcode":"20020;20020",
    "iso:country":"IT",
    "sg:address":"20020 Lainate",
    "sg:city":"Lainate",
    "sg:orig_category":"Forniture Per Edilizia E Lavori Pubblici",
    "sg:phone":"+39 02 9325 6353",
    "sg:postcode":"20020",
    "sg:province":"Milano",
    "wof:name":"Porro Francesco",
    "wof:placetype":"venue"
},
  "geometry": {"coordinates":[9.0391626358,45.5263023376],"type":"Point"}
}