{
  "type": "Feature",
  "properties": {
    "addr:full":"37060 Sona Sona Verona 37060",
    "addr:postcode":"37060;37060",
    "iso:country":"IT",
    "sg:address":"37060 Sona",
    "sg:city":"Sona",
    "sg:orig_category":"Servizi E Lavori Per Industria Alimentare E Bevande",
    "sg:phone":"+39 045 608 1282",
    "sg:postcode":"37060",
    "sg:province":"Verona",
    "wof:name":"Rossi Fratelli",
    "wof:placetype":"venue"
},
  "geometry": {"coordinates":[11.312815,45.352665],"type":"Point"}
}