{
  "type": "Feature",
  "properties": {
    "iso:country":"IT",
    "sg:address":"46045 Marmirolo",
    "sg:city":"Marmirolo",
    "sg:orig_category":"Automobili E Mezzi Di Trasporto",
    "sg:phone":"+39 0376 294094",
    "sg:postcode":"46045",
    "sg:province":"Mantova",
    "sg:website":"http://autojolli.it",
    "wof:name":"Auto Jolli",
    "wof:placetype":"venue"
},
  "geometry": {"coordinates":[10.762666,45.207962],"type":"Point"}
}