{
  "type": "Feature",
  "properties": {
    "addr:full":"31015 Conegliano Conegliano Treviso 31015",
    "addr:postcode":"31015;31015",
    "iso:country":"IT",
    "sg:address":"31015 Conegliano",
    "sg:city":"Conegliano",
    "sg:orig_category":"Elettrodomestici. Forniture Alle Strutture Ricettive",
    "sg:phone":"+39 0438 418035",
    "sg:postcode":"31015",
    "sg:province":"Treviso",
    "wof:name":"Gemm Srl",
    "wof:placetype":"venue"
},
  "geometry": {"coordinates":[12.313325,45.887653],"type":"Point"}
}