{
  "type": "Feature",
  "properties": {
    "addr:full":"74017 Mottola Mottola Taranto 74017",
    "addr:postcode":"74017;74017",
    "iso:country":"IT",
    "sg:address":"74017 Mottola",
    "sg:city":"Mottola",
    "sg:orig_category":"Prodotti Finiti Stampati. Forniture E Prodotti Informatici. Forniture Per Uffici",
    "sg:phone":"+39 099 886 1163",
    "sg:postcode":"74017",
    "sg:province":"Taranto",
    "wof:name":"Modul Cont Srl",
    "wof:placetype":"venue"
},
  "geometry": {"coordinates":[17.0303230286,40.6656951904],"type":"Point"}
}