{
  "type": "Feature",
  "properties": {
    "iso:country":"IT",
    "sg:address":"12/4, Via Monteu Roero 10022 Carmagnola",
    "sg:city":"Carmagnola",
    "sg:classifiers":[
        {
            "category":"Shopping",
            "type":"Retail Goods"
        }
    ],
    "sg:phone":"+39 011 972 3562",
    "sg:postcode":"10022",
    "sg:province":"Torino",
    "sg:tags":[
        "finished",
        "-",
        "metallic"
    ],
    "wof:name":"C.a.m. Costruz. Attrez. Meccaniche Srl",
    "wof:placetype":"venue"
},
  "geometry": {"coordinates":[7.7392430305,44.8528213501],"type":"Point"}
}