{
  "type": "Feature",
  "properties": {
    "addr:full":"37017 Lazise Lazise Verona 37017",
    "addr:postcode":"37017;37017",
    "iso:country":"IT",
    "sg:address":"37017 Lazise",
    "sg:city":"Lazise",
    "sg:orig_category":"Elettrotecnica Industriale, Prodotti E Apparecchiature. Elettronica Industriale, Prodotti E Apparecchiature",
    "sg:phone":"+39 045 647 0673",
    "sg:postcode":"37017",
    "sg:province":"Verona",
    "wof:name":"Emmegi Gruppi Elettrogeni (s.r.l.)",
    "wof:placetype":"venue"
},
  "geometry": {"coordinates":[10.761741,45.492832],"type":"Point"}
}