{
  "type": "Feature",
  "properties": {
    "addr:full":"23868 Valmadrera Valmadrera Lecco 23868",
    "addr:postcode":"23868;23868",
    "iso:country":"IT",
    "sg:address":"23868 Valmadrera",
    "sg:city":"Valmadrera",
    "sg:orig_category":"Motori Ed Organi Di Trasmissione",
    "sg:phone":"+39 0341 581116",
    "sg:postcode":"23868",
    "sg:province":"Lecco",
    "wof:name":"Carrera (s.n.c.)",
    "wof:placetype":"venue"
},
  "geometry": {"coordinates":[9.3682146072,45.8545188904],"type":"Point"}
}