{
  "type": "Feature",
  "properties": {
    "addr:full":"20030 Senago Senago Milano 20030",
    "addr:postcode":"20030;20030",
    "iso:country":"IT",
    "sg:address":"20030 Senago",
    "sg:city":"Senago",
    "sg:orig_category":"Lavorazioni Metalli, Stampaggio E Saldatura",
    "sg:phone":"+39 02 9905 5378",
    "sg:postcode":"20030",
    "sg:province":"Milano",
    "wof:name":"Dalla Bona Sergio",
    "wof:placetype":"venue"
},
  "geometry": {"coordinates":[9.161985,45.569992],"type":"Point"}
}