{
  "type": "Feature",
  "properties": {
    "iso:country":"IT",
    "sg:address":"Via Volta 26a 20052 Monza",
    "sg:city":"Monza",
    "sg:classifiers":[
        {
            "category":"Real Estate",
            "subcategory":"Surveying",
            "type":"Services"
        }
    ],
    "sg:phone":"+39 039 386196",
    "sg:postcode":"20052",
    "sg:province":"Milano",
    "sg:tags":[
        "stationery",
        "writing",
        "material",
        "creative"
    ],
    "wof:name":"Cartoleria Ravasi Di Siluri Roberto",
    "wof:placetype":"venue"
},
  "geometry": {"coordinates":[9.185298,45.538681],"type":"Point"}
}