{
  "type": "Feature",
  "properties": {
    "iso:country":"IT",
    "sg:address":"Via Italia 197; Busnago; 20040",
    "sg:city":"Busnago",
    "sg:classifiers":[
        {
            "category":"Banks & Credit Unions",
            "subcategory":"Bank",
            "type":"Services"
        }
    ],
    "sg:phone":"+39 039 609 5889",
    "sg:postcode":"20040",
    "sg:province":"Milano",
    "wof:name":"Istituto Bancario, San Paolo Di Torino Spa",
    "wof:placetype":"venue"
},
  "geometry": {"coordinates":[9.476277,45.619282],"type":"Point"}
}