{
  "type": "Feature",
  "properties": {
    "iso:country":"IT",
    "sg:address":"46, Corso Vigevano 10155 Torino",
    "sg:city":"Torino",
    "sg:classifiers":[
        {
            "category":"Communications",
            "subcategory":"Television Station",
            "type":"Services"
        }
    ],
    "sg:phone":"+39 011 248 7390",
    "sg:postcode":"10155",
    "sg:province":"Torino",
    "sg:tags":[
        "equipment",
        "optical",
        "instrument"
    ],
    "wof:name":"Multimmagine Di Fugolo Luciano & C. (s.a.s.)",
    "wof:placetype":"venue"
},
  "geometry": {"coordinates":[7.682322,45.089886],"type":"Point"}
}