{
  "type": "Feature",
  "properties": {
    "addr:full":"90129 Palermo Palermo Palermo 90129",
    "addr:postcode":"90129;90129",
    "iso:country":"IT",
    "sg:address":"90129 Palermo",
    "sg:city":"Palermo",
    "sg:orig_category":"Manufacturers: Prefabbricati",
    "sg:phone":"+39 091 485987",
    "sg:postcode":"90129",
    "sg:province":"Palermo",
    "wof:name":"L'arte Del Gesso Di Messina Nicolo'",
    "wof:placetype":"venue"
},
  "geometry": {"coordinates":[13.330498,38.105789],"type":"Point"}
}