{
  "type": "Feature",
  "properties": {
    "addr:full":"Via Giuseppe Di Vittorio 55 15076 Ovada Ovada Alessandria 15076",
    "addr:housenumber":"55",
    "addr:postcode":"15076;15076",
    "addr:street":"Via Giuseppe Di Vittorio",
    "iso:country":"IT",
    "sg:address":"Via Giuseppe Di Vittorio 55 15076 Ovada",
    "sg:city":"Ovada",
    "sg:classifiers":[
        {
            "category":"Wholesale",
            "subcategory":"Chemicals & Plastics",
            "type":"Manufacturing & Wholesale Goods"
        }
    ],
    "sg:phone":"+39 0143 80494",
    "sg:postcode":"15076",
    "sg:province":"Alessandria",
    "sg:tags":[
        "cleaning",
        "surface"
    ],
    "wof:name":"Kemika Spa",
    "wof:placetype":"venue"
},
  "geometry": {"coordinates":[8.609364,44.619595],"type":"Point"}
}