{
  "type": "Feature",
  "properties": {
    "addr:full":"16016 Cogoleto Cogoleto Genova 16016",
    "addr:postcode":"16016;16016",
    "iso:country":"IT",
    "sg:address":"16016 Cogoleto",
    "sg:city":"Cogoleto",
    "sg:orig_category":"Petroli, Gas E Combustibili",
    "sg:phone":"+39 800 112 277",
    "sg:postcode":"16016",
    "sg:province":"Genova",
    "wof:name":"Shell Gas Italia Spa",
    "wof:placetype":"venue"
},
  "geometry": {"coordinates":[8.6611824036,44.395740509],"type":"Point"}
}