{
  "type": "Feature",
  "properties": {
    "addr:full":"20090 Pantigliate Pantigliate Milano 20090",
    "addr:postcode":"20090;20090",
    "iso:country":"IT",
    "sg:address":"20090 Pantigliate",
    "sg:city":"Pantigliate",
    "sg:orig_category":"Trasporti Internazionali",
    "sg:phone":"+39 02 906021",
    "sg:postcode":"20090",
    "sg:province":"Milano",
    "sg:website":"http://www.francovago.com",
    "wof:name":"Franco Vago Spa",
    "wof:placetype":"venue"
},
  "geometry": {"coordinates":[9.352025,45.433365],"type":"Point"}
}