{
  "type": "Feature",
  "properties": {
    "iso:country":"IT",
    "sg:address":"20056 Trezzo Sull'adda",
    "sg:orig_category":"Metalli E Leghe",
    "sg:phone":"+39 02 9098 0145",
    "sg:postcode":"20056",
    "sg:province":"Milano",
    "wof:name":"Metal Trade Industry Srl",
    "wof:placetype":"venue"
},
  "geometry": {"coordinates":[9.5235462189,45.6070976257],"type":"Point"}
}