{
  "type": "Feature",
  "properties": {
    "iso:country":"IT",
    "sg:address":"40057 Granarolo Dell'emilia",
    "sg:orig_category":"Macchine, Impianti E Forniture Per Industria Grafica, Cartaria E Cartotecnica",
    "sg:phone":"+39 051 760604",
    "sg:postcode":"40057",
    "sg:province":"Bologna",
    "wof:name":"Renkalik (s.r.l.)",
    "wof:placetype":"venue"
},
  "geometry": {"coordinates":[11.439745,44.547112],"type":"Point"}
}