{
  "type": "Feature",
  "properties": {
    "addr:full":"3, Piazza Maria Teresa 10123 Torino Torino Torino 10123",
    "addr:postcode":"10123;10123",
    "addr:street":"Piazza Maria Teresa",
    "iso:country":"IT",
    "sg:address":"3, Piazza Maria Teresa 10123 Torino",
    "sg:city":"Torino",
    "sg:classifiers":[
        {
            "category":"Manufacturing",
            "subcategory":"Printing",
            "type":"Manufacturing & Wholesale Goods"
        }
    ],
    "sg:phone":"+39 011 839 4505",
    "sg:postcode":"10123",
    "sg:province":"Torino",
    "sg:tags":[
        "publishing"
    ],
    "wof:name":"Vele Spiegate Edizioni Musicali Di Fabrizio Mazzardo E C.s.a.s.",
    "wof:placetype":"venue"
},
  "geometry": {"coordinates":[7.5794358253,45.0236549377],"type":"Point"}
}