{
  "type": "Feature",
  "properties": {
    "iso:country":"IT",
    "sg:address":"23900 Lecco",
    "sg:city":"Lecco",
    "sg:orig_category":"Mobili Giardini E Terrazzi",
    "sg:phone":"+39 0341 283610",
    "sg:postcode":"23900",
    "sg:province":"Lecco",
    "sg:website":"http://www.zanellatocarlo.it",
    "wof:name":"Zanellato Carlo",
    "wof:placetype":"venue"
},
  "geometry": {"coordinates":[9.3900232315,45.8507499695],"type":"Point"}
}