{
  "type": "Feature",
  "properties": {
    "iso:country":"IT",
    "sg:address":"Via Monte Ortigara 25 36040 Grisignano Di Zocco",
    "sg:city":"Grisignano di Zocco",
    "sg:classifiers":[
        {
            "category":"Building & Trades",
            "subcategory":"Construction",
            "type":"Services"
        }
    ],
    "sg:phone":"+39 0444 614509",
    "sg:postcode":"36040",
    "sg:province":"Vicenza",
    "sg:tags":[
        "granite",
        "working"
    ],
    "wof:name":"Arcaro Graniti Sas",
    "wof:placetype":"venue"
},
  "geometry": {"coordinates":[11.699825,45.477188],"type":"Point"}
}