{
  "type": "Feature",
  "properties": {
    "iso:country":"IT",
    "sg:address":"1, Via Guido Rossa 40050 Monteveglio",
    "sg:city":"Monteveglio",
    "sg:classifiers":[
        {
            "category":"Professional",
            "subcategory":"Engineering",
            "type":"Services"
        }
    ],
    "sg:phone":"+39 39051832543",
    "sg:postcode":"40050",
    "sg:province":"Bologna",
    "sg:tags":[
        "machine",
        "-",
        "mechanical"
    ],
    "wof:name":"Deublin Italiana S.r.l.",
    "wof:placetype":"venue"
},
  "geometry": {"coordinates":[11.17182,44.516014],"type":"Point"}
}