{
  "type": "Feature",
  "properties": {
    "iso:country":"IT",
    "sg:address":"25017 Lonato",
    "sg:city":"Lonato",
    "sg:orig_category":"Arredi Ed Attrezzature Per Uffici",
    "sg:phone":"+39 030 912 0151",
    "sg:postcode":"25017",
    "sg:province":"Brescia",
    "wof:name":"Zanoni Franco",
    "wof:placetype":"venue"
},
  "geometry": {"coordinates":[10.515557,45.488117],"type":"Point"}
}