{
  "type": "Feature",
  "properties": {
    "iso:country":"IT",
    "sg:address":"Via Dante Ruffini 22 26100 Cremona",
    "sg:city":"Cremona",
    "sg:orig_category":"Trailers, Semi-trailers",
    "sg:phone":"+39 0372 454139",
    "sg:postcode":"26100",
    "sg:province":"Cremona",
    "sg:website":"www.multitrax.it",
    "wof:name":"Multitrax Srl",
    "wof:placetype":"venue"
},
  "geometry": {"coordinates":[10.039937,45.138836],"type":"Point"}
}