{
  "type": "Feature",
  "properties": {
    "addr:full":"73, Via Della Produzione Chiusa Di Ginestreto 61025 Montelabbate Montelabbate Pesaro E Urbino 61025",
    "addr:postcode":"61025;61025",
    "addr:street":"Via Della Produzione;Di Ginestreto",
    "iso:country":"IT",
    "sg:address":"73, Via Della Produzione Chiusa Di Ginestreto 61025 Montelabbate",
    "sg:city":"Montelabbate",
    "sg:classifiers":[
        {
            "category":"Manufacturing",
            "subcategory":"Metals",
            "type":"Manufacturing & Wholesale Goods"
        }
    ],
    "sg:phone":"+39 0721 481295",
    "sg:postcode":"61025",
    "sg:province":"Pesaro E Urbino",
    "sg:tags":[
        "processing"
    ],
    "wof:name":"Rima Di Mantaroni Marzia & C. Sas",
    "wof:placetype":"venue"
},
  "geometry": {"coordinates":[12.5298032761,43.633556366],"type":"Point"}
}