{
  "type": "Feature",
  "properties": {
    "addr:full":"11, Via Dettori Giovanni Maria 09124 Cagliari Cagliari Cagliari 09124",
    "addr:postcode":"09124;09124",
    "addr:street":"Via Dettori Giovanni Maria",
    "iso:country":"IT",
    "sg:address":"11, Via Dettori Giovanni Maria 09124 Cagliari",
    "sg:city":"Cagliari",
    "sg:classifiers":[
        {
            "category":"Shopping",
            "subcategory":"Crafts & Fabrics",
            "type":"Retail Goods"
        }
    ],
    "sg:phone":"+39 39070658423",
    "sg:postcode":"09124",
    "sg:province":"Cagliari",
    "sg:tags":[
        "linen"
    ],
    "wof:name":"La Via Della Seta",
    "wof:placetype":"venue"
},
  "geometry": {"coordinates":[9.1092281342,39.2154579163],"type":"Point"}
}