{
  "type": "Feature",
  "properties": {
    "addr:full":"20134 Milano Milano Milano 20134",
    "addr:postcode":"20134;20134",
    "iso:country":"IT",
    "sg:address":"20134 Milano",
    "sg:city":"Milano",
    "sg:orig_category":"Cine-foto-ottica",
    "sg:phone":"+39 02 215 3443",
    "sg:postcode":"20134",
    "sg:province":"Milano",
    "wof:name":"Imago Press Di Mario Finazzi & C. (s.a.s.)",
    "wof:placetype":"venue"
},
  "geometry": {"coordinates":[9.246098,45.491261],"type":"Point"}
}