{
  "type": "Feature",
  "properties": {
    "iso:country":"IT",
    "sg:address":"37051 Bovolone",
    "sg:city":"Bovolone",
    "sg:orig_category":"Ceramiche: Prodotti E Lavorazioni",
    "sg:phone":"+39 045 690 0588",
    "sg:postcode":"37051",
    "sg:province":"Verona",
    "sg:website":"http://www.centroceramiche.it",
    "wof:name":"Centro Ceramiche Di Puttini Cristian",
    "wof:placetype":"venue"
},
  "geometry": {"coordinates":[11.09851,45.272766],"type":"Point"}
}