{
  "type": "Feature",
  "properties": {
    "iso:country":"IT",
    "sg:address":"20024 Garbagnate Milanese",
    "sg:city":"Garbagnate Milanese",
    "sg:orig_category":"Chiese Ed Associazioni Religiose",
    "sg:phone":"+39 02 9902 6644",
    "sg:postcode":"20024",
    "sg:province":"Milano",
    "wof:name":"Chiesa Apostolica Pentecostale Casa Del Pastore",
    "wof:placetype":"venue"
},
  "geometry": {"coordinates":[9.074162,45.576591],"type":"Point"}
}