{
  "type": "Feature",
  "properties": {
    "iso:country":"IT",
    "sg:address":"42027 Montecchio Emilia",
    "sg:orig_category":"Minuterie Di Precisione",
    "sg:phone":"+39 0522 664138",
    "sg:postcode":"42027",
    "sg:province":"Reggio Nell'Emilia",
    "wof:name":"Laif Di Silvi Ives",
    "wof:placetype":"venue"
},
  "geometry": {"coordinates":[10.4905910492,44.6856079102],"type":"Point"}
}