{
  "type": "Feature",
  "properties": {
    "iso:country":"IT",
    "sg:address":"29, Pl. Del Lavoro 21044 Cavaria Con Premezzo",
    "sg:city":"Cavaria con Premezzo",
    "sg:classifiers":[
        {
            "category":"Shopping",
            "subcategory":"Crafts & Fabrics",
            "type":"Retail Goods"
        }
    ],
    "sg:phone":"+39 0331 218717",
    "sg:postcode":"21044",
    "sg:province":"Varese",
    "sg:website":"http://www.ets-group.it",
    "wof:name":"E.t.s. Srl",
    "wof:placetype":"venue"
},
  "geometry": {"coordinates":[8.8263845444,45.8176040649],"type":"Point"}
}