{
  "type": "Feature",
  "properties": {
    "iso:country":"IT",
    "sg:address":"20146 Milano",
    "sg:city":"Milano",
    "sg:orig_category":"Subacquee Attrezzature - Produzione E Ingrosso",
    "sg:phone":"+39 02 4895 0229",
    "sg:postcode":"20146",
    "sg:province":"Milano",
    "wof:name":"Professional Sport Center Sas Di Bignotti Stefano",
    "wof:placetype":"venue"
},
  "geometry": {"coordinates":[9.146469,45.449856],"type":"Point"}
}