{
  "type": "Feature",
  "properties": {
    "iso:country":"IT",
    "sg:address":"22100 Como",
    "sg:city":"Como",
    "sg:orig_category":"Manufacturers: Prefabbricati",
    "sg:phone":"+39 031 541641",
    "sg:postcode":"22100",
    "sg:province":"Como",
    "wof:name":"Fattorini Carlo",
    "wof:placetype":"venue"
},
  "geometry": {"coordinates":[9.042769,45.831177],"type":"Point"}
}