{
  "type": "Feature",
  "properties": {
    "iso:country":"IT",
    "sg:address":"35030 Veggiano",
    "sg:city":"Veggiano",
    "sg:orig_category":"Tempo Libero - Articoli E Forniture. Automobili E Mezzi Di Trasporto",
    "sg:phone":"+39 049 900 3958",
    "sg:postcode":"35030",
    "sg:province":"Padova",
    "wof:name":"Portosa S.r.l.",
    "wof:placetype":"venue"
},
  "geometry": {"coordinates":[11.801554,45.420937],"type":"Point"}
}