{
  "type": "Feature",
  "properties": {
    "addr:full":"70010 Ceglie Del Campo Bari 70010",
    "addr:postcode":"70010;70010",
    "addr:street":"Del Campo",
    "iso:country":"IT",
    "sg:address":"70010 Ceglie Del Campo",
    "sg:orig_category":"Prodotti Alimentari",
    "sg:phone":"+39 080 565 7088",
    "sg:postcode":"70010",
    "sg:province":"Bari",
    "wof:name":"I. L. Man Srl",
    "wof:placetype":"venue"
},
  "geometry": {"coordinates":[16.8670558929,41.0659141541],"type":"Point"}
}