{
  "type": "Feature",
  "properties": {
    "iso:country":"IT",
    "sg:address":"28010 Ameno",
    "sg:city":"Ameno",
    "sg:orig_category":"Rubinetterie Ed Accessori",
    "sg:phone":"+39 0322 998898",
    "sg:postcode":"28010",
    "sg:province":"Novara",
    "sg:website":"http://www.hesasrl.it",
    "wof:name":"Hesa Srl",
    "wof:placetype":"venue"
},
  "geometry": {"coordinates":[8.442037,45.789703],"type":"Point"}
}