{
  "type": "Feature",
  "properties": {
    "addr:full":"Via Mancini 1-2; Gioiosa Jonica; 89042 Reggio Di Calabria 89042",
    "addr:housenumber":"1-2",
    "addr:postcode":"89042;89042",
    "addr:street":"Via Mancini;Jonica",
    "iso:country":"IT",
    "sg:address":"Via Mancini 1-2; Gioiosa Jonica; 89042",
    "sg:classifiers":[
        {
            "category":"Banks & Credit Unions",
            "subcategory":"Bank",
            "type":"Services"
        }
    ],
    "sg:phone":"+39 0964 51501",
    "sg:postcode":"89042",
    "sg:province":"Reggio Di Calabria",
    "wof:name":"Banco Di Napoli Spa",
    "wof:placetype":"venue"
},
  "geometry": {"coordinates":[16.311062,38.346375],"type":"Point"}
}