{
  "type": "Feature",
  "properties": {
    "iso:country":"IT",
    "sg:address":"04018 Sezze",
    "sg:city":"Sezze",
    "sg:orig_category":"Frutta E Verdura - Ingrosso",
    "sg:phone":"+39 0773 800022",
    "sg:postcode":"04018",
    "sg:province":"Latina",
    "sg:website":"http://www.lasezzese.it",
    "wof:name":"Azienda Agricola La Sezzese Srl",
    "wof:placetype":"venue"
},
  "geometry": {"coordinates":[13.0338935852,41.456199646],"type":"Point"}
}