{
  "type": "Feature",
  "properties": {
    "iso:country":"IT",
    "sg:address":"70031 Andria",
    "sg:city":"Andria",
    "sg:orig_category":"Servizi Ausiliari Di Certificati, Riproduzioni, Disegni E Foto",
    "sg:phone":"+39 339 408 5581",
    "sg:postcode":"70031",
    "sg:province":"Bari",
    "wof:name":"Di Lenardo Gino",
    "wof:placetype":"venue"
},
  "geometry": {"coordinates":[16.296864,41.231808],"type":"Point"}
}