{
  "type": "Feature",
  "properties": {
    "iso:country":"IT",
    "sg:address":"20080 Zibido San Giacomo",
    "sg:city":"Zibido San Giacomo",
    "sg:orig_category":"Gruppi Elettrogeni E Di Continuita'",
    "sg:phone":"+39 02 9000 5269",
    "sg:postcode":"20080",
    "sg:province":"Milano",
    "wof:name":"Electric Services Di Donzelli Roberto",
    "wof:placetype":"venue"
},
  "geometry": {"coordinates":[9.071702,45.42046],"type":"Point"}
}