{
  "type": "Feature",
  "properties": {
    "iso:country":"IT",
    "sg:address":"20147 Milano",
    "sg:city":"Milano",
    "sg:orig_category":"Servizi E Lavori Per Abbigliamento E Pelletterie",
    "sg:phone":"+39 02 403 5850",
    "sg:postcode":"20147",
    "sg:province":"Milano",
    "wof:name":"M.t. S.n.c. Di Rossi Mauro E Rossi Tiziana",
    "wof:placetype":"venue"
},
  "geometry": {"coordinates":[9.188323,45.468887],"type":"Point"}
}