{
  "type": "Feature",
  "properties": {
    "addr:full":"50018 Scandicci Scandicci Firenze 50018",
    "addr:postcode":"50018;50018",
    "iso:country":"IT",
    "sg:address":"50018 Scandicci",
    "sg:city":"Scandicci",
    "sg:orig_category":"Acquari Ornamentali Ed Accessori",
    "sg:phone":"+39 055 252713",
    "sg:postcode":"50018",
    "sg:province":"Firenze",
    "wof:name":"Scali Filippo",
    "wof:placetype":"venue"
},
  "geometry": {"coordinates":[11.20078,43.758152],"type":"Point"}
}