{
  "type": "Feature",
  "properties": {
    "iso:country":"IT",
    "sg:address":"22, Via Matteotti Giacomo 22066 Mariano Comense",
    "sg:city":"Mariano Comense",
    "sg:orig_category":"Miscellaneous Products",
    "sg:phone":"+39 39031745494",
    "sg:postcode":"22066",
    "sg:province":"Como",
    "wof:name":"Biassoni Giuseppe & Figli",
    "wof:placetype":"venue"
},
  "geometry": {"coordinates":[9.0854558945,45.8119659424],"type":"Point"}
}