{
  "type": "Feature",
  "properties": {
    "addr:full":"16, Via Pietrasanta 20087 Robecco Sul Naviglio Robecco sul Naviglio Milano 20087",
    "addr:postcode":"20087;20087",
    "addr:street":"Via Pietrasanta",
    "iso:country":"IT",
    "sg:address":"16, Via Pietrasanta 20087 Robecco Sul Naviglio",
    "sg:city":"Robecco sul Naviglio",
    "sg:classifiers":[
        {
            "category":"Manufacturing",
            "subcategory":"Metals",
            "type":"Manufacturing & Wholesale Goods"
        }
    ],
    "sg:phone":"+39 39029471770",
    "sg:postcode":"20087",
    "sg:province":"Milano",
    "sg:tags":[
        "metallurgy",
        "metalworking"
    ],
    "wof:name":"F.i.u.m. Fabbrica Italiana Utensileria Meccanica S.r.l.",
    "wof:placetype":"venue"
},
  "geometry": {"coordinates":[8.8848485947,45.4392051697],"type":"Point"}
}