{
  "type": "Feature",
  "properties": {
    "addr:full":"23868 Valmadrera Valmadrera Lecco 23868",
    "addr:postcode":"23868;23868",
    "iso:country":"IT",
    "sg:address":"23868 Valmadrera",
    "sg:city":"Valmadrera",
    "sg:orig_category":"Elettrotecnica Industriale, Prodotti E Apparecchiature",
    "sg:phone":"+39 0341 580736",
    "sg:postcode":"23868",
    "sg:province":"Lecco",
    "sg:website":"http://www.eluce.it",
    "wof:name":"\u00c9 Luce Srl",
    "wof:placetype":"venue"
},
  "geometry": {"coordinates":[9.350702,45.850121],"type":"Point"}
}