{
  "type": "Feature",
  "properties": {
    "iso:country":"IT",
    "sg:address":"81020 S.nicola La Strada",
    "sg:orig_category":"Ceramiche: Prodotti E Lavorazioni. Articoli Da Regalo. Arte Ed Artigianato Artistico. Shopping",
    "sg:phone":"+39 0823 452249",
    "sg:postcode":"81020",
    "sg:province":"Caserta",
    "wof:name":"Mec Project Srl",
    "wof:placetype":"venue"
},
  "geometry": {"coordinates":[14.324846,41.032391],"type":"Point"}
}