{
  "type": "Feature",
  "properties": {
    "addr:full":"98122 Messina Messina Messina 98122",
    "addr:postcode":"98122;98122",
    "iso:country":"IT",
    "sg:address":"98122 Messina",
    "sg:city":"Messina",
    "sg:orig_category":"Universita' Ed Istituti Superiori E Liberi",
    "sg:phone":"+39 800 019 773",
    "sg:postcode":"98122",
    "sg:province":"Messina",
    "wof:name":"Cepu Srl",
    "wof:placetype":"venue"
},
  "geometry": {"coordinates":[15.538645,38.199047],"type":"Point"}
}