{
  "type": "Feature",
  "properties": {
    "iso:country":"IT",
    "sg:address":"7, Via Tamagno Francesco 20124 Milano",
    "sg:city":"Milano",
    "sg:classifiers":[
        {
            "category":"Shopping",
            "subcategory":"Computers & Home Electronics",
            "type":"Retail Goods"
        }
    ],
    "sg:phone":"+39 02 2940 9482",
    "sg:postcode":"20124",
    "sg:province":"Milano",
    "sg:tags":[
        "electronic",
        "electrical",
        "equipment"
    ],
    "wof:name":"L'informatica Aziendale Srl",
    "wof:placetype":"venue"
},
  "geometry": {"coordinates":[9.212037,45.482506],"type":"Point"}
}