{
  "type": "Feature",
  "properties": {
    "iso:country":"IT",
    "sg:address":"16149 Genova",
    "sg:city":"Genova",
    "sg:orig_category":"Apparecchiature E Sistemi Per Imballaggio E Confezionamento. Apparecchiature E Sistemi Per Magazzinaggio E Movimentazione",
    "sg:phone":"+39 010 645 0387",
    "sg:postcode":"16149",
    "sg:province":"Genova",
    "wof:name":"C.t.e. Containers S.c.a.r.l.",
    "wof:placetype":"venue"
},
  "geometry": {"coordinates":[8.903655,44.408272],"type":"Point"}
}