{
  "type": "Feature",
  "properties": {
    "iso:country":"IT",
    "sg:address":"20/int.13, V. Darwin 20019 Settimo Milanese",
    "sg:city":"Settimo Milanese",
    "sg:classifiers":[
        {
            "category":"Parking",
            "subcategory":"Lot",
            "type":"Transportation"
        }
    ],
    "sg:phone":"+39 02 3351 2204",
    "sg:postcode":"20019",
    "sg:province":"Milano",
    "sg:tags":[
        "transport",
        "road"
    ],
    "sg:website":"http://www.paginegialle.it/movingservice",
    "wof:name":"Moving Service",
    "wof:placetype":"venue"
},
  "geometry": {"coordinates":[9.058441,45.46381],"type":"Point"}
}