{
  "type": "Feature",
  "properties": {
    "iso:country":"IT",
    "sg:address":"20122 Milano",
    "sg:city":"Milano",
    "sg:classifiers":[
        {
            "category":"Health Services",
            "subcategory":"Health Practitioner",
            "type":"Services"
        }
    ],
    "sg:phone":"+39 02 551 1520",
    "sg:postcode":"20122",
    "sg:province":"Milano",
    "sg:tags":[
        "medici"
    ],
    "wof:name":"Boschi Ermanno",
    "wof:placetype":"venue"
},
  "geometry": {"coordinates":[9.1948,45.463028],"type":"Point"}
}