{
  "type": "Feature",
  "properties": {
    "iso:country":"IT",
    "sg:address":"73017 Sannicola",
    "sg:city":"Sannicola",
    "sg:orig_category":"Non-classified Establishments",
    "sg:phone":"+39 0833 231980",
    "sg:postcode":"73017",
    "sg:province":"Lecce",
    "wof:name":"Vetreria Ciricugno",
    "wof:placetype":"venue"
},
  "geometry": {"coordinates":[18.036156,40.103298],"type":"Point"}
}