{
  "type": "Feature",
  "properties": {
    "addr:full":"73050 Secli' Lecce 73050",
    "addr:postcode":"73050;73050",
    "addr:street":"Secli ' Lecce",
    "iso:country":"IT",
    "sg:address":"73050 Secli'",
    "sg:orig_category":"Materiali Edili",
    "sg:phone":"+39 0836 550018",
    "sg:postcode":"73050",
    "sg:province":"Lecce",
    "wof:name":"Sud Tegole Di Zizzari Luigi",
    "wof:placetype":"venue"
},
  "geometry": {"coordinates":[18.098692,40.13237],"type":"Point"}
}