{
  "type": "Feature",
  "properties": {
    "iso:country":"IT",
    "sg:address":"25062 Concesio",
    "sg:city":"Concesio",
    "sg:orig_category":"Non-classified Establishments",
    "sg:phone":"+39 030 218 0349",
    "sg:postcode":"25062",
    "sg:province":"Brescia",
    "wof:name":"Cauto Cantiere Autolimitazione Cooperativa Sociale A R.l.",
    "wof:placetype":"venue"
},
  "geometry": {"coordinates":[10.204007,45.60791],"type":"Point"}
}