{
  "type": "Feature",
  "properties": {
    "iso:country":"IT",
    "sg:address":"20131 Milano",
    "sg:city":"Milano",
    "sg:orig_category":"Scuole E Servizi Scolastici. Alberghi E Strutture Extra Alberghiere",
    "sg:phone":"+39 02 706 4171",
    "sg:postcode":"20131",
    "sg:province":"Milano",
    "wof:name":"Fondazione Ceur",
    "wof:placetype":"venue"
},
  "geometry": {"coordinates":[9.226463,45.484398],"type":"Point"}
}