{
  "type": "Feature",
  "properties": {
    "addr:full":"57123 Livorno Livorno Livorno 57123",
    "addr:postcode":"57123;57123",
    "iso:country":"IT",
    "sg:address":"57123 Livorno",
    "sg:city":"Livorno",
    "sg:orig_category":"Depurazione E Trattamento Delle Acque - Impianti Ed Apparecchi",
    "sg:phone":"+39 0586 883209",
    "sg:postcode":"57123",
    "sg:province":"Livorno",
    "wof:name":"Nocilli Dr. Osvaldo",
    "wof:placetype":"venue"
},
  "geometry": {"coordinates":[10.311047,43.550613],"type":"Point"}
}