{
  "type": "Feature",
  "properties": {
    "iso:country":"IT",
    "sg:address":"20058 Villasanta",
    "sg:city":"Villasanta",
    "sg:orig_category":"Utensili Meccanici E Materiali",
    "sg:phone":"+39 039 305051",
    "sg:postcode":"20058",
    "sg:province":"Milano",
    "sg:website":"http://www.simespa.com",
    "wof:name":"Sime Spa",
    "wof:placetype":"venue"
},
  "geometry": {"coordinates":[9.207606,45.472046],"type":"Point"}
}