{
  "type": "Feature",
  "properties": {
    "iso:country":"IT",
    "sg:address":"22060 Cabiate",
    "sg:city":"Cabiate",
    "sg:orig_category":"Macchine, Impianti Ed Attrezzature Per Agricoltura E Zootecnia. Macchine E Forniture Per Arredamento E Industria Del Legno",
    "sg:phone":"+39 031 766473",
    "sg:postcode":"22060",
    "sg:province":"Como",
    "wof:name":"A2 Snc",
    "wof:placetype":"venue"
},
  "geometry": {"coordinates":[9.173768,45.674133],"type":"Point"}
}