{
  "type": "Feature",
  "properties": {
    "iso:country":"IT",
    "sg:address":"16, Via Petrarca 33041 Aiello Del Friuli",
    "sg:city":"Aiello del Friuli",
    "sg:classifiers":[
        {
            "category":"Shopping",
            "subcategory":"Clothing, Apparel, & Fashions",
            "type":"Retail Goods"
        }
    ],
    "sg:phone":"+39 39043199555",
    "sg:postcode":"33041",
    "sg:province":"Udine",
    "sg:tags":[
        "clothes"
    ],
    "wof:name":"Dana Sport",
    "wof:placetype":"venue"
},
  "geometry": {"coordinates":[13.230724,46.064941],"type":"Point"}
}