{
  "type": "Feature",
  "properties": {
    "iso:country":"IT",
    "sg:address":"5/h, Via Bernardi Enrico 37026 Pescantina",
    "sg:city":"Pescantina",
    "sg:classifiers":[
        {
            "category":"Shopping",
            "type":"Retail Goods"
        }
    ],
    "sg:phone":"+39 045 670 3333",
    "sg:postcode":"37026",
    "sg:province":"Verona",
    "sg:tags":[
        "finished",
        "-",
        "metallic"
    ],
    "wof:name":"Tekno-salute Srl",
    "wof:placetype":"venue"
},
  "geometry": {"coordinates":[10.9043340683,45.4808387756],"type":"Point"}
}