{
  "type": "Feature",
  "properties": {
    "iso:country":"IT",
    "sg:address":"87100 Cosenza",
    "sg:city":"Cosenza",
    "sg:orig_category":"Articoli Regalo - Vendita Al Dettaglio",
    "sg:phone":"+39 0984 23310",
    "sg:postcode":"87100",
    "sg:province":"Cosenza",
    "sg:website":"http://www.giocart.it",
    "wof:name":"Giocart Srl",
    "wof:placetype":"venue"
},
  "geometry": {"coordinates":[16.248438,39.290596],"type":"Point"}
}