{
  "type": "Feature",
  "properties": {
    "iso:country":"IT",
    "sg:address":"44, Via Casati Felice 20124 Milano",
    "sg:city":"Milano",
    "sg:classifiers":[
        {
            "category":"Building & Trades",
            "subcategory":"Construction",
            "type":"Services"
        }
    ],
    "sg:phone":"+39 02 6671 2923",
    "sg:postcode":"20124",
    "sg:province":"Milano",
    "sg:tags":[
        "work",
        "public"
    ],
    "wof:name":"Impresa Luigi Notari (s.p.a)",
    "wof:placetype":"venue"
},
  "geometry": {"coordinates":[9.199944,45.480446],"type":"Point"}
}