{
  "type": "Feature",
  "properties": {
    "addr:full":"Via Zafigo 18/a 39021 Laces Laces Bolzano/Bozen 39021",
    "addr:housenumber":"18 / a",
    "addr:postcode":"39021;39021",
    "addr:street":"Via Zafigo",
    "iso:country":"IT",
    "sg:address":"Via Zafigo 18/a 39021 Laces",
    "sg:city":"Laces",
    "sg:classifiers":[
        {
            "category":"Food & Beverages",
            "subcategory":"Chocolate",
            "type":"Retail Goods"
        }
    ],
    "sg:phone":"+39 0473 622000",
    "sg:postcode":"39021",
    "sg:province":"Bolzano/Bozen",
    "sg:tags":[
        "export"
    ],
    "wof:name":"Selimex Srl",
    "wof:placetype":"venue"
},
  "geometry": {"coordinates":[11.35800457,46.4967155457],"type":"Point"}
}