{
  "type": "Feature",
  "properties": {
    "iso:country":"IT",
    "sg:address":"65012 Cepagatti",
    "sg:city":"Cepagatti",
    "sg:classifiers":[
        {
            "category":"Manufacturing",
            "subcategory":"Tools & Machinery",
            "type":"Manufacturing & Wholesale Goods"
        }
    ],
    "sg:phone":"+39 085 977 1994",
    "sg:postcode":"65012",
    "sg:province":"Pescara",
    "sg:tags":[
        "machine",
        "system"
    ],
    "wof:name":"F.i.m.a. Srl",
    "wof:placetype":"venue"
},
  "geometry": {"coordinates":[14.125333,42.385166],"type":"Point"}
}