{
  "type": "Feature",
  "properties": {
    "addr:full":"56025 Pontedera La rotta Pisa 56025",
    "addr:postcode":"56025;56025",
    "iso:country":"IT",
    "sg:address":"56025 Pontedera",
    "sg:city":"La rotta",
    "sg:orig_category":"Macchine, Impianti Ed Attrezzature Industria Chimica. Macchine Ed Impianti Per Edilizia E Lavori Pubblici",
    "sg:phone":"+39 0587 484832",
    "sg:postcode":"56025",
    "sg:province":"Pisa",
    "wof:name":"Lombardini Giuseppe Srl",
    "wof:placetype":"venue"
},
  "geometry": {"coordinates":[10.673668,43.660007],"type":"Point"}
}