{
  "type": "Feature",
  "properties": {
    "iso:country":"IT",
    "sg:address":"81025 Marcianise",
    "sg:city":"Marcianise",
    "sg:classifiers":[
        {
            "category":"Professional",
            "subcategory":"Engineering",
            "type":"Services"
        }
    ],
    "sg:phone":"+39 0823 821366",
    "sg:postcode":"81025",
    "sg:province":"Caserta",
    "sg:tags":[
        "equipment",
        "product",
        "industrial",
        "electrical"
    ],
    "sg:website":"http://www.coelmo.it",
    "wof:name":"Co.el.mo. Srl",
    "wof:placetype":"venue"
},
  "geometry": {"coordinates":[14.297743,41.015236],"type":"Point"}
}