{
  "type": "Feature",
  "properties": {
    "addr:full":"41011 Campogalliano Campogalliano Modena 41011",
    "addr:postcode":"41011;41011",
    "iso:country":"IT",
    "sg:address":"41011 Campogalliano",
    "sg:city":"Campogalliano",
    "sg:orig_category":"Macchine E Forniture Per Arredamento E Industria Del Legno",
    "sg:phone":"+39 059 527887",
    "sg:postcode":"41011",
    "sg:province":"Modena",
    "wof:name":"Compa Srl",
    "wof:placetype":"venue"
},
  "geometry": {"coordinates":[10.852588,44.685623],"type":"Point"}
}