{
  "type": "Feature",
  "properties": {
    "iso:country":"IT",
    "sg:address":"Via Lombardia 30 20060 Vignate",
    "sg:city":"Vignate",
    "sg:classifiers":[
        {
            "category":"Real Estate",
            "subcategory":"Real Estate Agent",
            "type":"Services"
        }
    ],
    "sg:phone":"+39 02 959 3981",
    "sg:postcode":"20060",
    "sg:province":"Milano",
    "sg:tags":[
        "manipulator"
    ],
    "sg:website":"www.sytrama.com",
    "wof:name":"Sy.tra.ma. Srl",
    "wof:placetype":"venue"
},
  "geometry": {"coordinates":[9.326863,45.484261],"type":"Point"}
}