{
  "type": "Feature",
  "properties": {
    "iso:country":"IT",
    "sg:address":"41100 Modena",
    "sg:city":"Modena",
    "sg:orig_category":"Sport - Articoli E Forniture",
    "sg:phone":"+39 059 314341",
    "sg:postcode":"41100",
    "sg:province":"Modena",
    "wof:name":"F.a.n. Sport Snc",
    "wof:placetype":"venue"
},
  "geometry": {"coordinates":[10.938716,44.548519],"type":"Point"}
}