{
  "type": "Feature",
  "properties": {
    "iso:country":"IT",
    "sg:address":"20017 Rho",
    "sg:city":"Rho",
    "sg:orig_category":"Arredo Camera Letto E Complementi. Servizi E Lavori Per Arredamento E Industria Del Legno",
    "sg:phone":"+39 02 930 7708",
    "sg:postcode":"20017",
    "sg:province":"Milano",
    "wof:name":"Uboldi Giovanni",
    "wof:placetype":"venue"
},
  "geometry": {"coordinates":[9.043086,45.535995],"type":"Point"}
}