{
  "type": "Feature",
  "properties": {
    "iso:country":"IT",
    "sg:address":"10126 Torino",
    "sg:city":"Torino",
    "sg:orig_category":"Servizi Editoriali",
    "sg:phone":"+39 011 669 0016",
    "sg:postcode":"10126",
    "sg:province":"Torino",
    "wof:name":"Piccin Nuova Libraria Spa",
    "wof:placetype":"venue"
},
  "geometry": {"coordinates":[7.678607,45.048405],"type":"Point"}
}