{
  "type": "Feature",
  "properties": {
    "iso:country":"IT",
    "sg:address":"73020 Santa Cesarea Terme",
    "sg:city":"Santa Cesarea Terme",
    "sg:orig_category":"Terme",
    "sg:phone":"+39 0836 944070",
    "sg:postcode":"73020",
    "sg:province":"Lecce",
    "sg:website":"http://www.termesantacesarea.it",
    "wof:name":"Terme Di Santa Cesarea",
    "wof:placetype":"venue"
},
  "geometry": {"coordinates":[18.457666,40.037354],"type":"Point"}
}