{
  "type": "Feature",
  "properties": {
    "addr:full":"31, Strada Provinciale Tortona 15052 Casalnoceto Casalnoceto Alessandria 15052",
    "addr:postcode":"15052;15052",
    "addr:street":"Strada Provinciale",
    "iso:country":"IT",
    "sg:address":"31, Strada Provinciale Tortona 15052 Casalnoceto",
    "sg:city":"Casalnoceto",
    "sg:classifiers":[
        {
            "category":"Manufacturing",
            "subcategory":"Rubber & Plastics",
            "type":"Manufacturing & Wholesale Goods"
        }
    ],
    "sg:phone":"+39 0131 809406",
    "sg:postcode":"15052",
    "sg:province":"Alessandria",
    "wof:name":"Laminati Srl",
    "wof:placetype":"venue"
},
  "geometry": {"coordinates":[8.9690074921,44.9099998474],"type":"Point"}
}