{
  "type": "Feature",
  "properties": {
    "iso:country":"IT",
    "sg:address":"Via Castaldio, 21/23 42010 Gazzano",
    "sg:classifiers":[
        {
            "category":"Banks & Credit Unions",
            "subcategory":"Investment Brokerage",
            "type":"Services"
        }
    ],
    "sg:phone":"+39 0549 909000",
    "sg:postcode":"42010",
    "sg:province":"Reggio Nell'Emilia",
    "sg:tags":[
        "women's",
        "clothing",
        "accessory"
    ],
    "sg:website":"www.texile.sm",
    "wof:name":"Texile Sa",
    "wof:placetype":"venue"
},
  "geometry": {"coordinates":[10.627794,44.696228],"type":"Point"}
}