{
  "type": "Feature",
  "properties": {
    "addr:full":"90010 Ficarazzi Ficarazzi Palermo 90010",
    "addr:postcode":"90010;90010",
    "iso:country":"IT",
    "sg:address":"90010 Ficarazzi",
    "sg:city":"Ficarazzi",
    "sg:orig_category":"Prodotti Alimentari. Agricoltura, Orticoltura E Floricoltura",
    "sg:phone":"+39 091 614 4674",
    "sg:postcode":"90010",
    "sg:province":"Palermo",
    "wof:name":"Coop. Valle Verde",
    "wof:placetype":"venue"
},
  "geometry": {"coordinates":[13.4689102173,38.0892715454],"type":"Point"}
}