{
  "type": "Feature",
  "properties": {
    "addr:full":"Via Dei Fossi 14/c 59100 Prato Prato Prato 59100",
    "addr:housenumber":"14 / c",
    "addr:postcode":"59100;59100",
    "addr:street":"Via Dei Fossi",
    "iso:country":"IT",
    "sg:address":"Via Dei Fossi 14/c 59100 Prato",
    "sg:city":"Prato",
    "sg:classifiers":[
        {
            "category":"Shopping",
            "subcategory":"Clothing, Apparel, & Fashions",
            "type":"Retail Goods"
        }
    ],
    "sg:phone":"+39 0574 730016",
    "sg:postcode":"59100",
    "sg:province":"Prato",
    "sg:tags":[
        "clothing",
        "fabric"
    ],
    "sg:website":"www.atlanticavannini.it",
    "wof:name":"Atlantica Srl",
    "wof:placetype":"venue"
},
  "geometry": {"coordinates":[11.060114,43.853741],"type":"Point"}
}