{
  "type": "Feature",
  "properties": {
    "iso:country":"IT",
    "sg:address":"33048 S.giovanni Natisone",
    "sg:city":"Medeuzza",
    "sg:orig_category":"Non-classified Establishments",
    "sg:phone":"+39 0432 758025",
    "sg:postcode":"33048",
    "sg:province":"Udine",
    "wof:name":"Zilco Due Srl",
    "wof:placetype":"venue"
},
  "geometry": {"coordinates":[13.394526,45.94553],"type":"Point"}
}