{
  "type": "Feature",
  "properties": {
    "addr:full":"21054 Fagnano Olona Fagnano Olona Varese 21054",
    "addr:postcode":"21054;21054",
    "iso:country":"IT",
    "sg:address":"21054 Fagnano Olona",
    "sg:city":"Fagnano Olona",
    "sg:orig_category":"Tessuti E Stoffe. Filati E Materie Prime Tessili",
    "sg:phone":"+39 0331 361278",
    "sg:postcode":"21054",
    "sg:province":"Varese",
    "wof:name":"Penta Servizi Tessili Srl",
    "wof:placetype":"venue"
},
  "geometry": {"coordinates":[8.866028,45.676376],"type":"Point"}
}