{
  "type": "Feature",
  "properties": {
    "addr:full":"Via Europa 23846 Garbagnate Monastero Garbagnate Monastero Lecco 23846",
    "addr:postcode":"23846;23846",
    "addr:street":"Via Europa",
    "iso:country":"IT",
    "sg:address":"Via Europa 23846 Garbagnate Monastero",
    "sg:city":"Garbagnate Monastero",
    "sg:classifiers":[
        {
            "category":"Shopping",
            "subcategory":"Crafts & Fabrics",
            "type":"Retail Goods"
        }
    ],
    "sg:phone":"+39 031 357 3601",
    "sg:postcode":"23846",
    "sg:province":"Lecco",
    "wof:name":"Enzo Degli Angiuoni Tessitura Srl",
    "wof:placetype":"venue"
},
  "geometry": {"coordinates":[9.294336319,45.7689628601],"type":"Point"}
}