{
  "type": "Feature",
  "properties": {
    "iso:country":"IT",
    "sg:address":"20099 Sesto San Giovanni",
    "sg:city":"Sesto San Giovanni",
    "sg:orig_category":"Tessuti E Stoffe",
    "sg:phone":"+39 02 242 3833",
    "sg:postcode":"20099",
    "sg:province":"Milano",
    "wof:name":"Vemar (s.n.c.)",
    "wof:placetype":"venue"
},
  "geometry": {"coordinates":[9.228272,45.525063],"type":"Point"}
}