{
  "type": "Feature",
  "properties": {
    "addr:full":"70121 Bari Bari Bari 70121",
    "addr:postcode":"70121;70121",
    "iso:country":"IT",
    "sg:address":"70121 Bari",
    "sg:city":"Bari",
    "sg:orig_category":"Articoli Regalo - Vendita Al Dettaglio",
    "sg:phone":"+39 080 523 5472",
    "sg:postcode":"70121",
    "sg:province":"Bari",
    "wof:name":"Profumeria Pepe",
    "wof:placetype":"venue"
},
  "geometry": {"coordinates":[16.8653144836,41.1244354248],"type":"Point"}
}