{
  "type": "Feature",
  "properties": {
    "iso:country":"IT",
    "sg:address":"00183 Roma",
    "sg:city":"Roma",
    "sg:orig_category":"Cinematografia E Radiotelevisione",
    "sg:phone":"+39 06 7720 2817",
    "sg:postcode":"00183",
    "sg:province":"Roma",
    "wof:name":"Diadema Service Sas",
    "wof:placetype":"venue"
},
  "geometry": {"coordinates":[12.51174,41.879978],"type":"Point"}
}