{
  "type": "Feature",
  "properties": {
    "addr:full":"27052 Godiasco Godiasco Pavia 27052",
    "addr:postcode":"27052;27052",
    "iso:country":"IT",
    "sg:address":"27052 Godiasco",
    "sg:city":"Godiasco",
    "sg:orig_category":"Macchine, Impianti Ed Attrezzature Per Industria Alimentare E Bevande",
    "sg:phone":"+39 0383 940018",
    "sg:postcode":"27052",
    "sg:province":"Pavia",
    "wof:name":"Agro 2000 S.r.l.",
    "wof:placetype":"venue"
},
  "geometry": {"coordinates":[9.054148,44.898106],"type":"Point"}
}