{
  "type": "Feature",
  "properties": {
    "iso:country":"IT",
    "sg:address":"50126 Firenze",
    "sg:city":"Firenze",
    "sg:orig_category":"Servizi Ausiliari Dei Mezzi Di Trasporto",
    "sg:phone":"+39 055 682 1482",
    "sg:postcode":"50126",
    "sg:province":"Firenze",
    "wof:name":"Stazione Servizio Vangi Maresco",
    "wof:placetype":"venue"
},
  "geometry": {"coordinates":[10.747909,43.860737],"type":"Point"}
}