{
  "type": "Feature",
  "properties": {
    "iso:country":"IT",
    "sg:address":"Via Della Torre 24 20127 Milano",
    "sg:city":"Milano",
    "sg:classifiers":[
        {
            "category":"Bus Stop",
            "subcategory":"None",
            "type":"Transportation"
        }
    ],
    "sg:phone":"+39 02 289 2641",
    "sg:postcode":"20127",
    "sg:province":"Milano",
    "sg:tags":[
        "switch",
        "electronic"
    ],
    "sg:website":"www.electrica.it",
    "wof:name":"Electrica Srl",
    "wof:placetype":"venue"
},
  "geometry": {"coordinates":[9.223157,45.50074],"type":"Point"}
}