{
  "type": "Feature",
  "properties": {
    "addr:full":"66022 Fossacesia Fossacesia Chieti 66022",
    "addr:postcode":"66022;66022",
    "iso:country":"IT",
    "sg:address":"66022 Fossacesia",
    "sg:city":"Fossacesia",
    "sg:orig_category":"Engineering Societa'",
    "sg:phone":"+39 0872 57724",
    "sg:postcode":"66022",
    "sg:province":"Chieti",
    "sg:website":"http://www.cam-srl.com",
    "wof:name":"C.a.m. Srl",
    "wof:placetype":"venue"
},
  "geometry": {"coordinates":[14.503487,42.224842],"type":"Point"}
}