{
  "type": "Feature",
  "properties": {
    "iso:country":"IT",
    "sg:address":"70121 Bari",
    "sg:city":"Bari",
    "sg:orig_category":"Abbigliamento Esterno, Maglierie E Pelliccerie. Calzature, Pelletterie E Pelli. Shopping",
    "sg:phone":"+39 080 528 3984",
    "sg:postcode":"70121",
    "sg:province":"Bari",
    "wof:name":"The Bridge - Gresim Srl",
    "wof:placetype":"venue"
},
  "geometry": {"coordinates":[16.852179,41.12178],"type":"Point"}
}