{
  "type": "Feature",
  "properties": {
    "iso:country":"IT",
    "sg:address":"47900 Rimini",
    "sg:city":"Rimini",
    "sg:orig_category":"Elettrodomestici. Elettronica Professionale E Di Consumo. Arredi Ed Attrezzature Per Attivita' Commerciali Ed Artigianali. Macchine, Strumenti Ed Apparecchi Per Attivita' Industriali",
    "sg:phone":"+39 0541 772357",
    "sg:postcode":"47900",
    "sg:province":"Rimini",
    "wof:name":"R.c.r. Di Capucci G. - Da Rugna A.& C. Sas",
    "wof:placetype":"venue"
},
  "geometry": {"coordinates":[12.552751,44.026459],"type":"Point"}
}