{
  "type": "Feature",
  "properties": {
    "iso:country":"IT",
    "sg:address":"20010 Bareggio",
    "sg:city":"Bareggio",
    "sg:orig_category":"Vetro: Prodotti E Lavorazioni. Articoli Per Imballaggio E Confezionamento",
    "sg:phone":"+39 02 9036 4184",
    "sg:postcode":"20010",
    "sg:province":"Milano",
    "wof:name":"Vetronaviglio Srl",
    "wof:placetype":"venue"
},
  "geometry": {"coordinates":[9.004573,45.47102],"type":"Point"}
}