{
  "type": "Feature",
  "properties": {
    "iso:country":"IT",
    "sg:address":"20141 Milano",
    "sg:city":"Milano",
    "sg:orig_category":"Servizi Ausiliari Dei Mezzi Di Trasporto",
    "sg:phone":"+39 02 826 6983",
    "sg:postcode":"20141",
    "sg:province":"Milano",
    "wof:name":"Le Meur Marie Autodemolizione",
    "wof:placetype":"venue"
},
  "geometry": {"coordinates":[9.186866,45.416195],"type":"Point"}
}