{
  "type": "Feature",
  "properties": {
    "iso:country":"IT",
    "sg:address":"13045 Gattinara",
    "sg:city":"Gattinara",
    "sg:orig_category":"Antifurto",
    "sg:phone":"+39 0163 833796",
    "sg:postcode":"13045",
    "sg:province":"Vercelli",
    "wof:name":"I.t.m. Sas Di P. Marietta",
    "wof:placetype":"venue"
},
  "geometry": {"coordinates":[8.318778,45.539871],"type":"Point"}
}