{
  "type": "Feature",
  "properties": {
    "addr:full":"36073 Cornedo Vicentino Cornedo Vicentino Vicenza 36073",
    "addr:postcode":"36073;36073",
    "addr:street":"Vicentino",
    "iso:country":"IT",
    "sg:address":"36073 Cornedo Vicentino",
    "sg:city":"Cornedo Vicentino",
    "sg:orig_category":"Forniture Per Abbigliamento E Pelletterie. Impianti, Attrezzature E Forniture Sanitarie Ed Ospedaliere",
    "sg:phone":"+39 0445 430803",
    "sg:postcode":"36073",
    "sg:province":"Vicenza",
    "wof:name":"Diana Di Feriotti Diego",
    "wof:placetype":"venue"
},
  "geometry": {"coordinates":[11.3039398193,45.6356735229],"type":"Point"}
}