{
  "type": "Feature",
  "properties": {
    "addr:full":"06154 Perugia PG",
    "addr:postcode":"06154",
    "addr:street":"Pg",
    "iso:country":"IT",
    "sg:address":"06154 Perugia",
    "sg:orig_category":"Panetterie",
    "sg:phone":"+39 075 393110",
    "sg:province":"PG",
    "wof:name":"Panificio Ponte Snc",
    "wof:placetype":"venue"
},
  "geometry": {"coordinates":[-72.68589782710001,41.7638015747],"type":"Point"}
}