{
  "type": "Feature",
  "properties": {
    "iso:country":"IT",
    "sg:address":"90, Via Verro Bernardino 20141 Milano",
    "sg:city":"Milano",
    "sg:classifiers":[
        {
            "category":"Real Estate",
            "subcategory":"Surveying",
            "type":"Services"
        }
    ],
    "sg:phone":"+39 02 5730 0306",
    "sg:postcode":"20141",
    "sg:province":"Milano",
    "sg:tags":[
        "equipment",
        "material",
        "good",
        "-",
        "handling"
    ],
    "wof:name":"Dimasimma Srl",
    "wof:placetype":"venue"
},
  "geometry": {"coordinates":[9.18986,45.44022],"type":"Point"}
}