{
  "type": "Feature",
  "properties": {
    "addr:full":"20093 Cologno Monzese Cologno Monzese Milano 20093",
    "addr:postcode":"20093;20093",
    "iso:country":"IT",
    "sg:address":"20093 Cologno Monzese",
    "sg:city":"Cologno Monzese",
    "sg:orig_category":"Trattamenti Termici E Superficiali Metalli, Galvanotecnica",
    "sg:phone":"+39 02 254 2567",
    "sg:postcode":"20093",
    "sg:province":"Milano",
    "wof:name":"L'anodica (s.n.c.)",
    "wof:placetype":"venue"
},
  "geometry": {"coordinates":[9.272756,45.534107],"type":"Point"}
}