{
  "type": "Feature",
  "properties": {
    "iso:country":"IT",
    "sg:address":"10125 Torino",
    "sg:city":"Torino",
    "sg:orig_category":"Servizi Di Magazzinaggio E Movimentazione",
    "sg:phone":"+39 011 669 4772",
    "sg:postcode":"10125",
    "sg:province":"Torino",
    "wof:name":"Muller Worldwide Links S.r.l.",
    "wof:placetype":"venue"
},
  "geometry": {"coordinates":[7.577052,45.017765],"type":"Point"}
}