{
  "type": "Feature",
  "properties": {
    "addr:full":"Via Dei Gheghi 28 55010 Segromigno In Piano Lucca 55010",
    "addr:housenumber":"28",
    "addr:postcode":"55010;55010",
    "addr:street":"Via Dei Gheghi;In Piano",
    "iso:country":"IT",
    "sg:address":"Via Dei Gheghi 28 55010 Segromigno In Piano",
    "sg:classifiers":[
        {
            "category":"Personal",
            "subcategory":"Shoe Repair & Shine",
            "type":"Services"
        }
    ],
    "sg:phone":"+39 0583 929672",
    "sg:postcode":"55010",
    "sg:province":"Lucca",
    "sg:tags":[
        "item",
        "finishing"
    ],
    "sg:website":"www.jollyplastsrl.it",
    "wof:name":"Jolly Plast Srl",
    "wof:placetype":"venue"
},
  "geometry": {"coordinates":[10.585415,43.873871],"type":"Point"}
}