{
  "type": "Feature",
  "properties": {
    "iso:country":"IT",
    "sg:address":"60124 Ancona",
    "sg:city":"Ancona",
    "sg:orig_category":"Macchine, Impianti E Forniture Per Industria Grafica, Cartaria E Cartotecnica. Forniture Per Uffici",
    "sg:phone":"+39 071 200825",
    "sg:postcode":"60124",
    "sg:province":"Ancona",
    "wof:name":"Timbro Plastik Snc",
    "wof:placetype":"venue"
},
  "geometry": {"coordinates":[13.519131,43.615784],"type":"Point"}
}