{
  "type": "Feature",
  "properties": {
    "iso:country":"IT",
    "sg:address":"Corso Cavour 18; Novara; 28100",
    "sg:city":"Novara",
    "sg:classifiers":[
        {
            "category":"Banks & Credit Unions",
            "subcategory":"Bank",
            "type":"Services"
        }
    ],
    "sg:phone":"+39 0321 3851",
    "sg:postcode":"28100",
    "sg:province":"Novara",
    "wof:name":"Banca Commerciale Italiana Spa",
    "wof:placetype":"venue"
},
  "geometry": {"coordinates":[8.622142,45.448982],"type":"Point"}
}