{
  "type": "Feature",
  "properties": {
    "addr:full":"20093 Cologno Monzese Cologno Monzese Milano 20093",
    "addr:postcode":"20093;20093",
    "iso:country":"IT",
    "sg:address":"20093 Cologno Monzese",
    "sg:city":"Cologno Monzese",
    "sg:orig_category":"Prodotti Alimentari",
    "sg:phone":"+39 02 254 3297",
    "sg:postcode":"20093",
    "sg:province":"Milano",
    "wof:name":"Lacauzza Sebastiano",
    "wof:placetype":"venue"
},
  "geometry": {"coordinates":[9.2744922638,45.5246086121],"type":"Point"}
}