{
  "type": "Feature",
  "properties": {
    "iso:country":"IT",
    "sg:address":"24060 Brusaporto",
    "sg:city":"Brusaporto",
    "sg:orig_category":"Traslochi",
    "sg:phone":"+39 035 683536",
    "sg:postcode":"24060",
    "sg:province":"Bergamo",
    "wof:name":"Assembly Snc Di Manzoni Angelo E C.",
    "wof:placetype":"venue"
},
  "geometry": {"coordinates":[9.720078,45.682419],"type":"Point"}
}