{
  "type": "Feature",
  "properties": {
    "addr:full":"21, Via Cadabese 37053 Cerea Cerea Verona 37053",
    "addr:postcode":"37053;37053",
    "addr:street":"Via Cadabese",
    "iso:country":"IT",
    "sg:address":"21, Via Cadabese 37053 Cerea",
    "sg:city":"Cerea",
    "sg:classifiers":[
        {
            "category":"Home & Garden",
            "subcategory":"Home Furnishings",
            "type":"Retail Goods"
        }
    ],
    "sg:phone":"+39 39044283651",
    "sg:postcode":"37053",
    "sg:province":"Verona",
    "sg:tags":[
        "household"
    ],
    "wof:name":"Fraven Di Rodegher Tiziana Rodegher Flaviano E C.",
    "wof:placetype":"venue"
},
  "geometry": {"coordinates":[11.174103,45.205692],"type":"Point"}
}