{
  "type": "Feature",
  "properties": {
    "addr:full":"6, Via Friuli 31038 Paese Paese Treviso 31038",
    "addr:postcode":"31038;31038",
    "addr:street":"Via Friuli",
    "iso:country":"IT",
    "sg:address":"6, Via Friuli 31038 Paese",
    "sg:city":"Paese",
    "sg:classifiers":[
        {
            "category":"Shopping",
            "subcategory":"Computers & Home Electronics",
            "type":"Retail Goods"
        }
    ],
    "sg:phone":"+39 390 422 4575",
    "sg:postcode":"31038",
    "sg:province":"Treviso",
    "sg:tags":[
        "electronic",
        "electrical",
        "equipment"
    ],
    "wof:name":"Laguna Light S.p.a.",
    "wof:placetype":"venue"
},
  "geometry": {"coordinates":[12.132405,45.674927],"type":"Point"}
}