{
  "type": "Feature",
  "properties": {
    "iso:country":"IT",
    "sg:address":"Via Papa Giovanni 6; Capaci; 90040",
    "sg:city":"Capaci",
    "sg:classifiers":[
        {
            "category":"Banks & Credit Unions",
            "subcategory":"Bank",
            "type":"Services"
        }
    ],
    "sg:phone":"+39 091 867 2527",
    "sg:postcode":"90040",
    "sg:province":"Palermo",
    "wof:name":"Banco Di Sicilia Spa",
    "wof:placetype":"venue"
},
  "geometry": {"coordinates":[13.238765,38.173054],"type":"Point"}
}