{
  "type": "Feature",
  "properties": {
    "iso:country":"IT",
    "sg:address":"20037 Paderno Dugnano",
    "sg:city":"Paderno Dugnano",
    "sg:orig_category":"Elettronica Industriale, Prodotti E Apparecchiature",
    "sg:phone":"+39 02 918 2783",
    "sg:postcode":"20037",
    "sg:province":"Milano",
    "wof:name":"M.g.m. Srl",
    "wof:placetype":"venue"
},
  "geometry": {"coordinates":[9.174875,45.563877],"type":"Point"}
}