{
  "type": "Feature",
  "properties": {
    "iso:country":"IT",
    "sg:address":"21, Via S. Sebastiano 51100 Pistoia",
    "sg:city":"Pistoia",
    "sg:classifiers":[
        {
            "category":"Utilities",
            "subcategory":"Electric",
            "type":"Services"
        }
    ],
    "sg:phone":"+39 390 573 9221",
    "sg:postcode":"51100",
    "sg:province":"Pistoia",
    "sg:tags":[
        "component",
        "electronic"
    ],
    "wof:name":"Mas Spa",
    "wof:placetype":"venue"
},
  "geometry": {"coordinates":[10.918524,43.932156],"type":"Point"}
}