{
  "type": "Feature",
  "properties": {
    "addr:full":"Via Luppia Alberi 170 35044 Montagnana Montagnana Padova 35044",
    "addr:housenumber":"170",
    "addr:postcode":"35044;35044",
    "addr:street":"Via Luppia Alberi",
    "iso:country":"IT",
    "sg:address":"Via Luppia Alberi 170 35044 Montagnana",
    "sg:city":"Montagnana",
    "sg:classifiers":[
        {
            "category":"Community Center",
            "subcategory":"Senior",
            "type":"Public Place"
        }
    ],
    "sg:phone":"+39 0429 806311",
    "sg:postcode":"35044",
    "sg:province":"Padova",
    "sg:tags":[
        "air-conditioning",
        "ventilation",
        "centralised",
        "installation",
        "system"
    ],
    "sg:website":"www.fastar.com",
    "wof:name":"Fast Spa",
    "wof:placetype":"venue"
},
  "geometry": {"coordinates":[11.428923,45.237087],"type":"Point"}
}