{
  "type": "Feature",
  "properties": {
    "addr:full":"Vle Industria 5 20030 Lentate Sul Seveso Lentate sul Seveso Milano 20030",
    "addr:housenumber":"5",
    "addr:postcode":"20030;20030",
    "addr:street":"Vle Industria",
    "iso:country":"IT",
    "sg:address":"Vle Industria 5 20030 Lentate Sul Seveso",
    "sg:city":"Lentate sul Seveso",
    "sg:orig_category":"Furniture, General",
    "sg:phone":"+39 036 256 4304",
    "sg:postcode":"20030",
    "sg:province":"Milano",
    "sg:website":"www.fratelliboffi.it",
    "wof:name":"Fratelli Boffi Di Boffi Federico & C S.n.c.",
    "wof:placetype":"venue"
},
  "geometry": {"coordinates":[9.1881408691,45.4636878967],"type":"Point"}
}