{
  "type": "Feature",
  "properties": {
    "iso:country":"IT",
    "sg:address":"00042 Anzio",
    "sg:city":"Anzio",
    "sg:orig_category":"Prodotti Di Base E Forniture Per Industria Alimentare E Bevande. Carta, Cartone E Prodotti Primari. Forniture Per Attivita' Commerciali Ed Artigianali",
    "sg:phone":"+39 06 987 0484",
    "sg:postcode":"00042",
    "sg:province":"Roma",
    "wof:name":"Cart Italia Sas Di Tofani Loreto & C.",
    "wof:placetype":"venue"
},
  "geometry": {"coordinates":[12.6358032227,41.4819908142],"type":"Point"}
}