{
  "type": "Feature",
  "properties": {
    "iso:country":"IT",
    "sg:address":"Corso Italia 78; Ceriana; 18034",
    "sg:city":"Ceriana",
    "sg:classifiers":[
        {
            "category":"Banks & Credit Unions",
            "subcategory":"Bank",
            "type":"Services"
        }
    ],
    "sg:phone":"+39 0184 551074",
    "sg:postcode":"18034",
    "sg:province":"Imperia",
    "wof:name":"Banco Ambrosiano Veneto Spa",
    "wof:placetype":"venue"
},
  "geometry": {"coordinates":[7.774278,43.879723],"type":"Point"}
}