{
  "type": "Feature",
  "properties": {
    "iso:country":"IT",
    "sg:address":"20068 Peschiera Borromeo",
    "sg:city":"Peschiera Borromeo",
    "sg:orig_category":"Arredamenti E Mobili Professionali. Arredi Ed Attrezzature Per Uffici",
    "sg:phone":"+39 02 547 2395",
    "sg:postcode":"20068",
    "sg:province":"Milano",
    "wof:name":"Bertolesi Mobili E Scaffalature (s.r.l.)",
    "wof:placetype":"venue"
},
  "geometry": {"coordinates":[9.323743,45.431667],"type":"Point"}
}