{
  "type": "Feature",
  "properties": {
    "addr:full":"31011 Asolo Asolo Treviso 31011",
    "addr:postcode":"31011;31011",
    "iso:country":"IT",
    "sg:address":"31011 Asolo",
    "sg:city":"Asolo",
    "sg:orig_category":"Mobili - Produzione E Ingrosso",
    "sg:phone":"+39 0423 950672",
    "sg:postcode":"31011",
    "sg:province":"Treviso",
    "sg:website":"http://www.assidasolo.com",
    "wof:name":"Assi D'asolo Srl",
    "wof:placetype":"venue"
},
  "geometry": {"coordinates":[11.9228525162,45.7860412598],"type":"Point"}
}