{
  "type": "Feature",
  "properties": {
    "iso:country":"IT",
    "sg:address":"30, Via Cartiera 12045 Fossano",
    "sg:city":"Fossano",
    "sg:classifiers":[
        {
            "category":"Manufacturing",
            "subcategory":"Rubber & Plastics",
            "type":"Manufacturing & Wholesale Goods"
        }
    ],
    "sg:phone":"+39 39017260930",
    "sg:postcode":"12045",
    "sg:province":"Cuneo",
    "wof:name":"Pieffe (s.r.l.)",
    "wof:placetype":"venue"
},
  "geometry": {"coordinates":[7.729228,44.543976],"type":"Point"}
}