{
  "type": "Feature",
  "properties": {
    "iso:country":"IT",
    "sg:address":"54100 Massa",
    "sg:city":"Massa",
    "sg:orig_category":"Cinematografia E Radiotelevisione. Servizi Per Aziende, Manifestazioni E Supporto Agli Scambi Commerciali",
    "sg:phone":"+39 0585 793962",
    "sg:postcode":"54100",
    "sg:province":"Massa-Carrara",
    "sg:website":"http://www.nativedreams.com",
    "wof:name":"Maxisoft Srl - Nativedreams",
    "wof:placetype":"venue"
},
  "geometry": {"coordinates":[10.10463,44.023632],"type":"Point"}
}