{
  "type": "Feature",
  "properties": {
    "addr:full":"80076 Lacco Ameno Lacco Ameno Napoli 80076",
    "addr:postcode":"80076;80076",
    "iso:country":"IT",
    "sg:address":"80076 Lacco Ameno",
    "sg:city":"Lacco Ameno",
    "sg:orig_category":"Automobili E Mezzi Di Trasporto",
    "sg:phone":"+39 081 995440",
    "sg:postcode":"80076",
    "sg:province":"Napoli",
    "wof:name":"Con.bus Ischia Srl",
    "wof:placetype":"venue"
},
  "geometry": {"coordinates":[13.890338,40.750095],"type":"Point"}
}