{
  "type": "Feature",
  "properties": {
    "iso:country":"IT",
    "sg:address":"Via Cesaro 99/g; Erice; 91016",
    "sg:city":"Erice",
    "sg:classifiers":[
        {
            "category":"Banks & Credit Unions",
            "subcategory":"Bank",
            "type":"Services"
        }
    ],
    "sg:phone":"+39 0923 569023",
    "sg:postcode":"91016",
    "sg:province":"Trapani",
    "wof:name":"Banco Di Sicilia Spa",
    "wof:placetype":"venue"
},
  "geometry": {"coordinates":[12.546327,38.029846],"type":"Point"}
}