{
  "type": "Feature",
  "properties": {
    "iso:country":"IT",
    "sg:address":"Via Valtorta 38 20127 Milano",
    "sg:city":"Milano",
    "sg:classifiers":[
        {
            "category":"Park",
            "subcategory":"Provincial",
            "type":"Public Place"
        }
    ],
    "sg:phone":"+39 02 2614 1502",
    "sg:postcode":"20127",
    "sg:province":"Milano",
    "sg:tags":[
        "birthday",
        "card"
    ],
    "wof:name":"Cecami Srl",
    "wof:placetype":"venue"
},
  "geometry": {"coordinates":[9.225698,45.499752],"type":"Point"}
}