{
  "type": "Feature",
  "properties": {
    "iso:country":"IT",
    "sg:address":"87, Strada Sannitica Km.64.500 82037 Telese Terme",
    "sg:city":"Telese Terme",
    "sg:classifiers":[
        {
            "category":"Retail",
            "subcategory":"Animal Services",
            "type":"Services"
        }
    ],
    "sg:phone":"+39 0824 976680",
    "sg:postcode":"82037",
    "sg:province":"Benevento",
    "sg:tags":[
        "breeding"
    ],
    "wof:name":"Mangimi Liverini S.r.l.",
    "wof:placetype":"venue"
},
  "geometry": {"coordinates":[14.781174,41.130447],"type":"Point"}
}