{
  "type": "Feature",
  "properties": {
    "iso:country":"IT",
    "sg:address":"21013 Gallarate",
    "sg:city":"Gallarate",
    "sg:orig_category":"Abbigliamento Sportivo, Jeans E Casuals - Vendita Al Dettaglio",
    "sg:phone":"+39 0331 799140",
    "sg:postcode":"21013",
    "sg:province":"Varese",
    "wof:name":"Ricci Aldo",
    "wof:placetype":"venue"
},
  "geometry": {"coordinates":[8.7918,45.661762],"type":"Point"}
}