{
  "type": "Feature",
  "properties": {
    "iso:country":"IT",
    "sg:address":"1, Via Dell' Industria 36070 Castelgomberto",
    "sg:city":"Castelgomberto",
    "sg:classifiers":[
        {
            "category":"Retail",
            "subcategory":"Animal Services",
            "type":"Services"
        }
    ],
    "sg:phone":"+39 0445 940066",
    "sg:postcode":"36070",
    "sg:province":"Vicenza",
    "sg:tags":[
        "breeding"
    ],
    "wof:name":"F.b.e. Di Fongaro Enrico E C. (s.n.c.)",
    "wof:placetype":"venue"
},
  "geometry": {"coordinates":[11.379334,45.556015],"type":"Point"}
}