{
  "type": "Feature",
  "properties": {
    "addr:full":"Via Nino Bixio 1 Monza (MI) 20052",
    "addr:housenumber":"1",
    "addr:postcode":"20052",
    "addr:street":"Via Nino Bixio",
    "iso:country":"IT",
    "sg:address":"Via Nino Bixio 1",
    "sg:city":"Monza (MI)",
    "sg:classifiers":[
        {
            "category":"Professional",
            "subcategory":"Computer Services",
            "type":"Services"
        }
    ],
    "sg:postcode":"20052",
    "sg:tags":[
        "Open-Source",
        "Software",
        "Mobile",
        "Web-2.0",
        "Mobile-2.0",
        "SyncML",
        "Java",
        "System-Integration",
        "Document-Management",
        "VoIP"
    ],
    "sg:website":"http://www.key-vision.com",
    "wof:name":"KeyVision",
    "wof:placetype":"venue"
},
  "geometry": {"coordinates":[9.285378,45.587212],"type":"Point"}
}