{
  "type": "Feature",
  "properties": {
    "addr:full":"36030 Sarcedo Sarcedo Vicenza 36030",
    "addr:postcode":"36030;36030",
    "iso:country":"IT",
    "sg:address":"36030 Sarcedo",
    "sg:city":"Sarcedo",
    "sg:orig_category":"Pneumatici - Commercio E Riparazione",
    "sg:phone":"+39 0445 884036",
    "sg:postcode":"36030",
    "sg:province":"Vicenza",
    "wof:name":"C.f. Pneumatici Srl",
    "wof:placetype":"venue"
},
  "geometry": {"coordinates":[11.5271577835,45.6943817139],"type":"Point"}
}