{
  "type": "Feature",
  "properties": {
    "iso:country":"IT",
    "sg:address":"Via Nazionale 64 37036 San Martino Buon Albergo",
    "sg:city":"San Martino Buon Albergo",
    "sg:classifiers":[
        {
            "category":"Government",
            "subcategory":"Fire Station",
            "type":"Public Place"
        }
    ],
    "sg:phone":"+39 045 615 9411",
    "sg:postcode":"37036",
    "sg:province":"Verona",
    "sg:tags":[
        "interior",
        "steel",
        "fitting",
        "stainless"
    ],
    "sg:website":"www.at-os.com",
    "wof:name":"At Os Snc",
    "wof:placetype":"venue"
},
  "geometry": {"coordinates":[11.11092,45.421207],"type":"Point"}
}