{
  "type": "Feature",
  "properties": {
    "addr:full":"Corso Roma 53; Cesano Maderno; 20031 Cesano Maderno Milano 20031",
    "addr:housenumber":"53",
    "addr:postcode":"20031;20031",
    "addr:street":"Corso Roma",
    "iso:country":"IT",
    "sg:address":"Corso Roma 53; Cesano Maderno; 20031",
    "sg:city":"Cesano Maderno",
    "sg:classifiers":[
        {
            "category":"Banks & Credit Unions",
            "subcategory":"Bank",
            "type":"Services"
        }
    ],
    "sg:phone":"+39 036 252 1233",
    "sg:postcode":"20031",
    "sg:province":"Milano",
    "wof:name":"Istituto Bancario, San Paolo Di Torino Spa",
    "wof:placetype":"venue"
},
  "geometry": {"coordinates":[9.144736,45.622086],"type":"Point"}
}