{
  "type": "Feature",
  "properties": {
    "addr:full":"Via Independenza 2, 40121 Bologna, Bo Bologna Bologna 40121",
    "addr:housenumber":"2",
    "addr:postcode":"40121;40121",
    "addr:street":"Via Independenza",
    "iso:country":"IT",
    "sg:address":"Via Independenza 2, 40121 Bologna, Bo",
    "sg:city":"Bologna",
    "sg:classifiers":[
        {
            "category":"Banks & Credit Unions",
            "subcategory":"Bank",
            "type":"Services"
        }
    ],
    "sg:postcode":"40121",
    "sg:province":"Bologna",
    "wof:name":"Finemiro Banca Spa",
    "wof:placetype":"venue"
},
  "geometry": {"coordinates":[11.346481,44.494221],"type":"Point"}
}