{
  "type": "Feature",
  "properties": {
    "iso:country":"IT",
    "sg:address":"9, Via Leonardo Da Vinci 26865 San Rocco Al Porto",
    "sg:city":"San Rocco al Porto",
    "sg:classifiers":[
        {
            "category":"Wholesale",
            "subcategory":"Machinery & Supplies",
            "type":"Manufacturing & Wholesale Goods"
        }
    ],
    "sg:phone":"+39 0377 456057",
    "sg:postcode":"26865",
    "sg:province":"Lodi",
    "sg:tags":[
        "equipment",
        "-",
        "instrument",
        "measurement"
    ],
    "wof:name":"Scanvaegt Italia S.r.l.",
    "wof:placetype":"venue"
},
  "geometry": {"coordinates":[9.701961,45.080597],"type":"Point"}
}