{
  "type": "Feature",
  "properties": {
    "iso:country":"IT",
    "sg:address":"47, Viale Dante 07100 Sassari",
    "sg:city":"Sassari",
    "sg:classifiers":[
        {
            "category":"Travel",
            "subcategory":"Travel Agent",
            "type":"Entertainment"
        }
    ],
    "sg:phone":"+39 39079271235",
    "sg:postcode":"07100",
    "sg:province":"Sassari",
    "sg:tags":[
        "business"
    ],
    "wof:name":"Hotel Grazia Deledda",
    "wof:placetype":"venue"
},
  "geometry": {"coordinates":[8.553889,40.729443],"type":"Point"}
}