{
  "type": "Feature",
  "properties": {
    "addr:full":"24034 Cisano Bergamasco Cisano Bergamasco Bergamo 24034",
    "addr:postcode":"24034;24034",
    "iso:country":"IT",
    "sg:address":"24034 Cisano Bergamasco",
    "sg:city":"Cisano Bergamasco",
    "sg:orig_category":"Alberghi E Strutture Extra Alberghiere",
    "sg:phone":"+39 035 781287",
    "sg:postcode":"24034",
    "sg:province":"Bergamo",
    "wof:name":"Hotel Ristorante Fatur Srl",
    "wof:placetype":"venue"
},
  "geometry": {"coordinates":[9.479715,45.739788],"type":"Point"}
}