{
  "type": "Feature",
  "properties": {
    "iso:country":"IT",
    "sg:address":"Via S. S. 17 67039 Sulmona",
    "sg:classifiers":[
        {
            "category":"Manufacturing",
            "subcategory":"Rubber & Plastics",
            "type":"Manufacturing & Wholesale Goods"
        }
    ],
    "sg:phone":"+39 0864 251337",
    "sg:postcode":"67039",
    "sg:province":"L'Aquila",
    "wof:name":"Alaska Di Di Cioccio",
    "wof:placetype":"venue"
},
  "geometry": {"coordinates":[13.9330177307,42.0520019531],"type":"Point"}
}