{
  "type": "Feature",
  "properties": {
    "iso:country":"IT",
    "sg:address":"80057 Sant'antonio Abate",
    "sg:orig_category":"Servizi E Lavori Per Arredamento E Industria Del Legno",
    "sg:phone":"+39 081 873 4668",
    "sg:postcode":"80057",
    "sg:province":"Napoli",
    "wof:name":"Franco Costruzioni Di D'aniello Aniello",
    "wof:placetype":"venue"
},
  "geometry": {"coordinates":[14.5533828735,40.7242355347],"type":"Point"}
}