{
  "type": "Feature",
  "properties": {
    "addr:full":"27010 Cura Carpignano Cura Carpignano Pavia 27010",
    "addr:postcode":"27010;27010",
    "iso:country":"IT",
    "sg:address":"27010 Cura Carpignano",
    "sg:city":"Cura Carpignano",
    "sg:orig_category":"Imballaggi In Legno",
    "sg:phone":"+39 0382 483465",
    "sg:postcode":"27010",
    "sg:province":"Pavia",
    "wof:name":"T.i.c. Srl",
    "wof:placetype":"venue"
},
  "geometry": {"coordinates":[9.2198,45.205051],"type":"Point"}
}