{
  "type": "Feature",
  "properties": {
    "addr:full":"03039 Sora Sora Frosinone 03039",
    "addr:housenumber":"03039",
    "addr:postcode":"03039",
    "iso:country":"IT",
    "sg:address":"03039 Sora",
    "sg:city":"Sora",
    "sg:classifiers":[
        {
            "category":"Manufacturing",
            "subcategory":"Tools & Machinery",
            "type":"Manufacturing & Wholesale Goods"
        }
    ],
    "sg:phone":"+39 0776 832001",
    "sg:postcode":"03039",
    "sg:province":"Frosinone",
    "sg:tags":[
        "machining",
        "mechanical"
    ],
    "wof:name":"Mario Pisani & C. Sas",
    "wof:placetype":"venue"
},
  "geometry": {"coordinates":[13.578402,41.733109],"type":"Point"}
}