{
  "type": "Feature",
  "properties": {
    "addr:full":"Via Juvarra 1; Novara; 28100 Novara Novara 28100",
    "addr:housenumber":"1",
    "addr:postcode":"28100;28100",
    "addr:street":"Via Juvarra",
    "iso:country":"IT",
    "sg:address":"Via Juvarra 1; Novara; 28100",
    "sg:city":"Novara",
    "sg:classifiers":[
        {
            "category":"Banks & Credit Unions",
            "subcategory":"Bank",
            "type":"Services"
        }
    ],
    "sg:phone":"+39 0321 458434",
    "sg:postcode":"28100",
    "sg:province":"Novara",
    "wof:name":"Istituto Bancario, San Paolo Di Torino Spa",
    "wof:placetype":"venue"
},
  "geometry": {"coordinates":[8.618175,45.433479],"type":"Point"}
}