{
  "type": "Feature",
  "properties": {
    "iso:country":"IT",
    "sg:address":"5, Via Perugino 25024 Leno",
    "sg:city":"Leno",
    "sg:classifiers":[
        {
            "category":"Shopping",
            "subcategory":"Clothing, Apparel, & Fashions",
            "type":"Retail Goods"
        }
    ],
    "sg:phone":"+39 030 906 8950",
    "sg:postcode":"25024",
    "sg:province":"Brescia",
    "sg:tags":[
        "clothes"
    ],
    "wof:name":"Eurocucitura Di Sartorelli Iolanda E C. Snc",
    "wof:placetype":"venue"
},
  "geometry": {"coordinates":[10.208011,45.371605],"type":"Point"}
}