{
  "type": "Feature",
  "properties": {
    "iso:country":"IT",
    "sg:address":"90, Via Romana 42028 Poviglio",
    "sg:classifiers":[
        {
            "category":"Shopping",
            "subcategory":"Clothing, Apparel, & Fashions",
            "type":"Retail Goods"
        }
    ],
    "sg:phone":"+39 0522 966098",
    "sg:postcode":"42028",
    "sg:province":"Reggio Nell'Emilia",
    "sg:tags":[
        "clothing",
        "accessory"
    ],
    "wof:name":"Mode Di Moda S.r.l.",
    "wof:placetype":"venue"
},
  "geometry": {"coordinates":[10.627794,44.696228],"type":"Point"}
}