{
  "type": "Feature",
  "properties": {
    "iso:country":"IT",
    "sg:address":"43, V. Colombo 36100 Vicenza",
    "sg:city":"Vicenza",
    "sg:classifiers":[
        {
            "category":"Shopping",
            "subcategory":"Jewelry",
            "type":"Retail Goods"
        }
    ],
    "sg:phone":"+39 0444 564262",
    "sg:postcode":"36100",
    "sg:province":"Vicenza",
    "sg:tags":[
        "jewellery"
    ],
    "sg:website":"http://www.cam-ber.com",
    "wof:name":"Cam-ber Snc",
    "wof:placetype":"venue"
},
  "geometry": {"coordinates":[11.51616,45.556709],"type":"Point"}
}