{
  "type": "Feature",
  "properties": {
    "iso:country":"IT",
    "sg:address":"43029 Traversetolo",
    "sg:city":"Traversetolo",
    "sg:orig_category":"Ceramiche: Prodotti E Lavorazioni",
    "sg:phone":"+39 0521 842355",
    "sg:postcode":"43029",
    "sg:province":"Parma",
    "wof:name":"Ceramiche A.b. Di Anna Beggi",
    "wof:placetype":"venue"
},
  "geometry": {"coordinates":[10.228917,44.714348],"type":"Point"}
}