{
  "type": "Feature",
  "properties": {
    "iso:country":"IT",
    "sg:address":"Via Della Stazione 43 10080 Salassa",
    "sg:city":"Salassa",
    "sg:classifiers":[
        {
            "category":"Bars & Pubs",
            "subcategory":"Sports Bar",
            "type":"Food & Drink"
        }
    ],
    "sg:phone":"+39 0124 36495",
    "sg:postcode":"10080",
    "sg:province":"Torino",
    "sg:tags":[
        "foil",
        "stamping",
        "hot"
    ],
    "wof:name":"Mario Cavaletto Spa",
    "wof:placetype":"venue"
},
  "geometry": {"coordinates":[7.6866188049,45.0705604553],"type":"Point"}
}