{
  "type": "Feature",
  "properties": {
    "iso:country":"IT",
    "sg:address":"80123 Napoli",
    "sg:city":"Napoli",
    "sg:orig_category":"Medici Specialisti - Dermatologia E Malattie Veneree",
    "sg:phone":"+39 081 769 1020",
    "sg:postcode":"80123",
    "sg:province":"Napoli",
    "wof:name":"Studio Dermatologico Belsito",
    "wof:placetype":"venue"
},
  "geometry": {"coordinates":[14.226792,40.831657],"type":"Point"}
}