{
  "type": "Feature",
  "properties": {
    "addr:full":"Via Guglielmo Marconi, 7/9 56020 Santa Maria A Monte Santa Maria a Monte Pisa 56020",
    "addr:housenumber":"7 / 9",
    "addr:postcode":"56020;56020",
    "addr:street":"Via Guglielmo Marconi;Maria A Monte Pisa",
    "iso:country":"IT",
    "sg:address":"Via Guglielmo Marconi, 7/9 56020 Santa Maria A Monte",
    "sg:city":"Santa Maria a Monte",
    "sg:classifiers":[
        {
            "category":"Manufacturing",
            "subcategory":"Rubber & Plastics",
            "type":"Manufacturing & Wholesale Goods"
        }
    ],
    "sg:phone":"+39 0587 707426",
    "sg:postcode":"56020",
    "sg:province":"Pisa",
    "sg:tags":[
        "article"
    ],
    "wof:name":"Martiplast Srl",
    "wof:placetype":"venue"
},
  "geometry": {"coordinates":[10.7126073837,43.6941604614],"type":"Point"}
}