{
  "type": "Feature",
  "properties": {
    "iso:country":"IT",
    "sg:address":"10073 Ciri\u00e8",
    "sg:orig_category":"Ospedali E Servizi Sanitari",
    "sg:phone":"+39 338 925 8043",
    "sg:postcode":"10073",
    "sg:province":"Torino",
    "wof:name":"Pedone Dr. Aniello Psicologo E Psicoterapeuta",
    "wof:placetype":"venue"
},
  "geometry": {"coordinates":[7.594856,45.225658],"type":"Point"}
}