{
  "type": "Feature",
  "properties": {
    "iso:country":"IT",
    "sg:address":"00187 Roma",
    "sg:city":"Roma",
    "sg:orig_category":"Servizi E Lavori Per Edilizia E Lavori Pubblici. Acqua, Luce, Gas E Societa' Di Esercizio Pubblico",
    "sg:phone":"+39 06 4201 4417",
    "sg:postcode":"00187",
    "sg:province":"Roma",
    "wof:name":"Crea Spa",
    "wof:placetype":"venue"
},
  "geometry": {"coordinates":[12.493022,41.906586],"type":"Point"}
}