{
  "type": "Feature",
  "properties": {
    "iso:country":"IT",
    "sg:address":"Km. 22.300, Via Sannitica 81020 San Nicola La Strada",
    "sg:city":"San Nicola la Strada",
    "sg:classifiers":[
        {
            "category":"Manufacturing",
            "subcategory":"Printing",
            "type":"Manufacturing & Wholesale Goods"
        }
    ],
    "sg:phone":"+39 0823 454172",
    "sg:postcode":"81020",
    "sg:province":"Caserta",
    "sg:tags":[
        "publishing"
    ],
    "wof:name":"Paper Service Srl",
    "wof:placetype":"venue"
},
  "geometry": {"coordinates":[14.3321943283,41.0754165649],"type":"Point"}
}