{
  "type": "Feature",
  "properties": {
    "iso:country":"IT",
    "sg:address":"14, Via Salara Dragonara 66020 San Giovanni Teatino",
    "sg:city":"San Giovanni Teatino",
    "sg:classifiers":[
        {
            "category":"Wholesale",
            "subcategory":"Drugs",
            "type":"Manufacturing & Wholesale Goods"
        }
    ],
    "sg:phone":"+39 085 446 3630",
    "sg:postcode":"66020",
    "sg:province":"Chieti",
    "sg:tags":[
        "chemical",
        "pharmaceutical"
    ],
    "wof:name":"Adrizoo Srl",
    "wof:placetype":"venue"
},
  "geometry": {"coordinates":[14.167151,42.351791],"type":"Point"}
}