{
  "type": "Feature",
  "properties": {
    "iso:country":"IT",
    "sg:address":"10, Via Brun Stefano 84131 Salerno",
    "sg:city":"Salerno",
    "sg:classifiers":[
        {
            "category":"Autos & Motor Vehicles",
            "subcategory":"Automobile Sales",
            "type":"Retail Goods"
        }
    ],
    "sg:phone":"+39 089 772 4818",
    "sg:postcode":"84131",
    "sg:province":"Salerno",
    "sg:tags":[
        "motor-cars"
    ],
    "wof:name":"Di Riso S.r.l.",
    "wof:placetype":"venue"
},
  "geometry": {"coordinates":[14.765912056,40.6779556274],"type":"Point"}
}