{
  "type": "Feature",
  "properties": {
    "addr:full":"05100 Terni Terni Terni 05100",
    "addr:postcode":"05100;05100",
    "iso:country":"IT",
    "sg:address":"05100 Terni",
    "sg:city":"Terni",
    "sg:orig_category":"Forniture Alberghi, Bar, Ristoranti E Comunita'",
    "sg:phone":"+39 0744 800233",
    "sg:postcode":"05100",
    "sg:province":"Terni",
    "wof:name":"Divania Snc",
    "wof:placetype":"venue"
},
  "geometry": {"coordinates":[12.5939970016,42.5697135925],"type":"Point"}
}