{
  "type": "Feature",
  "properties": {
    "addr:full":"95127 Catania Catania Catania 95127",
    "addr:postcode":"95127;95127",
    "iso:country":"IT",
    "sg:address":"95127 Catania",
    "sg:city":"Catania",
    "sg:orig_category":"Pompe. Elettrotecnica Industriale, Prodotti E Apparecchiature",
    "sg:phone":"+39 095 712 4695",
    "sg:postcode":"95127",
    "sg:province":"Catania",
    "wof:name":"Inteco Di Gozza G. & C. (s.a.s.)",
    "wof:placetype":"venue"
},
  "geometry": {"coordinates":[15.1132650375,37.5242500305],"type":"Point"}
}