{
  "type": "Feature",
  "properties": {
    "addr:full":"8, Via Sassari 07023 Calangianus Calangianus Olbia-Tempio 07023",
    "addr:postcode":"07023;07023",
    "addr:street":"Via Sassari",
    "iso:country":"IT",
    "sg:address":"8, Via Sassari 07023 Calangianus",
    "sg:city":"Calangianus",
    "sg:classifiers":[
        {
            "category":"Manufacturing",
            "subcategory":"Wood Products",
            "type":"Manufacturing & Wholesale Goods"
        }
    ],
    "sg:phone":"+39 39079660351",
    "sg:postcode":"07023",
    "sg:province":"Olbia-Tempio",
    "sg:tags":[
        "furniture"
    ],
    "wof:name":"Special Sugheri S.r.l.",
    "wof:placetype":"venue"
},
  "geometry": {"coordinates":[9.195298,40.920101],"type":"Point"}
}