{
  "type": "Feature",
  "properties": {
    "iso:country":"IT",
    "sg:address":"20017 Rho",
    "sg:city":"Rho",
    "sg:orig_category":"Servizi E Lavori Per Industria Alimentare E Bevande",
    "sg:phone":"+39 02 9390 1332",
    "sg:postcode":"20017",
    "sg:province":"Milano",
    "wof:name":"Secoedis Servizi Cooperativi E Distribuzione Societa' Cooperativa A R.l.",
    "wof:placetype":"venue"
},
  "geometry": {"coordinates":[9.084416,45.52581],"type":"Point"}
}