{
  "type": "Feature",
  "properties": {
    "iso:country":"IT",
    "sg:address":"00030 San Cesareo",
    "sg:city":"San Cesareo",
    "sg:orig_category":"Legno E Semilavorati",
    "sg:phone":"+39 06 9559 9770",
    "sg:postcode":"00030",
    "sg:province":"Roma",
    "wof:name":"F.lli Pasquali Di Pasquali Antonio E Pio Snc",
    "wof:placetype":"venue"
},
  "geometry": {"coordinates":[12.78696,41.827923],"type":"Point"}
}