{
  "type": "Feature",
  "properties": {
    "iso:country":"IT",
    "sg:address":"64, V. Per Neviano 43029 Traversetolo",
    "sg:city":"Traversetolo",
    "sg:classifiers":[
        {
            "category":"Manufacturing",
            "subcategory":"Food",
            "type":"Manufacturing & Wholesale Goods"
        }
    ],
    "sg:phone":"+39 0521 844184",
    "sg:postcode":"43029",
    "sg:province":"Parma",
    "sg:tags":[
        "equipment",
        "processing",
        "-",
        "machinery"
    ],
    "wof:name":"Gimar Srl - Brovid Group",
    "wof:placetype":"venue"
},
  "geometry": {"coordinates":[10.377117157,44.6222991943],"type":"Point"}
}