{
  "type": "Feature",
  "properties": {
    "addr:full":"Piazza Duccio Galimberti,; Torino; 10134 Torino Torino 10134",
    "addr:postcode":"10134;10134",
    "addr:street":"Piazza Duccio Galimberti",
    "iso:country":"IT",
    "sg:address":"Piazza Duccio Galimberti,; Torino; 10134",
    "sg:city":"Torino",
    "sg:classifiers":[
        {
            "category":"Banks & Credit Unions",
            "subcategory":"Bank",
            "type":"Services"
        }
    ],
    "sg:phone":"+39 011 690862",
    "sg:postcode":"10134",
    "sg:province":"Torino",
    "wof:name":"Banco Di Roma",
    "wof:placetype":"venue"
},
  "geometry": {"coordinates":[7.669436,45.00803],"type":"Point"}
}