{
  "type": "Feature",
  "properties": {
    "iso:country":"IT",
    "sg:address":"20141 Milano",
    "sg:city":"Milano",
    "sg:orig_category":"Utensili Meccanici E Materiali",
    "sg:phone":"+39 02 539 2040",
    "sg:postcode":"20141",
    "sg:province":"Milano",
    "wof:name":"Jongen Italia Srl",
    "wof:placetype":"venue"
},
  "geometry": {"coordinates":[9.198195,45.446499],"type":"Point"}
}