{
  "type": "Feature",
  "properties": {
    "iso:country":"IT",
    "sg:address":"20129 Milano",
    "sg:city":"Milano",
    "sg:orig_category":"Forniture Per Agricoltura E Zootecnia. Prodotti Chimici Secondari",
    "sg:phone":"+39 02 7600 7440",
    "sg:postcode":"20129",
    "sg:province":"Milano",
    "wof:name":"Carrara Dante",
    "wof:placetype":"venue"
},
  "geometry": {"coordinates":[9.207859993,45.4678688049],"type":"Point"}
}