{
  "type": "Feature",
  "properties": {
    "iso:country":"IT",
    "sg:address":"05010 Parrano",
    "sg:city":"Parrano",
    "sg:orig_category":"Materiali Edili",
    "sg:phone":"+39 0763 838039",
    "sg:postcode":"05010",
    "sg:province":"Terni",
    "wof:name":"F.lli Ceccantoni Snc",
    "wof:placetype":"venue"
},
  "geometry": {"coordinates":[12.111259,42.867371],"type":"Point"}
}