{
  "type": "Feature",
  "properties": {
    "addr:full":"89128 Reggio Calabria RC",
    "addr:postcode":"89128",
    "iso:country":"IT",
    "sg:address":"89128 Reggio Calabria",
    "sg:orig_category":"Scuole Di Lingue",
    "sg:phone":"+39 0965 330926",
    "sg:province":"RC",
    "sg:website":"http://www.livinglanguages.it",
    "wof:name":"Living Languages Sas",
    "wof:placetype":"venue"
},
  "geometry": {"coordinates":[15.657382,38.101734],"type":"Point"}
}