{
  "type": "Feature",
  "properties": {
    "addr:full":"23874 Montevecchia Montevecchia Lecco 23874",
    "addr:postcode":"23874;23874",
    "iso:country":"IT",
    "sg:address":"23874 Montevecchia",
    "sg:city":"Montevecchia",
    "sg:orig_category":"Utensili Meccanici E Materiali",
    "sg:phone":"+39 039 993 0524",
    "sg:postcode":"23874",
    "sg:province":"Lecco",
    "sg:website":"http://www.krino.it",
    "wof:name":"Krino Spa",
    "wof:placetype":"venue"
},
  "geometry": {"coordinates":[9.373535,45.704807],"type":"Point"}
}