{
  "type": "Feature",
  "properties": {
    "addr:full":"6, Via Barsanti Eugenio 47100 Forli' Forl\u00ec-Cesena 47100",
    "addr:postcode":"47100;47100",
    "addr:street":"Via Barsanti Eugenio;Forli ' Forli\u0300-Cesena",
    "iso:country":"IT",
    "sg:address":"6, Via Barsanti Eugenio 47100 Forli'",
    "sg:classifiers":[
        {
            "category":"Food & Beverages",
            "subcategory":"Bakery",
            "type":"Retail Goods"
        }
    ],
    "sg:phone":"+39 0543 796153",
    "sg:postcode":"47100",
    "sg:province":"Forl\u00ec-Cesena",
    "sg:tags":[
        "grain",
        "cereal"
    ],
    "wof:name":"Agriflex (s.r.l.)",
    "wof:placetype":"venue"
},
  "geometry": {"coordinates":[11.980461,43.994766],"type":"Point"}
}