{
  "type": "Feature",
  "properties": {
    "iso:country":"IT",
    "sg:address":"Via Dell'artigiano 12 40065 Pianoro",
    "sg:city":"Pianoro",
    "sg:orig_category":"Metal Rounding, Bulging, Folding, Edging, And Bending Machines, Combined",
    "sg:phone":"+39 051 651 7420",
    "sg:postcode":"40065",
    "sg:province":"Bologna",
    "sg:website":"www.comaca.com",
    "wof:name":"Co.ma.ca. Srl",
    "wof:placetype":"venue"
},
  "geometry": {"coordinates":[11.3452033997,44.3948974609],"type":"Point"}
}