{
  "type": "Feature",
  "properties": {
    "addr:full":"Via Roma 20; Prata; 33080 Pordenone 33080",
    "addr:housenumber":"20",
    "addr:postcode":"33080;33080",
    "addr:street":"Via Roma",
    "iso:country":"IT",
    "sg:address":"Via Roma 20; Prata; 33080",
    "sg:classifiers":[
        {
            "category":"Banks & Credit Unions",
            "subcategory":"Bank",
            "type":"Services"
        }
    ],
    "sg:phone":"+39 0434 620000",
    "sg:postcode":"33080",
    "sg:province":"Pordenone",
    "wof:name":"Rolo Banca 1473 Spa",
    "wof:placetype":"venue"
},
  "geometry": {"coordinates":[12.597601,45.893761],"type":"Point"}
}