{
  "type": "Feature",
  "properties": {
    "iso:country":"IT",
    "sg:address":"Via Labiena, 66/a; Laveno Mombello; 21014",
    "sg:city":"Laveno",
    "sg:classifiers":[
        {
            "category":"Banks & Credit Unions",
            "subcategory":"Bank",
            "type":"Services"
        }
    ],
    "sg:phone":"+39 0332 668154",
    "sg:postcode":"21014",
    "sg:province":"Varese",
    "wof:name":"Banca Popolare Di Novara",
    "wof:placetype":"venue"
},
  "geometry": {"coordinates":[8.621157,45.909092],"type":"Point"}
}