{
  "type": "Feature",
  "properties": {
    "addr:full":"23023 Chiesa In Valmalenco Chiesa in Valmalenco Sondrio 23023",
    "addr:postcode":"23023;23023",
    "iso:country":"IT",
    "sg:address":"23023 Chiesa In Valmalenco",
    "sg:city":"Chiesa in Valmalenco",
    "sg:classifiers":[
        {
            "category":"Military Area",
            "subcategory":"Air Force Base",
            "type":"Public Place"
        }
    ],
    "sg:phone":"+39 0342 451119",
    "sg:postcode":"23023",
    "sg:province":"Sondrio",
    "sg:tags":[
        "cave",
        "e",
        "miniere"
    ],
    "sg:website":"http://www.serpentino.it",
    "wof:name":"Nuova Serpentino D'italia Spa",
    "wof:placetype":"venue"
},
  "geometry": {"coordinates":[9.8215360641,46.3061294556],"type":"Point"}
}