{
  "type": "Feature",
  "properties": {
    "iso:country":"IT",
    "sg:address":"Stabilimento: 17/19, V. Praga 09094 Marrubiu",
    "sg:city":"Marrubiu",
    "sg:classifiers":[
        {
            "category":"Food & Beverages",
            "subcategory":"Groceries & Convenience Stores",
            "type":"Retail Goods"
        }
    ],
    "sg:phone":"+39 0783 856163",
    "sg:postcode":"09094",
    "sg:province":"Oristano",
    "sg:tags":[
        "product",
        "related"
    ],
    "sg:website":"http://www.paginegialle.it/azzurro.it",
    "wof:name":"Azzurro Sardegna Conserve Ittiche",
    "wof:placetype":"venue"
},
  "geometry": {"coordinates":[8.59633255,39.9052734375],"type":"Point"}
}