{
  "type": "Feature",
  "properties": {
    "addr:full":"4, Via Dal Salet 33028 Tolmezzo Tolmezzo Udine 33028",
    "addr:postcode":"33028;33028",
    "addr:street":"Via Dal Salet",
    "iso:country":"IT",
    "sg:address":"4, Via Dal Salet 33028 Tolmezzo",
    "sg:city":"Tolmezzo",
    "sg:classifiers":[
        {
            "category":"Building & Trades",
            "subcategory":"Construction",
            "type":"Services"
        }
    ],
    "sg:phone":"+39 39043344236",
    "sg:postcode":"33028",
    "sg:province":"Udine",
    "sg:tags":[
        "work",
        "public"
    ],
    "wof:name":"I.co.n. S.r.l.",
    "wof:placetype":"venue"
},
  "geometry": {"coordinates":[13.230724,46.064941],"type":"Point"}
}