{
  "type": "Feature",
  "properties": {
    "iso:country":"IT",
    "sg:address":"21, Via Monte Corno 37057 San Giovanni Lupatoto",
    "sg:city":"San Giovanni Lupatoto",
    "sg:classifiers":[
        {
            "category":"Food & Beverages",
            "subcategory":"Groceries & Convenience Stores",
            "type":"Retail Goods"
        }
    ],
    "sg:phone":"+39 045 875 0627",
    "sg:postcode":"37057",
    "sg:province":"Verona",
    "sg:tags":[
        "product",
        "related"
    ],
    "wof:name":"Lilli S.r.l.",
    "wof:placetype":"venue"
},
  "geometry": {"coordinates":[11.0212097168,45.389831543],"type":"Point"}
}