{
  "type": "Feature",
  "properties": {
    "addr:full":"22070 Bregnano Bregnano Como 22070",
    "addr:postcode":"22070;22070",
    "iso:country":"IT",
    "sg:address":"22070 Bregnano",
    "sg:city":"Bregnano",
    "sg:orig_category":"Lavorazioni Metalli, Stampaggio E Saldatura",
    "sg:phone":"+39 031 773233",
    "sg:postcode":"22070",
    "sg:province":"Como",
    "wof:name":"Eurolam S.r.l.",
    "wof:placetype":"venue"
},
  "geometry": {"coordinates":[9.062121,45.708813],"type":"Point"}
}