{
  "type": "Feature",
  "properties": {
    "addr:full":"10, Via Castellana 31037 Loria Loria Treviso 31037",
    "addr:postcode":"31037;31037",
    "addr:street":"Via Castellana",
    "iso:country":"IT",
    "sg:address":"10, Via Castellana 31037 Loria",
    "sg:city":"Loria",
    "sg:classifiers":[
        {
            "category":"Professional",
            "subcategory":"Engineering",
            "type":"Services"
        }
    ],
    "sg:phone":"+39 0423 755115",
    "sg:postcode":"31037",
    "sg:province":"Treviso",
    "sg:tags":[
        "machine",
        "-",
        "mechanical"
    ],
    "wof:name":"Ciba Pack (s.n.c.)",
    "wof:placetype":"venue"
},
  "geometry": {"coordinates":[11.868096,45.712872],"type":"Point"}
}