{
  "type": "Feature",
  "properties": {
    "iso:country":"IT",
    "sg:address":"46030 Serravalle Pistoiese",
    "sg:orig_category":"Bevande, Vini E Liquori",
    "sg:phone":"+39 0573 518270",
    "sg:postcode":"46030",
    "sg:province":"Mantova",
    "wof:name":"Montalcino Vini Di Marliani E Nicolini",
    "wof:placetype":"venue"
},
  "geometry": {"coordinates":[11.098665,45.07177],"type":"Point"}
}