{
  "type": "Feature",
  "properties": {
    "addr:full":"71, Corso Lombardia 10099 San Mauro Torinese San Mauro Torinese Torino 10099",
    "addr:postcode":"10099;10099",
    "addr:street":"Corso Lombardia",
    "iso:country":"IT",
    "sg:address":"71, Corso Lombardia 10099 San Mauro Torinese",
    "sg:city":"San Mauro Torinese",
    "sg:classifiers":[
        {
            "category":"Manufacturing",
            "subcategory":"Paper Products",
            "type":"Manufacturing & Wholesale Goods"
        }
    ],
    "sg:phone":"+39 011 273 2696",
    "sg:postcode":"10099",
    "sg:province":"Torino",
    "sg:tags":[
        "cardboard"
    ],
    "wof:name":"Pieffea (s.r.l.)",
    "wof:placetype":"venue"
},
  "geometry": {"coordinates":[7.7421216965,45.1161766052],"type":"Point"}
}