{
  "type": "Feature",
  "properties": {
    "iso:country":"IT",
    "sg:address":"93, Via Enrico Fermi 22030 Orsenigo",
    "sg:city":"Orsenigo",
    "sg:classifiers":[
        {
            "category":"Utilities",
            "subcategory":"Electric",
            "type":"Services"
        }
    ],
    "sg:phone":"+39 39031636111",
    "sg:postcode":"22030",
    "sg:province":"Como",
    "sg:tags":[
        "component",
        "electronic"
    ],
    "wof:name":"Eldor Corporation Spa",
    "wof:placetype":"venue"
},
  "geometry": {"coordinates":[9.121295,45.737072],"type":"Point"}
}