{
  "type": "Feature",
  "properties": {
    "addr:full":"00144 Roma Roma Roma 00144",
    "addr:postcode":"00144;00144",
    "iso:country":"IT",
    "sg:address":"00144 Roma",
    "sg:city":"Roma",
    "sg:orig_category":"Dolciumi E Gelati. Shopping",
    "sg:phone":"+39 06 592 3091",
    "sg:postcode":"00144",
    "sg:province":"Roma",
    "wof:name":"Tomeucci Eur Caffe'",
    "wof:placetype":"venue"
},
  "geometry": {"coordinates":[12.463682,41.83242],"type":"Point"}
}