{
  "type": "Feature",
  "properties": {
    "addr:full":"20010 Pogliano Milanese Pogliano Milanese Milano 20010",
    "addr:postcode":"20010;20010",
    "iso:country":"IT",
    "sg:address":"20010 Pogliano Milanese",
    "sg:city":"Pogliano Milanese",
    "sg:orig_category":"Zootecnia E Pesca, Allevamento Piccoli Animali. Animali Domestici",
    "sg:phone":"+39 02 934 0368",
    "sg:postcode":"20010",
    "sg:province":"Milano",
    "wof:name":"Ornil Center Di Canti Sergio",
    "wof:placetype":"venue"
},
  "geometry": {"coordinates":[8.988704,45.537373],"type":"Point"}
}