{
  "type": "Feature",
  "properties": {
    "addr:full":"37135 Verona Verona Verona 37135",
    "addr:postcode":"37135;37135",
    "iso:country":"IT",
    "sg:address":"37135 Verona",
    "sg:city":"Verona",
    "sg:orig_category":"Elettronica Professionale E Di Consumo. Automazione E Macchine Per Ufficio",
    "sg:phone":"+39 045 509555",
    "sg:postcode":"37135",
    "sg:province":"Verona",
    "wof:name":"Banelli Ezio Srl",
    "wof:placetype":"venue"
},
  "geometry": {"coordinates":[10.978241,45.411499],"type":"Point"}
}