{
  "type": "Feature",
  "properties": {
    "addr:full":"80071 Anacapri Anacapri Napoli 80071",
    "addr:postcode":"80071;80071",
    "iso:country":"IT",
    "sg:address":"80071 Anacapri",
    "sg:city":"Anacapri",
    "sg:orig_category":"Impiantistica E Prodotti Tecnologici Per Edilizia. Macchine, Strumenti Ed Apparecchi Per Attivita' Industriali",
    "sg:phone":"+39 081 837 3986",
    "sg:postcode":"80071",
    "sg:province":"Napoli",
    "wof:name":"Edil Topocad Di Giordano Geom.orazio",
    "wof:placetype":"venue"
},
  "geometry": {"coordinates":[14.215727,40.553993],"type":"Point"}
}