{
  "type": "Feature",
  "properties": {
    "iso:country":"IT",
    "sg:address":"24050 Mozzanica",
    "sg:city":"Mozzanica",
    "sg:orig_category":"Servizi Di Magazzinaggio E Movimentazione",
    "sg:phone":"+39 036 382 8208",
    "sg:postcode":"24050",
    "sg:province":"Bergamo",
    "wof:name":"Oldoni Giovanni",
    "wof:placetype":"venue"
},
  "geometry": {"coordinates":[9.691107,45.48172],"type":"Point"}
}