{
  "type": "Feature",
  "properties": {
    "iso:country":"IT",
    "sg:address":"37019 Peschiera Del Garda",
    "sg:city":"Peschiera del Garda",
    "sg:orig_category":"Climatizzazione E Condizionamento, Apparecchiature E Servizi. Elettrodomestici",
    "sg:phone":"+39 045 640 1364",
    "sg:postcode":"37019",
    "sg:province":"Verona",
    "wof:name":"Cosmotec Spa",
    "wof:placetype":"venue"
},
  "geometry": {"coordinates":[10.662651,45.428829],"type":"Point"}
}