{
  "type": "Feature",
  "properties": {
    "iso:country":"IT",
    "sg:address":"70043 Monopoli",
    "sg:city":"Monopoli",
    "sg:orig_category":"Manufacturers: Prefabbricati",
    "sg:phone":"+39 080 690 9017",
    "sg:postcode":"70043",
    "sg:province":"Bari",
    "sg:website":"http://prebeton.com/betonprefabbricati",
    "wof:name":"Beton Prefabbricati Srl",
    "wof:placetype":"venue"
},
  "geometry": {"coordinates":[17.293434,40.932819],"type":"Point"}
}