{
  "type": "Feature",
  "properties": {
    "addr:full":"93010 Serradifalco Serradifalco Caltanissetta 93010",
    "addr:postcode":"93010;93010",
    "iso:country":"IT",
    "sg:address":"93010 Serradifalco",
    "sg:city":"Serradifalco",
    "sg:orig_category":"Bruciatori Nafta, Gasolio E Kerosene - Commercio",
    "sg:phone":"+39 0934 930730",
    "sg:postcode":"93010",
    "sg:province":"Caltanissetta",
    "wof:name":"Italmont Srl",
    "wof:placetype":"venue"
},
  "geometry": {"coordinates":[13.881556,37.454975],"type":"Point"}
}