{
  "type": "Feature",
  "properties": {
    "iso:country":"IT",
    "sg:address":"Via Garibaldi, 1; Racconigi; 12035",
    "sg:city":"Racconigi",
    "sg:classifiers":[
        {
            "category":"Banks & Credit Unions",
            "subcategory":"Bank",
            "type":"Services"
        }
    ],
    "sg:phone":"+39 0172 85153",
    "sg:postcode":"12035",
    "sg:province":"Cuneo",
    "wof:name":"Banca Crt",
    "wof:placetype":"venue"
},
  "geometry": {"coordinates":[7.678698,44.768337],"type":"Point"}
}