{
  "type": "Feature",
  "properties": {
    "addr:full":"Viale Trento 197; Vicenza; 36100 Vicenza Vicenza 36100",
    "addr:housenumber":"197",
    "addr:postcode":"36100;36100",
    "addr:street":"Viale Trento",
    "iso:country":"IT",
    "sg:address":"Viale Trento 197; Vicenza; 36100",
    "sg:city":"Vicenza",
    "sg:classifiers":[
        {
            "category":"Banks & Credit Unions",
            "subcategory":"Bank",
            "type":"Services"
        }
    ],
    "sg:phone":"+39 0444 395316",
    "sg:postcode":"36100",
    "sg:province":"Vicenza",
    "wof:name":"Cariverona Banca Spa",
    "wof:placetype":"venue"
},
  "geometry": {"coordinates":[11.526918,45.557232],"type":"Point"}
}