{
  "type": "Feature",
  "properties": {
    "addr:full":"7, Via Maura Ponti 27010 Copiano Copiano Pavia 27010",
    "addr:postcode":"27010;27010",
    "addr:street":"Via Maura Ponti",
    "iso:country":"IT",
    "sg:address":"7, Via Maura Ponti 27010 Copiano",
    "sg:city":"Copiano",
    "sg:classifiers":[
        {
            "category":"Shopping",
            "type":"Retail Goods"
        }
    ],
    "sg:phone":"+39 0382 975001",
    "sg:postcode":"27010",
    "sg:province":"Pavia",
    "sg:tags":[
        "finished",
        "-",
        "metallic"
    ],
    "wof:name":"I.c.s. S.p.a.",
    "wof:placetype":"venue"
},
  "geometry": {"coordinates":[9.3302516937,45.1990280151],"type":"Point"}
}