{
  "type": "Feature",
  "properties": {
    "iso:country":"IT",
    "sg:address":"60044 Fabriano",
    "sg:city":"Fabriano",
    "sg:orig_category":"Elettrotecnica Professionale E Di Consumo. Forniture Per Attivita' Commerciali Ed Artigianali",
    "sg:phone":"+39 0732 627179",
    "sg:postcode":"60044",
    "sg:province":"Ancona",
    "sg:website":"http://www.targotecnica.it",
    "wof:name":"Targotecnica Srl Unipersonale",
    "wof:placetype":"venue"
},
  "geometry": {"coordinates":[12.851483,43.331989],"type":"Point"}
}