{
  "type": "Feature",
  "properties": {
    "iso:country":"IT",
    "sg:address":"31057 Silea",
    "sg:city":"Silea",
    "sg:orig_category":"Salumifici E Prosciuttifici",
    "sg:phone":"+39 0422 362477",
    "sg:postcode":"31057",
    "sg:province":"Treviso",
    "wof:name":"Da Pian Antonio & C. Snc",
    "wof:placetype":"venue"
},
  "geometry": {"coordinates":[12.307489,45.64666],"type":"Point"}
}