{
  "type": "Feature",
  "properties": {
    "iso:country":"IT",
    "sg:address":"00185 Roma",
    "sg:city":"Roma",
    "sg:orig_category":"Impiantistica E Prodotti Tecnologici Per Edilizia. Elettrotecnica Professionale E Di Consumo. Telecomunicazioni E Telefonia, Impianti, Apparecchi E Servizi",
    "sg:phone":"+39 06 702 2420",
    "sg:postcode":"00185",
    "sg:province":"Roma",
    "sg:website":"http://www.mascar.com",
    "wof:name":"Mas.car. Sas Di A. Mastrorilli",
    "wof:placetype":"venue"
},
  "geometry": {"coordinates":[12.510909,41.890839],"type":"Point"}
}