{
  "type": "Feature",
  "properties": {
    "addr:full":"16, Via Braille L. 48100 Ravenna Ravenna Ravenna 48100",
    "addr:housenumber":"l.",
    "addr:postcode":"48100;48100",
    "addr:street":"Via Braille",
    "iso:country":"IT",
    "sg:address":"16, Via Braille L. 48100 Ravenna",
    "sg:city":"Ravenna",
    "sg:classifiers":[
        {
            "category":"Food & Beverages",
            "subcategory":"Groceries & Convenience Stores",
            "type":"Retail Goods"
        }
    ],
    "sg:phone":"+39 0544 460170",
    "sg:postcode":"48100",
    "sg:province":"Ravenna",
    "sg:tags":[
        "drink"
    ],
    "wof:name":"Erre Bi S.r.l.",
    "wof:placetype":"venue"
},
  "geometry": {"coordinates":[12.2250003815,44.3638877869],"type":"Point"}
}