{
  "type": "Feature",
  "properties": {
    "iso:country":"IT",
    "sg:address":"Via Manzoni 28 23845 Costa Masnaga",
    "sg:city":"Costa Masnaga",
    "sg:classifiers":[
        {
            "category":"Home & Garden",
            "subcategory":"Carpets & Floor Coverings",
            "type":"Retail Goods"
        }
    ],
    "sg:phone":"+39 031 856888",
    "sg:postcode":"23845",
    "sg:province":"Lecco",
    "sg:tags":[
        "animal",
        "skin"
    ],
    "wof:name":"Giemme Spa",
    "wof:placetype":"venue"
},
  "geometry": {"coordinates":[9.390071,45.852982],"type":"Point"}
}