{
  "type": "Feature",
  "properties": {
    "iso:country":"IT",
    "sg:address":"51, Via G. Di Vittorio 43045 Fornovo Di Taro",
    "sg:city":"Fornovo di Taro",
    "sg:classifiers":[
        {
            "category":"Manufacturing",
            "subcategory":"Metals",
            "type":"Manufacturing & Wholesale Goods"
        }
    ],
    "sg:phone":"+39 0525 401711",
    "sg:postcode":"43045",
    "sg:province":"Parma",
    "sg:tags":[
        "processing"
    ],
    "wof:name":"Praxair Surface Technologies S.p.a. - Divisione Flametal",
    "wof:placetype":"venue"
},
  "geometry": {"coordinates":[10.2282447815,44.7162628174],"type":"Point"}
}