{
  "type": "Feature",
  "properties": {
    "iso:country":"IT",
    "sg:address":"50053 Empoli",
    "sg:city":"Empoli",
    "sg:orig_category":"Macchine, Impianti E Forniture Per Industria Grafica, Cartaria E Cartotecnica",
    "sg:phone":"+39 0571 993267",
    "sg:postcode":"50053",
    "sg:province":"Firenze",
    "wof:name":"Del Conte Leonardo",
    "wof:placetype":"venue"
},
  "geometry": {"coordinates":[10.970459,43.725983],"type":"Point"}
}