{
  "type": "Feature",
  "properties": {
    "iso:country":"IT",
    "sg:address":"25016 Ghedi",
    "sg:city":"Ghedi",
    "sg:orig_category":"Cartotecnica E Servizi. Articoli Per Imballaggio E Confezionamento",
    "sg:phone":"+39 030 903 1561",
    "sg:postcode":"25016",
    "sg:province":"Brescia",
    "sg:website":"http://www.scatolificioghedese.it",
    "wof:name":"Scatolificio Ghedese Snc",
    "wof:placetype":"venue"
},
  "geometry": {"coordinates":[10.275102,45.421925],"type":"Point"}
}