{
  "type": "Feature",
  "properties": {
    "addr:full":"16, Via Ariosto Ludovico 15048 Valenza Valenza Alessandria 15048",
    "addr:postcode":"15048;15048",
    "addr:street":"Via Ariosto Ludovico",
    "iso:country":"IT",
    "sg:address":"16, Via Ariosto Ludovico 15048 Valenza",
    "sg:city":"Valenza",
    "sg:classifiers":[
        {
            "category":"Shopping",
            "subcategory":"Jewelry",
            "type":"Retail Goods"
        }
    ],
    "sg:phone":"+39 0131 942392",
    "sg:postcode":"15048",
    "sg:province":"Alessandria",
    "sg:tags":[
        "jewellery"
    ],
    "wof:name":"Platinori Snc Di Chioetto-bardozzo-lugani",
    "wof:placetype":"venue"
},
  "geometry": {"coordinates":[8.639498,45.0116],"type":"Point"}
}