{
  "type": "Feature",
  "properties": {
    "iso:country":"IT",
    "sg:address":"45026 Lendinara",
    "sg:city":"Lendinara",
    "sg:orig_category":"Autogru - Noleggio",
    "sg:phone":"+39 0425 669246",
    "sg:postcode":"45026",
    "sg:province":"Rovigo",
    "wof:name":"Tridello Genni E Moris",
    "wof:placetype":"venue"
},
  "geometry": {"coordinates":[11.644292,45.051945],"type":"Point"}
}