{
  "type": "Feature",
  "properties": {
    "iso:country":"IT",
    "sg:address":"95032 Belpasso",
    "sg:city":"Belpasso",
    "sg:orig_category":"Fiori E Piante - Ingrosso",
    "sg:phone":"+39 349 392 1858",
    "sg:postcode":"95032",
    "sg:province":"Catania",
    "wof:name":"Brogi M. Giuseppina",
    "wof:placetype":"venue"
},
  "geometry": {"coordinates":[14.9272041321,37.5203170776],"type":"Point"}
}