{
  "type": "Feature",
  "properties": {
    "addr:full":"136, Via Roma 55011 Altopascio Altopascio Lucca 55011",
    "addr:housenumber":"136",
    "addr:postcode":"55011;55011",
    "addr:street":"Via Roma",
    "iso:country":"IT",
    "sg:address":"136, Via Roma 55011 Altopascio",
    "sg:city":"Altopascio",
    "sg:classifiers":[
        {
            "category":"Professional",
            "subcategory":"Engineering",
            "type":"Services"
        }
    ],
    "sg:phone":"+39 0583 269002",
    "sg:postcode":"55011",
    "sg:province":"Lucca",
    "sg:tags":[
        "machine",
        "-",
        "mechanical"
    ],
    "wof:name":"Altopack (s.r.l.)",
    "wof:placetype":"venue"
},
  "geometry": {"coordinates":[10.680933,43.80975],"type":"Point"}
}