{
  "type": "Feature",
  "properties": {
    "iso:country":"IT",
    "sg:address":"Via Meucci 12 35028 Piove Di Sacco",
    "sg:city":"Piove di Sacco",
    "sg:classifiers":[
        {
            "category":"Shopping",
            "subcategory":"Clothing, Apparel, & Fashions",
            "type":"Retail Goods"
        }
    ],
    "sg:phone":"+39 049 971 2711",
    "sg:postcode":"35028",
    "sg:province":"Padova",
    "sg:tags":[
        "clothing",
        "fabric"
    ],
    "sg:website":"www.lapanama.com",
    "wof:name":"Pinato Tessuti S.p.a.",
    "wof:placetype":"venue"
},
  "geometry": {"coordinates":[11.876589,45.409569],"type":"Point"}
}