{
  "type": "Feature",
  "properties": {
    "addr:full":"36015 Schio Schio Vicenza 36015",
    "addr:postcode":"36015;36015",
    "iso:country":"IT",
    "sg:address":"36015 Schio",
    "sg:city":"Schio",
    "sg:orig_category":"Macchine, Impianti Ed Attrezzature Per Abbigliamento E Pelletterie",
    "sg:phone":"+39 0445 575266",
    "sg:postcode":"36015",
    "sg:province":"Vicenza",
    "wof:name":"Dizma Inox Srl",
    "wof:placetype":"venue"
},
  "geometry": {"coordinates":[11.385556,45.717331],"type":"Point"}
}