{
  "type": "Feature",
  "properties": {
    "iso:country":"IT",
    "sg:address":"18, Via Tiberio Claudio Felice 84131 Salerno",
    "sg:city":"Salerno",
    "sg:classifiers":[
        {
            "category":"Shopping",
            "subcategory":"Computers & Home Electronics",
            "type":"Retail Goods"
        }
    ],
    "sg:phone":"+39 39089302174",
    "sg:postcode":"84131",
    "sg:province":"Salerno",
    "sg:tags":[
        "electronic",
        "electrical",
        "equipment"
    ],
    "wof:name":"Besser Cavi Di Eredi Nastri Donato",
    "wof:placetype":"venue"
},
  "geometry": {"coordinates":[14.847672,40.640144],"type":"Point"}
}