{
  "type": "Feature",
  "properties": {
    "iso:country":"IT",
    "sg:address":"1, Piazza Grimaldi 61032 Fano",
    "sg:city":"Fano",
    "sg:classifiers":[
        {
            "category":"Building & Trades",
            "subcategory":"Construction",
            "type":"Services"
        }
    ],
    "sg:phone":"+39 0721 804641",
    "sg:postcode":"61032",
    "sg:province":"Pesaro E Urbino",
    "sg:tags":[
        "work",
        "public"
    ],
    "wof:name":"Impresa Solazzi & C. (s.p.a.)",
    "wof:placetype":"venue"
},
  "geometry": {"coordinates":[13.016822,43.846195],"type":"Point"}
}