{
  "type": "Feature",
  "properties": {
    "addr:full":"20159 Milano Milano Milano 20159",
    "addr:postcode":"20159;20159",
    "iso:country":"IT",
    "sg:address":"20159 Milano",
    "sg:city":"Milano",
    "sg:orig_category":"Chiese Ed Associazioni Religiose",
    "sg:phone":"+39 02 688 7374",
    "sg:postcode":"20159",
    "sg:province":"Milano",
    "wof:name":"Chiesa Di Altri Culti Chiesa Unita Pentecostale Internazionale",
    "wof:placetype":"venue"
},
  "geometry": {"coordinates":[9.183571,45.490448],"type":"Point"}
}