{
  "type": "Feature",
  "properties": {
    "addr:full":"Localit\u00e0 Fraticani 01038 Soriano Nel Cimino Soriano nel Cimino Viterbo 01038",
    "addr:postcode":"01038;01038",
    "addr:street":"Localita\u0300 Fraticani",
    "iso:country":"IT",
    "sg:address":"Localit\u00e0 Fraticani 01038 Soriano Nel Cimino",
    "sg:city":"Soriano nel Cimino",
    "sg:classifiers":[
        {
            "category":"Landmark",
            "subcategory":"City Walls",
            "type":"Public Place"
        }
    ],
    "sg:phone":"+39 0761 747121",
    "sg:postcode":"01038",
    "sg:province":"Viterbo",
    "sg:tags":[
        "stone",
        "working"
    ],
    "sg:website":"www.miccipeperino.com",
    "wof:name":"Micci Srl",
    "wof:placetype":"venue"
},
  "geometry": {"coordinates":[12.104854,42.417381],"type":"Point"}
}