{
  "type": "Feature",
  "properties": {
    "iso:country":"IT",
    "sg:address":"21042 Caronno Pertusella",
    "sg:city":"Caronno Pertusella",
    "sg:orig_category":"Abbigliamento Esterno, Maglierie E Pelliccerie. Shopping",
    "sg:phone":"+39 02 965 0687",
    "sg:postcode":"21042",
    "sg:province":"Varese",
    "wof:name":"Basilico Diffusione Moda (s.n.c.)",
    "wof:placetype":"venue"
},
  "geometry": {"coordinates":[9.058071,45.594124],"type":"Point"}
}