{
  "type": "Feature",
  "properties": {
    "iso:country":"IT",
    "sg:address":"56018 Tirrenia",
    "sg:orig_category":"Alberghi E Strutture Extra Alberghiere. Ospedali E Servizi Sanitari",
    "sg:phone":"+39 050 37245",
    "sg:province":"PI",
    "wof:name":"Fondazione Pro Verbo - Il Cenacolo",
    "wof:placetype":"venue"
},
  "geometry": {"coordinates":[10.294394,43.602985],"type":"Point"}
}