{
  "type": "Feature",
  "properties": {
    "addr:full":"13, Via Delle Industrie 60022 Castelfidardo Castelfidardo Ancona 60022",
    "addr:postcode":"60022;60022",
    "addr:street":"Via Delle Industrie",
    "iso:country":"IT",
    "sg:address":"13, Via Delle Industrie 60022 Castelfidardo",
    "sg:city":"Castelfidardo",
    "sg:classifiers":[
        {
            "category":"Manufacturing",
            "subcategory":"Metals",
            "type":"Manufacturing & Wholesale Goods"
        }
    ],
    "sg:phone":"+39 39071781523",
    "sg:postcode":"60022",
    "sg:province":"Ancona",
    "sg:tags":[
        "metallurgy",
        "metalworking"
    ],
    "wof:name":"Silver Lamina (s.r.l.)",
    "wof:placetype":"venue"
},
  "geometry": {"coordinates":[13.5592889786,43.4931869507],"type":"Point"}
}