{
  "type": "Feature",
  "properties": {
    "iso:country":"IT",
    "sg:address":"40013 Castel Maggiore",
    "sg:city":"Castel Maggiore",
    "sg:orig_category":"Apparecchiature E Sistemi Per Magazzinaggio E Movimentazione. Servizi Di Magazzinaggio E Movimentazione",
    "sg:phone":"+39 051 701710",
    "sg:postcode":"40013",
    "sg:province":"Bologna",
    "wof:name":"Bologna Gru Soc.coop.r.l.",
    "wof:placetype":"venue"
},
  "geometry": {"coordinates":[11.349236,44.556011],"type":"Point"}
}