{
  "type": "Feature",
  "properties": {
    "addr:full":"00166 Roma Roma Roma 00166",
    "addr:postcode":"00166;00166",
    "iso:country":"IT",
    "sg:address":"00166 Roma",
    "sg:city":"Roma",
    "sg:orig_category":"Alberghi E Strutture Extra Alberghiere. Ospedali E Servizi Sanitari",
    "sg:phone":"+39 06 614 0700",
    "sg:postcode":"00166",
    "sg:province":"Roma",
    "wof:name":"Residence Villa Belvedere Srl",
    "wof:placetype":"venue"
},
  "geometry": {"coordinates":[12.323482,41.905861],"type":"Point"}
}