{
  "type": "Feature",
  "properties": {
    "addr:full":"Via Leopardi - Malvaglio 20020 Robecchetto Con Induno Robecchetto con Induno Milano 20020",
    "addr:postcode":"20020;20020",
    "addr:street":"Via;Malvaglio;Con Induno",
    "iso:country":"IT",
    "sg:address":"Via Leopardi - Malvaglio 20020 Robecchetto Con Induno",
    "sg:city":"Robecchetto con Induno",
    "sg:classifiers":[
        {
            "category":"Home & Garden",
            "subcategory":"Carpets & Floor Coverings",
            "type":"Retail Goods"
        }
    ],
    "sg:phone":"+39 0331 875310",
    "sg:postcode":"20020",
    "sg:province":"Milano",
    "sg:tags":[
        "animal",
        "skin"
    ],
    "wof:name":"Conceria Guerino Di Foieni Giacomo",
    "wof:placetype":"venue"
},
  "geometry": {"coordinates":[9.188141,45.463688],"type":"Point"}
}