{
  "type": "Feature",
  "properties": {
    "iso:country":"IT",
    "sg:address":"16149 Genova",
    "sg:city":"Genova",
    "sg:orig_category":"Arredi Ed Attrezzature Per Uffici",
    "sg:phone":"+39 010 417830",
    "sg:postcode":"16149",
    "sg:province":"Genova",
    "wof:name":"Adib Srl",
    "wof:placetype":"venue"
},
  "geometry": {"coordinates":[8.895726,44.413914],"type":"Point"}
}