{
  "type": "Feature",
  "properties": {
    "iso:country":"IT",
    "sg:address":"20146 Milano",
    "sg:city":"Milano",
    "sg:orig_category":"Servizi Ausiliari Dei Mezzi Di Trasporto",
    "sg:phone":"+39 02 422 4584",
    "sg:postcode":"20146",
    "sg:province":"Milano",
    "wof:name":"Autorimessa Frattini Di Tosques Giuseppe",
    "wof:placetype":"venue"
},
  "geometry": {"coordinates":[9.140825,45.451252],"type":"Point"}
}