{
  "type": "Feature",
  "properties": {
    "iso:country":"IT",
    "sg:address":"Via Prof. Don A. Dalla Torre 9 31047 Ponte Di Piave",
    "sg:city":"Ponte di Piave",
    "sg:classifiers":[
        {
            "category":"Manufacturing",
            "subcategory":"Metals",
            "type":"Manufacturing & Wholesale Goods"
        }
    ],
    "sg:phone":"+39 0422 785399",
    "sg:postcode":"31047",
    "sg:province":"Treviso",
    "sg:tags":[
        "mould",
        "aluminium",
        "industry",
        "plastic"
    ],
    "sg:website":"www.moritz-production.de",
    "wof:name":"Moritz Tool S.n.c. Di Rizzotto Giovannimaria & C.",
    "wof:placetype":"venue"
},
  "geometry": {"coordinates":[12.242072,45.666286],"type":"Point"}
}