{
  "type": "Feature",
  "properties": {
    "iso:country":"IT",
    "sg:address":"80040 Cercola",
    "sg:city":"Cercola",
    "sg:orig_category":"Abbigliamento Esterno, Maglierie E Pelliccerie. Forniture Per Abbigliamento E Pelletterie",
    "sg:phone":"+39 081 733 2256",
    "sg:postcode":"80040",
    "sg:province":"Napoli",
    "wof:name":"Cozzolino Luigi",
    "wof:placetype":"venue"
},
  "geometry": {"coordinates":[14.360473,40.860565],"type":"Point"}
}