{
  "type": "Feature",
  "properties": {
    "addr:full":"Piazzale Dell'agricoltura 24, 00144 Rome, Rm Roma 00144",
    "addr:housenumber":"24",
    "addr:postcode":"00144;rm;00144",
    "addr:street":"Piazzale Dell'Agricoltura",
    "iso:country":"IT",
    "sg:address":"Piazzale Dell'agricoltura 24, 00144 Rome, Rm",
    "sg:classifiers":[
        {
            "category":"Banks & Credit Unions",
            "subcategory":"Bank",
            "type":"Services"
        }
    ],
    "sg:phone":"+39 039 659671",
    "sg:postcode":"00144",
    "sg:province":"Roma",
    "wof:name":"Bnl Multiservizi Spa",
    "wof:placetype":"venue"
},
  "geometry": {"coordinates":[12.47159,41.83683],"type":"Point"}
}