{
  "type": "Feature",
  "properties": {
    "addr:full":"20010 Bareggio Bareggio Milano 20010",
    "addr:postcode":"20010;20010",
    "iso:country":"IT",
    "sg:address":"20010 Bareggio",
    "sg:city":"Bareggio",
    "sg:orig_category":"Servizi E Lavori Per Agricoltura E Zootecnia. Animali Domestici",
    "sg:phone":"+39 02 901 4424",
    "sg:postcode":"20010",
    "sg:province":"Milano",
    "wof:name":"Antonini Carlo",
    "wof:placetype":"venue"
},
  "geometry": {"coordinates":[9.0047683716,45.4851226807],"type":"Point"}
}