{
  "type": "Feature",
  "properties": {
    "iso:country":"IT",
    "sg:address":"17, Via Brigata G.a.p. 61100 Pesaro",
    "sg:city":"Pesaro",
    "sg:classifiers":[
        {
            "category":"Shopping",
            "subcategory":"Computers & Home Electronics",
            "type":"Retail Goods"
        }
    ],
    "sg:phone":"+39 0721 281946",
    "sg:postcode":"61100",
    "sg:province":"Pesaro E Urbino",
    "sg:tags":[
        "electronic",
        "electrical",
        "equipment"
    ],
    "wof:name":"C.i.a.r. (s.r.l.)",
    "wof:placetype":"venue"
},
  "geometry": {"coordinates":[12.863443,43.881054],"type":"Point"}
}