{
  "type": "Feature",
  "properties": {
    "addr:full":"45, Via Delle Fosse 47032 Bertinoro Bertinoro Forl\u00ec-Cesena 47032",
    "addr:postcode":"47032;47032",
    "addr:street":"Via Delle Fosse",
    "iso:country":"IT",
    "sg:address":"45, Via Delle Fosse 47032 Bertinoro",
    "sg:city":"Bertinoro",
    "sg:classifiers":[
        {
            "category":"Professional",
            "subcategory":"Engineering",
            "type":"Services"
        }
    ],
    "sg:phone":"+39 0543 441080",
    "sg:postcode":"47032",
    "sg:province":"Forl\u00ec-Cesena",
    "sg:tags":[
        "machine",
        "-",
        "mechanical"
    ],
    "wof:name":"Mg S.r.l.",
    "wof:placetype":"venue"
},
  "geometry": {"coordinates":[11.980461,43.994766],"type":"Point"}
}