{
  "type": "Feature",
  "properties": {
    "iso:country":"IT",
    "sg:address":"Via Divisione Julia 15 36031 Dueville",
    "sg:city":"Dueville",
    "sg:classifiers":[
        {
            "category":"Wholesale",
            "subcategory":"Machinery & Supplies",
            "type":"Manufacturing & Wholesale Goods"
        }
    ],
    "sg:phone":"+39 0444 366000",
    "sg:postcode":"36031",
    "sg:province":"Vicenza",
    "sg:tags":[
        "dyeing",
        "machine",
        "piece"
    ],
    "sg:website":"www.colorservice.net",
    "wof:name":"Color Service Srl",
    "wof:placetype":"venue"
},
  "geometry": {"coordinates":[11.5681829453,45.6330909729],"type":"Point"}
}