{
  "type": "Feature",
  "properties": {
    "addr:full":"20019 Settimo Milanese Settimo Milanese Milano 20019",
    "addr:postcode":"20019;20019",
    "iso:country":"IT",
    "sg:address":"20019 Settimo Milanese",
    "sg:city":"Settimo Milanese",
    "sg:orig_category":"Servizi E Lavori Per Arredamento E Industria Del Legno. Servizi E Lavori Per Edilizia E Lavori Pubblici",
    "sg:phone":"+39 02 328 4887",
    "sg:postcode":"20019",
    "sg:province":"Milano",
    "wof:name":"Internipiu' Di Bossi Stefano",
    "wof:placetype":"venue"
},
  "geometry": {"coordinates":[9.055385,45.48859],"type":"Point"}
}