{
  "type": "Feature",
  "properties": {
    "addr:full":"00052 Cerveteri Cerveteri Roma 00052",
    "addr:postcode":"00052;roma 00052",
    "iso:country":"IT",
    "sg:address":"00052 Cerveteri",
    "sg:city":"Cerveteri",
    "sg:orig_category":"Pubblica Amministrazione",
    "sg:phone":"+39 06 990 1943",
    "sg:postcode":"00052",
    "sg:province":"Roma",
    "wof:name":"Comando 2 Regione Aerea Ufficio P.uma.s.",
    "wof:placetype":"venue"
},
  "geometry": {"coordinates":[12.0408439636,41.988571167],"type":"Point"}
}