{
  "type": "Feature",
  "properties": {
    "addr:full":"Viale Kennedy 29; Caltanissetta",
    "addr:housenumber":"29",
    "addr:street":"Viale Kennedy",
    "iso:country":"IT",
    "sg:address":"Viale Kennedy 29; Caltanissetta",
    "sg:classifiers":[
        {
            "category":"Banks & Credit Unions",
            "subcategory":"Bank",
            "type":"Services"
        }
    ],
    "sg:phone":"+39 0934 29052",
    "wof:name":"Banca Di Roma",
    "wof:placetype":"venue"
},
  "geometry": {"coordinates":[14.057753,37.491264],"type":"Point"}
}