{
  "type": "Feature",
  "properties": {
    "iso:country":"IT",
    "sg:address":"16, Via Colleverde 00131 Roma",
    "sg:city":"Roma",
    "sg:classifiers":[
        {
            "category":"Utilities",
            "subcategory":"Electric",
            "type":"Services"
        }
    ],
    "sg:phone":"+39 39064130978",
    "sg:postcode":"00131",
    "sg:province":"Roma",
    "sg:tags":[
        "component",
        "electronic"
    ],
    "wof:name":"Pansystem Srl",
    "wof:placetype":"venue"
},
  "geometry": {"coordinates":[12.631283,41.941711],"type":"Point"}
}