{
  "type": "Feature",
  "properties": {
    "iso:country":"IT",
    "sg:address":"22018 Porlezza",
    "sg:city":"Porlezza",
    "sg:orig_category":"Petroli, Gas E Combustibili. Termotecnica E Riscaldamento, Apparecchiature E Servizi",
    "sg:phone":"+39 0344 61653",
    "sg:postcode":"22018",
    "sg:province":"Como",
    "wof:name":"Policalor Snc",
    "wof:placetype":"venue"
},
  "geometry": {"coordinates":[9.1378412247,46.0373039246],"type":"Point"}
}