{
  "type": "Feature",
  "properties": {
    "iso:country":"IT",
    "sg:address":"00185 Roma",
    "sg:city":"Roma",
    "sg:orig_category":"Accessori Moda D'abbigliamento. Complementi Di Arredamento. Tempo Libero - Articoli E Forniture",
    "sg:phone":"+39 06 495 7683",
    "sg:postcode":"00185",
    "sg:province":"Roma",
    "wof:name":"Bellori Renato Sas",
    "wof:placetype":"venue"
},
  "geometry": {"coordinates":[12.515851,41.894566],"type":"Point"}
}