{
  "type": "Feature",
  "properties": {
    "addr:full":"20122 Milano Milano Milano 20122",
    "addr:postcode":"20122;20122",
    "iso:country":"IT",
    "sg:address":"20122 Milano",
    "sg:city":"Milano",
    "sg:orig_category":"Servizi Editoriali. Professionisti - Studi E Servizi Ed Associazioni Di Interesse Aziendale",
    "sg:phone":"+39 02 5830 9403",
    "sg:postcode":"20122",
    "sg:province":"Milano",
    "wof:name":"Tumiati Gaetano",
    "wof:placetype":"venue"
},
  "geometry": {"coordinates":[9.192426,45.454239],"type":"Point"}
}