{
  "type": "Feature",
  "properties": {
    "addr:full":"14, Via Cilea 20090 Trezzano Sul Naviglio Trezzano sul Naviglio Milano 20090",
    "addr:postcode":"20090;20090",
    "addr:street":"Via Cilea",
    "iso:country":"IT",
    "sg:address":"14, Via Cilea 20090 Trezzano Sul Naviglio",
    "sg:city":"Trezzano sul Naviglio",
    "sg:classifiers":[
        {
            "category":"Professional",
            "subcategory":"Printing & Photocopies",
            "type":"Services"
        }
    ],
    "sg:phone":"+39 39024452774",
    "sg:postcode":"20090",
    "sg:province":"Milano",
    "wof:name":"Miazzon S.n.c. Di Cane Ferdinando & C.",
    "wof:placetype":"venue"
},
  "geometry": {"coordinates":[9.0481033325,45.4140892029],"type":"Point"}
}