{
  "type": "Feature",
  "properties": {
    "iso:country":"IT",
    "sg:address":"09047 Selargius",
    "sg:city":"Selargius",
    "sg:orig_category":"Servizi Vari Di Interesse Pubblico",
    "sg:phone":"+39 070 543 5113",
    "sg:postcode":"09047",
    "sg:province":"Cagliari",
    "wof:name":"Parco Dei Bimbi Di Lucia Cossellu",
    "wof:placetype":"venue"
},
  "geometry": {"coordinates":[9.108444,39.25565],"type":"Point"}
}