{
  "type": "Feature",
  "properties": {
    "iso:country":"IT",
    "sg:address":"10095 Grugliasco",
    "sg:city":"Grugliasco",
    "sg:orig_category":"Elettrodomestici - Produzione E Ingrosso",
    "sg:phone":"+39 011 405 4646",
    "sg:postcode":"10095",
    "sg:province":"Torino",
    "wof:name":"Tecnocem",
    "wof:placetype":"venue"
},
  "geometry": {"coordinates":[7.561848,45.067642],"type":"Point"}
}