{
  "type": "Feature",
  "properties": {
    "addr:full":"20129 Milano Milano Milano 20129",
    "addr:postcode":"20129;20129",
    "iso:country":"IT",
    "sg:address":"20129 Milano",
    "sg:city":"Milano",
    "sg:orig_category":"Informatica - Consulenza E Servizi. Servizi Ausiliari Di Analisi, Controllo E Ricerca. Servizi Per Aziende, Manifestazioni E Supporto Agli Scambi Commerciali",
    "sg:phone":"+39 02 277181",
    "sg:postcode":"20129",
    "sg:province":"Milano",
    "sg:website":"http://www.inaz.it",
    "wof:name":"Inaz Paghe Srl",
    "wof:placetype":"venue"
},
  "geometry": {"coordinates":[9.2083511353,45.472454071],"type":"Point"}
}