{
  "type": "Feature",
  "properties": {
    "iso:country":"IT",
    "sg:address":"37060 Sona",
    "sg:city":"Sona",
    "sg:orig_category":"Macchine, Impianti Ed Attrezzature Per Agricoltura E Zootecnia",
    "sg:phone":"+39 045 608 1244",
    "sg:postcode":"37060",
    "sg:province":"Verona",
    "wof:name":"Isa Impianti Snc",
    "wof:placetype":"venue"
},
  "geometry": {"coordinates":[10.832362,45.434479],"type":"Point"}
}