{
  "type": "Feature",
  "properties": {
    "iso:country":"IT",
    "sg:address":"03034 Casalvieri",
    "sg:city":"Casalvieri",
    "sg:orig_category":"Aspirazione Impianti",
    "sg:phone":"+39 0776 617023",
    "sg:postcode":"03034",
    "sg:province":"Frosinone",
    "wof:name":"C.i.m.e.c. Di Rag. C. Mancini",
    "wof:placetype":"venue"
},
  "geometry": {"coordinates":[13.717333,41.638065],"type":"Point"}
}