{
  "type": "Feature",
  "properties": {
    "addr:full":"200, Via Aurelia Sud 55049 Viareggio Viareggio Lucca 55049",
    "addr:housenumber":"200",
    "addr:postcode":"55049;55049",
    "addr:street":"Via Aurelia Sud",
    "iso:country":"IT",
    "sg:address":"200, Via Aurelia Sud 55049 Viareggio",
    "sg:city":"Viareggio",
    "sg:classifiers":[
        {
            "category":"Parking",
            "subcategory":"Lot",
            "type":"Transportation"
        }
    ],
    "sg:phone":"+39 0584 387968",
    "sg:postcode":"55049",
    "sg:province":"Lucca",
    "sg:tags":[
        "transport",
        "road"
    ],
    "wof:name":"Autotrasporti Transbateaux Snc",
    "wof:placetype":"venue"
},
  "geometry": {"coordinates":[10.270657,43.860909],"type":"Point"}
}