{
  "type": "Feature",
  "properties": {
    "iso:country":"IT",
    "sg:address":"00131 Roma",
    "sg:city":"Roma",
    "sg:orig_category":"Acciaierie E Fonderie. Arte Ed Artigianato Artistico",
    "sg:phone":"+39 06 413 0686",
    "sg:postcode":"00131",
    "sg:province":"Roma",
    "wof:name":"Brasini Gino",
    "wof:placetype":"venue"
},
  "geometry": {"coordinates":[12.651573,41.932335],"type":"Point"}
}