{
  "type": "Feature",
  "properties": {
    "iso:country":"IT",
    "sg:address":"15, Via Amatrice 00199 Roma",
    "sg:city":"Roma",
    "sg:classifiers":[
        {
            "category":"Utilities",
            "subcategory":"Electric",
            "type":"Services"
        }
    ],
    "sg:phone":"+39 06 8620 3762",
    "sg:postcode":"00199",
    "sg:province":"Roma",
    "sg:tags":[
        "component",
        "electronic"
    ],
    "wof:name":"Hi - Rel (s.r.l.)",
    "wof:placetype":"venue"
},
  "geometry": {"coordinates":[12.519394,41.932919],"type":"Point"}
}