{
  "type": "Feature",
  "properties": {
    "addr:full":"54/b, V. S. Giuseppe 20050 Verano Brianza Verano Brianza Milano 20050",
    "addr:housenumber":"54 / b v.",
    "addr:postcode":"20050;20050",
    "iso:country":"IT",
    "sg:address":"54/b, V. S. Giuseppe 20050 Verano Brianza",
    "sg:city":"Verano Brianza",
    "sg:classifiers":[
        {
            "category":"Shopping",
            "subcategory":"Computers & Home Electronics",
            "type":"Retail Goods"
        }
    ],
    "sg:phone":"+39 036 299 1781",
    "sg:postcode":"20050",
    "sg:province":"Milano",
    "sg:tags":[
        "electronic",
        "electrical",
        "equipment"
    ],
    "sg:website":"http://www.cesel.com:ws_end: :mark:ws:http://www.paginegialle.it/cesel",
    "wof:name":"Cesel Snc",
    "wof:placetype":"venue"
},
  "geometry": {"coordinates":[9.188141,45.463688],"type":"Point"}
}