{
  "type": "Feature",
  "properties": {
    "iso:country":"IT",
    "sg:address":"22010 Argegno",
    "sg:city":"Argegno",
    "sg:orig_category":"Pubblica Amministrazione",
    "sg:phone":"+39 031 821334",
    "sg:postcode":"22010",
    "sg:province":"Como",
    "wof:name":"Comprensorio Alpino Di Caccia Prealpi Comasche",
    "wof:placetype":"venue"
},
  "geometry": {"coordinates":[9.0771141052,45.8104019165],"type":"Point"}
}