{
  "type": "Feature",
  "properties": {
    "iso:country":"IT",
    "sg:address":"56021 Marciana",
    "sg:city":"Marciana",
    "sg:orig_category":"Macchine, Impianti Ed Attrezzature Per Abbigliamento E Pelletterie",
    "sg:phone":"+39 050 742701",
    "sg:postcode":"56021",
    "sg:province":"Pisa",
    "wof:name":"Pieracci Angiolo",
    "wof:placetype":"venue"
},
  "geometry": {"coordinates":[10.540092,43.678104],"type":"Point"}
}