{
  "type": "Feature",
  "properties": {
    "iso:country":"IT",
    "sg:address":"43, Str. Della Cisa 42041 Brescello",
    "sg:classifiers":[
        {
            "category":"Home & Garden",
            "subcategory":"Home Furnishings",
            "type":"Retail Goods"
        }
    ],
    "sg:phone":"+39 0522 686009",
    "sg:postcode":"42041",
    "sg:province":"Reggio Nell'Emilia",
    "sg:tags":[
        "household"
    ],
    "sg:website":"http://www.armet.it:ws_end: :mark:ws:http://www.paginegialle.it/armetspa",
    "wof:name":"Armet",
    "wof:placetype":"venue"
},
  "geometry": {"coordinates":[10.627794,44.696228],"type":"Point"}
}