{
  "type": "Feature",
  "properties": {
    "iso:country":"IT",
    "sg:address":"80137 Napoli",
    "sg:city":"Napoli",
    "sg:orig_category":"Legno E Semilavorati. Macchine E Forniture Per Arredamento E Industria Del Legno. Hobbistica",
    "sg:phone":"+39 081 294993",
    "sg:postcode":"80137",
    "sg:province":"Napoli",
    "sg:website":"http://www.ostelegno.it",
    "wof:name":"Fratelli Oste Snc Di Antonio E Bruno Oste",
    "wof:placetype":"venue"
},
  "geometry": {"coordinates":[14.288633,40.902439],"type":"Point"}
}