{
  "type": "Feature",
  "properties": {
    "iso:country":"IT",
    "sg:address":"Via Dei Platani 11 22040 Alzate Brianza",
    "sg:city":"Alzate Brianza",
    "sg:classifiers":[
        {
            "category":"Utilities",
            "subcategory":"Recycling",
            "type":"Services"
        }
    ],
    "sg:phone":"+39 031 635511",
    "sg:postcode":"22040",
    "sg:province":"Como",
    "sg:tags":[
        "plant",
        "plastic"
    ],
    "sg:website":"www.previero.it",
    "wof:name":"Previero N. Srl",
    "wof:placetype":"venue"
},
  "geometry": {"coordinates":[9.167118,45.773499],"type":"Point"}
}