{
  "type": "Feature",
  "properties": {
    "iso:country":"IT",
    "sg:address":"Via Barsanti 23 47100 Forli'",
    "sg:classifiers":[
        {
            "category":"Professional",
            "subcategory":"Art Services",
            "type":"Services"
        }
    ],
    "sg:phone":"+39 0543 723405",
    "sg:postcode":"47100",
    "sg:province":"Forl\u00ec-Cesena",
    "sg:tags":[
        "catalogue"
    ],
    "sg:website":"www.speedgraphic.com",
    "wof:name":"Speedgraphic Srl",
    "wof:placetype":"venue"
},
  "geometry": {"coordinates":[12.084288,44.234535],"type":"Point"}
}