{
  "type": "Feature",
  "properties": {
    "iso:country":"IT",
    "sg:address":"Via Piave 54; Pompei; 80045",
    "sg:city":"Pompei",
    "sg:classifiers":[
        {
            "category":"Banks & Credit Unions",
            "subcategory":"Bank",
            "type":"Services"
        }
    ],
    "sg:phone":"+39 081 850 7018",
    "sg:postcode":"80045",
    "sg:province":"Napoli",
    "wof:name":"Banco Ambrosiano Veneto Spa",
    "wof:placetype":"venue"
},
  "geometry": {"coordinates":[14.501525,40.750908],"type":"Point"}
}