{
  "type": "Feature",
  "properties": {
    "iso:country":"IT",
    "sg:address":"20125 Milano",
    "sg:city":"Milano",
    "sg:orig_category":"Motori E Componenti - Produzione E Commercio",
    "sg:phone":"+39 02 6671 4727",
    "sg:postcode":"20125",
    "sg:province":"Milano",
    "sg:website":"http://www.aladata.it/autom",
    "wof:name":"Autom Elettrocostruzioni Industriali Srl",
    "wof:placetype":"venue"
},
  "geometry": {"coordinates":[9.2408103943,45.5273284912],"type":"Point"}
}