{
  "type": "Feature",
  "properties": {
    "iso:country":"IT",
    "sg:address":"41017 Casoni",
    "sg:orig_category":"Servizi Ausiliari Di Analisi, Controllo E Ricerca",
    "sg:phone":"+39 059 909038",
    "sg:postcode":"41017",
    "sg:province":"Modena",
    "wof:name":"Tecno Futur Service (s.r.l.)",
    "wof:placetype":"venue"
},
  "geometry": {"coordinates":[11.055175,44.722942],"type":"Point"}
}