{
  "type": "Feature",
  "properties": {
    "iso:country":"IT",
    "sg:address":"Corso Della Repubblica 9; Siderno; 89048",
    "sg:city":"Siderno",
    "sg:classifiers":[
        {
            "category":"Banks & Credit Unions",
            "subcategory":"Bank",
            "type":"Services"
        }
    ],
    "sg:phone":"+39 0964 381009",
    "sg:postcode":"89048",
    "sg:province":"Reggio Di Calabria",
    "wof:name":"Banco Di Napoli Spa",
    "wof:placetype":"venue"
},
  "geometry": {"coordinates":[16.296432,38.26738],"type":"Point"}
}