{
  "type": "Feature",
  "properties": {
    "iso:country":"IT",
    "sg:address":"81020 Castel Morrone",
    "sg:city":"Castel Morrone",
    "sg:classifiers":[
        {
            "category":"Health Services",
            "subcategory":"Nursing And Care Facility",
            "type":"Services"
        }
    ],
    "sg:phone":"+39 0823 391111",
    "sg:postcode":"81020",
    "sg:province":"Caserta",
    "sg:tags":[
        "case",
        "cura",
        "private",
        "di"
    ],
    "wof:name":"Villa Delle Magnolie",
    "wof:placetype":"venue"
},
  "geometry": {"coordinates":[14.376379,41.126541],"type":"Point"}
}