{
  "type": "Feature",
  "properties": {
    "addr:full":"32100 Belluno Belluno Belluno 32100",
    "addr:postcode":"32100;32100",
    "iso:country":"IT",
    "sg:address":"32100 Belluno",
    "sg:city":"Belluno",
    "sg:orig_category":"Servizi E Lavori Per Edilizia E Lavori Pubblici. Servizi E Lavori Per Ecologia E Smaltimento Rifiuti. Macchine E Forniture Per Ecologia E Smaltimento Rifiuti. Acqua, Luce, Gas E Societa' Di Esercizio ",
    "sg:phone":"+39 0437 940319",
    "sg:postcode":"32100",
    "sg:province":"Belluno",
    "wof:name":"Soccorso Alpino",
    "wof:placetype":"venue"
},
  "geometry": {"coordinates":[12.219366,46.136608],"type":"Point"}
}