{
  "type": "Feature",
  "properties": {
    "iso:country":"IT",
    "sg:address":"00182 Roma",
    "sg:city":"Roma",
    "sg:orig_category":"Scuole E Servizi Scolastici. Alberghi E Strutture Extra Alberghiere",
    "sg:phone":"+39 06 701 7464",
    "sg:postcode":"00182",
    "sg:province":"Roma",
    "wof:name":"Collegio Lituano Di S. Casimiro",
    "wof:placetype":"venue"
},
  "geometry": {"coordinates":[12.51933,41.881218],"type":"Point"}
}