{
  "type": "Feature",
  "properties": {
    "addr:full":"74, Corso Vercelli 28100 Novara Novara Novara 28100",
    "addr:postcode":"28100;28100",
    "addr:street":"Corso Vercelli",
    "iso:country":"IT",
    "sg:address":"74, Corso Vercelli 28100 Novara",
    "sg:city":"Novara",
    "sg:classifiers":[
        {
            "category":"Shopping",
            "subcategory":"Stationery & Office Supplies",
            "type":"Retail Goods"
        }
    ],
    "sg:phone":"+39 0321 453805",
    "sg:postcode":"28100",
    "sg:province":"Novara",
    "sg:tags":[
        "professional"
    ],
    "wof:name":"C.r.industria Mobili Ufficio Di Conti Rosimbo",
    "wof:placetype":"venue"
},
  "geometry": {"coordinates":[8.5973062515,45.4335212708],"type":"Point"}
}