{
  "type": "Feature",
  "properties": {
    "addr:full":"27025 Gambolo' Pavia 27025",
    "addr:postcode":"27025;27025",
    "addr:street":"Gambolo ' Pavia",
    "iso:country":"IT",
    "sg:address":"27025 Gambolo'",
    "sg:orig_category":"Metalli E Leghe",
    "sg:phone":"+39 0381 640144",
    "sg:postcode":"27025",
    "sg:province":"Pavia",
    "wof:name":"Metal Plast Srl",
    "wof:placetype":"venue"
},
  "geometry": {"coordinates":[8.8581218719,45.257232666],"type":"Point"}
}