{
  "type": "Feature",
  "properties": {
    "addr:full":"41100 Modena Modena Modena 41100",
    "addr:postcode":"41100;41100",
    "iso:country":"IT",
    "sg:address":"41100 Modena",
    "sg:city":"Modena",
    "sg:orig_category":"Termotecnica E Riscaldamento, Apparecchiature E Servizi",
    "sg:phone":"+39 059 362022",
    "sg:postcode":"41100",
    "sg:province":"Modena",
    "wof:name":"Con.ter. S.n.c.",
    "wof:placetype":"venue"
},
  "geometry": {"coordinates":[10.955677,44.636875],"type":"Point"}
}