{
  "type": "Feature",
  "properties": {
    "iso:country":"IT",
    "sg:address":"34147 Trieste",
    "sg:city":"Trieste",
    "sg:orig_category":"Bevande, Vini E Liquori",
    "sg:phone":"+39 040 832 3506",
    "sg:postcode":"34147",
    "sg:province":"Trieste",
    "wof:name":"Distillerie Triestine Srl",
    "wof:placetype":"venue"
},
  "geometry": {"coordinates":[13.814786,45.615547],"type":"Point"}
}