{
  "type": "Feature",
  "properties": {
    "iso:country":"IT",
    "sg:address":"Piazza Roma 8, 83050 Volturara Irpina, Av",
    "sg:city":"Volturara Irpina",
    "sg:classifiers":[
        {
            "category":"Banks & Credit Unions",
            "subcategory":"Bank",
            "type":"Services"
        }
    ],
    "sg:postcode":"83050",
    "sg:province":"Avellino",
    "wof:name":"Cassa Rurale Ed Artigiana Di Volturara Irpina - Banca Di Credito Cooperativo Scrl",
    "wof:placetype":"venue"
},
  "geometry": {"coordinates":[14.917091,40.87867],"type":"Point"}
}