{
  "type": "Feature",
  "properties": {
    "iso:country":"IT",
    "sg:address":"Via Grumello 47/49 24127 Bergamo",
    "sg:city":"Bergamo",
    "sg:orig_category":"Bleachers, Mobile",
    "sg:phone":"+39 035 454 8511",
    "sg:postcode":"24127",
    "sg:province":"Bergamo",
    "sg:website":"www.ceta.it",
    "wof:name":"Ceta Ponteggi Tubolari Spa",
    "wof:placetype":"venue"
},
  "geometry": {"coordinates":[9.636057,45.668732],"type":"Point"}
}