{
  "type": "Feature",
  "properties": {
    "iso:country":"IT",
    "sg:address":"20132 Milano",
    "sg:city":"Milano",
    "sg:orig_category":"Frigoriferi - Accessori E Parti",
    "sg:phone":"+39 02 2614 2097",
    "sg:postcode":"20132",
    "sg:province":"Milano",
    "wof:name":"Datcor Srl",
    "wof:placetype":"venue"
},
  "geometry": {"coordinates":[9.2389183044,45.4929351807],"type":"Point"}
}