{
  "type": "Feature",
  "properties": {
    "iso:country":"IT",
    "sg:address":"44029 Porto Garibaldi",
    "sg:city":"Porto Garibaldi",
    "sg:orig_category":"Macchine Utensili E Impianti. Macchine, Strumenti Ed Apparecchi Per Attivita' Industriali",
    "sg:phone":"+39 0533 326168",
    "sg:postcode":"44029",
    "sg:province":"Ferrara",
    "wof:name":"D.b.l. Elettronica Di De Biagi Luigi & C.snc",
    "wof:placetype":"venue"
},
  "geometry": {"coordinates":[12.240796,44.680019],"type":"Point"}
}