{
  "type": "Feature",
  "properties": {
    "iso:country":"IT",
    "sg:address":"40017 S.giovanni Persiceto",
    "sg:orig_category":"Abbigliamento Intimo, Calze E Costumi Da Bagno. Sport - Articoli E Forniture. Shopping",
    "sg:phone":"+39 051 681 0538",
    "sg:postcode":"40017",
    "sg:province":"Bologna",
    "wof:name":"C. & C. Sas",
    "wof:placetype":"venue"
},
  "geometry": {"coordinates":[11.284167,44.719383],"type":"Point"}
}