{
  "type": "Feature",
  "properties": {
    "addr:full":"10, Via Lama Luciano 52020 Pergine Valdarno Pergine Valdarno Arezzo 52020",
    "addr:housenumber":"valdarno",
    "addr:postcode":"52020;52020",
    "addr:street":"Via Lama Luciano",
    "iso:country":"IT",
    "sg:address":"10, Via Lama Luciano 52020 Pergine Valdarno",
    "sg:city":"Pergine Valdarno",
    "sg:classifiers":[
        {
            "category":"Manufacturing",
            "subcategory":"Metals",
            "type":"Manufacturing & Wholesale Goods"
        }
    ],
    "sg:phone":"+39 0575 896504",
    "sg:postcode":"52020",
    "sg:province":"Arezzo",
    "sg:tags":[
        "processing"
    ],
    "wof:name":"C.t.m. S.n.c. Di Bindi Dino & C.",
    "wof:placetype":"venue"
},
  "geometry": {"coordinates":[11.8630619049,43.4712028503],"type":"Point"}
}