{
  "type": "Feature",
  "properties": {
    "addr:full":"Piazza Giorgione 42; Castelfranco Veneto; 31033 Castelfranco Veneto Treviso 31033",
    "addr:housenumber":"42",
    "addr:postcode":"31033;31033",
    "addr:street":"Piazza Giorgione",
    "iso:country":"IT",
    "sg:address":"Piazza Giorgione 42; Castelfranco Veneto; 31033",
    "sg:city":"Castelfranco Veneto",
    "sg:classifiers":[
        {
            "category":"Banks & Credit Unions",
            "subcategory":"Bank",
            "type":"Services"
        }
    ],
    "sg:phone":"+39 0423 720380",
    "sg:postcode":"31033",
    "sg:province":"Treviso",
    "wof:name":"Banco Ambrosiano Veneto Spa",
    "wof:placetype":"venue"
},
  "geometry": {"coordinates":[11.926067,45.673042],"type":"Point"}
}