{
  "type": "Feature",
  "properties": {
    "addr:full":"22070 Appiano Gentile Appiano Gentile Como 22070",
    "addr:housenumber":"gentile",
    "addr:postcode":"22070;22070",
    "iso:country":"IT",
    "sg:address":"22070 Appiano Gentile",
    "sg:city":"Appiano Gentile",
    "sg:orig_category":"Abbigliamento Esterno, Maglierie E Pelliccerie",
    "sg:phone":"+39 031 930619",
    "sg:postcode":"22070",
    "sg:province":"Como",
    "wof:name":"Giuseppe Gregori",
    "wof:placetype":"venue"
},
  "geometry": {"coordinates":[9.045017,45.760708],"type":"Point"}
}