{
  "type": "Feature",
  "properties": {
    "iso:country":"IT",
    "sg:address":"85, Traversa Pistoiese 59100 Prato",
    "sg:city":"Prato",
    "sg:classifiers":[
        {
            "category":"Shopping",
            "subcategory":"Crafts & Fabrics",
            "type":"Retail Goods"
        }
    ],
    "sg:phone":"+39 39057436015",
    "sg:postcode":"59100",
    "sg:province":"Prato",
    "wof:name":"Texidea (s.r.l.)",
    "wof:placetype":"venue"
},
  "geometry": {"coordinates":[11.0602846146,43.8765106201],"type":"Point"}
}