{
  "type": "Feature",
  "properties": {
    "iso:country":"IT",
    "sg:address":"74024 Manduria",
    "sg:city":"Manduria",
    "sg:orig_category":"Internet, Telematica E Audiotex - Servizi",
    "sg:phone":"+39 099 971 3643",
    "sg:postcode":"74024",
    "sg:province":"Taranto",
    "wof:name":"Blackstorm Enterprise Di Nigro Biagio Antonio",
    "wof:placetype":"venue"
},
  "geometry": {"coordinates":[17.635601,40.401634],"type":"Point"}
}