{
  "type": "Feature",
  "properties": {
    "iso:country":"IT",
    "sg:address":"33080 San Quirino",
    "sg:city":"San Quirino",
    "sg:classifiers":[
        {
            "category":"Wholesale",
            "subcategory":"Chemicals & Plastics",
            "type":"Manufacturing & Wholesale Goods"
        }
    ],
    "sg:phone":"+39 0434 917053",
    "sg:postcode":"33080",
    "sg:province":"Pordenone",
    "sg:tags":[
        "article",
        "product",
        "plastics"
    ],
    "sg:website":"http://www.imacsrl.it",
    "wof:name":"I.ma.c. Srl",
    "wof:placetype":"venue"
},
  "geometry": {"coordinates":[12.6504964828,46.0310707092],"type":"Point"}
}