{
  "type": "Feature",
  "properties": {
    "addr:full":"20023 Cerro Maggiore Cerro Maggiore Milano 20023",
    "addr:housenumber":"20023",
    "addr:postcode":"20023",
    "addr:street":"Cerro",
    "iso:country":"IT",
    "sg:address":"20023 Cerro Maggiore",
    "sg:city":"Cerro Maggiore",
    "sg:orig_category":"Cemento E Calcestruzzo - Manufatti",
    "sg:phone":"+39 0331 519270",
    "sg:postcode":"20023",
    "sg:province":"Milano",
    "sg:website":"http://www.rotondiprefabbricati.it",
    "wof:name":"Rotondi Prefabbricati Srl",
    "wof:placetype":"venue"
},
  "geometry": {"coordinates":[8.95214,45.595787],"type":"Point"}
}