{
  "type": "Feature",
  "properties": {
    "addr:full":"1, Via Fascione 80078 Pozzuoli Pozzuoli Napoli 80078",
    "addr:postcode":"80078;80078",
    "addr:street":"Via Fascione",
    "iso:country":"IT",
    "sg:address":"1, Via Fascione 80078 Pozzuoli",
    "sg:city":"Pozzuoli",
    "sg:classifiers":[
        {
            "category":"Airport",
            "subcategory":"General Aviation",
            "type":"Transportation"
        }
    ],
    "sg:phone":"+39 081 866 5408",
    "sg:postcode":"80078",
    "sg:province":"Napoli",
    "sg:tags":[
        "transport",
        "air"
    ],
    "wof:name":"Tr.in.co.n.e.s.r.l.",
    "wof:placetype":"venue"
},
  "geometry": {"coordinates":[14.112552,40.838436],"type":"Point"}
}