{
  "type": "Feature",
  "properties": {
    "iso:country":"IT",
    "sg:address":"Via Udine 3 20036 Meda",
    "sg:city":"Meda",
    "sg:classifiers":[
        {
            "category":"Home & Garden",
            "subcategory":"Furniture",
            "type":"Retail Goods"
        }
    ],
    "sg:phone":"+39 036 23491",
    "sg:postcode":"20036",
    "sg:province":"Milano",
    "sg:tags":[
        "apartment"
    ],
    "sg:website":"www.colombostile.it",
    "wof:name":"Colombo Stile Spa",
    "wof:placetype":"venue"
},
  "geometry": {"coordinates":[9.1617212296,45.6521224976],"type":"Point"}
}