{
  "type": "Feature",
  "properties": {
    "iso:country":"IT",
    "sg:address":"20094 Corsico",
    "sg:city":"Corsico",
    "sg:orig_category":"Lavorazioni Metalli, Stampaggio E Saldatura",
    "sg:phone":"+39 02 4586 9893",
    "sg:postcode":"20094",
    "sg:province":"Milano",
    "wof:name":"Royal Toys Di Arienti Carlo & C. Snc",
    "wof:placetype":"venue"
},
  "geometry": {"coordinates":[9.083956,45.428722],"type":"Point"}
}