{
  "type": "Feature",
  "properties": {
    "addr:full":"Via Dell' Industria 30/32 35025 Cartura Cartura Padova 35025",
    "addr:housenumber":"30 / 32",
    "addr:postcode":"35025;35025",
    "addr:street":"Via Dell ' Industria",
    "iso:country":"IT",
    "sg:address":"Via Dell' Industria 30/32 35025 Cartura",
    "sg:city":"Cartura",
    "sg:classifiers":[
        {
            "category":"Farming",
            "subcategory":"Fish & Marine Products",
            "type":"Manufacturing & Wholesale Goods"
        }
    ],
    "sg:phone":"+39 049 955 6363",
    "sg:postcode":"35025",
    "sg:province":"Padova",
    "sg:tags":[
        "food",
        "chemical",
        "industry"
    ],
    "sg:website":"www.ikadogroup.com",
    "wof:name":"Ikado Group Srl",
    "wof:placetype":"venue"
},
  "geometry": {"coordinates":[11.852488,45.299473],"type":"Point"}
}