{
  "type": "Feature",
  "properties": {
    "addr:full":"3, Via Matteotti 28040 Dormelletto Dormelletto Novara 28040",
    "addr:postcode":"28040;28040",
    "addr:street":"Via Matteotti",
    "iso:country":"IT",
    "sg:address":"3, Via Matteotti 28040 Dormelletto",
    "sg:city":"Dormelletto",
    "sg:orig_category":"Miscellaneous Products",
    "sg:phone":"+39 0322 248663",
    "sg:postcode":"28040",
    "sg:province":"Novara",
    "wof:name":"Shd Italia S.r.l.",
    "wof:placetype":"venue"
},
  "geometry": {"coordinates":[8.5656280518,45.7432098389],"type":"Point"}
}