{
  "type": "Feature",
  "properties": {
    "iso:country":"IT",
    "sg:address":"73040 Melissano",
    "sg:city":"Melissano",
    "sg:classifiers":[
        {
            "category":"Home & Garden",
            "subcategory":"Hardware",
            "type":"Retail Goods"
        }
    ],
    "sg:phone":"+39 0833 55123",
    "sg:postcode":"73040",
    "sg:province":"Lecce",
    "sg:tags":[
        "activities",
        "industrial",
        "supply"
    ],
    "wof:name":"Icam Sud Srl",
    "wof:placetype":"venue"
},
  "geometry": {"coordinates":[18.12237,39.974998],"type":"Point"}
}