{
  "type": "Feature",
  "properties": {
    "addr:full":"20064 Gorgonzola Gorgonzola Milano 20064",
    "addr:postcode":"20064;20064",
    "iso:country":"IT",
    "sg:address":"20064 Gorgonzola",
    "sg:city":"Gorgonzola",
    "sg:orig_category":"Forniture Per Attivita' Industriali",
    "sg:phone":"+39 02 951 1150",
    "sg:postcode":"20064",
    "sg:province":"Milano",
    "wof:name":"Capardoni Srl",
    "wof:placetype":"venue"
},
  "geometry": {"coordinates":[9.4031305313,45.5234718323],"type":"Point"}
}