{
  "type": "Feature",
  "properties": {
    "iso:country":"IT",
    "sg:address":"80070 Bacoli",
    "sg:city":"Bacoli",
    "sg:orig_category":"Prodotti Chimici Secondari. Materiali Edili",
    "sg:phone":"+39 081 853 5162",
    "sg:postcode":"80070",
    "sg:province":"Napoli",
    "wof:name":"Maturo Mario",
    "wof:placetype":"venue"
},
  "geometry": {"coordinates":[14.0797958374,40.8013000488],"type":"Point"}
}