{
  "type": "Feature",
  "properties": {
    "iso:country":"IT",
    "sg:address":"Viale S. Longhi 24; Castiglione Delle Stiviere",
    "sg:classifiers":[
        {
            "category":"Banks & Credit Unions",
            "subcategory":"Bank",
            "type":"Services"
        }
    ],
    "sg:phone":"+39 0376 671290",
    "wof:name":"Banca Di Roma",
    "wof:placetype":"venue"
},
  "geometry": {"coordinates":[10.478764,45.394608],"type":"Point"}
}