{
  "type": "Feature",
  "properties": {
    "iso:country":"IT",
    "sg:address":"99, Viale Primavera 30027 San Dona' Di Piave",
    "sg:classifiers":[
        {
            "category":"Building & Trades",
            "subcategory":"Construction",
            "type":"Services"
        }
    ],
    "sg:phone":"+39 39042143603",
    "sg:postcode":"30027",
    "sg:province":"Venezia",
    "sg:tags":[
        "work",
        "public"
    ],
    "wof:name":"L'escavo Di Davanzo Paolo & Figli & C. (s.n.c.)",
    "wof:placetype":"venue"
},
  "geometry": {"coordinates":[12.588066,45.622822],"type":"Point"}
}