{
  "type": "Feature",
  "properties": {
    "addr:full":"10072 Caselle Torinese Caselle Torinese Torino 10072",
    "addr:postcode":"10072;10072",
    "iso:country":"IT",
    "sg:address":"10072 Caselle Torinese",
    "sg:city":"Caselle Torinese",
    "sg:orig_category":"Impianti Elettrici Industriali E Civili - Installazione E Manutenzione",
    "sg:phone":"+39 011 996 8984",
    "sg:postcode":"10072",
    "sg:province":"Torino",
    "wof:name":"Lo.sa. Impianti Elettrici Di Salierno Lorenzo",
    "wof:placetype":"venue"
},
  "geometry": {"coordinates":[7.70535,45.151913],"type":"Point"}
}