{
  "type": "Feature",
  "properties": {
    "addr:full":"58, Via Parauro 30035 Mirano Mirano Venezia 30035",
    "addr:postcode":"30035;30035",
    "addr:street":"Via Parauro",
    "iso:country":"IT",
    "sg:address":"58, Via Parauro 30035 Mirano",
    "sg:city":"Mirano",
    "sg:classifiers":[
        {
            "category":"Professional",
            "subcategory":"Engineering",
            "type":"Services"
        }
    ],
    "sg:phone":"+39 39041430091",
    "sg:postcode":"30035",
    "sg:province":"Venezia",
    "sg:tags":[
        "machine",
        "-",
        "mechanical"
    ],
    "wof:name":"F.lli Carraro Gianni E Dario (s.n.c.)",
    "wof:placetype":"venue"
},
  "geometry": {"coordinates":[12.10905,45.503498],"type":"Point"}
}