{
  "type": "Feature",
  "properties": {
    "addr:full":"20148 Milano Milano Milano 20148",
    "addr:postcode":"20148;20148",
    "iso:country":"IT",
    "sg:address":"20148 Milano",
    "sg:city":"Milano",
    "sg:orig_category":"Filati E Materie Prime Tessili. Prodotti E Manufatti In Materie Plastiche",
    "sg:phone":"+39 02 3926 6603",
    "sg:postcode":"20148",
    "sg:province":"Milano",
    "wof:name":"Elli Vittorio",
    "wof:placetype":"venue"
},
  "geometry": {"coordinates":[9.1469869614,45.4825439453],"type":"Point"}
}