{
  "type": "Feature",
  "properties": {
    "addr:full":"Via Carpi 25 47900 Rimini Rimini Rimini 47900",
    "addr:housenumber":"25",
    "addr:postcode":"47900;47900",
    "addr:street":"Via Carpi",
    "iso:country":"IT",
    "sg:address":"Via Carpi 25 47900 Rimini",
    "sg:city":"Rimini",
    "sg:classifiers":[
        {
            "category":"Building & Trades",
            "subcategory":"Construction",
            "type":"Services"
        }
    ],
    "sg:phone":"+39 0541 752210",
    "sg:postcode":"47900",
    "sg:province":"Rimini",
    "sg:tags":[
        "cast",
        "stone"
    ],
    "sg:website":"www.riminiroc.it",
    "wof:name":"Lega Costruzioni",
    "wof:placetype":"venue"
},
  "geometry": {"coordinates":[12.524247,44.022465],"type":"Point"}
}