{
  "type": "Feature",
  "properties": {
    "iso:country":"IT",
    "sg:address":"20124 Milano",
    "sg:city":"Milano",
    "sg:orig_category":"Serramenti Ed Infissi. Forniture Industriali Per Prevenzione, Controllo E Sicurezza",
    "sg:phone":"+39 02 2951 4791",
    "sg:postcode":"20124",
    "sg:province":"Milano",
    "wof:name":"Casseforti E Serrature Di Marelli Angelo & C.",
    "wof:placetype":"venue"
},
  "geometry": {"coordinates":[9.204403,45.47707],"type":"Point"}
}