{
  "type": "Feature",
  "properties": {
    "addr:full":"17011 Albisola Superiore Albisola Superiore Savona 17011",
    "addr:postcode":"17011;17011",
    "iso:country":"IT",
    "sg:address":"17011 Albisola Superiore",
    "sg:city":"Albisola Superiore",
    "sg:orig_category":"Carni, Salumi E Pesci",
    "sg:phone":"+39 019 489904",
    "sg:postcode":"17011",
    "sg:province":"Savona",
    "wof:name":"Albigadus Snc Di Spinetti S. & C.",
    "wof:placetype":"venue"
},
  "geometry": {"coordinates":[8.503522,44.340981],"type":"Point"}
}