{
  "type": "Feature",
  "properties": {
    "addr:full":"27100 Pavia Pavia Pavia 27100",
    "addr:postcode":"27100;27100",
    "iso:country":"IT",
    "sg:address":"27100 Pavia",
    "sg:city":"Pavia",
    "sg:orig_category":"Abbigliamento Intimo, Calze E Costumi Da Bagno. Articoli Medico-sanitari Ed Ortopedici",
    "sg:phone":"+39 0382 303607",
    "sg:postcode":"27100",
    "sg:province":"Pavia",
    "wof:name":"Noli Carlo",
    "wof:placetype":"venue"
},
  "geometry": {"coordinates":[9.152993,45.185078],"type":"Point"}
}