{
  "type": "Feature",
  "properties": {
    "addr:full":"00155 Roma Roma Roma 00155",
    "addr:postcode":"00155;00155",
    "iso:country":"IT",
    "sg:address":"00155 Roma",
    "sg:city":"Roma",
    "sg:orig_category":"Trasporti E Spedizioni Merci",
    "sg:phone":"+39 06 225 2248",
    "sg:postcode":"00155",
    "sg:province":"Roma",
    "wof:name":"Bartolini Spa",
    "wof:placetype":"venue"
},
  "geometry": {"coordinates":[12.609141,41.890545],"type":"Point"}
}