{
  "type": "Feature",
  "properties": {
    "addr:full":"10134 Torino Torino Torino 10134",
    "addr:postcode":"10134;10134",
    "iso:country":"IT",
    "sg:address":"10134 Torino",
    "sg:city":"Torino",
    "sg:orig_category":"Prodotti Alimentari",
    "sg:phone":"+39 011 318 7007",
    "sg:postcode":"10134",
    "sg:province":"Torino",
    "wof:name":"Nuova Socam Srl",
    "wof:placetype":"venue"
},
  "geometry": {"coordinates":[7.6554512978,45.0398902893],"type":"Point"}
}