{
  "type": "Feature",
  "properties": {
    "iso:country":"IT",
    "sg:address":"124, V. Ponara 47032 Bertinoro",
    "sg:city":"Bertinoro",
    "sg:classifiers":[
        {
            "category":"Home & Garden",
            "subcategory":"Home Furnishings",
            "type":"Retail Goods"
        }
    ],
    "sg:phone":"+39 0543 448025",
    "sg:postcode":"47032",
    "sg:province":"Forl\u00ec-Cesena",
    "sg:tags":[
        "household"
    ],
    "sg:website":"http://www.paginegialle.it/deddideleonardis",
    "wof:name":"D & D Di Federico De Leonardis",
    "wof:placetype":"venue"
},
  "geometry": {"coordinates":[12.140488,44.172085],"type":"Point"}
}