{
  "type": "Feature",
  "properties": {
    "addr:full":"9, Via Fernando Santi 43044 Collecchio Collecchio Parma 43044",
    "addr:postcode":"43044;43044",
    "addr:street":"Via Fernando Santi",
    "iso:country":"IT",
    "sg:address":"9, Via Fernando Santi 43044 Collecchio",
    "sg:city":"Collecchio",
    "sg:classifiers":[
        {
            "category":"Professional",
            "subcategory":"Computer Services",
            "type":"Services"
        }
    ],
    "sg:phone":"+39 0521 304375",
    "sg:postcode":"43044",
    "sg:province":"Parma",
    "sg:tags":[
        "information",
        "technology"
    ],
    "wof:name":"Bms Softeco S.r.l.",
    "wof:placetype":"venue"
},
  "geometry": {"coordinates":[10.329548,44.807865],"type":"Point"}
}