{
  "type": "Feature",
  "properties": {
    "addr:full":"24040 Lallio Lallio Bergamo 24040",
    "addr:postcode":"24040;24040",
    "iso:country":"IT",
    "sg:address":"24040 Lallio",
    "sg:city":"Lallio",
    "sg:orig_category":"Macchine Ed Impianti Per Edilizia E Lavori Pubblici",
    "sg:phone":"+39 035 201451",
    "sg:postcode":"24040",
    "sg:province":"Bergamo",
    "wof:name":"Kennington Link Di Rovaris Paolo",
    "wof:placetype":"venue"
},
  "geometry": {"coordinates":[9.625676,45.670345],"type":"Point"}
}