{
  "type": "Feature",
  "properties": {
    "iso:country":"IT",
    "sg:address":"31029 Vittorio Veneto",
    "sg:city":"Vittorio Veneto",
    "sg:orig_category":"Manufacturers: Prefabbricati",
    "sg:phone":"+39 0438 9111",
    "sg:postcode":"31029",
    "sg:province":"Treviso",
    "sg:website":"http://www.tegolacanadese.com",
    "wof:name":"Tegola Canadese Spa",
    "wof:placetype":"venue"
},
  "geometry": {"coordinates":[12.300996,45.996239],"type":"Point"}
}