{
  "type": "Feature",
  "properties": {
    "iso:country":"IT",
    "sg:address":"2, Via G.rossa 40030 Castel Di Casio",
    "sg:city":"Castel di Casio",
    "sg:classifiers":[
        {
            "category":"Manufacturing",
            "subcategory":"Lumber",
            "type":"Manufacturing & Wholesale Goods"
        }
    ],
    "sg:phone":"+39 39053431054",
    "sg:postcode":"40030",
    "sg:province":"Bologna",
    "sg:tags":[
        "wood"
    ],
    "wof:name":"Migliorini Mario",
    "wof:placetype":"venue"
},
  "geometry": {"coordinates":[11.346481,44.494221],"type":"Point"}
}