{
  "type": "Feature",
  "properties": {
    "addr:full":"16129 Genova Genova Genova 16129",
    "addr:postcode":"16129;16129",
    "iso:country":"IT",
    "sg:address":"16129 Genova",
    "sg:city":"Genova",
    "sg:orig_category":"Medici. Assicurazioni E Servizi Assicurativi. Avvocati, Notai E Servizi Legali. Professionisti - Studi E Servizi Ed Associazioni Di Interesse Aziendale",
    "sg:phone":"+39 010 362 7175",
    "sg:postcode":"16129",
    "sg:province":"Genova",
    "wof:name":"Studio Associato Medicina Del Lavoro Dott. Giuseppe Vibracci & C. Associazio",
    "wof:placetype":"venue"
},
  "geometry": {"coordinates":[8.954750061,44.4041137695],"type":"Point"}
}