{
  "type": "Feature",
  "properties": {
    "addr:full":"129, Via Straelle 35011 Campodarsego Campodarsego Padova 35011",
    "addr:housenumber":"129",
    "addr:postcode":"35011;35011",
    "addr:street":"Via Straelle",
    "iso:country":"IT",
    "sg:address":"129, Via Straelle 35011 Campodarsego",
    "sg:city":"Campodarsego",
    "sg:classifiers":[
        {
            "category":"Manufacturing",
            "subcategory":"Metals",
            "type":"Manufacturing & Wholesale Goods"
        }
    ],
    "sg:phone":"+39 049 556 4089",
    "sg:postcode":"35011",
    "sg:province":"Padova",
    "sg:tags":[
        "metallurgy",
        "metalworking"
    ],
    "wof:name":"Dovico Luigi",
    "wof:placetype":"venue"
},
  "geometry": {"coordinates":[11.9267244339,45.550743103],"type":"Point"}
}