{
  "type": "Feature",
  "properties": {
    "iso:country":"IT",
    "sg:address":"15, Via Valle Pusteria 39030 Chienes",
    "sg:city":"Chienes",
    "sg:classifiers":[
        {
            "category":"Shopping",
            "type":"Retail Goods"
        }
    ],
    "sg:phone":"+39 0474 565317",
    "sg:postcode":"39030",
    "sg:province":"Bolzano/Bozen",
    "sg:tags":[
        "finished",
        "-",
        "metallic"
    ],
    "wof:name":"Kammerer Serbatoi S.r.l.kammerer Tankbau G.m.b.h.",
    "wof:placetype":"venue"
},
  "geometry": {"coordinates":[11.8223619461,46.8078613281],"type":"Point"}
}