{
  "type": "Feature",
  "properties": {
    "addr:full":"16129 Genova Genova Genova 16129",
    "addr:postcode":"16129;16129",
    "iso:country":"IT",
    "sg:address":"16129 Genova",
    "sg:city":"Genova",
    "sg:orig_category":"Porte",
    "sg:phone":"+39 010 362 3810",
    "sg:postcode":"16129",
    "sg:province":"Genova",
    "wof:name":"Edil Porta Sas",
    "wof:placetype":"venue"
},
  "geometry": {"coordinates":[8.9527292252,44.4013252258],"type":"Point"}
}