{
  "type": "Feature",
  "properties": {
    "iso:country":"IT",
    "sg:address":"7 Via Crocera Di Corva 33082 Azzano Decimo",
    "sg:city":"Azzano Decimo",
    "sg:classifiers":[
        {
            "category":"Manufacturing",
            "subcategory":"Furniture",
            "type":"Manufacturing & Wholesale Goods"
        }
    ],
    "sg:phone":"+39 0434 632624",
    "sg:postcode":"33082",
    "sg:province":"Pordenone",
    "sg:tags":[
        "dental"
    ],
    "sg:website":"www.edarredo.it",
    "wof:name":"Edarredo Srl",
    "wof:placetype":"venue"
},
  "geometry": {"coordinates":[12.655044,45.96265],"type":"Point"}
}