{
  "type": "Feature",
  "properties": {
    "iso:country":"IT",
    "sg:address":"17011 Albisola Superiore",
    "sg:city":"Albisola Superiore",
    "sg:orig_category":"Arredi Ed Attrezzature Per Uffici",
    "sg:phone":"+39 019 487358",
    "sg:postcode":"17011",
    "sg:province":"Savona",
    "wof:name":"Nuova Reda Sas Di Francone P.l. E C.",
    "wof:placetype":"venue"
},
  "geometry": {"coordinates":[8.500964,44.33939],"type":"Point"}
}