{
  "type": "Feature",
  "properties": {
    "addr:full":"44/46, Via Pertile Antonio 35127 Padova Padova Padova 35127",
    "addr:housenumber":"44 / 46",
    "addr:postcode":"35127;35127",
    "addr:street":"Via Pertile Antonio",
    "iso:country":"IT",
    "sg:address":"44/46, Via Pertile Antonio 35127 Padova",
    "sg:city":"Padova",
    "sg:orig_category":"Miscellaneous Products",
    "sg:phone":"+39 39049757736",
    "sg:postcode":"35127",
    "sg:province":"Padova",
    "wof:name":"Lando Felice (s.r.l.)",
    "wof:placetype":"venue"
},
  "geometry": {"coordinates":[11.8441667557,45.3974990845],"type":"Point"}
}