{
  "type": "Feature",
  "properties": {
    "addr:full":"34147 Trieste Trieste Trieste 34147",
    "addr:postcode":"34147;34147",
    "iso:country":"IT",
    "sg:address":"34147 Trieste",
    "sg:city":"Trieste",
    "sg:classifiers":[
        {
            "category":"Building & Trades",
            "subcategory":"Construction",
            "type":"Services"
        }
    ],
    "sg:phone":"+39 040 382399",
    "sg:postcode":"34147",
    "sg:province":"Trieste",
    "sg:tags":[
        "industry",
        "work",
        "plastic"
    ],
    "wof:name":"General Service Trieste Srl",
    "wof:placetype":"venue"
},
  "geometry": {"coordinates":[13.8005437851,45.6187210083],"type":"Point"}
}