{
  "type": "Feature",
  "properties": {
    "iso:country":"IT",
    "sg:address":"65124 Pescara",
    "sg:city":"Pescara",
    "sg:orig_category":"Tessuti Arredamento, Tende E Tappeti",
    "sg:phone":"+39 085 293360",
    "sg:postcode":"65124",
    "sg:province":"Pescara",
    "wof:name":"Edi Le Tende Che Arredano Di Recchia Gianni",
    "wof:placetype":"venue"
},
  "geometry": {"coordinates":[14.150833,42.474998],"type":"Point"}
}