{
  "type": "Feature",
  "properties": {
    "addr:full":"20149 Milano Milano Milano 20149",
    "addr:postcode":"20149;20149",
    "iso:country":"IT",
    "sg:address":"20149 Milano",
    "sg:city":"Milano",
    "sg:orig_category":"Servizi Per Aziende, Manifestazioni E Supporto Agli Scambi Commerciali",
    "sg:phone":"+39 02 3300 7464",
    "sg:postcode":"20149",
    "sg:province":"Milano",
    "wof:name":"Tele Atlas B.v.",
    "wof:placetype":"venue"
},
  "geometry": {"coordinates":[9.151825,45.487572],"type":"Point"}
}