{
  "type": "Feature",
  "properties": {
    "iso:country":"IT",
    "sg:address":"145 Via Meisules 39048 Selva Di Val Gardena",
    "sg:city":"Selva",
    "sg:classifiers":[
        {
            "category":"Travel",
            "subcategory":"Travel Agent",
            "type":"Entertainment"
        }
    ],
    "sg:phone":"+39 0471 795211",
    "sg:postcode":"39048",
    "sg:province":"Bolzano/Bozen",
    "sg:tags":[
        "business"
    ],
    "wof:name":"Hotel Sport Gran Baita",
    "wof:placetype":"venue"
},
  "geometry": {"coordinates":[11.754748,46.556461],"type":"Point"}
}