{
  "type": "Feature",
  "properties": {
    "addr:full":"52024 Loro Ciuffenna Loro Ciuffenna Arezzo 52024",
    "addr:housenumber":"ciuffenna",
    "addr:postcode":"52024;52024",
    "iso:country":"IT",
    "sg:address":"52024 Loro Ciuffenna",
    "sg:city":"Loro Ciuffenna",
    "sg:orig_category":"Servizi Vari Di Interesse Pubblico",
    "sg:phone":"+39 055 917 2320",
    "sg:postcode":"52024",
    "sg:province":"Arezzo",
    "wof:name":"Il Mondo Di Bri",
    "wof:placetype":"venue"
},
  "geometry": {"coordinates":[11.715048,43.507473],"type":"Point"}
}