{
  "type": "Feature",
  "properties": {
    "addr:full":"20121 Milano Milano Milano 20121",
    "addr:postcode":"20121;20121",
    "iso:country":"IT",
    "sg:address":"20121 Milano",
    "sg:city":"Milano",
    "sg:orig_category":"Servizi Al Turismo. Ambasciate Ed Enti Internazionali",
    "sg:phone":"+39 02 7202 1905",
    "sg:postcode":"20121",
    "sg:province":"Milano",
    "wof:name":"Consolato Cina (repubblica Popolare)",
    "wof:placetype":"venue"
},
  "geometry": {"coordinates":[9.176452,45.469105],"type":"Point"}
}