{
  "type": "Feature",
  "properties": {
    "iso:country":"IT",
    "sg:address":"00178 Roma",
    "sg:city":"Roma",
    "sg:orig_category":"Ristorazione E Locali Pubblici Affini. Ristoranti Ed Esercizi Affini. Servizi Ausiliari Di Ristorazione E Di Intrattenimento",
    "sg:phone":"+39 06 718 3332",
    "sg:postcode":"00178",
    "sg:province":"Roma",
    "sg:website":"http://www.lenuovecoperture.it",
    "wof:name":"Le Coperture By Giovanni Da Fr\u00c9 Srl",
    "wof:placetype":"venue"
},
  "geometry": {"coordinates":[12.542293,41.842178],"type":"Point"}
}