{
  "type": "Feature",
  "properties": {
    "addr:full":"11, Via Milite Ignoto 16012 Busalla Busalla Genova 16012",
    "addr:postcode":"16012;16012",
    "addr:street":"Via Milite Ignoto",
    "iso:country":"IT",
    "sg:address":"11, Via Milite Ignoto 16012 Busalla",
    "sg:city":"Busalla",
    "sg:classifiers":[
        {
            "category":"Sports & Exercise",
            "subcategory":"Playing Field",
            "type":"Entertainment"
        }
    ],
    "sg:phone":"+39 010 964 0791",
    "sg:postcode":"16012",
    "sg:province":"Genova",
    "sg:tags":[
        "game"
    ],
    "wof:name":"Bardola (s.p.a.)",
    "wof:placetype":"venue"
},
  "geometry": {"coordinates":[8.955082,44.571659],"type":"Point"}
}