{
  "type": "Feature",
  "properties": {
    "addr:full":"80040 Poggiomarino Poggiomarino Napoli 80040",
    "addr:postcode":"80040;80040",
    "iso:country":"IT",
    "sg:address":"80040 Poggiomarino",
    "sg:city":"Poggiomarino",
    "sg:orig_category":"Non-classified Establishments",
    "sg:phone":"+39 081 865 1047",
    "sg:postcode":"80040",
    "sg:province":"Napoli",
    "wof:name":"A. Cutolo Arredamenti Srl",
    "wof:placetype":"venue"
},
  "geometry": {"coordinates":[14.545458,40.796677],"type":"Point"}
}