{
  "type": "Feature",
  "properties": {
    "iso:country":"IT",
    "sg:address":"20123 Milano",
    "sg:city":"Milano",
    "sg:orig_category":"Servizi Per Aziende, Manifestazioni E Supporto Agli Scambi Commerciali",
    "sg:phone":"+39 02 467 5101",
    "sg:postcode":"20123",
    "sg:province":"Milano",
    "wof:name":"Promunidi Srl",
    "wof:placetype":"venue"
},
  "geometry": {"coordinates":[9.169645,45.470371],"type":"Point"}
}