{
  "type": "Feature",
  "properties": {
    "iso:country":"IT",
    "sg:address":"09123 Cagliari",
    "sg:city":"Cagliari",
    "sg:orig_category":"Cancelleria",
    "sg:phone":"+39 070 662414",
    "sg:postcode":"09123",
    "sg:province":"Cagliari",
    "wof:name":"Collu Tonio",
    "wof:placetype":"venue"
},
  "geometry": {"coordinates":[9.104115,39.220673],"type":"Point"}
}