{
  "type": "Feature",
  "properties": {
    "addr:full":"62, V. Maestri Del Lavoro 30027 San Don\u00e0 Di Piave Venezia 30027",
    "addr:housenumber":"62",
    "addr:postcode":"30027;30027",
    "addr:street":"V. Maestri Del Lavoro",
    "iso:country":"IT",
    "sg:address":"62, V. Maestri Del Lavoro 30027 San Don\u00e0 Di Piave",
    "sg:classifiers":[
        {
            "category":"Home & Garden",
            "subcategory":"Home Furnishings",
            "type":"Retail Goods"
        }
    ],
    "sg:phone":"+39 39042141928",
    "sg:postcode":"30027",
    "sg:province":"Venezia",
    "sg:tags":[
        "household"
    ],
    "sg:website":"http://www.mobil-house.it:ws_end: :mark:ws:http://www.paginegialle.it/mobilhouse01",
    "wof:name":"Mobil House",
    "wof:placetype":"venue"
},
  "geometry": {"coordinates":[12.593901,45.621555],"type":"Point"}
}