{
  "type": "Feature",
  "properties": {
    "addr:full":"10042 Nichelino Nichelino Torino 10042",
    "addr:postcode":"10042;10042",
    "iso:country":"IT",
    "sg:address":"10042 Nichelino",
    "sg:city":"Nichelino",
    "sg:orig_category":"Frigotecnica, Apparecchiature E Servizi",
    "sg:phone":"+39 011 680 0347",
    "sg:postcode":"10042",
    "sg:province":"Torino",
    "wof:name":"Interdryers Srl",
    "wof:placetype":"venue"
},
  "geometry": {"coordinates":[7.6404495239,44.9755973816],"type":"Point"}
}