{
  "type": "Feature",
  "properties": {
    "addr:full":"51100 Pistoia Pistoia Pistoia 51100",
    "addr:postcode":"51100;51100",
    "iso:country":"IT",
    "sg:address":"51100 Pistoia",
    "sg:city":"Pistoia",
    "sg:orig_category":"Abiti Da Sposa E Cerimonia",
    "sg:phone":"+39 0573 26678",
    "sg:postcode":"51100",
    "sg:province":"Pistoia",
    "wof:name":"Fiori D'arancio Di Capecchi Massimo",
    "wof:placetype":"venue"
},
  "geometry": {"coordinates":[10.916872,43.931568],"type":"Point"}
}