{
  "type": "Feature",
  "properties": {
    "addr:full":"43030 Torrile Parma 43030",
    "addr:postcode":"43030;43030",
    "iso:country":"IT",
    "sg:address":"43030 Torrile",
    "sg:orig_category":"Abbigliamento Sportivo - Produzione E Ingrosso",
    "sg:phone":"+39 0521 813521",
    "sg:postcode":"43030",
    "sg:province":"Parma",
    "sg:website":"http://www.errea.it",
    "wof:name":"Errea' Sport Spa",
    "wof:placetype":"venue"
},
  "geometry": {"coordinates":[10.357239,44.886486],"type":"Point"}
}