{
  "type": "Feature",
  "properties": {
    "addr:full":"Via Molino 4; Vestone; 25078 Vestone Brescia 25078",
    "addr:housenumber":"4",
    "addr:postcode":"25078;25078",
    "addr:street":"Via Molino;Vestone",
    "iso:country":"IT",
    "sg:address":"Via Molino 4; Vestone; 25078",
    "sg:city":"Vestone",
    "sg:classifiers":[
        {
            "category":"Banks & Credit Unions",
            "subcategory":"Bank",
            "type":"Services"
        }
    ],
    "sg:phone":"+39 036 58291",
    "sg:postcode":"25078",
    "sg:province":"Brescia",
    "wof:name":"Banca Cooperativa Valsabbina",
    "wof:placetype":"venue"
},
  "geometry": {"coordinates":[10.404938,45.709896],"type":"Point"}
}