{
  "type": "Feature",
  "properties": {
    "addr:full":"Via Rondissone 9 10155 Torino Torino Torino 10155",
    "addr:housenumber":"9",
    "addr:postcode":"10155;10155",
    "addr:street":"Via Rondissone",
    "iso:country":"IT",
    "sg:address":"Via Rondissone 9 10155 Torino",
    "sg:city":"Torino",
    "sg:orig_category":"Repair Services For Medical Appliances",
    "sg:phone":"+39 011 205 3223",
    "sg:postcode":"10155",
    "sg:province":"Torino",
    "sg:website":"www.satap.net",
    "wof:name":"Satap Srl Servizi Assistenza Tecnica Attrezzature Professionali",
    "wof:placetype":"venue"
},
  "geometry": {"coordinates":[8.39892,45.462345],"type":"Point"}
}