{
  "type": "Feature",
  "properties": {
    "addr:full":"17031 Leca Leca Savona 17031",
    "addr:postcode":"17031;17031",
    "iso:country":"IT",
    "sg:address":"17031 Leca",
    "sg:city":"Leca",
    "sg:orig_category":"Macchine, Impianti Ed Attrezzature Per Agricoltura E Zootecnia",
    "sg:phone":"+39 0182 589045",
    "sg:postcode":"17031",
    "sg:province":"Savona",
    "wof:name":"Excoserre",
    "wof:placetype":"venue"
},
  "geometry": {"coordinates":[8.181136,44.061325],"type":"Point"}
}