{
  "type": "Feature",
  "properties": {
    "addr:full":"16134 Genova Genova Genova 16134",
    "addr:postcode":"16134;16134",
    "iso:country":"IT",
    "sg:address":"16134 Genova",
    "sg:city":"Genova",
    "sg:orig_category":"Ospedali E Servizi Sanitari",
    "sg:phone":"+39 010 230038",
    "sg:postcode":"16134",
    "sg:province":"Genova",
    "wof:name":"Pubblica Assistenza I Volontari",
    "wof:placetype":"venue"
},
  "geometry": {"coordinates":[8.9205913544,44.4268226624],"type":"Point"}
}