{
  "type": "Feature",
  "properties": {
    "iso:country":"IT",
    "sg:address":"22038 Tavernerio",
    "sg:city":"Tavernerio",
    "sg:orig_category":"Servizi E Lavori Per Abbigliamento E Pelletterie",
    "sg:phone":"+39 031 420791",
    "sg:postcode":"22038",
    "sg:province":"Como",
    "wof:name":"Studio Genny",
    "wof:placetype":"venue"
},
  "geometry": {"coordinates":[9.150097,45.803028],"type":"Point"}
}