{
  "type": "Feature",
  "properties": {
    "iso:country":"IT",
    "sg:address":"95126 Catania",
    "sg:city":"Catania",
    "sg:orig_category":"Sport - Articoli E Forniture",
    "sg:phone":"+39 095 712 2342",
    "sg:postcode":"95126",
    "sg:province":"Catania",
    "wof:name":"Isola Blu S.r.l.",
    "wof:placetype":"venue"
},
  "geometry": {"coordinates":[15.116213,37.524437],"type":"Point"}
}