{
  "type": "Feature",
  "properties": {
    "addr:full":"20010 Pogliano Milanese Pogliano Milanese Milano 20010",
    "addr:postcode":"20010;20010",
    "iso:country":"IT",
    "sg:address":"20010 Pogliano Milanese",
    "sg:city":"Pogliano Milanese",
    "sg:orig_category":"Materiali Semilavorati Metallici",
    "sg:phone":"+39 02 9325 5541",
    "sg:postcode":"20010",
    "sg:province":"Milano",
    "wof:name":"Nuova Idealtaglio (s.r.l.)",
    "wof:placetype":"venue"
},
  "geometry": {"coordinates":[9.00899,45.541115],"type":"Point"}
}