{
  "type": "Feature",
  "properties": {
    "iso:country":"IT",
    "sg:address":"16143 Genova",
    "sg:city":"Genova",
    "sg:orig_category":"Forniture Per Abbigliamento E Pelletterie",
    "sg:phone":"+39 010 511017",
    "sg:postcode":"16143",
    "sg:province":"Genova",
    "wof:name":"Rissotto Carla",
    "wof:placetype":"venue"
},
  "geometry": {"coordinates":[8.9586133957,44.4071159363],"type":"Point"}
}