{
  "type": "Feature",
  "properties": {
    "iso:country":"IT",
    "sg:address":"55049 Viareggio",
    "sg:city":"Viareggio",
    "sg:orig_category":"Servizi Ausiliari Per Il Trasporto",
    "sg:phone":"+39 0584 388869",
    "sg:postcode":"55049",
    "sg:province":"Lucca",
    "wof:name":"Bacci Luciano & Bitozzi Carla S.n.c",
    "wof:placetype":"venue"
},
  "geometry": {"coordinates":[10.246402,43.858383],"type":"Point"}
}