{
  "type": "Feature",
  "properties": {
    "iso:country":"IT",
    "sg:address":"12, Via S. Gregorio 20124 Milano",
    "sg:city":"Milano",
    "sg:classifiers":[
        {
            "category":"Professional",
            "subcategory":"Engineering",
            "type":"Services"
        }
    ],
    "sg:phone":"+39 02 2940 9466",
    "sg:postcode":"20124",
    "sg:province":"Milano",
    "sg:tags":[
        "machine",
        "-",
        "mechanical"
    ],
    "wof:name":"Sacconaghi Monaco (s.r.l.)",
    "wof:placetype":"venue"
},
  "geometry": {"coordinates":[9.206601,45.478512],"type":"Point"}
}