{
  "type": "Feature",
  "properties": {
    "iso:country":"IT",
    "sg:address":"74100 Taranto",
    "sg:city":"Taranto",
    "sg:orig_category":"Finanziamenti E Mutui",
    "sg:phone":"+39 099 732 8789",
    "sg:postcode":"74100",
    "sg:province":"Taranto",
    "wof:name":"Credit Service Di Di Cuia Marcello",
    "wof:placetype":"venue"
},
  "geometry": {"coordinates":[17.2586898804,40.4627075195],"type":"Point"}
}