{
  "type": "Feature",
  "properties": {
    "addr:full":"Via Madonna Del Golfo 14 54100 Massa Massa Massa-Carrara 54100",
    "addr:housenumber":"14",
    "addr:postcode":"54100;54100",
    "addr:street":"Via Madonna Del Golfo",
    "iso:country":"IT",
    "sg:address":"Via Madonna Del Golfo 14 54100 Massa",
    "sg:city":"Massa",
    "sg:classifiers":[
        {
            "category":"Home & Garden",
            "subcategory":"Building Materials",
            "type":"Retail Goods"
        }
    ],
    "sg:phone":"+39 0585 254355",
    "sg:postcode":"54100",
    "sg:province":"Massa-Carrara",
    "sg:tags":[
        "slab",
        "marble"
    ],
    "sg:website":"www.internationalmarmi.com",
    "wof:name":"International Italmarmi Srl",
    "wof:placetype":"venue"
},
  "geometry": {"coordinates":[10.119316,44.02002],"type":"Point"}
}