{
  "type": "Feature",
  "properties": {
    "addr:full":"Via Adriatica 165 47843 Misano Adriatico Misano Adriatico Rimini 47843",
    "addr:housenumber":"165",
    "addr:postcode":"47843;47843",
    "addr:street":"Via Adriatica",
    "iso:country":"IT",
    "sg:address":"Via Adriatica 165 47843 Misano Adriatico",
    "sg:city":"Misano Adriatico",
    "sg:classifiers":[
        {
            "category":"Bus Stop",
            "subcategory":"None",
            "type":"Transportation"
        }
    ],
    "sg:phone":"+39 0541 612664",
    "sg:postcode":"47843",
    "sg:province":"Rimini",
    "sg:tags":[
        "period",
        "furniture"
    ],
    "sg:website":"www.bassanmobili.it",
    "wof:name":"N. Bassano",
    "wof:placetype":"venue"
},
  "geometry": {"coordinates":[12.6644744873,43.9916381836],"type":"Point"}
}