{
  "type": "Feature",
  "properties": {
    "iso:country":"IT",
    "sg:address":"25080 Puegnago Del Garda",
    "sg:classifiers":[
        {
            "category":"Farming",
            "subcategory":"Berry Farm",
            "type":"Manufacturing & Wholesale Goods"
        }
    ],
    "sg:phone":"+39 036 565 1291",
    "sg:postcode":"25080",
    "sg:province":"Brescia",
    "sg:tags":[
        "vegetable",
        "growing",
        "flower",
        "agriculture"
    ],
    "wof:name":"Azienda Agricola Monteacuto Di Leali Antonio",
    "wof:placetype":"venue"
},
  "geometry": {"coordinates":[10.171578,45.459564],"type":"Point"}
}