{
  "type": "Feature",
  "properties": {
    "addr:full":"20149 Milano Milano Milano 20149",
    "addr:postcode":"20149;20149",
    "iso:country":"IT",
    "sg:address":"20149 Milano",
    "sg:city":"Milano",
    "sg:orig_category":"Professionisti - Studi E Servizi Ed Associazioni Di Interesse Aziendale. Associazioni Ed Organismi Di Interesse Pubblico",
    "sg:postcode":"20149",
    "sg:province":"Milano",
    "wof:name":"Istituto Italiano Dei Plastici Srl",
    "wof:placetype":"venue"
},
  "geometry": {"coordinates":[9.1522111893,45.4849128723],"type":"Point"}
}