{
  "type": "Feature",
  "properties": {
    "addr:full":"95039 Trecastagni Trecastagni Catania 95039",
    "addr:postcode":"95039;95039",
    "iso:country":"IT",
    "sg:address":"95039 Trecastagni",
    "sg:city":"Trecastagni",
    "sg:orig_category":"Macchine, Impianti Ed Attrezzature Per Industria Alimentare E Bevande",
    "sg:phone":"+39 095 780 1264",
    "sg:postcode":"95039",
    "sg:province":"Catania",
    "wof:name":"Fertec Del Geom.ferlito Biagio",
    "wof:placetype":"venue"
},
  "geometry": {"coordinates":[15.076741,37.614609],"type":"Point"}
}