{
  "type": "Feature",
  "properties": {
    "iso:country":"IT",
    "sg:address":"40, Via Mondovi' 12045 Fossano",
    "sg:city":"Fossano",
    "sg:classifiers":[
        {
            "category":"Retail",
            "subcategory":"Animal Services",
            "type":"Services"
        }
    ],
    "sg:phone":"+39 39017260572",
    "sg:postcode":"12045",
    "sg:province":"Cuneo",
    "sg:tags":[
        "breeding"
    ],
    "wof:name":"Mangimi 4 Torri (s.a.s.)",
    "wof:placetype":"venue"
},
  "geometry": {"coordinates":[7.754159,44.469563],"type":"Point"}
}