{
  "type": "Feature",
  "properties": {
    "iso:country":"IT",
    "sg:address":"24126 Bergamo",
    "sg:city":"Bergamo",
    "sg:orig_category":"Assicurazioni E Servizi Assicurativi",
    "sg:phone":"+39 035 313113",
    "sg:postcode":"24126",
    "sg:province":"Bergamo",
    "sg:website":"http://www.assicurazionicondominiali.it",
    "wof:name":"Mazzoleni Umberto - Zurigo Assicurazioni",
    "wof:placetype":"venue"
},
  "geometry": {"coordinates":[9.676105,45.681568],"type":"Point"}
}