{
  "type": "Feature",
  "properties": {
    "addr:full":"20141 Milano Milano Milano 20141",
    "addr:postcode":"20141;20141",
    "iso:country":"IT",
    "sg:address":"20141 Milano",
    "sg:city":"Milano",
    "sg:orig_category":"Prodotti Alimentari",
    "sg:phone":"+39 0252561",
    "sg:postcode":"20141",
    "sg:province":"Milano",
    "wof:name":"Heinz Italia Srl",
    "wof:placetype":"venue"
},
  "geometry": {"coordinates":[9.1997509003,45.4239616394],"type":"Point"}
}