{
  "type": "Feature",
  "properties": {
    "addr:full":"65129 Pescara Pescara Pescara 65129",
    "addr:postcode":"65129;65129",
    "iso:country":"IT",
    "sg:address":"65129 Pescara",
    "sg:city":"Pescara",
    "sg:orig_category":"Prodotti E Manufatti In Materie Plastiche. Forniture Per Edilizia E Lavori Pubblici",
    "sg:phone":"+39 085 471 0586",
    "sg:postcode":"65129",
    "sg:province":"Pescara",
    "wof:name":"F.a.t.i. Snc Dei Fratelli G. Carrer",
    "wof:placetype":"venue"
},
  "geometry": {"coordinates":[14.231136322,42.4418792725],"type":"Point"}
}