{
  "type": "Feature",
  "properties": {
    "iso:country":"IT",
    "sg:address":"22020 Pellio Intelvi",
    "sg:city":"Pellio",
    "sg:orig_category":"Studi E Consulenze Tecniche E Industriali. Consulenze Tecniche, Amministrative E Perizie. Professionisti - Studi E Servizi Ed Associazioni Di Interesse Aziendale",
    "sg:phone":"+39 031 832045",
    "sg:postcode":"22020",
    "sg:province":"Como",
    "wof:name":"Petrungaro Giovanni",
    "wof:placetype":"venue"
},
  "geometry": {"coordinates":[9.064402,45.977112],"type":"Point"}
}