{
  "type": "Feature",
  "properties": {
    "iso:country":"IT",
    "sg:address":"26/e, Via Limitese 50059 Vinci",
    "sg:city":"Vinci",
    "sg:classifiers":[
        {
            "category":"Shopping",
            "subcategory":"Clothing, Apparel, & Fashions",
            "type":"Retail Goods"
        }
    ],
    "sg:phone":"+39 0571 508068",
    "sg:postcode":"50059",
    "sg:province":"Firenze",
    "sg:tags":[
        "clothes"
    ],
    "wof:name":"Confezioni Stefil Nouvelle S.r.l.",
    "wof:placetype":"venue"
},
  "geometry": {"coordinates":[10.956163,43.73341],"type":"Point"}
}