{
  "type": "Feature",
  "properties": {
    "iso:country":"IT",
    "sg:address":"42019 Scandiano",
    "sg:orig_category":"Metalli E Leghe",
    "sg:phone":"+39 0522 857949",
    "sg:postcode":"42019",
    "sg:province":"Reggio Nell'Emilia",
    "wof:name":"Feredil Snc Di Lucenti E Rinaldi",
    "wof:placetype":"venue"
},
  "geometry": {"coordinates":[10.6737384796,44.6204452515],"type":"Point"}
}