{
  "type": "Feature",
  "properties": {
    "addr:full":"04012 Cisterna Di Latina Cisterna di Latina Latina 04012",
    "addr:postcode":"04012;04012",
    "iso:country":"IT",
    "sg:address":"04012 Cisterna Di Latina",
    "sg:city":"Cisterna di Latina",
    "sg:orig_category":"Prodotti E Manufatti In Materie Plastiche",
    "sg:phone":"+39 06 9687 2022",
    "sg:postcode":"04012",
    "sg:province":"Latina",
    "wof:name":"Sistemi Lavorazione Compositi Avanzati Srl",
    "wof:placetype":"venue"
},
  "geometry": {"coordinates":[12.8321113586,41.5818519592],"type":"Point"}
}