{
  "type": "Feature",
  "properties": {
    "iso:country":"IT",
    "sg:address":"81039 Villa Literno",
    "sg:city":"Villa Literno",
    "sg:orig_category":"Zootecnia E Pesca, Allevamento Piccoli Animali",
    "sg:phone":"+39 081 892 8170",
    "sg:postcode":"81039",
    "sg:province":"Caserta",
    "wof:name":"E.co.m. Soc.coop.a R.l.",
    "wof:placetype":"venue"
},
  "geometry": {"coordinates":[14.042065,40.987846],"type":"Point"}
}