{
  "type": "Feature",
  "properties": {
    "addr:full":"58019 Porto Ercole Grosseto 58019",
    "addr:housenumber":"58019",
    "addr:postcode":"58019",
    "iso:country":"IT",
    "sg:address":"58019 Porto Ercole",
    "sg:orig_category":"Servizi Ausiliari Per Il Trasporto. Agenzie D'affari E Servizi Commerciali",
    "sg:phone":"+39 0564 834285",
    "sg:postcode":"58019",
    "sg:province":"Grosseto",
    "wof:name":"Media Ship Srl",
    "wof:placetype":"venue"
},
  "geometry": {"coordinates":[11.203592,42.395069],"type":"Point"}
}