{
  "type": "Feature",
  "properties": {
    "iso:country":"IT",
    "sg:address":"35010 Sant'eufemia",
    "sg:orig_category":"Articoli Pulizia",
    "sg:phone":"+39 049 579 8444",
    "sg:postcode":"35010",
    "sg:province":"Padova",
    "wof:name":"Cagnin Giovanni",
    "wof:placetype":"venue"
},
  "geometry": {"coordinates":[11.985252,45.535591],"type":"Point"}
}