{
  "type": "Feature",
  "properties": {
    "iso:country":"IT",
    "sg:address":"41100 Modena",
    "sg:city":"Modena",
    "sg:orig_category":"Valvole E Apparecchiature Di Misura. Attrezzature E Forniture Per Officine Riparazione E Servizi Ausiliari. Macchine, Strumenti Ed Apparecchi Per Attivita' Industriali",
    "sg:phone":"+39 059 252096",
    "sg:postcode":"41100",
    "sg:province":"Modena",
    "wof:name":"Tecnotest (s.n.c.)",
    "wof:placetype":"venue"
},
  "geometry": {"coordinates":[10.962927,44.651272],"type":"Point"}
}