{
  "type": "Feature",
  "properties": {
    "iso:country":"IT",
    "sg:address":"10147 Torino",
    "sg:city":"Torino",
    "sg:orig_category":"Vetro: Prodotti E Lavorazioni",
    "sg:phone":"+39 011 221 7630",
    "sg:postcode":"10147",
    "sg:province":"Torino",
    "wof:name":"Elvezia Snc",
    "wof:placetype":"venue"
},
  "geometry": {"coordinates":[7.68099,45.097202],"type":"Point"}
}