{
  "type": "Feature",
  "properties": {
    "iso:country":"IT",
    "sg:address":"00016 Monterotondo",
    "sg:orig_category":"Apparecchiature E Sistemi Per Magazzinaggio E Movimentazione",
    "sg:phone":"+39 06 9008 0103",
    "sg:province":"RM",
    "wof:name":"Demma Sandro",
    "wof:placetype":"venue"
},
  "geometry": {"coordinates":[12.483,41.900002],"type":"Point"}
}