{
  "type": "Feature",
  "properties": {
    "iso:country":"IT",
    "sg:address":"20132 Milano",
    "sg:city":"Milano",
    "sg:orig_category":"Forniture Per Congressi, Fiere E Manifestazioni",
    "sg:phone":"+39 02 2611 6445",
    "sg:postcode":"20132",
    "sg:province":"Milano",
    "wof:name":"Microsistemi Sas Di Di Gennaro Gaetano & C.",
    "wof:placetype":"venue"
},
  "geometry": {"coordinates":[9.2375125885,45.5002861023],"type":"Point"}
}