{
  "type": "Feature",
  "properties": {
    "addr:full":"Via Asiago, 36 - San Zeno 36022 Cassola Cassola Vicenza 36022",
    "addr:housenumber":"36",
    "addr:postcode":"36022;36022",
    "addr:street":"Via Asiago",
    "iso:country":"IT",
    "sg:address":"Via Asiago, 36 - San Zeno 36022 Cassola",
    "sg:city":"Cassola",
    "sg:classifiers":[
        {
            "category":"Manufacturing",
            "subcategory":"Tools & Machinery",
            "type":"Manufacturing & Wholesale Goods"
        }
    ],
    "sg:phone":"+39 0424 570424",
    "sg:postcode":"36022",
    "sg:province":"Vicenza",
    "sg:tags":[
        "machine"
    ],
    "sg:website":"www.tgmacchineutensili.it",
    "wof:name":"Trento Giuseppe & Figli Snc",
    "wof:placetype":"venue"
},
  "geometry": {"coordinates":[11.540307,45.545906],"type":"Point"}
}