{
  "type": "Feature",
  "properties": {
    "addr:full":"20, Via Carmelitani Scalzi 37122 Verona Verona Verona 37122",
    "addr:postcode":"37122;37122",
    "addr:street":"Via Carmelitani Scalzi",
    "iso:country":"IT",
    "sg:address":"20, Via Carmelitani Scalzi 37122 Verona",
    "sg:city":"Verona",
    "sg:classifiers":[
        {
            "category":"Professional",
            "subcategory":"Computer Services",
            "type":"Services"
        }
    ],
    "sg:phone":"+39 39045597098",
    "sg:postcode":"37122",
    "sg:province":"Verona",
    "sg:tags":[
        "information",
        "technology"
    ],
    "wof:name":"Inforpragma (s.r.l.)",
    "wof:placetype":"venue"
},
  "geometry": {"coordinates":[10.9845,45.436741],"type":"Point"}
}