{
  "type": "Feature",
  "properties": {
    "iso:country":"IT",
    "sg:address":"6, Via Di Vittorio 41011 Campogalliano",
    "sg:city":"Campogalliano",
    "sg:classifiers":[
        {
            "category":"Shopping",
            "subcategory":"Clothing, Apparel, & Fashions",
            "type":"Retail Goods"
        }
    ],
    "sg:phone":"+39 39059851122",
    "sg:postcode":"41011",
    "sg:province":"Modena",
    "sg:tags":[
        "clothes"
    ],
    "wof:name":"Spruzzi Srl",
    "wof:placetype":"venue"
},
  "geometry": {"coordinates":[10.841426,44.692638],"type":"Point"}
}