{
  "type": "Feature",
  "properties": {
    "addr:full":"53100 Siena Siena Siena 53100",
    "addr:postcode":"53100;53100",
    "iso:country":"IT",
    "sg:address":"53100 Siena",
    "sg:city":"Siena",
    "sg:orig_category":"Forniture E Prodotti Informatici. Forniture Per Uffici",
    "sg:phone":"+39 0577 593856",
    "sg:postcode":"53100",
    "sg:province":"Siena",
    "wof:name":"Eco Office Di Castelli Francesca",
    "wof:placetype":"venue"
},
  "geometry": {"coordinates":[11.3008899689,43.3323936462],"type":"Point"}
}