{
  "type": "Feature",
  "properties": {
    "addr:full":"26100 Cremona Cremona Cremona 26100",
    "addr:postcode":"26100;26100",
    "iso:country":"IT",
    "sg:address":"26100 Cremona",
    "sg:city":"Cremona",
    "sg:orig_category":"Biancheria Intima Ed Abbigliamento Intimo - Vendita Al Dettaglio",
    "sg:phone":"+39 0372 410584",
    "sg:postcode":"26100",
    "sg:province":"Cremona",
    "wof:name":"Le Tentazioni Di Mascetti Marina",
    "wof:placetype":"venue"
},
  "geometry": {"coordinates":[10.03255,45.140419],"type":"Point"}
}