{
  "type": "Feature",
  "properties": {
    "addr:full":"22070 Guanzate Guanzate Como 22070",
    "addr:postcode":"22070;22070",
    "iso:country":"IT",
    "sg:address":"22070 Guanzate",
    "sg:city":"Guanzate",
    "sg:orig_category":"Elettrotecnica Industriale, Prodotti E Apparecchiature. Elettronica Industriale, Prodotti E Apparecchiature",
    "sg:phone":"+39 031 977155",
    "sg:postcode":"22070",
    "sg:province":"Como",
    "wof:name":"Vs. Tecnologie (s.n.c.)",
    "wof:placetype":"venue"
},
  "geometry": {"coordinates":[9.036554,45.761894],"type":"Point"}
}