{
  "type": "Feature",
  "properties": {
    "addr:full":"16154 Genova Genova Genova 16154",
    "addr:postcode":"16154;16154",
    "iso:country":"IT",
    "sg:address":"16154 Genova",
    "sg:city":"Genova",
    "sg:orig_category":"Scuole E Servizi Scolastici. Ricerca, Selezione E Formazione Del Personale",
    "sg:phone":"+39 010 651 4445",
    "sg:postcode":"16154",
    "sg:province":"Genova",
    "wof:name":"Istituto Palazzi Rossi",
    "wof:placetype":"venue"
},
  "geometry": {"coordinates":[8.848056,44.422501],"type":"Point"}
}