{
  "type": "Feature",
  "properties": {
    "iso:country":"IT",
    "sg:address":"50132 Firenze",
    "sg:city":"Firenze",
    "sg:orig_category":"Gioielleria, Oreficeria E Argenteria. Shopping",
    "sg:phone":"+39 055 583784",
    "sg:postcode":"50132",
    "sg:province":"Firenze",
    "wof:name":"Pierfa Di Fagioli Piero",
    "wof:placetype":"venue"
},
  "geometry": {"coordinates":[11.270802,43.779083],"type":"Point"}
}