{
  "type": "Feature",
  "properties": {
    "iso:country":"IT",
    "sg:address":"Via Pavia 100 21056 Induno Olona",
    "sg:city":"Induno Olona",
    "sg:classifiers":[
        {
            "category":"Communications",
            "subcategory":"Film & Video Production",
            "type":"Services"
        }
    ],
    "sg:phone":"+39 0332 202729",
    "sg:postcode":"21056",
    "sg:province":"Varese",
    "sg:tags":[
        "print",
        "demand"
    ],
    "wof:name":"Litografia Valli Snc",
    "wof:placetype":"venue"
},
  "geometry": {"coordinates":[8.836227417,45.8407287598],"type":"Point"}
}