{
  "type": "Feature",
  "properties": {
    "iso:country":"IT",
    "sg:address":"20052 Monza",
    "sg:city":"Monza",
    "sg:orig_category":"Servizi Per Lo Sport E Il Tempo Libero. Ristoranti Ed Esercizi Affini. Servizi Ausiliari Di Ristorazione E Di Intrattenimento",
    "sg:phone":"+39 039 232 1030",
    "sg:postcode":"20052",
    "sg:province":"Milano",
    "sg:website":"http://www.savageclub.it",
    "wof:name":"Savage Dinner Dance Club - Jungle Srl",
    "wof:placetype":"venue"
},
  "geometry": {"coordinates":[9.292102,45.575363],"type":"Point"}
}