{
  "type": "Feature",
  "properties": {
    "iso:country":"IT",
    "sg:address":"50013 Campi Bisenzio",
    "sg:city":"Campi Bisenzio",
    "sg:orig_category":"Forniture Per Abbigliamento E Pelletterie",
    "sg:phone":"+39 055 894 9010",
    "sg:postcode":"50013",
    "sg:province":"Firenze",
    "wof:name":"Fratelli Reali E C S P A",
    "wof:placetype":"venue"
},
  "geometry": {"coordinates":[11.138551712,43.7925338745],"type":"Point"}
}