{
  "type": "Feature",
  "properties": {
    "addr:full":"20038 Seregno Seregno Milano 20038",
    "addr:postcode":"20038;20038",
    "iso:country":"IT",
    "sg:address":"20038 Seregno",
    "sg:city":"Seregno",
    "sg:orig_category":"Impiantistica E Prodotti Tecnologici Per Edilizia. Elettrotecnica Industriale, Prodotti E Apparecchiature. Elettrotecnica Professionale E Di Consumo",
    "sg:phone":"+39 036 224 1164",
    "sg:postcode":"20038",
    "sg:province":"Milano",
    "sg:website":"http://www.euro-elettrica.it",
    "wof:name":"Euro Elettrica Sas",
    "wof:placetype":"venue"
},
  "geometry": {"coordinates":[9.181025,45.503437],"type":"Point"}
}