{
  "type": "Feature",
  "properties": {
    "addr:full":"00199 Roma Roma Roma 00199",
    "addr:postcode":"00199;00199",
    "iso:country":"IT",
    "sg:address":"00199 Roma",
    "sg:city":"Roma",
    "sg:classifiers":[
        {
            "category":"Health Services",
            "subcategory":"Health Practitioner",
            "type":"Services"
        }
    ],
    "sg:phone":"+39 06 884 0698",
    "sg:postcode":"00199",
    "sg:province":"Roma",
    "sg:tags":[
        "medici"
    ],
    "wof:name":"Celestino Domenico",
    "wof:placetype":"venue"
},
  "geometry": {"coordinates":[12.504086,41.923508],"type":"Point"}
}