{
  "type": "Feature",
  "properties": {
    "iso:country":"IT",
    "sg:address":"20123 Milano",
    "sg:city":"Milano",
    "sg:orig_category":"Non-classified Establishments",
    "sg:phone":"+39 02 8645 0667",
    "sg:postcode":"20123",
    "sg:province":"Milano",
    "wof:name":"Valigeria Vetra S.a.s. Di Marchino Roberto E C.",
    "wof:placetype":"venue"
},
  "geometry": {"coordinates":[9.185936,45.462093],"type":"Point"}
}