{
  "type": "Feature",
  "properties": {
    "iso:country":"IT",
    "sg:address":"30124 Venezia",
    "sg:city":"Venezia",
    "sg:classifiers":[
        {
            "category":"Government",
            "subcategory":"Office",
            "type":"Public Place"
        }
    ],
    "sg:phone":"+39 041 277 0561",
    "sg:postcode":"30124",
    "sg:province":"Venezia",
    "sg:tags":[
        "e",
        "lo",
        "tempo",
        "libero",
        "per",
        "spettacolo",
        "servizi",
        "culturali",
        "sport",
        "il"
    ],
    "wof:name":"Interpreti Veneziani Associazione",
    "wof:placetype":"venue"
},
  "geometry": {"coordinates":[12.334462,45.432533],"type":"Point"}
}