{
  "type": "Feature",
  "properties": {
    "iso:country":"IT",
    "sg:address":"11, Via Galatea 00155 Roma",
    "sg:city":"Roma",
    "sg:classifiers":[
        {
            "category":"Autos & Motor Vehicles",
            "subcategory":"Automobile Sales",
            "type":"Retail Goods"
        }
    ],
    "sg:phone":"+39 39062292533",
    "sg:postcode":"00155",
    "sg:province":"Roma",
    "sg:tags":[
        "equipment",
        "transport"
    ],
    "wof:name":"Veicoli Industriali Mattoni (s.r.l.)",
    "wof:placetype":"venue"
},
  "geometry": {"coordinates":[12.611341,41.912544],"type":"Point"}
}