{
  "type": "Feature",
  "properties": {
    "iso:country":"IT",
    "sg:address":"90011 Bagheria",
    "sg:city":"Bagheria",
    "sg:orig_category":"Gelaterie",
    "sg:phone":"+39 091 961151",
    "sg:postcode":"90011",
    "sg:province":"Palermo",
    "wof:name":"Gelato In Di Eucaliptus",
    "wof:placetype":"venue"
},
  "geometry": {"coordinates":[13.504707,38.080154],"type":"Point"}
}