{
  "type": "Feature",
  "properties": {
    "iso:country":"IT",
    "sg:address":"70121 Bari",
    "sg:city":"Bari",
    "sg:orig_category":"Argenterie - Vendita Al Dettaglio",
    "sg:phone":"+39 080 524 1636",
    "sg:postcode":"70121",
    "sg:province":"Bari",
    "sg:website":"http://www.mossa.com",
    "wof:name":"Mossa Gioiellieri Srl",
    "wof:placetype":"venue"
},
  "geometry": {"coordinates":[16.869526,41.123901],"type":"Point"}
}