{
  "type": "Feature",
  "properties": {
    "iso:country":"IT",
    "sg:address":"20090 Pieve Emanuele",
    "sg:city":"Pieve Emanuele",
    "sg:classifiers":[
        {
            "category":"Manufacturing",
            "subcategory":"Glass & Minerals",
            "type":"Manufacturing & Wholesale Goods"
        }
    ],
    "sg:phone":"+39 02 9072 3073",
    "sg:postcode":"20090",
    "sg:province":"Milano",
    "sg:tags":[
        "decorative",
        "product",
        "art",
        "furnishings",
        "craft",
        "processing",
        "objects",
        "artistic"
    ],
    "wof:name":"Ardea Srl",
    "wof:placetype":"venue"
},
  "geometry": {"coordinates":[9.1749792099,45.3742485046],"type":"Point"}
}