{
  "type": "Feature",
  "properties": {
    "addr:full":"00141 Roma Roma Roma 00141",
    "addr:postcode":"00141;00141",
    "iso:country":"IT",
    "sg:address":"00141 Roma",
    "sg:city":"Roma",
    "sg:orig_category":"Forniture Per Edilizia E Lavori Pubblici",
    "sg:phone":"+39 06 721 9353",
    "sg:postcode":"00141",
    "sg:province":"Roma",
    "sg:website":"http://www.coopcie.it",
    "wof:name":"C.i.e. Cooperativa Italiana Ecologia Srl",
    "wof:placetype":"venue"
},
  "geometry": {"coordinates":[12.5195503235,41.9435081482],"type":"Point"}
}