{
  "type": "Feature",
  "properties": {
    "addr:full":"25030 Castel Mella Castel Mella Brescia 25030",
    "addr:postcode":"25030;25030",
    "iso:country":"IT",
    "sg:address":"25030 Castel Mella",
    "sg:city":"Castel Mella",
    "sg:orig_category":"Servizi E Lavori Per Abbigliamento E Pelletterie",
    "sg:phone":"+39 030 258 7170",
    "sg:postcode":"25030",
    "sg:province":"Brescia",
    "wof:name":"Stireria Ines Di Corani Roberto",
    "wof:placetype":"venue"
},
  "geometry": {"coordinates":[10.146651,45.506989],"type":"Point"}
}