{
  "type": "Feature",
  "properties": {
    "iso:country":"IT",
    "sg:address":"61015 Novafeltria",
    "sg:city":"Novafeltria",
    "sg:orig_category":"Macchine Ed Impianti Per Edilizia E Lavori Pubblici",
    "sg:phone":"+39 0541 921882",
    "sg:postcode":"61015",
    "sg:province":"Pesaro E Urbino",
    "wof:name":"Bilancioni Gianfranco",
    "wof:placetype":"venue"
},
  "geometry": {"coordinates":[12.28508,43.897957],"type":"Point"}
}