{
  "type": "Feature",
  "properties": {
    "addr:full":"07026 Olbia Olbia Olbia-Tempio 07026",
    "addr:postcode":"07026;07026",
    "iso:country":"IT",
    "sg:address":"07026 Olbia",
    "sg:city":"Olbia",
    "sg:classifiers":[
        {
            "category":"Banks & Credit Unions",
            "subcategory":"Bureau De Change",
            "type":"Services"
        }
    ],
    "sg:phone":"+39 0789 33512",
    "sg:postcode":"07026",
    "sg:province":"Olbia-Tempio",
    "sg:tags":[
        "auxiliary",
        "vehicles",
        "leisure",
        "services",
        "motor",
        "boats",
        "sport",
        "tourism"
    ],
    "wof:name":"Nautica Portisco",
    "wof:placetype":"venue"
},
  "geometry": {"coordinates":[9.521259,41.041409],"type":"Point"}
}