{
  "type": "Feature",
  "properties": {
    "iso:country":"IT",
    "sg:address":"34170 Gorizia",
    "sg:city":"Gorizia",
    "sg:classifiers":[
        {
            "category":"Parking",
            "subcategory":"Lot",
            "type":"Transportation"
        }
    ],
    "sg:phone":"+39 0481 527111",
    "sg:postcode":"34170",
    "sg:province":"Gorizia",
    "sg:tags":[
        "good",
        "shipment",
        "transport"
    ],
    "sg:website":"http://www.paginegialle.it/lagoriziana",
    "wof:name":"La Goriziana Srl",
    "wof:placetype":"venue"
},
  "geometry": {"coordinates":[13.599144,45.943825],"type":"Point"}
}