{
  "type": "Feature",
  "properties": {
    "iso:country":"IT",
    "sg:address":"22100 Como",
    "sg:city":"Como",
    "sg:orig_category":"Impiantistica E Prodotti Tecnologici Per Edilizia. Elettronica Professionale E Di Consumo",
    "sg:phone":"+39 031 555485",
    "sg:postcode":"22100",
    "sg:province":"Como",
    "wof:name":"D.m.g. Elettrica Snc",
    "wof:placetype":"venue"
},
  "geometry": {"coordinates":[9.086944,45.809727],"type":"Point"}
}