{
  "type": "Feature",
  "properties": {
    "addr:full":"7, Via Nuvolari Tazio 55012 Capannori Capannori Lucca 55012",
    "addr:postcode":"55012;55012",
    "addr:street":"Via Nuvolari Tazio",
    "iso:country":"IT",
    "sg:address":"7, Via Nuvolari Tazio 55012 Capannori",
    "sg:city":"Capannori",
    "sg:classifiers":[
        {
            "category":"Shopping",
            "subcategory":"Clothing, Apparel, & Fashions",
            "type":"Retail Goods"
        }
    ],
    "sg:phone":"+39 0583 981414",
    "sg:postcode":"55012",
    "sg:province":"Lucca",
    "sg:tags":[
        "clothing",
        "accessory"
    ],
    "wof:name":"Ele Srl",
    "wof:placetype":"venue"
},
  "geometry": {"coordinates":[10.565001,43.823597],"type":"Point"}
}