{
  "type": "Feature",
  "properties": {
    "iso:country":"IT",
    "sg:address":"10078 Venaria",
    "sg:orig_category":"Macchine Ed Impianti Per Edilizia E Lavori Pubblici",
    "sg:phone":"+39 011 455 0732",
    "sg:postcode":"10078",
    "sg:province":"Torino",
    "wof:name":"Sclaverano Giuseppe S.r.l.",
    "wof:placetype":"venue"
},
  "geometry": {"coordinates":[7.6453,45.119133],"type":"Point"}
}