{
  "type": "Feature",
  "properties": {
    "iso:country":"IT",
    "sg:address":"12045 Fossano",
    "sg:city":"Fossano",
    "sg:orig_category":"Macchine Ed Impianti Per Edilizia E Lavori Pubblici. Forniture Per Edilizia E Lavori Pubblici",
    "sg:phone":"+39 0172 637296",
    "sg:postcode":"12045",
    "sg:province":"Cuneo",
    "wof:name":"Noledile Srl",
    "wof:placetype":"venue"
},
  "geometry": {"coordinates":[7.712029,44.53455],"type":"Point"}
}