{
  "type": "Feature",
  "properties": {
    "iso:country":"IT",
    "sg:address":"37136 Verona",
    "sg:city":"Verona",
    "sg:orig_category":"Impiantistica E Prodotti Tecnologici Per Edilizia. Telecomunicazioni E Telefonia, Impianti, Apparecchi E Servizi",
    "sg:phone":"+39 045 509511",
    "sg:postcode":"37136",
    "sg:province":"Verona",
    "sg:website":"http://www.sitelco.it",
    "wof:name":"Eximag Art Sistemi Srl",
    "wof:placetype":"venue"
},
  "geometry": {"coordinates":[10.965693,45.410999],"type":"Point"}
}