{
  "type": "Feature",
  "properties": {
    "addr:full":"24021 Albino Albino Bergamo 24021",
    "addr:postcode":"24021;24021",
    "iso:country":"IT",
    "sg:address":"24021 Albino",
    "sg:city":"Albino",
    "sg:orig_category":"Forniture Per Uffici. Arredi Ed Attrezzature Per Uffici. Automazione E Macchine Per Ufficio",
    "sg:phone":"+39 035 753145",
    "sg:postcode":"24021",
    "sg:province":"Bergamo",
    "wof:name":"Messi Luciano - Libreria Amministrativa",
    "wof:placetype":"venue"
},
  "geometry": {"coordinates":[9.7351531982,45.7379150391],"type":"Point"}
}