{
  "type": "Feature",
  "properties": {
    "iso:country":"IT",
    "sg:address":"50125 Firenze",
    "sg:city":"Firenze",
    "sg:orig_category":"Scuole E Servizi Scolastici. Servizi Per Lo Sport E Il Tempo Libero",
    "sg:phone":"+39 055 234 2870",
    "sg:postcode":"50125",
    "sg:province":"Firenze",
    "wof:name":"Lega Navale Italiana",
    "wof:placetype":"venue"
},
  "geometry": {"coordinates":[11.257592,43.764904],"type":"Point"}
}