{
  "type": "Feature",
  "properties": {
    "addr:full":"31040 Segusino Segusino Treviso 31040",
    "addr:postcode":"31040;31040",
    "iso:country":"IT",
    "sg:address":"31040 Segusino",
    "sg:city":"Segusino",
    "sg:orig_category":"Occhiali - Produzione E Ingrosso",
    "sg:phone":"+39 0423 979933",
    "sg:postcode":"31040",
    "sg:province":"Treviso",
    "wof:name":"Ciesse Di Coppe Evi E Stramare Rosanna Snc",
    "wof:placetype":"venue"
},
  "geometry": {"coordinates":[11.95674,45.91798],"type":"Point"}
}