{
  "type": "Feature",
  "properties": {
    "addr:full":"Via Sottorive 25 33050 Pozzuolo Del Friuli Pozzuolo del Friuli Udine 33050",
    "addr:housenumber":"25",
    "addr:postcode":"33050;33050",
    "addr:street":"Via Sottorive;Del Friuli",
    "iso:country":"IT",
    "sg:address":"Via Sottorive 25 33050 Pozzuolo Del Friuli",
    "sg:city":"Pozzuolo del Friuli",
    "sg:classifiers":[
        {
            "category":"Wholesale",
            "subcategory":"Office Equipment",
            "type":"Manufacturing & Wholesale Goods"
        }
    ],
    "sg:phone":"+39 0432 746338",
    "sg:postcode":"33050",
    "sg:province":"Udine",
    "sg:tags":[
        "chair",
        "seats"
    ],
    "sg:website":"www.prismasrl.it",
    "wof:name":"Prisma S.r.l.",
    "wof:placetype":"venue"
},
  "geometry": {"coordinates":[13.230724,46.064941],"type":"Point"}
}