{
  "type": "Feature",
  "properties": {
    "addr:full":"40069 Zola Predosa Zola Bologna 40069",
    "addr:postcode":"40069;40069",
    "iso:country":"IT",
    "sg:address":"40069 Zola Predosa",
    "sg:city":"Zola",
    "sg:orig_category":"Prodotti E Manufatti In Materie Plastiche",
    "sg:phone":"+39 051 758685",
    "sg:postcode":"40069",
    "sg:province":"Bologna",
    "wof:name":"Penta Resine (s.r.l.)",
    "wof:placetype":"venue"
},
  "geometry": {"coordinates":[11.2544898987,44.4941825867],"type":"Point"}
}