{
  "type": "Feature",
  "properties": {
    "addr:full":"20052 Monza Monza Milano 20052",
    "addr:postcode":"20052;20052",
    "iso:country":"IT",
    "sg:address":"20052 Monza",
    "sg:city":"Monza",
    "sg:orig_category":"Biancheria Intima Ed Abbigliamento Intimo - Vendita Al Dettaglio",
    "sg:phone":"+39 039 200 1025",
    "sg:postcode":"20052",
    "sg:province":"Milano",
    "wof:name":"Albatros Di Anfuso Alba",
    "wof:placetype":"venue"
},
  "geometry": {"coordinates":[9.199922,45.462212],"type":"Point"}
}