{
  "type": "Feature",
  "properties": {
    "addr:full":"11, Via Caduti Sul Lavoro 28883 Gravellona Toce Gravellona Toce Verbano-Cusio-Ossola 28883",
    "addr:postcode":"28883;28883",
    "addr:street":"Via Caduti Sul Lavoro",
    "iso:country":"IT",
    "sg:address":"11, Via Caduti Sul Lavoro 28883 Gravellona Toce",
    "sg:city":"Gravellona Toce",
    "sg:classifiers":[
        {
            "category":"Food & Beverages",
            "subcategory":"Groceries & Convenience Stores",
            "type":"Retail Goods"
        }
    ],
    "sg:phone":"+39 0323 846051",
    "sg:postcode":"28883",
    "sg:province":"Verbano-Cusio-Ossola",
    "sg:tags":[
        "product",
        "related"
    ],
    "wof:name":"Global Pesca S.p.a.",
    "wof:placetype":"venue"
},
  "geometry": {"coordinates":[8.4483709335,45.9321136475],"type":"Point"}
}