{
  "type": "Feature",
  "properties": {
    "addr:full":"19037 Santo Stefano Magra La Spezia 19037",
    "addr:postcode":"19037;19037",
    "addr:street":"Santo Stefano Magra",
    "iso:country":"IT",
    "sg:address":"19037 Santo Stefano Magra",
    "sg:orig_category":"Prodotti E Manufatti In Gomma. Servizi E Lavori Industria Della Gomma. Ricambi E Componenti Dei Mezzi Di Trasporto",
    "sg:phone":"+39 0187 630210",
    "sg:postcode":"19037",
    "sg:province":"La Spezia",
    "wof:name":"Zancolli Spa",
    "wof:placetype":"venue"
},
  "geometry": {"coordinates":[9.9297447205,44.1508560181],"type":"Point"}
}