{
  "type": "Feature",
  "properties": {
    "iso:country":"IT",
    "sg:address":"Ctr. Carrozza 88064 Chiaravalle Centrale",
    "sg:city":"Chiaravalle Centrale",
    "sg:classifiers":[
        {
            "category":"Manufacturing",
            "subcategory":"Lumber",
            "type":"Manufacturing & Wholesale Goods"
        }
    ],
    "sg:phone":"+39 0967 998200",
    "sg:postcode":"88064",
    "sg:province":"Catanzaro",
    "sg:tags":[
        "wood"
    ],
    "sg:website":"http://www.paginegialle.it/fabianolegnami",
    "wof:name":"Fabiano Legnami Srl",
    "wof:placetype":"venue"
},
  "geometry": {"coordinates":[16.587679,38.910599],"type":"Point"}
}