{
  "type": "Feature",
  "properties": {
    "iso:country":"IT",
    "sg:address":"25049 Iseo",
    "sg:city":"Iseo",
    "sg:orig_category":"Utensili Meccanici E Materiali",
    "sg:phone":"+39 030 982 1076",
    "sg:postcode":"25049",
    "sg:province":"Brescia",
    "wof:name":"Barbieri Silvana",
    "wof:placetype":"venue"
},
  "geometry": {"coordinates":[10.054017,45.661579],"type":"Point"}
}