{
  "type": "Feature",
  "properties": {
    "addr:full":"84080 Pellezzano Coperchia Salerno 84080",
    "addr:postcode":"84080;84080",
    "iso:country":"IT",
    "sg:address":"84080 Pellezzano",
    "sg:city":"Coperchia",
    "sg:orig_category":"Servizi Per Lo Sport E Il Tempo Libero. Servizi Al Turismo",
    "sg:phone":"+39 089 568001",
    "sg:postcode":"84080",
    "sg:province":"Salerno",
    "wof:name":"Associazione Gymnica",
    "wof:placetype":"venue"
},
  "geometry": {"coordinates":[14.767759,40.71944],"type":"Point"}
}