{
  "type": "Feature",
  "properties": {
    "iso:country":"IT",
    "sg:address":"90121 Palermo",
    "sg:city":"Palermo",
    "sg:orig_category":"Agricoltura, Orticoltura E Floricoltura",
    "sg:phone":"+39 091 472301",
    "sg:postcode":"90121",
    "sg:province":"Palermo",
    "wof:name":"Messina Salvatore",
    "wof:placetype":"venue"
},
  "geometry": {"coordinates":[13.414913,38.097706],"type":"Point"}
}