{
  "type": "Feature",
  "properties": {
    "iso:country":"IT",
    "sg:address":"1, Via Duca Degli Abruzzi 37069 Villafranca Di Verona",
    "sg:city":"Villafranca di Verona",
    "sg:classifiers":[
        {
            "category":"Manufacturing",
            "subcategory":"Rubber & Plastics",
            "type":"Manufacturing & Wholesale Goods"
        }
    ],
    "sg:phone":"+39 045 633 6521",
    "sg:postcode":"37069",
    "sg:province":"Verona",
    "wof:name":"Ilga (s.p.a.)",
    "wof:placetype":"venue"
},
  "geometry": {"coordinates":[10.832259,45.325058],"type":"Point"}
}