{
  "type": "Feature",
  "properties": {
    "iso:country":"IT",
    "sg:address":"119, Via Roma 64028 Silvi",
    "sg:city":"Silvi",
    "sg:classifiers":[
        {
            "category":"Personal",
            "subcategory":"Shoe Repair & Shine",
            "type":"Services"
        }
    ],
    "sg:phone":"+39 085 935 4061",
    "sg:postcode":"64028",
    "sg:province":"Teramo",
    "sg:tags":[
        "leather"
    ],
    "wof:name":"Creazioni Marzia Srl",
    "wof:placetype":"venue"
},
  "geometry": {"coordinates":[14.107004,42.561691],"type":"Point"}
}