{
  "type": "Feature",
  "properties": {
    "iso:country":"IT",
    "sg:address":"Loc Streppate Zi 86077 Pozzilli",
    "sg:city":"Pozzilli",
    "sg:classifiers":[
        {
            "category":"Manufacturing",
            "subcategory":"Metals",
            "type":"Manufacturing & Wholesale Goods"
        }
    ],
    "sg:phone":"+39 0865 9161",
    "sg:postcode":"86077",
    "sg:province":"Isernia",
    "sg:tags":[
        "cast",
        "unalloyed",
        "grey",
        "iron",
        "alloyed"
    ],
    "sg:website":"www.fondregisa.it",
    "wof:name":"Fonderghisa Spa",
    "wof:placetype":"venue"
},
  "geometry": {"coordinates":[14.230827,41.594334],"type":"Point"}
}