{
  "type": "Feature",
  "properties": {
    "iso:country":"IT",
    "sg:address":"00181 Roma",
    "sg:city":"Roma",
    "sg:orig_category":"Utensili Meccanici E Materiali. Elettrotecnica Industriale, Prodotti E Apparecchiature",
    "sg:phone":"+39 06 780 7205",
    "sg:postcode":"00181",
    "sg:province":"Roma",
    "wof:name":"Grazia Vittore",
    "wof:placetype":"venue"
},
  "geometry": {"coordinates":[12.530726,41.872593],"type":"Point"}
}