{
  "type": "Feature",
  "properties": {
    "iso:country":"IT",
    "sg:address":"06012 Citta'dicastello",
    "sg:orig_category":"Zootecnia E Pesca, Allevamento Piccoli Animali. Animali Domestici",
    "sg:phone":"+39 075 851781",
    "sg:postcode":"06012",
    "sg:province":"Perugia",
    "wof:name":"Con.ag.it Soc.coop.r.l.",
    "wof:placetype":"venue"
},
  "geometry": {"coordinates":[12.231905,43.457787],"type":"Point"}
}