{
  "type": "Feature",
  "properties": {
    "addr:full":"9, Via Case Nuove 13894 Gaglianico Gaglianico Biella 13894",
    "addr:postcode":"13894;13894",
    "addr:street":"Via Case Nuove",
    "iso:country":"IT",
    "sg:address":"9, Via Case Nuove 13894 Gaglianico",
    "sg:city":"Gaglianico",
    "sg:classifiers":[
        {
            "category":"Shopping",
            "subcategory":"Crafts & Fabrics",
            "type":"Retail Goods"
        }
    ],
    "sg:phone":"+39 39015541242",
    "sg:postcode":"13894",
    "sg:province":"Biella",
    "wof:name":"B.m.b. Lavorazione Filati S.a.s. Di Betassa Copet",
    "wof:placetype":"venue"
},
  "geometry": {"coordinates":[8.085146904,45.5381393433],"type":"Point"}
}