{
  "type": "Feature",
  "properties": {
    "iso:country":"IT",
    "sg:address":"00040 Ariccia",
    "sg:city":"Ariccia",
    "sg:orig_category":"Servizi E Lavori Per Agricoltura E Zootecnia. Animali Domestici",
    "sg:phone":"+39 06 933 3303",
    "sg:postcode":"00040",
    "sg:province":"Roma",
    "wof:name":"Basili Stefano Pippo & Company",
    "wof:placetype":"venue"
},
  "geometry": {"coordinates":[12.644164,41.743092],"type":"Point"}
}