{
  "type": "Feature",
  "properties": {
    "addr:full":"Corso Europa 16100 Genova GE",
    "addr:postcode":"16100",
    "addr:street":"Corso Europa",
    "iso:country":"IT",
    "sg:address":"Corso Europa 16100 Genova",
    "sg:classifiers":[
        {
            "category":"Professional",
            "subcategory":"Engineering",
            "type":"Services"
        }
    ],
    "sg:phone":"+39 390 103 4341",
    "sg:province":"GE",
    "sg:tags":[
        "machine",
        "-",
        "mechanical"
    ],
    "wof:name":"Siemens Orsi Automation Spa",
    "wof:placetype":"venue"
},
  "geometry": {"coordinates":[9.001346,44.394581],"type":"Point"}
}