{
  "type": "Feature",
  "properties": {
    "iso:country":"IT",
    "sg:address":"36, Via Lecco 24030 Mozzo",
    "sg:city":"Mozzo",
    "sg:classifiers":[
        {
            "category":"Professional",
            "subcategory":"Engineering",
            "type":"Services"
        }
    ],
    "sg:phone":"+39 39035614001",
    "sg:postcode":"24030",
    "sg:province":"Bergamo",
    "sg:tags":[
        "machine",
        "-",
        "mechanical"
    ],
    "wof:name":"Finazzi Automatismi Elettronici",
    "wof:placetype":"venue"
},
  "geometry": {"coordinates":[9.594754,45.698338],"type":"Point"}
}