{
  "type": "Feature",
  "properties": {
    "iso:country":"IT",
    "sg:address":"31040 Segusino",
    "sg:city":"Segusino",
    "sg:orig_category":"Lampadari - Produzione E Ingrosso",
    "sg:phone":"+39 0423 979521",
    "sg:postcode":"31040",
    "sg:province":"Treviso",
    "wof:name":"Ilas Srl",
    "wof:placetype":"venue"
},
  "geometry": {"coordinates":[12.225862,45.671669],"type":"Point"}
}