{
  "type": "Feature",
  "properties": {
    "addr:full":"20, Contrada Addolorata 62019 Recanati Recanati Macerata 62019",
    "addr:postcode":"62019;62019",
    "addr:street":"Contrada Addolorata",
    "iso:country":"IT",
    "sg:address":"20, Contrada Addolorata 62019 Recanati",
    "sg:city":"Recanati",
    "sg:classifiers":[
        {
            "category":"Shopping",
            "subcategory":"Jewelry",
            "type":"Retail Goods"
        }
    ],
    "sg:phone":"+39 071 757 4137",
    "sg:postcode":"62019",
    "sg:province":"Macerata",
    "sg:tags":[
        "jewellery"
    ],
    "wof:name":"Marcello Giorgio (s.r.l.)",
    "wof:placetype":"venue"
},
  "geometry": {"coordinates":[13.557313,43.426754],"type":"Point"}
}