{
  "type": "Feature",
  "properties": {
    "iso:country":"IT",
    "sg:address":"4328, Castello 30122 Venezia",
    "sg:city":"Castello",
    "sg:classifiers":[
        {
            "category":"Manufacturing",
            "subcategory":"Glass & Minerals",
            "type":"Manufacturing & Wholesale Goods"
        }
    ],
    "sg:phone":"+39 041 520 9422",
    "sg:postcode":"30122",
    "sg:province":"Venezia",
    "wof:name":"Laguna Murano Glass Srl",
    "wof:placetype":"venue"
},
  "geometry": {"coordinates":[12.340962,45.435192],"type":"Point"}
}