{
  "type": "Feature",
  "properties": {
    "addr:full":"11, Via Sardegna 25069 Villa Carcina Carcina Brescia 25069",
    "addr:postcode":"25069;carcina;25069",
    "addr:street":"Via Sardegna",
    "iso:country":"IT",
    "sg:address":"11, Via Sardegna 25069 Villa Carcina",
    "sg:city":"Carcina",
    "sg:classifiers":[
        {
            "category":"Shopping",
            "type":"Retail Goods"
        }
    ],
    "sg:phone":"+39 030 898 2314",
    "sg:postcode":"25069",
    "sg:province":"Brescia",
    "sg:tags":[
        "finished",
        "-",
        "metallic"
    ],
    "wof:name":"Elettrofiamma (s.r.l.)",
    "wof:placetype":"venue"
},
  "geometry": {"coordinates":[10.1963157654,45.6218299866],"type":"Point"}
}