{
  "type": "Feature",
  "properties": {
    "addr:full":"10070 Barbania Barbania Torino 10070",
    "addr:housenumber":"10070",
    "addr:postcode":"10070",
    "addr:street":"Barbania Barbania",
    "iso:country":"IT",
    "sg:address":"10070 Barbania",
    "sg:city":"Barbania",
    "sg:orig_category":"Servizi E Lavori Per Arredamento E Industria Del Legno. Servizi E Lavori Per Edilizia E Lavori Pubblici",
    "sg:phone":"+39 011 924 3256",
    "sg:postcode":"10070",
    "sg:province":"Torino",
    "wof:name":"Falqui Ignazio",
    "wof:placetype":"venue"
},
  "geometry": {"coordinates":[7.663112,45.07616],"type":"Point"}
}