{
  "type": "Feature",
  "properties": {
    "addr:full":"10128 Torino Torino Torino 10128",
    "addr:postcode":"10128;10128",
    "iso:country":"IT",
    "sg:address":"10128 Torino",
    "sg:city":"Torino",
    "sg:orig_category":"Ospedali E Servizi Sanitari",
    "sg:phone":"+39 011 561 6111",
    "sg:postcode":"10128",
    "sg:province":"Torino",
    "sg:website":"http://www.cidimu.it",
    "wof:name":"C.i.d.i.m.u.",
    "wof:placetype":"venue"
},
  "geometry": {"coordinates":[7.669951,45.060879],"type":"Point"}
}