{
  "type": "Feature",
  "properties": {
    "addr:full":"39031 Brunico Brunico Bolzano/Bozen 39031",
    "addr:postcode":"39031;39031",
    "iso:country":"IT",
    "sg:address":"39031 Brunico",
    "sg:city":"Brunico",
    "sg:orig_category":"Prodotti E Manufatti In Materie Plastiche. Servizi E Lavori Industria Delle Materie Plastiche",
    "sg:phone":"+39 0474 571700",
    "sg:postcode":"39031",
    "sg:province":"Bolzano/Bozen",
    "sg:website":"http://www.intercable.it",
    "wof:name":"Intercable Srl",
    "wof:placetype":"venue"
},
  "geometry": {"coordinates":[11.35800457,46.4967155457],"type":"Point"}
}