{
  "type": "Feature",
  "properties": {
    "iso:country":"IT",
    "sg:address":"Via De' Cattani 188/5 50145 Firenze",
    "sg:city":"Firenze",
    "sg:classifiers":[
        {
            "category":"Manufacturing",
            "subcategory":"Chemicals & Compounds",
            "type":"Manufacturing & Wholesale Goods"
        }
    ],
    "sg:phone":"+39 055 301170",
    "sg:postcode":"50145",
    "sg:province":"Firenze",
    "sg:tags":[
        "industrial"
    ],
    "wof:name":"Iris - S.r.l.",
    "wof:placetype":"venue"
},
  "geometry": {"coordinates":[11.17191,43.799484],"type":"Point"}
}