{
  "type": "Feature",
  "properties": {
    "addr:full":"00176 Roma Roma Roma 00176",
    "addr:postcode":"00176;00176",
    "iso:country":"IT",
    "sg:address":"00176 Roma",
    "sg:city":"Roma",
    "sg:orig_category":"Non-classified Establishments",
    "sg:phone":"+39 06 275 7205",
    "sg:postcode":"00176",
    "sg:province":"Roma",
    "wof:name":"Aloisy & C. (s.n.c.)",
    "wof:placetype":"venue"
},
  "geometry": {"coordinates":[12.537769,41.888683],"type":"Point"}
}