{
  "type": "Feature",
  "properties": {
    "addr:full":"122, Via Della Cupola 50145 Firenze Firenze Firenze 50145",
    "addr:housenumber":"122",
    "addr:postcode":"50145;50145",
    "addr:street":"Via Della Cupola",
    "iso:country":"IT",
    "sg:address":"122, Via Della Cupola 50145 Firenze",
    "sg:city":"Firenze",
    "sg:classifiers":[
        {
            "category":"Parking",
            "subcategory":"Lot",
            "type":"Transportation"
        }
    ],
    "sg:phone":"+39 39055311744",
    "sg:postcode":"50145",
    "sg:province":"Firenze",
    "sg:tags":[
        "transport",
        "road"
    ],
    "wof:name":"Cooperativa C.t.f. Trasporti Fiorentini (soc.coop.r.l.)",
    "wof:placetype":"venue"
},
  "geometry": {"coordinates":[11.195414,43.8022],"type":"Point"}
}