{
  "type": "Feature",
  "properties": {
    "iso:country":"IT",
    "sg:address":"80040 San Gennaro Vesuviano",
    "sg:city":"San Gennaro Vesuviano",
    "sg:orig_category":"Scuole E Servizi Scolastici. Servizi Per Lo Sport E Il Tempo Libero",
    "sg:phone":"+39 081 528 6633",
    "sg:postcode":"80040",
    "sg:province":"Napoli",
    "wof:name":"Autoscuola Motonautica La Pompeiana Iii Ddi Franzese Giuseppe",
    "wof:placetype":"venue"
},
  "geometry": {"coordinates":[14.525945,40.86002],"type":"Point"}
}