{
  "type": "Feature",
  "properties": {
    "addr:full":"Via Michelangelo Buonarroti 19 20090 Cesano Boscone Cesano Boscone Milano 20090",
    "addr:housenumber":"19",
    "addr:postcode":"20090;20090",
    "addr:street":"Via Michelangelo Buonarroti",
    "iso:country":"IT",
    "sg:address":"Via Michelangelo Buonarroti 19 20090 Cesano Boscone",
    "sg:city":"Cesano Boscone",
    "sg:orig_category":"Polyurethane Foam Installations, Mobile",
    "sg:phone":"+39 02 458 5762",
    "sg:postcode":"20090",
    "sg:province":"Milano",
    "wof:name":"F.lli Rossi S.r.l.",
    "wof:placetype":"venue"
},
  "geometry": {"coordinates":[9.1040000916,45.4430999756],"type":"Point"}
}