{
  "type": "Feature",
  "properties": {
    "iso:country":"IT",
    "sg:address":"Via Cerva 1 20122 Milano",
    "sg:city":"Milano",
    "sg:classifiers":[
        {
            "category":"Building & Trades",
            "subcategory":"Construction",
            "type":"Services"
        }
    ],
    "sg:phone":"+39 02 7602 1981",
    "sg:postcode":"20122",
    "sg:province":"Milano",
    "sg:tags":[
        "industrial",
        "timber"
    ],
    "wof:name":"Delpe Import Export Di Del Genio Rosario",
    "wof:placetype":"venue"
},
  "geometry": {"coordinates":[9.198071,45.463467],"type":"Point"}
}