{
  "type": "Feature",
  "properties": {
    "addr:full":"50013 Campi Bisenzio Campi Bisenzio Firenze 50013",
    "addr:postcode":"50013;50013",
    "addr:street":"Bisenzio",
    "iso:country":"IT",
    "sg:address":"50013 Campi Bisenzio",
    "sg:city":"Campi Bisenzio",
    "sg:orig_category":"Maglieria - Produzione E Ingrosso",
    "sg:phone":"+39 055 899 7066",
    "sg:postcode":"50013",
    "sg:province":"Firenze",
    "wof:name":"Maglificio Emmepi Puccini Di Gori Barbara",
    "wof:placetype":"venue"
},
  "geometry": {"coordinates":[11.143711,43.819553],"type":"Point"}
}