{
  "type": "Feature",
  "properties": {
    "addr:full":"38/a, Via Zanolini Antonio 40126 Bologna Bologna Bologna 40126",
    "addr:housenumber":"38 / a",
    "addr:postcode":"40126;40126",
    "addr:street":"Via Zanolini Antonio",
    "iso:country":"IT",
    "sg:address":"38/a, Via Zanolini Antonio 40126 Bologna",
    "sg:city":"Bologna",
    "sg:classifiers":[
        {
            "category":"Shopping",
            "type":"Retail Goods"
        }
    ],
    "sg:phone":"+39 39051242332",
    "sg:postcode":"40126",
    "sg:province":"Bologna",
    "sg:tags":[
        "finished",
        "-",
        "metallic"
    ],
    "wof:name":"Wal Italia (s.r.l.)",
    "wof:placetype":"venue"
},
  "geometry": {"coordinates":[11.3464813232,44.4942207336],"type":"Point"}
}