{
  "type": "Feature",
  "properties": {
    "addr:full":"22031 Albavilla Albavilla Como 22031",
    "addr:postcode":"22031;22031",
    "iso:country":"IT",
    "sg:address":"22031 Albavilla",
    "sg:city":"Albavilla",
    "sg:orig_category":"Materiali E Componenti Elettrotecnici. Elettrotecnica Industriale, Prodotti E Apparecchiature",
    "sg:phone":"+39 031 627007",
    "sg:postcode":"22031",
    "sg:province":"Como",
    "wof:name":"Electron-coil Snc",
    "wof:placetype":"venue"
},
  "geometry": {"coordinates":[9.183153,45.806358],"type":"Point"}
}