{
  "type": "Feature",
  "properties": {
    "iso:country":"IT",
    "sg:address":"Via Monfalcone 4 33085 Maniago",
    "sg:city":"Maniago",
    "sg:classifiers":[
        {
            "category":"Depot",
            "subcategory":"Train",
            "type":"Transportation"
        }
    ],
    "sg:phone":"+39 0427 706911",
    "sg:postcode":"33085",
    "sg:province":"Pordenone",
    "sg:tags":[
        "gear",
        "special"
    ],
    "sg:website":"www.carraro.com",
    "wof:name":"Siap Spa",
    "wof:placetype":"venue"
},
  "geometry": {"coordinates":[12.731326,46.151909],"type":"Point"}
}