{
  "type": "Feature",
  "properties": {
    "addr:full":"35027 Noventa Padovana Noventa Padovana Padova 35027",
    "addr:postcode":"35027;35027",
    "iso:country":"IT",
    "sg:address":"35027 Noventa Padovana",
    "sg:city":"Noventa Padovana",
    "sg:orig_category":"Servizi Ausiliari Di Analisi, Controllo E Ricerca",
    "sg:phone":"+39 049 893 5023",
    "sg:postcode":"35027",
    "sg:province":"Padova",
    "wof:name":"Tecnica S.r.l.",
    "wof:placetype":"venue"
},
  "geometry": {"coordinates":[11.986529,45.409405],"type":"Point"}
}