{
  "type": "Feature",
  "properties": {
    "addr:full":"1, Via Giovanni Monzio Compagnoni 24040 Castel Rozzone Castel Rozzone Bergamo 24040",
    "addr:housenumber":"rozzone",
    "addr:postcode":"24040;24040",
    "addr:street":"Via Giovanni Monzio Compagnoni",
    "iso:country":"IT",
    "sg:address":"1, Via Giovanni Monzio Compagnoni 24040 Castel Rozzone",
    "sg:city":"Castel Rozzone",
    "sg:classifiers":[
        {
            "category":"Manufacturing",
            "subcategory":"Rubber & Plastics",
            "type":"Manufacturing & Wholesale Goods"
        }
    ],
    "sg:phone":"+39 036 338 2893",
    "sg:postcode":"24040",
    "sg:province":"Bergamo",
    "wof:name":"Filplast S.r.l.",
    "wof:placetype":"venue"
},
  "geometry": {"coordinates":[9.6075229645,45.5516586304],"type":"Point"}
}