{
  "type": "Feature",
  "properties": {
    "iso:country":"IT",
    "sg:address":"84045 Altavilla Silentina",
    "sg:city":"Altavilla Silentina",
    "sg:orig_category":"Alimenti Conservati",
    "sg:phone":"+39 0828 987038",
    "sg:postcode":"84045",
    "sg:province":"Salerno",
    "wof:name":"Rispoli Luigi & C. Srl",
    "wof:placetype":"venue"
},
  "geometry": {"coordinates":[15.114202,40.532448],"type":"Point"}
}