{
  "type": "Feature",
  "properties": {
    "iso:country":"IT",
    "sg:address":"00177 Roma",
    "sg:city":"Roma",
    "sg:orig_category":"Macchine E Forniture Per Arredamento E Industria Del Legno",
    "sg:phone":"+39 06 241 3499",
    "sg:postcode":"00177",
    "sg:province":"Roma",
    "wof:name":"Samac Sas",
    "wof:placetype":"venue"
},
  "geometry": {"coordinates":[12.547586,41.876205],"type":"Point"}
}