{
  "type": "Feature",
  "properties": {
    "iso:country":"IT",
    "sg:address":"13, Via Bergamo 23801 Calolziocorte",
    "sg:city":"Calolziocorte",
    "sg:orig_category":"Miscellaneous Products",
    "sg:phone":"+39 0341 630500",
    "sg:postcode":"23801",
    "sg:province":"Lecco",
    "wof:name":"U.b.c. (s.r.l.)",
    "wof:placetype":"venue"
},
  "geometry": {"coordinates":[9.4405994415,45.7908668518],"type":"Point"}
}