{
  "type": "Feature",
  "properties": {
    "iso:country":"IT",
    "sg:address":"2, Vicolo Cavour 31020 Villorba",
    "sg:city":"Villorba",
    "sg:classifiers":[
        {
            "category":"Home & Garden",
            "subcategory":"Home Furnishings",
            "type":"Retail Goods"
        }
    ],
    "sg:phone":"+39 0422 446101",
    "sg:postcode":"31020",
    "sg:province":"Treviso",
    "sg:tags":[
        "household"
    ],
    "wof:name":"Veneta Cornici (s.r.l.)",
    "wof:placetype":"venue"
},
  "geometry": {"coordinates":[12.271647,45.714348],"type":"Point"}
}