{
  "type": "Feature",
  "properties": {
    "iso:country":"IT",
    "sg:address":"72, Via Savona 20144 Milano",
    "sg:city":"Milano",
    "sg:classifiers":[
        {
            "category":"Manufacturing",
            "subcategory":"Metals",
            "type":"Manufacturing & Wholesale Goods"
        }
    ],
    "sg:phone":"+39 02 4895 2785",
    "sg:postcode":"20144",
    "sg:province":"Milano",
    "sg:tags":[
        "metallurgy",
        "metalworking"
    ],
    "wof:name":"Dm Utensili S.r.l.",
    "wof:placetype":"venue"
},
  "geometry": {"coordinates":[9.160282135,45.452999115],"type":"Point"}
}