{
  "type": "Feature",
  "properties": {
    "addr:full":"51, Via Censi Dell' Arco 80040 Cercola Cercola Napoli 80040",
    "addr:postcode":"80040;80040",
    "addr:street":"Via Censi Dell ' Arco",
    "iso:country":"IT",
    "sg:address":"51, Via Censi Dell' Arco 80040 Cercola",
    "sg:city":"Cercola",
    "sg:classifiers":[
        {
            "category":"Professional",
            "subcategory":"Engineering",
            "type":"Services"
        }
    ],
    "sg:phone":"+39 081 555 0593",
    "sg:postcode":"80040",
    "sg:province":"Napoli",
    "sg:tags":[
        "machine",
        "-",
        "mechanical"
    ],
    "wof:name":"La Moderna Meccanica Di Annunziata Cassese E C. S.",
    "wof:placetype":"venue"
},
  "geometry": {"coordinates":[14.348908,40.851948],"type":"Point"}
}