{
  "type": "Feature",
  "properties": {
    "iso:country":"IT",
    "sg:address":"Via Mazzini, 31; Pordenone; 33170",
    "sg:city":"Pordenone",
    "sg:classifiers":[
        {
            "category":"Banks & Credit Unions",
            "subcategory":"Bank",
            "type":"Services"
        }
    ],
    "sg:phone":"+39 0434 208131",
    "sg:postcode":"33170",
    "sg:province":"Pordenone",
    "wof:name":"Banco Di Roma",
    "wof:placetype":"venue"
},
  "geometry": {"coordinates":[12.657386,45.958046],"type":"Point"}
}