{
  "type": "Feature",
  "properties": {
    "iso:country":"IT",
    "sg:address":"70042 Mola Di Bari",
    "sg:city":"Mola di Bari",
    "sg:orig_category":"Forniture Per Agricoltura E Zootecnia. Forniture Per Attivita' Industriali",
    "sg:phone":"+39 080 474 1129",
    "sg:postcode":"70042",
    "sg:province":"Bari",
    "wof:name":"Marino Vincenzo",
    "wof:placetype":"venue"
},
  "geometry": {"coordinates":[17.0945320129,41.0599136353],"type":"Point"}
}