{
  "type": "Feature",
  "properties": {
    "addr:full":"20158 Milano Milano Milano 20158",
    "addr:postcode":"20158;20158",
    "iso:country":"IT",
    "sg:address":"20158 Milano",
    "sg:city":"Milano",
    "sg:classifiers":[
        {
            "category":"Banks & Credit Unions",
            "subcategory":"Investment Brokerage",
            "type":"Services"
        }
    ],
    "sg:phone":"+39 02 3931 0001",
    "sg:postcode":"20158",
    "sg:province":"Milano",
    "sg:tags":[
        "capsule"
    ],
    "wof:name":"Pagani Capsule Srl",
    "wof:placetype":"venue"
},
  "geometry": {"coordinates":[9.161317,45.504265],"type":"Point"}
}