{
  "type": "Feature",
  "properties": {
    "addr:full":"84014 Nocera Inferiore Nocera Inferiore Salerno 84014",
    "addr:postcode":"84014;84014",
    "iso:country":"IT",
    "sg:address":"84014 Nocera Inferiore",
    "sg:city":"Nocera Inferiore",
    "sg:orig_category":"Prodotti Di Base E Forniture Per Industria Alimentare E Bevande. Prodotti Chimici Di Base",
    "sg:phone":"+39 081 924445",
    "sg:postcode":"84014",
    "sg:province":"Salerno",
    "wof:name":"Vi.sa Srl Aromi Mediterranei",
    "wof:placetype":"venue"
},
  "geometry": {"coordinates":[14.641292572,40.7584381104],"type":"Point"}
}