{
  "type": "Feature",
  "properties": {
    "addr:full":"13900 Biella Biella Biella 13900",
    "addr:postcode":"13900;13900",
    "iso:country":"IT",
    "sg:address":"13900 Biella",
    "sg:city":"Biella",
    "sg:classifiers":[
        {
            "category":"Health Services",
            "subcategory":"Health Practitioner",
            "type":"Services"
        }
    ],
    "sg:phone":"+39 015 849 1394",
    "sg:postcode":"13900",
    "sg:province":"Biella",
    "sg:tags":[
        "medici"
    ],
    "wof:name":"Nerva Franco",
    "wof:placetype":"venue"
},
  "geometry": {"coordinates":[8.0614738464,45.5595588684],"type":"Point"}
}