{
  "type": "Feature",
  "properties": {
    "addr:full":"33087 Pasiano Di Pordenone Cecchini Pordenone 33087",
    "addr:postcode":"33087;33087",
    "iso:country":"IT",
    "sg:address":"33087 Pasiano Di Pordenone",
    "sg:city":"Cecchini",
    "sg:orig_category":"Mobili - Produzione E Ingrosso",
    "sg:phone":"+39 0434 6291",
    "sg:postcode":"33087",
    "sg:province":"Pordenone",
    "sg:website":"http://www.msg.it",
    "wof:name":"Mobilificio Sangiacomo Spa",
    "wof:placetype":"venue"
},
  "geometry": {"coordinates":[12.6149158478,45.8730049133],"type":"Point"}
}