{
  "type": "Feature",
  "properties": {
    "iso:country":"IT",
    "sg:address":"12011 Borgo S. Dalmazzo",
    "sg:orig_category":"Abbigliamento Sportivo, Jeans E Casuals - Vendita Al Dettaglio",
    "sg:phone":"+39 0171 262404",
    "sg:postcode":"12011",
    "sg:province":"Cuneo",
    "wof:name":"Laudadio Carlo Snc - Basik - Marconisessantotto",
    "wof:placetype":"venue"
},
  "geometry": {"coordinates":[6.938113,44.396263],"type":"Point"}
}