{
  "type": "Feature",
  "properties": {
    "addr:full":"5, Via Lauro 84090 San Mango Piemonte San Mango Piemonte Salerno 84090",
    "addr:postcode":"84090;mango piemonte;84090",
    "addr:street":"Via Lauro",
    "iso:country":"IT",
    "sg:address":"5, Via Lauro 84090 San Mango Piemonte",
    "sg:city":"San Mango Piemonte",
    "sg:classifiers":[
        {
            "category":"Wholesale",
            "subcategory":"Medical Equipment & Supplies",
            "type":"Manufacturing & Wholesale Goods"
        }
    ],
    "sg:phone":"+39 39089631094",
    "sg:postcode":"84090",
    "sg:province":"Salerno",
    "sg:tags":[
        "-",
        "health",
        "instrument"
    ],
    "wof:name":"Decomedical Di Jean Marie Lorenz S.r.l.",
    "wof:placetype":"venue"
},
  "geometry": {"coordinates":[14.839924,40.697239],"type":"Point"}
}