{
  "type": "Feature",
  "properties": {
    "addr:full":"1, Via Maestri Del Lavoro 48018 Faenza Faenza Ravenna 48018",
    "addr:postcode":"48018;48018",
    "addr:street":"Via Maestri Del Lavoro",
    "iso:country":"IT",
    "sg:address":"1, Via Maestri Del Lavoro 48018 Faenza",
    "sg:city":"Faenza",
    "sg:classifiers":[
        {
            "category":"Shopping",
            "subcategory":"Clothing, Apparel, & Fashions",
            "type":"Retail Goods"
        }
    ],
    "sg:phone":"+39 0546 681681",
    "sg:postcode":"48018",
    "sg:province":"Ravenna",
    "sg:tags":[
        "clothes"
    ],
    "wof:name":"Mira S.r.l.",
    "wof:placetype":"venue"
},
  "geometry": {"coordinates":[11.890531,44.300003],"type":"Point"}
}