{
  "type": "Feature",
  "properties": {
    "iso:country":"IT",
    "sg:address":"03011 Alatri",
    "sg:city":"Alatri",
    "sg:orig_category":"Bagno - Accessori E Mobili",
    "sg:phone":"+39 0775 440625",
    "sg:postcode":"03011",
    "sg:province":"Frosinone",
    "wof:name":"Colella Srl",
    "wof:placetype":"venue"
},
  "geometry": {"coordinates":[13.338224,41.690231],"type":"Point"}
}