{
  "type": "Feature",
  "properties": {
    "addr:full":"00198 Roma Roma Roma 00198",
    "addr:postcode":"00198;00198",
    "iso:country":"IT",
    "sg:address":"00198 Roma",
    "sg:city":"Roma",
    "sg:orig_category":"Agenzie Viaggi E Turismo",
    "sg:phone":"+39 06 8620 6160",
    "sg:postcode":"00198",
    "sg:province":"Roma",
    "sg:website":"http://www.freereservation.com",
    "wof:name":"Le Chiavi Del Mondo Sas",
    "wof:placetype":"venue"
},
  "geometry": {"coordinates":[12.515276,41.923187],"type":"Point"}
}