{
  "type": "Feature",
  "properties": {
    "addr:full":"95125 Catania Catania Catania 95125",
    "addr:postcode":"95125;95125",
    "iso:country":"IT",
    "sg:address":"95125 Catania",
    "sg:city":"Catania",
    "sg:orig_category":"Servizi E Lavori Per Ecologia E Smaltimento Rifiuti. Ospedali E Servizi Sanitari. Servizi Ausiliari Di Analisi, Controllo E Ricerca",
    "sg:phone":"+39 095 339955",
    "sg:postcode":"95125",
    "sg:province":"Catania",
    "wof:name":"A. & A. Dr. Aita & Associated Inspectors Italia Sas",
    "wof:placetype":"venue"
},
  "geometry": {"coordinates":[15.085032,37.533287],"type":"Point"}
}