{
  "type": "Feature",
  "properties": {
    "addr:full":"Via Torricelli, 18/20 42027 Montecchio Emilia Reggio Nell'Emilia 42027",
    "addr:housenumber":"18 / 20",
    "addr:postcode":"42027;42027",
    "addr:street":"Via Torricelli",
    "iso:country":"IT",
    "sg:address":"Via Torricelli, 18/20 42027 Montecchio Emilia",
    "sg:classifiers":[
        {
            "category":"Shopping",
            "subcategory":"Stationery & Office Supplies",
            "type":"Retail Goods"
        }
    ],
    "sg:phone":"+39 0522 864981",
    "sg:postcode":"42027",
    "sg:province":"Reggio Nell'Emilia",
    "sg:tags":[
        "adhesive",
        "label"
    ],
    "sg:website":"www.serigrafia76.it",
    "wof:name":"Serigrafia 76 Snc",
    "wof:placetype":"venue"
},
  "geometry": {"coordinates":[10.480288,44.75433],"type":"Point"}
}