{
  "type": "Feature",
  "properties": {
    "iso:country":"IT",
    "sg:address":"50066 Reggello",
    "sg:city":"Reggello",
    "sg:orig_category":"Agricoltura - Attrezzi, Prodotti E Forniture",
    "sg:phone":"+39 055 863176",
    "sg:postcode":"50066",
    "sg:province":"Firenze",
    "wof:name":"Arnetoli Fabrizio",
    "wof:placetype":"venue"
},
  "geometry": {"coordinates":[11.45756,43.665466],"type":"Point"}
}