{
  "type": "Feature",
  "properties": {
    "iso:country":"IT",
    "sg:address":"20124 Milano",
    "sg:city":"Milano",
    "sg:orig_category":"Arredo Camera Letto E Complementi",
    "sg:phone":"+39 02 2952 4809",
    "sg:postcode":"20124",
    "sg:province":"Milano",
    "wof:name":"Sette Di Argentini Daniele E C. S.a.s.",
    "wof:placetype":"venue"
},
  "geometry": {"coordinates":[9.212688,45.482147],"type":"Point"}
}