{
  "type": "Feature",
  "properties": {
    "iso:country":"IT",
    "sg:address":"133, Via Vignazzola 20036 Meda",
    "sg:city":"Meda",
    "sg:classifiers":[
        {
            "category":"Home & Garden",
            "subcategory":"Home Furnishings",
            "type":"Retail Goods"
        }
    ],
    "sg:phone":"+39 39036270585",
    "sg:postcode":"20036",
    "sg:province":"Milano",
    "sg:tags":[
        "household"
    ],
    "wof:name":"Medea (s.r.l.)",
    "wof:placetype":"venue"
},
  "geometry": {"coordinates":[9.156642,45.650116],"type":"Point"}
}