{
  "type": "Feature",
  "properties": {
    "iso:country":"IT",
    "sg:address":"46, Viale Udine 30026 Portogruaro",
    "sg:city":"Portogruaro",
    "sg:classifiers":[
        {
            "category":"Building & Trades",
            "subcategory":"Construction",
            "type":"Services"
        }
    ],
    "sg:phone":"+39 39042175432",
    "sg:postcode":"30026",
    "sg:province":"Venezia",
    "sg:tags":[
        "work",
        "public"
    ],
    "wof:name":"Acco",
    "wof:placetype":"venue"
},
  "geometry": {"coordinates":[12.841661,45.789505],"type":"Point"}
}