{
  "type": "Feature",
  "properties": {
    "iso:country":"IT",
    "sg:address":"07026 Olbia",
    "sg:city":"Olbia",
    "sg:orig_category":"Climatizzazione E Condizionamento, Apparecchiature E Servizi",
    "sg:phone":"+39 0789 25124",
    "sg:postcode":"07026",
    "sg:province":"Olbia-Tempio",
    "wof:name":"Debidda Andrea Rappresentanze",
    "wof:placetype":"venue"
},
  "geometry": {"coordinates":[9.278559,40.826839],"type":"Point"}
}