{
  "type": "Feature",
  "properties": {
    "iso:country":"IT",
    "sg:address":"40138 Bologna",
    "sg:city":"Bologna",
    "sg:orig_category":"Macchine Utensili E Impianti",
    "sg:phone":"+39 051 533398",
    "sg:postcode":"40138",
    "sg:province":"Bologna",
    "wof:name":"Fioresi Gianni",
    "wof:placetype":"venue"
},
  "geometry": {"coordinates":[11.392351,44.490849],"type":"Point"}
}