{
  "type": "Feature",
  "properties": {
    "iso:country":"IT",
    "sg:address":"10029 Villastellone",
    "sg:city":"Villastellone",
    "sg:orig_category":"Fusti",
    "sg:phone":"+39 011 961 4711",
    "sg:postcode":"10029",
    "sg:province":"Torino",
    "wof:name":"La.fu.met. Srl",
    "wof:placetype":"venue"
},
  "geometry": {"coordinates":[7.727889061,44.9324188232],"type":"Point"}
}