{
  "type": "Feature",
  "properties": {
    "iso:country":"IT",
    "sg:address":"45100 Borsea",
    "sg:city":"Borsea",
    "sg:orig_category":"Articoli Pulizia. Macchine E Forniture Per Ecologia E Smaltimento Rifiuti. Forniture Per Attivita' Commerciali Ed Artigianali",
    "sg:phone":"+39 0425 475240",
    "sg:postcode":"45100",
    "sg:province":"Rovigo",
    "wof:name":"Puliveneta Srl",
    "wof:placetype":"venue"
},
  "geometry": {"coordinates":[11.772353,45.029903],"type":"Point"}
}