{
  "type": "Feature",
  "properties": {
    "iso:country":"IT",
    "sg:address":"00157 Roma",
    "sg:city":"Roma",
    "sg:classifiers":[
        {
            "category":"Sports & Exercise",
            "subcategory":"Tennis Court",
            "type":"Entertainment"
        }
    ],
    "sg:phone":"+39 06 451 3484",
    "sg:postcode":"00157",
    "sg:province":"Roma",
    "sg:tags":[
        "e",
        "lo",
        "tempo",
        "libero",
        "per",
        "impianti",
        "il",
        "attrezzature"
    ],
    "wof:name":"Tora Benito",
    "wof:placetype":"venue"
},
  "geometry": {"coordinates":[12.544124,41.914791],"type":"Point"}
}