{
  "type": "Feature",
  "properties": {
    "addr:full":"23878 Verderio Superiore Verderio Superiore Lecco 23878",
    "addr:postcode":"23878;23878",
    "iso:country":"IT",
    "sg:address":"23878 Verderio Superiore",
    "sg:city":"Verderio Superiore",
    "sg:orig_category":"Alberghi E Strutture Extra Alberghiere. Servizi Per Aziende, Manifestazioni E Supporto Agli Scambi Commerciali",
    "sg:phone":"+39 039 510152",
    "sg:postcode":"23878",
    "sg:province":"Lecco",
    "wof:name":"Tripicchio Luciano Ristorante Al Mediterraneo",
    "wof:placetype":"venue"
},
  "geometry": {"coordinates":[9.441247,45.667652],"type":"Point"}
}