{
  "type": "Feature",
  "properties": {
    "iso:country":"IT",
    "sg:address":"40135 Bologna",
    "sg:city":"Bologna",
    "sg:orig_category":"Studi E Consulenze Tecniche E Industriali. Consulenze Tecniche, Amministrative E Perizie",
    "sg:phone":"+39 051 614 6706",
    "sg:postcode":"40135",
    "sg:province":"Bologna",
    "sg:website":"http://www.arteasrl.it",
    "wof:name":"Artea Srl",
    "wof:placetype":"venue"
},
  "geometry": {"coordinates":[11.317469,44.488846],"type":"Point"}
}