{
  "type": "Feature",
  "properties": {
    "iso:country":"IT",
    "sg:address":"Vlo San Pio X 52/b 31020 San Vendemiano",
    "sg:city":"San Vendemiano",
    "sg:classifiers":[
        {
            "category":"Professional",
            "subcategory":"Art Services",
            "type":"Services"
        }
    ],
    "sg:phone":"+39 0438 412515",
    "sg:postcode":"31020",
    "sg:province":"Treviso",
    "sg:tags":[
        "shop",
        "design"
    ],
    "wof:name":"Gelmac S.a.s.",
    "wof:placetype":"venue"
},
  "geometry": {"coordinates":[12.242072,45.666286],"type":"Point"}
}