{
  "type": "Feature",
  "properties": {
    "iso:country":"IT",
    "sg:address":"55054 Piano Del Quercione",
    "sg:orig_category":"Forniture Per Agricoltura E Zootecnia. Forniture Per Attivita' Industriali",
    "sg:phone":"+39 0584 938642",
    "sg:postcode":"55054",
    "sg:province":"Lucca",
    "wof:name":"Moretto Reti",
    "wof:placetype":"venue"
},
  "geometry": {"coordinates":[10.3226137161,43.8809967041],"type":"Point"}
}