{
  "type": "Feature",
  "properties": {
    "addr:full":"44015 Portomaggiore Portomaggiore Ferrara 44015",
    "addr:postcode":"44015;44015",
    "iso:country":"IT",
    "sg:address":"44015 Portomaggiore",
    "sg:city":"Portomaggiore",
    "sg:orig_category":"Registrazione Sonora - Sale Prova",
    "sg:phone":"+39 0532 811198",
    "sg:postcode":"44015",
    "sg:province":"Ferrara",
    "wof:name":"Abhaco Studio Srl",
    "wof:placetype":"venue"
},
  "geometry": {"coordinates":[11.7523,44.766762],"type":"Point"}
}