{
  "type": "Feature",
  "properties": {
    "iso:country":"IT",
    "sg:address":"80141 Napoli",
    "sg:city":"Napoli",
    "sg:orig_category":"Utensili Meccanici E Materiali. Elettrotecnica Industriale, Prodotti E Apparecchiature",
    "sg:phone":"+39 081 751 2486",
    "sg:postcode":"80141",
    "sg:province":"Napoli",
    "wof:name":"Ma.de. Snc",
    "wof:placetype":"venue"
},
  "geometry": {"coordinates":[14.271946,40.861633],"type":"Point"}
}