{
  "type": "Feature",
  "properties": {
    "iso:country":"IT",
    "sg:address":"38057 Pergine Valsugana",
    "sg:city":"Pergine Valsugana",
    "sg:orig_category":"Carpenterie Legno",
    "sg:phone":"+39 0461 530105",
    "sg:postcode":"38057",
    "sg:province":"Trento",
    "sg:website":"http://www.luckyfloor.it",
    "wof:name":"Lucky Floor Di Prighl Dott. Lino",
    "wof:placetype":"venue"
},
  "geometry": {"coordinates":[11.238627,46.069321],"type":"Point"}
}