{
  "type": "Feature",
  "properties": {
    "addr:full":"20121 Milano Milano Milano 20121",
    "addr:postcode":"20121;20121",
    "iso:country":"IT",
    "sg:address":"20121 Milano",
    "sg:city":"Milano",
    "sg:orig_category":"Servizi Culturali E Per Lo Spettacolo",
    "sg:phone":"+39 02 7602 0650",
    "sg:postcode":"20121",
    "sg:province":"Milano",
    "wof:name":"Cinematografo Manzoni Auditorium",
    "wof:placetype":"venue"
},
  "geometry": {"coordinates":[9.193988,45.471272],"type":"Point"}
}