{
  "type": "Feature",
  "properties": {
    "addr:full":"20032 Cormano Cormano Milano 20032",
    "addr:postcode":"20032;20032",
    "iso:country":"IT",
    "sg:address":"20032 Cormano",
    "sg:city":"Cormano",
    "sg:orig_category":"Forniture Per Edilizia E Lavori Pubblici",
    "sg:phone":"+39 02 6630 6485",
    "sg:postcode":"20032",
    "sg:province":"Milano",
    "wof:name":"Tecnogivex Spa",
    "wof:placetype":"venue"
},
  "geometry": {"coordinates":[9.1707448959,45.5380325317],"type":"Point"}
}