{
  "type": "Feature",
  "properties": {
    "iso:country":"IT",
    "sg:address":"55100 Cappella",
    "sg:classifiers":[
        {
            "category":"Health Services",
            "subcategory":"Health Practitioner",
            "type":"Services"
        }
    ],
    "sg:phone":"+39 0583 395079",
    "sg:postcode":"55100",
    "sg:province":"Lucca",
    "sg:tags":[
        "medici"
    ],
    "wof:name":"Tassoni Dr. Franca Simonetta",
    "wof:placetype":"venue"
},
  "geometry": {"coordinates":[10.4837722778,43.8919372559],"type":"Point"}
}