{
  "type": "Feature",
  "properties": {
    "iso:country":"IT",
    "sg:address":"12040 Genola",
    "sg:city":"Genola",
    "sg:orig_category":"Nautica. Automobili E Mezzi Di Trasporto",
    "sg:phone":"+39 0172 68574",
    "sg:postcode":"12040",
    "sg:province":"Cuneo",
    "wof:name":"Nauticstore Di Marcarino Armando",
    "wof:placetype":"venue"
},
  "geometry": {"coordinates":[7.660135,44.597454],"type":"Point"}
}