{
  "type": "Feature",
  "properties": {
    "iso:country":"IT",
    "sg:address":"20059 Vimercate",
    "sg:city":"Vimercate",
    "sg:orig_category":"Traduttori Ed Interpreti",
    "sg:phone":"+39 039 660863",
    "sg:postcode":"20059",
    "sg:province":"Milano",
    "wof:name":"Kernel Snc Di Borgioli E Martinenghi",
    "wof:placetype":"venue"
},
  "geometry": {"coordinates":[9.099192,45.446037],"type":"Point"}
}