{
  "type": "Feature",
  "properties": {
    "iso:country":"IT",
    "sg:address":"40, Via Acquaviole 98057 Milazzo",
    "sg:city":"Milazzo",
    "sg:classifiers":[
        {
            "category":"Autos & Motor Vehicles",
            "subcategory":"Boat Sales",
            "type":"Retail Goods"
        }
    ],
    "sg:phone":"+39 090 924 0132",
    "sg:postcode":"98057",
    "sg:province":"Messina",
    "wof:name":"Base Boat Piccola Societa' Cooperativa A R.l.- Coverline Srl",
    "wof:placetype":"venue"
},
  "geometry": {"coordinates":[15.250182,38.209965],"type":"Point"}
}