{
  "type": "Feature",
  "properties": {
    "iso:country":"IT",
    "sg:address":"15033 Casale Monferrato",
    "sg:city":"Casale Monferrato",
    "sg:orig_category":"Alberghi",
    "sg:phone":"+39 0142 418728",
    "sg:postcode":"15033",
    "sg:province":"Alessandria",
    "sg:website":"http://www.cometoitaly.it/piemonte/candiani",
    "wof:name":"Hotel Candiani Srl",
    "wof:placetype":"venue"
},
  "geometry": {"coordinates":[8.455924,45.139442],"type":"Point"}
}