{
  "type": "Feature",
  "properties": {
    "addr:full":"151, Via Provinciale 23811 Ballabio Ballabio Lecco 23811",
    "addr:housenumber":"151",
    "addr:postcode":"23811;23811",
    "addr:street":"Via Provinciale",
    "iso:country":"IT",
    "sg:address":"151, Via Provinciale 23811 Ballabio",
    "sg:city":"Ballabio",
    "sg:classifiers":[
        {
            "category":"Manufacturing",
            "subcategory":"Metals",
            "type":"Manufacturing & Wholesale Goods"
        }
    ],
    "sg:phone":"+39 0341 530118",
    "sg:postcode":"23811",
    "sg:province":"Lecco",
    "sg:tags":[
        "metallurgy",
        "metalworking"
    ],
    "wof:name":"Trafilerie Galbani Di Galbani Attilio C. Snc",
    "wof:placetype":"venue"
},
  "geometry": {"coordinates":[9.4275007248,45.9028205872],"type":"Point"}
}