{
  "type": "Feature",
  "properties": {
    "addr:full":"107, Via Del Serafico 00142 Roma Roma Roma 00142",
    "addr:housenumber":"107",
    "addr:postcode":"00142;00142",
    "addr:street":"Via Del Serafico",
    "iso:country":"IT",
    "sg:address":"107, Via Del Serafico 00142 Roma",
    "sg:city":"Roma",
    "sg:classifiers":[
        {
            "category":"Professional",
            "subcategory":"Business Services",
            "type":"Services"
        }
    ],
    "sg:phone":"+39 390 654 591",
    "sg:postcode":"00142",
    "sg:province":"Roma",
    "sg:tags":[
        "advice"
    ],
    "wof:name":"Ifad",
    "wof:placetype":"venue"
},
  "geometry": {"coordinates":[12.488338,41.830475],"type":"Point"}
}