{
  "type": "Feature",
  "properties": {
    "addr:full":"24050 Grassobbio Grassobbio Bergamo 24050",
    "addr:postcode":"24050;24050",
    "iso:country":"IT",
    "sg:address":"24050 Grassobbio",
    "sg:city":"Grassobbio",
    "sg:orig_category":"Pavimenti Gomma, Linoleum E Plastica",
    "sg:phone":"+39 035 526968",
    "sg:postcode":"24050",
    "sg:province":"Bergamo",
    "wof:name":"Fratelli Lorenzi & C. Snc",
    "wof:placetype":"venue"
},
  "geometry": {"coordinates":[9.7268362045,45.6591758728],"type":"Point"}
}