{
  "type": "Feature",
  "properties": {
    "iso:country":"IT",
    "sg:address":"73048 Nard\u00f2",
    "sg:orig_category":"Tessuti E Stoffe. Tessuti Arredamento, Tende E Tappeti",
    "sg:phone":"+39 0833 578299",
    "sg:postcode":"73048",
    "sg:province":"Lecce",
    "wof:name":"Ricamificio Sirio Srl",
    "wof:placetype":"venue"
},
  "geometry": {"coordinates":[17.976887,40.202019],"type":"Point"}
}