{
  "type": "Feature",
  "properties": {
    "iso:country":"IT",
    "sg:address":"10093 Collegno",
    "sg:city":"Collegno",
    "sg:orig_category":"Materiali Semilavorati Metallici",
    "sg:phone":"+39 011 411 7250",
    "sg:postcode":"10093",
    "sg:province":"Torino",
    "wof:name":"Officina Meccanica Gallo (s.r.l.)",
    "wof:placetype":"venue"
},
  "geometry": {"coordinates":[7.58891,45.076496],"type":"Point"}
}