{
  "type": "Feature",
  "properties": {
    "addr:full":"Via Giacomo Matteotti 104 21051 Arcisate Arcisate Varese 21051",
    "addr:housenumber":"104",
    "addr:postcode":"21051;21051",
    "addr:street":"Via Giacomo Matteotti",
    "iso:country":"IT",
    "sg:address":"Via Giacomo Matteotti 104 21051 Arcisate",
    "sg:city":"Arcisate",
    "sg:classifiers":[
        {
            "category":"Manufacturing",
            "subcategory":"Rubber & Plastics",
            "type":"Manufacturing & Wholesale Goods"
        }
    ],
    "sg:phone":"+39 0332 850245",
    "sg:postcode":"21051",
    "sg:province":"Varese",
    "sg:tags":[
        "furniture"
    ],
    "sg:website":"www.dajo.it",
    "wof:name":"Dajo Srl",
    "wof:placetype":"venue"
},
  "geometry": {"coordinates":[8.8629827499,45.8631324768],"type":"Point"}
}