{
  "type": "Feature",
  "properties": {
    "addr:full":"Via Arena 22 20123 Milano Milano Milano 20123",
    "addr:housenumber":"22",
    "addr:postcode":"20123;20123",
    "addr:street":"Via Arena",
    "iso:country":"IT",
    "sg:address":"Via Arena 22 20123 Milano",
    "sg:city":"Milano",
    "sg:classifiers":[
        {
            "category":"Professional",
            "subcategory":"Business Services",
            "type":"Services"
        }
    ],
    "sg:phone":"+39 02 839 2270",
    "sg:postcode":"20123",
    "sg:province":"Milano",
    "sg:tags":[
        "industrial",
        "export"
    ],
    "sg:website":"www.temaxitalia.it",
    "wof:name":"Temax Italia Srl",
    "wof:placetype":"venue"
},
  "geometry": {"coordinates":[9.178839,45.455303],"type":"Point"}
}