{
  "type": "Feature",
  "properties": {
    "iso:country":"IT",
    "sg:address":"37045 Legnago",
    "sg:city":"Legnago",
    "sg:orig_category":"Prodotti E Manufatti In Gomma",
    "sg:phone":"+39 0442 20711",
    "sg:postcode":"37045",
    "sg:province":"Verona",
    "wof:name":"Moro Gedeone Sas",
    "wof:placetype":"venue"
},
  "geometry": {"coordinates":[11.3124370575,45.1617050171],"type":"Point"}
}