{
  "type": "Feature",
  "properties": {
    "iso:country":"IT",
    "sg:address":"Via Val Gardena 4 21052 Busto Arsizio",
    "sg:city":"Busto Arsizio",
    "sg:classifiers":[
        {
            "category":"Shopping",
            "subcategory":"Clothing, Apparel, & Fashions",
            "type":"Retail Goods"
        }
    ],
    "sg:phone":"+39 0331 684120",
    "sg:postcode":"21052",
    "sg:province":"Varese",
    "sg:tags":[
        "lingerie"
    ],
    "wof:name":"Confezioni Framar Di Giulio Genoni E Francesca Marzullo -s.n.c.",
    "wof:placetype":"venue"
},
  "geometry": {"coordinates":[8.832878,45.628681],"type":"Point"}
}