{
  "type": "Feature",
  "properties": {
    "iso:country":"IT",
    "sg:address":"20016 Pero",
    "sg:city":"Pero",
    "sg:orig_category":"Scuole E Servizi Scolastici. Ricerca, Selezione E Formazione Del Personale. Pubblica Amministrazione",
    "sg:phone":"+39 02 353 9365",
    "sg:postcode":"20016",
    "sg:province":"Milano",
    "wof:name":"Comune Di Pero",
    "wof:placetype":"venue"
},
  "geometry": {"coordinates":[9.07914,45.511059],"type":"Point"}
}