{
  "type": "Feature",
  "properties": {
    "iso:country":"IT",
    "sg:address":"1, Via Clerici 20090 Pieve Emanuele",
    "sg:city":"Pieve Emanuele",
    "sg:classifiers":[
        {
            "category":"Home & Garden",
            "subcategory":"Home Furnishings",
            "type":"Retail Goods"
        }
    ],
    "sg:phone":"+39 02 9072 2251",
    "sg:postcode":"20090",
    "sg:province":"Milano",
    "sg:tags":[
        "household"
    ],
    "wof:name":"Cierre Arredi Di Visco E Barbero (s.n.c.)",
    "wof:placetype":"venue"
},
  "geometry": {"coordinates":[9.178843,45.371891],"type":"Point"}
}