{
  "type": "Feature",
  "properties": {
    "iso:country":"IT",
    "sg:address":"56121 Pisa",
    "sg:city":"Pisa",
    "sg:orig_category":"Sport - Articoli E Forniture",
    "sg:phone":"+39 050 974014",
    "sg:postcode":"56121",
    "sg:province":"Pisa",
    "wof:name":"Esperia Srl",
    "wof:placetype":"venue"
},
  "geometry": {"coordinates":[10.431121,43.696907],"type":"Point"}
}