{
  "type": "Feature",
  "properties": {
    "addr:full":"40127 Bologna Bologna Bologna 40127",
    "addr:postcode":"40127;40127",
    "iso:country":"IT",
    "sg:address":"40127 Bologna",
    "sg:city":"Bologna",
    "sg:orig_category":"Trasporti E Spedizioni Merci",
    "sg:phone":"+39 051 504719",
    "sg:postcode":"40127",
    "sg:province":"Bologna",
    "wof:name":"Castelletti Rail Spa",
    "wof:placetype":"venue"
},
  "geometry": {"coordinates":[11.36799,44.50761],"type":"Point"}
}