{
  "type": "Feature",
  "properties": {
    "iso:country":"IT",
    "sg:address":"8, Via Da Verrazzano Giovanni 56029 Santa Croce Sull'arno",
    "sg:classifiers":[
        {
            "category":"Professional",
            "subcategory":"Engineering",
            "type":"Services"
        }
    ],
    "sg:phone":"+39 39057134380",
    "sg:postcode":"56029",
    "sg:province":"Pisa",
    "sg:tags":[
        "machine",
        "-",
        "mechanical"
    ],
    "wof:name":"Turini Macchine Per Conceria Srl",
    "wof:placetype":"venue"
},
  "geometry": {"coordinates":[10.396585,43.716137],"type":"Point"}
}