{
  "type": "Feature",
  "properties": {
    "iso:country":"IT",
    "sg:address":"Via Civilta' Del Lavoro 10 25028 Verolanuova",
    "sg:city":"Verolanuova",
    "sg:classifiers":[
        {
            "category":"Utilities",
            "subcategory":"Electric",
            "type":"Services"
        }
    ],
    "sg:phone":"+39 030 932533",
    "sg:postcode":"25028",
    "sg:province":"Brescia",
    "sg:tags":[
        "door",
        "pneumatic",
        "mechanisms"
    ],
    "sg:website":"www.el-mi.it",
    "wof:name":"El.mi. Srl",
    "wof:placetype":"venue"
},
  "geometry": {"coordinates":[10.083909,45.33559],"type":"Point"}
}