{
  "type": "Feature",
  "properties": {
    "iso:country":"IT",
    "sg:address":"22029 Uggiate Trevano",
    "sg:orig_category":"Serramenti Ed Infissi",
    "sg:phone":"+39 031 803036",
    "sg:postcode":"22029",
    "sg:province":"Como",
    "wof:name":"Micla",
    "wof:placetype":"venue"
},
  "geometry": {"coordinates":[8.954627,45.819881],"type":"Point"}
}