{
  "type": "Feature",
  "properties": {
    "iso:country":"IT",
    "sg:address":"Via Grieg 61 21047 Saronno",
    "sg:city":"Saronno",
    "sg:classifiers":[
        {
            "category":"Banks & Credit Unions",
            "subcategory":"Investment Brokerage",
            "type":"Services"
        }
    ],
    "sg:phone":"+39 02 962 6402",
    "sg:postcode":"21047",
    "sg:province":"Varese",
    "sg:tags":[
        "wheel",
        "rim",
        "bicycle",
        "moped"
    ],
    "sg:website":"www.berettacerchispa.it",
    "wof:name":"Beretta Cerchi Spa",
    "wof:placetype":"venue"
},
  "geometry": {"coordinates":[9.040055,45.613243],"type":"Point"}
}