{
  "type": "Feature",
  "properties": {
    "iso:country":"IT",
    "sg:address":"10, Via Dei Pellicciai Bl.1 Centergross 40050 Argelato",
    "sg:city":"Argelato",
    "sg:classifiers":[
        {
            "category":"Shopping",
            "subcategory":"Crafts & Fabrics",
            "type":"Retail Goods"
        }
    ],
    "sg:phone":"+39 051 664 7194",
    "sg:postcode":"40050",
    "sg:province":"Bologna",
    "sg:tags":[
        "linen"
    ],
    "wof:name":"Pezzoli (s.p.a.)",
    "wof:placetype":"venue"
},
  "geometry": {"coordinates":[11.3464813232,44.4942207336],"type":"Point"}
}