{
  "type": "Feature",
  "properties": {
    "iso:country":"IT",
    "sg:address":"2, Via Bruno Brandellero 36036 Torrebelvicino",
    "sg:city":"Torrebelvicino",
    "sg:classifiers":[
        {
            "category":"Shopping",
            "subcategory":"Computers & Home Electronics",
            "type":"Retail Goods"
        }
    ],
    "sg:phone":"+39 0445 595888",
    "sg:postcode":"36036",
    "sg:province":"Vicenza",
    "sg:tags":[
        "electronic",
        "electrical",
        "equipment"
    ],
    "wof:name":"Nuova Saccardo Motori Srl",
    "wof:placetype":"venue"
},
  "geometry": {"coordinates":[11.313936,45.715828],"type":"Point"}
}