{
  "type": "Feature",
  "properties": {
    "iso:country":"IT",
    "sg:address":"Via Di Vacciano 6b 50015 Grassina",
    "sg:classifiers":[
        {
            "category":"Shopping",
            "subcategory":"Department Store",
            "type":"Retail Goods"
        }
    ],
    "sg:phone":"+39 055 641744",
    "sg:province":"FI",
    "sg:tags":[
        "linen",
        "bed"
    ],
    "sg:website":"www.cottimaryanne.it",
    "wof:name":"Cottimaryanne Srl",
    "wof:placetype":"venue"
},
  "geometry": {"coordinates":[11.29635,43.723129],"type":"Point"}
}