{
  "type": "Feature",
  "properties": {
    "addr:full":"25071 Agnosine Agnosine Brescia 25071",
    "addr:postcode":"25071;25071",
    "iso:country":"IT",
    "sg:address":"25071 Agnosine",
    "sg:city":"Agnosine",
    "sg:orig_category":"Non-classified Establishments",
    "sg:phone":"+39 036 589 6102",
    "sg:postcode":"25071",
    "sg:province":"Brescia",
    "wof:name":"Inoxriv Di Rivadossi Francesco E Figli Spa",
    "wof:placetype":"venue"
},
  "geometry": {"coordinates":[10.348217,45.639217],"type":"Point"}
}