{
  "type": "Feature",
  "properties": {
    "iso:country":"IT",
    "sg:address":"21050 Gorla Maggiore",
    "sg:city":"Gorla Maggiore",
    "sg:orig_category":"Forniture Per Abbigliamento E Pelletterie",
    "sg:phone":"+39 0331 617450",
    "sg:postcode":"21050",
    "sg:province":"Varese",
    "wof:name":"Manifattura Piume Di Tiso Iris",
    "wof:placetype":"venue"
},
  "geometry": {"coordinates":[8.8667669296,45.6633224487],"type":"Point"}
}