{
  "type": "Feature",
  "properties": {
    "iso:country":"IT",
    "sg:address":"9, Via Spluga S. Cassiano 23020 Prata Camportaccio",
    "sg:city":"Prata Camportaccio",
    "sg:classifiers":[
        {
            "category":"Manufacturing",
            "subcategory":"Metals",
            "type":"Manufacturing & Wholesale Goods"
        }
    ],
    "sg:phone":"+39 39034320075",
    "sg:postcode":"23020",
    "sg:province":"Sondrio",
    "sg:tags":[
        "metallurgy",
        "metalworking"
    ],
    "wof:name":"F.i.m.a. Primex",
    "wof:placetype":"venue"
},
  "geometry": {"coordinates":[9.3914003372,46.2869758606],"type":"Point"}
}