{
  "type": "Feature",
  "properties": {
    "addr:full":"36061 Bassano Del Grappa Bassano del Grappa Vicenza 36061",
    "addr:postcode":"36061;36061",
    "iso:country":"IT",
    "sg:address":"36061 Bassano Del Grappa",
    "sg:city":"Bassano del Grappa",
    "sg:classifiers":[
        {
            "category":"Building & Trades",
            "subcategory":"Cleaning & Sanitation",
            "type":"Services"
        }
    ],
    "sg:phone":"+39 0424 382004",
    "sg:postcode":"36061",
    "sg:province":"Vicenza",
    "sg:tags":[
        "handling",
        "auxiliary",
        "storage",
        "surveillance",
        "maintenance",
        "services"
    ],
    "wof:name":"Bassano Coop",
    "wof:placetype":"venue"
},
  "geometry": {"coordinates":[11.748236,45.766998],"type":"Point"}
}