{
  "type": "Feature",
  "properties": {
    "addr:full":"Via Del Progresso 13 35014 Fontaniva Fontaniva Padova 35014",
    "addr:housenumber":"13",
    "addr:postcode":"35014;35014",
    "addr:street":"Via Del Progresso",
    "iso:country":"IT",
    "sg:address":"Via Del Progresso 13 35014 Fontaniva",
    "sg:city":"Fontaniva",
    "sg:classifiers":[
        {
            "category":"Home & Garden",
            "subcategory":"Hardware",
            "type":"Retail Goods"
        }
    ],
    "sg:phone":"+39 049 594 1313",
    "sg:postcode":"35014",
    "sg:province":"Padova",
    "sg:tags":[
        "small",
        "ironware",
        "item"
    ],
    "sg:website":"www.sariv.it",
    "wof:name":"Sariv Srl",
    "wof:placetype":"venue"
},
  "geometry": {"coordinates":[11.763787,45.625404],"type":"Point"}
}