{
  "type": "Feature",
  "properties": {
    "iso:country":"IT",
    "sg:address":"53031 Casole D'elsa",
    "sg:orig_category":"Articoli Da Regalo. Arte Ed Artigianato Artistico. Shopping",
    "sg:phone":"+39 0577 925005",
    "sg:postcode":"53031",
    "sg:province":"Siena",
    "wof:name":"S.p. Di Scribano",
    "wof:placetype":"venue"
},
  "geometry": {"coordinates":[11.048549,43.312912],"type":"Point"}
}