{
  "type": "Feature",
  "properties": {
    "iso:country":"IT",
    "sg:address":"20133 Milano",
    "sg:city":"Milano",
    "sg:orig_category":"Forniture Per Agricoltura E Zootecnia. Prodotti Chimici Secondari",
    "sg:phone":"+39 02 2951 7895",
    "sg:postcode":"20133",
    "sg:province":"Milano",
    "wof:name":"Tecniterra Srl",
    "wof:placetype":"venue"
},
  "geometry": {"coordinates":[9.2194042206,45.4777488708],"type":"Point"}
}