{
  "type": "Feature",
  "properties": {
    "iso:country":"IT",
    "sg:address":"08100 Nuoro",
    "sg:city":"Nuoro",
    "sg:orig_category":"Bruciatori Nafta, Gasolio E Kerosene - Commercio",
    "sg:phone":"+39 0784 204132",
    "sg:postcode":"08100",
    "sg:province":"Nuoro",
    "wof:name":"Te.i. Nuovo Srl",
    "wof:placetype":"venue"
},
  "geometry": {"coordinates":[9.314165,40.315865],"type":"Point"}
}