{
  "type": "Feature",
  "properties": {
    "iso:country":"IT",
    "sg:address":"20131 Milano",
    "sg:city":"Milano",
    "sg:orig_category":"Servizi E Lavori Per Abbigliamento E Pelletterie",
    "sg:phone":"+39 02 236 7289",
    "sg:postcode":"20131",
    "sg:province":"Milano",
    "wof:name":"Borghi Sara",
    "wof:placetype":"venue"
},
  "geometry": {"coordinates":[9.229906,45.484447],"type":"Point"}
}