{
  "type": "Feature",
  "properties": {
    "addr:full":"42013 Casalgrande Reggio Nell'Emilia 42013",
    "addr:postcode":"42013;42013",
    "iso:country":"IT",
    "sg:address":"42013 Casalgrande",
    "sg:orig_category":"Arredamenti - Produzione E Ingrosso",
    "sg:phone":"+39 0522 999125",
    "sg:postcode":"42013",
    "sg:province":"Reggio Nell'Emilia",
    "wof:name":"Cober Snc Di Costi D. E Bertolani G. E C.",
    "wof:placetype":"venue"
},
  "geometry": {"coordinates":[10.735072,44.612144],"type":"Point"}
}