{
  "type": "Feature",
  "properties": {
    "iso:country":"IT",
    "sg:address":"25080 Prevalle",
    "sg:city":"Prevalle",
    "sg:orig_category":"Zootecnia E Pesca, Allevamento Piccoli Animali",
    "sg:phone":"+39 030 603008",
    "sg:postcode":"25080",
    "sg:province":"Brescia",
    "wof:name":"Agricola Prevalle S.p.a.",
    "wof:placetype":"venue"
},
  "geometry": {"coordinates":[10.196267,45.491829],"type":"Point"}
}