{
  "type": "Feature",
  "properties": {
    "iso:country":"IT",
    "sg:address":"2, Via Don Luigi Sturzo 26029 Soncino",
    "sg:city":"Soncino",
    "sg:classifiers":[
        {
            "category":"Autos & Motor Vehicles",
            "subcategory":"Automobile Sales",
            "type":"Retail Goods"
        }
    ],
    "sg:phone":"+39 0374 837126",
    "sg:postcode":"26029",
    "sg:province":"Cremona",
    "sg:tags":[
        "industrial"
    ],
    "wof:name":"Dynastyplast.f1",
    "wof:placetype":"venue"
},
  "geometry": {"coordinates":[9.862476,45.399891],"type":"Point"}
}