{
  "type": "Feature",
  "properties": {
    "iso:country":"IT",
    "sg:address":"20123 Milano",
    "sg:city":"Milano",
    "sg:orig_category":"Arte Ed Artigianato Artistico",
    "sg:phone":"+39 02 836 1080",
    "sg:postcode":"20123",
    "sg:province":"Milano",
    "wof:name":"Melloni Maria Caterina",
    "wof:placetype":"venue"
},
  "geometry": {"coordinates":[9.173287,45.4603],"type":"Point"}
}