{
  "type": "Feature",
  "properties": {
    "addr:full":"85029 Venosa Venosa Potenza 85029",
    "addr:postcode":"85029;85029",
    "iso:country":"IT",
    "sg:address":"85029 Venosa",
    "sg:city":"Venosa",
    "sg:orig_category":"Termotecnica E Riscaldamento, Apparecchiature E Servizi",
    "sg:phone":"+39 0972 31585",
    "sg:postcode":"85029",
    "sg:province":"Potenza",
    "wof:name":"Luciano Tecnoimpianti Sas",
    "wof:placetype":"venue"
},
  "geometry": {"coordinates":[15.801201,40.647652],"type":"Point"}
}