{
  "type": "Feature",
  "properties": {
    "addr:full":"227, Via Europa 25062 Concesio Concesio Brescia 25062",
    "addr:housenumber":"227",
    "addr:postcode":"25062;25062",
    "addr:street":"Via Europa",
    "iso:country":"IT",
    "sg:address":"227, Via Europa 25062 Concesio",
    "sg:city":"Concesio",
    "sg:classifiers":[
        {
            "category":"Shopping",
            "type":"Retail Goods"
        }
    ],
    "sg:phone":"+39 030 218 4311",
    "sg:postcode":"25062",
    "sg:province":"Brescia",
    "sg:tags":[
        "finished",
        "-",
        "metallic"
    ],
    "wof:name":"Enolgas Bonomi S.p.a.",
    "wof:placetype":"venue"
},
  "geometry": {"coordinates":[10.2164745331,45.6036682129],"type":"Point"}
}