{
  "type": "Feature",
  "properties": {
    "iso:country":"IT",
    "sg:address":"89, Via Regio Parco 10036 Settimo Torinese",
    "sg:city":"Settimo Torinese",
    "sg:classifiers":[
        {
            "category":"Shopping",
            "subcategory":"Clothing, Apparel, & Fashions",
            "type":"Retail Goods"
        }
    ],
    "sg:phone":"+39 011 898 4800",
    "sg:postcode":"10036",
    "sg:province":"Torino",
    "sg:tags":[
        "clothes"
    ],
    "wof:name":"Nuova Montebianco S.r.l.",
    "wof:placetype":"venue"
},
  "geometry": {"coordinates":[7.749121,45.12524],"type":"Point"}
}