{
  "type": "Feature",
  "properties": {
    "iso:country":"IT",
    "sg:address":"40068 Bologna",
    "sg:orig_category":"Ristorazione E Locali Pubblici Affini. Ristoranti Ed Esercizi Affini. Servizi Ausiliari Di Ristorazione E Di Intrattenimento",
    "sg:phone":"+39 051 455280",
    "sg:postcode":"40068",
    "sg:province":"Bologna",
    "sg:website":"http://www.newservicericevimenti.com",
    "wof:name":"Newservice By Altura Srl",
    "wof:placetype":"venue"
},
  "geometry": {"coordinates":[11.394803,44.464767],"type":"Point"}
}