{
  "type": "Feature",
  "properties": {
    "iso:country":"IT",
    "sg:address":"16039 Sestri Levante",
    "sg:city":"Sestri Levante",
    "sg:orig_category":"Carni, Salumi E Pesci. Zootecnia E Pesca, Allevamento Piccoli Animali",
    "sg:phone":"+39 0185 41374",
    "sg:postcode":"16039",
    "sg:province":"Genova",
    "wof:name":"Leripesca Srl Prodotti Ittici",
    "wof:placetype":"venue"
},
  "geometry": {"coordinates":[9.41608,44.268963],"type":"Point"}
}