{
  "type": "Feature",
  "properties": {
    "iso:country":"IT",
    "sg:address":"Via Silvio Pellico, 40; Pontedera; 56025",
    "sg:city":"Pontedera",
    "sg:classifiers":[
        {
            "category":"Banks & Credit Unions",
            "subcategory":"Bank",
            "type":"Services"
        }
    ],
    "sg:phone":"+39 0587 52708",
    "sg:postcode":"56025",
    "sg:province":"Pisa",
    "wof:name":"Banca Popolare Di Novara",
    "wof:placetype":"venue"
},
  "geometry": {"coordinates":[10.632989,43.664406],"type":"Point"}
}