{
  "type": "Feature",
  "properties": {
    "iso:country":"IT",
    "sg:address":"10099 S.mauro Torinese",
    "sg:orig_category":"Elettrotecnica Industriale, Prodotti E Apparecchiature",
    "sg:phone":"+39 011 822 2709",
    "sg:postcode":"10099",
    "sg:province":"Torino",
    "sg:website":"http://www.a-e.it",
    "wof:name":"Ae Apparecchiature Elettroniche",
    "wof:placetype":"venue"
},
  "geometry": {"coordinates":[7.761849,45.109375],"type":"Point"}
}