{
  "type": "Feature",
  "properties": {
    "addr:full":"95128 Catania Catania Catania 95128",
    "addr:postcode":"95128;95128",
    "iso:country":"IT",
    "sg:address":"95128 Catania",
    "sg:city":"Catania",
    "sg:orig_category":"Servizi Per Lo Sport E Il Tempo Libero. Servizi Al Turismo. Servizi Ausiliari Dei Mezzi Di Trasporto. Servizi Ausiliari Per Il Trasporto",
    "sg:phone":"+39 095 505398",
    "sg:postcode":"95128",
    "sg:province":"Catania",
    "wof:name":"Autoservizi Russo Di Russo Salvatore & C. Snc",
    "wof:placetype":"venue"
},
  "geometry": {"coordinates":[15.082115,37.52462],"type":"Point"}
}