{
  "type": "Feature",
  "properties": {
    "addr:full":"20090 Vimodrone Vimodrone Milano 20090",
    "addr:postcode":"20090;20090",
    "iso:country":"IT",
    "sg:address":"20090 Vimodrone",
    "sg:city":"Vimodrone",
    "sg:orig_category":"Servizi E Lavori Per Ecologia E Smaltimento Rifiuti. Ospedali E Servizi Sanitari. Servizi Ausiliari Di Analisi, Controllo E Ricerca",
    "sg:phone":"+39 02 250 7151",
    "sg:postcode":"20090",
    "sg:province":"Milano",
    "sg:website":"http://www.biolab.it",
    "wof:name":"Biolab Spa",
    "wof:placetype":"venue"
},
  "geometry": {"coordinates":[9.2994318008,45.4995918274],"type":"Point"}
}