{
  "type": "Feature",
  "properties": {
    "addr:full":"22, Via Giambologna 21100 Varese Varese Varese 21100",
    "addr:postcode":"21100;21100",
    "addr:street":"Via Giambologna",
    "iso:country":"IT",
    "sg:address":"22, Via Giambologna 21100 Varese",
    "sg:city":"Varese",
    "sg:classifiers":[
        {
            "category":"Shopping",
            "subcategory":"Clothing, Apparel, & Fashions",
            "type":"Retail Goods"
        }
    ],
    "sg:phone":"+39 0332 331393",
    "sg:postcode":"21100",
    "sg:province":"Varese",
    "sg:tags":[
        "clothes"
    ],
    "wof:name":"Look S.r.l.",
    "wof:placetype":"venue"
},
  "geometry": {"coordinates":[8.836276,45.828873],"type":"Point"}
}