{
  "type": "Feature",
  "properties": {
    "iso:country":"IT",
    "sg:address":"60035 Jesi",
    "sg:city":"Jesi",
    "sg:orig_category":"Non-classified Establishments",
    "sg:phone":"+39 0731 4206",
    "sg:postcode":"60035",
    "sg:province":"Ancona",
    "wof:name":"Non Solo Orologi Antichita' Merli Di Merli Leonardo",
    "wof:placetype":"venue"
},
  "geometry": {"coordinates":[13.254805,43.52232],"type":"Point"}
}