{
  "type": "Feature",
  "properties": {
    "iso:country":"IT",
    "sg:address":"1, Via Molise 56025 Pontedera",
    "sg:city":"Pontedera",
    "sg:classifiers":[
        {
            "category":"Utilities",
            "subcategory":"Electric",
            "type":"Services"
        }
    ],
    "sg:phone":"+39 0587 296014",
    "sg:postcode":"56025",
    "sg:province":"Pisa",
    "sg:tags":[
        "component",
        "electronic"
    ],
    "wof:name":"Elcon (s.n.c.)",
    "wof:placetype":"venue"
},
  "geometry": {"coordinates":[10.396585,43.716137],"type":"Point"}
}