{
  "type": "Feature",
  "properties": {
    "iso:country":"IT",
    "sg:address":"17, Via Monte Ferrante 24020 Colere",
    "sg:city":"Colere",
    "sg:classifiers":[
        {
            "category":"Wholesale",
            "subcategory":"Drugs",
            "type":"Manufacturing & Wholesale Goods"
        }
    ],
    "sg:phone":"+39 39034654079",
    "sg:postcode":"24020",
    "sg:province":"Bergamo",
    "sg:tags":[
        "chemical",
        "pharmaceutical"
    ],
    "wof:name":"Finiscol (s.r.l.)",
    "wof:placetype":"venue"
},
  "geometry": {"coordinates":[10.085363,45.973038],"type":"Point"}
}