{
  "type": "Feature",
  "properties": {
    "iso:country":"IT",
    "sg:address":"10090 San Raffaele Cimena",
    "sg:city":"San Raffaele Cimena",
    "sg:orig_category":"Attrezzature E Forniture Per Officine Riparazione E Servizi Ausiliari",
    "sg:phone":"+39 011 981 1010",
    "sg:postcode":"10090",
    "sg:province":"Torino",
    "wof:name":"Car & Styling S.r.l.",
    "wof:placetype":"venue"
},
  "geometry": {"coordinates":[7.856569,45.15276],"type":"Point"}
}