{
  "type": "Feature",
  "properties": {
    "addr:full":"83, Corso Magenta 20123 Milano Milano Milano 20123",
    "addr:postcode":"20123;20123",
    "addr:street":"Corso Magenta",
    "iso:country":"IT",
    "sg:address":"83, Corso Magenta 20123 Milano",
    "sg:city":"Milano",
    "sg:classifiers":[
        {
            "category":"Manufacturing",
            "subcategory":"Printing",
            "type":"Manufacturing & Wholesale Goods"
        }
    ],
    "sg:phone":"+39 02 4800 7708",
    "sg:postcode":"20123",
    "sg:province":"Milano",
    "sg:tags":[
        "publishing"
    ],
    "wof:name":"Colour Separation Trust Srl",
    "wof:placetype":"venue"
},
  "geometry": {"coordinates":[9.1670675278,45.465877533],"type":"Point"}
}