{
  "type": "Feature",
  "properties": {
    "addr:full":"4, Via Giuseppina 26040 Cella Dati Cella Dati Cremona 26040",
    "addr:postcode":"26040;26040",
    "addr:street":"Via Giuseppina",
    "iso:country":"IT",
    "sg:address":"4, Via Giuseppina 26040 Cella Dati",
    "sg:city":"Cella Dati",
    "sg:classifiers":[
        {
            "category":"Professional",
            "subcategory":"Engineering",
            "type":"Services"
        }
    ],
    "sg:phone":"+39 39037267892",
    "sg:postcode":"26040",
    "sg:province":"Cremona",
    "sg:tags":[
        "machine",
        "-",
        "mechanical"
    ],
    "wof:name":"O.m.a.t. Di Milani Giuseppe & C. (s.n.c.)",
    "wof:placetype":"venue"
},
  "geometry": {"coordinates":[10.213243,45.09716],"type":"Point"}
}