{
  "type": "Feature",
  "properties": {
    "addr:full":"20090 Trezzano Naviglio Milano 20090",
    "addr:postcode":"20090;20090",
    "addr:street":"Trezzano Naviglio Milano",
    "iso:country":"IT",
    "sg:address":"20090 Trezzano Naviglio",
    "sg:orig_category":"Minuterie Metalliche E Ferramenta",
    "sg:phone":"+39 02 4840 9301",
    "sg:postcode":"20090",
    "sg:province":"Milano",
    "sg:website":"http://www.work-net.it/schnorr-italia",
    "wof:name":"Schnorr Italia Srl",
    "wof:placetype":"venue"
},
  "geometry": {"coordinates":[9.0689430237,45.4305496216],"type":"Point"}
}