{
  "type": "Feature",
  "properties": {
    "addr:full":"2, Via Agusta Mario 21010 Ferno Ferno Varese 21010",
    "addr:postcode":"21010;21010",
    "addr:street":"Via Agusta Mario",
    "iso:country":"IT",
    "sg:address":"2, Via Agusta Mario 21010 Ferno",
    "sg:city":"Ferno",
    "sg:classifiers":[
        {
            "category":"Communications",
            "subcategory":"Television Station",
            "type":"Services"
        }
    ],
    "sg:phone":"+39 0331 726106",
    "sg:postcode":"21010",
    "sg:province":"Varese",
    "sg:tags":[
        "audio-visual"
    ],
    "wof:name":"Icem S.r.l.",
    "wof:placetype":"venue"
},
  "geometry": {"coordinates":[8.826385,45.817604],"type":"Point"}
}