{
  "type": "Feature",
  "properties": {
    "addr:full":"20090 Segrate Segrate Milano 20090",
    "addr:postcode":"20090;20090",
    "iso:country":"IT",
    "sg:address":"20090 Segrate",
    "sg:city":"Segrate",
    "sg:orig_category":"Verniciatura Metalli",
    "sg:phone":"+39 02 213 1470",
    "sg:postcode":"20090",
    "sg:province":"Milano",
    "wof:name":"Zamboni Bruno",
    "wof:placetype":"venue"
},
  "geometry": {"coordinates":[9.262651,45.490772],"type":"Point"}
}