{
  "type": "Feature",
  "properties": {
    "addr:full":"37061 Ca'didavid VR",
    "addr:postcode":"37061",
    "iso:country":"IT",
    "sg:address":"37061 Ca'didavid",
    "sg:orig_category":"Forniture E Materiali Per Imballaggio E Confezionamento",
    "sg:phone":"+39 045 540123",
    "sg:province":"VR",
    "wof:name":"Filippi Giovanni",
    "wof:placetype":"venue"
},
  "geometry": {"coordinates":[-87.638381958,36.3049049377],"type":"Point"}
}