{
  "type": "Feature",
  "properties": {
    "addr:full":"00185 Roma Roma Roma 00185",
    "addr:postcode":"00185;00185",
    "iso:country":"IT",
    "sg:address":"00185 Roma",
    "sg:city":"Roma",
    "sg:orig_category":"Associazioni Ed Organismi Di Interesse Pubblico",
    "sg:phone":"+39 06 7720 5596",
    "sg:postcode":"00185",
    "sg:province":"Roma",
    "wof:name":"Circolo Sottufficiali E Guardie P.s. In Congedo",
    "wof:placetype":"venue"
},
  "geometry": {"coordinates":[12.50875,41.88937],"type":"Point"}
}