{
  "type": "Feature",
  "properties": {
    "iso:country":"IT",
    "sg:address":"45030 Ceneselli",
    "sg:city":"Ceneselli",
    "sg:orig_category":"Zootecnia E Pesca, Allevamento Piccoli Animali",
    "sg:phone":"+39 0425 88154",
    "sg:postcode":"45030",
    "sg:province":"Rovigo",
    "wof:name":"Allevamento Suinicolo Bentivoglio",
    "wof:placetype":"venue"
},
  "geometry": {"coordinates":[11.392447,45.026981],"type":"Point"}
}