{
  "type": "Feature",
  "properties": {
    "iso:country":"IT",
    "sg:address":"Via Dei Lavoratori 17 20092 Cinisello Balsamo",
    "sg:city":"Cinisello Balsamo",
    "sg:classifiers":[
        {
            "category":"Manufacturing",
            "subcategory":"Signs",
            "type":"Manufacturing & Wholesale Goods"
        }
    ],
    "sg:phone":"+39 02 6601 7241",
    "sg:postcode":"20092",
    "sg:province":"Milano",
    "sg:tags":[
        "identification",
        "card"
    ],
    "wof:name":"Dec Digital Electronic Company S.r.l.",
    "wof:placetype":"venue"
},
  "geometry": {"coordinates":[9.229423,45.556953],"type":"Point"}
}