{
  "type": "Feature",
  "properties": {
    "addr:full":"58100 Grosseto Grosseto Grosseto 58100",
    "addr:postcode":"58100;58100",
    "iso:country":"IT",
    "sg:address":"58100 Grosseto",
    "sg:city":"Grosseto",
    "sg:orig_category":"Prodotti Alimentari",
    "sg:phone":"+39 0564 402558",
    "sg:postcode":"58100",
    "sg:province":"Grosseto",
    "wof:name":"Cartanova '96",
    "wof:placetype":"venue"
},
  "geometry": {"coordinates":[11.1349105835,42.8168792725],"type":"Point"}
}