{
  "type": "Feature",
  "properties": {
    "iso:country":"IT",
    "sg:address":"3, Strada Paganina 43010 Roccabianca",
    "sg:city":"Roccabianca",
    "sg:classifiers":[
        {
            "category":"Manufacturing",
            "subcategory":"Rubber & Plastics",
            "type":"Manufacturing & Wholesale Goods"
        }
    ],
    "sg:phone":"+39 390 521 5291",
    "sg:postcode":"43010",
    "sg:province":"Parma",
    "wof:name":"Padana Plast S.p.a.",
    "wof:placetype":"venue"
},
  "geometry": {"coordinates":[10.2154712677,44.9820976257],"type":"Point"}
}