{
  "type": "Feature",
  "properties": {
    "iso:country":"IT",
    "sg:address":"20083 Gaggiano",
    "sg:city":"Gaggiano",
    "sg:orig_category":"Arredamenti - Produzione E Ingrosso",
    "sg:phone":"+39 02 908 5039",
    "sg:postcode":"20083",
    "sg:province":"Milano",
    "sg:website":"http://www.paghini.it",
    "wof:name":"Centro Arredamenti Paghini",
    "wof:placetype":"venue"
},
  "geometry": {"coordinates":[9.099045,45.440762],"type":"Point"}
}