{
  "type": "Feature",
  "properties": {
    "addr:full":"Via Della Motorizzazione 19 12020 Cuneo Cuneo 12020",
    "addr:housenumber":"19",
    "addr:postcode":"12020;12020",
    "addr:street":"Via Della Motorizzazione",
    "iso:country":"IT",
    "sg:address":"Via Della Motorizzazione 19 12020 Cuneo",
    "sg:classifiers":[
        {
            "category":"Manufacturing",
            "subcategory":"Printing",
            "type":"Manufacturing & Wholesale Goods"
        }
    ],
    "sg:phone":"+39 0171 412192",
    "sg:postcode":"12020",
    "sg:province":"Cuneo",
    "sg:tags":[
        "plastic"
    ],
    "sg:website":"www.roboplast.com",
    "wof:name":"Roboplast S.r.l.",
    "wof:placetype":"venue"
},
  "geometry": {"coordinates":[7.5471105576,44.38879776],"type":"Point"}
}