{
  "type": "Feature",
  "properties": {
    "iso:country":"IT",
    "sg:address":"169, Via Del Brennero 38100 Trento",
    "sg:city":"Trento",
    "sg:classifiers":[
        {
            "category":"Wholesale",
            "subcategory":"Drugs",
            "type":"Manufacturing & Wholesale Goods"
        }
    ],
    "sg:phone":"+39 0461 433300",
    "sg:postcode":"38100",
    "sg:province":"Trento",
    "sg:tags":[
        "chemical",
        "pharmaceutical"
    ],
    "wof:name":"Petrolvilla E Bortolotti S.p.a.",
    "wof:placetype":"venue"
},
  "geometry": {"coordinates":[11.111047,46.093517],"type":"Point"}
}