{
  "type": "Feature",
  "properties": {
    "iso:country":"IT",
    "sg:address":"86039 Termoli",
    "sg:city":"Termoli",
    "sg:orig_category":"Impiantistica E Prodotti Tecnologici Per Edilizia. Elettronica Professionale E Di Consumo",
    "sg:phone":"+39 0875 704988",
    "sg:postcode":"86039",
    "sg:province":"Campobasso",
    "wof:name":"Tecno 2 Di Di Fabio Michele",
    "wof:placetype":"venue"
},
  "geometry": {"coordinates":[14.997031,41.993187],"type":"Point"}
}