{
  "type": "Feature",
  "properties": {
    "iso:country":"IT",
    "sg:address":"35139 Padova",
    "sg:city":"Padova",
    "sg:orig_category":"Studi E Consulenze Tecniche E Industriali. Servizi E Lavori Per Edilizia E Lavori Pubblici. Professionisti - Studi E Servizi Ed Associazioni Di Interesse Aziendale",
    "sg:phone":"+39 049 876 2733",
    "sg:postcode":"35139",
    "sg:province":"Padova",
    "wof:name":"Studio Ing. Michele Greif",
    "wof:placetype":"venue"
},
  "geometry": {"coordinates":[11.656878,44.977913],"type":"Point"}
}