{
  "type": "Feature",
  "properties": {
    "iso:country":"IT",
    "sg:address":"22075 Lurate Caccivio",
    "sg:city":"Lurate Caccivio",
    "sg:classifiers":[
        {
            "category":"Manufacturing",
            "subcategory":"Tools & Machinery",
            "type":"Manufacturing & Wholesale Goods"
        }
    ],
    "sg:phone":"+39 031 490356",
    "sg:postcode":"22075",
    "sg:province":"Como",
    "sg:tags":[
        "leather",
        "equipment",
        "goods",
        "clothing"
    ],
    "wof:name":"Of.fri Officine Meccaniche Srl",
    "wof:placetype":"venue"
},
  "geometry": {"coordinates":[9.008524,45.76281],"type":"Point"}
}