{
  "type": "Feature",
  "properties": {
    "iso:country":"IT",
    "sg:address":"20090 Segrate",
    "sg:city":"Segrate",
    "sg:orig_category":"Elettrotecnica Industriale, Prodotti E Apparecchiature. Elettrotecnica Professionale E Di Consumo",
    "sg:phone":"+39 02 269 9211",
    "sg:postcode":"20090",
    "sg:province":"Milano",
    "wof:name":"Telmotor S.p.a.",
    "wof:placetype":"venue"
},
  "geometry": {"coordinates":[9.282232,45.494598],"type":"Point"}
}