{
  "type": "Feature",
  "properties": {
    "addr:full":"73040 Morciano Di Leuca Leuca Lecce 73040",
    "addr:postcode":"73040;73040",
    "iso:country":"IT",
    "sg:address":"73040 Morciano Di Leuca",
    "sg:city":"Leuca",
    "sg:orig_category":"Subacquee Attrezzature - Vendita Al Dettaglio E Corsi",
    "sg:phone":"+39 0833 711439",
    "sg:postcode":"73040",
    "sg:province":"Lecce",
    "wof:name":"Diving Service",
    "wof:placetype":"venue"
},
  "geometry": {"coordinates":[18.313295,39.848927],"type":"Point"}
}