{
  "type": "Feature",
  "properties": {
    "addr:full":"41012 Carpi Carpi Modena 41012",
    "addr:postcode":"41012;41012",
    "iso:country":"IT",
    "sg:address":"41012 Carpi",
    "sg:city":"Carpi",
    "sg:classifiers":[
        {
            "category":"Home & Garden",
            "subcategory":"Carpets & Floor Coverings",
            "type":"Retail Goods"
        }
    ],
    "sg:phone":"+39 059 645577",
    "sg:postcode":"41012",
    "sg:province":"Modena",
    "sg:tags":[
        "curtain",
        "material",
        "fabric",
        "fabrics",
        "furnishing"
    ],
    "wof:name":"Intertex Srl",
    "wof:placetype":"venue"
},
  "geometry": {"coordinates":[10.8632650375,44.8377151489],"type":"Point"}
}