{
  "type": "Feature",
  "properties": {
    "iso:country":"IT",
    "sg:address":"Via Salieri 24 37050 Vallese",
    "sg:city":"Vallese",
    "sg:orig_category":"Light Metal Rods",
    "sg:phone":"+39 045 699 7411",
    "sg:postcode":"37050",
    "sg:province":"Verona",
    "sg:website":"www.spsit.com",
    "wof:name":"S.p.s. Spa Sider Plating Scaligera",
    "wof:placetype":"venue"
},
  "geometry": {"coordinates":[11.060934,45.348042],"type":"Point"}
}