{
  "type": "Feature",
  "properties": {
    "iso:country":"IT",
    "sg:address":"10023 Chieri",
    "sg:city":"Chieri",
    "sg:orig_category":"Articoli Da Regalo. Forniture Per Uffici. Regalistica Aziendale",
    "sg:phone":"+39 011 941 2809",
    "sg:postcode":"10023",
    "sg:province":"Torino",
    "wof:name":"Carta E Penna Di Pennazio Vittorio",
    "wof:placetype":"venue"
},
  "geometry": {"coordinates":[7.750886,45.016159],"type":"Point"}
}