{
  "type": "Feature",
  "properties": {
    "iso:country":"IT",
    "sg:address":"38, Via San Salvatore 15048 Valenza",
    "sg:city":"Valenza",
    "sg:classifiers":[
        {
            "category":"Shopping",
            "subcategory":"Jewelry",
            "type":"Retail Goods"
        }
    ],
    "sg:phone":"+39 0131 947920",
    "sg:postcode":"15048",
    "sg:province":"Alessandria",
    "sg:tags":[
        "jewellery"
    ],
    "wof:name":"Dipiemme S.r.l.",
    "wof:placetype":"venue"
},
  "geometry": {"coordinates":[8.638844,45.010761],"type":"Point"}
}