{
  "type": "Feature",
  "properties": {
    "addr:full":"47, Via Vittorio Veneto 22079 Villa Guardia Villa Guardia Como 22079",
    "addr:housenumber":"guardia",
    "addr:postcode":"22079;22079",
    "addr:street":"Via Vittorio Veneto;Guardia",
    "iso:country":"IT",
    "sg:address":"47, Via Vittorio Veneto 22079 Villa Guardia",
    "sg:city":"Villa Guardia",
    "sg:classifiers":[
        {
            "category":"Real Estate",
            "subcategory":"Architect",
            "type":"Services"
        }
    ],
    "sg:phone":"+39 39031480890",
    "sg:postcode":"22079",
    "sg:province":"Como",
    "sg:tags":[
        "textile",
        "clothing"
    ],
    "wof:name":"Tessiture Meccaniche Seterie",
    "wof:placetype":"venue"
},
  "geometry": {"coordinates":[9.023107,45.777367],"type":"Point"}
}