{
  "type": "Feature",
  "properties": {
    "iso:country":"IT",
    "sg:address":"25010 Borgosatollo",
    "sg:city":"Borgosatollo",
    "sg:orig_category":"Autotrasporti",
    "sg:phone":"+39 030 270 1445",
    "sg:postcode":"25010",
    "sg:province":"Brescia",
    "wof:name":"Fontanazza Srl",
    "wof:placetype":"venue"
},
  "geometry": {"coordinates":[10.235942,45.463402],"type":"Point"}
}