{
  "type": "Feature",
  "properties": {
    "addr:full":"33058 San Giorgio Di Nogaro San Giorgio di Nogaro Udine 33058",
    "addr:postcode":"33058;33058",
    "iso:country":"IT",
    "sg:address":"33058 San Giorgio Di Nogaro",
    "sg:city":"San Giorgio di Nogaro",
    "sg:orig_category":"Servizi Ausiliari Dei Mezzi Di Trasporto. Servizi Ausiliari Per Il Trasporto. Acqua, Luce, Gas E Societa' Di Esercizio Pubblico",
    "sg:phone":"+39 0431 65318",
    "sg:postcode":"33058",
    "sg:province":"Udine",
    "wof:name":"Impresa Portuale Porto Nogaro Srl",
    "wof:placetype":"venue"
},
  "geometry": {"coordinates":[13.202553,45.832108],"type":"Point"}
}