{
  "type": "Feature",
  "properties": {
    "iso:country":"IT",
    "sg:address":"10070 Viu'",
    "sg:orig_category":"Pubblica Amministrazione",
    "sg:phone":"+39 0123 696300",
    "sg:postcode":"10070",
    "sg:province":"Torino",
    "wof:name":"Vigili Del Fuoco Volontari",
    "wof:placetype":"venue"
},
  "geometry": {"coordinates":[7.3766012192,45.2389068604],"type":"Point"}
}