{
  "type": "Feature",
  "properties": {
    "iso:country":"IT",
    "sg:address":"25055 Pisogne",
    "sg:city":"Pisogne",
    "sg:orig_category":"Lavorazioni Meccaniche E Servizi",
    "sg:phone":"+39 036 486721",
    "sg:postcode":"25055",
    "sg:province":"Brescia",
    "wof:name":"Camuna Installazioni Srl",
    "wof:placetype":"venue"
},
  "geometry": {"coordinates":[10.220412,45.546452],"type":"Point"}
}