{
  "type": "Feature",
  "properties": {
    "iso:country":"IT",
    "sg:address":"57128 Livorno",
    "sg:city":"Livorno",
    "sg:orig_category":"Arredi Ed Attrezzature Per Uffici",
    "sg:phone":"+39 0586 501919",
    "sg:postcode":"57128",
    "sg:province":"Livorno",
    "wof:name":"Torrefazione Tirrenia Caffe' Snc",
    "wof:placetype":"venue"
},
  "geometry": {"coordinates":[10.747925,43.67762],"type":"Point"}
}