{
  "type": "Feature",
  "properties": {
    "addr:full":"81100 Caserta Caserta Caserta 81100",
    "addr:postcode":"81100;81100",
    "iso:country":"IT",
    "sg:address":"81100 Caserta",
    "sg:city":"Caserta",
    "sg:orig_category":"Pubblicita', Marketing E Comunicazione",
    "sg:phone":"+39 800 908 941",
    "sg:postcode":"81100",
    "sg:province":"Caserta",
    "sg:website":"http://www.sposinweb.it",
    "wof:name":"Ag. Sposi In Web",
    "wof:placetype":"venue"
},
  "geometry": {"coordinates":[14.3675527573,41.0854377747],"type":"Point"}
}