{
  "type": "Feature",
  "properties": {
    "iso:country":"IT",
    "sg:address":"31050 Ponzano Veneto",
    "sg:city":"Ponzano Veneto",
    "sg:orig_category":"Porte Basculanti E Ribaltabili",
    "sg:phone":"+39 0422 440714",
    "sg:postcode":"31050",
    "sg:province":"Treviso",
    "wof:name":"Scandiuzzi Snc Di F. Scandiuzzi & Figli",
    "wof:placetype":"venue"
},
  "geometry": {"coordinates":[12.2207155228,45.7300643921],"type":"Point"}
}