{
  "type": "Feature",
  "properties": {
    "iso:country":"IT",
    "sg:address":"20090 Segrate",
    "sg:city":"Segrate",
    "sg:orig_category":"Scuole E Servizi Scolastici. Ricerca, Selezione E Formazione Del Personale. Pubblica Amministrazione",
    "sg:phone":"+39 02 213 5789",
    "sg:postcode":"20090",
    "sg:province":"Milano",
    "wof:name":"Comune Di Segrate",
    "wof:placetype":"venue"
},
  "geometry": {"coordinates":[9.286714,45.496983],"type":"Point"}
}