{
  "type": "Feature",
  "properties": {
    "addr:full":"20047 Brugherio Brugherio Milano 20047",
    "addr:postcode":"20047;20047",
    "iso:country":"IT",
    "sg:address":"20047 Brugherio",
    "sg:city":"Brugherio",
    "sg:classifiers":[
        {
            "category":"Manufacturing",
            "subcategory":"Metals",
            "type":"Manufacturing & Wholesale Goods"
        }
    ],
    "sg:phone":"+39 039 870691",
    "sg:postcode":"20047",
    "sg:province":"Milano",
    "sg:tags":[
        "forming",
        "working",
        "welding"
    ],
    "sg:website":"http://www.metallindustria.com",
    "wof:name":"Metallindustria Srl",
    "wof:placetype":"venue"
},
  "geometry": {"coordinates":[9.2915096283,45.5453720093],"type":"Point"}
}