{
  "type": "Feature",
  "properties": {
    "addr:full":"06012 Citta'dicastello Cerbara Perugia 06012",
    "addr:postcode":"06012;06012",
    "iso:country":"IT",
    "sg:address":"06012 Citta'dicastello",
    "sg:city":"Cerbara",
    "sg:orig_category":"Cartotecnica E Servizi. Forniture Per Uffici",
    "sg:phone":"+39 075 851 1510",
    "sg:postcode":"06012",
    "sg:province":"Perugia",
    "sg:website":"http://www.pasquispa.com",
    "wof:name":"Modul Lama Srl",
    "wof:placetype":"venue"
},
  "geometry": {"coordinates":[12.231905,43.457787],"type":"Point"}
}