{
  "type": "Feature",
  "properties": {
    "addr:full":"Via Mantova 43058 Sorbolo Sorbolo Parma 43058",
    "addr:postcode":"43058;43058",
    "addr:street":"Via Mantova",
    "iso:country":"IT",
    "sg:address":"Via Mantova 43058 Sorbolo",
    "sg:city":"Sorbolo",
    "sg:classifiers":[
        {
            "category":"Real Estate",
            "subcategory":"Surveying",
            "type":"Services"
        }
    ],
    "sg:phone":"+39 0521 604200",
    "sg:postcode":"43058",
    "sg:province":"Parma",
    "sg:tags":[
        "equipment",
        "material",
        "good",
        "-",
        "handling"
    ],
    "wof:name":"Bp Battioni E Pagani (s.p.a.)",
    "wof:placetype":"venue"
},
  "geometry": {"coordinates":[10.398984,44.829403],"type":"Point"}
}