{
  "type": "Feature",
  "properties": {
    "addr:full":"41100 Modena Modena Modena 41100",
    "addr:postcode":"41100;41100",
    "iso:country":"IT",
    "sg:address":"41100 Modena",
    "sg:city":"Modena",
    "sg:orig_category":"Materiali E Componenti Elettronici",
    "sg:phone":"+39 059 282777",
    "sg:postcode":"41100",
    "sg:province":"Modena",
    "wof:name":"I.c.s. Srl",
    "wof:placetype":"venue"
},
  "geometry": {"coordinates":[10.975468,44.634628],"type":"Point"}
}