{
  "type": "Feature",
  "properties": {
    "addr:full":"Via Sferracavallo 03043 Cassino Cassino Frosinone 03043",
    "addr:postcode":"03043;03043",
    "addr:street":"Via Sferracavallo",
    "iso:country":"IT",
    "sg:address":"Via Sferracavallo 03043 Cassino",
    "sg:city":"Cassino",
    "sg:classifiers":[
        {
            "category":"Wholesale",
            "subcategory":"Machinery & Supplies",
            "type":"Manufacturing & Wholesale Goods"
        }
    ],
    "sg:phone":"+39 39077621428",
    "sg:postcode":"03043",
    "sg:province":"Frosinone",
    "sg:tags":[
        "-",
        "agriculture",
        "equipment"
    ],
    "wof:name":"Francesco Di Gruso (s.r.l.)",
    "wof:placetype":"venue"
},
  "geometry": {"coordinates":[13.835046,41.512634],"type":"Point"}
}