{
  "type": "Feature",
  "properties": {
    "addr:full":"Via A. Volta 13 30020 Noventa Di Piave Noventa di Piave Venezia 30020",
    "addr:housenumber":"13",
    "addr:postcode":"30020;30020",
    "addr:street":"Via A. Volta",
    "iso:country":"IT",
    "sg:address":"Via A. Volta 13 30020 Noventa Di Piave",
    "sg:city":"Noventa di Piave",
    "sg:classifiers":[
        {
            "category":"Building & Trades",
            "subcategory":"Electrical",
            "type":"Services"
        }
    ],
    "sg:phone":"+39 0421 658682",
    "sg:postcode":"30020",
    "sg:province":"Venezia",
    "sg:tags":[
        "plants",
        "plant",
        "industrial",
        "buildings",
        "construction"
    ],
    "wof:name":"Sv Impianti Srl",
    "wof:placetype":"venue"
},
  "geometry": {"coordinates":[12.970455,45.810093],"type":"Point"}
}