{
  "type": "Feature",
  "properties": {
    "iso:country":"IT",
    "sg:address":"21, Via Liguria 40064 Ozzano Dell'emilia",
    "sg:classifiers":[
        {
            "category":"Professional",
            "subcategory":"Printing & Photocopies",
            "type":"Services"
        }
    ],
    "sg:phone":"+39 39051799901",
    "sg:postcode":"40064",
    "sg:province":"Bologna",
    "wof:name":"La Nuova Legatoria Di Luciani Renzo & C. S.n.c.",
    "wof:placetype":"venue"
},
  "geometry": {"coordinates":[11.5037765503,44.4532585144],"type":"Point"}
}