{
  "type": "Feature",
  "properties": {
    "iso:country":"IT",
    "sg:address":"54033 Carrara",
    "sg:city":"Carrara",
    "sg:orig_category":"Graniti",
    "sg:phone":"+39 0585 844726",
    "sg:postcode":"54033",
    "sg:province":"Massa-Carrara",
    "wof:name":"Fruendi Luigi",
    "wof:placetype":"venue"
},
  "geometry": {"coordinates":[10.088034,44.071949],"type":"Point"}
}