{
  "type": "Feature",
  "properties": {
    "iso:country":"IT",
    "sg:address":"Via Sille 5 38045 Civezzano",
    "sg:city":"Civezzano",
    "sg:orig_category":"Felsite Porphyry",
    "sg:phone":"+39 0461 858710",
    "sg:postcode":"38045",
    "sg:province":"Trento",
    "sg:website":"www.porfidieuropa.com",
    "wof:name":"Porfidi Europa Srl",
    "wof:placetype":"venue"
},
  "geometry": {"coordinates":[11.1995859146,46.0824890137],"type":"Point"}
}