{
  "type": "Feature",
  "properties": {
    "addr:full":"Sda Statale 115 92013 Menfi Menfi Agrigento 92013",
    "addr:housenumber":"115",
    "addr:postcode":"92013;92013",
    "iso:country":"IT",
    "sg:address":"Sda Statale 115 92013 Menfi",
    "sg:city":"Menfi",
    "sg:classifiers":[
        {
            "category":"Food & Beverages",
            "subcategory":"Liquor & Beverages",
            "type":"Retail Goods"
        }
    ],
    "sg:phone":"+39 0925 77111",
    "sg:postcode":"92013",
    "sg:province":"Agrigento",
    "sg:tags":[
        "wine",
        "italian"
    ],
    "sg:website":"www.cantinesettesoli.it",
    "wof:name":"Cantine Settesoli Soc Coop Arl",
    "wof:placetype":"venue"
},
  "geometry": {"coordinates":[13.236134,37.453125],"type":"Point"}
}