{
  "type": "Feature",
  "properties": {
    "addr:full":"93013 Mazzarino Mazzarino Caltanissetta 93013",
    "addr:postcode":"93013;93013",
    "iso:country":"IT",
    "sg:address":"93013 Mazzarino",
    "sg:city":"Mazzarino",
    "sg:orig_category":"Graniti",
    "sg:phone":"+39 0934 381317",
    "sg:postcode":"93013",
    "sg:province":"Caltanissetta",
    "wof:name":"Zafarana Filippo & C. Snc",
    "wof:placetype":"venue"
},
  "geometry": {"coordinates":[14.135767,37.416904],"type":"Point"}
}