{
  "type": "Feature",
  "properties": {
    "iso:country":"IT",
    "sg:address":"62/66, Via Brescia 59013 Montemurlo",
    "sg:city":"Montemurlo",
    "sg:classifiers":[
        {
            "category":"Home & Garden",
            "subcategory":"Home Furnishings",
            "type":"Retail Goods"
        }
    ],
    "sg:phone":"+39 0574 720629",
    "sg:postcode":"59013",
    "sg:province":"Prato",
    "sg:tags":[
        "household"
    ],
    "wof:name":"Flexinn S.a.s",
    "wof:placetype":"venue"
},
  "geometry": {"coordinates":[11.05219,43.908222],"type":"Point"}
}