{
  "type": "Feature",
  "properties": {
    "iso:country":"IT",
    "sg:address":"Via G. Zanella, 23; Chiampo; 36072",
    "sg:city":"Chiampo",
    "sg:classifiers":[
        {
            "category":"Banks & Credit Unions",
            "subcategory":"Bank",
            "type":"Services"
        }
    ],
    "sg:phone":"+39 0444 624666",
    "sg:postcode":"36072",
    "sg:province":"Vicenza",
    "wof:name":"Banca Popolare Di Arzignano",
    "wof:placetype":"venue"
},
  "geometry": {"coordinates":[11.278863,45.544567],"type":"Point"}
}