{
  "type": "Feature",
  "properties": {
    "addr:full":"40061 Minerbio Minerbio Bologna 40061",
    "addr:postcode":"40061;minerbio bologna 40061",
    "iso:country":"IT",
    "sg:address":"40061 Minerbio",
    "sg:city":"Minerbio",
    "sg:orig_category":"Mobili Metallici",
    "sg:phone":"+39 051 660 5486",
    "sg:postcode":"40061",
    "sg:province":"Bologna",
    "wof:name":"Promobil Attrezzature Industriali Srl",
    "wof:placetype":"venue"
},
  "geometry": {"coordinates":[11.4761266708,44.6159591675],"type":"Point"}
}