{
  "type": "Feature",
  "properties": {
    "addr:full":"56125 Pisa Pisa Pisa 56125",
    "addr:postcode":"56125;56125",
    "iso:country":"IT",
    "sg:address":"56125 Pisa",
    "sg:city":"Pisa",
    "sg:orig_category":"Termotecnica E Riscaldamento, Apparecchiature E Servizi",
    "sg:phone":"+39 050 41155",
    "sg:postcode":"56125",
    "sg:province":"Pisa",
    "wof:name":"Fanfano Domenico",
    "wof:placetype":"venue"
},
  "geometry": {"coordinates":[10.407035,43.708134],"type":"Point"}
}