{
  "type": "Feature",
  "properties": {
    "iso:country":"IT",
    "sg:address":"Via Fratelli Bandiera 36 20025 Legnano",
    "sg:city":"Legnano",
    "sg:classifiers":[
        {
            "category":"Manufacturing",
            "subcategory":"Tools & Machinery",
            "type":"Manufacturing & Wholesale Goods"
        }
    ],
    "sg:phone":"+39 0331 442074",
    "sg:postcode":"20025",
    "sg:province":"Milano",
    "sg:tags":[
        "measuring",
        "precision"
    ],
    "sg:website":"www.rotondi.it",
    "wof:name":"Fratelli Rotondi Sas",
    "wof:placetype":"venue"
},
  "geometry": {"coordinates":[8.8911552429,45.5566444397],"type":"Point"}
}