{
  "type": "Feature",
  "properties": {
    "addr:full":"20049 Concorezzo Concorezzo Milano 20049",
    "addr:postcode":"20049;20049",
    "iso:country":"IT",
    "sg:address":"20049 Concorezzo",
    "sg:city":"Concorezzo",
    "sg:orig_category":"Arredi Ed Attrezzature Per Attivita' Commerciali Ed Artigianali",
    "sg:phone":"+39 039 604 0961",
    "sg:postcode":"20049",
    "sg:province":"Milano",
    "sg:website":"http://www.giovanardi-srl.com",
    "wof:name":"Giovanardi Srl",
    "wof:placetype":"venue"
},
  "geometry": {"coordinates":[9.212082,45.480274],"type":"Point"}
}