{
  "type": "Feature",
  "properties": {
    "iso:country":"IT",
    "sg:address":"36100 Vicenza",
    "sg:city":"Vicenza",
    "sg:orig_category":"Articoli Da Regalo. Arte Ed Artigianato Artistico",
    "sg:phone":"+39 0444 964417",
    "sg:postcode":"36100",
    "sg:province":"Vicenza",
    "wof:name":"Gold Lion Di Basso Maria Teresa",
    "wof:placetype":"venue"
},
  "geometry": {"coordinates":[11.561045,45.53619],"type":"Point"}
}