{
  "type": "Feature",
  "properties": {
    "iso:country":"IT",
    "sg:address":"4, Via Polati 35027 Noventa Padovana",
    "sg:city":"Noventa Padovana",
    "sg:classifiers":[
        {
            "category":"Personal",
            "subcategory":"Shoe Repair & Shine",
            "type":"Services"
        }
    ],
    "sg:phone":"+39 39049625672",
    "sg:postcode":"35027",
    "sg:province":"Padova",
    "sg:tags":[
        "leather"
    ],
    "wof:name":"Eurosab S.r.l. Societa' Unipersonale",
    "wof:placetype":"venue"
},
  "geometry": {"coordinates":[11.987682,45.410992],"type":"Point"}
}