{
  "type": "Feature",
  "properties": {
    "addr:full":"S.s. 115 Per Vittoria Gela Caltanissetta 93012",
    "addr:postcode":"93012",
    "addr:street":"S.S. 115 Per Vittoria",
    "iso:country":"IT",
    "sg:address":"S.s. 115 Per Vittoria",
    "sg:city":"Gela",
    "sg:classifiers":[
        {
            "category":"Food & Beverages",
            "subcategory":"Groceries & Convenience Stores",
            "type":"Retail Goods"
        }
    ],
    "sg:phone":"+39 0933 917523",
    "sg:postcode":"93012",
    "sg:province":"Caltanissetta",
    "sg:tags":[
        "product",
        "related"
    ],
    "sg:website":"http://www.agroverde.it",
    "wof:name":"Agroverde A Rl Coop. Ortofrutticola",
    "wof:placetype":"venue"
},
  "geometry": {"coordinates":[14.0632896423,37.4899101257],"type":"Point"}
}