{
  "type": "Feature",
  "properties": {
    "addr:full":"Via Nuova San Marzano 14 84010 San Pietro Di Scafati Salerno 84010",
    "addr:housenumber":"14",
    "addr:postcode":"84010;84010",
    "addr:street":"Via Nuova San Marzano",
    "iso:country":"IT",
    "sg:address":"Via Nuova San Marzano 14 84010 San Pietro Di Scafati",
    "sg:orig_category":"Tomatoes, Peeled",
    "sg:phone":"+39 081 859 0515",
    "sg:postcode":"84010",
    "sg:province":"Salerno",
    "sg:website":"www.lareginadisanmarzano.it",
    "wof:name":"La Regina Di San Marzano Di Romano Snc",
    "wof:placetype":"venue"
},
  "geometry": {"coordinates":[14.516899,40.745766],"type":"Point"}
}