{
  "type": "Feature",
  "properties": {
    "iso:country":"IT",
    "sg:address":"28070 Tornaco",
    "sg:city":"Tornaco",
    "sg:orig_category":"Macchine, Impianti E Forniture Per Industria Grafica, Cartaria E Cartotecnica. Prodotti Chimici Secondari",
    "sg:phone":"+39 0321 846305",
    "sg:postcode":"28070",
    "sg:province":"Novara",
    "wof:name":"A.g.m. Srl",
    "wof:placetype":"venue"
},
  "geometry": {"coordinates":[8.730545,45.347641],"type":"Point"}
}