{
  "type": "Feature",
  "properties": {
    "iso:country":"IT",
    "sg:address":"33040 Premariacco",
    "sg:city":"Premariacco",
    "sg:orig_category":"Bagno - Accessori E Mobili",
    "sg:phone":"+39 0432 716288",
    "sg:postcode":"33040",
    "sg:province":"Udine",
    "wof:name":"Fratelli Todone Snc",
    "wof:placetype":"venue"
},
  "geometry": {"coordinates":[13.392321,46.032181],"type":"Point"}
}