{
  "type": "Feature",
  "properties": {
    "iso:country":"IT",
    "sg:address":"20090 Cusago",
    "sg:city":"Cusago",
    "sg:orig_category":"Macchine, Impianti Ed Attrezzature Industria Chimica. Pompe",
    "sg:phone":"+39 02 903581",
    "sg:postcode":"20090",
    "sg:province":"Milano",
    "sg:website":"http://www.flygt.it",
    "wof:name":"Itt Flygt Spa",
    "wof:placetype":"venue"
},
  "geometry": {"coordinates":[9.04367,45.440315],"type":"Point"}
}