{
  "type": "Feature",
  "properties": {
    "iso:country":"IT",
    "sg:address":"42100 Reggio Emilia",
    "sg:classifiers":[
        {
            "category":"Professional",
            "subcategory":"Business Services",
            "type":"Services"
        }
    ],
    "sg:phone":"+39 0522 433027",
    "sg:postcode":"42100",
    "sg:province":"Reggio Nell'Emilia",
    "sg:tags":[
        "support",
        "companies",
        "events",
        "trade"
    ],
    "wof:name":"Kosmos Srl",
    "wof:placetype":"venue"
},
  "geometry": {"coordinates":[10.628998,44.697845],"type":"Point"}
}