{
  "type": "Feature",
  "properties": {
    "iso:country":"IT",
    "sg:address":"80040 Volla",
    "sg:city":"Volla",
    "sg:orig_category":"Banche E Servizi Finanziari",
    "sg:phone":"+39 081 774 8464",
    "sg:postcode":"80040",
    "sg:province":"Napoli",
    "wof:name":"Euro Service",
    "wof:placetype":"venue"
},
  "geometry": {"coordinates":[14.342911,40.878105],"type":"Point"}
}