{
  "type": "Feature",
  "properties": {
    "addr:full":"20038 Seregno Seregno Milano 20038",
    "addr:postcode":"20038;20038",
    "iso:country":"IT",
    "sg:address":"20038 Seregno",
    "sg:city":"Seregno",
    "sg:orig_category":"Parrucche E Toupets",
    "sg:phone":"+39 036 224 0064",
    "sg:postcode":"20038",
    "sg:province":"Milano",
    "wof:name":"San Gregorio Daniele",
    "wof:placetype":"venue"
},
  "geometry": {"coordinates":[9.2035732269,45.6519165039],"type":"Point"}
}