{
  "type": "Feature",
  "properties": {
    "iso:country":"IT",
    "sg:address":"2, Piazzale Dateo 20129 Milano",
    "sg:city":"Milano",
    "sg:classifiers":[
        {
            "category":"Professional",
            "subcategory":"Business Services",
            "type":"Services"
        }
    ],
    "sg:phone":"+39 02 7010 0435",
    "sg:postcode":"20129",
    "sg:province":"Milano",
    "sg:tags":[
        "advice"
    ],
    "wof:name":"M.z.l. Fortune Company Srl",
    "wof:placetype":"venue"
},
  "geometry": {"coordinates":[9.203226,45.482468],"type":"Point"}
}