{
  "type": "Feature",
  "properties": {
    "iso:country":"IT",
    "sg:address":"Via Combattenti E Reduci 6 25070 Bione",
    "sg:city":"Bione",
    "sg:orig_category":"Wooden Garden Furniture",
    "sg:phone":"+39 036 589 6668",
    "sg:postcode":"25070",
    "sg:province":"Brescia",
    "sg:website":"www.arredamentiitalia.net",
    "wof:name":"Arredamenti Italia Group Srl",
    "wof:placetype":"venue"
},
  "geometry": {"coordinates":[10.338049,45.665077],"type":"Point"}
}