{
  "type": "Feature",
  "properties": {
    "iso:country":"IT",
    "sg:address":"17100 Savona",
    "sg:city":"Savona",
    "sg:orig_category":"Petroli, Gas E Combustibili",
    "sg:phone":"+39 019 802001",
    "sg:postcode":"17100",
    "sg:province":"Savona",
    "wof:name":"Societa' Funiviaria Alto Tirreno P.a.",
    "wof:placetype":"venue"
},
  "geometry": {"coordinates":[8.482676506,44.3092880249],"type":"Point"}
}