{
  "type": "Feature",
  "properties": {
    "iso:country":"IT",
    "sg:address":"Via Porpora Nicola 29/8 10155 Torino",
    "sg:city":"Torino",
    "sg:classifiers":[
        {
            "category":"Bars & Pubs",
            "subcategory":"Sports Bar",
            "type":"Food & Drink"
        }
    ],
    "sg:phone":"+39 011 205 0053",
    "sg:postcode":"10155",
    "sg:province":"Torino",
    "sg:tags":[
        "packaging",
        "manufacturing",
        "customized"
    ],
    "wof:name":"Sag Di Biolo A. E Leonardi S. Snc",
    "wof:placetype":"venue"
},
  "geometry": {"coordinates":[7.6866188049,45.0705604553],"type":"Point"}
}