{
  "type": "Feature",
  "properties": {
    "iso:country":"IT",
    "sg:address":"00198 Roma",
    "sg:city":"Roma",
    "sg:orig_category":"Servizi Per Lo Sport E Il Tempo Libero. Servizi Vari Di Interesse Pubblico",
    "sg:phone":"+39 06 855 2113",
    "sg:postcode":"00198",
    "sg:province":"Roma",
    "wof:name":"Agenzia Ippica Iovinelli Snc",
    "wof:placetype":"venue"
},
  "geometry": {"coordinates":[12.379663,42.137684],"type":"Point"}
}