{
  "type": "Feature",
  "properties": {
    "iso:country":"IT",
    "sg:address":"20040 Cambiago",
    "sg:city":"Cambiago",
    "sg:orig_category":"Climatizzazione E Condizionamento, Apparecchiature E Servizi",
    "sg:phone":"+39 02 9530 8391",
    "sg:postcode":"20040",
    "sg:province":"Milano",
    "wof:name":"C.b.i.service (s.r.l.)",
    "wof:placetype":"venue"
},
  "geometry": {"coordinates":[9.434326,45.579643],"type":"Point"}
}