{
  "type": "Feature",
  "properties": {
    "iso:country":"IT",
    "sg:address":"39012 Merano",
    "sg:city":"Merano",
    "sg:orig_category":"Imprese Di Costruzioni Civili Ed Industriali",
    "sg:phone":"+39 0473 247080",
    "sg:postcode":"39012",
    "sg:province":"Bolzano/Bozen",
    "sg:website":"http://www.erdbau.it",
    "wof:name":"Erdbau Srl",
    "wof:placetype":"venue"
},
  "geometry": {"coordinates":[11.184663,46.624752],"type":"Point"}
}