{
  "type": "Feature",
  "properties": {
    "addr:full":"114, Via Ameglia 19021 Arcola Arcola La Spezia 19021",
    "addr:housenumber":"114",
    "addr:postcode":"19021;19021",
    "addr:street":"Via Ameglia",
    "iso:country":"IT",
    "sg:address":"114, Via Ameglia 19021 Arcola",
    "sg:city":"Arcola",
    "sg:classifiers":[
        {
            "category":"Farming",
            "subcategory":"Livestock Farm",
            "type":"Manufacturing & Wholesale Goods"
        }
    ],
    "sg:phone":"+39 0187 988492",
    "sg:postcode":"19021",
    "sg:province":"La Spezia",
    "sg:tags":[
        "agriculture"
    ],
    "wof:name":"Crastan Caffe' (s.r.l.)",
    "wof:placetype":"venue"
},
  "geometry": {"coordinates":[9.939002,44.095531],"type":"Point"}
}