{
  "type": "Feature",
  "properties": {
    "iso:country":"IT",
    "sg:address":"42100 Reggio Emilia",
    "sg:orig_category":"Ospedali E Servizi Sanitari",
    "sg:phone":"+39 0522 307237",
    "sg:postcode":"42100",
    "sg:province":"Reggio Nell'Emilia",
    "wof:name":"Pronta Assistenza Servizi Infermieristici",
    "wof:placetype":"venue"
},
  "geometry": {"coordinates":[10.611371,44.695641],"type":"Point"}
}