{
  "type": "Feature",
  "properties": {
    "iso:country":"IT",
    "sg:address":"Piazza Umberto I 15-16; Padula; 84034",
    "sg:city":"Padula",
    "sg:classifiers":[
        {
            "category":"Banks & Credit Unions",
            "subcategory":"Bank",
            "type":"Services"
        }
    ],
    "sg:phone":"+39 0975 77135",
    "sg:postcode":"84034",
    "sg:province":"Salerno",
    "wof:name":"Banco Di Napoli Spa",
    "wof:placetype":"venue"
},
  "geometry": {"coordinates":[15.65774,40.341667],"type":"Point"}
}