{
  "type": "Feature",
  "properties": {
    "iso:country":"IT",
    "sg:address":"50124 Firenze",
    "sg:city":"Firenze",
    "sg:orig_category":"Articoli Da Regalo. Tempo Libero - Articoli E Forniture. Regalistica Aziendale",
    "sg:phone":"+39 055 222272",
    "sg:postcode":"50124",
    "sg:province":"Firenze",
    "wof:name":"Grand Prix Coppe Di Pelatti Giancarlo",
    "wof:placetype":"venue"
},
  "geometry": {"coordinates":[11.238827,43.766033],"type":"Point"}
}