{
  "type": "Feature",
  "properties": {
    "addr:full":"90146 Palermo Palermo Palermo 90146",
    "addr:postcode":"90146;90146",
    "iso:country":"IT",
    "sg:address":"90146 Palermo",
    "sg:city":"Palermo",
    "sg:orig_category":"Servizi Per Lo Sport E Il Tempo Libero. Servizi Al Turismo. Acqua, Luce, Gas E Societa' Di Esercizio Pubblico",
    "sg:phone":"+39 091 671 6066",
    "sg:postcode":"90146",
    "sg:province":"Palermo",
    "wof:name":"Rangers D'italia Ente",
    "wof:placetype":"venue"
},
  "geometry": {"coordinates":[13.342687,38.158493],"type":"Point"}
}