{
  "type": "Feature",
  "properties": {
    "addr:full":"11, Via Eurialo 91100 Trapani Trapani Trapani 91100",
    "addr:postcode":"91100;91100",
    "addr:street":"Via Eurialo",
    "iso:country":"IT",
    "sg:address":"11, Via Eurialo 91100 Trapani",
    "sg:city":"Trapani",
    "sg:classifiers":[
        {
            "category":"Marine",
            "type":"Transportation"
        }
    ],
    "sg:phone":"+39 39092321655",
    "sg:postcode":"91100",
    "sg:province":"Trapani",
    "sg:tags":[
        "transport",
        "sea"
    ],
    "wof:name":"Sanges Riccardo & C. S.r.l.",
    "wof:placetype":"venue"
},
  "geometry": {"coordinates":[12.521556,38.015053],"type":"Point"}
}