{
  "type": "Feature",
  "properties": {
    "iso:country":"IT",
    "sg:address":"20052 Monza",
    "sg:city":"Monza",
    "sg:orig_category":"Nautica. Accessori Dei Mezzi Di Trasporto",
    "sg:phone":"+39 039 231 0685",
    "sg:postcode":"20052",
    "sg:province":"Milano",
    "sg:website":"http://www.rossmanif.it",
    "wof:name":"Manifatture C. Rossini & C. Srl",
    "wof:placetype":"venue"
},
  "geometry": {"coordinates":[9.029795,45.525597],"type":"Point"}
}