{
  "type": "Feature",
  "properties": {
    "iso:country":"IT",
    "sg:address":"15061 Arquata Scrivia",
    "sg:city":"Arquata Scrivia",
    "sg:orig_category":"Hobbistica",
    "sg:phone":"+39 0143 666236",
    "sg:postcode":"15061",
    "sg:province":"Alessandria",
    "wof:name":"Il Mercato Dell'usato S.r.l.",
    "wof:placetype":"venue"
},
  "geometry": {"coordinates":[8.869581,44.694172],"type":"Point"}
}