{
  "type": "Feature",
  "properties": {
    "iso:country":"IT",
    "sg:address":"29010 Gragnano Trebbiense",
    "sg:city":"Gragnano Trebbiense",
    "sg:orig_category":"Carpenterie Ferro",
    "sg:phone":"+39 0523 788768",
    "sg:postcode":"29010",
    "sg:province":"Piacenza",
    "wof:name":"Carpe D.i.e.m. Snc Di G. Ferrari & S. Morandi",
    "wof:placetype":"venue"
},
  "geometry": {"coordinates":[10.009874,45.017605],"type":"Point"}
}