{
  "type": "Feature",
  "properties": {
    "addr:full":"19020 Vezzano Ligure Valeriano La Spezia 19020",
    "addr:postcode":"19020;19020",
    "iso:country":"IT",
    "sg:address":"19020 Vezzano Ligure",
    "sg:city":"Valeriano",
    "sg:orig_category":"Carni, Salumi E Pesci. Zootecnia E Pesca, Allevamento Piccoli Animali",
    "sg:phone":"+39 0187 515466",
    "sg:postcode":"19020",
    "sg:province":"La Spezia",
    "sg:website":"http://www.majesticfood.com",
    "wof:name":"Majestic Food Di Papini Paolo",
    "wof:placetype":"venue"
},
  "geometry": {"coordinates":[9.8539857864,44.1387786865],"type":"Point"}
}