{
  "type": "Feature",
  "properties": {
    "addr:full":"63018 Porto S. Elpidio Ascoli Piceno 63018",
    "addr:housenumber":"63018",
    "addr:postcode":"63018",
    "addr:street":"Porto S. Elpidio;Piceno",
    "iso:country":"IT",
    "sg:address":"63018 Porto S. Elpidio",
    "sg:orig_category":"Forniture Per Abbigliamento E Pelletterie. Forniture Per Attivita' Commerciali Ed Artigianali",
    "sg:phone":"+39 0734 991034",
    "sg:postcode":"63018",
    "sg:province":"Ascoli Piceno",
    "wof:name":"Solettificio Monica Di Marziali Ezio",
    "wof:placetype":"venue"
},
  "geometry": {"coordinates":[13.5749769211,42.8554000854],"type":"Point"}
}