{
  "type": "Feature",
  "properties": {
    "iso:country":"IT",
    "sg:address":"40132 Bologna",
    "sg:city":"Bologna",
    "sg:orig_category":"Prodotti Chimici Di Base",
    "sg:phone":"+39 051 400086",
    "sg:postcode":"40132",
    "sg:province":"Bologna",
    "wof:name":"Joint (s.r.l.)",
    "wof:placetype":"venue"
},
  "geometry": {"coordinates":[11.2517776489,44.5357818604],"type":"Point"}
}