{
  "type": "Feature",
  "properties": {
    "iso:country":"IT",
    "sg:address":"36030 Villaverla",
    "sg:city":"Villaverla",
    "sg:orig_category":"Stirerie - Macchine",
    "sg:phone":"+39 0445 855007",
    "sg:postcode":"36030",
    "sg:province":"Vicenza",
    "sg:website":"http://www.cometh.com",
    "wof:name":"Cometh Srl",
    "wof:placetype":"venue"
},
  "geometry": {"coordinates":[11.506622,45.61166],"type":"Point"}
}