{
  "type": "Feature",
  "properties": {
    "addr:full":"65126 Pescara Pescara Pescara 65126",
    "addr:postcode":"65126;65126",
    "iso:country":"IT",
    "sg:address":"65126 Pescara",
    "sg:city":"Pescara",
    "sg:orig_category":"Cinematografia E Radiotelevisione. Servizi Per Aziende, Manifestazioni E Supporto Agli Scambi Commerciali",
    "sg:phone":"+39 085 451 4637",
    "sg:postcode":"65126",
    "sg:province":"Pescara",
    "sg:website":"http://www.cdaudiovideo.com",
    "wof:name":"Cd Audio Video Di D'attanasio Carlo",
    "wof:placetype":"venue"
},
  "geometry": {"coordinates":[14.22482,42.45879],"type":"Point"}
}