{
  "type": "Feature",
  "properties": {
    "iso:country":"IT",
    "sg:address":"70033 Corato",
    "sg:city":"Corato",
    "sg:classifiers":[
        {
            "category":"Shopping",
            "subcategory":"Crafts & Fabrics",
            "type":"Retail Goods"
        }
    ],
    "sg:phone":"+39 080 872 4570",
    "sg:postcode":"70033",
    "sg:province":"Bari",
    "sg:tags":[
        "art",
        "gifts",
        "finished",
        "products",
        "printed",
        "crafts",
        "artistic"
    ],
    "wof:name":"Graziani Arti Grafiche Srl",
    "wof:placetype":"venue"
},
  "geometry": {"coordinates":[16.3699264526,41.0785446167],"type":"Point"}
}