{
  "type": "Feature",
  "properties": {
    "iso:country":"IT",
    "sg:address":"40055 Bologna",
    "sg:city":"Castenaso",
    "sg:orig_category":"Servizi E Lavori Per Arredamento E Industria Del Legno",
    "sg:phone":"+39 051 780656",
    "sg:postcode":"40055",
    "sg:province":"Bologna",
    "wof:name":"Fini & Rovetto Snc",
    "wof:placetype":"venue"
},
  "geometry": {"coordinates":[11.469176,44.509064],"type":"Point"}
}