{
  "type": "Feature",
  "properties": {
    "iso:country":"IT",
    "sg:address":"20082 Binasco",
    "sg:city":"Binasco",
    "sg:orig_category":"Cinematografia E Radiotelevisione. Pubblicita', Marketing E Comunicazione. Acqua, Luce, Gas E Societa' Di Esercizio Pubblico",
    "sg:phone":"+39 02 905 5773",
    "sg:postcode":"20082",
    "sg:province":"Milano",
    "wof:name":"Radio Hinterland Binasco",
    "wof:placetype":"venue"
},
  "geometry": {"coordinates":[9.056317,45.488686],"type":"Point"}
}