{
  "type": "Feature",
  "properties": {
    "addr:full":"13100 Vercelli Vercelli Vercelli 13100",
    "addr:postcode":"13100;13100",
    "iso:country":"IT",
    "sg:address":"13100 Vercelli",
    "sg:city":"Vercelli",
    "sg:orig_category":"Prodotti Alimentari. Agricoltura, Orticoltura E Floricoltura",
    "sg:postcode":"13100",
    "sg:province":"Vercelli",
    "wof:name":"Tenuta Castello",
    "wof:placetype":"venue"
},
  "geometry": {"coordinates":[8.4263935089,45.3210601807],"type":"Point"}
}