{
  "type": "Feature",
  "properties": {
    "iso:country":"IT",
    "sg:address":"93100 Caltanissetta",
    "sg:city":"Caltanissetta",
    "sg:orig_category":"Campeggio. Automobili E Mezzi Di Trasporto",
    "sg:phone":"+39 0934 575533",
    "sg:postcode":"93100",
    "sg:province":"Caltanissetta",
    "wof:name":"Ita Sud Srl",
    "wof:placetype":"venue"
},
  "geometry": {"coordinates":[14.055708,37.468143],"type":"Point"}
}