{
  "type": "Feature",
  "properties": {
    "addr:full":"16151 Genova Genova Genova 16151",
    "addr:housenumber":"16151",
    "addr:postcode":"16151",
    "iso:country":"IT",
    "sg:address":"16151 Genova",
    "sg:city":"Genova",
    "sg:orig_category":"Trasporti E Spedizioni Merci",
    "sg:phone":"+39 010 411526",
    "sg:postcode":"16151",
    "sg:province":"Genova",
    "wof:name":"Ligurtrans (s.r.l.)",
    "wof:placetype":"venue"
},
  "geometry": {"coordinates":[8.886828,44.413834],"type":"Point"}
}