{
  "type": "Feature",
  "properties": {
    "addr:full":"40126 Bologna Bologna Bologna 40126",
    "addr:postcode":"40126;40126",
    "iso:country":"IT",
    "sg:address":"40126 Bologna",
    "sg:city":"Bologna",
    "sg:orig_category":"Pubblica Amministrazione",
    "sg:phone":"+39 051 221892",
    "sg:postcode":"40126",
    "sg:province":"Bologna",
    "wof:name":"Forze Armate/esercito/distretto Militare Circolo Ufficiali Di Presidio",
    "wof:placetype":"venue"
},
  "geometry": {"coordinates":[11.3453979492,44.4973526001],"type":"Point"}
}