{
  "type": "Feature",
  "properties": {
    "addr:full":"42100 Reggio Emilia Reggio Nell'Emilia 42100",
    "addr:postcode":"42100;42100",
    "iso:country":"IT",
    "sg:address":"42100 Reggio Emilia",
    "sg:orig_category":"Acciaierie E Fonderie",
    "sg:phone":"+39 0522 554211",
    "sg:postcode":"42100",
    "sg:province":"Reggio Nell'Emilia",
    "wof:name":"Fonderia Vierre (s.n.c.)",
    "wof:placetype":"venue"
},
  "geometry": {"coordinates":[10.632545,44.678089],"type":"Point"}
}