{
  "type": "Feature",
  "properties": {
    "iso:country":"IT",
    "sg:address":"20019 Settimo Milanese",
    "sg:city":"Settimo Milanese",
    "sg:orig_category":"Macchine, Impianti E Forniture Per Industria Grafica, Cartaria E Cartotecnica",
    "sg:phone":"+39 02 328 8121",
    "sg:postcode":"20019",
    "sg:province":"Milano",
    "wof:name":"Printgraph Di Elia Levi Acobas & C. Sas",
    "wof:placetype":"venue"
},
  "geometry": {"coordinates":[9.067109,45.47826],"type":"Point"}
}