{
  "type": "Feature",
  "properties": {
    "iso:country":"IT",
    "sg:address":"Corso Sempione; Legnano; 20025",
    "sg:city":"Legnano",
    "sg:classifiers":[
        {
            "category":"Banks & Credit Unions",
            "subcategory":"Bank",
            "type":"Services"
        }
    ],
    "sg:phone":"+39 0331 542541",
    "sg:postcode":"20025",
    "sg:province":"Milano",
    "wof:name":"Credito Varesino",
    "wof:placetype":"venue"
},
  "geometry": {"coordinates":[8.920686,45.598068],"type":"Point"}
}