{
  "type": "Feature",
  "properties": {
    "iso:country":"IT",
    "sg:address":"10, Via Fonda 31044 Montebelluna",
    "sg:city":"Montebelluna",
    "sg:classifiers":[
        {
            "category":"Personal",
            "subcategory":"Shoe Repair & Shine",
            "type":"Services"
        }
    ],
    "sg:phone":"+39 0423 601836",
    "sg:postcode":"31044",
    "sg:province":"Treviso",
    "sg:tags":[
        "leather"
    ],
    "wof:name":"Doppio Ci Di Caeran Claudio",
    "wof:placetype":"venue"
},
  "geometry": {"coordinates":[12.063205,45.769497],"type":"Point"}
}