{
  "type": "Feature",
  "properties": {
    "iso:country":"IT",
    "sg:address":"92027 Licata",
    "sg:city":"Licata",
    "sg:orig_category":"Agenti D'affari In Mediazione",
    "sg:phone":"+39 0922 772181",
    "sg:postcode":"92027",
    "sg:province":"Agrigento",
    "wof:name":"Immobiliare Holidays Di Salvatore Incorvaia",
    "wof:placetype":"venue"
},
  "geometry": {"coordinates":[13.941431,37.103691],"type":"Point"}
}