{
  "type": "Feature",
  "properties": {
    "iso:country":"IT",
    "sg:address":"17100 Savona",
    "sg:city":"Savona",
    "sg:orig_category":"Servizi Ausiliari Per Il Trasporto. Agenzie D'affari E Servizi Commerciali",
    "sg:phone":"+39 019 840 1494",
    "sg:postcode":"17100",
    "sg:province":"Savona",
    "wof:name":"Ligurnavi",
    "wof:placetype":"venue"
},
  "geometry": {"coordinates":[8.487767,44.308308],"type":"Point"}
}