{
  "type": "Feature",
  "properties": {
    "addr:full":"35013 Cittadella Cittadella Padova 35013",
    "addr:postcode":"35013;35013",
    "iso:country":"IT",
    "sg:address":"35013 Cittadella",
    "sg:city":"Cittadella",
    "sg:orig_category":"Falegnami",
    "sg:phone":"+39 049 597 3271",
    "sg:postcode":"35013",
    "sg:province":"Padova",
    "wof:name":"Casaplus Sas Di Simioni Flavio & C.",
    "wof:placetype":"venue"
},
  "geometry": {"coordinates":[11.7872285843,45.6394882202],"type":"Point"}
}