{
  "type": "Feature",
  "properties": {
    "addr:full":"39052 Caldaro Strada Vino Bolzano/Bozen 39052",
    "addr:postcode":"39052;39052",
    "addr:street":"Strada Vino",
    "iso:country":"IT",
    "sg:address":"39052 Caldaro Strada Vino",
    "sg:classifiers":[
        {
            "category":"Home & Garden",
            "subcategory":"Building Materials",
            "type":"Retail Goods"
        }
    ],
    "sg:phone":"+39 0471 962510",
    "sg:postcode":"39052",
    "sg:province":"Bolzano/Bozen",
    "sg:tags":[
        "window",
        "door",
        "frame"
    ],
    "wof:name":"Mortec Snc",
    "wof:placetype":"venue"
},
  "geometry": {"coordinates":[11.326762,46.433266],"type":"Point"}
}