{
  "type": "Feature",
  "properties": {
    "iso:country":"IT",
    "sg:address":"24060 Bolgare",
    "sg:city":"Bolgare",
    "sg:orig_category":"Materie Plastiche In Granuli, Polveri E Pasta",
    "sg:phone":"+39 035 442 3467",
    "sg:postcode":"24060",
    "sg:province":"Bergamo",
    "wof:name":"Brevi Plast Srl",
    "wof:placetype":"venue"
},
  "geometry": {"coordinates":[9.84737,45.638462],"type":"Point"}
}