{
  "type": "Feature",
  "properties": {
    "iso:country":"IT",
    "sg:address":"15, Via Del Proconsolo 50122 Firenze",
    "sg:city":"Firenze",
    "sg:classifiers":[
        {
            "category":"Banks & Credit Unions",
            "subcategory":"Financial Services",
            "type":"Services"
        }
    ],
    "sg:phone":"+39 055 239 9449",
    "sg:postcode":"50122",
    "sg:province":"Firenze",
    "sg:tags":[
        "banking",
        "finance",
        "insurance"
    ],
    "wof:name":"Assicurazioni Lloyd Insurance Brokers (s.r.l.)",
    "wof:placetype":"venue"
},
  "geometry": {"coordinates":[11.257996,43.771885],"type":"Point"}
}