{
  "type": "Feature",
  "properties": {
    "iso:country":"IT",
    "sg:address":"27010 Miradolo Terme",
    "sg:city":"Miradolo Terme",
    "sg:orig_category":"Dolciumi E Gelati",
    "sg:phone":"+39 0382 75211",
    "sg:postcode":"27010",
    "sg:province":"Pavia",
    "wof:name":"Grand Hotel Milano",
    "wof:placetype":"venue"
},
  "geometry": {"coordinates":[9.446703,45.172035],"type":"Point"}
}