{
  "type": "Feature",
  "properties": {
    "addr:full":"Loc. Z.i. Loreto, Sn 60025 Loreto Loreto Ancona 60025",
    "addr:housenumber":"sn",
    "addr:postcode":"60025;60025",
    "addr:street":"Loc. Z.I. Loreto",
    "iso:country":"IT",
    "sg:address":"Loc. Z.i. Loreto, Sn 60025 Loreto",
    "sg:city":"Loreto",
    "sg:classifiers":[
        {
            "category":"Place Of Worship",
            "subcategory":"Church",
            "type":"Public Place"
        }
    ],
    "sg:phone":"+39 071 970636",
    "sg:postcode":"60025",
    "sg:province":"Ancona",
    "sg:tags":[
        "equipment"
    ],
    "sg:website":"www.asalinea.it",
    "wof:name":"A.s.a. Linea Srl",
    "wof:placetype":"venue"
},
  "geometry": {"coordinates":[13.518757,43.615856],"type":"Point"}
}