{
  "type": "Feature",
  "properties": {
    "iso:country":"IT",
    "sg:address":"20131 Milano",
    "sg:city":"Milano",
    "sg:orig_category":"Servizi Ausiliari Dei Mezzi Di Trasporto",
    "sg:phone":"+39 02 289 4707",
    "sg:postcode":"20131",
    "sg:province":"Milano",
    "wof:name":"Rinaldi Vincenzo",
    "wof:placetype":"venue"
},
  "geometry": {"coordinates":[9.22579,45.491199],"type":"Point"}
}