{
  "type": "Feature",
  "properties": {
    "iso:country":"IT",
    "sg:address":"41100 Modena",
    "sg:city":"Modena",
    "sg:orig_category":"Elaboratori Elettronici - Periferiche",
    "sg:phone":"+39 059 314914",
    "sg:postcode":"41100",
    "sg:province":"Modena",
    "sg:website":"http://www.zerox.it",
    "wof:name":"Zerosystem",
    "wof:placetype":"venue"
},
  "geometry": {"coordinates":[10.914429,44.663944],"type":"Point"}
}