{
  "type": "Feature",
  "properties": {
    "addr:full":"95034 Bronte Bronte Catania 95034",
    "addr:postcode":"95034;95034",
    "iso:country":"IT",
    "sg:address":"95034 Bronte",
    "sg:city":"Bronte",
    "sg:orig_category":"Abbigliamento Esterno, Maglierie E Pelliccerie",
    "sg:phone":"+39 095 772 2131",
    "sg:postcode":"95034",
    "sg:province":"Catania",
    "wof:name":"Top Jeans Di Avellina Maurizio",
    "wof:placetype":"venue"
},
  "geometry": {"coordinates":[14.824039,37.796425],"type":"Point"}
}