{
  "type": "Feature",
  "properties": {
    "iso:country":"IT",
    "sg:address":"10073 Cirie'",
    "sg:orig_category":"Copisterie",
    "sg:phone":"+39 011 920 9658",
    "sg:postcode":"10073",
    "sg:province":"Torino",
    "sg:website":"http://www.latecnigraf.it",
    "wof:name":"La Tecnigraf",
    "wof:placetype":"venue"
},
  "geometry": {"coordinates":[7.650805,45.060059],"type":"Point"}
}