{
  "type": "Feature",
  "properties": {
    "addr:full":"50058 Signa Signa Firenze 50058",
    "addr:postcode":"50058;50058",
    "iso:country":"IT",
    "sg:address":"50058 Signa",
    "sg:city":"Signa",
    "sg:orig_category":"Filati E Materie Prime Tessili",
    "sg:phone":"+39 055 873 5663",
    "sg:postcode":"50058",
    "sg:province":"Firenze",
    "wof:name":"Manzini Roberto Si Tagliabue Rosita Sas",
    "wof:placetype":"venue"
},
  "geometry": {"coordinates":[11.1338062286,43.8228759766],"type":"Point"}
}