{
  "type": "Feature",
  "properties": {
    "iso:country":"IT",
    "sg:address":"Via Montegrappa 26 41040 Ubersetto",
    "sg:classifiers":[
        {
            "category":"Real Estate",
            "subcategory":"Real Estate Services",
            "type":"Services"
        }
    ],
    "sg:phone":"+39 0536 843826",
    "sg:postcode":"41040",
    "sg:province":"Modena",
    "sg:tags":[
        "pharmaceutical",
        "material",
        "raw"
    ],
    "sg:website":"www.modenplast.com",
    "wof:name":"Modenplast Medical Srl",
    "wof:placetype":"venue"
},
  "geometry": {"coordinates":[10.8657464981,44.5256462097],"type":"Point"}
}