{
  "type": "Feature",
  "properties": {
    "iso:country":"IT",
    "sg:address":"19, Via Airuno 23883 Brivio",
    "sg:city":"Brivio",
    "sg:classifiers":[
        {
            "category":"Manufacturing",
            "subcategory":"Rubber & Plastics",
            "type":"Manufacturing & Wholesale Goods"
        }
    ],
    "sg:phone":"+39 039 532 1487",
    "sg:postcode":"23883",
    "sg:province":"Lecco",
    "wof:name":"2.s. S.r.l.",
    "wof:placetype":"venue"
},
  "geometry": {"coordinates":[9.440120697,45.7492790222],"type":"Point"}
}