{
  "type": "Feature",
  "properties": {
    "iso:country":"IT",
    "sg:address":"61100 Pesaro",
    "sg:city":"Pesaro",
    "sg:orig_category":"Macchine, Impianti E Forniture Per Industria Grafica, Cartaria E Cartotecnica",
    "sg:phone":"+39 0721 281380",
    "sg:postcode":"61100",
    "sg:province":"Pesaro E Urbino",
    "wof:name":"Co.m.s.s. Di Aiudi Antonio & C. Snc",
    "wof:placetype":"venue"
},
  "geometry": {"coordinates":[12.856481,43.881321],"type":"Point"}
}