{
  "type": "Feature",
  "properties": {
    "addr:full":"6, Via Ferri Enrico 20092 Cinisello Balsamo Cinisello Balsamo Milano 20092",
    "addr:postcode":"20092;20092",
    "addr:street":"Via Ferri Enrico",
    "iso:country":"IT",
    "sg:address":"6, Via Ferri Enrico 20092 Cinisello Balsamo",
    "sg:city":"Cinisello Balsamo",
    "sg:classifiers":[
        {
            "category":"Manufacturing",
            "subcategory":"Printing",
            "type":"Manufacturing & Wholesale Goods"
        }
    ],
    "sg:phone":"+39 390 266 0251",
    "sg:postcode":"20092",
    "sg:province":"Milano",
    "sg:tags":[
        "publishing"
    ],
    "wof:name":"Gruppo Editoriale Jce (s.r.l.)",
    "wof:placetype":"venue"
},
  "geometry": {"coordinates":[9.2189006805,45.5438079834],"type":"Point"}
}