{
  "type": "Feature",
  "properties": {
    "iso:country":"IT",
    "sg:address":"34139 Trieste",
    "sg:city":"Trieste",
    "sg:orig_category":"Clothing, Accessories",
    "sg:phone":"+39 040 390770",
    "sg:postcode":"34139",
    "sg:province":"Trieste",
    "wof:name":"Miramare Srl",
    "wof:placetype":"venue"
},
  "geometry": {"coordinates":[13.795337,45.642239],"type":"Point"}
}