{
  "type": "Feature",
  "properties": {
    "iso:country":"IT",
    "sg:address":"00198 Roma",
    "sg:city":"Roma",
    "sg:classifiers":[
        {
            "category":"Social Services",
            "subcategory":"Job Training",
            "type":"Services"
        }
    ],
    "sg:phone":"+39 06 855 7078",
    "sg:postcode":"00198",
    "sg:province":"Roma",
    "sg:tags":[
        "services",
        "personnel",
        "school",
        "educational",
        "recruitment"
    ],
    "sg:website":"http://www.istitutoquasar.com",
    "wof:name":"Istituto Quasar",
    "wof:placetype":"venue"
},
  "geometry": {"coordinates":[12.503621,41.914032],"type":"Point"}
}