{
  "type": "Feature",
  "properties": {
    "iso:country":"IT",
    "sg:address":"13, Via Mattei Enrico 20017 Rho",
    "sg:city":"Rho",
    "sg:orig_category":"Miscellaneous Products",
    "sg:phone":"+39 390 293 2651",
    "sg:postcode":"20017",
    "sg:province":"Milano",
    "wof:name":"Costruzioni Meccaniche Rho Spa",
    "wof:placetype":"venue"
},
  "geometry": {"coordinates":[9.023686409,45.5284309387],"type":"Point"}
}