{
  "type": "Feature",
  "properties": {
    "iso:country":"IT",
    "sg:address":"16145 Genova",
    "sg:city":"Genova",
    "sg:orig_category":"Impiantistica E Prodotti Tecnologici Per Edilizia. Elettronica Professionale E Di Consumo",
    "sg:phone":"+39 010 362 6602",
    "sg:postcode":"16145",
    "sg:province":"Genova",
    "wof:name":"C.r. Electronic Systems",
    "wof:placetype":"venue"
},
  "geometry": {"coordinates":[8.960418,44.39814],"type":"Point"}
}