{
  "type": "Feature",
  "properties": {
    "addr:full":"93012 Gela Gela Caltanissetta 93012",
    "addr:postcode":"93012;93012",
    "iso:country":"IT",
    "sg:address":"93012 Gela",
    "sg:city":"Gela",
    "sg:orig_category":"Studi E Consulenze Amministrative, Commerciali E Aziendali. Consulenze Tecniche, Amministrative E Perizie. Professionisti - Studi E Servizi Ed Associazioni Di Interesse Aziendale",
    "sg:phone":"+39 0933 927504",
    "sg:postcode":"93012",
    "sg:province":"Caltanissetta",
    "wof:name":"Licata Maria Grazia",
    "wof:placetype":"venue"
},
  "geometry": {"coordinates":[13.986057,37.481106],"type":"Point"}
}