{
  "type": "Feature",
  "properties": {
    "iso:country":"IT",
    "sg:address":"Strada Novi Reg. Lercaro 15076 Ovada",
    "sg:city":"Ovada",
    "sg:classifiers":[
        {
            "category":"Shopping",
            "subcategory":"Stationery & Office Supplies",
            "type":"Retail Goods"
        }
    ],
    "sg:phone":"+39 39014386437",
    "sg:postcode":"15076",
    "sg:province":"Alessandria",
    "sg:tags":[
        "professional"
    ],
    "wof:name":"Zenith Srl",
    "wof:placetype":"venue"
},
  "geometry": {"coordinates":[8.6169509888,44.9132156372],"type":"Point"}
}