{
  "type": "Feature",
  "properties": {
    "iso:country":"IT",
    "sg:address":"90139 Palermo",
    "sg:city":"Palermo",
    "sg:orig_category":"Automobili E Mezzi Di Trasporto. Riparazione Dei Mezzi Di Trasporto",
    "sg:phone":"+39 091 325434",
    "sg:postcode":"90139",
    "sg:province":"Palermo",
    "sg:website":"http://www.motoesse.it",
    "wof:name":"Motoesse Snc Di Scaglione S.re & C.",
    "wof:placetype":"venue"
},
  "geometry": {"coordinates":[13.248241,38.185276],"type":"Point"}
}