{
  "type": "Feature",
  "properties": {
    "iso:country":"IT",
    "sg:address":"00184 Roma",
    "sg:city":"Roma",
    "sg:orig_category":"Servizi E Lavori Per Agricoltura E Zootecnia. Consulenze Tecniche, Amministrative E Perizie",
    "sg:phone":"+39 06 488 3383",
    "sg:postcode":"00184",
    "sg:province":"Roma",
    "wof:name":"Angle Giordano",
    "wof:placetype":"venue"
},
  "geometry": {"coordinates":[12.498258,41.889187],"type":"Point"}
}