{
  "type": "Feature",
  "properties": {
    "addr:full":"2, Via Alessandro Volta 35010 Limena Limena Padova 35010",
    "addr:postcode":"35010;35010",
    "addr:street":"Via Alessandro Volta",
    "iso:country":"IT",
    "sg:address":"2, Via Alessandro Volta 35010 Limena",
    "sg:city":"Limena",
    "sg:classifiers":[
        {
            "category":"Personal",
            "subcategory":"Shoe Repair & Shine",
            "type":"Services"
        }
    ],
    "sg:phone":"+39 049 899 1111",
    "sg:postcode":"35010",
    "sg:province":"Padova",
    "sg:tags":[
        "leather"
    ],
    "wof:name":"Compar S.p.a.",
    "wof:placetype":"venue"
},
  "geometry": {"coordinates":[11.8535442352,45.4655838013],"type":"Point"}
}