{
  "type": "Feature",
  "properties": {
    "addr:full":"10128 Torino Torino Torino 10128",
    "addr:postcode":"10128;10128",
    "iso:country":"IT",
    "sg:address":"10128 Torino",
    "sg:city":"Torino",
    "sg:orig_category":"Attrezzature E Forniture Per Officine Riparazione E Servizi Ausiliari",
    "sg:phone":"+39 011 580 4717",
    "sg:postcode":"10128",
    "sg:province":"Torino",
    "wof:name":"Gomme Sul Ponte",
    "wof:placetype":"venue"
},
  "geometry": {"coordinates":[7.670135,45.058353],"type":"Point"}
}