{
  "type": "Feature",
  "properties": {
    "iso:country":"IT",
    "sg:address":"00185 Roma",
    "sg:city":"Roma",
    "sg:orig_category":"Calzature, Pelletterie E Pelli. Shopping",
    "sg:phone":"+39 06 7049 7916",
    "sg:postcode":"00185",
    "sg:province":"Roma",
    "wof:name":"Celentano Maria",
    "wof:placetype":"venue"
},
  "geometry": {"coordinates":[12.462966,41.85598],"type":"Point"}
}