{
  "type": "Feature",
  "properties": {
    "addr:full":"13/a, Via Zocco 25030 Adro Adro Brescia 25030",
    "addr:housenumber":"13 / a",
    "addr:postcode":"25030;25030",
    "addr:street":"Via Zocco",
    "iso:country":"IT",
    "sg:address":"13/a, Via Zocco 25030 Adro",
    "sg:city":"Adro",
    "sg:classifiers":[
        {
            "category":"Shopping",
            "subcategory":"Stationery & Office Supplies",
            "type":"Retail Goods"
        }
    ],
    "sg:phone":"+39 030 745 0481",
    "sg:postcode":"25030",
    "sg:province":"Brescia",
    "sg:tags":[
        "professional"
    ],
    "wof:name":"Comosca (s.r.l.)",
    "wof:placetype":"venue"
},
  "geometry": {"coordinates":[9.9555225372,45.5997314453],"type":"Point"}
}