{
  "type": "Feature",
  "properties": {
    "addr:full":"61033 Fermignano Fermignano Pesaro E Urbino 61033",
    "addr:postcode":"61033;61033",
    "iso:country":"IT",
    "sg:address":"61033 Fermignano",
    "sg:city":"Fermignano",
    "sg:orig_category":"Medicinali E Prodotti Parafarmaceutici",
    "sg:phone":"+39 0722 332782",
    "sg:postcode":"61033",
    "sg:province":"Pesaro E Urbino",
    "wof:name":"Gejma Sas",
    "wof:placetype":"venue"
},
  "geometry": {"coordinates":[12.5298032761,43.633556366],"type":"Point"}
}