{
  "type": "Feature",
  "properties": {
    "addr:full":"20149 Milano Milano Milano 20149",
    "addr:postcode":"20149;20149",
    "iso:country":"IT",
    "sg:address":"20149 Milano",
    "sg:city":"Milano",
    "sg:orig_category":"Pubblicita', Marketing E Comunicazione",
    "sg:phone":"+39 02 438091",
    "sg:postcode":"20149",
    "sg:province":"Milano",
    "sg:website":"http://www.eurisko.it",
    "wof:name":"Eurisko Spa",
    "wof:placetype":"venue"
},
  "geometry": {"coordinates":[9.148733139,45.4731674194],"type":"Point"}
}