{
  "type": "Feature",
  "properties": {
    "iso:country":"IT",
    "sg:address":"Via Carducci, 10; Carovigno; 72012",
    "sg:city":"Carovigno",
    "sg:classifiers":[
        {
            "category":"Banks & Credit Unions",
            "subcategory":"Bank",
            "type":"Services"
        }
    ],
    "sg:phone":"+39 0831 991018",
    "sg:postcode":"72012",
    "sg:province":"Brindisi",
    "wof:name":"Banca Popolare Di Bari",
    "wof:placetype":"venue"
},
  "geometry": {"coordinates":[17.660069,40.705238],"type":"Point"}
}