{
  "type": "Feature",
  "properties": {
    "iso:country":"IT",
    "sg:address":"80022 Arzano",
    "sg:city":"Arzano",
    "sg:orig_category":"Prodotti Finiti Stampati. Forniture E Materiali Per Imballaggio E Confezionamento. Forniture Per Attivita' Commerciali Ed Artigianali",
    "sg:phone":"+39 081 731 7266",
    "sg:postcode":"80022",
    "sg:province":"Napoli",
    "wof:name":"Cartotecnica Partenopea",
    "wof:placetype":"venue"
},
  "geometry": {"coordinates":[14.2655630112,40.905834198],"type":"Point"}
}