{
  "type": "Feature",
  "properties": {
    "iso:country":"IT",
    "sg:address":"72100 Brindisi",
    "sg:city":"Brindisi",
    "sg:orig_category":"Articoli Medico-sanitari Ed Ortopedici",
    "sg:phone":"+39 0831 521339",
    "sg:postcode":"72100",
    "sg:province":"Brindisi",
    "wof:name":"Tarantino Fabiola",
    "wof:placetype":"venue"
},
  "geometry": {"coordinates":[17.943113,40.633781],"type":"Point"}
}