{
  "type": "Feature",
  "properties": {
    "addr:full":"Corso Vittorio; Caltavuturo; 90022 Caltavuturo Palermo 90022",
    "addr:postcode":"90022;90022",
    "addr:street":"Corso Vittorio Caltavuturo",
    "iso:country":"IT",
    "sg:address":"Corso Vittorio; Caltavuturo; 90022",
    "sg:city":"Caltavuturo",
    "sg:classifiers":[
        {
            "category":"Banks & Credit Unions",
            "subcategory":"Bank",
            "type":"Services"
        }
    ],
    "sg:phone":"+39 0921 541013",
    "sg:postcode":"90022",
    "sg:province":"Palermo",
    "wof:name":"Banco Di Sicilia Spa",
    "wof:placetype":"venue"
},
  "geometry": {"coordinates":[13.889425,37.821789],"type":"Point"}
}