{
  "type": "Feature",
  "properties": {
    "addr:full":"50, Via Roma 46040 Casalromano Casalromano Mantova 46040",
    "addr:postcode":"46040;46040",
    "addr:street":"Via Roma",
    "iso:country":"IT",
    "sg:address":"50, Via Roma 46040 Casalromano",
    "sg:city":"Casalromano",
    "sg:classifiers":[
        {
            "category":"Wholesale",
            "subcategory":"Drugs",
            "type":"Manufacturing & Wholesale Goods"
        }
    ],
    "sg:phone":"+39 39037676217",
    "sg:postcode":"46040",
    "sg:province":"Mantova",
    "sg:tags":[
        "chemical",
        "pharmaceutical"
    ],
    "wof:name":"Polychem Systems (s.r.l.)",
    "wof:placetype":"venue"
},
  "geometry": {"coordinates":[10.368546,45.195583],"type":"Point"}
}