{
  "type": "Feature",
  "properties": {
    "iso:country":"IT",
    "sg:address":"Loc Itiani Zona Industriale 05021 Acquasparta",
    "sg:city":"Acquasparta",
    "sg:orig_category":"Video Monitors",
    "sg:phone":"+39 0744 941062",
    "sg:postcode":"05021",
    "sg:province":"Terni",
    "wof:name":"Sivid Srl",
    "wof:placetype":"venue"
},
  "geometry": {"coordinates":[12.646781,42.560219],"type":"Point"}
}