{
  "type": "Feature",
  "properties": {
    "addr:full":"20127 Milano Milano Milano 20127",
    "addr:postcode":"20127;20127",
    "iso:country":"IT",
    "sg:address":"20127 Milano",
    "sg:city":"Milano",
    "sg:orig_category":"Abbigliamento Esterno, Maglierie E Pelliccerie. Shopping",
    "sg:phone":"+39 02 282 6601",
    "sg:postcode":"20127",
    "sg:province":"Milano",
    "wof:name":"Ciaves Cadem",
    "wof:placetype":"venue"
},
  "geometry": {"coordinates":[9.235183,45.500999],"type":"Point"}
}