{
  "type": "Feature",
  "properties": {
    "iso:country":"IT",
    "sg:address":"2, Via Vittorio Veneto 36034 Malo",
    "sg:city":"Malo",
    "sg:classifiers":[
        {
            "category":"Parking",
            "subcategory":"Lot",
            "type":"Transportation"
        }
    ],
    "sg:phone":"+39 0445 581120",
    "sg:postcode":"36034",
    "sg:province":"Vicenza",
    "sg:tags":[
        "transport",
        "road"
    ],
    "wof:name":"Trasporti Romagna (s.r.l.)",
    "wof:placetype":"venue"
},
  "geometry": {"coordinates":[11.415079,45.658451],"type":"Point"}
}