{
  "type": "Feature",
  "properties": {
    "addr:full":"Via Alioli E Sassi 1 21026 Gavirate Gavirate Varese 21026",
    "addr:housenumber":"1",
    "addr:postcode":"21026;21026",
    "addr:street":"Via Alioli E Sassi",
    "iso:country":"IT",
    "sg:address":"Via Alioli E Sassi 1 21026 Gavirate",
    "sg:city":"Gavirate",
    "sg:classifiers":[
        {
            "category":"Manufacturing",
            "subcategory":"Rubber & Plastics",
            "type":"Manufacturing & Wholesale Goods"
        }
    ],
    "sg:phone":"+39 0332 731050",
    "sg:postcode":"21026",
    "sg:province":"Varese",
    "sg:tags":[
        "mould",
        "industry"
    ],
    "sg:website":"www.ilmaplastica.it",
    "wof:name":"Ilma Srl",
    "wof:placetype":"venue"
},
  "geometry": {"coordinates":[8.7411174774,45.8319854736],"type":"Point"}
}