{
  "type": "Feature",
  "properties": {
    "iso:country":"IT",
    "sg:address":"61034 Fossombrone",
    "sg:city":"Fossombrone",
    "sg:orig_category":"Generatori Elettrici Ed Elettronici",
    "sg:phone":"+39 0721 749171",
    "sg:postcode":"61034",
    "sg:province":"Pesaro E Urbino",
    "wof:name":"O.c.r.e.m. Srl",
    "wof:placetype":"venue"
},
  "geometry": {"coordinates":[12.856407,43.688461],"type":"Point"}
}