{
  "type": "Feature",
  "properties": {
    "iso:country":"IT",
    "sg:address":"55042 Forte Dei Marmi",
    "sg:city":"Forte dei Marmi",
    "sg:classifiers":[
        {
            "category":"Restaurant",
            "type":"Food & Drink"
        }
    ],
    "sg:phone":"+39 0584 89114",
    "sg:postcode":"55042",
    "sg:province":"Lucca",
    "sg:tags":[
        "auxiliary",
        "entertainment",
        "premises",
        "related",
        "catering",
        "similar",
        "public",
        "restaurants"
    ],
    "wof:name":"Midho Club - Kupido",
    "wof:placetype":"venue"
},
  "geometry": {"coordinates":[10.156493,43.967224],"type":"Point"}
}