{
  "type": "Feature",
  "properties": {
    "iso:country":"IT",
    "sg:address":"71045 Orta Nova",
    "sg:city":"Orta Nova",
    "sg:orig_category":"Ferro Battuto",
    "sg:phone":"+39 0885 781042",
    "sg:postcode":"71045",
    "sg:province":"Foggia",
    "wof:name":"Daniele & Liscio Snc",
    "wof:placetype":"venue"
},
  "geometry": {"coordinates":[15.7196445465,41.3276443481],"type":"Point"}
}