{
  "type": "Feature",
  "properties": {
    "iso:country":"IT",
    "sg:address":"00136 Roma",
    "sg:city":"Roma",
    "sg:orig_category":"Trasporti E Spedizioni Merci",
    "sg:phone":"+39 0639890",
    "sg:postcode":"00136",
    "sg:province":"Roma",
    "sg:website":"http://www.prestoexpress.it",
    "wof:name":"Presto Express Roma Srl",
    "wof:placetype":"venue"
},
  "geometry": {"coordinates":[12.447363,41.905972],"type":"Point"}
}