{
  "type": "Feature",
  "properties": {
    "iso:country":"IT",
    "sg:address":"21052 Busto Arsizio",
    "sg:city":"Busto Arsizio",
    "sg:orig_category":"Riparazione Dei Mezzi Di Trasporto. Servizi Ausiliari Dei Mezzi Di Trasporto",
    "sg:phone":"+39 0331 684463",
    "sg:postcode":"21052",
    "sg:province":"Varese",
    "sg:website":"http://www.steel-net.it/bustogomme",
    "wof:name":"Busto Gomme Snc",
    "wof:placetype":"venue"
},
  "geometry": {"coordinates":[8.838582,45.614056],"type":"Point"}
}