{
  "type": "Feature",
  "properties": {
    "addr:full":"81033 Casal Di Principe Casal di Principe Caserta 81033",
    "addr:housenumber":"di principe",
    "addr:postcode":"81033;81033",
    "iso:country":"IT",
    "sg:address":"81033 Casal Di Principe",
    "sg:city":"Casal di Principe",
    "sg:orig_category":"Pubblica Amministrazione",
    "sg:phone":"+39 081 892 1010",
    "sg:postcode":"81033",
    "sg:province":"Caserta",
    "wof:name":"Carabinieri",
    "wof:placetype":"venue"
},
  "geometry": {"coordinates":[14.111749649,41.0187721252],"type":"Point"}
}