{
  "type": "Feature",
  "properties": {
    "addr:full":"50145 Firenze Firenze Firenze 50145",
    "addr:postcode":"50145;50145",
    "iso:country":"IT",
    "sg:address":"50145 Firenze",
    "sg:city":"Firenze",
    "sg:orig_category":"Forniture Per Attivita' Commerciali Ed Artigianali. Pubblicita', Marketing E Comunicazione",
    "sg:phone":"+39 055 315548",
    "sg:postcode":"50145",
    "sg:province":"Firenze",
    "sg:website":"http://www.coinart.it",
    "wof:name":"Coinart Srl",
    "wof:placetype":"venue"
},
  "geometry": {"coordinates":[11.2153892517,43.7108726501],"type":"Point"}
}