{
  "type": "Feature",
  "properties": {
    "addr:full":"25, Via Enrico Mattei 26020 Madignano Madignano Cremona 26020",
    "addr:postcode":"26020;26020",
    "addr:street":"Via Enrico Mattei",
    "iso:country":"IT",
    "sg:address":"25, Via Enrico Mattei 26020 Madignano",
    "sg:city":"Madignano",
    "sg:classifiers":[
        {
            "category":"Professional",
            "subcategory":"Engineering",
            "type":"Services"
        }
    ],
    "sg:phone":"+39 39037365185",
    "sg:postcode":"26020",
    "sg:province":"Cremona",
    "sg:tags":[
        "machine",
        "-",
        "mechanical"
    ],
    "wof:name":"Ve.tra.co. S.r.l.",
    "wof:placetype":"venue"
},
  "geometry": {"coordinates":[9.736392,45.335026],"type":"Point"}
}