{
  "type": "Feature",
  "properties": {
    "iso:country":"IT",
    "sg:address":"10070 S. Carlo Canavese",
    "sg:city":"San Francesco al Campo",
    "sg:orig_category":"Arredo Cucina Ed Elettrodomestici",
    "sg:phone":"+39 011 921 5748",
    "sg:postcode":"10070",
    "sg:province":"Torino",
    "wof:name":"Mobili Triarico Snc",
    "wof:placetype":"venue"
},
  "geometry": {"coordinates":[7.653266,45.229504],"type":"Point"}
}