{
  "type": "Feature",
  "properties": {
    "iso:country":"IT",
    "sg:address":"13012 Borgo Vercelli",
    "sg:city":"Borgo Vercelli",
    "sg:orig_category":"Prodotti Di Base E Forniture Per Industria Alimentare E Bevande",
    "sg:phone":"+39 0161 32644",
    "sg:postcode":"13012",
    "sg:province":"Vercelli",
    "wof:name":"Giordano G. & C. (s.a.s.)",
    "wof:placetype":"venue"
},
  "geometry": {"coordinates":[8.4623308182,45.3594932556],"type":"Point"}
}