{
  "type": "Feature",
  "properties": {
    "addr:full":"39052 Caldaro Strada Vino Bolzano/Bozen 39052",
    "addr:postcode":"39052;39052",
    "addr:street":"Strada Vino",
    "iso:country":"IT",
    "sg:address":"39052 Caldaro Strada Vino",
    "sg:orig_category":"Forniture Per Edilizia E Lavori Pubblici",
    "sg:phone":"+39 0471 964848",
    "sg:postcode":"39052",
    "sg:province":"Bolzano/Bozen",
    "sg:website":"http://www.traficline.it",
    "wof:name":"Frank Srl",
    "wof:placetype":"venue"
},
  "geometry": {"coordinates":[11.2628965378,46.456653595],"type":"Point"}
}