{
  "type": "Feature",
  "properties": {
    "iso:country":"IT",
    "sg:address":"25, Via Comune Antico 20125 Milano",
    "sg:city":"Milano",
    "sg:classifiers":[
        {
            "category":"Utilities",
            "subcategory":"Telephone",
            "type":"Services"
        }
    ],
    "sg:phone":"+39 39026700750",
    "sg:postcode":"20125",
    "sg:province":"Milano",
    "sg:tags":[
        "telecommunication"
    ],
    "wof:name":"G.s. Radiotelefoni (s.a.s.)",
    "wof:placetype":"venue"
},
  "geometry": {"coordinates":[9.203226,45.482468],"type":"Point"}
}