{
  "type": "Feature",
  "properties": {
    "addr:full":"21051 Arcisate Arcisate Varese 21051",
    "addr:housenumber":"21051",
    "addr:postcode":"21051",
    "addr:street":"Arcisate Arcisate",
    "iso:country":"IT",
    "sg:address":"21051 Arcisate",
    "sg:city":"Arcisate",
    "sg:orig_category":"Apparecchiature E Sistemi Per Imballaggio E Confezionamento",
    "sg:phone":"+39 0332 472471",
    "sg:postcode":"21051",
    "sg:province":"Varese",
    "sg:website":"http://www.siscodata.com",
    "wof:name":"Siscodata Computer Srl",
    "wof:placetype":"venue"
},
  "geometry": {"coordinates":[8.86192,45.851158],"type":"Point"}
}