{
  "type": "Feature",
  "properties": {
    "addr:full":"84040 Camerota Camerota Salerno 84040",
    "addr:postcode":"84040;84040",
    "iso:country":"IT",
    "sg:address":"84040 Camerota",
    "sg:city":"Camerota",
    "sg:orig_category":"Agenzie Viaggi E Turismo",
    "sg:phone":"+39 0974 931457",
    "sg:postcode":"84040",
    "sg:province":"Salerno",
    "wof:name":"Camping Nessuno Snc",
    "wof:placetype":"venue"
},
  "geometry": {"coordinates":[15.372753,40.029793],"type":"Point"}
}