{
  "type": "Feature",
  "properties": {
    "iso:country":"IT",
    "sg:address":"Via Flaminia Km 187 06023 Gualdo Tadino",
    "sg:city":"Gualdo Tadino",
    "sg:classifiers":[
        {
            "category":"Professional",
            "subcategory":"Business Services",
            "type":"Services"
        }
    ],
    "sg:phone":"+39 075 914 2064",
    "sg:postcode":"06023",
    "sg:province":"Perugia",
    "sg:tags":[
        "advice"
    ],
    "wof:name":"Crimo Italia S.r.l.",
    "wof:placetype":"venue"
},
  "geometry": {"coordinates":[12.389172,43.110703],"type":"Point"}
}