{
  "type": "Feature",
  "properties": {
    "iso:country":"IT",
    "sg:address":"14053 Canelli",
    "sg:city":"Canelli",
    "sg:orig_category":"Enologia Macchine E Prodotti - Produzione E Ingrosso",
    "sg:phone":"+39 0141 824882",
    "sg:postcode":"14053",
    "sg:province":"Asti",
    "sg:website":"http://www.ferrero-machines.com",
    "wof:name":"Ferrero Di Ugo E Fabrizio Snc",
    "wof:placetype":"venue"
},
  "geometry": {"coordinates":[8.297633,44.736584],"type":"Point"}
}