{
  "type": "Feature",
  "properties": {
    "iso:country":"IT",
    "sg:address":"20024 Garbagnate Milanese",
    "sg:city":"Garbagnate Milanese",
    "sg:orig_category":"Ospedali E Servizi Sanitari. Pubblica Amministrazione. Servizi Sociali",
    "sg:phone":"+39 02 995 2068",
    "sg:postcode":"20024",
    "sg:province":"Milano",
    "wof:name":"Azienda Sanitaria Locale - Provincia Di Milano 1",
    "wof:placetype":"venue"
},
  "geometry": {"coordinates":[9.087238,45.580246],"type":"Point"}
}