{
  "type": "Feature",
  "properties": {
    "iso:country":"IT",
    "sg:address":"8, V. Monte Tagliaferro 21056 Induno Olona",
    "sg:city":"Induno Olona",
    "sg:classifiers":[
        {
            "category":"Wholesale",
            "subcategory":"Machinery & Supplies",
            "type":"Manufacturing & Wholesale Goods"
        }
    ],
    "sg:phone":"+39 0332 203626",
    "sg:postcode":"21056",
    "sg:province":"Varese",
    "sg:tags":[
        "equipment",
        "-",
        "instrument",
        "measurement"
    ],
    "sg:website":"http://www.easydur.com",
    "wof:name":"Easydur Italiana Di Affri Renato",
    "wof:placetype":"venue"
},
  "geometry": {"coordinates":[8.834014,45.839035],"type":"Point"}
}