{
  "type": "Feature",
  "properties": {
    "iso:country":"IT",
    "sg:address":"37029 S.pietro In Cariano",
    "sg:city":"Negarine",
    "sg:orig_category":"Termotecnica E Riscaldamento, Apparecchiature E Servizi",
    "sg:phone":"+39 045 685 9012",
    "sg:postcode":"37029",
    "sg:province":"Verona",
    "sg:website":"http://www.cipriani.it",
    "wof:name":"Cipriani Scambiatori Srl",
    "wof:placetype":"venue"
},
  "geometry": {"coordinates":[10.895,45.501259],"type":"Point"}
}