{
  "type": "Feature",
  "properties": {
    "iso:country":"IT",
    "sg:address":"18, Via Rosani Rita 37024 Negrar",
    "sg:city":"Negrar",
    "sg:classifiers":[
        {
            "category":"Shopping",
            "subcategory":"Computers & Home Electronics",
            "type":"Retail Goods"
        }
    ],
    "sg:phone":"+39 045 600 0044",
    "sg:postcode":"37024",
    "sg:province":"Verona",
    "sg:tags":[
        "electronic",
        "electrical",
        "equipment"
    ],
    "wof:name":"Tecnovap (s.n.c.)",
    "wof:placetype":"venue"
},
  "geometry": {"coordinates":[10.949392,45.545269],"type":"Point"}
}