{
  "type": "Feature",
  "properties": {
    "iso:country":"IT",
    "sg:address":"Via Edison 21 20058 Villasanta",
    "sg:city":"Villasanta",
    "sg:orig_category":"Marine Electrical Installation Material",
    "sg:phone":"+39 039 303161",
    "sg:postcode":"20058",
    "sg:province":"Milano",
    "sg:website":"www.sbm.it",
    "wof:name":"S.b.m. S.n.c.",
    "wof:placetype":"venue"
},
  "geometry": {"coordinates":[9.188141,45.463688],"type":"Point"}
}