{
  "type": "Feature",
  "properties": {
    "iso:country":"IT",
    "sg:address":"20124 Milano",
    "sg:city":"Milano",
    "sg:orig_category":"Arredo Cucina Ed Elettrodomestici",
    "sg:phone":"+39 02 655 2596",
    "sg:postcode":"20124",
    "sg:province":"Milano",
    "wof:name":"Sag 80 Arredamenti Srl",
    "wof:placetype":"venue"
},
  "geometry": {"coordinates":[9.198097,45.47813],"type":"Point"}
}