{
  "type": "Feature",
  "properties": {
    "addr:full":"Via Baccanello 22 24030 Terno D'isola Bergamo 24030",
    "addr:housenumber":"22",
    "addr:postcode":"24030;24030",
    "addr:street":"Via Baccanello",
    "iso:country":"IT",
    "sg:address":"Via Baccanello 22 24030 Terno D'isola",
    "sg:classifiers":[
        {
            "category":"Home & Garden",
            "subcategory":"Building Materials",
            "type":"Retail Goods"
        }
    ],
    "sg:phone":"+39 035 494 9001",
    "sg:postcode":"24030",
    "sg:province":"Bergamo",
    "sg:tags":[
        "handle",
        "door"
    ],
    "sg:website":"www.colombodesign.it",
    "wof:name":"Colombo Design Spa",
    "wof:placetype":"venue"
},
  "geometry": {"coordinates":[9.512227,45.687634],"type":"Point"}
}