{
  "type": "Feature",
  "properties": {
    "iso:country":"IT",
    "sg:address":"25040 Corte Franca",
    "sg:city":"Corte Franca",
    "sg:orig_category":"Elettrotecnica Industriale, Prodotti E Apparecchiature. Elettrotecnica Professionale E Di Consumo",
    "sg:phone":"+39 030 984128",
    "sg:postcode":"25040",
    "sg:province":"Brescia",
    "wof:name":"O.m.t. Srl",
    "wof:placetype":"venue"
},
  "geometry": {"coordinates":[9.989232,45.631023],"type":"Point"}
}