{
  "type": "Feature",
  "properties": {
    "addr:full":"1, Zona Industriale 66015 Fara San Martino Fara San Martino Chieti 66015",
    "addr:housenumber":"1",
    "addr:postcode":"66015;66015",
    "addr:street":"Zona Industriale",
    "iso:country":"IT",
    "sg:address":"1, Zona Industriale 66015 Fara San Martino",
    "sg:city":"Fara San Martino",
    "sg:classifiers":[
        {
            "category":"Food & Beverages",
            "subcategory":"Groceries & Convenience Stores",
            "type":"Retail Goods"
        }
    ],
    "sg:phone":"+39 390 872 9861",
    "sg:postcode":"66015",
    "sg:province":"Chieti",
    "sg:tags":[
        "product",
        "related"
    ],
    "wof:name":"De Cecco Sede E Stabilimento Fara S. Martino S.p.a.",
    "wof:placetype":"venue"
},
  "geometry": {"coordinates":[14.1671514511,42.3517913818],"type":"Point"}
}