{
  "type": "Feature",
  "properties": {
    "addr:full":"Via Merolini 87041 Acri Acri Cosenza 87041",
    "addr:postcode":"87041;87041",
    "addr:street":"Via Merolini",
    "iso:country":"IT",
    "sg:address":"Via Merolini 87041 Acri",
    "sg:city":"Acri",
    "sg:classifiers":[
        {
            "category":"Food & Beverages",
            "subcategory":"Groceries & Convenience Stores",
            "type":"Retail Goods"
        }
    ],
    "sg:phone":"+39 0984 954202",
    "sg:postcode":"87041",
    "sg:province":"Cosenza",
    "sg:tags":[
        "product",
        "related"
    ],
    "wof:name":"General Magazine (s.p.a.)",
    "wof:placetype":"venue"
},
  "geometry": {"coordinates":[16.3913326263,39.4966812134],"type":"Point"}
}