{
  "type": "Feature",
  "properties": {
    "addr:full":"Vle Del Progresso 12 35026 Conselve Conselve Padova 35026",
    "addr:housenumber":"12",
    "addr:postcode":"35026;35026",
    "addr:street":"Vle Del Progresso",
    "iso:country":"IT",
    "sg:address":"Vle Del Progresso 12 35026 Conselve",
    "sg:city":"Conselve",
    "sg:classifiers":[
        {
            "category":"Wholesale",
            "subcategory":"Farm Supplies",
            "type":"Manufacturing & Wholesale Goods"
        }
    ],
    "sg:phone":"+39 049 950 1224",
    "sg:postcode":"35026",
    "sg:province":"Padova",
    "sg:tags":[
        "agricultural",
        "part",
        "spare",
        "machinery",
        "accessory"
    ],
    "sg:website":"www.generalmix.it",
    "wof:name":"General Mix S.r.l.",
    "wof:placetype":"venue"
},
  "geometry": {"coordinates":[11.876589,45.409569],"type":"Point"}
}