{
  "type": "Feature",
  "properties": {
    "iso:country":"IT",
    "sg:address":"20023 Cerro Maggiore",
    "sg:city":"Cerro Maggiore",
    "sg:orig_category":"Climatizzazione E Condizionamento, Apparecchiature E Servizi",
    "sg:phone":"+39 0331 514400",
    "sg:postcode":"20023",
    "sg:province":"Milano",
    "wof:name":"G.f. Termotecnica Srl",
    "wof:placetype":"venue"
},
  "geometry": {"coordinates":[8.95214,45.595787],"type":"Point"}
}