{
  "type": "Feature",
  "properties": {
    "iso:country":"IT",
    "sg:address":"Via Torricelli Evangelista 2/a 37135 Verona",
    "sg:city":"Verona",
    "sg:orig_category":"Deck Cranes, Shipside Cranes, Container Cranes",
    "sg:phone":"+39 045 508877",
    "sg:postcode":"37135",
    "sg:province":"Verona",
    "sg:website":"www.mepel.it",
    "wof:name":"Mep Pellegrini Marine Equipments Srl",
    "wof:placetype":"venue"
},
  "geometry": {"coordinates":[10.972294,45.403458],"type":"Point"}
}