{
  "type": "Feature",
  "properties": {
    "addr:full":"34147 Trieste Trieste Trieste 34147",
    "addr:postcode":"34147;34147",
    "iso:country":"IT",
    "sg:address":"34147 Trieste",
    "sg:city":"Trieste",
    "sg:orig_category":"Ricambi E Componenti Dei Mezzi Di Trasporto",
    "sg:phone":"+39 040 832 3222",
    "sg:postcode":"34147",
    "sg:province":"Trieste",
    "wof:name":"Officina Navale Quaiat Di Marino Quaiat",
    "wof:placetype":"venue"
},
  "geometry": {"coordinates":[13.809273,45.615253],"type":"Point"}
}