{
  "type": "Feature",
  "properties": {
    "iso:country":"IT",
    "sg:address":"Via Due Portoni 29 40132 Bologna",
    "sg:city":"Bologna",
    "sg:classifiers":[
        {
            "category":"Manufacturing",
            "subcategory":"Motor Vehicles & Parts",
            "type":"Manufacturing & Wholesale Goods"
        }
    ],
    "sg:phone":"+39 051 641 4495",
    "sg:postcode":"40132",
    "sg:province":"Bologna",
    "sg:tags":[
        "plant",
        "spare",
        "conveyor"
    ],
    "sg:website":"www.tamarri.it",
    "wof:name":"Tamarri Srl",
    "wof:placetype":"venue"
},
  "geometry": {"coordinates":[11.275478,44.528618],"type":"Point"}
}