{
  "type": "Feature",
  "properties": {
    "iso:country":"IT",
    "sg:address":"86100 Campobasso",
    "sg:city":"Campobasso",
    "sg:orig_category":"Forniture Per Agricoltura E Zootecnia. Prodotti Chimici Secondari",
    "sg:phone":"+39 0874 65685",
    "sg:postcode":"86100",
    "sg:province":"Campobasso",
    "wof:name":"Colagiovanni Garden Del Geom. Colagiovanni Antonio",
    "wof:placetype":"venue"
},
  "geometry": {"coordinates":[14.6704425812,41.5770835876],"type":"Point"}
}