{
  "type": "Feature",
  "properties": {
    "addr:full":"20095 Cusano Milanino Cusano Milanino Milano 20095",
    "addr:postcode":"20095;20095",
    "iso:country":"IT",
    "sg:address":"20095 Cusano Milanino",
    "sg:city":"Cusano Milanino",
    "sg:orig_category":"Servizi E Lavori Per Ecologia E Smaltimento Rifiuti. Forniture Industriali Per Prevenzione, Controllo E Sicurezza",
    "sg:phone":"+39 02 619 4035",
    "sg:postcode":"20095",
    "sg:province":"Milano",
    "wof:name":"Tecnofon Sas",
    "wof:placetype":"venue"
},
  "geometry": {"coordinates":[9.183873,45.544624],"type":"Point"}
}