{
  "type": "Feature",
  "properties": {
    "addr:full":"62027 San Severino Marche San Severino Marche Macerata 62027",
    "addr:housenumber":"62027",
    "addr:postcode":"marche san;62027",
    "iso:country":"IT",
    "sg:address":"62027 San Severino Marche",
    "sg:city":"San Severino Marche",
    "sg:orig_category":"Antiquariato",
    "sg:phone":"+39 0733 634546",
    "sg:postcode":"62027",
    "sg:province":"Macerata",
    "wof:name":"Antiqua Di Raimondi Cristina",
    "wof:placetype":"venue"
},
  "geometry": {"coordinates":[13.17592,43.22916],"type":"Point"}
}