{
  "type": "Feature",
  "properties": {
    "addr:full":"41030 Bomporto Bomporto Modena 41030",
    "addr:postcode":"41030;41030",
    "iso:country":"IT",
    "sg:address":"41030 Bomporto",
    "sg:city":"Bomporto",
    "sg:orig_category":"Macchine Ed Impianti Per Edilizia E Lavori Pubblici",
    "sg:phone":"+39 059 909389",
    "sg:postcode":"41030",
    "sg:province":"Modena",
    "wof:name":"S.m.b. S.r.l.",
    "wof:placetype":"venue"
},
  "geometry": {"coordinates":[11.042864,44.734322],"type":"Point"}
}