{
  "type": "Feature",
  "properties": {
    "addr:full":"00192 Roma Roma Roma 00192",
    "addr:postcode":"00192;00192",
    "iso:country":"IT",
    "sg:address":"00192 Roma",
    "sg:city":"Roma",
    "sg:orig_category":"Prodotti Finiti Stampati. Forniture Per Uffici. Regalistica Aziendale",
    "sg:phone":"+39 06 370 1612",
    "sg:postcode":"00192",
    "sg:province":"Roma",
    "wof:name":"Trincia Bruno",
    "wof:placetype":"venue"
},
  "geometry": {"coordinates":[12.4599866867,41.9118080139],"type":"Point"}
}