{
  "type": "Feature",
  "properties": {
    "addr:full":"15100 Alessandria Alessandria Alessandria 15100",
    "addr:postcode":"15100;15100",
    "iso:country":"IT",
    "sg:address":"15100 Alessandria",
    "sg:city":"Alessandria",
    "sg:orig_category":"Forniture Per Edilizia E Lavori Pubblici",
    "sg:phone":"+39 0131 253760",
    "sg:postcode":"15100",
    "sg:province":"Alessandria",
    "wof:name":"Grassi Walter",
    "wof:placetype":"venue"
},
  "geometry": {"coordinates":[8.7030067444,44.8683700562],"type":"Point"}
}