{
  "type": "Feature",
  "properties": {
    "iso:country":"IT",
    "sg:address":"Via Averolda, 8/10 25039 Travagliato",
    "sg:city":"Travagliato",
    "sg:orig_category":"Resistors, Electrical",
    "sg:phone":"+39 030 686 3803",
    "sg:postcode":"25039",
    "sg:province":"Brescia",
    "sg:website":"www.bielettrica.com",
    "wof:name":"Bielettrica Srl",
    "wof:placetype":"venue"
},
  "geometry": {"coordinates":[10.100182,45.534237],"type":"Point"}
}