{
  "type": "Feature",
  "properties": {
    "addr:full":"21, Via S. Berardino 66036 Orsogna Orsogna Chieti 66036",
    "addr:postcode":"66036;66036",
    "addr:street":"Via S. Berardino",
    "iso:country":"IT",
    "sg:address":"21, Via S. Berardino 66036 Orsogna",
    "sg:city":"Orsogna",
    "sg:classifiers":[
        {
            "category":"Shopping",
            "subcategory":"Clothing, Apparel, & Fashions",
            "type":"Retail Goods"
        }
    ],
    "sg:phone":"+39 0871 869703",
    "sg:postcode":"66036",
    "sg:province":"Chieti",
    "sg:tags":[
        "clothes"
    ],
    "wof:name":"Lina Auriti Srl",
    "wof:placetype":"venue"
},
  "geometry": {"coordinates":[14.167151,42.351791],"type":"Point"}
}