{
  "type": "Feature",
  "properties": {
    "addr:full":"80035 Nola Nola Napoli 80035",
    "addr:housenumber":"80035",
    "addr:postcode":"80035",
    "addr:street":"Nola",
    "iso:country":"IT",
    "sg:address":"80035 Nola",
    "sg:city":"Nola",
    "sg:orig_category":"Prodotti Alimentari",
    "sg:phone":"+39 339 790 5160",
    "sg:postcode":"80035",
    "sg:province":"Napoli",
    "wof:name":"La Perla Bianca Sas",
    "wof:placetype":"venue"
},
  "geometry": {"coordinates":[15.170838356,41.0896759033],"type":"Point"}
}