{
  "type": "Feature",
  "properties": {
    "iso:country":"IT",
    "sg:address":"33170 Pordenone",
    "sg:city":"Pordenone",
    "sg:classifiers":[
        {
            "category":"Manufacturing",
            "subcategory":"Rubber & Plastics",
            "type":"Manufacturing & Wholesale Goods"
        }
    ],
    "sg:phone":"+39 0434 572440",
    "sg:postcode":"33170",
    "sg:province":"Pordenone",
    "sg:tags":[
        "activities",
        "product",
        "plastics",
        "articles",
        "supply",
        "industrial"
    ],
    "sg:website":"http://www.egonsrl.com",
    "wof:name":"Egon Srl",
    "wof:placetype":"venue"
},
  "geometry": {"coordinates":[12.6614522934,45.9563674927],"type":"Point"}
}