{
  "type": "Feature",
  "properties": {
    "iso:country":"IT",
    "sg:address":"33100 Udine",
    "sg:city":"Udine",
    "sg:classifiers":[
        {
            "category":"Shopping",
            "subcategory":"Clothing, Apparel, & Fashions",
            "type":"Retail Goods"
        }
    ],
    "sg:phone":"+39 0432 523408",
    "sg:postcode":"33100",
    "sg:province":"Udine",
    "sg:tags":[
        "knitwear",
        "furs",
        "clothing"
    ],
    "wof:name":"La Furlana Srl",
    "wof:placetype":"venue"
},
  "geometry": {"coordinates":[13.258805,46.027782],"type":"Point"}
}