{
  "type": "Feature",
  "properties": {
    "iso:country":"IT",
    "sg:address":"20131 Milano",
    "sg:city":"Milano",
    "sg:classifiers":[
        {
            "category":"Health Services",
            "subcategory":"Health Practitioner",
            "type":"Services"
        }
    ],
    "sg:phone":"+39 02 236 4277",
    "sg:postcode":"20131",
    "sg:province":"Milano",
    "sg:tags":[
        "medici"
    ],
    "wof:name":"Giovaninetti Umberto",
    "wof:placetype":"venue"
},
  "geometry": {"coordinates":[9.227928,45.486004],"type":"Point"}
}