{
  "type": "Feature",
  "properties": {
    "iso:country":"IT",
    "sg:address":"5, Via Belgio 41012 Carpi",
    "sg:city":"Carpi",
    "sg:classifiers":[
        {
            "category":"Shopping",
            "subcategory":"Clothing, Apparel, & Fashions",
            "type":"Retail Goods"
        }
    ],
    "sg:phone":"+39 39059640206",
    "sg:postcode":"41012",
    "sg:province":"Modena",
    "sg:tags":[
        "clothes"
    ],
    "wof:name":"Derby Tricot (s.r.l.)",
    "wof:placetype":"venue"
},
  "geometry": {"coordinates":[10.872088,44.772366],"type":"Point"}
}