{
  "type": "Feature",
  "properties": {
    "iso:country":"IT",
    "sg:address":"190, Via Canturina 22100 Como",
    "sg:city":"Como",
    "sg:classifiers":[
        {
            "category":"Shopping",
            "subcategory":"Clothing, Apparel, & Fashions",
            "type":"Retail Goods"
        }
    ],
    "sg:phone":"+39 39031591420",
    "sg:postcode":"22100",
    "sg:province":"Como",
    "sg:tags":[
        "clothing",
        "accessory"
    ],
    "wof:name":"Emporio Della Seta (s.r.l.)",
    "wof:placetype":"venue"
},
  "geometry": {"coordinates":[9.096237,45.778862],"type":"Point"}
}