{
  "type": "Feature",
  "properties": {
    "iso:country":"IT",
    "sg:address":"35020 Due Carrare",
    "sg:city":"Due Carrare",
    "sg:classifiers":[
        {
            "category":"Home & Garden",
            "subcategory":"Carpets & Floor Coverings",
            "type":"Retail Goods"
        }
    ],
    "sg:phone":"+39 049 912 5249",
    "sg:postcode":"35020",
    "sg:province":"Padova",
    "sg:tags":[
        "curtain",
        "material",
        "fabric",
        "fabrics",
        "furnishing"
    ],
    "sg:website":"http://www.solarsystems.net",
    "wof:name":"Solar Technology Srl",
    "wof:placetype":"venue"
},
  "geometry": {"coordinates":[11.8189048767,45.3303718567],"type":"Point"}
}