{
  "type": "Feature",
  "properties": {
    "iso:country":"IT",
    "sg:address":"88100 Catanzaro",
    "sg:city":"Catanzaro",
    "sg:orig_category":"Servizi E Lavori Per Agricoltura E Zootecnia. Servizi Ausiliari Di Analisi, Controllo E Ricerca",
    "sg:phone":"+39 0961 32715",
    "sg:postcode":"88100",
    "sg:province":"Catanzaro",
    "wof:name":"Istituto Zooprofilattico Sperimentale Del Mezzogiorno",
    "wof:placetype":"venue"
},
  "geometry": {"coordinates":[16.632753,38.833313],"type":"Point"}
}