{
  "type": "Feature",
  "properties": {
    "iso:country":"IT",
    "sg:address":"Via Delle Mura Sud 12; Massa; 54100",
    "sg:city":"Massa",
    "sg:classifiers":[
        {
            "category":"Banks & Credit Unions",
            "subcategory":"Bank",
            "type":"Services"
        }
    ],
    "sg:phone":"+39 0585 810751",
    "sg:postcode":"54100",
    "sg:province":"Massa-Carrara",
    "wof:name":"Cassa Di Risparmio Di Carrara Spa",
    "wof:placetype":"venue"
},
  "geometry": {"coordinates":[10.142767,44.034653],"type":"Point"}
}