{
  "type": "Feature",
  "properties": {
    "iso:country":"IT",
    "sg:address":"20020 Lazzate",
    "sg:city":"Lazzate",
    "sg:orig_category":"Cesoie Industriali",
    "sg:phone":"+39 02 9632 0231",
    "sg:postcode":"20020",
    "sg:province":"Milano",
    "wof:name":"Caimi & C. Di Caimi & Monti",
    "wof:placetype":"venue"
},
  "geometry": {"coordinates":[9.085848,45.672009],"type":"Point"}
}