{
  "type": "Feature",
  "properties": {
    "iso:country":"IT",
    "sg:address":"Via Roma 11/13 61040 Mercatello Sul Metauro",
    "sg:city":"Mercatello sul Metauro",
    "sg:classifiers":[
        {
            "category":"Building & Trades",
            "subcategory":"Construction",
            "type":"Services"
        }
    ],
    "sg:phone":"+39 0722 89910",
    "sg:postcode":"61040",
    "sg:province":"Pesaro E Urbino",
    "sg:tags":[
        "assembly",
        "customized",
        "machine",
        "equipment",
        "electronics",
        "jointing"
    ],
    "wof:name":"Power Srl",
    "wof:placetype":"venue"
},
  "geometry": {"coordinates":[12.336077,43.646206],"type":"Point"}
}