{
  "type": "Feature",
  "properties": {
    "addr:full":"20125 Milano Milano Milano 20125",
    "addr:postcode":"20125;20125",
    "iso:country":"IT",
    "sg:address":"20125 Milano",
    "sg:city":"Milano",
    "sg:orig_category":"Scuole E Servizi Scolastici",
    "sg:phone":"+39 02 669 1599",
    "sg:postcode":"20125",
    "sg:province":"Milano",
    "wof:name":"The Limelight Theatre Company-piccola Societa' Cooperativa Arl",
    "wof:placetype":"venue"
},
  "geometry": {"coordinates":[9.202109,45.486958],"type":"Point"}
}