{
  "type": "Feature",
  "properties": {
    "iso:country":"IT",
    "sg:address":"Via Mazzucconi 12 23900 Lecco",
    "sg:city":"Lecco",
    "sg:classifiers":[
        {
            "category":"Wholesale",
            "subcategory":"Vending Machines",
            "type":"Manufacturing & Wholesale Goods"
        }
    ],
    "sg:phone":"+39 0341 660246",
    "sg:postcode":"23900",
    "sg:province":"Lecco",
    "sg:tags":[
        "construction",
        "metal"
    ],
    "sg:website":"www.otomec.it",
    "wof:name":"Rusconi Metallurgica - Otomec Srl",
    "wof:placetype":"venue"
},
  "geometry": {"coordinates":[9.399973,45.868168],"type":"Point"}
}