{
  "type": "Feature",
  "properties": {
    "addr:full":"13900 Biella Biella Biella 13900",
    "addr:postcode":"13900;13900",
    "iso:country":"IT",
    "sg:address":"13900 Biella",
    "sg:city":"Biella",
    "sg:orig_category":"Filati E Materie Prime Tessili",
    "sg:phone":"+39 015 849 3813",
    "sg:postcode":"13900",
    "sg:province":"Biella",
    "wof:name":"Orlassino Lane",
    "wof:placetype":"venue"
},
  "geometry": {"coordinates":[8.052690506,45.5551223755],"type":"Point"}
}