{
  "type": "Feature",
  "properties": {
    "addr:full":"Via Del Commercio-paip 2 75100 Matera Matera Matera 75100",
    "addr:housenumber":"2",
    "addr:postcode":"75100;75100",
    "addr:street":"Via Del Commercio-Paip",
    "iso:country":"IT",
    "sg:address":"Via Del Commercio-paip 2 75100 Matera",
    "sg:city":"Matera",
    "sg:classifiers":[
        {
            "category":"Communications",
            "subcategory":"Television Station",
            "type":"Services"
        }
    ],
    "sg:phone":"+39 0835 381589",
    "sg:postcode":"75100",
    "sg:province":"Matera",
    "sg:tags":[
        "ignition",
        "cable"
    ],
    "sg:website":"www.brecav.com",
    "wof:name":"Brecav S.r.l.",
    "wof:placetype":"venue"
},
  "geometry": {"coordinates":[16.606087,40.668652],"type":"Point"}
}