{
  "type": "Feature",
  "properties": {
    "iso:country":"IT",
    "sg:address":"20121 Milano",
    "sg:city":"Milano",
    "sg:orig_category":"Agenzie D'affari E Servizi Commerciali",
    "sg:phone":"+39 02 777071",
    "sg:postcode":"20121",
    "sg:province":"Milano",
    "wof:name":"Symphonia S.i.m. (s.p.a.)",
    "wof:placetype":"venue"
},
  "geometry": {"coordinates":[9.195915,45.466908],"type":"Point"}
}