{
  "type": "Feature",
  "properties": {
    "iso:country":"IT",
    "sg:address":"80128 Napoli",
    "sg:city":"Napoli",
    "sg:orig_category":"Forniture Per Edilizia E Lavori Pubblici",
    "sg:phone":"+39 081 579 2920",
    "sg:postcode":"80128",
    "sg:province":"Napoli",
    "wof:name":"Rappresentanze Edili Ficar Sas",
    "wof:placetype":"venue"
},
  "geometry": {"coordinates":[14.2348413467,40.9476585388],"type":"Point"}
}