{
  "type": "Feature",
  "properties": {
    "iso:country":"IT",
    "sg:address":"625, Via Giardini Pietro 41100 Modena",
    "sg:city":"Modena",
    "sg:classifiers":[
        {
            "category":"Shopping",
            "subcategory":"Crafts & Fabrics",
            "type":"Retail Goods"
        }
    ],
    "sg:phone":"+39 39059359888",
    "sg:postcode":"41100",
    "sg:province":"Modena",
    "sg:tags":[
        "ceramic"
    ],
    "wof:name":"Alex Srl",
    "wof:placetype":"venue"
},
  "geometry": {"coordinates":[10.901021,44.63245],"type":"Point"}
}