{
  "type": "Feature",
  "properties": {
    "iso:country":"IT",
    "sg:address":"24035 Curno",
    "sg:city":"Curno",
    "sg:orig_category":"Elettronica Professionale E Di Consumo. Musica. Accessori Dei Mezzi Di Trasporto",
    "sg:phone":"+39 035 202100",
    "sg:postcode":"24035",
    "sg:province":"Bergamo",
    "sg:website":"http://www.mediaworld.it",
    "wof:name":"Mediamarket Spa - Media World",
    "wof:placetype":"venue"
},
  "geometry": {"coordinates":[9.616645,45.683575],"type":"Point"}
}