{
  "type": "Feature",
  "properties": {
    "iso:country":"IT",
    "sg:address":"2, Via Gargnano 38066 Riva Del Garda",
    "sg:city":"Riva del Garda",
    "sg:orig_category":"Miscellaneous Products",
    "sg:phone":"+39 0464 521831",
    "sg:postcode":"38066",
    "sg:province":"Trento",
    "wof:name":"Excelsior (s.n.c.)",
    "wof:placetype":"venue"
},
  "geometry": {"coordinates":[10.838013649,45.8809089661],"type":"Point"}
}