{
  "type": "Feature",
  "properties": {
    "iso:country":"IT",
    "sg:address":"35011 Campodarsego",
    "sg:city":"Campodarsego",
    "sg:orig_category":"Campeggio",
    "sg:phone":"+39 049 556 4455",
    "sg:postcode":"35011",
    "sg:province":"Padova",
    "sg:website":"http://www.novatecno.it",
    "wof:name":"Gepa Car Snc",
    "wof:placetype":"venue"
},
  "geometry": {"coordinates":[11.909645,45.483368],"type":"Point"}
}