{
  "type": "Feature",
  "properties": {
    "addr:full":"21040 Oggiona Con Santo Stefano Oggiona Varese 21040",
    "addr:postcode":"21040;21040",
    "iso:country":"IT",
    "sg:address":"21040 Oggiona Con Santo Stefano",
    "sg:city":"Oggiona",
    "sg:orig_category":"Non-classified Establishments",
    "sg:phone":"+39 0331 217259",
    "sg:postcode":"21040",
    "sg:province":"Varese",
    "wof:name":"De Bortoli Narciso",
    "wof:placetype":"venue"
},
  "geometry": {"coordinates":[8.820621,45.666557],"type":"Point"}
}