{
  "type": "Feature",
  "properties": {
    "iso:country":"IT",
    "sg:address":"57023 Cecina",
    "sg:city":"Cecina",
    "sg:orig_category":"Articoli Medico-sanitari Ed Ortopedici. Impianti, Attrezzature E Forniture Sanitarie Ed Ospedaliere",
    "sg:phone":"+39 0586 684509",
    "sg:postcode":"57023",
    "sg:province":"Livorno",
    "wof:name":"Ortopedia Bindi",
    "wof:placetype":"venue"
},
  "geometry": {"coordinates":[10.310265,43.526783],"type":"Point"}
}