{
  "type": "Feature",
  "properties": {
    "addr:full":"90015 Cefalu' Palermo 90015",
    "addr:postcode":"90015;90015",
    "addr:street":"Cefalu ' Palermo",
    "iso:country":"IT",
    "sg:address":"90015 Cefalu'",
    "sg:orig_category":"Servizi E Lavori Per Edilizia E Lavori Pubblici. Banche E Servizi Finanziari",
    "sg:phone":"+39 0921 921938",
    "sg:postcode":"90015",
    "sg:province":"Palermo",
    "wof:name":"Emmedierre Snc",
    "wof:placetype":"venue"
},
  "geometry": {"coordinates":[13.365691,38.11237],"type":"Point"}
}