{
  "type": "Feature",
  "properties": {
    "addr:full":"Viale Della Repubblica; Prato; 50047",
    "addr:postcode":"50047",
    "addr:street":"Viale Della Repubblica",
    "iso:country":"IT",
    "sg:address":"Viale Della Repubblica; Prato; 50047",
    "sg:classifiers":[
        {
            "category":"Banks & Credit Unions",
            "subcategory":"Bank",
            "type":"Services"
        }
    ],
    "sg:phone":"+39 0574 4931",
    "wof:name":"Banca Commerciale Italiana Spa",
    "wof:placetype":"venue"
},
  "geometry": {"coordinates":[11.112036,43.866241],"type":"Point"}
}