{
  "type": "Feature",
  "properties": {
    "addr:full":"80023 Caivano Caivano Napoli 80023",
    "addr:postcode":"80023;80023",
    "iso:country":"IT",
    "sg:address":"80023 Caivano",
    "sg:city":"Caivano",
    "sg:classifiers":[
        {
            "category":"Farming",
            "subcategory":"Fish & Marine Products",
            "type":"Manufacturing & Wholesale Goods"
        }
    ],
    "sg:phone":"+39 081 834 9184",
    "sg:postcode":"80023",
    "sg:province":"Napoli",
    "sg:tags":[
        "packaging",
        "articles",
        "packing",
        "plastics",
        "article"
    ],
    "wof:name":"Italiana Imballaggi Srl",
    "wof:placetype":"venue"
},
  "geometry": {"coordinates":[14.3210096359,40.9727401733],"type":"Point"}
}