{
  "type": "Feature",
  "properties": {
    "iso:country":"IT",
    "sg:address":"17046 Sassello",
    "sg:city":"Sassello",
    "sg:orig_category":"Elettrotecnica Industriale, Prodotti E Apparecchiature",
    "sg:phone":"+39 019 724715",
    "sg:postcode":"17046",
    "sg:province":"Savona",
    "wof:name":"Mancom Di Manfre' Francesca",
    "wof:placetype":"venue"
},
  "geometry": {"coordinates":[8.506201,44.477531],"type":"Point"}
}