{
  "type": "Feature",
  "properties": {
    "iso:country":"IT",
    "sg:address":"00154 Roma",
    "sg:city":"Roma",
    "sg:orig_category":"Banche E Servizi Finanziari. Acqua, Luce, Gas E Societa' Di Esercizio Pubblico. Pubblica Amministrazione",
    "sg:phone":"+39 06 575 0766",
    "sg:postcode":"00154",
    "sg:province":"Roma",
    "wof:name":"Agenzia Delle Dogane",
    "wof:placetype":"venue"
},
  "geometry": {"coordinates":[12.475118,41.872192],"type":"Point"}
}