{
  "type": "Feature",
  "properties": {
    "iso:country":"IT",
    "sg:address":"24030 Paladina",
    "sg:city":"Paladina",
    "sg:orig_category":"Antifurto",
    "sg:phone":"+39 035 545597",
    "sg:postcode":"24030",
    "sg:province":"Bergamo",
    "sg:website":"http://www.elettraimpianti.net",
    "wof:name":"Elettra Impianti Di Cattaneo Giordano Sas",
    "wof:placetype":"venue"
},
  "geometry": {"coordinates":[9.603033,45.650784],"type":"Point"}
}