{
  "type": "Feature",
  "properties": {
    "iso:country":"IT",
    "sg:address":"11, Cascina Faustina 20080 Albairate",
    "sg:city":"Albairate",
    "sg:classifiers":[
        {
            "category":"Shopping",
            "subcategory":"Computers & Home Electronics",
            "type":"Retail Goods"
        }
    ],
    "sg:phone":"+39 39029406708",
    "sg:postcode":"20080",
    "sg:province":"Milano",
    "sg:tags":[
        "electronic",
        "electrical",
        "equipment"
    ],
    "wof:name":"C.a.p.i.e. Componenti Avvolti Per Industria Elettronica S.n.c. Di Ferrari E Sala",
    "wof:placetype":"venue"
},
  "geometry": {"coordinates":[8.959012,45.429028],"type":"Point"}
}