{
  "type": "Feature",
  "properties": {
    "addr:full":"Via Antonino Pio 1 80078 Pozzuoli Pozzuoli Napoli 80078",
    "addr:housenumber":"1",
    "addr:postcode":"80078;80078",
    "addr:street":"Via Antonino Pio",
    "iso:country":"IT",
    "sg:address":"Via Antonino Pio 1 80078 Pozzuoli",
    "sg:city":"Pozzuoli",
    "sg:classifiers":[
        {
            "category":"Government",
            "subcategory":"Fire Station",
            "type":"Public Place"
        }
    ],
    "sg:phone":"+39 081 866 2450",
    "sg:postcode":"80078",
    "sg:province":"Napoli",
    "sg:tags":[
        "box",
        "alarm"
    ],
    "sg:website":"www.simaelettronica.com",
    "wof:name":"S.i.m.a. Elettronica Snc",
    "wof:placetype":"venue"
},
  "geometry": {"coordinates":[14.09226,40.844704],"type":"Point"}
}