{
  "type": "Feature",
  "properties": {
    "addr:full":"90142 Palermo Palermo Palermo 90142",
    "addr:postcode":"90142;90142",
    "iso:country":"IT",
    "sg:address":"90142 Palermo",
    "sg:city":"Palermo",
    "sg:orig_category":"Alberghi E Strutture Extra Alberghiere. Servizi Per Aziende, Manifestazioni E Supporto Agli Scambi Commerciali",
    "sg:phone":"+39 091 628 2111",
    "sg:postcode":"90142",
    "sg:province":"Palermo",
    "wof:name":"Astoria Palace Hotel",
    "wof:placetype":"venue"
},
  "geometry": {"coordinates":[13.357771,38.139248],"type":"Point"}
}