{
  "type": "Feature",
  "properties": {
    "addr:full":"57128 Livorno Livorno Livorno 57128",
    "addr:postcode":"57128;57128",
    "iso:country":"IT",
    "sg:address":"57128 Livorno",
    "sg:city":"Livorno",
    "sg:orig_category":"Carrozzerie Automobili",
    "sg:phone":"+39 0586 501482",
    "sg:postcode":"57128",
    "sg:province":"Livorno",
    "wof:name":"Carrozzeria L'ardenza Snc",
    "wof:placetype":"venue"
},
  "geometry": {"coordinates":[10.366962,43.515297],"type":"Point"}
}