{
  "type": "Feature",
  "properties": {
    "iso:country":"IT",
    "sg:address":"20154 Milano",
    "sg:city":"Milano",
    "sg:orig_category":"Servizi Editoriali. Servizi Per Aziende, Manifestazioni E Supporto Agli Scambi Commerciali",
    "sg:phone":"+39 02 625271",
    "sg:postcode":"20154",
    "sg:province":"Milano",
    "wof:name":"Grazia Neri Srl",
    "wof:placetype":"venue"
},
  "geometry": {"coordinates":[9.182794,45.483765],"type":"Point"}
}