{
  "type": "Feature",
  "properties": {
    "iso:country":"IT",
    "sg:address":"108, Via Dante Alighieri 20081 Abbiategrasso",
    "sg:city":"Abbiategrasso",
    "sg:classifiers":[
        {
            "category":"Professional",
            "subcategory":"Printing & Photocopies",
            "type":"Services"
        }
    ],
    "sg:phone":"+39 02 9496 7384",
    "sg:postcode":"20081",
    "sg:province":"Milano",
    "wof:name":"Orella (s.r.l.)",
    "wof:placetype":"venue"
},
  "geometry": {"coordinates":[8.9187431335,45.3868141174],"type":"Point"}
}