{
  "type": "Feature",
  "properties": {
    "addr:full":"Via Torino 12044 Centallo Centallo Cuneo 12044",
    "addr:postcode":"12044;12044",
    "addr:street":"Via Torino",
    "iso:country":"IT",
    "sg:address":"Via Torino 12044 Centallo",
    "sg:city":"Centallo",
    "sg:classifiers":[
        {
            "category":"Food & Beverages",
            "subcategory":"Groceries & Convenience Stores",
            "type":"Retail Goods"
        }
    ],
    "sg:phone":"+39 0171 214131",
    "sg:postcode":"12044",
    "sg:province":"Cuneo",
    "sg:tags":[
        "product",
        "related"
    ],
    "wof:name":"Operti S.n.c. Di Operti Francesco E C.",
    "wof:placetype":"venue"
},
  "geometry": {"coordinates":[7.5674362183,44.4536933899],"type":"Point"}
}