{
  "type": "Feature",
  "properties": {
    "addr:full":"14, Via Risorgimento 31025 Santa Lucia Di Piave Santa Lucia di Piave Treviso 31025",
    "addr:postcode":"31025;31025",
    "addr:street":"Via Risorgimento",
    "iso:country":"IT",
    "sg:address":"14, Via Risorgimento 31025 Santa Lucia Di Piave",
    "sg:city":"Santa Lucia di Piave",
    "sg:classifiers":[
        {
            "category":"Manufacturing",
            "subcategory":"Metals",
            "type":"Manufacturing & Wholesale Goods"
        }
    ],
    "sg:phone":"+39 39043862888",
    "sg:postcode":"31025",
    "sg:province":"Treviso",
    "sg:tags":[
        "metallurgy",
        "metalworking"
    ],
    "wof:name":"Barazza Fratelli (s.r.l.)",
    "wof:placetype":"venue"
},
  "geometry": {"coordinates":[12.2950201035,45.865486145],"type":"Point"}
}