{
  "type": "Feature",
  "properties": {
    "iso:country":"IT",
    "sg:address":"6/a, Via Milano 42048 Rubiera",
    "sg:classifiers":[
        {
            "category":"Shopping",
            "type":"Retail Goods"
        }
    ],
    "sg:phone":"+39 0522 627572",
    "sg:postcode":"42048",
    "sg:province":"Reggio Nell'Emilia",
    "sg:tags":[
        "finished",
        "-",
        "metallic"
    ],
    "wof:name":"Gvf Impianti S.r.l.",
    "wof:placetype":"venue"
},
  "geometry": {"coordinates":[10.7641782761,44.6569023132],"type":"Point"}
}