{
  "type": "Feature",
  "properties": {
    "addr:full":"80039 Saviano Saviano Napoli 80039",
    "addr:postcode":"80039;80039",
    "iso:country":"IT",
    "sg:address":"80039 Saviano",
    "sg:city":"Saviano",
    "sg:orig_category":"Forniture Per Abbigliamento E Pelletterie",
    "sg:phone":"+39 081 820 1462",
    "sg:postcode":"80039",
    "sg:province":"Napoli",
    "wof:name":"Pizzella Gaetano",
    "wof:placetype":"venue"
},
  "geometry": {"coordinates":[14.5097093582,40.9041900635],"type":"Point"}
}