{
  "type": "Feature",
  "properties": {
    "iso:country":"IT",
    "sg:address":"10142 Torino",
    "sg:city":"Torino",
    "sg:orig_category":"Cromatura E Nichelatura",
    "sg:phone":"+39 011 702280",
    "sg:postcode":"10142",
    "sg:province":"Torino",
    "wof:name":"Evolani Cromature",
    "wof:placetype":"venue"
},
  "geometry": {"coordinates":[7.830617,45.487606],"type":"Point"}
}