{
  "type": "Feature",
  "properties": {
    "iso:country":"IT",
    "sg:address":"174, Via Argine Po 46028 Sermide",
    "sg:city":"Sermide",
    "sg:classifiers":[
        {
            "category":"Wholesale",
            "subcategory":"Machinery & Supplies",
            "type":"Manufacturing & Wholesale Goods"
        }
    ],
    "sg:phone":"+39 0386 960268",
    "sg:postcode":"46028",
    "sg:province":"Mantova",
    "sg:tags":[
        "equipment",
        "precision"
    ],
    "wof:name":"Melloncelli Ing.n. & C. (s.n.c.)",
    "wof:placetype":"venue"
},
  "geometry": {"coordinates":[11.3024616241,45.0058631897],"type":"Point"}
}