{
  "type": "Feature",
  "properties": {
    "iso:country":"IT",
    "sg:address":"10090 Trana",
    "sg:city":"Trana",
    "sg:classifiers":[
        {
            "category":"Health Services",
            "subcategory":"Health Practitioner",
            "type":"Services"
        }
    ],
    "sg:phone":"+39 011 933176",
    "sg:postcode":"10090",
    "sg:province":"Torino",
    "sg:tags":[
        "medici"
    ],
    "wof:name":"Sacchetto Tommaso",
    "wof:placetype":"venue"
},
  "geometry": {"coordinates":[7.4229812622,45.0400009155],"type":"Point"}
}