{
  "type": "Feature",
  "properties": {
    "iso:country":"IT",
    "sg:address":"54100 Massa",
    "sg:city":"Massa",
    "sg:orig_category":"Pubblica Amministrazione",
    "sg:phone":"+39 0585 899811",
    "sg:postcode":"54100",
    "sg:province":"Massa-Carrara",
    "wof:name":"Vigili Del Fuoco Di Massa Centralino",
    "wof:placetype":"venue"
},
  "geometry": {"coordinates":[10.1221981049,44.0239868164],"type":"Point"}
}