{
  "type": "Feature",
  "properties": {
    "iso:country":"IT",
    "sg:address":"Via Giotto 5 21047 Saronno",
    "sg:city":"Saronno",
    "sg:orig_category":"Golf Course Equipment",
    "sg:phone":"+39 02 960 2513",
    "sg:postcode":"21047",
    "sg:province":"Varese",
    "wof:name":"Macchine Agricole Valentini Srl",
    "wof:placetype":"venue"
},
  "geometry": {"coordinates":[8.826385,45.817604],"type":"Point"}
}