{
  "type": "Feature",
  "properties": {
    "iso:country":"IT",
    "sg:address":"24011 Alme'",
    "sg:orig_category":"Centri Di Estetica E Cosmesi E Servizi",
    "sg:phone":"+39 035 542414",
    "sg:postcode":"24011",
    "sg:province":"Bergamo",
    "wof:name":"Belloli Omar",
    "wof:placetype":"venue"
},
  "geometry": {"coordinates":[9.61416,45.739262],"type":"Point"}
}