{
  "type": "Feature",
  "properties": {
    "iso:country":"IT",
    "sg:address":"33037 Pasian Di Prato",
    "sg:city":"Pasian di Prato",
    "sg:orig_category":"Prodotti Finiti Stampati. Servizi Editoriali. Tempo Libero - Articoli E Forniture",
    "sg:phone":"+39 0432 690242",
    "sg:postcode":"33037",
    "sg:province":"Udine",
    "wof:name":"Deimos Engineering S.r.l.",
    "wof:placetype":"venue"
},
  "geometry": {"coordinates":[13.1652183533,46.052646637],"type":"Point"}
}