{
  "type": "Feature",
  "properties": {
    "iso:country":"IT",
    "sg:address":"56035 Lari",
    "sg:city":"Lari",
    "sg:orig_category":"Serramenti Ed Infissi. Prodotti Vari In Metallo",
    "sg:phone":"+39 0587 616042",
    "sg:postcode":"56035",
    "sg:province":"Pisa",
    "sg:website":"http://www.simplexonline.it",
    "wof:name":"Simplex Srl",
    "wof:placetype":"venue"
},
  "geometry": {"coordinates":[10.6118,43.609402],"type":"Point"}
}