{
  "type": "Feature",
  "properties": {
    "iso:country":"IT",
    "sg:address":"70010 Valenzano",
    "sg:city":"Valenzano",
    "sg:orig_category":"Bevande, Vini E Liquori",
    "sg:phone":"+39 080 467 1157",
    "sg:postcode":"70010",
    "sg:province":"Bari",
    "sg:website":"http://www.battistasrl.com",
    "wof:name":"Battista Srl",
    "wof:placetype":"venue"
},
  "geometry": {"coordinates":[16.884399,41.044556],"type":"Point"}
}