{
  "type": "Feature",
  "properties": {
    "addr:full":"Via Michelangelo 3 46040 Guidizzolo Guidizzolo Mantova 46040",
    "addr:housenumber":"3",
    "addr:postcode":"46040;46040",
    "addr:street":"Via Michelangelo",
    "iso:country":"IT",
    "sg:address":"Via Michelangelo 3 46040 Guidizzolo",
    "sg:city":"Guidizzolo",
    "sg:classifiers":[
        {
            "category":"Real Estate",
            "subcategory":"Architect",
            "type":"Services"
        }
    ],
    "sg:phone":"+39 0376 840442",
    "sg:postcode":"46040",
    "sg:province":"Mantova",
    "sg:tags":[
        "pattern",
        "model",
        "making",
        "supplies"
    ],
    "sg:website":"www.grpgandini.com",
    "wof:name":"Grp Gandini Racing Production Srl",
    "wof:placetype":"venue"
},
  "geometry": {"coordinates":[10.7976980209,45.1603660583],"type":"Point"}
}