{
  "type": "Feature",
  "properties": {
    "iso:country":"IT",
    "sg:address":"16154 Genova",
    "sg:city":"Genova",
    "sg:orig_category":"Agricoltura, Orticoltura E Floricoltura",
    "sg:phone":"+39 010 601 8496",
    "sg:postcode":"16154",
    "sg:province":"Genova",
    "wof:name":"Ente Tabacchi Italiani E.t.i.",
    "wof:placetype":"venue"
},
  "geometry": {"coordinates":[8.844083,44.42461],"type":"Point"}
}