{
  "type": "Feature",
  "properties": {
    "iso:country":"IT",
    "sg:address":"06089 Torgiano",
    "sg:city":"Brufa",
    "sg:orig_category":"Istituti Di Bellezza",
    "sg:phone":"+39 075 988 9202",
    "sg:postcode":"06089",
    "sg:province":"Perugia",
    "wof:name":"Tutto Benessere Sas",
    "wof:placetype":"venue"
},
  "geometry": {"coordinates":[12.477863,43.059025],"type":"Point"}
}