{
  "type": "Feature",
  "properties": {
    "iso:country":"IT",
    "sg:address":"Via Nazionale 5 84015 Nocera Superiore",
    "sg:city":"Nocera Superiore",
    "sg:classifiers":[
        {
            "category":"Professional",
            "subcategory":"Advertising",
            "type":"Services"
        }
    ],
    "sg:phone":"+39 081 931672",
    "sg:postcode":"84015",
    "sg:province":"Salerno",
    "sg:tags":[
        "article",
        "porcelain",
        "ceramic"
    ],
    "sg:website":"www.vietri-ceramic.it",
    "wof:name":"Vietri Ceramic Group Scarl",
    "wof:placetype":"venue"
},
  "geometry": {"coordinates":[14.683858,40.734478],"type":"Point"}
}