{
  "type": "Feature",
  "properties": {
    "iso:country":"IT",
    "sg:address":"5, Via Caduti Del Lavoro 37049 Villa Bartolomea",
    "sg:city":"Villa Bartolomea",
    "sg:classifiers":[
        {
            "category":"Professional",
            "subcategory":"Engineering",
            "type":"Services"
        }
    ],
    "sg:phone":"+39 0442 659030",
    "sg:postcode":"37049",
    "sg:province":"Verona",
    "sg:tags":[
        "machine",
        "-",
        "mechanical"
    ],
    "wof:name":"Frigoveneta S.r.l.",
    "wof:placetype":"venue"
},
  "geometry": {"coordinates":[11.354968,45.144073],"type":"Point"}
}