{
  "type": "Feature",
  "properties": {
    "iso:country":"IT",
    "sg:address":"5, Via Santa Maria 63044 Comunanza",
    "sg:city":"Comunanza",
    "sg:classifiers":[
        {
            "category":"Manufacturing",
            "subcategory":"Metals",
            "type":"Manufacturing & Wholesale Goods"
        }
    ],
    "sg:phone":"+39 0736 845773",
    "sg:postcode":"63044",
    "sg:province":"Ascoli Piceno",
    "sg:tags":[
        "processing"
    ],
    "wof:name":"Metaltech 2000 Srl",
    "wof:placetype":"venue"
},
  "geometry": {"coordinates":[13.4258527756,42.9644508362],"type":"Point"}
}