{
  "type": "Feature",
  "properties": {
    "iso:country":"IT",
    "sg:address":"Via Erbera 1 28887 Omegna",
    "sg:city":"Omegna",
    "sg:orig_category":"Turned Parts Of Brass",
    "sg:phone":"+39 0323 862257",
    "sg:postcode":"28887",
    "sg:province":"Verbano-Cusio-Ossola",
    "sg:website":"www.tormet.com",
    "wof:name":"Tor.met Srl",
    "wof:placetype":"venue"
},
  "geometry": {"coordinates":[8.272465,46.139969],"type":"Point"}
}