{
  "type": "Feature",
  "properties": {
    "addr:full":"10078 Venaria Torino 10078",
    "addr:postcode":"10078;10078",
    "iso:country":"IT",
    "sg:address":"10078 Venaria",
    "sg:orig_category":"Utensili Meccanici E Materiali",
    "sg:phone":"+39 011 226 5346",
    "sg:postcode":"10078",
    "sg:province":"Torino",
    "wof:name":"Baldo Modelli S.n.c.",
    "wof:placetype":"venue"
},
  "geometry": {"coordinates":[7.640901,45.112282],"type":"Point"}
}