{
  "type": "Feature",
  "properties": {
    "iso:country":"IT",
    "sg:address":"22066 Mariano Comense",
    "sg:city":"Mariano Comense",
    "sg:orig_category":"Forniture Per Abbigliamento E Pelletterie. Forniture Per Attivita' Commerciali Ed Artigianali",
    "sg:phone":"+39 031 743666",
    "sg:postcode":"22066",
    "sg:province":"Como",
    "wof:name":"Almax Spa",
    "wof:placetype":"venue"
},
  "geometry": {"coordinates":[9.1737108231,45.6868362427],"type":"Point"}
}