{
  "type": "Feature",
  "properties": {
    "iso:country":"IT",
    "sg:address":"07035 Sedini",
    "sg:city":"Sedini",
    "sg:orig_category":"Pozzi Neri",
    "sg:phone":"+39 079 200252",
    "sg:postcode":"07035",
    "sg:province":"Sassari",
    "wof:name":"Ecologica Alfa Srl",
    "wof:placetype":"venue"
},
  "geometry": {"coordinates":[8.8032045364,40.854221344],"type":"Point"}
}