{
  "type": "Feature",
  "properties": {
    "addr:full":"12/200, Strada St. 125 09044 Quartucciu Quartucciu Cagliari 09044",
    "addr:housenumber":"12 / 200;125",
    "addr:postcode":"09044;09044",
    "addr:street":"Strada St.",
    "iso:country":"IT",
    "sg:address":"12/200, Strada St. 125 09044 Quartucciu",
    "sg:city":"Quartucciu",
    "sg:classifiers":[
        {
            "category":"Travel",
            "subcategory":"Travel Agent",
            "type":"Entertainment"
        }
    ],
    "sg:phone":"+39 39070850344",
    "sg:postcode":"09044",
    "sg:province":"Cagliari",
    "sg:tags":[
        "business"
    ],
    "wof:name":"Hotel I Ginepri",
    "wof:placetype":"venue"
},
  "geometry": {"coordinates":[9.109228,39.215458],"type":"Point"}
}