{
  "type": "Feature",
  "properties": {
    "iso:country":"IT",
    "sg:address":"42, Frazione Ca' Cappello 45014 Porto Viro",
    "sg:city":"Porto Viro",
    "sg:classifiers":[
        {
            "category":"Building & Trades",
            "subcategory":"Construction",
            "type":"Services"
        }
    ],
    "sg:phone":"+39 0426 632874",
    "sg:postcode":"45014",
    "sg:province":"Rovigo",
    "sg:tags":[
        "work",
        "public"
    ],
    "wof:name":"C.g.x Costruzioni Generali Xodo (s.r.l.)",
    "wof:placetype":"venue"
},
  "geometry": {"coordinates":[12.262171,45.052834],"type":"Point"}
}