{
  "type": "Feature",
  "properties": {
    "iso:country":"IT",
    "sg:address":"Via Molise 10 20098 S.giuliano Milanese",
    "sg:classifiers":[
        {
            "category":"Shopping",
            "subcategory":"Gifts & Souvenirs",
            "type":"Retail Goods"
        }
    ],
    "sg:phone":"+39 02 988 1021",
    "sg:postcode":"20098",
    "sg:province":"Milano",
    "sg:tags":[
        "item"
    ],
    "sg:website":"www.biancardi.com",
    "wof:name":"Biancardi International Srl",
    "wof:placetype":"venue"
},
  "geometry": {"coordinates":[9.257717,45.396847],"type":"Point"}
}