{
  "type": "Feature",
  "properties": {
    "iso:country":"IT",
    "sg:address":"87046 Montalto Uffugo",
    "sg:city":"Montalto Uffugo",
    "sg:orig_category":"Servizi Per Lo Sport E Il Tempo Libero. Ristoranti Ed Esercizi Affini. Servizi Ausiliari Di Ristorazione E Di Intrattenimento",
    "sg:phone":"+39 0984 938799",
    "sg:postcode":"87046",
    "sg:province":"Cosenza",
    "wof:name":"Giule' Di Pastore M. Antonietta",
    "wof:placetype":"venue"
},
  "geometry": {"coordinates":[16.244337,39.392654],"type":"Point"}
}