{
  "type": "Feature",
  "properties": {
    "addr:full":"60, Via S. Giovanni Bosco 24126 Bergamo Bergamo Bergamo 24126",
    "addr:postcode":"24126;24126",
    "addr:street":"Via S. Giovanni Bosco",
    "iso:country":"IT",
    "sg:address":"60, Via S. Giovanni Bosco 24126 Bergamo",
    "sg:city":"Bergamo",
    "sg:classifiers":[
        {
            "category":"Professional",
            "subcategory":"Business Services",
            "type":"Services"
        }
    ],
    "sg:phone":"+39 39035315600",
    "sg:postcode":"24126",
    "sg:province":"Bergamo",
    "sg:tags":[
        "advice"
    ],
    "wof:name":"O.s.i. Office Service Informatica (s.r.l.)",
    "wof:placetype":"venue"
},
  "geometry": {"coordinates":[9.669952,45.694904],"type":"Point"}
}