{
  "type": "Feature",
  "properties": {
    "iso:country":"IT",
    "sg:address":"Via Provinciale Di Mercatale 83 50059 Vinci",
    "sg:city":"Vinci",
    "sg:classifiers":[
        {
            "category":"Shopping",
            "subcategory":"Stationery & Office Supplies",
            "type":"Retail Goods"
        }
    ],
    "sg:phone":"+39 0571 902095",
    "sg:postcode":"50059",
    "sg:province":"Firenze",
    "sg:tags":[
        "adhesive",
        "label"
    ],
    "sg:website":"www.lamar.it",
    "wof:name":"Lamar Srl",
    "wof:placetype":"venue"
},
  "geometry": {"coordinates":[10.906584,43.755516],"type":"Point"}
}