{
  "type": "Feature",
  "properties": {
    "iso:country":"IT",
    "sg:address":"10, Via Olmetto 20123 Milano",
    "sg:city":"Milano",
    "sg:classifiers":[
        {
            "category":"Communications",
            "subcategory":"Newspaper",
            "type":"Services"
        }
    ],
    "sg:phone":"+39 39028900511",
    "sg:postcode":"20123",
    "sg:province":"Milano",
    "sg:tags":[
        "advertising"
    ],
    "wof:name":"Colombi C. & E. Srl",
    "wof:placetype":"venue"
},
  "geometry": {"coordinates":[9.185144,45.459351],"type":"Point"}
}