{
  "type": "Feature",
  "properties": {
    "iso:country":"IT",
    "sg:address":"11, Borgo Fagare' 31040 Pederobba",
    "sg:city":"Pederobba",
    "sg:classifiers":[
        {
            "category":"Farming",
            "subcategory":"Livestock Farm",
            "type":"Manufacturing & Wholesale Goods"
        }
    ],
    "sg:phone":"+39 39042383530",
    "sg:postcode":"31040",
    "sg:province":"Treviso",
    "sg:tags":[
        "agriculture"
    ],
    "wof:name":"Italspawn Italia (s.r.l.)",
    "wof:placetype":"venue"
},
  "geometry": {"coordinates":[11.98677,45.844765],"type":"Point"}
}