{
  "type": "Feature",
  "properties": {
    "iso:country":"IT",
    "sg:address":"00185 Roma",
    "sg:city":"Roma",
    "sg:orig_category":"Associazioni Ed Organismi Di Interesse Pubblico",
    "sg:phone":"+39 06 702 4973",
    "sg:postcode":"00185",
    "sg:province":"Roma",
    "wof:name":"Associazione Focus Federazione Organizz.consum.utenti E Soc",
    "wof:placetype":"venue"
},
  "geometry": {"coordinates":[12.509727,41.897701],"type":"Point"}
}