{
  "type": "Feature",
  "properties": {
    "iso:country":"IT",
    "sg:address":"47838 Riccione",
    "sg:city":"Riccione",
    "sg:orig_category":"Servizi Per Aziende, Manifestazioni E Supporto Agli Scambi Commerciali",
    "sg:phone":"+39 0541 644100",
    "sg:postcode":"47838",
    "sg:province":"Rimini",
    "sg:website":"http://www.hotelkursaal.it",
    "wof:name":"Hotel Kursaal",
    "wof:placetype":"venue"
},
  "geometry": {"coordinates":[12.651234,44.009365],"type":"Point"}
}