{
  "type": "Feature",
  "properties": {
    "iso:country":"IT",
    "sg:address":"4, Piazzale Donegani G. 05100 Terni",
    "sg:city":"Terni",
    "sg:classifiers":[
        {
            "category":"Manufacturing",
            "subcategory":"Rubber & Plastics",
            "type":"Manufacturing & Wholesale Goods"
        }
    ],
    "sg:phone":"+39 0744 806211",
    "sg:postcode":"05100",
    "sg:province":"Terni",
    "wof:name":"Novamont Spa",
    "wof:placetype":"venue"
},
  "geometry": {"coordinates":[12.6251974106,42.5723075867],"type":"Point"}
}