{
  "type": "Feature",
  "properties": {
    "iso:country":"IT",
    "sg:address":"Via Fara Gustavo 39 20124 Milano",
    "sg:city":"Milano",
    "sg:classifiers":[
        {
            "category":"Wholesale",
            "subcategory":"Office Equipment",
            "type":"Manufacturing & Wholesale Goods"
        }
    ],
    "sg:phone":"+39 02 670 9561",
    "sg:postcode":"20124",
    "sg:province":"Milano",
    "sg:tags":[
        "promotional"
    ],
    "sg:website":"www.sparaciari.it",
    "wof:name":"Sparaciari Hits Srl",
    "wof:placetype":"venue"
},
  "geometry": {"coordinates":[9.198387146,45.4838829041],"type":"Point"}
}