{
  "type": "Feature",
  "properties": {
    "iso:country":"IT",
    "sg:address":"59100 Prato",
    "sg:city":"Prato",
    "sg:orig_category":"Abbigliamento Esterno, Maglierie E Pelliccerie. Forniture Per Abbigliamento E Pelletterie",
    "sg:phone":"+39 0574 36993",
    "sg:postcode":"59100",
    "sg:province":"Prato",
    "wof:name":"Carlesi Roberto",
    "wof:placetype":"venue"
},
  "geometry": {"coordinates":[11.050637,43.924248],"type":"Point"}
}