{
  "type": "Feature",
  "properties": {
    "iso:country":"IT",
    "sg:address":"102, V. San Gaetanino 48100 Ravenna",
    "sg:city":"Ravenna",
    "sg:orig_category":"Miscellaneous Products",
    "sg:phone":"+39 0544 454020",
    "sg:postcode":"48100",
    "sg:province":"Ravenna",
    "sg:website":"http://www.domenichini.it",
    "wof:name":"Pompe Funebri Domenichini",
    "wof:placetype":"venue"
},
  "geometry": {"coordinates":[12.1981954575,44.4235343933],"type":"Point"}
}