{
  "type": "Feature",
  "properties": {
    "iso:country":"IT",
    "sg:address":"00185 Roma",
    "sg:city":"Roma",
    "sg:orig_category":"Pubblicita' Diretta",
    "sg:phone":"+39 06 7045 1270",
    "sg:postcode":"00185",
    "sg:province":"Roma",
    "wof:name":"S.c.a.i. Srl Servizi Consulenza Aziendale Internazionale",
    "wof:placetype":"venue"
},
  "geometry": {"coordinates":[12.4549541473,41.8578796387],"type":"Point"}
}