{
  "type": "Feature",
  "properties": {
    "iso:country":"IT",
    "sg:address":"20010 Casorezzo",
    "sg:city":"Casorezzo",
    "sg:orig_category":"Petroli, Gas E Combustibili. Servizi E Lavori Industria Chimica. Servizi E Lavori Per Edilizia E Lavori Pubblici. Acqua, Luce, Gas E Societa' Di Esercizio Pubblico",
    "sg:phone":"+39 02 9038 0534",
    "sg:postcode":"20010",
    "sg:province":"Milano",
    "wof:name":"A. Dim Srl",
    "wof:placetype":"venue"
},
  "geometry": {"coordinates":[8.9013748169,45.5237960815],"type":"Point"}
}