{
  "type": "Feature",
  "properties": {
    "addr:full":"21011 Casorate Sempione Casorate Sempione Varese 21011",
    "addr:postcode":"21011;21011",
    "iso:country":"IT",
    "sg:address":"21011 Casorate Sempione",
    "sg:city":"Casorate Sempione",
    "sg:orig_category":"Agenzie D'affari E Servizi Commerciali",
    "sg:phone":"+39 0331 296713",
    "sg:postcode":"21011",
    "sg:province":"Varese",
    "wof:name":"Cappelletti Antonio - Ufficio Seat Pagine Gialle",
    "wof:placetype":"venue"
},
  "geometry": {"coordinates":[8.748086,45.672691],"type":"Point"}
}