{
  "type": "Feature",
  "properties": {
    "addr:full":"25065 Lumezzane Lumezzane Brescia 25065",
    "addr:postcode":"25065;25065",
    "iso:country":"IT",
    "sg:address":"25065 Lumezzane",
    "sg:city":"Lumezzane",
    "sg:orig_category":"Servizi E Lavori Per Agricoltura E Zootecnia. Servizi E Lavori Industria Chimica. Servizi Ausiliari Di Analisi, Controllo E Ricerca",
    "sg:phone":"+39 030 829885",
    "sg:postcode":"25065",
    "sg:province":"Brescia",
    "wof:name":"Ageostan Di Bonetti Rosanna E C. S.n.c.",
    "wof:placetype":"venue"
},
  "geometry": {"coordinates":[10.167588,45.460186],"type":"Point"}
}