{
  "type": "Feature",
  "properties": {
    "addr:full":"95047 Patern\u00f2 Catania 95047",
    "addr:postcode":"95047;95047",
    "iso:country":"IT",
    "sg:address":"95047 Patern\u00f2",
    "sg:orig_category":"Servizi E Lavori Per Arredamento E Industria Del Legno. Forniture Per Congressi, Fiere E Manifestazioni. Servizi Per Aziende, Manifestazioni E Supporto Agli Scambi Commerciali",
    "sg:phone":"+39 095 843035",
    "sg:postcode":"95047",
    "sg:province":"Catania",
    "wof:name":"Motta Mario Pietro",
    "wof:placetype":"venue"
},
  "geometry": {"coordinates":[14.834902,37.487728],"type":"Point"}
}