{
  "type": "Feature",
  "properties": {
    "addr:full":"09134 Cagliari Cagliari Cagliari 09134",
    "addr:postcode":"09134;09134",
    "iso:country":"IT",
    "sg:address":"09134 Cagliari",
    "sg:city":"Cagliari",
    "sg:classifiers":[
        {
            "category":"Utilities",
            "subcategory":"Fuel Oil & Lpg",
            "type":"Services"
        }
    ],
    "sg:phone":"+39 070 554230",
    "sg:postcode":"09134",
    "sg:province":"Cagliari",
    "sg:tags":[
        "auxiliary",
        "light",
        "vehicles",
        "gas",
        "water",
        "motor",
        "services",
        "public",
        "transport"
    ],
    "wof:name":"S.i.ge. Societa' Interventi Generali Srl",
    "wof:placetype":"venue"
},
  "geometry": {"coordinates":[9.1216640472,39.2425537109],"type":"Point"}
}