{
  "type": "Feature",
  "properties": {
    "addr:full":"00147 Roma Roma Roma 00147",
    "addr:postcode":"00147;00147",
    "iso:country":"IT",
    "sg:address":"00147 Roma",
    "sg:city":"Roma",
    "sg:classifiers":[
        {
            "category":"Professional",
            "subcategory":"Engineering",
            "type":"Services"
        }
    ],
    "sg:phone":"+39 06 5160 5039",
    "sg:postcode":"00147",
    "sg:province":"Roma",
    "sg:tags":[
        "electronic",
        "music",
        "non-professional"
    ],
    "sg:website":"http://www.megavideo.it",
    "wof:name":"Megavideo Audiovisivi Srl",
    "wof:placetype":"venue"
},
  "geometry": {"coordinates":[12.5021247864,41.8538589478],"type":"Point"}
}