{
  "type": "Feature",
  "properties": {
    "iso:country":"IT",
    "sg:address":"55045 Pietrasanta",
    "sg:city":"Pietrasanta",
    "sg:orig_category":"Forniture Per Attivita' Industriali",
    "sg:phone":"+39 0584 791192",
    "sg:postcode":"55045",
    "sg:province":"Lucca",
    "sg:website":"http://www.gubres.com",
    "wof:name":"Gubres Di Bresciani P & C. Sas",
    "wof:placetype":"venue"
},
  "geometry": {"coordinates":[10.5047826767,43.8399200439],"type":"Point"}
}