{
  "type": "Feature",
  "properties": {
    "iso:country":"IT",
    "sg:address":"00167 Roma",
    "sg:city":"Roma",
    "sg:orig_category":"Carni, Salumi E Pesci",
    "sg:phone":"+39 06 3974 9880",
    "sg:postcode":"00167",
    "sg:province":"Roma",
    "wof:name":"Provendica Srl",
    "wof:placetype":"venue"
},
  "geometry": {"coordinates":[12.436146,41.901714],"type":"Point"}
}