{
  "type": "Feature",
  "properties": {
    "addr:full":"35010 Vigonza Vigonza Padova 35010",
    "addr:postcode":"35010;35010",
    "iso:country":"IT",
    "sg:address":"35010 Vigonza",
    "sg:city":"Vigonza",
    "sg:orig_category":"Modelli Per Fonderie",
    "sg:phone":"+39 049 893 0400",
    "sg:postcode":"35010",
    "sg:province":"Padova",
    "wof:name":"Modelleria Buggin Mario Snc",
    "wof:placetype":"venue"
},
  "geometry": {"coordinates":[11.9518842697,45.4333496094],"type":"Point"}
}