{
  "type": "Feature",
  "properties": {
    "addr:full":"10152 Torino Torino Torino 10152",
    "addr:postcode":"10152;10152",
    "iso:country":"IT",
    "sg:address":"10152 Torino",
    "sg:city":"Torino",
    "sg:orig_category":"Fotoriproduttori E Fotocopiatrici",
    "sg:phone":"+39 011 436 3391",
    "sg:postcode":"10152",
    "sg:province":"Torino",
    "wof:name":"C.v.a.",
    "wof:placetype":"venue"
},
  "geometry": {"coordinates":[7.6750397682,45.0856132507],"type":"Point"}
}