{
  "type": "Feature",
  "properties": {
    "addr:full":"42023 Cadelbosco Di Sopra Reggio Nell'Emilia 42023",
    "addr:postcode":"42023;42023",
    "iso:country":"IT",
    "sg:address":"42023 Cadelbosco Di Sopra",
    "sg:orig_category":"Cilindri E Pistoni Per Motori",
    "sg:phone":"+39 0522 915014",
    "sg:postcode":"42023",
    "sg:province":"Reggio Nell'Emilia",
    "wof:name":"Vertex Pistons A Division Of Dover Italy Srl",
    "wof:placetype":"venue"
},
  "geometry": {"coordinates":[10.602015,44.755329],"type":"Point"}
}