{
  "type": "Feature",
  "properties": {
    "addr:full":"27036 Mortara Mortara Pavia 27036",
    "addr:postcode":"27036;27036",
    "iso:country":"IT",
    "sg:address":"27036 Mortara",
    "sg:city":"Mortara",
    "sg:orig_category":"Servizi Per Aziende, Manifestazioni E Supporto Agli Scambi Commerciali",
    "sg:phone":"+39 0384 99833",
    "sg:postcode":"27036",
    "sg:province":"Pavia",
    "wof:name":"Passi Sandro",
    "wof:placetype":"venue"
},
  "geometry": {"coordinates":[8.73668,45.250366],"type":"Point"}
}