{
  "type": "Feature",
  "properties": {
    "addr:full":"Via Liguria, 11/15 41012 Carpi Carpi Modena 41012",
    "addr:housenumber":"11 / 15",
    "addr:postcode":"41012;41012",
    "addr:street":"Via Liguria",
    "iso:country":"IT",
    "sg:address":"Via Liguria, 11/15 41012 Carpi",
    "sg:city":"Carpi",
    "sg:orig_category":"Packaging Plants For Pharmaceuticals And Cosmetics",
    "sg:phone":"+39 059 694230",
    "sg:postcode":"41012",
    "sg:province":"Modena",
    "wof:name":"Partena Spa",
    "wof:placetype":"venue"
},
  "geometry": {"coordinates":[10.8805265427,44.7656135559],"type":"Point"}
}