{
  "type": "Feature",
  "properties": {
    "iso:country":"IT",
    "sg:address":"Localit\u00e0 S. Zeno 28 52100 Arezzo",
    "sg:city":"Arezzo",
    "sg:classifiers":[
        {
            "category":"Professional",
            "subcategory":"Art Services",
            "type":"Services"
        }
    ],
    "sg:phone":"+39 0575 99059",
    "sg:postcode":"52100",
    "sg:province":"Arezzo",
    "sg:tags":[
        "shop",
        "design"
    ],
    "wof:name":"Severi Snc",
    "wof:placetype":"venue"
},
  "geometry": {"coordinates":[11.819435,43.462509],"type":"Point"}
}