{
  "type": "Feature",
  "properties": {
    "addr:full":"Via Piemonte 34; Rome",
    "addr:housenumber":"34",
    "addr:street":"Via Piemonte",
    "iso:country":"IT",
    "sg:address":"Via Piemonte 34; Rome",
    "sg:classifiers":[
        {
            "category":"Travel",
            "subcategory":"Travel Agent",
            "type":"Entertainment"
        }
    ],
    "wof:name":"Vastours Srl",
    "wof:placetype":"venue"
},
  "geometry": {"coordinates":[12.493996,41.906609],"type":"Point"}
}