{
  "type": "Feature",
  "properties": {
    "iso:country":"IT",
    "sg:address":"10078 Venaria",
    "sg:orig_category":"Apparecchiature Pneumatiche Ed Idropneumatiche",
    "sg:phone":"+39 011 424 1810",
    "sg:postcode":"10078",
    "sg:province":"Torino",
    "wof:name":"A.n.s. Spa",
    "wof:placetype":"venue"
},
  "geometry": {"coordinates":[7.631154,45.114254],"type":"Point"}
}