{
  "type": "Feature",
  "properties": {
    "iso:country":"IT",
    "sg:address":"Via Manzoni 4 10092 Beinasco",
    "sg:city":"Beinasco",
    "sg:classifiers":[
        {
            "category":"Professional",
            "subcategory":"Printing & Photocopies",
            "type":"Services"
        }
    ],
    "sg:phone":"+39 011 397 2308",
    "sg:postcode":"10092",
    "sg:province":"Torino",
    "sg:tags":[
        "paper"
    ],
    "sg:website":"www.ibgroup.it",
    "wof:name":"Italcart Srl",
    "wof:placetype":"venue"
},
  "geometry": {"coordinates":[7.5743556023,45.0154418945],"type":"Point"}
}