{
  "type": "Feature",
  "properties": {
    "addr:full":"22100 Como Como Como 22100",
    "addr:postcode":"22100;22100",
    "iso:country":"IT",
    "sg:address":"22100 Como",
    "sg:city":"Como",
    "sg:orig_category":"Studi E Consulenze Amministrative, Commerciali E Aziendali. Banche E Servizi Finanziari. Agenzie D'affari E Servizi Commerciali. Consulenze Tecniche, Amministrative E Perizie",
    "sg:phone":"+39 031 271356",
    "sg:postcode":"22100",
    "sg:province":"Como",
    "sg:website":"http://www.immobiliarevolta.it",
    "wof:name":"Immobiliare Volta",
    "wof:placetype":"venue"
},
  "geometry": {"coordinates":[9.128322,45.741566],"type":"Point"}
}