{
  "type": "Feature",
  "properties": {
    "iso:country":"IT",
    "sg:address":"Via Ponte Pietra 11 48010 Cotignola",
    "sg:city":"Cotignola",
    "sg:classifiers":[
        {
            "category":"Military Area",
            "subcategory":"Air Force Base",
            "type":"Public Place"
        }
    ],
    "sg:phone":"+39 0545 40123",
    "sg:postcode":"48010",
    "sg:province":"Ravenna",
    "sg:tags":[
        "facing",
        "brick",
        "cement"
    ],
    "sg:website":"www.iblspa.it",
    "wof:name":"Ibl Spa",
    "wof:placetype":"venue"
},
  "geometry": {"coordinates":[11.919549,44.381088],"type":"Point"}
}