{
  "type": "Feature",
  "properties": {
    "addr:full":"57121 Livorno Livorno Livorno 57121",
    "addr:postcode":"57121;57121",
    "iso:country":"IT",
    "sg:address":"57121 Livorno",
    "sg:city":"Livorno",
    "sg:orig_category":"Cartotecnica E Servizi. Articoli Per Imballaggio E Confezionamento",
    "sg:phone":"+39 0586 420077",
    "sg:postcode":"57121",
    "sg:province":"Livorno",
    "sg:website":"http://www.artigrafiche.pellegrini.it",
    "wof:name":"Arti Grafiche Fratelli Pellegrini Snc",
    "wof:placetype":"venue"
},
  "geometry": {"coordinates":[10.337725,43.566814],"type":"Point"}
}