{
  "type": "Feature",
  "properties": {
    "addr:full":"5332, S. Marco 30124 Venezia Venezia Venezia 30124",
    "addr:housenumber":"5332",
    "addr:postcode":"30124;30124",
    "addr:street":"S. Marco",
    "iso:country":"IT",
    "sg:address":"5332, S. Marco 30124 Venezia",
    "sg:city":"Venezia",
    "sg:classifiers":[
        {
            "category":"Shopping",
            "subcategory":"Crafts & Fabrics",
            "type":"Retail Goods"
        }
    ],
    "sg:phone":"+39 041 528 6905",
    "sg:postcode":"30124",
    "sg:province":"Venezia",
    "wof:name":"Karin",
    "wof:placetype":"venue"
},
  "geometry": {"coordinates":[12.3344640732,45.4325065613],"type":"Point"}
}