{
  "type": "Feature",
  "properties": {
    "iso:country":"IT",
    "sg:address":"33100 Udine",
    "sg:city":"Udine",
    "sg:classifiers":[
        {
            "category":"Home & Garden",
            "subcategory":"Hardware",
            "type":"Retail Goods"
        }
    ],
    "sg:phone":"+39 0432 506051",
    "sg:postcode":"33100",
    "sg:province":"Udine",
    "wof:name":"Edil Friuli Spa",
    "wof:placetype":"venue"
},
  "geometry": {"coordinates":[13.234292,46.056099],"type":"Point"}
}