{
  "type": "Feature",
  "properties": {
    "addr:full":"39, Via Galliano Giuseppe 20013 Magenta Magenta Milano 20013",
    "addr:postcode":"20013;20013",
    "addr:street":"Via Galliano Giuseppe",
    "iso:country":"IT",
    "sg:address":"39, Via Galliano Giuseppe 20013 Magenta",
    "sg:city":"Magenta",
    "sg:classifiers":[
        {
            "category":"Home & Garden",
            "subcategory":"Home Furnishings",
            "type":"Retail Goods"
        }
    ],
    "sg:phone":"+39 02 9729 7222",
    "sg:postcode":"20013",
    "sg:province":"Milano",
    "sg:tags":[
        "household"
    ],
    "wof:name":"Oldani Arredamenti S.r.l.",
    "wof:placetype":"venue"
},
  "geometry": {"coordinates":[9.188141,45.463688],"type":"Point"}
}