{
  "type": "Feature",
  "properties": {
    "addr:full":"7, Via Quattro Vie 40050 Castello D'argile Bologna 40050",
    "addr:postcode":"40050;40050",
    "addr:street":"Via Quattro Vie",
    "iso:country":"IT",
    "sg:address":"7, Via Quattro Vie 40050 Castello D'argile",
    "sg:classifiers":[
        {
            "category":"Wholesale",
            "subcategory":"Drugs",
            "type":"Manufacturing & Wholesale Goods"
        }
    ],
    "sg:phone":"+39 051 686 7060",
    "sg:postcode":"40050",
    "sg:province":"Bologna",
    "sg:tags":[
        "chemical",
        "pharmaceutical"
    ],
    "wof:name":"Autoadesivi Magri (s.r.l.)",
    "wof:placetype":"venue"
},
  "geometry": {"coordinates":[11.341557,44.680233],"type":"Point"}
}