{
  "type": "Feature",
  "properties": {
    "iso:country":"IT",
    "sg:address":"Via Pra' Cabrolo 11 36036 Torrebelvicino",
    "sg:city":"Torrebelvicino",
    "sg:classifiers":[
        {
            "category":"Manufacturing",
            "subcategory":"Wood Products",
            "type":"Manufacturing & Wholesale Goods"
        }
    ],
    "sg:phone":"+39 0445 661240",
    "sg:postcode":"36036",
    "sg:province":"Vicenza",
    "sg:tags":[
        "semi-finished"
    ],
    "wof:name":"Rino Pretto & C. Snc",
    "wof:placetype":"venue"
},
  "geometry": {"coordinates":[11.277768,45.731285],"type":"Point"}
}