{
  "type": "Feature",
  "properties": {
    "addr:full":"63010 Torre San Patrizio Torre San Patrizio Ascoli Piceno 63010",
    "addr:postcode":"63010;63010",
    "addr:street":"San;San",
    "iso:country":"IT",
    "sg:address":"63010 Torre San Patrizio",
    "sg:city":"Torre San Patrizio",
    "sg:orig_category":"Trasporti E Spedizioni Merci",
    "sg:phone":"+39 0734 510220",
    "sg:postcode":"63010",
    "sg:province":"Ascoli Piceno",
    "wof:name":"Costanzi Claudio",
    "wof:placetype":"venue"
},
  "geometry": {"coordinates":[13.616502,43.17791],"type":"Point"}
}