{
  "type": "Feature",
  "properties": {
    "iso:country":"IT",
    "sg:address":"80059 Torre Del Greco",
    "sg:city":"Torre del Greco",
    "sg:orig_category":"Architetti - Studi",
    "sg:phone":"+39 081 881 6739",
    "sg:postcode":"80059",
    "sg:province":"Napoli",
    "wof:name":"Studio Tecnico G. & O.",
    "wof:placetype":"venue"
},
  "geometry": {"coordinates":[14.333396,40.820606],"type":"Point"}
}