{
  "type": "Feature",
  "properties": {
    "iso:country":"IT",
    "sg:address":"7, Via Dell' Industria 37010 Costermano",
    "sg:city":"Costermano",
    "sg:classifiers":[
        {
            "category":"Professional",
            "subcategory":"Engineering",
            "type":"Services"
        }
    ],
    "sg:phone":"+39 045 620 0851",
    "sg:postcode":"37010",
    "sg:province":"Verona",
    "sg:tags":[
        "machine",
        "-",
        "mechanical"
    ],
    "wof:name":"Euro Tools S.r.l.",
    "wof:placetype":"venue"
},
  "geometry": {"coordinates":[10.76964,45.567253],"type":"Point"}
}