{
  "type": "Feature",
  "properties": {
    "addr:full":"40124 Bologna Bologna Bologna 40124",
    "addr:postcode":"40124;40124",
    "iso:country":"IT",
    "sg:address":"40124 Bologna",
    "sg:city":"Bologna",
    "sg:orig_category":"Servizi Ausiliari Di Certificati, Riproduzioni, Disegni E Foto",
    "sg:phone":"+39 051 235409",
    "sg:postcode":"40124",
    "sg:province":"Bologna",
    "wof:name":"Studio Eliografico S. Stefano Sas",
    "wof:placetype":"venue"
},
  "geometry": {"coordinates":[11.350737,44.487724],"type":"Point"}
}