{
  "type": "Feature",
  "properties": {
    "iso:country":"IT",
    "sg:address":"20132 Milano",
    "sg:city":"Milano",
    "sg:orig_category":"Servizi Per Lo Sport E Il Tempo Libero. Servizi Al Turismo",
    "sg:phone":"+39 02 2641 2295",
    "sg:postcode":"20132",
    "sg:province":"Milano",
    "sg:website":"http://www.newtrefor.it",
    "wof:name":"Newtrefor",
    "wof:placetype":"venue"
},
  "geometry": {"coordinates":[9.240137,45.491909],"type":"Point"}
}