{
  "type": "Feature",
  "properties": {
    "addr:full":"90100 Palermo PA",
    "addr:postcode":"90100",
    "iso:country":"IT",
    "sg:address":"90100 Palermo",
    "sg:orig_category":"Forniture E Materiali Per Imballaggio E Confezionamento. Forniture Per Uffici. Forniture Per Attivita' Commerciali Ed Artigianali",
    "sg:phone":"+39 800 802 145",
    "sg:province":"PA",
    "wof:name":"3m Italia Spa",
    "wof:placetype":"venue"
},
  "geometry": {"coordinates":[13.3584499359,38.1213111877],"type":"Point"}
}