{
  "type": "Feature",
  "properties": {
    "iso:country":"IT",
    "sg:address":"90047 Partinico",
    "sg:city":"Partinico",
    "sg:orig_category":"Torrefazione Di Caffe' Ed Affini - Lavorazione E Ingrosso",
    "sg:phone":"+39 091 878 2275",
    "sg:postcode":"90047",
    "sg:province":"Palermo",
    "wof:name":"Torrefazione Brasil",
    "wof:placetype":"venue"
},
  "geometry": {"coordinates":[13.379439,38.102894],"type":"Point"}
}