{
  "type": "Feature",
  "properties": {
    "iso:country":"IT",
    "sg:address":"10152 Torino",
    "sg:city":"Torino",
    "sg:orig_category":"Associazioni Artistiche, Culturali E Ricreative",
    "sg:phone":"+39 011 287 6148",
    "sg:postcode":"10152",
    "sg:province":"Torino",
    "wof:name":"Blubs Srl",
    "wof:placetype":"venue"
},
  "geometry": {"coordinates":[7.683692,45.089436],"type":"Point"}
}