{
  "type": "Feature",
  "properties": {
    "iso:country":"IT",
    "sg:address":"50021 Barberino Val D'elsa",
    "sg:orig_category":"Ristorazione E Locali Pubblici Affini. Servizi Per Lo Sport E Il Tempo Libero. Alberghi E Strutture Extra Alberghiere. Ristoranti Ed Esercizi Affini",
    "sg:phone":"+39 055 807 2849",
    "sg:postcode":"50021",
    "sg:province":"Firenze",
    "sg:website":"http://www.villa-francesca.it",
    "wof:name":"Ristorante Villa Francesca Di Mari G. S.",
    "wof:placetype":"venue"
},
  "geometry": {"coordinates":[11.150411,43.522034],"type":"Point"}
}