{
  "type": "Feature",
  "properties": {
    "addr:full":"47020 Longiano Longiano Forl\u00ec-Cesena 47020",
    "addr:postcode":"47020;47020",
    "iso:country":"IT",
    "sg:address":"47020 Longiano",
    "sg:city":"Longiano",
    "sg:orig_category":"Elettrotecnica Industriale, Prodotti E Apparecchiature",
    "sg:phone":"+39 0547 665946",
    "sg:postcode":"47020",
    "sg:province":"Forl\u00ec-Cesena",
    "wof:name":"Tecnosistemi",
    "wof:placetype":"venue"
},
  "geometry": {"coordinates":[12.340556,44.094585],"type":"Point"}
}