{
  "type": "Feature",
  "properties": {
    "iso:country":"IT",
    "sg:address":"Via Provinciale 12 35010 Campo San Martino",
    "sg:city":"Campo San Martino",
    "sg:classifiers":[
        {
            "category":"Food & Beverages",
            "subcategory":"Meat & Fish",
            "type":"Retail Goods"
        }
    ],
    "sg:phone":"+39 049 963 0455",
    "sg:postcode":"35010",
    "sg:province":"Padova",
    "wof:name":"Fratelli Tosetto Sas Comm.lavoraz.carni Di Tosetto Walter & C.",
    "wof:placetype":"venue"
},
  "geometry": {"coordinates":[11.817341,45.553913],"type":"Point"}
}