{
  "type": "Feature",
  "properties": {
    "addr:full":"07026 Olbia Olbia Olbia-Tempio 07026",
    "addr:postcode":"07026;07026",
    "iso:country":"IT",
    "sg:address":"07026 Olbia",
    "sg:city":"Olbia",
    "sg:classifiers":[
        {
            "category":"Shopping",
            "subcategory":"Stationery & Office Supplies",
            "type":"Retail Goods"
        }
    ],
    "sg:phone":"+39 0789 202391",
    "sg:postcode":"07026",
    "sg:province":"Olbia-Tempio",
    "sg:tags":[
        "equipment",
        "furniture",
        "furnishing",
        "professional"
    ],
    "wof:name":"Import Jati Di Aldo Altea",
    "wof:placetype":"venue"
},
  "geometry": {"coordinates":[9.2785587311,40.826839447],"type":"Point"}
}