{
  "type": "Feature",
  "properties": {
    "iso:country":"IT",
    "sg:address":"7, Via Peirce 00137 Roma",
    "sg:city":"Roma",
    "sg:classifiers":[
        {
            "category":"Sports & Exercise",
            "subcategory":"Playing Field",
            "type":"Entertainment"
        }
    ],
    "sg:phone":"+39 39068276915",
    "sg:postcode":"00137",
    "sg:province":"Roma",
    "sg:tags":[
        "game"
    ],
    "wof:name":"Eclisse",
    "wof:placetype":"venue"
},
  "geometry": {"coordinates":[12.560258,41.94326],"type":"Point"}
}