{
  "type": "Feature",
  "properties": {
    "iso:country":"IT",
    "sg:address":"27036 Mortara",
    "sg:city":"Mortara",
    "sg:orig_category":"Prodotti E Manufatti In Materie Plastiche",
    "sg:phone":"+39 0384 296628",
    "sg:postcode":"27036",
    "sg:province":"Pavia",
    "wof:name":"Ilpra Spa",
    "wof:placetype":"venue"
},
  "geometry": {"coordinates":[9.0913057327,45.2324447632],"type":"Point"}
}