{
  "type": "Feature",
  "properties": {
    "iso:country":"IT",
    "sg:address":"09121 Cagliari",
    "sg:city":"Cagliari",
    "sg:orig_category":"Apparecchiature E Sistemi Per Imballaggio E Confezionamento",
    "sg:phone":"+39 070 522577",
    "sg:postcode":"09121",
    "sg:province":"Cagliari",
    "wof:name":"Axor Srl Impianti, Trasformazioni, Ricambi Per Pastifici",
    "wof:placetype":"venue"
},
  "geometry": {"coordinates":[9.095819,39.270271],"type":"Point"}
}