{
  "type": "Feature",
  "properties": {
    "iso:country":"IT",
    "sg:address":"24043 Caravaggio",
    "sg:city":"Caravaggio",
    "sg:orig_category":"Servizi Di Magazzinaggio E Movimentazione. Servizi Ausiliari Di Sorveglianza, Manutenzione E Pulizia. Servizi Per Aziende, Manifestazioni E Supporto Agli Scambi Commerciali",
    "sg:phone":"+39 036 335 1085",
    "sg:postcode":"24043",
    "sg:province":"Bergamo",
    "wof:name":"Cooperativa Co.ma.is. Pscrl",
    "wof:placetype":"venue"
},
  "geometry": {"coordinates":[9.638906,45.529804],"type":"Point"}
}