{
  "type": "Feature",
  "properties": {
    "addr:full":"46035 Ostiglia Ostiglia Mantova 46035",
    "addr:postcode":"46035;46035",
    "iso:country":"IT",
    "sg:address":"46035 Ostiglia",
    "sg:city":"Ostiglia",
    "sg:orig_category":"Studi E Consulenze Amministrative, Commerciali E Aziendali. Consulenze Tecniche, Amministrative E Perizie",
    "sg:phone":"+39 0386 802280",
    "sg:postcode":"46035",
    "sg:province":"Mantova",
    "wof:name":"Polacchini Enrico",
    "wof:placetype":"venue"
},
  "geometry": {"coordinates":[10.847911,45.095539],"type":"Point"}
}