{
  "type": "Feature",
  "properties": {
    "iso:country":"IT",
    "sg:address":"10077 S. Maurizio Canavese",
    "sg:orig_category":"Ristorazione E Locali Pubblici Affini. Servizi Ausiliari Di Ristorazione E Di Intrattenimento",
    "sg:phone":"+39 119 278 201",
    "sg:postcode":"10077",
    "sg:province":"Torino",
    "sg:website":"http://www.banqueting.it",
    "wof:name":"Banqueting & Banqueting Di Bettas Begalin Ernesto",
    "wof:placetype":"venue"
},
  "geometry": {"coordinates":[7.616177,45.209888],"type":"Point"}
}