{
  "type": "Feature",
  "properties": {
    "iso:country":"IT",
    "sg:address":"1/h, Via Sotto Provinciale 24021 Albino",
    "sg:city":"Albino",
    "sg:classifiers":[
        {
            "category":"Manufacturing",
            "subcategory":"Lumber",
            "type":"Manufacturing & Wholesale Goods"
        }
    ],
    "sg:phone":"+39 39035773302",
    "sg:postcode":"24021",
    "sg:province":"Bergamo",
    "sg:tags":[
        "wood"
    ],
    "wof:name":"Chiodi E C. S.r.l.",
    "wof:placetype":"venue"
},
  "geometry": {"coordinates":[9.669952,45.694904],"type":"Point"}
}