{
  "type": "Feature",
  "properties": {
    "iso:country":"IT",
    "sg:address":"48100 Ravenna",
    "sg:city":"Ravenna",
    "sg:orig_category":"Edilizia - Attrezzature",
    "sg:phone":"+39 0544 472163",
    "sg:postcode":"48100",
    "sg:province":"Ravenna",
    "wof:name":"Romagna Noleggi Sas",
    "wof:placetype":"venue"
},
  "geometry": {"coordinates":[12.213957,44.263042],"type":"Point"}
}