{
  "type": "Feature",
  "properties": {
    "iso:country":"IT",
    "sg:address":"80132 Napoli",
    "sg:city":"Napoli",
    "sg:orig_category":"Servizi E Lavori Per Edilizia E Lavori Pubblici. Servizi E Lavori Per Ecologia E Smaltimento Rifiuti. Macchine E Forniture Per Ecologia E Smaltimento Rifiuti. Acqua, Luce, Gas E Societa' Di Esercizio ",
    "sg:phone":"+39 081 245 5821",
    "sg:postcode":"80132",
    "sg:province":"Napoli",
    "wof:name":"Giunta Regionale Della Campania",
    "wof:placetype":"venue"
},
  "geometry": {"coordinates":[14.25028,40.838749],"type":"Point"}
}