{
  "type": "Feature",
  "properties": {
    "iso:country":"IT",
    "sg:address":"80132 Napoli",
    "sg:city":"Napoli",
    "sg:orig_category":"Avvocati - Studi",
    "sg:phone":"+39 081 405032",
    "sg:postcode":"80132",
    "sg:province":"Napoli",
    "sg:website":"http://www.studiolegalelarosa.com",
    "wof:name":"Avv. Bruno Larosa",
    "wof:placetype":"venue"
},
  "geometry": {"coordinates":[14.248784,40.842091],"type":"Point"}
}