{
  "type": "Feature",
  "properties": {
    "addr:full":"1, Via Della Merlata 20014 Nerviano Nerviano Milano 20014",
    "addr:postcode":"20014;20014",
    "addr:street":"Via Della Merlata",
    "iso:country":"IT",
    "sg:address":"1, Via Della Merlata 20014 Nerviano",
    "sg:city":"Nerviano",
    "sg:classifiers":[
        {
            "category":"Professional",
            "subcategory":"Engineering",
            "type":"Services"
        }
    ],
    "sg:phone":"+39 0331 406811",
    "sg:postcode":"20014",
    "sg:province":"Milano",
    "sg:tags":[
        "machine",
        "-",
        "mechanical"
    ],
    "wof:name":"Tecnos Spa",
    "wof:placetype":"venue"
},
  "geometry": {"coordinates":[8.996514,45.547741],"type":"Point"}
}