{
  "type": "Feature",
  "properties": {
    "iso:country":"IT",
    "sg:address":"Via Vecchia Madonna Sterpeto 70051 Barletta",
    "sg:city":"Barletta",
    "sg:classifiers":[
        {
            "category":"Professional",
            "subcategory":"Engineering",
            "type":"Services"
        }
    ],
    "sg:phone":"+39 0883 534656",
    "sg:postcode":"70051",
    "sg:province":"Bari",
    "sg:tags":[
        "machine",
        "-",
        "mechanical"
    ],
    "wof:name":"Metalmec Sud (s.n.c.)",
    "wof:placetype":"venue"
},
  "geometry": {"coordinates":[16.309153,41.306206],"type":"Point"}
}