{
  "type": "Feature",
  "properties": {
    "iso:country":"IT",
    "sg:address":"16121 Genova",
    "sg:city":"Genova",
    "sg:orig_category":"Materiali Edili",
    "sg:phone":"+39 010 570 5474",
    "sg:postcode":"16121",
    "sg:province":"Genova",
    "wof:name":"Oliveri Giulio",
    "wof:placetype":"venue"
},
  "geometry": {"coordinates":[8.939713,44.405628],"type":"Point"}
}