{
  "type": "Feature",
  "properties": {
    "addr:full":"00196 Roma Roma Roma 00196",
    "addr:postcode":"00196;00196",
    "iso:country":"IT",
    "sg:address":"00196 Roma",
    "sg:city":"Roma",
    "sg:orig_category":"Abbigliamento Esterno, Maglierie E Pelliccerie. Sport - Articoli E Forniture",
    "sg:phone":"+39 06 322 2487",
    "sg:postcode":"00196",
    "sg:province":"Roma",
    "wof:name":"Prama Srl",
    "wof:placetype":"venue"
},
  "geometry": {"coordinates":[12.46769,41.930283],"type":"Point"}
}