{
  "type": "Feature",
  "properties": {
    "addr:full":"10036 Settimo Torinese Settimo Torinese Torino 10036",
    "addr:postcode":"10036;10036",
    "iso:country":"IT",
    "sg:address":"10036 Settimo Torinese",
    "sg:city":"Settimo Torinese",
    "sg:orig_category":"Forniture Per Uffici. Regalistica Aziendale",
    "sg:phone":"+39 011 897 7818",
    "sg:postcode":"10036",
    "sg:province":"Torino",
    "wof:name":"Stilo Snc Di Frittella Livio & Pistone Pasqualino",
    "wof:placetype":"venue"
},
  "geometry": {"coordinates":[7.7310681343,45.1461219788],"type":"Point"}
}