{
  "type": "Feature",
  "properties": {
    "iso:country":"IT",
    "sg:address":"20082 Noviglio",
    "sg:city":"Noviglio",
    "sg:orig_category":"Servizi E Lavori Per Edilizia E Lavori Pubblici",
    "sg:phone":"+39 02 900 6198",
    "sg:postcode":"20082",
    "sg:province":"Milano",
    "wof:name":"Minichillo Pasqualino",
    "wof:placetype":"venue"
},
  "geometry": {"coordinates":[9.072036,45.416924],"type":"Point"}
}