{
  "type": "Feature",
  "properties": {
    "addr:full":"60025 Loreto Loreto Ancona 60025",
    "addr:postcode":"60025;60025",
    "iso:country":"IT",
    "sg:address":"60025 Loreto",
    "sg:city":"Loreto",
    "sg:orig_category":"Musica",
    "sg:phone":"+39 071 978172",
    "sg:postcode":"60025",
    "sg:province":"Ancona",
    "wof:name":"Serenellini Di Serenellini Luciano & C. (s.n.c.)",
    "wof:placetype":"venue"
},
  "geometry": {"coordinates":[13.5979833603,43.4415283203],"type":"Point"}
}