{
  "type": "Feature",
  "properties": {
    "iso:country":"IT",
    "sg:address":"Viale Richard Giulio 5 20143 Milano",
    "sg:city":"Milano",
    "sg:classifiers":[
        {
            "category":"Food & Beverages",
            "subcategory":"Groceries & Convenience Stores",
            "type":"Retail Goods"
        }
    ],
    "sg:phone":"+39 0281811",
    "sg:postcode":"20143",
    "sg:province":"Milano",
    "sg:tags":[
        "frozen",
        "goods",
        "baked"
    ],
    "sg:website":"www.nestle.it",
    "wof:name":"Nestle' Italiana S.p.a.",
    "wof:placetype":"venue"
},
  "geometry": {"coordinates":[9.147265,45.444035],"type":"Point"}
}