{
  "type": "Feature",
  "properties": {
    "iso:country":"IT",
    "sg:address":"40122 Bologna",
    "sg:city":"Bologna",
    "sg:orig_category":"Tempo Libero - Articoli E Forniture. Forniture Per Congressi, Fiere E Manifestazioni. Regalistica Aziendale",
    "sg:phone":"+39 051 550222",
    "sg:postcode":"40122",
    "sg:province":"Bologna",
    "wof:name":"T & T Targhe Trofei Srl",
    "wof:placetype":"venue"
},
  "geometry": {"coordinates":[11.333488,44.501068],"type":"Point"}
}