{
  "type": "Feature",
  "properties": {
    "addr:full":"12042 Bra Bra Cuneo 12042",
    "addr:postcode":"12042;12042",
    "iso:country":"IT",
    "sg:address":"12042 Bra",
    "sg:city":"Bra",
    "sg:orig_category":"Legno E Semilavorati",
    "sg:phone":"+39 0172 490107",
    "sg:postcode":"12042",
    "sg:province":"Cuneo",
    "wof:name":"Verrua Legnami Di Verrua Giacomo E C. Snc",
    "wof:placetype":"venue"
},
  "geometry": {"coordinates":[7.84944,44.683842],"type":"Point"}
}