{
  "type": "Feature",
  "properties": {
    "addr:full":"Piazza Di Monte; Roma; 00186 Roma Roma 00186",
    "addr:postcode":"00186;00186",
    "addr:street":"Piazza Di Monte Roma",
    "iso:country":"IT",
    "sg:address":"Piazza Di Monte; Roma; 00186",
    "sg:city":"Roma",
    "sg:classifiers":[
        {
            "category":"Banks & Credit Unions",
            "subcategory":"Bank",
            "type":"Services"
        }
    ],
    "sg:phone":"+39 06 686 4782",
    "sg:postcode":"00186",
    "sg:province":"Roma",
    "wof:name":"Banque Paribas",
    "wof:placetype":"venue"
},
  "geometry": {"coordinates":[12.479432,41.89064],"type":"Point"}
}