{
  "type": "Feature",
  "properties": {
    "addr:full":"Via Feltrina 11 31040 Pederobba Pederobba Treviso 31040",
    "addr:housenumber":"11",
    "addr:postcode":"31040;31040",
    "addr:street":"Via Feltrina",
    "iso:country":"IT",
    "sg:address":"Via Feltrina 11 31040 Pederobba",
    "sg:city":"Pederobba",
    "sg:classifiers":[
        {
            "category":"Manufacturing",
            "subcategory":"Glass & Minerals",
            "type":"Manufacturing & Wholesale Goods"
        }
    ],
    "sg:phone":"+39 0423 6804",
    "sg:postcode":"31040",
    "sg:province":"Treviso",
    "sg:tags":[
        "frame"
    ],
    "sg:website":"www.celes.it",
    "wof:name":"Celes Optical Srl",
    "wof:placetype":"venue"
},
  "geometry": {"coordinates":[11.962989,45.878471],"type":"Point"}
}