{
  "type": "Feature",
  "properties": {
    "addr:full":"53100 Siena Siena Siena 53100",
    "addr:postcode":"53100;53100",
    "iso:country":"IT",
    "sg:address":"53100 Siena",
    "sg:city":"Siena",
    "sg:orig_category":"Automazione E Macchine Per Ufficio. Arredi Ed Attrezzature Per Attivita' Commerciali Ed Artigianali",
    "sg:phone":"+39 0577 47188",
    "sg:postcode":"53100",
    "sg:province":"Siena",
    "wof:name":"Becatti Srl",
    "wof:placetype":"venue"
},
  "geometry": {"coordinates":[11.365801,43.31971],"type":"Point"}
}