{
  "type": "Feature",
  "properties": {
    "addr:full":"Via Vanzago 30 25030 Paratico Paratico Brescia 25030",
    "addr:housenumber":"30",
    "addr:postcode":"25030;25030",
    "addr:street":"Via Vanzago",
    "iso:country":"IT",
    "sg:address":"Via Vanzago 30 25030 Paratico",
    "sg:city":"Paratico",
    "sg:orig_category":"Gaskets, Washers, Seals",
    "sg:phone":"+39 035 917981",
    "sg:postcode":"25030",
    "sg:province":"Brescia",
    "wof:name":"Guarnipak Srl",
    "wof:placetype":"venue"
},
  "geometry": {"coordinates":[9.941109,45.64938],"type":"Point"}
}