{
  "type": "Feature",
  "properties": {
    "iso:country":"IT",
    "sg:address":"Via Vanzago 30 25030 Paratico",
    "sg:city":"Paratico",
    "sg:orig_category":"Gaskets, Washers, Seals",
    "sg:phone":"+39 035 917981",
    "sg:postcode":"25030",
    "sg:province":"Brescia",
    "wof:name":"Guarnipak Srl",
    "wof:placetype":"venue"
},
  "geometry": {"coordinates":[9.941109,45.64938],"type":"Point"}
}