{
  "type": "Feature",
  "properties": {
    "iso:country":"IT",
    "sg:address":"20121 Milano",
    "sg:city":"Milano",
    "sg:orig_category":"Impiantistica E Prodotti Tecnologici Per Edilizia",
    "sg:phone":"+39 02 8645 7479",
    "sg:postcode":"20121",
    "sg:province":"Milano",
    "wof:name":"Buonaparte Parking S.r.l.",
    "wof:placetype":"venue"
},
  "geometry": {"coordinates":[9.17948,45.467377],"type":"Point"}
}