{
  "type": "Feature",
  "properties": {
    "iso:country":"IT",
    "sg:address":"35127 Padova",
    "sg:city":"Padova",
    "sg:orig_category":"Automazione E Macchine Per Ufficio",
    "sg:phone":"+39 049 760355",
    "sg:postcode":"35127",
    "sg:province":"Padova",
    "wof:name":"Franco & Zoppello Snc",
    "wof:placetype":"venue"
},
  "geometry": {"coordinates":[11.928167,45.39748],"type":"Point"}
}