{
  "type": "Feature",
  "properties": {
    "addr:full":"20122 Milano Milano Milano 20122",
    "addr:postcode":"20122;20122",
    "iso:country":"IT",
    "sg:address":"20122 Milano",
    "sg:city":"Milano",
    "sg:orig_category":"Enti Turistici",
    "sg:phone":"+39 02 5845 7080",
    "sg:postcode":"20122",
    "sg:province":"Milano",
    "sg:website":"http://www.newasia-singapore.it",
    "wof:name":"Ente Nazionale Del Turismo Di Singapore",
    "wof:placetype":"venue"
},
  "geometry": {"coordinates":[9.191511,45.452114],"type":"Point"}
}