{
  "type": "Feature",
  "properties": {
    "iso:country":"IT",
    "sg:address":"31, Via Sassetti Filippo 20124 Milano",
    "sg:city":"Milano",
    "sg:classifiers":[
        {
            "category":"Professional",
            "subcategory":"Engineering",
            "type":"Services"
        }
    ],
    "sg:phone":"+39 39026688187",
    "sg:postcode":"20124",
    "sg:province":"Milano",
    "sg:tags":[
        "machine",
        "-",
        "mechanical"
    ],
    "wof:name":"Portolani Luigi Di Bianca Portolani & C. S.a.s.",
    "wof:placetype":"venue"
},
  "geometry": {"coordinates":[9.193014,45.488762],"type":"Point"}
}