{
  "type": "Feature",
  "properties": {
    "iso:country":"IT",
    "sg:address":"21042 Caronno Pertusella",
    "sg:city":"Caronno Pertusella",
    "sg:orig_category":"Campeggio",
    "sg:postcode":"21042",
    "sg:province":"Varese",
    "wof:name":"Camping Market (s.n.c.)",
    "wof:placetype":"venue"
},
  "geometry": {"coordinates":[9.046478,45.592075],"type":"Point"}
}