{
  "type": "Feature",
  "properties": {
    "iso:country":"IT",
    "sg:address":"21, V. Misericordia 83029 Solofra",
    "sg:city":"Solofra",
    "sg:classifiers":[
        {
            "category":"Shopping",
            "subcategory":"Clothing, Apparel, & Fashions",
            "type":"Retail Goods"
        }
    ],
    "sg:phone":"+39 0825 583697",
    "sg:postcode":"83029",
    "sg:province":"Avellino",
    "sg:tags":[
        "clothes"
    ],
    "sg:website":"http://www.confezionianna.it",
    "wof:name":"Confezioni Anna Srl",
    "wof:placetype":"venue"
},
  "geometry": {"coordinates":[14.840714,40.832569],"type":"Point"}
}