{
  "type": "Feature",
  "properties": {
    "addr:full":"20096 Pioltello Pioltello Milano 20096",
    "addr:postcode":"20096;20096",
    "iso:country":"IT",
    "sg:address":"20096 Pioltello",
    "sg:city":"Pioltello",
    "sg:orig_category":"Prodotti E Manufatti In Materie Plastiche. Articoli Per Imballaggio E Confezionamento",
    "sg:phone":"+39 02 9216 9169",
    "sg:postcode":"20096",
    "sg:province":"Milano",
    "wof:name":"Green Plast Snc",
    "wof:placetype":"venue"
},
  "geometry": {"coordinates":[9.3143815994,45.4953460693],"type":"Point"}
}