{
  "type": "Feature",
  "properties": {
    "iso:country":"IT",
    "sg:address":"78, Via Di Vigna Girelli 00148 Roma",
    "sg:city":"Roma",
    "sg:classifiers":[
        {
            "category":"Professional",
            "subcategory":"Printing & Photocopies",
            "type":"Services"
        }
    ],
    "sg:phone":"+39 39066532208",
    "sg:postcode":"00148",
    "sg:province":"Roma",
    "wof:name":"Litografica 79 (s.r.l.)",
    "wof:placetype":"venue"
},
  "geometry": {"coordinates":[12.4257564545,41.8421707153],"type":"Point"}
}