{
  "type": "Feature",
  "properties": {
    "addr:full":"61032 Fano Fano Pesaro E Urbino 61032",
    "addr:postcode":"61032;61032",
    "iso:country":"IT",
    "sg:address":"61032 Fano",
    "sg:city":"Fano",
    "sg:classifiers":[
        {
            "category":"Professional",
            "subcategory":"Art Services",
            "type":"Services"
        }
    ],
    "sg:phone":"+39 0721 802633",
    "sg:postcode":"61032",
    "sg:province":"Pesaro E Urbino",
    "sg:tags":[
        "gifts",
        "craft",
        "artistic"
    ],
    "wof:name":"Bomboniere Zaffini",
    "wof:placetype":"venue"
},
  "geometry": {"coordinates":[13.015432,43.842529],"type":"Point"}
}