{
  "type": "Feature",
  "properties": {
    "iso:country":"IT",
    "sg:address":"33058 San Giorgio Di Nogaro",
    "sg:city":"San Giorgio di Nogaro",
    "sg:orig_category":"Termotecnica E Riscaldamento, Apparecchiature E Servizi",
    "sg:phone":"+39 0431 65002",
    "sg:postcode":"33058",
    "sg:province":"Udine",
    "wof:name":"P.c.d.r. (s.n.c.)",
    "wof:placetype":"venue"
},
  "geometry": {"coordinates":[13.221848,45.809917],"type":"Point"}
}