{
  "type": "Feature",
  "properties": {
    "addr:full":"2/c, Via Delle Industrie 30030 Salzano Salzano Venezia 30030",
    "addr:housenumber":"2 / c",
    "addr:postcode":"30030;30030",
    "addr:street":"Via Delle Industrie",
    "iso:country":"IT",
    "sg:address":"2/c, Via Delle Industrie 30030 Salzano",
    "sg:city":"Salzano",
    "sg:classifiers":[
        {
            "category":"Shopping",
            "type":"Retail Goods"
        }
    ],
    "sg:phone":"+39 39041482879",
    "sg:postcode":"30030",
    "sg:province":"Venezia",
    "sg:tags":[
        "finished",
        "-",
        "metallic"
    ],
    "wof:name":"Stamec (s.r.l.)",
    "wof:placetype":"venue"
},
  "geometry": {"coordinates":[12.1467761993,45.4948883057],"type":"Point"}
}