{
  "type": "Feature",
  "properties": {
    "iso:country":"IT",
    "sg:address":"20146 Milano",
    "sg:city":"Milano",
    "sg:classifiers":[
        {
            "category":"Health Services",
            "subcategory":"Health Practitioner",
            "type":"Services"
        }
    ],
    "sg:phone":"+39 02 4870 1950",
    "sg:postcode":"20146",
    "sg:province":"Milano",
    "sg:tags":[
        "medici"
    ],
    "wof:name":"Lauri Delfino",
    "wof:placetype":"venue"
},
  "geometry": {"coordinates":[9.136307,45.461147],"type":"Point"}
}