{
  "type": "Feature",
  "properties": {
    "iso:country":"IT",
    "sg:address":"37056 Salizzole",
    "sg:city":"Salizzole",
    "sg:orig_category":"Macchine, Impianti Ed Attrezzature Per Agricoltura E Zootecnia. Macchine, Impianti Ed Attrezzature Industria Chimica. Macchine Utensili E Impianti",
    "sg:phone":"+39 045 710 0697",
    "sg:postcode":"37056",
    "sg:province":"Verona",
    "wof:name":"Finato Gino",
    "wof:placetype":"venue"
},
  "geometry": {"coordinates":[11.095448,45.221107],"type":"Point"}
}