{
  "type": "Feature",
  "properties": {
    "iso:country":"IT",
    "sg:address":"2, V. Cimitero",
    "sg:classifiers":[
        {
            "category":"Shopping",
            "subcategory":"Crafts & Fabrics",
            "type":"Retail Goods"
        }
    ],
    "sg:phone":"+39 39089465514",
    "sg:postcode":"84013",
    "sg:province":"Salerno",
    "sg:tags":[
        "ceramic"
    ],
    "sg:website":"http://www.cottomediterraneo.com:ws_end: :mark:ws:http://www.paginegialle.it/cottomedit",
    "wof:name":"Cotto Mediterraneo Srl",
    "wof:placetype":"venue"
},
  "geometry": {"coordinates":[14.765912,40.677956],"type":"Point"}
}