{
  "type": "Feature",
  "properties": {
    "addr:full":"21056 Induno Olona Induno Olona Varese 21056",
    "addr:postcode":"21056;21056",
    "iso:country":"IT",
    "sg:address":"21056 Induno Olona",
    "sg:city":"Induno Olona",
    "sg:orig_category":"Macchine, Impianti Ed Attrezzature Per Abbigliamento E Pelletterie",
    "sg:phone":"+39 0330 284 0330",
    "sg:postcode":"21056",
    "sg:province":"Varese",
    "sg:website":"http://www.mec-mor.com",
    "wof:name":"Mec-mor",
    "wof:placetype":"venue"
},
  "geometry": {"coordinates":[8.84108,45.838722],"type":"Point"}
}