{
  "type": "Feature",
  "properties": {
    "addr:full":"56025 Pontedera Pontedera Pisa 56025",
    "addr:postcode":"56025;56025",
    "iso:country":"IT",
    "sg:address":"56025 Pontedera",
    "sg:city":"Pontedera",
    "sg:orig_category":"Dentisti Medici Chirurghi Ed Odontoiatri",
    "sg:phone":"+39 0587 55856",
    "sg:postcode":"56025",
    "sg:province":"Pisa",
    "wof:name":"Bracci Alessandro",
    "wof:placetype":"venue"
},
  "geometry": {"coordinates":[10.747925,43.67762],"type":"Point"}
}