{
  "type": "Feature",
  "properties": {
    "addr:full":"54, V. Roma 23827 Lierna Lierna Lecco 23827",
    "addr:housenumber":"54",
    "addr:postcode":"23827;23827",
    "addr:street":"V. Roma",
    "iso:country":"IT",
    "sg:address":"54, V. Roma 23827 Lierna",
    "sg:city":"Lierna",
    "sg:classifiers":[
        {
            "category":"Autos & Motor Vehicles",
            "subcategory":"Automobile Sales",
            "type":"Retail Goods"
        }
    ],
    "sg:phone":"+39 0341 740149",
    "sg:postcode":"23827",
    "sg:province":"Lecco",
    "sg:tags":[
        "motor-cars"
    ],
    "sg:website":"http://www.paginegialle.it/sibilloni-01",
    "wof:name":"Sibilloni Vittorio Snc Di Sibilloni Sergio E Marcello",
    "wof:placetype":"venue"
},
  "geometry": {"coordinates":[9.3018474579,45.9543266296],"type":"Point"}
}