{
  "type": "Feature",
  "properties": {
    "iso:country":"IT",
    "sg:address":"245, V. S. Pio X 31033 Castelfranco Veneto",
    "sg:city":"Castelfranco Veneto",
    "sg:classifiers":[
        {
            "category":"Manufacturing",
            "subcategory":"Lumber",
            "type":"Manufacturing & Wholesale Goods"
        }
    ],
    "sg:phone":"+39 0423 496047",
    "sg:postcode":"31033",
    "sg:province":"Treviso",
    "sg:tags":[
        "wood"
    ],
    "sg:website":"http://www.paginegialle.it/maringino",
    "wof:name":"Marin Gino Spa",
    "wof:placetype":"venue"
},
  "geometry": {"coordinates":[11.941913,45.672989],"type":"Point"}
}