{
  "type": "Feature",
  "properties": {
    "iso:country":"IT",
    "sg:address":"62019 Recanati",
    "sg:city":"Recanati",
    "sg:orig_category":"Articoli Da Regalo. Regalistica Aziendale",
    "sg:phone":"+39 071 982566",
    "sg:postcode":"62019",
    "sg:province":"Macerata",
    "wof:name":"Frisa Di Amichetti & Petroselli S.n.c.",
    "wof:placetype":"venue"
},
  "geometry": {"coordinates":[13.430701,43.297131],"type":"Point"}
}