{
  "type": "Feature",
  "properties": {
    "iso:country":"IT",
    "sg:address":"16121 Genova",
    "sg:city":"Genova",
    "sg:classifiers":[
        {
            "category":"Shopping",
            "subcategory":"Jewelry",
            "type":"Retail Goods"
        }
    ],
    "sg:phone":"+39 010 585979",
    "sg:postcode":"16121",
    "sg:province":"Genova",
    "sg:tags":[
        "watchmaker",
        "jewelers",
        "gold",
        "silversmith"
    ],
    "sg:website":"http://www.arigio.it",
    "wof:name":"Clio Srl",
    "wof:placetype":"venue"
},
  "geometry": {"coordinates":[8.942158,44.403767],"type":"Point"}
}