{
  "type": "Feature",
  "properties": {
    "iso:country":"IT",
    "sg:address":"20019 Settimo Milanese",
    "sg:city":"Settimo Milanese",
    "sg:orig_category":"Cartotecnica E Servizi. Forniture Per Uffici",
    "sg:phone":"+39 02 3350 0184",
    "sg:postcode":"20019",
    "sg:province":"Milano",
    "sg:website":"http://www.dimuff.it",
    "wof:name":"Dimensione Ufficio Sas",
    "wof:placetype":"venue"
},
  "geometry": {"coordinates":[9.0574,45.463547],"type":"Point"}
}