{
  "type": "Feature",
  "properties": {
    "addr:full":"Via Roma 6; Thiene; 36016 Thiene Vicenza 36016",
    "addr:housenumber":"6",
    "addr:postcode":"36016;36016",
    "addr:street":"Via Roma",
    "iso:country":"IT",
    "sg:address":"Via Roma 6; Thiene; 36016",
    "sg:city":"Thiene",
    "sg:classifiers":[
        {
            "category":"Banks & Credit Unions",
            "subcategory":"Bank",
            "type":"Services"
        }
    ],
    "sg:phone":"+39 0445 381266",
    "sg:postcode":"36016",
    "sg:province":"Vicenza",
    "wof:name":"Istituto Bancario, San Paolo Di Torino Spa",
    "wof:placetype":"venue"
},
  "geometry": {"coordinates":[11.479619,45.704639],"type":"Point"}
}