{
  "type": "Feature",
  "properties": {
    "iso:country":"IT",
    "sg:address":"Viale Unit\u00e0 Europea 17 45100 Rovigo",
    "sg:city":"Rovigo",
    "sg:classifiers":[
        {
            "category":"Military Area",
            "subcategory":"Air Force Base",
            "type":"Public Place"
        }
    ],
    "sg:phone":"+39 0425 474691",
    "sg:postcode":"45100",
    "sg:province":"Rovigo",
    "sg:tags":[
        "hot",
        "part",
        "pressed"
    ],
    "sg:website":"www.rovit.com",
    "wof:name":"Rovit Sas",
    "wof:placetype":"venue"
},
  "geometry": {"coordinates":[11.775811,45.034252],"type":"Point"}
}