{
  "type": "Feature",
  "properties": {
    "iso:country":"IT",
    "sg:address":"11, Viale Lenin 27026 Garlasco",
    "sg:city":"Garlasco",
    "sg:classifiers":[
        {
            "category":"Manufacturing",
            "subcategory":"Rubber & Plastics",
            "type":"Manufacturing & Wholesale Goods"
        }
    ],
    "sg:phone":"+39 0382 821722",
    "sg:postcode":"27026",
    "sg:province":"Pavia",
    "wof:name":"Farina S.r.l.",
    "wof:placetype":"venue"
},
  "geometry": {"coordinates":[8.9268684387,45.1886940002],"type":"Point"}
}