{
  "type": "Feature",
  "properties": {
    "addr:full":"20090 Buccinasco Buccinasco Milano 20090",
    "addr:postcode":"20090;20090",
    "iso:country":"IT",
    "sg:address":"20090 Buccinasco",
    "sg:city":"Buccinasco",
    "sg:orig_category":"Forniture Per Edilizia E Lavori Pubblici. Prodotti Vari In Metallo",
    "sg:phone":"+39 02 5751 0871",
    "sg:postcode":"20090",
    "sg:province":"Milano",
    "wof:name":"L.f.m. Di Facchetti",
    "wof:placetype":"venue"
},
  "geometry": {"coordinates":[9.1146564484,45.4108428955],"type":"Point"}
}