{
  "type": "Feature",
  "properties": {
    "iso:country":"IT",
    "sg:address":"Via Marsala 2a; Noceto; 43015",
    "sg:city":"Noceto",
    "sg:classifiers":[
        {
            "category":"Banks & Credit Unions",
            "subcategory":"Bank",
            "type":"Services"
        }
    ],
    "sg:phone":"+39 0521 620579",
    "sg:postcode":"43015",
    "sg:province":"Parma",
    "wof:name":"Credito Emiliano Spa",
    "wof:placetype":"venue"
},
  "geometry": {"coordinates":[10.179978,44.810638],"type":"Point"}
}