{
  "type": "Feature",
  "properties": {
    "iso:country":"IT",
    "sg:address":"90044 Carini",
    "sg:city":"Carini",
    "sg:orig_category":"Materiali Edili",
    "sg:phone":"+39 091 866 0122",
    "sg:postcode":"90044",
    "sg:province":"Palermo",
    "wof:name":"Mediterranea Gessi Srl",
    "wof:placetype":"venue"
},
  "geometry": {"coordinates":[13.1625,38.129688],"type":"Point"}
}