{
  "type": "Feature",
  "properties": {
    "iso:country":"IT",
    "sg:address":"00179 Roma",
    "sg:city":"Roma",
    "sg:orig_category":"Servizi E Lavori Per Abbigliamento E Pelletterie",
    "sg:phone":"+39 06 780 3318",
    "sg:postcode":"00179",
    "sg:province":"Roma",
    "wof:name":"Caruso Carmela",
    "wof:placetype":"venue"
},
  "geometry": {"coordinates":[12.681538,41.704056],"type":"Point"}
}