{
  "type": "Feature",
  "properties": {
    "iso:country":"IT",
    "sg:address":"21040 Cislago",
    "sg:city":"Cislago",
    "sg:orig_category":"Legno E Semilavorati",
    "sg:phone":"+39 02 960 9876",
    "sg:postcode":"21040",
    "sg:province":"Varese",
    "wof:name":"Il Focolare Di De Micheli Marco & C. Sas",
    "wof:placetype":"venue"
},
  "geometry": {"coordinates":[8.972974,45.658886],"type":"Point"}
}