{
  "type": "Feature",
  "properties": {
    "addr:full":"96100 Siracusa Siracusa Siracusa 96100",
    "addr:postcode":"96100;96100",
    "iso:country":"IT",
    "sg:address":"96100 Siracusa",
    "sg:city":"Siracusa",
    "sg:orig_category":"Automobili E Mezzi Di Trasporto",
    "sg:phone":"+39 0931 492073",
    "sg:postcode":"96100",
    "sg:province":"Siracusa",
    "wof:name":"Sereco Italia Srl",
    "wof:placetype":"venue"
},
  "geometry": {"coordinates":[15.270372,37.085205],"type":"Point"}
}