{
  "type": "Feature",
  "properties": {
    "iso:country":"IT",
    "sg:address":"Via Classicana 401 48100 Ravenna",
    "sg:city":"Ravenna",
    "sg:classifiers":[
        {
            "category":"Professional",
            "subcategory":"Credit Reporting & Collection",
            "type":"Services"
        }
    ],
    "sg:phone":"+39 0544 289511",
    "sg:postcode":"48100",
    "sg:province":"Ravenna",
    "sg:tags":[
        "television",
        "camera",
        "rental",
        "film",
        "cinema"
    ],
    "sg:website":"www.maioli.com",
    "wof:name":"Valerio Maioli Servizi Srl",
    "wof:placetype":"venue"
},
  "geometry": {"coordinates":[12.225,44.363888],"type":"Point"}
}