{
  "type": "Feature",
  "properties": {
    "addr:full":"4, Localita' Socciglia 55023 Borgo A Mozzano Borgo a Mozzano Lucca 55023",
    "addr:housenumber":"mozzano",
    "addr:postcode":"55023;55023",
    "addr:street":"Localita ' Socciglia",
    "iso:country":"IT",
    "sg:address":"4, Localita' Socciglia 55023 Borgo A Mozzano",
    "sg:city":"Borgo a Mozzano",
    "sg:classifiers":[
        {
            "category":"Manufacturing",
            "subcategory":"Paper Products",
            "type":"Manufacturing & Wholesale Goods"
        }
    ],
    "sg:phone":"+39 0583 888803",
    "sg:postcode":"55023",
    "sg:province":"Lucca",
    "sg:tags":[
        "cardboard"
    ],
    "wof:name":"Euro Vast Spa",
    "wof:placetype":"venue"
},
  "geometry": {"coordinates":[10.541062355,43.9777793884],"type":"Point"}
}