{
  "type": "Feature",
  "properties": {
    "iso:country":"IT",
    "sg:address":"24010 Taleggio",
    "sg:city":"Peghera",
    "sg:classifiers":[
        {
            "category":"Home & Garden",
            "subcategory":"Home Furnishings",
            "type":"Retail Goods"
        }
    ],
    "sg:phone":"+39 0345 47322",
    "sg:postcode":"24010",
    "sg:province":"Bergamo",
    "sg:tags":[
        "bathroom",
        "accessories"
    ],
    "wof:name":"Offredi & C. Snc",
    "wof:placetype":"venue"
},
  "geometry": {"coordinates":[9.5729818344,45.8734436035],"type":"Point"}
}