{
  "type": "Feature",
  "properties": {
    "iso:country":"IT",
    "sg:address":"20026 Novate Milanese",
    "sg:city":"Novate Milanese",
    "sg:orig_category":"Verniciatura A Fuoco E A Forno",
    "sg:phone":"+39 02 356 7359",
    "sg:postcode":"20026",
    "sg:province":"Milano",
    "wof:name":"Finit Sas",
    "wof:placetype":"venue"
},
  "geometry": {"coordinates":[9.126347,45.527214],"type":"Point"}
}