{
  "type": "Feature",
  "properties": {
    "addr:full":"116/r., Via Borzoli 16161 Genova Genova Genova 16161",
    "addr:housenumber":"116 / r.",
    "addr:postcode":"16161;16161",
    "addr:street":"Via Borzoli",
    "iso:country":"IT",
    "sg:address":"116/r., Via Borzoli 16161 Genova",
    "sg:city":"Genova",
    "sg:classifiers":[
        {
            "category":"Professional",
            "subcategory":"Engineering",
            "type":"Services"
        }
    ],
    "sg:phone":"+39 010 650 1960",
    "sg:postcode":"16161",
    "sg:province":"Genova",
    "sg:tags":[
        "machine",
        "-",
        "mechanical"
    ],
    "wof:name":"Officine Meccaniche Riunite (s.r.l.)",
    "wof:placetype":"venue"
},
  "geometry": {"coordinates":[8.900267,44.433949],"type":"Point"}
}