{
  "type": "Feature",
  "properties": {
    "iso:country":"IT",
    "sg:address":"15, Via Aosta 10078 Venaria",
    "sg:classifiers":[
        {
            "category":"Sports & Exercise",
            "subcategory":"Playing Field",
            "type":"Entertainment"
        }
    ],
    "sg:phone":"+39 011 424 2060",
    "sg:postcode":"10078",
    "sg:province":"Torino",
    "sg:tags":[
        "game"
    ],
    "wof:name":"Cimenti Marco (s.r.l.)",
    "wof:placetype":"venue"
},
  "geometry": {"coordinates":[7.637535,45.115631],"type":"Point"}
}