{
  "type": "Feature",
  "properties": {
    "addr:full":"8, Strada Statale 45 Quarto 29020 Gossolengo Gossolengo Piacenza 29020",
    "addr:housenumber":"45",
    "addr:postcode":"29020;29020",
    "addr:street":"Strada Statale",
    "iso:country":"IT",
    "sg:address":"8, Strada Statale 45 Quarto 29020 Gossolengo",
    "sg:city":"Gossolengo",
    "sg:classifiers":[
        {
            "category":"Professional",
            "subcategory":"Engineering",
            "type":"Services"
        }
    ],
    "sg:phone":"+39 0523 557432",
    "sg:postcode":"29020",
    "sg:province":"Piacenza",
    "sg:tags":[
        "machine",
        "-",
        "mechanical"
    ],
    "wof:name":"Rinova Dischi",
    "wof:placetype":"venue"
},
  "geometry": {"coordinates":[9.654645,44.988014],"type":"Point"}
}