{
  "type": "Feature",
  "properties": {
    "iso:country":"IT",
    "sg:address":"Via Torino 275 10099 San Mauro Torinese",
    "sg:city":"San Mauro Torinese",
    "sg:classifiers":[
        {
            "category":"Wholesale",
            "subcategory":"Non-durable Goods",
            "type":"Manufacturing & Wholesale Goods"
        }
    ],
    "sg:phone":"+39 011 822 1575",
    "sg:postcode":"10099",
    "sg:province":"Torino",
    "sg:tags":[
        "woven",
        "label"
    ],
    "sg:website":"www.bonicatti.com",
    "wof:name":"Bonicatti Pietro Di Bonicatti V. Srl",
    "wof:placetype":"venue"
},
  "geometry": {"coordinates":[7.746788,45.091335],"type":"Point"}
}