{
  "type": "Feature",
  "properties": {
    "iso:country":"IT",
    "sg:address":"20154 Milano",
    "sg:city":"Milano",
    "sg:orig_category":"Agenzie D'affari E Servizi Commerciali",
    "sg:phone":"+39 02 342438",
    "sg:postcode":"20154",
    "sg:province":"Milano",
    "wof:name":"Lecco Eraclio",
    "wof:placetype":"venue"
},
  "geometry": {"coordinates":[9.176859,45.478676],"type":"Point"}
}