{
  "type": "Feature",
  "properties": {
    "iso:country":"IT",
    "sg:address":"85020 Atella",
    "sg:city":"Atella",
    "sg:orig_category":"Prodotti E Manufatti In Materie Plastiche. Articoli Per Imballaggio E Confezionamento",
    "sg:phone":"+39 0972 716297",
    "sg:postcode":"85020",
    "sg:province":"Potenza",
    "wof:name":"Agora' Packaging S.a.s.",
    "wof:placetype":"venue"
},
  "geometry": {"coordinates":[15.6513137817,40.8768081665],"type":"Point"}
}