{
  "type": "Feature",
  "properties": {
    "addr:full":"00162 Roma Roma Roma 00162",
    "addr:postcode":"00162;00162",
    "iso:country":"IT",
    "sg:address":"00162 Roma",
    "sg:city":"Roma",
    "sg:orig_category":"Metalli E Leghe",
    "sg:phone":"+39 06 860 3092",
    "sg:postcode":"00162",
    "sg:province":"Roma",
    "wof:name":"Centro Rottami Srl",
    "wof:placetype":"venue"
},
  "geometry": {"coordinates":[12.519744873,41.9208183289],"type":"Point"}
}