{
  "type": "Feature",
  "properties": {
    "iso:country":"IT",
    "sg:address":"00196 Roma",
    "sg:city":"Roma",
    "sg:orig_category":"Banche E Servizi Finanziari",
    "sg:phone":"+39 06 321 1559",
    "sg:postcode":"00196",
    "sg:province":"Roma",
    "wof:name":"Societa' Italiana Gestione Crediti Spa",
    "wof:placetype":"venue"
},
  "geometry": {"coordinates":[12.465665,41.931667],"type":"Point"}
}