{
  "type": "Feature",
  "properties": {
    "iso:country":"IT",
    "sg:address":"00193 Roma",
    "sg:city":"Roma",
    "sg:classifiers":[
        {
            "category":"Shopping",
            "subcategory":"Clothing, Apparel, & Fashions",
            "type":"Retail Goods"
        }
    ],
    "sg:phone":"+39 06 686 4554",
    "sg:postcode":"00193",
    "sg:province":"Roma",
    "sg:tags":[
        "clothing",
        "fur",
        "knitwear"
    ],
    "sg:website":"http://www.marstatue.it",
    "wof:name":"Mar Statue Sacre",
    "wof:placetype":"venue"
},
  "geometry": {"coordinates":[12.46242,41.904129],"type":"Point"}
}