{
  "type": "Feature",
  "properties": {
    "iso:country":"IT",
    "sg:address":"83022 Baiano",
    "sg:city":"Baiano",
    "sg:orig_category":"Campeggio. Automobili E Mezzi Di Trasporto",
    "sg:phone":"+39 081 824 3120",
    "sg:postcode":"83022",
    "sg:province":"Avellino",
    "wof:name":"Di Cecilia Camping Center",
    "wof:placetype":"venue"
},
  "geometry": {"coordinates":[14.787139,40.913807],"type":"Point"}
}