{
  "type": "Feature",
  "properties": {
    "iso:country":"IT",
    "sg:address":"20123 Milano",
    "sg:city":"Milano",
    "sg:orig_category":"Articoli Da Regalo. Regalistica Aziendale",
    "sg:phone":"+39 02 876660",
    "sg:postcode":"20123",
    "sg:province":"Milano",
    "wof:name":"Savinelli S.p.a.",
    "wof:placetype":"venue"
},
  "geometry": {"coordinates":[9.187932,45.46402],"type":"Point"}
}