{
  "type": "Feature",
  "properties": {
    "addr:full":"16010 Sant'olcese Genova 16010",
    "addr:housenumber":"16010",
    "addr:postcode":"16010",
    "addr:street":"Sant'Olcese Genova",
    "iso:country":"IT",
    "sg:address":"16010 Sant'olcese",
    "sg:orig_category":"Forniture Per Attivita' Industriali",
    "sg:phone":"+39 010 709621",
    "sg:postcode":"16010",
    "sg:province":"Genova",
    "wof:name":"Burroni Redo",
    "wof:placetype":"venue"
},
  "geometry": {"coordinates":[8.9526472092,44.4700202942],"type":"Point"}
}