{
  "type": "Feature",
  "properties": {
    "addr:full":"67010 L'aquila L'Aquila 67010",
    "addr:postcode":"67010;67010",
    "iso:country":"IT",
    "sg:address":"67010 L'aquila",
    "sg:orig_category":"Facchinaggio, Carico E Scarico Merci, Portabagagli - Servizio",
    "sg:phone":"+39 0862 314155",
    "sg:postcode":"67010",
    "sg:province":"L'Aquila",
    "wof:name":"Bea Servizi Snc Di Beatrice Scarano",
    "wof:placetype":"venue"
},
  "geometry": {"coordinates":[13.347568512,42.3716850281],"type":"Point"}
}