{
  "type": "Feature",
  "properties": {
    "iso:country":"IT",
    "sg:address":"34129 Trieste",
    "sg:city":"Trieste",
    "sg:orig_category":"Centri Di Estetica E Cosmesi E Servizi",
    "sg:phone":"+39 040 360050",
    "sg:postcode":"34129",
    "sg:province":"Trieste",
    "wof:name":"Tribe & Crew",
    "wof:placetype":"venue"
},
  "geometry": {"coordinates":[13.782949,45.647972],"type":"Point"}
}