{
  "type": "Feature",
  "properties": {
    "iso:country":"IT",
    "sg:address":"Via Torino 19 29010 Calendasco",
    "sg:city":"Calendasco",
    "sg:classifiers":[
        {
            "category":"Utilities",
            "subcategory":"Fuel Oil & Lpg",
            "type":"Services"
        }
    ],
    "sg:phone":"+39 0523 760047",
    "sg:postcode":"29010",
    "sg:province":"Piacenza",
    "sg:tags":[
        "bearing",
        "cylindrical",
        "roller"
    ],
    "wof:name":"Indi Srl",
    "wof:placetype":"venue"
},
  "geometry": {"coordinates":[9.632916,45.059711],"type":"Point"}
}