{
  "type": "Feature",
  "properties": {
    "addr:full":"45021 Badia Polesine Badia Polesine Rovigo 45021",
    "addr:postcode":"45021;45021",
    "iso:country":"IT",
    "sg:address":"45021 Badia Polesine",
    "sg:city":"Badia Polesine",
    "sg:orig_category":"Impianti, Attrezzature E Forniture Sanitarie Ed Ospedaliere",
    "sg:phone":"+39 0425 597611",
    "sg:postcode":"45021",
    "sg:province":"Rovigo",
    "sg:website":"http://www.zhermack.com",
    "wof:name":"Zhermack Spa",
    "wof:placetype":"venue"
},
  "geometry": {"coordinates":[11.483315,45.101479],"type":"Point"}
}