{
  "type": "Feature",
  "properties": {
    "iso:country":"IT",
    "sg:address":"64025 Pineto",
    "sg:city":"Pineto",
    "sg:orig_category":"Accessori Dei Mezzi Di Trasporto. Riparazione Dei Mezzi Di Trasporto",
    "sg:phone":"+39 085 946 3040",
    "sg:postcode":"64025",
    "sg:province":"Teramo",
    "wof:name":"Autoplas Sas Di Scarafone Lino",
    "wof:placetype":"venue"
},
  "geometry": {"coordinates":[13.84098,42.706467],"type":"Point"}
}