{
  "type": "Feature",
  "properties": {
    "addr:full":"1243, S. Marco 30124 Venezia Venezia Venezia 30124",
    "addr:housenumber":"1243",
    "addr:postcode":"30124;30124",
    "addr:street":"S. Marco",
    "iso:country":"IT",
    "sg:address":"1243, S. Marco 30124 Venezia",
    "sg:city":"Venezia",
    "sg:classifiers":[
        {
            "category":"Travel",
            "subcategory":"Travel Agent",
            "type":"Entertainment"
        }
    ],
    "sg:phone":"+39 041 528 9840",
    "sg:postcode":"30124",
    "sg:province":"Venezia",
    "sg:tags":[
        "business"
    ],
    "wof:name":"Albergo Luna Hotel Baglioni",
    "wof:placetype":"venue"
},
  "geometry": {"coordinates":[12.337202,45.433197],"type":"Point"}
}