{
  "type": "Feature",
  "properties": {
    "addr:full":"60015 Falconara Marittima Falconara Marittima Ancona 60015",
    "addr:postcode":"60015;60015",
    "iso:country":"IT",
    "sg:address":"60015 Falconara Marittima",
    "sg:city":"Falconara Marittima",
    "sg:orig_category":"Abbigliamento - Vendita Al Dettaglio",
    "sg:phone":"+39 071 910155",
    "sg:postcode":"60015",
    "sg:province":"Ancona",
    "wof:name":"La Tessile Di Vittorio Mondaini",
    "wof:placetype":"venue"
},
  "geometry": {"coordinates":[13.395833,43.630062],"type":"Point"}
}