{
  "type": "Feature",
  "properties": {
    "addr:full":"20135 Milano Milano Milano 20135",
    "addr:postcode":"20135;20135",
    "iso:country":"IT",
    "sg:address":"20135 Milano",
    "sg:city":"Milano",
    "sg:orig_category":"Carrozzelle E Poltrone Per Infermi",
    "sg:phone":"+39 02 5412 1498",
    "sg:postcode":"20135",
    "sg:province":"Milano",
    "wof:name":"Artimedica Snc",
    "wof:placetype":"venue"
},
  "geometry": {"coordinates":[9.28955,45.494167],"type":"Point"}
}