{
  "type": "Feature",
  "properties": {
    "iso:country":"IT",
    "sg:address":"98124 Messina",
    "sg:city":"Messina",
    "sg:orig_category":"Macchine Ed Impianti Per Edilizia E Lavori Pubblici. Forniture Per Edilizia E Lavori Pubblici",
    "sg:phone":"+39 090 293 9904",
    "sg:postcode":"98124",
    "sg:province":"Messina",
    "wof:name":"I.m.e.s. Srl",
    "wof:placetype":"venue"
},
  "geometry": {"coordinates":[15.548424,38.173107],"type":"Point"}
}