{
  "type": "Feature",
  "properties": {
    "addr:full":"39035 Monguelfo Monguelfo Bolzano/Bozen 39035",
    "addr:postcode":"39035;39035",
    "iso:country":"IT",
    "sg:address":"39035 Monguelfo",
    "sg:city":"Monguelfo",
    "sg:orig_category":"Antifurto",
    "sg:phone":"+39 0474 944127",
    "sg:postcode":"39035",
    "sg:province":"Bolzano/Bozen",
    "wof:name":"W.m.k. Srl",
    "wof:placetype":"venue"
},
  "geometry": {"coordinates":[12.115514,46.751625],"type":"Point"}
}