{
  "type": "Feature",
  "properties": {
    "iso:country":"IT",
    "sg:address":"00166 Roma",
    "sg:city":"Roma",
    "sg:orig_category":"Materiali Semilavorati Metallici",
    "sg:phone":"+39 06 6156 3637",
    "sg:postcode":"00166",
    "sg:province":"Roma",
    "wof:name":"Bovo Ugo",
    "wof:placetype":"venue"
},
  "geometry": {"coordinates":[12.371575,41.92976],"type":"Point"}
}