{
  "type": "Feature",
  "properties": {
    "addr:full":"53024 Montalcino Montalcino Siena 53024",
    "addr:postcode":"53024;53024",
    "iso:country":"IT",
    "sg:address":"53024 Montalcino",
    "sg:city":"Montalcino",
    "sg:orig_category":"Prodotti Chimici Di Base",
    "sg:phone":"+39 0577 834129",
    "sg:postcode":"53024",
    "sg:province":"Siena",
    "wof:name":"Solfotecnica Italiana (s.p.a.)",
    "wof:placetype":"venue"
},
  "geometry": {"coordinates":[11.4566297531,43.0427589417],"type":"Point"}
}