{
  "type": "Feature",
  "properties": {
    "iso:country":"IT",
    "sg:address":"30015 Chioggia",
    "sg:city":"Chioggia",
    "sg:orig_category":"Utensili Meccanici E Materiali",
    "sg:phone":"+39 041 550 1183",
    "sg:postcode":"30015",
    "sg:province":"Venezia",
    "wof:name":"Dormer Italia Spa",
    "wof:placetype":"venue"
},
  "geometry": {"coordinates":[12.278818,45.219482],"type":"Point"}
}