{
  "type": "Feature",
  "properties": {
    "iso:country":"IT",
    "sg:address":"10132 Torino",
    "sg:city":"Torino",
    "sg:orig_category":"Salotti, Poltrone, Sedie E Tavoli",
    "sg:phone":"+39 011 819 5822",
    "sg:postcode":"10132",
    "sg:province":"Torino",
    "wof:name":"Casa Del Sofa' - Bergallo Arese",
    "wof:placetype":"venue"
},
  "geometry": {"coordinates":[7.710447,45.067493],"type":"Point"}
}