{
  "type": "Feature",
  "properties": {
    "addr:full":"24058 Romano Di Lombardia Romano di Lombardia Bergamo 24058",
    "addr:postcode":"24058;24058",
    "iso:country":"IT",
    "sg:address":"24058 Romano Di Lombardia",
    "sg:city":"Romano di Lombardia",
    "sg:orig_category":"Forniture Per Abbigliamento E Pelletterie",
    "sg:phone":"+39 036 390 1650",
    "sg:postcode":"24058",
    "sg:province":"Bergamo",
    "wof:name":"Finazzi Maura",
    "wof:placetype":"venue"
},
  "geometry": {"coordinates":[9.7444067001,45.5224761963],"type":"Point"}
}