{
  "type": "Feature",
  "properties": {
    "iso:country":"IT",
    "sg:address":"16129 Genova",
    "sg:city":"Genova",
    "sg:orig_category":"Automobili E Mezzi Di Trasporto",
    "sg:phone":"+39 010 570 5437",
    "sg:postcode":"16129",
    "sg:province":"Genova",
    "wof:name":"Wings Di Cotteni Vincenzo",
    "wof:placetype":"venue"
},
  "geometry": {"coordinates":[8.950776,44.403034],"type":"Point"}
}