{
  "type": "Feature",
  "properties": {
    "iso:country":"IT",
    "sg:address":"36100 Vicenza",
    "sg:city":"Vicenza",
    "sg:orig_category":"Forniture Per Attivita' Industriali",
    "sg:phone":"+39 0444 535475",
    "sg:postcode":"36100",
    "sg:province":"Vicenza",
    "wof:name":"Piccolin Italo & C. Snc",
    "wof:placetype":"venue"
},
  "geometry": {"coordinates":[11.7757825851,45.6477928162],"type":"Point"}
}