{
  "type": "Feature",
  "properties": {
    "iso:country":"IT",
    "sg:address":"62010 Montelupone",
    "sg:city":"Montelupone",
    "sg:orig_category":"Musica",
    "sg:phone":"+39 0733 226271",
    "sg:postcode":"62010",
    "sg:province":"Macerata",
    "wof:name":"Res Srl",
    "wof:placetype":"venue"
},
  "geometry": {"coordinates":[13.4776620865,43.356426239],"type":"Point"}
}