{
  "type": "Feature",
  "properties": {
    "iso:country":"IT",
    "sg:address":"Ss. Selice 610, 42/c 40026 Imola",
    "sg:city":"Imola",
    "sg:classifiers":[
        {
            "category":"Shopping Center",
            "type":"Public Place"
        }
    ],
    "sg:phone":"+39 0542 623001",
    "sg:postcode":"40026",
    "sg:province":"Bologna",
    "sg:tags":[
        "aluminium",
        "casting"
    ],
    "sg:website":"www.tazzari-group.com",
    "wof:name":"Fomet Spa",
    "wof:placetype":"venue"
},
  "geometry": {"coordinates":[11.346481,44.494221],"type":"Point"}
}