{
  "type": "Feature",
  "properties": {
    "addr:full":"70031 Andria Andria Bari 70031",
    "addr:housenumber":"70031",
    "addr:postcode":"70031",
    "iso:country":"IT",
    "sg:address":"70031 Andria",
    "sg:city":"Andria",
    "sg:orig_category":"Climatizzazione E Condizionamento, Apparecchiature E Servizi. Elettrotecnica Professionale E Di Consumo",
    "sg:phone":"+39 0883 595132",
    "sg:postcode":"70031",
    "sg:province":"Bari",
    "wof:name":"Protec Del P.i. Claudio Prodon",
    "wof:placetype":"venue"
},
  "geometry": {"coordinates":[16.555191,40.831017],"type":"Point"}
}