{
  "type": "Feature",
  "properties": {
    "iso:country":"IT",
    "sg:address":"3/d, Strada V Primo Sole 95121 Catania",
    "sg:city":"Catania",
    "sg:classifiers":[
        {
            "category":"Airport",
            "subcategory":"General Aviation",
            "type":"Transportation"
        }
    ],
    "sg:phone":"+39 39095592047",
    "sg:postcode":"95121",
    "sg:province":"Catania",
    "sg:tags":[
        "transport",
        "air"
    ],
    "wof:name":"Ve.di.s. (s.p.a.)",
    "wof:placetype":"venue"
},
  "geometry": {"coordinates":[15.066168,37.467422],"type":"Point"}
}