{
  "type": "Feature",
  "properties": {
    "addr:full":"40134 Bologna Bologna Bologna 40134",
    "addr:postcode":"40134;40134",
    "iso:country":"IT",
    "sg:address":"40134 Bologna",
    "sg:city":"Bologna",
    "sg:orig_category":"Abbigliamento Intimo, Calze E Costumi Da Bagno",
    "sg:phone":"+39 051 614 2263",
    "sg:postcode":"40134",
    "sg:province":"Bologna",
    "wof:name":"Biotecnica",
    "wof:placetype":"venue"
},
  "geometry": {"coordinates":[11.32306,44.495537],"type":"Point"}
}