{
  "type": "Feature",
  "properties": {
    "addr:full":"50141 Firenze Firenze Firenze 50141",
    "addr:postcode":"50141;50141",
    "iso:country":"IT",
    "sg:address":"50141 Firenze",
    "sg:city":"Firenze",
    "sg:orig_category":"Tempo Libero - Articoli E Forniture. Regalistica Aziendale",
    "sg:phone":"+39 055 422 1935",
    "sg:postcode":"50141",
    "sg:province":"Firenze",
    "wof:name":"C.i.t.t.i. (s.a.s.)",
    "wof:placetype":"venue"
},
  "geometry": {"coordinates":[11.238152,43.800804],"type":"Point"}
}