{
  "type": "Feature",
  "properties": {
    "iso:country":"IT",
    "sg:address":"20121 Milano",
    "sg:city":"Milano",
    "sg:orig_category":"Tessuti Arredamento, Tende E Tappeti",
    "sg:phone":"+39 02 654430",
    "sg:postcode":"20121",
    "sg:province":"Milano",
    "wof:name":"Amiras Daniele (s.r.l.)",
    "wof:placetype":"venue"
},
  "geometry": {"coordinates":[9.194988,45.473164],"type":"Point"}
}