{
  "type": "Feature",
  "properties": {
    "iso:country":"IT",
    "sg:address":"10128 Torino",
    "sg:city":"Torino",
    "sg:orig_category":"Cine-foto-ottica. Articoli Medico-sanitari Ed Ortopedici",
    "sg:phone":"+39 011 561 3926",
    "sg:postcode":"10128",
    "sg:province":"Torino",
    "wof:name":"O.p. Ottica Piemontese (s.r.l.)",
    "wof:placetype":"venue"
},
  "geometry": {"coordinates":[7.672716,45.06078],"type":"Point"}
}