{
  "type": "Feature",
  "properties": {
    "iso:country":"IT",
    "sg:address":"24059 Urgnano",
    "sg:city":"Urgnano",
    "sg:orig_category":"Vernici Uso Industriale",
    "sg:phone":"+39 035 843002",
    "sg:postcode":"24059",
    "sg:province":"Bergamo",
    "wof:name":"Eurocolor Srl",
    "wof:placetype":"venue"
},
  "geometry": {"coordinates":[9.705448,45.58255],"type":"Point"}
}