{
  "type": "Feature",
  "properties": {
    "addr:full":"103, V. Serio - Nizzolina 21050 Marnate Marnate Varese 21050",
    "addr:housenumber":"103",
    "addr:postcode":"21050;21050",
    "addr:street":"V. Serio Nizzolina",
    "iso:country":"IT",
    "sg:address":"103, V. Serio - Nizzolina 21050 Marnate",
    "sg:city":"Marnate",
    "sg:classifiers":[
        {
            "category":"Wholesale",
            "subcategory":"Medical Equipment & Supplies",
            "type":"Manufacturing & Wholesale Goods"
        }
    ],
    "sg:phone":"+39 0331 367201",
    "sg:postcode":"21050",
    "sg:province":"Varese",
    "sg:tags":[
        "-",
        "health",
        "instrument"
    ],
    "sg:website":"http://www.hospitaltubing.it:ws_end: :mark:ws:http://www.paginegialle.it/hospital",
    "wof:name":"Hospital Tubing Snc",
    "wof:placetype":"venue"
},
  "geometry": {"coordinates":[8.926614,45.628036],"type":"Point"}
}