{
  "type": "Feature",
  "properties": {
    "addr:full":"Via Rossini 3; Rende; 87036 Rende Cosenza 87036",
    "addr:housenumber":"3",
    "addr:postcode":"87036;87036",
    "addr:street":"Via Rossini;Rende",
    "iso:country":"IT",
    "sg:address":"Via Rossini 3; Rende; 87036",
    "sg:city":"Rende",
    "sg:classifiers":[
        {
            "category":"Banks & Credit Unions",
            "subcategory":"Bank",
            "type":"Services"
        }
    ],
    "sg:phone":"+39 0984 402202",
    "sg:postcode":"87036",
    "sg:province":"Cosenza",
    "wof:name":"Credito Emiliano Spa",
    "wof:placetype":"venue"
},
  "geometry": {"coordinates":[16.242332,39.350136],"type":"Point"}
}