{
  "type": "Feature",
  "properties": {
    "addr:full":"Via Spartaco 3 20135 Milano Milano Milano 20135",
    "addr:housenumber":"3",
    "addr:postcode":"20135;20135",
    "addr:street":"Via Spartaco",
    "iso:country":"IT",
    "sg:address":"Via Spartaco 3 20135 Milano",
    "sg:city":"Milano",
    "sg:classifiers":[
        {
            "category":"Banks & Credit Unions",
            "subcategory":"Investment Brokerage",
            "type":"Services"
        }
    ],
    "sg:phone":"+39 02 550201",
    "sg:postcode":"20135",
    "sg:province":"Milano",
    "sg:tags":[
        "women's",
        "clothing",
        "accessory"
    ],
    "wof:name":"Etro Spa",
    "wof:placetype":"venue"
},
  "geometry": {"coordinates":[9.207508,45.459663],"type":"Point"}
}