{
  "type": "Feature",
  "properties": {
    "iso:country":"IT",
    "sg:address":"Via Circonvallazione, 15/a; Pont S. Martin; 11026",
    "sg:classifiers":[
        {
            "category":"Banks & Credit Unions",
            "subcategory":"Bank",
            "type":"Services"
        }
    ],
    "sg:phone":"+39 0125 806 1121",
    "sg:postcode":"11026",
    "sg:province":"Aosta",
    "wof:name":"Banca Sella",
    "wof:placetype":"venue"
},
  "geometry": {"coordinates":[7.789685,45.598],"type":"Point"}
}