{
  "type": "Feature",
  "properties": {
    "iso:country":"IT",
    "sg:address":"20026 Novate Milanese",
    "sg:city":"Novate Milanese",
    "sg:orig_category":"Servizi Di Magazzinaggio E Movimentazione",
    "sg:phone":"+39 02 356 4950",
    "sg:postcode":"20026",
    "sg:province":"Milano",
    "wof:name":"Ge.di.mer Srl",
    "wof:placetype":"venue"
},
  "geometry": {"coordinates":[9.141828,45.533119],"type":"Point"}
}