{
  "type": "Feature",
  "properties": {
    "iso:country":"IT",
    "sg:address":"70019 Triggiano",
    "sg:city":"Triggiano",
    "sg:orig_category":"Caffe' Crudo E Torrefatto",
    "sg:phone":"+39 080 549 4492",
    "sg:postcode":"70019",
    "sg:province":"Bari",
    "sg:website":"http://www.battista.it",
    "wof:name":"Torrefazione Caff\u00c9 Luigi & Michele Battista Srl",
    "wof:placetype":"venue"
},
  "geometry": {"coordinates":[16.95643,41.096279],"type":"Point"}
}