{
  "type": "Feature",
  "properties": {
    "iso:country":"IT",
    "sg:address":"39028 Silandro",
    "sg:city":"Silandro",
    "sg:orig_category":"Avvocati - Studi",
    "sg:phone":"+39 0473 730410",
    "sg:postcode":"39028",
    "sg:province":"Bolzano/Bozen",
    "sg:website":"http://www.paginegialle.it/teppeinerdrpeter",
    "wof:name":"Tappeiner Dr. Peter",
    "wof:placetype":"venue"
},
  "geometry": {"coordinates":[10.774199,46.627804],"type":"Point"}
}