{
  "type": "Feature",
  "properties": {
    "iso:country":"IT",
    "sg:address":"Via Municipio; Guardia Sanframondi; 82034",
    "sg:city":"Guardia Sanframondi",
    "sg:classifiers":[
        {
            "category":"Banks & Credit Unions",
            "subcategory":"Bank",
            "type":"Services"
        }
    ],
    "sg:phone":"+39 0824 817477",
    "sg:postcode":"82034",
    "sg:province":"Benevento",
    "wof:name":"Banco Di Napoli Spa",
    "wof:placetype":"venue"
},
  "geometry": {"coordinates":[14.604916,41.255119],"type":"Point"}
}