{
  "type": "Feature",
  "properties": {
    "addr:full":"22036 Erba Erba Como 22036",
    "addr:postcode":"22036;22036",
    "iso:country":"IT",
    "sg:address":"22036 Erba",
    "sg:city":"Erba",
    "sg:orig_category":"Fucinatura",
    "sg:phone":"+39 031 641610",
    "sg:postcode":"22036",
    "sg:province":"Como",
    "wof:name":"Faer Srl",
    "wof:placetype":"venue"
},
  "geometry": {"coordinates":[9.246386528,45.8071479797],"type":"Point"}
}