{
  "type": "Feature",
  "properties": {
    "iso:country":"IT",
    "sg:address":"Via Poerio 81025 Marcianise",
    "sg:city":"Marcianise",
    "sg:classifiers":[
        {
            "category":"Real Estate",
            "subcategory":"Architect",
            "type":"Services"
        }
    ],
    "sg:phone":"+39 0823 832184",
    "sg:postcode":"81025",
    "sg:province":"Caserta",
    "sg:tags":[
        "textile",
        "clothing"
    ],
    "wof:name":"Sud Conf S.r.l.",
    "wof:placetype":"venue"
},
  "geometry": {"coordinates":[14.278797,41.038147],"type":"Point"}
}