{
  "type": "Feature",
  "properties": {
    "iso:country":"IT",
    "sg:address":"10148 Torino",
    "sg:city":"Torino",
    "sg:orig_category":"Arredamenti E Mobili Professionali. Apparecchi, Attrezzature E Forniture Per Centri Estetici. Arredi Ed Attrezzature Per Attivita' Commerciali Ed Artigianali",
    "sg:phone":"+39 011 226 4584",
    "sg:postcode":"10148",
    "sg:province":"Torino",
    "wof:name":"G. Di Fiore & C. Snc",
    "wof:placetype":"venue"
},
  "geometry": {"coordinates":[7.670722,45.112335],"type":"Point"}
}