{
  "type": "Feature",
  "properties": {
    "iso:country":"IT",
    "sg:address":"270, Via Grandi Achille 41100 Modena",
    "sg:city":"Modena",
    "sg:classifiers":[
        {
            "category":"Shopping",
            "subcategory":"Clothing, Apparel, & Fashions",
            "type":"Retail Goods"
        }
    ],
    "sg:phone":"+39 39059310617",
    "sg:postcode":"41100",
    "sg:province":"Modena",
    "sg:tags":[
        "clothes"
    ],
    "wof:name":"Confezioni 2 Piu' 1",
    "wof:placetype":"venue"
},
  "geometry": {"coordinates":[10.935829,44.552532],"type":"Point"}
}