{
  "type": "Feature",
  "properties": {
    "iso:country":"IT",
    "sg:address":"91026 Mazara Del Vallo",
    "sg:city":"Mazara del Vallo",
    "sg:orig_category":"Macchine Utensili E Impianti",
    "sg:phone":"+39 0923 947395",
    "sg:postcode":"91026",
    "sg:province":"Trapani",
    "wof:name":"Mediterranea Gas Tecnici S.n.c Di Bianco Giovan Battista & C.",
    "wof:placetype":"venue"
},
  "geometry": {"coordinates":[12.644587,37.738953],"type":"Point"}
}