{
  "type": "Feature",
  "properties": {
    "iso:country":"IT",
    "sg:address":"360, Via Tiburtina 00159 Roma",
    "sg:city":"Roma",
    "sg:classifiers":[
        {
            "category":"Sports & Exercise",
            "subcategory":"Playing Field",
            "type":"Entertainment"
        }
    ],
    "sg:phone":"+39 390 643 6971",
    "sg:postcode":"00159",
    "sg:province":"Roma",
    "sg:tags":[
        "game"
    ],
    "wof:name":"Cherubini Musical S.n.c.",
    "wof:placetype":"venue"
},
  "geometry": {"coordinates":[12.535477,41.908146],"type":"Point"}
}