{
  "type": "Feature",
  "properties": {
    "iso:country":"IT",
    "sg:address":"Via Lomazzo Paolo 52 20154 Milano",
    "sg:city":"Milano",
    "sg:classifiers":[
        {
            "category":"Shopping",
            "subcategory":"Books",
            "type":"Retail Goods"
        }
    ],
    "sg:phone":"+39 0230221",
    "sg:postcode":"20154",
    "sg:province":"Milano",
    "sg:website":"www.ilsole24ore.com",
    "wof:name":"Il Sole 24 Ore Gruppo Editoriale",
    "wof:placetype":"venue"
},
  "geometry": {"coordinates":[9.169875,45.484383],"type":"Point"}
}