{
  "type": "Feature",
  "properties": {
    "iso:country":"IT",
    "sg:address":"56124 Pisa",
    "sg:city":"Pisa",
    "sg:orig_category":"Automobili E Mezzi Di Trasporto",
    "sg:phone":"+39 050 542238",
    "sg:postcode":"56124",
    "sg:province":"Pisa",
    "wof:name":"Idea Moto Srl",
    "wof:placetype":"venue"
},
  "geometry": {"coordinates":[10.420633,43.719799],"type":"Point"}
}