{
  "type": "Feature",
  "properties": {
    "iso:country":"IT",
    "sg:address":"20040 Usmate Velate",
    "sg:city":"Usmate Velate",
    "sg:orig_category":"Arti Grafiche",
    "sg:phone":"+39 039 671039",
    "sg:postcode":"20040",
    "sg:province":"Milano",
    "wof:name":"Tipolitografia Vigano' Sas",
    "wof:placetype":"venue"
},
  "geometry": {"coordinates":[9.362482,45.650841],"type":"Point"}
}