{
  "type": "Feature",
  "properties": {
    "addr:full":"8, Via Faedis 33040 Povoletto Faedis Udine 33040",
    "addr:postcode":"33040;33040",
    "addr:street":"Via Faedis",
    "iso:country":"IT",
    "sg:address":"8, Via Faedis 33040 Povoletto",
    "sg:city":"Faedis",
    "sg:classifiers":[
        {
            "category":"Manufacturing",
            "subcategory":"Metals",
            "type":"Manufacturing & Wholesale Goods"
        }
    ],
    "sg:phone":"+39 0432 679194",
    "sg:postcode":"33040",
    "sg:province":"Udine",
    "sg:tags":[
        "processing"
    ],
    "wof:name":"Ramo S.r.l.",
    "wof:placetype":"venue"
},
  "geometry": {"coordinates":[13.2322463989,46.07629776],"type":"Point"}
}