{
  "type": "Feature",
  "properties": {
    "iso:country":"IT",
    "sg:address":"Via Torino 575 14020 Robella",
    "sg:city":"Robella",
    "sg:classifiers":[
        {
            "category":"Home & Garden",
            "subcategory":"Household Appliances",
            "type":"Retail Goods"
        }
    ],
    "sg:phone":"+39 0141 998293",
    "sg:postcode":"14020",
    "sg:province":"Asti",
    "sg:tags":[
        "electric"
    ],
    "wof:name":"La Rosa S.r.l.",
    "wof:placetype":"venue"
},
  "geometry": {"coordinates":[8.095837,45.06654],"type":"Point"}
}