{
  "type": "Feature",
  "properties": {
    "iso:country":"IT",
    "sg:address":"33, Via Merano 39011 Lana",
    "sg:city":"Lana",
    "sg:classifiers":[
        {
            "category":"Building & Trades",
            "subcategory":"Construction",
            "type":"Services"
        }
    ],
    "sg:phone":"+39 0473 564550",
    "sg:postcode":"39011",
    "sg:province":"Bolzano/Bozen",
    "sg:tags":[
        "work",
        "public"
    ],
    "wof:name":"Poolshop (s.n.c.)",
    "wof:placetype":"venue"
},
  "geometry": {"coordinates":[11.143844,46.621338],"type":"Point"}
}