{
  "type": "Feature",
  "properties": {
    "addr:full":"29100 Piacenza Piacenza Piacenza 29100",
    "addr:postcode":"29100;29100",
    "iso:country":"IT",
    "sg:address":"29100 Piacenza",
    "sg:city":"Piacenza",
    "sg:orig_category":"Legno E Semilavorati. Articoli Per Imballaggio E Confezionamento",
    "sg:phone":"+39 0523 579129",
    "sg:postcode":"29100",
    "sg:province":"Piacenza",
    "wof:name":"Merli Angelo, Pietro E Massimo",
    "wof:placetype":"venue"
},
  "geometry": {"coordinates":[9.7431459427,45.0441207886],"type":"Point"}
}