{
  "type": "Feature",
  "properties": {
    "addr:full":"00121 Roma Roma Roma 00121",
    "addr:postcode":"00121;00121",
    "iso:country":"IT",
    "sg:address":"00121 Roma",
    "sg:city":"Roma",
    "sg:classifiers":[
        {
            "category":"Shopping",
            "subcategory":"Computers & Home Electronics",
            "type":"Retail Goods"
        }
    ],
    "sg:phone":"+39 06 5603 0330",
    "sg:postcode":"00121",
    "sg:province":"Roma",
    "sg:tags":[
        "personal",
        "ed",
        "accessori"
    ],
    "wof:name":"Istituto Gamma",
    "wof:placetype":"venue"
},
  "geometry": {"coordinates":[12.2731952667,41.7395477295],"type":"Point"}
}