{
  "type": "Feature",
  "properties": {
    "addr:full":"1, Via Torricelli 43015 Noceto Noceto Parma 43015",
    "addr:postcode":"43015;43015",
    "addr:street":"Via Torricelli",
    "iso:country":"IT",
    "sg:address":"1, Via Torricelli 43015 Noceto",
    "sg:city":"Noceto",
    "sg:classifiers":[
        {
            "category":"Professional",
            "subcategory":"Engineering",
            "type":"Services"
        }
    ],
    "sg:phone":"+39 0521 621072",
    "sg:postcode":"43015",
    "sg:province":"Parma",
    "sg:tags":[
        "machine",
        "-",
        "mechanical"
    ],
    "wof:name":"Garlini Meccanica Di Garlini Ivo & C. Snc",
    "wof:placetype":"venue"
},
  "geometry": {"coordinates":[10.184443,44.817207],"type":"Point"}
}