{
  "type": "Feature",
  "properties": {
    "addr:full":"09129 Cagliari Cagliari Cagliari 09129",
    "addr:postcode":"09129;09129",
    "iso:country":"IT",
    "sg:address":"09129 Cagliari",
    "sg:city":"Cagliari",
    "sg:orig_category":"Centri Di Estetica E Cosmesi E Servizi",
    "sg:phone":"+39 070 44960",
    "sg:postcode":"09129",
    "sg:province":"Cagliari",
    "wof:name":"Deplano Marcello",
    "wof:placetype":"venue"
},
  "geometry": {"coordinates":[9.136853,39.226795],"type":"Point"}
}