{
  "type": "Feature",
  "properties": {
    "addr:full":"13900 Biella Biella Biella 13900",
    "addr:postcode":"13900;13900",
    "iso:country":"IT",
    "sg:address":"13900 Biella",
    "sg:city":"Biella",
    "sg:orig_category":"Caminetti, Forni Da Giardino E Barbecues",
    "sg:phone":"+39 015 21718",
    "sg:postcode":"13900",
    "sg:province":"Biella",
    "wof:name":"Oliaro Giorgio",
    "wof:placetype":"venue"
},
  "geometry": {"coordinates":[8.077347,45.568344],"type":"Point"}
}