{
  "type": "Feature",
  "properties": {
    "addr:full":"41011 Campogalliano Campogalliano Modena 41011",
    "addr:postcode":"41011;41011",
    "iso:country":"IT",
    "sg:address":"41011 Campogalliano",
    "sg:city":"Campogalliano",
    "sg:orig_category":"Lavorazioni Metalli, Stampaggio E Saldatura",
    "sg:phone":"+39 059 851732",
    "sg:postcode":"41011",
    "sg:province":"Modena",
    "wof:name":"Euro Inox Srl",
    "wof:placetype":"venue"
},
  "geometry": {"coordinates":[10.840667,44.696156],"type":"Point"}
}