{
  "type": "Feature",
  "properties": {
    "iso:country":"IT",
    "sg:address":"74, Via Braglio 36015 Schio",
    "sg:city":"Schio",
    "sg:classifiers":[
        {
            "category":"Professional",
            "subcategory":"Engineering",
            "type":"Services"
        }
    ],
    "sg:phone":"+39 0445 575356",
    "sg:postcode":"36015",
    "sg:province":"Vicenza",
    "sg:tags":[
        "machine",
        "-",
        "mechanical"
    ],
    "wof:name":"Somec (s.r.l.)",
    "wof:placetype":"venue"
},
  "geometry": {"coordinates":[11.387696,45.722626],"type":"Point"}
}