{
  "type": "Feature",
  "properties": {
    "addr:full":"97100 Ragusa Ragusa Ragusa 97100",
    "addr:postcode":"97100;97100",
    "iso:country":"IT",
    "sg:address":"97100 Ragusa",
    "sg:city":"Ragusa",
    "sg:orig_category":"Arredamenti - Produzione E Ingrosso",
    "sg:phone":"+39 0932 667009",
    "sg:postcode":"97100",
    "sg:province":"Ragusa",
    "sg:website":"http://www.cucinegiunta.it",
    "wof:name":"G & C Italia Srl",
    "wof:placetype":"venue"
},
  "geometry": {"coordinates":[14.682105,36.912518],"type":"Point"}
}