{
  "type": "Feature",
  "properties": {
    "iso:country":"IT",
    "sg:address":"70010 Casamassima",
    "sg:city":"Casamassima",
    "sg:classifiers":[
        {
            "category":"Shopping",
            "subcategory":"Clothing, Apparel, & Fashions",
            "type":"Retail Goods"
        }
    ],
    "sg:phone":"+39 080 697 7089",
    "sg:postcode":"70010",
    "sg:province":"Bari",
    "sg:tags":[
        "knitwear",
        "furs",
        "clothing"
    ],
    "sg:website":"http://www.modamodi.com",
    "wof:name":"Modi' Di Manginelli Carlo",
    "wof:placetype":"venue"
},
  "geometry": {"coordinates":[16.918135,40.955307],"type":"Point"}
}