{
  "type": "Feature",
  "properties": {
    "iso:country":"IT",
    "sg:address":"16035 Rapallo",
    "sg:city":"Rapallo",
    "sg:orig_category":"Maglieria - Produzione E Ingrosso",
    "sg:phone":"+39 0185 231148",
    "sg:postcode":"16035",
    "sg:province":"Genova",
    "wof:name":"San Michele 49",
    "wof:placetype":"venue"
},
  "geometry": {"coordinates":[9.223865,44.340542],"type":"Point"}
}