{
  "type": "Feature",
  "properties": {
    "addr:full":"20010 Bareggio Bareggio Milano 20010",
    "addr:postcode":"20010;20010",
    "iso:country":"IT",
    "sg:address":"20010 Bareggio",
    "sg:city":"Bareggio",
    "sg:orig_category":"Dolciumi E Gelati",
    "sg:phone":"+39 02 9036 4211",
    "sg:postcode":"20010",
    "sg:province":"Milano",
    "wof:name":"Gelcrem S.r.l.",
    "wof:placetype":"venue"
},
  "geometry": {"coordinates":[9.018973,45.484859],"type":"Point"}
}