{
  "type": "Feature",
  "properties": {
    "iso:country":"IT",
    "sg:address":"4, Via Enrico Toti 13816 Sagliano Micca",
    "sg:city":"Sagliano Micca",
    "sg:classifiers":[
        {
            "category":"Manufacturing",
            "subcategory":"Rubber & Plastics",
            "type":"Manufacturing & Wholesale Goods"
        }
    ],
    "sg:phone":"+39 015 247 6033",
    "sg:postcode":"13816",
    "sg:province":"Biella",
    "wof:name":"L.a.p. Lavorazione Articoli Plastici S.r.l.",
    "wof:placetype":"venue"
},
  "geometry": {"coordinates":[8.0456142426,45.6092605591],"type":"Point"}
}