{
  "type": "Feature",
  "properties": {
    "iso:country":"IT",
    "sg:address":"35030 Selvazzano Dentro",
    "sg:city":"Selvazzano Dentro",
    "sg:orig_category":"Chiese Ed Associazioni Religiose",
    "sg:phone":"+39 049 805 5629",
    "sg:postcode":"35030",
    "sg:province":"Padova",
    "wof:name":"Ente Patrimoniale Chiesa Gesu' Cristo S.u.g.",
    "wof:placetype":"venue"
},
  "geometry": {"coordinates":[11.787673,45.384865],"type":"Point"}
}