{
  "type": "Feature",
  "properties": {
    "iso:country":"IT",
    "sg:address":"Via Asti 6; Murisengo; 15020",
    "sg:city":"Murisengo",
    "sg:classifiers":[
        {
            "category":"Banks & Credit Unions",
            "subcategory":"Bank",
            "type":"Services"
        }
    ],
    "sg:phone":"+39 0141 993577",
    "sg:postcode":"15020",
    "sg:province":"Alessandria",
    "wof:name":"Istituto Bancario, San Paolo Di Torino Spa",
    "wof:placetype":"venue"
},
  "geometry": {"coordinates":[8.135235,45.081108],"type":"Point"}
}