{
  "type": "Feature",
  "properties": {
    "addr:full":"10147 Torino Torino Torino 10147",
    "addr:postcode":"10147;10147",
    "iso:country":"IT",
    "sg:address":"10147 Torino",
    "sg:city":"Torino",
    "sg:orig_category":"Antifurto",
    "sg:phone":"+39 011 253834",
    "sg:postcode":"10147",
    "sg:province":"Torino",
    "sg:website":"http://www.sfregolafrancesco.it",
    "wof:name":"Sfregola Francesco",
    "wof:placetype":"venue"
},
  "geometry": {"coordinates":[7.678333,45.100372],"type":"Point"}
}