{
  "type": "Feature",
  "properties": {
    "iso:country":"IT",
    "sg:address":"Via G. Castaldio 29 47891 Galazzano",
    "sg:classifiers":[
        {
            "category":"Shopping",
            "subcategory":"Computers & Home Electronics",
            "type":"Retail Goods"
        }
    ],
    "sg:phone":"+39 0549 908638",
    "sg:tags":[
        "industrial",
        "power"
    ],
    "sg:website":"www.electra.sm",
    "wof:name":"Electra Sa",
    "wof:placetype":"venue"
},
  "geometry": {"coordinates":[12.4763889313,43.9786338806],"type":"Point"}
}