{
  "type": "Feature",
  "properties": {
    "iso:country":"IT",
    "sg:address":"47900 Rimini",
    "sg:city":"Rimini",
    "sg:orig_category":"Antincendio - Impianti, Attrezzature E Materiali",
    "sg:phone":"+39 0541 774401",
    "sg:postcode":"47900",
    "sg:province":"Rimini",
    "wof:name":"Antincendio Riminese Di Alessi Cinzia & C. Sas",
    "wof:placetype":"venue"
},
  "geometry": {"coordinates":[12.507329,44.05061],"type":"Point"}
}