{
  "type": "Feature",
  "properties": {
    "addr:full":"38068 Rovereto Rovereto Trento 38068",
    "addr:postcode":"38068;38068",
    "iso:country":"IT",
    "sg:address":"38068 Rovereto",
    "sg:city":"Rovereto",
    "sg:orig_category":"Bullonerie",
    "sg:phone":"+39 0464 835300",
    "sg:postcode":"38068",
    "sg:province":"Trento",
    "wof:name":"Zeni Bullonerie Srl",
    "wof:placetype":"venue"
},
  "geometry": {"coordinates":[11.034306,45.887314],"type":"Point"}
}