{
  "type": "Feature",
  "properties": {
    "iso:country":"IT",
    "sg:address":"71, Via Redipuglia 24047 Treviglio",
    "sg:city":"Treviglio",
    "sg:classifiers":[
        {
            "category":"Farming",
            "subcategory":"Livestock Farm",
            "type":"Manufacturing & Wholesale Goods"
        }
    ],
    "sg:phone":"+39 39036349145",
    "sg:postcode":"24047",
    "sg:province":"Bergamo",
    "sg:tags":[
        "agriculture"
    ],
    "wof:name":"I.s.a. Industria Sottoprodotti Della Macellazione Di Conti Virginio & C. (s.n.c.)",
    "wof:placetype":"venue"
},
  "geometry": {"coordinates":[9.595572,45.511395],"type":"Point"}
}