{
  "type": "Feature",
  "properties": {
    "iso:country":"IT",
    "sg:address":"20122 Milano",
    "sg:city":"Milano",
    "sg:orig_category":"Scuole Di Lingue",
    "sg:phone":"+39 02 5843 1171",
    "sg:postcode":"20122",
    "sg:province":"Milano",
    "sg:website":"http://www.oise.net",
    "wof:name":"Oise",
    "wof:placetype":"venue"
},
  "geometry": {"coordinates":[9.187624,45.455536],"type":"Point"}
}