{
  "type": "Feature",
  "properties": {
    "addr:full":"00192 Roma Roma Roma 00192",
    "addr:postcode":"00192;00192",
    "iso:country":"IT",
    "sg:address":"00192 Roma",
    "sg:city":"Roma",
    "sg:orig_category":"Podologia - Centri E Studi",
    "sg:phone":"+39 06 3973 5191",
    "sg:postcode":"00192",
    "sg:province":"Roma",
    "wof:name":"Cappelletti Podologi",
    "wof:placetype":"venue"
},
  "geometry": {"coordinates":[12.4587039948,41.907951355],"type":"Point"}
}