{
  "type": "Feature",
  "properties": {
    "iso:country":"IT",
    "sg:address":"Via Giulio Pastore, 15/17 42046 Reggiolo",
    "sg:classifiers":[
        {
            "category":"Shopping",
            "subcategory":"Clothing, Apparel, & Fashions",
            "type":"Retail Goods"
        }
    ],
    "sg:phone":"+39 0522 211201",
    "sg:postcode":"42046",
    "sg:province":"Reggio Nell'Emilia",
    "sg:tags":[
        "knitted",
        "knitwear",
        "clothes"
    ],
    "sg:website":"www.milar.it",
    "wof:name":"Manifattura Italiana La Rocca Milar",
    "wof:placetype":"venue"
},
  "geometry": {"coordinates":[10.627794,44.696228],"type":"Point"}
}