{
  "type": "Feature",
  "properties": {
    "iso:country":"IT",
    "sg:address":"31010 Mareno Di Piave",
    "sg:city":"Mareno di Piave",
    "sg:orig_category":"Cucine Per Comunita'",
    "sg:phone":"+39 0438 4981",
    "sg:postcode":"31010",
    "sg:province":"Treviso",
    "sg:website":"http://www.mareno.it",
    "wof:name":"Mareno Industrie Ali Spa",
    "wof:placetype":"venue"
},
  "geometry": {"coordinates":[12.317298,45.847546],"type":"Point"}
}