{
  "type": "Feature",
  "properties": {
    "iso:country":"IT",
    "sg:address":"96014 Floridia",
    "sg:city":"Floridia",
    "sg:orig_category":"Ceramiche Per Pavimenti E Rivestimenti - Vendita Al Dettaglio",
    "sg:phone":"+39 0931 943900",
    "sg:postcode":"96014",
    "sg:province":"Siracusa",
    "wof:name":"Guardo & Martogli Snc",
    "wof:placetype":"venue"
},
  "geometry": {"coordinates":[15.157092,37.086338],"type":"Point"}
}