{
  "type": "Feature",
  "properties": {
    "addr:full":"56123 Pisa Pisa Pisa 56123",
    "addr:postcode":"56123;56123",
    "iso:country":"IT",
    "sg:address":"56123 Pisa",
    "sg:city":"Pisa",
    "sg:orig_category":"Servizi E Lavori Industria Della Gomma",
    "sg:phone":"+39 050 552419",
    "sg:postcode":"56123",
    "sg:province":"Pisa",
    "wof:name":"Pilotta & Lo Cocco",
    "wof:placetype":"venue"
},
  "geometry": {"coordinates":[10.397215,43.724007],"type":"Point"}
}