{
  "type": "Feature",
  "properties": {
    "iso:country":"IT",
    "sg:address":"Viale Mattei 26823 Castiglione D'adda",
    "sg:classifiers":[
        {
            "category":"Utilities",
            "subcategory":"Electric",
            "type":"Services"
        }
    ],
    "sg:phone":"+39 39037741581",
    "sg:postcode":"26823",
    "sg:province":"Lodi",
    "sg:tags":[
        "component",
        "electronic"
    ],
    "wof:name":"Technoelectric S.r.l.",
    "wof:placetype":"venue"
},
  "geometry": {"coordinates":[9.683271,45.213131],"type":"Point"}
}