{
  "type": "Feature",
  "properties": {
    "iso:country":"IT",
    "sg:address":"15038 Ottiglio",
    "sg:city":"Ottiglio",
    "sg:orig_category":"Bevande, Vini E Liquori. Shopping",
    "sg:phone":"+39 0142 921468",
    "sg:postcode":"15038",
    "sg:province":"Alessandria",
    "sg:website":"http://www.moleto.it",
    "wof:name":"Cave Di Moleto",
    "wof:placetype":"venue"
},
  "geometry": {"coordinates":[8.369076,45.052929],"type":"Point"}
}