{
  "type": "Feature",
  "properties": {
    "addr:full":"20080 Vermezzo Vermezzo Milano 20080",
    "addr:postcode":"20080;20080",
    "iso:country":"IT",
    "sg:address":"20080 Vermezzo",
    "sg:city":"Vermezzo",
    "sg:classifiers":[
        {
            "category":"Sports & Exercise",
            "subcategory":"Tennis Court",
            "type":"Entertainment"
        }
    ],
    "sg:phone":"+39 02 9494 1294",
    "sg:postcode":"20080",
    "sg:province":"Milano",
    "sg:tags":[
        "e",
        "lo",
        "tempo",
        "libero",
        "per",
        "impianti",
        "il",
        "attrezzature"
    ],
    "sg:website":"http://www.caratti.it",
    "wof:name":"International Caratti Srl",
    "wof:placetype":"venue"
},
  "geometry": {"coordinates":[8.997987,45.37513],"type":"Point"}
}