{
  "type": "Feature",
  "properties": {
    "addr:full":"22070 Bregnano Bregnano Como 22070",
    "addr:postcode":"22070;22070",
    "iso:country":"IT",
    "sg:address":"22070 Bregnano",
    "sg:city":"Bregnano",
    "sg:classifiers":[
        {
            "category":"Manufacturing",
            "subcategory":"Tools & Machinery",
            "type":"Manufacturing & Wholesale Goods"
        }
    ],
    "sg:phone":"+39 031 728311",
    "sg:postcode":"22070",
    "sg:province":"Como",
    "sg:tags":[
        "material",
        "mechanical"
    ],
    "sg:website":"http://www.bavelloni.com",
    "wof:name":"Bavelloni Z. Spa",
    "wof:placetype":"venue"
},
  "geometry": {"coordinates":[9.062121,45.708813],"type":"Point"}
}