{
  "type": "Feature",
  "properties": {
    "iso:country":"IT",
    "sg:address":"87, Via Asti 14053 Canelli",
    "sg:city":"Canelli",
    "sg:classifiers":[
        {
            "category":"Manufacturing",
            "subcategory":"Lumber",
            "type":"Manufacturing & Wholesale Goods"
        }
    ],
    "sg:phone":"+39 0141 823126",
    "sg:postcode":"14053",
    "sg:province":"Asti",
    "sg:tags":[
        "wood"
    ],
    "wof:name":"S.i.p.a. (s.p.a.)",
    "wof:placetype":"venue"
},
  "geometry": {"coordinates":[8.224209,44.775116],"type":"Point"}
}