{
  "type": "Feature",
  "properties": {
    "addr:full":"Via Citernese 128/130 06016 San Giustino San Giustino Perugia 06016",
    "addr:housenumber":"128 / 130",
    "addr:postcode":"06016;06016",
    "addr:street":"Via Citernese",
    "iso:country":"IT",
    "sg:address":"Via Citernese 128/130 06016 San Giustino",
    "sg:city":"San Giustino",
    "sg:orig_category":"Accessories For Internal Combustion Engines",
    "sg:phone":"+39 075 861811",
    "sg:postcode":"06016",
    "sg:province":"Perugia",
    "sg:website":"www.arrow.it",
    "wof:name":"Arrows Special Parts Spa",
    "wof:placetype":"venue"
},
  "geometry": {"coordinates":[12.172967,43.540642],"type":"Point"}
}