{
  "type": "Feature",
  "properties": {
    "iso:country":"IT",
    "sg:address":"35040 Granze",
    "sg:city":"Granze",
    "sg:orig_category":"Forniture Per Abbigliamento E Pelletterie",
    "sg:phone":"+39 0429 98755",
    "sg:postcode":"35040",
    "sg:province":"Padova",
    "wof:name":"Sevarin Giuliano",
    "wof:placetype":"venue"
},
  "geometry": {"coordinates":[11.7274885178,45.1633110046],"type":"Point"}
}