{
  "type": "Feature",
  "properties": {
    "iso:country":"IT",
    "sg:address":"41012 Carpi",
    "sg:city":"Carpi",
    "sg:classifiers":[
        {
            "category":"Health Services",
            "subcategory":"Health Practitioner",
            "type":"Services"
        }
    ],
    "sg:phone":"+39 059 652885",
    "sg:postcode":"41012",
    "sg:province":"Modena",
    "sg:tags":[
        "medici"
    ],
    "wof:name":"Palladini Paolo Donato",
    "wof:placetype":"venue"
},
  "geometry": {"coordinates":[10.8988809586,44.7928962708],"type":"Point"}
}