{
  "type": "Feature",
  "properties": {
    "addr:full":"16122 Genova Genova Genova 16122",
    "addr:postcode":"16122;16122",
    "iso:country":"IT",
    "sg:address":"16122 Genova",
    "sg:city":"Genova",
    "sg:orig_category":"Servizi E Lavori Per Abbigliamento E Pelletterie",
    "sg:phone":"+39 010 272 2024",
    "sg:postcode":"16122",
    "sg:province":"Genova",
    "wof:name":"Timone Alda",
    "wof:placetype":"venue"
},
  "geometry": {"coordinates":[8.938987,44.416893],"type":"Point"}
}