{
  "type": "Feature",
  "properties": {
    "addr:full":"16016 Cogoleto Cogoleto Genova 16016",
    "addr:postcode":"16016;16016",
    "iso:country":"IT",
    "sg:address":"16016 Cogoleto",
    "sg:city":"Cogoleto",
    "sg:orig_category":"Autonoleggio",
    "sg:phone":"+39 010 918 8211",
    "sg:postcode":"16016",
    "sg:province":"Genova",
    "wof:name":"Guido Viaggi Di Gotro Guido & C. Snc",
    "wof:placetype":"venue"
},
  "geometry": {"coordinates":[8.669268,44.405861],"type":"Point"}
}