{
  "type": "Feature",
  "properties": {
    "iso:country":"IT",
    "sg:address":"60131 Ancona",
    "sg:city":"Ancona",
    "sg:orig_category":"Arredamenti E Mobili Professionali. Impianti, Attrezzature E Forniture Sanitarie Ed Ospedaliere",
    "sg:phone":"+39 071 280 4104",
    "sg:postcode":"60131",
    "sg:province":"Ancona",
    "wof:name":"Novellini Diffusion Srl",
    "wof:placetype":"venue"
},
  "geometry": {"coordinates":[13.500479,43.581085],"type":"Point"}
}