{
  "type": "Feature",
  "properties": {
    "addr:full":"24068 Seriate Seriate Bergamo 24068",
    "addr:postcode":"24068;24068",
    "iso:country":"IT",
    "sg:address":"24068 Seriate",
    "sg:city":"Seriate",
    "sg:orig_category":"Macchine Utensili E Impianti",
    "sg:phone":"+39 035 296540",
    "sg:postcode":"24068",
    "sg:province":"Bergamo",
    "wof:name":"A.t.p. (s.r.l.)",
    "wof:placetype":"venue"
},
  "geometry": {"coordinates":[9.733427,45.679729],"type":"Point"}
}