{
  "type": "Feature",
  "properties": {
    "addr:full":"Via I\u00b0 Maggio 35 48010 Casola Valsenio Casola Valsenio Ravenna 48010",
    "addr:housenumber":"35",
    "addr:postcode":"48010;48010",
    "addr:street":"Via I\u00b0 Maggio",
    "iso:country":"IT",
    "sg:address":"Via I\u00b0 Maggio 35 48010 Casola Valsenio",
    "sg:city":"Casola Valsenio",
    "sg:orig_category":"Enamel Frits",
    "sg:phone":"+39 0546 76711",
    "sg:postcode":"48010",
    "sg:province":"Ravenna",
    "sg:website":"www.vetriceramici.com",
    "wof:name":"Vetriceramici Srl",
    "wof:placetype":"venue"
},
  "geometry": {"coordinates":[12.196571,44.41573],"type":"Point"}
}