{
  "type": "Feature",
  "properties": {
    "iso:country":"IT",
    "sg:address":"41039 San Possidonio",
    "sg:city":"San Possidonio",
    "sg:classifiers":[
        {
            "category":"Government",
            "subcategory":"Office",
            "type":"Public Place"
        }
    ],
    "sg:phone":"+39 0535 39955",
    "sg:postcode":"41039",
    "sg:province":"Modena",
    "sg:tags":[
        "decorative",
        "equipment",
        "objects",
        "furnishings",
        "furnishing"
    ],
    "wof:name":"Safila Snc",
    "wof:placetype":"venue"
},
  "geometry": {"coordinates":[10.9918251038,44.8926887512],"type":"Point"}
}