{
  "type": "Feature",
  "properties": {
    "iso:country":"IT",
    "sg:address":"74100 Taranto",
    "sg:city":"Taranto",
    "sg:classifiers":[
        {
            "category":"Health Services",
            "subcategory":"Health Practitioner",
            "type":"Services"
        }
    ],
    "sg:phone":"+39 099 471 2129",
    "sg:postcode":"74100",
    "sg:province":"Taranto",
    "sg:tags":[
        "medici"
    ],
    "wof:name":"Scarano Rosa",
    "wof:placetype":"venue"
},
  "geometry": {"coordinates":[17.2291622162,40.4927330017],"type":"Point"}
}