{
  "type": "Feature",
  "properties": {
    "iso:country":"IT",
    "sg:address":"50053 Empoli",
    "sg:city":"Empoli",
    "sg:orig_category":"Forniture Per Abbigliamento E Pelletterie. Forniture E Materiali Per Imballaggio E Confezionamento",
    "sg:phone":"+39 0571 74136",
    "sg:postcode":"50053",
    "sg:province":"Firenze",
    "sg:website":"http://www.francioninastrificio.com",
    "wof:name":"Francioni & C. Snc",
    "wof:placetype":"venue"
},
  "geometry": {"coordinates":[11.2004346848,43.8358383179],"type":"Point"}
}