{
  "type": "Feature",
  "properties": {
    "iso:country":"IT",
    "sg:address":"47853 Coriano",
    "sg:city":"Coriano",
    "sg:orig_category":"Calzature, Pelletterie E Pelli",
    "sg:phone":"+39 0541 362111",
    "sg:postcode":"47853",
    "sg:province":"Rimini",
    "wof:name":"Consorzio San Patrignano S.c.r.l.",
    "wof:placetype":"venue"
},
  "geometry": {"coordinates":[12.555186,43.983852],"type":"Point"}
}