{
  "type": "Feature",
  "properties": {
    "addr:full":"20/b, Via Salvi Cristiani 50135 Firenze Firenze Firenze 50135",
    "addr:housenumber":"20 / b",
    "addr:postcode":"50135;50135",
    "addr:street":"Via Salvi Cristiani",
    "iso:country":"IT",
    "sg:address":"20/b, Via Salvi Cristiani 50135 Firenze",
    "sg:city":"Firenze",
    "sg:classifiers":[
        {
            "category":"Shopping",
            "subcategory":"Clothing, Apparel, & Fashions",
            "type":"Retail Goods"
        }
    ],
    "sg:phone":"+39 39055605778",
    "sg:postcode":"50135",
    "sg:province":"Firenze",
    "sg:tags":[
        "clothing",
        "accessory"
    ],
    "wof:name":"Ideale Cantini' S Ties Confezioni",
    "wof:placetype":"venue"
},
  "geometry": {"coordinates":[11.256902,43.768734],"type":"Point"}
}