{
  "type": "Feature",
  "properties": {
    "iso:country":"IT",
    "sg:address":"00041 Albano Laziale",
    "sg:city":"Albano Laziale",
    "sg:orig_category":"Macchine, Impianti Ed Attrezzature Per Abbigliamento E Pelletterie",
    "sg:phone":"+39 06 931 5478",
    "sg:postcode":"00041",
    "sg:province":"Roma",
    "wof:name":"Sa.com.srl",
    "wof:placetype":"venue"
},
  "geometry": {"coordinates":[12.6078,41.723694],"type":"Point"}
}