{
  "type": "Feature",
  "properties": {
    "iso:country":"IT",
    "sg:address":"70031 Andria",
    "sg:city":"Andria",
    "sg:orig_category":"Prodotti E Manufatti In Materie Plastiche. Articoli Per Imballaggio E Confezionamento",
    "sg:phone":"+39 0883 597142",
    "sg:postcode":"70031",
    "sg:province":"Bari",
    "wof:name":"Salerno Pasquale - Meridional Plast",
    "wof:placetype":"venue"
},
  "geometry": {"coordinates":[16.2972545624,41.2314376831],"type":"Point"}
}