{
  "type": "Feature",
  "properties": {
    "iso:country":"IT",
    "sg:address":"10127 Torino",
    "sg:city":"Torino",
    "sg:orig_category":"Macchine Utensili E Impianti",
    "sg:phone":"+39 011 605 4331",
    "sg:postcode":"10127",
    "sg:province":"Torino",
    "wof:name":"Ghirelli Nazzareno Srl",
    "wof:placetype":"venue"
},
  "geometry": {"coordinates":[7.653599,45.010014],"type":"Point"}
}