{
  "type": "Feature",
  "properties": {
    "iso:country":"IT",
    "sg:address":"15, V. E. Fermi 63010 Torre San Patrizio",
    "sg:city":"Torre San Patrizio",
    "sg:classifiers":[
        {
            "category":"Personal",
            "subcategory":"Shoe Repair & Shine",
            "type":"Services"
        }
    ],
    "sg:phone":"+39 0734 510250",
    "sg:postcode":"63010",
    "sg:province":"Ascoli Piceno",
    "sg:tags":[
        "leather"
    ],
    "sg:website":"http://www.paginegialle.it/torreplastic",
    "wof:name":"Torreplastic Sas",
    "wof:placetype":"venue"
},
  "geometry": {"coordinates":[13.574977,42.8554],"type":"Point"}
}