{
  "type": "Feature",
  "properties": {
    "iso:country":"IT",
    "sg:address":"2, Zona Industriale Vi Strada 30030 Fosso'",
    "sg:classifiers":[
        {
            "category":"Personal",
            "subcategory":"Shoe Repair & Shine",
            "type":"Services"
        }
    ],
    "sg:phone":"+39 041 517 0103",
    "sg:postcode":"30030",
    "sg:province":"Venezia",
    "sg:tags":[
        "leather"
    ],
    "wof:name":"Calzaturificio Saint Germain",
    "wof:placetype":"venue"
},
  "geometry": {"coordinates":[12.338784,45.434338],"type":"Point"}
}