{
  "type": "Feature",
  "properties": {
    "iso:country":"IT",
    "sg:address":"235, Via Della Cupola 50145 Firenze",
    "sg:city":"Firenze",
    "sg:classifiers":[
        {
            "category":"Manufacturing",
            "subcategory":"Rubber & Plastics",
            "type":"Manufacturing & Wholesale Goods"
        }
    ],
    "sg:phone":"+39 39055311819",
    "sg:postcode":"50145",
    "sg:province":"Firenze",
    "wof:name":"Gomoil S.r.l.",
    "wof:placetype":"venue"
},
  "geometry": {"coordinates":[11.193869,43.8009],"type":"Point"}
}