{
  "type": "Feature",
  "properties": {
    "iso:country":"IT",
    "sg:address":"26013 Crema",
    "sg:city":"Crema",
    "sg:orig_category":"Petroli, Gas E Combustibili",
    "sg:phone":"+39 0373 202817",
    "sg:postcode":"26013",
    "sg:province":"Cremona",
    "wof:name":"Panta Distribuzione Spa",
    "wof:placetype":"venue"
},
  "geometry": {"coordinates":[9.6677217484,45.35729599],"type":"Point"}
}