{
  "type": "Feature",
  "properties": {
    "iso:country":"IT",
    "sg:address":"36010 Carre'",
    "sg:orig_category":"Macchine, Impianti Ed Attrezzature Per Abbigliamento E Pelletterie",
    "sg:phone":"+39 0445 314725",
    "sg:postcode":"36010",
    "sg:province":"Vicenza",
    "wof:name":"In.te.co. Srl",
    "wof:placetype":"venue"
},
  "geometry": {"coordinates":[11.530158,45.734112],"type":"Point"}
}