{
  "type": "Feature",
  "properties": {
    "iso:country":"IT",
    "sg:address":"14015 S.damiano D'asti",
    "sg:orig_category":"Bevande, Vini E Liquori",
    "sg:phone":"+39 0141 971410",
    "sg:postcode":"14015",
    "sg:province":"Asti",
    "wof:name":"Al Centro Snc",
    "wof:placetype":"venue"
},
  "geometry": {"coordinates":[8.060925,44.846283],"type":"Point"}
}