{
  "type": "Feature",
  "properties": {
    "addr:full":"00186 Roma Roma Roma 00186",
    "addr:postcode":"00186;00186",
    "iso:country":"IT",
    "sg:address":"00186 Roma",
    "sg:city":"Roma",
    "sg:orig_category":"Servizi Editoriali. Shopping",
    "sg:phone":"+39 06 686 4741",
    "sg:postcode":"00186",
    "sg:province":"Roma",
    "wof:name":"Coliseum Srl",
    "wof:placetype":"venue"
},
  "geometry": {"coordinates":[12.474178,41.897274],"type":"Point"}
}