{
  "type": "Feature",
  "properties": {
    "addr:full":"81022 Casagiove Casagiove Caserta 81022",
    "addr:postcode":"81022;81022",
    "iso:country":"IT",
    "sg:address":"81022 Casagiove",
    "sg:city":"Casagiove",
    "sg:orig_category":"Pianoforti",
    "sg:phone":"+39 0823 466048",
    "sg:postcode":"81022",
    "sg:province":"Caserta",
    "wof:name":"Barone Raffaele",
    "wof:placetype":"venue"
},
  "geometry": {"coordinates":[14.3064680099,41.0857658386],"type":"Point"}
}