{
  "type": "Feature",
  "properties": {
    "addr:full":"70010 Sammichele Di Bari Sammichele di Bari Bari 70010",
    "addr:postcode":"70010;70010",
    "iso:country":"IT",
    "sg:address":"70010 Sammichele Di Bari",
    "sg:city":"Sammichele di Bari",
    "sg:orig_category":"Arredo Cucina Ed Elettrodomestici. Frigotecnica, Apparecchiature E Servizi. Elettrodomestici",
    "sg:phone":"+39 080 891 8241",
    "sg:postcode":"70010",
    "sg:province":"Bari",
    "wof:name":"Mastrangelo Domenico",
    "wof:placetype":"venue"
},
  "geometry": {"coordinates":[16.950821,40.888611],"type":"Point"}
}