{
  "type": "Feature",
  "properties": {
    "addr:full":"33, Via Borsellino Paolo 20024 Garbagnate Milanese Garbagnate Milanese Milano 20024",
    "addr:postcode":"20024;20024",
    "addr:street":"Via Borsellino Paolo",
    "iso:country":"IT",
    "sg:address":"33, Via Borsellino Paolo 20024 Garbagnate Milanese",
    "sg:city":"Garbagnate Milanese",
    "sg:classifiers":[
        {
            "category":"Shopping",
            "subcategory":"Crafts & Fabrics",
            "type":"Retail Goods"
        }
    ],
    "sg:phone":"+39 02 9902 6290",
    "sg:postcode":"20024",
    "sg:province":"Milano",
    "sg:tags":[
        "linen"
    ],
    "wof:name":"S.i.l.m.a. (s.r.l.)",
    "wof:placetype":"venue"
},
  "geometry": {"coordinates":[9.1881408691,45.4636878967],"type":"Point"}
}