{
  "type": "Feature",
  "properties": {
    "iso:country":"IT",
    "sg:address":"31015 Conegliano",
    "sg:city":"Conegliano",
    "sg:orig_category":"Periti Danni E Infortunistica Stradale",
    "sg:phone":"+39 0438 24200",
    "sg:postcode":"31015",
    "sg:province":"Treviso",
    "wof:name":"A.i.s.e.l. Sas",
    "wof:placetype":"venue"
},
  "geometry": {"coordinates":[12.300652504,45.8804321289],"type":"Point"}
}