{
  "type": "Feature",
  "properties": {
    "addr:full":"40122 Bologna Bologna Bologna 40122",
    "addr:postcode":"40122;40122",
    "iso:country":"IT",
    "sg:address":"40122 Bologna",
    "sg:city":"Bologna",
    "sg:orig_category":"Marketing E Ricerche Di Mercato",
    "sg:phone":"+39 051 528 1511",
    "sg:postcode":"40122",
    "sg:province":"Bologna",
    "sg:website":"http://www.gmpr.it",
    "wof:name":"G.m.p.r. Snc Di Gualerzi Corrado & C.",
    "wof:placetype":"venue"
},
  "geometry": {"coordinates":[11.335675,44.500454],"type":"Point"}
}