{
  "type": "Feature",
  "properties": {
    "addr:full":"26, Via Rivolta 56029 Santa Croce Sull'arno Pisa 56029",
    "addr:postcode":"56029;56029",
    "addr:street":"Via Rivolta",
    "iso:country":"IT",
    "sg:address":"26, Via Rivolta 56029 Santa Croce Sull'arno",
    "sg:orig_category":"Miscellaneous Products",
    "sg:phone":"+39 39057131773",
    "sg:postcode":"56029",
    "sg:province":"Pisa",
    "wof:name":"Chimera Srl",
    "wof:placetype":"venue"
},
  "geometry": {"coordinates":[10.7913961411,43.7135238647],"type":"Point"}
}