{
  "type": "Feature",
  "properties": {
    "addr:full":"2, Via Dell' Artigianato 35023 Bagnoli Di Sopra Bagnoli di Sopra Padova 35023",
    "addr:postcode":"35023;35023",
    "addr:street":"Via Dell ' Artigianato",
    "iso:country":"IT",
    "sg:address":"2, Via Dell' Artigianato 35023 Bagnoli Di Sopra",
    "sg:city":"Bagnoli di Sopra",
    "sg:classifiers":[
        {
            "category":"Manufacturing",
            "subcategory":"Rubber & Plastics",
            "type":"Manufacturing & Wholesale Goods"
        }
    ],
    "sg:phone":"+39 049 538 0099",
    "sg:postcode":"35023",
    "sg:province":"Padova",
    "wof:name":"Plastimec S N C Di Tomasoni Danilo E C.",
    "wof:placetype":"venue"
},
  "geometry": {"coordinates":[11.8940591812,45.1994514465],"type":"Point"}
}