{
  "type": "Feature",
  "properties": {
    "iso:country":"IT",
    "sg:address":"39016 Ultimo",
    "sg:city":"Ultimo",
    "sg:orig_category":"Carpenterie Legno",
    "sg:phone":"+39 0473 799002",
    "sg:postcode":"39016",
    "sg:province":"Bolzano/Bozen",
    "wof:name":"Gamper Roman",
    "wof:placetype":"venue"
},
  "geometry": {"coordinates":[10.999275,46.546806],"type":"Point"}
}