{
  "type": "Feature",
  "properties": {
    "iso:country":"IT",
    "sg:address":"44100 Ferrara",
    "sg:city":"Ferrara",
    "sg:orig_category":"Salotti, Poltrone, Sedie E Tavoli",
    "sg:phone":"+39 0532 796399",
    "sg:postcode":"44100",
    "sg:province":"Ferrara",
    "sg:website":"http://www.paginegialle.it/siriomaterassi",
    "wof:name":"Sirio Srl",
    "wof:placetype":"venue"
},
  "geometry": {"coordinates":[11.559533,44.934235],"type":"Point"}
}