{
  "type": "Feature",
  "properties": {
    "iso:country":"IT",
    "sg:address":"43, Via Archimede 16142 Genova",
    "sg:city":"Genova",
    "sg:classifiers":[
        {
            "category":"Building & Trades",
            "subcategory":"Construction",
            "type":"Services"
        }
    ],
    "sg:phone":"+39 39010515727",
    "sg:postcode":"16142",
    "sg:province":"Genova",
    "sg:tags":[
        "work",
        "public"
    ],
    "wof:name":"Pozzi Guizzetti Giuseppe & C. (s.a.s.)",
    "wof:placetype":"venue"
},
  "geometry": {"coordinates":[8.95161,44.406517],"type":"Point"}
}