{
  "type": "Feature",
  "properties": {
    "addr:full":"47900 Rimini Rimini Rimini 47900",
    "addr:postcode":"47900;47900",
    "iso:country":"IT",
    "sg:address":"47900 Rimini",
    "sg:city":"Rimini",
    "sg:classifiers":[
        {
            "category":"Health Services",
            "subcategory":"Health Practitioner",
            "type":"Services"
        }
    ],
    "sg:phone":"+39 0541 28034",
    "sg:postcode":"47900",
    "sg:province":"Rimini",
    "sg:tags":[
        "medici"
    ],
    "wof:name":"Cortellini Gabriele",
    "wof:placetype":"venue"
},
  "geometry": {"coordinates":[12.574271,44.060257],"type":"Point"}
}