{
  "type": "Feature",
  "properties": {
    "iso:country":"IT",
    "sg:address":"36040 Pedemonte",
    "sg:city":"Pedemonte",
    "sg:orig_category":"Calzature, Pelletterie E Pelli",
    "sg:phone":"+39 0445 747199",
    "sg:postcode":"36040",
    "sg:province":"Vicenza",
    "sg:website":"http://www.contactum.com/gabri",
    "wof:name":"Calzaturificio Molo Sante Snc Di Molo Bortolo & C.",
    "wof:placetype":"venue"
},
  "geometry": {"coordinates":[11.30713,45.908779],"type":"Point"}
}