{
  "type": "Feature",
  "properties": {
    "addr:full":"20060 Cassina De'pecchi Milano 20060",
    "addr:postcode":"20060;20060",
    "addr:street":"De'Pecchi",
    "iso:country":"IT",
    "sg:address":"20060 Cassina De'pecchi",
    "sg:orig_category":"Manufacturers: Prefabbricati",
    "sg:phone":"+39 02 952 2445",
    "sg:postcode":"20060",
    "sg:province":"Milano",
    "wof:name":"T.d. Williamson Italiana Srl",
    "wof:placetype":"venue"
},
  "geometry": {"coordinates":[9.32883,45.503044],"type":"Point"}
}