{
  "type": "Feature",
  "properties": {
    "iso:country":"IT",
    "sg:address":"95127 Catania",
    "sg:city":"Catania",
    "sg:orig_category":"Alberghi E Strutture Extra Alberghiere. Ospedali E Servizi Sanitari",
    "sg:phone":"+39 06 9572 27076",
    "sg:postcode":"95127",
    "sg:province":"Catania",
    "wof:name":"Centro Servizi Sociali Cristo Re",
    "wof:placetype":"venue"
},
  "geometry": {"coordinates":[15.100786,37.518559],"type":"Point"}
}