{
  "type": "Feature",
  "properties": {
    "iso:country":"IT",
    "sg:address":"Via Campana 00048 Nettuno",
    "sg:city":"Nettuno",
    "sg:classifiers":[
        {
            "category":"Professional",
            "subcategory":"Engineering",
            "type":"Services"
        }
    ],
    "sg:phone":"+39 39069858201",
    "sg:postcode":"00048",
    "sg:province":"Roma",
    "sg:tags":[
        "machine",
        "-",
        "mechanical"
    ],
    "wof:name":"Amati Carlo E C. S.n.c.",
    "wof:placetype":"venue"
},
  "geometry": {"coordinates":[12.6410217285,41.4808769226],"type":"Point"}
}