{
  "type": "Feature",
  "properties": {
    "iso:country":"IT",
    "sg:address":"70, Via A. Gramsci 42023 Cadelbosco Di Sopra",
    "sg:classifiers":[
        {
            "category":"Manufacturing",
            "subcategory":"Metals",
            "type":"Manufacturing & Wholesale Goods"
        }
    ],
    "sg:phone":"+39 0522 912097",
    "sg:postcode":"42023",
    "sg:province":"Reggio Nell'Emilia",
    "sg:tags":[
        "metallurgy",
        "metalworking"
    ],
    "wof:name":"New Casting Nironi S.r.l.",
    "wof:placetype":"venue"
},
  "geometry": {"coordinates":[10.6305332184,44.7763824463],"type":"Point"}
}