{
  "type": "Feature",
  "properties": {
    "addr:full":"52044 Cortona Cortona Arezzo 52044",
    "addr:postcode":"52044;52044",
    "iso:country":"IT",
    "sg:address":"52044 Cortona",
    "sg:city":"Cortona",
    "sg:orig_category":"Servizi E Lavori Per Agricoltura E Zootecnia. Imprese Di Costruzioni Civili Ed Industriali",
    "sg:phone":"+39 0575 603569",
    "sg:postcode":"52044",
    "sg:province":"Arezzo",
    "wof:name":"Finocchi Silvano Di Adriano E Claudio Finocchi",
    "wof:placetype":"venue"
},
  "geometry": {"coordinates":[11.975817,43.258865],"type":"Point"}
}