{
  "type": "Feature",
  "properties": {
    "addr:full":"Via Alberto Mario 28 36100 Vicenza Vicenza Vicenza 36100",
    "addr:housenumber":"28",
    "addr:postcode":"36100;36100",
    "addr:street":"Via Alberto Mario",
    "iso:country":"IT",
    "sg:address":"Via Alberto Mario 28 36100 Vicenza",
    "sg:city":"Vicenza",
    "sg:classifiers":[
        {
            "category":"Shopping",
            "subcategory":"Clothing, Apparel, & Fashions",
            "type":"Retail Goods"
        }
    ],
    "sg:phone":"+39 0444 569971",
    "sg:postcode":"36100",
    "sg:province":"Vicenza",
    "sg:tags":[
        "leather",
        "clothing"
    ],
    "wof:name":"International Apparel Srl",
    "wof:placetype":"venue"
},
  "geometry": {"coordinates":[11.526389,45.575279],"type":"Point"}
}