{
  "type": "Feature",
  "properties": {
    "iso:country":"IT",
    "sg:address":"27020 Valle Lomellina",
    "sg:city":"Valle Lomellina",
    "sg:orig_category":"Prodotti Alimentari. Agricoltura, Orticoltura E Floricoltura",
    "sg:phone":"+39 0384 79217",
    "sg:postcode":"27020",
    "sg:province":"Pavia",
    "wof:name":"Riso Eurico Italia S.p.a.",
    "wof:placetype":"venue"
},
  "geometry": {"coordinates":[8.6834058762,45.1505355835],"type":"Point"}
}