{
  "type": "Feature",
  "properties": {
    "iso:country":"IT",
    "sg:address":"85028 Rionero In Vulture",
    "sg:city":"Rionero in Vulture",
    "sg:orig_category":"Marmo, Pietre Ed Affini",
    "sg:phone":"+39 0972 721186",
    "sg:postcode":"85028",
    "sg:province":"Potenza",
    "wof:name":"Comm. Edil E. & V. Terzulli Snc",
    "wof:placetype":"venue"
},
  "geometry": {"coordinates":[15.559161,40.927738],"type":"Point"}
}