{
  "type": "Feature",
  "properties": {
    "iso:country":"IT",
    "sg:address":"46037 Roncoferraro",
    "sg:city":"Roncoferraro",
    "sg:classifiers":[
        {
            "category":"Restaurant",
            "type":"Food & Drink"
        }
    ],
    "sg:phone":"+39 0376 664300",
    "sg:postcode":"46037",
    "sg:province":"Mantova",
    "sg:tags":[
        "auxiliary",
        "entertainment",
        "premises",
        "related",
        "catering",
        "similar",
        "public",
        "restaurants"
    ],
    "wof:name":"Villa Cavriani",
    "wof:placetype":"venue"
},
  "geometry": {"coordinates":[10.924145,45.111435],"type":"Point"}
}