{
  "type": "Feature",
  "properties": {
    "iso:country":"IT",
    "sg:address":"35020 Masera'dipadova",
    "sg:orig_category":"Forniture E Prodotti Informatici. Forniture Per Uffici",
    "sg:phone":"+39 049 886 2316",
    "sg:postcode":"35020",
    "sg:province":"Padova",
    "wof:name":"Easycom Srl",
    "wof:placetype":"venue"
},
  "geometry": {"coordinates":[11.8406829834,45.3298950195],"type":"Point"}
}