{
  "type": "Feature",
  "properties": {
    "addr:full":"Via Sandro Pertini 20 30020 Annone Veneto Annone Veneto Venezia 30020",
    "addr:housenumber":"20",
    "addr:postcode":"30020;30020",
    "addr:street":"Via Sandro Pertini",
    "iso:country":"IT",
    "sg:address":"Via Sandro Pertini 20 30020 Annone Veneto",
    "sg:city":"Annone Veneto",
    "sg:classifiers":[
        {
            "category":"Food & Beverages",
            "subcategory":"Groceries & Convenience Stores",
            "type":"Retail Goods"
        }
    ],
    "sg:phone":"+39 0422 769763",
    "sg:postcode":"30020",
    "sg:province":"Venezia",
    "sg:tags":[
        "dietetic",
        "foodstuff"
    ],
    "sg:website":"www.conadromagna.it",
    "wof:name":"Conad Friul Veneto Scrl",
    "wof:placetype":"venue"
},
  "geometry": {"coordinates":[12.690795,45.798756],"type":"Point"}
}