{
  "type": "Feature",
  "properties": {
    "iso:country":"IT",
    "sg:address":"29, Via Calucci Giuseppe 30174 Venezia",
    "sg:city":"Venezia",
    "sg:classifiers":[
        {
            "category":"Wholesale",
            "subcategory":"Drugs",
            "type":"Manufacturing & Wholesale Goods"
        }
    ],
    "sg:phone":"+39 39041916035",
    "sg:postcode":"30174",
    "sg:province":"Venezia",
    "sg:tags":[
        "chemical",
        "pharmaceutical"
    ],
    "wof:name":"Campion Dino",
    "wof:placetype":"venue"
},
  "geometry": {"coordinates":[12.326627,45.440895],"type":"Point"}
}