{
  "type": "Feature",
  "properties": {
    "addr:full":"Regione San Bernardino 12073 Ceva Ceva Cuneo 12073",
    "addr:postcode":"12073;12073",
    "addr:street":"Regione San Bernardino",
    "iso:country":"IT",
    "sg:address":"Regione San Bernardino 12073 Ceva",
    "sg:city":"Ceva",
    "sg:classifiers":[
        {
            "category":"Professional",
            "subcategory":"Advertising",
            "type":"Services"
        }
    ],
    "sg:phone":"+39 0174 722222",
    "sg:postcode":"12073",
    "sg:province":"Cuneo",
    "sg:tags":[
        "industrial"
    ],
    "sg:website":"www.merlinopubblicita.com",
    "wof:name":"Merlino Pubblicita'",
    "wof:placetype":"venue"
},
  "geometry": {"coordinates":[8.041574,44.378128],"type":"Point"}
}