{
  "type": "Feature",
  "properties": {
    "iso:country":"IT",
    "sg:address":"2, Via Como 20063 Cernusco Sul Naviglio",
    "sg:city":"Cernusco sul Naviglio",
    "sg:classifiers":[
        {
            "category":"Shopping",
            "subcategory":"Crafts & Fabrics",
            "type":"Retail Goods"
        }
    ],
    "sg:phone":"+39 02 9214 7104",
    "sg:postcode":"20063",
    "sg:province":"Milano",
    "wof:name":"Camilla Textiles Spa",
    "wof:placetype":"venue"
},
  "geometry": {"coordinates":[9.3188428879,45.5001525879],"type":"Point"}
}