{
  "type": "Feature",
  "properties": {
    "iso:country":"IT",
    "sg:address":"46030 Dosolo",
    "sg:city":"Dosolo",
    "sg:orig_category":"Legno E Semilavorati",
    "sg:phone":"+39 0375 89298",
    "sg:postcode":"46030",
    "sg:province":"Mantova",
    "wof:name":"Gasparini Ferdinando E Figli (s.n.c.)",
    "wof:placetype":"venue"
},
  "geometry": {"coordinates":[10.640906,44.953835],"type":"Point"}
}