{
  "type": "Feature",
  "properties": {
    "iso:country":"IT",
    "sg:address":"Via Lorenzini Giovanni 10/12 20139 Milano",
    "sg:city":"Milano",
    "sg:classifiers":[
        {
            "category":"Community Center",
            "subcategory":"Senior",
            "type":"Public Place"
        }
    ],
    "sg:phone":"+39 02 535431",
    "sg:postcode":"20139",
    "sg:province":"Milano",
    "sg:tags":[
        "pen",
        "ball",
        "point"
    ],
    "sg:website":"www.bicworld.com",
    "wof:name":"Bic Italia Spa",
    "wof:placetype":"venue"
},
  "geometry": {"coordinates":[9.200167,45.443604],"type":"Point"}
}