{
  "type": "Feature",
  "properties": {
    "iso:country":"IT",
    "sg:address":"00152 Roma",
    "sg:city":"Roma",
    "sg:orig_category":"Servizi E Lavori Per Arredamento E Industria Del Legno. Servizi E Lavori Per Edilizia E Lavori Pubblici. Arte Ed Artigianato Artistico",
    "sg:phone":"+39 06 538974",
    "sg:postcode":"00152",
    "sg:province":"Roma",
    "wof:name":"Fratelli Anzilotti David E Stefano Snc",
    "wof:placetype":"venue"
},
  "geometry": {"coordinates":[12.458121,41.878933],"type":"Point"}
}