{
  "type": "Feature",
  "properties": {
    "addr:full":"96100 Siracusa Siracusa Siracusa 96100",
    "addr:postcode":"96100;96100",
    "iso:country":"IT",
    "sg:address":"96100 Siracusa",
    "sg:city":"Siracusa",
    "sg:orig_category":"Minuterie Metalliche E Ferramenta. Ricambi E Componenti Dei Mezzi Di Trasporto",
    "sg:phone":"+39 0931 24049",
    "sg:postcode":"96100",
    "sg:province":"Siracusa",
    "wof:name":"Campisi Salvatore",
    "wof:placetype":"venue"
},
  "geometry": {"coordinates":[15.2656297684,37.0547904968],"type":"Point"}
}