{
  "type": "Feature",
  "properties": {
    "addr:full":"16128 Genova Genova Genova 16128",
    "addr:postcode":"16128;16128",
    "iso:country":"IT",
    "sg:address":"16128 Genova",
    "sg:city":"Genova",
    "sg:orig_category":"Pubblica Amministrazione",
    "sg:phone":"+39 010 530 7111",
    "sg:postcode":"16128",
    "sg:province":"Genova",
    "wof:name":"Forze Armate-marina-ufficio Tecnico Marina Militare-navalgenarmi",
    "wof:placetype":"venue"
},
  "geometry": {"coordinates":[8.9381923676,44.397605896],"type":"Point"}
}