{
  "type": "Feature",
  "properties": {
    "addr:full":"14, Via Dell' Orso 20121 Milano Milano Milano 20121",
    "addr:postcode":"20121;20121",
    "addr:street":"Via Dell ' Orso",
    "iso:country":"IT",
    "sg:address":"14, Via Dell' Orso 20121 Milano",
    "sg:city":"Milano",
    "sg:classifiers":[
        {
            "category":"Professional",
            "subcategory":"Printing & Photocopies",
            "type":"Services"
        }
    ],
    "sg:phone":"+39 02 8646 3767",
    "sg:postcode":"20121",
    "sg:province":"Milano",
    "wof:name":"Eliorapid S.r.l.",
    "wof:placetype":"venue"
},
  "geometry": {"coordinates":[9.1864776611,45.4690551758],"type":"Point"}
}