{
  "type": "Feature",
  "properties": {
    "iso:country":"IT",
    "sg:address":"25, V. Rainoldi 21100 Varese",
    "sg:city":"Varese",
    "sg:classifiers":[
        {
            "category":"Manufacturing",
            "subcategory":"Tools & Machinery",
            "type":"Manufacturing & Wholesale Goods"
        }
    ],
    "sg:phone":"+39 0332 283996",
    "sg:postcode":"21100",
    "sg:province":"Varese",
    "sg:tags":[
        "environment",
        "equipment",
        "-"
    ],
    "sg:website":"http://www.paginegialle.it/eet",
    "wof:name":"E.e.t.",
    "wof:placetype":"venue"
},
  "geometry": {"coordinates":[8.832169,45.819317],"type":"Point"}
}