{
  "type": "Feature",
  "properties": {
    "addr:full":"90029 Valledolmo Valledolmo Palermo 90029",
    "addr:postcode":"90029;90029",
    "iso:country":"IT",
    "sg:address":"90029 Valledolmo",
    "sg:city":"Valledolmo",
    "sg:classifiers":[
        {
            "category":"Bars & Pubs",
            "subcategory":"Champagne Bar",
            "type":"Food & Drink"
        }
    ],
    "sg:phone":"+39 0921 544121",
    "sg:postcode":"90029",
    "sg:province":"Palermo",
    "sg:tags":[
        "caffe'",
        "e"
    ],
    "wof:name":"Vallone Carmelo - Rica Caff\u00c8",
    "wof:placetype":"venue"
},
  "geometry": {"coordinates":[13.435851,38.079319],"type":"Point"}
}