{
  "type": "Feature",
  "properties": {
    "iso:country":"IT",
    "sg:address":"44, Piazza S. Allende 47021 Bagno Di Romagna",
    "sg:city":"Bagno di Romagna",
    "sg:classifiers":[
        {
            "category":"Farming",
            "subcategory":"Livestock Farm",
            "type":"Manufacturing & Wholesale Goods"
        }
    ],
    "sg:phone":"+39 0543 917726",
    "sg:postcode":"47021",
    "sg:province":"Forl\u00ec-Cesena",
    "sg:tags":[
        "agriculture"
    ],
    "wof:name":"C.l.a.f.c.",
    "wof:placetype":"venue"
},
  "geometry": {"coordinates":[11.959402,43.835804],"type":"Point"}
}