{
  "type": "Feature",
  "properties": {
    "iso:country":"IT",
    "sg:address":"10051 Avigliana",
    "sg:city":"Avigliana",
    "sg:orig_category":"Prodotti E Manufatti In Materie Plastiche",
    "sg:phone":"+39 011 934 8752",
    "sg:postcode":"10051",
    "sg:province":"Torino",
    "wof:name":"Espaplast S.r.l.",
    "wof:placetype":"venue"
},
  "geometry": {"coordinates":[7.4136023521,45.086479187],"type":"Point"}
}