{
  "type": "Feature",
  "properties": {
    "iso:country":"IT",
    "sg:address":"Via Lombardia 8 50050 Ponte A Cappiano",
    "sg:classifiers":[
        {
            "category":"Home & Garden",
            "subcategory":"Carpets & Floor Coverings",
            "type":"Retail Goods"
        }
    ],
    "sg:phone":"+39 0571 297820",
    "sg:postcode":"50050",
    "sg:province":"Firenze",
    "sg:tags":[
        "animal",
        "skin"
    ],
    "wof:name":"Conceria Virginia Spa",
    "wof:placetype":"venue"
},
  "geometry": {"coordinates":[11.256902,43.768734],"type":"Point"}
}