{
  "type": "Feature",
  "properties": {
    "addr:full":"20123 Milano Milano Milano 20123",
    "addr:postcode":"20123;20123",
    "iso:country":"IT",
    "sg:address":"20123 Milano",
    "sg:city":"Milano",
    "sg:orig_category":"Abbigliamento Esterno, Maglierie E Pelliccerie. Calzature, Pelletterie E Pelli. Shopping",
    "sg:phone":"+39 02 839 4135",
    "sg:postcode":"20123",
    "sg:province":"Milano",
    "wof:name":"Cut Snc",
    "wof:placetype":"venue"
},
  "geometry": {"coordinates":[9.180556,45.456196],"type":"Point"}
}