{
  "type": "Feature",
  "properties": {
    "addr:full":"00147 Roma Roma Roma 00147",
    "addr:postcode":"00147;00147",
    "iso:country":"IT",
    "sg:address":"00147 Roma",
    "sg:city":"Roma",
    "sg:classifiers":[
        {
            "category":"Travel",
            "subcategory":"Hotels & Motels",
            "type":"Entertainment"
        }
    ],
    "sg:phone":"+39 06 510772",
    "sg:postcode":"00147",
    "sg:province":"Roma",
    "sg:tags":[
        "hotels",
        "facility"
    ],
    "sg:website":"http://www.paginegialle.it/hortiflaviani",
    "wof:name":"Sette Chiese Spa",
    "wof:placetype":"venue"
},
  "geometry": {"coordinates":[12.505767,41.859047],"type":"Point"}
}