{
  "type": "Feature",
  "properties": {
    "addr:full":"12051 Alba Alba Cuneo 12051",
    "addr:postcode":"12051;12051",
    "iso:country":"IT",
    "sg:address":"12051 Alba",
    "sg:city":"Alba",
    "sg:orig_category":"Pelliccerie",
    "sg:phone":"+39 0173 441778",
    "sg:postcode":"12051",
    "sg:province":"Cuneo",
    "wof:name":"Raballo Lorenzo",
    "wof:placetype":"venue"
},
  "geometry": {"coordinates":[8.0349674225,44.6999359131],"type":"Point"}
}