{
  "type": "Feature",
  "properties": {
    "addr:full":"19, Via Vespucci Amerigo 21013 Gallarate Gallarate Varese 21013",
    "addr:postcode":"21013;21013",
    "addr:street":"Via Vespucci Amerigo",
    "iso:country":"IT",
    "sg:address":"19, Via Vespucci Amerigo 21013 Gallarate",
    "sg:city":"Gallarate",
    "sg:classifiers":[
        {
            "category":"Shopping",
            "subcategory":"Crafts & Fabrics",
            "type":"Retail Goods"
        }
    ],
    "sg:phone":"+39 0331 777123",
    "sg:postcode":"21013",
    "sg:province":"Varese",
    "wof:name":"Nightex By Filippini Srl",
    "wof:placetype":"venue"
},
  "geometry": {"coordinates":[8.8263845444,45.8176040649],"type":"Point"}
}