{
  "type": "Feature",
  "properties": {
    "addr:full":"203, Via Panisperna 00184 Roma Roma Roma 00184",
    "addr:housenumber":"203",
    "addr:postcode":"00184;00184",
    "addr:street":"Via Panisperna",
    "iso:country":"IT",
    "sg:address":"203, Via Panisperna 00184 Roma",
    "sg:city":"Roma",
    "sg:classifiers":[
        {
            "category":"Professional",
            "subcategory":"Advertising",
            "type":"Services"
        }
    ],
    "sg:phone":"+39 39064817877",
    "sg:postcode":"00184",
    "sg:province":"Roma",
    "sg:tags":[
        "communication",
        "medium"
    ],
    "wof:name":"Associazione Ips Inter Press Service Srl",
    "wof:placetype":"venue"
},
  "geometry": {"coordinates":[12.492743,41.896763],"type":"Point"}
}