{
  "type": "Feature",
  "properties": {
    "iso:country":"IT",
    "sg:address":"14, Corso Spagna 35127 Padova",
    "sg:city":"Padova",
    "sg:classifiers":[
        {
            "category":"Autos & Motor Vehicles",
            "subcategory":"Automobile Sales",
            "type":"Retail Goods"
        }
    ],
    "sg:phone":"+39 049 870 0611",
    "sg:postcode":"35127",
    "sg:province":"Padova",
    "sg:tags":[
        "equipment",
        "transport"
    ],
    "wof:name":"Nord Est Terminal S.p.a.",
    "wof:placetype":"venue"
},
  "geometry": {"coordinates":[11.923043,45.353905],"type":"Point"}
}