{
  "type": "Feature",
  "properties": {
    "iso:country":"IT",
    "sg:address":"16132 Genova",
    "sg:city":"Genova",
    "sg:orig_category":"Ospedali E Servizi Sanitari",
    "sg:phone":"+39 010 396690",
    "sg:postcode":"16132",
    "sg:province":"Genova",
    "wof:name":"Bruzzo Massimo",
    "wof:placetype":"venue"
},
  "geometry": {"coordinates":[8.985502,44.40469],"type":"Point"}
}