{
  "type": "Feature",
  "properties": {
    "iso:country":"IT",
    "sg:address":"00054 Fiumicino",
    "sg:city":"Fiumicino",
    "sg:orig_category":"Servizi Per Lo Sport E Il Tempo Libero. Servizi Ausiliari Dei Mezzi Di Trasporto",
    "sg:phone":"+39 06 652 3513",
    "sg:postcode":"00054",
    "sg:province":"Roma",
    "wof:name":"Balena Yachting Service Srl",
    "wof:placetype":"venue"
},
  "geometry": {"coordinates":[12.276525,41.760368],"type":"Point"}
}