{
  "type": "Feature",
  "properties": {
    "iso:country":"IT",
    "sg:address":"Corso Umberto 251/253; Macomer",
    "sg:classifiers":[
        {
            "category":"Banks & Credit Unions",
            "subcategory":"Bank",
            "type":"Services"
        }
    ],
    "sg:phone":"+39 0785 71071",
    "wof:name":"Banco Di Sardegna Spa",
    "wof:placetype":"venue"
},
  "geometry": {"coordinates":[8.775123,40.267979],"type":"Point"}
}