{
  "type": "Feature",
  "properties": {
    "iso:country":"IT",
    "sg:address":"21050 Lonate Ceppino",
    "sg:city":"Lonate Ceppino",
    "sg:orig_category":"Termotecnica E Riscaldamento, Apparecchiature E Servizi",
    "sg:phone":"+39 0331 842142",
    "sg:postcode":"21050",
    "sg:province":"Varese",
    "wof:name":"Pensotti Srl",
    "wof:placetype":"venue"
},
  "geometry": {"coordinates":[8.879797,45.714081],"type":"Point"}
}