{
  "type": "Feature",
  "properties": {
    "addr:full":"Corso Cavour 3, 09014 Carloforte, Ca Carloforte Carbonia-Iglesias 09014",
    "addr:housenumber":"3",
    "addr:postcode":"09014;09014",
    "addr:street":"Corso Cavour",
    "iso:country":"IT",
    "sg:address":"Corso Cavour 3, 09014 Carloforte, Ca",
    "sg:city":"Carloforte",
    "sg:classifiers":[
        {
            "category":"Banks & Credit Unions",
            "subcategory":"Bank",
            "type":"Services"
        }
    ],
    "sg:postcode":"09014",
    "sg:province":"Carbonia-Iglesias",
    "wof:name":"Consorzio Per Lo Sviluppo Turistico Di Carloforte",
    "wof:placetype":"venue"
},
  "geometry": {"coordinates":[8.308528,39.146957],"type":"Point"}
}