{
  "type": "Feature",
  "properties": {
    "addr:full":"Via Del Lavoro 17 47035 Gambettola Gambettola Forl\u00ec-Cesena 47035",
    "addr:housenumber":"17",
    "addr:postcode":"47035;47035",
    "addr:street":"Via Del Lavoro",
    "iso:country":"IT",
    "sg:address":"Via Del Lavoro 17 47035 Gambettola",
    "sg:city":"Gambettola",
    "sg:classifiers":[
        {
            "category":"Professional",
            "subcategory":"Advertising",
            "type":"Services"
        }
    ],
    "sg:phone":"+39 0547 58759",
    "sg:postcode":"47035",
    "sg:province":"Forl\u00ec-Cesena",
    "sg:tags":[
        "full-service"
    ],
    "sg:website":"www.ilpuntoimmagini.com",
    "wof:name":"Gentile Claudio",
    "wof:placetype":"venue"
},
  "geometry": {"coordinates":[12.3357191086,44.110408783],"type":"Point"}
}