{
  "type": "Feature",
  "properties": {
    "iso:country":"IT",
    "sg:address":"Via Delle Valli 1 20042 Albiate",
    "sg:city":"Albiate",
    "sg:classifiers":[
        {
            "category":"Banks & Credit Unions",
            "subcategory":"Bureau De Change",
            "type":"Services"
        }
    ],
    "sg:phone":"+39 036 293531",
    "sg:postcode":"20042",
    "sg:province":"Milano",
    "sg:tags":[
        "punching",
        "series",
        "press"
    ],
    "sg:website":"www.castinggroup.net",
    "wof:name":"Casting Srl",
    "wof:placetype":"venue"
},
  "geometry": {"coordinates":[9.240597,45.644127],"type":"Point"}
}