{
  "type": "Feature",
  "properties": {
    "addr:full":"19, Via Caduti Del Lavoro 46027 San Benedetto Po San Benedetto Po Mantova 46027",
    "addr:postcode":"46027;46027",
    "addr:street":"Via Caduti Del Lavoro;Po",
    "iso:country":"IT",
    "sg:address":"19, Via Caduti Del Lavoro 46027 San Benedetto Po",
    "sg:city":"San Benedetto Po",
    "sg:classifiers":[
        {
            "category":"Shopping",
            "subcategory":"Clothing, Apparel, & Fashions",
            "type":"Retail Goods"
        }
    ],
    "sg:phone":"+39 0376 620476",
    "sg:postcode":"46027",
    "sg:province":"Mantova",
    "sg:tags":[
        "clothes"
    ],
    "wof:name":"Tessilmoda (s.n.c.)",
    "wof:placetype":"venue"
},
  "geometry": {"coordinates":[10.797698,45.160366],"type":"Point"}
}