{
  "type": "Feature",
  "properties": {
    "addr:full":"56021 Cascina Cascina Pisa 56021",
    "addr:postcode":"56021;56021",
    "addr:street":"Cascina Pisa",
    "iso:country":"IT",
    "sg:address":"56021 Cascina",
    "sg:city":"Cascina",
    "sg:orig_category":"Antinfortunistica - Attrezzature Ed Articoli",
    "sg:phone":"+39 050 700878",
    "sg:postcode":"56021",
    "sg:province":"Pisa",
    "wof:name":"Donati Fratelli",
    "wof:placetype":"venue"
},
  "geometry": {"coordinates":[10.433776,43.706348],"type":"Point"}
}