{
  "type": "Feature",
  "properties": {
    "iso:country":"IT",
    "sg:address":"Contrada Cusatino 93010 Serradifalco",
    "sg:city":"Serradifalco",
    "sg:classifiers":[
        {
            "category":"Autos & Motor Vehicles",
            "subcategory":"Automobile Sales",
            "type":"Retail Goods"
        }
    ],
    "sg:phone":"+39 0934 940035",
    "sg:postcode":"93010",
    "sg:province":"Caltanissetta",
    "sg:tags":[
        "industrial"
    ],
    "wof:name":"Gimon Srl",
    "wof:placetype":"venue"
},
  "geometry": {"coordinates":[13.925729,37.457798],"type":"Point"}
}