{
  "type": "Feature",
  "properties": {
    "iso:country":"IT",
    "sg:address":"20019 Settimo Milanese",
    "sg:city":"Settimo Milanese",
    "sg:orig_category":"Carni, Salumi E Pesci",
    "sg:phone":"+39 02 3350 3132",
    "sg:postcode":"20019",
    "sg:province":"Milano",
    "wof:name":"Lunghi Giuseppe",
    "wof:placetype":"venue"
},
  "geometry": {"coordinates":[9.071602,45.476593],"type":"Point"}
}