{
  "type": "Feature",
  "properties": {
    "iso:country":"IT",
    "sg:address":"24021 Albino",
    "sg:city":"Albino",
    "sg:orig_category":"Ristorazione E Locali Pubblici Affini. Ristoranti Ed Esercizi Affini. Servizi Ausiliari Di Ristorazione E Di Intrattenimento",
    "sg:phone":"+39 035 770820",
    "sg:postcode":"24021",
    "sg:province":"Bergamo",
    "sg:website":"http://www.bigioplayjazz.it",
    "wof:name":"Bigio L'oster",
    "wof:placetype":"venue"
},
  "geometry": {"coordinates":[9.852188,45.768696],"type":"Point"}
}