{
  "type": "Feature",
  "properties": {
    "iso:country":"IT",
    "sg:address":"4, Via Morgagni Gianbattista 37135 Verona",
    "sg:city":"Verona",
    "sg:classifiers":[
        {
            "category":"Shopping",
            "subcategory":"Clothing, Apparel, & Fashions",
            "type":"Retail Goods"
        }
    ],
    "sg:phone":"+39 39045582696",
    "sg:postcode":"37135",
    "sg:province":"Verona",
    "sg:tags":[
        "clothes"
    ],
    "wof:name":"Max Sport",
    "wof:placetype":"venue"
},
  "geometry": {"coordinates":[10.969073,45.408798],"type":"Point"}
}