{
  "type": "Feature",
  "properties": {
    "iso:country":"IT",
    "sg:address":"00184 Roma",
    "sg:city":"Roma",
    "sg:orig_category":"Cine-foto-ottica. Articoli Medico-sanitari Ed Ortopedici",
    "sg:phone":"+39 06 474 1274",
    "sg:postcode":"00184",
    "sg:province":"Roma",
    "wof:name":"Istituto Ottico F.i.o.s. Srl",
    "wof:placetype":"venue"
},
  "geometry": {"coordinates":[12.495067,41.899822],"type":"Point"}
}