{
  "type": "Feature",
  "properties": {
    "addr:full":"80138 Napoli Napoli Napoli 80138",
    "addr:housenumber":"80138",
    "addr:postcode":"80138",
    "iso:country":"IT",
    "sg:address":"80138 Napoli",
    "sg:city":"Napoli",
    "sg:orig_category":"Scuole E Servizi Scolastici. Centri Di Estetica E Cosmesi E Servizi. Ricerca, Selezione E Formazione Del Personale",
    "sg:phone":"+39 081 440495",
    "sg:postcode":"80138",
    "sg:province":"Napoli",
    "sg:website":"http://www.isdnapoli.it",
    "wof:name":"Isd - Istituto Superiore Di Design",
    "wof:placetype":"venue"
},
  "geometry": {"coordinates":[14.259453,40.852707],"type":"Point"}
}