{
  "type": "Feature",
  "properties": {
    "addr:full":"10088 Volpiano Volpiano Torino 10088",
    "addr:postcode":"10088;10088",
    "iso:country":"IT",
    "sg:address":"10088 Volpiano",
    "sg:city":"Volpiano",
    "sg:orig_category":"Adesivi",
    "sg:phone":"+39 011 982 5811",
    "sg:postcode":"10088",
    "sg:province":"Torino",
    "wof:name":"Lacat Srl",
    "wof:placetype":"venue"
},
  "geometry": {"coordinates":[7.759646,45.168266],"type":"Point"}
}