{
  "type": "Feature",
  "properties": {
    "iso:country":"IT",
    "sg:address":"Via Europa 10 24040 Comun Nuovo",
    "sg:city":"Comun Nuovo",
    "sg:classifiers":[
        {
            "category":"Shopping",
            "subcategory":"Discount & Variety Stores",
            "type":"Retail Goods"
        }
    ],
    "sg:phone":"+39 035 454 4244",
    "sg:postcode":"24040",
    "sg:province":"Bergamo",
    "sg:tags":[
        "shop",
        "fitting"
    ],
    "sg:website":"www.rachfinazziarredamenti.com",
    "wof:name":"Rach Finazzi Arredamenti Srl",
    "wof:placetype":"venue"
},
  "geometry": {"coordinates":[9.6275491714,45.6623535156],"type":"Point"}
}