{
  "type": "Feature",
  "properties": {
    "addr:full":"Via Delle Industrie 7 35040 Villa Estense Villa Estense Padova 35040",
    "addr:housenumber":"7",
    "addr:postcode":"35040;35040",
    "addr:street":"Via Delle Industrie",
    "iso:country":"IT",
    "sg:address":"Via Delle Industrie 7 35040 Villa Estense",
    "sg:city":"Villa Estense",
    "sg:classifiers":[
        {
            "category":"Wholesale",
            "subcategory":"Electrical",
            "type":"Manufacturing & Wholesale Goods"
        }
    ],
    "sg:phone":"+39 0429 91270",
    "sg:postcode":"35040",
    "sg:province":"Padova",
    "sg:tags":[
        "component"
    ],
    "sg:website":"www.eurocablaggi.it",
    "wof:name":"Eurocablaggi Snc Di Magon Adriano & C.",
    "wof:placetype":"venue"
},
  "geometry": {"coordinates":[11.670881,45.17654],"type":"Point"}
}