{
  "type": "Feature",
  "properties": {
    "iso:country":"IT",
    "sg:address":"8, Via Giovanni Ciocchi 17047 Vado Ligure",
    "sg:city":"Vado Ligure",
    "sg:classifiers":[
        {
            "category":"Utilities",
            "subcategory":"Electric",
            "type":"Services"
        }
    ],
    "sg:phone":"+39 39019884221",
    "sg:postcode":"17047",
    "sg:province":"Savona",
    "sg:tags":[
        "component",
        "electronic"
    ],
    "wof:name":"S.i.ci.s. S.r.l.",
    "wof:placetype":"venue"
},
  "geometry": {"coordinates":[8.477246,44.311069],"type":"Point"}
}