{
  "type": "Feature",
  "properties": {
    "iso:country":"IT",
    "sg:address":"2, Via Madama Mussone 12050 Castellinaldo",
    "sg:city":"Castellinaldo",
    "sg:classifiers":[
        {
            "category":"Food & Beverages",
            "subcategory":"Groceries & Convenience Stores",
            "type":"Retail Goods"
        }
    ],
    "sg:phone":"+39 0173 213048",
    "sg:postcode":"12050",
    "sg:province":"Cuneo",
    "sg:tags":[
        "drink"
    ],
    "wof:name":"Marsaglia",
    "wof:placetype":"venue"
},
  "geometry": {"coordinates":[8.027136,44.774403],"type":"Point"}
}