{
  "type": "Feature",
  "properties": {
    "iso:country":"IT",
    "sg:address":"20124 Milano",
    "sg:city":"Milano",
    "sg:orig_category":"Orologeria",
    "sg:phone":"+39 02 2940 9053",
    "sg:postcode":"20124",
    "sg:province":"Milano",
    "wof:name":"Calisei Alfredo - Cx Calisex",
    "wof:placetype":"venue"
},
  "geometry": {"coordinates":[9.208214,45.47971],"type":"Point"}
}