{
  "type": "Feature",
  "properties": {
    "iso:country":"IT",
    "sg:address":"Via G. Verga, 1/27 - Rovereto Sul Secchia 41016 Novi Di Modena",
    "sg:city":"Novi di Modena",
    "sg:classifiers":[
        {
            "category":"Manufacturing",
            "subcategory":"Rubber & Plastics",
            "type":"Manufacturing & Wholesale Goods"
        }
    ],
    "sg:phone":"+39 059 673811",
    "sg:postcode":"41016",
    "sg:province":"Modena",
    "sg:tags":[
        "mould",
        "industry"
    ],
    "sg:website":"www.lameplast.it",
    "wof:name":"Lameplast Spa",
    "wof:placetype":"venue"
},
  "geometry": {"coordinates":[10.9468860626,44.8227310181],"type":"Point"}
}