{
  "type": "Feature",
  "properties": {
    "iso:country":"IT",
    "sg:address":"195, Via Chisini 31053 Pieve Di Soligo",
    "sg:city":"Pieve di Soligo",
    "sg:classifiers":[
        {
            "category":"Home & Garden",
            "subcategory":"Home Furnishings",
            "type":"Retail Goods"
        }
    ],
    "sg:phone":"+39 39043883670",
    "sg:postcode":"31053",
    "sg:province":"Treviso",
    "sg:tags":[
        "household"
    ],
    "wof:name":"I.c.m.a. (s.r.l.)",
    "wof:placetype":"venue"
},
  "geometry": {"coordinates":[12.179374,45.8908],"type":"Point"}
}