{
  "type": "Feature",
  "properties": {
    "addr:full":"40010 Sala Bolognese Sala Bolognese Bologna 40010",
    "addr:postcode":"40010;40010",
    "addr:street":"Bolognese",
    "iso:country":"IT",
    "sg:address":"40010 Sala Bolognese",
    "sg:city":"Sala Bolognese",
    "sg:orig_category":"Prodotti Vari In Metallo. Articoli Per Imballaggio E Confezionamento",
    "sg:phone":"+39 051 828182",
    "sg:postcode":"40010",
    "sg:province":"Bologna",
    "wof:name":"Casma S.n.c. Di Pagani Walter & C.",
    "wof:placetype":"venue"
},
  "geometry": {"coordinates":[11.2726297379,44.5622634888],"type":"Point"}
}