{
  "type": "Feature",
  "properties": {
    "iso:country":"IT",
    "sg:address":"28053 Castelletto Sopra Ticino",
    "sg:city":"Castelletto sopra Ticino",
    "sg:orig_category":"Termotecnica E Riscaldamento, Apparecchiature E Servizi",
    "sg:phone":"+39 0331 928800",
    "sg:postcode":"28053",
    "sg:province":"Novara",
    "wof:name":"Imit S P A",
    "wof:placetype":"venue"
},
  "geometry": {"coordinates":[8.61783,45.716892],"type":"Point"}
}