{
  "type": "Feature",
  "properties": {
    "addr:full":"28043 Badia Di Dulzago Novara 28043",
    "addr:postcode":"28043;28043",
    "addr:street":"Di Dulzago",
    "iso:country":"IT",
    "sg:address":"28043 Badia Di Dulzago",
    "sg:orig_category":"Prodotti Alimentari. Agricoltura, Orticoltura E Floricoltura",
    "sg:phone":"+39 0321 98180",
    "sg:postcode":"28043",
    "sg:province":"Novara",
    "wof:name":"Barbero Giuseppe Riseria & C.(s.n.c.)",
    "wof:placetype":"venue"
},
  "geometry": {"coordinates":[8.6132917404,45.5497550964],"type":"Point"}
}