{
  "type": "Feature",
  "properties": {
    "addr:full":"47838 Riccione Riccione Rimini 47838",
    "addr:postcode":"47838;47838",
    "iso:country":"IT",
    "sg:address":"47838 Riccione",
    "sg:city":"Riccione",
    "sg:orig_category":"Servizi E Lavori Per Edilizia E Lavori Pubblici. Servizi Ausiliari Di Sorveglianza, Manutenzione E Pulizia",
    "sg:phone":"+39 0541 690238",
    "sg:postcode":"47838",
    "sg:province":"Rimini",
    "wof:name":"Adriatica Impianti Services",
    "wof:placetype":"venue"
},
  "geometry": {"coordinates":[12.639243,43.983467],"type":"Point"}
}