{
  "type": "Feature",
  "properties": {
    "addr:full":"20085 Locate Di Triulzi Locate di Triulzi Milano 20085",
    "addr:postcode":"20085;20085",
    "iso:country":"IT",
    "sg:address":"20085 Locate Di Triulzi",
    "sg:city":"Locate di Triulzi",
    "sg:orig_category":"Ospedali E Servizi Sanitari. Centri Di Estetica E Cosmesi E Servizi",
    "sg:phone":"+39 02 9073 0553",
    "sg:postcode":"20085",
    "sg:province":"Milano",
    "wof:name":"Ricci Maria Rosa",
    "wof:placetype":"venue"
},
  "geometry": {"coordinates":[9.224951,45.358967],"type":"Point"}
}