{
  "type": "Feature",
  "properties": {
    "addr:full":"80040 Cercola Cercola Napoli 80040",
    "addr:postcode":"80040;80040",
    "iso:country":"IT",
    "sg:address":"80040 Cercola",
    "sg:city":"Cercola",
    "sg:orig_category":"Utensili Meccanici E Materiali",
    "sg:phone":"+39 081 555 1777",
    "sg:postcode":"80040",
    "sg:province":"Napoli",
    "wof:name":"Cryo Welding And Service Srl",
    "wof:placetype":"venue"
},
  "geometry": {"coordinates":[14.359378,40.859188],"type":"Point"}
}