{
  "type": "Feature",
  "properties": {
    "addr:full":"07026 Olbia Olbia Olbia-Tempio 07026",
    "addr:postcode":"07026;07026",
    "iso:country":"IT",
    "sg:address":"07026 Olbia",
    "sg:city":"Olbia",
    "sg:orig_category":"Prodotti Alimentari. Servizi E Lavori Per Industria Alimentare E Bevande",
    "sg:phone":"+39 0789 51639",
    "sg:postcode":"07026",
    "sg:province":"Olbia-Tempio",
    "sg:website":"http://www.derosaspanifici.it",
    "wof:name":"Derosas Srl",
    "wof:placetype":"venue"
},
  "geometry": {"coordinates":[9.2785587311,40.826839447],"type":"Point"}
}