{
  "type": "Feature",
  "properties": {
    "iso:country":"IT",
    "sg:address":"Largo Della Fragola Rossa 13 56029 Santa Croce Sull'arno",
    "sg:classifiers":[
        {
            "category":"Home & Garden",
            "subcategory":"Carpets & Floor Coverings",
            "type":"Retail Goods"
        }
    ],
    "sg:phone":"+39 0571 33641",
    "sg:postcode":"56029",
    "sg:province":"Pisa",
    "sg:tags":[
        "animal",
        "skin"
    ],
    "sg:website":"www.arcapelli.com",
    "wof:name":"Arcapelli S.a.s.",
    "wof:placetype":"venue"
},
  "geometry": {"coordinates":[10.780838,43.717049],"type":"Point"}
}