{
  "type": "Feature",
  "properties": {
    "addr:full":"Via Piave 26; Porto D'ascoli; 63037",
    "addr:housenumber":"26",
    "addr:postcode":"63037",
    "addr:street":"Via Piave",
    "iso:country":"IT",
    "sg:address":"Via Piave 26; Porto D'ascoli; 63037",
    "sg:classifiers":[
        {
            "category":"Banks & Credit Unions",
            "subcategory":"Bank",
            "type":"Services"
        }
    ],
    "sg:phone":"+39 0735 751998",
    "wof:name":"Cariverona Banca Spa",
    "wof:placetype":"venue"
},
  "geometry": {"coordinates":[13.891497,42.910744],"type":"Point"}
}