{
  "type": "Feature",
  "properties": {
    "iso:country":"IT",
    "sg:address":"98072 Caronia",
    "sg:city":"Caronia",
    "sg:orig_category":"Ceramiche: Prodotti E Lavorazioni. Articoli Da Regalo. Arte Ed Artigianato Artistico. Shopping",
    "sg:phone":"+39 0921 335208",
    "sg:postcode":"98072",
    "sg:province":"Messina",
    "sg:website":"http://www.filadelfio.it",
    "wof:name":"Modellati Filadelfio Todaro",
    "wof:placetype":"venue"
},
  "geometry": {"coordinates":[14.495624,37.980774],"type":"Point"}
}