{
  "type": "Feature",
  "properties": {
    "addr:full":"00162 Roma Roma Roma 00162",
    "addr:postcode":"00162;00162",
    "iso:country":"IT",
    "sg:address":"00162 Roma",
    "sg:city":"Roma",
    "sg:orig_category":"Servizi E Lavori Per Arredamento E Industria Del Legno. Vetro: Prodotti E Lavorazioni",
    "sg:phone":"+39 06 8620 5274",
    "sg:postcode":"00162",
    "sg:province":"Roma",
    "wof:name":"Esa Vetro Di Ettore Savarese & C. Snc",
    "wof:placetype":"venue"
},
  "geometry": {"coordinates":[12.526935,41.905579],"type":"Point"}
}