{
  "type": "Feature",
  "properties": {
    "addr:full":"9, Circonvallazione Esterna 10043 Orbassano Orbassano Torino 10043",
    "addr:postcode":"10043;10043",
    "addr:street":"Circonvallazione Esterna",
    "iso:country":"IT",
    "sg:address":"9, Circonvallazione Esterna 10043 Orbassano",
    "sg:city":"Orbassano",
    "sg:classifiers":[
        {
            "category":"Wholesale",
            "subcategory":"Drugs",
            "type":"Manufacturing & Wholesale Goods"
        }
    ],
    "sg:phone":"+39 011 901 1950",
    "sg:postcode":"10043",
    "sg:province":"Torino",
    "sg:tags":[
        "chemical",
        "pharmaceutical"
    ],
    "wof:name":"Isva Vernici (s.r.l.)",
    "wof:placetype":"venue"
},
  "geometry": {"coordinates":[7.546068,44.995964],"type":"Point"}
}