{
  "type": "Feature",
  "properties": {
    "iso:country":"IT",
    "sg:address":"Corso Mazzini 8/10; Cervia; 48015",
    "sg:city":"Cervia",
    "sg:classifiers":[
        {
            "category":"Banks & Credit Unions",
            "subcategory":"Bank",
            "type":"Services"
        }
    ],
    "sg:phone":"+39 0544 970970",
    "sg:postcode":"48015",
    "sg:province":"Ravenna",
    "wof:name":"Cassa Di Risparmio Di Cesena Spa",
    "wof:placetype":"venue"
},
  "geometry": {"coordinates":[12.349648,44.260674],"type":"Point"}
}