{
  "type": "Feature",
  "properties": {
    "iso:country":"IT",
    "sg:address":"03039 Sora",
    "sg:city":"Sora",
    "sg:classifiers":[
        {
            "category":"Health Services",
            "subcategory":"Health Practitioner",
            "type":"Services"
        }
    ],
    "sg:phone":"+39 0776 831409",
    "sg:postcode":"03039",
    "sg:province":"Frosinone",
    "sg:tags":[
        "medici"
    ],
    "wof:name":"Badalamenti Giovanni",
    "wof:placetype":"venue"
},
  "geometry": {"coordinates":[13.616551,41.724087],"type":"Point"}
}