{
  "type": "Feature",
  "properties": {
    "iso:country":"IT",
    "sg:address":"Corso Galliera 83r 16142 Genova",
    "sg:city":"Genova",
    "sg:classifiers":[
        {
            "category":"Shopping",
            "subcategory":"Discount & Variety Stores",
            "type":"Retail Goods"
        }
    ],
    "sg:phone":"+39 010 505029",
    "sg:postcode":"16142",
    "sg:province":"Genova",
    "sg:tags":[
        "household",
        "sewing",
        "machines"
    ],
    "sg:website":"www.seikopruzzorenato.com",
    "wof:name":"Pruzzo Renato & C. Sas",
    "wof:placetype":"venue"
},
  "geometry": {"coordinates":[8.933989,44.407063],"type":"Point"}
}