{
  "type": "Feature",
  "properties": {
    "iso:country":"IT",
    "sg:address":"20093 Cologno Monzese",
    "sg:city":"Cologno Monzese",
    "sg:orig_category":"Materiali E Componenti Elettrotecnici. Elettrotecnica Industriale, Prodotti E Apparecchiature",
    "sg:phone":"+39 02 254 7888",
    "sg:postcode":"20093",
    "sg:province":"Milano",
    "wof:name":"Specialtrasfo Spa",
    "wof:placetype":"venue"
},
  "geometry": {"coordinates":[9.273151,45.526474],"type":"Point"}
}