{
  "type": "Feature",
  "properties": {
    "addr:full":"00175 Roma Roma Roma 00175",
    "addr:postcode":"00175;00175",
    "iso:country":"IT",
    "sg:address":"00175 Roma",
    "sg:city":"Roma",
    "sg:classifiers":[
        {
            "category":"Health Services",
            "subcategory":"Dentist",
            "type":"Services"
        }
    ],
    "sg:phone":"+39 06 2430 2222",
    "sg:postcode":"00175",
    "sg:province":"Roma",
    "sg:tags":[
        "hospital"
    ],
    "wof:name":"Nuova Croce Verde Romana Srl",
    "wof:placetype":"venue"
},
  "geometry": {"coordinates":[12.559922,41.861591],"type":"Point"}
}