{
  "type": "Feature",
  "properties": {
    "iso:country":"IT",
    "sg:address":"Frazione Crosi 42 10084 Forno Canavese",
    "sg:city":"Forno Canavese",
    "sg:classifiers":[
        {
            "category":"Banks & Credit Unions",
            "subcategory":"Investment Brokerage",
            "type":"Services"
        }
    ],
    "sg:phone":"+39 0124 77026",
    "sg:postcode":"10084",
    "sg:province":"Torino",
    "sg:tags":[
        "fuel",
        "cap",
        "tank"
    ],
    "sg:website":"www.casetti.it",
    "wof:name":"F.lli Casetti Srl",
    "wof:placetype":"venue"
},
  "geometry": {"coordinates":[7.6050605774,45.3374824524],"type":"Point"}
}