{
  "type": "Feature",
  "properties": {
    "iso:country":"IT",
    "sg:address":"98066 Patti",
    "sg:city":"Patti",
    "sg:orig_category":"Casalinghi",
    "sg:phone":"+39 0941 241242",
    "sg:postcode":"98066",
    "sg:province":"Messina",
    "wof:name":"Leone Srl",
    "wof:placetype":"venue"
},
  "geometry": {"coordinates":[15.561604,38.186562],"type":"Point"}
}