{
  "type": "Feature",
  "properties": {
    "iso:country":"IT",
    "sg:address":"28, Via Del Commercio 36050 Sovizzo",
    "sg:city":"Sovizzo",
    "sg:classifiers":[
        {
            "category":"Professional",
            "subcategory":"Engineering",
            "type":"Services"
        }
    ],
    "sg:phone":"+39 0444 536241",
    "sg:postcode":"36050",
    "sg:province":"Vicenza",
    "sg:tags":[
        "machine",
        "-",
        "mechanical"
    ],
    "wof:name":"Brevetti C.e.a. (s.p.a.)",
    "wof:placetype":"venue"
},
  "geometry": {"coordinates":[11.451141,45.526112],"type":"Point"}
}