{
  "type": "Feature",
  "properties": {
    "iso:country":"IT",
    "sg:address":"16121 Genova",
    "sg:city":"Genova",
    "sg:orig_category":"Servizi Al Turismo. Trasporto Pubblico E Privato",
    "sg:phone":"+39 010 55091",
    "sg:postcode":"16121",
    "sg:province":"Genova",
    "wof:name":"Grimaldi Compagnia Di Navigazione (s.p.a.)",
    "wof:placetype":"venue"
},
  "geometry": {"coordinates":[8.936028,44.40435],"type":"Point"}
}