{
  "type": "Feature",
  "properties": {
    "iso:country":"IT",
    "sg:address":"43052 Colorno",
    "sg:city":"Colorno",
    "sg:orig_category":"Gelateria E Pasticceria Fresca - Macchine E Forniture",
    "sg:phone":"+39 0521 814881",
    "sg:postcode":"43052",
    "sg:province":"Parma",
    "wof:name":"Dolcelinea Srl",
    "wof:placetype":"venue"
},
  "geometry": {"coordinates":[10.313891,44.903095],"type":"Point"}
}