{
  "type": "Feature",
  "properties": {
    "addr:full":"Via Montini; Lumezzane",
    "addr:street":"Via Montini",
    "iso:country":"IT",
    "sg:address":"Via Montini; Lumezzane",
    "sg:classifiers":[
        {
            "category":"Banks & Credit Unions",
            "subcategory":"Bank",
            "type":"Services"
        }
    ],
    "sg:phone":"+39 030 827575",
    "wof:name":"Banca Agricola Mantovana Scarl",
    "wof:placetype":"venue"
},
  "geometry": {"coordinates":[10.274136,45.650017],"type":"Point"}
}