{
  "type": "Feature",
  "properties": {
    "iso:country":"IT",
    "sg:address":"52025 Montevarchi",
    "sg:city":"Montevarchi",
    "sg:orig_category":"Tessuti E Stoffe",
    "sg:phone":"+39 055 910 2009",
    "sg:postcode":"52025",
    "sg:province":"Arezzo",
    "wof:name":"Torelli T.",
    "wof:placetype":"venue"
},
  "geometry": {"coordinates":[11.855974,43.472115],"type":"Point"}
}