{
  "type": "Feature",
  "properties": {
    "iso:country":"IT",
    "sg:address":"03012 Anagni",
    "sg:city":"Anagni",
    "sg:orig_category":"Non-classified Establishments",
    "sg:phone":"+39 0775 769942",
    "sg:postcode":"03012",
    "sg:province":"Frosinone",
    "wof:name":"Mobilificio Tootsie",
    "wof:placetype":"venue"
},
  "geometry": {"coordinates":[13.29578,41.610405],"type":"Point"}
}