{
  "type": "Feature",
  "properties": {
    "iso:country":"IT",
    "sg:address":"Contrada Ripoli 64023 Mosciano Sant'angelo",
    "sg:classifiers":[
        {
            "category":"Shopping",
            "subcategory":"Stationery & Office Supplies",
            "type":"Retail Goods"
        }
    ],
    "sg:phone":"+39 085 807 1520",
    "sg:postcode":"64023",
    "sg:province":"Teramo",
    "sg:tags":[
        "furniture"
    ],
    "sg:website":"www.timeoffice.it",
    "wof:name":"Time Office Srl",
    "wof:placetype":"venue"
},
  "geometry": {"coordinates":[13.905109,42.721867],"type":"Point"}
}