{
  "type": "Feature",
  "properties": {
    "addr:full":"60125 Ancona Ancona Ancona 60125",
    "addr:postcode":"60125;60125",
    "iso:country":"IT",
    "sg:address":"60125 Ancona",
    "sg:city":"Ancona",
    "sg:orig_category":"Lavorazioni Meccaniche E Servizi. Riparazione Dei Mezzi Di Trasporto",
    "sg:phone":"+39 071 501 1111",
    "sg:postcode":"60125",
    "sg:province":"Ancona",
    "wof:name":"Crn-ferretti Group",
    "wof:placetype":"venue"
},
  "geometry": {"coordinates":[13.491475,43.609753],"type":"Point"}
}