{
  "type": "Feature",
  "properties": {
    "addr:full":"80075 Forio Forio Napoli 80075",
    "addr:postcode":"80075;80075",
    "iso:country":"IT",
    "sg:address":"80075 Forio",
    "sg:city":"Forio",
    "sg:orig_category":"Alberghi E Strutture Extra Alberghiere. Ospedali E Servizi Sanitari",
    "sg:phone":"+39 081 989584",
    "sg:postcode":"80075",
    "sg:province":"Napoli",
    "wof:name":"Ccoperativa Sociale Doc Srl",
    "wof:placetype":"venue"
},
  "geometry": {"coordinates":[13.873803,40.725731],"type":"Point"}
}