{
  "type": "Feature",
  "properties": {
    "iso:country":"IT",
    "sg:address":"00165 Roma",
    "sg:city":"Roma",
    "sg:classifiers":[
        {
            "category":"Professional",
            "subcategory":"Art Services",
            "type":"Services"
        }
    ],
    "sg:phone":"+39 06 3937 6627",
    "sg:postcode":"00165",
    "sg:province":"Roma",
    "sg:tags":[
        "entertainment",
        "cultural",
        "artistic",
        "crafts",
        "services",
        "tourism"
    ],
    "wof:name":"Antiquariato Europeo Srl",
    "wof:placetype":"venue"
},
  "geometry": {"coordinates":[12.440144,41.89613],"type":"Point"}
}