{
  "type": "Feature",
  "properties": {
    "iso:country":"IT",
    "sg:address":"20124 Milano",
    "sg:city":"Milano",
    "sg:orig_category":"Agenzie Di Spettacolo E Di Animazione",
    "sg:phone":"+39 02 2900 6958",
    "sg:postcode":"20124",
    "sg:province":"Milano",
    "wof:name":"Associazione Italiana Musicisti Srl",
    "wof:placetype":"venue"
},
  "geometry": {"coordinates":[9.200007,45.4795],"type":"Point"}
}