{
  "type": "Feature",
  "properties": {
    "iso:country":"IT",
    "sg:address":"37, Via Vittorio Veneto 21050 Cairate",
    "sg:city":"Cairate",
    "sg:classifiers":[
        {
            "category":"Shopping",
            "subcategory":"Crafts & Fabrics",
            "type":"Retail Goods"
        }
    ],
    "sg:phone":"+39 0331 360487",
    "sg:postcode":"21050",
    "sg:province":"Varese",
    "wof:name":"Felisi Valmorea (s.r.l.)",
    "wof:placetype":"venue"
},
  "geometry": {"coordinates":[8.8703832626,45.6870269775],"type":"Point"}
}