{
  "type": "Feature",
  "properties": {
    "iso:country":"IT",
    "sg:address":"29014 Castell'arquato",
    "sg:orig_category":"Valvole E Apparecchiature Di Misura. Attrezzature E Forniture Per Officine Riparazione E Servizi Ausiliari. Macchine, Strumenti Ed Apparecchi Per Attivita' Industriali",
    "sg:phone":"+39 0523 803832",
    "sg:postcode":"29014",
    "sg:province":"Piacenza",
    "wof:name":"L.s.b. Di Sabino Luigi",
    "wof:placetype":"venue"
},
  "geometry": {"coordinates":[9.87657,44.862255],"type":"Point"}
}