{
  "type": "Feature",
  "properties": {
    "iso:country":"IT",
    "sg:address":"80128 Napoli",
    "sg:city":"Napoli",
    "sg:orig_category":"Banche E Servizi Finanziari",
    "sg:phone":"+39 081 578 3196",
    "sg:postcode":"80128",
    "sg:province":"Napoli",
    "wof:name":"Monteforte Antonietta",
    "wof:placetype":"venue"
},
  "geometry": {"coordinates":[14.224568,40.859787],"type":"Point"}
}