{
  "type": "Feature",
  "properties": {
    "addr:full":"21, Via Valdoni 31013 Codogne' Treviso 31013",
    "addr:postcode":"31013;31013",
    "addr:street":"Via Valdoni",
    "iso:country":"IT",
    "sg:address":"21, Via Valdoni 31013 Codogne'",
    "sg:classifiers":[
        {
            "category":"Manufacturing",
            "subcategory":"Metals",
            "type":"Manufacturing & Wholesale Goods"
        }
    ],
    "sg:phone":"+39 0438 778247",
    "sg:postcode":"31013",
    "sg:province":"Treviso",
    "sg:tags":[
        "processing"
    ],
    "wof:name":"L.m.c. Di Carnelos Lino",
    "wof:placetype":"venue"
},
  "geometry": {"coordinates":[12.3822383881,45.8664588928],"type":"Point"}
}