{
  "type": "Feature",
  "properties": {
    "iso:country":"IT",
    "sg:address":"20048 Carate Brianza",
    "sg:city":"Carate Brianza",
    "sg:orig_category":"Prodotti E Manufatti In Materie Plastiche. Articoli Per Imballaggio E Confezionamento",
    "sg:phone":"+39 036 299 1082",
    "sg:postcode":"20048",
    "sg:province":"Milano",
    "wof:name":"Nuova Tecnopol Snc",
    "wof:placetype":"venue"
},
  "geometry": {"coordinates":[9.2369832993,45.6630401611],"type":"Point"}
}