{
  "type": "Feature",
  "properties": {
    "iso:country":"IT",
    "sg:address":"Via Garibaldi 9; Misano; 47046",
    "sg:classifiers":[
        {
            "category":"Banks & Credit Unions",
            "subcategory":"Bank",
            "type":"Services"
        }
    ],
    "sg:phone":"+39 0541 615120",
    "wof:name":"Rolo Banca 1473 Spa",
    "wof:placetype":"venue"
},
  "geometry": {"coordinates":[9.677781,45.496334],"type":"Point"}
}