{
  "type": "Feature",
  "properties": {
    "addr:full":"74026 Taranto Taranto 74026",
    "addr:postcode":"74026;74026",
    "iso:country":"IT",
    "sg:address":"74026 Taranto",
    "sg:orig_category":"Imprese Di Costruzioni Civili Ed Industriali. Servizi E Lavori Per Ecologia E Smaltimento Rifiuti",
    "sg:phone":"+39 099 777 5610",
    "sg:postcode":"74026",
    "sg:province":"Taranto",
    "wof:name":"De Santis Ferdinando",
    "wof:placetype":"venue"
},
  "geometry": {"coordinates":[17.242998,40.574089],"type":"Point"}
}