{
  "type": "Feature",
  "properties": {
    "iso:country":"IT",
    "sg:address":"15, V. Corsari 70010 Casamassima",
    "sg:city":"Casamassima",
    "sg:orig_category":"Miscellaneous Products",
    "sg:phone":"+39 080 453 0065",
    "sg:postcode":"70010",
    "sg:province":"Bari",
    "wof:name":"Euroantique Di Blum Mechtilde",
    "wof:placetype":"venue"
},
  "geometry": {"coordinates":[16.9220924377,40.9532699585],"type":"Point"}
}