{
  "type": "Feature",
  "properties": {
    "addr:full":"97019 Vittoria Vittoria Ragusa 97019",
    "addr:postcode":"97019;97019",
    "iso:country":"IT",
    "sg:address":"97019 Vittoria",
    "sg:city":"Vittoria",
    "sg:orig_category":"Prodotti E Manufatti In Materie Plastiche. Articoli Per Imballaggio E Confezionamento",
    "sg:phone":"+39 0932 997211",
    "sg:postcode":"97019",
    "sg:province":"Ragusa",
    "sg:website":"http://www.agriplast.com",
    "wof:name":"Grinplast Srl",
    "wof:placetype":"venue"
},
  "geometry": {"coordinates":[14.4956235886,36.9358253479],"type":"Point"}
}