{
  "type": "Feature",
  "properties": {
    "addr:full":"Via Nazionale, 320; Salerno; 84012 Salerno 84012",
    "addr:housenumber":"320",
    "addr:postcode":"84012;84012",
    "addr:street":"Via Nazionale",
    "iso:country":"IT",
    "sg:address":"Via Nazionale, 320; Salerno; 84012",
    "sg:classifiers":[
        {
            "category":"Industrial Area",
            "type":"Public Place"
        }
    ],
    "sg:phone":"+39 081 516 6111",
    "sg:postcode":"84012",
    "sg:province":"Salerno",
    "sg:tags":[
        "large",
        "private"
    ],
    "sg:website":"www.ladoria.it",
    "wof:name":"La Doria S.p.a.",
    "wof:placetype":"venue"
},
  "geometry": {"coordinates":[14.9149608612,40.627784729],"type":"Point"}
}