{
  "type": "Feature",
  "properties": {
    "addr:full":"95046 Palagonia Palagonia Catania 95046",
    "addr:postcode":"95046;95046",
    "iso:country":"IT",
    "sg:address":"95046 Palagonia",
    "sg:city":"Palagonia",
    "sg:orig_category":"Forniture Per Abbigliamento E Pelletterie",
    "sg:phone":"+39 095 795 5614",
    "sg:postcode":"95046",
    "sg:province":"Catania",
    "wof:name":"Centro Idea S.r.l.",
    "wof:placetype":"venue"
},
  "geometry": {"coordinates":[14.7637615204,37.3532676697],"type":"Point"}
}