{
  "type": "Feature",
  "properties": {
    "addr:full":"29100 Piacenza Piacenza Piacenza 29100",
    "addr:postcode":"29100;29100",
    "iso:country":"IT",
    "sg:address":"29100 Piacenza",
    "sg:city":"Piacenza",
    "sg:orig_category":"Pareti Mobili E Divisorie",
    "sg:phone":"+39 0523 337223",
    "sg:postcode":"29100",
    "sg:province":"Piacenza",
    "wof:name":"U-glass Piacenza Srl",
    "wof:placetype":"venue"
},
  "geometry": {"coordinates":[10.1211681366,45.2473983765],"type":"Point"}
}