{
  "type": "Feature",
  "properties": {
    "iso:country":"IT",
    "sg:address":"10040 La Loggia",
    "sg:city":"La Loggia",
    "sg:orig_category":"Materiali Edili",
    "sg:phone":"+39 011 962 8177",
    "sg:postcode":"10040",
    "sg:province":"Torino",
    "sg:website":"http://www.gallina.it",
    "wof:name":"Dr. Gallina Srl E.i.m.p.",
    "wof:placetype":"venue"
},
  "geometry": {"coordinates":[7.670872,44.984604],"type":"Point"}
}