{
  "type": "Feature",
  "properties": {
    "addr:full":"47023 Cesena Cesena Forl\u00ec-Cesena 47023",
    "addr:postcode":"47023;47023",
    "iso:country":"IT",
    "sg:address":"47023 Cesena",
    "sg:city":"Cesena",
    "sg:orig_category":"Termotecnica E Riscaldamento, Apparecchiature E Servizi. Prodotti Vari In Metallo",
    "sg:phone":"+39 0547 334134",
    "sg:postcode":"47023",
    "sg:province":"Forl\u00ec-Cesena",
    "wof:name":"Ati Di Mariani Mario & C. Snc",
    "wof:placetype":"venue"
},
  "geometry": {"coordinates":[12.210908,44.159801],"type":"Point"}
}