{
  "type": "Feature",
  "properties": {
    "iso:country":"IT",
    "sg:address":"41019 Soliera",
    "sg:city":"Soliera",
    "sg:orig_category":"Acciai Inossidabili - Lavorazione",
    "sg:phone":"+39 059 561094",
    "sg:postcode":"41019",
    "sg:province":"Modena",
    "sg:website":"http://www.icam-inox.com",
    "wof:name":"Icam Inox Srl",
    "wof:placetype":"venue"
},
  "geometry": {"coordinates":[10.898629,44.744762],"type":"Point"}
}