{
  "type": "Feature",
  "properties": {
    "iso:country":"IT",
    "sg:address":"4, Via Venezia 37053 Cerea",
    "sg:city":"Cerea",
    "sg:classifiers":[
        {
            "category":"Manufacturing",
            "subcategory":"Lumber",
            "type":"Manufacturing & Wholesale Goods"
        }
    ],
    "sg:phone":"+39 0442 320225",
    "sg:postcode":"37053",
    "sg:province":"Verona",
    "sg:tags":[
        "wood"
    ],
    "wof:name":"Bernardinello (s.r.l.)",
    "wof:placetype":"venue"
},
  "geometry": {"coordinates":[10.991748,45.438366],"type":"Point"}
}