{
  "type": "Feature",
  "properties": {
    "iso:country":"IT",
    "sg:address":"Via Meucci, 9 - Visano 50031 Barberino Di Mugello",
    "sg:city":"Barberino di Mugello",
    "sg:classifiers":[
        {
            "category":"Home & Garden",
            "subcategory":"Furniture",
            "type":"Retail Goods"
        }
    ],
    "sg:phone":"+39 055 84721",
    "sg:postcode":"50031",
    "sg:province":"Firenze",
    "sg:tags":[
        "apartment"
    ],
    "sg:website":"www.emmelunga.it",
    "wof:name":"Emmelunga Spa",
    "wof:placetype":"venue"
},
  "geometry": {"coordinates":[11.256902,43.768734],"type":"Point"}
}