{
  "type": "Feature",
  "properties": {
    "addr:full":"38030 Ceola Trento 38030",
    "addr:postcode":"38030;38030",
    "addr:street":"Ceola Trento",
    "iso:country":"IT",
    "sg:address":"38030 Ceola",
    "sg:classifiers":[
        {
            "category":"Arena",
            "subcategory":"Sports Club",
            "type":"Entertainment"
        }
    ],
    "sg:phone":"+39 0461 684577",
    "sg:postcode":"38030",
    "sg:province":"Trento",
    "sg:tags":[
        "e",
        "lo",
        "tempo",
        "libero",
        "per",
        "servizi",
        "il"
    ],
    "wof:name":"Brugnara Franco Giorgio",
    "wof:placetype":"venue"
},
  "geometry": {"coordinates":[11.169865,46.159279],"type":"Point"}
}