{
  "type": "Feature",
  "properties": {
    "iso:country":"IT",
    "sg:address":"21, Viale Del Popolo 06083 Bastia",
    "sg:city":"Bastia",
    "sg:classifiers":[
        {
            "category":"Manufacturing",
            "subcategory":"Rubber & Plastics",
            "type":"Manufacturing & Wholesale Goods"
        }
    ],
    "sg:phone":"+39 075 801 0952",
    "sg:postcode":"06083",
    "sg:province":"Perugia",
    "wof:name":"Ziarelli Fratelli Gomme (s.r.l.)",
    "wof:placetype":"venue"
},
  "geometry": {"coordinates":[12.540763,43.076767],"type":"Point"}
}