{
  "type": "Feature",
  "properties": {
    "iso:country":"IT",
    "sg:address":"00040 Roma",
    "sg:orig_category":"Forniture Per Agricoltura E Zootecnia",
    "sg:phone":"+39 06 7984 7343",
    "sg:postcode":"00040",
    "sg:province":"Roma",
    "wof:name":"La Veterinaria S.r.l.",
    "wof:placetype":"venue"
},
  "geometry": {"coordinates":[12.6065616608,41.8119277954],"type":"Point"}
}