{
  "type": "Feature",
  "properties": {
    "addr:full":"7, Via Amendola 51010 Uzzano Uzzano Pistoia 51010",
    "addr:postcode":"51010;51010",
    "addr:street":"Via Amendola",
    "iso:country":"IT",
    "sg:address":"7, Via Amendola 51010 Uzzano",
    "sg:city":"Uzzano",
    "sg:classifiers":[
        {
            "category":"Manufacturing",
            "subcategory":"Food",
            "type":"Manufacturing & Wholesale Goods"
        }
    ],
    "sg:phone":"+39 0572 451012",
    "sg:postcode":"51010",
    "sg:province":"Pistoia",
    "sg:tags":[
        "equipment",
        "processing",
        "-",
        "machinery"
    ],
    "wof:name":"Pavan S.p.a.",
    "wof:placetype":"venue"
},
  "geometry": {"coordinates":[10.9185237885,43.9321556091],"type":"Point"}
}