{
  "type": "Feature",
  "properties": {
    "addr:full":"Via Negrotto 38 20157 Milano Milano Milano 20157",
    "addr:housenumber":"38",
    "addr:postcode":"20157;20157",
    "addr:street":"Via Negrotto",
    "iso:country":"IT",
    "sg:address":"Via Negrotto 38 20157 Milano",
    "sg:city":"Milano",
    "sg:classifiers":[
        {
            "category":"Manufacturing",
            "subcategory":"Metals",
            "type":"Manufacturing & Wholesale Goods"
        }
    ],
    "sg:phone":"+39 02 3800 3800",
    "sg:postcode":"20157",
    "sg:province":"Milano",
    "sg:tags":[
        "heavy",
        "melting",
        "non-ferrous",
        "furnace",
        "metals"
    ],
    "sg:website":"www.marconiforni.com",
    "wof:name":"Marconi Srl",
    "wof:placetype":"venue"
},
  "geometry": {"coordinates":[9.1472177505,45.504108429],"type":"Point"}
}