{
  "type": "Feature",
  "properties": {
    "iso:country":"IT",
    "sg:address":"20090 Segrate",
    "sg:city":"Segrate",
    "sg:orig_category":"Materiali Semilavorati Metallici",
    "sg:phone":"+39 02 2692 0738",
    "sg:postcode":"20090",
    "sg:province":"Milano",
    "wof:name":"Jannone Ferro Tubi Spa",
    "wof:placetype":"venue"
},
  "geometry": {"coordinates":[9.297803,45.500275],"type":"Point"}
}