{
  "type": "Feature",
  "properties": {
    "addr:full":"Via Gramsci Antonio 4-6 16010 Manesseno Manesseno Genova 16010",
    "addr:housenumber":"4-6",
    "addr:postcode":"16010;16010",
    "addr:street":"Via Gramsci Antonio",
    "iso:country":"IT",
    "sg:address":"Via Gramsci Antonio 4-6 16010 Manesseno",
    "sg:city":"Manesseno",
    "sg:classifiers":[
        {
            "category":"Building & Trades",
            "subcategory":"Equipment Rental",
            "type":"Services"
        }
    ],
    "sg:phone":"+39 010 726 1006",
    "sg:postcode":"16010",
    "sg:province":"Genova",
    "sg:tags":[
        "rescue",
        "accessory"
    ],
    "sg:website":"www.canepaecampi.com",
    "wof:name":"Canepa & Campi Srl",
    "wof:placetype":"venue"
},
  "geometry": {"coordinates":[8.928761,44.476585],"type":"Point"}
}