{
  "type": "Feature",
  "properties": {
    "iso:country":"IT",
    "sg:address":"Strada Priv. 202 Belleteste 14/16 27043 Broni",
    "sg:city":"Broni",
    "sg:classifiers":[
        {
            "category":"Retail",
            "subcategory":"Auto Repair",
            "type":"Services"
        }
    ],
    "sg:phone":"+39 0385 245878",
    "sg:postcode":"27043",
    "sg:province":"Pavia",
    "sg:tags":[
        "machine",
        "bakery"
    ],
    "sg:website":"www.steno.it",
    "wof:name":"Steno Fratelli Nazzari Snc",
    "wof:placetype":"venue"
},
  "geometry": {"coordinates":[9.156563,45.185886],"type":"Point"}
}