{
  "type": "Feature",
  "properties": {
    "iso:country":"IT",
    "sg:address":"Via Svevo Italo 9 20143 Milano",
    "sg:city":"Milano",
    "sg:classifiers":[
        {
            "category":"Autos & Motor Vehicles",
            "subcategory":"Recreational Vehicle Sales",
            "type":"Retail Goods"
        }
    ],
    "sg:phone":"+39 02 813 6005",
    "sg:postcode":"20143",
    "sg:province":"Milano",
    "sg:tags":[
        "machine",
        "tool",
        "accessory"
    ],
    "wof:name":"Rapid Original Snc",
    "wof:placetype":"venue"
},
  "geometry": {"coordinates":[9.160414,45.44133],"type":"Point"}
}