{
  "type": "Feature",
  "properties": {
    "iso:country":"IT",
    "sg:address":"10094 Giaveno",
    "sg:city":"Giaveno",
    "sg:orig_category":"Servizi E Lavori Per Abbigliamento E Pelletterie. Arte Ed Artigianato Artistico. Shopping",
    "sg:phone":"+39 011 936 4044",
    "sg:postcode":"10094",
    "sg:province":"Torino",
    "wof:name":"Calza Di Cuoio",
    "wof:placetype":"venue"
},
  "geometry": {"coordinates":[7.352404,45.041912],"type":"Point"}
}