{
  "type": "Feature",
  "properties": {
    "iso:country":"IT",
    "sg:address":"16163 Genova",
    "sg:city":"Genova",
    "sg:orig_category":"Arredamenti Ed Architettura D'interni",
    "sg:phone":"+39 010 714145",
    "sg:postcode":"16163",
    "sg:province":"Genova",
    "wof:name":"Abac Sas",
    "wof:placetype":"venue"
},
  "geometry": {"coordinates":[8.916994,44.486153],"type":"Point"}
}