{
  "type": "Feature",
  "properties": {
    "addr:full":"13037 Serravalle Sesia Serravalle Sesia Vercelli 13037",
    "addr:postcode":"13037;13037",
    "iso:country":"IT",
    "sg:address":"13037 Serravalle Sesia",
    "sg:city":"Serravalle Sesia",
    "sg:orig_category":"Materiali Edili",
    "sg:phone":"+39 0163 459301",
    "sg:postcode":"13037",
    "sg:province":"Vercelli",
    "wof:name":"Lis Srl",
    "wof:placetype":"venue"
},
  "geometry": {"coordinates":[8.304489,45.673477],"type":"Point"}
}