{
  "type": "Feature",
  "properties": {
    "iso:country":"IT",
    "sg:address":"Via Bruno Buozzi 15 20090 Pieve Emanuele",
    "sg:city":"Pieve Emanuele",
    "sg:classifiers":[
        {
            "category":"Structure",
            "subcategory":"Office Building",
            "type":"Public Place"
        }
    ],
    "sg:phone":"+39 02 9072 4771",
    "sg:postcode":"20090",
    "sg:province":"Milano",
    "sg:tags":[
        "lubricating",
        "central",
        "system"
    ],
    "sg:website":"www.technosystemsbotti.com",
    "wof:name":"Technosystems Srl",
    "wof:placetype":"venue"
},
  "geometry": {"coordinates":[9.180287,45.37991],"type":"Point"}
}