{
  "type": "Feature",
  "properties": {
    "addr:full":"Viale Del Lavoro 11 36021 Ponte Di Barbarano Ponte di Barbarano Vicenza 36021",
    "addr:housenumber":"11",
    "addr:postcode":"36021;36021",
    "addr:street":"Viale Del Lavoro;Di Barbarano",
    "iso:country":"IT",
    "sg:address":"Viale Del Lavoro 11 36021 Ponte Di Barbarano",
    "sg:city":"Ponte di Barbarano",
    "sg:classifiers":[
        {
            "category":"Banks & Credit Unions",
            "subcategory":"Investment Brokerage",
            "type":"Services"
        }
    ],
    "sg:phone":"+39 0444 896939",
    "sg:postcode":"36021",
    "sg:province":"Vicenza",
    "sg:tags":[
        "shutter",
        "roller",
        "accessory"
    ],
    "sg:website":"www.mimetal.com",
    "wof:name":"Mi - Metal Srl",
    "wof:placetype":"venue"
},
  "geometry": {"coordinates":[11.575398,45.381321],"type":"Point"}
}