{
  "type": "Feature",
  "properties": {
    "iso:country":"IT",
    "sg:address":"33070 Brugnera",
    "sg:city":"Brugnera",
    "sg:orig_category":"Arredo Bagno Ed Idrosanitari",
    "sg:phone":"+39 0434 617111",
    "sg:postcode":"33070",
    "sg:province":"Pordenone",
    "sg:website":"http://www.copat.it",
    "wof:name":"Gruppo Copat - Marketing Center",
    "wof:placetype":"venue"
},
  "geometry": {"coordinates":[12.550886,45.909702],"type":"Point"}
}