{
  "type": "Feature",
  "properties": {
    "iso:country":"IT",
    "sg:address":"Via Toscana 105 21052 Busto Arsizio",
    "sg:city":"Busto Arsizio",
    "sg:classifiers":[
        {
            "category":"Communications",
            "subcategory":"Film & Video Production",
            "type":"Services"
        }
    ],
    "sg:phone":"+39 0331 340084",
    "sg:postcode":"21052",
    "sg:province":"Varese",
    "sg:tags":[
        "foil",
        "graphic"
    ],
    "wof:name":"Reprochim Srl",
    "wof:placetype":"venue"
},
  "geometry": {"coordinates":[8.860595,45.580734],"type":"Point"}
}