{
  "type": "Feature",
  "properties": {
    "addr:full":"18, Via Magnetti Don 10040 Leini' Torino 10040",
    "addr:postcode":"10040 leini;10040",
    "addr:street":"Via Magnetti Don",
    "iso:country":"IT",
    "sg:address":"18, Via Magnetti Don 10040 Leini'",
    "sg:classifiers":[
        {
            "category":"Shopping",
            "subcategory":"Stationery & Office Supplies",
            "type":"Retail Goods"
        }
    ],
    "sg:phone":"+39 011 997 3324",
    "sg:postcode":"10040",
    "sg:province":"Torino",
    "sg:tags":[
        "professional"
    ],
    "wof:name":"Sereno Hospital S.r.l.",
    "wof:placetype":"venue"
},
  "geometry": {"coordinates":[7.7177219391,45.1592216492],"type":"Point"}
}