{
  "type": "Feature",
  "properties": {
    "iso:country":"IT",
    "sg:address":"Via Monte Grappa 36063 Marostica",
    "sg:city":"Marostica",
    "sg:classifiers":[
        {
            "category":"Professional",
            "subcategory":"Computer Services",
            "type":"Services"
        }
    ],
    "sg:phone":"+39 39042475342",
    "sg:postcode":"36063",
    "sg:province":"Vicenza",
    "sg:tags":[
        "information",
        "technology"
    ],
    "wof:name":"Cuman Valentino & C. (s.a.s.)",
    "wof:placetype":"venue"
},
  "geometry": {"coordinates":[11.659869,45.74749],"type":"Point"}
}