{
  "type": "Feature",
  "properties": {
    "iso:country":"IT",
    "sg:address":"40124 Bologna",
    "sg:city":"Bologna",
    "sg:orig_category":"Servizi Per Aziende, Manifestazioni E Supporto Agli Scambi Commerciali",
    "sg:phone":"+39 335 305 651",
    "sg:postcode":"40124",
    "sg:province":"Bologna",
    "wof:name":"Ciampoli Investigazioni",
    "wof:placetype":"venue"
},
  "geometry": {"coordinates":[11.346962,44.491463],"type":"Point"}
}