{
  "type": "Feature",
  "properties": {
    "iso:country":"IT",
    "sg:address":"24010 Ponteranica",
    "sg:city":"Ponteranica",
    "sg:orig_category":"Macchine E Forniture Per Arredamento E Industria Del Legno. Colori, Vernici E Smalti",
    "sg:phone":"+39 035 573263",
    "sg:postcode":"24010",
    "sg:province":"Bergamo",
    "wof:name":"Max Color Due Di Locatelli C.e C. (s.a.s.)",
    "wof:placetype":"venue"
},
  "geometry": {"coordinates":[9.656702,45.724346],"type":"Point"}
}