{
  "type": "Feature",
  "properties": {
    "addr:full":"20122 Milano Milano Milano 20122",
    "addr:postcode":"20122;20122",
    "iso:country":"IT",
    "sg:address":"20122 Milano",
    "sg:city":"Milano",
    "sg:orig_category":"Studi E Consulenze Amministrative, Commerciali E Aziendali. Consulenze Tecniche, Amministrative E Perizie. Professionisti - Studi E Servizi Ed Associazioni Di Interesse Aziendale",
    "sg:phone":"+39 02 8942 1036",
    "sg:postcode":"20122",
    "sg:province":"Milano",
    "wof:name":"Di Noto Giuseppina Elvira",
    "wof:placetype":"venue"
},
  "geometry": {"coordinates":[9.184252,45.45311],"type":"Point"}
}