{
  "type": "Feature",
  "properties": {
    "iso:country":"IT",
    "sg:address":"18, Via Merano 20127 Milano",
    "sg:city":"Milano",
    "sg:classifiers":[
        {
            "category":"Shopping",
            "subcategory":"Stationery & Office Supplies",
            "type":"Retail Goods"
        }
    ],
    "sg:phone":"+39 390 228 3131",
    "sg:postcode":"20127",
    "sg:province":"Milano",
    "sg:tags":[
        "professional"
    ],
    "wof:name":"Ente Gestione Mostre Comufficio Smau",
    "wof:placetype":"venue"
},
  "geometry": {"coordinates":[9.2212467194,45.49766922],"type":"Point"}
}