{
  "type": "Feature",
  "properties": {
    "addr:full":"37068 Vigasio Vigasio Verona 37068",
    "addr:postcode":"37068;37068",
    "iso:country":"IT",
    "sg:address":"37068 Vigasio",
    "sg:city":"Vigasio",
    "sg:orig_category":"Prodotti Alimentari. Agricoltura, Orticoltura E Floricoltura",
    "sg:phone":"+39 045 736 3221",
    "sg:postcode":"37068",
    "sg:province":"Verona",
    "wof:name":"Riseria Gazzani",
    "wof:placetype":"venue"
},
  "geometry": {"coordinates":[10.9553756714,45.3229293823],"type":"Point"}
}