{
  "type": "Feature",
  "properties": {
    "addr:full":"77, Localita' San Bovo 12054 Cossano Belbo Cossano Belbo Cuneo 12054",
    "addr:postcode":"12054;12054",
    "addr:street":"Localita ' San Bovo",
    "iso:country":"IT",
    "sg:address":"77, Localita' San Bovo 12054 Cossano Belbo",
    "sg:city":"Cossano Belbo",
    "sg:classifiers":[
        {
            "category":"Manufacturing",
            "subcategory":"Food",
            "type":"Manufacturing & Wholesale Goods"
        }
    ],
    "sg:phone":"+39 39014188494",
    "sg:postcode":"12054",
    "sg:province":"Cuneo",
    "sg:tags":[
        "equipment",
        "processing",
        "-",
        "machinery"
    ],
    "wof:name":"Enolmeccanica Vallebelbo S.n.c.",
    "wof:placetype":"venue"
},
  "geometry": {"coordinates":[8.2045316696,44.6884231567],"type":"Point"}
}