{
  "type": "Feature",
  "properties": {
    "iso:country":"IT",
    "sg:address":"77/79, V. Della Molinara 24064 Grumello Del Monte",
    "sg:city":"Grumello del Monte",
    "sg:classifiers":[
        {
            "category":"Professional",
            "subcategory":"Engineering",
            "type":"Services"
        }
    ],
    "sg:phone":"+39 39035832962",
    "sg:postcode":"24064",
    "sg:province":"Bergamo",
    "sg:tags":[
        "machine",
        "-",
        "mechanical"
    ],
    "sg:website":"http://www.ffgi.it:ws_end: :mark:ws:http://www.paginegialle.it/ffgi",
    "wof:name":"Ff.gi. Srl",
    "wof:placetype":"venue"
},
  "geometry": {"coordinates":[9.8802,45.630253],"type":"Point"}
}