{
  "type": "Feature",
  "properties": {
    "addr:full":"27010 Cura Carpignano Cura Carpignano Pavia 27010",
    "addr:postcode":"27010;27010",
    "iso:country":"IT",
    "sg:address":"27010 Cura Carpignano",
    "sg:city":"Cura Carpignano",
    "sg:orig_category":"Macchine Utensili E Impianti",
    "sg:phone":"+39 0382 474301",
    "sg:postcode":"27010",
    "sg:province":"Pavia",
    "wof:name":"Delta (s.p.a.)",
    "wof:placetype":"venue"
},
  "geometry": {"coordinates":[9.220668,45.205441],"type":"Point"}
}