{
  "type": "Feature",
  "properties": {
    "iso:country":"IT",
    "sg:address":"49, Via Maremmana 50059 Vinci",
    "sg:city":"Vinci",
    "sg:classifiers":[
        {
            "category":"Manufacturing",
            "subcategory":"Textiles",
            "type":"Manufacturing & Wholesale Goods"
        }
    ],
    "sg:phone":"+39 0571 585854",
    "sg:postcode":"50059",
    "sg:province":"Firenze",
    "sg:tags":[
        "leather",
        "raw",
        "material",
        "-"
    ],
    "wof:name":"Italian Style Import-export Srl",
    "wof:placetype":"venue"
},
  "geometry": {"coordinates":[10.873394,43.791897],"type":"Point"}
}