{
  "type": "Feature",
  "properties": {
    "iso:country":"IT",
    "sg:address":"03036 Isola Del Liri",
    "sg:city":"Isola del Liri",
    "sg:orig_category":"Materiali E Componenti Elettrotecnici",
    "sg:phone":"+39 0776 803090",
    "sg:postcode":"03036",
    "sg:province":"Frosinone",
    "wof:name":"Elettroliri Srl",
    "wof:placetype":"venue"
},
  "geometry": {"coordinates":[13.560805,41.675129],"type":"Point"}
}