{
  "type": "Feature",
  "properties": {
    "addr:full":"00156 Roma Roma Roma 00156",
    "addr:postcode":"00156;00156",
    "iso:country":"IT",
    "sg:address":"00156 Roma",
    "sg:city":"Roma",
    "sg:orig_category":"Servizi Editoriali. Servizi Ausiliari Per Il Trasporto",
    "sg:phone":"+39 06 407 2432",
    "sg:postcode":"00156",
    "sg:province":"Roma",
    "wof:name":"Croce Claudia Maria",
    "wof:placetype":"venue"
},
  "geometry": {"coordinates":[12.569384,41.928856],"type":"Point"}
}