{
  "type": "Feature",
  "properties": {
    "iso:country":"IT",
    "sg:address":"2 Piazza Cavour Camillo Benso, 60121 Ancona",
    "sg:city":"Ancona",
    "sg:classifiers":[
        {
            "category":"Banks & Credit Unions",
            "subcategory":"Financial Services",
            "type":"Services"
        }
    ],
    "sg:phone":"+39 390 715 4961",
    "sg:postcode":"60121",
    "sg:province":"Ancona",
    "sg:tags":[
        "banking",
        "finance",
        "insurance"
    ],
    "wof:name":"Aon Nikols (srl)",
    "wof:placetype":"venue"
},
  "geometry": {"coordinates":[13.5187568665,43.6158561707],"type":"Point"}
}