{
  "type": "Feature",
  "properties": {
    "iso:country":"IT",
    "sg:address":"00181 Roma",
    "sg:city":"Roma",
    "sg:orig_category":"Arredamenti E Mobili Professionali. Arredi Ed Attrezzature Per Uffici",
    "sg:phone":"+39 06 780 4424",
    "sg:postcode":"00181",
    "sg:province":"Roma",
    "wof:name":"U.spalmach E C.snc",
    "wof:placetype":"venue"
},
  "geometry": {"coordinates":[12.528516,41.877499],"type":"Point"}
}