{
  "type": "Feature",
  "properties": {
    "iso:country":"IT",
    "sg:address":"00054 Fiumicino",
    "sg:city":"Fiumicino",
    "sg:orig_category":"Servizi Al Turismo. Trasporto Pubblico E Privato",
    "sg:phone":"+39 06 6502 4042",
    "sg:postcode":"00054",
    "sg:province":"Roma",
    "wof:name":"Ministero Dei Trasporti E Della Navigazione",
    "wof:placetype":"venue"
},
  "geometry": {"coordinates":[12.229013,41.77071],"type":"Point"}
}