{
  "type": "Feature",
  "properties": {
    "iso:country":"IT",
    "sg:address":"164, Via Emilia Parmense 29100 Piacenza",
    "sg:city":"Piacenza",
    "sg:classifiers":[
        {
            "category":"Professional",
            "subcategory":"Engineering",
            "type":"Services"
        }
    ],
    "sg:phone":"+39 0523 549611",
    "sg:postcode":"29100",
    "sg:province":"Piacenza",
    "sg:tags":[
        "machine",
        "-",
        "mechanical"
    ],
    "wof:name":"Jobs S.p.a.",
    "wof:placetype":"venue"
},
  "geometry": {"coordinates":[9.743766,45.025452],"type":"Point"}
}