{
  "type": "Feature",
  "properties": {
    "addr:full":"Via Foglia 2 61026 Lunano Lunano Pesaro E Urbino 61026",
    "addr:housenumber":"2",
    "addr:postcode":"61026;61026",
    "addr:street":"Via Foglia",
    "iso:country":"IT",
    "sg:address":"Via Foglia 2 61026 Lunano",
    "sg:city":"Lunano",
    "sg:orig_category":"Pump Units",
    "sg:phone":"+39 0722 700315",
    "sg:postcode":"61026",
    "sg:province":"Pesaro E Urbino",
    "wof:name":"Ferbo Srl",
    "wof:placetype":"venue"
},
  "geometry": {"coordinates":[12.445476532,43.7355232239],"type":"Point"}
}