{
  "type": "Feature",
  "properties": {
    "iso:country":"IT",
    "sg:address":"37, Via Marconi Guglielmo 60125 Ancona",
    "sg:city":"Ancona",
    "sg:classifiers":[
        {
            "category":"Marine",
            "type":"Transportation"
        }
    ],
    "sg:phone":"+39 39071206351",
    "sg:postcode":"60125",
    "sg:province":"Ancona",
    "sg:tags":[
        "transport",
        "sea"
    ],
    "wof:name":"Selenav S.r.l.",
    "wof:placetype":"venue"
},
  "geometry": {"coordinates":[13.500196,43.607975],"type":"Point"}
}