{
  "type": "Feature",
  "properties": {
    "iso:country":"IT",
    "sg:address":"24128 Bergamo",
    "sg:city":"Bergamo",
    "sg:orig_category":"Servizi Editoriali. Shopping",
    "sg:phone":"+39 035 233353",
    "sg:postcode":"24128",
    "sg:province":"Bergamo",
    "wof:name":"Villa Barcella Paola",
    "wof:placetype":"venue"
},
  "geometry": {"coordinates":[9.660286,45.699154],"type":"Point"}
}