{
  "type": "Feature",
  "properties": {
    "iso:country":"IT",
    "sg:address":"89129 Reggio Calabria",
    "sg:orig_category":"Valvole E Apparecchiature Di Misura",
    "sg:phone":"+39 0965 51483",
    "sg:province":"RC",
    "wof:name":"Ediltubi Sas",
    "wof:placetype":"venue"
},
  "geometry": {"coordinates":[15.63832,38.082397],"type":"Point"}
}