{
  "type": "Feature",
  "properties": {
    "iso:country":"IT",
    "sg:address":"98123 Messina",
    "sg:city":"Messina",
    "sg:orig_category":"Forniture Per Agricoltura E Zootecnia. Prodotti Chimici Secondari. Macchine E Forniture Per Ecologia E Smaltimento Rifiuti",
    "sg:phone":"+39 090 293 5933",
    "sg:postcode":"98123",
    "sg:province":"Messina",
    "wof:name":"Monari Mario",
    "wof:placetype":"venue"
},
  "geometry": {"coordinates":[15.5567054749,38.1821746826],"type":"Point"}
}