{
  "type": "Feature",
  "properties": {
    "addr:full":"20040 Busnago Busnago Milano 20040",
    "addr:postcode":"20040;20040",
    "iso:country":"IT",
    "sg:address":"20040 Busnago",
    "sg:city":"Busnago",
    "sg:orig_category":"Imballaggi Metallici",
    "sg:phone":"+39 039 695 6071",
    "sg:postcode":"20040",
    "sg:province":"Milano",
    "wof:name":"Nuova Simet Srl",
    "wof:placetype":"venue"
},
  "geometry": {"coordinates":[9.462466,45.613186],"type":"Point"}
}