{
  "type": "Feature",
  "properties": {
    "addr:full":"86039 Termoli Termoli Campobasso 86039",
    "addr:postcode":"86039;86039",
    "iso:country":"IT",
    "sg:address":"86039 Termoli",
    "sg:city":"Termoli",
    "sg:orig_category":"Termotecnica E Riscaldamento, Apparecchiature E Servizi",
    "sg:phone":"+39 0875 751788",
    "sg:postcode":"86039",
    "sg:province":"Campobasso",
    "wof:name":"Fratelli Pacini Snc",
    "wof:placetype":"venue"
},
  "geometry": {"coordinates":[15.031981,41.958469],"type":"Point"}
}