{
  "type": "Feature",
  "properties": {
    "iso:country":"IT",
    "sg:address":"50142 Firenze",
    "sg:city":"Firenze",
    "sg:orig_category":"Servizi Vari Di Interesse Pubblico",
    "sg:phone":"+39 055 701680",
    "sg:postcode":"50142",
    "sg:province":"Firenze",
    "wof:name":"Bacherini Luciano",
    "wof:placetype":"venue"
},
  "geometry": {"coordinates":[11.227297,43.773087],"type":"Point"}
}