{
  "type": "Feature",
  "properties": {
    "iso:country":"IT",
    "sg:address":"Via Grota Del Diau Zot 34074 Monfalcone",
    "sg:city":"Monfalcone",
    "sg:classifiers":[
        {
            "category":"Manufacturing",
            "subcategory":"Paper Products",
            "type":"Manufacturing & Wholesale Goods"
        }
    ],
    "sg:phone":"+39 0481 791597",
    "sg:postcode":"34074",
    "sg:province":"Gorizia",
    "sg:tags":[
        "cardboard"
    ],
    "wof:name":"Cartiera Di Monfalcone S.p.a.",
    "wof:placetype":"venue"
},
  "geometry": {"coordinates":[13.5746259689,45.7909393311],"type":"Point"}
}