{
  "type": "Feature",
  "properties": {
    "addr:full":"2, Via Rosa Salvatore 21052 Busto Arsizio Busto Arsizio Varese 21052",
    "addr:postcode":"21052;21052",
    "addr:street":"Via Rosa Salvatore",
    "iso:country":"IT",
    "sg:address":"2, Via Rosa Salvatore 21052 Busto Arsizio",
    "sg:city":"Busto Arsizio",
    "sg:classifiers":[
        {
            "category":"Shopping",
            "subcategory":"Clothing, Apparel, & Fashions",
            "type":"Retail Goods"
        }
    ],
    "sg:phone":"+39 0331 627066",
    "sg:postcode":"21052",
    "sg:province":"Varese",
    "sg:tags":[
        "clothes"
    ],
    "wof:name":"Speroni Maglierie",
    "wof:placetype":"venue"
},
  "geometry": {"coordinates":[8.8263845444,45.8176040649],"type":"Point"}
}