{
  "type": "Feature",
  "properties": {
    "iso:country":"IT",
    "sg:address":"22/24, Via Golgi Camillo 25064 Gussago",
    "sg:city":"Gussago",
    "sg:classifiers":[
        {
            "category":"Food & Beverages",
            "subcategory":"Groceries & Convenience Stores",
            "type":"Retail Goods"
        }
    ],
    "sg:phone":"+39 030 373 1781",
    "sg:postcode":"25064",
    "sg:province":"Brescia",
    "sg:tags":[
        "product",
        "related"
    ],
    "wof:name":"Confezionamento Commerciale Lombardo (s.r.l.)",
    "wof:placetype":"venue"
},
  "geometry": {"coordinates":[10.1609897614,45.5574226379],"type":"Point"}
}