{
  "type": "Feature",
  "properties": {
    "iso:country":"IT",
    "sg:address":"31026 Sarmede",
    "sg:city":"Sarmede",
    "sg:orig_category":"Materiali Edili",
    "sg:phone":"+39 0438 582392",
    "sg:postcode":"31026",
    "sg:province":"Treviso",
    "wof:name":"Dal Cin Giulio",
    "wof:placetype":"venue"
},
  "geometry": {"coordinates":[12.394106,45.975563],"type":"Point"}
}