{
  "type": "Feature",
  "properties": {
    "addr:full":"Contrada San Cusumano 96010 Priolo Gargallo Priolo Gargallo Siracusa 96010",
    "addr:postcode":"96010;96010",
    "addr:street":"Contrada San Cusumano",
    "iso:country":"IT",
    "sg:address":"Contrada San Cusumano 96010 Priolo Gargallo",
    "sg:city":"Priolo Gargallo",
    "sg:classifiers":[
        {
            "category":"Wholesale",
            "subcategory":"Medical Equipment & Supplies",
            "type":"Manufacturing & Wholesale Goods"
        }
    ],
    "sg:phone":"+39 0931 771100",
    "sg:postcode":"96010",
    "sg:province":"Siracusa",
    "sg:tags":[
        "-",
        "health",
        "instrument"
    ],
    "wof:name":"High Tecnology System",
    "wof:placetype":"venue"
},
  "geometry": {"coordinates":[15.28444,37.066483],"type":"Point"}
}