{
  "type": "Feature",
  "properties": {
    "addr:full":"67/69, Viale Campania 20093 Cologno Monzese Cologno Monzese Milano 20093",
    "addr:housenumber":"67 / 69",
    "addr:postcode":"20093;20093",
    "addr:street":"Viale Campania",
    "iso:country":"IT",
    "sg:address":"67/69, Viale Campania 20093 Cologno Monzese",
    "sg:city":"Cologno Monzese",
    "sg:classifiers":[
        {
            "category":"Shopping",
            "type":"Retail Goods"
        }
    ],
    "sg:phone":"+39 39022549917",
    "sg:postcode":"20093",
    "sg:province":"Milano",
    "sg:tags":[
        "finished",
        "-",
        "metallic"
    ],
    "wof:name":"Micam S.a.s. Di Agostino Arduini & C.",
    "wof:placetype":"venue"
},
  "geometry": {"coordinates":[9.2821445465,45.5417366028],"type":"Point"}
}