{
  "type": "Feature",
  "properties": {
    "iso:country":"IT",
    "sg:address":"130, Via Flaminia 47900 Rimini",
    "sg:city":"Rimini",
    "sg:classifiers":[
        {
            "category":"Shopping",
            "subcategory":"Jewelry",
            "type":"Retail Goods"
        }
    ],
    "sg:phone":"+39 0541 382525",
    "sg:postcode":"47900",
    "sg:province":"Rimini",
    "sg:tags":[
        "jewellery"
    ],
    "wof:name":"Riva S.n.c. Di Mori R. E Riva C. E A.",
    "wof:placetype":"venue"
},
  "geometry": {"coordinates":[12.587249,44.043777],"type":"Point"}
}