{
  "type": "Feature",
  "properties": {
    "addr:full":"20020 Arese Arese Milano 20020",
    "addr:postcode":"20020;20020",
    "iso:country":"IT",
    "sg:address":"20020 Arese",
    "sg:city":"Arese",
    "sg:orig_category":"Prodotti Alimentari",
    "sg:phone":"+39 02 938 1598",
    "sg:postcode":"20020",
    "sg:province":"Milano",
    "wof:name":"Fiort Neorossi S.a.s.",
    "wof:placetype":"venue"
},
  "geometry": {"coordinates":[9.0873289108,45.5360679626],"type":"Point"}
}