{
  "type": "Feature",
  "properties": {
    "iso:country":"IT",
    "sg:address":"20144 Milano",
    "sg:city":"Milano",
    "sg:orig_category":"Gioielleria, Oreficeria E Argenteria. Shopping",
    "sg:phone":"+39 02 3361 1616",
    "sg:postcode":"20144",
    "sg:province":"Milano",
    "wof:name":"Argenti Unione Srl",
    "wof:placetype":"venue"
},
  "geometry": {"coordinates":[9.164159,45.460602],"type":"Point"}
}