{
  "type": "Feature",
  "properties": {
    "iso:country":"IT",
    "sg:address":"10098 Rivoli",
    "sg:city":"Rivoli",
    "sg:orig_category":"Termotecnica E Riscaldamento, Apparecchiature E Servizi",
    "sg:phone":"+39 011 957 4253",
    "sg:postcode":"10098",
    "sg:province":"Torino",
    "wof:name":"Staget Clima (s.n.c.)",
    "wof:placetype":"venue"
},
  "geometry": {"coordinates":[7.543903,45.068867],"type":"Point"}
}