{
  "type": "Feature",
  "properties": {
    "iso:country":"IT",
    "sg:address":"00147 Roma",
    "sg:city":"Roma",
    "sg:orig_category":"Cartotecnica E Servizi. Composizione, Stampa E Confezione. Forniture E Prodotti Informatici. Forniture Per Congressi, Fiere E Manifestazioni",
    "sg:phone":"+39 06 518 0751",
    "sg:postcode":"00147",
    "sg:province":"Roma",
    "sg:website":"http://www.haroma.it",
    "wof:name":"Hugnot Automation Roma Srl",
    "wof:placetype":"venue"
},
  "geometry": {"coordinates":[12.505805,41.855106],"type":"Point"}
}