{
  "type": "Feature",
  "properties": {
    "addr:full":"15048 Valenza Valenza Alessandria 15048",
    "addr:postcode":"15048;15048",
    "iso:country":"IT",
    "sg:address":"15048 Valenza",
    "sg:city":"Valenza",
    "sg:orig_category":"Servizi Per Lo Sport E Il Tempo Libero. Servizi Al Turismo. Acqua, Luce, Gas E Societa' Di Esercizio Pubblico",
    "sg:phone":"+39 0131 927555",
    "sg:postcode":"15048",
    "sg:province":"Alessandria",
    "wof:name":"Parco Fluviale Del Po E Dell'orba",
    "wof:placetype":"venue"
},
  "geometry": {"coordinates":[8.636287,45.009258],"type":"Point"}
}