{
  "type": "Feature",
  "properties": {
    "iso:country":"IT",
    "sg:address":"80014 Giugliano In Campania",
    "sg:city":"Giugliano in Campania",
    "sg:orig_category":"Macchine, Impianti Ed Attrezzature Industria Chimica. Macchine E Impianti Per Attivita' Commerciali Ed Artigianali",
    "sg:phone":"+39 081 330 5892",
    "sg:postcode":"80014",
    "sg:province":"Napoli",
    "wof:name":"Ciccarelli Carmela",
    "wof:placetype":"venue"
},
  "geometry": {"coordinates":[14.191822,40.928879],"type":"Point"}
}