{
  "type": "Feature",
  "properties": {
    "addr:full":"46044 Goito Goito Mantova 46044",
    "addr:postcode":"46044;46044",
    "iso:country":"IT",
    "sg:address":"46044 Goito",
    "sg:city":"Goito",
    "sg:orig_category":"Macchine, Impianti Ed Attrezzature Per Abbigliamento E Pelletterie",
    "sg:phone":"+39 0376 604403",
    "sg:postcode":"46044",
    "sg:province":"Mantova",
    "wof:name":"Bicchierai S.r.l.",
    "wof:placetype":"venue"
},
  "geometry": {"coordinates":[10.776244,45.149345],"type":"Point"}
}