{
  "type": "Feature",
  "properties": {
    "addr:full":"95, V. R. Margherita 72024 Oria Oria Brindisi 72024",
    "addr:housenumber":"95",
    "addr:postcode":"72024;72024",
    "addr:street":"R.",
    "iso:country":"IT",
    "sg:address":"95, V. R. Margherita 72024 Oria",
    "sg:city":"Oria",
    "sg:classifiers":[
        {
            "category":"Food & Beverages",
            "subcategory":"Groceries & Convenience Stores",
            "type":"Retail Goods"
        }
    ],
    "sg:phone":"+39 0831 817102",
    "sg:postcode":"72024",
    "sg:province":"Brindisi",
    "sg:tags":[
        "product",
        "related"
    ],
    "sg:website":"http://www.detommaso.com:ws_end: :mark:ws:http://www.paginegialle.it/detommasoconserve",
    "wof:name":"De Tommaso Specialita' Pugliesi",
    "wof:placetype":"venue"
},
  "geometry": {"coordinates":[17.7117080688,40.5429267883],"type":"Point"}
}