{
  "type": "Feature",
  "properties": {
    "addr:full":"00019 Tivoli Tivoli Roma 00019",
    "addr:postcode":"00019;roma 00019",
    "iso:country":"IT",
    "sg:address":"00019 Tivoli",
    "sg:city":"Tivoli",
    "sg:orig_category":"Cine-foto-ottica. Articoli Medico-sanitari Ed Ortopedici",
    "sg:phone":"+39 0774 333200",
    "sg:postcode":"00019",
    "sg:province":"Roma",
    "wof:name":"De Paolis & Pascucci Ottici",
    "wof:placetype":"venue"
},
  "geometry": {"coordinates":[12.799146,41.959747],"type":"Point"}
}