{
  "type": "Feature",
  "properties": {
    "addr:full":"47039 Savignano Sul Rubicone Savignano sul Rubicone Forl\u00ec-Cesena 47039",
    "addr:postcode":"47039;47039",
    "iso:country":"IT",
    "sg:address":"47039 Savignano Sul Rubicone",
    "sg:city":"Savignano sul Rubicone",
    "sg:orig_category":"Legno E Semilavorati. Materiali Edili",
    "sg:phone":"+39 0541 945102",
    "sg:postcode":"47039",
    "sg:province":"Forl\u00ec-Cesena",
    "wof:name":"Legnami E Materiali Edili Srl",
    "wof:placetype":"venue"
},
  "geometry": {"coordinates":[12.403609,44.088165],"type":"Point"}
}