{
  "type": "Feature",
  "properties": {
    "addr:full":"Piazza Della Liberta 17; Bassano; 36061 Vicenza 36061",
    "addr:housenumber":"17",
    "addr:postcode":"36061;36061",
    "addr:street":"Piazza Della Liberta;Bassano",
    "iso:country":"IT",
    "sg:address":"Piazza Della Liberta 17; Bassano; 36061",
    "sg:classifiers":[
        {
            "category":"Banks & Credit Unions",
            "subcategory":"Bank",
            "type":"Services"
        }
    ],
    "sg:phone":"+39 0424 524291",
    "sg:postcode":"36061",
    "sg:province":"Vicenza",
    "wof:name":"Banco Ambrosiano Veneto Spa",
    "wof:placetype":"venue"
},
  "geometry": {"coordinates":[11.733456,45.766506],"type":"Point"}
}