{
  "type": "Feature",
  "properties": {
    "iso:country":"IT",
    "sg:address":"30022 Ceggia",
    "sg:city":"Ceggia",
    "sg:orig_category":"Stampaggio Metalli A Freddo",
    "sg:phone":"+39 0421 329623",
    "sg:postcode":"30022",
    "sg:province":"Venezia",
    "sg:website":"http://www.ucisap.it/soci/database/venetastampidifurlanvittoriocsas.html",
    "wof:name":"Veneta Stampi Sas Di Furlan Vittorio & C.",
    "wof:placetype":"venue"
},
  "geometry": {"coordinates":[12.665827,45.685997],"type":"Point"}
}