{
  "type": "Feature",
  "properties": {
    "addr:full":"74015 Martina Franca Martina Franca Taranto 74015",
    "addr:housenumber":"74015",
    "addr:postcode":"74015",
    "iso:country":"IT",
    "sg:address":"74015 Martina Franca",
    "sg:city":"Martina Franca",
    "sg:orig_category":"Servizi E Lavori Per Abbigliamento E Pelletterie. Scuole E Servizi Scolastici. Ricerca, Selezione E Formazione Del Personale",
    "sg:phone":"+39 080 480 1812",
    "sg:postcode":"74015",
    "sg:province":"Taranto",
    "wof:name":"Panaro A. Scuola Stilisti Moda",
    "wof:placetype":"venue"
},
  "geometry": {"coordinates":[17.3342094421,40.704334259],"type":"Point"}
}