{
  "type": "Feature",
  "properties": {
    "iso:country":"IT",
    "sg:address":"21010 Ferno",
    "sg:city":"Ferno",
    "sg:orig_category":"Porte",
    "sg:phone":"+39 0331 240236",
    "sg:postcode":"21010",
    "sg:province":"Varese",
    "wof:name":"Blindart Snc",
    "wof:placetype":"venue"
},
  "geometry": {"coordinates":[8.7556295395,45.6172027588],"type":"Point"}
}