{
  "type": "Feature",
  "properties": {
    "iso:country":"IT",
    "sg:address":"20027 Rescaldina",
    "sg:city":"Rescaldina",
    "sg:orig_category":"Prodotti Chimici Di Base. Forniture Per Attivita' Industriali",
    "sg:phone":"+39 0331 466908",
    "sg:postcode":"20027",
    "sg:province":"Milano",
    "wof:name":"Gi.di.s Sas",
    "wof:placetype":"venue"
},
  "geometry": {"coordinates":[8.9579963684,45.614364624],"type":"Point"}
}