{
  "type": "Feature",
  "properties": {
    "addr:full":"53, Via Vigone 10061 Cavour Cavour Torino 10061",
    "addr:postcode":"10061;10061",
    "addr:street":"Via Vigone",
    "iso:country":"IT",
    "sg:address":"53, Via Vigone 10061 Cavour",
    "sg:city":"Cavour",
    "sg:classifiers":[
        {
            "category":"Professional",
            "subcategory":"Engineering",
            "type":"Services"
        }
    ],
    "sg:phone":"+39 0121 600511",
    "sg:postcode":"10061",
    "sg:province":"Torino",
    "sg:tags":[
        "machine",
        "-",
        "mechanical"
    ],
    "wof:name":"La Stampotecnica Piemontese Srl",
    "wof:placetype":"venue"
},
  "geometry": {"coordinates":[7.377857,44.787861],"type":"Point"}
}