{
  "type": "Feature",
  "properties": {
    "iso:country":"IT",
    "sg:address":"10, Via Ca' Rossa 35010 Limena",
    "sg:city":"Limena",
    "sg:classifiers":[
        {
            "category":"Manufacturing",
            "subcategory":"Paper Products",
            "type":"Manufacturing & Wholesale Goods"
        }
    ],
    "sg:phone":"+39 049 907 6409",
    "sg:postcode":"35010",
    "sg:province":"Padova",
    "sg:tags":[
        "cardboard"
    ],
    "wof:name":"Dermit Srl",
    "wof:placetype":"venue"
},
  "geometry": {"coordinates":[11.8303756714,45.4620704651],"type":"Point"}
}