{
  "type": "Feature",
  "properties": {
    "addr:full":"46100 Mantova Mantova Mantova 46100",
    "addr:postcode":"46100;46100",
    "iso:country":"IT",
    "sg:address":"46100 Mantova",
    "sg:city":"Mantova",
    "sg:classifiers":[
        {
            "category":"Banks & Credit Unions",
            "subcategory":"Investment Brokerage",
            "type":"Services"
        }
    ],
    "sg:phone":"+39 0376 223636",
    "sg:postcode":"46100",
    "sg:province":"Mantova",
    "sg:tags":[
        "vehicles",
        "auxiliary",
        "motor"
    ],
    "wof:name":"Solci Srl",
    "wof:placetype":"venue"
},
  "geometry": {"coordinates":[10.7912254333,45.1554679871],"type":"Point"}
}