{
  "type": "Feature",
  "properties": {
    "iso:country":"IT",
    "sg:address":"7, Via Amburgo 24040 Zingonia",
    "sg:city":"Zingonia",
    "sg:classifiers":[
        {
            "category":"Professional",
            "subcategory":"Engineering",
            "type":"Services"
        }
    ],
    "sg:phone":"+39 39035884390",
    "sg:postcode":"24040",
    "sg:province":"Bergamo",
    "sg:tags":[
        "machine",
        "-",
        "mechanical"
    ],
    "wof:name":"Ci.vi.elle (s.n.c.)",
    "wof:placetype":"venue"
},
  "geometry": {"coordinates":[9.618655,45.593056],"type":"Point"}
}