{
  "type": "Feature",
  "properties": {
    "addr:full":"00047 Santa Maria Delle Mole Roma 00047",
    "addr:postcode":"00047;00047",
    "addr:street":"Delle Mole",
    "iso:country":"IT",
    "sg:address":"00047 Santa Maria Delle Mole",
    "sg:orig_category":"Prodotti Alimentari",
    "sg:phone":"+39 06 930 9602",
    "sg:postcode":"00047",
    "sg:province":"Roma",
    "wof:name":"Nesci Francesca",
    "wof:placetype":"venue"
},
  "geometry": {"coordinates":[12.6028966904,41.7709846497],"type":"Point"}
}