{
  "type": "Feature",
  "properties": {
    "addr:full":"36, Via Meucci Antonio 37036 San Martino Buon Albergo San Martino Buon Albergo Verona 37036",
    "addr:postcode":"37036;buon albergo;37036",
    "addr:street":"Via Meucci Antonio",
    "iso:country":"IT",
    "sg:address":"36, Via Meucci Antonio 37036 San Martino Buon Albergo",
    "sg:city":"San Martino Buon Albergo",
    "sg:classifiers":[
        {
            "category":"Shopping",
            "subcategory":"Stationery & Office Supplies",
            "type":"Retail Goods"
        }
    ],
    "sg:phone":"+39 045 878 1211",
    "sg:postcode":"37036",
    "sg:province":"Verona",
    "sg:tags":[
        "professional"
    ],
    "wof:name":"Bombieri S.r.l.",
    "wof:placetype":"venue"
},
  "geometry": {"coordinates":[11.1090326309,45.4202842712],"type":"Point"}
}