{
  "type": "Feature",
  "properties": {
    "iso:country":"IT",
    "sg:address":"Via Della Scola 64 36100 Vicenza",
    "sg:city":"Vicenza",
    "sg:classifiers":[
        {
            "category":"Shopping",
            "subcategory":"Jewelry",
            "type":"Retail Goods"
        }
    ],
    "sg:phone":"+39 0444 500661",
    "sg:postcode":"36100",
    "sg:province":"Vicenza",
    "sg:tags":[
        "watch"
    ],
    "sg:website":"www.goldenterprise.com",
    "wof:name":"Gold Enterprise S.r.l.",
    "wof:placetype":"venue"
},
  "geometry": {"coordinates":[11.526389,45.575279],"type":"Point"}
}