{
  "type": "Feature",
  "properties": {
    "addr:full":"Sda Statale 300 19500 90047 Partinico Partinico Palermo 90047",
    "addr:housenumber":"300",
    "addr:postcode":"19500 90047;90047",
    "iso:country":"IT",
    "sg:address":"Sda Statale 300 19500 90047 Partinico",
    "sg:city":"Partinico",
    "sg:classifiers":[
        {
            "category":"Home & Garden",
            "subcategory":"Building Materials",
            "type":"Retail Goods"
        }
    ],
    "sg:phone":"+39 091 878 9036",
    "sg:postcode":"90047",
    "sg:province":"Palermo",
    "sg:tags":[
        "slab",
        "marble"
    ],
    "wof:name":"Settipani Marmi Srl",
    "wof:placetype":"venue"
},
  "geometry": {"coordinates":[13.361376,38.11562],"type":"Point"}
}