{
  "type": "Feature",
  "properties": {
    "iso:country":"IT",
    "sg:address":"5423, Via Melona 47023 Cesena",
    "sg:city":"Cesena",
    "sg:classifiers":[
        {
            "category":"Banks & Credit Unions",
            "subcategory":"Investment Brokerage",
            "type":"Services"
        }
    ],
    "sg:phone":"+39 0547 324170",
    "sg:postcode":"47023",
    "sg:province":"Forl\u00ec-Cesena",
    "sg:tags":[
        "-",
        "transport",
        "related"
    ],
    "wof:name":"Demm Srl",
    "wof:placetype":"venue"
},
  "geometry": {"coordinates":[12.309543,44.189754],"type":"Point"}
}