{
  "type": "Feature",
  "properties": {
    "iso:country":"IT",
    "sg:address":"17019 Varazze",
    "sg:city":"Varazze",
    "sg:orig_category":"Acque Minerali E Bevande, Naturali E Gassate - Commercio",
    "sg:phone":"+39 019 934661",
    "sg:postcode":"17019",
    "sg:province":"Savona",
    "wof:name":"Ditta Schiappapietra",
    "wof:placetype":"venue"
},
  "geometry": {"coordinates":[8.561114,44.389042],"type":"Point"}
}