{
  "type": "Feature",
  "properties": {
    "iso:country":"IT",
    "sg:address":"39047 S. Cristina Valgardena",
    "sg:classifiers":[
        {
            "category":"Professional",
            "subcategory":"Art Services",
            "type":"Services"
        }
    ],
    "sg:phone":"+39 0471 793468",
    "sg:postcode":"39047",
    "sg:province":"Bolzano/Bozen",
    "sg:tags":[
        "craft",
        "artistic"
    ],
    "sg:website":"http://www.karldemetz.com",
    "wof:name":"Demetz Karl & C. Snc",
    "wof:placetype":"venue"
},
  "geometry": {"coordinates":[11.358005,46.496716],"type":"Point"}
}