{
  "type": "Feature",
  "properties": {
    "addr:full":"Via Sotto I Boschi Di Saruggia 22031 Albavilla Albavilla Como 22031",
    "addr:postcode":"22031;22031",
    "addr:street":"Via Sotto I",
    "iso:country":"IT",
    "sg:address":"Via Sotto I Boschi Di Saruggia 22031 Albavilla",
    "sg:city":"Albavilla",
    "sg:classifiers":[
        {
            "category":"Manufacturing",
            "subcategory":"Paper Products",
            "type":"Manufacturing & Wholesale Goods"
        }
    ],
    "sg:phone":"+39 39031627492",
    "sg:postcode":"22031",
    "sg:province":"Como",
    "sg:tags":[
        "cardboard"
    ],
    "wof:name":"Arti Grafiche Villalba (s.r.l.)",
    "wof:placetype":"venue"
},
  "geometry": {"coordinates":[9.1814088821,45.7874145508],"type":"Point"}
}