{
  "type": "Feature",
  "properties": {
    "iso:country":"IT",
    "sg:address":"142, Via Del Casone 51039 Quarrata",
    "sg:city":"Quarrata",
    "sg:classifiers":[
        {
            "category":"Shopping",
            "subcategory":"Crafts & Fabrics",
            "type":"Retail Goods"
        }
    ],
    "sg:phone":"+39 0573 738630",
    "sg:postcode":"51039",
    "sg:province":"Pistoia",
    "wof:name":"Filatura Bonfil S.r.l.",
    "wof:placetype":"venue"
},
  "geometry": {"coordinates":[10.9769687653,43.8666152954],"type":"Point"}
}