{
  "type": "Feature",
  "properties": {
    "addr:full":"543/c, Via Cesenatico 47042 Cesenatico Cesenatico Forl\u00ec-Cesena 47042",
    "addr:housenumber":"543 / c",
    "addr:postcode":"47042;47042",
    "addr:street":"Via Cesenatico",
    "iso:country":"IT",
    "sg:address":"543/c, Via Cesenatico 47042 Cesenatico",
    "sg:city":"Cesenatico",
    "sg:classifiers":[
        {
            "category":"Food & Beverages",
            "subcategory":"Groceries & Convenience Stores",
            "type":"Retail Goods"
        }
    ],
    "sg:phone":"+39 0547 310075",
    "sg:postcode":"47042",
    "sg:province":"Forl\u00ec-Cesena",
    "sg:tags":[
        "product",
        "related"
    ],
    "wof:name":"Barducci",
    "wof:placetype":"venue"
},
  "geometry": {"coordinates":[11.9804611206,43.9947662354],"type":"Point"}
}