{
  "type": "Feature",
  "properties": {
    "iso:country":"IT",
    "sg:address":"20090 Rodano",
    "sg:city":"Rodano",
    "sg:orig_category":"Impiantistica E Prodotti Tecnologici Per Edilizia. Forniture Industriali Per Prevenzione, Controllo E Sicurezza",
    "sg:phone":"+39 02 950 0171",
    "sg:postcode":"20090",
    "sg:province":"Milano",
    "sg:website":"http://www.carver.it",
    "wof:name":"Carver Srl",
    "wof:placetype":"venue"
},
  "geometry": {"coordinates":[9.334034,45.472107],"type":"Point"}
}