{
  "type": "Feature",
  "properties": {
    "addr:full":"180, Via Bonicalza Albino 21012 Cassano Magnago Cassano Magnago Varese 21012",
    "addr:housenumber":"180",
    "addr:postcode":"21012;21012",
    "addr:street":"Via Bonicalza Albino",
    "iso:country":"IT",
    "sg:address":"180, Via Bonicalza Albino 21012 Cassano Magnago",
    "sg:city":"Cassano Magnago",
    "sg:classifiers":[
        {
            "category":"Shopping",
            "subcategory":"Clothing, Apparel, & Fashions",
            "type":"Retail Goods"
        }
    ],
    "sg:phone":"+39 0331 201280",
    "sg:postcode":"21012",
    "sg:province":"Varese",
    "sg:tags":[
        "clothes"
    ],
    "wof:name":"Co - Ba Lingerie (s.a.s.)",
    "wof:placetype":"venue"
},
  "geometry": {"coordinates":[8.826385,45.817604],"type":"Point"}
}