{
  "type": "Feature",
  "properties": {
    "addr:full":"5, Via Addis Abeba 13900 Biella Biella Biella 13900",
    "addr:postcode":"13900;13900",
    "addr:street":"Via Addis Abeba",
    "iso:country":"IT",
    "sg:address":"5, Via Addis Abeba 13900 Biella",
    "sg:city":"Biella",
    "sg:classifiers":[
        {
            "category":"Professional",
            "subcategory":"Computer Services",
            "type":"Services"
        }
    ],
    "sg:phone":"+39 015 849 4103",
    "sg:postcode":"13900",
    "sg:province":"Biella",
    "sg:tags":[
        "information",
        "technology"
    ],
    "wof:name":"Iride Centre Srl",
    "wof:placetype":"venue"
},
  "geometry": {"coordinates":[8.06044,45.557518],"type":"Point"}
}