{
  "type": "Feature",
  "properties": {
    "addr:full":"09030 Elmas Elmas Cagliari 09030",
    "addr:postcode":"09030;09030",
    "iso:country":"IT",
    "sg:address":"09030 Elmas",
    "sg:city":"Elmas",
    "sg:orig_category":"Frigoriferi - Accessori E Parti",
    "sg:phone":"+39 070 240695",
    "sg:postcode":"09030",
    "sg:province":"Cagliari",
    "wof:name":"M.c.r. Srl",
    "wof:placetype":"venue"
},
  "geometry": {"coordinates":[9.0754947662,39.2625007629],"type":"Point"}
}