{
  "type": "Feature",
  "properties": {
    "addr:full":"40068 San Lazzaro Di Savena San Lazzaro Bologna 40068",
    "addr:housenumber":"40068",
    "addr:postcode":"40068",
    "addr:street":"San;San;Bologna",
    "iso:country":"IT",
    "sg:address":"40068 San Lazzaro Di Savena",
    "sg:city":"San Lazzaro",
    "sg:orig_category":"Agenzie D'affari E Servizi Commerciali. Acqua, Luce, Gas E Societa' Di Esercizio Pubblico",
    "sg:phone":"+39 051 453155",
    "sg:postcode":"40068",
    "sg:province":"Bologna",
    "wof:name":"Istituto Vendite Giudiziarie E Fiduciarie Srl",
    "wof:placetype":"venue"
},
  "geometry": {"coordinates":[11.41456,44.477703],"type":"Point"}
}