{
  "type": "Feature",
  "properties": {
    "addr:full":"34, Via Di Vittorio 46045 Marmirolo Marmirolo Mantova 46045",
    "addr:postcode":"46045;46045",
    "addr:street":"Via Di Vittorio",
    "iso:country":"IT",
    "sg:address":"34, Via Di Vittorio 46045 Marmirolo",
    "sg:city":"Marmirolo",
    "sg:classifiers":[
        {
            "category":"Professional",
            "subcategory":"Engineering",
            "type":"Services"
        }
    ],
    "sg:phone":"+39 0376 467492",
    "sg:postcode":"46045",
    "sg:province":"Mantova",
    "sg:tags":[
        "machine",
        "-",
        "mechanical"
    ],
    "wof:name":"C.r.m. Di Gorgati Corrado & C. (s.n.c.)",
    "wof:placetype":"venue"
},
  "geometry": {"coordinates":[10.765014,45.206795],"type":"Point"}
}