{
  "type": "Feature",
  "properties": {
    "iso:country":"IT",
    "sg:address":"01010 Gradoli",
    "sg:city":"Gradoli",
    "sg:orig_category":"Servizi E Lavori Per Arredamento E Industria Del Legno. Servizi E Lavori Per Edilizia E Lavori Pubblici",
    "sg:phone":"+39 0761 456428",
    "sg:postcode":"01010",
    "sg:province":"Viterbo",
    "wof:name":"Onorati Armando",
    "wof:placetype":"venue"
},
  "geometry": {"coordinates":[11.855963,42.644539],"type":"Point"}
}