{
  "type": "Feature",
  "properties": {
    "addr:full":"5/c, V. Bernini 43100 Parma Parma Parma 43100",
    "addr:housenumber":"5 / c v.",
    "addr:postcode":"43100;43100",
    "addr:street":"Bernini",
    "iso:country":"IT",
    "sg:address":"5/c, V. Bernini 43100 Parma",
    "sg:city":"Parma",
    "sg:classifiers":[
        {
            "category":"Professional",
            "subcategory":"Engineering",
            "type":"Services"
        }
    ],
    "sg:phone":"+39 0521 980653",
    "sg:postcode":"43100",
    "sg:province":"Parma",
    "sg:tags":[
        "machine",
        "-",
        "mechanical"
    ],
    "sg:website":"http://www.universalflex.it",
    "wof:name":"Universalflex Srl",
    "wof:placetype":"venue"
},
  "geometry": {"coordinates":[10.303952,44.808083],"type":"Point"}
}