{
  "type": "Feature",
  "properties": {
    "iso:country":"IT",
    "sg:address":"20038 Seregno",
    "sg:city":"Seregno",
    "sg:orig_category":"Autogru - Noleggio",
    "sg:phone":"+39 036 223 9166",
    "sg:postcode":"20038",
    "sg:province":"Milano",
    "wof:name":"Marta Trasporti & Spedizioni Sas",
    "wof:placetype":"venue"
},
  "geometry": {"coordinates":[9.203573,45.651917],"type":"Point"}
}