{
  "type": "Feature",
  "properties": {
    "addr:full":"Via Delle Orobie 189 24059 Urgnano Urgnano Bergamo 24059",
    "addr:housenumber":"189",
    "addr:postcode":"24059;24059",
    "addr:street":"Via Delle Orobie",
    "iso:country":"IT",
    "sg:address":"Via Delle Orobie 189 24059 Urgnano",
    "sg:city":"Urgnano",
    "sg:classifiers":[
        {
            "category":"Professional",
            "subcategory":"Engineering",
            "type":"Services"
        }
    ],
    "sg:phone":"+39 035 891395",
    "sg:postcode":"24059",
    "sg:province":"Bergamo",
    "sg:tags":[
        "textile",
        "technology",
        "machinery",
        "special"
    ],
    "sg:website":"www.mp-italy.com",
    "wof:name":"Mp Srl",
    "wof:placetype":"venue"
},
  "geometry": {"coordinates":[9.684187,45.593216],"type":"Point"}
}