{
  "type": "Feature",
  "properties": {
    "iso:country":"IT",
    "sg:address":"20127 Milano",
    "sg:city":"Milano",
    "sg:orig_category":"Cinematografia E Radiotelevisione. Cine-foto-ottica",
    "sg:phone":"+39 02 669 6458",
    "sg:postcode":"20127",
    "sg:province":"Milano",
    "wof:name":"Poker Cinematografica S.r.l.",
    "wof:placetype":"venue"
},
  "geometry": {"coordinates":[9.21013,45.488907],"type":"Point"}
}