{
  "type": "Feature",
  "properties": {
    "addr:full":"10152 Torino Torino Torino 10152",
    "addr:postcode":"10152;10152",
    "iso:country":"IT",
    "sg:address":"10152 Torino",
    "sg:city":"Torino",
    "sg:orig_category":"Servizi E Lavori Per Edilizia E Lavori Pubblici",
    "sg:phone":"+39 011 436 3133",
    "sg:postcode":"10152",
    "sg:province":"Torino",
    "wof:name":"Del Monte Cosimo",
    "wof:placetype":"venue"
},
  "geometry": {"coordinates":[7.677628,45.083385],"type":"Point"}
}