{
  "type": "Feature",
  "properties": {
    "addr:full":"36033 Isola Vicentina Isola Vicentina Vicenza 36033",
    "addr:postcode":"36033;36033",
    "iso:country":"IT",
    "sg:address":"36033 Isola Vicentina",
    "sg:city":"Isola Vicentina",
    "sg:orig_category":"Servizi Ausiliari Dei Mezzi Di Trasporto",
    "sg:phone":"+39 0444 975516",
    "sg:postcode":"36033",
    "sg:province":"Vicenza",
    "wof:name":"Bertoldo Fratelli Antonio & Francesco Snc",
    "wof:placetype":"venue"
},
  "geometry": {"coordinates":[11.466496,45.6147],"type":"Point"}
}