{
  "type": "Feature",
  "properties": {
    "iso:country":"IT",
    "sg:address":"2, Via Del Lavoro 61020 Sant'angelo In Lizzola",
    "sg:classifiers":[
        {
            "category":"Manufacturing",
            "subcategory":"Tools & Machinery",
            "type":"Manufacturing & Wholesale Goods"
        }
    ],
    "sg:phone":"+39 0721 498517",
    "sg:postcode":"61020",
    "sg:province":"Pesaro E Urbino",
    "sg:tags":[
        "environment",
        "equipment",
        "-"
    ],
    "wof:name":"Barucca Impianti Di Barucca Otello & C. S.n.c.",
    "wof:placetype":"venue"
},
  "geometry": {"coordinates":[12.772305,43.850994],"type":"Point"}
}