{
  "type": "Feature",
  "properties": {
    "iso:country":"IT",
    "sg:address":"20143 Milano",
    "sg:city":"Milano",
    "sg:orig_category":"Serramenti Ed Infissi. Forniture Industriali Per Prevenzione, Controllo E Sicurezza",
    "sg:phone":"+39 02 832 3296",
    "sg:postcode":"20143",
    "sg:province":"Milano",
    "wof:name":"Paulon Renato",
    "wof:placetype":"venue"
},
  "geometry": {"coordinates":[9.173919,45.443989],"type":"Point"}
}