{
  "type": "Feature",
  "properties": {
    "iso:country":"IT",
    "sg:address":"38066 Riva Del Garda",
    "sg:city":"Riva del Garda",
    "sg:orig_category":"Tubi Plastica",
    "sg:phone":"+39 0464 520520",
    "sg:postcode":"38066",
    "sg:province":"Trento",
    "wof:name":"A.t.e. Alta Tecnologia Estrusione Spa",
    "wof:placetype":"venue"
},
  "geometry": {"coordinates":[10.824932,45.896542],"type":"Point"}
}