{
  "type": "Feature",
  "properties": {
    "addr:full":"12, Via Ibla 95128 Catania Catania Catania 95128",
    "addr:postcode":"95128;95128",
    "addr:street":"Via Ibla",
    "iso:country":"IT",
    "sg:address":"12, Via Ibla 95128 Catania",
    "sg:city":"Catania",
    "sg:classifiers":[
        {
            "category":"Manufacturing",
            "subcategory":"Metals",
            "type":"Manufacturing & Wholesale Goods"
        }
    ],
    "sg:phone":"+39 39095436583",
    "sg:postcode":"95128",
    "sg:province":"Catania",
    "sg:tags":[
        "processing"
    ],
    "wof:name":"Sicilmetano S.p.a.",
    "wof:placetype":"venue"
},
  "geometry": {"coordinates":[15.0830039978,37.524181366],"type":"Point"}
}