{
  "type": "Feature",
  "properties": {
    "addr:full":"42015 Correggio Reggio Nell'Emilia 42015",
    "addr:postcode":"42015;42015",
    "iso:country":"IT",
    "sg:address":"42015 Correggio",
    "sg:orig_category":"Termotecnica E Riscaldamento, Apparecchiature E Servizi",
    "sg:phone":"+39 0522 692944",
    "sg:postcode":"42015",
    "sg:province":"Reggio Nell'Emilia",
    "wof:name":"Tabo",
    "wof:placetype":"venue"
},
  "geometry": {"coordinates":[10.620666,44.706406],"type":"Point"}
}