{
  "type": "Feature",
  "properties": {
    "addr:full":"20124 Milano Milano Milano 20124",
    "addr:postcode":"20124;20124",
    "iso:country":"IT",
    "sg:address":"20124 Milano",
    "sg:city":"Milano",
    "sg:orig_category":"Telecomunicazioni E Telefonia, Impianti, Apparecchi E Servizi. Acqua, Luce, Gas E Societa' Di Esercizio Pubblico. Servizi Vari Di Interesse Pubblico",
    "sg:phone":"+39 02 2953 0185",
    "sg:postcode":"20124",
    "sg:province":"Milano",
    "wof:name":"Mian Phone Way S.a.s.",
    "wof:placetype":"venue"
},
  "geometry": {"coordinates":[9.203288,45.476593],"type":"Point"}
}