{
  "type": "Feature",
  "properties": {
    "iso:country":"IT",
    "sg:address":"51100 Pistoia",
    "sg:city":"Pistoia",
    "sg:orig_category":"Servizi E Lavori Per Edilizia E Lavori Pubblici. Professionisti - Studi E Servizi Ed Associazioni Di Interesse Aziendale",
    "sg:phone":"+39 0573 33277",
    "sg:postcode":"51100",
    "sg:province":"Pistoia",
    "wof:name":"Bartoli Silvio",
    "wof:placetype":"venue"
},
  "geometry": {"coordinates":[10.923737,43.928688],"type":"Point"}
}