{
  "type": "Feature",
  "properties": {
    "iso:country":"IT",
    "sg:address":"36040 Grisignano Di Zocco",
    "sg:city":"Grisignano di Zocco",
    "sg:classifiers":[
        {
            "category":"Food & Beverages",
            "subcategory":"Fruits & Vegetables",
            "type":"Retail Goods"
        }
    ],
    "sg:phone":"+39 0444 414262",
    "sg:postcode":"36040",
    "sg:province":"Vicenza",
    "sg:tags":[
        "growing",
        "agriculture",
        "flower",
        "products"
    ],
    "wof:name":"Azienda Agricola Funghi Grotte Di Costozza",
    "wof:placetype":"venue"
},
  "geometry": {"coordinates":[11.7167291641,45.4895362854],"type":"Point"}
}