{
  "type": "Feature",
  "properties": {
    "addr:full":"38, Via Iv Novembre 32040 Vigo Di Cadore Vigo di Cadore Belluno 32040",
    "addr:postcode":"32040;belluno 32040",
    "addr:street":"Via Iv Novembre;Di Cadore",
    "iso:country":"IT",
    "sg:address":"38, Via Iv Novembre 32040 Vigo Di Cadore",
    "sg:city":"Vigo di Cadore",
    "sg:classifiers":[
        {
            "category":"Wholesale",
            "subcategory":"Medical Equipment & Supplies",
            "type":"Manufacturing & Wholesale Goods"
        }
    ],
    "sg:phone":"+39 39043577078",
    "sg:postcode":"32040",
    "sg:province":"Belluno",
    "sg:tags":[
        "-",
        "health",
        "instrument"
    ],
    "wof:name":"Farben",
    "wof:placetype":"venue"
},
  "geometry": {"coordinates":[12.21759,46.139965],"type":"Point"}
}