{
  "type": "Feature",
  "properties": {
    "iso:country":"IT",
    "sg:address":"6/8, V. Dell'olmo 40010 Saletto Di Bentivoglio",
    "sg:city":"Bentivoglio",
    "sg:classifiers":[
        {
            "category":"Shopping",
            "subcategory":"Stationery & Office Supplies",
            "type":"Retail Goods"
        }
    ],
    "sg:phone":"+39 051 664 5004",
    "sg:postcode":"40010",
    "sg:province":"Bologna",
    "sg:tags":[
        "professional"
    ],
    "sg:website":"http://www.ponteggigabbi.com:ws_end: :mark:ws:http://www.paginegialle.it/gabbi",
    "wof:name":"Ponteggi Gabbi Srl",
    "wof:placetype":"venue"
},
  "geometry": {"coordinates":[11.6568784714,44.9779129028],"type":"Point"}
}