{
  "type": "Feature",
  "properties": {
    "iso:country":"IT",
    "sg:address":"20090 Segrate",
    "sg:city":"Segrate",
    "sg:orig_category":"Materiali E Componenti Elettrotecnici",
    "sg:phone":"+39 02 2692 2944",
    "sg:postcode":"20090",
    "sg:province":"Milano",
    "wof:name":"Everwatt (s.r.l.)",
    "wof:placetype":"venue"
},
  "geometry": {"coordinates":[9.267848,45.481155],"type":"Point"}
}