{
  "type": "Feature",
  "properties": {
    "iso:country":"IT",
    "sg:address":"20090 Vimodrone",
    "sg:city":"Vimodrone",
    "sg:orig_category":"Macchine Ed Impianti Per Edilizia E Lavori Pubblici. Macchine, Strumenti Ed Apparecchi Per Attivita' Industriali",
    "sg:phone":"+39 02 250 4098",
    "sg:postcode":"20090",
    "sg:province":"Milano",
    "wof:name":"Jelosil Srl",
    "wof:placetype":"venue"
},
  "geometry": {"coordinates":[9.298594,45.513565],"type":"Point"}
}