{
  "type": "Feature",
  "properties": {
    "iso:country":"IT",
    "sg:address":"41042 Fiorano Modenese",
    "sg:city":"Fiorano Modenese",
    "sg:orig_category":"Elaboratori Elettronici",
    "sg:phone":"+39 0536 911596",
    "sg:postcode":"41042",
    "sg:province":"Modena",
    "wof:name":"Eco Tre Srl",
    "wof:placetype":"venue"
},
  "geometry": {"coordinates":[10.867924,44.525875],"type":"Point"}
}