{
  "type": "Feature",
  "properties": {
    "iso:country":"IT",
    "sg:address":"20010 Cornaredo",
    "sg:city":"Cornaredo",
    "sg:orig_category":"Articoli Medico-sanitari Ed Ortopedici",
    "sg:phone":"+39 02 9356 2013",
    "sg:postcode":"20010",
    "sg:province":"Milano",
    "wof:name":"Centro Acustico Di Paola Donato",
    "wof:placetype":"venue"
},
  "geometry": {"coordinates":[9.025882,45.505428],"type":"Point"}
}