{
  "type": "Feature",
  "properties": {
    "iso:country":"IT",
    "sg:address":"20132 Milano",
    "sg:city":"Milano",
    "sg:classifiers":[
        {
            "category":"Utilities",
            "subcategory":"Natural Gas",
            "type":"Services"
        }
    ],
    "sg:phone":"+39 02 2720 3860",
    "sg:postcode":"20132",
    "sg:province":"Milano",
    "sg:tags":[
        "aria",
        "e",
        "compressori"
    ],
    "sg:website":"http://www.knf.it",
    "wof:name":"Knf Italia Srl",
    "wof:placetype":"venue"
},
  "geometry": {"coordinates":[9.246213,45.504959],"type":"Point"}
}