{
  "type": "Feature",
  "properties": {
    "iso:country":"IT",
    "sg:address":"20154 Milano",
    "sg:city":"Milano",
    "sg:orig_category":"Servizi Editoriali",
    "sg:phone":"+39 02 314990",
    "sg:postcode":"20154",
    "sg:province":"Milano",
    "wof:name":"Ferretti Nicoletta",
    "wof:placetype":"venue"
},
  "geometry": {"coordinates":[9.168509,45.488491],"type":"Point"}
}