{
  "type": "Feature",
  "properties": {
    "iso:country":"IT",
    "sg:address":"52024 Loro Ciuffenna",
    "sg:city":"Loro Ciuffenna",
    "sg:orig_category":"Materiali E Componenti Elettrotecnici",
    "sg:phone":"+39 055 917 2572",
    "sg:postcode":"52024",
    "sg:province":"Arezzo",
    "wof:name":"Cioncolini Stefano",
    "wof:placetype":"venue"
},
  "geometry": {"coordinates":[11.638533,43.634224],"type":"Point"}
}