{
  "type": "Feature",
  "properties": {
    "iso:country":"IT",
    "sg:address":"00123 Roma",
    "sg:city":"Roma",
    "sg:classifiers":[
        {
            "category":"Health Services",
            "subcategory":"Health Practitioner",
            "type":"Services"
        }
    ],
    "sg:phone":"+39 06 3089 1536",
    "sg:postcode":"00123",
    "sg:province":"Roma",
    "sg:tags":[
        "medici"
    ],
    "wof:name":"Radiologica Romana (s.r.l.)",
    "wof:placetype":"venue"
},
  "geometry": {"coordinates":[12.3234815598,42.0230903625],"type":"Point"}
}