{
  "type": "Feature",
  "properties": {
    "iso:country":"IT",
    "sg:address":"16137 Genova",
    "sg:city":"Genova",
    "sg:orig_category":"Depuratori E Depuranti",
    "sg:phone":"+39 010 839 1671",
    "sg:postcode":"16137",
    "sg:province":"Genova",
    "sg:website":"http://www.cattanizanelli.it",
    "wof:name":"Cattani E Zanelli Snc",
    "wof:placetype":"venue"
},
  "geometry": {"coordinates":[8.943854,44.432243],"type":"Point"}
}