{
  "type": "Feature",
  "properties": {
    "addr:full":"193, Via Quarantadue Martiri 28924 Verbania Verbania Verbano-Cusio-Ossola 28924",
    "addr:housenumber":"193",
    "addr:postcode":"28924;28924",
    "addr:street":"Via Quarantadue Martiri",
    "iso:country":"IT",
    "sg:address":"193, Via Quarantadue Martiri 28924 Verbania",
    "sg:city":"Verbania",
    "sg:classifiers":[
        {
            "category":"Professional",
            "subcategory":"Engineering",
            "type":"Services"
        }
    ],
    "sg:phone":"+39 0323 586798",
    "sg:postcode":"28924",
    "sg:province":"Verbano-Cusio-Ossola",
    "sg:tags":[
        "machine",
        "-",
        "mechanical"
    ],
    "wof:name":"Ecomin Srl",
    "wof:placetype":"venue"
},
  "geometry": {"coordinates":[8.475947,45.943501],"type":"Point"}
}