{
  "type": "Feature",
  "properties": {
    "addr:full":"62, Via Rismondo Francesco 27100 Pavia Pavia Pavia 27100",
    "addr:postcode":"27100;27100",
    "addr:street":"Via Rismondo Francesco",
    "iso:country":"IT",
    "sg:address":"62, Via Rismondo Francesco 27100 Pavia",
    "sg:city":"Pavia",
    "sg:classifiers":[
        {
            "category":"Food & Beverages",
            "subcategory":"Dairy",
            "type":"Retail Goods"
        }
    ],
    "sg:phone":"+39 0382 530525",
    "sg:postcode":"27100",
    "sg:province":"Pavia",
    "sg:tags":[
        "product"
    ],
    "wof:name":"Pasetti F. S.a.s.",
    "wof:placetype":"venue"
},
  "geometry": {"coordinates":[9.157342,45.196213],"type":"Point"}
}