{
  "type": "Feature",
  "properties": {
    "iso:country":"IT",
    "sg:address":"60035 Jesi",
    "sg:city":"Jesi",
    "sg:orig_category":"Agenzie Viaggi E Turismo",
    "sg:phone":"+39 0731 213154",
    "sg:postcode":"60035",
    "sg:province":"Ancona",
    "sg:website":"http://www.incontrieuropei.com",
    "wof:name":"Thema Viaggi Srl",
    "wof:placetype":"venue"
},
  "geometry": {"coordinates":[13.519804,43.577175],"type":"Point"}
}