{
  "type": "Feature",
  "properties": {
    "iso:country":"IT",
    "sg:address":"95014 Giarre",
    "sg:city":"Giarre",
    "sg:orig_category":"Accessori Dei Mezzi Di Trasporto",
    "sg:phone":"+39 095 930155",
    "sg:postcode":"95014",
    "sg:province":"Catania",
    "wof:name":"Franceschino Santo",
    "wof:placetype":"venue"
},
  "geometry": {"coordinates":[15.187407,37.723969],"type":"Point"}
}