{
  "type": "Feature",
  "properties": {
    "iso:country":"IT",
    "sg:address":"20144 Milano",
    "sg:city":"Milano",
    "sg:orig_category":"Servizi E Lavori Industria Della Gomma. Servizi E Lavori Industria Delle Materie Plastiche. Forniture Per Edilizia E Lavori Pubblici",
    "sg:phone":"+39 02 5811 1041",
    "sg:postcode":"20144",
    "sg:province":"Milano",
    "sg:website":"http://www.tg.com",
    "wof:name":"Tg Srl",
    "wof:placetype":"venue"
},
  "geometry": {"coordinates":[9.168298,45.455467],"type":"Point"}
}