{
  "type": "Feature",
  "properties": {
    "iso:country":"IT",
    "sg:address":"12100 Cuneo",
    "sg:city":"Cuneo",
    "sg:orig_category":"Antiquariato",
    "sg:phone":"+39 0171 692007",
    "sg:postcode":"12100",
    "sg:province":"Cuneo",
    "wof:name":"Cavaglion Enzo & C. Snc",
    "wof:placetype":"venue"
},
  "geometry": {"coordinates":[7.546261,44.387108],"type":"Point"}
}