{
  "type": "Feature",
  "properties": {
    "iso:country":"IT",
    "sg:address":"16035 Rapallo",
    "sg:city":"Rapallo",
    "sg:orig_category":"Persiane Ed Avvolgibili",
    "sg:phone":"+39 0185 231263",
    "sg:postcode":"16035",
    "sg:province":"Genova",
    "wof:name":"A.t.m. Di Mancioppi Angelo & C. Snc",
    "wof:placetype":"venue"
},
  "geometry": {"coordinates":[9.2340631485,44.3512611389],"type":"Point"}
}