{
  "type": "Feature",
  "properties": {
    "addr:full":"50031 Barberino Di Mugello Barberino di Mugello Firenze 50031",
    "addr:postcode":"50031;50031",
    "iso:country":"IT",
    "sg:address":"50031 Barberino Di Mugello",
    "sg:city":"Barberino di Mugello",
    "sg:orig_category":"Articoli Per Imballaggio E Confezionamento",
    "sg:phone":"+39 055 842 0198",
    "sg:postcode":"50031",
    "sg:province":"Firenze",
    "wof:name":"Termomeccanica Srl",
    "wof:placetype":"venue"
},
  "geometry": {"coordinates":[11.229711,44.015396],"type":"Point"}
}