{
  "type": "Feature",
  "properties": {
    "addr:full":"5, Viale Europa 56038 Ponsacco Ponsacco Pisa 56038",
    "addr:postcode":"56038;56038",
    "addr:street":"Viale Europa",
    "iso:country":"IT",
    "sg:address":"5, Viale Europa 56038 Ponsacco",
    "sg:city":"Ponsacco",
    "sg:classifiers":[
        {
            "category":"Home & Garden",
            "subcategory":"Home Furnishings",
            "type":"Retail Goods"
        }
    ],
    "sg:phone":"+39 0587 733449",
    "sg:postcode":"56038",
    "sg:province":"Pisa",
    "sg:tags":[
        "household"
    ],
    "wof:name":"Vani (s.r.l.)",
    "wof:placetype":"venue"
},
  "geometry": {"coordinates":[10.62221,43.630814],"type":"Point"}
}