{
  "type": "Feature",
  "properties": {
    "addr:full":"131, Via Villafontana 37050 Oppeano Oppeano Verona 37050",
    "addr:housenumber":"131",
    "addr:postcode":"37050;37050",
    "addr:street":"Via Villafontana",
    "iso:country":"IT",
    "sg:address":"131, Via Villafontana 37050 Oppeano",
    "sg:city":"Oppeano",
    "sg:classifiers":[
        {
            "category":"Home & Garden",
            "subcategory":"Home Furnishings",
            "type":"Retail Goods"
        }
    ],
    "sg:phone":"+39 045 698 9039",
    "sg:postcode":"37050",
    "sg:province":"Verona",
    "sg:tags":[
        "household"
    ],
    "wof:name":"Mozzo Fabbrica Armadi (s.r.l.)",
    "wof:placetype":"venue"
},
  "geometry": {"coordinates":[11.071208,45.311592],"type":"Point"}
}