{
  "type": "Feature",
  "properties": {
    "addr:full":"09122 Cagliari Cagliari Cagliari 09122",
    "addr:postcode":"09122;09122",
    "iso:country":"IT",
    "sg:address":"09122 Cagliari",
    "sg:city":"Cagliari",
    "sg:orig_category":"Servizi E Lavori Per Industria Alimentare E Bevande",
    "sg:phone":"+39 070 283227",
    "sg:postcode":"09122",
    "sg:province":"Cagliari",
    "wof:name":"Carboni Marco",
    "wof:placetype":"venue"
},
  "geometry": {"coordinates":[9.094766,39.24815],"type":"Point"}
}