{
  "type": "Feature",
  "properties": {
    "addr:full":"36075 Montecchio Maggiore Montecchio Maggiore Vicenza 36075",
    "addr:postcode":"36075;36075",
    "iso:country":"IT",
    "sg:address":"36075 Montecchio Maggiore",
    "sg:city":"Montecchio Maggiore",
    "sg:orig_category":"Fotografia Apparecchi E Materiali - Vendita Al Dettaglio",
    "sg:phone":"+39 0444 696533",
    "sg:postcode":"36075",
    "sg:province":"Vicenza",
    "wof:name":"Centro Ottico Carta Di Scarpa Srl Di Scarpa Stefania & C.",
    "wof:placetype":"venue"
},
  "geometry": {"coordinates":[11.4480485916,45.5267906189],"type":"Point"}
}