{
  "type": "Feature",
  "properties": {
    "iso:country":"IT",
    "sg:address":"40010 Bonconvento",
    "sg:orig_category":"Servizi E Lavori Per Agricoltura E Zootecnia",
    "sg:phone":"+39 051 828327",
    "sg:postcode":"40010",
    "sg:province":"Bologna",
    "wof:name":"Montanari Luigi",
    "wof:placetype":"venue"
},
  "geometry": {"coordinates":[11.304596,44.591782],"type":"Point"}
}