{
  "type": "Feature",
  "properties": {
    "addr:full":"80128 Napoli Napoli Napoli 80128",
    "addr:housenumber":"80128",
    "addr:postcode":"80128",
    "iso:country":"IT",
    "sg:address":"80128 Napoli",
    "sg:city":"Napoli",
    "sg:orig_category":"Zootecnia E Pesca, Allevamento Piccoli Animali. Animali Domestici",
    "sg:phone":"+39 081 560 1908",
    "sg:postcode":"80128",
    "sg:province":"Napoli",
    "wof:name":"Trapani Amedeo",
    "wof:placetype":"venue"
},
  "geometry": {"coordinates":[14.338594,40.872627],"type":"Point"}
}