{
  "type": "Feature",
  "properties": {
    "iso:country":"IT",
    "sg:address":"50050 Gambassi Terme",
    "sg:city":"Gambassi Terme",
    "sg:orig_category":"Macchine, Impianti Ed Attrezzature Per Abbigliamento E Pelletterie",
    "sg:phone":"+39 0571 667719",
    "sg:postcode":"50050",
    "sg:province":"Firenze",
    "wof:name":"Dainelli Riccardo Dainelli Aratri",
    "wof:placetype":"venue"
},
  "geometry": {"coordinates":[10.954871,43.540104],"type":"Point"}
}