{
  "type": "Feature",
  "properties": {
    "iso:country":"IT",
    "sg:address":"29, Via Monte Bisbino 20021 Bollate",
    "sg:city":"Bollate",
    "sg:classifiers":[
        {
            "category":"Wholesale",
            "subcategory":"Drugs",
            "type":"Manufacturing & Wholesale Goods"
        }
    ],
    "sg:phone":"+39 02 3820 1674",
    "sg:postcode":"20021",
    "sg:province":"Milano",
    "sg:tags":[
        "chemical",
        "pharmaceutical"
    ],
    "wof:name":"Industria Chimica Pertex (s.p.a.)",
    "wof:placetype":"venue"
},
  "geometry": {"coordinates":[9.106244,45.524437],"type":"Point"}
}