{
  "type": "Feature",
  "properties": {
    "addr:full":"Viale Industrie, 15/13 20020 Arese Arese Milano 20020",
    "addr:housenumber":"15 / 13",
    "addr:postcode":"20020;20020",
    "addr:street":"Viale Industrie",
    "iso:country":"IT",
    "sg:address":"Viale Industrie, 15/13 20020 Arese",
    "sg:city":"Arese",
    "sg:classifiers":[
        {
            "category":"Home & Garden",
            "subcategory":"Hardware",
            "type":"Retail Goods"
        }
    ],
    "sg:phone":"+39 02 938 3378",
    "sg:postcode":"20020",
    "sg:province":"Milano",
    "sg:tags":[
        "component",
        "electronic"
    ],
    "sg:website":"www.kendeil.com",
    "wof:name":"Kendeil Srl",
    "wof:placetype":"venue"
},
  "geometry": {"coordinates":[9.087852,45.535484],"type":"Point"}
}