{
  "type": "Feature",
  "properties": {
    "iso:country":"IT",
    "sg:address":"95126 Catania",
    "sg:city":"Catania",
    "sg:orig_category":"Materiali Edili",
    "sg:phone":"+39 095 494148",
    "sg:postcode":"95126",
    "sg:province":"Catania",
    "wof:name":"Ferbatt Siciliana Di L. Motta & C. Snc",
    "wof:placetype":"venue"
},
  "geometry": {"coordinates":[15.101819,37.53653],"type":"Point"}
}