{
  "type": "Feature",
  "properties": {
    "iso:country":"IT",
    "sg:address":"02100 Rieti",
    "sg:city":"Rieti",
    "sg:orig_category":"Manufacturers: Prefabbricati. Servizi E Lavori Per Ecologia E Smaltimento Rifiuti",
    "sg:phone":"+39 0746 484840",
    "sg:postcode":"02100",
    "sg:province":"Rieti",
    "wof:name":"Omnia Srl",
    "wof:placetype":"venue"
},
  "geometry": {"coordinates":[12.828477,42.39465],"type":"Point"}
}