{
  "type": "Feature",
  "properties": {
    "iso:country":"IT",
    "sg:address":"22075 Lurate Caccivio",
    "sg:city":"Lurate Caccivio",
    "sg:orig_category":"Manufacturers: Prefabbricati",
    "sg:phone":"+39 031 491459",
    "sg:postcode":"22075",
    "sg:province":"Como",
    "wof:name":"Berlusconi Tomaso Snc",
    "wof:placetype":"venue"
},
  "geometry": {"coordinates":[8.993656,45.764156],"type":"Point"}
}