{
  "type": "Feature",
  "properties": {
    "addr:full":"Via Iv Novembre 8 40060 Toscanella Toscanella Bologna 40060",
    "addr:housenumber":"8",
    "addr:postcode":"40060;toscanella bologna 40060",
    "addr:street":"Via Iv Novembre",
    "iso:country":"IT",
    "sg:address":"Via Iv Novembre 8 40060 Toscanella",
    "sg:city":"Toscanella",
    "sg:classifiers":[
        {
            "category":"Manufacturing",
            "subcategory":"Tools & Machinery",
            "type":"Manufacturing & Wholesale Goods"
        }
    ],
    "sg:phone":"+39 0542 672514",
    "sg:postcode":"40060",
    "sg:province":"Bologna",
    "sg:tags":[
        "abrasive"
    ],
    "sg:website":"www.abrex-system.com",
    "wof:name":"Abrex System Srl",
    "wof:placetype":"venue"
},
  "geometry": {"coordinates":[11.346481,44.494221],"type":"Point"}
}