{
  "type": "Feature",
  "properties": {
    "addr:full":"Via Frizzoni 52/c 24048 Treviolo Treviolo Bergamo 24048",
    "addr:housenumber":"52 / c",
    "addr:postcode":"24048;24048",
    "addr:street":"Via Frizzoni",
    "iso:country":"IT",
    "sg:address":"Via Frizzoni 52/c 24048 Treviolo",
    "sg:city":"Treviolo",
    "sg:classifiers":[
        {
            "category":"Autos & Motor Vehicles",
            "subcategory":"Automobile Sales",
            "type":"Retail Goods"
        }
    ],
    "sg:phone":"+39 035 200000",
    "sg:postcode":"24048",
    "sg:province":"Bergamo",
    "sg:tags":[
        "machine",
        "injection",
        "moulding",
        "automation"
    ],
    "sg:website":"www.alfameccanica.it",
    "wof:name":"Alfa Meccanica Srl",
    "wof:placetype":"venue"
},
  "geometry": {"coordinates":[9.593619,45.665691],"type":"Point"}
}