{
  "type": "Feature",
  "properties": {
    "iso:country":"IT",
    "sg:address":"Via Vignolese 1285; San Damaso; 41010",
    "sg:classifiers":[
        {
            "category":"Banks & Credit Unions",
            "subcategory":"Bank",
            "type":"Services"
        }
    ],
    "sg:phone":"+39 059 465006",
    "sg:postcode":"41010",
    "sg:province":"Modena",
    "wof:name":"Rolo Banca 1473 Spa",
    "wof:placetype":"venue"
},
  "geometry": {"coordinates":[10.969145,44.603745],"type":"Point"}
}