{
  "type": "Feature",
  "properties": {
    "addr:full":"90138 Palermo Palermo Palermo 90138",
    "addr:postcode":"90138;90138",
    "iso:country":"IT",
    "sg:address":"90138 Palermo",
    "sg:city":"Palermo",
    "sg:orig_category":"Servizi E Lavori Per Ecologia E Smaltimento Rifiuti",
    "sg:phone":"+39 091 335500",
    "sg:postcode":"90138",
    "sg:province":"Palermo",
    "wof:name":"Queensi",
    "wof:placetype":"venue"
},
  "geometry": {"coordinates":[13.348366,38.118698],"type":"Point"}
}