{
  "type": "Feature",
  "properties": {
    "addr:full":"35010 Marsango Marsango Padova 35010",
    "addr:postcode":"35010;35010",
    "addr:street":"Marsango",
    "iso:country":"IT",
    "sg:address":"35010 Marsango",
    "sg:city":"Marsango",
    "sg:orig_category":"Prodotti E Manufatti In Materie Plastiche. Forniture Per Edilizia E Lavori Pubblici. Forniture E Materiali Per Imballaggio E Confezionamento",
    "sg:phone":"+39 049 552078",
    "sg:postcode":"35010",
    "sg:province":"Padova",
    "wof:name":"Veneta Espansi S.r.l.",
    "wof:placetype":"venue"
},
  "geometry": {"coordinates":[11.8291187286,45.5501708984],"type":"Point"}
}