{
  "type": "Feature",
  "properties": {
    "iso:country":"IT",
    "sg:address":"20090 Pantigliate",
    "sg:city":"Pantigliate",
    "sg:orig_category":"Termotecnica E Riscaldamento, Apparecchiature E Servizi",
    "sg:phone":"+39 02 9068 6572",
    "sg:postcode":"20090",
    "sg:province":"Milano",
    "wof:name":"Eliovelox Electromaker Di Locatelli Amalia",
    "wof:placetype":"venue"
},
  "geometry": {"coordinates":[9.311753,45.428509],"type":"Point"}
}