{
  "type": "Feature",
  "properties": {
    "iso:country":"IT",
    "sg:address":"18038 Bussana",
    "sg:city":"Bussana",
    "sg:orig_category":"Servizi E Lavori Per Abbigliamento E Pelletterie. Arte Ed Artigianato Artistico. Shopping",
    "sg:phone":"+39 0184 513411",
    "sg:postcode":"18038",
    "sg:province":"Imperia",
    "wof:name":"Scagliarini Francesco",
    "wof:placetype":"venue"
},
  "geometry": {"coordinates":[7.834116,43.831306],"type":"Point"}
}