{
  "type": "Feature",
  "properties": {
    "addr:full":"37012 Bussolengo Bussolengo Verona 37012",
    "addr:postcode":"37012;37012",
    "iso:country":"IT",
    "sg:address":"37012 Bussolengo",
    "sg:city":"Bussolengo",
    "sg:orig_category":"Parchi Zoologici, Acquari E Rettilari",
    "sg:phone":"+39 045 717 0052",
    "sg:postcode":"37012",
    "sg:province":"Verona",
    "sg:website":"http://www.parconaturaviva.it",
    "wof:name":"Parco Natura Viva",
    "wof:placetype":"venue"
},
  "geometry": {"coordinates":[10.848651886,45.4683876038],"type":"Point"}
}