{
  "type": "Feature",
  "properties": {
    "iso:country":"IT",
    "sg:address":"100/16, Via Tevere 50019 Sesto Fiorentino",
    "sg:city":"Sesto Fiorentino",
    "sg:classifiers":[
        {
            "category":"Shopping",
            "subcategory":"Clothing, Apparel, & Fashions",
            "type":"Retail Goods"
        }
    ],
    "sg:phone":"+39 39055374051",
    "sg:postcode":"50019",
    "sg:province":"Firenze",
    "sg:tags":[
        "clothes"
    ],
    "wof:name":"Enterpryse Co.(s.r.l.)",
    "wof:placetype":"venue"
},
  "geometry": {"coordinates":[11.171671,43.809948],"type":"Point"}
}