{
  "type": "Feature",
  "properties": {
    "addr:full":"268, Via Napoli 80022 Arzano Arzano Napoli 80022",
    "addr:housenumber":"268",
    "addr:postcode":"80022;80022",
    "addr:street":"Via Napoli",
    "iso:country":"IT",
    "sg:address":"268, Via Napoli 80022 Arzano",
    "sg:city":"Arzano",
    "sg:classifiers":[
        {
            "category":"Shopping",
            "subcategory":"Crafts & Fabrics",
            "type":"Retail Goods"
        }
    ],
    "sg:phone":"+39 081 573 4839",
    "sg:postcode":"80022",
    "sg:province":"Napoli",
    "sg:tags":[
        "linen"
    ],
    "wof:name":"Mid S.r.l.",
    "wof:placetype":"venue"
},
  "geometry": {"coordinates":[14.2653026581,40.9055557251],"type":"Point"}
}