{
  "type": "Feature",
  "properties": {
    "iso:country":"IT",
    "sg:address":"00159 Roma",
    "sg:city":"Roma",
    "sg:orig_category":"Servizi Culturali E Per Lo Spettacolo. Cine-foto-ottica",
    "sg:phone":"+39 06 438 2420",
    "sg:postcode":"00159",
    "sg:province":"Roma",
    "wof:name":"D.v.r. Srl",
    "wof:placetype":"venue"
},
  "geometry": {"coordinates":[12.537905,41.906593],"type":"Point"}
}