{
  "type": "Feature",
  "properties": {
    "iso:country":"IT",
    "sg:address":"00067 Morlupo",
    "sg:city":"Morlupo",
    "sg:orig_category":"Non-classified Establishments",
    "sg:phone":"+39 06 907 2192",
    "sg:postcode":"00067",
    "sg:province":"Roma",
    "wof:name":"Vetro Arredo",
    "wof:placetype":"venue"
},
  "geometry": {"coordinates":[12.656409,41.984566],"type":"Point"}
}