{
  "type": "Feature",
  "properties": {
    "iso:country":"IT",
    "sg:address":"24067 Sarnico",
    "sg:city":"Sarnico",
    "sg:orig_category":"Servizi E Lavori Per Agricoltura E Zootecnia. Servizi E Lavori Per Ecologia E Smaltimento Rifiuti",
    "sg:phone":"+39 035 914171",
    "sg:postcode":"24067",
    "sg:province":"Bergamo",
    "wof:name":"Geoservice Srl",
    "wof:placetype":"venue"
},
  "geometry": {"coordinates":[9.952893,45.66951],"type":"Point"}
}