{
  "type": "Feature",
  "properties": {
    "iso:country":"IT",
    "sg:address":"64, Via Dos Roda 38057 Pergine Valsugana",
    "sg:city":"Pergine Valsugana",
    "sg:classifiers":[
        {
            "category":"Manufacturing",
            "subcategory":"Metals",
            "type":"Manufacturing & Wholesale Goods"
        }
    ],
    "sg:phone":"+39 0461 538330",
    "sg:postcode":"38057",
    "sg:province":"Trento",
    "sg:tags":[
        "metallurgy",
        "metalworking"
    ],
    "wof:name":"Tecnogen S.r.l.",
    "wof:placetype":"venue"
},
  "geometry": {"coordinates":[11.2102556229,46.0753631592],"type":"Point"}
}