{
  "type": "Feature",
  "properties": {
    "iso:country":"IT",
    "sg:address":"121, Via Montottone 00010 Roma",
    "sg:classifiers":[
        {
            "category":"Parking",
            "subcategory":"Lot",
            "type":"Transportation"
        }
    ],
    "sg:phone":"+39 39062203584",
    "sg:postcode":"00010",
    "sg:province":"Roma",
    "sg:tags":[
        "transport",
        "road"
    ],
    "wof:name":"D.c.a.l.m.a. Srl",
    "wof:placetype":"venue"
},
  "geometry": {"coordinates":[12.721939,41.924061],"type":"Point"}
}