{
  "type": "Feature",
  "properties": {
    "addr:full":"44011 Argenta Argenta Ferrara 44011",
    "addr:postcode":"44011;44011",
    "iso:country":"IT",
    "sg:address":"44011 Argenta",
    "sg:city":"Argenta",
    "sg:classifiers":[
        {
            "category":"Structure",
            "subcategory":"Shopping Mall",
            "type":"Public Place"
        }
    ],
    "sg:phone":"+39 0532 809151",
    "sg:postcode":"44011",
    "sg:province":"Ferrara",
    "sg:tags":[
        "shop",
        "sexy"
    ],
    "wof:name":"Paprika",
    "wof:placetype":"venue"
},
  "geometry": {"coordinates":[11.734239,44.730438],"type":"Point"}
}