{
  "type": "Feature",
  "properties": {
    "addr:full":"20059 Vimercate Vimercate Milano 20059",
    "addr:postcode":"20059;20059",
    "iso:country":"IT",
    "sg:address":"20059 Vimercate",
    "sg:city":"Vimercate",
    "sg:orig_category":"Banche E Servizi Finanziari. Acqua, Luce, Gas E Societa' Di Esercizio Pubblico",
    "sg:phone":"+39 039 661 2064",
    "sg:postcode":"20059",
    "sg:province":"Milano",
    "wof:name":"Feba Tributi (s.p.a.)",
    "wof:placetype":"venue"
},
  "geometry": {"coordinates":[9.359053,45.60162],"type":"Point"}
}