{
  "type": "Feature",
  "properties": {
    "iso:country":"IT",
    "sg:address":"25125 Brescia",
    "sg:city":"Brescia",
    "sg:classifiers":[
        {
            "category":"Health Services",
            "subcategory":"Health Practitioner",
            "type":"Services"
        }
    ],
    "sg:phone":"+39 030 242 1504",
    "sg:postcode":"25125",
    "sg:province":"Brescia",
    "sg:tags":[
        "medici"
    ],
    "wof:name":"Besozzi Valentini Francesco",
    "wof:placetype":"venue"
},
  "geometry": {"coordinates":[10.207964,45.531006],"type":"Point"}
}