{
  "type": "Feature",
  "properties": {
    "iso:country":"IT",
    "sg:address":"52020 Laterina",
    "sg:city":"Laterina",
    "sg:orig_category":"Gioiellerie E Oreficerie - Vendita Al Dettaglio",
    "sg:phone":"+39 0575 89323",
    "sg:postcode":"52020",
    "sg:province":"Arezzo",
    "wof:name":"Edenoro Sas",
    "wof:placetype":"venue"
},
  "geometry": {"coordinates":[11.711743,43.5042],"type":"Point"}
}