{
  "type": "Feature",
  "properties": {
    "addr:full":"40134 Bologna Bologna Bologna 40134",
    "addr:postcode":"40134;40134",
    "iso:country":"IT",
    "sg:address":"40134 Bologna",
    "sg:city":"Bologna",
    "sg:classifiers":[
        {
            "category":"Banks & Credit Unions",
            "subcategory":"Investment Brokerage",
            "type":"Services"
        }
    ],
    "sg:phone":"+39 051 614 3661",
    "sg:postcode":"40134",
    "sg:province":"Bologna",
    "sg:tags":[
        "parrucchieri",
        "per",
        "donna"
    ],
    "wof:name":"Burnelli \u00c9quipe Parrucchieri",
    "wof:placetype":"venue"
},
  "geometry": {"coordinates":[11.3207912445,44.495716095],"type":"Point"}
}