{
  "type": "Feature",
  "properties": {
    "iso:country":"IT",
    "sg:address":"Via A.eistein 8 30033 Noale",
    "sg:city":"Noale",
    "sg:classifiers":[
        {
            "category":"Shopping Center",
            "type":"Public Place"
        }
    ],
    "sg:phone":"+39 041 589 7311",
    "sg:postcode":"30033",
    "sg:province":"Venezia",
    "sg:tags":[
        "aluminium",
        "section"
    ],
    "sg:website":"www.alupro.it",
    "wof:name":"Alu-pro S.r.l.",
    "wof:placetype":"venue"
},
  "geometry": {"coordinates":[12.338784,45.434338],"type":"Point"}
}