{
  "type": "Feature",
  "properties": {
    "iso:country":"IT",
    "sg:address":"00159 Roma",
    "sg:city":"Roma",
    "sg:orig_category":"Ospedali E Servizi Sanitari",
    "sg:phone":"+39 06 439 3141",
    "sg:postcode":"00159",
    "sg:province":"Roma",
    "wof:name":"Medica Ray Srl",
    "wof:placetype":"venue"
},
  "geometry": {"coordinates":[12.537213,41.898888],"type":"Point"}
}