{
  "type": "Feature",
  "properties": {
    "iso:country":"IT",
    "sg:address":"90127 Palermo",
    "sg:city":"Palermo",
    "sg:orig_category":"Materiali E Componenti Elettrotecnici",
    "sg:phone":"+39 091 617 0050",
    "sg:postcode":"90127",
    "sg:province":"Palermo",
    "wof:name":"Elettrica Vip",
    "wof:placetype":"venue"
},
  "geometry": {"coordinates":[13.363873,38.104439],"type":"Point"}
}