{
  "type": "Feature",
  "properties": {
    "iso:country":"IT",
    "sg:address":"144, Via Venezia 36015 Schio",
    "sg:city":"Schio",
    "sg:classifiers":[
        {
            "category":"Wholesale",
            "subcategory":"Medical Equipment & Supplies",
            "type":"Manufacturing & Wholesale Goods"
        }
    ],
    "sg:phone":"+39 0445 511983",
    "sg:postcode":"36015",
    "sg:province":"Vicenza",
    "sg:tags":[
        "-",
        "health",
        "instrument"
    ],
    "wof:name":"Maison Casanova Srl",
    "wof:placetype":"venue"
},
  "geometry": {"coordinates":[11.364777,45.708138],"type":"Point"}
}