{
  "type": "Feature",
  "properties": {
    "addr:full":"13, Via Cascione 18013 Diano Marina Diano Marina Imperia 18013",
    "addr:postcode":"18013;18013",
    "addr:street":"Via Cascione",
    "iso:country":"IT",
    "sg:address":"13, Via Cascione 18013 Diano Marina",
    "sg:city":"Diano Marina",
    "sg:classifiers":[
        {
            "category":"Travel",
            "subcategory":"Travel Agent",
            "type":"Entertainment"
        }
    ],
    "sg:phone":"+39 0183 495474",
    "sg:postcode":"18013",
    "sg:province":"Imperia",
    "sg:tags":[
        "business"
    ],
    "wof:name":"Albergo Roma",
    "wof:placetype":"venue"
},
  "geometry": {"coordinates":[8.077394,43.905067],"type":"Point"}
}