{
  "type": "Feature",
  "properties": {
    "iso:country":"IT",
    "sg:address":"Piazza Degli Uffici 13; Moggio Udinese; 33015",
    "sg:city":"Moggio Udinese",
    "sg:classifiers":[
        {
            "category":"Banks & Credit Unions",
            "subcategory":"Bank",
            "type":"Services"
        }
    ],
    "sg:phone":"+39 0443 51161",
    "sg:postcode":"33015",
    "sg:province":"Udine",
    "wof:name":"Rolo Banca 1473 Spa",
    "wof:placetype":"venue"
},
  "geometry": {"coordinates":[13.194992,46.40995],"type":"Point"}
}