{
  "type": "Feature",
  "properties": {
    "addr:full":"8, V. Rossini40067 Rastignano Rastignano Bologna 40067",
    "addr:housenumber":"8;rossini40067",
    "addr:postcode":"40067",
    "addr:street":"V.",
    "iso:country":"IT",
    "sg:address":"8, V. Rossini40067 Rastignano",
    "sg:city":"Rastignano",
    "sg:classifiers":[
        {
            "category":"Shopping",
            "type":"Retail Goods"
        }
    ],
    "sg:phone":"+39 39051743190",
    "sg:postcode":"40067",
    "sg:province":"Bologna",
    "sg:tags":[
        "finished",
        "-",
        "metallic"
    ],
    "sg:website":"http://www.sta-stampi.com:ws_end: :mark:ws:http://www.paginegialle.it/stastampi",
    "wof:name":"S.t.a. Srl",
    "wof:placetype":"venue"
},
  "geometry": {"coordinates":[11.3505783081,44.4245376587],"type":"Point"}
}