{
  "type": "Feature",
  "properties": {
    "iso:country":"IT",
    "sg:address":"00144 Roma",
    "sg:city":"Roma",
    "sg:orig_category":"Servizi Al Turismo. Servizi Ausiliari Dei Mezzi Di Trasporto. Servizi Ausiliari Per Il Trasporto. Acqua, Luce, Gas E Societa' Di Esercizio Pubblico",
    "sg:phone":"+39 06 591 2120",
    "sg:postcode":"00144",
    "sg:province":"Roma",
    "wof:name":"Gruppo Anziani Alitalia",
    "wof:placetype":"venue"
},
  "geometry": {"coordinates":[12.472635,41.826134],"type":"Point"}
}