{
  "type": "Feature",
  "properties": {
    "iso:country":"IT",
    "sg:address":"20154 Milano",
    "sg:city":"Milano",
    "sg:orig_category":"Traduttori Ed Interpreti",
    "sg:phone":"+39 02 342793",
    "sg:postcode":"20154",
    "sg:province":"Milano",
    "sg:website":"http://www.agostiniassociati.com",
    "wof:name":"Agostini & Associati Srl",
    "wof:placetype":"venue"
},
  "geometry": {"coordinates":[9.170356,45.481438],"type":"Point"}
}