{
  "type": "Feature",
  "properties": {
    "iso:country":"IT",
    "sg:address":"22100 Como",
    "sg:city":"Como",
    "sg:orig_category":"Calzature, Pelletterie E Pelli. Shopping",
    "sg:phone":"+39 031 270008",
    "sg:postcode":"22100",
    "sg:province":"Como",
    "wof:name":"Mandarina Duck",
    "wof:placetype":"venue"
},
  "geometry": {"coordinates":[9.092748,45.799282],"type":"Point"}
}