{
  "type": "Feature",
  "properties": {
    "addr:full":"16128 Genova Genova Genova 16128",
    "addr:postcode":"16128;16128",
    "iso:country":"IT",
    "sg:address":"16128 Genova",
    "sg:city":"Genova",
    "sg:orig_category":"Fognature",
    "sg:phone":"+39 010 594007",
    "sg:postcode":"16128",
    "sg:province":"Genova",
    "wof:name":"Docks Lanterna Srl",
    "wof:placetype":"venue"
},
  "geometry": {"coordinates":[8.9377946854,44.4012947083],"type":"Point"}
}