{
  "type": "Feature",
  "properties": {
    "iso:country":"IT",
    "sg:address":"55, Via Dei Nebrodi 90146 Palermo",
    "sg:city":"Palermo",
    "sg:classifiers":[
        {
            "category":"Professional",
            "subcategory":"Engineering",
            "type":"Services"
        }
    ],
    "sg:phone":"+39 39091516582",
    "sg:postcode":"90146",
    "sg:province":"Palermo",
    "sg:tags":[
        "machine",
        "-",
        "mechanical"
    ],
    "wof:name":"Societa' Tecnica Del Freddo S.r.l.",
    "wof:placetype":"venue"
},
  "geometry": {"coordinates":[13.329318,38.149788],"type":"Point"}
}