{
  "type": "Feature",
  "properties": {
    "addr:full":"1, Piazza Roma 25080 Calvagese Della Riviera Calvagese della Riviera Brescia 25080",
    "addr:postcode":"25080;25080",
    "addr:street":"Piazza Roma",
    "iso:country":"IT",
    "sg:address":"1, Piazza Roma 25080 Calvagese Della Riviera",
    "sg:city":"Calvagese della Riviera",
    "sg:classifiers":[
        {
            "category":"Wholesale",
            "subcategory":"Drugs",
            "type":"Manufacturing & Wholesale Goods"
        }
    ],
    "sg:phone":"+39 39030601031",
    "sg:postcode":"25080",
    "sg:province":"Brescia",
    "sg:tags":[
        "chemical",
        "pharmaceutical"
    ],
    "wof:name":"Luciano Sorlini Spa",
    "wof:placetype":"venue"
},
  "geometry": {"coordinates":[10.460979,45.56292],"type":"Point"}
}