{
  "type": "Feature",
  "properties": {
    "addr:full":"46, Via Fermi 24035 Curno Curno Bergamo 24035",
    "addr:postcode":"24035;24035",
    "addr:street":"Via Fermi",
    "iso:country":"IT",
    "sg:address":"46, Via Fermi 24035 Curno",
    "sg:city":"Curno",
    "sg:classifiers":[
        {
            "category":"Personal",
            "subcategory":"Shoe Repair & Shine",
            "type":"Services"
        }
    ],
    "sg:phone":"+39 39035615171",
    "sg:postcode":"24035",
    "sg:province":"Bergamo",
    "sg:tags":[
        "leather"
    ],
    "wof:name":"Grismondi Ernesto Di Leidi Fratelli (s.p.a.)",
    "wof:placetype":"venue"
},
  "geometry": {"coordinates":[9.622238,45.688755],"type":"Point"}
}