{
  "type": "Feature",
  "properties": {
    "iso:country":"IT",
    "sg:address":"10121 Torino",
    "sg:city":"Torino",
    "sg:orig_category":"Abbigliamento - Vendita Al Dettaglio",
    "sg:phone":"+39 011 542355",
    "sg:postcode":"10121",
    "sg:province":"Torino",
    "wof:name":"Absolut Joy",
    "wof:placetype":"venue"
},
  "geometry": {"coordinates":[7.579069,45.066582],"type":"Point"}
}