{
  "type": "Feature",
  "properties": {
    "addr:full":"50032 Borgo San Lorenzo Borgo San Lorenzo Firenze 50032",
    "addr:postcode":"50032;50032",
    "addr:street":"Borgo San Lorenzo Borgo San Lorenzo",
    "iso:country":"IT",
    "sg:address":"50032 Borgo San Lorenzo",
    "sg:city":"Borgo San Lorenzo",
    "sg:classifiers":[
        {
            "category":"Retail",
            "subcategory":"Event Space",
            "type":"Services"
        }
    ],
    "sg:phone":"+39 055 849 6083",
    "sg:postcode":"50032",
    "sg:province":"Firenze",
    "sg:tags":[
        "articles",
        "product",
        "plastics",
        "publishing",
        "packaging",
        "packing",
        "services",
        "article"
    ],
    "wof:name":"Nuova Graphopack",
    "wof:placetype":"venue"
},
  "geometry": {"coordinates":[11.3687849045,43.9586524963],"type":"Point"}
}