{
  "type": "Feature",
  "properties": {
    "iso:country":"IT",
    "sg:address":"08100 Nuoro",
    "sg:city":"Nuoro",
    "sg:orig_category":"Imprese Di Costruzioni Civili Ed Industriali",
    "sg:phone":"+39 0784 255052",
    "sg:postcode":"08100",
    "sg:province":"Nuoro",
    "wof:name":"Sigeco Sas",
    "wof:placetype":"venue"
},
  "geometry": {"coordinates":[9.331533,40.318066],"type":"Point"}
}