{
  "type": "Feature",
  "properties": {
    "addr:full":"30122 Venezia Castello Venezia 30122",
    "addr:postcode":"30122;30122",
    "iso:country":"IT",
    "sg:address":"30122 Venezia",
    "sg:city":"Castello",
    "sg:orig_category":"Alberghi E Strutture Extra Alberghiere",
    "sg:phone":"+39 041 522 3706",
    "sg:postcode":"30122",
    "sg:province":"Venezia",
    "wof:name":"Alloggi Stemar Srl",
    "wof:placetype":"venue"
},
  "geometry": {"coordinates":[12.341408,45.434361],"type":"Point"}
}