{
  "type": "Feature",
  "properties": {
    "iso:country":"IT",
    "sg:address":"24030 Barzana",
    "sg:city":"Barzana",
    "sg:orig_category":"Lavorazioni Metalli, Stampaggio E Saldatura",
    "sg:phone":"+39 035 554711",
    "sg:postcode":"24030",
    "sg:province":"Bergamo",
    "sg:website":"http://www.oasa.it",
    "wof:name":"O.a.s.a. Olimpio Alde' Spa",
    "wof:placetype":"venue"
},
  "geometry": {"coordinates":[9.568444,45.736572],"type":"Point"}
}