{
  "type": "Feature",
  "properties": {
    "iso:country":"IT",
    "sg:address":"06012 Citta' Di Castello",
    "sg:orig_category":"Autotrasporti",
    "sg:phone":"+39 075 855 7631",
    "sg:postcode":"06012",
    "sg:province":"Perugia",
    "wof:name":"Volpi Roberto",
    "wof:placetype":"venue"
},
  "geometry": {"coordinates":[12.252334,43.458984],"type":"Point"}
}