{
  "type": "Feature",
  "properties": {
    "iso:country":"IT",
    "sg:address":"07021 Arzachena",
    "sg:city":"Arzachena",
    "sg:orig_category":"Energia Solare Ed Energie Alternative - Impianti E Componenti",
    "sg:phone":"+39 0789 81716",
    "sg:postcode":"07021",
    "sg:province":"Olbia-Tempio",
    "wof:name":"Hubert Schmidt",
    "wof:placetype":"venue"
},
  "geometry": {"coordinates":[9.516914,40.899803],"type":"Point"}
}