{
  "type": "Feature",
  "properties": {
    "iso:country":"IT",
    "sg:address":"6, Contrada Cona 66030 Treglio",
    "sg:city":"Treglio",
    "sg:classifiers":[
        {
            "category":"Home & Garden",
            "subcategory":"Home Furnishings",
            "type":"Retail Goods"
        }
    ],
    "sg:phone":"+39 39087249006",
    "sg:postcode":"66030",
    "sg:province":"Chieti",
    "sg:tags":[
        "household"
    ],
    "wof:name":"Barbarossa Leonardo",
    "wof:placetype":"venue"
},
  "geometry": {"coordinates":[14.405517,42.26178],"type":"Point"}
}