{
  "type": "Feature",
  "properties": {
    "iso:country":"IT",
    "sg:address":"1, V. Fava 40055 Castenaso",
    "sg:city":"Castenaso",
    "sg:classifiers":[
        {
            "category":"Home & Garden",
            "subcategory":"Home Furnishings",
            "type":"Retail Goods"
        }
    ],
    "sg:phone":"+39 39051787405",
    "sg:postcode":"40055",
    "sg:province":"Bologna",
    "sg:tags":[
        "household"
    ],
    "wof:name":"Farn\u00c8 Group Srl",
    "wof:placetype":"venue"
},
  "geometry": {"coordinates":[11.457733,44.503361],"type":"Point"}
}