{
  "type": "Feature",
  "properties": {
    "iso:country":"IT",
    "sg:address":"Via Fura 38/a 25125 Brescia",
    "sg:city":"Brescia",
    "sg:classifiers":[
        {
            "category":"Autos & Motor Vehicles",
            "subcategory":"Fuel & Gas Station",
            "type":"Retail Goods"
        }
    ],
    "sg:phone":"+39 030 353 1332",
    "sg:postcode":"25125",
    "sg:province":"Brescia",
    "sg:tags":[
        "appliance",
        "heating"
    ],
    "wof:name":"Aertermica Spa",
    "wof:placetype":"venue"
},
  "geometry": {"coordinates":[10.222958,45.539829],"type":"Point"}
}