{
  "type": "Feature",
  "properties": {
    "iso:country":"IT",
    "sg:address":"31050 Casacorba",
    "sg:city":"Casacorba",
    "sg:orig_category":"Forniture Per Attivita' Industriali",
    "sg:phone":"+39 0423 452005",
    "sg:postcode":"31050",
    "sg:province":"Treviso",
    "wof:name":"T.p.m. Di Tessaro & C. (s.n.c.)",
    "wof:placetype":"venue"
},
  "geometry": {"coordinates":[12.0295877457,45.664276123],"type":"Point"}
}