{
  "type": "Feature",
  "properties": {
    "addr:full":"35010 Vigonza Vigonza Padova 35010",
    "addr:postcode":"35010;35010",
    "iso:country":"IT",
    "sg:address":"35010 Vigonza",
    "sg:city":"Vigonza",
    "sg:orig_category":"Macchine Utensili - Commercio",
    "sg:phone":"+39 049 893 2255",
    "sg:postcode":"35010",
    "sg:province":"Padova",
    "wof:name":"Mios Di Sturaro Franco & Giuseppe Snc",
    "wof:placetype":"venue"
},
  "geometry": {"coordinates":[11.944839,45.473358],"type":"Point"}
}