{
  "type": "Feature",
  "properties": {
    "iso:country":"IT",
    "sg:address":"89018 Villa San Giovanni",
    "sg:city":"Villa San Giovanni",
    "sg:classifiers":[
        {
            "category":"Utilities",
            "subcategory":"Refuse",
            "type":"Services"
        }
    ],
    "sg:phone":"+39 0965 794053",
    "sg:postcode":"89018",
    "sg:province":"Reggio Di Calabria",
    "sg:tags":[
        "auxiliary",
        "disposal",
        "surveillance",
        "environmental",
        "protection",
        "cleaning",
        "maintenance",
        "works"
    ],
    "wof:name":"Actives Srl",
    "wof:placetype":"venue"
},
  "geometry": {"coordinates":[15.659421,38.233597],"type":"Point"}
}