{
  "type": "Feature",
  "properties": {
    "iso:country":"IT",
    "sg:address":"26017 Trescore Cremasco",
    "sg:city":"Trescore Cremasco",
    "sg:orig_category":"Carta, Cartone E Prodotti Primari. Forniture E Materiali Per Imballaggio E Confezionamento",
    "sg:phone":"+39 0373 274464",
    "sg:postcode":"26017",
    "sg:province":"Cremona",
    "wof:name":"Lacchinelli Antonio Paolo & C. (s.n.c.)",
    "wof:placetype":"venue"
},
  "geometry": {"coordinates":[9.626111,45.4025],"type":"Point"}
}