{
  "type": "Feature",
  "properties": {
    "iso:country":"IT",
    "sg:address":"60022 Castelfidardo",
    "sg:city":"Castelfidardo",
    "sg:orig_category":"Piattaforme E Scale Aeree",
    "sg:phone":"+39 071 781 9090",
    "sg:postcode":"60022",
    "sg:province":"Ancona",
    "sg:website":"http://www.braviisol.it",
    "wof:name":"Braviisol Srl",
    "wof:placetype":"venue"
},
  "geometry": {"coordinates":[13.5552606583,43.4676475525],"type":"Point"}
}