{
  "type": "Feature",
  "properties": {
    "iso:country":"IT",
    "sg:address":"Cso Europa 18 20031 Cesano Maderno",
    "sg:city":"Cesano Maderno",
    "sg:classifiers":[
        {
            "category":"Government",
            "subcategory":"Court House",
            "type":"Public Place"
        }
    ],
    "sg:phone":"+39 036 250 3178",
    "sg:postcode":"20031",
    "sg:province":"Milano",
    "sg:tags":[
        "accommodation",
        "furniture"
    ],
    "sg:website":"www.capuzzi-arredamenti.it",
    "wof:name":"Capuzzi Arredamenti S.n.c.",
    "wof:placetype":"venue"
},
  "geometry": {"coordinates":[9.188141,45.463688],"type":"Point"}
}