{
  "type": "Feature",
  "properties": {
    "addr:full":"20094 Corsico Corsico Milano 20094",
    "addr:postcode":"20094;20094",
    "iso:country":"IT",
    "sg:address":"20094 Corsico",
    "sg:city":"Corsico",
    "sg:orig_category":"Servizi E Lavori Per Abbigliamento E Pelletterie",
    "sg:phone":"+39 02 447 9964",
    "sg:postcode":"20094",
    "sg:province":"Milano",
    "wof:name":"Pecfurs S.r.l.",
    "wof:placetype":"venue"
},
  "geometry": {"coordinates":[9.10995,45.432541],"type":"Point"}
}