{
  "type": "Feature",
  "properties": {
    "iso:country":"IT",
    "sg:address":"42015 Correggio",
    "sg:orig_category":"Abbigliamento Intimo, Calze E Costumi Da Bagno. Shopping",
    "sg:phone":"+39 0522 691893",
    "sg:postcode":"42015",
    "sg:province":"Reggio Nell'Emilia",
    "wof:name":"Cristina Intimo",
    "wof:placetype":"venue"
},
  "geometry": {"coordinates":[10.676799,44.765285],"type":"Point"}
}