{
  "type": "Feature",
  "properties": {
    "addr:full":"54, Via Montagnola 35014 Fontaniva Fontaniva Padova 35014",
    "addr:postcode":"35014;35014",
    "addr:street":"Via Montagnola",
    "iso:country":"IT",
    "sg:address":"54, Via Montagnola 35014 Fontaniva",
    "sg:city":"Fontaniva",
    "sg:classifiers":[
        {
            "category":"Manufacturing",
            "subcategory":"Metals",
            "type":"Manufacturing & Wholesale Goods"
        }
    ],
    "sg:phone":"+39 049 942 0077",
    "sg:postcode":"35014",
    "sg:province":"Padova",
    "sg:tags":[
        "processing"
    ],
    "wof:name":"Cma Baccega S.r.l.",
    "wof:placetype":"venue"
},
  "geometry": {"coordinates":[11.769826889,45.6122779846],"type":"Point"}
}