{
  "type": "Feature",
  "properties": {
    "addr:full":"Via Pasubio 7/c 43100 Parma Parma Parma 43100",
    "addr:housenumber":"7 / c",
    "addr:postcode":"43100;43100",
    "addr:street":"Via Pasubio",
    "iso:country":"IT",
    "sg:address":"Via Pasubio 7/c 43100 Parma",
    "sg:city":"Parma",
    "sg:classifiers":[
        {
            "category":"Banks & Credit Unions",
            "subcategory":"Bureau De Change",
            "type":"Services"
        }
    ],
    "sg:phone":"+39 0521 772156",
    "sg:postcode":"43100",
    "sg:province":"Parma",
    "sg:tags":[
        "leather",
        "article",
        "customized"
    ],
    "sg:website":"www.maeni.com",
    "wof:name":"Maeni Snc",
    "wof:placetype":"venue"
},
  "geometry": {"coordinates":[10.29492,44.823208],"type":"Point"}
}