{
  "type": "Feature",
  "properties": {
    "iso:country":"IT",
    "sg:address":"95122 Aci Castello",
    "sg:orig_category":"Animali Domestici - Toeletta",
    "sg:phone":"+39 095 752 1542",
    "sg:postcode":"95122",
    "sg:province":"Catania",
    "wof:name":"I Fedelissimi Di Maugeri Bruno",
    "wof:placetype":"venue"
},
  "geometry": {"coordinates":[15.126889,37.560452],"type":"Point"}
}