{
  "type": "Feature",
  "properties": {
    "addr:full":"Via Chiusa Di Sotto 83014 Ospedaletto D'alpinolo Avellino 83014",
    "addr:postcode":"83014;83014",
    "addr:street":"Via Chiusa Di Sotto",
    "iso:country":"IT",
    "sg:address":"Via Chiusa Di Sotto 83014 Ospedaletto D'alpinolo",
    "sg:classifiers":[
        {
            "category":"Food & Beverages",
            "subcategory":"Groceries & Convenience Stores",
            "type":"Retail Goods"
        }
    ],
    "sg:phone":"+39 0825 691336",
    "sg:postcode":"83014",
    "sg:province":"Avellino",
    "sg:tags":[
        "product",
        "related"
    ],
    "wof:name":"G.m. & F. Oliviero Fratelli S.a.s",
    "wof:placetype":"venue"
},
  "geometry": {"coordinates":[14.7489900589,40.938621521],"type":"Point"}
}