{
  "type": "Feature",
  "properties": {
    "iso:country":"IT",
    "sg:address":"25080 Nuvolento",
    "sg:city":"Nuvolento",
    "sg:orig_category":"Servizi E Lavori Per Abbigliamento E Pelletterie",
    "sg:phone":"+39 030 691 9597",
    "sg:postcode":"25080",
    "sg:province":"Brescia",
    "wof:name":"Lavanderia E Stireria Bresciana",
    "wof:placetype":"venue"
},
  "geometry": {"coordinates":[10.385777,45.54385],"type":"Point"}
}