{
  "type": "Feature",
  "properties": {
    "iso:country":"IT",
    "sg:address":"50144 Firenze",
    "sg:city":"Firenze",
    "sg:orig_category":"Servizi Vari Di Interesse Pubblico",
    "sg:phone":"+39 055 351278",
    "sg:postcode":"50144",
    "sg:province":"Firenze",
    "wof:name":"Magisus Emporio Della Magia",
    "wof:placetype":"venue"
},
  "geometry": {"coordinates":[11.226877,43.782269],"type":"Point"}
}