{
  "type": "Feature",
  "properties": {
    "iso:country":"IT",
    "sg:address":"71013 San Giovanni Rotondo",
    "sg:city":"San Giovanni Rotondo",
    "sg:orig_category":"Decoratori",
    "sg:phone":"+39 0882 452135",
    "sg:postcode":"71013",
    "sg:province":"Foggia",
    "wof:name":"Ciccone Donato - Artista Del Pennello",
    "wof:placetype":"venue"
},
  "geometry": {"coordinates":[15.758591,41.673962],"type":"Point"}
}