{
  "type": "Feature",
  "properties": {
    "iso:country":"IT",
    "sg:address":"264, Via Scipione L'africano 70124 Bari",
    "sg:city":"Bari",
    "sg:classifiers":[
        {
            "category":"Manufacturing",
            "subcategory":"Printing",
            "type":"Manufacturing & Wholesale Goods"
        }
    ],
    "sg:phone":"+39 080 557 6907",
    "sg:postcode":"70124",
    "sg:province":"Bari",
    "sg:tags":[
        "publishing"
    ],
    "wof:name":"Edisud Spa.",
    "wof:placetype":"venue"
},
  "geometry": {"coordinates":[16.8692913055,41.1260528564],"type":"Point"}
}