{
  "type": "Feature",
  "properties": {
    "iso:country":"IT",
    "sg:address":"24, Via Lanzo 10071 Borgaro Torinese",
    "sg:city":"Borgaro Torinese",
    "sg:classifiers":[
        {
            "category":"Shopping",
            "subcategory":"Gifts & Souvenirs",
            "type":"Retail Goods"
        }
    ],
    "sg:phone":"+39 011 470 2338",
    "sg:postcode":"10071",
    "sg:province":"Torino",
    "wof:name":"Argon S.r.l.",
    "wof:placetype":"venue"
},
  "geometry": {"coordinates":[7.65606,45.138046],"type":"Point"}
}