{
  "type": "Feature",
  "properties": {
    "iso:country":"IT",
    "sg:address":"20060 Vignate",
    "sg:city":"Vignate",
    "sg:orig_category":"Forniture Per Attivita' Commerciali Ed Artigianali",
    "sg:phone":"+39 02 9536 0757",
    "sg:postcode":"20060",
    "sg:province":"Milano",
    "wof:name":"Lombarda Astucci Soc.coop.r.l.",
    "wof:placetype":"venue"
},
  "geometry": {"coordinates":[9.3262195587,45.4824867249],"type":"Point"}
}