{
  "type": "Feature",
  "properties": {
    "addr:full":"95127 Catania Catania Catania 95127",
    "addr:postcode":"95127;95127",
    "iso:country":"IT",
    "sg:address":"95127 Catania",
    "sg:city":"Catania",
    "sg:orig_category":"Forniture E Prodotti Informatici. Forniture Per Uffici",
    "sg:phone":"+39 095 722 3647",
    "sg:postcode":"95127",
    "sg:province":"Catania",
    "wof:name":"Ekos Di Missorici Antonio & C. Sas",
    "wof:placetype":"venue"
},
  "geometry": {"coordinates":[15.1023244858,37.5194702148],"type":"Point"}
}