{
  "type": "Feature",
  "properties": {
    "addr:full":"00060 Castelnuovo Di Porto Castelnuovo di Porto Roma 00060",
    "addr:postcode":"00060;00060",
    "addr:street":"Porto Castelnuovo",
    "iso:country":"IT",
    "sg:address":"00060 Castelnuovo Di Porto",
    "sg:city":"Castelnuovo di Porto",
    "sg:orig_category":"Pubblica Amministrazione",
    "sg:phone":"+39 06 9038 0562",
    "sg:postcode":"00060",
    "sg:province":"Roma",
    "wof:name":"Corpo Forestale Dello Stato - Centro Polifunz.protezione Civile",
    "wof:placetype":"venue"
},
  "geometry": {"coordinates":[12.5022039413,42.1268882751],"type":"Point"}
}