{
  "type": "Feature",
  "properties": {
    "iso:country":"IT",
    "sg:address":"22060 Arosio",
    "sg:city":"Arosio",
    "sg:orig_category":"Ospedali E Servizi Sanitari",
    "sg:phone":"+39 031 761908",
    "sg:postcode":"22060",
    "sg:province":"Como",
    "wof:name":"Colombo Marinella",
    "wof:placetype":"venue"
},
  "geometry": {"coordinates":[9.204981,45.715988],"type":"Point"}
}