{
  "type": "Feature",
  "properties": {
    "addr:full":"16137 Genova Genova Genova 16137",
    "addr:postcode":"16137;16137",
    "iso:country":"IT",
    "sg:address":"16137 Genova",
    "sg:city":"Genova",
    "sg:orig_category":"Servizi E Lavori Per Ecologia E Smaltimento Rifiuti. Termotecnica E Riscaldamento, Apparecchiature E Servizi. Servizi Ausiliari Di Sorveglianza, Manutenzione E Pulizia",
    "sg:phone":"+39 010 887883",
    "sg:postcode":"16137",
    "sg:province":"Genova",
    "wof:name":"Mandruzzato Gianfranco",
    "wof:placetype":"venue"
},
  "geometry": {"coordinates":[8.943854,44.432243],"type":"Point"}
}