{
  "type": "Feature",
  "properties": {
    "iso:country":"IT",
    "sg:address":"Via Tosi 3 46017 Rivarolo Mantovano",
    "sg:city":"Rivarolo Mantovano",
    "sg:orig_category":"Ladies' Trousers Suits, Suits, Jackets, Skirts, And Trousers",
    "sg:phone":"+39 0376 958195",
    "sg:postcode":"46017",
    "sg:province":"Mantova",
    "sg:website":"www.extro-fashion.it",
    "wof:name":"F.lli Bresciani S.r.l.",
    "wof:placetype":"venue"
},
  "geometry": {"coordinates":[10.43326,45.068752],"type":"Point"}
}