{
  "type": "Feature",
  "properties": {
    "iso:country":"IT",
    "sg:address":"16, Via Toscanini Arturo 44100 Ferrara",
    "sg:city":"Ferrara",
    "sg:classifiers":[
        {
            "category":"Real Estate",
            "subcategory":"Architect",
            "type":"Services"
        }
    ],
    "sg:phone":"+39 0532 903786",
    "sg:postcode":"44100",
    "sg:province":"Ferrara",
    "sg:tags":[
        "textile",
        "clothing"
    ],
    "wof:name":"Novantanove S.u.r.l.",
    "wof:placetype":"venue"
},
  "geometry": {"coordinates":[11.62044,44.837894],"type":"Point"}
}