{
  "type": "Feature",
  "properties": {
    "addr:full":"25136 Brescia Brescia Brescia 25136",
    "addr:postcode":"25136;25136",
    "iso:country":"IT",
    "sg:address":"25136 Brescia",
    "sg:city":"Brescia",
    "sg:classifiers":[
        {
            "category":"Health Services",
            "subcategory":"Health Practitioner",
            "type":"Services"
        }
    ],
    "sg:phone":"+39 030 200 0668",
    "sg:postcode":"25136",
    "sg:province":"Brescia",
    "sg:tags":[
        "medici"
    ],
    "wof:name":"De Nard Fabio",
    "wof:placetype":"venue"
},
  "geometry": {"coordinates":[10.230882,45.577957],"type":"Point"}
}