{
  "type": "Feature",
  "properties": {
    "iso:country":"IT",
    "sg:address":"25045 Castegnato",
    "sg:city":"Castegnato",
    "sg:orig_category":"Utensili Meccanici E Materiali",
    "sg:phone":"+39 030 214 0907",
    "sg:postcode":"25045",
    "sg:province":"Brescia",
    "wof:name":"A.s.p. S.r.l.",
    "wof:placetype":"venue"
},
  "geometry": {"coordinates":[10.115302,45.563641],"type":"Point"}
}