{
  "type": "Feature",
  "properties": {
    "iso:country":"IT",
    "sg:address":"3, Via Edison 40017 San Giovanni In Persiceto",
    "sg:city":"San Giovanni in Persiceto",
    "sg:classifiers":[
        {
            "category":"Professional",
            "subcategory":"Engineering",
            "type":"Services"
        }
    ],
    "sg:phone":"+39 39051821601",
    "sg:postcode":"40017",
    "sg:province":"Bologna",
    "sg:tags":[
        "machine",
        "-",
        "mechanical"
    ],
    "wof:name":"Co.ma.s (s.n.c.)",
    "wof:placetype":"venue"
},
  "geometry": {"coordinates":[11.17096,44.634487],"type":"Point"}
}