{
  "type": "Feature",
  "properties": {
    "addr:full":"20021 Baranzate Baranzate Milano 20021",
    "addr:postcode":"20021;20021",
    "iso:country":"IT",
    "sg:address":"20021 Baranzate",
    "sg:city":"Baranzate",
    "sg:orig_category":"Prodotti Di Base E Forniture Per Industria Alimentare E Bevande. Prodotti Chimici Secondari. Forniture Alle Strutture Ricettive",
    "sg:phone":"+39 02 356 0610",
    "sg:postcode":"20021",
    "sg:province":"Milano",
    "wof:name":"Ghiaccio Secco (s.r.l.)",
    "wof:placetype":"venue"
},
  "geometry": {"coordinates":[9.1170110703,45.5273895264],"type":"Point"}
}