{
  "type": "Feature",
  "properties": {
    "addr:full":"V Oberdan 30/32; Teramo; 64100 Teramo Teramo 64100",
    "addr:housenumber":"30 / 32",
    "addr:postcode":"v;64100;64100",
    "addr:street":"Oberdan",
    "iso:country":"IT",
    "sg:address":"V Oberdan 30/32; Teramo; 64100",
    "sg:city":"Teramo",
    "sg:classifiers":[
        {
            "category":"Banks & Credit Unions",
            "subcategory":"Bank",
            "type":"Services"
        }
    ],
    "sg:phone":"+39 0861 339269",
    "sg:postcode":"64100",
    "sg:province":"Teramo",
    "wof:name":"Banca Popolare Dell'adriatico",
    "wof:placetype":"venue"
},
  "geometry": {"coordinates":[13.70373,42.659935],"type":"Point"}
}