{
  "type": "Feature",
  "properties": {
    "iso:country":"IT",
    "sg:address":"Via Indipendenza 2 33044 Manzano",
    "sg:city":"Manzano",
    "sg:classifiers":[
        {
            "category":"Wholesale",
            "subcategory":"Home Furnishings",
            "type":"Manufacturing & Wholesale Goods"
        }
    ],
    "sg:phone":"+39 0432 754161",
    "sg:postcode":"33044",
    "sg:province":"Udine",
    "sg:tags":[
        "chair"
    ],
    "sg:website":"www.costantinisedie.com",
    "wof:name":"Fratelli Costantini Sas",
    "wof:placetype":"venue"
},
  "geometry": {"coordinates":[13.375821,45.985832],"type":"Point"}
}