{
  "type": "Feature",
  "properties": {
    "iso:country":"IT",
    "sg:address":"Via Rovereto 5 27029 Vigevano",
    "sg:city":"Vigevano",
    "sg:classifiers":[
        {
            "category":"Shopping",
            "subcategory":"Shoes",
            "type":"Retail Goods"
        }
    ],
    "sg:phone":"+39 0381 691289",
    "sg:postcode":"27029",
    "sg:province":"Pavia",
    "sg:tags":[
        "children's"
    ],
    "sg:website":"www.amccalzature.it",
    "wof:name":"A.m.c. Calzature Srl",
    "wof:placetype":"venue"
},
  "geometry": {"coordinates":[8.85639,45.324085],"type":"Point"}
}