{
  "type": "Feature",
  "properties": {
    "iso:country":"IT",
    "sg:address":"24, Via Sauro Nazario 40121 Bologna",
    "sg:city":"Bologna",
    "sg:classifiers":[
        {
            "category":"Communications",
            "subcategory":"Newspaper",
            "type":"Services"
        }
    ],
    "sg:phone":"+39 39051236061",
    "sg:postcode":"40121",
    "sg:province":"Bologna",
    "sg:tags":[
        "advertising"
    ],
    "wof:name":"Societa' Di Gestione E Partecipazione Srl",
    "wof:placetype":"venue"
},
  "geometry": {"coordinates":[11.33943,44.497486],"type":"Point"}
}