{
  "type": "Feature",
  "properties": {
    "iso:country":"IT",
    "sg:address":"30174 Mestre",
    "sg:city":"Mestre",
    "sg:orig_category":"Autodemolizioni",
    "sg:phone":"+39 041 535 1029",
    "sg:postcode":"30174",
    "sg:province":"Venezia",
    "wof:name":"Artuso Nerio",
    "wof:placetype":"venue"
},
  "geometry": {"coordinates":[12.274776,45.491898],"type":"Point"}
}