{
  "type": "Feature",
  "properties": {
    "iso:country":"IT",
    "sg:address":"20094 Corsico",
    "sg:city":"Corsico",
    "sg:orig_category":"Audiovisivi Apparecchi Ed Impianti - Produzione, Commercio E Noleggio",
    "sg:phone":"+39 02 440 0110",
    "sg:postcode":"20094",
    "sg:province":"Milano",
    "wof:name":"All Over Video Service Sas",
    "wof:placetype":"venue"
},
  "geometry": {"coordinates":[9.111356,45.432304],"type":"Point"}
}