{
  "type": "Feature",
  "properties": {
    "addr:full":"09125 Cagliari Cagliari Cagliari 09125",
    "addr:postcode":"09125;09125",
    "iso:country":"IT",
    "sg:address":"09125 Cagliari",
    "sg:city":"Cagliari",
    "sg:orig_category":"Servizi Al Turismo. Trasporto Pubblico E Privato",
    "sg:phone":"+39 070 655613",
    "sg:postcode":"09125",
    "sg:province":"Cagliari",
    "wof:name":"Lloyd Sardegna Compagnia Di Navigazione Srl",
    "wof:placetype":"venue"
},
  "geometry": {"coordinates":[9.119201,39.212006],"type":"Point"}
}