{
  "type": "Feature",
  "properties": {
    "addr:full":"36, Via Del Chianti 50028 Tavarnelle Val Di Pesa Tavarnelle Val di Pesa Firenze 50028",
    "addr:postcode":"50028;50028",
    "addr:street":"Via Del Chianti;Val Di Pesa",
    "iso:country":"IT",
    "sg:address":"36, Via Del Chianti 50028 Tavarnelle Val Di Pesa",
    "sg:city":"Tavarnelle Val di Pesa",
    "sg:classifiers":[
        {
            "category":"Food & Beverages",
            "subcategory":"Groceries & Convenience Stores",
            "type":"Retail Goods"
        }
    ],
    "sg:phone":"+39 055 805 0465",
    "sg:postcode":"50028",
    "sg:province":"Firenze",
    "sg:tags":[
        "product",
        "related"
    ],
    "wof:name":"Castel Del Chianti Spa",
    "wof:placetype":"venue"
},
  "geometry": {"coordinates":[11.2205896378,43.5380554199],"type":"Point"}
}