{
  "type": "Feature",
  "properties": {
    "iso:country":"IT",
    "sg:address":"24067 Sarnico",
    "sg:city":"Sarnico",
    "sg:orig_category":"Forniture Per Agricoltura E Zootecnia. Prodotti Chimici Secondari. Macchine E Forniture Per Ecologia E Smaltimento Rifiuti",
    "sg:phone":"+39 035 910063",
    "sg:postcode":"24067",
    "sg:province":"Bergamo",
    "wof:name":"Sonzogni Giovanni",
    "wof:placetype":"venue"
},
  "geometry": {"coordinates":[9.9395856857,45.6650352478],"type":"Point"}
}