{
  "type": "Feature",
  "properties": {
    "iso:country":"IT",
    "sg:address":"00179 Roma",
    "sg:city":"Roma",
    "sg:orig_category":"Manufacturers: Prefabbricati",
    "sg:phone":"+39 06 782 7511",
    "sg:postcode":"00179",
    "sg:province":"Roma",
    "wof:name":"Italceramiche Srl",
    "wof:placetype":"venue"
},
  "geometry": {"coordinates":[12.525725,41.868298],"type":"Point"}
}