{
  "type": "Feature",
  "properties": {
    "iso:country":"IT",
    "sg:address":"37136 Verona",
    "sg:city":"Verona",
    "sg:orig_category":"Serramenti Ed Infissi",
    "sg:phone":"+39 045 584477",
    "sg:postcode":"37136",
    "sg:province":"Verona",
    "sg:website":"http://www.trs-standard.it",
    "wof:name":"Trs Standard Srl",
    "wof:placetype":"venue"
},
  "geometry": {"coordinates":[10.964589,45.409691],"type":"Point"}
}