{
  "type": "Feature",
  "properties": {
    "addr:full":"24, Via Baldanzese 50041 Calenzano Calenzano Firenze 50041",
    "addr:postcode":"50041;50041",
    "addr:street":"Via Baldanzese",
    "iso:country":"IT",
    "sg:address":"24, Via Baldanzese 50041 Calenzano",
    "sg:city":"Calenzano",
    "sg:classifiers":[
        {
            "category":"Wholesale",
            "subcategory":"Machinery & Supplies",
            "type":"Manufacturing & Wholesale Goods"
        }
    ],
    "sg:phone":"+39 055 881 1241",
    "sg:postcode":"50041",
    "sg:province":"Firenze",
    "sg:tags":[
        "equipment",
        "precision"
    ],
    "wof:name":"Ot-las Srl",
    "wof:placetype":"venue"
},
  "geometry": {"coordinates":[11.1708269119,43.8459968567],"type":"Point"}
}