{
  "type": "Feature",
  "properties": {
    "iso:country":"IT",
    "sg:address":"20093 Cologno Monzese",
    "sg:city":"Cologno Monzese",
    "sg:classifiers":[
        {
            "category":"Health Services",
            "subcategory":"Health Practitioner",
            "type":"Services"
        }
    ],
    "sg:phone":"+39 02 253 3449",
    "sg:postcode":"20093",
    "sg:province":"Milano",
    "sg:tags":[
        "medici"
    ],
    "wof:name":"Cittadino Raffaele",
    "wof:placetype":"venue"
},
  "geometry": {"coordinates":[9.277541,45.527348],"type":"Point"}
}