{
  "type": "Feature",
  "properties": {
    "addr:full":"14, Via Vicinale Per Parabiago 20014 Nerviano Nerviano Milano 20014",
    "addr:postcode":"20014;20014",
    "addr:street":"Via Vicinale Per Parabiago",
    "iso:country":"IT",
    "sg:address":"14, Via Vicinale Per Parabiago 20014 Nerviano",
    "sg:city":"Nerviano",
    "sg:classifiers":[
        {
            "category":"Professional",
            "subcategory":"Engineering",
            "type":"Services"
        }
    ],
    "sg:phone":"+39 0331 580064",
    "sg:postcode":"20014",
    "sg:province":"Milano",
    "sg:tags":[
        "machine",
        "-",
        "mechanical"
    ],
    "wof:name":"Castelmonte S.r.l.",
    "wof:placetype":"venue"
},
  "geometry": {"coordinates":[9.188141,45.463688],"type":"Point"}
}