{
  "type": "Feature",
  "properties": {
    "addr:full":"86019 Vinchiaturo Vinchiaturo Campobasso 86019",
    "addr:postcode":"86019;86019",
    "iso:country":"IT",
    "sg:address":"86019 Vinchiaturo",
    "sg:city":"Vinchiaturo",
    "sg:orig_category":"Prodotti Alimentari",
    "sg:phone":"+39 0874 34780",
    "sg:postcode":"86019",
    "sg:province":"Campobasso",
    "wof:name":"Caseificio Molisano L. Barone Snc",
    "wof:placetype":"venue"
},
  "geometry": {"coordinates":[14.589884758,41.4937820435],"type":"Point"}
}