{
  "type": "Feature",
  "properties": {
    "addr:full":"80040 Volla Volla Napoli 80040",
    "addr:postcode":"80040;80040",
    "iso:country":"IT",
    "sg:address":"80040 Volla",
    "sg:city":"Volla",
    "sg:orig_category":"Abbigliamento Esterno, Maglierie E Pelliccerie. Forniture Per Abbigliamento E Pelletterie",
    "sg:phone":"+39 081 773 5548",
    "sg:postcode":"80040",
    "sg:province":"Napoli",
    "wof:name":"Vitiello Pascal",
    "wof:placetype":"venue"
},
  "geometry": {"coordinates":[14.3526,40.879311],"type":"Point"}
}