{
  "type": "Feature",
  "properties": {
    "iso:country":"IT",
    "sg:address":"00172 Roma",
    "sg:city":"Roma",
    "sg:orig_category":"Ospedali E Servizi Sanitari. Servizi Sociali",
    "sg:phone":"+39 06 231 6040",
    "sg:postcode":"00172",
    "sg:province":"Roma",
    "wof:name":"Coop Cospexa",
    "wof:placetype":"venue"
},
  "geometry": {"coordinates":[12.575428,41.882351],"type":"Point"}
}