{
  "type": "Feature",
  "properties": {
    "iso:country":"IT",
    "sg:address":"24060 Tavernola Bergamasca",
    "sg:city":"Tavernola Bergamasca",
    "sg:orig_category":"Tessuti E Stoffe. Filati E Materie Prime Tessili",
    "sg:phone":"+39 035 932885",
    "sg:postcode":"24060",
    "sg:province":"Bergamo",
    "wof:name":"B.b. Lavorazioni Tessili S.r.l.",
    "wof:placetype":"venue"
},
  "geometry": {"coordinates":[10.036127,45.716175],"type":"Point"}
}