{
  "type": "Feature",
  "properties": {
    "iso:country":"IT",
    "sg:address":"Via M Stabile 152; Palermo; 90139",
    "sg:city":"Palermo",
    "sg:classifiers":[
        {
            "category":"Banks & Credit Unions",
            "subcategory":"Bank",
            "type":"Services"
        }
    ],
    "sg:phone":"+39 091 602 5111",
    "sg:postcode":"90139",
    "sg:province":"Palermo",
    "wof:name":"Banca Commerciale Italiana Spa",
    "wof:placetype":"venue"
},
  "geometry": {"coordinates":[13.357871,38.122997],"type":"Point"}
}