{
  "type": "Feature",
  "properties": {
    "iso:country":"IT",
    "sg:address":"36030 Sarcedo",
    "sg:city":"Sarcedo",
    "sg:orig_category":"Macchine, Impianti Ed Attrezzature Per Abbigliamento E Pelletterie. Macchine E Impianti Per Attivita' Commerciali Ed Artigianali",
    "sg:phone":"+39 0445 381140",
    "sg:postcode":"36030",
    "sg:province":"Vicenza",
    "wof:name":"Tonello Srl",
    "wof:placetype":"venue"
},
  "geometry": {"coordinates":[11.511843,45.705818],"type":"Point"}
}