{
  "type": "Feature",
  "properties": {
    "iso:country":"IT",
    "sg:address":"20061 Carugate",
    "sg:city":"Carugate",
    "sg:orig_category":"Materiali Edili",
    "sg:phone":"+39 02 925 1697",
    "sg:postcode":"20061",
    "sg:province":"Milano",
    "wof:name":"Fratelli Bellavia Di Renzo E Giuseppe Snc",
    "wof:placetype":"venue"
},
  "geometry": {"coordinates":[9.178378,45.370857],"type":"Point"}
}