{
  "type": "Feature",
  "properties": {
    "addr:full":"27029 Vigevano Vigevano Pavia 27029",
    "addr:postcode":"27029;27029",
    "iso:country":"IT",
    "sg:address":"27029 Vigevano",
    "sg:city":"Vigevano",
    "sg:orig_category":"Macchine E Forniture Per Arredamento E Industria Del Legno. Prodotti E Manufatti In Gomma",
    "sg:phone":"+39 0381 697311",
    "sg:postcode":"27029",
    "sg:province":"Pavia",
    "wof:name":"Fiscagomma Spa",
    "wof:placetype":"venue"
},
  "geometry": {"coordinates":[8.885058,45.315739],"type":"Point"}
}