{
  "type": "Feature",
  "properties": {
    "addr:full":"Via A De Gasperi 108; Bussolengo",
    "addr:housenumber":"108",
    "addr:street":"Via A De Gasperi",
    "iso:country":"IT",
    "sg:address":"Via A De Gasperi 108; Bussolengo",
    "sg:classifiers":[
        {
            "category":"Banks & Credit Unions",
            "subcategory":"Bank",
            "type":"Services"
        }
    ],
    "sg:phone":"+39 045 670 2277",
    "wof:name":"Banca Di Roma",
    "wof:placetype":"venue"
},
  "geometry": {"coordinates":[10.845771,45.471054],"type":"Point"}
}