{
  "type": "Feature",
  "properties": {
    "iso:country":"IT",
    "sg:address":"24043 Caravaggio",
    "sg:city":"Caravaggio",
    "sg:classifiers":[
        {
            "category":"Organizations",
            "subcategory":"Labor Organization",
            "type":"Services"
        }
    ],
    "sg:phone":"+39 036 335 0380",
    "sg:postcode":"24043",
    "sg:province":"Bergamo",
    "sg:tags":[
        "packaging",
        "equipment",
        "packing",
        "system"
    ],
    "sg:website":"http://www.fllipozzi.it",
    "wof:name":"Pozzi Fratelli Srl",
    "wof:placetype":"venue"
},
  "geometry": {"coordinates":[9.6537857056,45.5050239563],"type":"Point"}
}