{
  "type": "Feature",
  "properties": {
    "addr:full":"20080 Carpiano Carpiano Milano 20080",
    "addr:postcode":"20080;20080",
    "iso:country":"IT",
    "sg:address":"20080 Carpiano",
    "sg:city":"Carpiano",
    "sg:classifiers":[
        {
            "category":"Manufacturing",
            "subcategory":"Metals",
            "type":"Manufacturing & Wholesale Goods"
        }
    ],
    "sg:phone":"+39 02 985 0951",
    "sg:postcode":"20080",
    "sg:province":"Milano",
    "sg:tags":[
        "forming",
        "working",
        "welding"
    ],
    "sg:website":"http://www.officineorsi.it",
    "wof:name":"Officine Orsi Spa",
    "wof:placetype":"venue"
},
  "geometry": {"coordinates":[9.2820711136,45.3472518921],"type":"Point"}
}