{
  "type": "Feature",
  "properties": {
    "iso:country":"IT",
    "sg:address":"18100 Imperia",
    "sg:city":"Imperia",
    "sg:orig_category":"Macchine Ed Impianti Per Edilizia E Lavori Pubblici",
    "sg:phone":"+39 0183 764150",
    "sg:postcode":"18100",
    "sg:province":"Imperia",
    "wof:name":"Bodino Corrado",
    "wof:placetype":"venue"
},
  "geometry": {"coordinates":[8.033062,43.892994],"type":"Point"}
}