{
  "type": "Feature",
  "properties": {
    "iso:country":"IT",
    "sg:address":"56, Via Jesina 60022 Castelfidardo",
    "sg:city":"Castelfidardo",
    "sg:classifiers":[
        {
            "category":"Shopping",
            "subcategory":"Computers & Home Electronics",
            "type":"Retail Goods"
        }
    ],
    "sg:phone":"+39 390 717 2041",
    "sg:postcode":"60022",
    "sg:province":"Ancona",
    "sg:tags":[
        "electronic",
        "electrical",
        "equipment"
    ],
    "wof:name":"Fime S.p.a.",
    "wof:placetype":"venue"
},
  "geometry": {"coordinates":[13.537025,43.449814],"type":"Point"}
}