{
  "type": "Feature",
  "properties": {
    "addr:full":"00044 Frascati Frascati Roma 00044",
    "addr:postcode":"00044;00044",
    "iso:country":"IT",
    "sg:address":"00044 Frascati",
    "sg:city":"Frascati",
    "sg:orig_category":"Servizi Culturali E Per Lo Spettacolo",
    "sg:phone":"+39 06 942 0193",
    "sg:postcode":"00044",
    "sg:province":"Roma",
    "wof:name":"Supercinema",
    "wof:placetype":"venue"
},
  "geometry": {"coordinates":[12.680594,41.808304],"type":"Point"}
}