{
  "type": "Feature",
  "properties": {
    "addr:full":"48018 Faenza Faenza Ravenna 48018",
    "addr:postcode":"48018;48018",
    "iso:country":"IT",
    "sg:address":"48018 Faenza",
    "sg:city":"Faenza",
    "sg:orig_category":"Scuole E Servizi Scolastici",
    "sg:phone":"+39 0546 681481",
    "sg:postcode":"48018",
    "sg:province":"Ravenna",
    "wof:name":"Collegio Santa Umilta'",
    "wof:placetype":"venue"
},
  "geometry": {"coordinates":[11.881032,44.282593],"type":"Point"}
}