{
  "type": "Feature",
  "properties": {
    "iso:country":"IT",
    "sg:address":"Contrada Grignano 83031 Ariano Irpino",
    "sg:city":"Ariano Irpino",
    "sg:classifiers":[
        {
            "category":"Manufacturing",
            "subcategory":"Rubber & Plastics",
            "type":"Manufacturing & Wholesale Goods"
        }
    ],
    "sg:phone":"+39 0825 892058",
    "sg:postcode":"83031",
    "sg:province":"Avellino",
    "wof:name":"Deltaplast Spa",
    "wof:placetype":"venue"
},
  "geometry": {"coordinates":[15.0823192596,41.121723175],"type":"Point"}
}