{
  "type": "Feature",
  "properties": {
    "addr:full":"91026 Mazara Del Vallo Mazara del Vallo Trapani 91026",
    "addr:postcode":"91026;91026",
    "iso:country":"IT",
    "sg:address":"91026 Mazara Del Vallo",
    "sg:city":"Mazara del Vallo",
    "sg:orig_category":"Nautica - Equipaggiamenti",
    "sg:phone":"+39 0923 942581",
    "sg:postcode":"91026",
    "sg:province":"Trapani",
    "wof:name":"Telepesca Srl",
    "wof:placetype":"venue"
},
  "geometry": {"coordinates":[12.585284,37.654217],"type":"Point"}
}