{
  "type": "Feature",
  "properties": {
    "addr:full":"Via Della Fratta 2 40136 Bologna Bologna Bologna 40136",
    "addr:housenumber":"2",
    "addr:postcode":"40136;40136",
    "addr:street":"Via Della Fratta",
    "iso:country":"IT",
    "sg:address":"Via Della Fratta 2 40136 Bologna",
    "sg:city":"Bologna",
    "sg:classifiers":[
        {
            "category":"Food & Beverages",
            "subcategory":"Fruits & Vegetables",
            "type":"Retail Goods"
        }
    ],
    "sg:phone":"+39 051 331520",
    "sg:postcode":"40136",
    "sg:province":"Bologna",
    "sg:tags":[
        "processing",
        "machinery"
    ],
    "wof:name":"Kriotecnica Srl",
    "wof:placetype":"venue"
},
  "geometry": {"coordinates":[11.6568784714,44.9779129028],"type":"Point"}
}