{
  "type": "Feature",
  "properties": {
    "iso:country":"IT",
    "sg:address":"13856 Vigliano Biellese",
    "sg:city":"Vigliano Biellese",
    "sg:orig_category":"Servizi E Lavori Per Abbigliamento E Pelletterie",
    "sg:phone":"+39 015 513216",
    "sg:postcode":"13856",
    "sg:province":"Biella",
    "wof:name":"Artfil",
    "wof:placetype":"venue"
},
  "geometry": {"coordinates":[8.109101,45.56443],"type":"Point"}
}