{
  "type": "Feature",
  "properties": {
    "iso:country":"IT",
    "sg:address":"115, Via Umberto 95129 Catania",
    "sg:city":"Catania",
    "sg:classifiers":[
        {
            "category":"Shopping",
            "subcategory":"Clothing, Apparel, & Fashions",
            "type":"Retail Goods"
        }
    ],
    "sg:phone":"+39 39095327473",
    "sg:postcode":"95129",
    "sg:province":"Catania",
    "sg:tags":[
        "clothes"
    ],
    "wof:name":"Calabro' (s.r.l.)",
    "wof:placetype":"venue"
},
  "geometry": {"coordinates":[15.089238,37.511467],"type":"Point"}
}