{
  "type": "Feature",
  "properties": {
    "addr:full":"V. Regione Piemonte Pozzolo Formigaro Alessandria 15068",
    "addr:postcode":"15068",
    "addr:street":"Regione Piemonte",
    "iso:country":"IT",
    "sg:address":"V. Regione Piemonte",
    "sg:city":"Pozzolo Formigaro",
    "sg:classifiers":[
        {
            "category":"Home & Garden",
            "subcategory":"Home Furnishings",
            "type":"Retail Goods"
        }
    ],
    "sg:phone":"+39 0143 318500",
    "sg:postcode":"15068",
    "sg:province":"Alessandria",
    "sg:tags":[
        "household"
    ],
    "sg:website":"http://www.garlando.it:ws_end: :mark:ws:http://www.paginegialle.it/garlando-01",
    "wof:name":"Garlando Srl",
    "wof:placetype":"venue"
},
  "geometry": {"coordinates":[8.616951,44.913216],"type":"Point"}
}