{
  "type": "Feature",
  "properties": {
    "iso:country":"IT",
    "sg:address":"00122 Roma",
    "sg:city":"Roma",
    "sg:orig_category":"Telecomunicazioni E Telefonia, Impianti, Apparecchi E Servizi",
    "sg:phone":"+39 06 562 3693",
    "sg:postcode":"00122",
    "sg:province":"Roma",
    "wof:name":"Baraldi Maurizio",
    "wof:placetype":"venue"
},
  "geometry": {"coordinates":[12.289524,41.727089],"type":"Point"}
}