{
  "type": "Feature",
  "properties": {
    "iso:country":"IT",
    "sg:address":"Via Calzolai 55040 Capezzano Pianore",
    "sg:classifiers":[
        {
            "category":"Sports & Exercise",
            "subcategory":"Skate Park",
            "type":"Entertainment"
        }
    ],
    "sg:phone":"+39 0584 969436",
    "sg:postcode":"55040",
    "sg:province":"Lucca",
    "sg:tags":[
        "mushroom"
    ],
    "sg:website":"www.versilfungo.com",
    "wof:name":"Versilfungo 2 Srl",
    "wof:placetype":"venue"
},
  "geometry": {"coordinates":[10.2607927322,43.9018211365],"type":"Point"}
}