{
  "type": "Feature",
  "properties": {
    "iso:country":"IT",
    "sg:address":"20063 Cernusco Sul Naviglio",
    "sg:city":"Cernusco sul Naviglio",
    "sg:orig_category":"Petroli, Gas E Combustibili. Servizi E Lavori Industria Chimica. Servizi E Lavori Per Edilizia E Lavori Pubblici. Acqua, Luce, Gas E Societa' Di Esercizio Pubblico",
    "sg:phone":"+39 02 9210 6616",
    "sg:postcode":"20063",
    "sg:province":"Milano",
    "wof:name":"Edigas Esercizio Distribuzione Gas S.r.l.",
    "wof:placetype":"venue"
},
  "geometry": {"coordinates":[9.2789735794,45.5320510864],"type":"Point"}
}