{
  "type": "Feature",
  "properties": {
    "addr:full":"00155 Roma Roma Roma 00155",
    "addr:postcode":"00155;00155",
    "iso:country":"IT",
    "sg:address":"00155 Roma",
    "sg:city":"Roma",
    "sg:orig_category":"Scuole E Servizi Scolastici",
    "sg:phone":"+39 06 4080 0579",
    "sg:postcode":"00155",
    "sg:province":"Roma",
    "wof:name":"Tredicesimo Distretto Scolastico",
    "wof:placetype":"venue"
},
  "geometry": {"coordinates":[12.572933,41.917019],"type":"Point"}
}