{
  "type": "Feature",
  "properties": {
    "iso:country":"IT",
    "sg:address":"Piazza Minzoni 2; Dolcedo; 81024",
    "sg:classifiers":[
        {
            "category":"Banks & Credit Unions",
            "subcategory":"Bank",
            "type":"Services"
        }
    ],
    "sg:phone":"+39 0183 280074",
    "sg:postcode":"81024",
    "sg:province":"Caserta",
    "wof:name":"Banca Carige Spa",
    "wof:placetype":"venue"
},
  "geometry": {"coordinates":[14.39083,41.023216],"type":"Point"}
}