{
  "type": "Feature",
  "properties": {
    "iso:country":"IT",
    "sg:address":"9, Piazza Dott. Weiser 39018 Terlano",
    "sg:city":"Terlano",
    "sg:classifiers":[
        {
            "category":"Banks & Credit Unions",
            "subcategory":"Bank",
            "type":"Services"
        }
    ],
    "sg:phone":"+39 0471 257730",
    "sg:postcode":"39018",
    "sg:province":"Bolzano/Bozen",
    "sg:tags":[
        "banking",
        "institution"
    ],
    "wof:name":"Cassa Rurale Di Terlano",
    "wof:placetype":"venue"
},
  "geometry": {"coordinates":[11.358005,46.496716],"type":"Point"}
}