{
  "type": "Feature",
  "properties": {
    "iso:country":"IT",
    "sg:address":"27100 Pavia",
    "sg:city":"Pavia",
    "sg:orig_category":"Studi E Consulenze Amministrative, Commerciali E Aziendali. Consulenze Tecniche, Amministrative E Perizie",
    "sg:phone":"+39 0382 530802",
    "sg:postcode":"27100",
    "sg:province":"Pavia",
    "wof:name":"Doc Dottori Commercialisti Associati",
    "wof:placetype":"venue"
},
  "geometry": {"coordinates":[9.080951,45.253139],"type":"Point"}
}