{
  "type": "Feature",
  "properties": {
    "iso:country":"IT",
    "sg:address":"70014 Conversano",
    "sg:city":"Conversano",
    "sg:orig_category":"Campeggio. Accessori Dei Mezzi Di Trasporto",
    "sg:phone":"+39 080 495 4252",
    "sg:postcode":"70014",
    "sg:province":"Bari",
    "wof:name":"Teloni Di Maggio Di Di Maggio & C. Snc",
    "wof:placetype":"venue"
},
  "geometry": {"coordinates":[17.139454,41.038151],"type":"Point"}
}