{
  "type": "Feature",
  "properties": {
    "iso:country":"IT",
    "sg:address":"7, Via Gio Batta Del Negro 33037 Pasian Di Prato",
    "sg:city":"Pasian di Prato",
    "sg:classifiers":[
        {
            "category":"Manufacturing",
            "subcategory":"Tools & Machinery",
            "type":"Manufacturing & Wholesale Goods"
        }
    ],
    "sg:phone":"+39 0432 690430",
    "sg:postcode":"33037",
    "sg:province":"Udine",
    "sg:tags":[
        "environment",
        "equipment",
        "-"
    ],
    "wof:name":"Larla S.r.l.",
    "wof:placetype":"venue"
},
  "geometry": {"coordinates":[13.230724,46.064941],"type":"Point"}
}