{
  "type": "Feature",
  "properties": {
    "addr:full":"Via Marconi Lotto 7 24036 Ponte San Pietro Ponte San Pietro Bergamo 24036",
    "addr:housenumber":"7",
    "addr:postcode":"24036;24036",
    "addr:street":"Via",
    "iso:country":"IT",
    "sg:address":"Via Marconi Lotto 7 24036 Ponte San Pietro",
    "sg:city":"Ponte San Pietro",
    "sg:classifiers":[
        {
            "category":"Government",
            "subcategory":"Court House",
            "type":"Public Place"
        }
    ],
    "sg:phone":"+39 035 460222",
    "sg:postcode":"24036",
    "sg:province":"Bergamo",
    "sg:tags":[
        "filling",
        "sterile",
        "plant"
    ],
    "sg:website":"www.tekmi.it",
    "wof:name":"Tekmi S.r.l.",
    "wof:placetype":"venue"
},
  "geometry": {"coordinates":[9.669952,45.694904],"type":"Point"}
}