{
  "type": "Feature",
  "properties": {
    "iso:country":"IT",
    "sg:address":"06132 San Sisto",
    "sg:orig_category":"Macchine, Impianti E Forniture Per Industria Grafica, Cartaria E Cartotecnica",
    "sg:phone":"+39 075 529 2032",
    "sg:postcode":"06132",
    "sg:province":"Perugia",
    "wof:name":"Brozzi Snc Di Mauro Rodolfo E Stefano Aurelio Brozzi",
    "wof:placetype":"venue"
},
  "geometry": {"coordinates":[12.329194,43.069931],"type":"Point"}
}