{
  "type": "Feature",
  "properties": {
    "iso:country":"IT",
    "sg:address":"23815 Introbio",
    "sg:city":"Introbio",
    "sg:orig_category":"Servizi Per Lo Sport E Il Tempo Libero. Alberghi E Strutture Extra Alberghiere",
    "sg:phone":"+39 0341 980766",
    "sg:postcode":"23815",
    "sg:province":"Lecco",
    "wof:name":"Buzzoni Mauro",
    "wof:placetype":"venue"
},
  "geometry": {"coordinates":[9.453109,45.976231],"type":"Point"}
}