{
  "type": "Feature",
  "properties": {
    "addr:full":"60022 Castelfidardo Castelfidardo Ancona 60022",
    "addr:postcode":"60022;60022",
    "iso:country":"IT",
    "sg:address":"60022 Castelfidardo",
    "sg:city":"Castelfidardo",
    "sg:classifiers":[
        {
            "category":"Education",
            "subcategory":"Music School",
            "type":"Public Place"
        }
    ],
    "sg:phone":"+39 071 782 0982",
    "sg:postcode":"60022",
    "sg:province":"Ancona",
    "sg:website":"http://accordions.com/excelsior",
    "wof:name":"Cemex Srl",
    "wof:placetype":"venue"
},
  "geometry": {"coordinates":[13.5494918823,43.4789466858],"type":"Point"}
}