{
  "type": "Feature",
  "properties": {
    "addr:full":"05018 Orvieto Orvieto Terni 05018",
    "addr:postcode":"05018;05018",
    "iso:country":"IT",
    "sg:address":"05018 Orvieto",
    "sg:city":"Orvieto",
    "sg:orig_category":"Apparecchiature Elettroniche",
    "sg:phone":"+39 0763 342852",
    "sg:postcode":"05018",
    "sg:province":"Terni",
    "wof:name":"Orel Snc",
    "wof:placetype":"venue"
},
  "geometry": {"coordinates":[12.07962,42.740417],"type":"Point"}
}