{
  "type": "Feature",
  "properties": {
    "addr:full":"87018 San Marco Argentano San Marco Argentano Cosenza 87018",
    "addr:housenumber":"87018",
    "addr:postcode":"argentano;argentano;87018",
    "addr:street":"San Marco",
    "iso:country":"IT",
    "sg:address":"87018 San Marco Argentano",
    "sg:city":"San Marco Argentano",
    "sg:orig_category":"Prodotti Di Base E Forniture Per Industria Alimentare E Bevande. Carta, Cartone E Prodotti Primari. Forniture Per Attivita' Commerciali Ed Artigianali",
    "sg:phone":"+39 0984 522482",
    "sg:postcode":"87018",
    "sg:province":"Cosenza",
    "sg:website":"http://www.ottimo.net",
    "wof:name":"Ca.dis. Srl",
    "wof:placetype":"venue"
},
  "geometry": {"coordinates":[16.1698570251,39.5862388611],"type":"Point"}
}