{
  "type": "Feature",
  "properties": {
    "addr:full":"55049 Viareggio Viareggio Lucca 55049",
    "addr:postcode":"55049;55049",
    "iso:country":"IT",
    "sg:address":"55049 Viareggio",
    "sg:city":"Viareggio",
    "sg:orig_category":"Filatelia",
    "sg:phone":"+39 0584 47001",
    "sg:postcode":"55049",
    "sg:province":"Lucca",
    "wof:name":"Flora Karla Johanna - Monete Francobolli",
    "wof:placetype":"venue"
},
  "geometry": {"coordinates":[10.2473106384,43.8723564148],"type":"Point"}
}