{
  "type": "Feature",
  "properties": {
    "iso:country":"IT",
    "sg:address":"18016 Diano Marina",
    "sg:orig_category":"Gastronomie, Salumerie E Rosticcerie",
    "sg:phone":"+39 0183 497722",
    "sg:postcode":"18016",
    "sg:province":"Imperia",
    "wof:name":"Pescheria Azzurra Gastronomia/prodotti Tipici Regionali",
    "wof:placetype":"venue"
},
  "geometry": {"coordinates":[8.084098,43.910118],"type":"Point"}
}