{
  "type": "Feature",
  "properties": {
    "iso:country":"IT",
    "sg:address":"Via Caduti Per La Libert\u00e0 14 40057 Quarto Inferiore",
    "sg:city":"Quarto Inferiore",
    "sg:classifiers":[
        {
            "category":"Professional",
            "subcategory":"Engineering",
            "type":"Services"
        }
    ],
    "sg:phone":"+39 051 767195",
    "sg:postcode":"40057",
    "sg:province":"Bologna",
    "sg:tags":[
        "road",
        "surfacing",
        "asphalt",
        "highway"
    ],
    "wof:name":"C.i.s.e. - Costruzioni Idrauliche Stradali Edilizie Srl",
    "wof:placetype":"venue"
},
  "geometry": {"coordinates":[11.346481,44.494221],"type":"Point"}
}