{
  "type": "Feature",
  "properties": {
    "addr:full":"37057 Pozzo Verona 37057",
    "addr:postcode":"37057;37057",
    "iso:country":"IT",
    "sg:address":"37057 Pozzo",
    "sg:orig_category":"Macchine, Impianti Ed Attrezzature Per Agricoltura E Zootecnia. Macchine, Impianti Ed Attrezzature Industria Chimica. Macchine Utensili E Impianti",
    "sg:phone":"+39 045 875 0222",
    "sg:postcode":"37057",
    "sg:province":"Verona",
    "wof:name":"Ver.ma (s.p.a.)",
    "wof:placetype":"venue"
},
  "geometry": {"coordinates":[11.02931,45.377617],"type":"Point"}
}