{
  "type": "Feature",
  "properties": {
    "addr:full":"5, Via Milano 22070 Appiano Gentile Appiano Gentile Como 22070",
    "addr:housenumber":"gentile",
    "addr:postcode":"22070;22070",
    "addr:street":"Via Milano",
    "iso:country":"IT",
    "sg:address":"5, Via Milano 22070 Appiano Gentile",
    "sg:city":"Appiano Gentile",
    "sg:classifiers":[
        {
            "category":"Shopping",
            "subcategory":"Crafts & Fabrics",
            "type":"Retail Goods"
        }
    ],
    "sg:phone":"+39 39031890990",
    "sg:postcode":"22070",
    "sg:province":"Como",
    "wof:name":"Stamperia Nuove Iniziative (s.r.l.)",
    "wof:placetype":"venue"
},
  "geometry": {"coordinates":[9.0318613052,45.7634963989],"type":"Point"}
}