{
  "type": "Feature",
  "properties": {
    "addr:full":"Via Cavour Camillo 15 50129 Firenze Firenze Firenze 50129",
    "addr:housenumber":"15",
    "addr:postcode":"50129;50129",
    "addr:street":"Via Cavour Camillo",
    "iso:country":"IT",
    "sg:address":"Via Cavour Camillo 15 50129 Firenze",
    "sg:city":"Firenze",
    "sg:classifiers":[
        {
            "category":"Communications",
            "type":"Services"
        }
    ],
    "sg:phone":"+39 055 265 8133",
    "sg:postcode":"50129",
    "sg:province":"Firenze",
    "sg:tags":[
        "translation"
    ],
    "sg:website":"www.gmt-ils.it",
    "wof:name":"Global Multilingual Translations",
    "wof:placetype":"venue"
},
  "geometry": {"coordinates":[11.255646,43.775543],"type":"Point"}
}