{
  "type": "Feature",
  "properties": {
    "iso:country":"IT",
    "sg:address":"27, Via Roma 10085 Pont Canavese",
    "sg:classifiers":[
        {
            "category":"Professional",
            "subcategory":"Engineering",
            "type":"Services"
        }
    ],
    "sg:phone":"+39 39012484158",
    "sg:postcode":"10085",
    "sg:province":"Torino",
    "sg:tags":[
        "machine",
        "-",
        "mechanical"
    ],
    "wof:name":"Fasana Giuseppe Di Fasana G. E C. (s.n.c.)",
    "wof:placetype":"venue"
},
  "geometry": {"coordinates":[7.601415,45.421509],"type":"Point"}
}