{
  "type": "Feature",
  "properties": {
    "iso:country":"IT",
    "sg:address":"10136 Torino",
    "sg:city":"Torino",
    "sg:orig_category":"Pubblica Amministrazione",
    "sg:phone":"+39 011 319 9905",
    "sg:postcode":"10136",
    "sg:province":"Torino",
    "wof:name":"Forze Armate/esercito/caserma Montegrappa",
    "wof:placetype":"venue"
},
  "geometry": {"coordinates":[7.6402754784,45.0509681702],"type":"Point"}
}