{
  "type": "Feature",
  "properties": {
    "iso:country":"IT",
    "sg:address":"90139 Palermo",
    "sg:city":"Palermo",
    "sg:orig_category":"Professionisti - Studi E Servizi Ed Associazioni Di Interesse Aziendale. Servizi Sociali. Associazioni Ed Organismi Di Interesse Pubblico",
    "sg:phone":"+39 091 587373",
    "sg:postcode":"90139",
    "sg:province":"Palermo",
    "wof:name":"Ipsema - Istituto Di Previdenza Per Il Settore Marittimo",
    "wof:placetype":"venue"
},
  "geometry": {"coordinates":[13.3634233475,38.1242103577],"type":"Point"}
}