{
  "type": "Feature",
  "properties": {
    "addr:full":"29, Via Europa 25040 Monticelli Brusati Monticelli Brusati Brescia 25040",
    "addr:postcode":"25040;brusati;25040",
    "addr:street":"Via Europa;Brescia",
    "iso:country":"IT",
    "sg:address":"29, Via Europa 25040 Monticelli Brusati",
    "sg:city":"Monticelli Brusati",
    "sg:classifiers":[
        {
            "category":"Shopping",
            "subcategory":"Computers & Home Electronics",
            "type":"Retail Goods"
        }
    ],
    "sg:phone":"+39 39030653100",
    "sg:postcode":"25040",
    "sg:province":"Brescia",
    "sg:tags":[
        "electronic",
        "electrical",
        "equipment"
    ],
    "wof:name":"Elettromeccanica Valotti (s.r.l.)",
    "wof:placetype":"venue"
},
  "geometry": {"coordinates":[10.082948,45.625343],"type":"Point"}
}