{
  "type": "Feature",
  "properties": {
    "iso:country":"IT",
    "sg:address":"88100 Catanzaro",
    "sg:city":"Catanzaro",
    "sg:orig_category":"Servizi Per Aziende, Manifestazioni E Supporto Agli Scambi Commerciali",
    "sg:phone":"+39 0961 725432",
    "sg:postcode":"88100",
    "sg:province":"Catanzaro",
    "wof:name":"F.b.i. Investigations Di Ciro Boccuzzi",
    "wof:placetype":"venue"
},
  "geometry": {"coordinates":[16.592739,38.907043],"type":"Point"}
}