{
  "type": "Feature",
  "properties": {
    "addr:full":"Via Barenghi 49 27058 Voghera Voghera Pavia 27058",
    "addr:housenumber":"49",
    "addr:postcode":"27058;27058",
    "addr:street":"Via Barenghi",
    "iso:country":"IT",
    "sg:address":"Via Barenghi 49 27058 Voghera",
    "sg:city":"Voghera",
    "sg:classifiers":[
        {
            "category":"Food & Beverages",
            "subcategory":"Fruits & Vegetables",
            "type":"Retail Goods"
        }
    ],
    "sg:phone":"+39 0383 44875",
    "sg:postcode":"27058",
    "sg:province":"Pavia",
    "sg:tags":[
        "machine",
        "processing",
        "complete",
        "systems"
    ],
    "wof:name":"Varzifrutta Sas Di Lazzati Peppino",
    "wof:placetype":"venue"
},
  "geometry": {"coordinates":[9.0154418945,44.9938812256],"type":"Point"}
}