{
  "type": "Feature",
  "properties": {
    "addr:full":"06061 Castiglione Del Lago Castiglione del Lago Perugia 06061",
    "addr:postcode":"06061;06061",
    "iso:country":"IT",
    "sg:address":"06061 Castiglione Del Lago",
    "sg:city":"Castiglione del Lago",
    "sg:orig_category":"Pubblicita', Marketing E Comunicazione",
    "sg:phone":"+39 075 965 3055",
    "sg:postcode":"06061",
    "sg:province":"Perugia",
    "wof:name":"Elesystem Di Righetti Luciana",
    "wof:placetype":"venue"
},
  "geometry": {"coordinates":[12.0466003418,43.1254806519],"type":"Point"}
}