{
  "type": "Feature",
  "properties": {
    "iso:country":"IT",
    "sg:address":"73055 Racale",
    "sg:city":"Racale",
    "sg:orig_category":"Articoli Medico-sanitari Ed Ortopedici",
    "sg:phone":"+39 0833 584380",
    "sg:postcode":"73055",
    "sg:province":"Lecce",
    "sg:website":"http://www.delorenzis.it",
    "wof:name":"Salvatore De Lorenzis",
    "wof:placetype":"venue"
},
  "geometry": {"coordinates":[18.065794,39.964466],"type":"Point"}
}