{
  "type": "Feature",
  "properties": {
    "addr:full":"Via Lorenzini Giovanni 4 20139 Milano Milano Milano 20139",
    "addr:housenumber":"4",
    "addr:postcode":"20139;20139",
    "addr:street":"Via Lorenzini Giovanni",
    "iso:country":"IT",
    "sg:address":"Via Lorenzini Giovanni 4 20139 Milano",
    "sg:city":"Milano",
    "sg:classifiers":[
        {
            "category":"Manufacturing",
            "subcategory":"Chemicals & Compounds",
            "type":"Manufacturing & Wholesale Goods"
        }
    ],
    "sg:phone":"+39 02 535 7141",
    "sg:postcode":"20139",
    "sg:province":"Milano",
    "sg:tags":[
        "base"
    ],
    "wof:name":"B.c. - M.c. Srl",
    "wof:placetype":"venue"
},
  "geometry": {"coordinates":[9.200778,45.44371],"type":"Point"}
}