{
  "type": "Feature",
  "properties": {
    "addr:full":"12020 Sampeyre Sampeyre Cuneo 12020",
    "addr:housenumber":"12020",
    "addr:postcode":"12020",
    "addr:street":"Sampeyre Sampeyre",
    "iso:country":"IT",
    "sg:address":"12020 Sampeyre",
    "sg:city":"Sampeyre",
    "sg:orig_category":"Non-classified Establishments",
    "sg:phone":"+39 0175 977164",
    "sg:postcode":"12020",
    "sg:province":"Cuneo",
    "wof:name":"L'artigiano Del Rustico Di Boerio Giuseppe & C. S.n.c.",
    "wof:placetype":"venue"
},
  "geometry": {"coordinates":[7.5513000488,44.3929328918],"type":"Point"}
}