{
  "type": "Feature",
  "properties": {
    "iso:country":"IT",
    "sg:address":"223, Via Consolare Valeria Pistunina 98100 Messina",
    "sg:classifiers":[
        {
            "category":"Food & Beverages",
            "subcategory":"Groceries & Convenience Stores",
            "type":"Retail Goods"
        }
    ],
    "sg:phone":"+39 39090621339",
    "sg:province":"ME",
    "sg:tags":[
        "drink"
    ],
    "wof:name":"Inagrus (s.a.s.)",
    "wof:placetype":"venue"
},
  "geometry": {"coordinates":[15.535219,38.157558],"type":"Point"}
}