{
  "type": "Feature",
  "properties": {
    "iso:country":"IT",
    "sg:address":"34015 Muggia",
    "sg:city":"Muggia",
    "sg:orig_category":"Apparecchiature Ed Attrezzature Meccaniche",
    "sg:phone":"+39 040 231041",
    "sg:postcode":"34015",
    "sg:province":"Trieste",
    "wof:name":"Tecnogroup Srl",
    "wof:placetype":"venue"
},
  "geometry": {"coordinates":[13.803515,45.592384],"type":"Point"}
}