{
  "type": "Feature",
  "properties": {
    "iso:country":"IT",
    "sg:address":"95125 Catania",
    "sg:city":"Catania",
    "sg:orig_category":"Servizi E Lavori Per Abbigliamento E Pelletterie",
    "sg:phone":"+39 095 716 7542",
    "sg:postcode":"95125",
    "sg:province":"Catania",
    "wof:name":"Coop. Ancora Services",
    "wof:placetype":"venue"
},
  "geometry": {"coordinates":[15.079363,37.522503],"type":"Point"}
}