{
  "type": "Feature",
  "properties": {
    "iso:country":"IT",
    "sg:address":"20134 Milano",
    "sg:city":"Milano",
    "sg:orig_category":"Dischi, Audio E Videocassette, Compact Disc - Produzione E Ingrosso",
    "sg:phone":"+39 02 2641 4543",
    "sg:postcode":"20134",
    "sg:province":"Milano",
    "wof:name":"D.v.s. Dupli Video Sound Spa",
    "wof:placetype":"venue"
},
  "geometry": {"coordinates":[9.247256,45.48185],"type":"Point"}
}