{
  "type": "Feature",
  "properties": {
    "iso:country":"IT",
    "sg:address":"24060 Castelli Calepio",
    "sg:city":"Castelli Calepio",
    "sg:orig_category":"Prodotti Chimici Secondari. Prodotti Cosmetici E Da Toeletta",
    "sg:phone":"+39 035 847508",
    "sg:postcode":"24060",
    "sg:province":"Bergamo",
    "wof:name":"Nettuno Srl",
    "wof:placetype":"venue"
},
  "geometry": {"coordinates":[9.8916902542,45.6267852783],"type":"Point"}
}