{
  "type": "Feature",
  "properties": {
    "iso:country":"IT",
    "sg:address":"09028 Sestu",
    "sg:city":"Sestu",
    "sg:orig_category":"Campeggio. Accessori Dei Mezzi Di Trasporto",
    "sg:phone":"+39 070 22318",
    "sg:postcode":"09028",
    "sg:province":"Cagliari",
    "wof:name":"Balzano Luisa & C. Snc",
    "wof:placetype":"venue"
},
  "geometry": {"coordinates":[9.090287,39.306751],"type":"Point"}
}