{
  "type": "Feature",
  "properties": {
    "iso:country":"IT",
    "sg:address":"28, Via De Santis F. 73042 Casarano",
    "sg:city":"Casarano",
    "sg:classifiers":[
        {
            "category":"Personal",
            "subcategory":"Shoe Repair & Shine",
            "type":"Services"
        }
    ],
    "sg:phone":"+39 0833 505356",
    "sg:postcode":"73042",
    "sg:province":"Lecce",
    "sg:tags":[
        "leather"
    ],
    "wof:name":"Mark Shoes S.r.l.",
    "wof:placetype":"venue"
},
  "geometry": {"coordinates":[18.174015,40.353291],"type":"Point"}
}