{
  "type": "Feature",
  "properties": {
    "iso:country":"IT",
    "sg:address":"94013 Leonforte",
    "sg:city":"Leonforte",
    "sg:orig_category":"Servizi E Lavori Per Edilizia E Lavori Pubblici. Professionisti - Studi E Servizi Ed Associazioni Di Interesse Aziendale",
    "sg:phone":"+39 0935 902660",
    "sg:postcode":"94013",
    "sg:province":"Enna",
    "wof:name":"Prestifilippo Geom. Emilio",
    "wof:placetype":"venue"
},
  "geometry": {"coordinates":[14.390391,37.637596],"type":"Point"}
}