{
  "type": "Feature",
  "properties": {
    "iso:country":"IT",
    "sg:address":"09123 Cagliari",
    "sg:city":"Cagliari",
    "sg:classifiers":[
        {
            "category":"Health Services",
            "subcategory":"Health Practitioner",
            "type":"Services"
        }
    ],
    "sg:phone":"+39 070 663446",
    "sg:postcode":"09123",
    "sg:province":"Cagliari",
    "sg:tags":[
        "medici"
    ],
    "wof:name":"Corte Idimo",
    "wof:placetype":"venue"
},
  "geometry": {"coordinates":[9.102136,39.222931],"type":"Point"}
}