{
  "type": "Feature",
  "properties": {
    "addr:full":"72100 Brindisi Brindisi Brindisi 72100",
    "addr:postcode":"72100;72100",
    "iso:country":"IT",
    "sg:address":"72100 Brindisi",
    "sg:city":"Brindisi",
    "sg:orig_category":"Agenzie Marittime",
    "sg:phone":"+39 0831 568098",
    "sg:postcode":"72100",
    "sg:province":"Brindisi",
    "wof:name":"Adriatic Sea Travel",
    "wof:placetype":"venue"
},
  "geometry": {"coordinates":[17.993591,40.483829],"type":"Point"}
}