{
  "type": "Feature",
  "properties": {
    "addr:full":"Via Ermes; Udine; 33100 Udine Udine 33100",
    "addr:postcode":"33100;33100",
    "addr:street":"Via Ermes",
    "iso:country":"IT",
    "sg:address":"Via Ermes; Udine; 33100",
    "sg:city":"Udine",
    "sg:classifiers":[
        {
            "category":"Banks & Credit Unions",
            "subcategory":"Bank",
            "type":"Services"
        }
    ],
    "sg:phone":"+39 0432 545438",
    "sg:postcode":"33100",
    "sg:province":"Udine",
    "wof:name":"Cariverona Banca Spa",
    "wof:placetype":"venue"
},
  "geometry": {"coordinates":[13.232295,46.071632],"type":"Point"}
}