{
  "type": "Feature",
  "properties": {
    "iso:country":"IT",
    "sg:address":"Via Nazionale, 153; Mira; 30030",
    "sg:classifiers":[
        {
            "category":"Banks & Credit Unions",
            "subcategory":"Bank",
            "type":"Services"
        }
    ],
    "sg:phone":"+39 041 420522",
    "sg:postcode":"30030",
    "sg:province":"Venezia",
    "wof:name":"Banco San Marco",
    "wof:placetype":"venue"
},
  "geometry": {"coordinates":[12.12263,45.433586],"type":"Point"}
}