{
  "type": "Feature",
  "properties": {
    "iso:country":"IT",
    "sg:address":"27010 Cura Carpignano",
    "sg:city":"Cura Carpignano",
    "sg:orig_category":"Forniture Per Edilizia E Lavori Pubblici",
    "sg:phone":"+39 0382 483450",
    "sg:postcode":"27010",
    "sg:province":"Pavia",
    "wof:name":"R.t.a. (s.r.l.)",
    "wof:placetype":"venue"
},
  "geometry": {"coordinates":[9.2217006683,45.2075004578],"type":"Point"}
}