{
  "type": "Feature",
  "properties": {
    "addr:full":"25078 Vestone Vestone Brescia 25078",
    "addr:postcode":"25078;25078",
    "iso:country":"IT",
    "sg:address":"25078 Vestone",
    "sg:city":"Vestone",
    "sg:classifiers":[
        {
            "category":"Manufacturing",
            "subcategory":"Tools & Machinery",
            "type":"Manufacturing & Wholesale Goods"
        }
    ],
    "sg:phone":"+39 036 582 0859",
    "sg:postcode":"25078",
    "sg:province":"Brescia",
    "sg:tags":[
        "machining",
        "mechanical"
    ],
    "wof:name":"Necofer Di Cottali Maurizio & C.",
    "wof:placetype":"venue"
},
  "geometry": {"coordinates":[10.411237,45.708576],"type":"Point"}
}