{
  "type": "Feature",
  "properties": {
    "addr:full":"28053 Castelletto Ticino Novara 28053",
    "addr:postcode":"28053;28053",
    "addr:street":"Ticino",
    "iso:country":"IT",
    "sg:address":"28053 Castelletto Ticino",
    "sg:orig_category":"Campeggio. Automobili E Mezzi Di Trasporto",
    "sg:phone":"+39 0331 922545",
    "sg:postcode":"28053",
    "sg:province":"Novara",
    "sg:website":"http://www.caravancenter.it",
    "wof:name":"Caravan Center Di Lazzaro Severino & C. Sas",
    "wof:placetype":"venue"
},
  "geometry": {"coordinates":[8.603868,45.719456],"type":"Point"}
}