{
  "type": "Feature",
  "properties": {
    "addr:full":"65013 Citta' S.angelo Pescara 65013",
    "addr:postcode":"65013;65013",
    "iso:country":"IT",
    "sg:address":"65013 Citta' S.angelo",
    "sg:orig_category":"Animali Domestici - Allevamento E Addestramento",
    "sg:phone":"+39 337 669 277",
    "sg:postcode":"65013",
    "sg:province":"Pescara",
    "wof:name":"Ghindero's Di D'alonzo Carmine",
    "wof:placetype":"venue"
},
  "geometry": {"coordinates":[14.214094,42.464825],"type":"Point"}
}