{
  "type": "Feature",
  "properties": {
    "iso:country":"IT",
    "sg:address":"1, Via Saggese 80013 Casalnuovo Di Napoli",
    "sg:city":"Casalnuovo di Napoli",
    "sg:classifiers":[
        {
            "category":"Autos & Motor Vehicles",
            "subcategory":"Automobile Sales",
            "type":"Retail Goods"
        }
    ],
    "sg:phone":"+39 081 522 5252",
    "sg:postcode":"80013",
    "sg:province":"Napoli",
    "sg:tags":[
        "equipment",
        "transport"
    ],
    "wof:name":"Mecoser Spa",
    "wof:placetype":"venue"
},
  "geometry": {"coordinates":[14.333541,40.919868],"type":"Point"}
}