{
  "type": "Feature",
  "properties": {
    "addr:full":"64023 Mosciano Sant'angelo Teramo 64023",
    "addr:postcode":"64023;64023",
    "iso:country":"IT",
    "sg:address":"64023 Mosciano Sant'angelo",
    "sg:orig_category":"Forniture Per Abbigliamento E Pelletterie",
    "sg:phone":"+39 085 807 1807",
    "sg:postcode":"64023",
    "sg:province":"Teramo",
    "wof:name":"Di Remigio D. & Diodoro Donatella",
    "wof:placetype":"venue"
},
  "geometry": {"coordinates":[13.9055557251,42.7118415833],"type":"Point"}
}