{
  "type": "Feature",
  "properties": {
    "iso:country":"IT",
    "sg:address":"2, Via Dei Cestari 00186 Roma",
    "sg:city":"Roma",
    "sg:orig_category":"Miscellaneous Products",
    "sg:phone":"+39 39066790956",
    "sg:postcode":"00186",
    "sg:province":"Roma",
    "wof:name":"Statuaria Arte Sacra (s.n.c.)",
    "wof:placetype":"venue"
},
  "geometry": {"coordinates":[12.4773521423,41.8969573975],"type":"Point"}
}