{
  "type": "Feature",
  "properties": {
    "iso:country":"IT",
    "sg:address":"Corso Sempione 215; Legnano; 20025",
    "sg:city":"Legnano",
    "sg:classifiers":[
        {
            "category":"Banks & Credit Unions",
            "subcategory":"Bank",
            "type":"Services"
        }
    ],
    "sg:phone":"+39 0331 544005",
    "sg:postcode":"20025",
    "sg:province":"Milano",
    "wof:name":"Banco Ambrosiano Veneto Spa",
    "wof:placetype":"venue"
},
  "geometry": {"coordinates":[8.916053,45.601582],"type":"Point"}
}