{
  "type": "Feature",
  "properties": {
    "addr:full":"Piazza G.mazzini 5; Roma",
    "addr:housenumber":"5",
    "addr:street":"Piazza G.Mazzini",
    "iso:country":"IT",
    "sg:address":"Piazza G.mazzini 5; Roma",
    "sg:classifiers":[
        {
            "category":"Banks & Credit Unions",
            "subcategory":"Bank",
            "type":"Services"
        }
    ],
    "sg:phone":"+39 06 321 7941",
    "wof:name":"Banca Di Roma",
    "wof:placetype":"venue"
},
  "geometry": {"coordinates":[12.464227,41.915554],"type":"Point"}
}