{
  "type": "Feature",
  "properties": {
    "iso:country":"IT",
    "sg:address":"37, Via Romea 44022 Comacchio",
    "sg:city":"Comacchio",
    "sg:classifiers":[
        {
            "category":"Communications",
            "subcategory":"Newspaper",
            "type":"Services"
        }
    ],
    "sg:phone":"+39 0533 330616",
    "sg:postcode":"44022",
    "sg:province":"Ferrara",
    "sg:tags":[
        "advertising"
    ],
    "wof:name":"Industria Pubbligrafica Ferroni S.r.l.",
    "wof:placetype":"venue"
},
  "geometry": {"coordinates":[12.247256,44.59906],"type":"Point"}
}