{
  "type": "Feature",
  "properties": {
    "addr:full":"21, Via Sicilia 40024 Castel San Pietro Terme Castel San Pietro Terme Bologna 40024",
    "addr:postcode":"40024;40024",
    "addr:street":"Via Sicilia",
    "iso:country":"IT",
    "sg:address":"21, Via Sicilia 40024 Castel San Pietro Terme",
    "sg:city":"Castel San Pietro Terme",
    "sg:classifiers":[
        {
            "category":"Autos & Motor Vehicles",
            "subcategory":"Automobile Sales",
            "type":"Retail Goods"
        }
    ],
    "sg:phone":"+39 39051945000",
    "sg:postcode":"40024",
    "sg:province":"Bologna",
    "sg:tags":[
        "motor-cars"
    ],
    "wof:name":"Tecbo Srl",
    "wof:placetype":"venue"
},
  "geometry": {"coordinates":[11.5217199326,44.4332809448],"type":"Point"}
}