{
  "type": "Feature",
  "properties": {
    "addr:full":"40131 Bologna Bologna Bologna 40131",
    "addr:postcode":"40131;40131",
    "iso:country":"IT",
    "sg:address":"40131 Bologna",
    "sg:city":"Bologna",
    "sg:classifiers":[
        {
            "category":"Manufacturing",
            "subcategory":"Chemicals & Compounds",
            "type":"Manufacturing & Wholesale Goods"
        }
    ],
    "sg:phone":"+39 051 557548",
    "sg:postcode":"40131",
    "sg:province":"Bologna",
    "sg:tags":[
        "product",
        "chemicals",
        "basic"
    ],
    "wof:name":"A.d.i.c.a. Srl",
    "wof:placetype":"venue"
},
  "geometry": {"coordinates":[11.321144,44.501293],"type":"Point"}
}