{
  "type": "Feature",
  "properties": {
    "addr:full":"23861 Cesana Brianza Cesana Brianza Lecco 23861",
    "addr:postcode":"23861;brianza;23861",
    "iso:country":"IT",
    "sg:address":"23861 Cesana Brianza",
    "sg:city":"Cesana Brianza",
    "sg:orig_category":"Stampaggio Metalli A Caldo",
    "sg:phone":"+39 031 655936",
    "sg:postcode":"23861",
    "sg:province":"Lecco",
    "wof:name":"Evasi E Castelnuovo",
    "wof:placetype":"venue"
},
  "geometry": {"coordinates":[9.389861,45.85445],"type":"Point"}
}