{
  "type": "Feature",
  "properties": {
    "addr:full":"20010 Vittuone Vittuone Milano 20010",
    "addr:postcode":"20010;20010",
    "iso:country":"IT",
    "sg:address":"20010 Vittuone",
    "sg:city":"Vittuone",
    "sg:orig_category":"Macchine Utensili E Impianti. Apparecchiature Ed Attrezzature Meccaniche",
    "sg:phone":"+39 02 9011 1116",
    "sg:postcode":"20010",
    "sg:province":"Milano",
    "wof:name":"Finimac (s.r.l.)",
    "wof:placetype":"venue"
},
  "geometry": {"coordinates":[9.163152,45.447487],"type":"Point"}
}