{
  "type": "Feature",
  "properties": {
    "iso:country":"IT",
    "sg:address":"Corso Giulioo Cesare 56; Torino; 10152",
    "sg:city":"Torino",
    "sg:classifiers":[
        {
            "category":"Banks & Credit Unions",
            "subcategory":"Bank",
            "type":"Services"
        }
    ],
    "sg:phone":"+39 011 248 7848",
    "sg:postcode":"10152",
    "sg:province":"Torino",
    "wof:name":"Banca Sella Spa",
    "wof:placetype":"venue"
},
  "geometry": {"coordinates":[7.700304,45.103149],"type":"Point"}
}