{
  "type": "Feature",
  "properties": {
    "iso:country":"IT",
    "sg:address":"31100 Treviso",
    "sg:city":"Treviso",
    "sg:orig_category":"Macchine, Impianti Ed Attrezzature Per Industria Alimentare E Bevande",
    "sg:phone":"+39 0422 302615",
    "sg:postcode":"31100",
    "sg:province":"Treviso",
    "wof:name":"Lorenzon Giuseppe C.i.e. Srl",
    "wof:placetype":"venue"
},
  "geometry": {"coordinates":[12.168638,45.677132],"type":"Point"}
}