{
  "type": "Feature",
  "properties": {
    "addr:full":"10145 Torino Torino Torino 10145",
    "addr:housenumber":"10145",
    "addr:postcode":"10145",
    "iso:country":"IT",
    "sg:address":"10145 Torino",
    "sg:city":"Torino",
    "sg:orig_category":"Impianti, Attrezzature E Forniture Sanitarie Ed Ospedaliere. Macchine, Strumenti Ed Apparecchi Per Attivita' Industriali",
    "sg:phone":"+39 011 749 2003",
    "sg:postcode":"10145",
    "sg:province":"Torino",
    "wof:name":"Archimede Sas",
    "wof:placetype":"venue"
},
  "geometry": {"coordinates":[7.641165,45.080257],"type":"Point"}
}