{
  "type": "Feature",
  "properties": {
    "addr:full":"Zona Ind. S. Nicola Di Melfi 85025 Melfi Melfi Potenza 85025",
    "addr:postcode":"85025;85025",
    "addr:street":"Zona Ind. S. Nicola Di Melfi",
    "iso:country":"IT",
    "sg:address":"Zona Ind. S. Nicola Di Melfi 85025 Melfi",
    "sg:city":"Melfi",
    "sg:classifiers":[
        {
            "category":"Wholesale",
            "subcategory":"Machinery & Supplies",
            "type":"Manufacturing & Wholesale Goods"
        }
    ],
    "sg:phone":"+39 39097278032",
    "sg:postcode":"85025",
    "sg:province":"Potenza",
    "sg:tags":[
        "-",
        "agriculture",
        "equipment"
    ],
    "wof:name":"O.m.p. Pettorruso & C. S.r.l",
    "wof:placetype":"venue"
},
  "geometry": {"coordinates":[15.802221,40.637241],"type":"Point"}
}