{
  "type": "Feature",
  "properties": {
    "iso:country":"IT",
    "sg:address":"Via Lazio 1; Salaparuta; 91020",
    "sg:city":"Salaparuta",
    "sg:classifiers":[
        {
            "category":"Banks & Credit Unions",
            "subcategory":"Bank",
            "type":"Services"
        }
    ],
    "sg:phone":"+39 0924 75733",
    "sg:postcode":"91020",
    "sg:province":"Trapani",
    "wof:name":"Banco Di Sicilia Spa",
    "wof:placetype":"venue"
},
  "geometry": {"coordinates":[13.010774,37.759033],"type":"Point"}
}