{
  "type": "Feature",
  "properties": {
    "iso:country":"IT",
    "sg:address":"50123 Firenze",
    "sg:city":"Firenze",
    "sg:orig_category":"Pubblica Amministrazione",
    "sg:phone":"+39 055 284550",
    "sg:postcode":"50123",
    "sg:province":"Firenze",
    "wof:name":"Guardia Di Finanza - Comando Regionale Toscana",
    "wof:placetype":"venue"
},
  "geometry": {"coordinates":[11.2482442856,43.7796058655],"type":"Point"}
}