{
  "type": "Feature",
  "properties": {
    "iso:country":"IT",
    "sg:address":"1, Via Al Pascolo 23842 Bosisio Parini",
    "sg:city":"Bosisio Parini",
    "sg:classifiers":[
        {
            "category":"Professional",
            "subcategory":"Printing & Photocopies",
            "type":"Services"
        }
    ],
    "sg:phone":"+39 39031866900",
    "sg:postcode":"23842",
    "sg:province":"Lecco",
    "wof:name":"Fram S.a.s. Di Mario Rigamonti & C.",
    "wof:placetype":"venue"
},
  "geometry": {"coordinates":[9.3900709152,45.8529815674],"type":"Point"}
}