{
  "type": "Feature",
  "properties": {
    "iso:country":"IT",
    "sg:address":"16124 Genova",
    "sg:city":"Genova",
    "sg:orig_category":"Apparecchiature E Sistemi Per Imballaggio E Confezionamento. Apparecchiature E Sistemi Per Magazzinaggio E Movimentazione",
    "sg:phone":"+39 010 235971",
    "sg:postcode":"16124",
    "sg:province":"Genova",
    "wof:name":"Interconsult Srl",
    "wof:placetype":"venue"
},
  "geometry": {"coordinates":[8.928475,44.411766],"type":"Point"}
}