{
  "type": "Feature",
  "properties": {
    "iso:country":"IT",
    "sg:address":"10081 Castellamonte",
    "sg:city":"Castellamonte",
    "sg:orig_category":"Stufe",
    "sg:phone":"+39 0124 581560",
    "sg:postcode":"10081",
    "sg:province":"Torino",
    "wof:name":"Ceramica Castellamonte Di Giampietro Elisa",
    "wof:placetype":"venue"
},
  "geometry": {"coordinates":[7.710948,45.382961],"type":"Point"}
}