{
  "type": "Feature",
  "properties": {
    "addr:full":"Piazza 24 Maggio 1; Romano Di Lombardia; 24058 Romano di Lombardia Bergamo 24058",
    "addr:housenumber":"1",
    "addr:postcode":"24058;24058",
    "addr:street":"Piazza 24 Maggio",
    "iso:country":"IT",
    "sg:address":"Piazza 24 Maggio 1; Romano Di Lombardia; 24058",
    "sg:city":"Romano di Lombardia",
    "sg:classifiers":[
        {
            "category":"Banks & Credit Unions",
            "subcategory":"Bank",
            "type":"Services"
        }
    ],
    "sg:phone":"+39 036 391 2444",
    "sg:postcode":"24058",
    "sg:province":"Bergamo",
    "wof:name":"Cassa Di Risparmio, Delle Provincie Lombarde Spa",
    "wof:placetype":"venue"
},
  "geometry": {"coordinates":[9.753812,45.519615],"type":"Point"}
}