{
  "type": "Feature",
  "properties": {
    "iso:country":"IT",
    "sg:address":"00142 Roma",
    "sg:city":"Roma",
    "sg:orig_category":"Prodotti Alimentari",
    "sg:phone":"+39 06 503 1380",
    "sg:postcode":"00142",
    "sg:province":"Roma",
    "wof:name":"Furi Mauro",
    "wof:placetype":"venue"
},
  "geometry": {"coordinates":[12.4881982803,41.8296051025],"type":"Point"}
}