{
  "type": "Feature",
  "properties": {
    "iso:country":"IT",
    "sg:address":"30037 Scorze'",
    "sg:orig_category":"Prodotti Alimentari",
    "sg:phone":"+39 041 584 0899",
    "sg:postcode":"30037",
    "sg:province":"Venezia",
    "wof:name":"Cagnin Giorgio E Figli S.n.c.",
    "wof:placetype":"venue"
},
  "geometry": {"coordinates":[12.1573534012,45.5282859802],"type":"Point"}
}