{
  "type": "Feature",
  "properties": {
    "iso:country":"IT",
    "sg:address":"20146 Milano",
    "sg:city":"Milano",
    "sg:orig_category":"Agenzie D'affari E Servizi Commerciali",
    "sg:phone":"+39 02 472158",
    "sg:postcode":"20146",
    "sg:province":"Milano",
    "wof:name":"E.c.f Agency S.a.s. Di F.rossi & C.",
    "wof:placetype":"venue"
},
  "geometry": {"coordinates":[9.14911,45.45393],"type":"Point"}
}