{
  "type": "Feature",
  "properties": {
    "iso:country":"IT",
    "sg:address":"Via Tufarole 1a 83100 Avellino",
    "sg:city":"Avellino",
    "sg:classifiers":[
        {
            "category":"Food & Beverages",
            "subcategory":"Chocolate",
            "type":"Retail Goods"
        }
    ],
    "sg:phone":"+39 0825 756562",
    "sg:postcode":"83100",
    "sg:province":"Avellino",
    "sg:tags":[
        "export"
    ],
    "wof:name":"Piano S.r.l.",
    "wof:placetype":"venue"
},
  "geometry": {"coordinates":[14.8082790375,40.9058380127],"type":"Point"}
}