{
  "type": "Feature",
  "properties": {
    "iso:country":"IT",
    "sg:address":"20060 Pessano Con Bornago",
    "sg:city":"Ornago",
    "sg:orig_category":"Materiali E Componenti Elettrotecnici",
    "sg:phone":"+39 02 9574 1412",
    "sg:postcode":"20060",
    "sg:province":"Milano",
    "wof:name":"Agerco Service S.r.l.",
    "wof:placetype":"venue"
},
  "geometry": {"coordinates":[9.391765,45.551136],"type":"Point"}
}