{
  "type": "Feature",
  "properties": {
    "addr:full":"00161 Roma Roma Roma 00161",
    "addr:postcode":"00161;00161",
    "iso:country":"IT",
    "sg:address":"00161 Roma",
    "sg:city":"Roma",
    "sg:orig_category":"Servizi Al Turismo. Trasporto Pubblico E Privato. Acqua, Luce, Gas E Societa' Di Esercizio Pubblico. Pubblica Amministrazione",
    "sg:phone":"+39 0644101",
    "sg:postcode":"00161",
    "sg:province":"Roma",
    "wof:name":"Ferrovie Dello Stato S.p.a.",
    "wof:placetype":"venue"
},
  "geometry": {"coordinates":[12.515463,41.911732],"type":"Point"}
}