{
  "type": "Feature",
  "properties": {
    "addr:full":"68, Via Battisti Cesare 20043 Arcore Arcore Milano 20043",
    "addr:postcode":"20043;20043",
    "addr:street":"Via Battisti Cesare",
    "iso:country":"IT",
    "sg:address":"68, Via Battisti Cesare 20043 Arcore",
    "sg:city":"Arcore",
    "sg:classifiers":[
        {
            "category":"Manufacturing",
            "subcategory":"Motor Vehicles & Parts",
            "type":"Manufacturing & Wholesale Goods"
        }
    ],
    "sg:phone":"+39 390 396 0751",
    "sg:postcode":"20043",
    "sg:province":"Milano",
    "sg:tags":[
        "engine"
    ],
    "wof:name":"Knorr - Bremse Sistemi Per Autoveicoli Commerciali Spa",
    "wof:placetype":"venue"
},
  "geometry": {"coordinates":[9.188141,45.463688],"type":"Point"}
}