{
  "type": "Feature",
  "properties": {
    "iso:country":"IT",
    "sg:address":"00152 Roma",
    "sg:city":"Roma",
    "sg:orig_category":"Scuole E Servizi Scolastici. Ospedali E Servizi Sanitari",
    "sg:phone":"+39 06 535597",
    "sg:postcode":"00152",
    "sg:province":"Roma",
    "wof:name":"A.n.f.f.a.s.",
    "wof:placetype":"venue"
},
  "geometry": {"coordinates":[12.451108,41.881084],"type":"Point"}
}