{
  "type": "Feature",
  "properties": {
    "iso:country":"IT",
    "sg:address":"20123 Milano",
    "sg:city":"Milano",
    "sg:classifiers":[
        {
            "category":"Personal",
            "subcategory":"Beauty Salon",
            "type":"Services"
        }
    ],
    "sg:phone":"+39 02 877634",
    "sg:postcode":"20123",
    "sg:province":"Milano",
    "sg:tags":[
        "school",
        "personnel",
        "cosmetic",
        "educational",
        "recruitment",
        "services",
        "training"
    ],
    "wof:name":"Scuola Imperiale Di Locatelli M. W. Snc",
    "wof:placetype":"venue"
},
  "geometry": {"coordinates":[9.183925,45.460629],"type":"Point"}
}