{
  "type": "Feature",
  "properties": {
    "iso:country":"IT",
    "sg:address":"34147 Trieste",
    "sg:city":"Trieste",
    "sg:orig_category":"Termotecnica E Riscaldamento, Apparecchiature E Servizi",
    "sg:phone":"+39 040 383555",
    "sg:postcode":"34147",
    "sg:province":"Trieste",
    "wof:name":"Siram S.p.a.",
    "wof:placetype":"venue"
},
  "geometry": {"coordinates":[13.79474,45.61615],"type":"Point"}
}