{
  "type": "Feature",
  "properties": {
    "addr:full":"50018 Scandicci Scandicci Firenze 50018",
    "addr:postcode":"50018;50018",
    "iso:country":"IT",
    "sg:address":"50018 Scandicci",
    "sg:city":"Scandicci",
    "sg:orig_category":"Trasporti E Spedizioni Merci",
    "sg:phone":"+39 055 419773",
    "sg:postcode":"50018",
    "sg:province":"Firenze",
    "sg:website":"http://www.coopfiorentinaservizi.it",
    "wof:name":"Cooperativa Fiorentina Servizi Soc.coop. (a.r.l.)",
    "wof:placetype":"venue"
},
  "geometry": {"coordinates":[11.180569,43.764473],"type":"Point"}
}