{
  "type": "Feature",
  "properties": {
    "iso:country":"IT",
    "sg:address":"20048 Carate Brianza",
    "sg:city":"Carate Brianza",
    "sg:orig_category":"Servizi E Lavori Industria Chimica. Trattamenti Termici E Superficiali Metalli, Galvanotecnica",
    "sg:phone":"+39 036 290 1115",
    "sg:postcode":"20048",
    "sg:province":"Milano",
    "wof:name":"Ates Sas Di Colombo Sergio Elia",
    "wof:placetype":"venue"
},
  "geometry": {"coordinates":[9.228264,45.660774],"type":"Point"}
}