{
  "type": "Feature",
  "properties": {
    "addr:full":"00122 Roma Roma Roma 00122",
    "addr:postcode":"00122;00122",
    "iso:country":"IT",
    "sg:address":"00122 Roma",
    "sg:city":"Roma",
    "sg:orig_category":"Servizi Per Lo Sport E Il Tempo Libero. Alberghi E Strutture Extra Alberghiere",
    "sg:phone":"+39 06 5647 0437",
    "sg:postcode":"00122",
    "sg:province":"Roma",
    "wof:name":"La Rotonda Srl",
    "wof:placetype":"venue"
},
  "geometry": {"coordinates":[12.41241,41.78611],"type":"Point"}
}