{
  "type": "Feature",
  "properties": {
    "iso:country":"IT",
    "sg:address":"97100 Ragusa",
    "sg:city":"Ragusa",
    "sg:orig_category":"Servizi Ausiliari Dei Mezzi Di Trasporto",
    "sg:phone":"+39 0932 255950",
    "sg:postcode":"97100",
    "sg:province":"Ragusa",
    "wof:name":"Blundo Aurelio - Autoparco Blundo",
    "wof:placetype":"venue"
},
  "geometry": {"coordinates":[14.685569,36.931721],"type":"Point"}
}