{
  "type": "Feature",
  "properties": {
    "iso:country":"IT",
    "sg:address":"52100 Arezzo",
    "sg:city":"Arezzo",
    "sg:orig_category":"Calzature, Pelletterie E Pelli. Shopping",
    "sg:phone":"+39 0575 370037",
    "sg:postcode":"52100",
    "sg:province":"Arezzo",
    "wof:name":"Modi E Moda Spa",
    "wof:placetype":"venue"
},
  "geometry": {"coordinates":[11.838281,43.462059],"type":"Point"}
}