{
  "type": "Feature",
  "properties": {
    "iso:country":"IT",
    "sg:address":"47039 Savignano Sul Rubicone",
    "sg:city":"Savignano sul Rubicone",
    "sg:orig_category":"Imballaggi - Produzione E Commercio",
    "sg:phone":"+39 0541 945239",
    "sg:postcode":"47039",
    "sg:province":"Forl\u00ec-Cesena",
    "wof:name":"Scatolificio Ceccarelli Di Giovagnoli Anita & C. Snc",
    "wof:placetype":"venue"
},
  "geometry": {"coordinates":[12.418632,44.086773],"type":"Point"}
}