{
  "type": "Feature",
  "properties": {
    "iso:country":"IT",
    "sg:address":"Via Xxv Aprile 15 28010 Gargallo",
    "sg:city":"Gargallo",
    "sg:orig_category":"Ladies' Shoes",
    "sg:phone":"+39 0322 913327",
    "sg:postcode":"28010",
    "sg:province":"Novara",
    "wof:name":"Maxxel Srl",
    "wof:placetype":"venue"
},
  "geometry": {"coordinates":[8.618671,45.445084],"type":"Point"}
}