{
  "type": "Feature",
  "properties": {
    "addr:full":"54033 Carrara Carrara Massa-Carrara 54033",
    "addr:postcode":"54033;54033",
    "iso:country":"IT",
    "sg:address":"54033 Carrara",
    "sg:city":"Carrara",
    "sg:orig_category":"Pratiche Automobilistiche",
    "sg:phone":"+39 0585 858233",
    "sg:postcode":"54033",
    "sg:province":"Massa-Carrara",
    "wof:name":"Autoconsult Di Corsini Davide E C. Snc",
    "wof:placetype":"venue"
},
  "geometry": {"coordinates":[10.0554418564,44.0495300293],"type":"Point"}
}