{
  "type": "Feature",
  "properties": {
    "addr:full":"78, Via Falterona-porrena 52014 Poppi Poppi Arezzo 52014",
    "addr:postcode":"52014;52014",
    "addr:street":"Via Falterona-Porrena",
    "iso:country":"IT",
    "sg:address":"78, Via Falterona-porrena 52014 Poppi",
    "sg:city":"Poppi",
    "sg:classifiers":[
        {
            "category":"Real Estate",
            "subcategory":"Architect",
            "type":"Services"
        }
    ],
    "sg:phone":"+39 0575 500177",
    "sg:postcode":"52014",
    "sg:province":"Arezzo",
    "sg:tags":[
        "textile",
        "clothing"
    ],
    "wof:name":"Tessiltaglio",
    "wof:placetype":"venue"
},
  "geometry": {"coordinates":[11.745964,43.743748],"type":"Point"}
}