{
  "type": "Feature",
  "properties": {
    "iso:country":"IT",
    "sg:address":"00138 Roma",
    "sg:city":"Roma",
    "sg:orig_category":"Pubblica Amministrazione",
    "sg:phone":"+39 06 881 3643",
    "sg:postcode":"00138",
    "sg:province":"Roma",
    "wof:name":"Comando Generale G.f.rep.tecn.log.amm.rep.sp",
    "wof:placetype":"venue"
},
  "geometry": {"coordinates":[12.5046100616,41.974407196],"type":"Point"}
}