{
  "type": "Feature",
  "properties": {
    "iso:country":"IT",
    "sg:address":"24060 Credaro",
    "sg:city":"Credaro",
    "sg:orig_category":"Porfidi E Pietre Per Pavimenti E Rivestimenti",
    "sg:phone":"+39 335 241 077",
    "sg:postcode":"24060",
    "sg:province":"Bergamo",
    "wof:name":"Cava Bettoni Srl",
    "wof:placetype":"venue"
},
  "geometry": {"coordinates":[9.9319419861,45.6615867615],"type":"Point"}
}