{
  "type": "Feature",
  "properties": {
    "iso:country":"IT",
    "sg:address":"135, V. Annunziata 64021 Giulianova",
    "sg:city":"Giulianova",
    "sg:orig_category":"Miscellaneous Products",
    "sg:phone":"+39 085 800 5810",
    "sg:postcode":"64021",
    "sg:province":"Teramo",
    "sg:website":"http://www.paginegialle.it/",
    "wof:name":"La Giugliese Pompe Funebri",
    "wof:placetype":"venue"
},
  "geometry": {"coordinates":[13.9722795486,42.7390785217],"type":"Point"}
}