{
  "type": "Feature",
  "properties": {
    "addr:full":"52045 Foiano Della Chiana Foiano della Chiana Arezzo 52045",
    "addr:housenumber":"della chiana",
    "addr:postcode":"52045;52045",
    "iso:country":"IT",
    "sg:address":"52045 Foiano Della Chiana",
    "sg:city":"Foiano della Chiana",
    "sg:orig_category":"Calzature, Pelletterie E Pelli",
    "sg:phone":"+39 0575 648132",
    "sg:postcode":"52045",
    "sg:province":"Arezzo",
    "wof:name":"A.f. Amadori & Ferretti",
    "wof:placetype":"venue"
},
  "geometry": {"coordinates":[11.815585,43.315193],"type":"Point"}
}