{
  "type": "Feature",
  "properties": {
    "addr:full":"95045 Misterbianco Misterbianco Catania 95045",
    "addr:postcode":"95045;95045",
    "iso:country":"IT",
    "sg:address":"95045 Misterbianco",
    "sg:city":"Misterbianco",
    "sg:orig_category":"Palestre",
    "sg:phone":"+39 095 301252",
    "sg:postcode":"95045",
    "sg:province":"Catania",
    "wof:name":"Sabor Latino",
    "wof:placetype":"venue"
},
  "geometry": {"coordinates":[15.0183734894,37.5167884827],"type":"Point"}
}