{
  "type": "Feature",
  "properties": {
    "iso:country":"IT",
    "sg:address":"40024 Castel San Pietro Terme",
    "sg:city":"Castel San Pietro Terme",
    "sg:orig_category":"Arredamenti E Mobili Professionali. Impianti, Attrezzature E Forniture Sanitarie Ed Ospedaliere",
    "sg:phone":"+39 051 945148",
    "sg:postcode":"40024",
    "sg:province":"Bologna",
    "wof:name":"Sergo Di Gottarelli Roberto",
    "wof:placetype":"venue"
},
  "geometry": {"coordinates":[11.613653,44.392414],"type":"Point"}
}