{
  "type": "Feature",
  "properties": {
    "addr:full":"40132 Bologna Bologna Bologna 40132",
    "addr:postcode":"40132;40132",
    "iso:country":"IT",
    "sg:address":"40132 Bologna",
    "sg:city":"Bologna",
    "sg:orig_category":"Macchine, Impianti Ed Attrezzature Per Abbigliamento E Pelletterie",
    "sg:phone":"+39 051 569736",
    "sg:postcode":"40132",
    "sg:province":"Bologna",
    "wof:name":"Bongelli Beppe",
    "wof:placetype":"venue"
},
  "geometry": {"coordinates":[11.286501,44.512184],"type":"Point"}
}