{
  "type": "Feature",
  "properties": {
    "iso:country":"IT",
    "sg:address":"83031 Ariano Irpino",
    "sg:city":"Ariano Irpino",
    "sg:orig_category":"Elettronica Professionale E Di Consumo. Automazione E Macchine Per Ufficio. Forniture Per Congressi, Fiere E Manifestazioni",
    "sg:phone":"+39 0825 825618",
    "sg:postcode":"83031",
    "sg:province":"Avellino",
    "wof:name":"Centro Didattico Irpino",
    "wof:placetype":"venue"
},
  "geometry": {"coordinates":[15.149219,41.078075],"type":"Point"}
}