{
  "type": "Feature",
  "properties": {
    "iso:country":"IT",
    "sg:address":"20010 Cornaredo",
    "sg:city":"Cornaredo",
    "sg:orig_category":"Arte Ed Artigianato Artistico",
    "sg:phone":"+39 02 936 2829",
    "sg:postcode":"20010",
    "sg:province":"Milano",
    "wof:name":"Nuova Labo 3 S.d.f.",
    "wof:placetype":"venue"
},
  "geometry": {"coordinates":[9.023957,45.501537],"type":"Point"}
}