{
  "type": "Feature",
  "properties": {
    "iso:country":"IT",
    "sg:address":"Via Dell' Industria 13 36016 Thiene",
    "sg:city":"Thiene",
    "sg:orig_category":"Closing Speed Controllers, Mechanical",
    "sg:phone":"+39 0445 368532",
    "sg:postcode":"36016",
    "sg:province":"Vicenza",
    "sg:website":"www.varmec.com",
    "wof:name":"Varmec Srl",
    "wof:placetype":"venue"
},
  "geometry": {"coordinates":[11.511846,45.706509],"type":"Point"}
}