{
  "type": "Feature",
  "properties": {
    "iso:country":"IT",
    "sg:address":"3, Strada Basaglie 46026 Quistello",
    "sg:city":"Quistello",
    "sg:classifiers":[
        {
            "category":"Shopping",
            "subcategory":"Crafts & Fabrics",
            "type":"Retail Goods"
        }
    ],
    "sg:phone":"+39 0376 619630",
    "sg:postcode":"46026",
    "sg:province":"Mantova",
    "wof:name":"Industria Tessile Mantovana Sas Di Lanzi Renza E C",
    "wof:placetype":"venue"
},
  "geometry": {"coordinates":[11.0016527176,45.0025939941],"type":"Point"}
}