{
  "type": "Feature",
  "properties": {
    "iso:country":"IT",
    "sg:address":"34, V. Cercone 24060 Castelli Calepio",
    "sg:city":"Castelli Calepio",
    "sg:classifiers":[
        {
            "category":"Professional",
            "subcategory":"Engineering",
            "type":"Services"
        }
    ],
    "sg:phone":"+39 035 442 5115",
    "sg:postcode":"24060",
    "sg:province":"Bergamo",
    "sg:tags":[
        "machine",
        "-",
        "mechanical"
    ],
    "sg:website":"http://www.fluorten.com:ws_end: :mark:ws:http://www.paginegialle.it/fluorten",
    "wof:name":"Fluorten Srl",
    "wof:placetype":"venue"
},
  "geometry": {"coordinates":[9.897492,45.626419],"type":"Point"}
}