{
  "type": "Feature",
  "properties": {
    "iso:country":"IT",
    "sg:address":"06087 Perugia",
    "sg:orig_category":"Elettrotecnica Industriale, Prodotti E Apparecchiature. Elettronica Industriale, Prodotti E Apparecchiature",
    "sg:phone":"+39 075 394512",
    "sg:province":"PG",
    "wof:name":"Umbra Elettroforniture",
    "wof:placetype":"venue"
},
  "geometry": {"coordinates":[12.72494,42.605156],"type":"Point"}
}