{
  "type": "Feature",
  "properties": {
    "iso:country":"IT",
    "sg:address":"22066 Mariano Comense",
    "sg:city":"Mariano Comense",
    "sg:orig_category":"Macchine Utensili E Impianti",
    "sg:phone":"+39 031 750640",
    "sg:postcode":"22066",
    "sg:province":"Como",
    "wof:name":"Safed Italia S.r.l.",
    "wof:placetype":"venue"
},
  "geometry": {"coordinates":[9.186583,45.678474],"type":"Point"}
}