{
  "type": "Feature",
  "properties": {
    "iso:country":"IT",
    "sg:address":"12, Via Posorti 21029 Vergiate",
    "sg:city":"Vergiate",
    "sg:classifiers":[
        {
            "category":"Shopping",
            "subcategory":"Crafts & Fabrics",
            "type":"Retail Goods"
        }
    ],
    "sg:phone":"+39 0331 946107",
    "sg:postcode":"21029",
    "sg:province":"Varese",
    "wof:name":"T - Tex Srl",
    "wof:placetype":"venue"
},
  "geometry": {"coordinates":[8.6855669022,45.7144088745],"type":"Point"}
}