{
  "type": "Feature",
  "properties": {
    "iso:country":"IT",
    "sg:address":"61, Via Vigne 47023 Cesena",
    "sg:city":"Cesena",
    "sg:classifiers":[
        {
            "category":"Shopping",
            "type":"Retail Goods"
        }
    ],
    "sg:phone":"+39 0547 317388",
    "sg:postcode":"47023",
    "sg:province":"Forl\u00ec-Cesena",
    "sg:tags":[
        "finished",
        "-",
        "metallic"
    ],
    "wof:name":"Cooperativa Metallurgica Cesenate Soc.coop.a R.l.",
    "wof:placetype":"venue"
},
  "geometry": {"coordinates":[12.1913366318,44.0860748291],"type":"Point"}
}