{
  "type": "Feature",
  "properties": {
    "addr:full":"131, Borgo Treviso 31033 Castelfranco Veneto Castelfranco Veneto Treviso 31033",
    "addr:housenumber":"131",
    "addr:postcode":"31033;31033",
    "addr:street":"Borgo Treviso",
    "iso:country":"IT",
    "sg:address":"131, Borgo Treviso 31033 Castelfranco Veneto",
    "sg:city":"Castelfranco Veneto",
    "sg:classifiers":[
        {
            "category":"Shopping",
            "subcategory":"Clothing, Apparel, & Fashions",
            "type":"Retail Goods"
        }
    ],
    "sg:phone":"+39 0423 722204",
    "sg:postcode":"31033",
    "sg:province":"Treviso",
    "sg:tags":[
        "clothes"
    ],
    "wof:name":"Commerciale Veneta Abbigliamento S.r.l.",
    "wof:placetype":"venue"
},
  "geometry": {"coordinates":[11.941913,45.672989],"type":"Point"}
}