{
  "type": "Feature",
  "properties": {
    "iso:country":"IT",
    "sg:address":"12, Via Baracca Francesco 36060 Romano D'ezzelino",
    "sg:classifiers":[
        {
            "category":"Shopping",
            "subcategory":"Clothing, Apparel, & Fashions",
            "type":"Retail Goods"
        }
    ],
    "sg:phone":"+39 39042432862",
    "sg:postcode":"36060",
    "sg:province":"Vicenza",
    "sg:tags":[
        "clothes"
    ],
    "wof:name":"Bigi Sport Di Battaglia G. & S. (s.n.c.)",
    "wof:placetype":"venue"
},
  "geometry": {"coordinates":[11.540307,45.545906],"type":"Point"}
}