{
  "type": "Feature",
  "properties": {
    "addr:full":"73010 Veglie Veglie Lecce 73010",
    "addr:postcode":"73010;73010",
    "iso:country":"IT",
    "sg:address":"73010 Veglie",
    "sg:city":"Veglie",
    "sg:orig_category":"Medicinali E Prodotti Parafarmaceutici. Prodotti Cosmetici E Da Toeletta",
    "sg:phone":"+39 0832 966576",
    "sg:postcode":"73010",
    "sg:province":"Lecce",
    "sg:website":"http://www.devilab.it",
    "wof:name":"Devilab Di Moccia Enrico",
    "wof:placetype":"venue"
},
  "geometry": {"coordinates":[18.1738052368,40.3668403625],"type":"Point"}
}