{
  "type": "Feature",
  "properties": {
    "addr:full":"20125 Milano Milano Milano 20125",
    "addr:postcode":"20125;20125",
    "iso:country":"IT",
    "sg:address":"20125 Milano",
    "sg:city":"Milano",
    "sg:orig_category":"Musica",
    "sg:phone":"+39 02 669 1622",
    "sg:postcode":"20125",
    "sg:province":"Milano",
    "wof:name":"Chiara Sandro",
    "wof:placetype":"venue"
},
  "geometry": {"coordinates":[9.203877449,45.49477005],"type":"Point"}
}