{
  "type": "Feature",
  "properties": {
    "iso:country":"IT",
    "sg:address":"Ctr. Albereto 94014 Nicosia",
    "sg:city":"Nicosia",
    "sg:classifiers":[
        {
            "category":"Bars & Pubs",
            "subcategory":"Nightclub",
            "type":"Food & Drink"
        }
    ],
    "sg:phone":"+39 0935 630212",
    "sg:postcode":"94014",
    "sg:province":"Enna",
    "sg:tags":[
        "cake",
        "bread"
    ],
    "sg:website":"http://www.paginegialle.it/pasticceriasuamaesta",
    "wof:name":"Pasticceria Sua Maest\u00c0",
    "wof:placetype":"venue"
},
  "geometry": {"coordinates":[14.279706,37.567596],"type":"Point"}
}