{
  "type": "Feature",
  "properties": {
    "iso:country":"IT",
    "sg:address":"29, Via Postumia 31100 Treviso",
    "sg:city":"Treviso",
    "sg:orig_category":"Miscellaneous Products",
    "sg:phone":"+39 0422 545650",
    "sg:postcode":"31100",
    "sg:province":"Treviso",
    "wof:name":"New Import Export (s.r.l.)",
    "wof:placetype":"venue"
},
  "geometry": {"coordinates":[12.1904382706,45.6678924561],"type":"Point"}
}