{
  "type": "Feature",
  "properties": {
    "addr:full":"Via Cesare Battisti 32/34; Isola Della Scala; 37063 Isola della Scala Verona 37063",
    "addr:housenumber":"32 / 34",
    "addr:postcode":"37063;37063",
    "addr:street":"Via Cesare Battisti;Scala",
    "iso:country":"IT",
    "sg:address":"Via Cesare Battisti 32/34; Isola Della Scala; 37063",
    "sg:city":"Isola della Scala",
    "sg:classifiers":[
        {
            "category":"Banks & Credit Unions",
            "subcategory":"Bank",
            "type":"Services"
        }
    ],
    "sg:phone":"+39 045 730 1088",
    "sg:postcode":"37063",
    "sg:province":"Verona",
    "wof:name":"Banco Ambrosiano Veneto Spa",
    "wof:placetype":"venue"
},
  "geometry": {"coordinates":[11.008407,45.272514],"type":"Point"}
}