{
  "type": "Feature",
  "properties": {
    "iso:country":"IT",
    "sg:address":"13, Viale Dell' Artigianato 36030 San Vito Di Leguzzano",
    "sg:city":"San Vito di Leguzzano",
    "sg:classifiers":[
        {
            "category":"Manufacturing",
            "subcategory":"Metals",
            "type":"Manufacturing & Wholesale Goods"
        }
    ],
    "sg:phone":"+39 0445 519044",
    "sg:postcode":"36030",
    "sg:province":"Vicenza",
    "sg:tags":[
        "metallurgy",
        "metalworking"
    ],
    "wof:name":"Fa.ve.",
    "wof:placetype":"venue"
},
  "geometry": {"coordinates":[11.4003248215,45.6869812012],"type":"Point"}
}