{
  "type": "Feature",
  "properties": {
    "addr:full":"20145 Milano Milano Milano 20145",
    "addr:postcode":"20145;20145",
    "iso:country":"IT",
    "sg:address":"20145 Milano",
    "sg:city":"Milano",
    "sg:orig_category":"Apparecchiature E Sistemi Per Magazzinaggio E Movimentazione",
    "sg:phone":"+39 02 462221",
    "sg:postcode":"20145",
    "sg:province":"Milano",
    "wof:name":"Ciftat Coop. Italiana Facchini Trasporto E Ausiliari Traffico Soc.coop.r.l.",
    "wof:placetype":"venue"
},
  "geometry": {"coordinates":[9.160143,45.476067],"type":"Point"}
}