{
  "type": "Feature",
  "properties": {
    "addr:full":"00195 Roma Roma Roma 00195",
    "addr:postcode":"00195;00195",
    "iso:country":"IT",
    "sg:address":"00195 Roma",
    "sg:city":"Roma",
    "sg:orig_category":"Macchine, Impianti Ed Attrezzature Per Abbigliamento E Pelletterie",
    "sg:phone":"+39 06 3751 5723",
    "sg:postcode":"00195",
    "sg:province":"Roma",
    "wof:name":"Cafissi Maria",
    "wof:placetype":"venue"
},
  "geometry": {"coordinates":[12.460463,41.913342],"type":"Point"}
}