{
  "type": "Feature",
  "properties": {
    "iso:country":"IT",
    "sg:address":"4, V. Roma - Forcoli56030 Palaia",
    "sg:classifiers":[
        {
            "category":"Farming",
            "subcategory":"Livestock Farm",
            "type":"Manufacturing & Wholesale Goods"
        }
    ],
    "sg:phone":"+39 0587 628037",
    "sg:postcode":"56030",
    "sg:province":"Pisa",
    "sg:tags":[
        "agriculture"
    ],
    "sg:website":"http://www.savinitartufi.com:ws_end: :mark:ws:http://www.paginegialle.it/savinitart",
    "wof:name":"Savini Tartufi",
    "wof:placetype":"venue"
},
  "geometry": {"coordinates":[10.396585,43.716137],"type":"Point"}
}