{
  "type": "Feature",
  "properties": {
    "iso:country":"IT",
    "sg:address":"7, Via Gualtiero Gustinelli 06012 Citta' Di Castello",
    "sg:classifiers":[
        {
            "category":"Real Estate",
            "subcategory":"Architect",
            "type":"Services"
        }
    ],
    "sg:phone":"+39 075 854 0384",
    "sg:postcode":"06012",
    "sg:province":"Perugia",
    "sg:tags":[
        "textile",
        "clothing"
    ],
    "wof:name":"Rofin (s.r.l.)",
    "wof:placetype":"venue"
},
  "geometry": {"coordinates":[12.269888,43.36871],"type":"Point"}
}