{
  "type": "Feature",
  "properties": {
    "iso:country":"IT",
    "sg:address":"20041 Agrate Brianza",
    "sg:city":"Agrate Brianza",
    "sg:orig_category":"Prodotti E Manufatti In Gomma. Forniture Per Attivita' Industriali",
    "sg:phone":"+39 039 650868",
    "sg:postcode":"20041",
    "sg:province":"Milano",
    "sg:website":"http://www.tagliabueluigi.it",
    "wof:name":"Tagliabue Luigi E C. Snc",
    "wof:placetype":"venue"
},
  "geometry": {"coordinates":[9.3596143723,45.5657119751],"type":"Point"}
}