{
  "type": "Feature",
  "properties": {
    "iso:country":"IT",
    "sg:address":"50033 Firenzuola",
    "sg:city":"Firenzuola",
    "sg:orig_category":"Servizi E Lavori Per Agricoltura E Zootecnia. Servizi E Lavori Per Ecologia E Smaltimento Rifiuti",
    "sg:phone":"+39 055 819063",
    "sg:postcode":"50033",
    "sg:province":"Firenze",
    "wof:name":"Consorzio Bonifica Romagna Occidentale",
    "wof:placetype":"venue"
},
  "geometry": {"coordinates":[11.365801,44.152103],"type":"Point"}
}