{
  "type": "Feature",
  "properties": {
    "addr:full":"06055 Marsciano Marsciano Perugia 06055",
    "addr:postcode":"06055;06055",
    "iso:country":"IT",
    "sg:address":"06055 Marsciano",
    "sg:city":"Marsciano",
    "sg:orig_category":"Riscaldamento - Combustibili",
    "sg:phone":"+39 075 874 2829",
    "sg:postcode":"06055",
    "sg:province":"Perugia",
    "wof:name":"Moretti Snc",
    "wof:placetype":"venue"
},
  "geometry": {"coordinates":[12.323482,42.951721],"type":"Point"}
}