{
  "type": "Feature",
  "properties": {
    "iso:country":"IT",
    "sg:address":"4, Via Codignola Ernesto 50018 Scandicci",
    "sg:city":"Scandicci",
    "sg:classifiers":[
        {
            "category":"Shopping",
            "subcategory":"Crafts & Fabrics",
            "type":"Retail Goods"
        }
    ],
    "sg:phone":"+39 39055757079",
    "sg:postcode":"50018",
    "sg:province":"Firenze",
    "wof:name":"Boldrini Luigi & Figli Spa",
    "wof:placetype":"venue"
},
  "geometry": {"coordinates":[11.1683950424,43.763381958],"type":"Point"}
}