{
  "type": "Feature",
  "properties": {
    "iso:country":"IT",
    "sg:address":"13, Via Dalla Chiesa Generale Carlo Alberto 44034 Copparo",
    "sg:city":"Copparo",
    "sg:classifiers":[
        {
            "category":"Shopping",
            "subcategory":"Clothing, Apparel, & Fashions",
            "type":"Retail Goods"
        }
    ],
    "sg:phone":"+39 0532 866941",
    "sg:postcode":"44034",
    "sg:province":"Ferrara",
    "sg:tags":[
        "clothes"
    ],
    "wof:name":"Pontini S.a.s. Di Pontini Gianni & C.",
    "wof:placetype":"venue"
},
  "geometry": {"coordinates":[11.62044,44.837894],"type":"Point"}
}