{
  "type": "Feature",
  "properties": {
    "iso:country":"IT",
    "sg:address":"50122 Firenze",
    "sg:city":"Firenze",
    "sg:orig_category":"Lenti A Contatto E Per Occhiali - Produzione E Ingrosso",
    "sg:phone":"+39 055 287960",
    "sg:postcode":"50122",
    "sg:province":"Firenze",
    "wof:name":"Elca Sas Di Campolmi Riccardo & C.",
    "wof:placetype":"venue"
},
  "geometry": {"coordinates":[11.257076,43.769527],"type":"Point"}
}