{
  "type": "Feature",
  "properties": {
    "addr:full":"95128 Catania Catania Catania 95128",
    "addr:postcode":"95128;95128",
    "iso:country":"IT",
    "sg:address":"95128 Catania",
    "sg:city":"Catania",
    "sg:classifiers":[
        {
            "category":"Health Services",
            "subcategory":"Health Practitioner",
            "type":"Services"
        }
    ],
    "sg:phone":"+39 095 445182",
    "sg:postcode":"95128",
    "sg:province":"Catania",
    "sg:tags":[
        "medici"
    ],
    "wof:name":"Sapienza Francesco",
    "wof:placetype":"venue"
},
  "geometry": {"coordinates":[15.0841760635,37.5261764526],"type":"Point"}
}