{
  "type": "Feature",
  "properties": {
    "addr:full":"01030 Corchiano Corchiano Viterbo 01030",
    "addr:postcode":"01030;01030",
    "iso:country":"IT",
    "sg:address":"01030 Corchiano",
    "sg:city":"Corchiano",
    "sg:orig_category":"Materiali Edili",
    "sg:phone":"+39 0761 572585",
    "sg:postcode":"01030",
    "sg:province":"Viterbo",
    "wof:name":"C.i.s. Snc Di Ba.co.tra",
    "wof:placetype":"venue"
},
  "geometry": {"coordinates":[12.361909,42.343838],"type":"Point"}
}