{
  "type": "Feature",
  "properties": {
    "iso:country":"IT",
    "sg:address":"91025 Marsala",
    "sg:city":"Marsala",
    "sg:orig_category":"Telecomunicazioni Impianti Ed Apparecchi - Vendita Al Dettaglio",
    "sg:phone":"+39 0923 718288",
    "sg:postcode":"91025",
    "sg:province":"Trapani",
    "wof:name":"Contrino Emanuela",
    "wof:placetype":"venue"
},
  "geometry": {"coordinates":[12.509362,38.015945],"type":"Point"}
}