{
  "type": "Feature",
  "properties": {
    "iso:country":"IT",
    "sg:address":"70126 Bari",
    "sg:city":"Bari",
    "sg:orig_category":"Servizi Al Turismo. Trasporto Pubblico E Privato. Acqua, Luce, Gas E Societa' Di Esercizio Pubblico",
    "sg:phone":"+39 080 553 3772",
    "sg:postcode":"70126",
    "sg:province":"Bari",
    "wof:name":"Metropolis Spa",
    "wof:placetype":"venue"
},
  "geometry": {"coordinates":[16.918154,41.090496],"type":"Point"}
}