{
  "type": "Feature",
  "properties": {
    "iso:country":"IT",
    "sg:address":"16, Via Galilei Galileo 20054 Nova Milanese",
    "sg:city":"Nova Milanese",
    "sg:classifiers":[
        {
            "category":"Utilities",
            "subcategory":"Electric",
            "type":"Services"
        }
    ],
    "sg:phone":"+39 39036240449",
    "sg:postcode":"20054",
    "sg:province":"Milano",
    "sg:tags":[
        "component",
        "electronic"
    ],
    "wof:name":"Lab.e.m. (s.n.c.)",
    "wof:placetype":"venue"
},
  "geometry": {"coordinates":[9.155632,45.560951],"type":"Point"}
}