{
  "type": "Feature",
  "properties": {
    "iso:country":"IT",
    "sg:address":"24064 Grumello Del Monte",
    "sg:city":"Grumello del Monte",
    "sg:orig_category":"Forniture Per Abbigliamento E Pelletterie",
    "sg:phone":"+39 035 830333",
    "sg:postcode":"24064",
    "sg:province":"Bergamo",
    "wof:name":"New Style Spa",
    "wof:placetype":"venue"
},
  "geometry": {"coordinates":[9.8852176666,45.6292610168],"type":"Point"}
}