{
  "type": "Feature",
  "properties": {
    "iso:country":"IT",
    "sg:address":"06074 Perugia",
    "sg:orig_category":"Sport - Articoli E Forniture",
    "sg:phone":"+39 075 517 0814",
    "sg:province":"PG",
    "wof:name":"Galex Srl",
    "wof:placetype":"venue"
},
  "geometry": {"coordinates":[12.317647,43.102306],"type":"Point"}
}