{
  "type": "Feature",
  "properties": {
    "iso:country":"IT",
    "sg:address":"22079 Villa Guardia",
    "sg:city":"Villa Guardia",
    "sg:orig_category":"Prodotti Vari In Metallo. Forniture Per Attivita' Industriali",
    "sg:phone":"+39 031 480529",
    "sg:postcode":"22079",
    "sg:province":"Como",
    "wof:name":"Robustelli Snc Di Robustelli Lino & C",
    "wof:placetype":"venue"
},
  "geometry": {"coordinates":[9.0185079575,45.7700424194],"type":"Point"}
}