{
  "type": "Feature",
  "properties": {
    "iso:country":"IT",
    "sg:address":"84013 Cava De' Tirreni",
    "sg:orig_category":"Dolciumi - Produzione",
    "sg:phone":"+39 089 463137",
    "sg:postcode":"84013",
    "sg:province":"Salerno",
    "wof:name":"Ingros Sas Di Senatore Pasquale & C.",
    "wof:placetype":"venue"
},
  "geometry": {"coordinates":[14.699801,40.711781],"type":"Point"}
}