{
  "type": "Feature",
  "properties": {
    "addr:full":"07100 Sassari Sassari Sassari 07100",
    "addr:postcode":"07100;07100",
    "iso:country":"IT",
    "sg:address":"07100 Sassari",
    "sg:city":"Sassari",
    "sg:orig_category":"Agenzie D'affari E Servizi Commerciali. Acqua, Luce, Gas E Societa' Di Esercizio Pubblico",
    "sg:phone":"+39 079 260228",
    "sg:postcode":"07100",
    "sg:province":"Sassari",
    "wof:name":"Istituto Vendite Giudiziarie",
    "wof:placetype":"venue"
},
  "geometry": {"coordinates":[8.501695,40.734165],"type":"Point"}
}