{
  "type": "Feature",
  "properties": {
    "iso:country":"IT",
    "sg:address":"1, Via Fiandra 23900 Lecco",
    "sg:city":"Lecco",
    "sg:classifiers":[
        {
            "category":"Wholesale",
            "subcategory":"Drugs",
            "type":"Manufacturing & Wholesale Goods"
        }
    ],
    "sg:phone":"+39 0341 282723",
    "sg:postcode":"23900",
    "sg:province":"Lecco",
    "sg:tags":[
        "chemical",
        "pharmaceutical"
    ],
    "wof:name":"Petrolcarbo (s.r.l.)",
    "wof:placetype":"venue"
},
  "geometry": {"coordinates":[9.403655,45.848354],"type":"Point"}
}