{
  "type": "Feature",
  "properties": {
    "iso:country":"IT",
    "sg:address":"30030 Pianiga",
    "sg:city":"Pianiga",
    "sg:orig_category":"Prodotti Alimentari",
    "sg:phone":"+39 041 411195",
    "sg:postcode":"30030",
    "sg:province":"Venezia",
    "wof:name":"Frison Eliseo (s.n.c.)",
    "wof:placetype":"venue"
},
  "geometry": {"coordinates":[12.1753234863,45.4522018433],"type":"Point"}
}