{
  "type": "Feature",
  "properties": {
    "iso:country":"IT",
    "sg:address":"20037 Paderno Dugnano",
    "sg:city":"Paderno Dugnano",
    "sg:orig_category":"Lavorazioni Metalli, Stampaggio E Saldatura",
    "sg:phone":"+39 02 918 2290",
    "sg:postcode":"20037",
    "sg:province":"Milano",
    "wof:name":"Rifici Inox Snc",
    "wof:placetype":"venue"
},
  "geometry": {"coordinates":[9.154184,45.575153],"type":"Point"}
}