{
  "type": "Feature",
  "properties": {
    "addr:full":"2, Via Parenzo 35010 Vigonza Vigonza Padova 35010",
    "addr:postcode":"35010;35010",
    "addr:street":"Via Parenzo",
    "iso:country":"IT",
    "sg:address":"2, Via Parenzo 35010 Vigonza",
    "sg:city":"Vigonza",
    "sg:classifiers":[
        {
            "category":"Personal",
            "subcategory":"Shoe Repair & Shine",
            "type":"Services"
        }
    ],
    "sg:phone":"+39 39049626238",
    "sg:postcode":"35010",
    "sg:province":"Padova",
    "sg:tags":[
        "leather"
    ],
    "wof:name":"Thermoshoe Di Baldin & C. (s.n.c.)",
    "wof:placetype":"venue"
},
  "geometry": {"coordinates":[11.973516,45.423374],"type":"Point"}
}