{
  "type": "Feature",
  "properties": {
    "iso:country":"IT",
    "sg:address":"00186 Roma",
    "sg:city":"Roma",
    "sg:orig_category":"Ferro Battuto",
    "sg:phone":"+39 06 6880 5660",
    "sg:postcode":"00186",
    "sg:province":"Roma",
    "wof:name":"Prili Cav. Luciano",
    "wof:placetype":"venue"
},
  "geometry": {"coordinates":[12.467414856,41.8995704651],"type":"Point"}
}