{
  "type": "Feature",
  "properties": {
    "iso:country":"IT",
    "sg:address":"50058 Signa",
    "sg:city":"Signa",
    "sg:orig_category":"Macchine Pulizia Industriale",
    "sg:phone":"+39 055 879 0447",
    "sg:postcode":"50058",
    "sg:province":"Firenze",
    "sg:website":"http://www.easyclean.it",
    "wof:name":"Easy Clean Di Scarselli Simone & C. Sas",
    "wof:placetype":"venue"
},
  "geometry": {"coordinates":[11.128779,43.795982],"type":"Point"}
}