{
  "type": "Feature",
  "properties": {
    "addr:full":"31053 Pieve Di Soligo Pieve di Soligo Treviso 31053",
    "addr:postcode":"31053;31053",
    "iso:country":"IT",
    "sg:address":"31053 Pieve Di Soligo",
    "sg:city":"Pieve di Soligo",
    "sg:orig_category":"Prodotti E Manufatti In Materie Plastiche",
    "sg:phone":"+39 0438 980929",
    "sg:postcode":"31053",
    "sg:province":"Treviso",
    "wof:name":"All Line Furniture Srl",
    "wof:placetype":"venue"
},
  "geometry": {"coordinates":[12.1664953232,45.886013031],"type":"Point"}
}