{
  "type": "Feature",
  "properties": {
    "addr:full":"34015 Muggia Muggia Trieste 34015",
    "addr:postcode":"34015;34015",
    "iso:country":"IT",
    "sg:address":"34015 Muggia",
    "sg:city":"Muggia",
    "sg:orig_category":"Pubblica Amministrazione",
    "sg:phone":"+39 040 231084",
    "sg:postcode":"34015",
    "sg:province":"Trieste",
    "wof:name":"Guardia Di Finanza",
    "wof:placetype":"venue"
},
  "geometry": {"coordinates":[13.7590999603,45.6009597778],"type":"Point"}
}