{
  "type": "Feature",
  "properties": {
    "addr:full":"Via R. Wagner 189 20038 Seregno Seregno Milano 20038",
    "addr:housenumber":"189",
    "addr:postcode":"20038;20038",
    "addr:street":"Via R. Wagner",
    "iso:country":"IT",
    "sg:address":"Via R. Wagner 189 20038 Seregno",
    "sg:city":"Seregno",
    "sg:classifiers":[
        {
            "category":"Manufacturing",
            "subcategory":"Furniture",
            "type":"Manufacturing & Wholesale Goods"
        }
    ],
    "sg:phone":"+39 036 222 0957",
    "sg:postcode":"20038",
    "sg:province":"Milano",
    "sg:tags":[
        "fabric"
    ],
    "sg:website":"www.tpatessuti.com",
    "wof:name":"Tpa Srl",
    "wof:placetype":"venue"
},
  "geometry": {"coordinates":[9.1881408691,45.4636878967],"type":"Point"}
}