{
  "type": "Feature",
  "properties": {
    "addr:full":"19, Via Dolomiti 39034 Dobbiaco Dobbiaco Bolzano/Bozen 39034",
    "addr:postcode":"39034;39034",
    "addr:street":"Via Dolomiti",
    "iso:country":"IT",
    "sg:address":"19, Via Dolomiti 39034 Dobbiaco",
    "sg:city":"Dobbiaco",
    "sg:classifiers":[
        {
            "category":"Food & Beverages",
            "subcategory":"Groceries & Convenience Stores",
            "type":"Retail Goods"
        }
    ],
    "sg:phone":"+39 0474 972186",
    "sg:postcode":"39034",
    "sg:province":"Bolzano/Bozen",
    "sg:tags":[
        "product",
        "related"
    ],
    "wof:name":"Nocker A. & C. (s.n.c.)",
    "wof:placetype":"venue"
},
  "geometry": {"coordinates":[12.2230482101,46.7260894775],"type":"Point"}
}