{
  "type": "Feature",
  "properties": {
    "addr:full":"35, Via Filippo Lussana 24069 Cenate Sotto Cenate Sotto Bergamo 24069",
    "addr:postcode":"24069;24069",
    "addr:street":"Via Filippo Lussana",
    "iso:country":"IT",
    "sg:address":"35, Via Filippo Lussana 24069 Cenate Sotto",
    "sg:city":"Cenate Sotto",
    "sg:classifiers":[
        {
            "category":"Manufacturing",
            "subcategory":"Paper Products",
            "type":"Manufacturing & Wholesale Goods"
        }
    ],
    "sg:phone":"+39 39035940081",
    "sg:postcode":"24069",
    "sg:province":"Bergamo",
    "sg:tags":[
        "cardboard"
    ],
    "wof:name":"Sob S.p.a.",
    "wof:placetype":"venue"
},
  "geometry": {"coordinates":[9.8218450546,45.6934432983],"type":"Point"}
}