{
  "type": "Feature",
  "properties": {
    "iso:country":"IT",
    "sg:address":"13, Via Romero 47853 Coriano",
    "sg:city":"Coriano",
    "sg:classifiers":[
        {
            "category":"Personal",
            "subcategory":"Shoe Repair & Shine",
            "type":"Services"
        }
    ],
    "sg:phone":"+39 0541 657198",
    "sg:postcode":"47853",
    "sg:province":"Rimini",
    "sg:tags":[
        "leather"
    ],
    "wof:name":"Valleverde Accessori S.r.l.",
    "wof:placetype":"venue"
},
  "geometry": {"coordinates":[12.597621,43.974255],"type":"Point"}
}