{
  "type": "Feature",
  "properties": {
    "iso:country":"IT",
    "sg:address":"1/f, Via Pisani Vittor 00136 Roma",
    "sg:city":"Roma",
    "sg:classifiers":[
        {
            "category":"Shopping",
            "subcategory":"Clothing, Apparel, & Fashions",
            "type":"Retail Goods"
        }
    ],
    "sg:phone":"+39 06 3972 0651",
    "sg:postcode":"00136",
    "sg:province":"Roma",
    "sg:tags":[
        "clothes"
    ],
    "wof:name":"Annamode 68 (s.r.l.)",
    "wof:placetype":"venue"
},
  "geometry": {"coordinates":[12.482325,41.895466],"type":"Point"}
}