{
  "type": "Feature",
  "properties": {
    "addr:full":"18, Via Busca Antonio 21100 Varese Varese Varese 21100",
    "addr:postcode":"21100;21100",
    "addr:street":"Via Busca Antonio",
    "iso:country":"IT",
    "sg:address":"18, Via Busca Antonio 21100 Varese",
    "sg:city":"Varese",
    "sg:classifiers":[
        {
            "category":"Shopping",
            "subcategory":"Clothing, Apparel, & Fashions",
            "type":"Retail Goods"
        }
    ],
    "sg:phone":"+39 0332 831432",
    "sg:postcode":"21100",
    "sg:province":"Varese",
    "sg:tags":[
        "clothes"
    ],
    "wof:name":"Valmode Di Papalillo M. E C. Snc",
    "wof:placetype":"venue"
},
  "geometry": {"coordinates":[8.817236,45.834713],"type":"Point"}
}