{
  "type": "Feature",
  "properties": {
    "addr:full":"Via Dei Legnai 26 39015 San Leonardo In Passiria San Leonardo in Passiria Bolzano/Bozen 39015",
    "addr:housenumber":"26",
    "addr:postcode":"39015;39015",
    "addr:street":"Via Dei Legnai",
    "iso:country":"IT",
    "sg:address":"Via Dei Legnai 26 39015 San Leonardo In Passiria",
    "sg:city":"San Leonardo in Passiria",
    "sg:classifiers":[
        {
            "category":"Manufacturing",
            "subcategory":"Wood Products",
            "type":"Manufacturing & Wholesale Goods"
        }
    ],
    "sg:phone":"+39 0473 641255",
    "sg:postcode":"39015",
    "sg:province":"Bolzano/Bozen",
    "sg:tags":[
        "solid",
        "door"
    ],
    "sg:website":"www.tischlerei-hofer.it",
    "wof:name":"Heinrich Hofer & C. Sas",
    "wof:placetype":"venue"
},
  "geometry": {"coordinates":[11.233569,46.790253],"type":"Point"}
}