{
  "type": "Feature",
  "properties": {
    "addr:full":"80133 Napoli Napoli Napoli 80133",
    "addr:housenumber":"80133",
    "addr:postcode":"80133",
    "iso:country":"IT",
    "sg:address":"80133 Napoli",
    "sg:city":"Napoli",
    "sg:orig_category":"Studi E Consulenze Legali E Notarili. Avvocati, Notai E Servizi Legali. Professionisti - Studi E Servizi Ed Associazioni Di Interesse Aziendale",
    "sg:phone":"+39 081 420 2011",
    "sg:postcode":"80133",
    "sg:province":"Napoli",
    "wof:name":"Gruppo Imperiali Network Service Srl",
    "wof:placetype":"venue"
},
  "geometry": {"coordinates":[14.25495,40.842407],"type":"Point"}
}