{
  "type": "Feature",
  "properties": {
    "iso:country":"IT",
    "sg:address":"Via Cenisio 20 20154 Milano",
    "sg:city":"Milano",
    "sg:classifiers":[
        {
            "category":"Utilities",
            "subcategory":"Fuel Oil & Lpg",
            "type":"Services"
        }
    ],
    "sg:phone":"+39 02 3366 8800",
    "sg:postcode":"20154",
    "sg:province":"Milano",
    "sg:tags":[
        "dental",
        "product"
    ],
    "sg:website":"www.apexdental.it",
    "wof:name":"Apex Dental Srl",
    "wof:placetype":"venue"
},
  "geometry": {"coordinates":[9.168719,45.487869],"type":"Point"}
}