{
  "type": "Feature",
  "properties": {
    "iso:country":"IT",
    "sg:address":"10155 Torino",
    "sg:city":"Torino",
    "sg:orig_category":"Pompe. Macchine, Strumenti Ed Apparecchi Per Attivita' Industriali",
    "sg:phone":"+39 011 241 1411",
    "sg:postcode":"10155",
    "sg:province":"Torino",
    "sg:website":"http://audolibertola.com",
    "wof:name":"Audoli & Bertola",
    "wof:placetype":"venue"
},
  "geometry": {"coordinates":[8.3989200592,45.4623451233],"type":"Point"}
}