{
  "type": "Feature",
  "properties": {
    "addr:full":"00197 Roma Roma Roma 00197",
    "addr:postcode":"00197;00197",
    "iso:country":"IT",
    "sg:address":"00197 Roma",
    "sg:city":"Roma",
    "sg:orig_category":"Gallerie D'arte",
    "sg:phone":"+39 06 322 0555",
    "sg:postcode":"00197",
    "sg:province":"Roma",
    "wof:name":"Edieuropa Gallerie D'arte Srl",
    "wof:placetype":"venue"
},
  "geometry": {"coordinates":[12.647618,41.753956],"type":"Point"}
}