{
  "type": "Feature",
  "properties": {
    "iso:country":"IT",
    "sg:address":"Via Quinto Mansuino ,16/10 18038 San Remo",
    "sg:city":"San Remo",
    "sg:classifiers":[
        {
            "category":"Food & Beverages",
            "subcategory":"Fruits & Vegetables",
            "type":"Retail Goods"
        }
    ],
    "sg:phone":"+39 0184 514099",
    "sg:postcode":"18038",
    "sg:province":"Imperia",
    "sg:tags":[
        "bulb",
        "flower",
        "tuber"
    ],
    "sg:website":"www.puntofiori.it",
    "wof:name":"Punto Fiori Srl",
    "wof:placetype":"venue"
},
  "geometry": {"coordinates":[7.8322477341,43.8248023987],"type":"Point"}
}