{
  "type": "Feature",
  "properties": {
    "addr:full":"20021 Bollate Bollate Milano 20021",
    "addr:postcode":"20021;20021",
    "iso:country":"IT",
    "sg:address":"20021 Bollate",
    "sg:city":"Bollate",
    "sg:orig_category":"Prodotti Alimentari",
    "sg:phone":"+39 02 350 5443",
    "sg:postcode":"20021",
    "sg:province":"Milano",
    "wof:name":"Ai Buoni Frutti Di Foglia & C. (s.n.c.)",
    "wof:placetype":"venue"
},
  "geometry": {"coordinates":[9.1161642075,45.5439796448],"type":"Point"}
}