{
  "type": "Feature",
  "properties": {
    "iso:country":"IT",
    "sg:address":"Via Della Liberta' 16 13816 Sagliano Micca",
    "sg:city":"Sagliano Micca",
    "sg:classifiers":[
        {
            "category":"Personal",
            "subcategory":"Hair Removal",
            "type":"Services"
        }
    ],
    "sg:phone":"+39 015 473635",
    "sg:postcode":"13816",
    "sg:province":"Biella",
    "sg:tags":[
        "cap",
        "hat"
    ],
    "sg:website":"www.cappellificiocervo.it",
    "wof:name":"Cappellificio Cervo - S.r.l.",
    "wof:placetype":"venue"
},
  "geometry": {"coordinates":[8.043339,45.62875],"type":"Point"}
}