{
  "type": "Feature",
  "properties": {
    "iso:country":"IT",
    "sg:address":"48018 Faenza",
    "sg:city":"Faenza",
    "sg:orig_category":"Forniture Per Edilizia E Lavori Pubblici",
    "sg:phone":"+39 0546 620989",
    "sg:postcode":"48018",
    "sg:province":"Ravenna",
    "wof:name":"Epoxytecnica Srl",
    "wof:placetype":"venue"
},
  "geometry": {"coordinates":[11.867978096,44.3018722534],"type":"Point"}
}