{
  "type": "Feature",
  "properties": {
    "iso:country":"IT",
    "sg:address":"20122 Milano",
    "sg:city":"Milano",
    "sg:orig_category":"Scuole E Servizi Scolastici. Ricerca, Selezione E Formazione Del Personale. Pubblica Amministrazione",
    "sg:phone":"+39 02 584 5731",
    "sg:postcode":"20122",
    "sg:province":"Milano",
    "wof:name":"Universita' Degli Studi",
    "wof:placetype":"venue"
},
  "geometry": {"coordinates":[9.193972,45.460545],"type":"Point"}
}