{
  "type": "Feature",
  "properties": {
    "iso:country":"IT",
    "sg:address":"40133 Bologna",
    "sg:city":"Bologna",
    "sg:orig_category":"Trattamenti Termici E Superficiali Metalli, Galvanotecnica",
    "sg:phone":"+39 051 560200",
    "sg:postcode":"40133",
    "sg:province":"Bologna",
    "wof:name":"Trame Srl",
    "wof:placetype":"venue"
},
  "geometry": {"coordinates":[11.290395,44.501167],"type":"Point"}
}