{
  "type": "Feature",
  "properties": {
    "iso:country":"IT",
    "sg:address":"00037 Segni",
    "sg:city":"Segni",
    "sg:orig_category":"Agricoltura, Orticoltura E Floricoltura",
    "sg:phone":"+39 06 976 7867",
    "sg:postcode":"00037",
    "sg:province":"Roma",
    "wof:name":"Mondo Animale Di Palazzi Riccardo E C Sas Felice",
    "wof:placetype":"venue"
},
  "geometry": {"coordinates":[12.904542,41.645294],"type":"Point"}
}