{
  "type": "Feature",
  "properties": {
    "iso:country":"IT",
    "sg:address":"Viale Delle Provincie 62; Roma",
    "sg:classifiers":[
        {
            "category":"Banks & Credit Unions",
            "subcategory":"Bank",
            "type":"Services"
        }
    ],
    "sg:phone":"+39 06 4429 1029",
    "wof:name":"Banca Di Roma",
    "wof:placetype":"venue"
},
  "geometry": {"coordinates":[12.520809,41.911221],"type":"Point"}
}