{
  "type": "Feature",
  "properties": {
    "addr:full":"39010 San Martino In Passiria San Martino in Passiria Bolzano/Bozen 39010",
    "addr:postcode":"39010;39010",
    "iso:country":"IT",
    "sg:address":"39010 San Martino In Passiria",
    "sg:city":"San Martino in Passiria",
    "sg:orig_category":"Imprese Di Costruzioni Civili Ed Industriali. Servizi E Lavori Per Ecologia E Smaltimento Rifiuti",
    "sg:phone":"+39 0473 641811",
    "sg:postcode":"39010",
    "sg:province":"Bolzano/Bozen",
    "sg:website":"http://www.maieranton.it",
    "wof:name":"Passeirer Bau G.m.b.h. - Edilpassiria Srl",
    "wof:placetype":"venue"
},
  "geometry": {"coordinates":[11.228463,46.784851],"type":"Point"}
}