{
  "type": "Feature",
  "properties": {
    "iso:country":"IT",
    "sg:address":"41019 Soliera",
    "sg:city":"Soliera",
    "sg:orig_category":"Elettrotecnica Industriale, Prodotti E Apparecchiature",
    "sg:phone":"+39 059 561604",
    "sg:postcode":"41019",
    "sg:province":"Modena",
    "sg:website":"http://www.fimec.it",
    "wof:name":"Fimec Spa",
    "wof:placetype":"venue"
},
  "geometry": {"coordinates":[10.919884,44.764877],"type":"Point"}
}