{
  "type": "Feature",
  "properties": {
    "addr:full":"70016 Noicattaro Noicattaro Bari 70016",
    "addr:postcode":"70016;70016",
    "iso:country":"IT",
    "sg:address":"70016 Noicattaro",
    "sg:city":"Noicattaro",
    "sg:orig_category":"Studi E Consulenze Amministrative, Commerciali E Aziendali. Consulenze Tecniche, Amministrative E Perizie. Professionisti - Studi E Servizi Ed Associazioni Di Interesse Aziendale",
    "sg:phone":"+39 080 478 3437",
    "sg:postcode":"70016",
    "sg:province":"Bari",
    "wof:name":"Studio Liturri Giuseppe",
    "wof:placetype":"venue"
},
  "geometry": {"coordinates":[16.993393,41.038216],"type":"Point"}
}