{
  "type": "Feature",
  "properties": {
    "addr:full":"22066 Mariano Comense Mariano Comense Como 22066",
    "addr:housenumber":"22066",
    "addr:postcode":"22066",
    "iso:country":"IT",
    "sg:address":"22066 Mariano Comense",
    "sg:city":"Mariano Comense",
    "sg:orig_category":"Macchine, Impianti Ed Attrezzature Per Agricoltura E Zootecnia",
    "sg:phone":"+39 031 355 1174",
    "sg:postcode":"22066",
    "sg:province":"Como",
    "wof:name":"Ferro Rosso Spa",
    "wof:placetype":"venue"
},
  "geometry": {"coordinates":[9.173983,45.717331],"type":"Point"}
}