{
  "type": "Feature",
  "properties": {
    "addr:full":"74, Via Valpolicella 37024 Negrar Negrar Verona 37024",
    "addr:postcode":"37024;37024",
    "addr:street":"Via Valpolicella",
    "iso:country":"IT",
    "sg:address":"74, Via Valpolicella 37024 Negrar",
    "sg:city":"Negrar",
    "sg:classifiers":[
        {
            "category":"Parking",
            "subcategory":"Lot",
            "type":"Transportation"
        }
    ],
    "sg:phone":"+39 045 751 3806",
    "sg:postcode":"37024",
    "sg:province":"Verona",
    "sg:tags":[
        "transport",
        "road"
    ],
    "wof:name":"Adami Autotrasporti (s.r.l.)",
    "wof:placetype":"venue"
},
  "geometry": {"coordinates":[10.941113,45.489784],"type":"Point"}
}