{
  "type": "Feature",
  "properties": {
    "iso:country":"IT",
    "sg:address":"41100 Modena",
    "sg:city":"Modena",
    "sg:orig_category":"Lavorazioni Metalli, Stampaggio E Saldatura",
    "sg:phone":"+39 059 370329",
    "sg:postcode":"41100",
    "sg:province":"Modena",
    "wof:name":"Jas Srl",
    "wof:placetype":"venue"
},
  "geometry": {"coordinates":[10.938463,44.667152],"type":"Point"}
}