{
  "type": "Feature",
  "properties": {
    "iso:country":"IT",
    "sg:address":"Localit\u00e0 Paludi 32014 Ponte Nelle Alpi",
    "sg:city":"Ponte nelle Alpi",
    "sg:orig_category":"Stabilization Of Boulders And Loose Rock",
    "sg:phone":"+39 0437 989010",
    "sg:postcode":"32014",
    "sg:province":"Belluno",
    "sg:website":"www.dolomitirocce.it",
    "wof:name":"Dolomiti Rocce Srl",
    "wof:placetype":"venue"
},
  "geometry": {"coordinates":[12.326574,46.151409],"type":"Point"}
}