{
  "type": "Feature",
  "properties": {
    "addr:full":"27, Via Iglesias 20128 Milano Milano Milano 20128",
    "addr:postcode":"20128;20128",
    "addr:street":"Via Iglesias",
    "iso:country":"IT",
    "sg:address":"27, Via Iglesias 20128 Milano",
    "sg:city":"Milano",
    "sg:classifiers":[
        {
            "category":"Manufacturing",
            "subcategory":"Metals",
            "type":"Manufacturing & Wholesale Goods"
        }
    ],
    "sg:phone":"+39 39022575241",
    "sg:postcode":"20128",
    "sg:province":"Milano",
    "sg:tags":[
        "metallurgy",
        "metalworking"
    ],
    "wof:name":"Fi.mo.tec. (s.r.l.)",
    "wof:placetype":"venue"
},
  "geometry": {"coordinates":[9.2307395935,45.5051727295],"type":"Point"}
}