{
  "type": "Feature",
  "properties": {
    "iso:country":"IT",
    "sg:address":"80073 Capri",
    "sg:city":"Capri",
    "sg:classifiers":[
        {
            "category":"Home & Garden",
            "subcategory":"Hardware",
            "type":"Retail Goods"
        }
    ],
    "sg:phone":"+39 081 559 2341",
    "sg:postcode":"80073",
    "sg:province":"Napoli",
    "wof:name":"Kingtool Srl",
    "wof:placetype":"venue"
},
  "geometry": {"coordinates":[14.248315,40.552414],"type":"Point"}
}