{
  "type": "Feature",
  "properties": {
    "addr:full":"34074 Monfalcone Marina julia Gorizia 34074",
    "addr:postcode":"34074;34074",
    "addr:street":"Julia",
    "iso:country":"IT",
    "sg:address":"34074 Monfalcone",
    "sg:city":"Marina julia",
    "sg:orig_category":"Alberghi E Strutture Extra Alberghiere",
    "sg:phone":"+39 0481 40561",
    "sg:postcode":"34074",
    "sg:province":"Gorizia",
    "wof:name":"Albatros Villaggio Turistico",
    "wof:placetype":"venue"
},
  "geometry": {"coordinates":[13.527518,45.776573],"type":"Point"}
}