{
  "type": "Feature",
  "properties": {
    "iso:country":"IT",
    "sg:address":"72100 Brindisi",
    "sg:city":"Brindisi",
    "sg:orig_category":"Prodotti Alimentari",
    "sg:phone":"+39 0831 523908",
    "sg:postcode":"72100",
    "sg:province":"Brindisi",
    "wof:name":"Rizzo Elsa Erboristeria Hamamelis",
    "wof:placetype":"venue"
},
  "geometry": {"coordinates":[17.9356536865,40.6332397461],"type":"Point"}
}