{
  "type": "Feature",
  "properties": {
    "addr:full":"00186 Roma Roma Roma 00186",
    "addr:postcode":"00186;00186",
    "iso:country":"IT",
    "sg:address":"00186 Roma",
    "sg:city":"Roma",
    "sg:orig_category":"Elettrotecnica Industriale, Prodotti E Apparecchiature. Ricambi E Componenti Dei Mezzi Di Trasporto",
    "sg:phone":"+39 06 679 1965",
    "sg:postcode":"00186",
    "sg:province":"Roma",
    "wof:name":"Gambelli Batterie",
    "wof:placetype":"venue"
},
  "geometry": {"coordinates":[12.483185,41.888233],"type":"Point"}
}