{
  "type": "Feature",
  "properties": {
    "iso:country":"IT",
    "sg:address":"00192 Roma",
    "sg:city":"Roma",
    "sg:classifiers":[
        {
            "category":"Shopping",
            "subcategory":"Bicycles & Sporting Goods",
            "type":"Retail Goods"
        }
    ],
    "sg:phone":"+39 06 324 3401",
    "sg:postcode":"00192",
    "sg:province":"Roma",
    "sg:tags":[
        "tempo",
        "lo",
        "-",
        "libero",
        "per",
        "servizi",
        "forniture",
        "articoli",
        "e",
        "sport",
        "il"
    ],
    "sg:website":"http://www.bertiottica.com",
    "wof:name":"Berti Optometria Srl",
    "wof:placetype":"venue"
},
  "geometry": {"coordinates":[12.462566,41.910435],"type":"Point"}
}