{
  "type": "Feature",
  "properties": {
    "addr:full":"10137 Torino Torino Torino 10137",
    "addr:postcode":"10137;10137",
    "iso:country":"IT",
    "sg:address":"10137 Torino",
    "sg:city":"Torino",
    "sg:orig_category":"Tessuti Arredamento, Tende E Tappeti",
    "sg:phone":"+39 011 355234",
    "sg:postcode":"10137",
    "sg:province":"Torino",
    "wof:name":"Arduino Di Arduino Mario E Manassero Silvia (s.n.c.)",
    "wof:placetype":"venue"
},
  "geometry": {"coordinates":[7.644061,45.042416],"type":"Point"}
}