{
  "type": "Feature",
  "properties": {
    "iso:country":"IT",
    "sg:address":"23, Viale Europa 31018 Gaiarine",
    "sg:city":"Gaiarine",
    "sg:classifiers":[
        {
            "category":"Home & Garden",
            "subcategory":"Home Furnishings",
            "type":"Retail Goods"
        }
    ],
    "sg:phone":"+39 39043475029",
    "sg:postcode":"31018",
    "sg:province":"Treviso",
    "sg:tags":[
        "household"
    ],
    "wof:name":"De Carlo (s.r.l.)",
    "wof:placetype":"venue"
},
  "geometry": {"coordinates":[12.513537,45.882374],"type":"Point"}
}