{
  "type": "Feature",
  "properties": {
    "iso:country":"IT",
    "sg:address":"20121 Milano",
    "sg:city":"Milano",
    "sg:orig_category":"Avvocati - Studi",
    "sg:phone":"+39 02 624 9981",
    "sg:postcode":"20121",
    "sg:province":"Milano",
    "wof:name":"Studio Professionale Associato Gft & Partners",
    "wof:placetype":"venue"
},
  "geometry": {"coordinates":[9.195054,45.472778],"type":"Point"}
}