{
  "type": "Feature",
  "properties": {
    "iso:country":"IT",
    "sg:address":"18100 Imperia",
    "sg:city":"Imperia",
    "sg:orig_category":"Impiantistica E Prodotti Tecnologici Per Edilizia. Termotecnica E Riscaldamento, Apparecchiature E Servizi",
    "sg:phone":"+39 0183 710890",
    "sg:postcode":"18100",
    "sg:province":"Imperia",
    "wof:name":"C.m.a. Srl",
    "wof:placetype":"venue"
},
  "geometry": {"coordinates":[8.022969,43.882839],"type":"Point"}
}