{
  "type": "Feature",
  "properties": {
    "iso:country":"IT",
    "sg:address":"81025 Marcianise",
    "sg:city":"Marcianise",
    "sg:orig_category":"Pompe",
    "sg:phone":"+39 0823 821533",
    "sg:postcode":"81025",
    "sg:province":"Caserta",
    "wof:name":"Worthington Spa",
    "wof:placetype":"venue"
},
  "geometry": {"coordinates":[14.2977428436,41.0152359009],"type":"Point"}
}