{
  "type": "Feature",
  "properties": {
    "iso:country":"IT",
    "sg:address":"00192 Roma",
    "sg:city":"Roma",
    "sg:orig_category":"Articoli Per Imballaggio E Confezionamento",
    "sg:phone":"+39 06 3972 0847",
    "sg:postcode":"00192",
    "sg:province":"Roma",
    "wof:name":"Marucci Sas",
    "wof:placetype":"venue"
},
  "geometry": {"coordinates":[12.451506,41.908001],"type":"Point"}
}