{
  "type": "Feature",
  "properties": {
    "addr:full":"00181 Roma Roma Roma 00181",
    "addr:postcode":"00181;00181",
    "iso:country":"IT",
    "sg:address":"00181 Roma",
    "sg:city":"Roma",
    "sg:orig_category":"Ospedali E Servizi Sanitari. Centri Di Estetica E Cosmesi E Servizi",
    "sg:phone":"+39 06 782 4987",
    "sg:postcode":"00181",
    "sg:province":"Roma",
    "wof:name":"Masini Gloria Barbara",
    "wof:placetype":"venue"
},
  "geometry": {"coordinates":[12.523922,41.87524],"type":"Point"}
}