{
  "type": "Feature",
  "properties": {
    "iso:country":"IT",
    "sg:address":"25071 Agnosine",
    "sg:city":"Agnosine",
    "sg:orig_category":"Assemblaggio Conto Terzi",
    "sg:phone":"+39 036 589 6195",
    "sg:postcode":"25071",
    "sg:province":"Brescia",
    "sg:website":"http://www.ferremi.it",
    "wof:name":"Ferremi Ugo & C. Snc",
    "wof:placetype":"venue"
},
  "geometry": {"coordinates":[10.348217,45.639217],"type":"Point"}
}