{
  "type": "Feature",
  "properties": {
    "addr:full":"24047 Treviglio Treviglio Bergamo 24047",
    "addr:postcode":"24047;24047",
    "iso:country":"IT",
    "sg:address":"24047 Treviglio",
    "sg:city":"Treviglio",
    "sg:orig_category":"Forniture Per Abbigliamento E Pelletterie",
    "sg:phone":"+39 036 341 9295",
    "sg:postcode":"24047",
    "sg:province":"Bergamo",
    "wof:name":"Chiesa San Francesco",
    "wof:placetype":"venue"
},
  "geometry": {"coordinates":[9.6026515961,45.5463066101],"type":"Point"}
}