{
  "type": "Feature",
  "properties": {
    "addr:full":"14049 Nizza Monferrato Nizza Monferrato Asti 14049",
    "addr:postcode":"14049;14049",
    "iso:country":"IT",
    "sg:address":"14049 Nizza Monferrato",
    "sg:city":"Nizza Monferrato",
    "sg:orig_category":"Prodotti Di Base E Forniture Per Industria Alimentare E Bevande. Vetro: Prodotti E Lavorazioni. Articoli Per Imballaggio E Confezionamento",
    "sg:phone":"+39 0141 721707",
    "sg:postcode":"14049",
    "sg:province":"Asti",
    "wof:name":"Vetrerie Ricci Di Ricci & C. (s.n.c.)",
    "wof:placetype":"venue"
},
  "geometry": {"coordinates":[8.3086423874,44.8265953064],"type":"Point"}
}