{
  "type": "Feature",
  "properties": {
    "iso:country":"IT",
    "sg:address":"59, Via Della Pergola 23900 Lecco",
    "sg:city":"Lecco",
    "sg:classifiers":[
        {
            "category":"Shopping",
            "type":"Retail Goods"
        }
    ],
    "sg:phone":"+39 0341 369150",
    "sg:postcode":"23900",
    "sg:province":"Lecco",
    "sg:tags":[
        "finished",
        "-",
        "metallic"
    ],
    "wof:name":"Anghileri Eufrasio Srl Ferro Tubi Lamiere Srl - Ae Srl",
    "wof:placetype":"venue"
},
  "geometry": {"coordinates":[9.4070472717,45.8431282043],"type":"Point"}
}