{
  "type": "Feature",
  "properties": {
    "addr:full":"45100 Rovigo Rovigo Rovigo 45100",
    "addr:postcode":"45100;45100",
    "iso:country":"IT",
    "sg:address":"45100 Rovigo",
    "sg:city":"Rovigo",
    "sg:orig_category":"Servizi E Lavori Per Agricoltura E Zootecnia. Servizi Ausiliari Di Analisi, Controllo E Ricerca",
    "sg:phone":"+39 0425 360113",
    "sg:postcode":"45100",
    "sg:province":"Rovigo",
    "wof:name":"Istituto Sperimentale Per Le Colture Industriali",
    "wof:placetype":"venue"
},
  "geometry": {"coordinates":[11.727038,45.078667],"type":"Point"}
}