{
  "type": "Feature",
  "properties": {
    "iso:country":"IT",
    "sg:address":"20049 Concorezzo",
    "sg:city":"Concorezzo",
    "sg:orig_category":"Materiali Edili",
    "sg:phone":"+39 039 604 0024",
    "sg:postcode":"20049",
    "sg:province":"Milano",
    "wof:name":"Ferrario Costante & C. Di Ferrario Diego",
    "wof:placetype":"venue"
},
  "geometry": {"coordinates":[9.32721,45.582657],"type":"Point"}
}