{
  "type": "Feature",
  "properties": {
    "iso:country":"IT",
    "sg:address":"20124 Milano",
    "sg:city":"Milano",
    "sg:orig_category":"Macchine, Impianti Ed Attrezzature Per Abbigliamento E Pelletterie",
    "sg:phone":"+39 02 6749 3615",
    "sg:postcode":"20124",
    "sg:province":"Milano",
    "wof:name":"Inter Busuness Net",
    "wof:placetype":"venue"
},
  "geometry": {"coordinates":[9.203011,45.483749],"type":"Point"}
}