{
  "type": "Feature",
  "properties": {
    "iso:country":"IT",
    "sg:address":"20131 Milano",
    "sg:city":"Milano",
    "sg:orig_category":"Chiese Ed Associazioni Religiose",
    "sg:phone":"+39 02 2682 9578",
    "sg:postcode":"20131",
    "sg:province":"Milano",
    "wof:name":"Pie Ancelle Della Provvidenza",
    "wof:placetype":"venue"
},
  "geometry": {"coordinates":[9.225422,45.487057],"type":"Point"}
}