{
  "type": "Feature",
  "properties": {
    "iso:country":"IT",
    "sg:address":"00187 Roma",
    "sg:city":"Roma",
    "sg:orig_category":"Automobili E Mezzi Di Trasporto",
    "sg:phone":"+39 06 4202 0664",
    "sg:postcode":"00187",
    "sg:province":"Roma",
    "wof:name":"Wasteels International Italia S.r.l.",
    "wof:placetype":"venue"
},
  "geometry": {"coordinates":[12.488222,41.906181],"type":"Point"}
}