{
  "type": "Feature",
  "properties": {
    "iso:country":"IT",
    "sg:address":"24050 Cortenuova",
    "sg:city":"Cortenuova",
    "sg:orig_category":"Forniture Per Abbigliamento E Pelletterie",
    "sg:phone":"+39 036 399 2155",
    "sg:postcode":"24050",
    "sg:province":"Bergamo",
    "wof:name":"Lanfranchi Giovanni (s.p.a.)",
    "wof:placetype":"venue"
},
  "geometry": {"coordinates":[9.683599472,45.6381072998],"type":"Point"}
}