{
  "type": "Feature",
  "properties": {
    "iso:country":"IT",
    "sg:address":"20048 Carate Brianza",
    "sg:city":"Carate Brianza",
    "sg:orig_category":"Trattamenti Termici E Superficiali Metalli, Galvanotecnica",
    "sg:phone":"+39 036 299 3572",
    "sg:postcode":"20048",
    "sg:province":"Milano",
    "wof:name":"Oxsa S.r.l.",
    "wof:placetype":"venue"
},
  "geometry": {"coordinates":[9.237514,45.665421],"type":"Point"}
}