{
  "type": "Feature",
  "properties": {
    "addr:full":"50142 Firenze Firenze Firenze 50142",
    "addr:postcode":"50142;50142",
    "iso:country":"IT",
    "sg:address":"50142 Firenze",
    "sg:city":"Firenze",
    "sg:orig_category":"Forniture Alle Strutture Ricettive. Forniture Per Attivita' Commerciali Ed Artigianali",
    "sg:phone":"+39 055 783263",
    "sg:postcode":"50142",
    "sg:province":"Firenze",
    "sg:website":"http://www.bartalesiguido.it",
    "wof:name":"Bartalesi Guido Srl",
    "wof:placetype":"venue"
},
  "geometry": {"coordinates":[11.1918182373,43.7751235962],"type":"Point"}
}