{
  "type": "Feature",
  "properties": {
    "iso:country":"IT",
    "sg:address":"00157 Roma",
    "sg:city":"Roma",
    "sg:orig_category":"Riparazione Dei Mezzi Di Trasporto",
    "sg:phone":"+39 06 418 2073",
    "sg:postcode":"00157",
    "sg:province":"Roma",
    "wof:name":"Antonacci Siro & Vitali Massimiliano Snc",
    "wof:placetype":"venue"
},
  "geometry": {"coordinates":[12.542283,41.913677],"type":"Point"}
}