{
  "type": "Feature",
  "properties": {
    "iso:country":"IT",
    "sg:address":"765, Via Settignano 03042 Atina",
    "sg:city":"Atina",
    "sg:classifiers":[
        {
            "category":"Shopping",
            "subcategory":"Stationery & Office Supplies",
            "type":"Retail Goods"
        }
    ],
    "sg:phone":"+39 0776 691321",
    "sg:postcode":"03042",
    "sg:province":"Frosinone",
    "sg:tags":[
        "professional"
    ],
    "wof:name":"Imarconte Steel S.r.l.",
    "wof:placetype":"venue"
},
  "geometry": {"coordinates":[13.7676115036,41.6346168518],"type":"Point"}
}