{
  "type": "Feature",
  "properties": {
    "iso:country":"IT",
    "sg:address":"66026 Ortona",
    "sg:city":"Ortona",
    "sg:orig_category":"Prodotti Di Base E Forniture Per Industria Alimentare E Bevande. Carta, Cartone E Prodotti Primari. Forniture Per Attivita' Commerciali Ed Artigianali",
    "sg:phone":"+39 085 906 6212",
    "sg:postcode":"66026",
    "sg:province":"Chieti",
    "wof:name":"Di Deo Pierluigi",
    "wof:placetype":"venue"
},
  "geometry": {"coordinates":[14.3675527573,42.3349189758],"type":"Point"}
}