{
  "type": "Feature",
  "properties": {
    "addr:full":"Via Abbeveratioia 65/b; Parma",
    "addr:housenumber":"65 / b",
    "addr:street":"Via Abbeveratioia",
    "iso:country":"IT",
    "sg:address":"Via Abbeveratioia 65/b; Parma",
    "sg:classifiers":[
        {
            "category":"Banks & Credit Unions",
            "subcategory":"Bank",
            "type":"Services"
        }
    ],
    "sg:phone":"+39 0521 980503",
    "wof:name":"Credito Bergamasco Spa",
    "wof:placetype":"venue"
},
  "geometry": {"coordinates":[10.305518,44.798721],"type":"Point"}
}