{
  "type": "Feature",
  "properties": {
    "addr:full":"Via Dell'industria 22 33043 Cividale Del Friuli Cividale del Friuli Udine 33043",
    "addr:housenumber":"22",
    "addr:postcode":"33043;33043",
    "addr:street":"Via Dell'Industria",
    "iso:country":"IT",
    "sg:address":"Via Dell'industria 22 33043 Cividale Del Friuli",
    "sg:city":"Cividale del Friuli",
    "sg:classifiers":[
        {
            "category":"Manufacturing",
            "subcategory":"Motor Vehicles & Parts",
            "type":"Manufacturing & Wholesale Goods"
        }
    ],
    "sg:phone":"+39 0432 705111",
    "sg:postcode":"33043",
    "sg:province":"Udine",
    "sg:tags":[
        "cooling",
        "unit",
        "refrigerating",
        "evaporators"
    ],
    "sg:website":"www.cgaspa.it",
    "wof:name":"Cga Compagnia Generale Alluminio Spa",
    "wof:placetype":"venue"
},
  "geometry": {"coordinates":[13.230724,46.064941],"type":"Point"}
}