{
  "type": "Feature",
  "properties": {
    "iso:country":"IT",
    "sg:address":"Via Roma 73; Trigolo; 26018",
    "sg:city":"Trigolo",
    "sg:classifiers":[
        {
            "category":"Banks & Credit Unions",
            "subcategory":"Bank",
            "type":"Services"
        }
    ],
    "sg:phone":"+39 0374 370123",
    "sg:postcode":"26018",
    "sg:province":"Cremona",
    "wof:name":"Cassa Di Risparmio Di Parma, E Piacenza Spa",
    "wof:placetype":"venue"
},
  "geometry": {"coordinates":[9.816751,45.328335],"type":"Point"}
}