{
  "type": "Feature",
  "properties": {
    "addr:full":"20129 Milano Milano Milano 20129",
    "addr:postcode":"20129;20129",
    "iso:country":"IT",
    "sg:address":"20129 Milano",
    "sg:city":"Milano",
    "sg:orig_category":"Servizi Vari Di Interesse Pubblico",
    "sg:phone":"+39 02 2940 0688",
    "sg:postcode":"20129",
    "sg:province":"Milano",
    "wof:name":"Maga Vera",
    "wof:placetype":"venue"
},
  "geometry": {"coordinates":[9.211876,45.479572],"type":"Point"}
}