{
  "type": "Feature",
  "properties": {
    "iso:country":"IT",
    "sg:address":"15048 Valenza",
    "sg:city":"Valenza",
    "sg:orig_category":"Gioielleria, Oreficeria E Argenteria",
    "sg:phone":"+39 0131 945700",
    "sg:postcode":"15048",
    "sg:province":"Alessandria",
    "sg:website":"http://www.raima.it",
    "wof:name":"Raima Srl",
    "wof:placetype":"venue"
},
  "geometry": {"coordinates":[8.641449,45.019276],"type":"Point"}
}