{
  "type": "Feature",
  "properties": {
    "addr:full":"20156 Milano Milano Milano 20156",
    "addr:postcode":"20156;20156",
    "iso:country":"IT",
    "sg:address":"20156 Milano",
    "sg:city":"Milano",
    "sg:orig_category":"Arredo Bagno Ed Idrosanitari. Elettrodomestici",
    "sg:phone":"+39 02 325768",
    "sg:postcode":"20156",
    "sg:province":"Milano",
    "wof:name":"A.a.a. Di Gangi Giuseppe",
    "wof:placetype":"venue"
},
  "geometry": {"coordinates":[9.134976,45.502777],"type":"Point"}
}