{
  "type": "Feature",
  "properties": {
    "addr:full":"Via Volturno, 2c; Rome; 00185 Roma 00185",
    "addr:housenumber":"2c",
    "addr:postcode":"00185;00185",
    "addr:street":"Via Volturno",
    "iso:country":"IT",
    "sg:address":"Via Volturno, 2c; Rome; 00185",
    "sg:classifiers":[
        {
            "category":"Travel",
            "subcategory":"Travel Agent",
            "type":"Entertainment"
        }
    ],
    "sg:phone":"+39 390 648 9020",
    "sg:postcode":"00185",
    "sg:province":"Roma",
    "sg:website":"www.gartour.net",
    "wof:name":"Gartour Incoming Operator",
    "wof:placetype":"venue"
},
  "geometry": {"coordinates":[12.499087,41.90498],"type":"Point"}
}