{
  "type": "Feature",
  "properties": {
    "addr:full":"23871 Lomagna Lomagna Lecco 23871",
    "addr:postcode":"23871;23871",
    "iso:country":"IT",
    "sg:address":"23871 Lomagna",
    "sg:city":"Lomagna",
    "sg:orig_category":"Motori Ed Organi Di Trasmissione. Ricambi E Componenti Dei Mezzi Di Trasporto",
    "sg:phone":"+39 039 927 8068",
    "sg:postcode":"23871",
    "sg:province":"Lecco",
    "wof:name":"Partnet Srl",
    "wof:placetype":"venue"
},
  "geometry": {"coordinates":[9.3789644241,45.6688079834],"type":"Point"}
}