{
  "type": "Feature",
  "properties": {
    "iso:country":"IT",
    "sg:address":"30013 Venezia",
    "sg:city":"Cavallino",
    "sg:orig_category":"Carni, Salumi E Pesci",
    "sg:phone":"+39 041 968155",
    "sg:postcode":"30013",
    "sg:province":"Venezia",
    "wof:name":"Ittica Center Sas Di Bozzato Rudi & C.",
    "wof:placetype":"venue"
},
  "geometry": {"coordinates":[12.550079,45.480343],"type":"Point"}
}