{
  "type": "Feature",
  "properties": {
    "iso:country":"IT",
    "sg:address":"Via Donizetti 11; Marina Di Pietrasanta; 55044",
    "sg:classifiers":[
        {
            "category":"Banks & Credit Unions",
            "subcategory":"Bank",
            "type":"Services"
        }
    ],
    "sg:phone":"+39 0584 55044",
    "wof:name":"Cassa Rurale Ed Artigiana, Di Pietrasanta",
    "wof:placetype":"venue"
},
  "geometry": {"coordinates":[10.20049,43.927414],"type":"Point"}
}