{
  "type": "Feature",
  "properties": {
    "iso:country":"IT",
    "sg:address":"22100 Como",
    "sg:city":"Como",
    "sg:orig_category":"Articoli Medico-sanitari Ed Ortopedici",
    "sg:phone":"+39 031 268522",
    "sg:postcode":"22100",
    "sg:province":"Como",
    "wof:name":"Ottica Codato",
    "wof:placetype":"venue"
},
  "geometry": {"coordinates":[9.122934,45.74884],"type":"Point"}
}