{
  "type": "Feature",
  "properties": {
    "addr:full":"42048 Rubiera Reggio Nell'Emilia 42048",
    "addr:postcode":"42048;42048",
    "iso:country":"IT",
    "sg:address":"42048 Rubiera",
    "sg:orig_category":"Generatori Aria Calda E Vapore",
    "sg:phone":"+39 0522 620941",
    "sg:postcode":"42048",
    "sg:province":"Reggio Nell'Emilia",
    "wof:name":"Mec To Srl",
    "wof:placetype":"venue"
},
  "geometry": {"coordinates":[10.792078,44.656776],"type":"Point"}
}