{
  "type": "Feature",
  "properties": {
    "iso:country":"IT",
    "sg:address":"4, Via S. Maria Grazie 80017 Melito Di Napoli",
    "sg:city":"Melito di Napoli",
    "sg:classifiers":[
        {
            "category":"Wholesale",
            "subcategory":"Machinery & Supplies",
            "type":"Manufacturing & Wholesale Goods"
        }
    ],
    "sg:phone":"+39 081 711 1953",
    "sg:postcode":"80017",
    "sg:province":"Napoli",
    "sg:tags":[
        "equipment",
        "-",
        "instrument",
        "measurement"
    ],
    "wof:name":"Fresmec Sud",
    "wof:placetype":"venue"
},
  "geometry": {"coordinates":[14.251636,40.840096],"type":"Point"}
}