{
  "type": "Feature",
  "properties": {
    "iso:country":"IT",
    "sg:address":"1, Via Della Marzorata 20011 Corbetta",
    "sg:city":"Corbetta",
    "sg:classifiers":[
        {
            "category":"Manufacturing",
            "subcategory":"Rubber & Plastics",
            "type":"Manufacturing & Wholesale Goods"
        }
    ],
    "sg:phone":"+39 02 9727 1848",
    "sg:postcode":"20011",
    "sg:province":"Milano",
    "wof:name":"Nord Pneumatici Spa",
    "wof:placetype":"venue"
},
  "geometry": {"coordinates":[8.959912,45.463505],"type":"Point"}
}