{
  "type": "Feature",
  "properties": {
    "iso:country":"IT",
    "sg:address":"34146 Trieste",
    "sg:city":"Trieste",
    "sg:orig_category":"Campeggio, Tende, Attrezzature Ed Articoli - Vendita Al Dettaglio",
    "sg:phone":"+39 040 810387",
    "sg:postcode":"34146",
    "sg:province":"Trieste",
    "sg:website":"http://www.motorcaravantrieste.com",
    "wof:name":"Motorcaravan Trieste",
    "wof:placetype":"venue"
},
  "geometry": {"coordinates":[13.791993,45.63245],"type":"Point"}
}