{
  "type": "Feature",
  "properties": {
    "addr:full":"Via Don Eugenio Bruno 27 10029 Villastellone Villastellone Torino 10029",
    "addr:housenumber":"27",
    "addr:postcode":"10029;10029",
    "addr:street":"Via Don Eugenio Bruno",
    "iso:country":"IT",
    "sg:address":"Via Don Eugenio Bruno 27 10029 Villastellone",
    "sg:city":"Villastellone",
    "sg:classifiers":[
        {
            "category":"Arts & Performance",
            "subcategory":"Music",
            "type":"Entertainment"
        }
    ],
    "sg:phone":"+39 011 961 0014",
    "sg:postcode":"10029",
    "sg:province":"Torino",
    "sg:tags":[
        "pattern"
    ],
    "wof:name":"Mabert Srl",
    "wof:placetype":"venue"
},
  "geometry": {"coordinates":[7.727889061,44.9324188232],"type":"Point"}
}