{
  "type": "Feature",
  "properties": {
    "iso:country":"IT",
    "sg:address":"40033 Casalecchio Di Reno",
    "sg:city":"Casalecchio di Reno",
    "sg:orig_category":"Lavorazioni Metalli, Stampaggio E Saldatura",
    "sg:phone":"+39 051 592704",
    "sg:postcode":"40033",
    "sg:province":"Bologna",
    "wof:name":"G. E G. Snc",
    "wof:placetype":"venue"
},
  "geometry": {"coordinates":[11.27194,44.462467],"type":"Point"}
}