{
  "type": "Feature",
  "properties": {
    "addr:full":"Trav. I, Zanica 24050 Grassobbio Grassobbio Bergamo 24050",
    "addr:postcode":"24050;24050",
    "addr:street":"I Zanica",
    "iso:country":"IT",
    "sg:address":"Trav. I, Zanica 24050 Grassobbio",
    "sg:city":"Grassobbio",
    "sg:classifiers":[
        {
            "category":"Shopping",
            "type":"Retail Goods"
        }
    ],
    "sg:phone":"+39 39035335225",
    "sg:postcode":"24050",
    "sg:province":"Bergamo",
    "sg:tags":[
        "finished",
        "-",
        "metallic"
    ],
    "sg:website":"http://www.crstampi.it",
    "wof:name":"C.r. Stampi Srl",
    "wof:placetype":"venue"
},
  "geometry": {"coordinates":[9.6699523926,45.6949043274],"type":"Point"}
}