{
  "type": "Feature",
  "properties": {
    "iso:country":"IT",
    "sg:address":"Via Locatelli 94 20046 Biassono",
    "sg:city":"Biassono",
    "sg:classifiers":[
        {
            "category":"Transit Center",
            "subcategory":"Freight",
            "type":"Transportation"
        }
    ],
    "sg:phone":"+39 039 491605",
    "sg:postcode":"20046",
    "sg:province":"Milano",
    "sg:tags":[
        "eye",
        "cosmetic"
    ],
    "wof:name":"Officina Cosmetica Europea Oce Srl",
    "wof:placetype":"venue"
},
  "geometry": {"coordinates":[9.266484,45.62524],"type":"Point"}
}