{
  "type": "Feature",
  "properties": {
    "iso:country":"IT",
    "sg:address":"20, Via Dominutti Alberto 37135 Verona",
    "sg:city":"Verona",
    "sg:classifiers":[
        {
            "category":"Professional",
            "subcategory":"Computer Services",
            "type":"Services"
        }
    ],
    "sg:phone":"+39 045 800 3671",
    "sg:postcode":"37135",
    "sg:province":"Verona",
    "sg:tags":[
        "information",
        "technology"
    ],
    "wof:name":"La Tecnica S.r.l.",
    "wof:placetype":"venue"
},
  "geometry": {"coordinates":[10.991748,45.438366],"type":"Point"}
}