{
  "type": "Feature",
  "properties": {
    "addr:full":"41049 Sassuolo Sassuolo Modena 41049",
    "addr:postcode":"41049;41049",
    "iso:country":"IT",
    "sg:address":"41049 Sassuolo",
    "sg:city":"Sassuolo",
    "sg:orig_category":"Termotecnica E Riscaldamento, Apparecchiature E Servizi",
    "sg:phone":"+39 0536 980971",
    "sg:postcode":"41049",
    "sg:province":"Modena",
    "wof:name":"General (s.r.l.)",
    "wof:placetype":"venue"
},
  "geometry": {"coordinates":[10.851196,44.57896],"type":"Point"}
}