{
  "type": "Feature",
  "properties": {
    "addr:full":"35, Via Carretta 31040 Nervesa Della Battaglia Nervesa della Battaglia Treviso 31040",
    "addr:housenumber":"della",
    "addr:postcode":"31040;31040",
    "addr:street":"Via Carretta;Treviso",
    "iso:country":"IT",
    "sg:address":"35, Via Carretta 31040 Nervesa Della Battaglia",
    "sg:city":"Nervesa della Battaglia",
    "sg:classifiers":[
        {
            "category":"Food & Beverages",
            "subcategory":"Groceries & Convenience Stores",
            "type":"Retail Goods"
        }
    ],
    "sg:phone":"+39 0422 771017",
    "sg:postcode":"31040",
    "sg:province":"Treviso",
    "sg:tags":[
        "product",
        "related"
    ],
    "wof:name":"Azienda Agricola Montello Di Colomberotto Tommaso & C. (s.n.c.)",
    "wof:placetype":"venue"
},
  "geometry": {"coordinates":[12.1524524689,45.8364639282],"type":"Point"}
}