{
  "type": "Feature",
  "properties": {
    "addr:full":"8, Via Benini Rocco 50013 Campi Bisenzio Campi Bisenzio Firenze 50013",
    "addr:postcode":"50013;50013",
    "addr:street":"Via Benini Rocco;Bisenzio",
    "iso:country":"IT",
    "sg:address":"8, Via Benini Rocco 50013 Campi Bisenzio",
    "sg:city":"Campi Bisenzio",
    "sg:classifiers":[
        {
            "category":"Shopping",
            "subcategory":"Clothing, Apparel, & Fashions",
            "type":"Retail Goods"
        }
    ],
    "sg:phone":"+39 39055894061",
    "sg:postcode":"50013",
    "sg:province":"Firenze",
    "sg:tags":[
        "clothes"
    ],
    "wof:name":"Maglificio Baroni Spa",
    "wof:placetype":"venue"
},
  "geometry": {"coordinates":[11.119177,43.827705],"type":"Point"}
}