{
  "type": "Feature",
  "properties": {
    "iso:country":"IT",
    "sg:address":"31050 Ponzano Veneto",
    "sg:city":"Ponzano Veneto",
    "sg:classifiers":[
        {
            "category":"Restaurant",
            "type":"Food & Drink"
        }
    ],
    "sg:phone":"+39 0422 9641",
    "sg:postcode":"31050",
    "sg:province":"Treviso",
    "sg:tags":[
        "auxiliary",
        "entertainment",
        "premises",
        "related",
        "catering",
        "similar",
        "public",
        "restaurants"
    ],
    "sg:website":"http://www.relaismonaco.it",
    "wof:name":"Relais Monaco Srl",
    "wof:placetype":"venue"
},
  "geometry": {"coordinates":[12.199465,45.727055],"type":"Point"}
}