{
  "type": "Feature",
  "properties": {
    "iso:country":"IT",
    "sg:address":"10, V. Albana Vicolo 81055 Santa Maria Capua Vetere",
    "sg:city":"Santa Maria Capua Vetere",
    "sg:classifiers":[
        {
            "category":"Manufacturing",
            "subcategory":"Tools & Machinery",
            "type":"Manufacturing & Wholesale Goods"
        }
    ],
    "sg:phone":"+39 0823 840636",
    "sg:postcode":"81055",
    "sg:province":"Caserta",
    "sg:tags":[
        "environment",
        "equipment",
        "-"
    ],
    "sg:website":"http://www.paginegialle.it/geoinrobertosimeone",
    "wof:name":"Geo.in Di Roberto Geologo Simeone",
    "wof:placetype":"venue"
},
  "geometry": {"coordinates":[14.260363,41.076839],"type":"Point"}
}