{
  "type": "Feature",
  "properties": {
    "iso:country":"IT",
    "sg:address":"Via Fermi 53 33010 Feletto Umberto",
    "sg:city":"Feletto Umberto",
    "sg:orig_category":"Menswear, Suits, Trousers, Sports Jackets",
    "sg:phone":"+39 0432 570765",
    "sg:postcode":"33010",
    "sg:province":"Udine",
    "wof:name":"Marchiol Luciano & C Sas",
    "wof:placetype":"venue"
},
  "geometry": {"coordinates":[13.2210159302,46.1058998108],"type":"Point"}
}