{
  "type": "Feature",
  "properties": {
    "addr:full":"20092 Cinisello Balsamo Cinisello Balsamo Milano 20092",
    "addr:postcode":"20092;20092",
    "iso:country":"IT",
    "sg:address":"20092 Cinisello Balsamo",
    "sg:city":"Cinisello Balsamo",
    "sg:orig_category":"Forniture Per Edilizia E Lavori Pubblici. Forniture Per Attivita' Industriali",
    "sg:phone":"+39 02 6601 2159",
    "sg:postcode":"20092",
    "sg:province":"Milano",
    "wof:name":"Dell'orto Fabio",
    "wof:placetype":"venue"
},
  "geometry": {"coordinates":[9.2305431366,45.5330314636],"type":"Point"}
}