{
  "type": "Feature",
  "properties": {
    "addr:full":"51036 Larciano Larciano Pistoia 51036",
    "addr:postcode":"51036;51036",
    "iso:country":"IT",
    "sg:address":"51036 Larciano",
    "sg:city":"Larciano",
    "sg:orig_category":"Articoli Pulizia",
    "sg:phone":"+39 0573 83025",
    "sg:postcode":"51036",
    "sg:province":"Pistoia",
    "wof:name":"Home Line Srl",
    "wof:placetype":"venue"
},
  "geometry": {"coordinates":[10.918368,43.928497],"type":"Point"}
}