{
  "type": "Feature",
  "properties": {
    "iso:country":"IT",
    "sg:address":"00184 Roma",
    "sg:city":"Roma",
    "sg:orig_category":"Chiese Ed Associazioni Religiose",
    "sg:phone":"+39 06 4782 5757",
    "sg:postcode":"00184",
    "sg:province":"Roma",
    "wof:name":"Comunita' Israelitica Di Roma",
    "wof:placetype":"venue"
},
  "geometry": {"coordinates":[12.49429,41.897713],"type":"Point"}
}