{
  "type": "Feature",
  "properties": {
    "addr:full":"50135 Firenze Firenze Firenze 50135",
    "addr:postcode":"50135;50135",
    "iso:country":"IT",
    "sg:address":"50135 Firenze",
    "sg:city":"Firenze",
    "sg:orig_category":"Caravans, Campers, Roulottes E Accessori",
    "sg:phone":"+39 055 613459",
    "sg:postcode":"50135",
    "sg:province":"Firenze",
    "wof:name":"New L.a.s.e.r. Srl",
    "wof:placetype":"venue"
},
  "geometry": {"coordinates":[11.314745,43.775883],"type":"Point"}
}