{
  "type": "Feature",
  "properties": {
    "addr:full":"20154 Milano Milano Milano 20154",
    "addr:postcode":"20154;20154",
    "iso:country":"IT",
    "sg:address":"20154 Milano",
    "sg:city":"Milano",
    "sg:orig_category":"Prodotti Vari In Metallo. Articoli Per Imballaggio E Confezionamento",
    "sg:postcode":"20154",
    "sg:province":"Milano",
    "wof:name":"I.n.c.a. Industria Nazionale Cosmetici Affini (s.r.l.)",
    "wof:placetype":"venue"
},
  "geometry": {"coordinates":[9.1656723022,45.4813117981],"type":"Point"}
}