{
  "type": "Feature",
  "properties": {
    "addr:full":"41012 Carpi Carpi Modena 41012",
    "addr:postcode":"41012;41012",
    "iso:country":"IT",
    "sg:address":"41012 Carpi",
    "sg:city":"Carpi",
    "sg:classifiers":[
        {
            "category":"Banks & Credit Unions",
            "subcategory":"Bank",
            "type":"Services"
        }
    ],
    "sg:phone":"+39 059 652589",
    "sg:postcode":"41012",
    "sg:province":"Modena",
    "sg:tags":[
        "services",
        "publishing",
        "supply"
    ],
    "wof:name":"Siam Italia Srl",
    "wof:placetype":"venue"
},
  "geometry": {"coordinates":[10.8599567413,44.7891273499],"type":"Point"}
}