{
  "type": "Feature",
  "properties": {
    "addr:full":"42021 Bibbiano Reggio Nell'Emilia 42021",
    "addr:postcode":"42021;42021",
    "iso:country":"IT",
    "sg:address":"42021 Bibbiano",
    "sg:orig_category":"Macchine E Forniture Per Industria Orafa E Per Orologeria",
    "sg:phone":"+39 0522 875844",
    "sg:postcode":"42021",
    "sg:province":"Reggio Nell'Emilia",
    "wof:name":"Tecno - Tress (s.n.c.)",
    "wof:placetype":"venue"
},
  "geometry": {"coordinates":[10.627794,44.696228],"type":"Point"}
}