{
  "type": "Feature",
  "properties": {
    "addr:full":"Via Torino 1 17031 Albenga Albenga Savona 17031",
    "addr:housenumber":"1",
    "addr:postcode":"17031;17031",
    "addr:street":"Via Torino",
    "iso:country":"IT",
    "sg:address":"Via Torino 1 17031 Albenga",
    "sg:city":"Albenga",
    "sg:classifiers":[
        {
            "category":"Autos & Motor Vehicles",
            "subcategory":"Auto Supplies",
            "type":"Retail Goods"
        }
    ],
    "sg:phone":"+39 0182 555050",
    "sg:postcode":"17031",
    "sg:province":"Savona",
    "sg:tags":[
        "automobile",
        "accessory"
    ],
    "wof:name":"Aicardi Srl",
    "wof:placetype":"venue"
},
  "geometry": {"coordinates":[8.209645,44.052471],"type":"Point"}
}