{
  "type": "Feature",
  "properties": {
    "addr:full":"Via Nazionale 15 37046 Minerbe Minerbe Verona 37046",
    "addr:housenumber":"15",
    "addr:postcode":"37046;37046",
    "addr:street":"Via Nazionale",
    "iso:country":"IT",
    "sg:address":"Via Nazionale 15 37046 Minerbe",
    "sg:city":"Minerbe",
    "sg:classifiers":[
        {
            "category":"Wholesale",
            "subcategory":"Machinery & Supplies",
            "type":"Manufacturing & Wholesale Goods"
        }
    ],
    "sg:phone":"+39 0442 640185",
    "sg:postcode":"37046",
    "sg:province":"Verona",
    "sg:tags":[
        "agricultural",
        "equipment"
    ],
    "sg:website":"www.rossettoflli.it",
    "wof:name":"F.lli Rossetto Snc",
    "wof:placetype":"venue"
},
  "geometry": {"coordinates":[11.366006,45.230846],"type":"Point"}
}