{
  "type": "Feature",
  "properties": {
    "iso:country":"IT",
    "sg:address":"66020 San Giovanni Teatino",
    "sg:city":"Sambuceto",
    "sg:classifiers":[
        {
            "category":"Professional",
            "subcategory":"Management & Consulting",
            "type":"Services"
        }
    ],
    "sg:phone":"+39 085 440 9081",
    "sg:postcode":"66020",
    "sg:province":"Chieti",
    "sg:tags":[
        "control",
        "auxiliary",
        "technical",
        "consultant",
        "analysis",
        "research",
        "appraisers",
        "administrative"
    ],
    "wof:name":"Export Solutions Srl",
    "wof:placetype":"venue"
},
  "geometry": {"coordinates":[14.202207,42.410213],"type":"Point"}
}