{
  "type": "Feature",
  "properties": {
    "addr:full":"52100 Arezzo Arezzo Arezzo 52100",
    "addr:postcode":"52100;52100",
    "iso:country":"IT",
    "sg:address":"52100 Arezzo",
    "sg:city":"Arezzo",
    "sg:orig_category":"Articoli Per Imballaggio E Confezionamento",
    "sg:phone":"+39 0575 323577",
    "sg:postcode":"52100",
    "sg:province":"Arezzo",
    "wof:name":"Arezzo Nastri Di Chimenti Carlo & C. Snc",
    "wof:placetype":"venue"
},
  "geometry": {"coordinates":[11.84591,43.464619],"type":"Point"}
}