{
  "type": "Feature",
  "properties": {
    "addr:full":"07021 Arzachena Arzachena Olbia-Tempio 07021",
    "addr:postcode":"07021;07021",
    "iso:country":"IT",
    "sg:address":"07021 Arzachena",
    "sg:city":"Arzachena",
    "sg:orig_category":"Tappezzerie In Stoffa, Plastica E Pelle",
    "sg:phone":"+39 0789 88460",
    "sg:postcode":"07021",
    "sg:province":"Olbia-Tempio",
    "wof:name":"Piano Aurora",
    "wof:placetype":"venue"
},
  "geometry": {"coordinates":[9.388149,41.078754],"type":"Point"}
}