{
  "type": "Feature",
  "properties": {
    "iso:country":"IT",
    "sg:address":"22066 Mariano Comense",
    "sg:city":"Mariano Comense",
    "sg:orig_category":"Macchine E Forniture Per Arredamento E Industria Del Legno. Utensili Meccanici E Materiali",
    "sg:phone":"+39 031 744634",
    "sg:postcode":"22066",
    "sg:province":"Como",
    "wof:name":"A.m.",
    "wof:placetype":"venue"
},
  "geometry": {"coordinates":[9.164767,45.712048],"type":"Point"}
}