{
  "type": "Feature",
  "properties": {
    "addr:full":"30020 Marcon Marcon Venezia 30020",
    "addr:postcode":"30020;30020",
    "iso:country":"IT",
    "sg:address":"30020 Marcon",
    "sg:city":"Marcon",
    "sg:orig_category":"Servizi Di Magazzinaggio E Movimentazione",
    "sg:phone":"+39 041 595 2786",
    "sg:postcode":"30020",
    "sg:province":"Venezia",
    "wof:name":"Societa' Cooperativa Euroservizi Scarl",
    "wof:placetype":"venue"
},
  "geometry": {"coordinates":[12.295627,45.546673],"type":"Point"}
}