{
  "type": "Feature",
  "properties": {
    "iso:country":"IT",
    "sg:address":"22073 Fino Mornasco",
    "sg:city":"Fino Mornasco",
    "sg:orig_category":"Articoli Da Regalo. Tempo Libero - Articoli E Forniture. Regalistica Aziendale",
    "sg:phone":"+39 031 921096",
    "sg:postcode":"22073",
    "sg:province":"Como",
    "wof:name":"Coppe E Trofei (s.n.c.)",
    "wof:placetype":"venue"
},
  "geometry": {"coordinates":[9.048832,45.746395],"type":"Point"}
}