{
  "type": "Feature",
  "properties": {
    "addr:full":"32, Via Vittorio Emanuele 24037 Rota D'imagna Bergamo 24037",
    "addr:postcode":"24037;24037",
    "addr:street":"Via Vittorio Emanuele",
    "iso:country":"IT",
    "sg:address":"32, Via Vittorio Emanuele 24037 Rota D'imagna",
    "sg:classifiers":[
        {
            "category":"Travel",
            "subcategory":"Travel Agent",
            "type":"Entertainment"
        }
    ],
    "sg:phone":"+39 39035868000",
    "sg:postcode":"24037",
    "sg:province":"Bergamo",
    "sg:tags":[
        "business"
    ],
    "wof:name":"Albergo Miramonti",
    "wof:placetype":"venue"
},
  "geometry": {"coordinates":[9.514009,45.830666],"type":"Point"}
}