{
  "type": "Feature",
  "properties": {
    "iso:country":"IT",
    "sg:address":"38, Via San Giovanni 46028 Sermide",
    "sg:city":"Sermide",
    "sg:classifiers":[
        {
            "category":"Shopping",
            "subcategory":"Stationery & Office Supplies",
            "type":"Retail Goods"
        }
    ],
    "sg:phone":"+39 39038661307",
    "sg:postcode":"46028",
    "sg:province":"Mantova",
    "sg:tags":[
        "professional"
    ],
    "wof:name":"Sarti Srl",
    "wof:placetype":"venue"
},
  "geometry": {"coordinates":[11.3085021973,44.9935035706],"type":"Point"}
}