{
  "type": "Feature",
  "properties": {
    "addr:full":"93016 Riesi Riesi Caltanissetta 93016",
    "addr:postcode":"93016;93016",
    "iso:country":"IT",
    "sg:address":"93016 Riesi",
    "sg:city":"Riesi",
    "sg:orig_category":"Articoli Per Neonati E Bambini",
    "sg:phone":"+39 0934 924036",
    "sg:postcode":"93016",
    "sg:province":"Caltanissetta",
    "wof:name":"Arcobaleno Tessuti Di Cutaia Francesca",
    "wof:placetype":"venue"
},
  "geometry": {"coordinates":[14.066922,37.491444],"type":"Point"}
}