{
  "type": "Feature",
  "properties": {
    "addr:full":"20124 Milano Milano Milano 20124",
    "addr:postcode":"20124;20124",
    "iso:country":"IT",
    "sg:address":"20124 Milano",
    "sg:city":"Milano",
    "sg:orig_category":"Autoaccessori - Commercio",
    "sg:phone":"+39 02 204 9231",
    "sg:postcode":"20124",
    "sg:province":"Milano",
    "sg:website":"http://www.varamilano.it",
    "wof:name":"V.a.r.a. Di Fabrizio Ballestrin",
    "wof:placetype":"venue"
},
  "geometry": {"coordinates":[9.204268,45.477814],"type":"Point"}
}