{
  "type": "Feature",
  "properties": {
    "addr:full":"30121 Venezia Cannaregio Venezia 30121",
    "addr:postcode":"30121;30121",
    "addr:street":"Cannaregio",
    "iso:country":"IT",
    "sg:address":"30121 Venezia",
    "sg:city":"Cannaregio",
    "sg:orig_category":"Marmo, Pietre Ed Affini. Arte Ed Artigianato Artistico",
    "sg:phone":"+39 041 524 0736",
    "sg:postcode":"30121",
    "sg:province":"Venezia",
    "wof:name":"Angelo Orsoni Di Ruggero E Lucio Orsoni (s.n.c.)",
    "wof:placetype":"venue"
},
  "geometry": {"coordinates":[12.323284,45.444878],"type":"Point"}
}