{
  "type": "Feature",
  "properties": {
    "iso:country":"IT",
    "sg:address":"Via Sturzo Don Luigi 90044 Carini",
    "sg:city":"Carini",
    "sg:classifiers":[
        {
            "category":"Food & Beverages",
            "subcategory":"Dairy",
            "type":"Retail Goods"
        }
    ],
    "sg:phone":"+39 091 881 4001",
    "sg:postcode":"90044",
    "sg:province":"Palermo",
    "sg:tags":[
        "product"
    ],
    "wof:name":"Gambino Industrie Alimentari Spa",
    "wof:placetype":"venue"
},
  "geometry": {"coordinates":[13.220803,38.165516],"type":"Point"}
}