{
  "type": "Feature",
  "properties": {
    "addr:full":"10080 San Benigno Canavese San Benigno Canavese Torino 10080",
    "addr:housenumber":"10080",
    "addr:postcode":"benigno canavese;10080",
    "addr:street":"San",
    "iso:country":"IT",
    "sg:address":"10080 San Benigno Canavese",
    "sg:city":"San Benigno Canavese",
    "sg:orig_category":"Lavorazioni Metalli, Stampaggio E Saldatura",
    "sg:phone":"+39 011 988 0503",
    "sg:postcode":"10080",
    "sg:province":"Torino",
    "wof:name":"Eurosider Srl",
    "wof:placetype":"venue"
},
  "geometry": {"coordinates":[7.78995,45.222866],"type":"Point"}
}