{
  "type": "Feature",
  "properties": {
    "addr:full":"10127 Torino Torino Torino 10127",
    "addr:postcode":"10127;10127",
    "iso:country":"IT",
    "sg:address":"10127 Torino",
    "sg:city":"Torino",
    "sg:orig_category":"Trasporti E Spedizioni Merci",
    "sg:phone":"+39 011 617 7611",
    "sg:postcode":"10127",
    "sg:province":"Torino",
    "sg:website":"http://www.elia.it",
    "wof:name":"Elia Fratelli Srl",
    "wof:placetype":"venue"
},
  "geometry": {"coordinates":[7.651407,45.0214],"type":"Point"}
}