{
  "type": "Feature",
  "properties": {
    "iso:country":"IT",
    "sg:address":"62011 Cingoli",
    "sg:city":"Cingoli",
    "sg:orig_category":"Termotecnica E Riscaldamento, Apparecchiature E Servizi",
    "sg:phone":"+39 0733 615212",
    "sg:postcode":"62011",
    "sg:province":"Macerata",
    "wof:name":"Ilari Armando",
    "wof:placetype":"venue"
},
  "geometry": {"coordinates":[13.270916,43.386593],"type":"Point"}
}