{
  "type": "Feature",
  "properties": {
    "iso:country":"IT",
    "sg:address":"Via Santarcaniolese 3054; Poggio Berni; 47030",
    "sg:classifiers":[
        {
            "category":"Banks & Credit Unions",
            "subcategory":"Bank",
            "type":"Services"
        }
    ],
    "sg:phone":"+39 0541 688054",
    "sg:postcode":"47030",
    "sg:province":"Forl\u00ec-Cesena",
    "wof:name":"Rolo Banca 1473 Spa",
    "wof:placetype":"venue"
},
  "geometry": {"coordinates":[12.277684,43.98164],"type":"Point"}
}