{
  "type": "Feature",
  "properties": {
    "iso:country":"IT",
    "sg:address":"00187 Roma",
    "sg:city":"Roma",
    "sg:orig_category":"Articoli Per Fumatori",
    "sg:phone":"+39 06 678 5435",
    "sg:postcode":"00187",
    "sg:province":"Roma",
    "wof:name":"Becker & Musico'",
    "wof:placetype":"venue"
},
  "geometry": {"coordinates":[12.440943,41.861435],"type":"Point"}
}