{
  "type": "Feature",
  "properties": {
    "iso:country":"IT",
    "sg:address":"Contrada San Giovanni 93013 Mazzarino",
    "sg:city":"Mazzarino",
    "sg:classifiers":[
        {
            "category":"Shopping",
            "subcategory":"Clothing, Apparel, & Fashions",
            "type":"Retail Goods"
        }
    ],
    "sg:phone":"+39 0934 381018",
    "sg:postcode":"93013",
    "sg:province":"Caltanissetta",
    "sg:tags":[
        "clothes"
    ],
    "wof:name":"Reil Di Russo Linda & C. Sas",
    "wof:placetype":"venue"
},
  "geometry": {"coordinates":[14.06329,37.48991],"type":"Point"}
}