{
  "type": "Feature",
  "properties": {
    "iso:country":"IT",
    "sg:address":"95047 Patern\u00f2",
    "sg:orig_category":"Prodotti Alimentari",
    "sg:phone":"+39 095 798 1093",
    "sg:postcode":"95047",
    "sg:province":"Catania",
    "sg:website":"http://www.terredisicilia.com",
    "wof:name":"Terre Di Siciia Srl",
    "wof:placetype":"venue"
},
  "geometry": {"coordinates":[15.2467565536,37.800327301],"type":"Point"}
}