{
  "type": "Feature",
  "properties": {
    "iso:country":"IT",
    "sg:address":"64/t, Localita' Penna 52028 Terranuova Bracciolini",
    "sg:city":"Penna",
    "sg:classifiers":[
        {
            "category":"Manufacturing",
            "subcategory":"Rubber & Plastics",
            "type":"Manufacturing & Wholesale Goods"
        }
    ],
    "sg:phone":"+39 055 970 5207",
    "sg:postcode":"52028",
    "sg:province":"Arezzo",
    "wof:name":"Omv Di Vieri Enzo Enzo",
    "wof:placetype":"venue"
},
  "geometry": {"coordinates":[11.7376909256,43.5053596497],"type":"Point"}
}