{
  "type": "Feature",
  "properties": {
    "iso:country":"IT",
    "sg:address":"70051 Barletta",
    "sg:city":"Barletta",
    "sg:orig_category":"Abbigliamento In Pelle - Produzione E Ingrosso",
    "sg:phone":"+39 0883 334320",
    "sg:postcode":"70051",
    "sg:province":"Bari",
    "wof:name":"Confezioni Lara Di Delvecchio Francesco",
    "wof:placetype":"venue"
},
  "geometry": {"coordinates":[16.287571,41.316265],"type":"Point"}
}