{
  "type": "Feature",
  "properties": {
    "iso:country":"IT",
    "sg:address":"00142 Roma",
    "sg:city":"Roma",
    "sg:orig_category":"Musica",
    "sg:phone":"+39 06 540 6880",
    "sg:postcode":"00142",
    "sg:province":"Roma",
    "wof:name":"Eurmusica Di Olivieri & C. Sas",
    "wof:placetype":"venue"
},
  "geometry": {"coordinates":[12.4835443497,41.8474884033],"type":"Point"}
}