{
  "type": "Feature",
  "properties": {
    "iso:country":"IT",
    "sg:address":"25036 Palazzolo Sull'oglio",
    "sg:orig_category":"Macchine, Impianti Ed Attrezzature Per Industria Alimentare E Bevande",
    "sg:phone":"+39 030 731220",
    "sg:postcode":"25036",
    "sg:province":"Brescia",
    "wof:name":"Bemeco Di Mena R. E C. Sas",
    "wof:placetype":"venue"
},
  "geometry": {"coordinates":[9.891188,45.594101],"type":"Point"}
}