{
  "type": "Feature",
  "properties": {
    "iso:country":"IT",
    "sg:address":"20143 Milano",
    "sg:city":"Milano",
    "sg:orig_category":"Prodotti Alimentari",
    "sg:phone":"+39 02 837 5617",
    "sg:postcode":"20143",
    "sg:province":"Milano",
    "wof:name":"Osteria Le Vigne Roberto",
    "wof:placetype":"venue"
},
  "geometry": {"coordinates":[9.1714258194,45.4508590698],"type":"Point"}
}