{
  "type": "Feature",
  "properties": {
    "iso:country":"IT",
    "sg:address":"25019 Sirmione",
    "sg:city":"Sirmione",
    "sg:classifiers":[
        {
            "category":"Shopping",
            "subcategory":"Bicycles & Sporting Goods",
            "type":"Retail Goods"
        }
    ],
    "sg:phone":"+39 030 990 4361",
    "sg:postcode":"25019",
    "sg:province":"Brescia",
    "sg:tags":[
        "tempo",
        "lo",
        "-",
        "libero",
        "per",
        "servizi",
        "forniture",
        "articoli",
        "e",
        "sport",
        "il"
    ],
    "wof:name":"Ginette Sub",
    "wof:placetype":"venue"
},
  "geometry": {"coordinates":[10.217809,45.544636],"type":"Point"}
}