{
  "type": "Feature",
  "properties": {
    "addr:full":"10154 Torino Torino Torino 10154",
    "addr:postcode":"10154;10154",
    "iso:country":"IT",
    "sg:address":"10154 Torino",
    "sg:city":"Torino",
    "sg:orig_category":"Macchine, Impianti Ed Attrezzature Per Abbigliamento E Pelletterie",
    "sg:phone":"+39 011 246 2160",
    "sg:postcode":"10154",
    "sg:province":"Torino",
    "sg:website":"http://www.paginegialle.it/santistore",
    "wof:name":"Santistore Snc",
    "wof:placetype":"venue"
},
  "geometry": {"coordinates":[7.830617,45.487606],"type":"Point"}
}