{
  "type": "Feature",
  "properties": {
    "addr:full":"36100 Vicenza Vicenza Vicenza 36100",
    "addr:postcode":"36100;36100",
    "iso:country":"IT",
    "sg:address":"36100 Vicenza",
    "sg:city":"Vicenza",
    "sg:classifiers":[
        {
            "category":"Shopping",
            "subcategory":"Computers & Home Electronics",
            "type":"Retail Goods"
        }
    ],
    "sg:phone":"+39 0444 341020",
    "sg:postcode":"36100",
    "sg:province":"Vicenza",
    "sg:tags":[
        "personal",
        "ed",
        "accessori"
    ],
    "sg:website":"http://www.atigservice.it",
    "wof:name":"Atig Service Srl",
    "wof:placetype":"venue"
},
  "geometry": {"coordinates":[11.561044693,45.536190033],"type":"Point"}
}