{
  "type": "Feature",
  "properties": {
    "iso:country":"IT",
    "sg:address":"254, Via Giuseppe Zanardelli 25083 Gardone Riviera",
    "sg:city":"Gardone Riviera",
    "sg:classifiers":[
        {
            "category":"Travel",
            "subcategory":"Travel Agent",
            "type":"Entertainment"
        }
    ],
    "sg:phone":"+39 39036521883",
    "sg:postcode":"25083",
    "sg:province":"Brescia",
    "sg:tags":[
        "business"
    ],
    "wof:name":"Hotel Villa Paradiso Srl",
    "wof:placetype":"venue"
},
  "geometry": {"coordinates":[10.569952,45.622448],"type":"Point"}
}