{
  "type": "Feature",
  "properties": {
    "addr:full":"Via Provinciale 87, 95020 Santa Venerina, Ct Catania 95020",
    "addr:housenumber":"87",
    "addr:postcode":"95020;95020",
    "addr:street":"Via Provinciale;Ct",
    "iso:country":"IT",
    "sg:address":"Via Provinciale 87, 95020 Santa Venerina, Ct",
    "sg:classifiers":[
        {
            "category":"Banks & Credit Unions",
            "subcategory":"Bank",
            "type":"Services"
        }
    ],
    "sg:postcode":"95020",
    "sg:province":"Catania",
    "wof:name":"Banca Di Credito Cooperativo Cassa Rurale-linera",
    "wof:placetype":"venue"
},
  "geometry": {"coordinates":[15.087834,37.502483],"type":"Point"}
}