{
  "type": "Feature",
  "properties": {
    "addr:full":"87041 Acri Acri Cosenza 87041",
    "addr:postcode":"87041;87041",
    "iso:country":"IT",
    "sg:address":"87041 Acri",
    "sg:city":"Acri",
    "sg:orig_category":"Caldaie - Produzione E Commercio",
    "sg:phone":"+39 0984 950781",
    "sg:postcode":"87041",
    "sg:province":"Cosenza",
    "wof:name":"Lavia Fratelli Snc",
    "wof:placetype":"venue"
},
  "geometry": {"coordinates":[16.41703,39.480255],"type":"Point"}
}