{
  "type": "Feature",
  "properties": {
    "addr:full":"Via Carbonari 14 20030 Palazzolo Milanese Palazzolo Milanese Milano 20030",
    "addr:housenumber":"14",
    "addr:postcode":"20030;20030",
    "addr:street":"Via Carbonari",
    "iso:country":"IT",
    "sg:address":"Via Carbonari 14 20030 Palazzolo Milanese",
    "sg:city":"Palazzolo Milanese",
    "sg:classifiers":[
        {
            "category":"Structure",
            "subcategory":"Tunnel",
            "type":"Public Place"
        }
    ],
    "sg:phone":"+39 02 918 6065",
    "sg:postcode":"20030",
    "sg:province":"Milano",
    "sg:tags":[
        "wiring",
        "system"
    ],
    "sg:website":"www.fioresrl.com",
    "wof:name":"Fiore Srl",
    "wof:placetype":"venue"
},
  "geometry": {"coordinates":[9.164661,45.586349],"type":"Point"}
}