{
  "type": "Feature",
  "properties": {
    "iso:country":"IT",
    "sg:address":"Via V. Arata 10/a 16044 Monleone",
    "sg:city":"Monleone",
    "sg:classifiers":[
        {
            "category":"Landmark",
            "subcategory":"City Walls",
            "type":"Public Place"
        }
    ],
    "sg:phone":"+39 0185 92125",
    "sg:postcode":"16044",
    "sg:province":"Genova",
    "sg:tags":[
        "raw",
        "roofing",
        "slate",
        "dressed"
    ],
    "sg:website":"www.cuneo-lagomarsino.it",
    "wof:name":"Cuneo Lagomarsino Srl",
    "wof:placetype":"venue"
},
  "geometry": {"coordinates":[8.933989,44.407063],"type":"Point"}
}