{
  "type": "Feature",
  "properties": {
    "addr:full":"Via Abetone Brennero Nord 19/e 46035 Ostiglia Ostiglia Mantova 46035",
    "addr:housenumber":"19 / e",
    "addr:postcode":"46035;46035",
    "addr:street":"Via Abetone Brennero Nord",
    "iso:country":"IT",
    "sg:address":"Via Abetone Brennero Nord 19/e 46035 Ostiglia",
    "sg:city":"Ostiglia",
    "sg:classifiers":[
        {
            "category":"Landmark",
            "subcategory":"City Walls",
            "type":"Public Place"
        }
    ],
    "sg:phone":"+39 0386 802437",
    "sg:postcode":"46035",
    "sg:province":"Mantova",
    "sg:tags":[
        "protective",
        "metal",
        "spiral"
    ],
    "sg:website":"www.augers.it",
    "wof:name":"Tecnofer Srl",
    "wof:placetype":"venue"
},
  "geometry": {"coordinates":[10.7976980209,45.1603660583],"type":"Point"}
}