{
  "type": "Feature",
  "properties": {
    "iso:country":"IT",
    "sg:address":"50, Via Colombo Cristoforo 24046 Osio Sotto",
    "sg:city":"Osio Sotto",
    "sg:classifiers":[
        {
            "category":"Professional",
            "subcategory":"Engineering",
            "type":"Services"
        }
    ],
    "sg:phone":"+39 035 482 3250",
    "sg:postcode":"24046",
    "sg:province":"Bergamo",
    "sg:tags":[
        "machine",
        "-",
        "mechanical"
    ],
    "wof:name":"C.s.t. (s.n.c.)",
    "wof:placetype":"venue"
},
  "geometry": {"coordinates":[9.658195,45.647179],"type":"Point"}
}