{
  "type": "Feature",
  "properties": {
    "iso:country":"IT",
    "sg:address":"24068 Seriate",
    "sg:city":"Seriate",
    "sg:orig_category":"Motori Ed Organi Di Trasmissione",
    "sg:phone":"+39 035 303969",
    "sg:postcode":"24068",
    "sg:province":"Bergamo",
    "wof:name":"Zunt Italiana Srl",
    "wof:placetype":"venue"
},
  "geometry": {"coordinates":[9.7392644882,45.6591873169],"type":"Point"}
}