{
  "type": "Feature",
  "properties": {
    "iso:country":"IT",
    "sg:address":"Via Roma 59a/59b; Capizzi; 98031",
    "sg:city":"Capizzi",
    "sg:classifiers":[
        {
            "category":"Banks & Credit Unions",
            "subcategory":"Bank",
            "type":"Services"
        }
    ],
    "sg:phone":"+39 0935 933086",
    "sg:postcode":"98031",
    "sg:province":"Messina",
    "wof:name":"Isituto Bancario, San Paolo Di Torino Spa",
    "wof:placetype":"venue"
},
  "geometry": {"coordinates":[14.481133,37.849907],"type":"Point"}
}