{
  "type": "Feature",
  "properties": {
    "iso:country":"IT",
    "sg:address":"00159 Roma",
    "sg:city":"Roma",
    "sg:orig_category":"Elettrotecnica Industriale, Prodotti E Apparecchiature",
    "sg:phone":"+39 06 4353 1453",
    "sg:postcode":"00159",
    "sg:province":"Roma",
    "sg:website":"http://www.lavera.it",
    "wof:name":"La Vera Fabbrica Lampadari",
    "wof:placetype":"venue"
},
  "geometry": {"coordinates":[12.512096,41.901852],"type":"Point"}
}