{
  "type": "Feature",
  "properties": {
    "addr:full":"77, Via Ottorino Alessandrini 31059 Zero Branco Zero Branco Treviso 31059",
    "addr:postcode":"31059;31059",
    "addr:street":"Via Ottorino Alessandrini",
    "iso:country":"IT",
    "sg:address":"77, Via Ottorino Alessandrini 31059 Zero Branco",
    "sg:city":"Zero Branco",
    "sg:classifiers":[
        {
            "category":"Food & Beverages",
            "subcategory":"Dairy",
            "type":"Retail Goods"
        }
    ],
    "sg:phone":"+39 39042297621",
    "sg:postcode":"31059",
    "sg:province":"Treviso",
    "sg:tags":[
        "product"
    ],
    "wof:name":"Caseificio Tonon Di Tonon Tarcisio & C. (s.n.c.)",
    "wof:placetype":"venue"
},
  "geometry": {"coordinates":[12.128207,45.61166],"type":"Point"}
}