{
  "type": "Feature",
  "properties": {
    "iso:country":"IT",
    "sg:address":"156, Frazione Peghera 24010 Taleggio",
    "sg:city":"Peghera",
    "sg:classifiers":[
        {
            "category":"Food & Beverages",
            "subcategory":"Dairy",
            "type":"Retail Goods"
        }
    ],
    "sg:phone":"+39 39034547068",
    "sg:postcode":"24010",
    "sg:province":"Bergamo",
    "sg:tags":[
        "product"
    ],
    "wof:name":"Ca' De Ambros Di Ambrogio Arnoldi",
    "wof:placetype":"venue"
},
  "geometry": {"coordinates":[9.565206,45.873783],"type":"Point"}
}