{
  "type": "Feature",
  "properties": {
    "iso:country":"IT",
    "sg:address":"27100 Pavia",
    "sg:city":"Pavia",
    "sg:orig_category":"Pubblicita', Marketing E Comunicazione",
    "sg:phone":"+39 0382 577837",
    "sg:postcode":"27100",
    "sg:province":"Pavia",
    "wof:name":"Retus Pubblicita'",
    "wof:placetype":"venue"
},
  "geometry": {"coordinates":[9.1579351425,45.2049064636],"type":"Point"}
}