{
  "type": "Feature",
  "properties": {
    "iso:country":"IT",
    "sg:address":"35030 Rubano",
    "sg:city":"Rubano",
    "sg:orig_category":"Elettrotecnica Industriale, Prodotti E Apparecchiature. Ricambi E Componenti Dei Mezzi Di Trasporto",
    "sg:phone":"+39 049 630300",
    "sg:postcode":"35030",
    "sg:province":"Padova",
    "wof:name":"C.d.b. Srl",
    "wof:placetype":"venue"
},
  "geometry": {"coordinates":[11.811622,45.423023],"type":"Point"}
}