{
  "type": "Feature",
  "properties": {
    "addr:full":"40012 Calderara Di Reno Calderara di Reno Bologna 40012",
    "addr:postcode":"40012;40012",
    "iso:country":"IT",
    "sg:address":"40012 Calderara Di Reno",
    "sg:city":"Calderara di Reno",
    "sg:orig_category":"Macchine, Impianti Ed Attrezzature Industria Delle Materie Plastiche E Gomma",
    "sg:phone":"+39 051 726351",
    "sg:postcode":"40012",
    "sg:province":"Bologna",
    "wof:name":"Matteuzzi (s.r.l.)",
    "wof:placetype":"venue"
},
  "geometry": {"coordinates":[11.299883,44.543701],"type":"Point"}
}