{
  "type": "Feature",
  "properties": {
    "addr:full":"2/4, Via Ruffilli 20060 Pessano Con Bornago Ornago Milano 20060",
    "addr:housenumber":"2 / 4",
    "addr:postcode":"20060;20060",
    "addr:street":"Via Ruffilli",
    "iso:country":"IT",
    "sg:address":"2/4, Via Ruffilli 20060 Pessano Con Bornago",
    "sg:city":"Ornago",
    "sg:classifiers":[
        {
            "category":"Wholesale",
            "subcategory":"Machinery & Supplies",
            "type":"Manufacturing & Wholesale Goods"
        }
    ],
    "sg:phone":"+39 39029596901",
    "sg:postcode":"20060",
    "sg:province":"Milano",
    "sg:tags":[
        "equipment",
        "-",
        "instrument",
        "measurement"
    ],
    "wof:name":"Balance Systems S.p.a.",
    "wof:placetype":"venue"
},
  "geometry": {"coordinates":[9.400857,45.543865],"type":"Point"}
}