{
  "type": "Feature",
  "properties": {
    "addr:full":"108, Via Monti Vincenzo 41100 Modena Modena Modena 41100",
    "addr:housenumber":"108",
    "addr:postcode":"41100;41100",
    "addr:street":"Via Monti Vincenzo",
    "iso:country":"IT",
    "sg:address":"108, Via Monti Vincenzo 41100 Modena",
    "sg:city":"Modena",
    "sg:classifiers":[
        {
            "category":"Professional",
            "subcategory":"Advertising",
            "type":"Services"
        }
    ],
    "sg:phone":"+39 39059827827",
    "sg:postcode":"41100",
    "sg:province":"Modena",
    "sg:tags":[
        "communication",
        "medium"
    ],
    "wof:name":"Sirio Sicurezza S.r.l.",
    "wof:placetype":"venue"
},
  "geometry": {"coordinates":[10.92522,44.647079],"type":"Point"}
}