{
  "type": "Feature",
  "properties": {
    "iso:country":"IT",
    "sg:address":"176/8, Via Fiorentina 51100 Pistoia",
    "sg:city":"Pistoia",
    "sg:classifiers":[
        {
            "category":"Manufacturing",
            "subcategory":"Lumber",
            "type":"Manufacturing & Wholesale Goods"
        }
    ],
    "sg:phone":"+39 0573 382766",
    "sg:postcode":"51100",
    "sg:province":"Pistoia",
    "sg:tags":[
        "wood"
    ],
    "wof:name":"Bolognini Imballaggi Industrii Spa",
    "wof:placetype":"venue"
},
  "geometry": {"coordinates":[10.920127,43.925766],"type":"Point"}
}