{
  "type": "Feature",
  "properties": {
    "addr:full":"74100 Taranto Taranto Taranto 74100",
    "addr:postcode":"74100;74100",
    "iso:country":"IT",
    "sg:address":"74100 Taranto",
    "sg:city":"Taranto",
    "sg:orig_category":"Abbigliamento Esterno, Maglierie E Pelliccerie. Calzature, Pelletterie E Pelli",
    "sg:phone":"+39 099 459 4836",
    "sg:postcode":"74100",
    "sg:province":"Taranto",
    "wof:name":"Ulisse S.r.l.",
    "wof:placetype":"venue"
},
  "geometry": {"coordinates":[17.244621,40.4716],"type":"Point"}
}