{
  "type": "Feature",
  "properties": {
    "iso:country":"IT",
    "sg:address":"24068 Seriate",
    "sg:city":"Seriate",
    "sg:orig_category":"Carni, Salumi E Pesci",
    "sg:phone":"+39 035 293407",
    "sg:postcode":"24068",
    "sg:province":"Bergamo",
    "wof:name":"Donzelli Giovanni",
    "wof:placetype":"venue"
},
  "geometry": {"coordinates":[9.721669,45.685059],"type":"Point"}
}