{
  "type": "Feature",
  "properties": {
    "iso:country":"IT",
    "sg:address":"90143 Palermo",
    "sg:city":"Palermo",
    "sg:orig_category":"Macchine, Impianti Ed Attrezzature Industria Chimica. Impiantistica E Prodotti Tecnologici Per Edilizia. Impianti, Attrezzature E Forniture Sanitarie Ed Ospedaliere",
    "sg:phone":"+39 091 625 9203",
    "sg:postcode":"90143",
    "sg:province":"Palermo",
    "wof:name":"Ramoneur Di Martines & C. Snc",
    "wof:placetype":"venue"
},
  "geometry": {"coordinates":[13.348907,38.138546],"type":"Point"}
}