{
  "type": "Feature",
  "properties": {
    "iso:country":"IT",
    "sg:address":"20154 Milano",
    "sg:city":"Milano",
    "sg:orig_category":"Chiese Ed Associazioni Religiose",
    "sg:phone":"+39 02 342375",
    "sg:postcode":"20154",
    "sg:province":"Milano",
    "wof:name":"Casa Di Riposo B. L. Guanella",
    "wof:placetype":"venue"
},
  "geometry": {"coordinates":[9.172688,45.478111],"type":"Point"}
}