{
  "type": "Feature",
  "properties": {
    "iso:country":"IT",
    "sg:address":"16, Via Mascagni Pietro 31038 Paese",
    "sg:city":"Paese",
    "sg:classifiers":[
        {
            "category":"Home & Garden",
            "subcategory":"Home Furnishings",
            "type":"Retail Goods"
        }
    ],
    "sg:phone":"+39 0422 959534",
    "sg:postcode":"31038",
    "sg:province":"Treviso",
    "sg:tags":[
        "household"
    ],
    "wof:name":"Pozzebon S.r.l.",
    "wof:placetype":"venue"
},
  "geometry": {"coordinates":[12.167229,45.666691],"type":"Point"}
}