{
  "type": "Feature",
  "properties": {
    "addr:full":"60027 Osimo Osimo Ancona 60027",
    "addr:postcode":"60027;60027",
    "iso:country":"IT",
    "sg:address":"60027 Osimo",
    "sg:city":"Osimo",
    "sg:orig_category":"Persiane Ed Avvolgibili",
    "sg:phone":"+39 071 715309",
    "sg:postcode":"60027",
    "sg:province":"Ancona",
    "wof:name":"Crucianelli Mario",
    "wof:placetype":"venue"
},
  "geometry": {"coordinates":[13.4904346466,43.4871253967],"type":"Point"}
}