{
  "type": "Feature",
  "properties": {
    "iso:country":"IT",
    "sg:address":"2, Via Lombardia 56025 Pontedera",
    "sg:city":"Pontedera",
    "sg:classifiers":[
        {
            "category":"Home & Garden",
            "subcategory":"Home Furnishings",
            "type":"Retail Goods"
        }
    ],
    "sg:phone":"+39 0587 291483",
    "sg:postcode":"56025",
    "sg:province":"Pisa",
    "sg:tags":[
        "household"
    ],
    "wof:name":"Bitossi Luciano & Figli (s.n.c)",
    "wof:placetype":"venue"
},
  "geometry": {"coordinates":[10.59811,43.64257],"type":"Point"}
}