{
  "type": "Feature",
  "properties": {
    "addr:full":"41043 Formigine Formigine Modena 41043",
    "addr:postcode":"41043;41043",
    "iso:country":"IT",
    "sg:address":"41043 Formigine",
    "sg:city":"Formigine",
    "sg:orig_category":"Forniture Per Edilizia E Lavori Pubblici. Forniture Per Attivita' Industriali",
    "sg:phone":"+39 059 571008",
    "sg:postcode":"41043",
    "sg:province":"Modena",
    "wof:name":"P.g.r. Di Giovini Luigi & C. Snc",
    "wof:placetype":"venue"
},
  "geometry": {"coordinates":[10.8515167236,44.5613822937],"type":"Point"}
}