{
  "type": "Feature",
  "properties": {
    "iso:country":"IT",
    "sg:address":"24124 Bergamo",
    "sg:city":"Bergamo",
    "sg:orig_category":"Forniture Per Abbigliamento E Pelletterie. Forniture Per Attivita' Commerciali Ed Artigianali",
    "sg:phone":"+39 035 239960",
    "sg:postcode":"24124",
    "sg:province":"Bergamo",
    "wof:name":"Idea Di Piceni Caterina & C. (s.n.c.)",
    "wof:placetype":"venue"
},
  "geometry": {"coordinates":[9.6796598434,45.7009735107],"type":"Point"}
}