{
  "type": "Feature",
  "properties": {
    "iso:country":"IT",
    "sg:address":"00133 Roma",
    "sg:city":"Roma",
    "sg:orig_category":"Arredo Camera Letto E Complementi. Servizi E Lavori Per Arredamento E Industria Del Legno",
    "sg:phone":"+39 06 205 3654",
    "sg:postcode":"00133",
    "sg:province":"Roma",
    "wof:name":"Diso Pietro",
    "wof:placetype":"venue"
},
  "geometry": {"coordinates":[12.633103,41.862022],"type":"Point"}
}