{
  "type": "Feature",
  "properties": {
    "addr:full":"Vle Delle Provincie 209 95014 Giarre Giarre Catania 95014",
    "addr:housenumber":"209",
    "addr:postcode":"95014;95014",
    "addr:street":"Vle Delle Provincie",
    "iso:country":"IT",
    "sg:address":"Vle Delle Provincie 209 95014 Giarre",
    "sg:city":"Giarre",
    "sg:classifiers":[
        {
            "category":"Home & Garden",
            "subcategory":"Building Materials",
            "type":"Retail Goods"
        }
    ],
    "sg:phone":"+39 095 933111",
    "sg:postcode":"95014",
    "sg:province":"Catania",
    "sg:tags":[
        "tile",
        "ceramic"
    ],
    "sg:website":"www.fimas.it",
    "wof:name":"Fimas Fusione Industrie Mattonelle Srl",
    "wof:placetype":"venue"
},
  "geometry": {"coordinates":[15.191558,37.725204],"type":"Point"}
}