{
  "type": "Feature",
  "properties": {
    "iso:country":"IT",
    "sg:address":"21100 Varese",
    "sg:city":"Varese",
    "sg:orig_category":"Tempo Libero - Articoli E Forniture. Regalistica Aziendale",
    "sg:phone":"+39 0332 228401",
    "sg:postcode":"21100",
    "sg:province":"Varese",
    "wof:name":"Poker Trophy",
    "wof:placetype":"venue"
},
  "geometry": {"coordinates":[8.799985,45.828453],"type":"Point"}
}