{
  "type": "Feature",
  "properties": {
    "iso:country":"IT",
    "sg:address":"20131 Milano",
    "sg:city":"Milano",
    "sg:classifiers":[
        {
            "category":"Health Services",
            "subcategory":"Health Practitioner",
            "type":"Services"
        }
    ],
    "sg:phone":"+39 02 284 0085",
    "sg:postcode":"20131",
    "sg:province":"Milano",
    "sg:tags":[
        "medici"
    ],
    "wof:name":"Berti Edoardo",
    "wof:placetype":"venue"
},
  "geometry": {"coordinates":[9.226404,45.48716],"type":"Point"}
}