{
  "type": "Feature",
  "properties": {
    "iso:country":"IT",
    "sg:address":"Via Dei Colli 240 50058 Signa",
    "sg:city":"Signa",
    "sg:classifiers":[
        {
            "category":"Personal",
            "subcategory":"Shoe Repair & Shine",
            "type":"Services"
        }
    ],
    "sg:phone":"+39 055 876125",
    "sg:postcode":"50058",
    "sg:province":"Firenze",
    "sg:tags":[
        "health"
    ],
    "wof:name":"Siam Line Srl",
    "wof:placetype":"venue"
},
  "geometry": {"coordinates":[11.111938,43.802174],"type":"Point"}
}