{
  "type": "Feature",
  "properties": {
    "iso:country":"IT",
    "sg:address":"12043 Canale",
    "sg:city":"Canale",
    "sg:orig_category":"Macchine, Impianti Ed Attrezzature Per Industria Alimentare E Bevande. Macchine, Impianti Ed Attrezzature Industria Chimica",
    "sg:phone":"+39 0173 979257",
    "sg:postcode":"12043",
    "sg:province":"Cuneo",
    "wof:name":"Scanferlato Gino",
    "wof:placetype":"venue"
},
  "geometry": {"coordinates":[7.997794,44.799965],"type":"Point"}
}