{
  "type": "Feature",
  "properties": {
    "addr:full":"29, V. Ciaikowsky 20092 Cinisello Balsamo Cinisello Balsamo Milano 20092",
    "addr:housenumber":"29",
    "addr:postcode":"20092;20092",
    "addr:street":"V. Ciaikowsky",
    "iso:country":"IT",
    "sg:address":"29, V. Ciaikowsky 20092 Cinisello Balsamo",
    "sg:city":"Cinisello Balsamo",
    "sg:classifiers":[
        {
            "category":"Professional",
            "subcategory":"Engineering",
            "type":"Services"
        }
    ],
    "sg:phone":"+39 39026125495",
    "sg:postcode":"20092",
    "sg:province":"Milano",
    "sg:tags":[
        "machine",
        "-",
        "mechanical"
    ],
    "sg:website":"http://www.labelpack.it",
    "wof:name":"Labelpack Sas",
    "wof:placetype":"venue"
},
  "geometry": {"coordinates":[9.188141,45.463688],"type":"Point"}
}