{
  "type": "Feature",
  "properties": {
    "iso:country":"IT",
    "sg:address":"24035 Curno",
    "sg:city":"Curno",
    "sg:orig_category":"Musica. Shopping",
    "sg:phone":"+39 035 202100",
    "sg:postcode":"24035",
    "sg:province":"Bergamo",
    "sg:website":"http://www.mediaworld.it",
    "wof:name":"Mediamarket Spa - Media World",
    "wof:placetype":"venue"
},
  "geometry": {"coordinates":[9.6166448593,45.6835746765],"type":"Point"}
}