{
  "type": "Feature",
  "properties": {
    "iso:country":"IT",
    "sg:address":"80059 Torre Del Greco",
    "sg:city":"Torre del Greco",
    "sg:orig_category":"Gioielleria, Oreficeria E Argenteria. Shopping",
    "sg:phone":"+39 081 849 2363",
    "sg:postcode":"80059",
    "sg:province":"Napoli",
    "wof:name":"Petrucci Giuseppe",
    "wof:placetype":"venue"
},
  "geometry": {"coordinates":[14.370937,40.791069],"type":"Point"}
}