{
  "type": "Feature",
  "properties": {
    "addr:full":"33, Via Cascinelle 30024 Musile Di Piave Musile di Piave Venezia 30024",
    "addr:postcode":"30024;30024",
    "addr:street":"Via Cascinelle",
    "iso:country":"IT",
    "sg:address":"33, Via Cascinelle 30024 Musile Di Piave",
    "sg:city":"Musile di Piave",
    "sg:classifiers":[
        {
            "category":"Wholesale",
            "subcategory":"Drugs",
            "type":"Manufacturing & Wholesale Goods"
        }
    ],
    "sg:phone":"+39 39042150749",
    "sg:postcode":"30024",
    "sg:province":"Venezia",
    "sg:tags":[
        "chemical",
        "pharmaceutical"
    ],
    "wof:name":"Tecnochimital (s.a.s.)",
    "wof:placetype":"venue"
},
  "geometry": {"coordinates":[12.533172,45.609882],"type":"Point"}
}