{
  "type": "Feature",
  "properties": {
    "iso:country":"IT",
    "sg:address":"21020 Bodio Lomnago",
    "sg:city":"Bodio",
    "sg:orig_category":"Prodotti E Manufatti In Gomma. Forniture Per Attivita' Industriali",
    "sg:phone":"+39 0332 948626",
    "sg:postcode":"21020",
    "sg:province":"Varese",
    "sg:website":"http://www.stampaggiogomma.it",
    "wof:name":"Stampaggio Gomma Snc",
    "wof:placetype":"venue"
},
  "geometry": {"coordinates":[8.7448205948,45.7930526733],"type":"Point"}
}