{
  "type": "Feature",
  "properties": {
    "iso:country":"IT",
    "sg:address":"06089 Torgiano",
    "sg:city":"Torgiano",
    "sg:orig_category":"Lavorazioni Metalli, Stampaggio E Saldatura",
    "sg:phone":"+39 075 395156",
    "sg:postcode":"06089",
    "sg:province":"Perugia",
    "wof:name":"Gregori Marcello",
    "wof:placetype":"venue"
},
  "geometry": {"coordinates":[12.449522,43.043266],"type":"Point"}
}