{
  "type": "Feature",
  "properties": {
    "iso:country":"IT",
    "sg:address":"35020 Sant'angelo Di Piove Di Sacco",
    "sg:orig_category":"Forniture Per Agricoltura E Zootecnia. Animali Domestici",
    "sg:phone":"+39 049 584 7377",
    "sg:postcode":"35020",
    "sg:province":"Padova",
    "wof:name":"Ferrin & Co. S.r.l.",
    "wof:placetype":"venue"
},
  "geometry": {"coordinates":[11.9571590424,45.3540992737],"type":"Point"}
}