{
  "type": "Feature",
  "properties": {
    "iso:country":"IT",
    "sg:address":"30038 Spinea",
    "sg:city":"Spinea",
    "sg:orig_category":"Prodotti E Manufatti In Materie Plastiche",
    "sg:phone":"+39 041 541 0866",
    "sg:postcode":"30038",
    "sg:province":"Venezia",
    "wof:name":"Baroni Resine Di Baroni Michela & C. S.a.s.",
    "wof:placetype":"venue"
},
  "geometry": {"coordinates":[12.1451530457,45.5062103271],"type":"Point"}
}