{
  "type": "Feature",
  "properties": {
    "iso:country":"IT",
    "sg:address":"10083 Favria",
    "sg:city":"Favria",
    "sg:orig_category":"Modelli Per Fonderie",
    "sg:phone":"+39 0124 34039",
    "sg:postcode":"10083",
    "sg:province":"Torino",
    "wof:name":"C.i.m.a. Snc Di Poletto Mario",
    "wof:placetype":"venue"
},
  "geometry": {"coordinates":[7.6914157867,45.3344154358],"type":"Point"}
}