{
  "type": "Feature",
  "properties": {
    "addr:full":"20090 Assago Assago Milano 20090",
    "addr:postcode":"20090;20090",
    "addr:street":"Assago",
    "iso:country":"IT",
    "sg:address":"20090 Assago",
    "sg:city":"Assago",
    "sg:orig_category":"Macchine Utensili E Impianti",
    "sg:phone":"+39 02 824 2851",
    "sg:postcode":"20090",
    "sg:province":"Milano",
    "sg:website":"http://www.tecnormacchine.it",
    "wof:name":"Tecnor Macchine Spa",
    "wof:placetype":"venue"
},
  "geometry": {"coordinates":[9.130413,45.404922],"type":"Point"}
}