{
  "type": "Feature",
  "properties": {
    "addr:full":"Corso Alla Mano 127/b 10090 Cascine Vica Torino 10090",
    "addr:housenumber":"127 / b",
    "addr:postcode":"10090;10090",
    "addr:street":"Corso Alla Mano",
    "iso:country":"IT",
    "sg:address":"Corso Alla Mano 127/b 10090 Cascine Vica",
    "sg:orig_category":"Gearboxes, Drives",
    "sg:phone":"+39 011 957 6404",
    "sg:postcode":"10090",
    "sg:province":"Torino",
    "sg:website":"www.licat.it",
    "wof:name":"Licat Srl",
    "wof:placetype":"venue"
},
  "geometry": {"coordinates":[7.686619,45.07056],"type":"Point"}
}