{
  "type": "Feature",
  "properties": {
    "iso:country":"IT",
    "sg:address":"10134 Torino",
    "sg:city":"Torino",
    "sg:classifiers":[
        {
            "category":"Health Services",
            "subcategory":"Health Practitioner",
            "type":"Services"
        }
    ],
    "sg:phone":"+39 011 396275",
    "sg:postcode":"10134",
    "sg:province":"Torino",
    "sg:tags":[
        "medici"
    ],
    "wof:name":"Istituto Di Medicina Dello Sport Di Torino",
    "wof:placetype":"venue"
},
  "geometry": {"coordinates":[7.652199,45.03957],"type":"Point"}
}