{
  "type": "Feature",
  "properties": {
    "addr:full":"80056 Ercolano Ercolano Napoli 80056",
    "addr:postcode":"80056;80056",
    "iso:country":"IT",
    "sg:address":"80056 Ercolano",
    "sg:city":"Ercolano",
    "sg:orig_category":"Biancheria, Telerie E Coperte. Forniture Alle Strutture Ricettive",
    "sg:phone":"+39 081 739 7075",
    "sg:postcode":"80056",
    "sg:province":"Napoli",
    "wof:name":"Badipatex S.d.f.",
    "wof:placetype":"venue"
},
  "geometry": {"coordinates":[14.353667,40.80661],"type":"Point"}
}