{
  "type": "Feature",
  "properties": {
    "addr:full":"24061 Albano Sant'alessandro Bergamo 24061",
    "addr:postcode":"24061;24061",
    "iso:country":"IT",
    "sg:address":"24061 Albano Sant'alessandro",
    "sg:orig_category":"Prodotti E Manufatti In Materie Plastiche. Forniture Per Attivita' Industriali",
    "sg:phone":"+39 035 581444",
    "sg:postcode":"24061",
    "sg:province":"Bergamo",
    "wof:name":"S.i.p. Di Dr.ing.ascanio Pelizzari & C. (s.n.c.)",
    "wof:placetype":"venue"
},
  "geometry": {"coordinates":[9.7505903244,45.6871337891],"type":"Point"}
}