{
  "type": "Feature",
  "properties": {
    "addr:full":"26015 Soresina Soresina Cremona 26015",
    "addr:postcode":"26015;26015",
    "iso:country":"IT",
    "sg:address":"26015 Soresina",
    "sg:city":"Soresina",
    "sg:orig_category":"Servizi Di Magazzinaggio E Movimentazione",
    "sg:phone":"+39 0374 342721",
    "sg:postcode":"26015",
    "sg:province":"Cremona",
    "wof:name":"Ciboldi Snc Di Ciboldi R.& C.",
    "wof:placetype":"venue"
},
  "geometry": {"coordinates":[9.974378,45.148712],"type":"Point"}
}