{
  "type": "Feature",
  "properties": {
    "iso:country":"IT",
    "sg:address":"20091 Bresso",
    "sg:city":"Bresso",
    "sg:orig_category":"Impianti, Attrezzature E Forniture Sanitarie Ed Ospedaliere. Macchine, Strumenti Ed Apparecchi Per Attivita' Industriali",
    "sg:phone":"+39 02 614 0412",
    "sg:postcode":"20091",
    "sg:province":"Milano",
    "wof:name":"Maint-air S.a.s. Di Ferrari Romeo",
    "wof:placetype":"venue"
},
  "geometry": {"coordinates":[9.19422,45.529743],"type":"Point"}
}