{
  "type": "Feature",
  "properties": {
    "iso:country":"IT",
    "sg:address":"22063 Cantu'",
    "sg:orig_category":"Servizi E Lavori Per Arredamento E Industria Del Legno",
    "sg:phone":"+39 031 716635",
    "sg:postcode":"22063",
    "sg:province":"Como",
    "wof:name":"Unilegno (s.r.l.)",
    "wof:placetype":"venue"
},
  "geometry": {"coordinates":[9.125119,45.732307],"type":"Point"}
}