{
  "type": "Feature",
  "properties": {
    "addr:full":"66, Via Aurelia Nord 58100 Grosseto Grosseto Grosseto 58100",
    "addr:postcode":"58100;58100",
    "addr:street":"Via Aurelia Nord",
    "iso:country":"IT",
    "sg:address":"66, Via Aurelia Nord 58100 Grosseto",
    "sg:city":"Grosseto",
    "sg:classifiers":[
        {
            "category":"Manufacturing",
            "subcategory":"Lumber",
            "type":"Manufacturing & Wholesale Goods"
        }
    ],
    "sg:phone":"+39 0564 458964",
    "sg:postcode":"58100",
    "sg:province":"Grosseto",
    "sg:tags":[
        "wood"
    ],
    "wof:name":"Quercia E Antichi Srl",
    "wof:placetype":"venue"
},
  "geometry": {"coordinates":[11.106072,42.772106],"type":"Point"}
}