{
  "type": "Feature",
  "properties": {
    "iso:country":"IT",
    "sg:address":"80026 Casoria",
    "sg:city":"Casoria",
    "sg:orig_category":"Materiali E Componenti Elettronici",
    "sg:phone":"+39 081 759 0226",
    "sg:postcode":"80026",
    "sg:province":"Napoli",
    "wof:name":"Mivar Di Carlo Vichi Sapa",
    "wof:placetype":"venue"
},
  "geometry": {"coordinates":[14.299227,40.900738],"type":"Point"}
}