{
  "type": "Feature",
  "properties": {
    "addr:full":"59/d, Via Cesare Battisti 35010 Limena Limena Padova 35010",
    "addr:housenumber":"59 / d",
    "addr:postcode":"35010;35010",
    "addr:street":"Via Cesare Battisti",
    "iso:country":"IT",
    "sg:address":"59/d, Via Cesare Battisti 35010 Limena",
    "sg:city":"Limena",
    "sg:classifiers":[
        {
            "category":"Wholesale",
            "subcategory":"Machinery & Supplies",
            "type":"Manufacturing & Wholesale Goods"
        }
    ],
    "sg:phone":"+39 39049767313",
    "sg:postcode":"35010",
    "sg:province":"Padova",
    "sg:tags":[
        "-",
        "agriculture",
        "equipment"
    ],
    "wof:name":"Tecno Garden (s.r.l.)",
    "wof:placetype":"venue"
},
  "geometry": {"coordinates":[11.842989,45.46748],"type":"Point"}
}