{
  "type": "Feature",
  "properties": {
    "iso:country":"IT",
    "sg:address":"17025 Loano",
    "sg:city":"Loano",
    "sg:orig_category":"Termotecnica E Riscaldamento, Apparecchiature E Servizi",
    "sg:phone":"+39 019 670122",
    "sg:postcode":"17025",
    "sg:province":"Savona",
    "wof:name":"Trabattoni Giuseppe",
    "wof:placetype":"venue"
},
  "geometry": {"coordinates":[8.243361,44.1241],"type":"Point"}
}