{
  "type": "Feature",
  "properties": {
    "iso:country":"IT",
    "sg:address":"59013 Montemurlo",
    "sg:city":"Montemurlo",
    "sg:orig_category":"Sport - Articoli E Forniture",
    "sg:phone":"+39 0574 652603",
    "sg:postcode":"59013",
    "sg:province":"Prato",
    "wof:name":"G.p.r. Srl",
    "wof:placetype":"venue"
},
  "geometry": {"coordinates":[11.045696,43.906754],"type":"Point"}
}