{
  "type": "Feature",
  "properties": {
    "iso:country":"IT",
    "sg:address":"36066 Sandrigo",
    "sg:city":"Sandrigo",
    "sg:orig_category":"Imprese Di Costruzioni Civili Ed Industriali",
    "sg:phone":"+39 0444 659592",
    "sg:postcode":"36066",
    "sg:province":"Vicenza",
    "sg:website":"http://www.pozzatotappezzieri.com",
    "wof:name":"Pozzato Tappezzieri Di Pozzato Rolando",
    "wof:placetype":"venue"
},
  "geometry": {"coordinates":[11.5504,45.632317],"type":"Point"}
}