{
  "type": "Feature",
  "properties": {
    "iso:country":"IT",
    "sg:address":"86, Via Delle Cateratte 57122 Livorno",
    "sg:city":"Livorno",
    "sg:classifiers":[
        {
            "category":"Shopping",
            "subcategory":"Computers & Home Electronics",
            "type":"Retail Goods"
        }
    ],
    "sg:phone":"+39 0586 829938",
    "sg:postcode":"57122",
    "sg:province":"Livorno",
    "sg:tags":[
        "electronic",
        "electrical",
        "equipment"
    ],
    "wof:name":"C.e.me. Srl",
    "wof:placetype":"venue"
},
  "geometry": {"coordinates":[10.312929,43.565918],"type":"Point"}
}