{
  "type": "Feature",
  "properties": {
    "addr:full":"25031 Capriolo Capriolo Brescia 25031",
    "addr:postcode":"25031;25031",
    "iso:country":"IT",
    "sg:address":"25031 Capriolo",
    "sg:city":"Capriolo",
    "sg:orig_category":"Servizi E Lavori Per Arredamento E Industria Del Legno. Servizi E Lavori Per Edilizia E Lavori Pubblici",
    "sg:phone":"+39 030 736 4310",
    "sg:postcode":"25031",
    "sg:province":"Brescia",
    "wof:name":"Palazzi Pietro",
    "wof:placetype":"venue"
},
  "geometry": {"coordinates":[10.01613,45.635952],"type":"Point"}
}