{
  "type": "Feature",
  "properties": {
    "addr:full":"70124 Bari Bari Bari 70124",
    "addr:postcode":"70124;70124",
    "iso:country":"IT",
    "sg:address":"70124 Bari",
    "sg:city":"Bari",
    "sg:orig_category":"Servizi E Lavori Per Ecologia E Smaltimento Rifiuti. Forniture Industriali Per Prevenzione, Controllo E Sicurezza",
    "sg:phone":"+39 080 504 1025",
    "sg:postcode":"70124",
    "sg:province":"Bari",
    "wof:name":"I.c.e.f. Di Rotondo Anna & C. Sas",
    "wof:placetype":"venue"
},
  "geometry": {"coordinates":[16.881926,41.043045],"type":"Point"}
}