{
  "type": "Feature",
  "properties": {
    "iso:country":"IT",
    "sg:address":"Via Piave 8 31050 Ponzano",
    "sg:classifiers":[
        {
            "category":"Train Station",
            "subcategory":"Light Rail",
            "type":"Transportation"
        }
    ],
    "sg:phone":"+39 0422 440665",
    "sg:postcode":"31050",
    "sg:province":"Treviso",
    "sg:tags":[
        "steel",
        "stainless",
        "machining"
    ],
    "sg:website":"www.atlas-italia.it",
    "wof:name":"A.t.l.a.s. Snc",
    "wof:placetype":"venue"
},
  "geometry": {"coordinates":[12.216823,45.702919],"type":"Point"}
}