{
  "type": "Feature",
  "properties": {
    "addr:full":"10024 Moncalieri Moncalieri Torino 10024",
    "addr:postcode":"10024;10024",
    "iso:country":"IT",
    "sg:address":"10024 Moncalieri",
    "sg:city":"Moncalieri",
    "sg:orig_category":"Prodotti Finiti Stampati. Forniture E Materiali Per Imballaggio E Confezionamento. Forniture Per Attivita' Commerciali Ed Artigianali",
    "sg:phone":"+39 011 682 9200",
    "sg:postcode":"10024",
    "sg:province":"Torino",
    "wof:name":"Sa.ni.cart Snc Di Tibaldi G. & C.",
    "wof:placetype":"venue"
},
  "geometry": {"coordinates":[7.666765213,44.9896240234],"type":"Point"}
}