{
  "type": "Feature",
  "properties": {
    "iso:country":"IT",
    "sg:address":"20121 Milano",
    "sg:city":"Milano",
    "sg:orig_category":"Hobbistica",
    "sg:phone":"+39 02 659 6179",
    "sg:postcode":"20121",
    "sg:province":"Milano",
    "wof:name":"Memoli Ernesto",
    "wof:placetype":"venue"
},
  "geometry": {"coordinates":[9.183088,45.480331],"type":"Point"}
}