{
  "type": "Feature",
  "properties": {
    "addr:full":"25024 Leno Leno Brescia 25024",
    "addr:postcode":"25024;25024",
    "iso:country":"IT",
    "sg:address":"25024 Leno",
    "sg:city":"Leno",
    "sg:orig_category":"Servizi Ausiliari Di Analisi, Controllo E Ricerca",
    "sg:phone":"+39 030 904 8489",
    "sg:postcode":"25024",
    "sg:province":"Brescia",
    "wof:name":"Sqs System Quality Service Srl",
    "wof:placetype":"venue"
},
  "geometry": {"coordinates":[10.212001,45.543854],"type":"Point"}
}