{
  "type": "Feature",
  "properties": {
    "iso:country":"IT",
    "sg:address":"94010 Villarosa",
    "sg:city":"Villarosa",
    "sg:orig_category":"Marmo, Pietre Ed Affini. Arte Ed Artigianato Artistico",
    "sg:phone":"+39 0935 31560",
    "sg:postcode":"94010",
    "sg:province":"Enna",
    "wof:name":"L.c.a. Fotoceramiche Di Lafuria Lorenzo",
    "wof:placetype":"venue"
},
  "geometry": {"coordinates":[14.172171,37.586979],"type":"Point"}
}