{
  "type": "Feature",
  "properties": {
    "iso:country":"IT",
    "sg:address":"70051 Barletta",
    "sg:city":"Barletta",
    "sg:orig_category":"Prodotti Vari In Metallo. Articoli Per Imballaggio E Confezionamento",
    "sg:phone":"+39 0883 510700",
    "sg:postcode":"70051",
    "sg:province":"Bari",
    "wof:name":"Rizzi Ruggero",
    "wof:placetype":"venue"
},
  "geometry": {"coordinates":[16.2347106934,41.3255577087],"type":"Point"}
}