{
  "type": "Feature",
  "properties": {
    "addr:full":"Viale Trento 30 26845 Codogno Codogno Lodi 26845",
    "addr:housenumber":"30",
    "addr:postcode":"26845;26845",
    "addr:street":"Viale Trento",
    "iso:country":"IT",
    "sg:address":"Viale Trento 30 26845 Codogno",
    "sg:city":"Codogno",
    "sg:classifiers":[
        {
            "category":"Manufacturing",
            "subcategory":"Textiles",
            "type":"Manufacturing & Wholesale Goods"
        }
    ],
    "sg:phone":"+39 0377 31341",
    "sg:postcode":"26845",
    "sg:province":"Lodi",
    "sg:tags":[
        "natural"
    ],
    "sg:website":"www.leoni-felisi.com",
    "wof:name":"Leoni Felisi Spa",
    "wof:placetype":"venue"
},
  "geometry": {"coordinates":[9.696589,45.162395],"type":"Point"}
}