{
  "type": "Feature",
  "properties": {
    "iso:country":"IT",
    "sg:address":"00198 Roma",
    "sg:city":"Roma",
    "sg:orig_category":"Impiantistica E Prodotti Tecnologici Per Edilizia. Servizi Ausiliari Di Sorveglianza, Manutenzione E Pulizia",
    "sg:phone":"+39 06 841 1005",
    "sg:postcode":"00198",
    "sg:province":"Roma",
    "wof:name":"Si.m.av. Spa",
    "wof:placetype":"venue"
},
  "geometry": {"coordinates":[12.643183,42.039501],"type":"Point"}
}