{
  "type": "Feature",
  "properties": {
    "addr:full":"2, Corso Umberto I 62012 Civitanova Marche Civitanova Marche Macerata 62012",
    "addr:postcode":"62012;62012",
    "addr:street":"Corso Umberto I",
    "iso:country":"IT",
    "sg:address":"2, Corso Umberto I 62012 Civitanova Marche",
    "sg:city":"Civitanova Marche",
    "sg:classifiers":[
        {
            "category":"Shopping",
            "subcategory":"Clothing, Apparel, & Fashions",
            "type":"Retail Goods"
        }
    ],
    "sg:phone":"+39 0733 816139",
    "sg:postcode":"62012",
    "sg:province":"Macerata",
    "sg:tags":[
        "clothes"
    ],
    "wof:name":"Kinder (s.a.s.)",
    "wof:placetype":"venue"
},
  "geometry": {"coordinates":[13.72833,43.307083],"type":"Point"}
}