{
  "type": "Feature",
  "properties": {
    "addr:full":"24034 Cisano Bergamasco Cisano Bergamasco Bergamo 24034",
    "addr:postcode":"24034;24034",
    "iso:country":"IT",
    "sg:address":"24034 Cisano Bergamasco",
    "sg:city":"Cisano Bergamasco",
    "sg:orig_category":"Informatica - Consulenza E Servizi. Editoria",
    "sg:phone":"+39 035 787714",
    "sg:postcode":"24034",
    "sg:province":"Bergamo",
    "sg:website":"http://www.gsr.it",
    "wof:name":"G.s.r. Srl",
    "wof:placetype":"venue"
},
  "geometry": {"coordinates":[9.4692850113,45.7446289062],"type":"Point"}
}