{
  "type": "Feature",
  "properties": {
    "iso:country":"IT",
    "sg:address":"Vle Dell' Industria, 9/11 35010 Pieve Di Curtarolo",
    "sg:city":"Curtarolo",
    "sg:classifiers":[
        {
            "category":"Food & Beverages",
            "subcategory":"Meat & Fish",
            "type":"Retail Goods"
        }
    ],
    "sg:phone":"+39 049 969 8666",
    "sg:postcode":"35010",
    "sg:province":"Padova",
    "sg:tags":[
        "cutter-machines"
    ],
    "sg:website":"www.sirman.com",
    "wof:name":"Sirman S.p.a.",
    "wof:placetype":"venue"
},
  "geometry": {"coordinates":[11.876589,45.409569],"type":"Point"}
}