{
  "type": "Feature",
  "properties": {
    "iso:country":"IT",
    "sg:address":"24035 Curno",
    "sg:city":"Curno",
    "sg:classifiers":[
        {
            "category":"Wholesale",
            "subcategory":"Home Furnishings",
            "type":"Manufacturing & Wholesale Goods"
        }
    ],
    "sg:phone":"+39 035 202100",
    "sg:postcode":"24035",
    "sg:province":"Bergamo",
    "sg:tags":[
        "household",
        "appliance",
        "furnishings",
        "appliances",
        "kitchen"
    ],
    "sg:website":"http://www.mediaworld.it",
    "wof:name":"Mediamarket Spa - Media World",
    "wof:placetype":"venue"
},
  "geometry": {"coordinates":[9.6166448593,45.6835746765],"type":"Point"}
}