{
  "type": "Feature",
  "properties": {
    "iso:country":"IT",
    "sg:address":"16, Localita' Fracanzana 36054 Montebello Vicentino",
    "sg:city":"Montebello Vicentino",
    "sg:classifiers":[
        {
            "category":"Shopping",
            "subcategory":"Crafts & Fabrics",
            "type":"Retail Goods"
        }
    ],
    "sg:phone":"+39 0444 648692",
    "sg:postcode":"36054",
    "sg:province":"Vicenza",
    "wof:name":"Montebello Trading (s.r.l.)",
    "wof:placetype":"venue"
},
  "geometry": {"coordinates":[11.373468399,45.4392318726],"type":"Point"}
}