{
  "type": "Feature",
  "properties": {
    "addr:full":"153, Via Papa Giovanni Xxiii 20010 Arluno Arluno Milano 20010",
    "addr:housenumber":"153",
    "addr:postcode":"20010;20010",
    "addr:street":"Via Papa Giovanni Xxiii",
    "iso:country":"IT",
    "sg:address":"153, Via Papa Giovanni Xxiii 20010 Arluno",
    "sg:city":"Arluno",
    "sg:classifiers":[
        {
            "category":"Autos & Motor Vehicles",
            "subcategory":"Automobile Sales",
            "type":"Retail Goods"
        }
    ],
    "sg:phone":"+39 39029017837",
    "sg:postcode":"20010",
    "sg:province":"Milano",
    "sg:tags":[
        "industrial"
    ],
    "wof:name":"Con.a.p.",
    "wof:placetype":"venue"
},
  "geometry": {"coordinates":[8.927085,45.50597],"type":"Point"}
}