{
  "type": "Feature",
  "properties": {
    "addr:full":"1/11, Via Romani Carolina 20091 Bresso Bresso Milano 20091",
    "addr:housenumber":"1 / 11",
    "addr:postcode":"20091;20091",
    "addr:street":"Via Romani",
    "iso:country":"IT",
    "sg:address":"1/11, Via Romani Carolina 20091 Bresso",
    "sg:city":"Bresso",
    "sg:classifiers":[
        {
            "category":"Wholesale",
            "subcategory":"Machinery & Supplies",
            "type":"Manufacturing & Wholesale Goods"
        }
    ],
    "sg:phone":"+39 02 6650 3204",
    "sg:postcode":"20091",
    "sg:province":"Milano",
    "sg:tags":[
        "equipment",
        "precision"
    ],
    "wof:name":"Chugai Boyeki Uk Ltd Italia",
    "wof:placetype":"venue"
},
  "geometry": {"coordinates":[9.1892356873,45.5443305969],"type":"Point"}
}