{
  "type": "Feature",
  "properties": {
    "addr:full":"34170 Gorizia Gorizia Gorizia 34170",
    "addr:postcode":"34170;34170",
    "iso:country":"IT",
    "sg:address":"34170 Gorizia",
    "sg:city":"Gorizia",
    "sg:orig_category":"Pompe. Ricambi E Componenti Dei Mezzi Di Trasporto",
    "sg:phone":"+39 0481 20425",
    "sg:postcode":"34170",
    "sg:province":"Gorizia",
    "wof:name":"A. Mlakar Srl",
    "wof:placetype":"venue"
},
  "geometry": {"coordinates":[13.5991439819,45.9438247681],"type":"Point"}
}