{
  "type": "Feature",
  "properties": {
    "iso:country":"IT",
    "sg:address":"04011 Aprilia",
    "sg:city":"Aprilia",
    "sg:orig_category":"Servizi Ausiliari Dei Mezzi Di Trasporto",
    "sg:phone":"+39 06 9270 7996",
    "sg:postcode":"04011",
    "sg:province":"Latina",
    "wof:name":"Greci Pietro Paolo",
    "wof:placetype":"venue"
},
  "geometry": {"coordinates":[12.656704,41.648254],"type":"Point"}
}