{
  "type": "Feature",
  "properties": {
    "addr:full":"88100 Catanzaro Catanzaro Catanzaro 88100",
    "addr:postcode":"88100;88100",
    "iso:country":"IT",
    "sg:address":"88100 Catanzaro",
    "sg:city":"Catanzaro",
    "sg:orig_category":"Antifurto",
    "sg:phone":"+39 0961 741263",
    "sg:postcode":"88100",
    "sg:province":"Catanzaro",
    "wof:name":"M & B Elettronica",
    "wof:placetype":"venue"
},
  "geometry": {"coordinates":[16.591059,38.91399],"type":"Point"}
}