{
  "type": "Feature",
  "properties": {
    "iso:country":"IT",
    "sg:address":"14100 Asti",
    "sg:city":"Asti",
    "sg:orig_category":"Arredo Cucina Ed Elettrodomestici. Frigotecnica, Apparecchiature E Servizi. Elettrodomestici",
    "sg:phone":"+39 0141 273716",
    "sg:postcode":"14100",
    "sg:province":"Asti",
    "wof:name":"Accornero Mauro",
    "wof:placetype":"venue"
},
  "geometry": {"coordinates":[8.217356,44.908909],"type":"Point"}
}