{
  "type": "Feature",
  "properties": {
    "addr:full":"00166 Roma Roma Roma 00166",
    "addr:postcode":"00166;00166",
    "iso:country":"IT",
    "sg:address":"00166 Roma",
    "sg:city":"Roma",
    "sg:orig_category":"Pubblica Amministrazione",
    "sg:phone":"+39 06 6156 6334",
    "sg:postcode":"00166",
    "sg:province":"Roma",
    "wof:name":"Carabinieri",
    "wof:placetype":"venue"
},
  "geometry": {"coordinates":[12.3726491928,41.9161987305],"type":"Point"}
}