{
  "type": "Feature",
  "properties": {
    "addr:full":"06023 Gualdo Tadino Gualdo Tadino Perugia 06023",
    "addr:postcode":"06023;06023",
    "iso:country":"IT",
    "sg:address":"06023 Gualdo Tadino",
    "sg:city":"Gualdo Tadino",
    "sg:orig_category":"Materiali Semilavorati Metallici",
    "sg:phone":"+39 075 916701",
    "sg:postcode":"06023",
    "sg:province":"Perugia",
    "wof:name":"B & B Di Bucci Gianni E Buglioni Cesare S.n.c.",
    "wof:placetype":"venue"
},
  "geometry": {"coordinates":[12.779157,43.230736],"type":"Point"}
}