{
  "type": "Feature",
  "properties": {
    "iso:country":"IT",
    "sg:address":"73040 Morciano Di Leuca",
    "sg:city":"Leuca",
    "sg:orig_category":"Prodotti Chimici Secondari",
    "sg:phone":"+39 0833 743131",
    "sg:postcode":"73040",
    "sg:province":"Lecce",
    "wof:name":"Fracasso Antonio",
    "wof:placetype":"venue"
},
  "geometry": {"coordinates":[18.3132953644,39.8489265442],"type":"Point"}
}