{
  "type": "Feature",
  "properties": {
    "addr:full":"Via Battisti 35 50013 Campi Bisenzio Campi Bisenzio Firenze 50013",
    "addr:housenumber":"35",
    "addr:postcode":"50013;50013",
    "addr:street":"Via Battisti;Bisenzio",
    "iso:country":"IT",
    "sg:address":"Via Battisti 35 50013 Campi Bisenzio",
    "sg:city":"Campi Bisenzio",
    "sg:classifiers":[
        {
            "category":"Manufacturing",
            "subcategory":"Furniture",
            "type":"Manufacturing & Wholesale Goods"
        }
    ],
    "sg:phone":"+39 055 896 0380",
    "sg:postcode":"50013",
    "sg:province":"Firenze",
    "sg:tags":[
        "fabric"
    ],
    "wof:name":"Eredi Baldi Lido S.n.c. Di Baldi Alessandro",
    "wof:placetype":"venue"
},
  "geometry": {"coordinates":[11.1306266785,43.8162155151],"type":"Point"}
}