{
  "type": "Feature",
  "properties": {
    "iso:country":"IT",
    "sg:address":"20052 Monza",
    "sg:city":"Monza",
    "sg:orig_category":"Accessori Moda D'abbigliamento",
    "sg:phone":"+39 039 202 6782",
    "sg:postcode":"20052",
    "sg:province":"Milano",
    "wof:name":"Agam Srl",
    "wof:placetype":"venue"
},
  "geometry": {"coordinates":[9.175843,45.41671],"type":"Point"}
}