{
  "type": "Feature",
  "properties": {
    "iso:country":"IT",
    "sg:address":"Via Dell' Aione Sorbano Giudice 55100 Lucca",
    "sg:city":"Lucca",
    "sg:classifiers":[
        {
            "category":"Manufacturing",
            "subcategory":"Rubber & Plastics",
            "type":"Manufacturing & Wholesale Goods"
        }
    ],
    "sg:phone":"+39 0583 584071",
    "sg:postcode":"55100",
    "sg:province":"Lucca",
    "wof:name":"Ma.gi.plast S.r.l.",
    "wof:placetype":"venue"
},
  "geometry": {"coordinates":[10.5079936981,43.8430137634],"type":"Point"}
}