{
  "type": "Feature",
  "properties": {
    "iso:country":"IT",
    "sg:address":"20030 Camnago",
    "sg:city":"Camnago",
    "sg:orig_category":"Macchine E Forniture Per Ecologia E Smaltimento Rifiuti. Ricambi E Componenti Dei Mezzi Di Trasporto",
    "sg:phone":"+39 036 255 7722",
    "sg:postcode":"20030",
    "sg:province":"Milano",
    "wof:name":"Lombarda Filtri (s.r.l.)",
    "wof:placetype":"venue"
},
  "geometry": {"coordinates":[9.03625,45.526287],"type":"Point"}
}