{
  "type": "Feature",
  "properties": {
    "addr:full":"10142 Torino Torino Torino 10142",
    "addr:postcode":"10142;10142",
    "iso:country":"IT",
    "sg:address":"10142 Torino",
    "sg:city":"Torino",
    "sg:orig_category":"Forniture Per Edilizia E Lavori Pubblici. Forniture Per Attivita' Industriali",
    "sg:phone":"+39 011 700205",
    "sg:postcode":"10142",
    "sg:province":"Torino",
    "wof:name":"Borrelli Nicola Silvano",
    "wof:placetype":"venue"
},
  "geometry": {"coordinates":[7.6131873131,45.0689048767],"type":"Point"}
}