{
  "type": "Feature",
  "properties": {
    "iso:country":"IT",
    "sg:address":"41013 Castelfranco Emilia",
    "sg:city":"Castelfranco Emilia",
    "sg:orig_category":"Trattamenti Termici E Superficiali Metalli, Galvanotecnica",
    "sg:phone":"+39 059 922105",
    "sg:postcode":"41013",
    "sg:province":"Modena",
    "sg:website":"http://www.i-sr.com",
    "wof:name":"Industrial Solutions Research Srl",
    "wof:placetype":"venue"
},
  "geometry": {"coordinates":[11.014598,44.61673],"type":"Point"}
}