{
  "type": "Feature",
  "properties": {
    "addr:full":"Via Elpidiense Sud 63014 Montegranaro Montegranaro Ascoli Piceno 63014",
    "addr:postcode":"63014;63014",
    "addr:street":"Via Elpidiense Sud",
    "iso:country":"IT",
    "sg:address":"Via Elpidiense Sud 63014 Montegranaro",
    "sg:city":"Montegranaro",
    "sg:classifiers":[
        {
            "category":"Personal",
            "subcategory":"Shoe Repair & Shine",
            "type":"Services"
        }
    ],
    "sg:phone":"+39 0734 891337",
    "sg:postcode":"63014",
    "sg:province":"Ascoli Piceno",
    "sg:tags":[
        "leather"
    ],
    "wof:name":"Calzaturificio Saint Ferry (s.p.a.)",
    "wof:placetype":"venue"
},
  "geometry": {"coordinates":[13.649,43.236984],"type":"Point"}
}