{
  "type": "Feature",
  "properties": {
    "addr:full":"06062 Citt\u00e0 Della Pieve Perugia 06062",
    "addr:postcode":"06062;06062",
    "iso:country":"IT",
    "sg:address":"06062 Citt\u00e0 Della Pieve",
    "sg:orig_category":"Prodotti E Manufatti In Gomma. Servizi E Lavori Industria Della Gomma. Ricambi E Componenti Dei Mezzi Di Trasporto. Riparazione Dei Mezzi Di Trasporto",
    "sg:phone":"+39 0578 299211",
    "sg:postcode":"06062",
    "sg:province":"Perugia",
    "sg:website":"http://www.rubeca.it",
    "wof:name":"Rubeca Francesco & C. Snc",
    "wof:placetype":"venue"
},
  "geometry": {"coordinates":[12.0032958984,42.9477729797],"type":"Point"}
}