{
  "type": "Feature",
  "properties": {
    "addr:full":"00193 Roma Roma Roma 00193",
    "addr:postcode":"00193;00193",
    "iso:country":"IT",
    "sg:address":"00193 Roma",
    "sg:city":"Roma",
    "sg:orig_category":"Servizi Ausiliari Di Certificati, Riproduzioni, Disegni E Foto",
    "sg:phone":"+39 06 322 6982",
    "sg:postcode":"00193",
    "sg:province":"Roma",
    "wof:name":"Allucinazione",
    "wof:placetype":"venue"
},
  "geometry": {"coordinates":[12.884376,41.889793],"type":"Point"}
}