{
  "type": "Feature",
  "properties": {
    "iso:country":"IT",
    "sg:address":"38100 Trento",
    "sg:city":"Trento",
    "sg:orig_category":"Abbigliamento Esterno, Maglierie E Pelliccerie. Calzature, Pelletterie E Pelli",
    "sg:phone":"+39 0461 910143",
    "sg:postcode":"38100",
    "sg:province":"Trento",
    "wof:name":"Zanolli (s.a.s.)",
    "wof:placetype":"venue"
},
  "geometry": {"coordinates":[11.128464,46.057194],"type":"Point"}
}