{
  "type": "Feature",
  "properties": {
    "iso:country":"IT",
    "sg:address":"Via Provinciale Sud 74 42017 Novellara",
    "sg:classifiers":[
        {
            "category":"Manufacturing",
            "subcategory":"Tools & Machinery",
            "type":"Manufacturing & Wholesale Goods"
        }
    ],
    "sg:phone":"+39 0522 657117",
    "sg:postcode":"42017",
    "sg:province":"Reggio Nell'Emilia",
    "sg:tags":[
        "wheel",
        "agricultural"
    ],
    "sg:website":"www.monariruote.it",
    "wof:name":"Monari Ruote Srl",
    "wof:placetype":"venue"
},
  "geometry": {"coordinates":[10.705789,44.818977],"type":"Point"}
}