{
  "type": "Feature",
  "properties": {
    "iso:country":"IT",
    "sg:address":"24052 Azzano San Paolo",
    "sg:city":"Azzano San Paolo",
    "sg:orig_category":"Lavorazioni Metalli, Stampaggio E Saldatura",
    "sg:phone":"+39 035 530060",
    "sg:postcode":"24052",
    "sg:province":"Bergamo",
    "wof:name":"Officina Meccanica Fratelli Stroppa Srl",
    "wof:placetype":"venue"
},
  "geometry": {"coordinates":[9.679255,45.657684],"type":"Point"}
}