{
  "type": "Feature",
  "properties": {
    "iso:country":"IT",
    "sg:address":"22079 Villa Guardia",
    "sg:city":"Villa Guardia",
    "sg:orig_category":"Servizi E Lavori Per Agricoltura E Zootecnia. Servizi E Lavori Industria Chimica. Servizi Ausiliari Di Analisi, Controllo E Ricerca",
    "sg:phone":"+39 031 480870",
    "sg:postcode":"22079",
    "sg:province":"Como",
    "wof:name":"Tecnoeco S.r.l.",
    "wof:placetype":"venue"
},
  "geometry": {"coordinates":[9.041237,45.781586],"type":"Point"}
}