{
  "type": "Feature",
  "properties": {
    "iso:country":"IT",
    "sg:address":"Via Dell' Areonautica 24035 Curno",
    "sg:city":"Curno",
    "sg:classifiers":[
        {
            "category":"Shopping",
            "subcategory":"Crafts & Fabrics",
            "type":"Retail Goods"
        }
    ],
    "sg:phone":"+39 39035615053",
    "sg:postcode":"24035",
    "sg:province":"Bergamo",
    "sg:tags":[
        "linen"
    ],
    "wof:name":"Beppe Visconti (s.r.l.)",
    "wof:placetype":"venue"
},
  "geometry": {"coordinates":[9.6187801361,45.6937789917],"type":"Point"}
}