{
  "type": "Feature",
  "properties": {
    "iso:country":"IT",
    "sg:address":"20121 Milano",
    "sg:city":"Milano",
    "sg:orig_category":"Cucine Componibili",
    "sg:phone":"+39 02 2900 0316",
    "sg:postcode":"20121",
    "sg:province":"Milano",
    "sg:website":"http://www.febal.it",
    "wof:name":"Febal Cucine Spa",
    "wof:placetype":"venue"
},
  "geometry": {"coordinates":[9.191478,45.473034],"type":"Point"}
}