{
  "type": "Feature",
  "properties": {
    "addr:full":"20156 Milano Milano Milano 20156",
    "addr:postcode":"20156;20156",
    "iso:country":"IT",
    "sg:address":"20156 Milano",
    "sg:city":"Milano",
    "sg:orig_category":"Telecomunicazioni E Telefonia, Impianti, Apparecchi E Servizi. Acqua, Luce, Gas E Societa' Di Esercizio Pubblico. Servizi Vari Di Interesse Pubblico",
    "sg:phone":"+39 02 392 5265",
    "sg:postcode":"20156",
    "sg:province":"Milano",
    "wof:name":"Torre Eiffel Di Ahmed Ali",
    "wof:placetype":"venue"
},
  "geometry": {"coordinates":[9.146535,45.494293],"type":"Point"}
}