{
  "type": "Feature",
  "properties": {
    "iso:country":"IT",
    "sg:address":"16, Via Primo Maggio 46030 San Giorgio Di Mantova",
    "sg:city":"San Giorgio di Mantova",
    "sg:classifiers":[
        {
            "category":"Professional",
            "subcategory":"Engineering",
            "type":"Services"
        }
    ],
    "sg:phone":"+39 0376 372206",
    "sg:postcode":"46030",
    "sg:province":"Mantova",
    "sg:tags":[
        "machine",
        "-",
        "mechanical"
    ],
    "wof:name":"Arca (s.r.l.)",
    "wof:placetype":"venue"
},
  "geometry": {"coordinates":[10.871956,45.172455],"type":"Point"}
}