{
  "type": "Feature",
  "properties": {
    "addr:full":"10095 Grugliasco Grugliasco Torino 10095",
    "addr:postcode":"10095;10095",
    "iso:country":"IT",
    "sg:address":"10095 Grugliasco",
    "sg:city":"Grugliasco",
    "sg:orig_category":"Attrezzature Meccaniche",
    "sg:phone":"+39 011 785757",
    "sg:postcode":"10095",
    "sg:province":"Torino",
    "wof:name":"Rotomors Spa",
    "wof:placetype":"venue"
},
  "geometry": {"coordinates":[7.585043,45.049137],"type":"Point"}
}