{
  "type": "Feature",
  "properties": {
    "iso:country":"IT",
    "sg:address":"20127 Milano",
    "sg:city":"Milano",
    "sg:orig_category":"Servizi E Lavori Per Abbigliamento E Pelletterie",
    "sg:phone":"+39 02 284 0840",
    "sg:postcode":"20127",
    "sg:province":"Milano",
    "wof:name":"Gatto Anna Maria",
    "wof:placetype":"venue"
},
  "geometry": {"coordinates":[9.2195625305,45.4949073792],"type":"Point"}
}