{
  "type": "Feature",
  "properties": {
    "iso:country":"IT",
    "sg:address":"27039 Sannazzaro Burgondi",
    "sg:orig_category":"Termotecnica E Riscaldamento, Apparecchiature E Servizi",
    "sg:phone":"+39 0382 997146",
    "sg:postcode":"27039",
    "sg:province":"Pavia",
    "wof:name":"Impes Costruzioni Termotecniche Snc Di Fasani C. & Tassi C.",
    "wof:placetype":"venue"
},
  "geometry": {"coordinates":[9.180284,45.192577],"type":"Point"}
}