{
  "type": "Feature",
  "properties": {
    "iso:country":"IT",
    "sg:address":"Via Trento 2 20067 Tribiano",
    "sg:city":"Tribiano",
    "sg:classifiers":[
        {
            "category":"Wholesale",
            "subcategory":"Vending Machines",
            "type":"Manufacturing & Wholesale Goods"
        }
    ],
    "sg:phone":"+39 02 906 4717",
    "sg:postcode":"20067",
    "sg:province":"Milano",
    "sg:tags":[
        "food",
        "special-design",
        "processing",
        "industry"
    ],
    "sg:website":"www.velati.com",
    "wof:name":"Velati Srl",
    "wof:placetype":"venue"
},
  "geometry": {"coordinates":[9.382344,45.410007],"type":"Point"}
}