{
  "type": "Feature",
  "properties": {
    "iso:country":"IT",
    "sg:address":"Via Colognola 1/b 24060 Viadanica",
    "sg:city":"Viadanica",
    "sg:classifiers":[
        {
            "category":"Professional",
            "type":"Services"
        }
    ],
    "sg:phone":"+39 035 928489",
    "sg:postcode":"24060",
    "sg:province":"Bergamo",
    "sg:tags":[
        "mould",
        "construction"
    ],
    "sg:website":"www.orpstampi.com",
    "wof:name":"Or.p. Stampi Srl",
    "wof:placetype":"venue"
},
  "geometry": {"coordinates":[9.6699523926,45.6949043274],"type":"Point"}
}