{
  "type": "Feature",
  "properties": {
    "iso:country":"IT",
    "sg:address":"26010 Bolzone",
    "sg:city":"Bolzone",
    "sg:orig_category":"Prodotti Vari In Metallo",
    "sg:phone":"+39 0373 258642",
    "sg:postcode":"26010",
    "sg:province":"Cremona",
    "wof:name":"Allanconi Giordano  Ottavio E Pietro S.n.c.",
    "wof:placetype":"venue"
},
  "geometry": {"coordinates":[10.1128387451,45.1358108521],"type":"Point"}
}