{
  "type": "Feature",
  "properties": {
    "iso:country":"IT",
    "sg:address":"95020 Ficarazzi Di Catania",
    "sg:orig_category":"Macchine E Forniture Per Arredamento E Industria Del Legno. Macchine Utensili E Impianti",
    "sg:phone":"+39 095 279100",
    "sg:postcode":"95020",
    "sg:province":"Catania",
    "wof:name":"Fabio Guardo",
    "wof:placetype":"venue"
},
  "geometry": {"coordinates":[15.125436,37.55912],"type":"Point"}
}