{
  "type": "Feature",
  "properties": {
    "iso:country":"IT",
    "sg:address":"37050 Concamarise",
    "sg:city":"Concamarise",
    "sg:orig_category":"Valvole E Apparecchiature Di Misura. Attrezzature E Forniture Per Officine Riparazione E Servizi Ausiliari. Macchine, Strumenti Ed Apparecchi Per Attivita' Industriali",
    "sg:phone":"+39 0442 83208",
    "sg:postcode":"37050",
    "sg:province":"Verona",
    "wof:name":"Furlan Emanuele",
    "wof:placetype":"venue"
},
  "geometry": {"coordinates":[11.143103,45.21487],"type":"Point"}
}