{
  "type": "Feature",
  "properties": {
    "addr:full":"Via N. Tommaseo 4 36015 Schio Schio Vicenza 36015",
    "addr:housenumber":"4",
    "addr:postcode":"36015;36015",
    "addr:street":"Via N. Tommaseo",
    "iso:country":"IT",
    "sg:address":"Via N. Tommaseo 4 36015 Schio",
    "sg:city":"Schio",
    "sg:classifiers":[
        {
            "category":"Arena",
            "subcategory":"Auto Racetrack",
            "type":"Entertainment"
        }
    ],
    "sg:phone":"+39 0445 670266",
    "sg:postcode":"36015",
    "sg:province":"Vicenza",
    "sg:tags":[
        "machine",
        "cutting-out"
    ],
    "sg:website":"www.optima.it/bolla",
    "wof:name":"Luigi Bolla Srl",
    "wof:placetype":"venue"
},
  "geometry": {"coordinates":[11.540307,45.545906],"type":"Point"}
}