{
  "type": "Feature",
  "properties": {
    "iso:country":"IT",
    "sg:address":"70017 Putignano",
    "sg:city":"Putignano",
    "sg:orig_category":"Bevande, Vini E Liquori",
    "sg:phone":"+39 080 491 3586",
    "sg:postcode":"70017",
    "sg:province":"Bari",
    "wof:name":"Drink Shop Di Lippolis Stefania & C. S.a.s.",
    "wof:placetype":"venue"
},
  "geometry": {"coordinates":[17.119753,40.849991],"type":"Point"}
}