{
  "type": "Feature",
  "properties": {
    "iso:country":"IT",
    "sg:address":"3, V. Basse 35010 Campo San Martino",
    "sg:city":"Campo San Martino",
    "sg:classifiers":[
        {
            "category":"Utilities",
            "subcategory":"Telephone",
            "type":"Services"
        }
    ],
    "sg:phone":"+39 049 960 0440",
    "sg:postcode":"35010",
    "sg:province":"Padova",
    "sg:tags":[
        "telecommunication"
    ],
    "sg:website":"http://www.paginegialle.it/",
    "wof:name":"Squizzato Arturo",
    "wof:placetype":"venue"
},
  "geometry": {"coordinates":[11.115941,45.418343],"type":"Point"}
}