{
  "type": "Feature",
  "properties": {
    "addr:full":"80041 Boscoreale Boscoreale Napoli 80041",
    "addr:postcode":"80041;80041",
    "iso:country":"IT",
    "sg:address":"80041 Boscoreale",
    "sg:city":"Boscoreale",
    "sg:orig_category":"Macchine, Impianti E Forniture Per Industria Grafica, Cartaria E Cartotecnica",
    "sg:phone":"+39 081 858 5182",
    "sg:postcode":"80041",
    "sg:province":"Napoli",
    "wof:name":"Imperatore Anna",
    "wof:placetype":"venue"
},
  "geometry": {"coordinates":[14.476203,40.771473],"type":"Point"}
}