{
  "type": "Feature",
  "properties": {
    "iso:country":"IT",
    "sg:address":"80142 Napoli",
    "sg:city":"Napoli",
    "sg:orig_category":"Banche E Servizi Finanziari",
    "sg:phone":"+39 081 269173",
    "sg:postcode":"80142",
    "sg:province":"Napoli",
    "wof:name":"Progetto Finanza",
    "wof:placetype":"venue"
},
  "geometry": {"coordinates":[14.375828,40.864239],"type":"Point"}
}