{
  "type": "Feature",
  "properties": {
    "addr:full":"80133 Napoli Napoli Napoli 80133",
    "addr:housenumber":"80133",
    "addr:postcode":"80133",
    "iso:country":"IT",
    "sg:address":"80133 Napoli",
    "sg:city":"Napoli",
    "sg:orig_category":"Professionisti - Studi E Servizi Ed Associazioni Di Interesse Aziendale. Servizi Sociali. Associazioni Ed Organismi Di Interesse Pubblico",
    "sg:phone":"+39 081 542 7111",
    "sg:postcode":"80133",
    "sg:province":"Napoli",
    "wof:name":"Ipsema - Istituto Di Previdenza Per Il Settore Marittimo",
    "wof:placetype":"venue"
},
  "geometry": {"coordinates":[14.2555828094,40.8410720825],"type":"Point"}
}