{
  "type": "Feature",
  "properties": {
    "iso:country":"IT",
    "sg:address":"12062 Cherasco",
    "sg:city":"Cherasco",
    "sg:orig_category":"Autogru - Noleggio",
    "sg:phone":"+39 0172 495164",
    "sg:postcode":"12062",
    "sg:province":"Cuneo",
    "wof:name":"Sts Di G.b. Veglio & C. Sas",
    "wof:placetype":"venue"
},
  "geometry": {"coordinates":[7.812692,44.660686],"type":"Point"}
}