{
  "type": "Feature",
  "properties": {
    "iso:country":"IT",
    "sg:address":"41043 Formigine",
    "sg:city":"Formigine",
    "sg:orig_category":"Abbigliamento Intimo, Calze E Costumi Da Bagno. Articoli Medico-sanitari Ed Ortopedici",
    "sg:phone":"+39 059 554177",
    "sg:postcode":"41043",
    "sg:province":"Modena",
    "wof:name":"Creazioni P.l. Spa",
    "wof:placetype":"venue"
},
  "geometry": {"coordinates":[10.806056,44.594261],"type":"Point"}
}