{
  "type": "Feature",
  "properties": {
    "iso:country":"IT",
    "sg:address":"00176 Roma",
    "sg:city":"Roma",
    "sg:orig_category":"Vetrate Artistiche",
    "sg:phone":"+39 06 275 4663",
    "sg:postcode":"00176",
    "sg:province":"Roma",
    "wof:name":"Sciarra Vetreria Srl",
    "wof:placetype":"venue"
},
  "geometry": {"coordinates":[12.533494,41.886917],"type":"Point"}
}