{
  "type": "Feature",
  "properties": {
    "iso:country":"IT",
    "sg:address":"00183 Roma",
    "sg:city":"Roma",
    "sg:orig_category":"Automobili E Mezzi Di Trasporto. Riparazione Dei Mezzi Di Trasporto",
    "sg:phone":"+39 06 7049 3942",
    "sg:postcode":"00183",
    "sg:province":"Roma",
    "wof:name":"Rosci Francesco",
    "wof:placetype":"venue"
},
  "geometry": {"coordinates":[12.508293,41.879524],"type":"Point"}
}