{
  "type": "Feature",
  "properties": {
    "addr:full":"11, Via Papa Giovanni Xxiii 24040 Comun Nuovo Comun Nuovo Bergamo 24040",
    "addr:postcode":"24040;24040",
    "addr:street":"Via Papa Giovanni Xxiii",
    "iso:country":"IT",
    "sg:address":"11, Via Papa Giovanni Xxiii 24040 Comun Nuovo",
    "sg:city":"Comun Nuovo",
    "sg:classifiers":[
        {
            "category":"Food & Beverages",
            "subcategory":"Groceries & Convenience Stores",
            "type":"Retail Goods"
        }
    ],
    "sg:phone":"+39 39035595004",
    "sg:postcode":"24040",
    "sg:province":"Bergamo",
    "sg:tags":[
        "product",
        "related"
    ],
    "wof:name":"Lorenzi Gianbattista & C. (s.n.c.)",
    "wof:placetype":"venue"
},
  "geometry": {"coordinates":[9.6758480072,45.6600761414],"type":"Point"}
}