{
  "type": "Feature",
  "properties": {
    "iso:country":"IT",
    "sg:address":"29010 Alseno",
    "sg:city":"Alseno",
    "sg:orig_category":"Fuoristrada Ed Accessori",
    "sg:phone":"+39 0523 945788",
    "sg:postcode":"29010",
    "sg:province":"Piacenza",
    "wof:name":"Aylmer Motors Italiana Srl",
    "wof:placetype":"venue"
},
  "geometry": {"coordinates":[9.9575634003,44.9021186829],"type":"Point"}
}