{
  "type": "Feature",
  "properties": {
    "iso:country":"IT",
    "sg:address":"20052 Monza",
    "sg:city":"Monza",
    "sg:orig_category":"Metalli E Leghe",
    "sg:phone":"+39 039 232 8220",
    "sg:postcode":"20052",
    "sg:province":"Milano",
    "wof:name":"Impex Metals Trading Co. Srl",
    "wof:placetype":"venue"
},
  "geometry": {"coordinates":[9.1104431152,45.4474868774],"type":"Point"}
}