{
  "type": "Feature",
  "properties": {
    "addr:full":"80053 Castellammare Di Stabia Castellammare di Stabia Napoli 80053",
    "addr:postcode":"80053;80053",
    "iso:country":"IT",
    "sg:address":"80053 Castellammare Di Stabia",
    "sg:city":"Castellammare di Stabia",
    "sg:orig_category":"Cosmetici, Prodotti Di Bellezza E Di Igiene",
    "sg:phone":"+39 081 871 8932",
    "sg:postcode":"80053",
    "sg:province":"Napoli",
    "wof:name":"Farmacia S. Carlo Della Dott.ssa Milena Gallerani",
    "wof:placetype":"venue"
},
  "geometry": {"coordinates":[14.494008,40.704746],"type":"Point"}
}