{
  "type": "Feature",
  "properties": {
    "iso:country":"IT",
    "sg:address":"23032 Bormio",
    "sg:city":"Bormio",
    "sg:orig_category":"Pubblica Amministrazione",
    "sg:phone":"+39 0342 905151",
    "sg:postcode":"23032",
    "sg:province":"Sondrio",
    "wof:name":"Corpo Forestale Dello Stato Coordinamento Territoriale Di Bormio",
    "wof:placetype":"venue"
},
  "geometry": {"coordinates":[10.369137764,46.4719848633],"type":"Point"}
}