{
  "type": "Feature",
  "properties": {
    "iso:country":"IT",
    "sg:address":"30122 Venezia",
    "sg:city":"Castello",
    "sg:orig_category":"Banche E Servizi Finanziari",
    "sg:phone":"+39 041 520 9511",
    "sg:postcode":"30122",
    "sg:province":"Venezia",
    "wof:name":"Maccorp Italiana Spa",
    "wof:placetype":"venue"
},
  "geometry": {"coordinates":[12.346391,45.433842],"type":"Point"}
}