{
  "type": "Feature",
  "properties": {
    "iso:country":"IT",
    "sg:address":"2/a, Vicolo Valle 37122 Verona",
    "sg:city":"Verona",
    "sg:classifiers":[
        {
            "category":"Sports & Exercise",
            "subcategory":"Playing Field",
            "type":"Entertainment"
        }
    ],
    "sg:phone":"+39 39045594069",
    "sg:postcode":"37122",
    "sg:province":"Verona",
    "sg:tags":[
        "game"
    ],
    "wof:name":"Ancora",
    "wof:placetype":"venue"
},
  "geometry": {"coordinates":[10.915382,45.391899],"type":"Point"}
}