{
  "type": "Feature",
  "properties": {
    "iso:country":"IT",
    "sg:address":"Via Emilia Romagna 35020 Saonara",
    "sg:city":"Saonara",
    "sg:classifiers":[
        {
            "category":"Manufacturing",
            "subcategory":"Paper Products",
            "type":"Manufacturing & Wholesale Goods"
        }
    ],
    "sg:phone":"+39 39049640366",
    "sg:postcode":"35020",
    "sg:province":"Padova",
    "sg:tags":[
        "cardboard"
    ],
    "wof:name":"Scatolificio 2 G Di Giantin Giancarlo & C. (s.a.s.)",
    "wof:placetype":"venue"
},
  "geometry": {"coordinates":[11.9630565643,45.3785743713],"type":"Point"}
}