{
  "type": "Feature",
  "properties": {
    "addr:full":"24031 Almenno San Salvatore Almenno San Salvatore Bergamo 24031",
    "addr:postcode":"24031;24031",
    "addr:street":"San Salvatore Bergamo",
    "iso:country":"IT",
    "sg:address":"24031 Almenno San Salvatore",
    "sg:city":"Almenno San Salvatore",
    "sg:orig_category":"Pubblica Amministrazione",
    "sg:phone":"+39 035 640064",
    "sg:postcode":"24031",
    "sg:province":"Bergamo",
    "wof:name":"Carabinieri",
    "wof:placetype":"venue"
},
  "geometry": {"coordinates":[9.599943161,45.7440605164],"type":"Point"}
}