{
  "type": "Feature",
  "properties": {
    "iso:country":"IT",
    "sg:address":"90137 Palermo",
    "sg:city":"Palermo",
    "sg:orig_category":"Pubblica Amministrazione",
    "sg:phone":"+39 091 668 0826",
    "sg:postcode":"90137",
    "sg:province":"Palermo",
    "wof:name":"Guardia Di Finanza/comando Sezione Aerea Boccadifalco",
    "wof:placetype":"venue"
},
  "geometry": {"coordinates":[13.2750053406,38.1090621948],"type":"Point"}
}