{
  "type": "Feature",
  "properties": {
    "iso:country":"IT",
    "sg:address":"29, Via Gravellona 28071 Borgolavezzaro",
    "sg:city":"Borgolavezzaro",
    "sg:classifiers":[
        {
            "category":"Wholesale",
            "subcategory":"Drugs",
            "type":"Manufacturing & Wholesale Goods"
        }
    ],
    "sg:phone":"+39 0321 885116",
    "sg:postcode":"28071",
    "sg:province":"Novara",
    "sg:tags":[
        "chemical",
        "pharmaceutical"
    ],
    "wof:name":"Borgal (s.r.l.)",
    "wof:placetype":"venue"
},
  "geometry": {"coordinates":[8.704572,45.32114],"type":"Point"}
}