{
  "type": "Feature",
  "properties": {
    "iso:country":"IT",
    "sg:address":"89123 Reggio Calabria",
    "sg:orig_category":"Servizi E Lavori Per Ecologia E Smaltimento Rifiuti. Acqua, Luce, Gas E Societa' Di Esercizio Pubblico",
    "sg:phone":"+39 0965 200271",
    "sg:province":"RC",
    "wof:name":"Multari Giuseppe",
    "wof:placetype":"venue"
},
  "geometry": {"coordinates":[15.654449,38.117607],"type":"Point"}
}