{
  "type": "Feature",
  "properties": {
    "addr:full":"20040 Bellusco Bellusco Milano 20040",
    "addr:postcode":"20040;20040",
    "iso:country":"IT",
    "sg:address":"20040 Bellusco",
    "sg:city":"Bellusco",
    "sg:orig_category":"Cucine Componibili",
    "sg:phone":"+39 039 602 0217",
    "sg:postcode":"20040",
    "sg:province":"Milano",
    "wof:name":"C.d.e. Centro Dell'elettrodomestico",
    "wof:placetype":"venue"
},
  "geometry": {"coordinates":[9.47944,45.579384],"type":"Point"}
}