{
  "type": "Feature",
  "properties": {
    "iso:country":"IT",
    "sg:address":"Via Della Provvidenza 13 35030 Rubano",
    "sg:city":"Rubano",
    "sg:classifiers":[
        {
            "category":"Building & Trades",
            "subcategory":"Electrical",
            "type":"Services"
        }
    ],
    "sg:phone":"+39 049 631699",
    "sg:postcode":"35030",
    "sg:province":"Padova",
    "sg:tags":[
        "communication",
        "computers",
        "equipment",
        "terminals",
        "computer",
        "data"
    ],
    "sg:website":"www.schirato.it",
    "wof:name":"Schirato Srl",
    "wof:placetype":"venue"
},
  "geometry": {"coordinates":[11.821797,45.419216],"type":"Point"}
}