{
  "type": "Feature",
  "properties": {
    "iso:country":"IT",
    "sg:address":"22070 Grandate",
    "sg:city":"Grandate",
    "sg:orig_category":"Macchine, Impianti Ed Attrezzature Per Abbigliamento E Pelletterie",
    "sg:phone":"+39 031 565491",
    "sg:postcode":"22070",
    "sg:province":"Como",
    "wof:name":"Texma Srl",
    "wof:placetype":"venue"
},
  "geometry": {"coordinates":[9.062348,45.773746],"type":"Point"}
}