{
  "type": "Feature",
  "properties": {
    "iso:country":"IT",
    "sg:address":"70126 Bari",
    "sg:city":"Bari",
    "sg:orig_category":"Articoli Da Regalo. Arte Ed Artigianato Artistico. Shopping",
    "sg:phone":"+39 080 548 4968",
    "sg:postcode":"70126",
    "sg:province":"Bari",
    "wof:name":"Laboratorio Artistico Antares S.r.l.",
    "wof:placetype":"venue"
},
  "geometry": {"coordinates":[16.891739,41.093803],"type":"Point"}
}