{
  "type": "Feature",
  "properties": {
    "iso:country":"IT",
    "sg:address":"Via C. Battisti 49; Sonnino",
    "sg:classifiers":[
        {
            "category":"Banks & Credit Unions",
            "subcategory":"Bank",
            "type":"Services"
        }
    ],
    "sg:phone":"+39 0773 98566",
    "wof:name":"Banca Di Roma",
    "wof:placetype":"venue"
},
  "geometry": {"coordinates":[13.181759,41.470924],"type":"Point"}
}