{
  "type": "Feature",
  "properties": {
    "iso:country":"IT",
    "sg:address":"Galleria Crispi 95; Vicenza; 36100",
    "sg:city":"Vicenza",
    "sg:classifiers":[
        {
            "category":"Banks & Credit Unions",
            "subcategory":"Bank",
            "type":"Services"
        }
    ],
    "sg:phone":"+39 0444 962611",
    "sg:postcode":"36100",
    "sg:province":"Vicenza",
    "wof:name":"K\u00e4rntner Landes- Und, Hypothekenbank Ag",
    "wof:placetype":"venue"
},
  "geometry": {"coordinates":[11.518202,45.545773],"type":"Point"}
}