{
  "type": "Feature",
  "properties": {
    "addr:full":"Via Cocchi Antonio Ospedaletto 56121 Pisa Pisa Pisa 56121",
    "addr:postcode":"56121;56121",
    "addr:street":"Via Cocchi Antonio Ospedaletto",
    "iso:country":"IT",
    "sg:address":"Via Cocchi Antonio Ospedaletto 56121 Pisa",
    "sg:city":"Pisa",
    "sg:classifiers":[
        {
            "category":"Wholesale",
            "subcategory":"Drugs",
            "type":"Manufacturing & Wholesale Goods"
        }
    ],
    "sg:phone":"+39 39050976111",
    "sg:postcode":"56121",
    "sg:province":"Pisa",
    "sg:tags":[
        "chemical",
        "pharmaceutical"
    ],
    "wof:name":"Baxter Spa",
    "wof:placetype":"venue"
},
  "geometry": {"coordinates":[10.396585,43.716137],"type":"Point"}
}