{
  "type": "Feature",
  "properties": {
    "iso:country":"IT",
    "sg:address":"43100 Parma",
    "sg:city":"Parma",
    "sg:orig_category":"Servizi Ausiliari Per Il Trasporto. Servizi Vari Di Interesse Pubblico",
    "sg:phone":"+39 0521 290722",
    "sg:postcode":"43100",
    "sg:province":"Parma",
    "wof:name":"Cof Srl Consorzio Onoranze Funebri Parmense",
    "wof:placetype":"venue"
},
  "geometry": {"coordinates":[10.32296,44.7756],"type":"Point"}
}