{
  "type": "Feature",
  "properties": {
    "addr:full":"20099 Sesto San Giovanni Sesto San Giovanni Milano 20099",
    "addr:postcode":"20099;20099",
    "iso:country":"IT",
    "sg:address":"20099 Sesto San Giovanni",
    "sg:city":"Sesto San Giovanni",
    "sg:orig_category":"Telecomunicazioni E Telefonia, Impianti, Apparecchi E Servizi",
    "sg:phone":"+39 02 2247 8154",
    "sg:postcode":"20099",
    "sg:province":"Milano",
    "sg:website":"http://www.allcomtlc.com",
    "wof:name":"Allcom Di Valentini Ottimo",
    "wof:placetype":"venue"
},
  "geometry": {"coordinates":[9.228028,45.539627],"type":"Point"}
}