{
  "type": "Feature",
  "properties": {
    "iso:country":"IT",
    "sg:address":"15011 Acqui Terme",
    "sg:city":"Acqui Terme",
    "sg:orig_category":"Macchine, Impianti Ed Attrezzature Per Industria Alimentare E Bevande. Apparecchiature E Sistemi Per Imballaggio E Confezionamento",
    "sg:phone":"+39 0144 329053",
    "sg:postcode":"15011",
    "sg:province":"Alessandria",
    "wof:name":"Ghione Corrado",
    "wof:placetype":"venue"
},
  "geometry": {"coordinates":[8.473271,44.676262],"type":"Point"}
}