{
  "type": "Feature",
  "properties": {
    "iso:country":"IT",
    "sg:address":"Viale Kennedy 53/55, 81030 San Marcellino, Ce",
    "sg:city":"San Marcellino",
    "sg:classifiers":[
        {
            "category":"Banks & Credit Unions",
            "subcategory":"Bank",
            "type":"Services"
        }
    ],
    "sg:postcode":"81030",
    "sg:province":"Caserta",
    "wof:name":"Banca Di Credito Cooperativo Di San Marcellino Scrl",
    "wof:placetype":"venue"
},
  "geometry": {"coordinates":[14.211175,40.962631],"type":"Point"}
}