{
  "type": "Feature",
  "properties": {
    "addr:full":"40017 San Giovanni In Persiceto San Giovanni in Persiceto Bologna 40017",
    "addr:housenumber":"40017",
    "addr:postcode":"40017",
    "iso:country":"IT",
    "sg:address":"40017 San Giovanni In Persiceto",
    "sg:city":"San Giovanni in Persiceto",
    "sg:orig_category":"Impiantistica E Prodotti Tecnologici Per Edilizia. Macchine, Strumenti Ed Apparecchi Per Attivita' Industriali",
    "sg:phone":"+39 051 826068",
    "sg:postcode":"40017",
    "sg:province":"Bologna",
    "wof:name":"Massari Leone",
    "wof:placetype":"venue"
},
  "geometry": {"coordinates":[11.186806,44.639835],"type":"Point"}
}