{
  "type": "Feature",
  "properties": {
    "iso:country":"IT",
    "sg:address":"Via Germania 20083 Gaggiano",
    "sg:city":"Gaggiano",
    "sg:classifiers":[
        {
            "category":"Building & Trades",
            "subcategory":"Construction",
            "type":"Services"
        }
    ],
    "sg:phone":"+39 02 9084 1609",
    "sg:postcode":"20083",
    "sg:province":"Milano",
    "sg:tags":[
        "work",
        "public"
    ],
    "wof:name":"Patentverwag Italia S.r.l.",
    "wof:placetype":"venue"
},
  "geometry": {"coordinates":[9.031767,45.38036],"type":"Point"}
}