{
  "type": "Feature",
  "properties": {
    "addr:full":"116, V. Galliani - Loc. Fossatone 40059 Medicina Medicina Bologna 40059",
    "addr:housenumber":"116",
    "addr:postcode":"40059;40059",
    "addr:street":"V. Galliani Loc. Fossatone",
    "iso:country":"IT",
    "sg:address":"116, V. Galliani - Loc. Fossatone 40059 Medicina",
    "sg:city":"Medicina",
    "sg:classifiers":[
        {
            "category":"Manufacturing",
            "subcategory":"Motor Vehicles & Parts",
            "type":"Manufacturing & Wholesale Goods"
        }
    ],
    "sg:phone":"+39 051 696 0911",
    "sg:postcode":"40059",
    "sg:province":"Bologna",
    "sg:tags":[
        "engine"
    ],
    "sg:website":"http://www.paginegialle.it/comex",
    "wof:name":"Comex Spa",
    "wof:placetype":"venue"
},
  "geometry": {"coordinates":[11.346481,44.494221],"type":"Point"}
}