{
  "type": "Feature",
  "properties": {
    "addr:full":"Ctr. Peschiera 11 62010 Montelupone Montelupone Macerata 62010",
    "addr:housenumber":"11",
    "addr:postcode":"62010;62010",
    "iso:country":"IT",
    "sg:address":"Ctr. Peschiera 11 62010 Montelupone",
    "sg:city":"Montelupone",
    "sg:classifiers":[
        {
            "category":"Bars & Pubs",
            "subcategory":"Sports Bar",
            "type":"Food & Drink"
        }
    ],
    "sg:phone":"+39 0733 225005",
    "sg:postcode":"62010",
    "sg:province":"Macerata",
    "sg:tags":[
        "dy",
        "forging"
    ],
    "sg:website":"www.cgf.it",
    "wof:name":"Cgf Di Pranzetti Srl",
    "wof:placetype":"venue"
},
  "geometry": {"coordinates":[13.4562616348,43.3007469177],"type":"Point"}
}