{
  "type": "Feature",
  "properties": {
    "iso:country":"IT",
    "sg:address":"57123 Livorno",
    "sg:city":"Livorno",
    "sg:orig_category":"Informatica - Consulenza E Software",
    "sg:phone":"+39 0586 210919",
    "sg:postcode":"57123",
    "sg:province":"Livorno",
    "sg:website":"http://www.librinformatica.it",
    "wof:name":"Librinformatica Srl",
    "wof:placetype":"venue"
},
  "geometry": {"coordinates":[10.311007,43.550911],"type":"Point"}
}