{
  "type": "Feature",
  "properties": {
    "iso:country":"IT",
    "sg:address":"20056 Grezzago",
    "sg:city":"Grezzago",
    "sg:orig_category":"Agricoltura, Orticoltura E Floricoltura",
    "sg:phone":"+39 02 9096 7221",
    "sg:postcode":"20056",
    "sg:province":"Milano",
    "wof:name":"Mapelli D.c.c Di Mapelli Dante Carmelo Carlo (s.n.c.)",
    "wof:placetype":"venue"
},
  "geometry": {"coordinates":[9.536872,45.597786],"type":"Point"}
}