{
  "type": "Feature",
  "properties": {
    "iso:country":"IT",
    "sg:address":"31010 Pianzano",
    "sg:city":"Pianzano",
    "sg:orig_category":"Accessori Moda D'abbigliamento. Shopping",
    "sg:phone":"+39 0438 38227",
    "sg:postcode":"31010",
    "sg:province":"Treviso",
    "wof:name":"Pizzinato Luigi",
    "wof:placetype":"venue"
},
  "geometry": {"coordinates":[12.234553,45.692444],"type":"Point"}
}