{
  "type": "Feature",
  "properties": {
    "iso:country":"IT",
    "sg:address":"20017 Rho",
    "sg:city":"Rho",
    "sg:orig_category":"Macchine Utensili E Impianti",
    "sg:phone":"+39 02 930 9617",
    "sg:postcode":"20017",
    "sg:province":"Milano",
    "wof:name":"Mario Lupi Snc",
    "wof:placetype":"venue"
},
  "geometry": {"coordinates":[9.05262,45.525738],"type":"Point"}
}