{
  "type": "Feature",
  "properties": {
    "addr:full":"25060 Cellatica Cellatica Brescia 25060",
    "addr:postcode":"25060;25060",
    "iso:country":"IT",
    "sg:address":"25060 Cellatica",
    "sg:city":"Cellatica",
    "sg:orig_category":"Utensili Meccanici E Materiali",
    "sg:phone":"+39 030 252 3693",
    "sg:postcode":"25060",
    "sg:province":"Brescia",
    "wof:name":"S.t.s. Sist. Per Il Trat. Super. Di Andreoli M. E Calabro' S",
    "wof:placetype":"venue"
},
  "geometry": {"coordinates":[10.163032,45.583439],"type":"Point"}
}