{
  "type": "Feature",
  "properties": {
    "addr:full":"98051 Barcellona Gotto Messina 98051",
    "addr:postcode":"98051;98051",
    "iso:country":"IT",
    "sg:address":"98051 Barcellona Gotto",
    "sg:orig_category":"Bagno - Accessori E Mobili",
    "sg:phone":"+39 090 976 3146",
    "sg:postcode":"98051",
    "sg:province":"Messina",
    "wof:name":"Ceramiche Fratelli Di Pasquale Srl",
    "wof:placetype":"venue"
},
  "geometry": {"coordinates":[15.231183,38.124077],"type":"Point"}
}