{
  "type": "Feature",
  "properties": {
    "iso:country":"IT",
    "sg:address":"04024 Gaeta",
    "sg:city":"Gaeta",
    "sg:orig_category":"Ristoranti",
    "sg:phone":"+39 0771 743071",
    "sg:postcode":"04024",
    "sg:province":"Latina",
    "wof:name":"Ristorante S. Agostino Di Valente G.p.p. & C. Snc",
    "wof:placetype":"venue"
},
  "geometry": {"coordinates":[13.555261,41.244724],"type":"Point"}
}