{
  "type": "Feature",
  "properties": {
    "iso:country":"IT",
    "sg:address":"12035 Racconigi",
    "sg:city":"Racconigi",
    "sg:orig_category":"Perizie, Stime E Valutazioni - Consulenza",
    "sg:phone":"+39 0172 84187",
    "sg:postcode":"12035",
    "sg:province":"Cuneo",
    "wof:name":"Studio Tecnico Annibale Enrico",
    "wof:placetype":"venue"
},
  "geometry": {"coordinates":[7.6730651855,44.7703208923],"type":"Point"}
}