{
  "type": "Feature",
  "properties": {
    "addr:full":"Via Battisti 86 25073 Bovezzo Bovezzo Brescia 25073",
    "addr:housenumber":"86",
    "addr:postcode":"25073;25073",
    "addr:street":"Via Battisti",
    "iso:country":"IT",
    "sg:address":"Via Battisti 86 25073 Bovezzo",
    "sg:city":"Bovezzo",
    "sg:orig_category":"Cutter Heads",
    "sg:phone":"+39 030 271 1109",
    "sg:postcode":"25073",
    "sg:province":"Brescia",
    "sg:website":"www.cm-srl.it",
    "wof:name":"C.m. Srl",
    "wof:placetype":"venue"
},
  "geometry": {"coordinates":[10.237679,45.594238],"type":"Point"}
}