{
  "type": "Feature",
  "properties": {
    "iso:country":"IT",
    "sg:address":"16/18, Via Boscone 22077 Olgiate Comasco",
    "sg:city":"Olgiate Comasco",
    "sg:classifiers":[
        {
            "category":"Shopping",
            "subcategory":"Crafts & Fabrics",
            "type":"Retail Goods"
        }
    ],
    "sg:phone":"+39 39031986486",
    "sg:postcode":"22077",
    "sg:province":"Como",
    "wof:name":"Fontetessile S.r.l.",
    "wof:placetype":"venue"
},
  "geometry": {"coordinates":[8.9827041626,45.8017539978],"type":"Point"}
}