{
  "type": "Feature",
  "properties": {
    "iso:country":"IT",
    "sg:address":"20155 Milano",
    "sg:city":"Milano",
    "sg:orig_category":"Macchine, Impianti Ed Attrezzature Per Abbigliamento E Pelletterie",
    "sg:phone":"+39 02 3360 8119",
    "sg:postcode":"20155",
    "sg:province":"Milano",
    "wof:name":"Mazzola Enrico Dei F.lli Mazzola & C. (s.n.c.)",
    "wof:placetype":"venue"
},
  "geometry": {"coordinates":[9.162745,45.494614],"type":"Point"}
}