{
  "type": "Feature",
  "properties": {
    "addr:full":"27, Via Guido Rossa 53017 Radda In Chianti Radda in Chianti Siena 53017",
    "addr:postcode":"53017;53017",
    "addr:street":"Via Guido Rossa",
    "iso:country":"IT",
    "sg:address":"27, Via Guido Rossa 53017 Radda In Chianti",
    "sg:city":"Radda in Chianti",
    "sg:classifiers":[
        {
            "category":"Food & Beverages",
            "subcategory":"Bakery",
            "type":"Retail Goods"
        }
    ],
    "sg:phone":"+39 0577 735604",
    "sg:postcode":"53017",
    "sg:province":"Siena",
    "sg:tags":[
        "grain",
        "cereal"
    ],
    "wof:name":"Kimline S.r.l.",
    "wof:placetype":"venue"
},
  "geometry": {"coordinates":[11.393611,43.491581],"type":"Point"}
}