{
  "type": "Feature",
  "properties": {
    "iso:country":"IT",
    "sg:address":"170, Strada Padana Verso Padova 36100 Vicenza",
    "sg:city":"Vicenza",
    "sg:classifiers":[
        {
            "category":"Wholesale",
            "subcategory":"Machinery & Supplies",
            "type":"Manufacturing & Wholesale Goods"
        }
    ],
    "sg:phone":"+39 0444 239233",
    "sg:postcode":"36100",
    "sg:province":"Vicenza",
    "sg:tags":[
        "equipment",
        "-",
        "instrument",
        "measurement"
    ],
    "wof:name":"Arredamenti G.n. (s.r.l.)",
    "wof:placetype":"venue"
},
  "geometry": {"coordinates":[11.526389,45.575279],"type":"Point"}
}