{
  "type": "Feature",
  "properties": {
    "iso:country":"IT",
    "sg:address":"6, Via Delle Prese 36014 Santorso",
    "sg:city":"Santorso",
    "sg:classifiers":[
        {
            "category":"Professional",
            "subcategory":"Engineering",
            "type":"Services"
        }
    ],
    "sg:phone":"+39 0445 640156",
    "sg:postcode":"36014",
    "sg:province":"Vicenza",
    "sg:tags":[
        "machine",
        "-",
        "mechanical"
    ],
    "wof:name":"Arcoprofil S.r.l.",
    "wof:placetype":"venue"
},
  "geometry": {"coordinates":[11.390285,45.723289],"type":"Point"}
}