{
  "type": "Feature",
  "properties": {
    "addr:full":"Strada Statale 593 13040 Alice Castello Alice Castello Vercelli 13040",
    "addr:postcode":"13040;13040",
    "addr:street":"Strada Statale 593",
    "iso:country":"IT",
    "sg:address":"Strada Statale 593 13040 Alice Castello",
    "sg:city":"Alice Castello",
    "sg:classifiers":[
        {
            "category":"Autos & Motor Vehicles",
            "subcategory":"Automobile Sales",
            "type":"Retail Goods"
        }
    ],
    "sg:phone":"+39 0161 909157",
    "sg:postcode":"13040",
    "sg:province":"Vercelli",
    "sg:tags":[
        "motor-cars"
    ],
    "wof:name":"C.d.a. S.p.a.",
    "wof:placetype":"venue"
},
  "geometry": {"coordinates":[8.0734958649,45.361366272],"type":"Point"}
}