{
  "type": "Feature",
  "properties": {
    "addr:full":"58, Strada Di Salt 33047 Remanzacco Remanzacco Udine 33047",
    "addr:postcode":"33047;33047",
    "addr:street":"Strada Di Salt",
    "iso:country":"IT",
    "sg:address":"58, Strada Di Salt 33047 Remanzacco",
    "sg:city":"Remanzacco",
    "sg:classifiers":[
        {
            "category":"Manufacturing",
            "subcategory":"Rubber & Plastics",
            "type":"Manufacturing & Wholesale Goods"
        }
    ],
    "sg:phone":"+39 0432 668762",
    "sg:postcode":"33047",
    "sg:province":"Udine",
    "wof:name":"Replast Corrugati Srl",
    "wof:placetype":"venue"
},
  "geometry": {"coordinates":[13.2948160172,46.0842132568],"type":"Point"}
}