{
  "type": "Feature",
  "properties": {
    "iso:country":"IT",
    "sg:address":"00199 Roma",
    "sg:city":"Roma",
    "sg:orig_category":"Servizi E Lavori Per Abbigliamento E Pelletterie",
    "sg:phone":"+39 06 8620 8618",
    "sg:postcode":"00199",
    "sg:province":"Roma",
    "wof:name":"Rigoni Vera",
    "wof:placetype":"venue"
},
  "geometry": {"coordinates":[12.521735,41.931194],"type":"Point"}
}