{
  "type": "Feature",
  "properties": {
    "addr:full":"63012 Cupra Marittima Cupra Marittima Ascoli Piceno 63012",
    "addr:postcode":"63012;63012",
    "iso:country":"IT",
    "sg:address":"63012 Cupra Marittima",
    "sg:city":"Cupra Marittima",
    "sg:orig_category":"Forniture Per Edilizia E Lavori Pubblici",
    "sg:phone":"+39 0735 777933",
    "sg:postcode":"63012",
    "sg:province":"Ascoli Piceno",
    "wof:name":"Edilcupra Di Lanciotti Leandro",
    "wof:placetype":"venue"
},
  "geometry": {"coordinates":[13.8390159607,43.0199165344],"type":"Point"}
}