{
  "type": "Feature",
  "properties": {
    "addr:full":"Via S. Pertini, 27/29 - Z.i. A 62012 Civitanova Marche Civitanova Marche Macerata 62012",
    "addr:housenumber":"27 / 29",
    "addr:postcode":"62012;62012",
    "addr:street":"Via S. Pertini;Z.I. A",
    "iso:country":"IT",
    "sg:address":"Via S. Pertini, 27/29 - Z.i. A 62012 Civitanova Marche",
    "sg:city":"Civitanova Marche",
    "sg:classifiers":[
        {
            "category":"Autos & Motor Vehicles",
            "subcategory":"Fuel & Gas Station",
            "type":"Retail Goods"
        }
    ],
    "sg:phone":"+39 0733 898194",
    "sg:postcode":"62012",
    "sg:province":"Macerata",
    "sg:tags":[
        "steel",
        "gray",
        "installation",
        "foundry",
        "cast",
        "iron",
        "casting"
    ],
    "sg:website":"www.paginegialle.it/fondvalch-01",
    "wof:name":"Fonderie Valchienti Srl",
    "wof:placetype":"venue"
},
  "geometry": {"coordinates":[13.4562616348,43.3007469177],"type":"Point"}
}