{
  "type": "Feature",
  "properties": {
    "iso:country":"IT",
    "sg:address":"38061 Chizzola",
    "sg:city":"Chizzola",
    "sg:orig_category":"Prodotti Chimici Di Base",
    "sg:phone":"+39 0464 696005",
    "sg:postcode":"38061",
    "sg:province":"Trento",
    "wof:name":"Cipriani F.lli Distillerie (s.p.a.)",
    "wof:placetype":"venue"
},
  "geometry": {"coordinates":[11.0203113556,45.7870597839],"type":"Point"}
}