{
  "type": "Feature",
  "properties": {
    "addr:full":"00121 Lido Di Ostia Roma 00121",
    "addr:postcode":"00121;00121",
    "addr:street":"Di Ostia Roma",
    "iso:country":"IT",
    "sg:address":"00121 Lido Di Ostia",
    "sg:orig_category":"Chiese Ed Associazioni Religiose",
    "sg:phone":"+39 06 569 2868",
    "sg:postcode":"00121",
    "sg:province":"Roma",
    "wof:name":"Chiesa Cristiana Evangelica",
    "wof:placetype":"venue"
},
  "geometry": {"coordinates":[12.267702,41.738468],"type":"Point"}
}