{
  "type": "Feature",
  "properties": {
    "iso:country":"IT",
    "sg:address":"Via Croce Rossa Italiana 12 20054 Nova Milanese",
    "sg:city":"Nova Milanese",
    "sg:classifiers":[
        {
            "category":"Wholesale",
            "subcategory":"Construction Materials",
            "type":"Manufacturing & Wholesale Goods"
        }
    ],
    "sg:phone":"+39 036 236 5068",
    "sg:postcode":"20054",
    "sg:province":"Milano",
    "sg:tags":[
        "pipe",
        "resisting",
        "bends",
        "wear"
    ],
    "sg:website":"www.vimoter.it/eurotubi/index.htm",
    "wof:name":"Eurotubi Europa S.r.l.",
    "wof:placetype":"venue"
},
  "geometry": {"coordinates":[9.1881408691,45.4636878967],"type":"Point"}
}