{
  "type": "Feature",
  "properties": {
    "iso:country":"IT",
    "sg:address":"31044 Montebelluna",
    "sg:city":"Montebelluna",
    "sg:orig_category":"Trasporti E Spedizioni Merci",
    "sg:phone":"+39 0423 601444",
    "sg:postcode":"31044",
    "sg:province":"Treviso",
    "wof:name":"Marca Service Srl",
    "wof:placetype":"venue"
},
  "geometry": {"coordinates":[12.117026,45.743374],"type":"Point"}
}