{
  "type": "Feature",
  "properties": {
    "iso:country":"IT",
    "sg:address":"10098 Rivoli",
    "sg:city":"Cascine vica",
    "sg:orig_category":"Forniture Alle Strutture Ricettive. Macchine E Impianti Per Attivita' Commerciali Ed Artigianali",
    "sg:phone":"+39 011 959 4666",
    "sg:postcode":"10098",
    "sg:province":"Torino",
    "sg:website":"http://www.gda-srl.it",
    "wof:name":"G.d.a. Srl",
    "wof:placetype":"venue"
},
  "geometry": {"coordinates":[7.5500831604,45.0632324219],"type":"Point"}
}