{
  "type": "Feature",
  "properties": {
    "iso:country":"IT",
    "sg:address":"24039 Sotto Il Monte Giovanni Xxiii",
    "sg:city":"Sotto il Monte Giovanni XXIII",
    "sg:orig_category":"Servizi Vari Di Interesse Pubblico",
    "sg:phone":"+39 035 790861",
    "sg:postcode":"24039",
    "sg:province":"Bergamo",
    "wof:name":"Zonca Giuliano Diego",
    "wof:placetype":"venue"
},
  "geometry": {"coordinates":[9.504308,45.703522],"type":"Point"}
}