{
  "type": "Feature",
  "properties": {
    "addr:full":"20068 Peschiera Borromeo Peschiera Borromeo Milano 20068",
    "addr:postcode":"20068;20068",
    "iso:country":"IT",
    "sg:address":"20068 Peschiera Borromeo",
    "sg:city":"Peschiera Borromeo",
    "sg:orig_category":"Macchine Ed Impianti Per Edilizia E Lavori Pubblici",
    "sg:phone":"+39 02 547471",
    "sg:postcode":"20068",
    "sg:province":"Milano",
    "wof:name":"Tamrock Italiana Spa",
    "wof:placetype":"venue"
},
  "geometry": {"coordinates":[9.289344,45.433365],"type":"Point"}
}