{
  "type": "Feature",
  "properties": {
    "addr:full":"28010 Pella Alzo Novara 28010",
    "addr:postcode":"28010;28010",
    "iso:country":"IT",
    "sg:address":"28010 Pella",
    "sg:city":"Alzo",
    "sg:classifiers":[
        {
            "category":"Home & Garden",
            "subcategory":"Home Furnishings",
            "type":"Retail Goods"
        }
    ],
    "sg:phone":"+39 0322 969241",
    "sg:postcode":"28010",
    "sg:province":"Novara",
    "sg:tags":[
        "bathroom",
        "accessories"
    ],
    "wof:name":"Gattoni Rubinetteria Spa",
    "wof:placetype":"venue"
},
  "geometry": {"coordinates":[8.3786916733,45.7952651978],"type":"Point"}
}