{
  "type": "Feature",
  "properties": {
    "iso:country":"IT",
    "sg:address":"10154 Torino",
    "sg:city":"Torino",
    "sg:orig_category":"Servizi E Lavori Per Edilizia E Lavori Pubblici. Acqua, Luce, Gas E Societa' Di Esercizio Pubblico",
    "sg:phone":"+39 011 246 8111",
    "sg:postcode":"10154",
    "sg:province":"Torino",
    "wof:name":"Grtn - Centro Di Ripartizione",
    "wof:placetype":"venue"
},
  "geometry": {"coordinates":[7.709631,45.090912],"type":"Point"}
}