{
  "type": "Feature",
  "properties": {
    "iso:country":"IT",
    "sg:address":"50144 Firenze",
    "sg:city":"Firenze",
    "sg:orig_category":"Motori Ed Organi Di Trasmissione. Ricambi E Componenti Dei Mezzi Di Trasporto",
    "sg:phone":"+39 055 351931",
    "sg:postcode":"50144",
    "sg:province":"Firenze",
    "wof:name":"Panerai Motori (s.r.l.)",
    "wof:placetype":"venue"
},
  "geometry": {"coordinates":[11.2301931381,43.7888526917],"type":"Point"}
}