{
  "type": "Feature",
  "properties": {
    "addr:full":"Via Magnadola 56 31045 Motta Di Livenza Motta di Livenza Treviso 31045",
    "addr:housenumber":"56",
    "addr:postcode":"31045;31045",
    "addr:street":"Via Magnadola",
    "iso:country":"IT",
    "sg:address":"Via Magnadola 56 31045 Motta Di Livenza",
    "sg:city":"Motta di Livenza",
    "sg:classifiers":[
        {
            "category":"Manufacturing",
            "subcategory":"Rubber & Plastics",
            "type":"Manufacturing & Wholesale Goods"
        }
    ],
    "sg:phone":"+39 0422 768529",
    "sg:postcode":"31045",
    "sg:province":"Treviso",
    "sg:tags":[
        "appliance",
        "sub-assembly",
        "domestic"
    ],
    "sg:website":"www.satt.biz",
    "wof:name":"Satt Srl",
    "wof:placetype":"venue"
},
  "geometry": {"coordinates":[12.6137924194,45.75],"type":"Point"}
}