{
  "type": "Feature",
  "properties": {
    "addr:full":"38100 Trento Trento Trento 38100",
    "addr:postcode":"38100;38100",
    "iso:country":"IT",
    "sg:address":"38100 Trento",
    "sg:city":"Trento",
    "sg:orig_category":"Frutta E Verdura - Ingrosso",
    "sg:phone":"+39 0461 961859",
    "sg:postcode":"38100",
    "sg:province":"Trento",
    "wof:name":"Safin Srl",
    "wof:placetype":"venue"
},
  "geometry": {"coordinates":[11.1011447906,46.0721130371],"type":"Point"}
}