{
  "type": "Feature",
  "properties": {
    "iso:country":"IT",
    "sg:address":"56010 Pisa",
    "sg:orig_category":"Servizi Per Lo Sport E Il Tempo Libero. Servizi Ausiliari Dei Mezzi Di Trasporto",
    "sg:phone":"+39 050 988564",
    "sg:postcode":"56010",
    "sg:province":"Pisa",
    "wof:name":"Navicelli Boat Service Di Gianetti Fabrizio",
    "wof:placetype":"venue"
},
  "geometry": {"coordinates":[10.358276,43.681919],"type":"Point"}
}