{
  "type": "Feature",
  "properties": {
    "iso:country":"IT",
    "sg:address":"246, Via Vittorio Veneto 19124 La Spezia",
    "sg:classifiers":[
        {
            "category":"Building & Trades",
            "subcategory":"Construction",
            "type":"Services"
        }
    ],
    "sg:phone":"+39 0187 503361",
    "sg:province":"SP",
    "sg:tags":[
        "work",
        "public"
    ],
    "wof:name":"Ghironi Srl Impresa Edile Stradale",
    "wof:placetype":"venue"
},
  "geometry": {"coordinates":[9.835562,44.114155],"type":"Point"}
}