{
  "type": "Feature",
  "properties": {
    "iso:country":"IT",
    "sg:address":"25080 Nuvolento",
    "sg:city":"Nuvolento",
    "sg:orig_category":"Bevande, Vini E Liquori",
    "sg:phone":"+39 030 689 8193",
    "sg:postcode":"25080",
    "sg:province":"Brescia",
    "wof:name":"Fonte Sole (s.r.l.)",
    "wof:placetype":"venue"
},
  "geometry": {"coordinates":[10.387815,45.546722],"type":"Point"}
}