{
  "type": "Feature",
  "properties": {
    "addr:full":"Localita' Valle 38052 Caldonazzo Caldonazzo Trento 38052",
    "addr:postcode":"38052;38052",
    "addr:street":"Localita ' Valle",
    "iso:country":"IT",
    "sg:address":"Localita' Valle 38052 Caldonazzo",
    "sg:city":"Caldonazzo",
    "sg:classifiers":[
        {
            "category":"Banks & Credit Unions",
            "subcategory":"Investment Brokerage",
            "type":"Services"
        }
    ],
    "sg:phone":"+39 0461 723458",
    "sg:postcode":"38052",
    "sg:province":"Trento",
    "sg:tags":[
        "cap",
        "protective",
        "aerosol",
        "valve"
    ],
    "wof:name":"Costerplast Spa",
    "wof:placetype":"venue"
},
  "geometry": {"coordinates":[11.2635383606,45.9971542358],"type":"Point"}
}