{
  "type": "Feature",
  "properties": {
    "iso:country":"IT",
    "sg:address":"81040 Curti",
    "sg:city":"Curti",
    "sg:orig_category":"Servizi E Lavori Per Agricoltura E Zootecnia. Imprese Di Costruzioni Civili Ed Industriali",
    "sg:phone":"+39 0823 841945",
    "sg:postcode":"81040",
    "sg:province":"Caserta",
    "wof:name":"Rauccio Trivellazioni Di Rauccio Francesco",
    "wof:placetype":"venue"
},
  "geometry": {"coordinates":[14.280605,41.07325],"type":"Point"}
}