{
  "type": "Feature",
  "properties": {
    "addr:full":"1, Via Milano 24040 Bonate Sopra Bonate Sopra Bergamo 24040",
    "addr:postcode":"24040;24040",
    "addr:street":"Via Milano;Sopra",
    "iso:country":"IT",
    "sg:address":"1, Via Milano 24040 Bonate Sopra",
    "sg:city":"Bonate Sopra",
    "sg:classifiers":[
        {
            "category":"Shopping",
            "subcategory":"Clothing, Apparel, & Fashions",
            "type":"Retail Goods"
        }
    ],
    "sg:phone":"+39 39035995490",
    "sg:postcode":"24040",
    "sg:province":"Bergamo",
    "sg:tags":[
        "clothes"
    ],
    "wof:name":"Emmeci Srl",
    "wof:placetype":"venue"
},
  "geometry": {"coordinates":[9.578451,45.695816],"type":"Point"}
}