{
  "type": "Feature",
  "properties": {
    "iso:country":"IT",
    "sg:address":"13, Via San Giacomo 39055 Laives",
    "sg:city":"Laives",
    "sg:classifiers":[
        {
            "category":"Manufacturing",
            "subcategory":"Tools & Machinery",
            "type":"Manufacturing & Wholesale Goods"
        }
    ],
    "sg:phone":"+39 0471 250006",
    "sg:postcode":"39055",
    "sg:province":"Bolzano/Bozen",
    "sg:tags":[
        "environment",
        "equipment",
        "-"
    ],
    "wof:name":"S.a.i.r.e. S.r.l.",
    "wof:placetype":"venue"
},
  "geometry": {"coordinates":[11.33431,46.462822],"type":"Point"}
}