{
  "type": "Feature",
  "properties": {
    "addr:full":"183, Via Alle Fabbriche 10072 Caselle Torinese Caselle Torinese Torino 10072",
    "addr:housenumber":"183",
    "addr:postcode":"10072;10072",
    "addr:street":"Via Alle Fabbriche",
    "iso:country":"IT",
    "sg:address":"183, Via Alle Fabbriche 10072 Caselle Torinese",
    "sg:city":"Caselle Torinese",
    "sg:classifiers":[
        {
            "category":"Shopping",
            "subcategory":"Crafts & Fabrics",
            "type":"Retail Goods"
        }
    ],
    "sg:phone":"+39 011 996 1877",
    "sg:postcode":"10072",
    "sg:province":"Torino",
    "wof:name":"Tessitura Mabiel (s.r.l.)",
    "wof:placetype":"venue"
},
  "geometry": {"coordinates":[7.6444129944,45.1658477783],"type":"Point"}
}