{
  "type": "Feature",
  "properties": {
    "addr:full":"2, Via Tevere 95027 San Gregorio Di Catania San Gregorio di Catania Catania 95027",
    "addr:postcode":"95027;95027",
    "addr:street":"Via Tevere",
    "iso:country":"IT",
    "sg:address":"2, Via Tevere 95027 San Gregorio Di Catania",
    "sg:city":"San Gregorio di Catania",
    "sg:classifiers":[
        {
            "category":"Utilities",
            "subcategory":"Electric",
            "type":"Services"
        }
    ],
    "sg:phone":"+39 095 717 9100",
    "sg:postcode":"95027",
    "sg:province":"Catania",
    "sg:tags":[
        "energy"
    ],
    "wof:name":"Smedigas S.p.a.",
    "wof:placetype":"venue"
},
  "geometry": {"coordinates":[15.116455,37.551239],"type":"Point"}
}