{
  "type": "Feature",
  "properties": {
    "iso:country":"IT",
    "sg:address":"20131 Milano",
    "sg:city":"Milano",
    "sg:orig_category":"Materiali E Componenti Elettrotecnici",
    "sg:phone":"+39 02 236 5497",
    "sg:postcode":"20131",
    "sg:province":"Milano",
    "wof:name":"Spernazzati",
    "wof:placetype":"venue"
},
  "geometry": {"coordinates":[9.231159,45.484192],"type":"Point"}
}