{
  "type": "Feature",
  "properties": {
    "iso:country":"IT",
    "sg:address":"80012 Calvizzano",
    "sg:city":"Calvizzano",
    "sg:orig_category":"Zootecnia E Pesca, Allevamento Piccoli Animali. Animali Domestici",
    "sg:phone":"+39 081 712 3274",
    "sg:postcode":"80012",
    "sg:province":"Napoli",
    "wof:name":"Dentice Amalia",
    "wof:placetype":"venue"
},
  "geometry": {"coordinates":[14.19174,40.906151],"type":"Point"}
}