{
  "type": "Feature",
  "properties": {
    "addr:full":"20030 Senago Senago Milano 20030",
    "addr:postcode":"20030;20030",
    "iso:country":"IT",
    "sg:address":"20030 Senago",
    "sg:city":"Senago",
    "sg:orig_category":"Forniture Per Abbigliamento E Pelletterie",
    "sg:phone":"+39 02 9905 6096",
    "sg:postcode":"20030",
    "sg:province":"Milano",
    "wof:name":"A.m. Sas Di Savoldelli D. & C",
    "wof:placetype":"venue"
},
  "geometry": {"coordinates":[9.1043367386,45.5475578308],"type":"Point"}
}