{
  "type": "Feature",
  "properties": {
    "iso:country":"IT",
    "sg:address":"65020 Salle Nuova",
    "sg:city":"Salle",
    "sg:orig_category":"Prodotti Di Base E Forniture Per Industria Alimentare E Bevande",
    "sg:phone":"+39 085 928111",
    "sg:postcode":"65020",
    "sg:province":"Pescara",
    "wof:name":"Eurocord",
    "wof:placetype":"venue"
},
  "geometry": {"coordinates":[14.2086877823,42.4702758789],"type":"Point"}
}