{
  "type": "Feature",
  "properties": {
    "iso:country":"IT",
    "sg:address":"20020 Barbaiana",
    "sg:city":"Barbaiana",
    "sg:orig_category":"Acciaierie E Fonderie",
    "sg:phone":"+39 02 9325 5016",
    "sg:postcode":"20020",
    "sg:province":"Milano",
    "wof:name":"Albini G. (s.r.l.)",
    "wof:placetype":"venue"
},
  "geometry": {"coordinates":[9.019691,45.545776],"type":"Point"}
}