{
  "type": "Feature",
  "properties": {
    "iso:country":"IT",
    "sg:address":"35132 Padova",
    "sg:city":"Padova",
    "sg:orig_category":"Impiantistica E Prodotti Tecnologici Per Edilizia. Elettrotecnica Professionale E Di Consumo. Telecomunicazioni E Telefonia, Impianti, Apparecchi E Servizi",
    "sg:phone":"+39 049 605122",
    "sg:postcode":"35132",
    "sg:province":"Padova",
    "wof:name":"Bettella Roberto Iem",
    "wof:placetype":"venue"
},
  "geometry": {"coordinates":[11.890794,45.423203],"type":"Point"}
}