{
  "type": "Feature",
  "properties": {
    "iso:country":"IT",
    "sg:address":"67051 Avezzano",
    "sg:orig_category":"Antifurto",
    "sg:phone":"+39 0863 49801",
    "sg:postcode":"67051",
    "sg:province":"L'Aquila",
    "wof:name":"Metropol Istituto Di Sorveglianza Srl",
    "wof:placetype":"venue"
},
  "geometry": {"coordinates":[13.436081,41.997795],"type":"Point"}
}