{
  "type": "Feature",
  "properties": {
    "iso:country":"IT",
    "sg:address":"41053 Maranello",
    "sg:city":"Maranello",
    "sg:orig_category":"Ceramica Uso Tecnico Ed Industriale",
    "sg:phone":"+39 0536 945501",
    "sg:postcode":"41053",
    "sg:province":"Modena",
    "wof:name":"Emil Pack Di Mastio Salvatore",
    "wof:placetype":"venue"
},
  "geometry": {"coordinates":[10.877437,44.531189],"type":"Point"}
}