{
  "type": "Feature",
  "properties": {
    "iso:country":"IT",
    "sg:address":"129, V. Delle Industrie 17012 Albissola Marina",
    "sg:city":"Albissola Marina",
    "sg:classifiers":[
        {
            "category":"Utilities",
            "subcategory":"Electric",
            "type":"Services"
        }
    ],
    "sg:phone":"+39 39019480281",
    "sg:postcode":"17012",
    "sg:province":"Savona",
    "sg:tags":[
        "component",
        "electronic"
    ],
    "sg:website":"http://www.paginegialle.it/cabur-01",
    "wof:name":"Cabur",
    "wof:placetype":"venue"
},
  "geometry": {"coordinates":[8.502886,44.336983],"type":"Point"}
}