{
  "type": "Feature",
  "properties": {
    "addr:full":"51100 Pistoia Pistoia Pistoia 51100",
    "addr:postcode":"51100;51100",
    "iso:country":"IT",
    "sg:address":"51100 Pistoia",
    "sg:city":"Pistoia",
    "sg:orig_category":"Macchine, Impianti Ed Attrezzature Per Industria Alimentare E Bevande",
    "sg:phone":"+39 0573 400281",
    "sg:postcode":"51100",
    "sg:province":"Pistoia",
    "wof:name":"Chessa Giuseppa",
    "wof:placetype":"venue"
},
  "geometry": {"coordinates":[10.899745,43.965134],"type":"Point"}
}