{
  "type": "Feature",
  "properties": {
    "iso:country":"IT",
    "sg:address":"Via Veneto 119; Roma",
    "sg:classifiers":[
        {
            "category":"Banks & Credit Unions",
            "subcategory":"Bank",
            "type":"Services"
        }
    ],
    "sg:phone":"+39 06 4674 2282",
    "wof:name":"Banca Di Roma",
    "wof:placetype":"venue"
},
  "geometry": {"coordinates":[12.490108,41.906307],"type":"Point"}
}