{
  "type": "Feature",
  "properties": {
    "iso:country":"IT",
    "sg:address":"60044 Fabriano",
    "sg:city":"Fabriano",
    "sg:orig_category":"Energia Solare Ed Energie Alternative - Impianti E Componenti",
    "sg:phone":"+39 0732 625722",
    "sg:postcode":"60044",
    "sg:province":"Ancona",
    "sg:website":"http://www.sunnyday.it",
    "wof:name":"Janus Energy",
    "wof:placetype":"venue"
},
  "geometry": {"coordinates":[13.501712,43.569683],"type":"Point"}
}