{
  "type": "Feature",
  "properties": {
    "iso:country":"IT",
    "sg:address":"51039 Quarrata",
    "sg:city":"Quarrata",
    "sg:orig_category":"Articoli Per Imballaggio E Confezionamento",
    "sg:phone":"+39 0573 72023",
    "sg:postcode":"51039",
    "sg:province":"Pistoia",
    "wof:name":"Bartolini Ciano",
    "wof:placetype":"venue"
},
  "geometry": {"coordinates":[11.007518,43.903103],"type":"Point"}
}