{
  "type": "Feature",
  "properties": {
    "addr:full":"20060 Pozzo D'adda Milano 20060",
    "addr:postcode":"20060;20060",
    "iso:country":"IT",
    "sg:address":"20060 Pozzo D'adda",
    "sg:orig_category":"Prodotti Alimentari. Shopping",
    "sg:phone":"+39 02 9096 9503",
    "sg:postcode":"20060",
    "sg:province":"Milano",
    "wof:name":"Coti Zelati Giuseppe",
    "wof:placetype":"venue"
},
  "geometry": {"coordinates":[9.4941606522,45.5595588684],"type":"Point"}
}