{
  "type": "Feature",
  "properties": {
    "addr:full":"20098 San Giuliano Milanese San Giuliano Milanese Milano 20098",
    "addr:housenumber":"20098",
    "addr:postcode":"20098",
    "addr:street":"San",
    "iso:country":"IT",
    "sg:address":"20098 San Giuliano Milanese",
    "sg:city":"San Giuliano Milanese",
    "sg:orig_category":"Arredo Camera Letto E Complementi",
    "sg:phone":"+39 02 984 4658",
    "sg:postcode":"20098",
    "sg:province":"Milano",
    "wof:name":"Angelo Sommariva & Figli Srl",
    "wof:placetype":"venue"
},
  "geometry": {"coordinates":[9.291634,45.397217],"type":"Point"}
}