{
  "type": "Feature",
  "properties": {
    "addr:full":"20144 Milano Milano Milano 20144",
    "addr:postcode":"20144;20144",
    "iso:country":"IT",
    "sg:address":"20144 Milano",
    "sg:city":"Milano",
    "sg:orig_category":"Servizi Per Lo Sport E Il Tempo Libero. Servizi Al Turismo",
    "sg:phone":"+39 02 481 8028",
    "sg:postcode":"20144",
    "sg:province":"Milano",
    "wof:name":"Palestra Sportime Di Simonetta Moro",
    "wof:placetype":"venue"
},
  "geometry": {"coordinates":[9.158999,45.465485],"type":"Point"}
}