{
  "type": "Feature",
  "properties": {
    "iso:country":"IT",
    "sg:address":"84122 Salerno",
    "sg:city":"Salerno",
    "sg:orig_category":"Impiantistica E Prodotti Tecnologici Per Edilizia. Macchine, Strumenti Ed Apparecchi Per Attivita' Industriali",
    "sg:phone":"+39 089 224697",
    "sg:postcode":"84122",
    "sg:province":"Salerno",
    "wof:name":"Caggiano Michele",
    "wof:placetype":"venue"
},
  "geometry": {"coordinates":[14.765949,40.678368],"type":"Point"}
}