{
  "type": "Feature",
  "properties": {
    "iso:country":"IT",
    "sg:address":"00148 Roma",
    "sg:city":"Roma",
    "sg:orig_category":"Termotecnica E Riscaldamento, Apparecchiature E Servizi",
    "sg:phone":"+39 06 655 1040",
    "sg:postcode":"00148",
    "sg:province":"Roma",
    "sg:website":"http://web.tiscali.it/eurotermica",
    "wof:name":"Eurotermica Snc Di Mauro Giorgi",
    "wof:placetype":"venue"
},
  "geometry": {"coordinates":[12.424788,41.85257],"type":"Point"}
}