{
  "type": "Feature",
  "properties": {
    "addr:full":"40069 Zola Predosa Zola Bologna 40069",
    "addr:postcode":"40069;40069",
    "iso:country":"IT",
    "sg:address":"40069 Zola Predosa",
    "sg:city":"Zola",
    "sg:orig_category":"Metalli E Leghe",
    "sg:phone":"+39 051 758719",
    "sg:postcode":"40069",
    "sg:province":"Bologna",
    "wof:name":"Rodacciai Industria Trafilati (s.p.a.)",
    "wof:placetype":"venue"
},
  "geometry": {"coordinates":[11.2536077499,44.4945297241],"type":"Point"}
}