{
  "type": "Feature",
  "properties": {
    "iso:country":"IT",
    "sg:address":"4, Via Palestro 20121 Milano",
    "sg:city":"Milano",
    "sg:classifiers":[
        {
            "category":"Professional",
            "subcategory":"Engineering",
            "type":"Services"
        }
    ],
    "sg:phone":"+39 02 7600 3065",
    "sg:postcode":"20121",
    "sg:province":"Milano",
    "sg:tags":[
        "machine",
        "-",
        "mechanical"
    ],
    "wof:name":"Schlatter Italiana (s.r.l.)",
    "wof:placetype":"venue"
},
  "geometry": {"coordinates":[9.196857,45.472897],"type":"Point"}
}