{
  "type": "Feature",
  "properties": {
    "iso:country":"IT",
    "sg:address":"Via Fiocchetti 14 42045 Luzzara",
    "sg:classifiers":[
        {
            "category":"Manufacturing",
            "subcategory":"Tools & Machinery",
            "type":"Manufacturing & Wholesale Goods"
        }
    ],
    "sg:phone":"+39 0522 976707",
    "sg:postcode":"42045",
    "sg:province":"Reggio Nell'Emilia",
    "sg:tags":[
        "wheel",
        "agricultural"
    ],
    "sg:website":"www.simol.com",
    "wof:name":"Simol Spa",
    "wof:placetype":"venue"
},
  "geometry": {"coordinates":[10.727183,44.975281],"type":"Point"}
}