{
  "type": "Feature",
  "properties": {
    "iso:country":"IT",
    "sg:address":"50067 Rosano",
    "sg:city":"Rosano",
    "sg:orig_category":"Nautica. Forniture Per Attivita' Commerciali Ed Artigianali",
    "sg:phone":"+39 055 830 3156",
    "sg:postcode":"50067",
    "sg:province":"Firenze",
    "wof:name":"Fantechi (s.p.a.)",
    "wof:placetype":"venue"
},
  "geometry": {"coordinates":[11.424389,43.769852],"type":"Point"}
}