{
  "type": "Feature",
  "properties": {
    "iso:country":"IT",
    "sg:address":"20068 Peschiera Borromeo",
    "sg:city":"Peschiera Borromeo",
    "sg:orig_category":"Servizi Editoriali",
    "sg:phone":"+39 02 547 2665",
    "sg:postcode":"20068",
    "sg:province":"Milano",
    "wof:name":"Prezzano Gianfranco",
    "wof:placetype":"venue"
},
  "geometry": {"coordinates":[9.334831,45.470749],"type":"Point"}
}