{
  "type": "Feature",
  "properties": {
    "iso:country":"IT",
    "sg:address":"21010 Besnate",
    "sg:city":"Besnate",
    "sg:orig_category":"Arredamenti - Produzione E Ingrosso",
    "sg:phone":"+39 0331 274066",
    "sg:postcode":"21010",
    "sg:province":"Varese",
    "wof:name":"L.i.l.e.a. Di Bordoni R. & C. Snc",
    "wof:placetype":"venue"
},
  "geometry": {"coordinates":[8.818946,45.81744],"type":"Point"}
}