{
  "type": "Feature",
  "properties": {
    "iso:country":"IT",
    "sg:address":"25010 Visano",
    "sg:city":"Isorella",
    "sg:orig_category":"Trattamenti Termici E Superficiali Metalli, Galvanotecnica",
    "sg:phone":"+39 030 995 2230",
    "sg:postcode":"25010",
    "sg:province":"Brescia",
    "wof:name":"Scalmana Fratelli Di Scalmana Sergio & C. (s.n.c.)",
    "wof:placetype":"venue"
},
  "geometry": {"coordinates":[10.750884,45.797962],"type":"Point"}
}