{
  "type": "Feature",
  "properties": {
    "addr:full":"Sda Antica Di Pinerolo 37 10040 Gerbole Gerbole Torino 10040",
    "addr:housenumber":"37",
    "addr:postcode":"10040;10040",
    "addr:street":"Gerbole",
    "iso:country":"IT",
    "sg:address":"Sda Antica Di Pinerolo 37 10040 Gerbole",
    "sg:city":"Gerbole",
    "sg:classifiers":[
        {
            "category":"Building & Trades",
            "subcategory":"Cleaning & Sanitation",
            "type":"Services"
        }
    ],
    "sg:phone":"+39 011 990 6721",
    "sg:postcode":"10040",
    "sg:province":"Torino",
    "sg:tags":[
        "broom"
    ],
    "sg:website":"www.dea-ulmo.it",
    "wof:name":"Dea Ulmo Srl",
    "wof:placetype":"venue"
},
  "geometry": {"coordinates":[7.686619,45.07056],"type":"Point"}
}