{
  "type": "Feature",
  "properties": {
    "iso:country":"IT",
    "sg:address":"00174 Roma",
    "sg:city":"Roma",
    "sg:classifiers":[
        {
            "category":"Wholesale",
            "subcategory":"Vending Machines",
            "type":"Manufacturing & Wholesale Goods"
        }
    ],
    "sg:phone":"+39 06 761 5436",
    "sg:postcode":"00174",
    "sg:province":"Roma",
    "sg:tags":[
        "automation"
    ],
    "wof:name":"Spal Centro Italia Srl",
    "wof:placetype":"venue"
},
  "geometry": {"coordinates":[12.547577,41.862545],"type":"Point"}
}