{
  "type": "Feature",
  "properties": {
    "addr:full":"1, Contrada S. Giovanni 60010 Ostra Vetere Ostra Ancona 60010",
    "addr:postcode":"60010;60010",
    "addr:street":"Contrada S. Giovanni",
    "iso:country":"IT",
    "sg:address":"1, Contrada S. Giovanni 60010 Ostra Vetere",
    "sg:city":"Ostra",
    "sg:classifiers":[
        {
            "category":"Professional",
            "subcategory":"Printing & Photocopies",
            "type":"Services"
        }
    ],
    "sg:phone":"+39 39071964030",
    "sg:postcode":"60010",
    "sg:province":"Ancona",
    "wof:name":"Tecnostampa S.r.l.",
    "wof:placetype":"venue"
},
  "geometry": {"coordinates":[13.5187568665,43.6158561707],"type":"Point"}
}