{
  "type": "Feature",
  "properties": {
    "iso:country":"IT",
    "sg:address":"Via Tevere 9 22070 Casnate",
    "sg:city":"Casnate",
    "sg:classifiers":[
        {
            "category":"Banks & Credit Unions",
            "subcategory":"Investment Brokerage",
            "type":"Services"
        }
    ],
    "sg:phone":"+39 031 451436",
    "sg:postcode":"22070",
    "sg:province":"Como",
    "sg:tags":[
        "accessory",
        "high-fashion"
    ],
    "wof:name":"Gentili Mosconi Spa",
    "wof:placetype":"venue"
},
  "geometry": {"coordinates":[9.057607,45.763054],"type":"Point"}
}