{
  "type": "Feature",
  "properties": {
    "iso:country":"IT",
    "sg:address":"20143 Milano",
    "sg:city":"Milano",
    "sg:orig_category":"Editoria",
    "sg:phone":"+39 0283398",
    "sg:postcode":"20143",
    "sg:province":"Milano",
    "wof:name":"Secondamano Srl",
    "wof:placetype":"venue"
},
  "geometry": {"coordinates":[9.174175,45.451431],"type":"Point"}
}