{
  "type": "Feature",
  "properties": {
    "addr:full":"40034 Castel D'aiano Bologna 40034",
    "addr:postcode":"40034;40034",
    "addr:street":"Castel;Bologna",
    "iso:country":"IT",
    "sg:address":"40034 Castel D'aiano",
    "sg:orig_category":"Prodotti Chimici Secondari. Tempo Libero - Articoli E Forniture. Servizi Per Lo Sport E Il Tempo Libero. Servizi Per Aziende, Manifestazioni E Supporto Agli Scambi Commerciali",
    "sg:phone":"+39 051 912940",
    "sg:postcode":"40034",
    "sg:province":"Bologna",
    "wof:name":"Pirotecnica Benassi S.n.c.",
    "wof:placetype":"venue"
},
  "geometry": {"coordinates":[11.0549249649,44.287727356],"type":"Point"}
}