{
  "type": "Feature",
  "properties": {
    "iso:country":"IT",
    "sg:address":"25018 Montichiari",
    "sg:city":"Montichiari",
    "sg:orig_category":"Articoli Pulizia. Forniture Per Attivita' Industriali",
    "sg:phone":"+39 030 965 0744",
    "sg:postcode":"25018",
    "sg:province":"Brescia",
    "wof:name":"Nuova Sisal Dei F.lli Rocca Snc",
    "wof:placetype":"venue"
},
  "geometry": {"coordinates":[10.233589,45.536961],"type":"Point"}
}