{
  "type": "Feature",
  "properties": {
    "iso:country":"IT",
    "sg:address":"56028 S. Miniato",
    "sg:classifiers":[
        {
            "category":"Farming",
            "subcategory":"Livestock Farm",
            "type":"Manufacturing & Wholesale Goods"
        }
    ],
    "sg:phone":"+39 0571 42552",
    "sg:postcode":"56028",
    "sg:province":"Pisa",
    "sg:tags":[
        "equipment",
        "breeding",
        "agriculture",
        "machinery",
        "supply"
    ],
    "wof:name":"Giglio Plast",
    "wof:placetype":"venue"
},
  "geometry": {"coordinates":[10.396585,43.716137],"type":"Point"}
}