{
  "type": "Feature",
  "properties": {
    "addr:full":"51100 Pistoia Pistoia Pistoia 51100",
    "addr:postcode":"51100;51100",
    "iso:country":"IT",
    "sg:address":"51100 Pistoia",
    "sg:city":"Pistoia",
    "sg:orig_category":"Banche E Servizi Finanziari",
    "sg:phone":"+39 0573 3691",
    "sg:postcode":"51100",
    "sg:province":"Pistoia",
    "sg:website":"http://www.caript.it",
    "wof:name":"Cassa Di Risparmio Di Pistoia E Pescia Spa",
    "wof:placetype":"venue"
},
  "geometry": {"coordinates":[10.917107,43.932911],"type":"Point"}
}