{
  "type": "Feature",
  "properties": {
    "addr:full":"33170 Pordenone Pordenone Pordenone 33170",
    "addr:postcode":"33170;33170",
    "iso:country":"IT",
    "sg:address":"33170 Pordenone",
    "sg:city":"Pordenone",
    "sg:orig_category":"Assicurazioni",
    "sg:phone":"+39 0434 508411",
    "sg:postcode":"33170",
    "sg:province":"Pordenone",
    "wof:name":"Dal Cin Studio Di Assicurazioni Sas",
    "wof:placetype":"venue"
},
  "geometry": {"coordinates":[12.663079,45.960064],"type":"Point"}
}