{
  "type": "Feature",
  "properties": {
    "iso:country":"IT",
    "sg:address":"00162 Roma",
    "sg:city":"Roma",
    "sg:orig_category":"Filati E Materie Prime Tessili",
    "sg:phone":"+39 06 8632 3467",
    "sg:postcode":"00162",
    "sg:province":"Roma",
    "wof:name":"I Filati Angel's Tricots",
    "wof:placetype":"venue"
},
  "geometry": {"coordinates":[12.5086593628,41.8222007751],"type":"Point"}
}