{
  "type": "Feature",
  "properties": {
    "addr:full":"42025 Cavriago Reggio Nell'Emilia 42025",
    "addr:postcode":"42025;42025",
    "iso:country":"IT",
    "sg:address":"42025 Cavriago",
    "sg:classifiers":[
        {
            "category":"Banks & Credit Unions",
            "subcategory":"Financial Services",
            "type":"Services"
        }
    ],
    "sg:phone":"+39 0522 575781",
    "sg:postcode":"42025",
    "sg:province":"Reggio Nell'Emilia",
    "sg:tags":[
        "articles",
        "product",
        "plastics",
        "industry",
        "work",
        "plastic"
    ],
    "sg:website":"http://www.tecnoplastica.it",
    "wof:name":"Tecnoplastica Srl Di A. & C.",
    "wof:placetype":"venue"
},
  "geometry": {"coordinates":[10.5161237717,44.6970863342],"type":"Point"}
}