{
  "type": "Feature",
  "properties": {
    "addr:full":"24020 Ranica Ranica Bergamo 24020",
    "addr:postcode":"24020;24020",
    "iso:country":"IT",
    "sg:address":"24020 Ranica",
    "sg:city":"Ranica",
    "sg:orig_category":"Agenzie Immobiliari",
    "sg:phone":"+39 035 347060",
    "sg:postcode":"24020",
    "sg:province":"Bergamo",
    "wof:name":"Immobiliare Lara Spa",
    "wof:placetype":"venue"
},
  "geometry": {"coordinates":[9.717016,45.722908],"type":"Point"}
}