{
  "type": "Feature",
  "properties": {
    "iso:country":"IT",
    "sg:address":"4, Via Boschetto 34070 San Lorenzo Isontino",
    "sg:city":"San Lorenzo Isontino",
    "sg:classifiers":[
        {
            "category":"Food & Beverages",
            "subcategory":"Groceries & Convenience Stores",
            "type":"Retail Goods"
        }
    ],
    "sg:phone":"+39 39048180024",
    "sg:postcode":"34070",
    "sg:province":"Gorizia",
    "sg:tags":[
        "drink"
    ],
    "wof:name":"Scolaris Vini S.r.l.",
    "wof:placetype":"venue"
},
  "geometry": {"coordinates":[13.526855,45.932758],"type":"Point"}
}