{
  "type": "Feature",
  "properties": {
    "iso:country":"IT",
    "sg:address":"12, V. Turati 20046 Biassono",
    "sg:city":"Biassono",
    "sg:classifiers":[
        {
            "category":"Shopping",
            "subcategory":"Computers & Home Electronics",
            "type":"Retail Goods"
        }
    ],
    "sg:phone":"+39 039 275 3847",
    "sg:postcode":"20046",
    "sg:province":"Milano",
    "sg:tags":[
        "electronic",
        "electrical",
        "equipment"
    ],
    "sg:website":"http://www.sae-collettori.it",
    "wof:name":"Sae Srl",
    "wof:placetype":"venue"
},
  "geometry": {"coordinates":[9.267695,45.629101],"type":"Point"}
}