{
  "type": "Feature",
  "properties": {
    "iso:country":"IT",
    "sg:address":"86038 Petacciato",
    "sg:city":"Petacciato",
    "sg:orig_category":"Carpenterie Meccaniche",
    "sg:phone":"+39 0875 678438",
    "sg:postcode":"86038",
    "sg:province":"Campobasso",
    "wof:name":"Greco Meccanica Srl",
    "wof:placetype":"venue"
},
  "geometry": {"coordinates":[14.857137,42.019943],"type":"Point"}
}