{
  "type": "Feature",
  "properties": {
    "iso:country":"IT",
    "sg:address":"47023 Cesena",
    "sg:city":"Calisese",
    "sg:orig_category":"Prodotti Alimentari",
    "sg:phone":"+39 0547 58166",
    "sg:postcode":"47023",
    "sg:province":"Forl\u00ec-Cesena",
    "wof:name":"Co.p.r.a. Soc.coop.r.l.",
    "wof:placetype":"venue"
},
  "geometry": {"coordinates":[12.3139657974,44.1112098694],"type":"Point"}
}