{
  "type": "Feature",
  "properties": {
    "iso:country":"IT",
    "sg:address":"98122 Messina",
    "sg:city":"Messina",
    "sg:orig_category":"Materassi - Vendita Al Dettaglio",
    "sg:phone":"+39 090 641 4686",
    "sg:postcode":"98122",
    "sg:province":"Messina",
    "sg:website":"http://www.paginegialle.it/ergosan",
    "wof:name":"Ergosan Sas",
    "wof:placetype":"venue"
},
  "geometry": {"coordinates":[15.55621,38.190193],"type":"Point"}
}