{
  "type": "Feature",
  "properties": {
    "iso:country":"IT",
    "sg:address":"20021 Bollate",
    "sg:city":"Bollate",
    "sg:orig_category":"Motori Ed Organi Di Trasmissione",
    "sg:phone":"+39 02 356 1540",
    "sg:postcode":"20021",
    "sg:province":"Milano",
    "wof:name":"Ferrari Ingranaggi Snc Di Ferrari Giuseppe & C.",
    "wof:placetype":"venue"
},
  "geometry": {"coordinates":[9.1152553558,45.5433425903],"type":"Point"}
}