{
  "type": "Feature",
  "properties": {
    "iso:country":"IT",
    "sg:address":"21012 Cassano Magnago",
    "sg:city":"Cassano Magnago",
    "sg:orig_category":"Forniture Per Edilizia E Lavori Pubblici",
    "sg:phone":"+39 0331 201337",
    "sg:postcode":"21012",
    "sg:province":"Varese",
    "wof:name":"Ripar Di De Franceschi Rag. Giuseppe",
    "wof:placetype":"venue"
},
  "geometry": {"coordinates":[8.8472242355,45.653842926],"type":"Point"}
}