{
  "type": "Feature",
  "properties": {
    "iso:country":"IT",
    "sg:address":"57023 Cecina",
    "sg:city":"Cecina",
    "sg:orig_category":"Servizi Per Lo Sport E Il Tempo Libero. Servizi Al Turismo",
    "sg:phone":"+39 0586 632239",
    "sg:postcode":"57023",
    "sg:province":"Livorno",
    "wof:name":"Enjoy Lab.",
    "wof:placetype":"venue"
},
  "geometry": {"coordinates":[10.517584,43.306423],"type":"Point"}
}