{
  "type": "Feature",
  "properties": {
    "iso:country":"IT",
    "sg:address":"20142 Milano",
    "sg:city":"Milano",
    "sg:orig_category":"Gomma Articoli Vari - Vendita Al Dettaglio",
    "sg:phone":"+39 02 8951 6786",
    "sg:postcode":"20142",
    "sg:province":"Milano",
    "wof:name":"Eurogomma",
    "wof:placetype":"venue"
},
  "geometry": {"coordinates":[9.171592,45.441902],"type":"Point"}
}