{
  "type": "Feature",
  "properties": {
    "iso:country":"IT",
    "sg:address":"Via Rontani D. 55054 Massarosa",
    "sg:city":"Massarosa",
    "sg:classifiers":[
        {
            "category":"Personal",
            "subcategory":"Shoe Repair & Shine",
            "type":"Services"
        }
    ],
    "sg:phone":"+39 39058493163",
    "sg:postcode":"55054",
    "sg:province":"Lucca",
    "sg:tags":[
        "leather"
    ],
    "wof:name":"Calzaturificio Toscana Nord (s.r.l.)",
    "wof:placetype":"venue"
},
  "geometry": {"coordinates":[10.353848,43.861404],"type":"Point"}
}