{
  "type": "Feature",
  "properties": {
    "iso:country":"IT",
    "sg:address":"38, V. Passo Sella 41049 Sassuolo",
    "sg:city":"Sassuolo",
    "sg:classifiers":[
        {
            "category":"Shopping",
            "subcategory":"Crafts & Fabrics",
            "type":"Retail Goods"
        }
    ],
    "sg:phone":"+39 0536 810610",
    "sg:postcode":"41049",
    "sg:province":"Modena",
    "sg:tags":[
        "ceramic"
    ],
    "sg:website":"http://www.creaceramica.it:ws_end: :mark:ws:http://www.paginegialle.it/creasrl-01",
    "wof:name":"Crea Srl",
    "wof:placetype":"venue"
},
  "geometry": {"coordinates":[10.806664,44.561203],"type":"Point"}
}