{
  "type": "Feature",
  "properties": {
    "iso:country":"IT",
    "sg:address":"41043 Formigine",
    "sg:city":"Formigine",
    "sg:orig_category":"Arredo Bagno Ed Idrosanitari",
    "sg:phone":"+39 059 570606",
    "sg:postcode":"41043",
    "sg:province":"Modena",
    "wof:name":"Sangiorgi Geom. Fausto S.f.",
    "wof:placetype":"venue"
},
  "geometry": {"coordinates":[10.860903,44.523922],"type":"Point"}
}