{
  "type": "Feature",
  "properties": {
    "addr:full":"Localita' Padule 06024 Gubbio Gubbio Perugia 06024",
    "addr:postcode":"06024;06024",
    "addr:street":"Localita ' Padule",
    "iso:country":"IT",
    "sg:address":"Localita' Padule 06024 Gubbio",
    "sg:city":"Gubbio",
    "sg:classifiers":[
        {
            "category":"Parking",
            "subcategory":"Lot",
            "type":"Transportation"
        }
    ],
    "sg:phone":"+39 075 929 2118",
    "sg:postcode":"06024",
    "sg:province":"Perugia",
    "sg:tags":[
        "transport",
        "road"
    ],
    "wof:name":"Mori Augusto & Adriano (s.n.c.)",
    "wof:placetype":"venue"
},
  "geometry": {"coordinates":[12.389172,43.110703],"type":"Point"}
}