{
  "type": "Feature",
  "properties": {
    "addr:full":"Via G. Abbate 189 14054 Castagnole Lanze Asti 14054",
    "addr:housenumber":"189",
    "addr:postcode":"14054;14054",
    "addr:street":"Via G. Abbate",
    "iso:country":"IT",
    "sg:address":"Via G. Abbate 189 14054 Castagnole Lanze",
    "sg:classifiers":[
        {
            "category":"Banks & Credit Unions",
            "subcategory":"Investment Brokerage",
            "type":"Services"
        }
    ],
    "sg:phone":"+39 0141 876100",
    "sg:postcode":"14054",
    "sg:province":"Asti",
    "sg:tags":[
        "bale",
        "round",
        "chopper"
    ],
    "sg:website":"www.dragoneweb.org",
    "wof:name":"Dragone Snc Di Boeri Guido & C",
    "wof:placetype":"venue"
},
  "geometry": {"coordinates":[8.171361,44.75882],"type":"Point"}
}