{
  "type": "Feature",
  "properties": {
    "iso:country":"IT",
    "sg:address":"09045 Quartu Sant'elena",
    "sg:orig_category":"Forniture Per Edilizia E Lavori Pubblici",
    "sg:phone":"+39 070 883242",
    "sg:postcode":"09045",
    "sg:province":"Cagliari",
    "wof:name":"Technova Srl",
    "wof:placetype":"venue"
},
  "geometry": {"coordinates":[9.1840982437,39.2436637878],"type":"Point"}
}