{
  "type": "Feature",
  "properties": {
    "addr:full":"00176 Roma Roma Roma 00176",
    "addr:postcode":"00176;00176",
    "iso:country":"IT",
    "sg:address":"00176 Roma",
    "sg:city":"Roma",
    "sg:orig_category":"Chiese Ed Associazioni Religiose",
    "sg:phone":"+39 06 2170 2785",
    "sg:postcode":"00176",
    "sg:province":"Roma",
    "wof:name":"Chiesa Di Altri Culti Evangelica =assemblee Di Dio=",
    "wof:placetype":"venue"
},
  "geometry": {"coordinates":[12.533195,41.884373],"type":"Point"}
}