{
  "type": "Feature",
  "properties": {
    "addr:full":"98, Corso Regina Margherita 10153 Torino Torino Torino 10153",
    "addr:postcode":"10153;10153",
    "addr:street":"Corso Regina Margherita",
    "iso:country":"IT",
    "sg:address":"98, Corso Regina Margherita 10153 Torino",
    "sg:city":"Torino",
    "sg:classifiers":[
        {
            "category":"Shopping",
            "subcategory":"Clothing, Apparel, & Fashions",
            "type":"Retail Goods"
        }
    ],
    "sg:phone":"+39 011 521 4188",
    "sg:postcode":"10153",
    "sg:province":"Torino",
    "sg:tags":[
        "clothes"
    ],
    "wof:name":"Gi.ti. Confezioni (s.a.s.)",
    "wof:placetype":"venue"
},
  "geometry": {"coordinates":[7.690645,45.074558],"type":"Point"}
}