{
  "type": "Feature",
  "properties": {
    "iso:country":"IT",
    "sg:address":"20010 Canegrate",
    "sg:city":"Canegrate",
    "sg:orig_category":"Macchine, Impianti Ed Attrezzature Per Abbigliamento E Pelletterie",
    "sg:phone":"+39 0331 414005",
    "sg:postcode":"20010",
    "sg:province":"Milano",
    "wof:name":"Zito Salvatore",
    "wof:placetype":"venue"
},
  "geometry": {"coordinates":[9.212727,45.48119],"type":"Point"}
}