{
  "type": "Feature",
  "properties": {
    "addr:full":"3, Via Ferraris 21020 Monvalle Monvalle Varese 21020",
    "addr:postcode":"21020;21020",
    "addr:street":"Via Ferraris",
    "iso:country":"IT",
    "sg:address":"3, Via Ferraris 21020 Monvalle",
    "sg:city":"Monvalle",
    "sg:classifiers":[
        {
            "category":"Manufacturing",
            "subcategory":"Rubber & Plastics",
            "type":"Manufacturing & Wholesale Goods"
        }
    ],
    "sg:phone":"+39 0332 799518",
    "sg:postcode":"21020",
    "sg:province":"Varese",
    "wof:name":"Flexostar S.r.l.",
    "wof:placetype":"venue"
},
  "geometry": {"coordinates":[8.6362514496,45.8507194519],"type":"Point"}
}