{
  "type": "Feature",
  "properties": {
    "addr:full":"Via Volturno, 18; Udine; 33100 Udine Udine 33100",
    "addr:housenumber":"18",
    "addr:postcode":"33100;33100",
    "addr:street":"Via Volturno",
    "iso:country":"IT",
    "sg:address":"Via Volturno, 18; Udine; 33100",
    "sg:city":"Udine",
    "sg:classifiers":[
        {
            "category":"Banks & Credit Unions",
            "subcategory":"Bank",
            "type":"Services"
        }
    ],
    "sg:phone":"+39 0432 530771",
    "sg:postcode":"33100",
    "sg:province":"Udine",
    "wof:name":"Cassa Di Risparmio Di Udine, E Pondenone",
    "wof:placetype":"venue"
},
  "geometry": {"coordinates":[13.229076,46.055481],"type":"Point"}
}