{
  "type": "Feature",
  "properties": {
    "iso:country":"IT",
    "sg:address":"06034 Foligno",
    "sg:city":"Foligno",
    "sg:orig_category":"Non-classified Establishments",
    "sg:phone":"+39 0742 22003",
    "sg:postcode":"06034",
    "sg:province":"Perugia",
    "wof:name":"Serr Design Di Franco Perticoni",
    "wof:placetype":"venue"
},
  "geometry": {"coordinates":[12.782477,42.977386],"type":"Point"}
}