{
  "type": "Feature",
  "properties": {
    "addr:full":"Via Papa Roncalli , 21/23 25022 Borgo San Giacomo Borgo San Giacomo Brescia 25022",
    "addr:housenumber":"21 / 23",
    "addr:postcode":"25022;25022",
    "addr:street":"Via Papa Roncalli;Borgo San Giacomo Brescia",
    "iso:country":"IT",
    "sg:address":"Via Papa Roncalli , 21/23 25022 Borgo San Giacomo",
    "sg:city":"Borgo San Giacomo",
    "sg:classifiers":[
        {
            "category":"Sports & Exercise",
            "subcategory":"Athletic Track",
            "type":"Entertainment"
        }
    ],
    "sg:phone":"+39 030 948390",
    "sg:postcode":"25022",
    "sg:province":"Brescia",
    "sg:tags":[
        "men's",
        "knee-length",
        "stocking"
    ],
    "wof:name":"C & L D Srl",
    "wof:placetype":"venue"
},
  "geometry": {"coordinates":[9.9592838287,45.3558044434],"type":"Point"}
}