{
  "type": "Feature",
  "properties": {
    "addr:full":"13, Frazione Ponzone 13835 Trivero Ponzone Biella 13835",
    "addr:postcode":"13835;13835",
    "addr:street":"Frazione Ponzone",
    "iso:country":"IT",
    "sg:address":"13, Frazione Ponzone 13835 Trivero",
    "sg:city":"Ponzone",
    "sg:classifiers":[
        {
            "category":"Shopping",
            "subcategory":"Crafts & Fabrics",
            "type":"Retail Goods"
        }
    ],
    "sg:phone":"+39 015 738 8025",
    "sg:postcode":"13835",
    "sg:province":"Biella",
    "wof:name":"Ferla Egidio - Lanificio (s.p.a.)",
    "wof:placetype":"venue"
},
  "geometry": {"coordinates":[8.1884822845,45.6505393982],"type":"Point"}
}