{
  "type": "Feature",
  "properties": {
    "iso:country":"IT",
    "sg:address":"Via Xxv Aprile 39 20053 Muggio'",
    "sg:classifiers":[
        {
            "category":"Government",
            "subcategory":"Police Station",
            "type":"Public Place"
        }
    ],
    "sg:phone":"+39 039 794769",
    "sg:postcode":"20053",
    "sg:province":"Milano",
    "sg:tags":[
        "cafeteria",
        "furnishing"
    ],
    "sg:website":"www.bellinispa.it",
    "wof:name":"Bellini Fratelli S.p.a.",
    "wof:placetype":"venue"
},
  "geometry": {"coordinates":[9.188141,45.463688],"type":"Point"}
}