{
  "type": "Feature",
  "properties": {
    "iso:country":"IT",
    "sg:address":"20148 Milano",
    "sg:city":"Milano",
    "sg:orig_category":"Accessori Moda D'abbigliamento. Forniture Per Abbigliamento E Pelletterie. Shopping",
    "sg:phone":"+39 02 4800 0911",
    "sg:postcode":"20148",
    "sg:province":"Milano",
    "wof:name":"Persiani Aquinati Vera",
    "wof:placetype":"venue"
},
  "geometry": {"coordinates":[9.147132,45.481789],"type":"Point"}
}