{
  "type": "Feature",
  "properties": {
    "addr:full":"310, Viale Lombardia 20047 Brugherio Brugherio Milano 20047",
    "addr:postcode":"20047;20047",
    "addr:street":"Viale Lombardia",
    "iso:country":"IT",
    "sg:address":"310, Viale Lombardia 20047 Brugherio",
    "sg:city":"Brugherio",
    "sg:classifiers":[
        {
            "category":"Professional",
            "subcategory":"Printing & Photocopies",
            "type":"Services"
        }
    ],
    "sg:phone":"+39 039 202 4010",
    "sg:postcode":"20047",
    "sg:province":"Milano",
    "wof:name":"Musto C.di Musto Francesco Tipo Litografia",
    "wof:placetype":"venue"
},
  "geometry": {"coordinates":[9.2909574509,45.5446128845],"type":"Point"}
}