{
  "type": "Feature",
  "properties": {
    "addr:full":"Via Mulini 74 25039 Travagliato Travagliato Brescia 25039",
    "addr:housenumber":"74",
    "addr:postcode":"25039;25039",
    "addr:street":"Via Mulini",
    "iso:country":"IT",
    "sg:address":"Via Mulini 74 25039 Travagliato",
    "sg:city":"Travagliato",
    "sg:classifiers":[
        {
            "category":"Shopping",
            "subcategory":"Crafts & Fabrics",
            "type":"Retail Goods"
        }
    ],
    "sg:phone":"+39 030 661177",
    "sg:postcode":"25039",
    "sg:province":"Brescia",
    "sg:tags":[
        "textile",
        "woven",
        "ribbon",
        "nonwoven"
    ],
    "sg:website":"www.giorinastri.com",
    "wof:name":"Giorinastri Snc Di Giori Giuseppe & C",
    "wof:placetype":"venue"
},
  "geometry": {"coordinates":[10.076113,45.534405],"type":"Point"}
}