{
  "type": "Feature",
  "properties": {
    "iso:country":"IT",
    "sg:address":"40069 Zola Predosa",
    "sg:city":"Zola",
    "sg:orig_category":"Climatizzazione E Condizionamento, Apparecchiature E Servizi. Accessori Dei Mezzi Di Trasporto",
    "sg:phone":"+39 051 758650",
    "sg:postcode":"40069",
    "sg:province":"Bologna",
    "wof:name":"Centro Polivalente 'lolli Auto' Srl",
    "wof:placetype":"venue"
},
  "geometry": {"coordinates":[11.252951,44.494747],"type":"Point"}
}