{
  "type": "Feature",
  "properties": {
    "addr:full":"Via Del Dosso 10 22040 Alzate Brianza Alzate Brianza Como 22040",
    "addr:housenumber":"10",
    "addr:postcode":"22040;22040",
    "addr:street":"Via Del Dosso",
    "iso:country":"IT",
    "sg:address":"Via Del Dosso 10 22040 Alzate Brianza",
    "sg:city":"Alzate Brianza",
    "sg:classifiers":[
        {
            "category":"Transit Center",
            "subcategory":"Freight",
            "type":"Transportation"
        }
    ],
    "sg:phone":"+39 031 632433",
    "sg:postcode":"22040",
    "sg:province":"Como",
    "sg:tags":[
        "necktie"
    ],
    "wof:name":"Laboratorio Santina Di Manciaracina Susanna",
    "wof:placetype":"venue"
},
  "geometry": {"coordinates":[9.175448,45.768414],"type":"Point"}
}