{
  "type": "Feature",
  "properties": {
    "iso:country":"IT",
    "sg:address":"S. S. Lucchese 193 51030 Serravalle Pistoiese",
    "sg:city":"Serravalle Pistoiese",
    "sg:classifiers":[
        {
            "category":"Manufacturing",
            "subcategory":"Rubber & Plastics",
            "type":"Manufacturing & Wholesale Goods"
        }
    ],
    "sg:phone":"+39 0573 91501",
    "sg:postcode":"51030",
    "sg:province":"Pistoia",
    "sg:tags":[
        "material"
    ],
    "wof:name":"Febo Spa",
    "wof:placetype":"venue"
},
  "geometry": {"coordinates":[10.8236722946,43.8981056213],"type":"Point"}
}