{
  "type": "Feature",
  "properties": {
    "iso:country":"IT",
    "sg:address":"10122 Torino",
    "sg:city":"Torino",
    "sg:orig_category":"Forniture Per Edilizia E Lavori Pubblici. Forniture Per Attivita' Industriali",
    "sg:phone":"+39 011 521 5307",
    "sg:postcode":"10122",
    "sg:province":"Torino",
    "wof:name":"Falco & Boulanger",
    "wof:placetype":"venue"
},
  "geometry": {"coordinates":[7.6732234955,45.0777511597],"type":"Point"}
}