{
  "type": "Feature",
  "properties": {
    "addr:full":"28064 Carpignano Sesia Carpignano Sesia Novara 28064",
    "addr:postcode":"28064;28064",
    "iso:country":"IT",
    "sg:address":"28064 Carpignano Sesia",
    "sg:city":"Carpignano Sesia",
    "sg:orig_category":"Materiali Semilavorati Metallici",
    "sg:phone":"+39 0321 824539",
    "sg:postcode":"28064",
    "sg:province":"Novara",
    "wof:name":"Soeco S.r.l.",
    "wof:placetype":"venue"
},
  "geometry": {"coordinates":[8.407554,45.53175],"type":"Point"}
}