{
  "type": "Feature",
  "properties": {
    "addr:full":"33035 Martignacco Martignacco Udine 33035",
    "addr:postcode":"33035;33035",
    "iso:country":"IT",
    "sg:address":"33035 Martignacco",
    "sg:city":"Martignacco",
    "sg:orig_category":"Termotecnica E Riscaldamento, Apparecchiature E Servizi",
    "sg:phone":"+39 0432 400028",
    "sg:postcode":"33035",
    "sg:province":"Udine",
    "wof:name":"R.e.t. Impianti Di Fuligni Marco",
    "wof:placetype":"venue"
},
  "geometry": {"coordinates":[13.184694,46.074116],"type":"Point"}
}