{
  "type": "Feature",
  "properties": {
    "iso:country":"IT",
    "sg:address":"12, Calle Miotti 30141 Venezia",
    "sg:city":"Venezia",
    "sg:classifiers":[
        {
            "category":"Manufacturing",
            "subcategory":"Glass & Minerals",
            "type":"Manufacturing & Wholesale Goods"
        }
    ],
    "sg:phone":"+39 041 527 4720",
    "sg:postcode":"30141",
    "sg:province":"Venezia",
    "wof:name":"Gondola Murano Glass S.r.l.",
    "wof:placetype":"venue"
},
  "geometry": {"coordinates":[12.353233,45.453197],"type":"Point"}
}