{
  "type": "Feature",
  "properties": {
    "iso:country":"IT",
    "sg:address":"Viale Venezia 31015 Conegliano",
    "sg:city":"Conegliano",
    "sg:classifiers":[
        {
            "category":"Shopping",
            "subcategory":"Computers & Home Electronics",
            "type":"Retail Goods"
        }
    ],
    "sg:phone":"+39 0438 451099",
    "sg:postcode":"31015",
    "sg:province":"Treviso",
    "sg:tags":[
        "electronic",
        "electrical",
        "equipment"
    ],
    "wof:name":"Quasar Electronic Devices (s.r.l.)",
    "wof:placetype":"venue"
},
  "geometry": {"coordinates":[12.276065,45.869713],"type":"Point"}
}