{
  "type": "Feature",
  "properties": {
    "iso:country":"IT",
    "sg:address":"40131 Bologna",
    "sg:city":"Bologna",
    "sg:orig_category":"Ortopedia - Articoli",
    "sg:phone":"+39 051 522626",
    "sg:postcode":"40131",
    "sg:province":"Bologna",
    "sg:website":"http://www.monzali.it",
    "wof:name":"Laboratorio Ortopedico Monzali L.o.m.s. Srl",
    "wof:placetype":"venue"
},
  "geometry": {"coordinates":[11.325371,44.500397],"type":"Point"}
}