{
  "type": "Feature",
  "properties": {
    "iso:country":"IT",
    "sg:address":"20159 Milano",
    "sg:city":"Milano",
    "sg:orig_category":"Ricambi E Componenti Dei Mezzi Di Trasporto",
    "sg:phone":"+39 02 6680 0599",
    "sg:postcode":"20159",
    "sg:province":"Milano",
    "wof:name":"I Centro Tecnico Marmitte S.r.l.",
    "wof:placetype":"venue"
},
  "geometry": {"coordinates":[9.186899,45.500191],"type":"Point"}
}