{
  "type": "Feature",
  "properties": {
    "iso:country":"IT",
    "sg:address":"95, V. Del Casale Paoloni 00133 Roma",
    "sg:city":"Roma",
    "sg:classifiers":[
        {
            "category":"Food & Beverages",
            "subcategory":"Groceries & Convenience Stores",
            "type":"Retail Goods"
        }
    ],
    "sg:phone":"+39 39067200110",
    "sg:postcode":"00133",
    "sg:province":"Roma",
    "sg:tags":[
        "product",
        "related"
    ],
    "sg:website":"http://www.cagesitalia.com",
    "wof:name":"Cages Srl",
    "wof:placetype":"venue"
},
  "geometry": {"coordinates":[12.6386890411,41.8254699707],"type":"Point"}
}