{
  "type": "Feature",
  "properties": {
    "iso:country":"IT",
    "sg:address":"87036 Rende",
    "sg:city":"Rende",
    "sg:orig_category":"Studi E Consulenze Legali E Notarili. Avvocati, Notai E Servizi Legali. Professionisti - Studi E Servizi Ed Associazioni Di Interesse Aziendale",
    "sg:phone":"+39 0984 466265",
    "sg:postcode":"87036",
    "sg:province":"Cosenza",
    "wof:name":"Scornajenghi & Calvelli",
    "wof:placetype":"venue"
},
  "geometry": {"coordinates":[16.24379,39.325603],"type":"Point"}
}