{
  "type": "Feature",
  "properties": {
    "iso:country":"IT",
    "sg:address":"211, Via Milano 46019 Viadana",
    "sg:city":"Viadana",
    "sg:classifiers":[
        {
            "category":"Shopping",
            "subcategory":"Clothing, Apparel, & Fashions",
            "type":"Retail Goods"
        }
    ],
    "sg:phone":"+39 39037588289",
    "sg:postcode":"46019",
    "sg:province":"Mantova",
    "sg:tags":[
        "clothes"
    ],
    "wof:name":"Helenpell Di Orlandelli Elena & C. (s.n.c.)",
    "wof:placetype":"venue"
},
  "geometry": {"coordinates":[10.487244,44.940857],"type":"Point"}
}