{
  "type": "Feature",
  "properties": {
    "iso:country":"IT",
    "sg:address":"47010 Galeata",
    "sg:city":"Galeata",
    "sg:orig_category":"Servizi E Lavori Per Agricoltura E Zootecnia. Servizi E Lavori Industria Chimica. Servizi Ausiliari Di Analisi, Controllo E Ricerca",
    "sg:phone":"+39 0543 981532",
    "sg:postcode":"47010",
    "sg:province":"Forl\u00ec-Cesena",
    "wof:name":"Ecology Farm S.n.c. Di Maurizio Lippi E Marco Ravaioli",
    "wof:placetype":"venue"
},
  "geometry": {"coordinates":[11.980461,43.994766],"type":"Point"}
}