{
  "type": "Feature",
  "properties": {
    "addr:full":"00041 Albano Laziale Albano Laziale Roma 00041",
    "addr:postcode":"00041;00041",
    "addr:street":"Roma",
    "iso:country":"IT",
    "sg:address":"00041 Albano Laziale",
    "sg:city":"Albano Laziale",
    "sg:orig_category":"Banche E Servizi Finanziari. Acqua, Luce, Gas E Societa' Di Esercizio Pubblico",
    "sg:phone":"+39 06 930 6623",
    "sg:postcode":"00041",
    "sg:province":"Roma",
    "wof:name":"Esattoria Ii.dd.",
    "wof:placetype":"venue"
},
  "geometry": {"coordinates":[12.482522,41.928852],"type":"Point"}
}