{
  "type": "Feature",
  "properties": {
    "iso:country":"IT",
    "sg:address":"20145 Milano",
    "sg:city":"Milano",
    "sg:orig_category":"Macchine, Impianti Ed Attrezzature Industria Delle Materie Plastiche E Gomma",
    "sg:phone":"+39 02 469 1867",
    "sg:postcode":"20145",
    "sg:province":"Milano",
    "wof:name":"Plastimac (s.p.a.)",
    "wof:placetype":"venue"
},
  "geometry": {"coordinates":[9.153701,45.473301],"type":"Point"}
}