{
  "type": "Feature",
  "properties": {
    "iso:country":"IT",
    "sg:address":"5, Via Altmann Sebastian 39100 Bolzano",
    "sg:city":"Bolzano",
    "sg:classifiers":[
        {
            "category":"Sports & Exercise",
            "subcategory":"Playing Field",
            "type":"Entertainment"
        }
    ],
    "sg:phone":"+39 0471 912781",
    "sg:postcode":"39100",
    "sg:province":"Bolzano/Bozen",
    "sg:tags":[
        "game"
    ],
    "wof:name":"H. Klammsteiner & Co. (s.n.c.)",
    "wof:placetype":"venue"
},
  "geometry": {"coordinates":[11.328239,46.461643],"type":"Point"}
}