{
  "type": "Feature",
  "properties": {
    "addr:full":"20128 Milano Milano Milano 20128",
    "addr:postcode":"20128;20128",
    "iso:country":"IT",
    "sg:address":"20128 Milano",
    "sg:city":"Milano",
    "sg:orig_category":"Prodotti E Manufatti In Materie Plastiche",
    "sg:phone":"+39 02 2720 3323",
    "sg:postcode":"20128",
    "sg:province":"Milano",
    "wof:name":"Elleci Di Lorusso Donato & C. Snc",
    "wof:placetype":"venue"
},
  "geometry": {"coordinates":[9.2343406677,45.5068092346],"type":"Point"}
}