{
  "type": "Feature",
  "properties": {
    "iso:country":"IT",
    "sg:address":"52020 Meleto",
    "sg:orig_category":"Vetro: Prodotti E Lavorazioni",
    "sg:phone":"+39 055 961625",
    "sg:postcode":"52020",
    "sg:province":"Arezzo",
    "wof:name":"I.p.a. Di Cappelli A.",
    "wof:placetype":"venue"
},
  "geometry": {"coordinates":[11.863062,43.471203],"type":"Point"}
}