{
  "type": "Feature",
  "properties": {
    "addr:full":"Via Cantone 46030 Dosolo Dosolo Mantova 46030",
    "addr:postcode":"46030;46030",
    "addr:street":"Via Cantone",
    "iso:country":"IT",
    "sg:address":"Via Cantone 46030 Dosolo",
    "sg:city":"Dosolo",
    "sg:classifiers":[
        {
            "category":"Professional",
            "subcategory":"Engineering",
            "type":"Services"
        }
    ],
    "sg:phone":"+39 39037589825",
    "sg:postcode":"46030",
    "sg:province":"Mantova",
    "sg:tags":[
        "machine",
        "-",
        "mechanical"
    ],
    "wof:name":"Daolio",
    "wof:placetype":"venue"
},
  "geometry": {"coordinates":[10.628331,44.94558],"type":"Point"}
}