{
  "type": "Feature",
  "properties": {
    "iso:country":"IT",
    "sg:address":"05036 Narni Scalo",
    "sg:orig_category":"Prodotti Chimici Di Base",
    "sg:phone":"+39 0744 737971",
    "sg:province":"TR",
    "wof:name":"H.p.i. Srl",
    "wof:placetype":"venue"
},
  "geometry": {"coordinates":[12.4656677246,42.5121917725],"type":"Point"}
}