{
  "type": "Feature",
  "properties": {
    "iso:country":"IT",
    "sg:address":"20141 Milano",
    "sg:city":"Milano",
    "sg:orig_category":"Macchine, Impianti Ed Attrezzature Industria Chimica",
    "sg:postcode":"20141",
    "sg:province":"Milano",
    "wof:name":"Linetronic Europe S.p.a.",
    "wof:placetype":"venue"
},
  "geometry": {"coordinates":[9.189147,45.441055],"type":"Point"}
}