{
  "type": "Feature",
  "properties": {
    "iso:country":"IT",
    "sg:address":"54, Via Varian Fratelli 10040 Leini'",
    "sg:classifiers":[
        {
            "category":"Utilities",
            "subcategory":"Electric",
            "type":"Services"
        }
    ],
    "sg:phone":"+39 011 991 0857",
    "sg:postcode":"10040",
    "sg:province":"Torino",
    "sg:tags":[
        "component",
        "electronic"
    ],
    "wof:name":"Varian S.p.a.",
    "wof:placetype":"venue"
},
  "geometry": {"coordinates":[7.723631,45.150806],"type":"Point"}
}