{
  "type": "Feature",
  "properties": {
    "iso:country":"IT",
    "sg:address":"26020 Cappella Cantone",
    "sg:city":"Cappella Cantone",
    "sg:orig_category":"Servizi E Lavori Per Agricoltura E Zootecnia",
    "sg:phone":"+39 0374 372068",
    "sg:postcode":"26020",
    "sg:province":"Cremona",
    "wof:name":"Pozzali Eligio",
    "wof:placetype":"venue"
},
  "geometry": {"coordinates":[9.83939,45.247517],"type":"Point"}
}