{
  "type": "Feature",
  "properties": {
    "iso:country":"IT",
    "sg:address":"9, Via Brigata Tridentina 35020 Pernumia",
    "sg:city":"Pernumia",
    "sg:classifiers":[
        {
            "category":"Manufacturing",
            "subcategory":"Metals",
            "type":"Manufacturing & Wholesale Goods"
        }
    ],
    "sg:phone":"+39 0429 779150",
    "sg:postcode":"35020",
    "sg:province":"Padova",
    "sg:tags":[
        "processing"
    ],
    "wof:name":"Officine Meccaniche Moro Di Moro Giancarlo & C. S.a.s.",
    "wof:placetype":"venue"
},
  "geometry": {"coordinates":[11.7798709869,45.2537231445],"type":"Point"}
}