{
  "type": "Feature",
  "properties": {
    "addr:full":"70126 Bari Bari Bari 70126",
    "addr:postcode":"70126;70126",
    "iso:country":"IT",
    "sg:address":"70126 Bari",
    "sg:city":"Bari",
    "sg:orig_category":"Petroli, Gas E Combustibili. Servizi E Lavori Industria Chimica",
    "sg:phone":"+39 080 548 7001",
    "sg:postcode":"70126",
    "sg:province":"Bari",
    "wof:name":"Agip Petroli Spa",
    "wof:placetype":"venue"
},
  "geometry": {"coordinates":[16.888999939,41.099407196],"type":"Point"}
}