{
  "type": "Feature",
  "properties": {
    "iso:country":"IT",
    "sg:address":"20134 Milano",
    "sg:city":"Milano",
    "sg:orig_category":"Servizi Editoriali. Servizi Ausiliari Per Il Trasporto",
    "sg:phone":"+39 02 7611 8031",
    "sg:postcode":"20134",
    "sg:province":"Milano",
    "wof:name":"Parrini & C. Spa",
    "wof:placetype":"venue"
},
  "geometry": {"coordinates":[9.251833,45.476692],"type":"Point"}
}