{
  "type": "Feature",
  "properties": {
    "addr:full":"24060 Castelli Calepio Castelli Calepio Bergamo 24060",
    "addr:postcode":"24060;24060",
    "iso:country":"IT",
    "sg:address":"24060 Castelli Calepio",
    "sg:city":"Castelli Calepio",
    "sg:orig_category":"Prodotti E Manufatti In Gomma",
    "sg:phone":"+39 030 743 5471",
    "sg:postcode":"24060",
    "sg:province":"Bergamo",
    "wof:name":"I.s. S.n.c. Di Valtulini E Zanuzzi",
    "wof:placetype":"venue"
},
  "geometry": {"coordinates":[9.8965778351,45.6139144897],"type":"Point"}
}