{
  "type": "Feature",
  "properties": {
    "iso:country":"IT",
    "sg:address":"30123 Venezia",
    "sg:city":"Dorsoduro",
    "sg:classifiers":[
        {
            "category":"Bars & Pubs",
            "subcategory":"Champagne Bar",
            "type":"Food & Drink"
        }
    ],
    "sg:phone":"+39 041 528 6396",
    "sg:postcode":"30123",
    "sg:province":"Venezia",
    "sg:tags":[
        "caffe'",
        "e"
    ],
    "sg:website":"http://www.aigondolieri.com",
    "wof:name":"'ai Gondolieri' Di Giovanni Trevisan & C.",
    "wof:placetype":"venue"
},
  "geometry": {"coordinates":[12.322415,45.432846],"type":"Point"}
}