{
  "type": "Feature",
  "properties": {
    "iso:country":"IT",
    "sg:address":"00048 Nettuno",
    "sg:city":"Nettuno",
    "sg:orig_category":"Bevande, Vini E Liquori",
    "sg:phone":"+39 06 9898 8042",
    "sg:postcode":"00048",
    "sg:province":"Roma",
    "wof:name":"Eurodrink 92 Sas Di Trulli Isabelle E C.",
    "wof:placetype":"venue"
},
  "geometry": {"coordinates":[12.359755,41.761677],"type":"Point"}
}