{
  "type": "Feature",
  "properties": {
    "iso:country":"IT",
    "sg:address":"37121 Verona",
    "sg:city":"Verona",
    "sg:orig_category":"Articoli Da Regalo. Forniture Per Uffici. Regalistica Aziendale",
    "sg:phone":"+39 045 594736",
    "sg:postcode":"37121",
    "sg:province":"Verona",
    "wof:name":"Saccomani Di Rocca Pietro",
    "wof:placetype":"venue"
},
  "geometry": {"coordinates":[10.994884,45.441193],"type":"Point"}
}