{
  "type": "Feature",
  "properties": {
    "iso:country":"IT",
    "sg:address":"20141 Milano",
    "sg:city":"Milano",
    "sg:orig_category":"Forniture Per Uffici",
    "sg:phone":"+39 02 522 0061",
    "sg:postcode":"20141",
    "sg:province":"Milano",
    "sg:website":"http://www.gruppobdf.com",
    "wof:name":"B.d.f. Spa",
    "wof:placetype":"venue"
},
  "geometry": {"coordinates":[9.1898603439,45.4402198792],"type":"Point"}
}