{
  "type": "Feature",
  "properties": {
    "iso:country":"IT",
    "sg:address":"26030 Cicognolo",
    "sg:city":"Cicognolo",
    "sg:orig_category":"Lucernari",
    "sg:phone":"+39 0372 835996",
    "sg:postcode":"26030",
    "sg:province":"Cremona",
    "wof:name":"O.s.a.c. Snc",
    "wof:placetype":"venue"
},
  "geometry": {"coordinates":[10.19563,45.165649],"type":"Point"}
}