{
  "type": "Feature",
  "properties": {
    "addr:full":"95045 Misterbianco Misterbianco Catania 95045",
    "addr:postcode":"95045;95045",
    "iso:country":"IT",
    "sg:address":"95045 Misterbianco",
    "sg:city":"Misterbianco",
    "sg:orig_category":"Acciaierie E Fonderie",
    "sg:phone":"+39 095 476729",
    "sg:postcode":"95045",
    "sg:province":"Catania",
    "wof:name":"Nasello Salvatore & Figli Snc",
    "wof:placetype":"venue"
},
  "geometry": {"coordinates":[15.026083,37.512421],"type":"Point"}
}