{
  "type": "Feature",
  "properties": {
    "addr:full":"50025 Montespertoli Montespertoli Firenze 50025",
    "addr:postcode":"50025;50025",
    "iso:country":"IT",
    "sg:address":"50025 Montespertoli",
    "sg:city":"Montespertoli",
    "sg:orig_category":"Arredo Bagno Ed Idrosanitari. Elettrodomestici",
    "sg:phone":"+39 0571 671349",
    "sg:postcode":"50025",
    "sg:province":"Firenze",
    "wof:name":"Bagno Look Srl",
    "wof:placetype":"venue"
},
  "geometry": {"coordinates":[11.082663,43.658222],"type":"Point"}
}