{
  "type": "Feature",
  "properties": {
    "iso:country":"IT",
    "sg:address":"25030 Paratico",
    "sg:city":"Paratico",
    "sg:orig_category":"Prodotti E Manufatti In Gomma. Forniture Per Attivita' Industriali",
    "sg:phone":"+39 035 924411",
    "sg:postcode":"25030",
    "sg:province":"Brescia",
    "sg:website":"http://www.tecnicagasket.com",
    "wof:name":"Tecnica Gasket Spa",
    "wof:placetype":"venue"
},
  "geometry": {"coordinates":[9.9441728592,45.6564216614],"type":"Point"}
}