{
  "type": "Feature",
  "properties": {
    "addr:full":"31040 Volpago Del Montello Volpago del Montello Treviso 31040",
    "addr:housenumber":"del montello",
    "addr:postcode":"31040;31040",
    "addr:street":"Del Montello",
    "iso:country":"IT",
    "sg:address":"31040 Volpago Del Montello",
    "sg:city":"Volpago del Montello",
    "sg:orig_category":"Prodotti Vari In Metallo",
    "sg:phone":"+39 0423 621976",
    "sg:postcode":"31040",
    "sg:province":"Treviso",
    "wof:name":"Ferrobeton Srl",
    "wof:placetype":"venue"
},
  "geometry": {"coordinates":[12.17100811,45.6756629944],"type":"Point"}
}