{
  "type": "Feature",
  "properties": {
    "addr:full":"95041 Caltagirone Caltagirone Catania 95041",
    "addr:postcode":"95041;95041",
    "iso:country":"IT",
    "sg:address":"95041 Caltagirone",
    "sg:city":"Caltagirone",
    "sg:orig_category":"Ceramiche: Prodotti E Lavorazioni. Articoli Da Regalo. Arte Ed Artigianato Artistico. Shopping",
    "sg:phone":"+39 0933 34111",
    "sg:postcode":"95041",
    "sg:province":"Catania",
    "sg:website":"http://www.lalumiera.com",
    "wof:name":"Societ\u00c0 Consorzile 'la Lumiera'",
    "wof:placetype":"venue"
},
  "geometry": {"coordinates":[14.518922,37.206078],"type":"Point"}
}