{
  "type": "Feature",
  "properties": {
    "iso:country":"IT",
    "sg:address":"Via Piave 1; Lonate Ceppino; 21050",
    "sg:city":"Lonate Ceppino",
    "sg:classifiers":[
        {
            "category":"Banks & Credit Unions",
            "subcategory":"Bank",
            "type":"Services"
        }
    ],
    "sg:phone":"+39 0331 842080",
    "sg:postcode":"21050",
    "sg:province":"Varese",
    "wof:name":"Banco Ambrosiano Veneto Spa",
    "wof:placetype":"venue"
},
  "geometry": {"coordinates":[8.882339,45.706318],"type":"Point"}
}