{
  "type": "Feature",
  "properties": {
    "iso:country":"IT",
    "sg:address":"29010 Nibbiano",
    "sg:city":"Nibbiano",
    "sg:orig_category":"Trasporto Pubblico E Privato",
    "sg:phone":"+39 348 873 6194",
    "sg:postcode":"29010",
    "sg:province":"Piacenza",
    "wof:name":"Blue Car Service Di Vasta Ciro",
    "wof:placetype":"venue"
},
  "geometry": {"coordinates":[9.3575153351,44.9253234863],"type":"Point"}
}