{
  "type": "Feature",
  "properties": {
    "iso:country":"IT",
    "sg:address":"57, Via Maestri Del Lavoro 62012 Civitanova Marche",
    "sg:city":"Civitanova Marche",
    "sg:classifiers":[
        {
            "category":"Personal",
            "subcategory":"Shoe Repair & Shine",
            "type":"Services"
        }
    ],
    "sg:phone":"+39 0733 897382",
    "sg:postcode":"62012",
    "sg:province":"Macerata",
    "sg:tags":[
        "leather"
    ],
    "wof:name":"Suol System Di Paola Zallocco & C. Sas",
    "wof:placetype":"venue"
},
  "geometry": {"coordinates":[13.687974,43.28949],"type":"Point"}
}