{
  "type": "Feature",
  "properties": {
    "iso:country":"IT",
    "sg:address":"Via Per Modena 152 41014 Castelvetro Di Modena",
    "sg:city":"Castelvetro di Modena",
    "sg:classifiers":[
        {
            "category":"Government",
            "subcategory":"Department Of Motor Vehicles",
            "type":"Public Place"
        }
    ],
    "sg:phone":"+39 059 704111",
    "sg:postcode":"41014",
    "sg:province":"Modena",
    "sg:tags":[
        "caterpillar",
        "chassis",
        "excavator"
    ],
    "sg:website":"www.passinigroup.com",
    "wof:name":"Italtractor Itm Spa",
    "wof:placetype":"venue"
},
  "geometry": {"coordinates":[10.947031,44.509079],"type":"Point"}
}