{
  "type": "Feature",
  "properties": {
    "iso:country":"IT",
    "sg:address":"36022 Cassola",
    "sg:city":"Cassola",
    "sg:orig_category":"Forniture Per Edilizia E Lavori Pubblici",
    "sg:phone":"+39 0424 533082",
    "sg:postcode":"36022",
    "sg:province":"Vicenza",
    "sg:website":"http://www.maspe.com",
    "wof:name":"Maspe Srl",
    "wof:placetype":"venue"
},
  "geometry": {"coordinates":[11.589091301,45.5390472412],"type":"Point"}
}