{
  "type": "Feature",
  "properties": {
    "addr:full":"23/2, Via Stromboli 20144 Milano Milano Milano 20144",
    "addr:housenumber":"23 / 2",
    "addr:postcode":"20144;20144",
    "addr:street":"Via Stromboli",
    "iso:country":"IT",
    "sg:address":"23/2, Via Stromboli 20144 Milano",
    "sg:city":"Milano",
    "sg:classifiers":[
        {
            "category":"Real Estate",
            "subcategory":"Architect",
            "type":"Services"
        }
    ],
    "sg:phone":"+39 02 4895 5457",
    "sg:postcode":"20144",
    "sg:province":"Milano",
    "sg:tags":[
        "textile",
        "clothing"
    ],
    "wof:name":"Cudicini (s.r.l.)",
    "wof:placetype":"venue"
},
  "geometry": {"coordinates":[9.157257,45.458225],"type":"Point"}
}