{
  "type": "Feature",
  "properties": {
    "iso:country":"IT",
    "sg:address":"20099 Sesto San Giovanni",
    "sg:city":"Sesto San Giovanni",
    "sg:classifiers":[
        {
            "category":"Building & Trades",
            "subcategory":"Cleaning & Sanitation",
            "type":"Services"
        }
    ],
    "sg:phone":"+39 02 2247 6415",
    "sg:postcode":"20099",
    "sg:province":"Milano",
    "sg:tags":[
        "handling",
        "auxiliary",
        "storage",
        "support",
        "companies",
        "surveillance",
        "maintenance",
        "services",
        "events"
    ],
    "wof:name":"Logistica & Lavoro Scrl",
    "wof:placetype":"venue"
},
  "geometry": {"coordinates":[9.2286,45.529819],"type":"Point"}
}