{
  "type": "Feature",
  "properties": {
    "iso:country":"IT",
    "sg:address":"40050 Monteveglio",
    "sg:city":"Monteveglio",
    "sg:orig_category":"Petroli, Gas E Combustibili. Materiali Edili",
    "sg:phone":"+39 051 831315",
    "sg:postcode":"40050",
    "sg:province":"Bologna",
    "wof:name":"Seaf Srl",
    "wof:placetype":"venue"
},
  "geometry": {"coordinates":[11.0951862335,44.4942131042],"type":"Point"}
}