{
  "type": "Feature",
  "properties": {
    "iso:country":"IT",
    "sg:address":"31100 Treviso",
    "sg:city":"Treviso",
    "sg:orig_category":"Arredamenti E Mobili Professionali. Forniture Alle Strutture Ricettive. Arredi Ed Attrezzature Per Attivita' Commerciali Ed Artigianali",
    "sg:phone":"+39 0422 300245",
    "sg:postcode":"31100",
    "sg:province":"Treviso",
    "sg:website":"http://www.storage-gm.com",
    "wof:name":"Storage - Spe.a. Srl",
    "wof:placetype":"venue"
},
  "geometry": {"coordinates":[12.22861,45.65741],"type":"Point"}
}