{
  "type": "Feature",
  "properties": {
    "addr:full":"91011 Alcamo Alcamo Trapani 91011",
    "addr:postcode":"91011;91011",
    "iso:country":"IT",
    "sg:address":"91011 Alcamo",
    "sg:city":"Alcamo",
    "sg:orig_category":"Forniture E Materiali Per Imballaggio E Confezionamento. Forniture Per Uffici. Forniture Per Attivita' Commerciali Ed Artigianali",
    "sg:phone":"+39 0924 28300",
    "sg:postcode":"91011",
    "sg:province":"Trapani",
    "wof:name":"Etigraf Di Milito Pietro",
    "wof:placetype":"venue"
},
  "geometry": {"coordinates":[12.9665822983,37.9540710449],"type":"Point"}
}