{
  "type": "Feature",
  "properties": {
    "iso:country":"IT",
    "sg:address":"2, Via Bellini Vincenzo 40065 Pianoro",
    "sg:city":"Pianoro",
    "sg:classifiers":[
        {
            "category":"Shopping",
            "subcategory":"Clothing, Apparel, & Fashions",
            "type":"Retail Goods"
        }
    ],
    "sg:phone":"+39 051 620 5111",
    "sg:postcode":"40065",
    "sg:province":"Bologna",
    "sg:tags":[
        "clothes"
    ],
    "wof:name":"Wings S.p.a.",
    "wof:placetype":"venue"
},
  "geometry": {"coordinates":[11.348639,44.419941],"type":"Point"}
}