{
  "type": "Feature",
  "properties": {
    "addr:full":"Via Gambalera 15100 Alessandria Alessandria Alessandria 15100",
    "addr:postcode":"15100;15100",
    "addr:street":"Via Gambalera",
    "iso:country":"IT",
    "sg:address":"Via Gambalera 15100 Alessandria",
    "sg:city":"Alessandria",
    "sg:classifiers":[
        {
            "category":"Manufacturing",
            "subcategory":"Rubber & Plastics",
            "type":"Manufacturing & Wholesale Goods"
        }
    ],
    "sg:phone":"+39 0131 213411",
    "sg:postcode":"15100",
    "sg:province":"Alessandria",
    "sg:tags":[
        "packaging",
        "material",
        "-"
    ],
    "wof:name":"Guala Dispensing S.r.l.",
    "wof:placetype":"venue"
},
  "geometry": {"coordinates":[8.696814537,44.8908615112],"type":"Point"}
}