{
  "type": "Feature",
  "properties": {
    "iso:country":"IT",
    "sg:address":"20090 Pieve Emanuele",
    "sg:city":"Pieve Emanuele",
    "sg:orig_category":"Macchine, Impianti E Forniture Per Industria Grafica, Cartaria E Cartotecnica",
    "sg:phone":"+39 02 9078 1941",
    "sg:postcode":"20090",
    "sg:province":"Milano",
    "wof:name":"Seri Assistance Di Pugni Marco Angelo",
    "wof:placetype":"venue"
},
  "geometry": {"coordinates":[9.168053,45.374195],"type":"Point"}
}