{
  "type": "Feature",
  "properties": {
    "iso:country":"IT",
    "sg:address":"38100 Trento",
    "sg:city":"Trento",
    "sg:orig_category":"Servizi E Lavori Per Ecologia E Smaltimento Rifiuti. Termotecnica E Riscaldamento, Apparecchiature E Servizi. Servizi Ausiliari Di Sorveglianza, Manutenzione E Pulizia",
    "sg:phone":"+39 0461 236092",
    "sg:postcode":"38100",
    "sg:province":"Trento",
    "wof:name":"Malfer Aldo",
    "wof:placetype":"venue"
},
  "geometry": {"coordinates":[11.117494,46.071953],"type":"Point"}
}