{
  "type": "Feature",
  "properties": {
    "addr:full":"11, Via Giuseppe Mazzini 35024 Bovolenta Bovolenta Padova 35024",
    "addr:postcode":"35024;35024",
    "addr:street":"Via Giuseppe Mazzini",
    "iso:country":"IT",
    "sg:address":"11, Via Giuseppe Mazzini 35024 Bovolenta",
    "sg:city":"Bovolenta",
    "sg:classifiers":[
        {
            "category":"Shopping",
            "subcategory":"Crafts & Fabrics",
            "type":"Retail Goods"
        }
    ],
    "sg:phone":"+39 049 959 9711",
    "sg:postcode":"35024",
    "sg:province":"Padova",
    "wof:name":"Berto E.g. Industria Tessile S.p.a.",
    "wof:placetype":"venue"
},
  "geometry": {"coordinates":[11.8765888214,45.4095687866],"type":"Point"}
}