{
  "type": "Feature",
  "properties": {
    "addr:full":"14, Via Casonetto 36050 Pozzoleone Pozzoleone Vicenza 36050",
    "addr:postcode":"36050;36050",
    "addr:street":"Via Casonetto",
    "iso:country":"IT",
    "sg:address":"14, Via Casonetto 36050 Pozzoleone",
    "sg:city":"Pozzoleone",
    "sg:classifiers":[
        {
            "category":"Shopping",
            "subcategory":"Computers & Home Electronics",
            "type":"Retail Goods"
        }
    ],
    "sg:phone":"+39 0444 668065",
    "sg:postcode":"36050",
    "sg:province":"Vicenza",
    "sg:tags":[
        "electronic",
        "electrical",
        "equipment"
    ],
    "wof:name":"Multiproget S.r.l.",
    "wof:placetype":"venue"
},
  "geometry": {"coordinates":[11.681482,45.682503],"type":"Point"}
}