{
  "type": "Feature",
  "properties": {
    "iso:country":"IT",
    "sg:address":"63, Via Caselle 10040 Leini'",
    "sg:classifiers":[
        {
            "category":"Communications",
            "subcategory":"Newspaper",
            "type":"Services"
        }
    ],
    "sg:phone":"+39 011 997 4472",
    "sg:postcode":"10040",
    "sg:province":"Torino",
    "sg:tags":[
        "advertising"
    ],
    "wof:name":"Hitech Sistems (s.r.l.)",
    "wof:placetype":"venue"
},
  "geometry": {"coordinates":[7.655047,45.153961],"type":"Point"}
}