{
  "type": "Feature",
  "properties": {
    "iso:country":"IT",
    "sg:address":"20124 Milano",
    "sg:city":"Milano",
    "sg:orig_category":"Servizi Vari Di Interesse Pubblico",
    "sg:phone":"+39 02 2953 7328",
    "sg:postcode":"20124",
    "sg:province":"Milano",
    "wof:name":"Classica Group Srl",
    "wof:placetype":"venue"
},
  "geometry": {"coordinates":[9.208126,45.477474],"type":"Point"}
}