{
  "type": "Feature",
  "properties": {
    "iso:country":"IT",
    "sg:address":"20157 Milano",
    "sg:city":"Milano",
    "sg:orig_category":"Elettrotecnica Industriale, Prodotti E Apparecchiature. Elettrotecnica Professionale E Di Consumo",
    "sg:phone":"+39 02 3820 3373",
    "sg:postcode":"20157",
    "sg:province":"Milano",
    "wof:name":"Fiar",
    "wof:placetype":"venue"
},
  "geometry": {"coordinates":[9.182652,45.473198],"type":"Point"}
}