{
  "type": "Feature",
  "properties": {
    "addr:full":"22100 Como Como Como 22100",
    "addr:postcode":"22100;22100",
    "iso:country":"IT",
    "sg:address":"22100 Como",
    "sg:city":"Como",
    "sg:orig_category":"Disegni Per Tessuti",
    "sg:phone":"+39 031 242440",
    "sg:postcode":"22100",
    "sg:province":"Como",
    "wof:name":"Due Elle Snc",
    "wof:placetype":"venue"
},
  "geometry": {"coordinates":[9.078395,45.808186],"type":"Point"}
}