{
  "type": "Feature",
  "properties": {
    "addr:full":"16142 Genova Genova Genova 16142",
    "addr:postcode":"16142;16142",
    "iso:country":"IT",
    "sg:address":"16142 Genova",
    "sg:city":"Genova",
    "sg:orig_category":"Servizi Editoriali. Pubblicita', Marketing E Comunicazione",
    "sg:phone":"+39 010 53691",
    "sg:postcode":"16142",
    "sg:province":"Genova",
    "wof:name":"Corriere Mercantile - Gazzetta Del Luned\u00cc",
    "wof:placetype":"venue"
},
  "geometry": {"coordinates":[8.951192,44.406311],"type":"Point"}
}