{
  "type": "Feature",
  "properties": {
    "iso:country":"IT",
    "sg:address":"00187 Roma",
    "sg:city":"Roma",
    "sg:orig_category":"Articoli Da Regalo. Regalistica Aziendale",
    "sg:phone":"+39 06 4281 9384",
    "sg:postcode":"00187",
    "sg:province":"Roma",
    "wof:name":"Borraccetti Mauro",
    "wof:placetype":"venue"
},
  "geometry": {"coordinates":[12.497794,41.910076],"type":"Point"}
}