{
  "type": "Feature",
  "properties": {
    "iso:country":"IT",
    "sg:address":"20020 Busto Garolfo",
    "sg:city":"Busto Garolfo",
    "sg:orig_category":"Servizi Al Turismo. Trasporto Pubblico E Privato",
    "sg:phone":"+39 0331 569296",
    "sg:postcode":"20020",
    "sg:province":"Milano",
    "wof:name":"Societa' Di Navigazione Aurantium (s.p.a.)",
    "wof:placetype":"venue"
},
  "geometry": {"coordinates":[8.872903,45.548092],"type":"Point"}
}