{
  "type": "Feature",
  "properties": {
    "iso:country":"IT",
    "sg:address":"Via E. Mattei 46 31010 Maser",
    "sg:city":"Maser",
    "sg:classifiers":[
        {
            "category":"Personal",
            "subcategory":"Shoe Repair & Shine",
            "type":"Services"
        }
    ],
    "sg:phone":"+39 0423 925026",
    "sg:postcode":"31010",
    "sg:province":"Treviso",
    "sg:tags":[
        "protective",
        "safety",
        "boots"
    ],
    "sg:website":"www.cosmas.it",
    "wof:name":"Bittante Spa",
    "wof:placetype":"venue"
},
  "geometry": {"coordinates":[12.242072,45.666286],"type":"Point"}
}