{
  "type": "Feature",
  "properties": {
    "addr:full":"Via Mandolossa 110 25064 Gussago Gussago Brescia 25064",
    "addr:housenumber":"110",
    "addr:postcode":"25064;25064",
    "addr:street":"Via Mandolossa",
    "iso:country":"IT",
    "sg:address":"Via Mandolossa 110 25064 Gussago",
    "sg:city":"Gussago",
    "sg:orig_category":"High-pressure Valves",
    "sg:phone":"+39 030 373 0655",
    "sg:postcode":"25064",
    "sg:province":"Brescia",
    "wof:name":"Mantovani Spa",
    "wof:placetype":"venue"
},
  "geometry": {"coordinates":[10.155327,45.559109],"type":"Point"}
}