{
  "type": "Feature",
  "properties": {
    "addr:full":"Via Tonale 50 24026 Leffe Leffe Bergamo 24026",
    "addr:housenumber":"50",
    "addr:postcode":"24026;24026",
    "addr:street":"Via Tonale",
    "iso:country":"IT",
    "sg:address":"Via Tonale 50 24026 Leffe",
    "sg:city":"Leffe",
    "sg:orig_category":"Quilt Fabrics",
    "sg:phone":"+39 035 731172",
    "sg:postcode":"24026",
    "sg:province":"Bergamo",
    "sg:website":"www.texotessuti.com",
    "wof:name":"Texo Di Bosio Adriano",
    "wof:placetype":"venue"
},
  "geometry": {"coordinates":[9.877846,45.797749],"type":"Point"}
}