{
  "type": "Feature",
  "properties": {
    "iso:country":"IT",
    "sg:address":"70031 Andria",
    "sg:city":"Andria",
    "sg:orig_category":"Macchine, Impianti Ed Attrezzature Per Agricoltura E Zootecnia. Forniture Per Agricoltura E Zootecnia",
    "sg:phone":"+39 0883 545521",
    "sg:postcode":"70031",
    "sg:province":"Bari",
    "wof:name":"Agricola Pugliese Di Petruzzelli Nicola",
    "wof:placetype":"venue"
},
  "geometry": {"coordinates":[16.22868,41.138248],"type":"Point"}
}