{
  "type": "Feature",
  "properties": {
    "addr:full":"198, V. San Polo 35020 Sant'angelo Di Piove Di Sacco Padova 35020",
    "addr:housenumber":"198;polo",
    "addr:postcode":"35020;35020",
    "addr:street":"V. San",
    "iso:country":"IT",
    "sg:address":"198, V. San Polo 35020 Sant'angelo Di Piove Di Sacco",
    "sg:classifiers":[
        {
            "category":"Personal",
            "subcategory":"Shoe Repair & Shine",
            "type":"Services"
        }
    ],
    "sg:phone":"+39 049 979 0300",
    "sg:postcode":"35020",
    "sg:province":"Padova",
    "sg:tags":[
        "leather"
    ],
    "sg:website":"http://www.paginegialle.it/peldelfino",
    "wof:name":"Pelletterie Delfino",
    "wof:placetype":"venue"
},
  "geometry": {"coordinates":[11.997729,45.403011],"type":"Point"}
}