{
  "type": "Feature",
  "properties": {
    "iso:country":"IT",
    "sg:address":"04019 Terracina",
    "sg:city":"Terracina",
    "sg:orig_category":"Servizi Per Lo Sport E Il Tempo Libero. Alberghi E Strutture Extra Alberghiere",
    "sg:phone":"+39 0773 702521",
    "sg:postcode":"04019",
    "sg:province":"Latina",
    "sg:website":"http://www.ilgrappoloduva.it",
    "wof:name":"Agostino A Mare Srl",
    "wof:placetype":"venue"
},
  "geometry": {"coordinates":[13.257014,41.286736],"type":"Point"}
}