{
  "type": "Feature",
  "properties": {
    "iso:country":"IT",
    "sg:address":"2, V. A. Volta 23879 Verderio Inferiore",
    "sg:city":"Verderio Inferiore",
    "sg:classifiers":[
        {
            "category":"Manufacturing",
            "subcategory":"Tools & Machinery",
            "type":"Manufacturing & Wholesale Goods"
        }
    ],
    "sg:phone":"+39 39039514312",
    "sg:postcode":"23879",
    "sg:province":"Lecco",
    "sg:tags":[
        "environment",
        "equipment",
        "-"
    ],
    "sg:website":"http://www.progeco.com",
    "wof:name":"Progeco Ecologa Srl",
    "wof:placetype":"venue"
},
  "geometry": {"coordinates":[9.390071,45.852982],"type":"Point"}
}