{
  "type": "Feature",
  "properties": {
    "addr:full":"18/20, Viale Del Lavoro 24058 Romano Di Lombardia Romano di Lombardia Bergamo 24058",
    "addr:housenumber":"18 / 20",
    "addr:postcode":"24058;24058",
    "addr:street":"Viale Del Lavoro",
    "iso:country":"IT",
    "sg:address":"18/20, Viale Del Lavoro 24058 Romano Di Lombardia",
    "sg:city":"Romano di Lombardia",
    "sg:orig_category":"Miscellaneous Products",
    "sg:phone":"+39 036 390 3152",
    "sg:postcode":"24058",
    "sg:province":"Bergamo",
    "wof:name":"Manifacturing Artleva (soc.coop.r.l.)",
    "wof:placetype":"venue"
},
  "geometry": {"coordinates":[9.7407054901,45.5262794495],"type":"Point"}
}