{
  "type": "Feature",
  "properties": {
    "addr:full":"116, Strada Del Francese 10156 Torino Torino Torino 10156",
    "addr:postcode":"10156;10156",
    "addr:street":"Strada Del Francese",
    "iso:country":"IT",
    "sg:address":"116, Strada Del Francese 10156 Torino",
    "sg:city":"Torino",
    "sg:classifiers":[
        {
            "category":"Food & Beverages",
            "subcategory":"Groceries & Convenience Stores",
            "type":"Retail Goods"
        }
    ],
    "sg:phone":"+39 011 470 2802",
    "sg:postcode":"10156",
    "sg:province":"Torino",
    "sg:tags":[
        "product",
        "related"
    ],
    "wof:name":"Lipitalia (s.p.a.)",
    "wof:placetype":"venue"
},
  "geometry": {"coordinates":[7.6723217964,45.1343994141],"type":"Point"}
}