{
  "type": "Feature",
  "properties": {
    "addr:full":"59 Via Sannio, 00183 Roma Roma Roma 00183",
    "addr:postcode":"00183;00183",
    "addr:street":"Via Sannio",
    "iso:country":"IT",
    "sg:address":"59 Via Sannio, 00183 Roma",
    "sg:city":"Roma",
    "sg:classifiers":[
        {
            "category":"Banks & Credit Unions",
            "subcategory":"Financial Services",
            "type":"Services"
        }
    ],
    "sg:phone":"+39 39067009121",
    "sg:postcode":"00183",
    "sg:province":"Roma",
    "sg:tags":[
        "banking",
        "finance",
        "insurance"
    ],
    "wof:name":"Serfin E Mark (srl)",
    "wof:placetype":"venue"
},
  "geometry": {"coordinates":[12.5068731308,41.883731842],"type":"Point"}
}