{
  "type": "Feature",
  "properties": {
    "addr:full":"Via Trani Strada Statale 16 70051 Barletta Barletta Bari 70051",
    "addr:housenumber":"16",
    "addr:postcode":"70051;70051",
    "addr:street":"Via Trani Strada Statale",
    "iso:country":"IT",
    "sg:address":"Via Trani Strada Statale 16 70051 Barletta",
    "sg:city":"Barletta",
    "sg:orig_category":"Hoisiery Goods",
    "sg:phone":"+39 0883 534097",
    "sg:postcode":"70051",
    "sg:province":"Bari",
    "sg:website":"www.imapier.it",
    "wof:name":"Maglificio Imapier Di Campese Teodoro",
    "wof:placetype":"venue"
},
  "geometry": {"coordinates":[16.869291,41.126053],"type":"Point"}
}