{
  "type": "Feature",
  "properties": {
    "iso:country":"IT",
    "sg:address":"13017 Quarona",
    "sg:city":"Quarona",
    "sg:orig_category":"Valvole E Apparecchiature Di Misura",
    "sg:phone":"+39 0163 430117",
    "sg:postcode":"13017",
    "sg:province":"Vercelli",
    "sg:website":"http://www.valvomec.it",
    "wof:name":"Valvomec Srl",
    "wof:placetype":"venue"
},
  "geometry": {"coordinates":[8.249975,45.763233],"type":"Point"}
}