{
  "type": "Feature",
  "properties": {
    "addr:full":"Via Bonagge 26a 36065 Mussolente Mussolente Vicenza 36065",
    "addr:housenumber":"26a",
    "addr:postcode":"36065;36065",
    "addr:street":"Via Bonagge",
    "iso:country":"IT",
    "sg:address":"Via Bonagge 26a 36065 Mussolente",
    "sg:city":"Mussolente",
    "sg:classifiers":[
        {
            "category":"Restaurant",
            "type":"Food & Drink"
        }
    ],
    "sg:phone":"+39 0424 577117",
    "sg:postcode":"36065",
    "sg:province":"Vicenza",
    "sg:tags":[
        "pasta"
    ],
    "sg:website":"www.pastamontegrappa.com",
    "wof:name":"Industria Alimentare Ferraro Srl",
    "wof:placetype":"venue"
},
  "geometry": {"coordinates":[11.8096036911,45.7827301025],"type":"Point"}
}