{
  "type": "Feature",
  "properties": {
    "iso:country":"IT",
    "sg:address":"10080 Busano",
    "sg:city":"Busano",
    "sg:orig_category":"Macchine Ed Impianti Per Edilizia E Lavori Pubblici",
    "sg:phone":"+39 0124 48289",
    "sg:postcode":"10080",
    "sg:province":"Torino",
    "wof:name":"Grosso Giuseppe Romualdo",
    "wof:placetype":"venue"
},
  "geometry": {"coordinates":[7.65707,45.33313],"type":"Point"}
}