{
  "type": "Feature",
  "properties": {
    "iso:country":"IT",
    "sg:address":"33010 Venzone",
    "sg:city":"Venzone",
    "sg:orig_category":"Zootecnia E Pesca, Allevamento Piccoli Animali. Servizi Per Lo Sport E Il Tempo Libero",
    "sg:phone":"+39 0432 985282",
    "sg:postcode":"33010",
    "sg:province":"Udine",
    "wof:name":"Agriturismo Casali Scjs",
    "wof:placetype":"venue"
},
  "geometry": {"coordinates":[13.140486,46.332195],"type":"Point"}
}