{
  "type": "Feature",
  "properties": {
    "iso:country":"IT",
    "sg:address":"50136 Firenze",
    "sg:city":"Firenze",
    "sg:orig_category":"Arredo Cucina Ed Elettrodomestici",
    "sg:phone":"+39 055 691539",
    "sg:postcode":"50136",
    "sg:province":"Firenze",
    "wof:name":"Angelini Sas",
    "wof:placetype":"venue"
},
  "geometry": {"coordinates":[11.302567,43.767693],"type":"Point"}
}