{
  "type": "Feature",
  "properties": {
    "iso:country":"IT",
    "sg:address":"10053 Bussoleno",
    "sg:city":"Bussoleno",
    "sg:orig_category":"Macchine, Impianti E Forniture Per Industria Grafica, Cartaria E Cartotecnica. Automazione E Macchine Per Ufficio",
    "sg:phone":"+39 0122 640701",
    "sg:postcode":"10053",
    "sg:province":"Torino",
    "wof:name":"Copia Piu' Di Rossero Simonetta",
    "wof:placetype":"venue"
},
  "geometry": {"coordinates":[7.120077,45.126019],"type":"Point"}
}