{
  "type": "Feature",
  "properties": {
    "addr:full":"60022 Castelfidardo Castelfidardo Ancona 60022",
    "addr:postcode":"60022;60022",
    "iso:country":"IT",
    "sg:address":"60022 Castelfidardo",
    "sg:city":"Castelfidardo",
    "sg:orig_category":"Prodotti Chimici Di Base",
    "sg:phone":"+39 071 721 1048",
    "sg:postcode":"60022",
    "sg:province":"Ancona",
    "sg:website":"http://www.foridra.it",
    "wof:name":"Foridra Sas",
    "wof:placetype":"venue"
},
  "geometry": {"coordinates":[13.5596647263,43.4916000366],"type":"Point"}
}