{
  "type": "Feature",
  "properties": {
    "iso:country":"IT",
    "sg:address":"Localita' Novegno 32030 Arsie'",
    "sg:classifiers":[
        {
            "category":"Communications",
            "subcategory":"Television Station",
            "type":"Services"
        }
    ],
    "sg:phone":"+39 0439 578090",
    "sg:postcode":"32030",
    "sg:province":"Belluno",
    "sg:tags":[
        "audio-visual"
    ],
    "wof:name":"G.b. Elettronica Di Angelotti Dall'agnol Fulgenzio",
    "wof:placetype":"venue"
},
  "geometry": {"coordinates":[11.741777,45.971504],"type":"Point"}
}