{
  "type": "Feature",
  "properties": {
    "addr:full":"00192 Roma Roma Roma 00192",
    "addr:postcode":"00192;00192",
    "iso:country":"IT",
    "sg:address":"00192 Roma",
    "sg:city":"Roma",
    "sg:orig_category":"Argenterie - Vendita Al Dettaglio",
    "sg:phone":"+39 06 372 4300",
    "sg:postcode":"00192",
    "sg:province":"Roma",
    "wof:name":"Marzoli Claudio",
    "wof:placetype":"venue"
},
  "geometry": {"coordinates":[12.45714,41.90929],"type":"Point"}
}