{
  "type": "Feature",
  "properties": {
    "addr:full":"16128 Genova Genova Genova 16128",
    "addr:postcode":"16128;16128",
    "iso:country":"IT",
    "sg:address":"16128 Genova",
    "sg:city":"Genova",
    "sg:classifiers":[
        {
            "category":"Home & Garden",
            "subcategory":"Furniture",
            "type":"Retail Goods"
        }
    ],
    "sg:phone":"+39 010 248531",
    "sg:postcode":"16128",
    "sg:province":"Genova",
    "sg:tags":[
        "furnishing"
    ],
    "wof:name":"Scorza Gerolamo Spa",
    "wof:placetype":"venue"
},
  "geometry": {"coordinates":[9.1881484985,44.5234451294],"type":"Point"}
}