{
  "type": "Feature",
  "properties": {
    "iso:country":"IT",
    "sg:address":"Piazzale Roma 96; Piacenza",
    "sg:classifiers":[
        {
            "category":"Banks & Credit Unions",
            "subcategory":"Bank",
            "type":"Services"
        }
    ],
    "sg:phone":"+39 0523 330644",
    "wof:name":"Banca Monte Parma Spa",
    "wof:placetype":"venue"
},
  "geometry": {"coordinates":[9.699598,45.050919],"type":"Point"}
}