{
  "type": "Feature",
  "properties": {
    "iso:country":"IT",
    "sg:address":"61, V. Vigevano - San Martino Di Trecate 28068 Trecate",
    "sg:classifiers":[
        {
            "category":"Professional",
            "subcategory":"Engineering",
            "type":"Services"
        }
    ],
    "sg:phone":"+39 0321 789710",
    "sg:postcode":"28068",
    "sg:province":"Novara",
    "sg:tags":[
        "machine",
        "-",
        "mechanical"
    ],
    "sg:website":"http://www.paginegialle.it/macdermidsrl",
    "wof:name":"Macdermid Italiana Srl",
    "wof:placetype":"venue"
},
  "geometry": {"coordinates":[8.618671,45.445084],"type":"Point"}
}