{
  "type": "Feature",
  "properties": {
    "addr:full":"20127 Milano Milano Milano 20127",
    "addr:postcode":"20127;20127",
    "iso:country":"IT",
    "sg:address":"20127 Milano",
    "sg:city":"Milano",
    "sg:orig_category":"Prodotti Alimentari",
    "sg:phone":"+39 02 284 7868",
    "sg:postcode":"20127",
    "sg:province":"Milano",
    "wof:name":"Serafini Berenice Anna",
    "wof:placetype":"venue"
},
  "geometry": {"coordinates":[9.2210569382,45.500328064],"type":"Point"}
}