{
  "type": "Feature",
  "properties": {
    "addr:full":"Vle Europa, 19/21 06083 Bastia Umbra Bastia Perugia 06083",
    "addr:housenumber":"19 / 21",
    "addr:postcode":"06083;06083",
    "addr:street":"Vle Europa",
    "iso:country":"IT",
    "sg:address":"Vle Europa, 19/21 06083 Bastia Umbra",
    "sg:city":"Bastia",
    "sg:classifiers":[
        {
            "category":"Wholesale",
            "subcategory":"Motor Vehicles",
            "type":"Manufacturing & Wholesale Goods"
        }
    ],
    "sg:phone":"+39 075 801581",
    "sg:postcode":"06083",
    "sg:province":"Perugia",
    "sg:tags":[
        "tube",
        "inner",
        "tyre"
    ],
    "wof:name":"Carloni Srl",
    "wof:placetype":"venue"
},
  "geometry": {"coordinates":[12.516869,43.076248],"type":"Point"}
}