{
  "type": "Feature",
  "properties": {
    "iso:country":"IT",
    "sg:address":"11, Viale Italia 20020 Lainate",
    "sg:city":"Lainate",
    "sg:classifiers":[
        {
            "category":"Personal",
            "subcategory":"Shoe Repair & Shine",
            "type":"Services"
        }
    ],
    "sg:phone":"+39 39029370673",
    "sg:postcode":"20020",
    "sg:province":"Milano",
    "sg:tags":[
        "leather"
    ],
    "wof:name":"Fa.bo.ss. Srl",
    "wof:placetype":"venue"
},
  "geometry": {"coordinates":[9.041711,45.526695],"type":"Point"}
}