{
  "type": "Feature",
  "properties": {
    "iso:country":"IT",
    "sg:address":"20127 Milano",
    "sg:city":"Milano",
    "sg:orig_category":"Forniture Per Abbigliamento E Pelletterie",
    "sg:phone":"+39 0228861",
    "sg:postcode":"20127",
    "sg:province":"Milano",
    "wof:name":"Freudenberg (s.p.a.)",
    "wof:placetype":"venue"
},
  "geometry": {"coordinates":[9.2184505463,45.4916992188],"type":"Point"}
}