{
  "type": "Feature",
  "properties": {
    "iso:country":"IT",
    "sg:address":"03020 Pastena",
    "sg:city":"Pastena",
    "sg:orig_category":"Pubblica Amministrazione",
    "sg:phone":"+39 0776 546531",
    "sg:postcode":"03020",
    "sg:province":"Frosinone",
    "wof:name":"Comune Di Pastena",
    "wof:placetype":"venue"
},
  "geometry": {"coordinates":[13.4920549393,41.4682617188],"type":"Point"}
}