{
  "type": "Feature",
  "properties": {
    "iso:country":"IT",
    "sg:address":"43022 Montechiarugolo",
    "sg:city":"Montechiarugolo",
    "sg:classifiers":[
        {
            "category":"Home & Garden",
            "subcategory":"Furniture",
            "type":"Retail Goods"
        }
    ],
    "sg:phone":"+39 0521 681911",
    "sg:postcode":"43022",
    "sg:province":"Parma",
    "sg:tags":[
        "craft",
        "art",
        "furnishing",
        "artistic"
    ],
    "wof:name":"Graffiti Glass 2001",
    "wof:placetype":"venue"
},
  "geometry": {"coordinates":[10.3713493347,44.6931915283],"type":"Point"}
}