{
  "type": "Feature",
  "properties": {
    "addr:full":"20124 Milano Milano Milano 20124",
    "addr:postcode":"20124;20124",
    "iso:country":"IT",
    "sg:address":"20124 Milano",
    "sg:city":"Milano",
    "sg:orig_category":"Servizi Al Turismo. Servizi Ausiliari Per Il Trasporto",
    "sg:phone":"+39 02 693 9671",
    "sg:postcode":"20124",
    "sg:province":"Milano",
    "wof:name":"Gastaldi & C. Spa",
    "wof:placetype":"venue"
},
  "geometry": {"coordinates":[9.195617,45.4884],"type":"Point"}
}