{
  "type": "Feature",
  "properties": {
    "addr:full":"75100 La Martella La Martella Matera 75100",
    "addr:housenumber":"75100",
    "addr:postcode":"75100",
    "addr:street":"La Martella La",
    "iso:country":"IT",
    "sg:address":"75100 La Martella",
    "sg:city":"La Martella",
    "sg:orig_category":"Prodotti E Manufatti In Materie Plastiche. Materiali Edili",
    "sg:phone":"+39 0835 307728",
    "sg:postcode":"75100",
    "sg:province":"Matera",
    "wof:name":"Sofaline Srl",
    "wof:placetype":"venue"
},
  "geometry": {"coordinates":[16.5376720428,40.6608505249],"type":"Point"}
}