{
  "type": "Feature",
  "properties": {
    "iso:country":"IT",
    "sg:address":"00183 Roma",
    "sg:city":"Roma",
    "sg:orig_category":"Abbigliamento Esterno, Maglierie E Pelliccerie. Sport - Articoli E Forniture. Shopping",
    "sg:phone":"+39 06 7720 6605",
    "sg:postcode":"00183",
    "sg:province":"Roma",
    "wof:name":"Eliomoto",
    "wof:placetype":"venue"
},
  "geometry": {"coordinates":[12.505604,41.882484],"type":"Point"}
}