{
  "type": "Feature",
  "properties": {
    "addr:full":"20098 S.giuliano Milanese Milano 20098",
    "addr:postcode":"20098;20098",
    "addr:street":"S.Giuliano Milanese",
    "iso:country":"IT",
    "sg:address":"20098 S.giuliano Milanese",
    "sg:classifiers":[
        {
            "category":"Structure",
            "subcategory":"Shopping Mall",
            "type":"Public Place"
        }
    ],
    "sg:phone":"+39 02 984 8474",
    "sg:postcode":"20098",
    "sg:province":"Milano",
    "sg:tags":[
        "premises",
        "restaurants",
        "similar",
        "related",
        "restaurant"
    ],
    "sg:website":"http://www.backstagecatering.com",
    "wof:name":"Backstage Srl",
    "wof:placetype":"venue"
},
  "geometry": {"coordinates":[9.188141,45.463688],"type":"Point"}
}