{
  "type": "Feature",
  "properties": {
    "iso:country":"IT",
    "sg:address":"20122 Milano",
    "sg:city":"Milano",
    "sg:orig_category":"Servizi Per Aziende, Manifestazioni E Supporto Agli Scambi Commerciali. Ambasciate Ed Enti Internazionali",
    "sg:phone":"+39 02 805 6371",
    "sg:postcode":"20122",
    "sg:province":"Milano",
    "wof:name":"China Council For The Promotion Of International Trade",
    "wof:placetype":"venue"
},
  "geometry": {"coordinates":[9.193656,45.462666],"type":"Point"}
}