{
  "type": "Feature",
  "properties": {
    "iso:country":"IT",
    "sg:address":"00198 Roma",
    "sg:city":"Roma",
    "sg:orig_category":"Hobbistica",
    "sg:phone":"+39 06 855 3081",
    "sg:postcode":"00198",
    "sg:province":"Roma",
    "wof:name":"F.i.n. (s.r.l.)",
    "wof:placetype":"venue"
},
  "geometry": {"coordinates":[12.498978,41.920246],"type":"Point"}
}