{
  "type": "Feature",
  "properties": {
    "iso:country":"IT",
    "sg:address":"25030 Paratico",
    "sg:city":"Paratico",
    "sg:orig_category":"Servizi E Lavori Industria Della Gomma",
    "sg:phone":"+39 035 913627",
    "sg:postcode":"25030",
    "sg:province":"Brescia",
    "wof:name":"Girelli Gianalberto & C. (s.n.c.)",
    "wof:placetype":"venue"
},
  "geometry": {"coordinates":[10.210705,45.53701],"type":"Point"}
}