{
  "type": "Feature",
  "properties": {
    "iso:country":"IT",
    "sg:address":"8, Via Badie 24060 Castelli Calepio",
    "sg:city":"Castelli Calepio",
    "sg:classifiers":[
        {
            "category":"Shopping",
            "subcategory":"Clothing, Apparel, & Fashions",
            "type":"Retail Goods"
        }
    ],
    "sg:phone":"+39 030 743 8830",
    "sg:postcode":"24060",
    "sg:province":"Bergamo",
    "sg:tags":[
        "clothing",
        "accessory"
    ],
    "wof:name":"Bottonificio Paris E G. S.r.l.",
    "wof:placetype":"venue"
},
  "geometry": {"coordinates":[9.894086,45.61824],"type":"Point"}
}