{
  "type": "Feature",
  "properties": {
    "addr:full":"12, Via Della Tecnica 20041 Agrate Brianza Agrate Brianza Milano 20041",
    "addr:postcode":"20041;20041",
    "addr:street":"Via Della Tecnica",
    "iso:country":"IT",
    "sg:address":"12, Via Della Tecnica 20041 Agrate Brianza",
    "sg:city":"Agrate Brianza",
    "sg:classifiers":[
        {
            "category":"Parking",
            "subcategory":"Lot",
            "type":"Transportation"
        }
    ],
    "sg:phone":"+39 39039650704",
    "sg:postcode":"20041",
    "sg:province":"Milano",
    "sg:tags":[
        "transport",
        "road"
    ],
    "wof:name":"Donnanno",
    "wof:placetype":"venue"
},
  "geometry": {"coordinates":[9.359189,45.564411],"type":"Point"}
}