{
  "type": "Feature",
  "properties": {
    "iso:country":"IT",
    "sg:address":"Via Kennedy 8-10; Pzzo 16; Quarto; Naples; 80010",
    "sg:city":"Quarto",
    "sg:classifiers":[
        {
            "category":"Travel",
            "subcategory":"Travel Agent",
            "type":"Entertainment"
        }
    ],
    "sg:phone":"+39 390 818 7683",
    "sg:postcode":"80010",
    "sg:province":"Napoli",
    "sg:website":"103connection.it",
    "wof:name":"103 Connection Travel Service",
    "wof:placetype":"venue"
},
  "geometry": {"coordinates":[14.140795,40.88147],"type":"Point"}
}