{
  "type": "Feature",
  "properties": {
    "iso:country":"IT",
    "sg:address":"405, Via S. Paolo 59100 Prato",
    "sg:city":"Prato",
    "sg:classifiers":[
        {
            "category":"Professional",
            "subcategory":"Engineering",
            "type":"Services"
        }
    ],
    "sg:phone":"+39 39057428218",
    "sg:postcode":"59100",
    "sg:province":"Prato",
    "sg:tags":[
        "machine",
        "-",
        "mechanical"
    ],
    "wof:name":"L.a.i.p. Srl",
    "wof:placetype":"venue"
},
  "geometry": {"coordinates":[11.093779,43.90451],"type":"Point"}
}