{
  "type": "Feature",
  "properties": {
    "iso:country":"IT",
    "sg:address":"21040 Carnago",
    "sg:city":"Carnago",
    "sg:orig_category":"Utensili Meccanici E Materiali",
    "sg:phone":"+39 0331 990411",
    "sg:postcode":"21040",
    "sg:province":"Varese",
    "wof:name":"Electronics Futura Srl",
    "wof:placetype":"venue"
},
  "geometry": {"coordinates":[8.843806,45.714996],"type":"Point"}
}