{
  "type": "Feature",
  "properties": {
    "iso:country":"IT",
    "sg:address":"16, Via Degli Artigiani 22021 Bellagio",
    "sg:city":"Bellagio",
    "sg:classifiers":[
        {
            "category":"Manufacturing",
            "subcategory":"Glass & Minerals",
            "type":"Manufacturing & Wholesale Goods"
        }
    ],
    "sg:phone":"+39 39031951115",
    "sg:postcode":"22021",
    "sg:province":"Como",
    "wof:name":"Mortelmans Srl",
    "wof:placetype":"venue"
},
  "geometry": {"coordinates":[9.264864,45.999477],"type":"Point"}
}