{
  "type": "Feature",
  "properties": {
    "iso:country":"IT",
    "sg:address":"23900 Lecco",
    "sg:city":"Lecco",
    "sg:orig_category":"Apparecchiature Ed Attrezzature Meccaniche",
    "sg:phone":"+39 0341 286868",
    "sg:postcode":"23900",
    "sg:province":"Lecco",
    "wof:name":"Ferramenta Utensileria Lecchese Di Crippa E C. Snc",
    "wof:placetype":"venue"
},
  "geometry": {"coordinates":[9.397904,45.846413],"type":"Point"}
}