{
  "type": "Feature",
  "properties": {
    "addr:full":"1, Piazza Jolando Nuzzi 70029 Santeramo In Colle Santeramo in Colle Bari 70029",
    "addr:postcode":"70029;70029",
    "addr:street":"Piazza Jolando Nuzzi",
    "iso:country":"IT",
    "sg:address":"1, Piazza Jolando Nuzzi 70029 Santeramo In Colle",
    "sg:city":"Santeramo in Colle",
    "sg:classifiers":[
        {
            "category":"Travel",
            "subcategory":"Travel Agent",
            "type":"Entertainment"
        }
    ],
    "sg:phone":"+39 080 303 6797",
    "sg:postcode":"70029",
    "sg:province":"Bari",
    "sg:tags":[
        "business"
    ],
    "wof:name":"Il Poligono Srl",
    "wof:placetype":"venue"
},
  "geometry": {"coordinates":[16.752533,40.785954],"type":"Point"}
}