{
  "type": "Feature",
  "properties": {
    "addr:full":"84010 Maiori Maiori Salerno 84010",
    "addr:postcode":"84010;maiori;84010",
    "addr:street":"Salerno",
    "iso:country":"IT",
    "sg:address":"84010 Maiori",
    "sg:city":"Maiori",
    "sg:orig_category":"Impiantistica E Prodotti Tecnologici Per Edilizia",
    "sg:phone":"+39 089 853637",
    "sg:postcode":"84010",
    "sg:province":"Salerno",
    "wof:name":"Milito Pagliara Leopoldo",
    "wof:placetype":"venue"
},
  "geometry": {"coordinates":[14.64233,40.64822],"type":"Point"}
}