{
  "type": "Feature",
  "properties": {
    "iso:country":"IT",
    "sg:address":"30174 Venezia",
    "sg:city":"Venezia",
    "sg:orig_category":"Studi E Consulenze Tecniche E Industriali. Servizi E Lavori Per Edilizia E Lavori Pubblici. Professionisti - Studi E Servizi Ed Associazioni Di Interesse Aziendale",
    "sg:phone":"+39 041 943343",
    "sg:postcode":"30174",
    "sg:province":"Venezia",
    "wof:name":"Facchinetto Arch. Mario",
    "wof:placetype":"venue"
},
  "geometry": {"coordinates":[12.212565,45.505871],"type":"Point"}
}