{
  "type": "Feature",
  "properties": {
    "addr:full":"Via Lombardia, 24/26 20098 Sesto Ulteriano Sesto Ulteriano Milano 20098",
    "addr:housenumber":"24 / 26",
    "addr:postcode":"20098;20098",
    "addr:street":"Via Lombardia",
    "iso:country":"IT",
    "sg:address":"Via Lombardia, 24/26 20098 Sesto Ulteriano",
    "sg:city":"Sesto Ulteriano",
    "sg:classifiers":[
        {
            "category":"Manufacturing",
            "subcategory":"Food",
            "type":"Manufacturing & Wholesale Goods"
        }
    ],
    "sg:phone":"+39 02 988 0379",
    "sg:postcode":"20098",
    "sg:province":"Milano",
    "sg:tags":[
        "packaging",
        "retailer"
    ],
    "sg:website":"www.facover.com",
    "wof:name":"Facover Srl",
    "wof:placetype":"venue"
},
  "geometry": {"coordinates":[9.2537899017,45.3970489502],"type":"Point"}
}