{
  "type": "Feature",
  "properties": {
    "iso:country":"IT",
    "sg:address":"10098 Rivoli",
    "sg:city":"Rivoli",
    "sg:orig_category":"Apparecchiature Ed Attrezzature Meccaniche",
    "sg:phone":"+39 011 958 4978",
    "sg:postcode":"10098",
    "sg:province":"Torino",
    "wof:name":"Reco S.a.s.",
    "wof:placetype":"venue"
},
  "geometry": {"coordinates":[7.501947,45.072018],"type":"Point"}
}