{
  "type": "Feature",
  "properties": {
    "iso:country":"IT",
    "sg:address":"4, V. Bosco 35040 Santa Margherita D'adige",
    "sg:classifiers":[
        {
            "category":"Home & Garden",
            "subcategory":"Home Furnishings",
            "type":"Retail Goods"
        }
    ],
    "sg:phone":"+39 0429 840204",
    "sg:postcode":"35040",
    "sg:province":"Padova",
    "sg:tags":[
        "household"
    ],
    "sg:website":"http://www.paginegialle.it/mobilificiobf",
    "wof:name":"B.f. Srl",
    "wof:placetype":"venue"
},
  "geometry": {"coordinates":[11.551992,45.211933],"type":"Point"}
}