{
  "type": "Feature",
  "properties": {
    "iso:country":"IT",
    "sg:address":"00186 Roma",
    "sg:city":"Roma",
    "sg:orig_category":"Orologerie",
    "sg:phone":"+39 06 686 4716",
    "sg:postcode":"00186",
    "sg:province":"Roma",
    "wof:name":"G.i.s. Srl",
    "wof:placetype":"venue"
},
  "geometry": {"coordinates":[12.472588,41.900497],"type":"Point"}
}