{
  "type": "Feature",
  "properties": {
    "addr:full":"Via Gastone Sozzi 14 56029 Santa Croce Sull'arno Pisa 56029",
    "addr:housenumber":"14",
    "addr:postcode":"56029;56029",
    "addr:street":"Via Gastone Sozzi",
    "iso:country":"IT",
    "sg:address":"Via Gastone Sozzi 14 56029 Santa Croce Sull'arno",
    "sg:classifiers":[
        {
            "category":"Home & Garden",
            "subcategory":"Carpets & Floor Coverings",
            "type":"Retail Goods"
        }
    ],
    "sg:phone":"+39 0571 360530",
    "sg:postcode":"56029",
    "sg:province":"Pisa",
    "sg:tags":[
        "animal",
        "skin"
    ],
    "wof:name":"Atlas Srl",
    "wof:placetype":"venue"
},
  "geometry": {"coordinates":[10.774914,43.715954],"type":"Point"}
}