{
  "type": "Feature",
  "properties": {
    "addr:full":"27025 Gambolo' Pavia 27025",
    "addr:postcode":"27025;27025",
    "addr:street":"Gambolo ' Pavia",
    "iso:country":"IT",
    "sg:address":"27025 Gambolo'",
    "sg:orig_category":"Laminati Plastici - Commercio",
    "sg:phone":"+39 0381 937111",
    "sg:postcode":"27025",
    "sg:province":"Pavia",
    "wof:name":"Pannelli Plastici Soc. Coop Arl",
    "wof:placetype":"venue"
},
  "geometry": {"coordinates":[8.854809,45.266712],"type":"Point"}
}