{
  "type": "Feature",
  "properties": {
    "addr:full":"Via Raffaello 29 42100 Reggio Emilia Reggio Nell'Emilia 42100",
    "addr:housenumber":"29",
    "addr:postcode":"42100;42100",
    "addr:street":"Via Raffaello",
    "iso:country":"IT",
    "sg:address":"Via Raffaello 29 42100 Reggio Emilia",
    "sg:orig_category":"Mounting Components For Metal Construction",
    "sg:phone":"+39 0522 929411",
    "sg:postcode":"42100",
    "sg:province":"Reggio Nell'Emilia",
    "sg:website":"www.franzini.it",
    "wof:name":"Franzini Annibale S.p.a.",
    "wof:placetype":"venue"
},
  "geometry": {"coordinates":[10.6529111862,44.7363204956],"type":"Point"}
}