{
  "type": "Feature",
  "properties": {
    "addr:full":"02100 Rieti Rieti Rieti 02100",
    "addr:postcode":"02100;02100",
    "iso:country":"IT",
    "sg:address":"02100 Rieti",
    "sg:city":"Rieti",
    "sg:orig_category":"Forniture Per Uffici. Arredi Ed Attrezzature Per Uffici. Automazione E Macchine Per Ufficio",
    "sg:phone":"+39 0746 271838",
    "sg:postcode":"02100",
    "sg:province":"Rieti",
    "wof:name":"Omnium Srl",
    "wof:placetype":"venue"
},
  "geometry": {"coordinates":[12.8575601578,42.399810791],"type":"Point"}
}