{
  "type": "Feature",
  "properties": {
    "iso:country":"IT",
    "sg:address":"19, Via Trieste 63020 Ponzano Di Fermo",
    "sg:city":"Ponzano di Fermo",
    "sg:classifiers":[
        {
            "category":"Personal",
            "subcategory":"Shoe Repair & Shine",
            "type":"Services"
        }
    ],
    "sg:phone":"+39 0734 631961",
    "sg:postcode":"63020",
    "sg:province":"Ascoli Piceno",
    "sg:tags":[
        "leather"
    ],
    "wof:name":"Mg3 Srl",
    "wof:placetype":"venue"
},
  "geometry": {"coordinates":[13.625478,43.133137],"type":"Point"}
}