{
  "type": "Feature",
  "properties": {
    "iso:country":"IT",
    "sg:address":"104, Via De Gasperi 20017 Rho",
    "sg:city":"Rho",
    "sg:classifiers":[
        {
            "category":"Shopping",
            "type":"Retail Goods"
        }
    ],
    "sg:phone":"+39 02 9390 0171",
    "sg:postcode":"20017",
    "sg:province":"Milano",
    "sg:tags":[
        "finished",
        "-",
        "metallic"
    ],
    "wof:name":"Dimo (spa)",
    "wof:placetype":"venue"
},
  "geometry": {"coordinates":[9.0823812485,45.5285110474],"type":"Point"}
}