{
  "type": "Feature",
  "properties": {
    "iso:country":"IT",
    "sg:address":"25125 Brescia",
    "sg:city":"Brescia",
    "sg:orig_category":"Filati E Materie Prime Tessili",
    "sg:phone":"+39 030 347289",
    "sg:postcode":"25125",
    "sg:province":"Brescia",
    "wof:name":"Bertagna Filati (s.r.l.)",
    "wof:placetype":"venue"
},
  "geometry": {"coordinates":[10.1874723434,45.5156669617],"type":"Point"}
}