{
  "type": "Feature",
  "properties": {
    "iso:country":"IT",
    "sg:address":"31, Via Stelvio 20026 Novate Milanese",
    "sg:city":"Novate Milanese",
    "sg:classifiers":[
        {
            "category":"Shopping",
            "subcategory":"Crafts & Fabrics",
            "type":"Retail Goods"
        }
    ],
    "sg:phone":"+39 39023541642",
    "sg:postcode":"20026",
    "sg:province":"Milano",
    "sg:tags":[
        "ceramic"
    ],
    "wof:name":"La Boutique Della Piastrella",
    "wof:placetype":"venue"
},
  "geometry": {"coordinates":[9.13408,45.538002],"type":"Point"}
}