{
  "type": "Feature",
  "properties": {
    "iso:country":"IT",
    "sg:address":"13, Via Mafalda Di Savoia 70010 Locorotondo",
    "sg:city":"Locorotondo",
    "sg:classifiers":[
        {
            "category":"Real Estate",
            "subcategory":"Architect",
            "type":"Services"
        }
    ],
    "sg:phone":"+39 080 431 7291",
    "sg:postcode":"70010",
    "sg:province":"Bari",
    "sg:tags":[
        "textile",
        "clothing"
    ],
    "wof:name":"Edo's Company Srl Soc. Unipersonale",
    "wof:placetype":"venue"
},
  "geometry": {"coordinates":[17.327576,40.758812],"type":"Point"}
}