{
  "type": "Feature",
  "properties": {
    "addr:full":"95124 Catania Catania Catania 95124",
    "addr:postcode":"95124;95124",
    "iso:country":"IT",
    "sg:address":"95124 Catania",
    "sg:city":"Catania",
    "sg:classifiers":[
        {
            "category":"Health Services",
            "subcategory":"Health Practitioner",
            "type":"Services"
        }
    ],
    "sg:phone":"+39 095 320718",
    "sg:postcode":"95124",
    "sg:province":"Catania",
    "sg:tags":[
        "medici"
    ],
    "wof:name":"Mazzeo Pietro",
    "wof:placetype":"venue"
},
  "geometry": {"coordinates":[15.079448,37.508625],"type":"Point"}
}