{
  "type": "Feature",
  "properties": {
    "iso:country":"IT",
    "sg:address":"11, Via I Maggio 22073 Fino Mornasco",
    "sg:city":"Fino Mornasco",
    "sg:classifiers":[
        {
            "category":"Professional",
            "subcategory":"Engineering",
            "type":"Services"
        }
    ],
    "sg:phone":"+39 39031880164",
    "sg:postcode":"22073",
    "sg:province":"Como",
    "sg:tags":[
        "machine",
        "-",
        "mechanical"
    ],
    "wof:name":"Vimco (s.n.c.)",
    "wof:placetype":"venue"
},
  "geometry": {"coordinates":[9.075201,45.78492],"type":"Point"}
}