{
  "type": "Feature",
  "properties": {
    "iso:country":"IT",
    "sg:address":"95019 Zafferana Etnea",
    "sg:city":"Zafferana Etnea",
    "sg:orig_category":"Prodotti Alimentari",
    "sg:phone":"+39 095 708 3849",
    "sg:postcode":"95019",
    "sg:province":"Catania",
    "wof:name":"Co.a.si. Consorzio Apicoltori Di Sicilia",
    "wof:placetype":"venue"
},
  "geometry": {"coordinates":[15.0674314499,37.7103843689],"type":"Point"}
}