{
  "type": "Feature",
  "properties": {
    "addr:full":"60127 Ancona Ancona Ancona 60127",
    "addr:postcode":"60127;60127",
    "iso:country":"IT",
    "sg:address":"60127 Ancona",
    "sg:city":"Ancona",
    "sg:orig_category":"Elettrotecnica Industriale, Prodotti E Apparecchiature",
    "sg:phone":"+39 071 872682",
    "sg:postcode":"60127",
    "sg:province":"Ancona",
    "wof:name":"Delta Impianti Snc",
    "wof:placetype":"venue"
},
  "geometry": {"coordinates":[13.502151,43.597858],"type":"Point"}
}