{
  "type": "Feature",
  "properties": {
    "addr:full":"37036 San Martino Buon Albergo San Martino Buon Albergo Verona 37036",
    "addr:housenumber":"37036",
    "addr:postcode":"buon albergo;37036",
    "iso:country":"IT",
    "sg:address":"37036 San Martino Buon Albergo",
    "sg:city":"San Martino Buon Albergo",
    "sg:orig_category":"Prodotti Alimentari",
    "sg:phone":"+39 045 878 0495",
    "sg:postcode":"37036",
    "sg:province":"Verona",
    "wof:name":"Molino Mercanti Snc",
    "wof:placetype":"venue"
},
  "geometry": {"coordinates":[11.0916070938,45.4205207825],"type":"Point"}
}