{
  "type": "Feature",
  "properties": {
    "iso:country":"IT",
    "sg:address":"Via Verona, 15 San Floriano Olmi 31048 San Biagio Di Callalta",
    "sg:city":"Olmi",
    "sg:classifiers":[
        {
            "category":"Wholesale",
            "subcategory":"Vending Machines",
            "type":"Manufacturing & Wholesale Goods"
        }
    ],
    "sg:phone":"+39 0422 899071",
    "sg:postcode":"31048",
    "sg:province":"Treviso",
    "sg:tags":[
        "crushing",
        "installation"
    ],
    "wof:name":"Omt Srl",
    "wof:placetype":"venue"
},
  "geometry": {"coordinates":[12.323121,45.673988],"type":"Point"}
}