{
  "type": "Feature",
  "properties": {
    "addr:full":"40057 Granarolo Dell'emilia Bologna 40057",
    "addr:postcode":"40057;40057",
    "iso:country":"IT",
    "sg:address":"40057 Granarolo Dell'emilia",
    "sg:orig_category":"Prodotti Chimici Di Base",
    "sg:phone":"+39 051 766469",
    "sg:postcode":"40057",
    "sg:province":"Bologna",
    "wof:name":"Sutoria Srl",
    "wof:placetype":"venue"
},
  "geometry": {"coordinates":[11.3936786652,44.542930603],"type":"Point"}
}