{
  "type": "Feature",
  "properties": {
    "iso:country":"IT",
    "sg:address":"Contrada Barriera 95032 Piano Tavola",
    "sg:city":"Piano tavola",
    "sg:classifiers":[
        {
            "category":"Building & Trades",
            "subcategory":"Pest Control",
            "type":"Services"
        }
    ],
    "sg:phone":"+39 095 713 1903",
    "sg:postcode":"95032",
    "sg:province":"Catania",
    "sg:tags":[
        "insecticide"
    ],
    "wof:name":"Elf Atochem Agri Italia Srl",
    "wof:placetype":"venue"
},
  "geometry": {"coordinates":[14.974471,37.537685],"type":"Point"}
}