{
  "type": "Feature",
  "properties": {
    "iso:country":"IT",
    "sg:address":"31025 Santa Lucia Di Piave",
    "sg:city":"Santa Lucia di Piave",
    "sg:orig_category":"Arredo Cucina Ed Elettrodomestici. Elettrodomestici",
    "sg:phone":"+39 0438 738669",
    "sg:postcode":"31025",
    "sg:province":"Treviso",
    "wof:name":"Cadel S.r.l.",
    "wof:placetype":"venue"
},
  "geometry": {"coordinates":[12.2646694183,45.8472557068],"type":"Point"}
}