{
  "type": "Feature",
  "properties": {
    "iso:country":"IT",
    "sg:address":"Localita' S.felice 53019 Castelnuovo Berardenga",
    "sg:city":"Castelnuovo Berardenga",
    "sg:classifiers":[
        {
            "category":"Food & Beverages",
            "subcategory":"Groceries & Convenience Stores",
            "type":"Retail Goods"
        }
    ],
    "sg:phone":"+39 0577 359387",
    "sg:postcode":"53019",
    "sg:province":"Siena",
    "sg:tags":[
        "drink"
    ],
    "wof:name":"Agricola San Felice S.p.a.",
    "wof:placetype":"venue"
},
  "geometry": {"coordinates":[11.446403,43.36618],"type":"Point"}
}