{
  "type": "Feature",
  "properties": {
    "iso:country":"IT",
    "sg:address":"Via Montefeltresca 6 61023 Macerata Feltria",
    "sg:city":"Macerata Feltria",
    "sg:classifiers":[
        {
            "category":"Building & Trades",
            "subcategory":"Electrical",
            "type":"Services"
        }
    ],
    "sg:phone":"+39 0722 74449",
    "sg:postcode":"61023",
    "sg:province":"Pesaro E Urbino",
    "sg:tags":[
        "plants",
        "plant",
        "industrial",
        "buildings",
        "construction"
    ],
    "wof:name":"Pascucci & Vannucci Spa",
    "wof:placetype":"venue"
},
  "geometry": {"coordinates":[12.369908,43.806263],"type":"Point"}
}