{
  "type": "Feature",
  "properties": {
    "iso:country":"IT",
    "sg:address":"37026 Pescantina",
    "sg:city":"Pescantina",
    "sg:orig_category":"Prodotti Vari In Metallo",
    "sg:phone":"+39 045 715 0600",
    "sg:postcode":"37026",
    "sg:province":"Verona",
    "wof:name":"Adami Siderurgica Srl",
    "wof:placetype":"venue"
},
  "geometry": {"coordinates":[10.9086732864,45.4825592041],"type":"Point"}
}