{
  "type": "Feature",
  "properties": {
    "addr:full":"20121 Milano Milano Milano 20121",
    "addr:postcode":"20121;20121",
    "iso:country":"IT",
    "sg:address":"20121 Milano",
    "sg:city":"Milano",
    "sg:orig_category":"Pubblicita', Marketing E Comunicazione",
    "sg:phone":"+39 02 657 5811",
    "sg:postcode":"20121",
    "sg:province":"Milano",
    "wof:name":"Luisa Rumor Sas",
    "wof:placetype":"venue"
},
  "geometry": {"coordinates":[9.1865119934,45.4791679382],"type":"Point"}
}