{
  "type": "Feature",
  "properties": {
    "iso:country":"IT",
    "sg:address":"00128 Roma",
    "sg:city":"Roma",
    "sg:orig_category":"Materiali Semilavorati Metallici",
    "sg:phone":"+39 06 507 0917",
    "sg:postcode":"00128",
    "sg:province":"Roma",
    "wof:name":"Ve.co. Snc.",
    "wof:placetype":"venue"
},
  "geometry": {"coordinates":[12.461414,41.787281],"type":"Point"}
}