{
  "type": "Feature",
  "properties": {
    "iso:country":"IT",
    "sg:address":"10, Via Rosaspina 47900 Rimini",
    "sg:city":"Rimini",
    "sg:classifiers":[
        {
            "category":"Communications",
            "subcategory":"Newspaper",
            "type":"Services"
        }
    ],
    "sg:phone":"+39 0541 780122",
    "sg:postcode":"47900",
    "sg:province":"Rimini",
    "sg:tags":[
        "advertising"
    ],
    "wof:name":"Gambarini & Muti S.r.l.",
    "wof:placetype":"venue"
},
  "geometry": {"coordinates":[12.566462,44.052818],"type":"Point"}
}