{
  "type": "Feature",
  "properties": {
    "addr:full":"85010 Guardia Perticara Guardia Perticara Potenza 85010",
    "addr:postcode":"85010;85010",
    "addr:street":"Perticara",
    "iso:country":"IT",
    "sg:address":"85010 Guardia Perticara",
    "sg:city":"Guardia Perticara",
    "sg:orig_category":"Agriturismo",
    "sg:phone":"+39 0971 965248",
    "sg:postcode":"85010",
    "sg:province":"Potenza",
    "wof:name":"Azienda Agrituristica Fornabaio Raffaele",
    "wof:placetype":"venue"
},
  "geometry": {"coordinates":[16.100403,40.358292],"type":"Point"}
}