{
  "type": "Feature",
  "properties": {
    "iso:country":"IT",
    "sg:address":"Via De Gasperi 4 22072 Cermenate",
    "sg:city":"Cermenate",
    "sg:classifiers":[
        {
            "category":"Professional",
            "subcategory":"Printing & Photocopies",
            "type":"Services"
        }
    ],
    "sg:phone":"+39 031 724111",
    "sg:postcode":"22072",
    "sg:province":"Como",
    "sg:tags":[
        "agency"
    ],
    "sg:website":"www.masperofontana.it",
    "wof:name":"Arti Grafiche Maspero Fontana & C. S P.a.",
    "wof:placetype":"venue"
},
  "geometry": {"coordinates":[9.1309242249,45.7485275269],"type":"Point"}
}