{
  "type": "Feature",
  "properties": {
    "iso:country":"IT",
    "sg:address":"102, Via Galoppat 33087 Pasiano Di Pordenone",
    "sg:city":"Pasiano",
    "sg:classifiers":[
        {
            "category":"Home & Garden",
            "subcategory":"Home Furnishings",
            "type":"Retail Goods"
        }
    ],
    "sg:phone":"+39 0434 625191",
    "sg:postcode":"33087",
    "sg:province":"Pordenone",
    "sg:tags":[
        "household"
    ],
    "wof:name":"R.c.r. S.r.l.",
    "wof:placetype":"venue"
},
  "geometry": {"coordinates":[12.619761,45.870102],"type":"Point"}
}