{
  "type": "Feature",
  "properties": {
    "addr:full":"1, Via Binasco 20080 Casarile Casarile Milano 20080",
    "addr:postcode":"20080;20080",
    "addr:street":"Via Binasco",
    "iso:country":"IT",
    "sg:address":"1, Via Binasco 20080 Casarile",
    "sg:city":"Casarile",
    "sg:classifiers":[
        {
            "category":"Shopping",
            "type":"Retail Goods"
        }
    ],
    "sg:phone":"+39 39029055649",
    "sg:postcode":"20080",
    "sg:province":"Milano",
    "sg:tags":[
        "finished",
        "-",
        "metallic"
    ],
    "wof:name":"I.l.l.c.a. (s.r.l.)",
    "wof:placetype":"venue"
},
  "geometry": {"coordinates":[9.1068849564,45.3146018982],"type":"Point"}
}