{
  "type": "Feature",
  "properties": {
    "iso:country":"IT",
    "sg:address":"109, V. Birmania 58100 Grosseto",
    "sg:city":"Grosseto",
    "sg:classifiers":[
        {
            "category":"Wholesale",
            "subcategory":"Machinery & Supplies",
            "type":"Manufacturing & Wholesale Goods"
        }
    ],
    "sg:phone":"+39 0564 455595",
    "sg:postcode":"58100",
    "sg:province":"Grosseto",
    "sg:tags":[
        "equipment",
        "precision"
    ],
    "sg:website":"http://www.faenzi.com",
    "wof:name":"Faenzi Srl",
    "wof:placetype":"venue"
},
  "geometry": {"coordinates":[11.1026887894,42.7860984802],"type":"Point"}
}