{
  "type": "Feature",
  "properties": {
    "addr:full":"23, Via Per Turbigo 20022 Castano Primo Castano Primo Milano 20022",
    "addr:postcode":"20022;20022",
    "addr:street":"Via Per Turbigo",
    "iso:country":"IT",
    "sg:address":"23, Via Per Turbigo 20022 Castano Primo",
    "sg:city":"Castano Primo",
    "sg:classifiers":[
        {
            "category":"Manufacturing",
            "subcategory":"Metals",
            "type":"Manufacturing & Wholesale Goods"
        }
    ],
    "sg:phone":"+39 0331 880603",
    "sg:postcode":"20022",
    "sg:province":"Milano",
    "sg:tags":[
        "processing"
    ],
    "wof:name":"Remor Di Renato Morelli & C. (s.n.c.)",
    "wof:placetype":"venue"
},
  "geometry": {"coordinates":[8.7632474899,45.5442581177],"type":"Point"}
}