{
  "type": "Feature",
  "properties": {
    "iso:country":"IT",
    "sg:address":"00162 Roma",
    "sg:city":"Roma",
    "sg:orig_category":"Ospedali E Servizi Sanitari",
    "sg:phone":"+39 06 4429 1180",
    "sg:postcode":"00162",
    "sg:province":"Roma",
    "wof:name":"Fedele Dr. Cosimo",
    "wof:placetype":"venue"
},
  "geometry": {"coordinates":[12.521742,41.914288],"type":"Point"}
}