{
  "type": "Feature",
  "properties": {
    "addr:full":"95128 Catania Catania Catania 95128",
    "addr:postcode":"95128;95128",
    "iso:country":"IT",
    "sg:address":"95128 Catania",
    "sg:city":"Catania",
    "sg:orig_category":"Assicurazioni E Servizi Assicurativi",
    "sg:phone":"+39 095 446190",
    "sg:postcode":"95128",
    "sg:province":"Catania",
    "wof:name":"Gruppo Ferri Broker",
    "wof:placetype":"venue"
},
  "geometry": {"coordinates":[15.091994,37.516262],"type":"Point"}
}