{
  "type": "Feature",
  "properties": {
    "iso:country":"IT",
    "sg:address":"53026 Pienza",
    "sg:city":"Pienza",
    "sg:classifiers":[
        {
            "category":"Restaurant",
            "type":"Food & Drink"
        }
    ],
    "sg:phone":"+39 0578 755050",
    "sg:postcode":"53026",
    "sg:province":"Siena",
    "sg:tags":[
        "auxiliary",
        "entertainment",
        "premises",
        "related",
        "catering",
        "similar",
        "public",
        "restaurants"
    ],
    "sg:website":"http://www.tavernadimoranda.it",
    "wof:name":"Taverna Di Moranda",
    "wof:placetype":"venue"
},
  "geometry": {"coordinates":[11.332772,43.322529],"type":"Point"}
}