{
  "type": "Feature",
  "properties": {
    "iso:country":"IT",
    "sg:address":"50, V. San Siro 24064 Grumello Del Monte",
    "sg:city":"Grumello del Monte",
    "sg:classifiers":[
        {
            "category":"Shopping",
            "subcategory":"Clothing, Apparel, & Fashions",
            "type":"Retail Goods"
        }
    ],
    "sg:phone":"+39 035 442 1040",
    "sg:postcode":"24064",
    "sg:province":"Bergamo",
    "sg:tags":[
        "clothing",
        "accessory"
    ],
    "sg:website":"http://www.paginegialle.it/bluemarlin-bg",
    "wof:name":"Blue Marlin Srl",
    "wof:placetype":"venue"
},
  "geometry": {"coordinates":[9.870891,45.632439],"type":"Point"}
}