{
  "type": "Feature",
  "properties": {
    "addr:full":"20026 Novate Milanese Novate Milanese Milano 20026",
    "addr:postcode":"20026;20026",
    "iso:country":"IT",
    "sg:address":"20026 Novate Milanese",
    "sg:city":"Novate Milanese",
    "sg:orig_category":"Prodotti Chimici Secondari. Prodotti Cosmetici E Da Toeletta",
    "sg:phone":"+39 02 3910 0378",
    "sg:postcode":"20026",
    "sg:province":"Milano",
    "wof:name":"D.r.g. Cosmetics Di Sgroi",
    "wof:placetype":"venue"
},
  "geometry": {"coordinates":[9.1495065689,45.5249061584],"type":"Point"}
}