{
  "type": "Feature",
  "properties": {
    "iso:country":"IT",
    "sg:address":"20090 Cesano Boscone",
    "sg:city":"Cesano Boscone",
    "sg:orig_category":"Carni, Salumi E Pesci",
    "sg:phone":"+39 02 450 1772",
    "sg:postcode":"20090",
    "sg:province":"Milano",
    "wof:name":"Cobelli Luciano",
    "wof:placetype":"venue"
},
  "geometry": {"coordinates":[9.084387,45.450726],"type":"Point"}
}