{
  "type": "Feature",
  "properties": {
    "addr:full":"16143 Genova Genova Genova 16143",
    "addr:postcode":"16143;16143",
    "iso:country":"IT",
    "sg:address":"16143 Genova",
    "sg:city":"Genova",
    "sg:orig_category":"Magazzini Custodia Mobili",
    "sg:phone":"+39 010 508985",
    "sg:postcode":"16143",
    "sg:province":"Genova",
    "wof:name":"Im.tra.de. Sas",
    "wof:placetype":"venue"
},
  "geometry": {"coordinates":[8.954864,44.406925],"type":"Point"}
}