{
  "type": "Feature",
  "properties": {
    "addr:full":"30175 Mestre Mestre Venezia 30175",
    "addr:postcode":"30175;30175",
    "addr:street":"Mestre Mestre Venezia",
    "iso:country":"IT",
    "sg:address":"30175 Mestre",
    "sg:city":"Mestre",
    "sg:orig_category":"Trasporti E Spedizioni Merci",
    "sg:phone":"+39 041 913420",
    "sg:postcode":"30175",
    "sg:province":"Venezia",
    "wof:name":"Bellin (s.r.l.)",
    "wof:placetype":"venue"
},
  "geometry": {"coordinates":[12.180252,45.474861],"type":"Point"}
}