{
  "type": "Feature",
  "properties": {
    "addr:full":"62020 Belforte Del Chienti Belforte del Chienti Macerata 62020",
    "addr:postcode":"62020;62020",
    "addr:street":"Del Chienti",
    "iso:country":"IT",
    "sg:address":"62020 Belforte Del Chienti",
    "sg:city":"Belforte del Chienti",
    "sg:orig_category":"Abiti Da Sposa E Cerimonia",
    "sg:phone":"+39 0733 906544",
    "sg:postcode":"62020",
    "sg:province":"Macerata",
    "sg:website":"http://www.delsa.it",
    "wof:name":"Delsa Confezioni Snc",
    "wof:placetype":"venue"
},
  "geometry": {"coordinates":[13.239085,43.164509],"type":"Point"}
}