{
  "type": "Feature",
  "properties": {
    "iso:country":"IT",
    "sg:address":"20123 Milano",
    "sg:city":"Milano",
    "sg:orig_category":"Ospedali E Servizi Sanitari",
    "sg:phone":"+39 02 466796",
    "sg:postcode":"20123",
    "sg:province":"Milano",
    "wof:name":"Geraci Agata",
    "wof:placetype":"venue"
},
  "geometry": {"coordinates":[9.172889,45.4673],"type":"Point"}
}