{
  "type": "Feature",
  "properties": {
    "iso:country":"IT",
    "sg:address":"20092 Cinisello Balsamo",
    "sg:city":"Cinisello Balsamo",
    "sg:orig_category":"Chiese Ed Associazioni Religiose",
    "sg:phone":"+39 02 6604 6034",
    "sg:postcode":"20092",
    "sg:province":"Milano",
    "wof:name":"Provincia Italiana Pie Discepole Del Divin Maestro",
    "wof:placetype":"venue"
},
  "geometry": {"coordinates":[9.176348,45.549599],"type":"Point"}
}