{
  "type": "Feature",
  "properties": {
    "iso:country":"IT",
    "sg:address":"41012 Carpi",
    "sg:city":"Carpi",
    "sg:orig_category":"Imprese Edili",
    "sg:phone":"+39 059 682321",
    "sg:postcode":"41012",
    "sg:province":"Modena",
    "wof:name":"Costruzioni Sagittario Srl",
    "wof:placetype":"venue"
},
  "geometry": {"coordinates":[10.927319,44.731758],"type":"Point"}
}