{
  "type": "Feature",
  "properties": {
    "iso:country":"IT",
    "sg:address":"16, Via Cavagnolo 10156 Torino",
    "sg:city":"Torino",
    "sg:classifiers":[
        {
            "category":"Bars & Pubs",
            "subcategory":"Nightclub",
            "type":"Food & Drink"
        }
    ],
    "sg:phone":"+39 011 262 4359",
    "sg:postcode":"10156",
    "sg:province":"Torino",
    "sg:tags":[
        "cake",
        "bread"
    ],
    "wof:name":"Gilber (s.r.l.)",
    "wof:placetype":"venue"
},
  "geometry": {"coordinates":[7.704136,45.116112],"type":"Point"}
}