{
  "type": "Feature",
  "properties": {
    "iso:country":"IT",
    "sg:address":"20090 Segrate",
    "sg:city":"Segrate",
    "sg:orig_category":"Servizi E Lavori Per Abbigliamento E Pelletterie",
    "sg:phone":"+39 02 213 3249",
    "sg:postcode":"20090",
    "sg:province":"Milano",
    "wof:name":"Rosa Paolo",
    "wof:placetype":"venue"
},
  "geometry": {"coordinates":[9.26594,45.49007],"type":"Point"}
}