{
  "type": "Feature",
  "properties": {
    "iso:country":"IT",
    "sg:address":"74100 Taranto",
    "sg:city":"Taranto",
    "sg:orig_category":"Prodotti Alimentari",
    "sg:phone":"+39 099 736 2080",
    "sg:postcode":"74100",
    "sg:province":"Taranto",
    "sg:website":"http://digilander.iol.it/igdr",
    "wof:name":"Il Giardino Dei Re Di Federico Catucci",
    "wof:placetype":"venue"
},
  "geometry": {"coordinates":[17.2391109467,40.4726028442],"type":"Point"}
}