{
  "type": "Feature",
  "properties": {
    "iso:country":"IT",
    "sg:address":"30, Via G.di Vittorio 40020 Casalfiumanese",
    "sg:city":"Casalfiumanese",
    "sg:classifiers":[
        {
            "category":"Food & Beverages",
            "subcategory":"Groceries & Convenience Stores",
            "type":"Retail Goods"
        }
    ],
    "sg:phone":"+39 0542 666072",
    "sg:postcode":"40020",
    "sg:province":"Bologna",
    "sg:tags":[
        "product",
        "related"
    ],
    "wof:name":"Agrimola (s.p.a.)",
    "wof:placetype":"venue"
},
  "geometry": {"coordinates":[11.3464813232,44.4942207336],"type":"Point"}
}