{
  "type": "Feature",
  "properties": {
    "iso:country":"IT",
    "sg:address":"11020 Champdepraz",
    "sg:city":"Champdepraz",
    "sg:orig_category":"Servizi Per Lo Sport E Il Tempo Libero. Servizi Al Turismo. Acqua, Luce, Gas E Societa' Di Esercizio Pubblico",
    "sg:phone":"+39 0125 960643",
    "sg:postcode":"11020",
    "sg:province":"Aosta",
    "wof:name":"Parco Naturale Del Mont Avic",
    "wof:placetype":"venue"
},
  "geometry": {"coordinates":[7.665615,45.685978],"type":"Point"}
}