{
  "type": "Feature",
  "properties": {
    "iso:country":"IT",
    "sg:address":"Via Campania 9 36015 Schio",
    "sg:city":"Schio",
    "sg:classifiers":[
        {
            "category":"Personal",
            "subcategory":"Skin Care",
            "type":"Services"
        }
    ],
    "sg:phone":"+39 0445 575273",
    "sg:postcode":"36015",
    "sg:province":"Vicenza",
    "sg:tags":[
        "perforating",
        "press",
        "all-across"
    ],
    "sg:website":"www.ims-cm.com",
    "wof:name":"Ims Industria Masetto Schio S.r.l.",
    "wof:placetype":"venue"
},
  "geometry": {"coordinates":[11.399467,45.722343],"type":"Point"}
}