{
  "type": "Feature",
  "properties": {
    "iso:country":"IT",
    "sg:address":"52022 Cavriglia",
    "sg:city":"Cavriglia",
    "sg:orig_category":"Materiali Edili",
    "sg:phone":"+39 055 966053",
    "sg:postcode":"52022",
    "sg:province":"Arezzo",
    "wof:name":"Poggiagliolmi Sauro",
    "wof:placetype":"venue"
},
  "geometry": {"coordinates":[11.486677,43.521988],"type":"Point"}
}