{
  "type": "Feature",
  "properties": {
    "addr:full":"Via Dossi 112 37058 Sanguinetto Sanguinetto Verona 37058",
    "addr:housenumber":"112",
    "addr:postcode":"37058;37058",
    "addr:street":"Via Dossi",
    "iso:country":"IT",
    "sg:address":"Via Dossi 112 37058 Sanguinetto",
    "sg:city":"Sanguinetto",
    "sg:classifiers":[
        {
            "category":"Bus Stop",
            "subcategory":"None",
            "type":"Transportation"
        }
    ],
    "sg:phone":"+39 0442 365200",
    "sg:postcode":"37058",
    "sg:province":"Verona",
    "sg:tags":[
        "period",
        "furniture"
    ],
    "wof:name":"Novalinea Srl",
    "wof:placetype":"venue"
},
  "geometry": {"coordinates":[11.1730365753,45.1783981323],"type":"Point"}
}