{
  "type": "Feature",
  "properties": {
    "iso:country":"IT",
    "sg:address":"20047 Brugherio",
    "sg:city":"Brugherio",
    "sg:orig_category":"Servizi E Lavori Per Abbigliamento E Pelletterie",
    "sg:phone":"+39 039 287 6002",
    "sg:postcode":"20047",
    "sg:province":"Milano",
    "wof:name":"Mackrapid Sas Di Errico Claudio",
    "wof:placetype":"venue"
},
  "geometry": {"coordinates":[9.227209,45.520309],"type":"Point"}
}