{
  "type": "Feature",
  "properties": {
    "iso:country":"IT",
    "sg:address":"46100 Mantova",
    "sg:city":"Mantova",
    "sg:orig_category":"Edilizia Materiali - Vendita Al Dettaglio",
    "sg:phone":"+39 0376 391268",
    "sg:postcode":"46100",
    "sg:province":"Mantova",
    "wof:name":"Societa' Mantovana Materiali Moderni Sas",
    "wof:placetype":"venue"
},
  "geometry": {"coordinates":[10.780667,45.180141],"type":"Point"}
}