{
  "type": "Feature",
  "properties": {
    "iso:country":"IT",
    "sg:address":"06081 Assisi",
    "sg:city":"Assisi",
    "sg:orig_category":"Servizi Per Lo Sport E Il Tempo Libero. Servizi Al Turismo. Acqua, Luce, Gas E Societa' Di Esercizio Pubblico",
    "sg:phone":"+39 075 815233",
    "sg:postcode":"06081",
    "sg:province":"Perugia",
    "wof:name":"Parco Del Monte Subasio - Consorzio Obbligatorio Area Naturale Protetta",
    "wof:placetype":"venue"
},
  "geometry": {"coordinates":[12.644587,43.069424],"type":"Point"}
}