{
  "type": "Feature",
  "properties": {
    "addr:full":"09086 Samugheo Samugheo Oristano 09086",
    "addr:postcode":"09086;09086",
    "iso:country":"IT",
    "sg:address":"09086 Samugheo",
    "sg:city":"Samugheo",
    "sg:orig_category":"Non-classified Establishments",
    "sg:phone":"+39 0783 64658",
    "sg:postcode":"09086",
    "sg:province":"Oristano",
    "wof:name":"Gianni Congiu",
    "wof:placetype":"venue"
},
  "geometry": {"coordinates":[8.946614,39.942848],"type":"Point"}
}