{
  "type": "Feature",
  "properties": {
    "iso:country":"IT",
    "sg:address":"43036 Fidenza",
    "sg:city":"Fidenza",
    "sg:orig_category":"Servizi Vari Di Interesse Pubblico",
    "sg:phone":"+39 0524 533547",
    "sg:postcode":"43036",
    "sg:province":"Parma",
    "wof:name":"Delmonte Roberta",
    "wof:placetype":"venue"
},
  "geometry": {"coordinates":[10.334328,44.814442],"type":"Point"}
}