{
  "type": "Feature",
  "properties": {
    "iso:country":"IT",
    "sg:address":"Sda Statale 96, Km 116 70026 Modugno",
    "sg:city":"Modugno",
    "sg:classifiers":[
        {
            "category":"Banks & Credit Unions",
            "subcategory":"Investment Brokerage",
            "type":"Services"
        }
    ],
    "sg:phone":"+39 080 536 7261",
    "sg:postcode":"70026",
    "sg:province":"Bari",
    "sg:tags":[
        "bearing",
        "ball"
    ],
    "sg:website":"www.michelecaroli.com",
    "wof:name":"Michele Caroli S.r.l.",
    "wof:placetype":"venue"
},
  "geometry": {"coordinates":[16.869291,41.126053],"type":"Point"}
}