{
  "type": "Feature",
  "properties": {
    "iso:country":"IT",
    "sg:address":"35020 Albignasego",
    "sg:city":"Albignasego",
    "sg:orig_category":"Macchine Ed Impianti Per Edilizia E Lavori Pubblici",
    "sg:phone":"+39 049 880 2254",
    "sg:postcode":"35020",
    "sg:province":"Padova",
    "wof:name":"Eurogru (s.r.l.)",
    "wof:placetype":"venue"
},
  "geometry": {"coordinates":[11.868297,45.348446],"type":"Point"}
}