{
  "type": "Feature",
  "properties": {
    "addr:full":"Via Silanello 20 36055 Nove Nove Vicenza 36055",
    "addr:housenumber":"20",
    "addr:postcode":"36055;36055",
    "addr:street":"Via Silanello",
    "iso:country":"IT",
    "sg:address":"Via Silanello 20 36055 Nove",
    "sg:city":"Nove",
    "sg:classifiers":[
        {
            "category":"Shopping",
            "subcategory":"Crafts & Fabrics",
            "type":"Retail Goods"
        }
    ],
    "sg:phone":"+39 0424 590063",
    "sg:postcode":"36055",
    "sg:province":"Vicenza",
    "sg:tags":[
        "decorative",
        "ceramic",
        "artistic"
    ],
    "sg:website":"www.carraroceramiche.it",
    "wof:name":"Vittorio Carraro Impresa Individuale",
    "wof:placetype":"venue"
},
  "geometry": {"coordinates":[11.679762,45.727356],"type":"Point"}
}