{
  "type": "Feature",
  "properties": {
    "iso:country":"IT",
    "sg:address":"04011 Aprilia",
    "sg:city":"Aprilia",
    "sg:orig_category":"Arredamenti - Produzione E Ingrosso",
    "sg:phone":"+39 06 928 2352",
    "sg:postcode":"04011",
    "sg:province":"Latina",
    "sg:website":"http://www.nonsolodivani.com",
    "wof:name":"Divani, Poltrone...non Solo",
    "wof:placetype":"venue"
},
  "geometry": {"coordinates":[12.690533,41.551586],"type":"Point"}
}