{
  "type": "Feature",
  "properties": {
    "addr:full":"00188 Roma Roma Roma 00188",
    "addr:postcode":"00188;00188",
    "iso:country":"IT",
    "sg:address":"00188 Roma",
    "sg:city":"Roma",
    "sg:orig_category":"Macchine, Impianti E Forniture Per Industria Grafica, Cartaria E Cartotecnica. Automazione E Macchine Per Ufficio",
    "sg:phone":"+39 0761 568474",
    "sg:postcode":"00188",
    "sg:province":"Roma",
    "wof:name":"Copy Net",
    "wof:placetype":"venue"
},
  "geometry": {"coordinates":[12.489949,41.989838],"type":"Point"}
}