{
  "type": "Feature",
  "properties": {
    "iso:country":"IT",
    "sg:address":"10093 Collegno",
    "sg:city":"Collegno",
    "sg:orig_category":"Bruciatori Nafta, Gasolio E Kerosene - Commercio",
    "sg:phone":"+39 011 411 1445",
    "sg:postcode":"10093",
    "sg:province":"Torino",
    "wof:name":"Ar-co Bruciatori Srl",
    "wof:placetype":"venue"
},
  "geometry": {"coordinates":[7.597016,45.07169],"type":"Point"}
}