{
  "type": "Feature",
  "properties": {
    "iso:country":"IT",
    "sg:address":"34, Via S. Bellino 35020 Albignasego",
    "sg:city":"Albignasego",
    "sg:classifiers":[
        {
            "category":"Utilities",
            "subcategory":"Telephone",
            "type":"Services"
        }
    ],
    "sg:phone":"+39 049 880 5266",
    "sg:postcode":"35020",
    "sg:province":"Padova",
    "sg:tags":[
        "telecommunication"
    ],
    "wof:name":"I.m.t.r. (s.r.l.)",
    "wof:placetype":"venue"
},
  "geometry": {"coordinates":[11.84951,45.365273],"type":"Point"}
}