{
  "type": "Feature",
  "properties": {
    "iso:country":"IT",
    "sg:address":"50019 Sesto Fiorentino",
    "sg:city":"Sesto Fiorentino",
    "sg:orig_category":"Articoli Per Imballaggio E Confezionamento. Forniture Per Uffici. Forniture Per Attivita' Commerciali Ed Artigianali",
    "sg:phone":"+39 055 315017",
    "sg:postcode":"50019",
    "sg:province":"Firenze",
    "sg:website":"http://www.bbccarta.com",
    "wof:name":"B.b.c. Snc Di Bertacci Biancalani Cantini",
    "wof:placetype":"venue"
},
  "geometry": {"coordinates":[11.170626,43.808144],"type":"Point"}
}