{
  "type": "Feature",
  "properties": {
    "iso:country":"IT",
    "sg:address":"17023 Ceriale",
    "sg:city":"Ceriale",
    "sg:orig_category":"Alberghi E Strutture Extra Alberghiere. Ospedali E Servizi Sanitari",
    "sg:phone":"+39 0182 990041",
    "sg:postcode":"17023",
    "sg:province":"Savona",
    "wof:name":"Istituto Marino Veronese",
    "wof:placetype":"venue"
},
  "geometry": {"coordinates":[8.204895,44.099918],"type":"Point"}
}