{
  "type": "Feature",
  "properties": {
    "iso:country":"IT",
    "sg:address":"10036 Settimo Torinese",
    "sg:city":"Settimo Torinese",
    "sg:orig_category":"Riparazione Dei Mezzi Di Trasporto. Servizi Ausiliari Dei Mezzi Di Trasporto",
    "sg:phone":"+39 011 897 7655",
    "sg:postcode":"10036",
    "sg:province":"Torino",
    "wof:name":"S.i.m. Marmitte Di Sacco Loris",
    "wof:placetype":"venue"
},
  "geometry": {"coordinates":[7.741124,45.148209],"type":"Point"}
}