{
  "type": "Feature",
  "properties": {
    "addr:full":"09126 Cagliari Cagliari Cagliari 09126",
    "addr:postcode":"09126;09126",
    "iso:country":"IT",
    "sg:address":"09126 Cagliari",
    "sg:city":"Cagliari",
    "sg:orig_category":"Pubblica Amministrazione",
    "sg:phone":"+39 070 379141",
    "sg:postcode":"09126",
    "sg:province":"Cagliari",
    "wof:name":"Compartimento E Sezione Polizia",
    "wof:placetype":"venue"
},
  "geometry": {"coordinates":[9.1452512741,39.1999320984],"type":"Point"}
}