{
  "type": "Feature",
  "properties": {
    "addr:full":"39, Via Como 23807 Merate Merate Lecco 23807",
    "addr:postcode":"23807;23807",
    "addr:street":"Via Como",
    "iso:country":"IT",
    "sg:address":"39, Via Como 23807 Merate",
    "sg:city":"Merate",
    "sg:classifiers":[
        {
            "category":"Shopping",
            "subcategory":"Clothing, Apparel, & Fashions",
            "type":"Retail Goods"
        }
    ],
    "sg:phone":"+39 039 990 6315",
    "sg:postcode":"23807",
    "sg:province":"Lecco",
    "sg:tags":[
        "clothes"
    ],
    "wof:name":"Lorenzini (s.p.a.)",
    "wof:placetype":"venue"
},
  "geometry": {"coordinates":[9.436308,45.737522],"type":"Point"}
}