{
  "type": "Feature",
  "properties": {
    "addr:full":"30172 Venezia Venezia Venezia 30172",
    "addr:postcode":"30172;30172",
    "iso:country":"IT",
    "sg:address":"30172 Venezia",
    "sg:city":"Venezia",
    "sg:classifiers":[
        {
            "category":"Professional",
            "subcategory":"Art Services",
            "type":"Services"
        }
    ],
    "sg:phone":"+39 041 987660",
    "sg:postcode":"30172",
    "sg:province":"Venezia",
    "sg:tags":[
        "studi",
        "designer",
        "-"
    ],
    "wof:name":"Finpatent Srl",
    "wof:placetype":"venue"
},
  "geometry": {"coordinates":[12.992643,45.766197],"type":"Point"}
}