{
  "type": "Feature",
  "properties": {
    "addr:full":"00122 Lido Di Ostia Roma 00122",
    "addr:postcode":"00122;00122",
    "addr:street":"Di Ostia Roma",
    "iso:country":"IT",
    "sg:address":"00122 Lido Di Ostia",
    "sg:classifiers":[
        {
            "category":"Health Services",
            "subcategory":"Health Practitioner",
            "type":"Services"
        }
    ],
    "sg:phone":"+39 06 568 0370",
    "sg:postcode":"00122",
    "sg:province":"Roma",
    "sg:tags":[
        "medici"
    ],
    "wof:name":"Bellei Vittorio",
    "wof:placetype":"venue"
},
  "geometry": {"coordinates":[12.285663,41.734596],"type":"Point"}
}