{
  "type": "Feature",
  "properties": {
    "addr:full":"89, Via Trento 32034 Pedavena Pedavena Belluno 32034",
    "addr:postcode":"32034;32034",
    "addr:street":"Via Trento",
    "iso:country":"IT",
    "sg:address":"89, Via Trento 32034 Pedavena",
    "sg:city":"Pedavena",
    "sg:classifiers":[
        {
            "category":"Wholesale",
            "subcategory":"Machinery & Supplies",
            "type":"Manufacturing & Wholesale Goods"
        }
    ],
    "sg:phone":"+39 0439 301643",
    "sg:postcode":"32034",
    "sg:province":"Belluno",
    "sg:tags":[
        "-",
        "agriculture",
        "equipment"
    ],
    "wof:name":"Eurotrafic (s.r.l.)",
    "wof:placetype":"venue"
},
  "geometry": {"coordinates":[11.905054,46.016796],"type":"Point"}
}