{
  "type": "Feature",
  "properties": {
    "iso:country":"IT",
    "sg:address":"32, Via Cassinone 24068 Seriate",
    "sg:city":"Cassinone",
    "sg:classifiers":[
        {
            "category":"Food & Beverages",
            "subcategory":"Dairy",
            "type":"Retail Goods"
        }
    ],
    "sg:phone":"+39 39035303884",
    "sg:postcode":"24068",
    "sg:province":"Bergamo",
    "sg:tags":[
        "product"
    ],
    "wof:name":"Caseificio Preziosa (s.r.l.)",
    "wof:placetype":"venue"
},
  "geometry": {"coordinates":[9.739078,45.667835],"type":"Point"}
}