{
  "type": "Feature",
  "properties": {
    "iso:country":"IT",
    "sg:address":"27100 Pavia",
    "sg:city":"Pavia",
    "sg:orig_category":"Tessuti Arredamento, Tende E Tappeti. Forniture Per Edilizia E Lavori Pubblici",
    "sg:phone":"+39 0382 472273",
    "sg:postcode":"27100",
    "sg:province":"Pavia",
    "wof:name":"Tappezzeria Pilla Snc",
    "wof:placetype":"venue"
},
  "geometry": {"coordinates":[9.157935,45.204906],"type":"Point"}
}