{
  "type": "Feature",
  "properties": {
    "iso:country":"IT",
    "sg:address":"17014 Cairo Montenotte",
    "sg:city":"Cairo Montenotte",
    "sg:orig_category":"Apparecchiature E Sistemi Per Magazzinaggio E Movimentazione",
    "sg:phone":"+39 019 506427",
    "sg:postcode":"17014",
    "sg:province":"Savona",
    "wof:name":"Autogomma Snc",
    "wof:placetype":"venue"
},
  "geometry": {"coordinates":[8.283983,44.400528],"type":"Point"}
}