{
  "type": "Feature",
  "properties": {
    "iso:country":"IT",
    "sg:address":"55020 Fornovolasco",
    "sg:city":"Fornovolasco",
    "sg:orig_category":"Articoli Da Regalo. Hobbistica. Shopping",
    "sg:phone":"+39 0583 722024",
    "sg:postcode":"55020",
    "sg:province":"Lucca",
    "wof:name":"Grotta Del Vento Srl",
    "wof:placetype":"venue"
},
  "geometry": {"coordinates":[10.358297,44.028091],"type":"Point"}
}