{
  "type": "Feature",
  "properties": {
    "iso:country":"IT",
    "sg:address":"17019 Varazze",
    "sg:city":"Varazze",
    "sg:orig_category":"Lavorazioni Meccaniche E Servizi. Riparazione Dei Mezzi Di Trasporto",
    "sg:phone":"+39 019 96244",
    "sg:postcode":"17019",
    "sg:province":"Savona",
    "wof:name":"Italmar S.a.s.",
    "wof:placetype":"venue"
},
  "geometry": {"coordinates":[8.566245,44.354958],"type":"Point"}
}