{
  "type": "Feature",
  "properties": {
    "iso:country":"IT",
    "sg:address":"51036 Larciano",
    "sg:city":"Larciano",
    "sg:classifiers":[
        {
            "category":"Home & Garden",
            "subcategory":"Home Furnishings",
            "type":"Retail Goods"
        }
    ],
    "sg:phone":"+39 0573 83025",
    "sg:postcode":"51036",
    "sg:province":"Pistoia",
    "sg:tags":[
        "bathroom",
        "accessories"
    ],
    "wof:name":"Home Line Srl",
    "wof:placetype":"venue"
},
  "geometry": {"coordinates":[10.9183683395,43.9284973145],"type":"Point"}
}