{
  "type": "Feature",
  "properties": {
    "iso:country":"IT",
    "sg:address":"4, V. Dell'industria 60127 Ancona",
    "sg:city":"Ancona",
    "sg:classifiers":[
        {
            "category":"Shopping",
            "subcategory":"Crafts & Fabrics",
            "type":"Retail Goods"
        }
    ],
    "sg:phone":"+39 071 280 0351",
    "sg:postcode":"60127",
    "sg:province":"Ancona",
    "sg:tags":[
        "linen"
    ],
    "sg:website":"http://www.paginegialle.it/deruschi-an",
    "wof:name":"Centro Tessile De Ruschi",
    "wof:placetype":"venue"
},
  "geometry": {"coordinates":[13.5039196014,43.594745636],"type":"Point"}
}