{
  "type": "Feature",
  "properties": {
    "addr:full":"39100 Bolzano Bolzano Bolzano/Bozen 39100",
    "addr:postcode":"39100;39100",
    "iso:country":"IT",
    "sg:address":"39100 Bolzano",
    "sg:city":"Bolzano",
    "sg:orig_category":"Autolinee",
    "sg:phone":"+39 0471 450111",
    "sg:postcode":"39100",
    "sg:province":"Bolzano/Bozen",
    "sg:website":"http://www.sad.it",
    "wof:name":"Sad - Trasporto Locale Spa",
    "wof:placetype":"venue"
},
  "geometry": {"coordinates":[11.357989,46.497723],"type":"Point"}
}