{
  "type": "Feature",
  "properties": {
    "iso:country":"IT",
    "sg:address":"20090 Settala",
    "sg:city":"Settala",
    "sg:orig_category":"Prodotti E Manufatti In Materie Plastiche",
    "sg:phone":"+39 02 9537 9250",
    "sg:postcode":"20090",
    "sg:province":"Milano",
    "wof:name":"Covet Srl",
    "wof:placetype":"venue"
},
  "geometry": {"coordinates":[9.1999168396,45.4627685547],"type":"Point"}
}