{
  "type": "Feature",
  "properties": {
    "iso:country":"IT",
    "sg:address":"70015 Noci",
    "sg:city":"Noci",
    "sg:orig_category":"Manufacturers: Prefabbricati",
    "sg:phone":"+39 080 494 9656",
    "sg:postcode":"70015",
    "sg:province":"Bari",
    "wof:name":"Palmisano Carlo",
    "wof:placetype":"venue"
},
  "geometry": {"coordinates":[17.124821,40.769562],"type":"Point"}
}