{
  "type": "Feature",
  "properties": {
    "iso:country":"IT",
    "sg:address":"40054 Budrio",
    "sg:city":"Budrio",
    "sg:orig_category":"Climatizzazione E Condizionamento, Apparecchiature E Servizi",
    "sg:phone":"+39 051 808338",
    "sg:postcode":"40054",
    "sg:province":"Bologna",
    "wof:name":"Mz Aspiratori S.p.a.",
    "wof:placetype":"venue"
},
  "geometry": {"coordinates":[11.553277,44.544365],"type":"Point"}
}