{
  "type": "Feature",
  "properties": {
    "iso:country":"IT",
    "sg:address":"25080 Nuvolento",
    "sg:city":"Nuvolento",
    "sg:orig_category":"Agricoltura, Orticoltura E Floricoltura. Articoli Da Regalo. Shopping",
    "sg:phone":"+39 030 689 8780",
    "sg:postcode":"25080",
    "sg:province":"Brescia",
    "wof:name":"Azienda Agricola Paradiso Verde",
    "wof:placetype":"venue"
},
  "geometry": {"coordinates":[10.389575,45.509373],"type":"Point"}
}