{
  "type": "Feature",
  "properties": {
    "addr:full":"32, Via Del Risorgimento 24060 Villongo Villongo Bergamo 24060",
    "addr:postcode":"24060;24060",
    "addr:street":"Via Del Risorgimento",
    "iso:country":"IT",
    "sg:address":"32, Via Del Risorgimento 24060 Villongo",
    "sg:city":"Villongo",
    "sg:classifiers":[
        {
            "category":"Professional",
            "subcategory":"Engineering",
            "type":"Services"
        }
    ],
    "sg:phone":"+39 39035926600",
    "sg:postcode":"24060",
    "sg:province":"Bergamo",
    "sg:tags":[
        "machine",
        "-",
        "mechanical"
    ],
    "wof:name":"Promain (s.r.l.)",
    "wof:placetype":"venue"
},
  "geometry": {"coordinates":[9.924503,45.668541],"type":"Point"}
}