{
  "type": "Feature",
  "properties": {
    "iso:country":"IT",
    "sg:address":"72014 Cisternino",
    "sg:city":"Cisternino",
    "sg:classifiers":[
        {
            "category":"Restaurant",
            "type":"Food & Drink"
        }
    ],
    "sg:phone":"+39 080 444 8388",
    "sg:postcode":"72014",
    "sg:province":"Brindisi",
    "sg:tags":[
        "auxiliary",
        "entertainment",
        "premises",
        "related",
        "catering",
        "similar",
        "public",
        "restaurants"
    ],
    "wof:name":"Aia Del Vento Hotel Ristorante Srl",
    "wof:placetype":"venue"
},
  "geometry": {"coordinates":[17.328596,40.754967],"type":"Point"}
}