{
  "type": "Feature",
  "properties": {
    "addr:full":"Via Dei Ronchi 91 21058 Solbiate Olona Solbiate Olona Varese 21058",
    "addr:housenumber":"91",
    "addr:postcode":"21058;21058",
    "addr:street":"Via Dei Ronchi",
    "iso:country":"IT",
    "sg:address":"Via Dei Ronchi 91 21058 Solbiate Olona",
    "sg:city":"Solbiate Olona",
    "sg:classifiers":[
        {
            "category":"Wholesale",
            "subcategory":"Machinery & Supplies",
            "type":"Manufacturing & Wholesale Goods"
        }
    ],
    "sg:phone":"+39 0331 649093",
    "sg:postcode":"21058",
    "sg:province":"Varese",
    "sg:tags":[
        "pin",
        "clevis"
    ],
    "sg:website":"www.beagroup.com",
    "wof:name":"Bea Srl",
    "wof:placetype":"venue"
},
  "geometry": {"coordinates":[8.883669,45.800201],"type":"Point"}
}