{
  "type": "Feature",
  "properties": {
    "iso:country":"IT",
    "sg:address":"37050 Bonavicina",
    "sg:city":"Bonavicina",
    "sg:orig_category":"Non-classified Establishments",
    "sg:phone":"+39 045 712 5138",
    "sg:postcode":"37050",
    "sg:province":"Verona",
    "wof:name":"Signoretto Giorgio",
    "wof:placetype":"venue"
},
  "geometry": {"coordinates":[11.186412,45.247292],"type":"Point"}
}