{
  "type": "Feature",
  "properties": {
    "addr:full":"123, Via Dell' Acquedotto 62100 Macerata Macerata Macerata 62100",
    "addr:housenumber":"123",
    "addr:postcode":"62100;62100",
    "addr:street":"Via Dell ' Acquedotto",
    "iso:country":"IT",
    "sg:address":"123, Via Dell' Acquedotto 62100 Macerata",
    "sg:city":"Macerata",
    "sg:classifiers":[
        {
            "category":"Manufacturing",
            "subcategory":"Textiles",
            "type":"Manufacturing & Wholesale Goods"
        }
    ],
    "sg:phone":"+39 0733 492262",
    "sg:postcode":"62100",
    "sg:province":"Macerata",
    "sg:tags":[
        "leather",
        "raw",
        "material",
        "-"
    ],
    "wof:name":"Tomaificio Hema",
    "wof:placetype":"venue"
},
  "geometry": {"coordinates":[13.423544,43.320042],"type":"Point"}
}