{
  "type": "Feature",
  "properties": {
    "iso:country":"IT",
    "sg:address":"20128 Milano",
    "sg:city":"Milano",
    "sg:orig_category":"Cancelli, Porte E Portoni Automatici E Telecomandati",
    "sg:phone":"+39 02 257 8823",
    "sg:postcode":"20128",
    "sg:province":"Milano",
    "wof:name":"Eredi Di Guerrini Geom. Luigi",
    "wof:placetype":"venue"
},
  "geometry": {"coordinates":[9.230499,45.511616],"type":"Point"}
}