{
  "type": "Feature",
  "properties": {
    "addr:full":"63100 Ascoli Piceno Ascoli Piceno Ascoli Piceno 63100",
    "addr:postcode":"63100;63100",
    "iso:country":"IT",
    "sg:address":"63100 Ascoli Piceno",
    "sg:city":"Ascoli Piceno",
    "sg:classifiers":[
        {
            "category":"Communications",
            "subcategory":"Newspaper",
            "type":"Services"
        }
    ],
    "sg:phone":"+39 0736 342560",
    "sg:postcode":"63100",
    "sg:province":"Ascoli Piceno",
    "sg:tags":[
        "graphic",
        "publishing",
        "industry",
        "automation",
        "machine",
        "equipment",
        "paper",
        "machinery",
        "supplies"
    ],
    "sg:website":"http://www.proietti.it",
    "wof:name":"Ap Di Antonio Proietti & C. Snc",
    "wof:placetype":"venue"
},
  "geometry": {"coordinates":[13.620031,42.843727],"type":"Point"}
}