{
  "type": "Feature",
  "properties": {
    "iso:country":"IT",
    "sg:address":"Localita' Il Pianello 52046 Lucignano",
    "sg:city":"Lucignano",
    "sg:classifiers":[
        {
            "category":"Shopping",
            "subcategory":"Clothing, Apparel, & Fashions",
            "type":"Retail Goods"
        }
    ],
    "sg:phone":"+39 0575 836149",
    "sg:postcode":"52046",
    "sg:province":"Arezzo",
    "sg:tags":[
        "clothes"
    ],
    "wof:name":"Confezioni Silvj",
    "wof:placetype":"venue"
},
  "geometry": {"coordinates":[11.863062,43.471203],"type":"Point"}
}