{
  "type": "Feature",
  "properties": {
    "iso:country":"IT",
    "sg:address":"32043 Cortina D'ampezzo",
    "sg:classifiers":[
        {
            "category":"Wholesale",
            "subcategory":"Home Furnishings",
            "type":"Manufacturing & Wholesale Goods"
        }
    ],
    "sg:phone":"+39 0436 860696",
    "sg:postcode":"32043",
    "sg:province":"Belluno",
    "sg:tags":[
        "household",
        "appliance",
        "furnishings",
        "appliances",
        "kitchen"
    ],
    "wof:name":"Majoni Osvaldo",
    "wof:placetype":"venue"
},
  "geometry": {"coordinates":[12.0993032455,46.5525474548],"type":"Point"}
}