{
  "type": "Feature",
  "properties": {
    "iso:country":"IT",
    "sg:address":"23862 Civate",
    "sg:city":"Civate",
    "sg:orig_category":"Minuterie Metalliche E Ferramenta",
    "sg:phone":"+39 0341 210244",
    "sg:postcode":"23862",
    "sg:province":"Lecco",
    "wof:name":"Giani Snc",
    "wof:placetype":"venue"
},
  "geometry": {"coordinates":[9.3457574844,45.8359527588],"type":"Point"}
}