{
  "type": "Feature",
  "properties": {
    "addr:full":"22070 Appiano Gentile Appiano Gentile Como 22070",
    "addr:housenumber":"gentile",
    "addr:postcode":"22070;22070",
    "iso:country":"IT",
    "sg:address":"22070 Appiano Gentile",
    "sg:city":"Appiano Gentile",
    "sg:orig_category":"Forniture Per Uffici",
    "sg:phone":"+39 031 890580",
    "sg:postcode":"22070",
    "sg:province":"Como",
    "wof:name":"Larit Di Lucchetti & C. Sas",
    "wof:placetype":"venue"
},
  "geometry": {"coordinates":[9.0367412567,45.76121521],"type":"Point"}
}