{
  "type": "Feature",
  "properties": {
    "iso:country":"IT",
    "sg:address":"Via Industriale, 47/49 25020 Capriano Del Colle",
    "sg:city":"Capriano del Colle",
    "sg:classifiers":[
        {
            "category":"Wholesale",
            "subcategory":"Scrap",
            "type":"Manufacturing & Wholesale Goods"
        }
    ],
    "sg:phone":"+39 030 974 8983",
    "sg:postcode":"25020",
    "sg:province":"Brescia",
    "sg:tags":[
        "metal"
    ],
    "sg:website":"www.fondal.it",
    "wof:name":"Fondal S.p.a.",
    "wof:placetype":"venue"
},
  "geometry": {"coordinates":[10.145132,45.477955],"type":"Point"}
}