{
  "type": "Feature",
  "properties": {
    "addr:full":"33080 Fiume Veneto Fiume Veneto Pordenone 33080",
    "addr:postcode":"33080;33080",
    "iso:country":"IT",
    "sg:address":"33080 Fiume Veneto",
    "sg:city":"Fiume Veneto",
    "sg:orig_category":"Molle - Produzione E Commercio",
    "sg:phone":"+39 0434 959020",
    "sg:postcode":"33080",
    "sg:province":"Pordenone",
    "wof:name":"Mollificio Bortolussi Srl",
    "wof:placetype":"venue"
},
  "geometry": {"coordinates":[12.7312726974,45.9222145081],"type":"Point"}
}