{
  "type": "Feature",
  "properties": {
    "addr:full":"20122 Milano Milano Milano 20122",
    "addr:postcode":"20122;20122",
    "iso:country":"IT",
    "sg:address":"20122 Milano",
    "sg:city":"Milano",
    "sg:orig_category":"Macchine, Impianti Ed Attrezzature Per Agricoltura E Zootecnia",
    "sg:phone":"+39 02 8645 3552",
    "sg:postcode":"20122",
    "sg:province":"Milano",
    "wof:name":"Ente Iniziative Zooprofilatrici",
    "wof:placetype":"venue"
},
  "geometry": {"coordinates":[9.188099,45.458061],"type":"Point"}
}