{
  "type": "Feature",
  "properties": {
    "addr:full":"10, Via Alessandro Manzoni 24040 Filago Filago Bergamo 24040",
    "addr:postcode":"24040;24040",
    "addr:street":"Via Alessandro Manzoni",
    "iso:country":"IT",
    "sg:address":"10, Via Alessandro Manzoni 24040 Filago",
    "sg:city":"Filago",
    "sg:classifiers":[
        {
            "category":"Sports & Exercise",
            "subcategory":"Playing Field",
            "type":"Entertainment"
        }
    ],
    "sg:phone":"+39 39035801488",
    "sg:postcode":"24040",
    "sg:province":"Bergamo",
    "sg:tags":[
        "game"
    ],
    "wof:name":"Italtende Di Bonazza E. & C. (s.n.c.)",
    "wof:placetype":"venue"
},
  "geometry": {"coordinates":[9.531252,45.668613],"type":"Point"}
}