{
  "type": "Feature",
  "properties": {
    "addr:full":"15, Via Maggio 50125 Firenze Firenze Firenze 50125",
    "addr:postcode":"50125;50125",
    "addr:street":"Via Maggio",
    "iso:country":"IT",
    "sg:address":"15, Via Maggio 50125 Firenze",
    "sg:city":"Firenze",
    "sg:classifiers":[
        {
            "category":"Shopping",
            "subcategory":"Clothing, Apparel, & Fashions",
            "type":"Retail Goods"
        }
    ],
    "sg:phone":"+39 39055213815",
    "sg:postcode":"50125",
    "sg:province":"Firenze",
    "sg:tags":[
        "clothes"
    ],
    "wof:name":"Morbar",
    "wof:placetype":"venue"
},
  "geometry": {"coordinates":[11.214581,43.708813],"type":"Point"}
}