{
  "type": "Feature",
  "properties": {
    "addr:full":"55, V. Campagnola 23854 Olginate Olginate Lecco 23854",
    "addr:housenumber":"55",
    "addr:postcode":"23854;23854",
    "addr:street":"V. Campagnola",
    "iso:country":"IT",
    "sg:address":"55, V. Campagnola 23854 Olginate",
    "sg:city":"Olginate",
    "sg:classifiers":[
        {
            "category":"Manufacturing",
            "subcategory":"Metals",
            "type":"Manufacturing & Wholesale Goods"
        }
    ],
    "sg:phone":"+39 0341 680108",
    "sg:postcode":"23854",
    "sg:province":"Lecco",
    "sg:tags":[
        "metallurgy",
        "metalworking"
    ],
    "sg:website":"http://www.minonzio.it",
    "wof:name":"Minonzio Srl",
    "wof:placetype":"venue"
},
  "geometry": {"coordinates":[9.4247016907,45.7900810242],"type":"Point"}
}