{
  "type": "Feature",
  "properties": {
    "iso:country":"IT",
    "sg:address":"96010 Melilli",
    "sg:city":"Melilli",
    "sg:orig_category":"Calce",
    "sg:phone":"+39 0931 914001",
    "sg:postcode":"96010",
    "sg:province":"Siracusa",
    "wof:name":"Leone La Ferla Spa",
    "wof:placetype":"venue"
},
  "geometry": {"coordinates":[15.092445,37.25087],"type":"Point"}
}