{
  "type": "Feature",
  "properties": {
    "iso:country":"IT",
    "sg:address":"00134 Roma",
    "sg:city":"Roma",
    "sg:orig_category":"Prodotti Chimici Di Base",
    "sg:phone":"+39 06 505 9020",
    "sg:postcode":"00134",
    "sg:province":"Roma",
    "wof:name":"Centralcool 2000 S.r.l.",
    "wof:placetype":"venue"
},
  "geometry": {"coordinates":[12.5019693375,41.7860145569],"type":"Point"}
}