{
  "type": "Feature",
  "properties": {
    "addr:full":"86, V. Piave - Bannia 33080 Fiume Veneto Bannia Pordenone 33080",
    "addr:housenumber":"86",
    "addr:postcode":"33080;33080",
    "addr:street":"V. Piave Bannia",
    "iso:country":"IT",
    "sg:address":"86, V. Piave - Bannia 33080 Fiume Veneto",
    "sg:city":"Bannia",
    "sg:classifiers":[
        {
            "category":"Home & Garden",
            "subcategory":"Home Furnishings",
            "type":"Retail Goods"
        }
    ],
    "sg:phone":"+39 0434 560656",
    "sg:postcode":"33080",
    "sg:province":"Pordenone",
    "sg:tags":[
        "household"
    ],
    "sg:website":"http://www.muzzin.it:ws_end: :mark:ws:http://www.paginegialle.it/muzzinspa",
    "wof:name":"Muzzin Spa",
    "wof:placetype":"venue"
},
  "geometry": {"coordinates":[12.744733,45.910355],"type":"Point"}
}