{
  "type": "Feature",
  "properties": {
    "addr:full":"00062 Bracciano Bracciano Roma 00062",
    "addr:postcode":"00062;roma 00062",
    "iso:country":"IT",
    "sg:address":"00062 Bracciano",
    "sg:city":"Bracciano",
    "sg:orig_category":"Banche E Servizi Finanziari. Acqua, Luce, Gas E Societa' Di Esercizio Pubblico. Pubblica Amministrazione",
    "sg:phone":"+39 06 9980 2149",
    "sg:postcode":"00062",
    "sg:province":"Roma",
    "wof:name":"Custer Srl Censimenti Utenze Servizi Tributi Energia Rifiuti",
    "wof:placetype":"venue"
},
  "geometry": {"coordinates":[12.172197,42.100853],"type":"Point"}
}