{
  "type": "Feature",
  "properties": {
    "addr:full":"7, Via Della Scala 50123 Firenze Firenze Firenze 50123",
    "addr:postcode":"50123;50123",
    "addr:street":"Via Della Scala",
    "iso:country":"IT",
    "sg:address":"7, Via Della Scala 50123 Firenze",
    "sg:city":"Firenze",
    "sg:classifiers":[
        {
            "category":"Travel",
            "subcategory":"Travel Agent",
            "type":"Entertainment"
        }
    ],
    "sg:phone":"+39 39055218351",
    "sg:postcode":"50123",
    "sg:province":"Firenze",
    "sg:tags":[
        "business"
    ],
    "wof:name":"Albergo Croce Di Malta",
    "wof:placetype":"venue"
},
  "geometry": {"coordinates":[11.245748,43.775356],"type":"Point"}
}