{
  "type": "Feature",
  "properties": {
    "iso:country":"IT",
    "sg:address":"20154 Milano",
    "sg:city":"Milano",
    "sg:orig_category":"Audiovisivi Filmati, Spot E Multimediali - Realizzazione E Duplicazione",
    "sg:phone":"+39 02 2900 1564",
    "sg:postcode":"20154",
    "sg:province":"Milano",
    "sg:website":"http://www.paginegialle.it/filmmaster",
    "wof:name":"Film Master Srl",
    "wof:placetype":"venue"
},
  "geometry": {"coordinates":[9.18165,45.483223],"type":"Point"}
}