{
  "type": "Feature",
  "properties": {
    "iso:country":"IT",
    "sg:address":"80011 Acerra",
    "sg:city":"Acerra",
    "sg:orig_category":"Prodotti Chimici Secondari",
    "sg:phone":"+39 081 884 4436",
    "sg:postcode":"80011",
    "sg:province":"Napoli",
    "wof:name":"V.e.r. S.r.l.",
    "wof:placetype":"venue"
},
  "geometry": {"coordinates":[14.39083004,40.9638938904],"type":"Point"}
}