{
  "type": "Feature",
  "properties": {
    "iso:country":"IT",
    "sg:address":"Via Malcom X - Contrada Baronia 74027 San Giorgio Jonico",
    "sg:classifiers":[
        {
            "category":"Shopping",
            "subcategory":"Jewelry",
            "type":"Retail Goods"
        }
    ],
    "sg:phone":"+39 099 592 7002",
    "sg:postcode":"74027",
    "sg:province":"Taranto",
    "sg:tags":[
        "item",
        "made",
        "silver",
        "gift"
    ],
    "sg:website":"www.silverart.it",
    "wof:name":"Silver Art S.r.l.",
    "wof:placetype":"venue"
},
  "geometry": {"coordinates":[17.240009,40.469238],"type":"Point"}
}