{
  "type": "Feature",
  "properties": {
    "iso:country":"IT",
    "sg:address":"10, Via Dell' Artigianato 37024 Negrar",
    "sg:city":"Negrar",
    "sg:classifiers":[
        {
            "category":"Manufacturing",
            "subcategory":"Metals",
            "type":"Manufacturing & Wholesale Goods"
        }
    ],
    "sg:phone":"+39 045 750 0408",
    "sg:postcode":"37024",
    "sg:province":"Verona",
    "sg:tags":[
        "processing"
    ],
    "wof:name":"Campagnola & Fedeli (s.n.c.)",
    "wof:placetype":"venue"
},
  "geometry": {"coordinates":[10.9389867783,45.5250663757],"type":"Point"}
}