{
  "type": "Feature",
  "properties": {
    "iso:country":"IT",
    "sg:address":"50141 Firenze",
    "sg:city":"Firenze",
    "sg:orig_category":"Sport - Articoli E Forniture",
    "sg:phone":"+39 055 454419",
    "sg:postcode":"50141",
    "sg:province":"Firenze",
    "wof:name":"Multisport Di Monselvi Massimo & C. Sas",
    "wof:placetype":"venue"
},
  "geometry": {"coordinates":[11.236895,43.802406],"type":"Point"}
}