{
  "type": "Feature",
  "properties": {
    "iso:country":"IT",
    "sg:address":"Via Carlo Pisacane 24 41012 Carpi",
    "sg:city":"Carpi",
    "sg:classifiers":[
        {
            "category":"Organizations",
            "subcategory":"Labor Organization",
            "type":"Services"
        }
    ],
    "sg:phone":"+39 059 622 2511",
    "sg:postcode":"41012",
    "sg:province":"Modena",
    "sg:tags":[
        "woodworking",
        "machinery"
    ],
    "sg:website":"www.agazzani.it",
    "wof:name":"Agazzani Srl",
    "wof:placetype":"venue"
},
  "geometry": {"coordinates":[10.88397,44.770027],"type":"Point"}
}