{
  "type": "Feature",
  "properties": {
    "addr:full":"7, Viale Virgilio 21052 Busto Arsizio Busto Arsizio Varese 21052",
    "addr:postcode":"21052;21052",
    "addr:street":"Viale Virgilio",
    "iso:country":"IT",
    "sg:address":"7, Viale Virgilio 21052 Busto Arsizio",
    "sg:city":"Busto Arsizio",
    "sg:classifiers":[
        {
            "category":"Autos & Motor Vehicles",
            "subcategory":"Automobile Sales",
            "type":"Retail Goods"
        }
    ],
    "sg:phone":"+39 0331 678160",
    "sg:postcode":"21052",
    "sg:province":"Varese",
    "sg:tags":[
        "motor-cars"
    ],
    "wof:name":"Real Motors Spa",
    "wof:placetype":"venue"
},
  "geometry": {"coordinates":[8.861746788,45.6057243347],"type":"Point"}
}