{
  "type": "Feature",
  "properties": {
    "iso:country":"IT",
    "sg:address":"20, Via Balzani 40069 Zola Predosa",
    "sg:city":"Zola",
    "sg:classifiers":[
        {
            "category":"Manufacturing",
            "subcategory":"Metals",
            "type":"Manufacturing & Wholesale Goods"
        }
    ],
    "sg:phone":"+39 051 616 7811",
    "sg:postcode":"40069",
    "sg:province":"Bologna",
    "sg:tags":[
        "metallurgy",
        "metalworking"
    ],
    "wof:name":"Nuova Star S.p.a.",
    "wof:placetype":"venue"
},
  "geometry": {"coordinates":[11.2410554886,44.5016174316],"type":"Point"}
}