{
  "type": "Feature",
  "properties": {
    "addr:full":"15, Via Reggia Di Portici 80142 Napoli Napoli Napoli 80142",
    "addr:postcode":"80142;80142",
    "addr:street":"Via Reggia Di Portici",
    "iso:country":"IT",
    "sg:address":"15, Via Reggia Di Portici 80142 Napoli",
    "sg:city":"Napoli",
    "sg:classifiers":[
        {
            "category":"Parking",
            "subcategory":"Lot",
            "type":"Transportation"
        }
    ],
    "sg:phone":"+39 081 752 7799",
    "sg:postcode":"80142",
    "sg:province":"Napoli",
    "sg:tags":[
        "transport",
        "road"
    ],
    "wof:name":"Girace Fratelli S.r.l.",
    "wof:placetype":"venue"
},
  "geometry": {"coordinates":[14.285195,40.843498],"type":"Point"}
}