{
  "type": "Feature",
  "properties": {
    "iso:country":"IT",
    "sg:address":"4, Via Giuseppe Verdi 23844 Sirone",
    "sg:city":"Sirone",
    "sg:classifiers":[
        {
            "category":"Real Estate",
            "subcategory":"Surveying",
            "type":"Services"
        }
    ],
    "sg:phone":"+39 031 357 4974",
    "sg:postcode":"23844",
    "sg:province":"Lecco",
    "sg:tags":[
        "equipment",
        "material",
        "good",
        "-",
        "handling"
    ],
    "wof:name":"S.t. Special Tanks S.r.l.",
    "wof:placetype":"venue"
},
  "geometry": {"coordinates":[9.326185,45.767441],"type":"Point"}
}