{
  "type": "Feature",
  "properties": {
    "iso:country":"IT",
    "sg:address":"10041 Carignano",
    "sg:city":"Carignano",
    "sg:orig_category":"Materiali Edili",
    "sg:phone":"+39 011 971 3582",
    "sg:postcode":"10041",
    "sg:province":"Torino",
    "sg:website":"http://www.nuovacavit.it",
    "wof:name":"Cave Germaire Spa",
    "wof:placetype":"venue"
},
  "geometry": {"coordinates":[7.664135,44.901745],"type":"Point"}
}