{
  "type": "Feature",
  "properties": {
    "iso:country":"IT",
    "sg:address":"20026 Novate Milanese",
    "sg:city":"Novate Milanese",
    "sg:orig_category":"Climatizzazione E Condizionamento, Apparecchiature E Servizi",
    "sg:phone":"+39 02 356 4779",
    "sg:postcode":"20026",
    "sg:province":"Milano",
    "wof:name":"Dil.ma Srl",
    "wof:placetype":"venue"
},
  "geometry": {"coordinates":[9.126823,45.527271],"type":"Point"}
}