{
  "type": "Feature",
  "properties": {
    "iso:country":"IT",
    "sg:address":"26022 Castelverde",
    "sg:city":"Castelverde",
    "sg:orig_category":"Non-classified Establishments",
    "sg:phone":"+39 0372 429064",
    "sg:postcode":"26022",
    "sg:province":"Cremona",
    "wof:name":"Papermon Srl",
    "wof:placetype":"venue"
},
  "geometry": {"coordinates":[9.998497,45.191589],"type":"Point"}
}