{
  "type": "Feature",
  "properties": {
    "iso:country":"IT",
    "sg:address":"66054 Vasto",
    "sg:city":"Vasto",
    "sg:orig_category":"Servizi Al Turismo. Servizi Ausiliari Per Il Trasporto",
    "sg:phone":"+39 0873 367174",
    "sg:postcode":"66054",
    "sg:province":"Chieti",
    "sg:website":"http://www.massacesiviaggi.it",
    "wof:name":"Agenzia Viaggi E Marittima Massacesi",
    "wof:placetype":"venue"
},
  "geometry": {"coordinates":[14.693768,42.11887],"type":"Point"}
}