{
  "type": "Feature",
  "properties": {
    "iso:country":"IT",
    "sg:address":"16126 Genova",
    "sg:city":"Genova",
    "sg:orig_category":"Articoli Da Regalo. Arte Ed Artigianato Artistico. Shopping",
    "sg:phone":"+39 010 246 6452",
    "sg:postcode":"16126",
    "sg:province":"Genova",
    "wof:name":"Wei Jian Xiong",
    "wof:placetype":"venue"
},
  "geometry": {"coordinates":[8.909358,44.40567],"type":"Point"}
}