{
  "type": "Feature",
  "properties": {
    "iso:country":"IT",
    "sg:address":"40, Via Fiume 22037 Ponte Lambro",
    "sg:city":"Ponte Lambro",
    "sg:classifiers":[
        {
            "category":"Manufacturing",
            "subcategory":"Paper Products",
            "type":"Manufacturing & Wholesale Goods"
        }
    ],
    "sg:phone":"+39 39031620384",
    "sg:postcode":"22037",
    "sg:province":"Como",
    "sg:tags":[
        "cardboard"
    ],
    "wof:name":"Bormio (s.p.a.)",
    "wof:placetype":"venue"
},
  "geometry": {"coordinates":[9.2287302017,45.8241691589],"type":"Point"}
}