{
  "type": "Feature",
  "properties": {
    "iso:country":"IT",
    "sg:address":"Ctr Mercen\u00f2 94019 Valguarnera",
    "sg:classifiers":[
        {
            "category":"Shopping",
            "subcategory":"Clothing, Apparel, & Fashions",
            "type":"Retail Goods"
        }
    ],
    "sg:phone":"+39 0935 958800",
    "sg:postcode":"94019",
    "sg:province":"Enna",
    "sg:tags":[
        "coat",
        "men's"
    ],
    "wof:name":"Dalcos Abbigliamento Srl",
    "wof:placetype":"venue"
},
  "geometry": {"coordinates":[14.2797060013,37.5675964355],"type":"Point"}
}