{
  "type": "Feature",
  "properties": {
    "iso:country":"IT",
    "sg:address":"31021 Mogliano Veneto",
    "sg:city":"Mogliano Veneto",
    "sg:orig_category":"Macchine, Impianti Ed Attrezzature Per Abbigliamento E Pelletterie",
    "sg:phone":"+39 041 593 8054",
    "sg:postcode":"31021",
    "sg:province":"Treviso",
    "wof:name":"B.m.l. Di Bonotto Luciano",
    "wof:placetype":"venue"
},
  "geometry": {"coordinates":[12.204016,45.573891],"type":"Point"}
}