{
  "type": "Feature",
  "properties": {
    "addr:full":"33082 Tiezzo Corva Pordenone 33082",
    "addr:postcode":"33082;33082",
    "addr:street":"Corva",
    "iso:country":"IT",
    "sg:address":"33082 Tiezzo",
    "sg:city":"Corva",
    "sg:orig_category":"Arredo Cucina Ed Elettrodomestici. Climatizzazione E Condizionamento, Apparecchiature E Servizi",
    "sg:phone":"+39 0434 640602",
    "sg:postcode":"33082",
    "sg:province":"Pordenone",
    "wof:name":"Fim Di Sandrin Luciano E C. Snc",
    "wof:placetype":"venue"
},
  "geometry": {"coordinates":[12.673116,45.892673],"type":"Point"}
}