{
  "type": "Feature",
  "properties": {
    "iso:country":"IT",
    "sg:address":"20032 Cormano",
    "sg:city":"Cormano",
    "sg:orig_category":"Essenze, Estratti E Prodotti Aromatici Per Profumeria",
    "sg:phone":"+39 02 615 0664",
    "sg:postcode":"20032",
    "sg:province":"Milano",
    "wof:name":"Cerizza Spa",
    "wof:placetype":"venue"
},
  "geometry": {"coordinates":[9.159343,45.539337],"type":"Point"}
}