{
  "type": "Feature",
  "properties": {
    "addr:full":"00, Via Luppia S. Zeno 35044 Montagnana Montagnana Padova 35044",
    "addr:postcode":"35044;35044",
    "addr:street":"Via Luppia S. Zeno",
    "iso:country":"IT",
    "sg:address":"00, Via Luppia S. Zeno 35044 Montagnana",
    "sg:city":"Montagnana",
    "sg:classifiers":[
        {
            "category":"Shopping",
            "subcategory":"Clothing, Apparel, & Fashions",
            "type":"Retail Goods"
        }
    ],
    "sg:phone":"+39 39042982982",
    "sg:postcode":"35044",
    "sg:province":"Padova",
    "sg:tags":[
        "clothes"
    ],
    "wof:name":"Emi-maglia S.p.a.",
    "wof:placetype":"venue"
},
  "geometry": {"coordinates":[11.876589,45.409569],"type":"Point"}
}