{
  "type": "Feature",
  "properties": {
    "iso:country":"IT",
    "sg:address":"10138 Torino",
    "sg:city":"Torino",
    "sg:orig_category":"Materiali E Componenti Elettrotecnici",
    "sg:phone":"+39 011 447 4463",
    "sg:postcode":"10138",
    "sg:province":"Torino",
    "wof:name":"Ciceri Renato Elettrotermica",
    "wof:placetype":"venue"
},
  "geometry": {"coordinates":[7.652204,45.066093],"type":"Point"}
}