{
  "type": "Feature",
  "properties": {
    "iso:country":"IT",
    "sg:address":"137, Via M. Pasubio 36010 Zane'",
    "sg:classifiers":[
        {
            "category":"Professional",
            "subcategory":"Engineering",
            "type":"Services"
        }
    ],
    "sg:phone":"+39 0445 804444",
    "sg:postcode":"36010",
    "sg:province":"Vicenza",
    "sg:tags":[
        "machine",
        "-",
        "mechanical"
    ],
    "wof:name":"Arroweld Italia S.p.a.",
    "wof:placetype":"venue"
},
  "geometry": {"coordinates":[11.478968,45.724266],"type":"Point"}
}