{
  "type": "Feature",
  "properties": {
    "iso:country":"IT",
    "sg:address":"10035 Mazze'",
    "sg:orig_category":"Servizi E Lavori Per Agricoltura E Zootecnia. Servizi E Lavori Per Ecologia E Smaltimento Rifiuti",
    "sg:phone":"+39 011 983 5909",
    "sg:postcode":"10035",
    "sg:province":"Torino",
    "wof:name":"Associazione Irrigazione Est Sesia",
    "wof:placetype":"venue"
},
  "geometry": {"coordinates":[7.65248,45.099091],"type":"Point"}
}