{
  "type": "Feature",
  "properties": {
    "addr:full":"Via Artigiani 31035 Crocetta Del Montello Crocetta del Montello Treviso 31035",
    "addr:postcode":"31035;31035",
    "addr:street":"Via Artigiani",
    "iso:country":"IT",
    "sg:address":"Via Artigiani 31035 Crocetta Del Montello",
    "sg:city":"Crocetta del Montello",
    "sg:classifiers":[
        {
            "category":"Food & Beverages",
            "subcategory":"Groceries & Convenience Stores",
            "type":"Retail Goods"
        }
    ],
    "sg:phone":"+39 0423 639222",
    "sg:postcode":"31035",
    "sg:province":"Treviso",
    "sg:tags":[
        "product",
        "related"
    ],
    "wof:name":"Dali' (s.p.a.)",
    "wof:placetype":"venue"
},
  "geometry": {"coordinates":[12.024105072,45.8145599365],"type":"Point"}
}