{
  "type": "Feature",
  "properties": {
    "iso:country":"IT",
    "sg:address":"29100 Piacenza",
    "sg:city":"Piacenza",
    "sg:orig_category":"Agenzie Viaggi E Turismo",
    "sg:phone":"+39 0523 338762",
    "sg:postcode":"29100",
    "sg:province":"Piacenza",
    "sg:website":"http://www.nuovagnelli.it",
    "wof:name":"Agenzia Viaggi Nuova Agnelli",
    "wof:placetype":"venue"
},
  "geometry": {"coordinates":[9.767375,45.050365],"type":"Point"}
}