{
  "type": "Feature",
  "properties": {
    "addr:full":"20129 Milano Milano Milano 20129",
    "addr:postcode":"20129;20129",
    "iso:country":"IT",
    "sg:address":"20129 Milano",
    "sg:city":"Milano",
    "sg:orig_category":"Sport And Leisure, Services. Tourism, Services. Motor Vehicles, Auxiliary Services. Transport, Auxiliary Services",
    "sg:phone":"+39 02 2940 1721",
    "sg:postcode":"20129",
    "sg:province":"Milano",
    "wof:name":"Cooperativa Autonoleggio Stella Srl",
    "wof:placetype":"venue"
},
  "geometry": {"coordinates":[9.218527,45.474472],"type":"Point"}
}