{
  "type": "Feature",
  "properties": {
    "addr:full":"3, Strada Borra 12069 Santa Vittoria D'alba Cuneo 12069",
    "addr:postcode":"12069;12069",
    "addr:street":"Strada Borra",
    "iso:country":"IT",
    "sg:address":"3, Strada Borra 12069 Santa Vittoria D'alba",
    "sg:classifiers":[
        {
            "category":"Food & Beverages",
            "subcategory":"Groceries & Convenience Stores",
            "type":"Retail Goods"
        }
    ],
    "sg:phone":"+39 0172 478827",
    "sg:postcode":"12069",
    "sg:province":"Cuneo",
    "sg:tags":[
        "drink"
    ],
    "wof:name":"Grapperia S. Anna (s.r.l.)",
    "wof:placetype":"venue"
},
  "geometry": {"coordinates":[7.922602,44.692085],"type":"Point"}
}