{
  "type": "Feature",
  "properties": {
    "iso:country":"IT",
    "sg:address":"31021 Mogliano Veneto",
    "sg:city":"Mogliano Veneto",
    "sg:orig_category":"Impiantistica E Prodotti Tecnologici Per Edilizia. Elettrotecnica Industriale, Prodotti E Apparecchiature",
    "sg:phone":"+39 041 597 0149",
    "sg:postcode":"31021",
    "sg:province":"Treviso",
    "wof:name":"Alb Sas Di A. Brutesco & C.",
    "wof:placetype":"venue"
},
  "geometry": {"coordinates":[12.26002,45.558147],"type":"Point"}
}