{
  "type": "Feature",
  "properties": {
    "iso:country":"IT",
    "sg:address":"117, Via Dei Mille 24060 Castelli Calepio",
    "sg:city":"Castelli Calepio",
    "sg:classifiers":[
        {
            "category":"Professional",
            "subcategory":"Engineering",
            "type":"Services"
        }
    ],
    "sg:phone":"+39 39035848011",
    "sg:postcode":"24060",
    "sg:province":"Bergamo",
    "sg:tags":[
        "machine",
        "-",
        "mechanical"
    ],
    "wof:name":"Guin (s.r.l.)",
    "wof:placetype":"venue"
},
  "geometry": {"coordinates":[9.895364,45.639217],"type":"Point"}
}