{
  "type": "Feature",
  "properties": {
    "iso:country":"IT",
    "sg:address":"13866 Masserano",
    "sg:city":"Masserano",
    "sg:orig_category":"Servizi E Lavori Per Ecologia E Smaltimento Rifiuti. Termotecnica E Riscaldamento, Apparecchiature E Servizi. Servizi Ausiliari Di Sorveglianza, Manutenzione E Pulizia",
    "sg:phone":"+39 015 99544",
    "sg:postcode":"13866",
    "sg:province":"Biella",
    "wof:name":"Tonelli Impianti S.a.s. Di Tonelli Verusca & C.",
    "wof:placetype":"venue"
},
  "geometry": {"coordinates":[8.217814,45.59798],"type":"Point"}
}