{
  "type": "Feature",
  "properties": {
    "iso:country":"IT",
    "sg:address":"Via Roma 41 30020 Cinto Caomaggiore",
    "sg:city":"Cinto Caomaggiore",
    "sg:classifiers":[
        {
            "category":"Government",
            "subcategory":"Court House",
            "type":"Public Place"
        }
    ],
    "sg:phone":"+39 0421 241241",
    "sg:postcode":"30020",
    "sg:province":"Venezia",
    "sg:tags":[
        "residential",
        "intercom"
    ],
    "sg:website":"www.bpt.it",
    "wof:name":"B P T Spa",
    "wof:placetype":"venue"
},
  "geometry": {"coordinates":[12.737942,45.813946],"type":"Point"}
}