{
  "type": "Feature",
  "properties": {
    "iso:country":"IT",
    "sg:address":"50135 Firenze",
    "sg:city":"Firenze",
    "sg:orig_category":"Calzature, Pelletterie E Pelli. Shopping",
    "sg:phone":"+39 055 609544",
    "sg:postcode":"50135",
    "sg:province":"Firenze",
    "sg:website":"http://www.calzaturecaruso.it",
    "wof:name":"Calzature Caruso",
    "wof:placetype":"venue"
},
  "geometry": {"coordinates":[11.314745,43.775883],"type":"Point"}
}