{
  "type": "Feature",
  "properties": {
    "addr:full":"1, Via Guglielmo Marconi 35020 Legnaro Legnaro Padova 35020",
    "addr:postcode":"35020;35020",
    "addr:street":"Via Guglielmo Marconi",
    "iso:country":"IT",
    "sg:address":"1, Via Guglielmo Marconi 35020 Legnaro",
    "sg:city":"Legnaro",
    "sg:classifiers":[
        {
            "category":"Professional",
            "subcategory":"Engineering",
            "type":"Services"
        }
    ],
    "sg:phone":"+39 39049641679",
    "sg:postcode":"35020",
    "sg:province":"Padova",
    "sg:tags":[
        "machine",
        "-",
        "mechanical"
    ],
    "wof:name":"Aerservice (s.r.l.)",
    "wof:placetype":"venue"
},
  "geometry": {"coordinates":[11.954766,45.352314],"type":"Point"}
}