{
  "type": "Feature",
  "properties": {
    "iso:country":"IT",
    "sg:address":"8, Viale Dell' Artigianato 24049 Verdello",
    "sg:city":"Verdello",
    "sg:classifiers":[
        {
            "category":"Personal",
            "subcategory":"Shoe Repair & Shine",
            "type":"Services"
        }
    ],
    "sg:phone":"+39 035 482 2711",
    "sg:postcode":"24049",
    "sg:province":"Bergamo",
    "sg:tags":[
        "leather"
    ],
    "wof:name":"Lemie (s.p.a.)",
    "wof:placetype":"venue"
},
  "geometry": {"coordinates":[9.615128,45.647205],"type":"Point"}
}