{
  "type": "Feature",
  "properties": {
    "addr:full":"Via Sparone 14c 10148 Torino Torino Torino 10148",
    "addr:housenumber":"14c",
    "addr:postcode":"10148;10148",
    "addr:street":"Via Sparone",
    "iso:country":"IT",
    "sg:address":"Via Sparone 14c 10148 Torino",
    "sg:city":"Torino",
    "sg:classifiers":[
        {
            "category":"Manufacturing",
            "subcategory":"Tools & Machinery",
            "type":"Manufacturing & Wholesale Goods"
        }
    ],
    "sg:phone":"+39 011 220 7782",
    "sg:postcode":"10148",
    "sg:province":"Torino",
    "sg:tags":[
        "abrasive"
    ],
    "wof:name":"Ialta Srl",
    "wof:placetype":"venue"
},
  "geometry": {"coordinates":[7.663723,45.107666],"type":"Point"}
}