{
  "type": "Feature",
  "properties": {
    "addr:full":"20063 Cernusco Sul Naviglio Cernusco sul Naviglio Milano 20063",
    "addr:postcode":"20063;20063",
    "iso:country":"IT",
    "sg:address":"20063 Cernusco Sul Naviglio",
    "sg:city":"Cernusco sul Naviglio",
    "sg:orig_category":"Forniture Per Agricoltura E Zootecnia. Animali Domestici",
    "sg:phone":"+39 02 9211 1060",
    "sg:postcode":"20063",
    "sg:province":"Milano",
    "wof:name":"Nonsologatto Snc",
    "wof:placetype":"venue"
},
  "geometry": {"coordinates":[9.3274440765,45.5296669006],"type":"Point"}
}