{
  "type": "Feature",
  "properties": {
    "addr:full":"7, Via Ezio Vanoni 23014 Andalo Valtellino Andalo Valtellino Sondrio 23014",
    "addr:postcode":"23014;23014",
    "addr:street":"Via Ezio Vanoni",
    "iso:country":"IT",
    "sg:address":"7, Via Ezio Vanoni 23014 Andalo Valtellino",
    "sg:city":"Andalo Valtellino",
    "sg:classifiers":[
        {
            "category":"Autos & Motor Vehicles",
            "subcategory":"Automobile Sales",
            "type":"Retail Goods"
        }
    ],
    "sg:phone":"+39 0342 696047",
    "sg:postcode":"23014",
    "sg:province":"Sondrio",
    "sg:tags":[
        "motor-cars"
    ],
    "wof:name":"Centrauto Srl",
    "wof:placetype":"venue"
},
  "geometry": {"coordinates":[9.4720087051,46.1363296509],"type":"Point"}
}