{
  "type": "Feature",
  "properties": {
    "iso:country":"IT",
    "sg:address":"Via F. Turati 747 47020 Pievesestina",
    "sg:classifiers":[
        {
            "category":"Building & Trades",
            "subcategory":"Construction",
            "type":"Services"
        }
    ],
    "sg:phone":"+39 0547 316311",
    "sg:postcode":"47020",
    "sg:province":"Forl\u00ec-Cesena",
    "sg:tags":[
        "carpenter's",
        "work",
        "supraregional"
    ],
    "sg:website":"www.celbo-spa.it",
    "wof:name":"Celbo Spa",
    "wof:placetype":"venue"
},
  "geometry": {"coordinates":[12.32827,44.075146],"type":"Point"}
}