{
  "type": "Feature",
  "properties": {
    "iso:country":"IT",
    "sg:address":"Vle Vicenza 34a 36071 Arzignano",
    "sg:city":"Arzignano",
    "sg:classifiers":[
        {
            "category":"Manufacturing",
            "subcategory":"Rubber & Plastics",
            "type":"Manufacturing & Wholesale Goods"
        }
    ],
    "sg:phone":"+39 0444 452038",
    "sg:postcode":"36071",
    "sg:province":"Vicenza",
    "sg:tags":[
        "bags",
        "polyethylene",
        "sack",
        "bag"
    ],
    "sg:website":"www.sigilplast.it",
    "wof:name":"Sigilplast Srl Di Albiero Sergio E Preto Giannino",
    "wof:placetype":"venue"
},
  "geometry": {"coordinates":[11.540307045,45.5459060669],"type":"Point"}
}