{
  "type": "Feature",
  "properties": {
    "iso:country":"IT",
    "sg:address":"16044 Cicagna",
    "sg:city":"Cicagna",
    "sg:orig_category":"Marmo, Pietre Ed Affini",
    "sg:phone":"+39 0185 92190",
    "sg:postcode":"16044",
    "sg:province":"Genova",
    "wof:name":"L.e.a.n.i. (s.n.c.)",
    "wof:placetype":"venue"
},
  "geometry": {"coordinates":[9.251129,44.406052],"type":"Point"}
}