{
  "type": "Feature",
  "properties": {
    "addr:full":"14, Piazza S. Paolo 12051 Alba Alba Cuneo 12051",
    "addr:postcode":"12051;12051",
    "addr:street":"Piazza S. Paolo",
    "iso:country":"IT",
    "sg:address":"14, Piazza S. Paolo 12051 Alba",
    "sg:city":"Alba",
    "sg:classifiers":[
        {
            "category":"Professional",
            "subcategory":"Printing & Photocopies",
            "type":"Services"
        }
    ],
    "sg:phone":"+39 0173 363264",
    "sg:postcode":"12051",
    "sg:province":"Cuneo",
    "wof:name":"Gazzetta D'alba S.r.l.",
    "wof:placetype":"venue"
},
  "geometry": {"coordinates":[7.5471105576,44.38879776],"type":"Point"}
}