{
  "type": "Feature",
  "properties": {
    "iso:country":"IT",
    "sg:address":"11/10, Viale Orazio Flacco 70124 Bari",
    "sg:city":"Bari",
    "sg:classifiers":[
        {
            "category":"Food & Beverages",
            "subcategory":"Dairy",
            "type":"Retail Goods"
        }
    ],
    "sg:phone":"+39 080 561 3529",
    "sg:postcode":"70124",
    "sg:province":"Bari",
    "sg:tags":[
        "product"
    ],
    "wof:name":"Gasperini",
    "wof:placetype":"venue"
},
  "geometry": {"coordinates":[16.860542,41.11039],"type":"Point"}
}