{
  "type": "Feature",
  "properties": {
    "addr:full":"Via Forlanini 1 20090 Buccinasco Buccinasco Milano 20090",
    "addr:housenumber":"1",
    "addr:postcode":"20090;20090",
    "addr:street":"Via Forlanini",
    "iso:country":"IT",
    "sg:address":"Via Forlanini 1 20090 Buccinasco",
    "sg:city":"Buccinasco",
    "sg:classifiers":[
        {
            "category":"Utilities",
            "subcategory":"Natural Gas",
            "type":"Services"
        }
    ],
    "sg:phone":"+39 02 4570 8412",
    "sg:postcode":"20090",
    "sg:province":"Milano",
    "sg:tags":[
        "exhaust",
        "hood"
    ],
    "sg:website":"www.lab2000.com/folabo",
    "wof:name":"Folabo Srl",
    "wof:placetype":"venue"
},
  "geometry": {"coordinates":[9.114485,45.411392],"type":"Point"}
}