{
  "type": "Feature",
  "properties": {
    "iso:country":"IT",
    "sg:address":"9, Via Statuto 10040 Volvera",
    "sg:city":"Volvera",
    "sg:classifiers":[
        {
            "category":"Manufacturing",
            "subcategory":"Lumber",
            "type":"Manufacturing & Wholesale Goods"
        }
    ],
    "sg:phone":"+39 011 985 0612",
    "sg:postcode":"10040",
    "sg:province":"Torino",
    "sg:tags":[
        "wood"
    ],
    "wof:name":"Racca",
    "wof:placetype":"venue"
},
  "geometry": {"coordinates":[7.514829,44.9552],"type":"Point"}
}