{
  "type": "Feature",
  "properties": {
    "addr:full":"Regione Moie 10084 Forno Canavese Forno Canavese Torino 10084",
    "addr:postcode":"10084;10084",
    "addr:street":"Regione Moie",
    "iso:country":"IT",
    "sg:address":"Regione Moie 10084 Forno Canavese",
    "sg:city":"Forno Canavese",
    "sg:classifiers":[
        {
            "category":"Manufacturing",
            "subcategory":"Metals",
            "type":"Manufacturing & Wholesale Goods"
        }
    ],
    "sg:phone":"+39 390 124 7113",
    "sg:postcode":"10084",
    "sg:province":"Torino",
    "sg:tags":[
        "processing"
    ],
    "wof:name":"Rolle Fratelli Fu Virgilio (s.r.l.)",
    "wof:placetype":"venue"
},
  "geometry": {"coordinates":[7.5462675095,45.2968177795],"type":"Point"}
}