{
  "type": "Feature",
  "properties": {
    "iso:country":"IT",
    "sg:address":"20127 Milano",
    "sg:city":"Milano",
    "sg:orig_category":"Studi E Consulenze Tecniche E Industriali. Consulenze Tecniche, Amministrative E Perizie. Servizi Ausiliari Di Analisi, Controllo E Ricerca",
    "sg:phone":"+39 02 288 5881",
    "sg:postcode":"20127",
    "sg:province":"Milano",
    "wof:name":"Sea Srl Societa' Di Ergonomia Applicata",
    "wof:placetype":"venue"
},
  "geometry": {"coordinates":[9.223149,45.499336],"type":"Point"}
}