{
  "type": "Feature",
  "properties": {
    "addr:full":"Viale Martiri Della Libert\u00e0 144/a 52010 Subbiano Subbiano Arezzo 52010",
    "addr:housenumber":"144 / a",
    "addr:postcode":"52010;52010",
    "addr:street":"Viale Martiri Della Liberta\u0300",
    "iso:country":"IT",
    "sg:address":"Viale Martiri Della Libert\u00e0 144/a 52010 Subbiano",
    "sg:city":"Subbiano",
    "sg:classifiers":[
        {
            "category":"Autos & Motor Vehicles",
            "subcategory":"Motorcycle Sales",
            "type":"Retail Goods"
        }
    ],
    "sg:phone":"+39 0575 420435",
    "sg:postcode":"52010",
    "sg:province":"Arezzo",
    "sg:tags":[
        "press",
        "eccentric"
    ],
    "sg:website":"www.ompsa.com",
    "wof:name":"Ompsa Srl",
    "wof:placetype":"venue"
},
  "geometry": {"coordinates":[11.870492,43.578735],"type":"Point"}
}