{
  "type": "Feature",
  "properties": {
    "iso:country":"IT",
    "sg:address":"Via Borsari 31/a 43100 Parma",
    "sg:city":"Parma",
    "sg:classifiers":[
        {
            "category":"Government",
            "subcategory":"Fire Station",
            "type":"Public Place"
        }
    ],
    "sg:phone":"+39 0521 983955",
    "sg:postcode":"43100",
    "sg:province":"Parma",
    "sg:tags":[
        "heating",
        "accessory",
        "ventilation",
        "air conditioning"
    ],
    "wof:name":"Tgk Europe S.r.l.",
    "wof:placetype":"venue"
},
  "geometry": {"coordinates":[10.29492,44.823208],"type":"Point"}
}