{
  "type": "Feature",
  "properties": {
    "iso:country":"IT",
    "sg:address":"20129 Milano",
    "sg:city":"Milano",
    "sg:orig_category":"Banche E Servizi Finanziari. Avvocati, Notai E Servizi Legali",
    "sg:phone":"+39 02 7611 3190",
    "sg:postcode":"20129",
    "sg:province":"Milano",
    "sg:website":"http://www.gmcitalia.it",
    "wof:name":"Gmc Global Management Srl",
    "wof:placetype":"venue"
},
  "geometry": {"coordinates":[9.212657,45.472752],"type":"Point"}
}