{
  "type": "Feature",
  "properties": {
    "iso:country":"IT",
    "sg:address":"59015 Carmignano",
    "sg:city":"Carmignano",
    "sg:orig_category":"Tessuti E Stoffe. Forniture Per Attivita' Industriali",
    "sg:phone":"+39 055 871 0200",
    "sg:postcode":"59015",
    "sg:province":"Prato",
    "wof:name":"Co.te.co Srl",
    "wof:placetype":"venue"
},
  "geometry": {"coordinates":[11.071518,43.791569],"type":"Point"}
}