{
  "type": "Feature",
  "properties": {
    "iso:country":"IT",
    "sg:address":"95121 Catania",
    "sg:city":"Catania",
    "sg:orig_category":"Nautica. Forniture Per Attivita' Commerciali Ed Artigianali",
    "sg:phone":"+39 095 341987",
    "sg:postcode":"95121",
    "sg:province":"Catania",
    "wof:name":"Amorini Luigi",
    "wof:placetype":"venue"
},
  "geometry": {"coordinates":[15.087129,37.498737],"type":"Point"}
}