{
  "type": "Feature",
  "properties": {
    "addr:full":"25121 Brescia Brescia Brescia 25121",
    "addr:postcode":"25121;25121",
    "iso:country":"IT",
    "sg:address":"25121 Brescia",
    "sg:city":"Brescia",
    "sg:orig_category":"Gioiellerie E Oreficerie - Vendita Al Dettaglio",
    "sg:phone":"+39 030 377 3661",
    "sg:postcode":"25121",
    "sg:province":"Brescia",
    "sg:website":"http://www.anticoro.it",
    "wof:name":"Bonetti Alessandro",
    "wof:placetype":"venue"
},
  "geometry": {"coordinates":[10.2233,45.53368],"type":"Point"}
}