{
  "type": "Feature",
  "properties": {
    "addr:full":"41100 Modena Modena Modena 41100",
    "addr:postcode":"41100;41100",
    "iso:country":"IT",
    "sg:address":"41100 Modena",
    "sg:city":"Modena",
    "sg:orig_category":"Termotecnica E Riscaldamento, Apparecchiature E Servizi",
    "sg:phone":"+39 059 828600",
    "sg:postcode":"41100",
    "sg:province":"Modena",
    "wof:name":"Calor Modena Di Mai Enea",
    "wof:placetype":"venue"
},
  "geometry": {"coordinates":[10.901141,44.654007],"type":"Point"}
}