{
  "type": "Feature",
  "properties": {
    "iso:country":"IT",
    "sg:address":"Via R. Cadorna, 24; Torino; 10136",
    "sg:city":"Torino",
    "sg:classifiers":[
        {
            "category":"Banks & Credit Unions",
            "subcategory":"Bank",
            "type":"Services"
        }
    ],
    "sg:phone":"+39 011 329 0046",
    "sg:postcode":"10136",
    "sg:province":"Torino",
    "wof:name":"Banco Ambrosiano Veneto Spa",
    "wof:placetype":"venue"
},
  "geometry": {"coordinates":[7.647536,45.044613],"type":"Point"}
}