{
  "type": "Feature",
  "properties": {
    "iso:country":"IT",
    "sg:address":"10040 Stupinigi",
    "sg:orig_category":"Riparazione Dei Mezzi Di Trasporto. Servizi Ausiliari Dei Mezzi Di Trasporto",
    "sg:phone":"+39 011 358 6611",
    "sg:postcode":"10040",
    "sg:province":"Torino",
    "wof:name":"Arvin Exhaust Spa",
    "wof:placetype":"venue"
},
  "geometry": {"coordinates":[7.610468,45.007584],"type":"Point"}
}