{
  "type": "Feature",
  "properties": {
    "iso:country":"IT",
    "sg:address":"00187 Roma",
    "sg:city":"Roma",
    "sg:orig_category":"Servizi Al Turismo. Ambasciate Ed Enti Internazionali",
    "sg:phone":"+39 06 678 0530",
    "sg:postcode":"00187",
    "sg:province":"Roma",
    "wof:name":"Consolato Seychelles",
    "wof:placetype":"venue"
},
  "geometry": {"coordinates":[12.483439,41.902351],"type":"Point"}
}