{
  "type": "Feature",
  "properties": {
    "iso:country":"IT",
    "sg:address":"26041 Roncadello",
    "sg:city":"Roncadello",
    "sg:orig_category":"Tessuti Arredamento, Tende E Tappeti",
    "sg:phone":"+39 0375 59132",
    "sg:postcode":"26041",
    "sg:province":"Cremona",
    "wof:name":"Rosa Pietro & Figli (s.n.c.)",
    "wof:placetype":"venue"
},
  "geometry": {"coordinates":[10.474793,44.946335],"type":"Point"}
}