{
  "type": "Feature",
  "properties": {
    "iso:country":"IT",
    "sg:address":"47814 Bellaria Igea Marina",
    "sg:city":"Bellaria",
    "sg:orig_category":"Impiantistica E Prodotti Tecnologici Per Edilizia. Elettrotecnica Industriale, Prodotti E Apparecchiature. Elettrotecnica Professionale E Di Consumo",
    "sg:phone":"+39 0541 330041",
    "sg:postcode":"47814",
    "sg:province":"Rimini",
    "wof:name":"Elettrocentro 2 Di Boschetti Claudio & C. Snc",
    "wof:placetype":"venue"
},
  "geometry": {"coordinates":[12.470168,44.128994],"type":"Point"}
}