{
  "type": "Feature",
  "properties": {
    "addr:full":"20158 Milano Milano Milano 20158",
    "addr:postcode":"20158;20158",
    "iso:country":"IT",
    "sg:address":"20158 Milano",
    "sg:city":"Milano",
    "sg:orig_category":"Prodotti Alimentari",
    "sg:phone":"+39 02 376 0582",
    "sg:postcode":"20158",
    "sg:province":"Milano",
    "wof:name":"Galantino Angelo",
    "wof:placetype":"venue"
},
  "geometry": {"coordinates":[9.1761693954,45.5044555664],"type":"Point"}
}