{
  "type": "Feature",
  "properties": {
    "iso:country":"IT",
    "sg:address":"Via Julius Durst 20a 39042 Bressanone",
    "sg:city":"Bressanone",
    "sg:orig_category":"Ladies' Shoes",
    "sg:phone":"+39 0472 270711",
    "sg:postcode":"39042",
    "sg:province":"Bolzano/Bozen",
    "sg:website":"www.interga.it",
    "wof:name":"Interga S.p.a.",
    "wof:placetype":"venue"
},
  "geometry": {"coordinates":[11.644151,46.693684],"type":"Point"}
}