{
  "type": "Feature",
  "properties": {
    "iso:country":"IT",
    "sg:address":"20016 Cerchiate",
    "sg:city":"Cerchiate",
    "sg:orig_category":"Trattamenti Termici E Superficiali Metalli, Galvanotecnica",
    "sg:phone":"+39 02 353 4024",
    "sg:postcode":"20016",
    "sg:province":"Milano",
    "wof:name":"T.s.t. Trattamenti Termici Speciali (s.r.l.)",
    "wof:placetype":"venue"
},
  "geometry": {"coordinates":[9.082224,45.514225],"type":"Point"}
}