{
  "type": "Feature",
  "properties": {
    "iso:country":"IT",
    "sg:address":"10099 San Mauro Torinese",
    "sg:city":"San Mauro Torinese",
    "sg:orig_category":"Marketing E Ricerche Di Mercato",
    "sg:phone":"+39 011 222 7411",
    "sg:postcode":"10099",
    "sg:province":"Torino",
    "sg:website":"http://www.cemit.it",
    "wof:name":"Cemit Interactive Media Spa",
    "wof:placetype":"venue"
},
  "geometry": {"coordinates":[7.750328,45.115276],"type":"Point"}
}