{
  "type": "Feature",
  "properties": {
    "addr:full":"Via Mauri 4 21010 Besnate Besnate Varese 21010",
    "addr:housenumber":"4",
    "addr:postcode":"21010;21010",
    "addr:street":"Via Mauri",
    "iso:country":"IT",
    "sg:address":"Via Mauri 4 21010 Besnate",
    "sg:city":"Besnate",
    "sg:classifiers":[
        {
            "category":"Structure",
            "subcategory":"Warehouse",
            "type":"Public Place"
        }
    ],
    "sg:phone":"+39 0331 275316",
    "sg:postcode":"21010",
    "sg:province":"Varese",
    "sg:tags":[
        "air-conditioning",
        "system"
    ],
    "sg:website":"www.mariel.it",
    "wof:name":"Mariel Srl",
    "wof:placetype":"venue"
},
  "geometry": {"coordinates":[8.762689,45.699009],"type":"Point"}
}