{
  "type": "Feature",
  "properties": {
    "iso:country":"IT",
    "sg:address":"Via A Moro 4; Villanova Sull'arda; 29010",
    "sg:city":"Villanova",
    "sg:classifiers":[
        {
            "category":"Banks & Credit Unions",
            "subcategory":"Bank",
            "type":"Services"
        }
    ],
    "sg:phone":"+39 0523 837122",
    "sg:postcode":"29010",
    "sg:province":"Piacenza",
    "wof:name":"Cassa Di Risparmio, Di Parma E Piacenza Spa",
    "wof:placetype":"venue"
},
  "geometry": {"coordinates":[9.997403,45.026646],"type":"Point"}
}