{
  "type": "Feature",
  "properties": {
    "iso:country":"IT",
    "sg:address":"16121 Genova",
    "sg:city":"Genova",
    "sg:orig_category":"Macchine, Impianti Ed Attrezzature Industria Chimica. Attrezzature E Forniture Per Officine Riparazione E Servizi Ausiliari",
    "sg:phone":"+39 010 553 2221",
    "sg:postcode":"16121",
    "sg:province":"Genova",
    "wof:name":"P.c.m. Srl",
    "wof:placetype":"venue"
},
  "geometry": {"coordinates":[8.941298,44.402466],"type":"Point"}
}