{
  "type": "Feature",
  "properties": {
    "iso:country":"IT",
    "sg:address":"20144 Milano",
    "sg:city":"Milano",
    "sg:orig_category":"Servizi Ausiliari Di Certificati, Riproduzioni, Disegni E Foto",
    "sg:phone":"+39 02 670 4396",
    "sg:postcode":"20144",
    "sg:province":"Milano",
    "sg:website":"http://breatheweb.com/washington",
    "wof:name":"Agenzia Washington Di B.fedriga Snc",
    "wof:placetype":"venue"
},
  "geometry": {"coordinates":[9.16492,45.460064],"type":"Point"}
}