{
  "type": "Feature",
  "properties": {
    "iso:country":"IT",
    "sg:address":"20131 Milano",
    "sg:city":"Milano",
    "sg:orig_category":"Servizi Vari Di Interesse Pubblico",
    "sg:phone":"+39 02 2951 7438",
    "sg:postcode":"20131",
    "sg:province":"Milano",
    "wof:name":"Studio Lucia Pavesi Sas Di M.r.lucia Pavesi & C.",
    "wof:placetype":"venue"
},
  "geometry": {"coordinates":[9.21639,45.485172],"type":"Point"}
}