{
  "type": "Feature",
  "properties": {
    "iso:country":"IT",
    "sg:address":"80039 Saviano",
    "sg:city":"Saviano",
    "sg:orig_category":"Cartotecnica E Servizi. Composizione, Stampa E Confezione. Servizi E Lavori Industria Delle Materie Plastiche. Servizi Per Imballaggio E Confezionamento",
    "sg:phone":"+39 081 511 0433",
    "sg:postcode":"80039",
    "sg:province":"Napoli",
    "wof:name":"La Marca Giovambattista",
    "wof:placetype":"venue"
},
  "geometry": {"coordinates":[14.499702,40.914898],"type":"Point"}
}