{
  "type": "Feature",
  "properties": {
    "iso:country":"IT",
    "sg:address":"35037 Teolo",
    "sg:city":"Teolo",
    "sg:orig_category":"Lavanderie Industriali E Noleggio Biancheria",
    "sg:phone":"+39 049 990 2748",
    "sg:postcode":"35037",
    "sg:province":"Padova",
    "wof:name":"Lavanderia Campesato Srl",
    "wof:placetype":"venue"
},
  "geometry": {"coordinates":[11.78407,45.349194],"type":"Point"}
}