{
  "type": "Feature",
  "properties": {
    "addr:full":"5/a, Via Statuto 21013 Gallarate Gallarate Varese 21013",
    "addr:housenumber":"5 / a",
    "addr:postcode":"21013;21013",
    "addr:street":"Via Statuto",
    "iso:country":"IT",
    "sg:address":"5/a, Via Statuto 21013 Gallarate",
    "sg:city":"Gallarate",
    "sg:classifiers":[
        {
            "category":"Shopping",
            "subcategory":"Clothing, Apparel, & Fashions",
            "type":"Retail Goods"
        }
    ],
    "sg:phone":"+39 0331 795744",
    "sg:postcode":"21013",
    "sg:province":"Varese",
    "sg:tags":[
        "clothes"
    ],
    "wof:name":"Calzificio Fratelli Puricelli (s.a.s.)",
    "wof:placetype":"venue"
},
  "geometry": {"coordinates":[8.826385,45.817604],"type":"Point"}
}