{
  "type": "Feature",
  "properties": {
    "iso:country":"IT",
    "sg:address":"148, Via S. Donato 40127 Bologna",
    "sg:city":"Bologna",
    "sg:classifiers":[
        {
            "category":"Professional",
            "subcategory":"Computer Services",
            "type":"Services"
        }
    ],
    "sg:phone":"+39 39051511932",
    "sg:postcode":"40127",
    "sg:province":"Bologna",
    "sg:tags":[
        "information",
        "technology"
    ],
    "wof:name":"Datamatic S.p.a.",
    "wof:placetype":"venue"
},
  "geometry": {"coordinates":[11.366362,44.540157],"type":"Point"}
}