{
  "type": "Feature",
  "properties": {
    "addr:full":"92024 Canicatt\u00ec Agrigento 92024",
    "addr:postcode":"92024;92024",
    "iso:country":"IT",
    "sg:address":"92024 Canicatt\u00ec",
    "sg:orig_category":"Arredamento Negozi E Supermercati",
    "sg:phone":"+39 0922 853977",
    "sg:postcode":"92024",
    "sg:province":"Agrigento",
    "wof:name":"Studio Arreda Srl",
    "wof:placetype":"venue"
},
  "geometry": {"coordinates":[13.841773,37.353031],"type":"Point"}
}