{
  "type": "Feature",
  "properties": {
    "iso:country":"IT",
    "sg:address":"3, Via Chiassatello 56122 Pisa",
    "sg:city":"Pisa",
    "sg:orig_category":"Miscellaneous Products",
    "sg:phone":"+39 390 502 3128",
    "sg:postcode":"56122",
    "sg:province":"Pisa",
    "wof:name":"Tnt A.l. (s.p.a.)",
    "wof:placetype":"venue"
},
  "geometry": {"coordinates":[10.3825149536,43.7074584961],"type":"Point"}
}