{
  "type": "Feature",
  "properties": {
    "addr:full":"31010 Mareno Di Piave Mareno di Piave Treviso 31010",
    "addr:housenumber":"di piave",
    "addr:postcode":"31010;31010",
    "iso:country":"IT",
    "sg:address":"31010 Mareno Di Piave",
    "sg:city":"Mareno di Piave",
    "sg:orig_category":"Arredo Camera Letto E Complementi",
    "sg:phone":"+39 0438 488188",
    "sg:postcode":"31010",
    "sg:province":"Treviso",
    "wof:name":"Mobili D'arredamento Di Dare Giovanna Sas & C.",
    "wof:placetype":"venue"
},
  "geometry": {"coordinates":[12.330819,45.830856],"type":"Point"}
}