{
  "type": "Feature",
  "properties": {
    "iso:country":"IT",
    "sg:address":"98122 Messina",
    "sg:city":"Messina",
    "sg:orig_category":"Consulenza Amministrativa, Fiscale E Tributaria",
    "sg:phone":"+39 090 774595",
    "sg:postcode":"98122",
    "sg:province":"Messina",
    "wof:name":"Cacciola Giuseppe",
    "wof:placetype":"venue"
},
  "geometry": {"coordinates":[15.538645,38.199047],"type":"Point"}
}