{
  "type": "Feature",
  "properties": {
    "addr:full":"Loc Battaina 24059 Urgnano Urgnano Bergamo 24059",
    "addr:postcode":"24059;24059",
    "addr:street":"Loc Battaina",
    "iso:country":"IT",
    "sg:address":"Loc Battaina 24059 Urgnano",
    "sg:city":"Urgnano",
    "sg:classifiers":[
        {
            "category":"Home & Garden",
            "subcategory":"Carpets & Floor Coverings",
            "type":"Retail Goods"
        }
    ],
    "sg:phone":"+39 035 893005",
    "sg:postcode":"24059",
    "sg:province":"Bergamo",
    "sg:tags":[
        "animal",
        "skin"
    ],
    "wof:name":"Conceria Di Urgnano Srl",
    "wof:placetype":"venue"
},
  "geometry": {"coordinates":[9.669952,45.694904],"type":"Point"}
}