{
  "type": "Feature",
  "properties": {
    "iso:country":"IT",
    "sg:address":"12070 Sale Delle Langhe",
    "sg:city":"Sale delle Langhe",
    "sg:orig_category":"Impiantistica E Prodotti Tecnologici Per Edilizia",
    "sg:phone":"+39 0174 75151",
    "sg:postcode":"12070",
    "sg:province":"Cuneo",
    "wof:name":"Giordano Enrico",
    "wof:placetype":"venue"
},
  "geometry": {"coordinates":[8.081259,44.396259],"type":"Point"}
}