{
  "type": "Feature",
  "properties": {
    "iso:country":"IT",
    "sg:address":"90139 Palermo",
    "sg:city":"Palermo",
    "sg:orig_category":"Abbigliamento - Produzione E Ingrosso",
    "sg:phone":"+39 091 329003",
    "sg:postcode":"90139",
    "sg:province":"Palermo",
    "wof:name":"Zone Berlino",
    "wof:placetype":"venue"
},
  "geometry": {"coordinates":[13.35594,38.12727],"type":"Point"}
}