{
  "type": "Feature",
  "properties": {
    "iso:country":"IT",
    "sg:address":"20017 Rho",
    "sg:city":"Rho",
    "sg:orig_category":"Filati E Materie Prime Tessili. Prodotti E Manufatti In Materie Plastiche",
    "sg:phone":"+39 02 931 2046",
    "sg:postcode":"20017",
    "sg:province":"Milano",
    "wof:name":"Esseplast Di Spada",
    "wof:placetype":"venue"
},
  "geometry": {"coordinates":[9.0407991409,45.5446777344],"type":"Point"}
}