{
  "type": "Feature",
  "properties": {
    "addr:full":"40124 Bologna Bologna Bologna 40124",
    "addr:postcode":"40124;40124",
    "iso:country":"IT",
    "sg:address":"40124 Bologna",
    "sg:city":"Bologna",
    "sg:orig_category":"Forniture Per Congressi, Fiere E Manifestazioni",
    "sg:phone":"+39 051 224392",
    "sg:postcode":"40124",
    "sg:province":"Bologna",
    "sg:website":"http://www.zingaroclub.com",
    "wof:name":"Zingaro' Soc.coop.r.l.",
    "wof:placetype":"venue"
},
  "geometry": {"coordinates":[11.3483819962,44.491317749],"type":"Point"}
}