{
  "type": "Feature",
  "properties": {
    "addr:full":"15/a, Strada Donella 46029 Suzzara Suzzara Mantova 46029",
    "addr:housenumber":"15 / a",
    "addr:postcode":"46029;46029",
    "addr:street":"Strada Donella",
    "iso:country":"IT",
    "sg:address":"15/a, Strada Donella 46029 Suzzara",
    "sg:city":"Suzzara",
    "sg:classifiers":[
        {
            "category":"Shopping",
            "type":"Retail Goods"
        }
    ],
    "sg:phone":"+39 0376 532255",
    "sg:postcode":"46029",
    "sg:province":"Mantova",
    "sg:tags":[
        "finished",
        "-",
        "metallic"
    ],
    "wof:name":"B.c.l. Di Bottazzi Terenzio & C. (s.n.c.)",
    "wof:placetype":"venue"
},
  "geometry": {"coordinates":[10.7976980209,45.1603660583],"type":"Point"}
}