{
  "type": "Feature",
  "properties": {
    "iso:country":"IT",
    "sg:address":"10071 Borgaro Torinese",
    "sg:city":"Borgaro Torinese",
    "sg:orig_category":"Servizi Per Lo Sport E Il Tempo Libero. Servizi Al Turismo. Servizi Ausiliari Dei Mezzi Di Trasporto. Servizi Ausiliari Per Il Trasporto",
    "sg:phone":"+39 011 450 1071",
    "sg:postcode":"10071",
    "sg:province":"Torino",
    "sg:website":"http://www.italrent.it",
    "wof:name":"Italrent Spa",
    "wof:placetype":"venue"
},
  "geometry": {"coordinates":[7.65577,45.141888],"type":"Point"}
}