{
  "type": "Feature",
  "properties": {
    "iso:country":"IT",
    "sg:address":"29, Via Antonello Da Messina 95021 Aci Castello",
    "sg:city":"Aci Castello",
    "sg:classifiers":[
        {
            "category":"Manufacturing",
            "subcategory":"Tools & Machinery",
            "type":"Manufacturing & Wholesale Goods"
        }
    ],
    "sg:phone":"+39 095 711 1070",
    "sg:postcode":"95021",
    "sg:province":"Catania",
    "sg:tags":[
        "environment",
        "equipment",
        "-"
    ],
    "wof:name":"Tekind (s.r.l.)",
    "wof:placetype":"venue"
},
  "geometry": {"coordinates":[15.135466,37.541496],"type":"Point"}
}