{
  "type": "Feature",
  "properties": {
    "addr:full":"00146 Roma Roma Roma 00146",
    "addr:postcode":"00146;00146",
    "iso:country":"IT",
    "sg:address":"00146 Roma",
    "sg:city":"Roma",
    "sg:orig_category":"Nautica. Automobili E Mezzi Di Trasporto",
    "sg:phone":"+39 06 541 1464",
    "sg:postcode":"00146",
    "sg:province":"Roma",
    "wof:name":"Itama Cantieri Navali Spa",
    "wof:placetype":"venue"
},
  "geometry": {"coordinates":[12.468783,41.85133],"type":"Point"}
}