{
  "type": "Feature",
  "properties": {
    "addr:full":"14, Viale V.veneto 56031 Bientina Bientina Pisa 56031",
    "addr:housenumber":"14",
    "addr:postcode":"56031;56031",
    "addr:street":"Viale V.Veneto",
    "iso:country":"IT",
    "sg:address":"14, Viale V.veneto 56031 Bientina",
    "sg:city":"Bientina",
    "sg:classifiers":[
        {
            "category":"Shopping",
            "subcategory":"Stationery & Office Supplies",
            "type":"Retail Goods"
        }
    ],
    "sg:phone":"+39 0587 757175",
    "sg:postcode":"56031",
    "sg:province":"Pisa",
    "sg:tags":[
        "professional"
    ],
    "wof:name":"Blob Arredamenti Di Ciacchini C. & C S.a.s.",
    "wof:placetype":"venue"
},
  "geometry": {"coordinates":[10.3965845108,43.7161369324],"type":"Point"}
}