{
  "type": "Feature",
  "properties": {
    "addr:full":"V Isonzo 36/42; Chiusi; 53043 Chiusi Siena 53043",
    "addr:housenumber":"36 / 42",
    "addr:postcode":"53043;53043",
    "addr:street":"V Isonzo",
    "iso:country":"IT",
    "sg:address":"V Isonzo 36/42; Chiusi; 53043",
    "sg:city":"Chiusi",
    "sg:classifiers":[
        {
            "category":"Banks & Credit Unions",
            "subcategory":"Bank",
            "type":"Services"
        }
    ],
    "sg:phone":"+39 0578 20061",
    "sg:postcode":"53043",
    "sg:province":"Siena",
    "wof:name":"Cassa Rurale & Artigiana",
    "wof:placetype":"venue"
},
  "geometry": {"coordinates":[11.955129,43.003342],"type":"Point"}
}