{
  "type": "Feature",
  "properties": {
    "iso:country":"IT",
    "sg:address":"117, Via G.matteotti 29020 Gossolengo",
    "sg:city":"Gossolengo",
    "sg:classifiers":[
        {
            "category":"Shopping",
            "subcategory":"Gifts & Souvenirs",
            "type":"Retail Goods"
        }
    ],
    "sg:phone":"+39 0523 778511",
    "sg:postcode":"29020",
    "sg:province":"Piacenza",
    "wof:name":"Omnia Pubblicita",
    "wof:placetype":"venue"
},
  "geometry": {"coordinates":[9.621749,45.003372],"type":"Point"}
}