{
  "type": "Feature",
  "properties": {
    "iso:country":"IT",
    "sg:address":"25125 Brescia",
    "sg:city":"Brescia",
    "sg:orig_category":"Motori Ed Organi Di Trasmissione. Ricambi E Componenti Dei Mezzi Di Trasporto",
    "sg:phone":"+39 030 347166",
    "sg:postcode":"25125",
    "sg:province":"Brescia",
    "wof:name":"T.i.m.a.f. Srl",
    "wof:placetype":"venue"
},
  "geometry": {"coordinates":[10.1897649765,45.5273399353],"type":"Point"}
}