{
  "type": "Feature",
  "properties": {
    "addr:full":"Strada Macello A Poggioreale 160/e 80143 Napoli Napoli Napoli 80143",
    "addr:housenumber":"160 / e",
    "addr:postcode":"80143;80143",
    "addr:street":"Strada Macello A Poggioreale",
    "iso:country":"IT",
    "sg:address":"Strada Macello A Poggioreale 160/e 80143 Napoli",
    "sg:city":"Napoli",
    "sg:classifiers":[
        {
            "category":"Professional",
            "subcategory":"Art Services",
            "type":"Services"
        }
    ],
    "sg:phone":"+39 081 759 0721",
    "sg:postcode":"80143",
    "sg:province":"Napoli",
    "sg:tags":[
        "glass",
        "article"
    ],
    "wof:name":"Franco Srl",
    "wof:placetype":"venue"
},
  "geometry": {"coordinates":[14.293479,40.902172],"type":"Point"}
}