{
  "type": "Feature",
  "properties": {
    "iso:country":"IT",
    "sg:address":"56126 Pisa",
    "sg:city":"Pisa",
    "sg:orig_category":"Ristorazione E Locali Pubblici Affini. Servizi Ausiliari Di Ristorazione E Di Intrattenimento",
    "sg:phone":"+39 050 562101",
    "sg:postcode":"56126",
    "sg:province":"Pisa",
    "wof:name":"Hotel Il Giardino",
    "wof:placetype":"venue"
},
  "geometry": {"coordinates":[10.39752,43.719376],"type":"Point"}
}