{
  "type": "Feature",
  "properties": {
    "addr:full":"426, Via Trieste 80036 Palma Campania Palma Campania Napoli 80036",
    "addr:housenumber":"426",
    "addr:postcode":"80036;80036",
    "addr:street":"Via Trieste",
    "iso:country":"IT",
    "sg:address":"426, Via Trieste 80036 Palma Campania",
    "sg:city":"Palma Campania",
    "sg:classifiers":[
        {
            "category":"Shopping",
            "subcategory":"Clothing, Apparel, & Fashions",
            "type":"Retail Goods"
        }
    ],
    "sg:phone":"+39 081 824 1793",
    "sg:postcode":"80036",
    "sg:province":"Napoli",
    "sg:tags":[
        "clothes"
    ],
    "wof:name":"Chery Confezioni S.r.l.",
    "wof:placetype":"venue"
},
  "geometry": {"coordinates":[14.543404,40.86644],"type":"Point"}
}