{
  "type": "Feature",
  "properties": {
    "iso:country":"IT",
    "sg:address":"15, Via Xx Settembre 48018 Faenza",
    "sg:city":"Faenza",
    "sg:classifiers":[
        {
            "category":"Professional",
            "subcategory":"Printing & Photocopies",
            "type":"Services"
        }
    ],
    "sg:phone":"+39 39054621400",
    "sg:postcode":"48018",
    "sg:province":"Ravenna",
    "wof:name":"Litografie Artistiche Faentine",
    "wof:placetype":"venue"
},
  "geometry": {"coordinates":[12.1965713501,44.4157295227],"type":"Point"}
}