{
  "type": "Feature",
  "properties": {
    "addr:full":"20154 Milano Milano Milano 20154",
    "addr:postcode":"20154;20154",
    "iso:country":"IT",
    "sg:address":"20154 Milano",
    "sg:city":"Milano",
    "sg:orig_category":"Prodotti Di Base E Forniture Per Industria Alimentare E Bevande. Forniture E Materiali Per Imballaggio E Confezionamento",
    "sg:phone":"+39 02 315118",
    "sg:postcode":"20154",
    "sg:province":"Milano",
    "wof:name":"Vintec Srl",
    "wof:placetype":"venue"
},
  "geometry": {"coordinates":[9.1638565063,45.4828414917],"type":"Point"}
}