{
  "type": "Feature",
  "properties": {
    "iso:country":"IT",
    "sg:address":"6, Via Calate 31014 Colle Umberto",
    "sg:city":"Colle Umberto",
    "sg:classifiers":[
        {
            "category":"Professional",
            "subcategory":"Engineering",
            "type":"Services"
        }
    ],
    "sg:phone":"+39 0438 200193",
    "sg:postcode":"31014",
    "sg:province":"Treviso",
    "sg:tags":[
        "machine",
        "-",
        "mechanical"
    ],
    "wof:name":"Mittel Group S.r.l.",
    "wof:placetype":"venue"
},
  "geometry": {"coordinates":[12.329512,45.940575],"type":"Point"}
}