{
  "type": "Feature",
  "properties": {
    "iso:country":"IT",
    "sg:address":"Ctr Bagni Isca 84020 Colliano",
    "sg:city":"Colliano",
    "sg:classifiers":[
        {
            "category":"Personal",
            "subcategory":"Shoe Repair & Shine",
            "type":"Services"
        }
    ],
    "sg:phone":"+39 0828 995520",
    "sg:postcode":"84020",
    "sg:province":"Salerno",
    "sg:tags":[
        "protective",
        "safety",
        "boots"
    ],
    "sg:website":"www.lewer.it",
    "wof:name":"Lewer Calzature Tecniche S.r.l.",
    "wof:placetype":"venue"
},
  "geometry": {"coordinates":[14.765912,40.677956],"type":"Point"}
}