{
  "type": "Feature",
  "properties": {
    "iso:country":"IT",
    "sg:address":"35020 Albignasego",
    "sg:city":"Albignasego",
    "sg:orig_category":"Pompe. Elettrotecnica Industriale, Prodotti E Apparecchiature",
    "sg:phone":"+39 049 681146",
    "sg:postcode":"35020",
    "sg:province":"Padova",
    "wof:name":"Elettromeccanica Creponi",
    "wof:placetype":"venue"
},
  "geometry": {"coordinates":[11.8682966232,45.3484458923],"type":"Point"}
}