{
  "type": "Feature",
  "properties": {
    "iso:country":"IT",
    "sg:address":"29010 Rottofreno",
    "sg:city":"Rottofreno",
    "sg:orig_category":"Servizi E Lavori Per Edilizia E Lavori Pubblici",
    "sg:phone":"+39 0523 769829",
    "sg:postcode":"29010",
    "sg:province":"Piacenza",
    "wof:name":"Merli F.lli",
    "wof:placetype":"venue"
},
  "geometry": {"coordinates":[9.606375,45.052189],"type":"Point"}
}