{
  "type": "Feature",
  "properties": {
    "iso:country":"IT",
    "sg:address":"Via Dell' Artigianato 36043 Camisano Vicentino",
    "sg:city":"Camisano Vicentino",
    "sg:classifiers":[
        {
            "category":"Shopping",
            "subcategory":"Crafts & Fabrics",
            "type":"Retail Goods"
        }
    ],
    "sg:phone":"+39 0444 410760",
    "sg:postcode":"36043",
    "sg:province":"Vicenza",
    "sg:tags":[
        "linen"
    ],
    "wof:name":"Noloinvest",
    "wof:placetype":"venue"
},
  "geometry": {"coordinates":[11.7120189667,45.5063743591],"type":"Point"}
}