{
  "type": "Feature",
  "properties": {
    "iso:country":"IT",
    "sg:address":"Via A. Moro, 121; Piano Di Sorrento; 19020",
    "sg:classifiers":[
        {
            "category":"Banks & Credit Unions",
            "subcategory":"Bank",
            "type":"Services"
        }
    ],
    "sg:phone":"+39 0187 930012",
    "sg:postcode":"19020",
    "sg:province":"La Spezia",
    "wof:name":"Cassa Di Risparmio Della Spezia",
    "wof:placetype":"venue"
},
  "geometry": {"coordinates":[9.767869,44.244793],"type":"Point"}
}