{
  "type": "Feature",
  "properties": {
    "iso:country":"IT",
    "sg:address":"Via Dell'industria 21 35010 Borgoricco",
    "sg:city":"Borgoricco",
    "sg:orig_category":"Rollers And Cylinders, Rubber And Plastic-coated",
    "sg:phone":"+39 049 933 5733",
    "sg:postcode":"35010",
    "sg:province":"Padova",
    "wof:name":"A. Piovan Srl",
    "wof:placetype":"venue"
},
  "geometry": {"coordinates":[11.955914,45.534458],"type":"Point"}
}