{
  "type": "Feature",
  "properties": {
    "iso:country":"IT",
    "sg:address":"Contrada Piana 82030 Ponte",
    "sg:city":"Ponte",
    "sg:classifiers":[
        {
            "category":"Real Estate",
            "subcategory":"Architect",
            "type":"Services"
        }
    ],
    "sg:phone":"+39 0824 874705",
    "sg:postcode":"82030",
    "sg:province":"Benevento",
    "sg:tags":[
        "textile",
        "clothing"
    ],
    "wof:name":"Consab Srl",
    "wof:placetype":"venue"
},
  "geometry": {"coordinates":[14.685897,41.212711],"type":"Point"}
}