{
  "type": "Feature",
  "properties": {
    "iso:country":"IT",
    "sg:address":"35, Piazza Della Radio 00146 Roma",
    "sg:city":"Roma",
    "sg:classifiers":[
        {
            "category":"Autos & Motor Vehicles",
            "subcategory":"Automobile Sales",
            "type":"Retail Goods"
        }
    ],
    "sg:phone":"+39 39065536731",
    "sg:postcode":"00146",
    "sg:province":"Roma",
    "sg:tags":[
        "motor-cars"
    ],
    "wof:name":"Romana Auto Srl",
    "wof:placetype":"venue"
},
  "geometry": {"coordinates":[12.4669427872,41.8690986633],"type":"Point"}
}