{
  "type": "Feature",
  "properties": {
    "iso:country":"IT",
    "sg:address":"56017 San Giuliano Terme",
    "sg:city":"San Giuliano Terme",
    "sg:orig_category":"Prodotti E Manufatti In Gomma. Servizi E Lavori Industria Della Gomma. Ricambi E Componenti Dei Mezzi Di Trasporto. Riparazione Dei Mezzi Di Trasporto",
    "sg:phone":"+39 050 871045",
    "sg:postcode":"56017",
    "sg:province":"Pisa",
    "wof:name":"Bierre Auto Srl",
    "wof:placetype":"venue"
},
  "geometry": {"coordinates":[10.5038709641,43.7241134644],"type":"Point"}
}