{
  "type": "Feature",
  "properties": {
    "iso:country":"IT",
    "sg:address":"11, Via Pizzoli P. 40012 Calderara Di Reno",
    "sg:city":"Calderara di Reno",
    "sg:classifiers":[
        {
            "category":"Professional",
            "subcategory":"Engineering",
            "type":"Services"
        }
    ],
    "sg:phone":"+39 39051729073",
    "sg:postcode":"40012",
    "sg:province":"Bologna",
    "sg:tags":[
        "machine",
        "-",
        "mechanical"
    ],
    "wof:name":"Marchi Impianti (s.r.l.)",
    "wof:placetype":"venue"
},
  "geometry": {"coordinates":[11.268679,44.541077],"type":"Point"}
}