{
  "type": "Feature",
  "properties": {
    "addr:full":"5, Via Molini 36030 Zugliano Zugliano Vicenza 36030",
    "addr:postcode":"36030;36030",
    "addr:street":"Via Molini",
    "iso:country":"IT",
    "sg:address":"5, Via Molini 36030 Zugliano",
    "sg:city":"Zugliano",
    "sg:classifiers":[
        {
            "category":"Shopping",
            "subcategory":"Crafts & Fabrics",
            "type":"Retail Goods"
        }
    ],
    "sg:phone":"+39 0445 330155",
    "sg:postcode":"36030",
    "sg:province":"Vicenza",
    "wof:name":"Nuova Filatura Di Zugliano Srl",
    "wof:placetype":"venue"
},
  "geometry": {"coordinates":[11.540307045,45.5459060669],"type":"Point"}
}