{
  "type": "Feature",
  "properties": {
    "iso:country":"IT",
    "sg:address":"00137 Roma",
    "sg:city":"Roma",
    "sg:orig_category":"Impiantistica E Prodotti Tecnologici Per Edilizia. Termotecnica E Riscaldamento, Apparecchiature E Servizi",
    "sg:phone":"+39 06 823294",
    "sg:postcode":"00137",
    "sg:province":"Roma",
    "wof:name":"Gruppo Tecno Italia Srl",
    "wof:placetype":"venue"
},
  "geometry": {"coordinates":[12.550578,41.941227],"type":"Point"}
}