{
  "type": "Feature",
  "properties": {
    "iso:country":"IT",
    "sg:address":"00171 Roma",
    "sg:city":"Roma",
    "sg:orig_category":"Forniture Per Abbigliamento E Pelletterie. Forniture Per Attivita' Commerciali Ed Artigianali",
    "sg:phone":"+39 06 2180 3174",
    "sg:postcode":"00171",
    "sg:province":"Roma",
    "wof:name":"Alfieri Piacentino",
    "wof:placetype":"venue"
},
  "geometry": {"coordinates":[12.990691185,42.0101966858],"type":"Point"}
}