{
  "type": "Feature",
  "properties": {
    "iso:country":"IT",
    "sg:address":"00165 Roma",
    "sg:city":"Roma",
    "sg:orig_category":"Ambasciate Ed Enti Internazionali",
    "sg:phone":"+39 06 3936 6680",
    "sg:postcode":"00165",
    "sg:province":"Roma",
    "wof:name":"Ambasciata Presso La S. Sede Cuba",
    "wof:placetype":"venue"
},
  "geometry": {"coordinates":[12.449476,41.899689],"type":"Point"}
}