{
  "type": "Feature",
  "properties": {
    "iso:country":"IT",
    "sg:address":"20149 Milano",
    "sg:city":"Milano",
    "sg:orig_category":"Agenzie D'affari E Servizi Commerciali",
    "sg:phone":"+39 02 324694",
    "sg:postcode":"20149",
    "sg:province":"Milano",
    "wof:name":"Chiba Di Chiara Batello",
    "wof:placetype":"venue"
},
  "geometry": {"coordinates":[9.14837,45.490383],"type":"Point"}
}