{
  "type": "Feature",
  "properties": {
    "iso:country":"IT",
    "sg:address":"05018 Orvieto",
    "sg:city":"Orvieto",
    "sg:orig_category":"Depurazione E Trattamento Delle Acque - Impianti Ed Apparecchi",
    "sg:phone":"+39 0763 302545",
    "sg:postcode":"05018",
    "sg:province":"Terni",
    "wof:name":"Soc. Ire Snc",
    "wof:placetype":"venue"
},
  "geometry": {"coordinates":[12.140404,42.740887],"type":"Point"}
}