{
  "type": "Feature",
  "properties": {
    "iso:country":"IT",
    "sg:address":"39031 Brunico",
    "sg:city":"Brunico",
    "sg:classifiers":[
        {
            "category":"Sports & Exercise",
            "subcategory":"Tennis Court",
            "type":"Entertainment"
        }
    ],
    "sg:phone":"+39 0474 410206",
    "sg:postcode":"39031",
    "sg:province":"Bolzano/Bozen",
    "sg:tags":[
        "e",
        "lo",
        "tempo",
        "libero",
        "per",
        "impianti",
        "il",
        "attrezzature"
    ],
    "wof:name":"Liftmont S.n.c.",
    "wof:placetype":"venue"
},
  "geometry": {"coordinates":[11.948372,46.796349],"type":"Point"}
}