{
  "type": "Feature",
  "properties": {
    "addr:full":"00153 Roma Roma Roma 00153",
    "addr:postcode":"00153;00153",
    "iso:country":"IT",
    "sg:address":"00153 Roma",
    "sg:city":"Roma",
    "sg:orig_category":"Medicali Ed Elettromedicali Impianti Ed Apparecchi - Commercio",
    "sg:phone":"+39 06 589 7627",
    "sg:postcode":"00153",
    "sg:province":"Roma",
    "wof:name":"Golden Star Snc",
    "wof:placetype":"venue"
},
  "geometry": {"coordinates":[12.468639,41.87479],"type":"Point"}
}