{
  "type": "Feature",
  "properties": {
    "iso:country":"IT",
    "sg:address":"7, Via Della Chimica 28924 Verbania",
    "sg:city":"Verbania",
    "sg:classifiers":[
        {
            "category":"Food & Beverages",
            "subcategory":"Groceries & Convenience Stores",
            "type":"Retail Goods"
        }
    ],
    "sg:phone":"+39 0323 586764",
    "sg:postcode":"28924",
    "sg:province":"Verbano-Cusio-Ossola",
    "sg:tags":[
        "drink"
    ],
    "wof:name":"Partesa Verbano",
    "wof:placetype":"venue"
},
  "geometry": {"coordinates":[8.455497,45.931881],"type":"Point"}
}