{
  "type": "Feature",
  "properties": {
    "addr:full":"62, Via Bocca Di Gora E Tinaia 51039 Quarrata Quarrata Pistoia 51039",
    "addr:postcode":"51039;51039",
    "addr:street":"Via Bocca Di Gora E Tinaia",
    "iso:country":"IT",
    "sg:address":"62, Via Bocca Di Gora E Tinaia 51039 Quarrata",
    "sg:city":"Quarrata",
    "sg:classifiers":[
        {
            "category":"Home & Garden",
            "subcategory":"Home Furnishings",
            "type":"Retail Goods"
        }
    ],
    "sg:phone":"+39 39057372885",
    "sg:postcode":"51039",
    "sg:province":"Pistoia",
    "sg:tags":[
        "household"
    ],
    "wof:name":"Nuova Fustex Srl",
    "wof:placetype":"venue"
},
  "geometry": {"coordinates":[10.991994,43.856876],"type":"Point"}
}