{
  "type": "Feature",
  "properties": {
    "iso:country":"IT",
    "sg:address":"20123 Milano",
    "sg:city":"Milano",
    "sg:orig_category":"Servizi Culturali E Per Lo Spettacolo",
    "sg:phone":"+39 02 867347",
    "sg:postcode":"20123",
    "sg:province":"Milano",
    "wof:name":"Anna Nove Sas Di Maria Crespi Di Sarro-ernesto Di Sarro & C.",
    "wof:placetype":"venue"
},
  "geometry": {"coordinates":[9.176483,45.46804],"type":"Point"}
}