{
  "type": "Feature",
  "properties": {
    "addr:full":"20146 Milano Milano Milano 20146",
    "addr:postcode":"20146;20146",
    "iso:country":"IT",
    "sg:address":"20146 Milano",
    "sg:city":"Milano",
    "sg:orig_category":"Automazione E Macchine Per Ufficio",
    "sg:phone":"+39 02 4009 1320",
    "sg:postcode":"20146",
    "sg:province":"Milano",
    "wof:name":"A.b.c. Software Di A. Borghi & A. Cuneo (s.n.c.)",
    "wof:placetype":"venue"
},
  "geometry": {"coordinates":[9.142455,45.461338],"type":"Point"}
}