{
  "type": "Feature",
  "properties": {
    "iso:country":"IT",
    "sg:address":"Corso Del Popolo 170; Rovigo; 45100",
    "sg:city":"Rovigo",
    "sg:classifiers":[
        {
            "category":"Banks & Credit Unions",
            "subcategory":"Bank",
            "type":"Services"
        }
    ],
    "sg:phone":"+39 0425 24503",
    "sg:postcode":"45100",
    "sg:province":"Rovigo",
    "wof:name":"Banca Nazionale Del Lavoro Spa",
    "wof:placetype":"venue"
},
  "geometry": {"coordinates":[11.789608,45.070065],"type":"Point"}
}