{
  "type": "Feature",
  "properties": {
    "iso:country":"IT",
    "sg:address":"135, Corso Cavour 05018 Orvieto",
    "sg:city":"Orvieto",
    "sg:classifiers":[
        {
            "category":"Food & Beverages",
            "subcategory":"Groceries & Convenience Stores",
            "type":"Retail Goods"
        }
    ],
    "sg:phone":"+39 0763 341657",
    "sg:postcode":"05018",
    "sg:province":"Terni",
    "sg:tags":[
        "drink"
    ],
    "wof:name":"La Loggia Srl",
    "wof:placetype":"venue"
},
  "geometry": {"coordinates":[12.113471,42.718723],"type":"Point"}
}