{
  "type": "Feature",
  "properties": {
    "addr:full":"86021 Campochiaro Campobasso 86021",
    "addr:postcode":"86021;86021",
    "iso:country":"IT",
    "sg:address":"86021 Campochiaro",
    "sg:orig_category":"Prodotti Finiti Stampati. Forniture E Materiali Per Imballaggio E Confezionamento. Forniture Per Attivita' Commerciali Ed Artigianali",
    "sg:phone":"+39 0874 775270",
    "sg:postcode":"86021",
    "sg:province":"Campobasso",
    "sg:website":"http://www.pringraf.it",
    "wof:name":"Arti Grafiche Pringraf",
    "wof:placetype":"venue"
},
  "geometry": {"coordinates":[14.6647987366,41.5600852966],"type":"Point"}
}