{
  "type": "Feature",
  "properties": {
    "iso:country":"IT",
    "sg:address":"90039 Villabate",
    "sg:city":"Villabate",
    "sg:orig_category":"Ricambi E Componenti Dei Mezzi Di Trasporto",
    "sg:phone":"+39 091 491572",
    "sg:postcode":"90039",
    "sg:province":"Palermo",
    "wof:name":"Arduino In Lo Monaco Felicita",
    "wof:placetype":"venue"
},
  "geometry": {"coordinates":[13.442507,38.079361],"type":"Point"}
}