{
  "type": "Feature",
  "properties": {
    "iso:country":"IT",
    "sg:address":"31030 Casier",
    "sg:city":"Casier",
    "sg:orig_category":"Elettronica Professionale E Di Consumo. Automazione E Macchine Per Ufficio. Forniture Per Congressi, Fiere E Manifestazioni",
    "sg:phone":"+39 0422 634040",
    "sg:postcode":"31030",
    "sg:province":"Treviso",
    "wof:name":"Codex Srl",
    "wof:placetype":"venue"
},
  "geometry": {"coordinates":[12.260416,45.612],"type":"Point"}
}