{
  "type": "Feature",
  "properties": {
    "iso:country":"IT",
    "sg:address":"30175 Venezia",
    "sg:city":"Marghera",
    "sg:orig_category":"Onoranze E Pompe Funebri",
    "sg:phone":"+39 041 923439",
    "sg:postcode":"30175",
    "sg:province":"Venezia",
    "sg:website":"http://151.22.111.177",
    "wof:name":"Bonivento Luciano",
    "wof:placetype":"venue"
},
  "geometry": {"coordinates":[12.226504,45.477734],"type":"Point"}
}