{
  "type": "Feature",
  "properties": {
    "iso:country":"IT",
    "sg:address":"73055 Racale",
    "sg:city":"Racale",
    "sg:orig_category":"Arredamenti Ed Architettura D'interni",
    "sg:phone":"+39 0833 585694",
    "sg:postcode":"73055",
    "sg:province":"Lecce",
    "wof:name":"Gesto' Architettura D'interni Di Davide Podda",
    "wof:placetype":"venue"
},
  "geometry": {"coordinates":[18.098972,39.964001],"type":"Point"}
}