{
  "type": "Feature",
  "properties": {
    "addr:full":"65013 Citta' Sant'angelo Marina Pescara 65013",
    "addr:postcode":"65013;65013",
    "iso:country":"IT",
    "sg:address":"65013 Citta' Sant'angelo",
    "sg:city":"Marina",
    "sg:orig_category":"Cucine Per Comunita'",
    "sg:phone":"+39 085 950 6101",
    "sg:postcode":"65013",
    "sg:province":"Pescara",
    "wof:name":"F.a.r.c.o. Grandi Impianti Srl",
    "wof:placetype":"venue"
},
  "geometry": {"coordinates":[14.138181,42.523907],"type":"Point"}
}