{
  "type": "Feature",
  "properties": {
    "addr:full":"Via Lombardi Riccardo 46010 Curtatone Curtatone Mantova 46010",
    "addr:postcode":"46010;46010",
    "addr:street":"Via Lombardi Riccardo",
    "iso:country":"IT",
    "sg:address":"Via Lombardi Riccardo 46010 Curtatone",
    "sg:city":"Curtatone",
    "sg:classifiers":[
        {
            "category":"Wholesale",
            "subcategory":"Medical Equipment & Supplies",
            "type":"Manufacturing & Wholesale Goods"
        }
    ],
    "sg:phone":"+39 0376 290104",
    "sg:postcode":"46010",
    "sg:province":"Mantova",
    "sg:tags":[
        "-",
        "health",
        "instrument"
    ],
    "wof:name":"Tognazzoni (s.n.c.)",
    "wof:placetype":"venue"
},
  "geometry": {"coordinates":[10.772674,45.130756],"type":"Point"}
}