{
  "type": "Feature",
  "properties": {
    "iso:country":"IT",
    "sg:address":"50054 Fucecchio",
    "sg:city":"Fucecchio",
    "sg:orig_category":"Servizi E Lavori Per Abbigliamento E Pelletterie",
    "sg:phone":"+39 0571 295048",
    "sg:postcode":"50054",
    "sg:province":"Firenze",
    "wof:name":"Conceria Mirage Srl",
    "wof:placetype":"venue"
},
  "geometry": {"coordinates":[11.194075,43.792839],"type":"Point"}
}