{
  "type": "Feature",
  "properties": {
    "iso:country":"IT",
    "sg:address":"Via Monte Rodano, 6 - Oliveto 40050 Monteveglio",
    "sg:city":"Monteveglio",
    "sg:classifiers":[
        {
            "category":"Food & Beverages",
            "subcategory":"Liquor & Beverages",
            "type":"Retail Goods"
        }
    ],
    "sg:phone":"+39 051 964521",
    "sg:postcode":"40050",
    "sg:province":"Bologna",
    "sg:tags":[
        "wine",
        "italian"
    ],
    "sg:website":"www.agricolasanvito.it",
    "wof:name":"Azienda Agricola San Vito Ss",
    "wof:placetype":"venue"
},
  "geometry": {"coordinates":[11.132011,44.486839],"type":"Point"}
}