{
  "type": "Feature",
  "properties": {
    "iso:country":"IT",
    "sg:address":"63020 Massa Fermana",
    "sg:city":"Massa Fermana",
    "sg:orig_category":"Accessori Moda D'abbigliamento",
    "sg:phone":"+39 0734 760201",
    "sg:postcode":"63020",
    "sg:province":"Ascoli Piceno",
    "wof:name":"Ciccioli Paolo",
    "wof:placetype":"venue"
},
  "geometry": {"coordinates":[13.477086,43.145367],"type":"Point"}
}