{
  "type": "Feature",
  "properties": {
    "addr:full":"5/2, Via Galliera 40010 Bentivoglio Bentivoglio Bologna 40010",
    "addr:housenumber":"5 / 2",
    "addr:postcode":"40010;bentivoglio bologna 40010",
    "addr:street":"Via Galliera",
    "iso:country":"IT",
    "sg:address":"5/2, Via Galliera 40010 Bentivoglio",
    "sg:city":"Bentivoglio",
    "sg:classifiers":[
        {
            "category":"Food & Beverages",
            "subcategory":"Groceries & Convenience Stores",
            "type":"Retail Goods"
        }
    ],
    "sg:phone":"+39 39051861807",
    "sg:postcode":"40010",
    "sg:province":"Bologna",
    "sg:tags":[
        "product",
        "related"
    ],
    "wof:name":"Bedeschi Salumi (s.r.l.)",
    "wof:placetype":"venue"
},
  "geometry": {"coordinates":[11.6568784714,44.9779129028],"type":"Point"}
}