{
  "type": "Feature",
  "properties": {
    "iso:country":"IT",
    "sg:address":"Via Degli Alpini 32031 Alano Di Piave",
    "sg:city":"Alano di Piave",
    "sg:classifiers":[
        {
            "category":"Wholesale",
            "subcategory":"Medical Equipment & Supplies",
            "type":"Manufacturing & Wholesale Goods"
        }
    ],
    "sg:phone":"+39 0439 779274",
    "sg:postcode":"32031",
    "sg:province":"Belluno",
    "sg:tags":[
        "-",
        "health",
        "instrument"
    ],
    "wof:name":"Coridal Line (s.r.l.)",
    "wof:placetype":"venue"
},
  "geometry": {"coordinates":[11.921476,45.90987],"type":"Point"}
}