{
  "type": "Feature",
  "properties": {
    "addr:full":"34/36, Via Barro 28045 Invorio Invorio Novara 28045",
    "addr:housenumber":"34 / 36",
    "addr:postcode":"28045;28045",
    "addr:street":"Via Barro",
    "iso:country":"IT",
    "sg:address":"34/36, Via Barro 28045 Invorio",
    "sg:city":"Invorio",
    "sg:classifiers":[
        {
            "category":"Manufacturing",
            "subcategory":"Metals",
            "type":"Manufacturing & Wholesale Goods"
        }
    ],
    "sg:phone":"+39 0322 255533",
    "sg:postcode":"28045",
    "sg:province":"Novara",
    "sg:tags":[
        "processing"
    ],
    "wof:name":"S.b. (s.r.l.)",
    "wof:placetype":"venue"
},
  "geometry": {"coordinates":[8.4802036285,45.7629394531],"type":"Point"}
}