{
  "type": "Feature",
  "properties": {
    "iso:country":"IT",
    "sg:address":"03024 Ceprano",
    "sg:city":"Ceprano",
    "sg:orig_category":"Accessori Dei Mezzi Di Trasporto",
    "sg:phone":"+39 0775 911105",
    "sg:postcode":"03024",
    "sg:province":"Frosinone",
    "wof:name":"L.c.a.l. Srl",
    "wof:placetype":"venue"
},
  "geometry": {"coordinates":[13.502602,41.528816],"type":"Point"}
}