{
  "type": "Feature",
  "properties": {
    "iso:country":"IT",
    "sg:address":"70037 Ruvo Di Puglia",
    "sg:city":"Ruvo di Puglia",
    "sg:classifiers":[
        {
            "category":"Retail",
            "subcategory":"Event Space",
            "type":"Services"
        }
    ],
    "sg:phone":"+39 080 362 8718",
    "sg:postcode":"70037",
    "sg:province":"Bari",
    "sg:tags":[
        "leather",
        "clothing",
        "goods",
        "work"
    ],
    "wof:name":"Lavanderia Mazzone Snc",
    "wof:placetype":"venue"
},
  "geometry": {"coordinates":[16.484974,41.116753],"type":"Point"}
}