{
  "type": "Feature",
  "properties": {
    "addr:full":"20148 Milano Milano Milano 20148",
    "addr:postcode":"20148;20148",
    "iso:country":"IT",
    "sg:address":"20148 Milano",
    "sg:city":"Milano",
    "sg:classifiers":[
        {
            "category":"Health Services",
            "subcategory":"Health Practitioner",
            "type":"Services"
        }
    ],
    "sg:phone":"+39 02 3921 4408",
    "sg:postcode":"20148",
    "sg:province":"Milano",
    "sg:tags":[
        "medici"
    ],
    "wof:name":"Picanha Srl",
    "wof:placetype":"venue"
},
  "geometry": {"coordinates":[9.1435499191,45.4804763794],"type":"Point"}
}