{
  "type": "Feature",
  "properties": {
    "addr:full":"Sda Per Portomaggiore 14 44020 Ostellato Ostellato Ferrara 44020",
    "addr:housenumber":"14",
    "addr:postcode":"44020;44020",
    "iso:country":"IT",
    "sg:address":"Sda Per Portomaggiore 14 44020 Ostellato",
    "sg:city":"Ostellato",
    "sg:classifiers":[
        {
            "category":"Coffee & Tea",
            "type":"Food & Drink"
        }
    ],
    "sg:phone":"+39 0533 650756",
    "sg:postcode":"44020",
    "sg:province":"Ferrara",
    "sg:tags":[
        "gardening",
        "seedling"
    ],
    "sg:website":"www.coop-habitat.it",
    "wof:name":"Habitat Scar",
    "wof:placetype":"venue"
},
  "geometry": {"coordinates":[11.62044,44.837894],"type":"Point"}
}