{
  "type": "Feature",
  "properties": {
    "iso:country":"IT",
    "sg:address":"3, Via Mottinello 36028 Rossano Veneto",
    "sg:city":"Rossano Veneto",
    "sg:classifiers":[
        {
            "category":"Manufacturing",
            "subcategory":"Metals",
            "type":"Manufacturing & Wholesale Goods"
        }
    ],
    "sg:phone":"+39 0424 540052",
    "sg:postcode":"36028",
    "sg:province":"Vicenza",
    "sg:tags":[
        "processing"
    ],
    "wof:name":"Plastimec Galvanica (s.r.l.)",
    "wof:placetype":"venue"
},
  "geometry": {"coordinates":[11.7754821777,45.6801795959],"type":"Point"}
}