{
  "type": "Feature",
  "properties": {
    "addr:full":"10010 Azeglio Azeglio Torino 10010",
    "addr:postcode":"10010;10010",
    "iso:country":"IT",
    "sg:address":"10010 Azeglio",
    "sg:city":"Azeglio",
    "sg:orig_category":"Tempo Libero - Articoli E Forniture. Regalistica Aziendale",
    "sg:phone":"+39 0125 72238",
    "sg:postcode":"10010",
    "sg:province":"Torino",
    "wof:name":"Meloni Cesone Irene",
    "wof:placetype":"venue"
},
  "geometry": {"coordinates":[7.991754,45.426151],"type":"Point"}
}