{
  "type": "Feature",
  "properties": {
    "iso:country":"IT",
    "sg:address":"41100 Modena",
    "sg:city":"Modena",
    "sg:orig_category":"Pubblicita', Marketing E Comunicazione",
    "sg:phone":"+39 059 340003",
    "sg:postcode":"41100",
    "sg:province":"Modena",
    "sg:website":"http://www.tsc4.com/sincron",
    "wof:name":"Sincron Inova Srl",
    "wof:placetype":"venue"
},
  "geometry": {"coordinates":[10.975071907,44.5574836731],"type":"Point"}
}