{
  "type": "Feature",
  "properties": {
    "addr:full":"1, Localita' Giulis 38083 Condino Condino Trento 38083",
    "addr:postcode":"38083;38083",
    "addr:street":"Localita ' Giulis",
    "iso:country":"IT",
    "sg:address":"1, Localita' Giulis 38083 Condino",
    "sg:city":"Condino",
    "sg:classifiers":[
        {
            "category":"Manufacturing",
            "subcategory":"Lumber",
            "type":"Manufacturing & Wholesale Goods"
        }
    ],
    "sg:phone":"+39 0465 621159",
    "sg:postcode":"38083",
    "sg:province":"Trento",
    "sg:tags":[
        "wood"
    ],
    "wof:name":"Lombardi Franco & C. S.n.c.",
    "wof:placetype":"venue"
},
  "geometry": {"coordinates":[10.605932,45.89534],"type":"Point"}
}