{
  "type": "Feature",
  "properties": {
    "iso:country":"IT",
    "sg:address":"16040 San Colombano Certenoli",
    "sg:city":"Orero",
    "sg:orig_category":"Abbigliamento Esterno, Maglierie E Pelliccerie. Sport - Articoli E Forniture",
    "sg:phone":"+39 0185 356301",
    "sg:postcode":"16040",
    "sg:province":"Genova",
    "wof:name":"Seac Diving Pro Srl",
    "wof:placetype":"venue"
},
  "geometry": {"coordinates":[9.32553,44.365192],"type":"Point"}
}