{
  "type": "Feature",
  "properties": {
    "addr:full":"20046 Biassono Biassono Milano 20046",
    "addr:postcode":"20046;20046",
    "iso:country":"IT",
    "sg:address":"20046 Biassono",
    "sg:city":"Biassono",
    "sg:orig_category":"Macchine, Impianti Ed Attrezzature Per Abbigliamento E Pelletterie. Apparecchiature Ed Attrezzature Meccaniche. Elettrotecnica Industriale, Prodotti E Apparecchiature",
    "sg:phone":"+39 039 249 4669",
    "sg:postcode":"20046",
    "sg:province":"Milano",
    "wof:name":"S.a.m.i.s. Systems Srl",
    "wof:placetype":"venue"
},
  "geometry": {"coordinates":[9.268409,45.618736],"type":"Point"}
}