{
  "type": "Feature",
  "properties": {
    "iso:country":"IT",
    "sg:address":"13060 Roasio",
    "sg:city":"Roasio",
    "sg:orig_category":"Filati E Materie Prime Tessili",
    "sg:phone":"+39 0163 860150",
    "sg:postcode":"13060",
    "sg:province":"Vercelli",
    "wof:name":"Filofin S.r.l.",
    "wof:placetype":"venue"
},
  "geometry": {"coordinates":[8.2870149612,45.5938644409],"type":"Point"}
}