{
  "type": "Feature",
  "properties": {
    "addr:full":"Viale Costa Smeralda 07021 Arzachena Arzachena Olbia-Tempio 07021",
    "addr:postcode":"07021;07021",
    "addr:street":"Viale Costa Smeralda",
    "iso:country":"IT",
    "sg:address":"Viale Costa Smeralda 07021 Arzachena",
    "sg:city":"Arzachena",
    "sg:classifiers":[
        {
            "category":"Travel",
            "subcategory":"Travel Agent",
            "type":"Entertainment"
        }
    ],
    "sg:phone":"+39 39078982790",
    "sg:postcode":"07021",
    "sg:province":"Olbia-Tempio",
    "sg:tags":[
        "business"
    ],
    "wof:name":"Hotel Casa Mia",
    "wof:placetype":"venue"
},
  "geometry": {"coordinates":[9.390853,41.077518],"type":"Point"}
}