{
  "type": "Feature",
  "properties": {
    "iso:country":"IT",
    "sg:address":"52021 Bucine",
    "sg:city":"Bucine",
    "sg:orig_category":"Servizi E Lavori Per Edilizia E Lavori Pubblici. Servizi E Lavori Per Ecologia E Smaltimento Rifiuti. Macchine E Forniture Per Ecologia E Smaltimento Rifiuti. Acqua, Luce, Gas E Societa' Di Esercizio ",
    "sg:phone":"+39 055 991 1536",
    "sg:postcode":"52021",
    "sg:province":"Arezzo",
    "wof:name":"Volontari Protezione Civile Bucine",
    "wof:placetype":"venue"
},
  "geometry": {"coordinates":[11.5861,43.457531],"type":"Point"}
}