{
  "type": "Feature",
  "properties": {
    "iso:country":"IT",
    "sg:address":"Via Della Regione 7; Motta S. Anastasia; 95040",
    "sg:classifiers":[
        {
            "category":"Banks & Credit Unions",
            "subcategory":"Bank",
            "type":"Services"
        }
    ],
    "sg:phone":"+39 095 306282",
    "sg:postcode":"95040",
    "sg:province":"Catania",
    "wof:name":"Banco Di Sicilia Spa",
    "wof:placetype":"venue"
},
  "geometry": {"coordinates":[14.965858,37.511955],"type":"Point"}
}