{
  "type": "Feature",
  "properties": {
    "addr:full":"73042 Casarano Casarano Lecce 73042",
    "addr:postcode":"73042;73042",
    "iso:country":"IT",
    "sg:address":"73042 Casarano",
    "sg:city":"Casarano",
    "sg:orig_category":"Materiali Edili",
    "sg:phone":"+39 0833 513224",
    "sg:postcode":"73042",
    "sg:province":"Lecce",
    "wof:name":"Simes Srl",
    "wof:placetype":"venue"
},
  "geometry": {"coordinates":[18.29394,40.12738],"type":"Point"}
}