{
  "type": "Feature",
  "properties": {
    "iso:country":"IT",
    "sg:address":"20048 Carate Brianza",
    "sg:city":"Carate Brianza",
    "sg:classifiers":[
        {
            "category":"Banks & Credit Unions",
            "subcategory":"Atm",
            "type":"Services"
        }
    ],
    "sg:phone":"+39 036 299 1008",
    "sg:postcode":"20048",
    "sg:province":"Milano",
    "sg:tags":[
        "goods",
        "publishing",
        "leather",
        "industry",
        "work",
        "plastic",
        "services",
        "works",
        "clothing"
    ],
    "sg:website":"http://omniapiega.it",
    "wof:name":"Omniapiega Srl",
    "wof:placetype":"venue"
},
  "geometry": {"coordinates":[9.233266,45.675598],"type":"Point"}
}