{
  "type": "Feature",
  "properties": {
    "iso:country":"IT",
    "sg:address":"58100 Grosseto",
    "sg:city":"Grosseto",
    "sg:orig_category":"Arredamenti E Mobili Professionali. Impianti, Attrezzature E Forniture Sanitarie Ed Ospedaliere",
    "sg:phone":"+39 0564 451693",
    "sg:postcode":"58100",
    "sg:province":"Grosseto",
    "wof:name":"Eurobieffe Srl",
    "wof:placetype":"venue"
},
  "geometry": {"coordinates":[11.097462,42.786148],"type":"Point"}
}