{
  "type": "Feature",
  "properties": {
    "iso:country":"IT",
    "sg:address":"24030 Medolago",
    "sg:city":"Medolago",
    "sg:orig_category":"Impiantistica E Prodotti Tecnologici Per Edilizia. Forniture Industriali Per Prevenzione, Controllo E Sicurezza",
    "sg:phone":"+39 035 902667",
    "sg:postcode":"24030",
    "sg:province":"Bergamo",
    "sg:website":"http://www.nordcontenitori.com",
    "wof:name":"Nordcontenitori Spa",
    "wof:placetype":"venue"
},
  "geometry": {"coordinates":[9.654799,45.653397],"type":"Point"}
}