{
  "type": "Feature",
  "properties": {
    "addr:full":"16128 Genova Genova Genova 16128",
    "addr:postcode":"16128;16128",
    "iso:country":"IT",
    "sg:address":"16128 Genova",
    "sg:city":"Genova",
    "sg:orig_category":"Servizi Ausiliari Di Analisi, Controllo E Ricerca",
    "sg:phone":"+39 010 541221",
    "sg:postcode":"16128",
    "sg:province":"Genova",
    "wof:name":"Bassi - Marine & Cargo Surveyors (s.r.l.)",
    "wof:placetype":"venue"
},
  "geometry": {"coordinates":[8.933851,44.399097],"type":"Point"}
}