{
  "type": "Feature",
  "properties": {
    "addr:full":"57029 Venturina LI",
    "addr:postcode":"57029",
    "iso:country":"IT",
    "sg:address":"57029 Venturina",
    "sg:orig_category":"Lavorazioni Meccaniche E Servizi",
    "sg:phone":"+39 0565 855881",
    "sg:province":"LI",
    "wof:name":"Meccanica Industriale Srl",
    "wof:placetype":"venue"
},
  "geometry": {"coordinates":[-97.481415,43.354557],"type":"Point"}
}