{
  "type": "Feature",
  "properties": {
    "addr:full":"23020 Gordona Gordona Sondrio 23020",
    "addr:postcode":"23020;23020",
    "iso:country":"IT",
    "sg:address":"23020 Gordona",
    "sg:city":"Gordona",
    "sg:orig_category":"Materiali Semilavorati Metallici",
    "sg:phone":"+39 0343 48028",
    "sg:postcode":"23020",
    "sg:province":"Sondrio",
    "wof:name":"T.laser S.r.l.",
    "wof:placetype":"venue"
},
  "geometry": {"coordinates":[9.383504,46.277908],"type":"Point"}
}