{
  "type": "Feature",
  "properties": {
    "addr:full":"00197 Roma Roma Roma 00197",
    "addr:postcode":"00197;00197",
    "iso:country":"IT",
    "sg:address":"00197 Roma",
    "sg:city":"Roma",
    "sg:orig_category":"Alberghi E Strutture Extra Alberghiere. Ospedali E Servizi Sanitari",
    "sg:phone":"+39 06 807 8175",
    "sg:postcode":"00197",
    "sg:province":"Roma",
    "wof:name":"Terme Di Acqua Santa",
    "wof:placetype":"venue"
},
  "geometry": {"coordinates":[12.490705,41.921864],"type":"Point"}
}