{
  "type": "Feature",
  "properties": {
    "iso:country":"IT",
    "sg:address":"Chiavari, Ge",
    "sg:classifiers":[
        {
            "category":"Banks & Credit Unions",
            "subcategory":"Bank",
            "type":"Services"
        }
    ],
    "wof:name":"Marina Chivari Servizi Portuali Turistici Srl",
    "wof:placetype":"venue"
},
  "geometry": {"coordinates":[9.320246,44.317062],"type":"Point"}
}