{
  "type": "Feature",
  "properties": {
    "iso:country":"IT",
    "sg:address":"25, Via Industriale 25030 Lograto",
    "sg:city":"Lograto",
    "sg:classifiers":[
        {
            "category":"Shopping",
            "subcategory":"Clothing, Apparel, & Fashions",
            "type":"Retail Goods"
        }
    ],
    "sg:phone":"+39 030 997 2050",
    "sg:postcode":"25030",
    "sg:province":"Brescia",
    "sg:tags":[
        "clothes"
    ],
    "wof:name":"Calzificio Prisco S.p.a.",
    "wof:placetype":"venue"
},
  "geometry": {"coordinates":[10.069359,45.490883],"type":"Point"}
}