{
  "type": "Feature",
  "properties": {
    "iso:country":"IT",
    "sg:address":"24047 Treviglio",
    "sg:city":"Treviglio",
    "sg:orig_category":"Macchine, Impianti Ed Attrezzature Industria Chimica. Impiantistica E Prodotti Tecnologici Per Edilizia. Impianti, Attrezzature E Forniture Sanitarie Ed Ospedaliere",
    "sg:phone":"+39 036 348357",
    "sg:postcode":"24047",
    "sg:province":"Bergamo",
    "wof:name":"Terruzzi Fercalx Spa",
    "wof:placetype":"venue"
},
  "geometry": {"coordinates":[9.591435,45.529339],"type":"Point"}
}