{
  "type": "Feature",
  "properties": {
    "addr:full":"20013 Magenta - Fr. Pontenuovo Magenta Milano 20013",
    "addr:postcode":"20013;20013",
    "addr:street":"Magenta",
    "iso:country":"IT",
    "sg:address":"20013 Magenta - Fr. Pontenuovo",
    "sg:city":"Magenta",
    "sg:orig_category":"Fiammiferi",
    "sg:phone":"+39 02 972341",
    "sg:postcode":"20013",
    "sg:province":"Milano",
    "wof:name":"Fabbriche Riunite Di Fiammiferi Srl",
    "wof:placetype":"venue"
},
  "geometry": {"coordinates":[8.8632202148,45.4601898193],"type":"Point"}
}