{
  "type": "Feature",
  "properties": {
    "iso:country":"IT",
    "sg:address":"26839 Zelo Buon Persico",
    "sg:city":"Zelo Buon Persico",
    "sg:orig_category":"Macchine, Impianti Ed Attrezzature Industria Delle Materie Plastiche E Gomma",
    "sg:phone":"+39 02 906 5461",
    "sg:postcode":"26839",
    "sg:province":"Lodi",
    "wof:name":"Chiaravalloti Giuseppe",
    "wof:placetype":"venue"
},
  "geometry": {"coordinates":[9.577169,45.350014],"type":"Point"}
}