{
  "type": "Feature",
  "properties": {
    "addr:full":"20061 Carugate Carugate Milano 20061",
    "addr:postcode":"20061;20061",
    "addr:street":"Carugate Carugate",
    "iso:country":"IT",
    "sg:address":"20061 Carugate",
    "sg:city":"Carugate",
    "sg:orig_category":"Servizi Per Aziende, Manifestazioni E Supporto Agli Scambi Commerciali",
    "sg:phone":"+39 02 9215 7327",
    "sg:postcode":"20061",
    "sg:province":"Milano",
    "wof:name":"Vetrinarte Sas Di Farin A Lucio E C.",
    "wof:placetype":"venue"
},
  "geometry": {"coordinates":[9.156861,45.462112],"type":"Point"}
}