{
  "type": "Feature",
  "properties": {
    "iso:country":"IT",
    "sg:address":"22070 Veniano",
    "sg:city":"Veniano",
    "sg:orig_category":"Apparecchiature Ed Attrezzature Meccaniche",
    "sg:phone":"+39 031 936111",
    "sg:postcode":"22070",
    "sg:province":"Como",
    "wof:name":"I.t.r. S.p.a.",
    "wof:placetype":"venue"
},
  "geometry": {"coordinates":[8.990314,45.720993],"type":"Point"}
}