{
  "type": "Feature",
  "properties": {
    "addr:full":"20099 Sesto San Giovanni Sesto San Giovanni Milano 20099",
    "addr:postcode":"20099;20099",
    "iso:country":"IT",
    "sg:address":"20099 Sesto San Giovanni",
    "sg:city":"Sesto San Giovanni",
    "sg:orig_category":"Servizi E Lavori Per Edilizia E Lavori Pubblici. Acqua, Luce, Gas E Societa' Di Esercizio Pubblico",
    "sg:phone":"+39 02 2412 3111",
    "sg:postcode":"20099",
    "sg:province":"Milano",
    "wof:name":"Grtn - Centro Di Ripartizione",
    "wof:placetype":"venue"
},
  "geometry": {"coordinates":[9.24114,45.529823],"type":"Point"}
}