{
  "type": "Feature",
  "properties": {
    "iso:country":"IT",
    "sg:address":"00174 Roma",
    "sg:city":"Roma",
    "sg:orig_category":"Abbigliamento - Vendita Al Dettaglio",
    "sg:phone":"+39 06 748 1510",
    "sg:postcode":"00174",
    "sg:province":"Roma",
    "wof:name":"Iron Srl",
    "wof:placetype":"venue"
},
  "geometry": {"coordinates":[12.560946,41.857407],"type":"Point"}
}