{
  "type": "Feature",
  "properties": {
    "addr:full":"35010 Carmignano Di Brenta Carmignano di Brenta Padova 35010",
    "addr:postcode":"35010;35010",
    "addr:street":"Di Brenta",
    "iso:country":"IT",
    "sg:address":"35010 Carmignano Di Brenta",
    "sg:city":"Carmignano di Brenta",
    "sg:orig_category":"Trasporti E Spedizioni Merci",
    "sg:phone":"+39 049 595 7249",
    "sg:postcode":"35010",
    "sg:province":"Padova",
    "wof:name":"Campagnolo Giovanni Dino Sas",
    "wof:placetype":"venue"
},
  "geometry": {"coordinates":[11.713774,45.623299],"type":"Point"}
}