{
  "type": "Feature",
  "properties": {
    "iso:country":"IT",
    "sg:address":"13100 Vercelli",
    "sg:city":"Vercelli",
    "sg:classifiers":[
        {
            "category":"Health Services",
            "subcategory":"Health Practitioner",
            "type":"Services"
        }
    ],
    "sg:phone":"+39 0161 210969",
    "sg:postcode":"13100",
    "sg:province":"Vercelli",
    "sg:tags":[
        "medici"
    ],
    "wof:name":"Tagliabue Paolo",
    "wof:placetype":"venue"
},
  "geometry": {"coordinates":[8.4306211472,45.3235740662],"type":"Point"}
}