{
  "type": "Feature",
  "properties": {
    "addr:full":"30135 Venezia Santa Croce Venezia 30135",
    "addr:postcode":"30135;30135",
    "iso:country":"IT",
    "sg:address":"30135 Venezia",
    "sg:city":"Santa Croce",
    "sg:orig_category":"Abbigliamento Esterno, Maglierie E Pelliccerie. Forniture Per Il Settore Dello Spettacolo",
    "sg:phone":"+39 041 717065",
    "sg:postcode":"30135",
    "sg:province":"Venezia",
    "sg:website":"http://www.meetingeurope.com",
    "wof:name":"Cultural Events Consulting International",
    "wof:placetype":"venue"
},
  "geometry": {"coordinates":[12.32814,45.441113],"type":"Point"}
}