{
  "type": "Feature",
  "properties": {
    "addr:full":"44042 Cento Cento Ferrara 44042",
    "addr:postcode":"44042;44042",
    "iso:country":"IT",
    "sg:address":"44042 Cento",
    "sg:city":"Cento",
    "sg:orig_category":"Prodotti E Manufatti In Materie Plastiche",
    "sg:phone":"+39 051 684 6044",
    "sg:postcode":"44042",
    "sg:province":"Ferrara",
    "wof:name":"Petra Polimeri S.r.l.",
    "wof:placetype":"venue"
},
  "geometry": {"coordinates":[11.3524923325,44.8212928772],"type":"Point"}
}