{
  "type": "Feature",
  "properties": {
    "iso:country":"IT",
    "sg:address":"28, Via De Logu 95125 Catania",
    "sg:city":"Catania",
    "sg:classifiers":[
        {
            "category":"Building & Trades",
            "subcategory":"Construction",
            "type":"Services"
        }
    ],
    "sg:phone":"+39 39095221003",
    "sg:postcode":"95125",
    "sg:province":"Catania",
    "sg:tags":[
        "work",
        "public"
    ],
    "wof:name":"La Ferlita Costruzioni S.p.a.",
    "wof:placetype":"venue"
},
  "geometry": {"coordinates":[15.081793,37.534058],"type":"Point"}
}