{
  "type": "Feature",
  "properties": {
    "iso:country":"IT",
    "sg:address":"16043 Chiavari",
    "sg:city":"Chiavari",
    "sg:orig_category":"Estetiste",
    "sg:phone":"+39 0185 385040",
    "sg:postcode":"16043",
    "sg:province":"Genova",
    "sg:website":"http://www.abbronzatura.it/club_del_sole.htm",
    "wof:name":"Probus Club Del Sole Snc",
    "wof:placetype":"venue"
},
  "geometry": {"coordinates":[8.820648,44.425873],"type":"Point"}
}