{
  "type": "Feature",
  "properties": {
    "addr:full":"38, V. Don Sturzo 20020 Lainate Lainate Milano 20020",
    "addr:housenumber":"38",
    "addr:postcode":"20020;20020",
    "addr:street":"V. Don Sturzo",
    "iso:country":"IT",
    "sg:address":"38, V. Don Sturzo 20020 Lainate",
    "sg:city":"Lainate",
    "sg:classifiers":[
        {
            "category":"Manufacturing",
            "subcategory":"Rubber & Plastics",
            "type":"Manufacturing & Wholesale Goods"
        }
    ],
    "sg:phone":"+39 390 293 7501",
    "sg:postcode":"20020",
    "sg:province":"Milano",
    "sg:tags":[
        "packaging",
        "material",
        "-"
    ],
    "sg:website":"http://www.alcanpackaging.com",
    "wof:name":"Lawson Mardon Alcan Packaging",
    "wof:placetype":"venue"
},
  "geometry": {"coordinates":[9.1881408691,45.4636878967],"type":"Point"}
}