{
  "type": "Feature",
  "properties": {
    "iso:country":"IT",
    "sg:address":"90139 Palermo",
    "sg:city":"Palermo",
    "sg:orig_category":"Ottica, Lenti A Contatto Ed Occhiali - Vendita Al Dettaglio",
    "sg:phone":"+39 091 328562",
    "sg:postcode":"90139",
    "sg:province":"Palermo",
    "wof:name":"Ottica Libert\u00c0 Sas Di Matteo Di Maio & C.",
    "wof:placetype":"venue"
},
  "geometry": {"coordinates":[13.354483,38.126755],"type":"Point"}
}