{
  "type": "Feature",
  "properties": {
    "addr:full":"Via Montegrappa 11 13888 Mongrando Mongrando Biella 13888",
    "addr:housenumber":"11",
    "addr:postcode":"13888;13888",
    "addr:street":"Via Montegrappa",
    "iso:country":"IT",
    "sg:address":"Via Montegrappa 11 13888 Mongrando",
    "sg:city":"Mongrando",
    "sg:classifiers":[
        {
            "category":"Retail",
            "subcategory":"Laundry & Dry Cleaning",
            "type":"Services"
        }
    ],
    "sg:phone":"+39 015 666160",
    "sg:postcode":"13888",
    "sg:province":"Biella",
    "sg:tags":[
        "good",
        "woollen"
    ],
    "sg:website":"www.pantex-spa.it",
    "wof:name":"Pantex Spa",
    "wof:placetype":"venue"
},
  "geometry": {"coordinates":[8.071016,45.542248],"type":"Point"}
}