{
  "type": "Feature",
  "properties": {
    "iso:country":"IT",
    "sg:address":"Via Cal Di Mezzo 1 31049 Valdobbiadene",
    "sg:city":"Valdobbiadene",
    "sg:classifiers":[
        {
            "category":"Shopping",
            "subcategory":"Clothing, Apparel, & Fashions",
            "type":"Retail Goods"
        }
    ],
    "sg:phone":"+39 0423 972085",
    "sg:postcode":"31049",
    "sg:province":"Treviso",
    "sg:tags":[
        "clothing",
        "fabric"
    ],
    "wof:name":"Industria Serica Mario Gerlin S.r.l",
    "wof:placetype":"venue"
},
  "geometry": {"coordinates":[12.088631,45.941074],"type":"Point"}
}