{
  "type": "Feature",
  "properties": {
    "iso:country":"IT",
    "sg:address":"20048 Carate Brianza",
    "sg:city":"Carate Brianza",
    "sg:orig_category":"Agricoltura, Orticoltura E Floricoltura. Articoli Da Regalo",
    "sg:phone":"+39 036 290 3351",
    "sg:postcode":"20048",
    "sg:province":"Milano",
    "sg:website":"http://nipponbonsai.it",
    "wof:name":"Nippon Bonsai",
    "wof:placetype":"venue"
},
  "geometry": {"coordinates":[9.235467,45.677937],"type":"Point"}
}