{
  "type": "Feature",
  "properties": {
    "addr:full":"93, Via Del Tonale E Della Mendola 24060 Endine Gaiano Endine Bergamo 24060",
    "addr:postcode":"24060;24060",
    "addr:street":"Via Del Tonale E Della Mendola;Gaiano",
    "iso:country":"IT",
    "sg:address":"93, Via Del Tonale E Della Mendola 24060 Endine Gaiano",
    "sg:city":"Endine",
    "sg:classifiers":[
        {
            "category":"Farming",
            "subcategory":"Livestock Farm",
            "type":"Manufacturing & Wholesale Goods"
        }
    ],
    "sg:phone":"+39 39035825390",
    "sg:postcode":"24060",
    "sg:province":"Bergamo",
    "sg:tags":[
        "agriculture"
    ],
    "wof:name":"Centro Lavorazioni Agroalimentari Di Elisabetta E Patrizia Berlai (s.n.c.)",
    "wof:placetype":"venue"
},
  "geometry": {"coordinates":[10.003973,45.7924],"type":"Point"}
}