{
  "type": "Feature",
  "properties": {
    "iso:country":"IT",
    "sg:address":"55100 Lucca",
    "sg:city":"Lucca",
    "sg:classifiers":[
        {
            "category":"Travel",
            "subcategory":"Hotels & Motels",
            "type":"Entertainment"
        }
    ],
    "sg:phone":"+39 0583 4991",
    "sg:postcode":"55100",
    "sg:province":"Lucca",
    "sg:tags":[
        "support",
        "companies",
        "trade",
        "facilities",
        "events",
        "hotels"
    ],
    "sg:website":"http://www.grandhotelguinigi.it",
    "wof:name":"Grand Hotel Guinigi",
    "wof:placetype":"venue"
},
  "geometry": {"coordinates":[10.680243,44.048477],"type":"Point"}
}