{
  "type": "Feature",
  "properties": {
    "iso:country":"IT",
    "sg:address":"20080 Carpiano",
    "sg:city":"Carpiano",
    "sg:orig_category":"Macchine Ed Impianti Per Edilizia E Lavori Pubblici",
    "sg:phone":"+39 0298501",
    "sg:postcode":"20080",
    "sg:province":"Milano",
    "wof:name":"Hilti Italia Spa",
    "wof:placetype":"venue"
},
  "geometry": {"coordinates":[9.282071,45.347252],"type":"Point"}
}