{
  "type": "Feature",
  "properties": {
    "addr:full":"Via Abbadia 6-z.i. 60021 Camerano Camerano Ancona 60021",
    "addr:housenumber":"6-z.i",
    "addr:postcode":"60021;60021",
    "addr:street":"Via Abbadia",
    "iso:country":"IT",
    "sg:address":"Via Abbadia 6-z.i. 60021 Camerano",
    "sg:city":"Camerano",
    "sg:classifiers":[
        {
            "category":"Manufacturing",
            "subcategory":"Rubber & Plastics",
            "type":"Manufacturing & Wholesale Goods"
        }
    ],
    "sg:phone":"+39 071 731336",
    "sg:postcode":"60021",
    "sg:province":"Ancona",
    "sg:tags":[
        "mould",
        "industry"
    ],
    "sg:website":"www.gibastampi.it",
    "wof:name":"Giba Stampi Srl",
    "wof:placetype":"venue"
},
  "geometry": {"coordinates":[13.5447950363,43.5173339844],"type":"Point"}
}