{
  "type": "Feature",
  "properties": {
    "iso:country":"IT",
    "sg:address":"14100 Asti",
    "sg:city":"Asti",
    "sg:orig_category":"Macchine E Forniture Per Arredamento E Industria Del Legno. Colori, Vernici E Smalti",
    "sg:phone":"+39 0141 271212",
    "sg:postcode":"14100",
    "sg:province":"Asti",
    "sg:website":"http://web.tin.it/ucic",
    "wof:name":"Ucic Srl",
    "wof:placetype":"venue"
},
  "geometry": {"coordinates":[8.200055,44.937271],"type":"Point"}
}