{
  "type": "Feature",
  "properties": {
    "addr:full":"00121 Lido Di Ostia Roma 00121",
    "addr:postcode":"00121;00121",
    "addr:street":"Di Ostia Roma",
    "iso:country":"IT",
    "sg:address":"00121 Lido Di Ostia",
    "sg:orig_category":"Servizi Per Lo Sport E Il Tempo Libero. Servizi Ausiliari Dei Mezzi Di Trasporto",
    "sg:phone":"+39 06 561 1504",
    "sg:postcode":"00121",
    "sg:province":"Roma",
    "wof:name":"Achab Yacht Services Sas",
    "wof:placetype":"venue"
},
  "geometry": {"coordinates":[12.252439,41.742741],"type":"Point"}
}