{
  "type": "Feature",
  "properties": {
    "iso:country":"IT",
    "sg:address":"Via Garibaldi 9; Trapani; 91100",
    "sg:city":"Trapani",
    "sg:classifiers":[
        {
            "category":"Banks & Credit Unions",
            "subcategory":"Bank",
            "type":"Services"
        }
    ],
    "sg:phone":"+39 0923 28222",
    "sg:postcode":"91100",
    "sg:province":"Trapani",
    "wof:name":"Banco Di Sicilia Spa",
    "wof:placetype":"venue"
},
  "geometry": {"coordinates":[12.510228,38.016891],"type":"Point"}
}