{
  "type": "Feature",
  "properties": {
    "iso:country":"IT",
    "sg:address":"20123 Milano",
    "sg:city":"Milano",
    "sg:orig_category":"Cinematografia E Radiotelevisione",
    "sg:phone":"+39 02 877456",
    "sg:postcode":"20123",
    "sg:province":"Milano",
    "wof:name":"Enorme Film Arts Snc",
    "wof:placetype":"venue"
},
  "geometry": {"coordinates":[9.183705,45.461456],"type":"Point"}
}