{
  "type": "Feature",
  "properties": {
    "iso:country":"IT",
    "sg:address":"Via Ca'ricchi 34 40068 San Lazzaro Di Savena",
    "sg:city":"San Lazzaro",
    "sg:classifiers":[
        {
            "category":"Shopping Center",
            "type":"Public Place"
        }
    ],
    "sg:phone":"+39 051 465640",
    "sg:postcode":"40068",
    "sg:province":"Bologna",
    "sg:tags":[
        "aluminium",
        "section"
    ],
    "sg:website":"www.midaalluminio.it",
    "wof:name":"Mida Alluminio Srl",
    "wof:placetype":"venue"
},
  "geometry": {"coordinates":[11.41367,44.477551],"type":"Point"}
}