{
  "type": "Feature",
  "properties": {
    "addr:full":"10095 Grugliasco Grugliasco Torino 10095",
    "addr:postcode":"10095;10095",
    "iso:country":"IT",
    "sg:address":"10095 Grugliasco",
    "sg:city":"Grugliasco",
    "sg:orig_category":"Servizi E Lavori Industria Della Gomma",
    "sg:phone":"+39 011 783618",
    "sg:postcode":"10095",
    "sg:province":"Torino",
    "wof:name":"Rizzo Stampi Srl",
    "wof:placetype":"venue"
},
  "geometry": {"coordinates":[7.587621,45.060951],"type":"Point"}
}