{
  "type": "Feature",
  "properties": {
    "addr:full":"21010 Cardano Al Campo Cardano al Campo Varese 21010",
    "addr:postcode":"21010;21010",
    "iso:country":"IT",
    "sg:address":"21010 Cardano Al Campo",
    "sg:city":"Cardano al Campo",
    "sg:orig_category":"Accessori Moda D'abbigliamento. Forniture Per Abbigliamento E Pelletterie",
    "sg:phone":"+39 0331 261744",
    "sg:postcode":"21010",
    "sg:province":"Varese",
    "wof:name":"C.m. Di Aspesi Giovanni & C. Sas",
    "wof:placetype":"venue"
},
  "geometry": {"coordinates":[8.777923,45.646626],"type":"Point"}
}