{
  "type": "Feature",
  "properties": {
    "iso:country":"IT",
    "sg:address":"8, Via Enrico Mattei 31010 Maser",
    "sg:city":"Maser",
    "sg:classifiers":[
        {
            "category":"Personal",
            "subcategory":"Shoe Repair & Shine",
            "type":"Services"
        }
    ],
    "sg:phone":"+39 0423 923163",
    "sg:postcode":"31010",
    "sg:province":"Treviso",
    "sg:tags":[
        "leather"
    ],
    "wof:name":"Zeith S.p.a.",
    "wof:placetype":"venue"
},
  "geometry": {"coordinates":[11.963973,45.794224],"type":"Point"}
}