{
  "type": "Feature",
  "properties": {
    "iso:country":"IT",
    "sg:address":"17014 Cairo Montenotte",
    "sg:city":"Cairo Montenotte",
    "sg:orig_category":"Amplificazione Sonora",
    "sg:phone":"+39 019 503105",
    "sg:postcode":"17014",
    "sg:province":"Savona",
    "wof:name":"Koncerto Di Bressan Lorena & C. Snc",
    "wof:placetype":"venue"
},
  "geometry": {"coordinates":[8.319795,44.406944],"type":"Point"}
}