{
  "type": "Feature",
  "properties": {
    "iso:country":"IT",
    "sg:address":"20026 Novate Milanese",
    "sg:city":"Novate Milanese",
    "sg:orig_category":"Impianti, Attrezzature E Forniture Sanitarie Ed Ospedaliere",
    "sg:phone":"+39 02 354 1241",
    "sg:postcode":"20026",
    "sg:province":"Milano",
    "wof:name":"Mayo International Srl",
    "wof:placetype":"venue"
},
  "geometry": {"coordinates":[9.153935,45.530663],"type":"Point"}
}