{
  "type": "Feature",
  "properties": {
    "addr:full":"38, Via Trento 25128 Brescia Brescia Brescia 25128",
    "addr:postcode":"25128;25128",
    "addr:street":"Via Trento",
    "iso:country":"IT",
    "sg:address":"38, Via Trento 25128 Brescia",
    "sg:city":"Brescia",
    "sg:classifiers":[
        {
            "category":"Professional",
            "subcategory":"Engineering",
            "type":"Services"
        }
    ],
    "sg:phone":"+39 39030303247",
    "sg:postcode":"25128",
    "sg:province":"Brescia",
    "sg:tags":[
        "machine",
        "-",
        "mechanical"
    ],
    "wof:name":"Massetti",
    "wof:placetype":"venue"
},
  "geometry": {"coordinates":[10.221648,45.54884],"type":"Point"}
}