{
  "type": "Feature",
  "properties": {
    "addr:full":"1, Via Zibido 20080 Zibido San Giacomo Zibido San Giacomo Milano 20080",
    "addr:postcode":"20080;20080",
    "addr:street":"Via Zibido;San",
    "iso:country":"IT",
    "sg:address":"1, Via Zibido 20080 Zibido San Giacomo",
    "sg:city":"Zibido San Giacomo",
    "sg:classifiers":[
        {
            "category":"Wholesale",
            "subcategory":"Drugs",
            "type":"Manufacturing & Wholesale Goods"
        }
    ],
    "sg:phone":"+39 39029059441",
    "sg:postcode":"20080",
    "sg:province":"Milano",
    "sg:tags":[
        "chemical",
        "pharmaceutical"
    ],
    "wof:name":"Italvis Protect Srl",
    "wof:placetype":"venue"
},
  "geometry": {"coordinates":[9.13113,45.369587],"type":"Point"}
}