{
  "type": "Feature",
  "properties": {
    "addr:full":"24011 Alme' Bergamo 24011",
    "addr:postcode":"24011;24011",
    "iso:country":"IT",
    "sg:address":"24011 Alme'",
    "sg:orig_category":"Tempo Libero - Articoli E Forniture. Automobili E Mezzi Di Trasporto",
    "sg:phone":"+39 035 543830",
    "sg:postcode":"24011",
    "sg:province":"Bergamo",
    "wof:name":"Viscardi Bruno",
    "wof:placetype":"venue"
},
  "geometry": {"coordinates":[9.619514,45.740768],"type":"Point"}
}