{
  "type": "Feature",
  "properties": {
    "iso:country":"IT",
    "sg:address":"43100 San Pancrazio",
    "sg:orig_category":"Macchine Ed Impianti Per Edilizia E Lavori Pubblici",
    "sg:phone":"+39 0521 674068",
    "sg:postcode":"43100",
    "sg:province":"Parma",
    "wof:name":"Hilti Italia Spa",
    "wof:placetype":"venue"
},
  "geometry": {"coordinates":[10.272688,44.81308],"type":"Point"}
}