{
  "type": "Feature",
  "properties": {
    "iso:country":"IT",
    "sg:address":"37121 Verona",
    "sg:city":"Verona",
    "sg:orig_category":"Arte Ed Artigianato Artistico. Scuole E Servizi Scolastici. Servizi Ausiliari Di Analisi, Controllo E Ricerca",
    "sg:phone":"+39 045 800 1715",
    "sg:postcode":"37121",
    "sg:province":"Verona",
    "wof:name":"Accademia Di Agricoltura Scienze E Lettere",
    "wof:placetype":"venue"
},
  "geometry": {"coordinates":[10.999091,45.439793],"type":"Point"}
}