{
  "type": "Feature",
  "properties": {
    "addr:full":"71011 Apricena Apricena Foggia 71011",
    "addr:postcode":"71011;71011",
    "iso:country":"IT",
    "sg:address":"71011 Apricena",
    "sg:city":"Apricena",
    "sg:orig_category":"Arredamento Negozi E Supermercati",
    "sg:phone":"+39 0882 642016",
    "sg:postcode":"71011",
    "sg:province":"Foggia",
    "wof:name":"Elektra-gel Di Tartaglia Michele",
    "wof:placetype":"venue"
},
  "geometry": {"coordinates":[15.477108,41.790829],"type":"Point"}
}