{
  "type": "Feature",
  "properties": {
    "addr:full":"28043 Bellinzago Novarese Bellinzago Novarese Novara 28043",
    "addr:postcode":"28043;28043",
    "iso:country":"IT",
    "sg:address":"28043 Bellinzago Novarese",
    "sg:city":"Bellinzago Novarese",
    "sg:orig_category":"Zootecnia E Pesca, Allevamento Piccoli Animali. Animali Domestici",
    "sg:phone":"+39 335 817 4463",
    "sg:postcode":"28043",
    "sg:province":"Novara",
    "sg:website":"http://www.paginegialle.it/cascinacrimea",
    "wof:name":"Cascina Crimea - Pensione Per Cani",
    "wof:placetype":"venue"
},
  "geometry": {"coordinates":[8.641912,45.54845],"type":"Point"}
}