{
  "type": "Feature",
  "properties": {
    "iso:country":"IT",
    "sg:address":"11, Via Delle Groane 24060 Bagnatica",
    "sg:city":"Bagnatica",
    "sg:classifiers":[
        {
            "category":"Professional",
            "subcategory":"Engineering",
            "type":"Services"
        }
    ],
    "sg:phone":"+39 39035682727",
    "sg:postcode":"24060",
    "sg:province":"Bergamo",
    "sg:tags":[
        "machine",
        "-",
        "mechanical"
    ],
    "wof:name":"Bike Machinery (s.p.a.)",
    "wof:placetype":"venue"
},
  "geometry": {"coordinates":[9.749417,45.653278],"type":"Point"}
}