{
  "type": "Feature",
  "properties": {
    "iso:country":"IT",
    "sg:address":"33, Via Cuoco Vincenzo 70043 Monopoli",
    "sg:city":"Monopoli",
    "sg:classifiers":[
        {
            "category":"Manufacturing",
            "subcategory":"Wood Products",
            "type":"Manufacturing & Wholesale Goods"
        }
    ],
    "sg:phone":"+39 39080777122",
    "sg:postcode":"70043",
    "sg:province":"Bari",
    "sg:tags":[
        "furniture"
    ],
    "wof:name":"C.p. Argenteria",
    "wof:placetype":"venue"
},
  "geometry": {"coordinates":[16.869291,41.126053],"type":"Point"}
}