{
  "type": "Feature",
  "properties": {
    "iso:country":"IT",
    "sg:address":"50013 Campi Bisenzio",
    "sg:city":"Campi Bisenzio",
    "sg:orig_category":"Servizi E Lavori Per Abbigliamento E Pelletterie",
    "sg:phone":"+39 055 895 2691",
    "sg:postcode":"50013",
    "sg:province":"Firenze",
    "wof:name":"Stireria Tre Ville Di Simoni Simonetta",
    "wof:placetype":"venue"
},
  "geometry": {"coordinates":[11.127766,43.827488],"type":"Point"}
}