{
  "type": "Feature",
  "properties": {
    "iso:country":"IT",
    "sg:address":"20124 Milano",
    "sg:city":"Milano",
    "sg:orig_category":"Macchine, Impianti Ed Attrezzature Industria Chimica",
    "sg:phone":"+39 02 653402",
    "sg:postcode":"20124",
    "sg:province":"Milano",
    "wof:name":"Cozimmer (s.r.l.)",
    "wof:placetype":"venue"
},
  "geometry": {"coordinates":[9.197825,45.480099],"type":"Point"}
}