{
  "type": "Feature",
  "properties": {
    "iso:country":"IT",
    "sg:address":"16128 Genova",
    "sg:city":"Genova",
    "sg:classifiers":[
        {
            "category":"Building & Trades",
            "subcategory":"Equipment Rental",
            "type":"Services"
        }
    ],
    "sg:phone":"+39 010 246 1210",
    "sg:postcode":"16128",
    "sg:province":"Genova",
    "sg:tags":[
        "refrigeration"
    ],
    "wof:name":"Ferfrigor Porto Srl",
    "wof:placetype":"venue"
},
  "geometry": {"coordinates":[8.926111,44.399822],"type":"Point"}
}