{
  "type": "Feature",
  "properties": {
    "iso:country":"IT",
    "sg:address":"Via Del Botteghino 24/26 50018 Scandicci",
    "sg:city":"Scandicci",
    "sg:classifiers":[
        {
            "category":"Professional",
            "type":"Services"
        }
    ],
    "sg:phone":"+39 055 52191",
    "sg:postcode":"50018",
    "sg:province":"Firenze",
    "sg:tags":[
        "transport"
    ],
    "sg:website":"www.sdb.it",
    "wof:name":"Agenzia Marittima Savino Del Bene Spa",
    "wof:placetype":"venue"
},
  "geometry": {"coordinates":[11.158925,43.768856],"type":"Point"}
}