{
  "type": "Feature",
  "properties": {
    "iso:country":"IT",
    "sg:address":"356, V. Collatina 00155 Roma",
    "sg:city":"Roma",
    "sg:classifiers":[
        {
            "category":"Banks & Credit Unions",
            "subcategory":"Investment Brokerage",
            "type":"Services"
        }
    ],
    "sg:phone":"+39 06 2275 1093",
    "sg:postcode":"00155",
    "sg:province":"Roma",
    "sg:tags":[
        "-",
        "transport",
        "related"
    ],
    "sg:website":"http://www.espazio.com",
    "wof:name":"Epazio",
    "wof:placetype":"venue"
},
  "geometry": {"coordinates":[12.598708,41.904945],"type":"Point"}
}