{
  "type": "Feature",
  "properties": {
    "addr:full":"50012 Grassina Firenze 50012",
    "addr:postcode":"50012;50012",
    "addr:street":"Grassina",
    "iso:country":"IT",
    "sg:address":"50012 Grassina",
    "sg:orig_category":"Prodotti Finiti Stampati. Servizi Editoriali. Tempo Libero - Articoli E Forniture",
    "sg:phone":"+39 055 644081",
    "sg:postcode":"50012",
    "sg:province":"Firenze",
    "wof:name":"Studio A Srl",
    "wof:placetype":"venue"
},
  "geometry": {"coordinates":[11.2935714722,43.7351074219],"type":"Point"}
}