{
  "type": "Feature",
  "properties": {
    "addr:full":"25, Via Lulli Giambattista 10148 Torino Torino Torino 10148",
    "addr:postcode":"10148;10148",
    "addr:street":"Via Lulli Giambattista",
    "iso:country":"IT",
    "sg:address":"25, Via Lulli Giambattista 10148 Torino",
    "sg:city":"Torino",
    "sg:classifiers":[
        {
            "category":"Home & Garden",
            "subcategory":"Home Furnishings",
            "type":"Retail Goods"
        }
    ],
    "sg:phone":"+39 011 226 7827",
    "sg:postcode":"10148",
    "sg:province":"Torino",
    "sg:tags":[
        "household"
    ],
    "wof:name":"Metalbox S.r.l.",
    "wof:placetype":"venue"
},
  "geometry": {"coordinates":[7.686619,45.07056],"type":"Point"}
}