{
  "type": "Feature",
  "properties": {
    "iso:country":"IT",
    "sg:address":"Km. 500, Strada Statale 211 28071 Borgolavezzaro",
    "sg:city":"Borgolavezzaro",
    "sg:classifiers":[
        {
            "category":"Shopping",
            "subcategory":"Computers & Home Electronics",
            "type":"Retail Goods"
        }
    ],
    "sg:phone":"+39 0321 885301",
    "sg:postcode":"28071",
    "sg:province":"Novara",
    "sg:tags":[
        "electronic",
        "electrical",
        "equipment"
    ],
    "wof:name":"C.e.t. (s.a.s.)",
    "wof:placetype":"venue"
},
  "geometry": {"coordinates":[8.618671,45.445084],"type":"Point"}
}