{
  "type": "Feature",
  "properties": {
    "iso:country":"IT",
    "sg:address":"30020 Pramaggiore",
    "sg:city":"Pramaggiore",
    "sg:orig_category":"Carni, Salumi E Pesci",
    "sg:phone":"+39 0421 200353",
    "sg:postcode":"30020",
    "sg:province":"Venezia",
    "wof:name":"Societa' Fratelli Costa Di Costa Gianninno & C. Snc",
    "wof:placetype":"venue"
},
  "geometry": {"coordinates":[12.729216,45.808659],"type":"Point"}
}