{
  "type": "Feature",
  "properties": {
    "iso:country":"IT",
    "sg:address":"20121 Milano",
    "sg:city":"Milano",
    "sg:orig_category":"Servizi E Lavori Per Edilizia E Lavori Pubblici. Banche E Servizi Finanziari",
    "sg:phone":"+39 02 798965",
    "sg:postcode":"20121",
    "sg:province":"Milano",
    "wof:name":"Progetti Immobiliari Sas Di Pianosi Massimo E C.",
    "wof:placetype":"venue"
},
  "geometry": {"coordinates":[9.20073,45.470268],"type":"Point"}
}