{
  "type": "Feature",
  "properties": {
    "iso:country":"IT",
    "sg:address":"50141 Firenze",
    "sg:city":"Firenze",
    "sg:orig_category":"Arredamenti E Mobili Professionali. Apparecchi, Attrezzature E Forniture Per Centri Estetici. Arredi Ed Attrezzature Per Attivita' Commerciali Ed Artigianali",
    "sg:phone":"+39 055 411620",
    "sg:postcode":"50141",
    "sg:province":"Firenze",
    "wof:name":"First Di Bogani Laura",
    "wof:placetype":"venue"
},
  "geometry": {"coordinates":[11.238195,43.800819],"type":"Point"}
}