{
  "type": "Feature",
  "properties": {
    "iso:country":"IT",
    "sg:address":"37067 Valeggio Sul Mincio",
    "sg:city":"Valeggio sul Mincio",
    "sg:orig_category":"Forniture Per Agricoltura E Zootecnia. Prodotti Chimici Secondari",
    "sg:phone":"+39 045 637 0888",
    "sg:postcode":"37067",
    "sg:province":"Verona",
    "wof:name":"Cordioli Srl",
    "wof:placetype":"venue"
},
  "geometry": {"coordinates":[10.7381381989,45.3424415588],"type":"Point"}
}