{
  "type": "Feature",
  "properties": {
    "iso:country":"IT",
    "sg:address":"10, Via Faveri 31010 Moriago Della Battaglia",
    "sg:city":"Moriago della Battaglia",
    "sg:classifiers":[
        {
            "category":"Home & Garden",
            "subcategory":"Home Furnishings",
            "type":"Retail Goods"
        }
    ],
    "sg:phone":"+39 390 438 8911",
    "sg:postcode":"31010",
    "sg:province":"Treviso",
    "sg:tags":[
        "household"
    ],
    "wof:name":"Mobil S.p.a.",
    "wof:placetype":"venue"
},
  "geometry": {"coordinates":[12.077939,45.871197],"type":"Point"}
}