{
  "type": "Feature",
  "properties": {
    "iso:country":"IT",
    "sg:address":"34122 Trieste",
    "sg:city":"Trieste",
    "sg:orig_category":"Servizi E Lavori Per Edilizia E Lavori Pubblici. Consulenze Tecniche, Amministrative E Perizie",
    "sg:phone":"+39 040 631338",
    "sg:postcode":"34122",
    "sg:province":"Trieste",
    "wof:name":"Amministrazione Stabili Malabotti Di Bruna Malabotti",
    "wof:placetype":"venue"
},
  "geometry": {"coordinates":[13.774359,45.650349],"type":"Point"}
}