{
  "type": "Feature",
  "properties": {
    "iso:country":"IT",
    "sg:address":"11, Via Delle Confina 56022 Castelfranco Di Sotto",
    "sg:city":"Castelfranco di Sotto",
    "sg:classifiers":[
        {
            "category":"Manufacturing",
            "subcategory":"Textiles",
            "type":"Manufacturing & Wholesale Goods"
        }
    ],
    "sg:phone":"+39 0571 478094",
    "sg:postcode":"56022",
    "sg:province":"Pisa",
    "sg:tags":[
        "leather",
        "raw",
        "material",
        "-"
    ],
    "wof:name":"Italconcia (s.n.c.)",
    "wof:placetype":"venue"
},
  "geometry": {"coordinates":[10.763603,43.704643],"type":"Point"}
}