{
  "type": "Feature",
  "properties": {
    "iso:country":"IT",
    "sg:address":"70123 Bari",
    "sg:city":"Bari",
    "sg:orig_category":"Macchine Utensili E Impianti",
    "sg:phone":"+39 080 531 1448",
    "sg:postcode":"70123",
    "sg:province":"Bari",
    "wof:name":"Jannone Tubi (s.r.l.)",
    "wof:placetype":"venue"
},
  "geometry": {"coordinates":[16.812691,41.120174],"type":"Point"}
}