{
  "type": "Feature",
  "properties": {
    "addr:full":"10122 Torino Torino Torino 10122",
    "addr:housenumber":"10122",
    "addr:postcode":"10122",
    "iso:country":"IT",
    "sg:address":"10122 Torino",
    "sg:city":"Torino",
    "sg:orig_category":"Telecomunicazioni E Telefonia, Impianti, Apparecchi E Servizi",
    "sg:phone":"+39 011 565 7811",
    "sg:postcode":"10122",
    "sg:province":"Torino",
    "sg:website":"http://www.corningcablesystem.com",
    "wof:name":"Corning Srl",
    "wof:placetype":"venue"
},
  "geometry": {"coordinates":[7.677382,45.070374],"type":"Point"}
}