{
  "type": "Feature",
  "properties": {
    "addr:full":"80025 Casandrino Casandrino Napoli 80025",
    "addr:postcode":"80025;80025",
    "iso:country":"IT",
    "sg:address":"80025 Casandrino",
    "sg:city":"Casandrino",
    "sg:orig_category":"Non-classified Establishments",
    "sg:phone":"+39 081 505 3150",
    "sg:postcode":"80025",
    "sg:province":"Napoli",
    "wof:name":"Europarati S.r.l.",
    "wof:placetype":"venue"
},
  "geometry": {"coordinates":[14.24813,40.923477],"type":"Point"}
}