{
  "type": "Feature",
  "properties": {
    "iso:country":"IT",
    "sg:address":"Via Paolo Caciagli, 5/7 50053 Empoli",
    "sg:city":"Empoli",
    "sg:orig_category":"Ladies' Shoes",
    "sg:phone":"+39 0571 930054",
    "sg:postcode":"50053",
    "sg:province":"Firenze",
    "sg:website":"www.frances.it",
    "wof:name":"Frances Srl",
    "wof:placetype":"venue"
},
  "geometry": {"coordinates":[10.903343,43.704899],"type":"Point"}
}