{
  "type": "Feature",
  "properties": {
    "iso:country":"IT",
    "sg:address":"14, Via Segni Antonio 00043 Ciampino",
    "sg:city":"Ciampino",
    "sg:classifiers":[
        {
            "category":"Shopping",
            "subcategory":"Gifts & Souvenirs",
            "type":"Retail Goods"
        }
    ],
    "sg:phone":"+39 39067932881",
    "sg:postcode":"00043",
    "sg:province":"Roma",
    "wof:name":"Felian Spa",
    "wof:placetype":"venue"
},
  "geometry": {"coordinates":[12.589391,41.818253],"type":"Point"}
}