{
  "type": "Feature",
  "properties": {
    "addr:full":"80022 Arzano Arzano Napoli 80022",
    "addr:postcode":"80022;80022",
    "iso:country":"IT",
    "sg:address":"80022 Arzano",
    "sg:city":"Arzano",
    "sg:orig_category":"Prodotti E Manufatti In Materie Plastiche. Forniture Per Edilizia E Lavori Pubblici. Forniture E Materiali Per Imballaggio E Confezionamento",
    "sg:phone":"+39 081 731 1577",
    "sg:postcode":"80022",
    "sg:province":"Napoli",
    "wof:name":"Tecnisol Snc",
    "wof:placetype":"venue"
},
  "geometry": {"coordinates":[14.2686662674,40.9149971008],"type":"Point"}
}