{
  "type": "Feature",
  "properties": {
    "iso:country":"IT",
    "sg:address":"75100 Matera",
    "sg:city":"Matera",
    "sg:orig_category":"Servizi E Lavori Per Agricoltura E Zootecnia. Servizi Ausiliari Di Analisi, Controllo E Ricerca",
    "sg:phone":"+39 0835 332951",
    "sg:postcode":"75100",
    "sg:province":"Matera",
    "wof:name":"Istituto Zooprofilattico Sperimentale Della Puglia",
    "wof:placetype":"venue"
},
  "geometry": {"coordinates":[16.603584,40.669579],"type":"Point"}
}