{
  "type": "Feature",
  "properties": {
    "iso:country":"IT",
    "sg:address":"32, Via Torretta 40012 Calderara Di Reno",
    "sg:city":"Calderara di Reno",
    "sg:classifiers":[
        {
            "category":"Professional",
            "subcategory":"Engineering",
            "type":"Services"
        }
    ],
    "sg:phone":"+39 051 646 4811",
    "sg:postcode":"40012",
    "sg:province":"Bologna",
    "sg:tags":[
        "machine",
        "-",
        "mechanical"
    ],
    "wof:name":"P.e.i. Protezioni Elaborazioni Industriali (s.r.l.)",
    "wof:placetype":"venue"
},
  "geometry": {"coordinates":[11.267003,44.547337],"type":"Point"}
}