{
  "type": "Feature",
  "properties": {
    "addr:full":"90046 Monreale Monreale Palermo 90046",
    "addr:postcode":"90046;90046",
    "iso:country":"IT",
    "sg:address":"90046 Monreale",
    "sg:city":"Monreale",
    "sg:orig_category":"Veterinaria - Ambulatori E Laboratori",
    "sg:phone":"+39 091 640 9550",
    "sg:postcode":"90046",
    "sg:province":"Palermo",
    "wof:name":"Sardisco Pierfilippo",
    "wof:placetype":"venue"
},
  "geometry": {"coordinates":[13.287687,38.079426],"type":"Point"}
}