{
  "type": "Feature",
  "properties": {
    "iso:country":"IT",
    "sg:address":"20125 Milano",
    "sg:city":"Milano",
    "sg:orig_category":"Macchine Ed Impianti Per Edilizia E Lavori Pubblici. Macchine, Strumenti Ed Apparecchi Per Attivita' Industriali",
    "sg:phone":"+39 02 670 5504",
    "sg:postcode":"20125",
    "sg:province":"Milano",
    "wof:name":"Nuova Arzano (s.r.l.)",
    "wof:placetype":"venue"
},
  "geometry": {"coordinates":[9.204624,45.501907],"type":"Point"}
}