{
  "type": "Feature",
  "properties": {
    "addr:full":"60122 Ancona Ancona Ancona 60122",
    "addr:postcode":"60122;60122",
    "iso:country":"IT",
    "sg:address":"60122 Ancona",
    "sg:city":"Ancona",
    "sg:orig_category":"Antenne Radio-televisione",
    "sg:phone":"+39 071 207 2420",
    "sg:postcode":"60122",
    "sg:province":"Ancona",
    "wof:name":"Elettro 2000",
    "wof:placetype":"venue"
},
  "geometry": {"coordinates":[16.496674,41.460228],"type":"Point"}
}