{
  "type": "Feature",
  "properties": {
    "iso:country":"IT",
    "sg:address":"1, Via Radici In Piano 41042 Fiorano Modenese",
    "sg:city":"Fiorano Modenese",
    "sg:classifiers":[
        {
            "category":"Shopping",
            "subcategory":"Crafts & Fabrics",
            "type":"Retail Goods"
        }
    ],
    "sg:phone":"+39 0536 864211",
    "sg:postcode":"41042",
    "sg:province":"Modena",
    "sg:tags":[
        "ceramic"
    ],
    "wof:name":"Sir Tiles - S.p.a.",
    "wof:placetype":"venue"
},
  "geometry": {"coordinates":[10.833138,44.582958],"type":"Point"}
}