{
  "type": "Feature",
  "properties": {
    "iso:country":"IT",
    "sg:address":"42, Via Nettunense 00040 Ariccia",
    "sg:city":"Ariccia",
    "sg:classifiers":[
        {
            "category":"Autos & Motor Vehicles",
            "subcategory":"Automobile Sales",
            "type":"Retail Goods"
        }
    ],
    "sg:phone":"+39 39069341868",
    "sg:postcode":"00040",
    "sg:province":"Roma",
    "sg:tags":[
        "motor-cars"
    ],
    "wof:name":"Elevox S.r.l.",
    "wof:placetype":"venue"
},
  "geometry": {"coordinates":[12.6450824738,41.7036323547],"type":"Point"}
}