{
  "type": "Feature",
  "properties": {
    "iso:country":"IT",
    "sg:address":"80044 Ottaviano",
    "sg:city":"Ottaviano",
    "sg:orig_category":"Macchine, Impianti Ed Attrezzature Per Agricoltura E Zootecnia. Forniture Per Agricoltura E Zootecnia",
    "sg:phone":"+39 081 827 0359",
    "sg:postcode":"80044",
    "sg:province":"Napoli",
    "sg:website":"http://www.lirsa.it",
    "wof:name":"Lirsa Srl",
    "wof:placetype":"venue"
},
  "geometry": {"coordinates":[14.478192,40.85294],"type":"Point"}
}