{
  "type": "Feature",
  "properties": {
    "iso:country":"IT",
    "sg:address":"22030 Lipomo",
    "sg:city":"Lipomo",
    "sg:orig_category":"Edilizia - Materiali",
    "sg:phone":"+39 031 283900",
    "sg:postcode":"22030",
    "sg:province":"Como",
    "sg:website":"http://www.toptaglio.it",
    "wof:name":"A.t. Toptaglio Srl",
    "wof:placetype":"venue"
},
  "geometry": {"coordinates":[9.136563,45.787567],"type":"Point"}
}