{
  "type": "Feature",
  "properties": {
    "iso:country":"IT",
    "sg:address":"40010 Sala Bolognese",
    "sg:city":"Sala Bolognese",
    "sg:orig_category":"Alluminio E Leghe",
    "sg:phone":"+39 051 681 4434",
    "sg:postcode":"40010",
    "sg:province":"Bologna",
    "wof:name":"S.b. Di Sangiorgi Daniele & C. Sas",
    "wof:placetype":"venue"
},
  "geometry": {"coordinates":[11.242684,44.580238],"type":"Point"}
}