{
  "type": "Feature",
  "properties": {
    "addr:full":"Via Giusti 197 50041 Calenzano Calenzano Firenze 50041",
    "addr:housenumber":"197",
    "addr:postcode":"50041;50041",
    "addr:street":"Via Giusti",
    "iso:country":"IT",
    "sg:address":"Via Giusti 197 50041 Calenzano",
    "sg:city":"Calenzano",
    "sg:orig_category":"Ladies' Knitwear",
    "sg:phone":"+39 055 887 7973",
    "sg:postcode":"50041",
    "sg:province":"Firenze",
    "wof:name":"Italtempo S.r.l.",
    "wof:placetype":"venue"
},
  "geometry": {"coordinates":[11.204296,43.829369],"type":"Point"}
}