{
  "type": "Feature",
  "properties": {
    "iso:country":"IT",
    "sg:address":"Via Europa 21a 35015 Galliera Veneta",
    "sg:city":"Galliera Veneta",
    "sg:classifiers":[
        {
            "category":"Shopping",
            "subcategory":"Clothing, Apparel, & Fashions",
            "type":"Retail Goods"
        }
    ],
    "sg:phone":"+39 049 947 0088",
    "sg:postcode":"35015",
    "sg:province":"Padova",
    "sg:tags":[
        "children's",
        "clothing"
    ],
    "sg:website":"www.creazionibrigitte.it",
    "wof:name":"Creazioni Brigitte Spa",
    "wof:placetype":"venue"
},
  "geometry": {"coordinates":[11.656878,44.977913],"type":"Point"}
}