{
  "type": "Feature",
  "properties": {
    "addr:full":"52028 Terranuova Bracc. Arezzo 52028",
    "addr:postcode":"52028;52028",
    "iso:country":"IT",
    "sg:address":"52028 Terranuova Bracc.",
    "sg:orig_category":"Banche E Servizi Finanziari. Avvocati, Notai E Servizi Legali",
    "sg:phone":"+39 055 973 7079",
    "sg:postcode":"52028",
    "sg:province":"Arezzo",
    "wof:name":"Business Security E Consulting",
    "wof:placetype":"venue"
},
  "geometry": {"coordinates":[11.863062,43.471203],"type":"Point"}
}