{
  "type": "Feature",
  "properties": {
    "iso:country":"IT",
    "sg:address":"70125 Bari",
    "sg:city":"Bari",
    "sg:orig_category":"Servizi E Lavori Per Arredamento E Industria Del Legno",
    "sg:phone":"+39 080 542 9700",
    "sg:postcode":"70125",
    "sg:province":"Bari",
    "sg:website":"http://www.inmedia.it/usd",
    "wof:name":"Samuelli Ubaldo",
    "wof:placetype":"venue"
},
  "geometry": {"coordinates":[16.873657,41.102005],"type":"Point"}
}