{
  "type": "Feature",
  "properties": {
    "addr:full":"30035 Mirano Mirano Venezia 30035",
    "addr:postcode":"30035;30035",
    "iso:country":"IT",
    "sg:address":"30035 Mirano",
    "sg:city":"Mirano",
    "sg:orig_category":"Prodotti Chimici Secondari. Materiali Edili",
    "sg:phone":"+39 041 570 0969",
    "sg:postcode":"30035",
    "sg:province":"Venezia",
    "sg:website":"http://www.ekos.it",
    "wof:name":"Ekos Italiana Srl",
    "wof:placetype":"venue"
},
  "geometry": {"coordinates":[12.1173248291,45.4764137268],"type":"Point"}
}