{
  "type": "Feature",
  "properties": {
    "iso:country":"IT",
    "sg:address":"Via Parrocchia 3 20050 Ronco Briantino",
    "sg:city":"Ronco Briantino",
    "sg:orig_category":"Stamped Parts For Gear, Motor And Apparatus Construction",
    "sg:phone":"+39 039 607 9016",
    "sg:postcode":"20050",
    "sg:province":"Milano",
    "sg:website":"www.peregoblankingdies.it",
    "wof:name":"Fratelli Perego Srl",
    "wof:placetype":"venue"
},
  "geometry": {"coordinates":[9.404366,45.666454],"type":"Point"}
}