{
  "type": "Feature",
  "properties": {
    "iso:country":"IT",
    "sg:address":"4, Via Isacco Zaffiro 22046 Merone",
    "sg:city":"Merone",
    "sg:classifiers":[
        {
            "category":"Shopping",
            "subcategory":"Crafts & Fabrics",
            "type":"Retail Goods"
        }
    ],
    "sg:phone":"+39 39031650106",
    "sg:postcode":"22046",
    "sg:province":"Como",
    "wof:name":"Industrie Tessili Bresciane (s.p.a.)",
    "wof:placetype":"venue"
},
  "geometry": {"coordinates":[9.0854558945,45.8119659424],"type":"Point"}
}