{
  "type": "Feature",
  "properties": {
    "iso:country":"IT",
    "sg:address":"50142 Firenze",
    "sg:city":"Firenze",
    "sg:orig_category":"Serramenti Ed Infissi. Prodotti Vari In Metallo",
    "sg:phone":"+39 055 782691",
    "sg:postcode":"50142",
    "sg:province":"Firenze",
    "wof:name":"Lumas Serramenti Di Migheli Massimo",
    "wof:placetype":"venue"
},
  "geometry": {"coordinates":[11.190053,43.778824],"type":"Point"}
}