{
  "type": "Feature",
  "properties": {
    "iso:country":"IT",
    "sg:address":"75, Via Nazionale 111 89013 Gioia Tauro",
    "sg:city":"Gioia Tauro",
    "sg:classifiers":[
        {
            "category":"Autos & Motor Vehicles",
            "subcategory":"Automobile Sales",
            "type":"Retail Goods"
        }
    ],
    "sg:phone":"+39 0966 504341",
    "sg:postcode":"89013",
    "sg:province":"Reggio Di Calabria",
    "sg:tags":[
        "motor-cars"
    ],
    "wof:name":"Vadala' Srl",
    "wof:placetype":"venue"
},
  "geometry": {"coordinates":[15.6501369476,38.1146888733],"type":"Point"}
}