{
  "type": "Feature",
  "properties": {
    "addr:full":"31, Via Pastore Giulio 47900 Rimini Rimini Rimini 47900",
    "addr:postcode":"47900;47900",
    "addr:street":"Via Pastore Giulio",
    "iso:country":"IT",
    "sg:address":"31, Via Pastore Giulio 47900 Rimini",
    "sg:city":"Rimini",
    "sg:classifiers":[
        {
            "category":"Shopping",
            "subcategory":"Computers & Home Electronics",
            "type":"Retail Goods"
        }
    ],
    "sg:phone":"+39 0541 732300",
    "sg:postcode":"47900",
    "sg:province":"Rimini",
    "sg:tags":[
        "electronic",
        "electrical",
        "equipment"
    ],
    "wof:name":"S.e.r.c. Di Battistini Cleto E Spadazzi Silver & C. S.a.s.",
    "wof:placetype":"venue"
},
  "geometry": {"coordinates":[12.566257,44.06078],"type":"Point"}
}