{
  "type": "Feature",
  "properties": {
    "addr:full":"Via A. Gobetti 15 37050 San Pietro Di Morubio San Pietro di Morubio Verona 37050",
    "addr:housenumber":"15",
    "addr:postcode":"37050;pietro di morubio;37050",
    "addr:street":"Via A. Gobetti",
    "iso:country":"IT",
    "sg:address":"Via A. Gobetti 15 37050 San Pietro Di Morubio",
    "sg:city":"San Pietro di Morubio",
    "sg:classifiers":[
        {
            "category":"Bus Stop",
            "subcategory":"None",
            "type":"Transportation"
        }
    ],
    "sg:phone":"+39 045 714 4009",
    "sg:postcode":"37050",
    "sg:province":"Verona",
    "sg:tags":[
        "period",
        "furniture"
    ],
    "sg:website":"www.guerravanni.com",
    "wof:name":"Guerra Vanni",
    "wof:placetype":"venue"
},
  "geometry": {"coordinates":[10.9917478561,45.4383659363],"type":"Point"}
}