{
  "type": "Feature",
  "properties": {
    "addr:full":"10077 San Maurizio Canavese San Maurizio Canavese Torino 10077",
    "addr:housenumber":"10077",
    "addr:postcode":"10077",
    "addr:street":"San",
    "iso:country":"IT",
    "sg:address":"10077 San Maurizio Canavese",
    "sg:city":"San Maurizio Canavese",
    "sg:orig_category":"Tessuti E Stoffe. Forniture Per Attivita' Industriali",
    "sg:phone":"+39 011 924 4736",
    "sg:postcode":"10077",
    "sg:province":"Torino",
    "wof:name":"Cortiplast S.p.a.",
    "wof:placetype":"venue"
},
  "geometry": {"coordinates":[7.640637,45.208466],"type":"Point"}
}