{
  "type": "Feature",
  "properties": {
    "addr:full":"20090 Trezzano Sul Naviglio Trezzano sul Naviglio Milano 20090",
    "addr:postcode":"20090;20090",
    "iso:country":"IT",
    "sg:address":"20090 Trezzano Sul Naviglio",
    "sg:city":"Trezzano sul Naviglio",
    "sg:orig_category":"Prodotti Chimici Di Base",
    "sg:phone":"+39 02 445731",
    "sg:postcode":"20090",
    "sg:province":"Milano",
    "wof:name":"Saratoga Int.sforza Spa",
    "wof:placetype":"venue"
},
  "geometry": {"coordinates":[9.0581645966,45.4187583923],"type":"Point"}
}