{
  "type": "Feature",
  "properties": {
    "addr:full":"Via Provinc. Francesca Nord ,25/27 56010 Vicopisano Vicopisano Pisa 56010",
    "addr:housenumber":"25 / 27",
    "addr:postcode":"56010;56010",
    "addr:street":"Via Provinc. Francesca Nord",
    "iso:country":"IT",
    "sg:address":"Via Provinc. Francesca Nord ,25/27 56010 Vicopisano",
    "sg:city":"Vicopisano",
    "sg:classifiers":[
        {
            "category":"Wholesale",
            "subcategory":"Home Furnishings",
            "type":"Manufacturing & Wholesale Goods"
        }
    ],
    "sg:phone":"+39 050 799296",
    "sg:postcode":"56010",
    "sg:province":"Pisa",
    "sg:tags":[
        "chair"
    ],
    "sg:website":"www.gambassi.it",
    "wof:name":"Gambassi Srl",
    "wof:placetype":"venue"
},
  "geometry": {"coordinates":[10.396585,43.716137],"type":"Point"}
}