{
  "type": "Feature",
  "properties": {
    "addr:full":"1, Localita' Tancau 08040 Baunei Baunei Ogliastra 08040",
    "addr:postcode":"08040;08040",
    "addr:street":"Localita ' Tancau",
    "iso:country":"IT",
    "sg:address":"1, Localita' Tancau 08040 Baunei",
    "sg:city":"Baunei",
    "sg:classifiers":[
        {
            "category":"Travel",
            "subcategory":"Travel Agent",
            "type":"Entertainment"
        }
    ],
    "sg:phone":"+39 0782 615380",
    "sg:postcode":"08040",
    "sg:province":"Ogliastra",
    "sg:tags":[
        "business"
    ],
    "wof:name":"Albergo Mediterraneo S.n.c.",
    "wof:placetype":"venue"
},
  "geometry": {"coordinates":[9.4561548233,39.841053009],"type":"Point"}
}