{
  "type": "Feature",
  "properties": {
    "iso:country":"IT",
    "sg:address":"42, Via Isangarda 13878 Candelo",
    "sg:city":"Candelo",
    "sg:classifiers":[
        {
            "category":"Shopping",
            "subcategory":"Crafts & Fabrics",
            "type":"Retail Goods"
        }
    ],
    "sg:phone":"+39 015 253 6525",
    "sg:postcode":"13878",
    "sg:province":"Biella",
    "wof:name":"Gomitolatura S. Eusebio Di Crestani Mirella & C S.n.c",
    "wof:placetype":"venue"
},
  "geometry": {"coordinates":[8.0582695007,45.5628356934],"type":"Point"}
}