{
  "type": "Feature",
  "properties": {
    "addr:full":"20052 Monza Monza Milano 20052",
    "addr:postcode":"20052;20052",
    "iso:country":"IT",
    "sg:address":"20052 Monza",
    "sg:city":"Monza",
    "sg:orig_category":"Servizi Editoriali. Pubblicita', Marketing E Comunicazione",
    "sg:phone":"+39 039 388292",
    "sg:postcode":"20052",
    "sg:province":"Milano",
    "wof:name":"Caprotti Elena - Agenzia Editoriale",
    "wof:placetype":"venue"
},
  "geometry": {"coordinates":[9.068739,45.531223],"type":"Point"}
}