{
  "type": "Feature",
  "properties": {
    "iso:country":"IT",
    "sg:address":"06083 Bastia Umbra",
    "sg:city":"Bastia",
    "sg:orig_category":"Apparecchiature E Sistemi Per Magazzinaggio E Movimentazione",
    "sg:phone":"+39 075 800 3630",
    "sg:postcode":"06083",
    "sg:province":"Perugia",
    "wof:name":"Ce.te.co Srl",
    "wof:placetype":"venue"
},
  "geometry": {"coordinates":[12.544118,43.058838],"type":"Point"}
}