{
  "type": "Feature",
  "properties": {
    "addr:full":"35010 Villanova Di Camposampiero Villanova Padova 35010",
    "addr:postcode":"35010;35010",
    "iso:country":"IT",
    "sg:address":"35010 Villanova Di Camposampiero",
    "sg:city":"Villanova",
    "sg:orig_category":"Servizi Vari Di Interesse Pubblico",
    "sg:phone":"+39 049 922 1598",
    "sg:postcode":"35010",
    "sg:province":"Padova",
    "wof:name":"Oppla' Di Carosiello Silvestri E Stella S.n.c.",
    "wof:placetype":"venue"
},
  "geometry": {"coordinates":[12.028543,45.455582],"type":"Point"}
}