{
  "type": "Feature",
  "properties": {
    "iso:country":"IT",
    "sg:address":"129, Via Mazzini Giuseppe 01100 Viterbo",
    "sg:city":"Viterbo",
    "sg:classifiers":[
        {
            "category":"Banks & Credit Unions",
            "subcategory":"Bank",
            "type":"Services"
        }
    ],
    "sg:phone":"+39 0761 344839",
    "sg:postcode":"01100",
    "sg:province":"Viterbo",
    "sg:tags":[
        "banking",
        "institution"
    ],
    "wof:name":"Cassa Di Risparmio Della Provincia Di Viterbo",
    "wof:placetype":"venue"
},
  "geometry": {"coordinates":[12.064167,42.430279],"type":"Point"}
}