{
  "type": "Feature",
  "properties": {
    "addr:full":"06049 Spoleto Spoleto Perugia 06049",
    "addr:postcode":"06049;06049",
    "iso:country":"IT",
    "sg:address":"06049 Spoleto",
    "sg:city":"Spoleto",
    "sg:orig_category":"Impiantistica E Prodotti Tecnologici Per Edilizia. Serramenti Ed Infissi",
    "sg:phone":"+39 0743 45972",
    "sg:postcode":"06049",
    "sg:province":"Perugia",
    "wof:name":"Zepponi Fabio",
    "wof:placetype":"venue"
},
  "geometry": {"coordinates":[12.750482,42.767517],"type":"Point"}
}