{
  "type": "Feature",
  "properties": {
    "addr:full":"Piazza Umberto I 51-55; Pignataro Maggiore; 81052 Pignataro Maggiore Caserta 81052",
    "addr:housenumber":"51-55",
    "addr:postcode":"81052;81052",
    "addr:street":"Piazza Umberto I;Maggiore",
    "iso:country":"IT",
    "sg:address":"Piazza Umberto I 51-55; Pignataro Maggiore; 81052",
    "sg:city":"Pignataro Maggiore",
    "sg:classifiers":[
        {
            "category":"Banks & Credit Unions",
            "subcategory":"Bank",
            "type":"Services"
        }
    ],
    "sg:phone":"+39 0823 872161",
    "sg:postcode":"81052",
    "sg:province":"Caserta",
    "wof:name":"Banco Di Napoli Spa",
    "wof:placetype":"venue"
},
  "geometry": {"coordinates":[14.172414,41.19154],"type":"Point"}
}