{
  "type": "Feature",
  "properties": {
    "iso:country":"IT",
    "sg:address":"36078 Valdagno",
    "sg:city":"Valdagno",
    "sg:orig_category":"Prodotti Chimici Di Base. Forniture Per Attivita' Industriali",
    "sg:phone":"+39 0445 401426",
    "sg:postcode":"36078",
    "sg:province":"Vicenza",
    "wof:name":"Pellizzari (s.r.l.)",
    "wof:placetype":"venue"
},
  "geometry": {"coordinates":[11.5332746506,45.5543289185],"type":"Point"}
}