{
  "type": "Feature",
  "properties": {
    "iso:country":"IT",
    "sg:address":"66016 Guardiagrele",
    "sg:city":"Guardiagrele",
    "sg:orig_category":"Metalli E Leghe",
    "sg:phone":"+39 0871 82091",
    "sg:postcode":"66016",
    "sg:province":"Chieti",
    "wof:name":"Ferri Adriano",
    "wof:placetype":"venue"
},
  "geometry": {"coordinates":[14.2342920303,42.2451324463],"type":"Point"}
}