{
  "type": "Feature",
  "properties": {
    "iso:country":"IT",
    "sg:address":"10098 Rivoli",
    "sg:city":"Cascine vica",
    "sg:orig_category":"Carpenterie Metalliche",
    "sg:phone":"+39 011 957 2364",
    "sg:postcode":"10098",
    "sg:province":"Torino",
    "wof:name":"Oscam Di C. Mus",
    "wof:placetype":"venue"
},
  "geometry": {"coordinates":[7.561288,45.063171],"type":"Point"}
}