{
  "type": "Feature",
  "properties": {
    "addr:full":"25122 Brescia Brescia Brescia 25122",
    "addr:postcode":"25122;25122",
    "iso:country":"IT",
    "sg:address":"25122 Brescia",
    "sg:city":"Brescia",
    "sg:orig_category":"Articoli Da Regalo. Hobbistica. Shopping",
    "sg:phone":"+39 030 290 6345",
    "sg:postcode":"25122",
    "sg:province":"Brescia",
    "wof:name":"Lithos Di Massarelli Claudio E C. S.a.s.",
    "wof:placetype":"venue"
},
  "geometry": {"coordinates":[10.215284,45.540356],"type":"Point"}
}