{
  "type": "Feature",
  "properties": {
    "iso:country":"IT",
    "sg:address":"52100 Arezzo",
    "sg:city":"Arezzo",
    "sg:orig_category":"Manufacturers: Prefabbricati",
    "sg:phone":"+39 0575 26334",
    "sg:postcode":"52100",
    "sg:province":"Arezzo",
    "wof:name":"Ruzzi Roberto",
    "wof:placetype":"venue"
},
  "geometry": {"coordinates":[11.879695,43.464279],"type":"Point"}
}