{
  "type": "Feature",
  "properties": {
    "iso:country":"IT",
    "sg:address":"20146 Milano",
    "sg:city":"Milano",
    "sg:orig_category":"Forniture Per Abbigliamento E Pelletterie",
    "sg:phone":"+39 02 423 8289",
    "sg:postcode":"20146",
    "sg:province":"Milano",
    "wof:name":"Marsella Nicolina",
    "wof:placetype":"venue"
},
  "geometry": {"coordinates":[9.1445245743,45.4487495422],"type":"Point"}
}