{
  "type": "Feature",
  "properties": {
    "addr:full":"Via Lovati 46 - Reschigliano 35011 Campodarsego Campodarsego Padova 35011",
    "addr:housenumber":"46",
    "addr:postcode":"35011;35011",
    "addr:street":"Via Lovati",
    "iso:country":"IT",
    "sg:address":"Via Lovati 46 - Reschigliano 35011 Campodarsego",
    "sg:city":"Campodarsego",
    "sg:classifiers":[
        {
            "category":"Building & Trades",
            "subcategory":"Construction",
            "type":"Services"
        }
    ],
    "sg:phone":"+39 049 556 4097",
    "sg:postcode":"35011",
    "sg:province":"Padova",
    "sg:tags":[
        "carpenter's",
        "work",
        "supraregional"
    ],
    "wof:name":"Sarti Battista",
    "wof:placetype":"venue"
},
  "geometry": {"coordinates":[11.93128,45.476749],"type":"Point"}
}