{
  "type": "Feature",
  "properties": {
    "iso:country":"IT",
    "sg:address":"Regione Truncone 07100 Sassari",
    "sg:city":"Sassari",
    "sg:classifiers":[
        {
            "category":"Wholesale",
            "subcategory":"Medical Equipment & Supplies",
            "type":"Manufacturing & Wholesale Goods"
        }
    ],
    "sg:phone":"+39 39079210070",
    "sg:postcode":"07100",
    "sg:province":"Sassari",
    "sg:tags":[
        "-",
        "health",
        "instrument"
    ],
    "wof:name":"Te.mo.sa. (s.r.l.)",
    "wof:placetype":"venue"
},
  "geometry": {"coordinates":[8.591715,40.789886],"type":"Point"}
}