{
  "type": "Feature",
  "properties": {
    "iso:country":"IT",
    "sg:address":"37030 Colognola Ai Colli",
    "sg:city":"Colognola ai Colli",
    "sg:orig_category":"Materiali E Componenti Elettrotecnici",
    "sg:phone":"+39 045 615 9211",
    "sg:postcode":"37030",
    "sg:province":"Verona",
    "wof:name":"Prisma Spa",
    "wof:placetype":"venue"
},
  "geometry": {"coordinates":[11.157243,45.422421],"type":"Point"}
}