{
  "type": "Feature",
  "properties": {
    "iso:country":"IT",
    "sg:address":"50132 Firenze",
    "sg:city":"Firenze",
    "sg:orig_category":"Studi E Consulenze Tecniche E Industriali. Consulenze Tecniche, Amministrative E Perizie",
    "sg:phone":"+39 055 573389",
    "sg:postcode":"50132",
    "sg:province":"Firenze",
    "wof:name":"Q.s.a. Studio Associato",
    "wof:placetype":"venue"
},
  "geometry": {"coordinates":[11.266548,43.780518],"type":"Point"}
}