{
  "type": "Feature",
  "properties": {
    "addr:full":"2, Via Rivoltana 20090 Segrate Segrate Milano 20090",
    "addr:postcode":"20090;20090",
    "addr:street":"Via Rivoltana",
    "iso:country":"IT",
    "sg:address":"2, Via Rivoltana 20090 Segrate",
    "sg:city":"Segrate",
    "sg:classifiers":[
        {
            "category":"Professional",
            "subcategory":"Computer Services",
            "type":"Services"
        }
    ],
    "sg:phone":"+39 390 270 3321",
    "sg:postcode":"20090",
    "sg:province":"Milano",
    "sg:tags":[
        "information",
        "technology"
    ],
    "wof:name":"Symantec Srl",
    "wof:placetype":"venue"
},
  "geometry": {"coordinates":[9.298078,45.477451],"type":"Point"}
}