{
  "type": "Feature",
  "properties": {
    "addr:full":"93, Via Setta 40037 Sasso Marconi Sasso Marconi Bologna 40037",
    "addr:postcode":"40037;40037",
    "addr:street":"Via Setta",
    "iso:country":"IT",
    "sg:address":"93, Via Setta 40037 Sasso Marconi",
    "sg:city":"Sasso Marconi",
    "sg:classifiers":[
        {
            "category":"Manufacturing",
            "subcategory":"Metals",
            "type":"Manufacturing & Wholesale Goods"
        }
    ],
    "sg:phone":"+39 051 675 1812",
    "sg:postcode":"40037",
    "sg:province":"Bologna",
    "sg:tags":[
        "metallurgy",
        "metalworking"
    ],
    "wof:name":"Appia 2000 Di Cerri Giorgio",
    "wof:placetype":"venue"
},
  "geometry": {"coordinates":[11.2744960785,44.3450737],"type":"Point"}
}