{
  "type": "Feature",
  "properties": {
    "iso:country":"IT",
    "sg:address":"24040 Suisio",
    "sg:city":"Suisio",
    "sg:orig_category":"Lavorazioni Meccaniche E Servizi",
    "sg:phone":"+39 035 494 8328",
    "sg:postcode":"24040",
    "sg:province":"Bergamo",
    "wof:name":"I.d.c. Montaggi Srl",
    "wof:placetype":"venue"
},
  "geometry": {"coordinates":[9.501219,45.658527],"type":"Point"}
}