{
  "type": "Feature",
  "properties": {
    "addr:full":"41100 Modena Cognento Modena 41100",
    "addr:postcode":"41100;41100",
    "iso:country":"IT",
    "sg:address":"41100 Modena",
    "sg:city":"Cognento",
    "sg:orig_category":"Servizi E Lavori Per Edilizia E Lavori Pubblici",
    "sg:phone":"+39 059 356363",
    "sg:postcode":"41100",
    "sg:province":"Modena",
    "sg:website":"http://www.maxver.com",
    "wof:name":"Maxver Srl",
    "wof:placetype":"venue"
},
  "geometry": {"coordinates":[10.874217,44.637634],"type":"Point"}
}