{
  "type": "Feature",
  "properties": {
    "addr:full":"09019 Teulada Teulada Cagliari 09019",
    "addr:postcode":"09019;09019",
    "iso:country":"IT",
    "sg:address":"09019 Teulada",
    "sg:city":"Teulada",
    "sg:orig_category":"Pubblica Amministrazione",
    "sg:phone":"+39 070 927 0100",
    "sg:postcode":"09019",
    "sg:province":"Cagliari",
    "wof:name":"Ispettorato Ripartimentale Foreste Caserme",
    "wof:placetype":"venue"
},
  "geometry": {"coordinates":[9.1199121475,39.2121772766],"type":"Point"}
}