{
  "type": "Feature",
  "properties": {
    "iso:country":"IT",
    "sg:address":"09122 Cagliari",
    "sg:city":"Cagliari",
    "sg:orig_category":"Arredo Cucina Ed Elettrodomestici. Elettrodomestici",
    "sg:phone":"+39 070 284666",
    "sg:postcode":"09122",
    "sg:province":"Cagliari",
    "sg:website":"http://www.pesolo.it",
    "wof:name":"Pesolo Michele",
    "wof:placetype":"venue"
},
  "geometry": {"coordinates":[9.096763,39.241108],"type":"Point"}
}