{
  "type": "Feature",
  "properties": {
    "addr:full":"38, Via Piero Della Francesca 20154 Milano Milano Milano 20154",
    "addr:postcode":"20154;20154",
    "addr:street":"Via Piero Della Francesca",
    "iso:country":"IT",
    "sg:address":"38, Via Piero Della Francesca 20154 Milano",
    "sg:city":"Milano",
    "sg:classifiers":[
        {
            "category":"Professional",
            "subcategory":"Printing & Photocopies",
            "type":"Services"
        }
    ],
    "sg:phone":"+39 39023452647",
    "sg:postcode":"20154",
    "sg:province":"Milano",
    "wof:name":"Tipolitografia Angelo Gazzaniga Di G. Gazzaniga E",
    "wof:placetype":"venue"
},
  "geometry": {"coordinates":[9.1636228561,45.4840736389],"type":"Point"}
}