{
  "type": "Feature",
  "properties": {
    "iso:country":"IT",
    "sg:address":"36065 Mussolente",
    "sg:city":"Mussolente",
    "sg:classifiers":[
        {
            "category":"Manufacturing",
            "subcategory":"Metals",
            "type":"Manufacturing & Wholesale Goods"
        }
    ],
    "sg:phone":"+39 0424 573850",
    "sg:postcode":"36065",
    "sg:province":"Vicenza",
    "sg:tags":[
        "forming",
        "working",
        "welding"
    ],
    "wof:name":"Metalfil Snc",
    "wof:placetype":"venue"
},
  "geometry": {"coordinates":[11.8130702972,45.7736549377],"type":"Point"}
}