{
  "type": "Feature",
  "properties": {
    "addr:full":"24024 Gandino Gandino Bergamo 24024",
    "addr:postcode":"24024;24024",
    "iso:country":"IT",
    "sg:address":"24024 Gandino",
    "sg:city":"Gandino",
    "sg:orig_category":"Sport - Articoli E Forniture",
    "sg:phone":"+39 035 745289",
    "sg:postcode":"24024",
    "sg:province":"Bergamo",
    "wof:name":"Carrara Alessandro",
    "wof:placetype":"venue"
},
  "geometry": {"coordinates":[9.93545,45.789349],"type":"Point"}
}