{
  "type": "Feature",
  "properties": {
    "addr:full":"10144 Torino Torino Torino 10144",
    "addr:postcode":"10144;10144",
    "iso:country":"IT",
    "sg:address":"10144 Torino",
    "sg:city":"Torino",
    "sg:orig_category":"Scuole E Servizi Scolastici. Centri Di Estetica E Cosmesi E Servizi. Ricerca, Selezione E Formazione Del Personale",
    "sg:phone":"+39 011 488365",
    "sg:postcode":"10144",
    "sg:province":"Torino",
    "wof:name":"Frolli Massimo",
    "wof:placetype":"venue"
},
  "geometry": {"coordinates":[7.665386,45.082153],"type":"Point"}
}