{
  "type": "Feature",
  "properties": {
    "addr:full":"43029 Traversetolo Traversetolo Parma 43029",
    "addr:postcode":"43029;43029",
    "iso:country":"IT",
    "sg:address":"43029 Traversetolo",
    "sg:city":"Traversetolo",
    "sg:orig_category":"Detergenti Industriali",
    "sg:phone":"+39 0521 841317",
    "sg:postcode":"43029",
    "sg:province":"Parma",
    "sg:website":"http://www.montanini-karcher.com",
    "wof:name":"Montanini Snc",
    "wof:placetype":"venue"
},
  "geometry": {"coordinates":[10.374886,44.630455],"type":"Point"}
}