{
  "type": "Feature",
  "properties": {
    "iso:country":"IT",
    "sg:address":"50127 Firenze",
    "sg:city":"Firenze",
    "sg:classifiers":[
        {
            "category":"Utilities",
            "subcategory":"Mobile Phone",
            "type":"Services"
        }
    ],
    "sg:phone":"+39 055 428 8282",
    "sg:postcode":"50127",
    "sg:province":"Firenze",
    "sg:tags":[
        "equipment",
        "telecommunication",
        "systems",
        "telephony"
    ],
    "wof:name":"C.p.f. Distribuzione E Servizi Srl",
    "wof:placetype":"venue"
},
  "geometry": {"coordinates":[11.224044,43.803814],"type":"Point"}
}