{
  "type": "Feature",
  "properties": {
    "iso:country":"IT",
    "sg:address":"8, Via Roma 35015 Galliera Veneta",
    "sg:city":"Galliera Veneta",
    "sg:classifiers":[
        {
            "category":"Manufacturing",
            "subcategory":"Lumber",
            "type":"Manufacturing & Wholesale Goods"
        }
    ],
    "sg:phone":"+39 049 947 0574",
    "sg:postcode":"35015",
    "sg:province":"Padova",
    "sg:tags":[
        "wood"
    ],
    "wof:name":"Cleto Munari Design Associati (s.r.l.)",
    "wof:placetype":"venue"
},
  "geometry": {"coordinates":[11.81289,45.656185],"type":"Point"}
}