{
  "type": "Feature",
  "properties": {
    "addr:full":"10153 Torino Torino Torino 10153",
    "addr:postcode":"10153;10153",
    "iso:country":"IT",
    "sg:address":"10153 Torino",
    "sg:city":"Torino",
    "sg:orig_category":"Imprese Di Costruzioni Civili Ed Industriali",
    "sg:phone":"+39 011 812 4343",
    "sg:postcode":"10153",
    "sg:province":"Torino",
    "wof:name":"Frolli Silvano",
    "wof:placetype":"venue"
},
  "geometry": {"coordinates":[7.71438,45.07032],"type":"Point"}
}