{
  "type": "Feature",
  "properties": {
    "iso:country":"IT",
    "sg:address":"87046 Montalto Uffugo",
    "sg:city":"Montalto Uffugo",
    "sg:orig_category":"Biancheria, Telerie E Coperte. Forniture Alle Strutture Ricettive",
    "sg:phone":"+39 0984 937041",
    "sg:postcode":"87046",
    "sg:province":"Cosenza",
    "sg:website":"http://www.paginegialle.it/ricamart-cs",
    "wof:name":"Ricami Artigianali Calabresi Di Luigi Car\u00c0",
    "wof:placetype":"venue"
},
  "geometry": {"coordinates":[16.244337,39.392654],"type":"Point"}
}