{
  "type": "Feature",
  "properties": {
    "addr:full":"20139 Milano Milano Milano 20139",
    "addr:postcode":"20139;20139",
    "iso:country":"IT",
    "sg:address":"20139 Milano",
    "sg:city":"Milano",
    "sg:orig_category":"Articoli Da Regalo. Regalistica Aziendale",
    "sg:phone":"+39 02 539 7812",
    "sg:postcode":"20139",
    "sg:province":"Milano",
    "wof:name":"Box Italia Imballaggi",
    "wof:placetype":"venue"
},
  "geometry": {"coordinates":[9.227516,45.428825],"type":"Point"}
}