{
  "type": "Feature",
  "properties": {
    "iso:country":"IT",
    "sg:address":"27030 Frascarolo",
    "sg:city":"Frascarolo",
    "sg:orig_category":"Alluminio Lavorazione - Macchine",
    "sg:phone":"+39 0384 84671",
    "sg:postcode":"27030",
    "sg:province":"Pavia",
    "sg:website":"http://www.mecal.com",
    "wof:name":"Me.c.al. Di Meschini Rosella Snc",
    "wof:placetype":"venue"
},
  "geometry": {"coordinates":[8.641614,45.053425],"type":"Point"}
}