{
  "type": "Feature",
  "properties": {
    "iso:country":"IT",
    "sg:address":"65128 Pescara",
    "sg:city":"Pescara",
    "sg:orig_category":"Biancheria Per Alberghi E Comunita'",
    "sg:phone":"+39 085 50330",
    "sg:postcode":"65128",
    "sg:province":"Pescara",
    "wof:name":"Giglio Service Srl",
    "wof:placetype":"venue"
},
  "geometry": {"coordinates":[14.190186,42.441769],"type":"Point"}
}