{
  "type": "Feature",
  "properties": {
    "iso:country":"IT",
    "sg:address":"25065 Lumezzane",
    "sg:city":"Lumezzane",
    "sg:classifiers":[
        {
            "category":"Home & Garden",
            "subcategory":"Kitchen Supply",
            "type":"Retail Goods"
        }
    ],
    "sg:phone":"+39 030 827229",
    "sg:postcode":"25065",
    "sg:province":"Brescia",
    "sg:tags":[
        "activities",
        "houseware",
        "utensil",
        "tool",
        "commercial",
        "materials",
        "artisan",
        "mechanical"
    ],
    "wof:name":"Coltelleria Valgobbia Snc",
    "wof:placetype":"venue"
},
  "geometry": {"coordinates":[10.215569,45.607738],"type":"Point"}
}