{
  "type": "Feature",
  "properties": {
    "iso:country":"IT",
    "sg:address":"80010 Villaricca",
    "sg:city":"Villaricca",
    "sg:orig_category":"Tessuti Arredamento, Tende E Tappeti",
    "sg:phone":"+39 081 330 3524",
    "sg:postcode":"80010",
    "sg:province":"Napoli",
    "wof:name":"Allestimenti Fieristici 3c Snc",
    "wof:placetype":"venue"
},
  "geometry": {"coordinates":[14.181264,40.923779],"type":"Point"}
}