{
  "type": "Feature",
  "properties": {
    "addr:full":"Via Stra Madonna 89 21047 Saronno Saronno Varese 21047",
    "addr:housenumber":"89",
    "addr:postcode":"21047;21047",
    "addr:street":"Via Stra Madonna",
    "iso:country":"IT",
    "sg:address":"Via Stra Madonna 89 21047 Saronno",
    "sg:city":"Saronno",
    "sg:classifiers":[
        {
            "category":"Building & Trades",
            "subcategory":"Cleaning & Sanitation",
            "type":"Services"
        }
    ],
    "sg:phone":"+39 02 9670 1505",
    "sg:postcode":"21047",
    "sg:province":"Varese",
    "sg:tags":[
        "biological",
        "exhaust",
        "systems",
        "air"
    ],
    "sg:website":"www.innovaterm.com",
    "wof:name":"Innovaterm Srl",
    "wof:placetype":"venue"
},
  "geometry": {"coordinates":[9.015652,45.624889],"type":"Point"}
}