{
  "type": "Feature",
  "properties": {
    "addr:full":"4, Via Della Repubblica Montiglio 14026 Montiglio Monferrato Montiglio Asti 14026",
    "addr:postcode":"14026;14026",
    "addr:street":"Via Della Repubblica",
    "iso:country":"IT",
    "sg:address":"4, Via Della Repubblica Montiglio 14026 Montiglio Monferrato",
    "sg:city":"Montiglio",
    "sg:classifiers":[
        {
            "category":"Professional",
            "subcategory":"Engineering",
            "type":"Services"
        }
    ],
    "sg:phone":"+39 0141 994642",
    "sg:postcode":"14026",
    "sg:province":"Asti",
    "sg:tags":[
        "machine",
        "-",
        "mechanical"
    ],
    "wof:name":"Co.m E.r. (s.r.l.)",
    "wof:placetype":"venue"
},
  "geometry": {"coordinates":[8.109362,45.068913],"type":"Point"}
}