{
  "type": "Feature",
  "properties": {
    "addr:full":"47838 Riccione Riccione Rimini 47838",
    "addr:postcode":"47838;47838",
    "iso:country":"IT",
    "sg:address":"47838 Riccione",
    "sg:city":"Riccione",
    "sg:orig_category":"Fotografia - Servizi, Studi, Sviluppo E Stampa",
    "sg:phone":"+39 0541 609111",
    "sg:postcode":"47838",
    "sg:province":"Rimini",
    "sg:website":"http://www.photosi.com",
    "wof:name":"Suprem Srl",
    "wof:placetype":"venue"
},
  "geometry": {"coordinates":[12.6362504959,43.9834365845],"type":"Point"}
}