{
  "type": "Feature",
  "properties": {
    "addr:full":"1, Via Pellico Silvio 30020 Marcon Marcon Venezia 30020",
    "addr:postcode":"30020;30020",
    "addr:street":"Via Pellico Silvio",
    "iso:country":"IT",
    "sg:address":"1, Via Pellico Silvio 30020 Marcon",
    "sg:city":"Marcon",
    "sg:classifiers":[
        {
            "category":"Manufacturing",
            "subcategory":"Metals",
            "type":"Manufacturing & Wholesale Goods"
        }
    ],
    "sg:phone":"+39 041 456 9417",
    "sg:postcode":"30020",
    "sg:province":"Venezia",
    "sg:tags":[
        "metallurgy",
        "metalworking"
    ],
    "wof:name":"I.f.i. (s.r.l.)",
    "wof:placetype":"venue"
},
  "geometry": {"coordinates":[12.3079938889,45.5491638184],"type":"Point"}
}