{
  "type": "Feature",
  "properties": {
    "iso:country":"IT",
    "sg:address":"16, Piazza S. Croce 50122 Firenze",
    "sg:city":"Firenze",
    "sg:classifiers":[
        {
            "category":"Personal",
            "subcategory":"Shoe Repair & Shine",
            "type":"Services"
        }
    ],
    "sg:phone":"+39 39055244534",
    "sg:postcode":"50122",
    "sg:province":"Firenze",
    "sg:tags":[
        "leather"
    ],
    "wof:name":"Scuola Del Cuoio",
    "wof:placetype":"venue"
},
  "geometry": {"coordinates":[11.2622365952,43.7686653137],"type":"Point"}
}