{
  "type": "Feature",
  "properties": {
    "iso:country":"IT",
    "sg:address":"7, Via Brescia 25076 Odolo",
    "sg:city":"Odolo",
    "sg:classifiers":[
        {
            "category":"Manufacturing",
            "subcategory":"Metals",
            "type":"Manufacturing & Wholesale Goods"
        }
    ],
    "sg:phone":"+39 036 582 6504",
    "sg:postcode":"25076",
    "sg:province":"Brescia",
    "sg:tags":[
        "processing"
    ],
    "wof:name":"Format Srl",
    "wof:placetype":"venue"
},
  "geometry": {"coordinates":[10.3825492859,45.6452217102],"type":"Point"}
}