{
  "type": "Feature",
  "properties": {
    "addr:full":"6, Via Milano 23873 Missaglia Missaglia Lecco 23873",
    "addr:postcode":"23873;23873",
    "addr:street":"Via Milano",
    "iso:country":"IT",
    "sg:address":"6, Via Milano 23873 Missaglia",
    "sg:city":"Missaglia",
    "sg:classifiers":[
        {
            "category":"Shopping",
            "subcategory":"Crafts & Fabrics",
            "type":"Retail Goods"
        }
    ],
    "sg:phone":"+39 039 924 1173",
    "sg:postcode":"23873",
    "sg:province":"Lecco",
    "wof:name":"Tessitura Fratelli Giussani Fu A (s.p.a.)",
    "wof:placetype":"venue"
},
  "geometry": {"coordinates":[9.3889284134,45.6692733765],"type":"Point"}
}