{
  "type": "Feature",
  "properties": {
    "addr:full":"28, Via Busca Regione Brignola Regione Brignola 12044 Centallo Centallo Cuneo 12044",
    "addr:postcode":"12044;12044",
    "addr:street":"Via Busca Regione Brignola Regione Brignola",
    "iso:country":"IT",
    "sg:address":"28, Via Busca Regione Brignola Regione Brignola 12044 Centallo",
    "sg:city":"Centallo",
    "sg:classifiers":[
        {
            "category":"Wholesale",
            "subcategory":"Machinery & Supplies",
            "type":"Manufacturing & Wholesale Goods"
        }
    ],
    "sg:phone":"+39 0171 214412",
    "sg:postcode":"12044",
    "sg:province":"Cuneo",
    "sg:tags":[
        "-",
        "agriculture",
        "equipment"
    ],
    "wof:name":"Ariaudo Mario & C. S.n.c.",
    "wof:placetype":"venue"
},
  "geometry": {"coordinates":[7.547111,44.388798],"type":"Point"}
}