{
  "type": "Feature",
  "properties": {
    "iso:country":"IT",
    "sg:address":"40135 Bologna",
    "sg:city":"Bologna",
    "sg:orig_category":"Etichette",
    "sg:phone":"+39 051 614 2218",
    "sg:postcode":"40135",
    "sg:province":"Bologna",
    "wof:name":"Etichettificio Felsineo Snc",
    "wof:placetype":"venue"
},
  "geometry": {"coordinates":[11.304871,44.49036],"type":"Point"}
}