{
  "type": "Feature",
  "properties": {
    "addr:full":"Via Ruffo 4; Sacile; 33077 Sacile Pordenone 33077",
    "addr:housenumber":"4",
    "addr:postcode":"33077;33077",
    "addr:street":"Via Ruffo",
    "iso:country":"IT",
    "sg:address":"Via Ruffo 4; Sacile; 33077",
    "sg:city":"Sacile",
    "sg:classifiers":[
        {
            "category":"Banks & Credit Unions",
            "subcategory":"Bank",
            "type":"Services"
        }
    ],
    "sg:phone":"+39 0434 781628",
    "sg:postcode":"33077",
    "sg:province":"Pordenone",
    "wof:name":"Banca Nazionale Del Lavoro Spa",
    "wof:placetype":"venue"
},
  "geometry": {"coordinates":[12.496186,45.954308],"type":"Point"}
}