{
  "type": "Feature",
  "properties": {
    "addr:full":"41100 Modena Modena Modena 41100",
    "addr:postcode":"41100;41100",
    "iso:country":"IT",
    "sg:address":"41100 Modena",
    "sg:city":"Modena",
    "sg:orig_category":"Professionisti - Studi E Servizi Ed Associazioni Di Interesse Aziendale. Associazioni Ed Organismi Di Interesse Pubblico",
    "sg:phone":"+39 059 893111",
    "sg:postcode":"41100",
    "sg:province":"Modena",
    "sg:website":"http://www.lapam.mo.it",
    "wof:name":"Lapam Licom Confartigianato",
    "wof:placetype":"venue"
},
  "geometry": {"coordinates":[10.9172067642,44.6388664246],"type":"Point"}
}