{
  "type": "Feature",
  "properties": {
    "addr:full":"90128 Palermo Palermo Palermo 90128",
    "addr:postcode":"90128;90128",
    "iso:country":"IT",
    "sg:address":"90128 Palermo",
    "sg:city":"Palermo",
    "sg:orig_category":"Dolciumi - Ingrosso",
    "sg:phone":"+39 091 484590",
    "sg:postcode":"90128",
    "sg:province":"Palermo",
    "wof:name":"Di Blanda Sas",
    "wof:placetype":"venue"
},
  "geometry": {"coordinates":[13.355922,38.098961],"type":"Point"}
}