{
  "type": "Feature",
  "properties": {
    "addr:full":"37/39, Via Vespucci Amerigo 14100 Asti Asti Asti 14100",
    "addr:housenumber":"37 / 39",
    "addr:postcode":"14100;14100",
    "addr:street":"Via Vespucci Amerigo",
    "iso:country":"IT",
    "sg:address":"37/39, Via Vespucci Amerigo 14100 Asti",
    "sg:city":"Asti",
    "sg:classifiers":[
        {
            "category":"Shopping",
            "type":"Retail Goods"
        }
    ],
    "sg:phone":"+39 0141 271206",
    "sg:postcode":"14100",
    "sg:province":"Asti",
    "sg:tags":[
        "finished",
        "-",
        "metallic"
    ],
    "wof:name":"O.c.m.o.a. (s.n.c.)",
    "wof:placetype":"venue"
},
  "geometry": {"coordinates":[8.2068128586,44.9008636475],"type":"Point"}
}