{
  "type": "Feature",
  "properties": {
    "addr:full":"28041 Arona Arona Novara 28041",
    "addr:postcode":"28041;28041",
    "iso:country":"IT",
    "sg:address":"28041 Arona",
    "sg:city":"Arona",
    "sg:orig_category":"Agenzie Matrimoniali",
    "sg:phone":"+39 0322 44722",
    "sg:postcode":"28041",
    "sg:province":"Novara",
    "sg:website":"http://www.agenziarmonia.com",
    "wof:name":"Vezzali Antonella - Agenzia Armonia",
    "wof:placetype":"venue"
},
  "geometry": {"coordinates":[8.555181,45.760361],"type":"Point"}
}