{
  "type": "Feature",
  "properties": {
    "iso:country":"IT",
    "sg:address":"36065 Mussolente",
    "sg:city":"Mussolente",
    "sg:orig_category":"Elettrotecnica",
    "sg:phone":"+39 0424 577771",
    "sg:postcode":"36065",
    "sg:province":"Vicenza",
    "wof:name":"Vicab Snc",
    "wof:placetype":"venue"
},
  "geometry": {"coordinates":[11.81307,45.773655],"type":"Point"}
}