{
  "type": "Feature",
  "properties": {
    "iso:country":"IT",
    "sg:address":"20081 Abbiategrasso",
    "sg:city":"Abbiategrasso",
    "sg:classifiers":[
        {
            "category":"Health Services",
            "subcategory":"Health Practitioner",
            "type":"Services"
        }
    ],
    "sg:phone":"+39 02 946 5886",
    "sg:postcode":"20081",
    "sg:province":"Milano",
    "sg:tags":[
        "medici"
    ],
    "wof:name":"Pierfederici Casadei Raffaella",
    "wof:placetype":"venue"
},
  "geometry": {"coordinates":[9.2113685608,45.5633125305],"type":"Point"}
}