{
  "type": "Feature",
  "properties": {
    "iso:country":"IT",
    "sg:address":"41100 Modena",
    "sg:city":"Modena",
    "sg:orig_category":"Bevande, Vini E Liquori",
    "sg:phone":"+39 059 205 3011",
    "sg:postcode":"41100",
    "sg:province":"Modena",
    "wof:name":"Coca Cola Bevande Italia Spa",
    "wof:placetype":"venue"
},
  "geometry": {"coordinates":[10.914429,44.663944],"type":"Point"}
}