{
  "type": "Feature",
  "properties": {
    "addr:full":"80147 Napoli Napoli Napoli 80147",
    "addr:postcode":"80147;80147",
    "iso:country":"IT",
    "sg:address":"80147 Napoli",
    "sg:city":"Napoli",
    "sg:orig_category":"Apparecchiature Ed Attrezzature Meccaniche",
    "sg:phone":"+39 081 752 7943",
    "sg:postcode":"80147",
    "sg:province":"Napoli",
    "wof:name":"2m Aria Compressa Sas",
    "wof:placetype":"venue"
},
  "geometry": {"coordinates":[14.31284,40.854443],"type":"Point"}
}