{
  "type": "Feature",
  "properties": {
    "iso:country":"IT",
    "sg:address":"55012 Capannori",
    "sg:city":"Capannori",
    "sg:orig_category":"Forniture Per Edilizia E Lavori Pubblici",
    "sg:phone":"+39 0583 407124",
    "sg:postcode":"55012",
    "sg:province":"Lucca",
    "sg:website":"http://www.pariv.it",
    "wof:name":"Pariv Di Guidi Gianfranco",
    "wof:placetype":"venue"
},
  "geometry": {"coordinates":[10.538775444,43.8850288391],"type":"Point"}
}