{
  "type": "Feature",
  "properties": {
    "iso:country":"IT",
    "sg:address":"00193 Roma",
    "sg:city":"Roma",
    "sg:orig_category":"Ambasciate Ed Enti Internazionali",
    "sg:phone":"+39 06 686 5740",
    "sg:postcode":"00193",
    "sg:province":"Roma",
    "wof:name":"Ambasciata Presso La S. Sede Costa D'avorio",
    "wof:placetype":"venue"
},
  "geometry": {"coordinates":[12.495478,41.895615],"type":"Point"}
}