{
  "type": "Feature",
  "properties": {
    "addr:full":"5/c, Via Staffora 20090 Opera Opera Milano 20090",
    "addr:housenumber":"5 / c",
    "addr:postcode":"20090;20090",
    "addr:street":"Via Staffora",
    "iso:country":"IT",
    "sg:address":"5/c, Via Staffora 20090 Opera",
    "sg:city":"Opera",
    "sg:classifiers":[
        {
            "category":"Professional",
            "subcategory":"Engineering",
            "type":"Services"
        }
    ],
    "sg:phone":"+39 02 5760 2178",
    "sg:postcode":"20090",
    "sg:province":"Milano",
    "sg:tags":[
        "machine",
        "-",
        "mechanical"
    ],
    "wof:name":"Agef (s.r.l.)",
    "wof:placetype":"venue"
},
  "geometry": {"coordinates":[9.204337,45.368835],"type":"Point"}
}