{
  "type": "Feature",
  "properties": {
    "addr:full":"00040 Pomezia Pomezia Roma 00040",
    "addr:postcode":"00040;roma 00040",
    "iso:country":"IT",
    "sg:address":"00040 Pomezia",
    "sg:city":"Pomezia",
    "sg:orig_category":"Metalli E Leghe",
    "sg:phone":"+39 06 910 8200",
    "sg:postcode":"00040",
    "sg:province":"Roma",
    "wof:name":"Edilsystem Srl",
    "wof:placetype":"venue"
},
  "geometry": {"coordinates":[12.4449357986,41.7761383057],"type":"Point"}
}