{
  "type": "Feature",
  "properties": {
    "addr:full":"22066 Mariano Comense Mariano Comense Como 22066",
    "addr:housenumber":"22066",
    "addr:postcode":"22066",
    "iso:country":"IT",
    "sg:address":"22066 Mariano Comense",
    "sg:city":"Mariano Comense",
    "sg:orig_category":"Prodotti Alimentari",
    "sg:phone":"+39 031 745252",
    "sg:postcode":"22066",
    "sg:province":"Como",
    "wof:name":"Mondial Miele Sas",
    "wof:placetype":"venue"
},
  "geometry": {"coordinates":[9.1722621918,45.6992149353],"type":"Point"}
}