{
  "type": "Feature",
  "properties": {
    "iso:country":"IT",
    "sg:address":"90047 Partinico",
    "sg:city":"Partinico",
    "sg:orig_category":"Dolciumi E Gelati",
    "sg:phone":"+39 091 890 1702",
    "sg:postcode":"90047",
    "sg:province":"Palermo",
    "wof:name":"New York Burgers Di Bono Pietro",
    "wof:placetype":"venue"
},
  "geometry": {"coordinates":[13.369066,38.110683],"type":"Point"}
}