{
  "type": "Feature",
  "properties": {
    "iso:country":"IT",
    "sg:address":"30034 Mira",
    "sg:city":"Mira",
    "sg:orig_category":"Servizi Per Aziende, Manifestazioni E Supporto Agli Scambi Commerciali",
    "sg:phone":"+39 041 472333",
    "sg:postcode":"30034",
    "sg:province":"Venezia",
    "wof:name":"Favaretto Maria Cristina",
    "wof:placetype":"venue"
},
  "geometry": {"coordinates":[12.174758,45.450741],"type":"Point"}
}