{
  "type": "Feature",
  "properties": {
    "addr:full":"20152 Milano Milano Milano 20152",
    "addr:postcode":"20152;20152",
    "iso:country":"IT",
    "sg:address":"20152 Milano",
    "sg:city":"Milano",
    "sg:orig_category":"Petroli, Gas E Combustibili. Servizi E Lavori Industria Chimica. Servizi E Lavori Per Edilizia E Lavori Pubblici. Acqua, Luce, Gas E Societa' Di Esercizio Pubblico",
    "sg:phone":"+39 02 4892 6188",
    "sg:postcode":"20152",
    "sg:province":"Milano",
    "wof:name":"Lz Assistance Snc Di Longo Massimo E Zonda Roberto",
    "wof:placetype":"venue"
},
  "geometry": {"coordinates":[9.0667657852,45.4441375732],"type":"Point"}
}