{
  "type": "Feature",
  "properties": {
    "iso:country":"IT",
    "sg:address":"Via Casamassima 70016 Noicattaro",
    "sg:city":"Noicattaro",
    "sg:classifiers":[
        {
            "category":"Food & Beverages",
            "subcategory":"Fruits & Vegetables",
            "type":"Retail Goods"
        }
    ],
    "sg:phone":"+39 080 478 0043",
    "sg:postcode":"70016",
    "sg:province":"Bari",
    "wof:name":"F.lli Dipinto S.r.l.",
    "wof:placetype":"venue"
},
  "geometry": {"coordinates":[16.9174461365,41.0401687622],"type":"Point"}
}