{
  "type": "Feature",
  "properties": {
    "addr:full":"20128 Milano Milano Milano 20128",
    "addr:postcode":"20128;20128",
    "iso:country":"IT",
    "sg:address":"20128 Milano",
    "sg:city":"Milano",
    "sg:orig_category":"Pubblica Amministrazione",
    "sg:phone":"+39 02 252951",
    "sg:postcode":"20128",
    "sg:province":"Milano",
    "wof:name":"Poste Italiane Spa",
    "wof:placetype":"venue"
},
  "geometry": {"coordinates":[9.2307100296,45.5168647766],"type":"Point"}
}