{
  "type": "Feature",
  "properties": {
    "addr:full":"00183 Roma Roma Roma 00183",
    "addr:postcode":"00183;00183",
    "iso:country":"IT",
    "sg:address":"00183 Roma",
    "sg:city":"Roma",
    "sg:classifiers":[
        {
            "category":"Health Services",
            "subcategory":"Health Practitioner",
            "type":"Services"
        }
    ],
    "sg:phone":"+39 06 700 4675",
    "sg:postcode":"00183",
    "sg:province":"Roma",
    "sg:tags":[
        "medici"
    ],
    "wof:name":"Tsoullou Savvas",
    "wof:placetype":"venue"
},
  "geometry": {"coordinates":[12.5082654953,41.8751907349],"type":"Point"}
}