{
  "type": "Feature",
  "properties": {
    "addr:full":"48100 Ravenna Ravenna Ravenna 48100",
    "addr:housenumber":"48100",
    "addr:postcode":"48100",
    "iso:country":"IT",
    "sg:address":"48100 Ravenna",
    "sg:city":"Ravenna",
    "sg:orig_category":"Servizi E Lavori Per Agricoltura E Zootecnia. Servizi E Lavori Per Ecologia E Smaltimento Rifiuti",
    "sg:phone":"+39 0544 453054",
    "sg:postcode":"48100",
    "sg:province":"Ravenna",
    "sg:website":"http://www.nuovasaimar.it",
    "wof:name":"Nuova Saimar Srl",
    "wof:placetype":"venue"
},
  "geometry": {"coordinates":[12.2244577408,44.3803138733],"type":"Point"}
}