{
  "type": "Feature",
  "properties": {
    "iso:country":"IT",
    "sg:address":"00136 Roma",
    "sg:city":"Roma",
    "sg:orig_category":"Lavorazioni Meccaniche E Servizi. Riparazione Dei Mezzi Di Trasporto",
    "sg:phone":"+39 06 3973 3683",
    "sg:postcode":"00136",
    "sg:province":"Roma",
    "wof:name":"Torbidoni Paolo",
    "wof:placetype":"venue"
},
  "geometry": {"coordinates":[12.450002,41.907181],"type":"Point"}
}