{
  "type": "Feature",
  "properties": {
    "addr:full":"Km. 771, Strada St. 16 70052 Bisceglie Bisceglie Bari 70052",
    "addr:housenumber":"16",
    "addr:postcode":"70052;70052",
    "addr:street":"Strada St.",
    "iso:country":"IT",
    "sg:address":"Km. 771, Strada St. 16 70052 Bisceglie",
    "sg:city":"Bisceglie",
    "sg:classifiers":[
        {
            "category":"Real Estate",
            "subcategory":"Surveying",
            "type":"Services"
        }
    ],
    "sg:phone":"+39 080 395 1482",
    "sg:postcode":"70052",
    "sg:province":"Bari",
    "sg:tags":[
        "equipment",
        "material",
        "good",
        "-",
        "handling"
    ],
    "wof:name":"Centro Carrelli Elevatori",
    "wof:placetype":"venue"
},
  "geometry": {"coordinates":[16.869291,41.126053],"type":"Point"}
}