{
  "type": "Feature",
  "properties": {
    "iso:country":"IT",
    "sg:address":"2, Via Provinciale Per Piverone 10010 Azeglio",
    "sg:city":"Azeglio",
    "sg:classifiers":[
        {
            "category":"Manufacturing",
            "subcategory":"Lumber",
            "type":"Manufacturing & Wholesale Goods"
        }
    ],
    "sg:phone":"+39 0125 687999",
    "sg:postcode":"10010",
    "sg:province":"Torino",
    "sg:tags":[
        "wood"
    ],
    "wof:name":"Compensati Toro (s.p.a.)",
    "wof:placetype":"venue"
},
  "geometry": {"coordinates":[7.686619,45.07056],"type":"Point"}
}