{
  "type": "Feature",
  "properties": {
    "iso:country":"IT",
    "sg:address":"06073 Corciano",
    "sg:city":"Corciano",
    "sg:orig_category":"Forniture Per Edilizia E Lavori Pubblici",
    "sg:phone":"+39 075 529 3437",
    "sg:postcode":"06073",
    "sg:province":"Perugia",
    "wof:name":"Edil Beton Perugia Spa",
    "wof:placetype":"venue"
},
  "geometry": {"coordinates":[12.2775001526,43.0831298828],"type":"Point"}
}