{
  "type": "Feature",
  "properties": {
    "addr:full":"3 Piazzale Cadorna Luigi, 20123 Milano Milano Milano 20123",
    "addr:postcode":"20123;20123",
    "addr:street":"Piazzale Cadorna Luigi",
    "iso:country":"IT",
    "sg:address":"3 Piazzale Cadorna Luigi, 20123 Milano",
    "sg:city":"Milano",
    "sg:classifiers":[
        {
            "category":"Banks & Credit Unions",
            "subcategory":"Financial Services",
            "type":"Services"
        }
    ],
    "sg:phone":"+39 390 288 701",
    "sg:postcode":"20123",
    "sg:province":"Milano",
    "sg:tags":[
        "banking",
        "finance",
        "insurance"
    ],
    "wof:name":"Banca Banca Intesa Rete Mediocredito Lombardo",
    "wof:placetype":"venue"
},
  "geometry": {"coordinates":[9.1775846481,45.4675521851],"type":"Point"}
}