{
  "type": "Feature",
  "properties": {
    "addr:full":"20068 Peschiera Borromeo Peschiera Borromeo Milano 20068",
    "addr:postcode":"20068;20068",
    "iso:country":"IT",
    "sg:address":"20068 Peschiera Borromeo",
    "sg:city":"Peschiera Borromeo",
    "sg:orig_category":"Manutenzioni Tecnologiche Industriali",
    "sg:phone":"+39 02 5530 0510",
    "sg:postcode":"20068",
    "sg:province":"Milano",
    "wof:name":"Effegi Sistemi Idrodinamici Srl",
    "wof:placetype":"venue"
},
  "geometry": {"coordinates":[9.285807,45.429497],"type":"Point"}
}