{
  "type": "Feature",
  "properties": {
    "addr:full":"24050 Mornico Al Serio Mornico al Serio Bergamo 24050",
    "addr:housenumber":"serio",
    "addr:postcode":"24050;24050",
    "addr:street":"Serio",
    "iso:country":"IT",
    "sg:address":"24050 Mornico Al Serio",
    "sg:city":"Mornico al Serio",
    "sg:orig_category":"Macchine, Impianti Ed Attrezzature Per Abbigliamento E Pelletterie",
    "sg:phone":"+39 035 844832",
    "sg:postcode":"24050",
    "sg:province":"Bergamo",
    "wof:name":"Bottonificio Padano (s.p.a.)",
    "wof:placetype":"venue"
},
  "geometry": {"coordinates":[9.790628,45.589928],"type":"Point"}
}