{
  "type": "Feature",
  "properties": {
    "addr:full":"Via Pievano Rolando 6; Empoli; 50053 Empoli Firenze 50053",
    "addr:housenumber":"6",
    "addr:postcode":"50053;50053",
    "addr:street":"Via Pievano Rolando",
    "iso:country":"IT",
    "sg:address":"Via Pievano Rolando 6; Empoli; 50053",
    "sg:city":"Empoli",
    "sg:classifiers":[
        {
            "category":"Banks & Credit Unions",
            "subcategory":"Bank",
            "type":"Services"
        }
    ],
    "sg:phone":"+39 0571 7031",
    "sg:postcode":"50053",
    "sg:province":"Firenze",
    "wof:name":"Cassa Di Risparmio Di Firenze Spa",
    "wof:placetype":"venue"
},
  "geometry": {"coordinates":[10.9484,43.722099],"type":"Point"}
}