{
  "type": "Feature",
  "properties": {
    "addr:full":"24060 Bossico Bossico Bergamo 24060",
    "addr:postcode":"24060;24060",
    "iso:country":"IT",
    "sg:address":"24060 Bossico",
    "sg:city":"Bossico",
    "sg:orig_category":"Forniture Per Edilizia E Lavori Pubblici. Prodotti Vari In Metallo",
    "sg:phone":"+39 035 968370",
    "sg:postcode":"24060",
    "sg:province":"Bergamo",
    "wof:name":"Belli Bruno",
    "wof:placetype":"venue"
},
  "geometry": {"coordinates":[10.0484657288,45.8286590576],"type":"Point"}
}