{
  "type": "Feature",
  "properties": {
    "iso:country":"IT",
    "sg:address":"7, Via Monferrato 20094 Corsico",
    "sg:city":"Corsico",
    "sg:classifiers":[
        {
            "category":"Professional",
            "subcategory":"Advertising",
            "type":"Services"
        }
    ],
    "sg:phone":"+39 39024587981",
    "sg:postcode":"20094",
    "sg:province":"Milano",
    "sg:tags":[
        "communication",
        "medium"
    ],
    "wof:name":"Barco S.r.l.",
    "wof:placetype":"venue"
},
  "geometry": {"coordinates":[9.108417,45.450001],"type":"Point"}
}