{
  "type": "Feature",
  "properties": {
    "iso:country":"IT",
    "sg:address":"64, Via Guglielmo Marconi 27019 Villanterio",
    "sg:city":"Villanterio",
    "sg:classifiers":[
        {
            "category":"Food & Beverages",
            "subcategory":"Groceries & Convenience Stores",
            "type":"Retail Goods"
        }
    ],
    "sg:phone":"+39 0382 967961",
    "sg:postcode":"27019",
    "sg:province":"Pavia",
    "sg:tags":[
        "product",
        "related"
    ],
    "wof:name":"Bolzoni Alimentari (s.a.s.)",
    "wof:placetype":"venue"
},
  "geometry": {"coordinates":[9.1565628052,45.1858863831],"type":"Point"}
}