{
  "type": "Feature",
  "properties": {
    "iso:country":"IT",
    "sg:address":"21038 Leggiuno",
    "sg:city":"Leggiuno",
    "sg:orig_category":"Filati E Materie Prime Tessili",
    "sg:phone":"+39 0332 648370",
    "sg:postcode":"21038",
    "sg:province":"Varese",
    "wof:name":"El Remissel",
    "wof:placetype":"venue"
},
  "geometry": {"coordinates":[8.612616539,45.8702583313],"type":"Point"}
}