{
  "type": "Feature",
  "properties": {
    "iso:country":"IT",
    "sg:address":"26018 Trigolo",
    "sg:city":"Trigolo",
    "sg:orig_category":"Non-classified Establishments",
    "sg:phone":"+39 0374 370132",
    "sg:postcode":"26018",
    "sg:province":"Cremona",
    "wof:name":"Nuova C.a.m.a. Snc",
    "wof:placetype":"venue"
},
  "geometry": {"coordinates":[9.825205,45.319408],"type":"Point"}
}