{
  "type": "Feature",
  "properties": {
    "addr:full":"15, Via Cristoforo Colombo 35011 Campodarsego Campodarsego Padova 35011",
    "addr:postcode":"35011;35011",
    "addr:street":"Via Cristoforo Colombo",
    "iso:country":"IT",
    "sg:address":"15, Via Cristoforo Colombo 35011 Campodarsego",
    "sg:city":"Campodarsego",
    "sg:classifiers":[
        {
            "category":"Wholesale",
            "subcategory":"Drugs",
            "type":"Manufacturing & Wholesale Goods"
        }
    ],
    "sg:phone":"+39 049 920 1166",
    "sg:postcode":"35011",
    "sg:province":"Padova",
    "sg:tags":[
        "chemical",
        "pharmaceutical"
    ],
    "wof:name":"Rossi Di Rossi Alessandro & C. (s.a.s.)",
    "wof:placetype":"venue"
},
  "geometry": {"coordinates":[11.906093,45.485035],"type":"Point"}
}