{
  "type": "Feature",
  "properties": {
    "iso:country":"IT",
    "sg:address":"49, Via Isonzo 15100 Alessandria",
    "sg:city":"Alessandria",
    "sg:classifiers":[
        {
            "category":"Shopping",
            "subcategory":"Stationery & Office Supplies",
            "type":"Retail Goods"
        }
    ],
    "sg:phone":"+39 0131 252925",
    "sg:postcode":"15100",
    "sg:province":"Alessandria",
    "sg:tags":[
        "professional"
    ],
    "wof:name":"Pelizza Srl",
    "wof:placetype":"venue"
},
  "geometry": {"coordinates":[8.6275272369,44.9102973938],"type":"Point"}
}