{
  "type": "Feature",
  "properties": {
    "iso:country":"IT",
    "sg:address":"Via Corte, 117; Taio; 38010",
    "sg:classifiers":[
        {
            "category":"Banks & Credit Unions",
            "subcategory":"Bank",
            "type":"Services"
        }
    ],
    "sg:phone":"+39 0463 38305",
    "sg:postcode":"38010",
    "sg:province":"Trento",
    "wof:name":"Cassa Rurale Di Segno",
    "wof:placetype":"venue"
},
  "geometry": {"coordinates":[11.071111,46.321705],"type":"Point"}
}