{
  "type": "Feature",
  "properties": {
    "addr:full":"54033 Carrara Carrara Massa-Carrara 54033",
    "addr:postcode":"54033;54033",
    "iso:country":"IT",
    "sg:address":"54033 Carrara",
    "sg:city":"Carrara",
    "sg:orig_category":"Antinfortunistica - Attrezzature Ed Articoli",
    "sg:phone":"+39 0585 884540",
    "sg:postcode":"54033",
    "sg:province":"Massa-Carrara",
    "sg:website":"http://www.quarryservice.com",
    "wof:name":"Quarry Service Srl",
    "wof:placetype":"venue"
},
  "geometry": {"coordinates":[10.069613,44.057018],"type":"Point"}
}