{
  "type": "Feature",
  "properties": {
    "addr:full":"21049 Tradate Tradate Varese 21049",
    "addr:postcode":"21049;21049",
    "iso:country":"IT",
    "sg:address":"21049 Tradate",
    "sg:city":"Tradate",
    "sg:orig_category":"Ricetrasmittenti Ed Attrezzature Per Radioamatori",
    "sg:phone":"+39 0331 842131",
    "sg:postcode":"21049",
    "sg:province":"Varese",
    "wof:name":"Vecchiato Maurizio - Telecomunicazioni Vecchiato",
    "wof:placetype":"venue"
},
  "geometry": {"coordinates":[8.890911,45.75753],"type":"Point"}
}