{
  "type": "Feature",
  "properties": {
    "iso:country":"IT",
    "sg:address":"22063 Cantu'",
    "sg:orig_category":"Servizi E Lavori Per Arredamento E Industria Del Legno. Arte Ed Artigianato Artistico",
    "sg:phone":"+39 031 711883",
    "sg:postcode":"22063",
    "sg:province":"Como",
    "wof:name":"Zappa Angelo",
    "wof:placetype":"venue"
},
  "geometry": {"coordinates":[9.129736,45.739044],"type":"Point"}
}