{
  "type": "Feature",
  "properties": {
    "iso:country":"IT",
    "sg:address":"20031 Cesano Maderno",
    "sg:city":"Cesano Maderno",
    "sg:orig_category":"Macchine, Impianti Ed Attrezzature Per Industria Alimentare E Bevande. Apparecchiature E Sistemi Per Imballaggio E Confezionamento",
    "sg:phone":"+39 036 250 8792",
    "sg:postcode":"20031",
    "sg:province":"Milano",
    "wof:name":"Siem S.r.l.",
    "wof:placetype":"venue"
},
  "geometry": {"coordinates":[9.148945,45.627731],"type":"Point"}
}