{
  "type": "Feature",
  "properties": {
    "iso:country":"IT",
    "sg:address":"Via Marano 46 33037 Pasian Di Prato",
    "sg:city":"Pasian di Prato",
    "sg:classifiers":[
        {
            "category":"Wholesale",
            "subcategory":"Books, Periodicals, & Newspapers",
            "type":"Manufacturing & Wholesale Goods"
        }
    ],
    "sg:phone":"+39 0432 699390",
    "sg:postcode":"33037",
    "sg:province":"Udine",
    "sg:tags":[
        "publisher",
        "book",
        "art"
    ],
    "sg:website":"www.campanottoeditore.it",
    "wof:name":"Campanotto Editore",
    "wof:placetype":"venue"
},
  "geometry": {"coordinates":[13.190882,46.039806],"type":"Point"}
}