{
  "type": "Feature",
  "properties": {
    "iso:country":"IT",
    "sg:address":"Via C. Battisti; Contarina; 45014",
    "sg:city":"Contarina",
    "sg:classifiers":[
        {
            "category":"Banks & Credit Unions",
            "subcategory":"Bank",
            "type":"Services"
        }
    ],
    "sg:phone":"+39 0426 631034",
    "sg:postcode":"45014",
    "sg:province":"Rovigo",
    "wof:name":"Banco Popolare Veneta",
    "wof:placetype":"venue"
},
  "geometry": {"coordinates":[12.219851,45.020218],"type":"Point"}
}