{
  "type": "Feature",
  "properties": {
    "iso:country":"IT",
    "sg:address":"30125 Venezia",
    "sg:city":"Venezia",
    "sg:classifiers":[
        {
            "category":"Professional",
            "subcategory":"Business Services",
            "type":"Services"
        }
    ],
    "sg:phone":"+39 041 522 9521",
    "sg:postcode":"30125",
    "sg:province":"Venezia",
    "sg:tags":[
        "support",
        "companies",
        "events",
        "trade"
    ],
    "sg:website":"http://www.paginegialle.it/rubelli",
    "wof:name":"A. Rubelli & C. Snc",
    "wof:placetype":"venue"
},
  "geometry": {"coordinates":[12.33392,45.438721],"type":"Point"}
}