{
  "type": "Feature",
  "properties": {
    "addr:full":"94018 Troina Troina Enna 94018",
    "addr:postcode":"94018;94018",
    "iso:country":"IT",
    "sg:address":"94018 Troina",
    "sg:city":"Troina",
    "sg:orig_category":"Studi E Consulenze Tecniche E Industriali. Servizi E Lavori Per Edilizia E Lavori Pubblici. Professionisti - Studi E Servizi Ed Associazioni Di Interesse Aziendale",
    "sg:phone":"+39 0935 657129",
    "sg:postcode":"94018",
    "sg:province":"Enna",
    "wof:name":"A.g.a. Ambiente E Geologia Applicata - Studio Geologico - Rizzo Geologo Antonio",
    "wof:placetype":"venue"
},
  "geometry": {"coordinates":[14.271918,37.567562],"type":"Point"}
}