{
  "type": "Feature",
  "properties": {
    "iso:country":"IT",
    "sg:address":"20090 Settala",
    "sg:city":"Caleppio",
    "sg:orig_category":"Arredo Cucina Ed Elettrodomestici. Elettrodomestici",
    "sg:phone":"+39 02 9530 7282",
    "sg:postcode":"20090",
    "sg:province":"Milano",
    "wof:name":"Scafuri Carmela",
    "wof:placetype":"venue"
},
  "geometry": {"coordinates":[9.380905,45.435616],"type":"Point"}
}