{
  "type": "Feature",
  "properties": {
    "iso:country":"IT",
    "sg:address":"80049 Somma Vesuviana",
    "sg:city":"Somma Vesuviana",
    "sg:orig_category":"Non-classified Establishments",
    "sg:phone":"+39 081 899 3262",
    "sg:postcode":"80049",
    "sg:province":"Napoli",
    "wof:name":"Il Gocciolatoio Di Casciello Pasquale",
    "wof:placetype":"venue"
},
  "geometry": {"coordinates":[14.437396,40.878773],"type":"Point"}
}