{
  "type": "Feature",
  "properties": {
    "addr:full":"73019 Trepuzzi Trepuzzi Lecce 73019",
    "addr:postcode":"73019;73019",
    "iso:country":"IT",
    "sg:address":"73019 Trepuzzi",
    "sg:city":"Trepuzzi",
    "sg:classifiers":[
        {
            "category":"Health Services",
            "subcategory":"Nursing And Care Facility",
            "type":"Services"
        }
    ],
    "sg:phone":"+39 0832 753338",
    "sg:postcode":"73019",
    "sg:province":"Lecce",
    "sg:tags":[
        "case",
        "cura",
        "private",
        "di"
    ],
    "wof:name":"Residenza Per Anziani Giada - Sibem Srl",
    "wof:placetype":"venue"
},
  "geometry": {"coordinates":[18.076578,40.405273],"type":"Point"}
}