{
  "type": "Feature",
  "properties": {
    "iso:country":"IT",
    "sg:address":"28883 Gravellona Toce",
    "sg:city":"Gravellona Toce",
    "sg:orig_category":"Manufacturers: Prefabbricati",
    "sg:phone":"+39 0323 848098",
    "sg:postcode":"28883",
    "sg:province":"Verbano-Cusio-Ossola",
    "wof:name":"Cavigioli Snc",
    "wof:placetype":"venue"
},
  "geometry": {"coordinates":[8.428492,45.930679],"type":"Point"}
}