{
  "type": "Feature",
  "properties": {
    "addr:full":"16156 Genova Genova Genova 16156",
    "addr:housenumber":"16156",
    "addr:postcode":"16156",
    "iso:country":"IT",
    "sg:address":"16156 Genova",
    "sg:city":"Genova",
    "sg:orig_category":"Animali Domestici - Vendita",
    "sg:phone":"+39 010 697 3734",
    "sg:postcode":"16156",
    "sg:province":"Genova",
    "wof:name":"Animal's House Di Orsenigo Marzorati Luigi",
    "wof:placetype":"venue"
},
  "geometry": {"coordinates":[8.808983,44.428402],"type":"Point"}
}