{
  "type": "Feature",
  "properties": {
    "iso:country":"IT",
    "sg:address":"Viale Martiri Della Liberta; Albenga; 17031",
    "sg:city":"Albenga",
    "sg:classifiers":[
        {
            "category":"Banks & Credit Unions",
            "subcategory":"Bank",
            "type":"Services"
        }
    ],
    "sg:phone":"+39 0182 540265",
    "sg:postcode":"17031",
    "sg:province":"Savona",
    "wof:name":"Banca Popolare Di Novara",
    "wof:placetype":"venue"
},
  "geometry": {"coordinates":[8.217738,44.047665],"type":"Point"}
}