{
  "type": "Feature",
  "properties": {
    "iso:country":"IT",
    "sg:address":"10060 Airasca",
    "sg:city":"Airasca",
    "sg:orig_category":"Ribaltabili Per Autocarri E Rimorchi",
    "sg:phone":"+39 011 985 8942",
    "sg:postcode":"10060",
    "sg:province":"Torino",
    "wof:name":"Barberis Guido",
    "wof:placetype":"venue"
},
  "geometry": {"coordinates":[7.75451,45.094978],"type":"Point"}
}