{
  "type": "Feature",
  "properties": {
    "addr:full":"Monte Sant'elia, 14/18 24047 Treviglio Treviglio Bergamo 24047",
    "addr:housenumber":"14 / 18",
    "addr:postcode":"24047;24047",
    "addr:street":"Monte Sant'Elia",
    "iso:country":"IT",
    "sg:address":"Monte Sant'elia, 14/18 24047 Treviglio",
    "sg:city":"Treviglio",
    "sg:classifiers":[
        {
            "category":"Utilities",
            "subcategory":"Electric",
            "type":"Services"
        }
    ],
    "sg:phone":"+39 036 347060",
    "sg:postcode":"24047",
    "sg:province":"Bergamo",
    "sg:tags":[
        "transformer"
    ],
    "sg:website":"www.dte-trasformatori.it",
    "wof:name":"D.t.e. Snc",
    "wof:placetype":"venue"
},
  "geometry": {"coordinates":[9.669952,45.694904],"type":"Point"}
}