{
  "type": "Feature",
  "properties": {
    "addr:full":"20020 Arese Arese Milano 20020",
    "addr:postcode":"20020;20020",
    "iso:country":"IT",
    "sg:address":"20020 Arese",
    "sg:city":"Arese",
    "sg:orig_category":"Forniture Per Agricoltura E Zootecnia. Prodotti Chimici Secondari",
    "sg:phone":"+39 02 9358 0861",
    "sg:postcode":"20020",
    "sg:province":"Milano",
    "wof:name":"Scotts Italia Srl",
    "wof:placetype":"venue"
},
  "geometry": {"coordinates":[9.086098671,45.5467987061],"type":"Point"}
}