{
  "type": "Feature",
  "properties": {
    "iso:country":"IT",
    "sg:address":"41100 Modena",
    "sg:city":"Modena",
    "sg:orig_category":"Videogiochi, Flippers E Biliardini - Vendita Al Dettaglio E Noleggio",
    "sg:phone":"+39 059 281122",
    "sg:postcode":"41100",
    "sg:province":"Modena",
    "wof:name":"Elettrogiochi Garuti & C. Srl",
    "wof:placetype":"venue"
},
  "geometry": {"coordinates":[10.965435,44.631721],"type":"Point"}
}