{
  "type": "Feature",
  "properties": {
    "iso:country":"IT",
    "sg:address":"2, Strada Delle Saline 34015 Muggia",
    "sg:city":"Muggia",
    "sg:classifiers":[
        {
            "category":"Autos & Motor Vehicles",
            "subcategory":"Automobile Sales",
            "type":"Retail Goods"
        }
    ],
    "sg:phone":"+39 39040232371",
    "sg:postcode":"34015",
    "sg:province":"Trieste",
    "sg:tags":[
        "motor-cars"
    ],
    "wof:name":"Auto Line Trieste Srl",
    "wof:placetype":"venue"
},
  "geometry": {"coordinates":[13.8004016876,45.5931243896],"type":"Point"}
}