{
  "type": "Feature",
  "properties": {
    "addr:full":"13019 Varallo Varallo Vercelli 13019",
    "addr:postcode":"13019;13019",
    "iso:country":"IT",
    "sg:address":"13019 Varallo",
    "sg:city":"Varallo",
    "sg:orig_category":"Servizi E Lavori Per Ecologia E Smaltimento Rifiuti. Termotecnica E Riscaldamento, Apparecchiature E Servizi. Servizi Ausiliari Di Sorveglianza, Manutenzione E Pulizia",
    "sg:phone":"+39 0163 51813",
    "sg:postcode":"13019",
    "sg:province":"Vercelli",
    "wof:name":"Bianconi Fulvio",
    "wof:placetype":"venue"
},
  "geometry": {"coordinates":[8.2479419708,45.8158874512],"type":"Point"}
}