{
  "type": "Feature",
  "properties": {
    "addr:full":"22070 Cirimido Cirimido Como 22070",
    "addr:postcode":"22070;22070",
    "iso:country":"IT",
    "sg:address":"22070 Cirimido",
    "sg:city":"Cirimido",
    "sg:orig_category":"Graniti",
    "sg:phone":"+39 031 895070",
    "sg:postcode":"22070",
    "sg:province":"Como",
    "wof:name":"Arredo Marmi E Graniti Di Castiglioni Dante",
    "wof:placetype":"venue"
},
  "geometry": {"coordinates":[9.013783,45.700523],"type":"Point"}
}