{
  "type": "Feature",
  "properties": {
    "iso:country":"IT",
    "sg:address":"Via Oslavia 21 21049 Tradate",
    "sg:city":"Tradate",
    "sg:orig_category":"Measuring Transducers For Temperature",
    "sg:phone":"+39 0331 841070",
    "sg:postcode":"21049",
    "sg:province":"Varese",
    "sg:website":"www.datexel.it",
    "wof:name":"Datexel Srl",
    "wof:placetype":"venue"
},
  "geometry": {"coordinates":[8.908618,45.703327],"type":"Point"}
}