{
  "type": "Feature",
  "properties": {
    "addr:full":"41051 Castelnuovo Rangone Castelnuovo Rangone Modena 41051",
    "addr:postcode":"41051;41051",
    "iso:country":"IT",
    "sg:address":"41051 Castelnuovo Rangone",
    "sg:city":"Castelnuovo Rangone",
    "sg:orig_category":"Porte Basculanti E Ribaltabili",
    "sg:phone":"+39 059 536250",
    "sg:postcode":"41051",
    "sg:province":"Modena",
    "sg:website":"http://www.tiemmeserramenti.it",
    "wof:name":"Ti-emme Srl",
    "wof:placetype":"venue"
},
  "geometry": {"coordinates":[10.9287128448,44.5521774292],"type":"Point"}
}