{
  "type": "Feature",
  "properties": {
    "iso:country":"IT",
    "sg:address":"20134 Milano",
    "sg:city":"Milano",
    "sg:orig_category":"Chiese Ed Associazioni Religiose",
    "sg:phone":"+39 02 2641 3054",
    "sg:postcode":"20134",
    "sg:province":"Milano",
    "wof:name":"Fraternita' Di Comunione E Liberazione",
    "wof:placetype":"venue"
},
  "geometry": {"coordinates":[9.253256,45.486923],"type":"Point"}
}