{
  "type": "Feature",
  "properties": {
    "addr:full":"17031 Albenga Albenga Savona 17031",
    "addr:postcode":"17031;17031",
    "iso:country":"IT",
    "sg:address":"17031 Albenga",
    "sg:city":"Albenga",
    "sg:orig_category":"Campeggio. Alberghi E Strutture Extra Alberghiere",
    "sg:phone":"+39 0182 51957",
    "sg:postcode":"17031",
    "sg:province":"Savona",
    "wof:name":"Delfino Maria",
    "wof:placetype":"venue"
},
  "geometry": {"coordinates":[8.212304,44.037579],"type":"Point"}
}