{
  "type": "Feature",
  "properties": {
    "addr:full":"43037 Lesignano De' Bagni Parma 43037",
    "addr:postcode":"43037;43037",
    "iso:country":"IT",
    "sg:address":"43037 Lesignano De' Bagni",
    "sg:orig_category":"Autofficine E Centri Assistenza",
    "sg:phone":"+39 0521 850631",
    "sg:postcode":"43037",
    "sg:province":"Parma",
    "wof:name":"Motoristica Salvato",
    "wof:placetype":"venue"
},
  "geometry": {"coordinates":[10.303425,44.647057],"type":"Point"}
}