{
  "type": "Feature",
  "properties": {
    "iso:country":"IT",
    "sg:address":"Corso Novara 35 10078 Venaria",
    "sg:classifiers":[
        {
            "category":"Shopping",
            "subcategory":"Books",
            "type":"Retail Goods"
        }
    ],
    "sg:phone":"+39 011 455 1433",
    "sg:postcode":"10078",
    "sg:province":"Torino",
    "wof:name":"Graf Art Officine Grafiche Artistiche Srl",
    "wof:placetype":"venue"
},
  "geometry": {"coordinates":[7.633712,45.113628],"type":"Point"}
}