{
  "type": "Feature",
  "properties": {
    "iso:country":"IT",
    "sg:address":"98040 Catania",
    "sg:orig_category":"Apparecchiature E Sistemi Per Magazzinaggio E Movimentazione",
    "sg:phone":"+39 095 295486",
    "sg:postcode":"98040",
    "sg:province":"Messina",
    "wof:name":"A.v.i.r. Spa",
    "wof:placetype":"venue"
},
  "geometry": {"coordinates":[15.555523,38.192333],"type":"Point"}
}