{
  "type": "Feature",
  "properties": {
    "iso:country":"IT",
    "sg:address":"06012 Citta' Di Castello",
    "sg:orig_category":"Mobili - Produzione E Ingrosso",
    "sg:phone":"+39 075 855 5006",
    "sg:postcode":"06012",
    "sg:province":"Perugia",
    "wof:name":"Artistica Rossi Srl",
    "wof:placetype":"venue"
},
  "geometry": {"coordinates":[12.2248487473,43.4753189087],"type":"Point"}
}