{
  "type": "Feature",
  "properties": {
    "iso:country":"IT",
    "sg:address":"60044 Fabriano",
    "sg:city":"Fabriano",
    "sg:orig_category":"Lavorazioni Meccaniche E Servizi",
    "sg:phone":"+39 0732 626370",
    "sg:postcode":"60044",
    "sg:province":"Ancona",
    "sg:website":"http://www.mosat.it",
    "wof:name":"Mosat Srl",
    "wof:placetype":"venue"
},
  "geometry": {"coordinates":[12.851483,43.331989],"type":"Point"}
}