{
  "type": "Feature",
  "properties": {
    "addr:full":"35127 Padova Padova Padova 35127",
    "addr:postcode":"35127;35127",
    "iso:country":"IT",
    "sg:address":"35127 Padova",
    "sg:city":"Padova",
    "sg:orig_category":"Elettricita' Materiali - Ingrosso",
    "sg:phone":"+39 049 870 1177",
    "sg:postcode":"35127",
    "sg:province":"Padova",
    "sg:website":"http://www.favaron.it",
    "wof:name":"Favaron Elettrorappresentanze Snc",
    "wof:placetype":"venue"
},
  "geometry": {"coordinates":[11.934061,45.387646],"type":"Point"}
}