{
  "type": "Feature",
  "properties": {
    "iso:country":"IT",
    "sg:address":"10022 Carmagnola",
    "sg:city":"Carmagnola",
    "sg:classifiers":[
        {
            "category":"Wholesale",
            "subcategory":"Machinery & Supplies",
            "type":"Manufacturing & Wholesale Goods"
        }
    ],
    "sg:phone":"+39 011 972 3760",
    "sg:postcode":"10022",
    "sg:province":"Torino",
    "sg:tags":[
        "activities",
        "industrial"
    ],
    "wof:name":"Rpm Srl",
    "wof:placetype":"venue"
},
  "geometry": {"coordinates":[7.711622,44.83749],"type":"Point"}
}