{
  "type": "Feature",
  "properties": {
    "addr:full":"56043 Acciaiolo Pisa 56043",
    "addr:postcode":"56043;56043",
    "iso:country":"IT",
    "sg:address":"56043 Acciaiolo",
    "sg:orig_category":"Riparazione Dei Mezzi Di Trasporto. Servizi Ausiliari Dei Mezzi Di Trasporto",
    "sg:phone":"+39 050 659052",
    "sg:postcode":"56043",
    "sg:province":"Pisa",
    "wof:name":"Cipriani Motorsport Di Cipriani Federico & C. Sas",
    "wof:placetype":"venue"
},
  "geometry": {"coordinates":[10.50893,43.548996],"type":"Point"}
}