{
  "type": "Feature",
  "properties": {
    "iso:country":"IT",
    "sg:address":"20122 Milano",
    "sg:city":"Milano",
    "sg:orig_category":"Studi E Consulenze Legali E Notarili. Avvocati, Notai E Servizi Legali. Professionisti - Studi E Servizi Ed Associazioni Di Interesse Aziendale",
    "sg:phone":"+39 02 545 5916",
    "sg:postcode":"20122",
    "sg:province":"Milano",
    "wof:name":"Fontana Alfiero",
    "wof:placetype":"venue"
},
  "geometry": {"coordinates":[9.200422,45.461826],"type":"Point"}
}