{
  "type": "Feature",
  "properties": {
    "iso:country":"IT",
    "sg:address":"38010 Andalo Valtellino",
    "sg:city":"Andalo",
    "sg:orig_category":"Legno E Semilavorati",
    "sg:phone":"+39 0342 685315",
    "sg:postcode":"38010",
    "sg:province":"Trento",
    "wof:name":"Mariana Franco & C. Snc",
    "wof:placetype":"venue"
},
  "geometry": {"coordinates":[11.005167,46.166111],"type":"Point"}
}