{
  "type": "Feature",
  "properties": {
    "iso:country":"IT",
    "sg:address":"41030 Bomporto",
    "sg:city":"Bomporto",
    "sg:orig_category":"Disinfezione, Disinfestazione E Derattizzazione",
    "sg:phone":"+39 059 907081",
    "sg:postcode":"41030",
    "sg:province":"Modena",
    "sg:website":"http://www.cleansnc.com",
    "wof:name":"Picardi Pasquale",
    "wof:placetype":"venue"
},
  "geometry": {"coordinates":[11.004678,44.747219],"type":"Point"}
}