{
  "type": "Feature",
  "properties": {
    "iso:country":"IT",
    "sg:address":"01100 Viterbo",
    "sg:city":"Viterbo",
    "sg:orig_category":"Pubblicita' - Agenzie Studi",
    "sg:phone":"+39 0761 270517",
    "sg:postcode":"01100",
    "sg:province":"Viterbo",
    "sg:website":"http://www.publigraphicline.com",
    "wof:name":"Graphic Line Di Aiello Giorgio",
    "wof:placetype":"venue"
},
  "geometry": {"coordinates":[12.0489788055,42.4415359497],"type":"Point"}
}