{
  "type": "Feature",
  "properties": {
    "addr:full":"Corso V. Veneto, 51; Osio Sotto; 24016 Bergamo 24016",
    "addr:housenumber":"51",
    "addr:postcode":"24016;24016",
    "addr:street":"Corso V. Veneto",
    "iso:country":"IT",
    "sg:address":"Corso V. Veneto, 51; Osio Sotto; 24016",
    "sg:classifiers":[
        {
            "category":"Banks & Credit Unions",
            "subcategory":"Bank",
            "type":"Services"
        }
    ],
    "sg:phone":"+39 035 808070",
    "sg:postcode":"24016",
    "sg:province":"Bergamo",
    "wof:name":"Banca Agricola Milanese Spa",
    "wof:placetype":"venue"
},
  "geometry": {"coordinates":[9.589703,45.613148],"type":"Point"}
}