{
  "type": "Feature",
  "properties": {
    "iso:country":"IT",
    "sg:address":"18, Via San Martino 23821 Abbadia Lariana",
    "sg:city":"Abbadia Lariana",
    "sg:classifiers":[
        {
            "category":"Communications",
            "subcategory":"Television Station",
            "type":"Services"
        }
    ],
    "sg:phone":"+39 0341 732161",
    "sg:postcode":"23821",
    "sg:province":"Lecco",
    "sg:tags":[
        "audio-visual"
    ],
    "wof:name":"Helman Elettronica (s.p.a.)",
    "wof:placetype":"venue"
},
  "geometry": {"coordinates":[9.400583,45.871326],"type":"Point"}
}