{
  "type": "Feature",
  "properties": {
    "iso:country":"IT",
    "sg:address":"Via Provinciale Per Sacca 55 43052 Colorno",
    "sg:city":"Colorno",
    "sg:classifiers":[
        {
            "category":"Manufacturing",
            "subcategory":"Textiles",
            "type":"Manufacturing & Wholesale Goods"
        }
    ],
    "sg:phone":"+39 0521 816371",
    "sg:postcode":"43052",
    "sg:province":"Parma",
    "sg:tags":[
        "polyester",
        "yarn"
    ],
    "sg:website":"www.effegidi.com",
    "wof:name":"Effegidi International Spa",
    "wof:placetype":"venue"
},
  "geometry": {"coordinates":[10.3295478821,44.8078651428],"type":"Point"}
}