{
  "type": "Feature",
  "properties": {
    "addr:full":"Vle Del Lavoro 80c 36021 Barbarano Vicentino Barbarano Vicentino Vicenza 36021",
    "addr:housenumber":"80c",
    "addr:postcode":"36021;36021",
    "addr:street":"Vle Del Lavoro;Vicentino",
    "iso:country":"IT",
    "sg:address":"Vle Del Lavoro 80c 36021 Barbarano Vicentino",
    "sg:city":"Barbarano Vicentino",
    "sg:classifiers":[
        {
            "category":"Manufacturing",
            "subcategory":"Rubber & Plastics",
            "type":"Manufacturing & Wholesale Goods"
        }
    ],
    "sg:phone":"+39 0444 795322",
    "sg:postcode":"36021",
    "sg:province":"Vicenza",
    "sg:tags":[
        "pipe",
        "piping"
    ],
    "sg:website":"www.plastmecpvc.it",
    "wof:name":"Plast Mec Pvc Spa",
    "wof:placetype":"venue"
},
  "geometry": {"coordinates":[11.526389122,45.5752792358],"type":"Point"}
}