{
  "type": "Feature",
  "properties": {
    "iso:country":"IT",
    "sg:address":"21013 Gallarate",
    "sg:city":"Gallarate",
    "sg:orig_category":"Prodotti Finiti Stampati. Forniture Per Uffici. Regalistica Aziendale",
    "sg:phone":"+39 0331 797024",
    "sg:postcode":"21013",
    "sg:province":"Varese",
    "wof:name":"Angelo Borghi Sas Di Tosi Pasquale & C.",
    "wof:placetype":"venue"
},
  "geometry": {"coordinates":[8.7992763519,45.6648635864],"type":"Point"}
}