{
  "type": "Feature",
  "properties": {
    "iso:country":"IT",
    "sg:address":"110, Via Trincea Delle Frasche 00054 Fiumicino",
    "sg:city":"Fiumicino",
    "sg:classifiers":[
        {
            "category":"Communications",
            "subcategory":"Television Station",
            "type":"Services"
        }
    ],
    "sg:phone":"+39 39066582529",
    "sg:postcode":"00054",
    "sg:province":"Roma",
    "sg:tags":[
        "audio-visual"
    ],
    "wof:name":"Proper Motion Srl",
    "wof:placetype":"venue"
},
  "geometry": {"coordinates":[12.253522,41.755268],"type":"Point"}
}