{
  "type": "Feature",
  "properties": {
    "addr:full":"10024 Moncalieri Moncalieri Torino 10024",
    "addr:postcode":"10024;10024",
    "iso:country":"IT",
    "sg:address":"10024 Moncalieri",
    "sg:city":"Moncalieri",
    "sg:orig_category":"Bevande, Vini E Liquori",
    "sg:phone":"+39 011 681 3872",
    "sg:postcode":"10024",
    "sg:province":"Torino",
    "wof:name":"Partesa Piemonte S.r.l.",
    "wof:placetype":"venue"
},
  "geometry": {"coordinates":[7.684765,45.001503],"type":"Point"}
}