{
  "type": "Feature",
  "properties": {
    "iso:country":"IT",
    "sg:address":"Via Spongano 73030 Diso",
    "sg:city":"Diso",
    "sg:classifiers":[
        {
            "category":"Manufacturing",
            "subcategory":"Metals",
            "type":"Manufacturing & Wholesale Goods"
        }
    ],
    "sg:phone":"+39 0836 920732",
    "sg:postcode":"73030",
    "sg:province":"Lecce",
    "sg:tags":[
        "processing"
    ],
    "wof:name":"Corvaglia Srl",
    "wof:placetype":"venue"
},
  "geometry": {"coordinates":[18.3864097595,40.009765625],"type":"Point"}
}