{
  "type": "Feature",
  "properties": {
    "addr:full":"80125 Napoli Napoli Napoli 80125",
    "addr:housenumber":"80125",
    "addr:postcode":"80125",
    "iso:country":"IT",
    "sg:address":"80125 Napoli",
    "sg:city":"Napoli",
    "sg:orig_category":"Medici. Assicurazioni E Servizi Assicurativi. Avvocati, Notai E Servizi Legali. Professionisti - Studi E Servizi Ed Associazioni Di Interesse Aziendale",
    "sg:phone":"+39 081 570 7447",
    "sg:postcode":"80125",
    "sg:province":"Napoli",
    "wof:name":"Co.di.me - Compagnia Diagnostica Mediterranea Srl",
    "wof:placetype":"venue"
},
  "geometry": {"coordinates":[14.2806415558,40.8998794556],"type":"Point"}
}