{
  "type": "Feature",
  "properties": {
    "iso:country":"IT",
    "sg:address":"36016 Thiene",
    "sg:city":"Thiene",
    "sg:orig_category":"Stampi Materie Plastiche E Gomma",
    "sg:phone":"+39 0445 854501",
    "sg:postcode":"36016",
    "sg:province":"Vicenza",
    "sg:website":"http://www.lpasrl.it",
    "wof:name":"L.p.a. Srl",
    "wof:placetype":"venue"
},
  "geometry": {"coordinates":[11.512211,45.527691],"type":"Point"}
}