{
  "type": "Feature",
  "properties": {
    "addr:full":"00136 Roma Roma Roma 00136",
    "addr:postcode":"00136;00136",
    "iso:country":"IT",
    "sg:address":"00136 Roma",
    "sg:city":"Roma",
    "sg:orig_category":"Forniture Per Edilizia E Lavori Pubblici. Forniture Per Attivita' Industriali",
    "sg:phone":"+39 06 3972 0708",
    "sg:postcode":"00136",
    "sg:province":"Roma",
    "wof:name":"Studio Roma Tre Soc. Coop. A R.l.",
    "wof:placetype":"venue"
},
  "geometry": {"coordinates":[12.4488763809,41.9062995911],"type":"Point"}
}