{
  "type": "Feature",
  "properties": {
    "iso:country":"IT",
    "sg:address":"Via Barozzi Michele 4 20122 Milano",
    "sg:city":"Milano",
    "sg:classifiers":[
        {
            "category":"Real Estate",
            "subcategory":"Real Estate Services",
            "type":"Services"
        }
    ],
    "sg:phone":"+39 02 7600 5021",
    "sg:postcode":"20122",
    "sg:province":"Milano",
    "sg:tags":[
        "pharmaceutical",
        "material",
        "raw"
    ],
    "wof:name":"Laboratori Derivati Organici Spa",
    "wof:placetype":"venue"
},
  "geometry": {"coordinates":[9.2027740479,45.4699440002],"type":"Point"}
}