{
  "type": "Feature",
  "properties": {
    "iso:country":"IT",
    "sg:address":"12030 Carmagnola",
    "sg:orig_category":"Studi E Consulenze Legali E Notarili. Avvocati, Notai E Servizi Legali. Professionisti - Studi E Servizi Ed Associazioni Di Interesse Aziendale",
    "sg:phone":"+39 011 972 2388",
    "sg:postcode":"12030",
    "sg:province":"Cuneo",
    "wof:name":"Osella Dott. Proc. Paolo Notaio",
    "wof:placetype":"venue"
},
  "geometry": {"coordinates":[7.71803,44.845581],"type":"Point"}
}