{
  "type": "Feature",
  "properties": {
    "iso:country":"IT",
    "sg:address":"00192 Roma",
    "sg:city":"Roma",
    "sg:classifiers":[
        {
            "category":"Shopping",
            "subcategory":"Stationery & Office Supplies",
            "type":"Retail Goods"
        }
    ],
    "sg:phone":"+39 06 321 3559",
    "sg:postcode":"00192",
    "sg:province":"Roma",
    "sg:website":"http://www.centrocartaroma.it",
    "wof:name":"Centro Carta Roma Srl",
    "wof:placetype":"venue"
},
  "geometry": {"coordinates":[12.46242,41.909019],"type":"Point"}
}