{
  "type": "Feature",
  "properties": {
    "iso:country":"IT",
    "sg:address":"60015 Falconara Marittima",
    "sg:city":"Falconara Marittima",
    "sg:orig_category":"Imprese Di Costruzioni Civili Ed Industriali",
    "sg:phone":"+39 071 917 0381",
    "sg:postcode":"60015",
    "sg:province":"Ancona",
    "wof:name":"Baldassini Maurizio",
    "wof:placetype":"venue"
},
  "geometry": {"coordinates":[13.401215,43.627403],"type":"Point"}
}