{
  "type": "Feature",
  "properties": {
    "iso:country":"IT",
    "sg:address":"23100 Sondrio",
    "sg:city":"Sondrio",
    "sg:orig_category":"Servizi Ausiliari Di Analisi, Controllo E Ricerca",
    "sg:phone":"+39 0342 214312",
    "sg:postcode":"23100",
    "sg:province":"Sondrio",
    "wof:name":"Istituto Zooprofilattico",
    "wof:placetype":"venue"
},
  "geometry": {"coordinates":[9.885954,46.166054],"type":"Point"}
}