{
  "type": "Feature",
  "properties": {
    "iso:country":"IT",
    "sg:address":"Via Zavaglia 600; Pievesestina; 47020",
    "sg:classifiers":[
        {
            "category":"Banks & Credit Unions",
            "subcategory":"Bank",
            "type":"Services"
        }
    ],
    "sg:phone":"+39 0547 317431",
    "sg:postcode":"47020",
    "sg:province":"Forl\u00ec-Cesena",
    "wof:name":"Cassa Di Risparmio Do Cesena Spa",
    "wof:placetype":"venue"
},
  "geometry": {"coordinates":[12.216783,44.184391],"type":"Point"}
}