{
  "type": "Feature",
  "properties": {
    "iso:country":"IT",
    "sg:address":"317, Strada Padana Superiore 20090 Vimodrone",
    "sg:city":"Vimodrone",
    "sg:classifiers":[
        {
            "category":"Professional",
            "subcategory":"Engineering",
            "type":"Services"
        }
    ],
    "sg:phone":"+39 39022504771",
    "sg:postcode":"20090",
    "sg:province":"Milano",
    "sg:tags":[
        "machine",
        "-",
        "mechanical"
    ],
    "wof:name":"Fratelli Sirtori (s.d.f.) Di Sirtori Enrico & Fausto",
    "wof:placetype":"venue"
},
  "geometry": {"coordinates":[9.298594,45.513565],"type":"Point"}
}