{
  "type": "Feature",
  "properties": {
    "iso:country":"IT",
    "sg:address":"50100 Firenze",
    "sg:orig_category":"Forniture Per Abbigliamento E Pelletterie",
    "sg:phone":"+39 055 282292",
    "sg:province":"FI",
    "wof:name":"Bini Alfonso",
    "wof:placetype":"venue"
},
  "geometry": {"coordinates":[11.254989624,43.782371521],"type":"Point"}
}