{
  "type": "Feature",
  "properties": {
    "iso:country":"IT",
    "sg:address":"46018 Sabbioneta",
    "sg:city":"Sabbioneta",
    "sg:orig_category":"Termotecnica E Riscaldamento, Apparecchiature E Servizi",
    "sg:phone":"+39 0375 52136",
    "sg:postcode":"46018",
    "sg:province":"Mantova",
    "wof:name":"Imar Gold Line Srl",
    "wof:placetype":"venue"
},
  "geometry": {"coordinates":[10.513807,44.999569],"type":"Point"}
}