{
  "type": "Feature",
  "properties": {
    "addr:full":"25011 Ponte San Marco Ponte San Marco Brescia 25011",
    "addr:postcode":"25011;25011",
    "addr:street":"Ponte San;Ponte;Brescia",
    "iso:country":"IT",
    "sg:address":"25011 Ponte San Marco",
    "sg:city":"Ponte San Marco",
    "sg:orig_category":"Servizi Ausiliari Di Analisi, Controllo E Ricerca",
    "sg:phone":"+39 030 963 6413",
    "sg:postcode":"25011",
    "sg:province":"Brescia",
    "wof:name":"Tuv Pfalz Palatina (s.r.l.)",
    "wof:placetype":"venue"
},
  "geometry": {"coordinates":[10.393537,45.46003],"type":"Point"}
}