{
  "type": "Feature",
  "properties": {
    "iso:country":"IT",
    "sg:address":"41, Via Casenuove 60010 Castelleone Di Suasa",
    "sg:city":"Castelleone di Suasa",
    "sg:classifiers":[
        {
            "category":"Shopping",
            "type":"Retail Goods"
        }
    ],
    "sg:phone":"+39 39071966163",
    "sg:postcode":"60010",
    "sg:province":"Ancona",
    "sg:tags":[
        "finished",
        "-",
        "metallic"
    ],
    "wof:name":"F.a.m. Srl",
    "wof:placetype":"venue"
},
  "geometry": {"coordinates":[13.5187568665,43.6158561707],"type":"Point"}
}