{
  "type": "Feature",
  "properties": {
    "iso:country":"IT",
    "sg:address":"8, Via Giuseppe Verdi 39031 Brunico",
    "sg:city":"Brunico",
    "sg:classifiers":[
        {
            "category":"Shopping",
            "type":"Retail Goods"
        }
    ],
    "sg:phone":"+39 0474 571000",
    "sg:postcode":"39031",
    "sg:province":"Bolzano/Bozen",
    "sg:tags":[
        "finished",
        "-",
        "metallic"
    ],
    "wof:name":"Sch\u00d6nhuber J. S.r.l.",
    "wof:placetype":"venue"
},
  "geometry": {"coordinates":[11.9362430573,46.7988090515],"type":"Point"}
}