{
  "type": "Feature",
  "properties": {
    "iso:country":"IT",
    "sg:address":"40, Via Tosco Romagnola Est Capanne 56020 Montopoli In Val D'arno",
    "sg:city":"Capanne",
    "sg:classifiers":[
        {
            "category":"Personal",
            "subcategory":"Shoe Repair & Shine",
            "type":"Services"
        }
    ],
    "sg:phone":"+39 0571 468351",
    "sg:postcode":"56020",
    "sg:province":"Pisa",
    "sg:tags":[
        "leather"
    ],
    "wof:name":"Calzaturificio Logica Srl",
    "wof:placetype":"venue"
},
  "geometry": {"coordinates":[10.748517,43.683411],"type":"Point"}
}