{
  "type": "Feature",
  "properties": {
    "iso:country":"IT",
    "sg:address":"21048 Solbiate Arno",
    "sg:city":"Solbiate Arno",
    "sg:orig_category":"Accessori Moda D'abbigliamento. Forniture Per Abbigliamento E Pelletterie",
    "sg:phone":"+39 0331 995104",
    "sg:postcode":"21048",
    "sg:province":"Varese",
    "wof:name":"Ricamificio Belga Snc",
    "wof:placetype":"venue"
},
  "geometry": {"coordinates":[8.816597,45.720737],"type":"Point"}
}