{
  "type": "Feature",
  "properties": {
    "iso:country":"IT",
    "sg:address":"Via G. Di Vittorio 3 60035 Jesi",
    "sg:city":"Jesi",
    "sg:classifiers":[
        {
            "category":"Home & Garden",
            "subcategory":"Home Furnishings",
            "type":"Retail Goods"
        }
    ],
    "sg:phone":"+39 0731 53680",
    "sg:postcode":"60035",
    "sg:province":"Ancona",
    "sg:tags":[
        "clutch",
        "plate"
    ],
    "sg:website":"www.star-clutch.com",
    "wof:name":"Star Clutch Srl",
    "wof:placetype":"venue"
},
  "geometry": {"coordinates":[13.518757,43.615856],"type":"Point"}
}