{
  "type": "Feature",
  "properties": {
    "iso:country":"IT",
    "sg:address":"00187 Roma",
    "sg:city":"Roma",
    "sg:orig_category":"Banche E Servizi Finanziari",
    "sg:phone":"+39 06 6992 3264",
    "sg:postcode":"00187",
    "sg:province":"Roma",
    "wof:name":"Arbib Change Srl",
    "wof:placetype":"venue"
},
  "geometry": {"coordinates":[12.482821,41.900627],"type":"Point"}
}