{
  "type": "Feature",
  "properties": {
    "iso:country":"IT",
    "sg:address":"Via Del Mandorlo, 21/6 59100 Prato",
    "sg:city":"Prato",
    "sg:classifiers":[
        {
            "category":"Shopping",
            "subcategory":"Clothing, Apparel, & Fashions",
            "type":"Retail Goods"
        }
    ],
    "sg:phone":"+39 0574 550388",
    "sg:postcode":"59100",
    "sg:province":"Prato",
    "sg:tags":[
        "image",
        "clothing",
        "basic"
    ],
    "wof:name":"Doppia Corsia Di Rosi Simone & C Sas",
    "wof:placetype":"venue"
},
  "geometry": {"coordinates":[11.138021,43.858067],"type":"Point"}
}