{
  "type": "Feature",
  "properties": {
    "addr:full":"80100 Napoli NA",
    "addr:postcode":"80100",
    "iso:country":"IT",
    "sg:address":"80100 Napoli",
    "sg:orig_category":"Ospedali E Servizi Sanitari",
    "sg:phone":"+39 081 743 3022",
    "sg:province":"NA",
    "wof:name":"Casa Di Cura Colucci Srl",
    "wof:placetype":"venue"
},
  "geometry": {"coordinates":[14.234183,40.868198],"type":"Point"}
}