{
  "type": "Feature",
  "properties": {
    "addr:full":"Via Flaminia Km 57,700 01033 Civita Castellana Civita Castellana Viterbo 01033",
    "addr:housenumber":"km 57,700",
    "addr:postcode":"01033;01033",
    "addr:street":"Via Flaminia",
    "iso:country":"IT",
    "sg:address":"Via Flaminia Km 57,700 01033 Civita Castellana",
    "sg:city":"Civita Castellana",
    "sg:classifiers":[
        {
            "category":"Building & Trades",
            "subcategory":"Plumbing",
            "type":"Services"
        }
    ],
    "sg:phone":"+39 0761 540054",
    "sg:postcode":"01033",
    "sg:province":"Viterbo",
    "sg:tags":[
        "fixtures",
        "enamelled"
    ],
    "sg:website":"www.ceramicascic.it",
    "wof:name":"Scic Srl",
    "wof:placetype":"venue"
},
  "geometry": {"coordinates":[12.1048536301,42.4173812866],"type":"Point"}
}