{
  "type": "Feature",
  "properties": {
    "iso:country":"IT",
    "sg:address":"Via Martiri Della Liberta\u00b4 155 13836 Cossato",
    "sg:city":"Cossato",
    "sg:classifiers":[
        {
            "category":"Autos & Motor Vehicles",
            "subcategory":"Auto Supplies",
            "type":"Retail Goods"
        }
    ],
    "sg:phone":"+39 015 927354",
    "sg:postcode":"13836",
    "sg:province":"Biella",
    "sg:tags":[
        "electric"
    ],
    "sg:website":"www.grossosrl.it",
    "wof:name":"Grosso Srl Elettrotecnica Industriale",
    "wof:placetype":"venue"
},
  "geometry": {"coordinates":[8.189717,45.568069],"type":"Point"}
}