{
  "type": "Feature",
  "properties": {
    "addr:full":"12049 Trinita' Cuneo 12049",
    "addr:postcode":"12049;12049",
    "addr:street":"Trinita ' Cuneo",
    "iso:country":"IT",
    "sg:address":"12049 Trinita'",
    "sg:orig_category":"Servizi Vari Di Interesse Pubblico",
    "sg:phone":"+39 0172 66047",
    "sg:postcode":"12049",
    "sg:province":"Cuneo",
    "wof:name":"Succo Margherita",
    "wof:placetype":"venue"
},
  "geometry": {"coordinates":[7.793377,44.478325],"type":"Point"}
}