{
  "type": "Feature",
  "properties": {
    "iso:country":"IT",
    "sg:address":"70022 Altamura",
    "sg:city":"Altamura",
    "sg:orig_category":"Trattamenti E Finiture Superficiali Metalli",
    "sg:phone":"+39 080 310 1178",
    "sg:postcode":"70022",
    "sg:province":"Bari",
    "wof:name":"Zincatura Lorusso Srl",
    "wof:placetype":"venue"
},
  "geometry": {"coordinates":[16.527229,40.824963],"type":"Point"}
}