{
  "type": "Feature",
  "properties": {
    "addr:full":"Piazza Xx Septtembre 4; Fano; 61032 Fano Pesaro E Urbino 61032",
    "addr:housenumber":"4",
    "addr:postcode":"61032;61032",
    "addr:street":"Piazza Xx Septtembre",
    "iso:country":"IT",
    "sg:address":"Piazza Xx Septtembre 4; Fano; 61032",
    "sg:city":"Fano",
    "sg:classifiers":[
        {
            "category":"Banks & Credit Unions",
            "subcategory":"Bank",
            "type":"Services"
        }
    ],
    "sg:phone":"+39 0721 886208",
    "sg:postcode":"61032",
    "sg:province":"Pesaro E Urbino",
    "wof:name":"Cassa Di Risparmio Di Fano Spa",
    "wof:placetype":"venue"
},
  "geometry": {"coordinates":[13.012652,43.824059],"type":"Point"}
}