{
  "type": "Feature",
  "properties": {
    "iso:country":"IT",
    "sg:address":"98055 Lipari",
    "sg:city":"Lipari",
    "sg:classifiers":[
        {
            "category":"Travel",
            "subcategory":"Hotels & Motels",
            "type":"Entertainment"
        }
    ],
    "sg:phone":"+39 090 985 2002",
    "sg:postcode":"98055",
    "sg:province":"Messina",
    "sg:tags":[
        "hotels",
        "facility"
    ],
    "wof:name":"Arcipelago Spa",
    "wof:placetype":"venue"
},
  "geometry": {"coordinates":[14.959497,38.428391],"type":"Point"}
}