{
  "type": "Feature",
  "properties": {
    "iso:country":"IT",
    "sg:address":"24050 Covo",
    "sg:city":"Covo",
    "sg:orig_category":"Termotecnica E Riscaldamento, Apparecchiature E Servizi",
    "sg:phone":"+39 036 393665",
    "sg:postcode":"24050",
    "sg:province":"Bergamo",
    "wof:name":"Galliani Lorenzo",
    "wof:placetype":"venue"
},
  "geometry": {"coordinates":[9.772352,45.501259],"type":"Point"}
}