{
  "type": "Feature",
  "properties": {
    "addr:full":"74019 Palagiano Palagiano Taranto 74019",
    "addr:postcode":"74019;74019",
    "iso:country":"IT",
    "sg:address":"74019 Palagiano",
    "sg:city":"Palagiano",
    "sg:orig_category":"Servizi E Lavori Per Arredamento E Industria Del Legno. Forniture Per Congressi, Fiere E Manifestazioni. Servizi Per Aziende, Manifestazioni E Supporto Agli Scambi Commerciali",
    "sg:phone":"+39 099 888 4139",
    "sg:postcode":"74019",
    "sg:province":"Taranto",
    "wof:name":"Buon Compleanno Di Vito Favale",
    "wof:placetype":"venue"
},
  "geometry": {"coordinates":[17.018513,40.558895],"type":"Point"}
}