{
  "type": "Feature",
  "properties": {
    "iso:country":"IT",
    "sg:address":"Via Foggia, Km 1,5 71016 San Severo",
    "sg:city":"San Severo",
    "sg:classifiers":[
        {
            "category":"Bars & Pubs",
            "subcategory":"Nightclub",
            "type":"Food & Drink"
        }
    ],
    "sg:phone":"+39 0882 374954",
    "sg:postcode":"71016",
    "sg:province":"Foggia",
    "sg:tags":[
        "crystal",
        "lamp",
        "chandelier"
    ],
    "sg:website":"www.gealuce.it",
    "wof:name":"G.e.a. Luce Snc",
    "wof:placetype":"venue"
},
  "geometry": {"coordinates":[15.5447,41.462334],"type":"Point"}
}