{
  "type": "Feature",
  "properties": {
    "addr:full":"32020 Lentiai Lentiai Belluno 32020",
    "addr:postcode":"32020;32020",
    "iso:country":"IT",
    "sg:address":"32020 Lentiai",
    "sg:city":"Lentiai",
    "sg:orig_category":"Macchine, Strumenti Ed Apparecchi Per Attivita' Industriali",
    "sg:phone":"+39 0437 552197",
    "sg:postcode":"32020",
    "sg:province":"Belluno",
    "wof:name":"Millennium S.r.l.",
    "wof:placetype":"venue"
},
  "geometry": {"coordinates":[12.012713,46.039112],"type":"Point"}
}