{
  "type": "Feature",
  "properties": {
    "iso:country":"IT",
    "sg:address":"70/a, Via Laghi Di Avigliana 12022 Busca",
    "sg:city":"Busca",
    "sg:classifiers":[
        {
            "category":"Wholesale",
            "subcategory":"Machinery & Supplies",
            "type":"Manufacturing & Wholesale Goods"
        }
    ],
    "sg:phone":"+39 0171 946756",
    "sg:postcode":"12022",
    "sg:province":"Cuneo",
    "sg:tags":[
        "-",
        "agriculture",
        "equipment"
    ],
    "wof:name":"Cta Milk S.r.l.",
    "wof:placetype":"venue"
},
  "geometry": {"coordinates":[7.501999,44.485172],"type":"Point"}
}