{
  "type": "Feature",
  "properties": {
    "addr:full":"20131 Milano Milano Milano 20131",
    "addr:postcode":"20131;20131",
    "iso:country":"IT",
    "sg:address":"20131 Milano",
    "sg:city":"Milano",
    "sg:orig_category":"Pubblicita', Marketing E Comunicazione",
    "sg:phone":"+39 02 2952 0671",
    "sg:postcode":"20131",
    "sg:province":"Milano",
    "sg:website":"http://www.arianiepartners.com",
    "wof:name":"Ariani E Partners Sas",
    "wof:placetype":"venue"
},
  "geometry": {"coordinates":[9.2205457687,45.4819641113],"type":"Point"}
}