{
  "type": "Feature",
  "properties": {
    "iso:country":"IT",
    "sg:address":"102, Via Zuretti Gianfranco 20125 Milano",
    "sg:city":"Milano",
    "sg:classifiers":[
        {
            "category":"Manufacturing",
            "subcategory":"Motor Vehicles & Parts",
            "type":"Manufacturing & Wholesale Goods"
        }
    ],
    "sg:phone":"+39 02 6698 1669",
    "sg:postcode":"20125",
    "sg:province":"Milano",
    "sg:tags":[
        "engine"
    ],
    "wof:name":"Bianchi Tas (s.p.a.)",
    "wof:placetype":"venue"
},
  "geometry": {"coordinates":[9.207645,45.493027],"type":"Point"}
}