{
  "type": "Feature",
  "properties": {
    "iso:country":"IT",
    "sg:address":"98100 Messina",
    "sg:orig_category":"Arredo Cucina Ed Elettrodomestici. Frigotecnica, Apparecchiature E Servizi. Elettrodomestici",
    "sg:phone":"+39 090 621979",
    "sg:province":"ME",
    "wof:name":"Parisi Fratelli",
    "wof:placetype":"venue"
},
  "geometry": {"coordinates":[15.534369,38.157619],"type":"Point"}
}