{
  "type": "Feature",
  "properties": {
    "addr:full":"1, Via Anelli Luigi 20122 Milano Milano Milano 20122",
    "addr:postcode":"20122;20122",
    "addr:street":"Via Anelli Luigi",
    "iso:country":"IT",
    "sg:address":"1, Via Anelli Luigi 20122 Milano",
    "sg:city":"Milano",
    "sg:classifiers":[
        {
            "category":"Shopping",
            "subcategory":"Clothing, Apparel, & Fashions",
            "type":"Retail Goods"
        }
    ],
    "sg:phone":"+39 02 5830 1444",
    "sg:postcode":"20122",
    "sg:province":"Milano",
    "sg:tags":[
        "clothing",
        "accessory"
    ],
    "wof:name":"Carnaval De Venise (s.a.s.)",
    "wof:placetype":"venue"
},
  "geometry": {"coordinates":[9.193,45.454056],"type":"Point"}
}