{
  "type": "Feature",
  "properties": {
    "iso:country":"IT",
    "sg:address":"36063 Marostica",
    "sg:city":"Marostica",
    "sg:orig_category":"Carburanti - Produzione E Commercio",
    "sg:phone":"+39 0424 75036",
    "sg:postcode":"36063",
    "sg:province":"Vicenza",
    "wof:name":"Scanagatta Carburanti Srl",
    "wof:placetype":"venue"
},
  "geometry": {"coordinates":[11.654541,45.73642],"type":"Point"}
}