{
  "type": "Feature",
  "properties": {
    "addr:full":"3/d, Via Tevere 24052 Azzano San Paolo Azzano San Paolo Bergamo 24052",
    "addr:housenumber":"3 / d",
    "addr:postcode":"24052;24052",
    "addr:street":"Via Tevere",
    "iso:country":"IT",
    "sg:address":"3/d, Via Tevere 24052 Azzano San Paolo",
    "sg:city":"Azzano San Paolo",
    "sg:classifiers":[
        {
            "category":"Shopping",
            "subcategory":"Crafts & Fabrics",
            "type":"Retail Goods"
        }
    ],
    "sg:phone":"+39 39035531574",
    "sg:postcode":"24052",
    "sg:province":"Bergamo",
    "wof:name":"Mery Dami Ricami (s.n.c.)",
    "wof:placetype":"venue"
},
  "geometry": {"coordinates":[9.6772127151,45.6590538025],"type":"Point"}
}