{
  "type": "Feature",
  "properties": {
    "iso:country":"IT",
    "sg:address":"Localit\u00e0 Novella Terza 26862 Guardamiglio",
    "sg:city":"Guardamiglio",
    "sg:orig_category":"Production Plant Cleaning Services",
    "sg:phone":"+39 0377 451124",
    "sg:postcode":"26862",
    "sg:province":"Lodi",
    "sg:website":"www.nilfisk-advance.it",
    "wof:name":"Nilfisk-advance Italia Spa",
    "wof:placetype":"venue"
},
  "geometry": {"coordinates":[9.4978504181,45.312877655],"type":"Point"}
}