{
  "type": "Feature",
  "properties": {
    "addr:full":"42042 Fabbrico Reggio Nell'Emilia 42042",
    "addr:postcode":"42042;42042",
    "iso:country":"IT",
    "sg:address":"42042 Fabbrico",
    "sg:classifiers":[
        {
            "category":"Personal",
            "subcategory":"Nail Salon",
            "type":"Services"
        }
    ],
    "sg:phone":"+39 0522 665477",
    "sg:postcode":"42042",
    "sg:province":"Reggio Nell'Emilia",
    "sg:tags":[
        "scale"
    ],
    "wof:name":"Piramide Di Zini Marco & C. Snc",
    "wof:placetype":"venue"
},
  "geometry": {"coordinates":[10.623377,44.707977],"type":"Point"}
}