{
  "type": "Feature",
  "properties": {
    "iso:country":"IT",
    "sg:address":"00181 Roma",
    "sg:city":"Roma",
    "sg:orig_category":"Articoli Medico-sanitari Ed Ortopedici",
    "sg:phone":"+39 06 701 1961",
    "sg:postcode":"00181",
    "sg:province":"Roma",
    "wof:name":"Eidos Srl",
    "wof:placetype":"venue"
},
  "geometry": {"coordinates":[12.578022,41.80909],"type":"Point"}
}