{
  "type": "Feature",
  "properties": {
    "iso:country":"IT",
    "sg:address":"63030 Acquaviva Picena",
    "sg:city":"Acquaviva Picena",
    "sg:orig_category":"Trasporti E Spedizioni Merci",
    "sg:phone":"+39 0735 584267",
    "sg:postcode":"63030",
    "sg:province":"Ascoli Piceno",
    "wof:name":"Transervice Srl",
    "wof:placetype":"venue"
},
  "geometry": {"coordinates":[13.839707,42.954865],"type":"Point"}
}