{
  "type": "Feature",
  "properties": {
    "addr:full":"35020 Correzzola Correzzola Padova 35020",
    "addr:postcode":"35020;35020",
    "iso:country":"IT",
    "sg:address":"35020 Correzzola",
    "sg:city":"Correzzola",
    "sg:orig_category":"Macchine, Impianti Ed Attrezzature Per Industria Alimentare E Bevande. Forniture Alle Strutture Ricettive. Macchine E Impianti Per Attivita' Commerciali Ed Artigianali",
    "sg:phone":"+39 049 585 3290",
    "sg:postcode":"35020",
    "sg:province":"Padova",
    "wof:name":"R.g. Inox Di Rebecca Giovanni E Cominato Diego S.n.c.",
    "wof:placetype":"venue"
},
  "geometry": {"coordinates":[12.037177,45.195793],"type":"Point"}
}