{
  "type": "Feature",
  "properties": {
    "addr:full":"17, Via Maso 36035 Marano Vicentino Marano Vicentino Vicenza 36035",
    "addr:postcode":"36035;36035",
    "addr:street":"Via Maso;Vicentino",
    "iso:country":"IT",
    "sg:address":"17, Via Maso 36035 Marano Vicentino",
    "sg:city":"Marano Vicentino",
    "sg:classifiers":[
        {
            "category":"Manufacturing",
            "subcategory":"Food",
            "type":"Manufacturing & Wholesale Goods"
        }
    ],
    "sg:phone":"+39 0445 621465",
    "sg:postcode":"36035",
    "sg:province":"Vicenza",
    "sg:tags":[
        "equipment",
        "processing",
        "-",
        "machinery"
    ],
    "wof:name":"M.b.m. Borriero (s.r.l.)",
    "wof:placetype":"venue"
},
  "geometry": {"coordinates":[11.4343414307,45.700378418],"type":"Point"}
}