{
  "type": "Feature",
  "properties": {
    "addr:full":"Frazione Cire' 31/a 38057 Pergine Valsugana Pergine Valsugana Trento 38057",
    "addr:housenumber":"31 / a",
    "addr:postcode":"38057;38057",
    "addr:street":"Frazione Cire '",
    "iso:country":"IT",
    "sg:address":"Frazione Cire' 31/a 38057 Pergine Valsugana",
    "sg:city":"Pergine Valsugana",
    "sg:classifiers":[
        {
            "category":"Utilities",
            "subcategory":"Sewage",
            "type":"Services"
        }
    ],
    "sg:phone":"+39 0461 530143",
    "sg:postcode":"38057",
    "sg:province":"Trento",
    "sg:tags":[
        "plant",
        "purification"
    ],
    "wof:name":"Nordeco Srl",
    "wof:placetype":"venue"
},
  "geometry": {"coordinates":[11.217103,46.084671],"type":"Point"}
}