{
  "type": "Feature",
  "properties": {
    "addr:full":"Via Giuriolo 1 36071 Arzignano Arzignano Vicenza 36071",
    "addr:housenumber":"1",
    "addr:postcode":"36071;36071",
    "addr:street":"Via Giuriolo",
    "iso:country":"IT",
    "sg:address":"Via Giuriolo 1 36071 Arzignano",
    "sg:city":"Arzignano",
    "sg:classifiers":[
        {
            "category":"Home & Garden",
            "subcategory":"Carpets & Floor Coverings",
            "type":"Retail Goods"
        }
    ],
    "sg:phone":"+39 0444 673291",
    "sg:postcode":"36071",
    "sg:province":"Vicenza",
    "sg:tags":[
        "animal",
        "skin"
    ],
    "sg:website":"www.primisleather.com",
    "wof:name":"Primis Leather S.r.l.",
    "wof:placetype":"venue"
},
  "geometry": {"coordinates":[11.330296,45.520813],"type":"Point"}
}