{
  "type": "Feature",
  "properties": {
    "addr:full":"Via Per Curnasco 38 24127 Bergamo Bergamo Bergamo 24127",
    "addr:housenumber":"38",
    "addr:postcode":"24127;24127",
    "addr:street":"Via Per Curnasco",
    "iso:country":"IT",
    "sg:address":"Via Per Curnasco 38 24127 Bergamo",
    "sg:city":"Bergamo",
    "sg:classifiers":[
        {
            "category":"Banks & Credit Unions",
            "subcategory":"Investment Brokerage",
            "type":"Services"
        }
    ],
    "sg:phone":"+39 035 260157",
    "sg:postcode":"24127",
    "sg:province":"Bergamo",
    "sg:tags":[
        "project",
        "work"
    ],
    "wof:name":"Tecnoprogetti - Bergamo Snc",
    "wof:placetype":"venue"
},
  "geometry": {"coordinates":[9.6448020935,45.6777839661],"type":"Point"}
}