{
  "type": "Feature",
  "properties": {
    "iso:country":"IT",
    "sg:address":"14, Via Turati 40010 Sala Bolognese",
    "sg:city":"Sala Bolognese",
    "sg:classifiers":[
        {
            "category":"Shopping",
            "type":"Retail Goods"
        }
    ],
    "sg:phone":"+39 051 681 4575",
    "sg:postcode":"40010",
    "sg:province":"Bologna",
    "sg:tags":[
        "finished",
        "-",
        "metallic"
    ],
    "wof:name":"Comest (s.r.l.)",
    "wof:placetype":"venue"
},
  "geometry": {"coordinates":[11.2680540085,44.5639724731],"type":"Point"}
}