{
  "type": "Feature",
  "properties": {
    "iso:country":"IT",
    "sg:address":"1555, Via Emilia Per Cesena 47034 Forlimpopoli",
    "sg:city":"Forlimpopoli",
    "sg:classifiers":[
        {
            "category":"Bars & Pubs",
            "subcategory":"Nightclub",
            "type":"Food & Drink"
        }
    ],
    "sg:phone":"+39 0543 748058",
    "sg:postcode":"47034",
    "sg:province":"Forl\u00ec-Cesena",
    "sg:tags":[
        "cake",
        "bread"
    ],
    "wof:name":"Oropan S.r.l.",
    "wof:placetype":"venue"
},
  "geometry": {"coordinates":[12.139989,44.181221],"type":"Point"}
}