{
  "type": "Feature",
  "properties": {
    "iso:country":"IT",
    "sg:address":"Strada St. 189 92025 Casteltermini",
    "sg:city":"Casteltermini",
    "sg:classifiers":[
        {
            "category":"Manufacturing",
            "subcategory":"Metals",
            "type":"Manufacturing & Wholesale Goods"
        }
    ],
    "sg:phone":"+39 0922 913245",
    "sg:postcode":"92025",
    "sg:province":"Agrigento",
    "sg:tags":[
        "metallurgy",
        "metalworking"
    ],
    "wof:name":"Predil Srl",
    "wof:placetype":"venue"
},
  "geometry": {"coordinates":[13.5769557953,37.3111877441],"type":"Point"}
}