{
  "type": "Feature",
  "properties": {
    "addr:full":"50, Via S. Lucia 80132 Napoli Napoli Napoli 80132",
    "addr:postcode":"80132;80132",
    "addr:street":"Via S. Lucia",
    "iso:country":"IT",
    "sg:address":"50, Via S. Lucia 80132 Napoli",
    "sg:city":"Napoli",
    "sg:classifiers":[
        {
            "category":"Marine",
            "type":"Transportation"
        }
    ],
    "sg:phone":"+39 081 764 7075",
    "sg:postcode":"80132",
    "sg:province":"Napoli",
    "sg:tags":[
        "transport",
        "sea"
    ],
    "wof:name":"Holme & Co. (s.r.l.)",
    "wof:placetype":"venue"
},
  "geometry": {"coordinates":[14.276432,40.8745],"type":"Point"}
}