{
  "type": "Feature",
  "properties": {
    "iso:country":"IT",
    "sg:address":"18038 Sanremo",
    "sg:orig_category":"Accessori Moda D'abbigliamento. Shopping",
    "sg:phone":"+39 0184 509025",
    "sg:postcode":"18038",
    "sg:province":"Imperia",
    "wof:name":"Maxx Di Marangon Fabio & C. Snc",
    "wof:placetype":"venue"
},
  "geometry": {"coordinates":[8.103015,43.922707],"type":"Point"}
}