{
  "type": "Feature",
  "properties": {
    "addr:full":"13100 Vercelli Vercelli Vercelli 13100",
    "addr:postcode":"13100;13100",
    "iso:country":"IT",
    "sg:address":"13100 Vercelli",
    "sg:city":"Vercelli",
    "sg:orig_category":"Ricerca, Selezione E Formazione Del Personale. Pubblica Amministrazione",
    "sg:phone":"+39 0161 54161",
    "sg:postcode":"13100",
    "sg:province":"Vercelli",
    "wof:name":"Comune Di Vercelli",
    "wof:placetype":"venue"
},
  "geometry": {"coordinates":[8.427577,45.33009],"type":"Point"}
}