{
  "type": "Feature",
  "properties": {
    "addr:full":"2, Via D'acquisto Salvo 20059 Vimercate Vimercate Milano 20059",
    "addr:postcode":"20059;20059",
    "addr:street":"Via D'Acquisto Salvo",
    "iso:country":"IT",
    "sg:address":"2, Via D'acquisto Salvo 20059 Vimercate",
    "sg:city":"Vimercate",
    "sg:classifiers":[
        {
            "category":"Manufacturing",
            "subcategory":"Paper Products",
            "type":"Manufacturing & Wholesale Goods"
        }
    ],
    "sg:phone":"+39 039 685 4545",
    "sg:postcode":"20059",
    "sg:province":"Milano",
    "sg:tags":[
        "cardboard"
    ],
    "wof:name":"Sacchettificio Monzese Srl",
    "wof:placetype":"venue"
},
  "geometry": {"coordinates":[9.1881408691,45.4636878967],"type":"Point"}
}