{
  "type": "Feature",
  "properties": {
    "iso:country":"IT",
    "sg:address":"20139 Milano",
    "sg:city":"Milano",
    "sg:orig_category":"Servizi E Lavori Per Agricoltura E Zootecnia. Animali Domestici",
    "sg:phone":"+39 02 539 8924",
    "sg:postcode":"20139",
    "sg:province":"Milano",
    "wof:name":"Gallotti Alessandro",
    "wof:placetype":"venue"
},
  "geometry": {"coordinates":[9.268991,45.489494],"type":"Point"}
}