{
  "type": "Feature",
  "properties": {
    "addr:full":"Via Pietro Micca 22; Torino",
    "addr:housenumber":"22",
    "addr:street":"Via Pietro Micca",
    "iso:country":"IT",
    "sg:address":"Via Pietro Micca 22; Torino",
    "sg:classifiers":[
        {
            "category":"Banks & Credit Unions",
            "subcategory":"Bank",
            "type":"Services"
        }
    ],
    "sg:phone":"+39 011 561 3685",
    "wof:name":"Banca Mercantile Italiana",
    "wof:placetype":"venue"
},
  "geometry": {"coordinates":[7.678555,45.070328],"type":"Point"}
}