{
  "type": "Feature",
  "properties": {
    "iso:country":"IT",
    "sg:address":"67, Via Nazionale 61022 Colbordolo",
    "sg:city":"Colbordolo",
    "sg:classifiers":[
        {
            "category":"Manufacturing",
            "subcategory":"Rubber & Plastics",
            "type":"Manufacturing & Wholesale Goods"
        }
    ],
    "sg:phone":"+39 0721 497293",
    "sg:postcode":"61022",
    "sg:province":"Pesaro E Urbino",
    "wof:name":"Camillini Resine (s.r.l.)",
    "wof:placetype":"venue"
},
  "geometry": {"coordinates":[12.7498655319,43.844871521],"type":"Point"}
}