{
  "type": "Feature",
  "properties": {
    "addr:full":"20030 Seveso Seveso Milano 20030",
    "addr:postcode":"20030;20030",
    "iso:country":"IT",
    "sg:address":"20030 Seveso",
    "sg:city":"Seveso",
    "sg:orig_category":"Decoratori",
    "sg:phone":"+39 036 255 1955",
    "sg:postcode":"20030",
    "sg:province":"Milano",
    "wof:name":"Decorlac System Snc Di Busnelli",
    "wof:placetype":"venue"
},
  "geometry": {"coordinates":[9.184443,45.465187],"type":"Point"}
}