{
  "type": "Feature",
  "properties": {
    "addr:full":"195, Corso Moncalieri 10133 Torino Torino Torino 10133",
    "addr:postcode":"10133;10133",
    "addr:street":"Corso Moncalieri",
    "iso:country":"IT",
    "sg:address":"195, Corso Moncalieri 10133 Torino",
    "sg:city":"Torino",
    "sg:classifiers":[
        {
            "category":"Professional",
            "subcategory":"Engineering",
            "type":"Services"
        }
    ],
    "sg:phone":"+39 011 661 3222",
    "sg:postcode":"10133",
    "sg:province":"Torino",
    "sg:tags":[
        "machine",
        "-",
        "mechanical"
    ],
    "wof:name":"Cappelluzzo & Ienna (s.p.a.)",
    "wof:placetype":"venue"
},
  "geometry": {"coordinates":[7.694828,45.058914],"type":"Point"}
}