{
  "type": "Feature",
  "properties": {
    "addr:full":"Corso Del Popolo 4; Padova; 35131 Padova Padova 35131",
    "addr:housenumber":"4",
    "addr:postcode":"35131;35131",
    "addr:street":"Corso Del Popolo",
    "iso:country":"IT",
    "sg:address":"Corso Del Popolo 4; Padova; 35131",
    "sg:city":"Padova",
    "sg:classifiers":[
        {
            "category":"Banks & Credit Unions",
            "subcategory":"Bank",
            "type":"Services"
        }
    ],
    "sg:phone":"+39 049 875 5992",
    "sg:postcode":"35131",
    "sg:province":"Padova",
    "wof:name":"Banca Popolare Di Verona",
    "wof:placetype":"venue"
},
  "geometry": {"coordinates":[11.879211,45.415264],"type":"Point"}
}