{
  "type": "Feature",
  "properties": {
    "iso:country":"IT",
    "sg:address":"13900 Biella",
    "sg:city":"Biella",
    "sg:orig_category":"Termotecnica E Riscaldamento, Apparecchiature E Servizi",
    "sg:phone":"+39 015 405566",
    "sg:postcode":"13900",
    "sg:province":"Biella",
    "wof:name":"Riello S.p.a.",
    "wof:placetype":"venue"
},
  "geometry": {"coordinates":[8.036505,45.57856],"type":"Point"}
}