{
  "type": "Feature",
  "properties": {
    "iso:country":"IT",
    "sg:address":"16161 Genova",
    "sg:city":"Genova",
    "sg:orig_category":"Articoli Per Imballaggio E Confezionamento",
    "sg:phone":"+39 010 741 1486",
    "sg:postcode":"16161",
    "sg:province":"Genova",
    "wof:name":"Ricupoil Srl",
    "wof:placetype":"venue"
},
  "geometry": {"coordinates":[8.883151,44.446373],"type":"Point"}
}