{
  "type": "Feature",
  "properties": {
    "addr:full":"Via C. Colombo 2 23844 Sirone Sirone Lecco 23844",
    "addr:housenumber":"2",
    "addr:postcode":"23844;23844",
    "addr:street":"Via C. Colombo",
    "iso:country":"IT",
    "sg:address":"Via C. Colombo 2 23844 Sirone",
    "sg:city":"Sirone",
    "sg:classifiers":[
        {
            "category":"Manufacturing",
            "subcategory":"Building Materials",
            "type":"Manufacturing & Wholesale Goods"
        }
    ],
    "sg:phone":"+39 031 850543",
    "sg:postcode":"23844",
    "sg:province":"Lecco",
    "sg:tags":[
        "netting",
        "plastic"
    ],
    "wof:name":"Siderplast Srl",
    "wof:placetype":"venue"
},
  "geometry": {"coordinates":[9.3900709152,45.8529815674],"type":"Point"}
}