{
  "type": "Feature",
  "properties": {
    "iso:country":"IT",
    "sg:address":"18, Via Valsugana 35010 Curtarolo",
    "sg:city":"Curtarolo",
    "sg:classifiers":[
        {
            "category":"Shopping",
            "type":"Retail Goods"
        }
    ],
    "sg:phone":"+39 39049557139",
    "sg:postcode":"35010",
    "sg:province":"Padova",
    "sg:tags":[
        "finished",
        "-",
        "metallic"
    ],
    "wof:name":"Tierre (s.r.l.)",
    "wof:placetype":"venue"
},
  "geometry": {"coordinates":[11.8311061859,45.5256500244],"type":"Point"}
}