{
  "type": "Feature",
  "properties": {
    "iso:country":"IT",
    "sg:address":"13, Via Podere Vigna 20019 Settimo Milanese",
    "sg:city":"Settimo Milanese",
    "sg:classifiers":[
        {
            "category":"Professional",
            "subcategory":"Engineering",
            "type":"Services"
        }
    ],
    "sg:phone":"+39 39023355961",
    "sg:postcode":"20019",
    "sg:province":"Milano",
    "sg:tags":[
        "machine",
        "-",
        "mechanical"
    ],
    "wof:name":"Redis Srl",
    "wof:placetype":"venue"
},
  "geometry": {"coordinates":[9.049624,45.484085],"type":"Point"}
}