{
  "type": "Feature",
  "properties": {
    "iso:country":"IT",
    "sg:address":"1, Via Dell' Industria 36065 Mussolente",
    "sg:city":"Mussolente",
    "sg:classifiers":[
        {
            "category":"Professional",
            "subcategory":"Engineering",
            "type":"Services"
        }
    ],
    "sg:phone":"+39 0424 577565",
    "sg:postcode":"36065",
    "sg:province":"Vicenza",
    "sg:tags":[
        "machine",
        "-",
        "mechanical"
    ],
    "wof:name":"Ciemmeo (s.r.l.)",
    "wof:placetype":"venue"
},
  "geometry": {"coordinates":[11.807279,45.767242],"type":"Point"}
}