{
  "type": "Feature",
  "properties": {
    "addr:full":"25045 Castegnato Castegnato Brescia 25045",
    "addr:postcode":"25045;25045",
    "iso:country":"IT",
    "sg:address":"25045 Castegnato",
    "sg:city":"Castegnato",
    "sg:orig_category":"Motori Ed Organi Di Trasmissione. Ricambi E Componenti Dei Mezzi Di Trasporto",
    "sg:phone":"+39 030 320072",
    "sg:postcode":"25045",
    "sg:province":"Brescia",
    "wof:name":"Omar Ricambi Di Pedrini Vanda E C. (s.n.c.)",
    "wof:placetype":"venue"
},
  "geometry": {"coordinates":[10.1141986847,45.5518989563],"type":"Point"}
}