{
  "type": "Feature",
  "properties": {
    "addr:full":"80055 Portici Portici Napoli 80055",
    "addr:postcode":"80055;80055",
    "iso:country":"IT",
    "sg:address":"80055 Portici",
    "sg:city":"Portici",
    "sg:orig_category":"Gioielleria, Oreficeria E Argenteria. Shopping",
    "sg:phone":"+39 081 775 2900",
    "sg:postcode":"80055",
    "sg:province":"Napoli",
    "wof:name":"Donadio Matteo E C. (s.n.c.)",
    "wof:placetype":"venue"
},
  "geometry": {"coordinates":[14.357695,40.818653],"type":"Point"}
}