{
  "type": "Feature",
  "properties": {
    "iso:country":"IT",
    "sg:address":"70058 Spinazzola",
    "sg:city":"Spinazzola",
    "sg:orig_category":"Abbigliamento Esterno, Maglierie E Pelliccerie. Shopping",
    "sg:phone":"+39 0883 681402",
    "sg:postcode":"70058",
    "sg:province":"Bari",
    "wof:name":"Confezioni Episcopo",
    "wof:placetype":"venue"
},
  "geometry": {"coordinates":[16.872383,41.121941],"type":"Point"}
}