{
  "type": "Feature",
  "properties": {
    "addr:full":"00196 Roma Roma Roma 00196",
    "addr:postcode":"00196;00196",
    "iso:country":"IT",
    "sg:address":"00196 Roma",
    "sg:city":"Roma",
    "sg:orig_category":"Servizi Culturali E Per Lo Spettacolo",
    "sg:phone":"+39 06 323 2912",
    "sg:postcode":"00196",
    "sg:province":"Roma",
    "wof:name":"Lodolo Film Sas",
    "wof:placetype":"venue"
},
  "geometry": {"coordinates":[12.46148,41.928867],"type":"Point"}
}