{
  "type": "Feature",
  "properties": {
    "addr:full":"16121 Genova Genova Genova 16121",
    "addr:postcode":"16121;16121",
    "iso:country":"IT",
    "sg:address":"16121 Genova",
    "sg:city":"Genova",
    "sg:orig_category":"Agenzie Viaggi E Turismo",
    "sg:phone":"+39 010 589331",
    "sg:postcode":"16121",
    "sg:province":"Genova",
    "sg:website":"http://www.grimaldi.it",
    "wof:name":"Grandi Navi Veloci",
    "wof:placetype":"venue"
},
  "geometry": {"coordinates":[8.936028,44.40435],"type":"Point"}
}