{
  "type": "Feature",
  "properties": {
    "iso:country":"IT",
    "sg:address":"5, Via Carmagnola 12050 Guarene",
    "sg:city":"Guarene",
    "sg:classifiers":[
        {
            "category":"Bars & Pubs",
            "subcategory":"Nightclub",
            "type":"Food & Drink"
        }
    ],
    "sg:phone":"+39 0173 286844",
    "sg:postcode":"12050",
    "sg:province":"Cuneo",
    "sg:tags":[
        "cake",
        "bread"
    ],
    "wof:name":"Grissinificio Europa (s.n.c.)",
    "wof:placetype":"venue"
},
  "geometry": {"coordinates":[8.006781,44.728565],"type":"Point"}
}