{
  "type": "Feature",
  "properties": {
    "iso:country":"IT",
    "sg:address":"20010 Pregnana Milanese",
    "sg:city":"Pregnana Milanese",
    "sg:orig_category":"Serramenti Ed Infissi. Arte Ed Artigianato Artistico. Shopping",
    "sg:phone":"+39 02 9359 2240",
    "sg:postcode":"20010",
    "sg:province":"Milano",
    "sg:website":"http://www.paginegialle.it/ilfabbrodicuccof",
    "wof:name":"Il Fabbro Di Cucco Felicia",
    "wof:placetype":"venue"
},
  "geometry": {"coordinates":[8.997761,45.507957],"type":"Point"}
}