{
  "type": "Feature",
  "properties": {
    "addr:full":"57027 S.vincenzo Livorno 57027",
    "addr:postcode":"57027;57027",
    "addr:street":"S.Vincenzo",
    "iso:country":"IT",
    "sg:address":"57027 S.vincenzo",
    "sg:orig_category":"Carni Fresche E Congelate - Lavorazione E Commercio",
    "sg:phone":"+39 0565 705151",
    "sg:postcode":"57027",
    "sg:province":"Livorno",
    "wof:name":"Tirrenia Carni Srl",
    "wof:placetype":"venue"
},
  "geometry": {"coordinates":[10.308011055,43.5518760681],"type":"Point"}
}