{
  "type": "Feature",
  "properties": {
    "addr:full":"44029 Comacchio Comacchio Ferrara 44029",
    "addr:postcode":"44029;44029",
    "iso:country":"IT",
    "sg:address":"44029 Comacchio",
    "sg:city":"Comacchio",
    "sg:orig_category":"Campeggi, Ostelli E Villaggi Turistici",
    "sg:phone":"+39 0533 327431",
    "sg:postcode":"44029",
    "sg:province":"Ferrara",
    "sg:website":"http://www.campingdicharme.it",
    "wof:name":"Camping Spiaggia E Mare",
    "wof:placetype":"venue"
},
  "geometry": {"coordinates":[12.240796,44.680019],"type":"Point"}
}