{
  "type": "Feature",
  "properties": {
    "iso:country":"IT",
    "sg:address":"96100 Siracusa",
    "sg:city":"Siracusa",
    "sg:orig_category":"Servizi Ausiliari Di Analisi, Controllo E Ricerca. Acqua, Luce, Gas E Societa' Di Esercizio Pubblico",
    "sg:phone":"+39 0931 412225",
    "sg:postcode":"96100",
    "sg:province":"Siracusa",
    "wof:name":"Osservatorio Provinciale",
    "wof:placetype":"venue"
},
  "geometry": {"coordinates":[15.212498,37.092697],"type":"Point"}
}