{
  "type": "Feature",
  "properties": {
    "addr:full":"Via Roma, 18 - Osmate Lentate 21018 Sesto Calende Osmate Varese 21018",
    "addr:housenumber":"18",
    "addr:postcode":"21018;21018",
    "addr:street":"Via Roma;Lentate",
    "iso:country":"IT",
    "sg:address":"Via Roma, 18 - Osmate Lentate 21018 Sesto Calende",
    "sg:city":"Osmate",
    "sg:classifiers":[
        {
            "category":"Building & Trades",
            "subcategory":"Construction",
            "type":"Services"
        }
    ],
    "sg:phone":"+39 0331 953116",
    "sg:postcode":"21018",
    "sg:province":"Varese",
    "sg:tags":[
        "industrial",
        "timber"
    ],
    "wof:name":"Fratelli Foglia E C. S.a.s.",
    "wof:placetype":"venue"
},
  "geometry": {"coordinates":[8.826385,45.817604],"type":"Point"}
}