{
  "type": "Feature",
  "properties": {
    "iso:country":"IT",
    "sg:address":"26841 Casalpusterlengo",
    "sg:city":"Casalpusterlengo",
    "sg:orig_category":"Macchine Ed Impianti Per Edilizia E Lavori Pubblici",
    "sg:phone":"+39 0377 919159",
    "sg:postcode":"26841",
    "sg:province":"Lodi",
    "wof:name":"Pft Systems Vertriebs Gmbh",
    "wof:placetype":"venue"
},
  "geometry": {"coordinates":[9.548949,45.188808],"type":"Point"}
}