{
  "type": "Feature",
  "properties": {
    "addr:full":"13900 Biella Biella Biella 13900",
    "addr:postcode":"13900;13900",
    "iso:country":"IT",
    "sg:address":"13900 Biella",
    "sg:city":"Biella",
    "sg:orig_category":"Filati E Materie Prime Tessili",
    "sg:phone":"+39 015 849 7528",
    "sg:postcode":"13900",
    "sg:province":"Biella",
    "wof:name":"Biella Yarn Project By Sudwolle Srl",
    "wof:placetype":"venue"
},
  "geometry": {"coordinates":[8.0528888702,45.5584526062],"type":"Point"}
}