{
  "type": "Feature",
  "properties": {
    "addr:full":"28, Via Manzoni Alessandro 36027 Rosa' Vicenza 36027",
    "addr:postcode":"36027;36027",
    "addr:street":"Via Manzoni Alessandro;Rosa ' Vicenza",
    "iso:country":"IT",
    "sg:address":"28, Via Manzoni Alessandro 36027 Rosa'",
    "sg:classifiers":[
        {
            "category":"Manufacturing",
            "subcategory":"Paper Products",
            "type":"Manufacturing & Wholesale Goods"
        }
    ],
    "sg:phone":"+39 0424 581786",
    "sg:postcode":"36027",
    "sg:province":"Vicenza",
    "sg:tags":[
        "cardboard"
    ],
    "wof:name":"Luber's (s.r.l.)",
    "wof:placetype":"venue"
},
  "geometry": {"coordinates":[11.540307045,45.5459060669],"type":"Point"}
}