{
  "type": "Feature",
  "properties": {
    "iso:country":"IT",
    "sg:address":"21019 Somma Lombardo",
    "sg:city":"Somma Lombardo",
    "sg:orig_category":"Informatica - Consulenza E Servizi. Automazione E Macchine Per Ufficio. Servizi Ausiliari Di Analisi, Controllo E Ricerca. Servizi Per Aziende, Manifestazioni E Supporto Agli Scambi Commerciali",
    "sg:phone":"+39 0331 250220",
    "sg:postcode":"21019",
    "sg:province":"Varese",
    "sg:website":"http://www.jokersrl.it",
    "wof:name":"Joker Srl",
    "wof:placetype":"venue"
},
  "geometry": {"coordinates":[8.704273,45.676941],"type":"Point"}
}