{
  "type": "Feature",
  "properties": {
    "iso:country":"IT",
    "sg:address":"Centro Commerciale Settore A 16 33170 Pordenone",
    "sg:city":"Pordenone",
    "sg:orig_category":"Ladies' Shoes",
    "sg:phone":"+39 0434 572882",
    "sg:postcode":"33170",
    "sg:province":"Pordenone",
    "wof:name":"Emmedi S.r.l.",
    "wof:placetype":"venue"
},
  "geometry": {"coordinates":[12.655044,45.96265],"type":"Point"}
}