{
  "type": "Feature",
  "properties": {
    "addr:full":"Piazza Principe Di; S. Oreste",
    "addr:street":"Piazza Principe Di S. Oreste",
    "iso:country":"IT",
    "sg:address":"Piazza Principe Di; S. Oreste",
    "sg:classifiers":[
        {
            "category":"Banks & Credit Unions",
            "subcategory":"Bank",
            "type":"Services"
        }
    ],
    "sg:phone":"+39 0761 579771",
    "wof:name":"Banca Di Roma",
    "wof:placetype":"venue"
},
  "geometry": {"coordinates":[12.520794,42.234062],"type":"Point"}
}