{
  "type": "Feature",
  "properties": {
    "addr:full":"18100 Imperia Imperia Imperia 18100",
    "addr:postcode":"18100;18100",
    "iso:country":"IT",
    "sg:address":"18100 Imperia",
    "sg:city":"Imperia",
    "sg:orig_category":"Climatizzazione E Condizionamento, Apparecchiature E Servizi",
    "sg:phone":"+39 0183 710767",
    "sg:postcode":"18100",
    "sg:province":"Imperia",
    "wof:name":"Decolux & C. Snc",
    "wof:placetype":"venue"
},
  "geometry": {"coordinates":[8.031564,43.887894],"type":"Point"}
}