{
  "type": "Feature",
  "properties": {
    "iso:country":"IT",
    "sg:address":"70, Via Nazario Sauro 42021 Bibbiano",
    "sg:classifiers":[
        {
            "category":"Professional",
            "subcategory":"Engineering",
            "type":"Services"
        }
    ],
    "sg:phone":"+39 0522 875453",
    "sg:postcode":"42021",
    "sg:province":"Reggio Nell'Emilia",
    "sg:tags":[
        "machine",
        "-",
        "mechanical"
    ],
    "wof:name":"Rabitti E C. S.n.c. Di Cocconcelli E Rabitti",
    "wof:placetype":"venue"
},
  "geometry": {"coordinates":[10.510665,44.694901],"type":"Point"}
}