{
  "type": "Feature",
  "properties": {
    "iso:country":"IT",
    "sg:address":"3, V. S. Sebastiano 80134 Napoli",
    "sg:city":"Napoli",
    "sg:classifiers":[
        {
            "category":"Sports & Exercise",
            "subcategory":"Playing Field",
            "type":"Entertainment"
        }
    ],
    "sg:phone":"+39 39081459859",
    "sg:postcode":"80134",
    "sg:province":"Napoli",
    "sg:tags":[
        "game"
    ],
    "sg:website":"http://www.paginegialle.it/nunneri",
    "wof:name":"Nunneri",
    "wof:placetype":"venue"
},
  "geometry": {"coordinates":[14.252051,40.849262],"type":"Point"}
}