{
  "type": "Feature",
  "properties": {
    "addr:full":"39030 San Lorenzo Di Sebato Badia Bolzano/Bozen 39030",
    "addr:postcode":"39030;39030",
    "iso:country":"IT",
    "sg:address":"39030 San Lorenzo Di Sebato",
    "sg:city":"Badia",
    "sg:orig_category":"Servizi E Lavori Per Ecologia E Smaltimento Rifiuti. Termotecnica E Riscaldamento, Apparecchiature E Servizi. Servizi Ausiliari Di Sorveglianza, Manutenzione E Pulizia",
    "sg:phone":"+39 0474 474218",
    "sg:postcode":"39030",
    "sg:province":"Bolzano/Bozen",
    "wof:name":"Hochgruber Paul",
    "wof:placetype":"venue"
},
  "geometry": {"coordinates":[11.910592,46.78677],"type":"Point"}
}