{
  "type": "Feature",
  "properties": {
    "addr:full":"24062 Costa Volpino Costa Volpino Bergamo 24062",
    "addr:housenumber":"24062;volpino",
    "addr:postcode":"24062",
    "addr:street":"Costa",
    "iso:country":"IT",
    "sg:address":"24062 Costa Volpino",
    "sg:city":"Costa Volpino",
    "sg:orig_category":"Forniture Per Abbigliamento E Pelletterie",
    "sg:phone":"+39 036 459 1858",
    "sg:postcode":"24062",
    "sg:province":"Bergamo",
    "wof:name":"Bieffe Di Bettoni Giovanni & C. Snc",
    "wof:placetype":"venue"
},
  "geometry": {"coordinates":[10.0867509842,45.8446083069],"type":"Point"}
}