{
  "type": "Feature",
  "properties": {
    "iso:country":"IT",
    "sg:address":"23895 Nibionno",
    "sg:city":"Nibionno",
    "sg:orig_category":"Servizi E Lavori Per Abbigliamento E Pelletterie. Arte Ed Artigianato Artistico. Shopping",
    "sg:phone":"+39 031 690057",
    "sg:postcode":"23895",
    "sg:province":"Lecco",
    "wof:name":"Papia Ciro",
    "wof:placetype":"venue"
},
  "geometry": {"coordinates":[9.243395,45.760414],"type":"Point"}
}