{
  "type": "Feature",
  "properties": {
    "addr:full":"52100 Arezzo Arezzo Arezzo 52100",
    "addr:postcode":"52100;52100",
    "iso:country":"IT",
    "sg:address":"52100 Arezzo",
    "sg:city":"Arezzo",
    "sg:orig_category":"Metalli Preziosi E Nobili",
    "sg:phone":"+39 0575 295890",
    "sg:postcode":"52100",
    "sg:province":"Arezzo",
    "wof:name":"Clipper Srl",
    "wof:placetype":"venue"
},
  "geometry": {"coordinates":[11.8961286545,43.4588088989],"type":"Point"}
}