{
  "type": "Feature",
  "properties": {
    "iso:country":"IT",
    "sg:address":"21041 Albizzate",
    "sg:city":"Albizzate",
    "sg:orig_category":"Materie Plastiche - Produzione E Lavorazione",
    "sg:phone":"+39 0331 990203",
    "sg:postcode":"21041",
    "sg:province":"Varese",
    "wof:name":"Fargo Di C. Quadrelli",
    "wof:placetype":"venue"
},
  "geometry": {"coordinates":[8.807462,45.72467],"type":"Point"}
}