{
  "type": "Feature",
  "properties": {
    "iso:country":"IT",
    "sg:address":"21013 Gallarate",
    "sg:city":"Gallarate",
    "sg:orig_category":"Estetiste",
    "sg:phone":"+39 0331 701384",
    "sg:postcode":"21013",
    "sg:province":"Varese",
    "wof:name":"American Nails Snc",
    "wof:placetype":"venue"
},
  "geometry": {"coordinates":[8.790606,45.660976],"type":"Point"}
}