{
  "type": "Feature",
  "properties": {
    "iso:country":"IT",
    "sg:address":"18013 Diano Marina",
    "sg:city":"Diano Marina",
    "sg:orig_category":"Minuterie Metalliche E Ferramenta",
    "sg:phone":"+39 099 827 7043",
    "sg:postcode":"18013",
    "sg:province":"Imperia",
    "wof:name":"Azimuth Pallotta",
    "wof:placetype":"venue"
},
  "geometry": {"coordinates":[8.0320672989,43.888092041],"type":"Point"}
}