{
  "type": "Feature",
  "properties": {
    "iso:country":"IT",
    "sg:address":"69/71, Via Rettifilo Al Bravo 80022 Arzano",
    "sg:city":"Arzano",
    "sg:classifiers":[
        {
            "category":"Manufacturing",
            "subcategory":"Metals",
            "type":"Manufacturing & Wholesale Goods"
        }
    ],
    "sg:phone":"+39 081 573 4815",
    "sg:postcode":"80022",
    "sg:province":"Napoli",
    "sg:tags":[
        "processing"
    ],
    "wof:name":"Angelini Sud S.r.l.",
    "wof:placetype":"venue"
},
  "geometry": {"coordinates":[14.2516355515,40.84009552],"type":"Point"}
}