{
  "type": "Feature",
  "properties": {
    "iso:country":"IT",
    "sg:address":"Via D. Alighieri 52 60021 Camerano",
    "sg:city":"Camerano",
    "sg:classifiers":[
        {
            "category":"Professional",
            "subcategory":"Art Services",
            "type":"Services"
        }
    ],
    "sg:phone":"+39 071 730051",
    "sg:postcode":"60021",
    "sg:province":"Ancona",
    "sg:tags":[
        "metalwork"
    ],
    "sg:website":"www.cantori.it",
    "wof:name":"Cantori Spa",
    "wof:placetype":"venue"
},
  "geometry": {"coordinates":[13.536055,43.522816],"type":"Point"}
}