{
  "type": "Feature",
  "properties": {
    "iso:country":"IT",
    "sg:address":"Via A. Volta 69 21010 Cardano Al Campo",
    "sg:city":"Cardano al Campo",
    "sg:classifiers":[
        {
            "category":"Shopping",
            "subcategory":"Department Store",
            "type":"Retail Goods"
        }
    ],
    "sg:phone":"+39 0331 263127",
    "sg:postcode":"21010",
    "sg:province":"Varese",
    "sg:tags":[
        "linen",
        "bed"
    ],
    "sg:website":"www.fazzinispa.com",
    "wof:name":"Fazzini Spa",
    "wof:placetype":"venue"
},
  "geometry": {"coordinates":[8.826385,45.817604],"type":"Point"}
}