{
  "type": "Feature",
  "properties": {
    "iso:country":"IT",
    "sg:address":"174, Via Asolana 31010 Fonte",
    "sg:city":"Fonte",
    "sg:classifiers":[
        {
            "category":"Personal",
            "subcategory":"Shoe Repair & Shine",
            "type":"Services"
        }
    ],
    "sg:phone":"+39 0423 949800",
    "sg:postcode":"31010",
    "sg:province":"Treviso",
    "sg:tags":[
        "leather"
    ],
    "wof:name":"Guardolificio Due Rocche (s.r.l.)",
    "wof:placetype":"venue"
},
  "geometry": {"coordinates":[11.890171,45.785202],"type":"Point"}
}