{
  "type": "Feature",
  "properties": {
    "iso:country":"IT",
    "sg:address":"80013 Casalnuovo Di Napoli",
    "sg:city":"Casalnuovo di Napoli",
    "sg:orig_category":"Antifurto",
    "sg:phone":"+39 081 842 0561",
    "sg:postcode":"80013",
    "sg:province":"Napoli",
    "sg:website":"http://www.officinemanganiello.com",
    "wof:name":"Officine Manganiello Srl",
    "wof:placetype":"venue"
},
  "geometry": {"coordinates":[14.353006,40.906826],"type":"Point"}
}