{
  "type": "Feature",
  "properties": {
    "iso:country":"IT",
    "sg:address":"33170 Pordenone",
    "sg:city":"Pordenone",
    "sg:classifiers":[
        {
            "category":"Communications",
            "subcategory":"Film & Video Production",
            "type":"Services"
        }
    ],
    "sg:phone":"+39 0434 573553",
    "sg:postcode":"33170",
    "sg:province":"Pordenone",
    "sg:tags":[
        "cinema",
        "support",
        "companies",
        "trade",
        "radio-television",
        "events"
    ],
    "wof:name":"Area Marketing & Comunicazione Srl",
    "wof:placetype":"venue"
},
  "geometry": {"coordinates":[12.613113,45.806042],"type":"Point"}
}