{
  "type": "Feature",
  "properties": {
    "addr:full":"25018 Montichiari Montichiari Brescia 25018",
    "addr:postcode":"25018;25018",
    "iso:country":"IT",
    "sg:address":"25018 Montichiari",
    "sg:city":"Montichiari",
    "sg:orig_category":"Servizi E Lavori Per Edilizia E Lavori Pubblici",
    "sg:phone":"+39 030 965 0223",
    "sg:postcode":"25018",
    "sg:province":"Brescia",
    "sg:website":"http://www.seninistone.it",
    "wof:name":"Senini Stone Srl",
    "wof:placetype":"venue"
},
  "geometry": {"coordinates":[10.367213,45.413536],"type":"Point"}
}