{
  "type": "Feature",
  "properties": {
    "iso:country":"IT",
    "sg:address":"00061 Anguillara Sabazia",
    "sg:city":"Anguillara Sabazia",
    "sg:classifiers":[
        {
            "category":"Health Services",
            "subcategory":"Health Practitioner",
            "type":"Services"
        }
    ],
    "sg:phone":"+39 06 996 8202",
    "sg:postcode":"00061",
    "sg:province":"Roma",
    "sg:tags":[
        "medici"
    ],
    "wof:name":"Corona Maria Enrichetta",
    "wof:placetype":"venue"
},
  "geometry": {"coordinates":[12.270707,42.091057],"type":"Point"}
}