{
  "type": "Feature",
  "properties": {
    "iso:country":"IT",
    "sg:address":"Via Italia 2/a 25080 Paitone",
    "sg:city":"Paitone",
    "sg:classifiers":[
        {
            "category":"Home & Garden",
            "subcategory":"Hardware",
            "type":"Retail Goods"
        }
    ],
    "sg:phone":"+39 030 690000",
    "sg:postcode":"25080",
    "sg:province":"Brescia",
    "sg:tags":[
        "tarpaulin"
    ],
    "sg:website":"www.brescianigroup.it",
    "wof:name":"Teloni Fratelli Bresciani Srl",
    "wof:placetype":"venue"
},
  "geometry": {"coordinates":[10.222958,45.539829],"type":"Point"}
}