{
  "type": "Feature",
  "properties": {
    "iso:country":"IT",
    "sg:address":"43014 Medesano",
    "sg:city":"Medesano",
    "sg:orig_category":"Apparecchiature E Sistemi Per Imballaggio E Confezionamento",
    "sg:phone":"+39 0525 431199",
    "sg:postcode":"43014",
    "sg:province":"Parma",
    "wof:name":"Fipal Srl",
    "wof:placetype":"venue"
},
  "geometry": {"coordinates":[9.963554,44.515194],"type":"Point"}
}