{
  "type": "Feature",
  "properties": {
    "addr:full":"17, Vl. Brianza 20036 Meda Meda Milano 20036",
    "addr:housenumber":"17",
    "addr:postcode":"20036;20036",
    "addr:street":"Vl. Brianza",
    "iso:country":"IT",
    "sg:address":"17, Vl. Brianza 20036 Meda",
    "sg:city":"Meda",
    "sg:classifiers":[
        {
            "category":"Shopping",
            "subcategory":"Crafts & Fabrics",
            "type":"Retail Goods"
        }
    ],
    "sg:phone":"+39 036 234 0544",
    "sg:postcode":"20036",
    "sg:province":"Milano",
    "sg:website":"http://www.paginegialle.it/toppitalia",
    "wof:name":"Topp Italia Srl",
    "wof:placetype":"venue"
},
  "geometry": {"coordinates":[9.1623563766,45.6620826721],"type":"Point"}
}