{
  "type": "Feature",
  "properties": {
    "addr:full":"00198 Roma Roma Roma 00198",
    "addr:postcode":"00198;00198",
    "iso:country":"IT",
    "sg:address":"00198 Roma",
    "sg:city":"Roma",
    "sg:orig_category":"Articoli Da Regalo. Regalistica Aziendale",
    "sg:phone":"+39 06 4425 0950",
    "sg:postcode":"00198",
    "sg:province":"Roma",
    "wof:name":"Grillo Antonino Snc",
    "wof:placetype":"venue"
},
  "geometry": {"coordinates":[12.506914,41.914665],"type":"Point"}
}