{
  "type": "Feature",
  "properties": {
    "addr:full":"90139 Palermo Palermo Palermo 90139",
    "addr:postcode":"90139;90139",
    "iso:country":"IT",
    "sg:address":"90139 Palermo",
    "sg:city":"Palermo",
    "sg:orig_category":"Trasporti E Spedizioni Merci",
    "sg:phone":"+39 091 605 7111",
    "sg:postcode":"90139",
    "sg:province":"Palermo",
    "sg:website":"http://www.italybycar.it",
    "wof:name":"Italy By Car Spa",
    "wof:placetype":"venue"
},
  "geometry": {"coordinates":[13.357285,38.129463],"type":"Point"}
}