{
  "type": "Feature",
  "properties": {
    "iso:country":"IT",
    "sg:address":"00138 Roma",
    "sg:city":"Roma",
    "sg:orig_category":"Piscine Ed Accessori - Costruzione E Manutenzione",
    "sg:phone":"+39 06 888 8110",
    "sg:postcode":"00138",
    "sg:province":"Roma",
    "wof:name":"Delta Piscine Srl",
    "wof:placetype":"venue"
},
  "geometry": {"coordinates":[12.5064201355,41.9496307373],"type":"Point"}
}