{
  "type": "Feature",
  "properties": {
    "addr:full":"Via De Magistris 8, Cremona, Cr",
    "addr:housenumber":"8",
    "addr:street":"Via De Magistris;Cremona Cr",
    "iso:country":"IT",
    "sg:address":"Via De Magistris 8, Cremona, Cr",
    "sg:classifiers":[
        {
            "category":"Banks & Credit Unions",
            "subcategory":"Bank",
            "type":"Services"
        }
    ],
    "wof:name":"Cassa Rurale Del Cremasco Banca Di Credito Cooperativo Scrl",
    "wof:placetype":"venue"
},
  "geometry": {"coordinates":[10.026135,45.133499],"type":"Point"}
}