{
  "type": "Feature",
  "properties": {
    "addr:full":"70014 Conversano Conversano Bari 70014",
    "addr:postcode":"70014;70014",
    "iso:country":"IT",
    "sg:address":"70014 Conversano",
    "sg:city":"Conversano",
    "sg:orig_category":"Ospedali E Servizi Sanitari. Centri Di Estetica E Cosmesi E Servizi",
    "sg:phone":"+39 080 495 5833",
    "sg:postcode":"70014",
    "sg:province":"Bari",
    "wof:name":"Rehamedica Srl",
    "wof:placetype":"venue"
},
  "geometry": {"coordinates":[17.1248207092,40.9660568237],"type":"Point"}
}