{
  "type": "Feature",
  "properties": {
    "iso:country":"IT",
    "sg:address":"80017 Melito Di Napoli",
    "sg:city":"Melito di Napoli",
    "sg:orig_category":"Salotti, Poltrone, Sedie E Tavoli",
    "sg:phone":"+39 081 710 1100",
    "sg:postcode":"80017",
    "sg:province":"Napoli",
    "wof:name":"Scep Srl",
    "wof:placetype":"venue"
},
  "geometry": {"coordinates":[14.242284,40.916534],"type":"Point"}
}