{
  "type": "Feature",
  "properties": {
    "iso:country":"IT",
    "sg:address":"21042 Caronno Pertusella",
    "sg:city":"Caronno Pertusella",
    "sg:orig_category":"Motori Ed Organi Di Trasmissione. Ricambi E Componenti Dei Mezzi Di Trasporto",
    "sg:phone":"+39 02 9645 0250",
    "sg:postcode":"21042",
    "sg:province":"Varese",
    "wof:name":"Galli Gomme Di Cesare Galli & C. Snc",
    "wof:placetype":"venue"
},
  "geometry": {"coordinates":[9.0392856598,45.6085929871],"type":"Point"}
}