{
  "type": "Feature",
  "properties": {
    "addr:full":"21040 Oggiona Con Santo Stefano Oggiona Varese 21040",
    "addr:postcode":"21040;21040",
    "iso:country":"IT",
    "sg:address":"21040 Oggiona Con Santo Stefano",
    "sg:city":"Oggiona",
    "sg:orig_category":"Macchine, Impianti Ed Attrezzature Per Industria Alimentare E Bevande. Elettrodomestici. Macchine E Impianti Per Attivita' Commerciali Ed Artigianali",
    "sg:phone":"+39 0331 739236",
    "sg:postcode":"21040",
    "sg:province":"Varese",
    "wof:name":"Morgan Di Morganti Marco",
    "wof:placetype":"venue"
},
  "geometry": {"coordinates":[8.822054,45.693134],"type":"Point"}
}