{
  "type": "Feature",
  "properties": {
    "iso:country":"IT",
    "sg:address":"Piazza Le Accursio 18; Milano; 20156",
    "sg:city":"Milano",
    "sg:classifiers":[
        {
            "category":"Banks & Credit Unions",
            "subcategory":"Bank",
            "type":"Services"
        }
    ],
    "sg:phone":"+39 02 327 0789",
    "sg:postcode":"20156",
    "sg:province":"Milano",
    "wof:name":"Banca Agricola Milanese Spa",
    "wof:placetype":"venue"
},
  "geometry": {"coordinates":[9.145782,45.493195],"type":"Point"}
}