{
  "type": "Feature",
  "properties": {
    "iso:country":"IT",
    "sg:address":"71013 San Giovanni Rotondo",
    "sg:city":"San Giovanni Rotondo",
    "sg:orig_category":"Arredi Sacri - Produzione E Ingrosso",
    "sg:phone":"+39 0882 457811",
    "sg:postcode":"71013",
    "sg:province":"Foggia",
    "wof:name":"Germano Luca - Arte Sacra Padre Pio",
    "wof:placetype":"venue"
},
  "geometry": {"coordinates":[15.758591,41.673962],"type":"Point"}
}