{
  "type": "Feature",
  "properties": {
    "iso:country":"IT",
    "sg:address":"20, Viale Romagna 20089 Rozzano",
    "sg:city":"Rozzano",
    "sg:classifiers":[
        {
            "category":"Utilities",
            "subcategory":"Telephone",
            "type":"Services"
        }
    ],
    "sg:phone":"+39 39028254551",
    "sg:postcode":"20089",
    "sg:province":"Milano",
    "sg:tags":[
        "telecommunication"
    ],
    "wof:name":"De Lorenzo (s.p.a.)",
    "wof:placetype":"venue"
},
  "geometry": {"coordinates":[9.166204,45.38372],"type":"Point"}
}