{
  "type": "Feature",
  "properties": {
    "iso:country":"IT",
    "sg:address":"20122 Milano",
    "sg:city":"Milano",
    "sg:orig_category":"Centri Di Estetica E Cosmesi E Servizi",
    "sg:phone":"+39 02 875036",
    "sg:postcode":"20122",
    "sg:province":"Milano",
    "wof:name":"Inti Center Centro Salute E Benessere",
    "wof:placetype":"venue"
},
  "geometry": {"coordinates":[9.186695,45.457024],"type":"Point"}
}