{
  "type": "Feature",
  "properties": {
    "iso:country":"IT",
    "sg:address":"28838 Stresa",
    "sg:city":"Stresa",
    "sg:orig_category":"Servizi Al Turismo. Trasporto Pubblico E Privato",
    "sg:phone":"+39 0323 31351",
    "sg:postcode":"28838",
    "sg:province":"Verbano-Cusio-Ossola",
    "wof:name":"Ferrigato Marcello",
    "wof:placetype":"venue"
},
  "geometry": {"coordinates":[8.530589,45.884033],"type":"Point"}
}