{
  "type": "Feature",
  "properties": {
    "addr:full":"98121 Messina Messina Messina 98121",
    "addr:postcode":"98121;98121",
    "iso:country":"IT",
    "sg:address":"98121 Messina",
    "sg:city":"Messina",
    "sg:orig_category":"Zootecnia E Pesca, Allevamento Piccoli Animali. Animali Domestici",
    "sg:phone":"+39 090 43415",
    "sg:postcode":"98121",
    "sg:province":"Messina",
    "wof:name":"Bernava Giuseppe",
    "wof:placetype":"venue"
},
  "geometry": {"coordinates":[15.562325,38.21365],"type":"Point"}
}