{
  "type": "Feature",
  "properties": {
    "addr:full":"20123 Milano Milano Milano 20123",
    "addr:postcode":"20123;20123",
    "iso:country":"IT",
    "sg:address":"20123 Milano",
    "sg:city":"Milano",
    "sg:orig_category":"Articoli Per Fumatori - Produzione E Ingrosso",
    "sg:phone":"+39 02 5811 2598",
    "sg:postcode":"20123",
    "sg:province":"Milano",
    "wof:name":"Piatti & Gentili - Humidors",
    "wof:placetype":"venue"
},
  "geometry": {"coordinates":[9.183911,45.456623],"type":"Point"}
}