{
  "type": "Feature",
  "properties": {
    "addr:full":"1, Piazza D'azeglio Massimo 55049 Viareggio Viareggio Lucca 55049",
    "addr:postcode":"55049;55049",
    "addr:street":"Piazza D'Azeglio Massimo",
    "iso:country":"IT",
    "sg:address":"1, Piazza D'azeglio Massimo 55049 Viareggio",
    "sg:city":"Viareggio",
    "sg:classifiers":[
        {
            "category":"Travel",
            "subcategory":"Travel Agent",
            "type":"Entertainment"
        }
    ],
    "sg:phone":"+39 39058444449",
    "sg:postcode":"55049",
    "sg:province":"Lucca",
    "sg:tags":[
        "business"
    ],
    "wof:name":"Hotel Plaza E De Russie",
    "wof:placetype":"venue"
},
  "geometry": {"coordinates":[10.507994,43.843014],"type":"Point"}
}