{
  "type": "Feature",
  "properties": {
    "addr:full":"16, Via Giuseppe Toniolo 31030 Altivole Altivole Treviso 31030",
    "addr:postcode":"31030;31030",
    "addr:street":"Via Giuseppe Toniolo",
    "iso:country":"IT",
    "sg:address":"16, Via Giuseppe Toniolo 31030 Altivole",
    "sg:city":"Altivole",
    "sg:classifiers":[
        {
            "category":"Manufacturing",
            "subcategory":"Rubber & Plastics",
            "type":"Manufacturing & Wholesale Goods"
        }
    ],
    "sg:phone":"+39 0423 915299",
    "sg:postcode":"31030",
    "sg:province":"Treviso",
    "wof:name":"Complast (s.r.l.)",
    "wof:placetype":"venue"
},
  "geometry": {"coordinates":[11.9838552475,45.7539100647],"type":"Point"}
}