{
  "type": "Feature",
  "properties": {
    "iso:country":"IT",
    "sg:address":"87038 San Lucido",
    "sg:city":"San Lucido",
    "sg:orig_category":"Servizi Culturali E Per Lo Spettacolo. Servizi Per Lo Sport E Il Tempo Libero. Servizi Per Aziende, Manifestazioni E Supporto Agli Scambi Commerciali",
    "sg:phone":"+39 0982 84289",
    "sg:postcode":"87038",
    "sg:province":"Cosenza",
    "wof:name":"Fantasilandia Di Francesca Trifoglio",
    "wof:placetype":"venue"
},
  "geometry": {"coordinates":[16.05176,39.307064],"type":"Point"}
}