{
  "type": "Feature",
  "properties": {
    "addr:full":"10042 Nichelino Nichelino Torino 10042",
    "addr:postcode":"10042;10042",
    "iso:country":"IT",
    "sg:address":"10042 Nichelino",
    "sg:city":"Nichelino",
    "sg:orig_category":"Astucci",
    "sg:phone":"+39 011 358 2704",
    "sg:postcode":"10042",
    "sg:province":"Torino",
    "wof:name":"A.li.t.",
    "wof:placetype":"venue"
},
  "geometry": {"coordinates":[7.624069,45.003403],"type":"Point"}
}