{
  "type": "Feature",
  "properties": {
    "iso:country":"IT",
    "sg:address":"37047 San Bonifacio",
    "sg:city":"San Bonifacio",
    "sg:orig_category":"Servizi E Lavori Per Ecologia E Smaltimento Rifiuti. Ospedali E Servizi Sanitari. Servizi Ausiliari Di Analisi, Controllo E Ricerca",
    "sg:phone":"+39 045 610 1643",
    "sg:postcode":"37047",
    "sg:province":"Verona",
    "sg:website":"http://www.pakelo.it",
    "wof:name":"Pakelo Motor Oil Srl",
    "wof:placetype":"venue"
},
  "geometry": {"coordinates":[11.283463,45.385017],"type":"Point"}
}