{
  "type": "Feature",
  "properties": {
    "iso:country":"IT",
    "sg:address":"20159 Milano",
    "sg:city":"Milano",
    "sg:orig_category":"Scuole E Servizi Scolastici",
    "sg:phone":"+39 02 608 1212",
    "sg:postcode":"20159",
    "sg:province":"Milano",
    "wof:name":"Musica E Bimbi",
    "wof:placetype":"venue"
},
  "geometry": {"coordinates":[9.191761,45.498196],"type":"Point"}
}