{
  "type": "Feature",
  "properties": {
    "addr:full":"00179 Roma Roma Roma 00179",
    "addr:postcode":"00179;00179",
    "iso:country":"IT",
    "sg:address":"00179 Roma",
    "sg:city":"Roma",
    "sg:orig_category":"Forniture Per Edilizia E Lavori Pubblici",
    "sg:phone":"+39 06 782 7511",
    "sg:postcode":"00179",
    "sg:province":"Roma",
    "wof:name":"Italceramiche Srl",
    "wof:placetype":"venue"
},
  "geometry": {"coordinates":[12.5257253647,41.8682975769],"type":"Point"}
}