{
  "type": "Feature",
  "properties": {
    "iso:country":"IT",
    "sg:address":"63020 Falerone",
    "sg:city":"Falerone",
    "sg:orig_category":"Abbigliamento In Pelle - Vendita Al Dettaglio",
    "sg:phone":"+39 0734 759747",
    "sg:postcode":"63020",
    "sg:province":"Ascoli Piceno",
    "wof:name":"L.m. Di Lucentini E Massimiliani",
    "wof:placetype":"venue"
},
  "geometry": {"coordinates":[13.574977,42.8554],"type":"Point"}
}