{
  "type": "Feature",
  "properties": {
    "addr:full":"14, Via Pietro Mascagni 25080 Nuvolera Nuvolera Brescia 25080",
    "addr:postcode":"25080;25080",
    "addr:street":"Via Pietro Mascagni",
    "iso:country":"IT",
    "sg:address":"14, Via Pietro Mascagni 25080 Nuvolera",
    "sg:city":"Nuvolera",
    "sg:classifiers":[
        {
            "category":"Shopping",
            "type":"Retail Goods"
        }
    ],
    "sg:phone":"+39 030 691 9046",
    "sg:postcode":"25080",
    "sg:province":"Brescia",
    "sg:tags":[
        "finished",
        "-",
        "metallic"
    ],
    "wof:name":"O.c.s. Di Alberici A. & C. S.n.c.",
    "wof:placetype":"venue"
},
  "geometry": {"coordinates":[10.3226776123,45.5126914978],"type":"Point"}
}