{
  "type": "Feature",
  "properties": {
    "iso:country":"IT",
    "sg:address":"20026 Novate Milanese",
    "sg:city":"Novate Milanese",
    "sg:orig_category":"Prodotti Chimici Di Base",
    "sg:phone":"+39 02 354 1629",
    "sg:postcode":"20026",
    "sg:province":"Milano",
    "wof:name":"Cominder (s.r.l.)",
    "wof:placetype":"venue"
},
  "geometry": {"coordinates":[9.1538324356,45.5306243896],"type":"Point"}
}