{
  "type": "Feature",
  "properties": {
    "addr:full":"64012 Campli Campli Teramo 64012",
    "addr:postcode":"64012;64012",
    "iso:country":"IT",
    "sg:address":"64012 Campli",
    "sg:city":"Campli",
    "sg:orig_category":"Suites, Armchairs, Chairs And Tables",
    "sg:phone":"+39 0861 5092",
    "sg:postcode":"64012",
    "sg:province":"Teramo",
    "sg:website":"http://www.sofflex.it",
    "wof:name":"Sofflex Srl",
    "wof:placetype":"venue"
},
  "geometry": {"coordinates":[13.889537,42.567005],"type":"Point"}
}