{
  "type": "Feature",
  "properties": {
    "addr:full":"38100 Trento Trento Trento 38100",
    "addr:postcode":"38100;38100",
    "iso:country":"IT",
    "sg:address":"38100 Trento",
    "sg:city":"Trento",
    "sg:orig_category":"Servizi E Lavori Per Agricoltura E Zootecnia. Servizi Ausiliari Di Analisi, Controllo E Ricerca",
    "sg:phone":"+39 0461 823202",
    "sg:postcode":"38100",
    "sg:province":"Trento",
    "wof:name":"Osservatorio Climatologico",
    "wof:placetype":"venue"
},
  "geometry": {"coordinates":[11.101193,46.095703],"type":"Point"}
}