{
  "type": "Feature",
  "properties": {
    "addr:full":"67, Via S. Pancrazio 25036 Palazzolo Sull'oglio Brescia 25036",
    "addr:postcode":"25036;25036",
    "addr:street":"Via S. Pancrazio",
    "iso:country":"IT",
    "sg:address":"67, Via S. Pancrazio 25036 Palazzolo Sull'oglio",
    "sg:classifiers":[
        {
            "category":"Manufacturing",
            "subcategory":"Wood Products",
            "type":"Manufacturing & Wholesale Goods"
        }
    ],
    "sg:phone":"+39 030 740 2343",
    "sg:postcode":"25036",
    "sg:province":"Brescia",
    "sg:tags":[
        "furniture"
    ],
    "wof:name":"Moretti Import-export Srl",
    "wof:placetype":"venue"
},
  "geometry": {"coordinates":[9.930488,45.614155],"type":"Point"}
}