{
  "type": "Feature",
  "properties": {
    "iso:country":"IT",
    "sg:address":"10126 Torino",
    "sg:city":"Torino",
    "sg:orig_category":"Impianti, Attrezzature E Forniture Sanitarie Ed Ospedaliere",
    "sg:phone":"+39 011 663 2575",
    "sg:postcode":"10126",
    "sg:province":"Torino",
    "wof:name":"Al - Ber (s.r.l.)",
    "wof:placetype":"venue"
},
  "geometry": {"coordinates":[7.669896,45.042122],"type":"Point"}
}