{
  "type": "Feature",
  "properties": {
    "addr:full":"37045 Legnago Legnago Verona 37045",
    "addr:postcode":"37045;37045",
    "iso:country":"IT",
    "sg:address":"37045 Legnago",
    "sg:city":"Legnago",
    "sg:orig_category":"Motori Ed Organi Di Trasmissione. Ricambi E Componenti Dei Mezzi Di Trasporto",
    "sg:phone":"+39 0442 20711",
    "sg:postcode":"37045",
    "sg:province":"Verona",
    "wof:name":"Moro Gedeone (s.a.s.)",
    "wof:placetype":"venue"
},
  "geometry": {"coordinates":[11.3124370575,45.1617050171],"type":"Point"}
}