{
  "type": "Feature",
  "properties": {
    "iso:country":"IT",
    "sg:address":"00040 Lanuvio",
    "sg:city":"Lanuvio",
    "sg:orig_category":"Bevande, Vini E Liquori. Shopping",
    "sg:phone":"+39 06 930 3636",
    "sg:postcode":"00040",
    "sg:province":"Roma",
    "sg:website":"http://www.casatamerge.it",
    "wof:name":"Alma Srl - Casata Merg\u00c8",
    "wof:placetype":"venue"
},
  "geometry": {"coordinates":[12.69758,41.674698],"type":"Point"}
}