{
  "type": "Feature",
  "properties": {
    "iso:country":"IT",
    "sg:address":"20123 Milano",
    "sg:city":"Milano",
    "sg:orig_category":"Banche E Servizi Finanziari",
    "sg:phone":"+39 02 864101",
    "sg:postcode":"20123",
    "sg:province":"Milano",
    "wof:name":"Cambival (s.r.l.)",
    "wof:placetype":"venue"
},
  "geometry": {"coordinates":[9.186592,45.464058],"type":"Point"}
}