{
  "type": "Feature",
  "properties": {
    "iso:country":"IT",
    "sg:address":"24125 Bergamo",
    "sg:city":"Bergamo",
    "sg:orig_category":"Servizi E Lavori Per Edilizia E Lavori Pubblici. Telecomunicazioni E Telefonia, Impianti, Apparecchi E Servizi. Acqua, Luce, Gas E Societa' Di Esercizio Pubblico",
    "sg:phone":"+39 035 412 0075",
    "sg:postcode":"24125",
    "sg:province":"Bergamo",
    "wof:name":"Scuole Generali Spa",
    "wof:placetype":"venue"
},
  "geometry": {"coordinates":[9.685461,45.699207],"type":"Point"}
}