{
  "type": "Feature",
  "properties": {
    "addr:full":"30030 Martellago Martellago Venezia 30030",
    "addr:postcode":"30030;30030",
    "iso:country":"IT",
    "sg:address":"30030 Martellago",
    "sg:city":"Martellago",
    "sg:orig_category":"Abrasivi",
    "sg:phone":"+39 041 540 1911",
    "sg:postcode":"30030",
    "sg:province":"Venezia",
    "wof:name":"Arbe Srl",
    "wof:placetype":"venue"
},
  "geometry": {"coordinates":[12.173745,45.537762],"type":"Point"}
}