{
  "type": "Feature",
  "properties": {
    "iso:country":"IT",
    "sg:address":"35031 Abano Terme",
    "sg:city":"Abano Terme",
    "sg:orig_category":"Abbigliamento - Produzione E Ingrosso",
    "sg:phone":"+39 049 860 0660",
    "sg:postcode":"35031",
    "sg:province":"Padova",
    "wof:name":"Sap Fur Snc Di Pajaro & C.",
    "wof:placetype":"venue"
},
  "geometry": {"coordinates":[11.808879,45.354744],"type":"Point"}
}