{
  "type": "Feature",
  "properties": {
    "iso:country":"IT",
    "sg:address":"10142 Torino",
    "sg:city":"Torino",
    "sg:orig_category":"Lavorazioni Meccaniche E Servizi",
    "sg:phone":"+39 011 797062",
    "sg:postcode":"10142",
    "sg:province":"Torino",
    "wof:name":"M.g.",
    "wof:placetype":"venue"
},
  "geometry": {"coordinates":[7.61724,45.070896],"type":"Point"}
}