{
  "type": "Feature",
  "properties": {
    "addr:full":"63018 Porto Sant'elpidio Ascoli Piceno 63018",
    "addr:housenumber":"63018",
    "addr:postcode":"63018",
    "iso:country":"IT",
    "sg:address":"63018 Porto Sant'elpidio",
    "sg:orig_category":"Calzaturifici E Calzolai - Forniture",
    "sg:phone":"+39 0734 996263",
    "sg:postcode":"63018",
    "sg:province":"Ascoli Piceno",
    "wof:name":"Uno C Di Calzetti Andrea & C. Sas",
    "wof:placetype":"venue"
},
  "geometry": {"coordinates":[13.746295,43.250172],"type":"Point"}
}