{
  "type": "Feature",
  "properties": {
    "addr:full":"24060 Borgo Di Terzo Borgo di Terzo Bergamo 24060",
    "addr:housenumber":"di terzo",
    "addr:postcode":"24060;24060",
    "addr:street":"Borgo",
    "iso:country":"IT",
    "sg:address":"24060 Borgo Di Terzo",
    "sg:city":"Borgo di Terzo",
    "sg:orig_category":"Servizi E Lavori Industria Della Gomma",
    "sg:phone":"+39 035 822833",
    "sg:postcode":"24060",
    "sg:province":"Bergamo",
    "wof:name":"Stagom (s.r.l.)",
    "wof:placetype":"venue"
},
  "geometry": {"coordinates":[9.847857,45.70713],"type":"Point"}
}