{
  "type": "Feature",
  "properties": {
    "iso:country":"IT",
    "sg:address":"55049 Viareggio",
    "sg:city":"Viareggio",
    "sg:orig_category":"Agricoltura, Orticoltura E Floricoltura",
    "sg:phone":"+39 0584 45383",
    "sg:postcode":"55049",
    "sg:province":"Lucca",
    "wof:name":"Cozzolino Nunzia",
    "wof:placetype":"venue"
},
  "geometry": {"coordinates":[10.27123,43.851627],"type":"Point"}
}