{
  "type": "Feature",
  "properties": {
    "iso:country":"IT",
    "sg:address":"12089 Villanova Mondov\u00ec",
    "sg:orig_category":"Climatizzazione E Condizionamento, Apparecchiature E Servizi. Elettrotecnica Professionale E Di Consumo",
    "sg:phone":"+39 0174 597254",
    "sg:postcode":"12089",
    "sg:province":"Cuneo",
    "wof:name":"Calleri & Fenoglio",
    "wof:placetype":"venue"
},
  "geometry": {"coordinates":[7.584759,44.501221],"type":"Point"}
}