{
  "type": "Feature",
  "properties": {
    "addr:full":"15, Via Padre Semeria 18014 Ospedaletti Ospedaletti Imperia 18014",
    "addr:postcode":"18014;18014",
    "addr:street":"Via Padre Semeria",
    "iso:country":"IT",
    "sg:address":"15, Via Padre Semeria 18014 Ospedaletti",
    "sg:city":"Ospedaletti",
    "sg:classifiers":[
        {
            "category":"Parking",
            "subcategory":"Lot",
            "type":"Transportation"
        }
    ],
    "sg:phone":"+39 0184 688281",
    "sg:postcode":"18014",
    "sg:province":"Imperia",
    "sg:tags":[
        "transport",
        "road"
    ],
    "wof:name":"Dinnocenzo Marco",
    "wof:placetype":"venue"
},
  "geometry": {"coordinates":[7.722294,43.804329],"type":"Point"}
}