{
  "type": "Feature",
  "properties": {
    "addr:full":"00040 Roma Roma 00040",
    "addr:postcode":"00040;00040",
    "iso:country":"IT",
    "sg:address":"00040 Roma",
    "sg:orig_category":"Cinematografia E Radiotelevisione. Forniture Per Il Settore Dello Spettacolo",
    "sg:phone":"+39 06 7984 5621",
    "sg:postcode":"00040",
    "sg:province":"Roma",
    "wof:name":"In Scena S.r.l.",
    "wof:placetype":"venue"
},
  "geometry": {"coordinates":[12.636884,41.810268],"type":"Point"}
}