{
  "type": "Feature",
  "properties": {
    "iso:country":"IT",
    "sg:address":"14100 Asti",
    "sg:city":"Asti",
    "sg:orig_category":"Impiantistica E Prodotti Tecnologici Per Edilizia. Forniture Industriali Per Prevenzione, Controllo E Sicurezza",
    "sg:phone":"+39 0141 214878",
    "sg:postcode":"14100",
    "sg:province":"Asti",
    "wof:name":"S.p. Di Mario Morlin",
    "wof:placetype":"venue"
},
  "geometry": {"coordinates":[8.213656,44.91024],"type":"Point"}
}