{
  "type": "Feature",
  "properties": {
    "iso:country":"IT",
    "sg:address":"29, Via Marconi 20089 Rozzano",
    "sg:city":"Rozzano",
    "sg:classifiers":[
        {
            "category":"Manufacturing",
            "subcategory":"Rubber & Plastics",
            "type":"Manufacturing & Wholesale Goods"
        }
    ],
    "sg:phone":"+39 02 5750 1010",
    "sg:postcode":"20089",
    "sg:province":"Milano",
    "wof:name":"C.c.z. (s.r.l.)",
    "wof:placetype":"venue"
},
  "geometry": {"coordinates":[9.167618,45.378338],"type":"Point"}
}