{
  "type": "Feature",
  "properties": {
    "iso:country":"IT",
    "sg:address":"16152 Genova",
    "sg:city":"Genova",
    "sg:orig_category":"Metalli E Leghe",
    "sg:phone":"+39 010 602211",
    "sg:postcode":"16152",
    "sg:province":"Genova",
    "wof:name":"San Giorgio Seigen Spa",
    "wof:placetype":"venue"
},
  "geometry": {"coordinates":[8.8493280411,44.4272460938],"type":"Point"}
}