{
  "type": "Feature",
  "properties": {
    "iso:country":"IT",
    "sg:address":"20122 Milano",
    "sg:city":"Milano",
    "sg:orig_category":"Avvocati, Notai E Servizi Legali. Consulenze Tecniche, Amministrative E Perizie",
    "sg:phone":"+39 02 7601 4174",
    "sg:postcode":"20122",
    "sg:province":"Milano",
    "wof:name":"Indicam",
    "wof:placetype":"venue"
},
  "geometry": {"coordinates":[9.201798,45.469955],"type":"Point"}
}