{
  "type": "Feature",
  "properties": {
    "iso:country":"IT",
    "sg:address":"57121 Livorno",
    "sg:city":"Livorno",
    "sg:classifiers":[
        {
            "category":"Professional",
            "subcategory":"Engineering",
            "type":"Services"
        }
    ],
    "sg:phone":"+39 0586 426406",
    "sg:postcode":"57121",
    "sg:province":"Livorno",
    "sg:tags":[
        "fair",
        "supply",
        "non-professional",
        "music",
        "congresses",
        "electronic",
        "events"
    ],
    "wof:name":"Music Empire Studios",
    "wof:placetype":"venue"
},
  "geometry": {"coordinates":[10.3192167282,43.5870819092],"type":"Point"}
}