{
  "type": "Feature",
  "properties": {
    "addr:full":"20017 Rho Rho Milano 20017",
    "addr:postcode":"20017;20017",
    "iso:country":"IT",
    "sg:address":"20017 Rho",
    "sg:city":"Rho",
    "sg:orig_category":"Elettronica Professionale E Di Consumo. Automazione E Macchine Per Ufficio",
    "sg:phone":"+39 02 9350 0075",
    "sg:postcode":"20017",
    "sg:province":"Milano",
    "wof:name":"F.i.m.m. Fatturazioni Immediate S.r.l.",
    "wof:placetype":"venue"
},
  "geometry": {"coordinates":[9.048947,45.529705],"type":"Point"}
}