{
  "type": "Feature",
  "properties": {
    "iso:country":"IT",
    "sg:address":"00171 Roma",
    "sg:city":"Roma",
    "sg:orig_category":"Casellari E Cassette Postali, Bacheche",
    "sg:phone":"+39 06 259 1460",
    "sg:postcode":"00171",
    "sg:province":"Roma",
    "sg:website":"http://www.acplepalme.com",
    "wof:name":"A.c.p. Le Palme Di Marco Stoppoloni",
    "wof:placetype":"venue"
},
  "geometry": {"coordinates":[12.567672,41.889893],"type":"Point"}
}