{
  "type": "Feature",
  "properties": {
    "addr:full":"00185 Roma Roma Roma 00185",
    "addr:postcode":"00185;00185",
    "iso:country":"IT",
    "sg:address":"00185 Roma",
    "sg:city":"Roma",
    "sg:orig_category":"Pubblica Amministrazione",
    "sg:phone":"+39 06 772 6911",
    "sg:postcode":"00185",
    "sg:province":"Roma",
    "wof:name":"Questura Di Roma",
    "wof:placetype":"venue"
},
  "geometry": {"coordinates":[12.5108146667,41.8916091919],"type":"Point"}
}