{
  "type": "Feature",
  "properties": {
    "iso:country":"IT",
    "sg:address":"35037 Teolo",
    "sg:city":"Teolo",
    "sg:orig_category":"Frigotecnica, Apparecchiature E Servizi. Arredi Ed Attrezzature Per Uffici",
    "sg:phone":"+39 049 990 3365",
    "sg:postcode":"35037",
    "sg:province":"Padova",
    "wof:name":"Friso Paolino",
    "wof:placetype":"venue"
},
  "geometry": {"coordinates":[11.7870292664,45.3479270935],"type":"Point"}
}