{
  "type": "Feature",
  "properties": {
    "addr:full":"309/a, Via S.apollinare 40050 Castello Di Serravalle Castello di Serravalle Bologna 40050",
    "addr:housenumber":"309 / a",
    "addr:postcode":"40050;40050",
    "addr:street":"Via S.Apollinare",
    "iso:country":"IT",
    "sg:address":"309/a, Via S.apollinare 40050 Castello Di Serravalle",
    "sg:city":"Castello di Serravalle",
    "sg:classifiers":[
        {
            "category":"Manufacturing",
            "subcategory":"Metals",
            "type":"Manufacturing & Wholesale Goods"
        }
    ],
    "sg:phone":"+39 051 670 4834",
    "sg:postcode":"40050",
    "sg:province":"Bologna",
    "sg:tags":[
        "processing"
    ],
    "wof:name":"Officine Parmeggiani S.r.l.",
    "wof:placetype":"venue"
},
  "geometry": {"coordinates":[11.3464813232,44.4942207336],"type":"Point"}
}