{
  "type": "Feature",
  "properties": {
    "iso:country":"IT",
    "sg:address":"Via Luigi Einaudi 56/a 36040 Brendola",
    "sg:city":"Brendola",
    "sg:classifiers":[
        {
            "category":"Military Area",
            "subcategory":"Air Force Base",
            "type":"Public Place"
        }
    ],
    "sg:phone":"+39 0444 695399",
    "sg:postcode":"36040",
    "sg:province":"Vicenza",
    "sg:tags":[
        "wall",
        "movable"
    ],
    "sg:website":"www.dosak.it",
    "wof:name":"Dosak Sas",
    "wof:placetype":"venue"
},
  "geometry": {"coordinates":[11.540307045,45.5459060669],"type":"Point"}
}