{
  "type": "Feature",
  "properties": {
    "iso:country":"IT",
    "sg:address":"80040 Volla",
    "sg:city":"Volla",
    "sg:orig_category":"Climatizzazione E Condizionamento, Apparecchiature E Servizi. Accessori Dei Mezzi Di Trasporto",
    "sg:phone":"+39 081 774 6697",
    "sg:postcode":"80040",
    "sg:province":"Napoli",
    "wof:name":"Officina Elettrauto Visone",
    "wof:placetype":"venue"
},
  "geometry": {"coordinates":[14.342882,40.880577],"type":"Point"}
}