{
  "type": "Feature",
  "properties": {
    "iso:country":"IT",
    "sg:address":"20155 Milano",
    "sg:city":"Milano",
    "sg:orig_category":"Utensili Meccanici E Materiali. Elettrotecnica Industriale, Prodotti E Apparecchiature",
    "sg:phone":"+39 02 3300 1528",
    "sg:postcode":"20155",
    "sg:province":"Milano",
    "wof:name":"Tarenzi Srl",
    "wof:placetype":"venue"
},
  "geometry": {"coordinates":[9.149349,45.49123],"type":"Point"}
}