{
  "type": "Feature",
  "properties": {
    "iso:country":"IT",
    "sg:address":"Loc. Fosci 6/a 53036 Poggibonsi",
    "sg:city":"Poggibonsi",
    "sg:classifiers":[
        {
            "category":"Wholesale",
            "subcategory":"Vending Machines",
            "type":"Manufacturing & Wholesale Goods"
        }
    ],
    "sg:phone":"+39 0577 936693",
    "sg:postcode":"53036",
    "sg:province":"Siena",
    "sg:tags":[
        "preparation",
        "processing",
        "meat"
    ],
    "sg:website":"www.omet-foodtech.it",
    "wof:name":"Omet Foodtech Srl",
    "wof:placetype":"venue"
},
  "geometry": {"coordinates":[11.330514,43.318661],"type":"Point"}
}