{
  "type": "Feature",
  "properties": {
    "iso:country":"IT",
    "sg:address":"22100 Como",
    "sg:city":"Como",
    "sg:orig_category":"Servizi E Lavori Per Abbigliamento E Pelletterie",
    "sg:phone":"+39 031 507374",
    "sg:postcode":"22100",
    "sg:province":"Como",
    "wof:name":"Berni Vittorio",
    "wof:placetype":"venue"
},
  "geometry": {"coordinates":[9.071479,45.789062],"type":"Point"}
}