{
  "type": "Feature",
  "properties": {
    "addr:full":"Via Di Vittorio 307/17 20099 Sesto San Giovanni Sesto San Giovanni Milano 20099",
    "addr:housenumber":"307 / 17",
    "addr:postcode":"20099;20099",
    "addr:street":"Via Di Vittorio",
    "iso:country":"IT",
    "sg:address":"Via Di Vittorio 307/17 20099 Sesto San Giovanni",
    "sg:city":"Sesto San Giovanni",
    "sg:orig_category":"Photopolymer Plates",
    "sg:phone":"+39 02 2622 4564",
    "sg:postcode":"20099",
    "sg:province":"Milano",
    "sg:website":"www.rotoflex.org",
    "wof:name":"Rotoflex Srl",
    "wof:placetype":"venue"
},
  "geometry": {"coordinates":[9.2611160278,45.5273971558],"type":"Point"}
}