{
  "type": "Feature",
  "properties": {
    "iso:country":"IT",
    "sg:address":"Via Sotto Gli Orti 84032 Buonabitacolo",
    "sg:city":"Buonabitacolo",
    "sg:orig_category":"Ladies' Shoes",
    "sg:phone":"+39 0975 91378",
    "sg:postcode":"84032",
    "sg:province":"Salerno",
    "wof:name":"Elia Soc. Coop. A R.l.",
    "wof:placetype":"venue"
},
  "geometry": {"coordinates":[14.765912,40.677956],"type":"Point"}
}