{
  "type": "Feature",
  "properties": {
    "iso:country":"IT",
    "sg:address":"70122 Bari",
    "sg:city":"Bari",
    "sg:orig_category":"Tourism, Services. Transport, Auxiliary Services",
    "sg:phone":"+39 080 524 0264",
    "sg:postcode":"70122",
    "sg:province":"Bari",
    "sg:website":"http://pwhux.tin.it/dgsgtn",
    "wof:name":"D.g. Cargo Srl",
    "wof:placetype":"venue"
},
  "geometry": {"coordinates":[16.861511,41.122364],"type":"Point"}
}