{
  "type": "Feature",
  "properties": {
    "iso:country":"IT",
    "sg:address":"31020 Villorba",
    "sg:city":"Villorba",
    "sg:orig_category":"Abbigliamento Esterno, Maglierie E Pelliccerie. Shopping",
    "sg:phone":"+39 0422 910291",
    "sg:postcode":"31020",
    "sg:province":"Treviso",
    "wof:name":"Publimarkacommunication Srl",
    "wof:placetype":"venue"
},
  "geometry": {"coordinates":[12.250945,45.728523],"type":"Point"}
}