{
  "type": "Feature",
  "properties": {
    "iso:country":"IT",
    "sg:address":"9, Via Della Zecca 10072 Caselle Torinese",
    "sg:city":"Caselle Torinese",
    "sg:classifiers":[
        {
            "category":"Travel",
            "subcategory":"Travel Agent",
            "type":"Entertainment"
        }
    ],
    "sg:phone":"+39 011 991 3733",
    "sg:postcode":"10072",
    "sg:province":"Torino",
    "sg:tags":[
        "business"
    ],
    "wof:name":"Jet Hotel",
    "wof:placetype":"venue"
},
  "geometry": {"coordinates":[7.649375,45.197468],"type":"Point"}
}