{
  "type": "Feature",
  "properties": {
    "iso:country":"IT",
    "sg:address":"40123 Bologna",
    "sg:city":"Bologna",
    "sg:orig_category":"Associazioni Sindacali E Di Categoria",
    "sg:phone":"+39 051 277111",
    "sg:postcode":"40123",
    "sg:province":"Bologna",
    "sg:website":"http://www.asppi.bo.it",
    "wof:name":"Asppi - Associazione Sindacale Piccoli Proprietari Immobiliari",
    "wof:placetype":"venue"
},
  "geometry": {"coordinates":[11.337578,44.494888],"type":"Point"}
}