{
  "type": "Feature",
  "properties": {
    "iso:country":"IT",
    "sg:address":"81, Via Ungheresca Sud 31010 Mareno Di Piave",
    "sg:city":"Mareno di Piave",
    "sg:classifiers":[
        {
            "category":"Shopping",
            "subcategory":"Computers & Home Electronics",
            "type":"Retail Goods"
        }
    ],
    "sg:phone":"+39 0438 281111",
    "sg:postcode":"31010",
    "sg:province":"Treviso",
    "sg:tags":[
        "electronic",
        "electrical",
        "equipment"
    ],
    "wof:name":"D'arsie' Srl",
    "wof:placetype":"venue"
},
  "geometry": {"coordinates":[12.309958,45.821953],"type":"Point"}
}