{
  "type": "Feature",
  "properties": {
    "iso:country":"IT",
    "sg:address":"7, Via Roma 22070 Casnate Con Bernate",
    "sg:city":"Casnate",
    "sg:classifiers":[
        {
            "category":"Shopping",
            "subcategory":"Crafts & Fabrics",
            "type":"Retail Goods"
        }
    ],
    "sg:phone":"+39 39031564685",
    "sg:postcode":"22070",
    "sg:province":"Como",
    "wof:name":"Pinto Achille Spa",
    "wof:placetype":"venue"
},
  "geometry": {"coordinates":[9.0715475082,45.7560806274],"type":"Point"}
}