{
  "type": "Feature",
  "properties": {
    "iso:country":"IT",
    "sg:address":"39, Via Torricelli Evangelista 37136 Verona",
    "sg:city":"Verona",
    "sg:classifiers":[
        {
            "category":"Shopping",
            "subcategory":"Computers & Home Electronics",
            "type":"Retail Goods"
        }
    ],
    "sg:phone":"+39 045 921 2333",
    "sg:postcode":"37136",
    "sg:province":"Verona",
    "sg:tags":[
        "electronic",
        "electrical",
        "equipment"
    ],
    "wof:name":"Cusinati S.r.l.",
    "wof:placetype":"venue"
},
  "geometry": {"coordinates":[10.955959,45.410919],"type":"Point"}
}