{
  "type": "Feature",
  "properties": {
    "iso:country":"IT",
    "sg:address":"73031 Alessano",
    "sg:city":"Alessano",
    "sg:orig_category":"Manufacturers: Prefabbricati. Servizi E Lavori Per Ecologia E Smaltimento Rifiuti",
    "sg:phone":"+39 0833 522986",
    "sg:postcode":"73031",
    "sg:province":"Lecce",
    "wof:name":"Colaci Oronzo",
    "wof:placetype":"venue"
},
  "geometry": {"coordinates":[18.320799,39.898357],"type":"Point"}
}