{
  "type": "Feature",
  "properties": {
    "iso:country":"IT",
    "sg:address":"Via Giacomo Leopardi 30 28060 San Pietro Mosezzo",
    "sg:city":"San Pietro Mosezzo",
    "sg:classifiers":[
        {
            "category":"Manufacturing",
            "subcategory":"Paper Products",
            "type":"Manufacturing & Wholesale Goods"
        }
    ],
    "sg:phone":"+39 0321 468735",
    "sg:postcode":"28060",
    "sg:province":"Novara",
    "sg:tags":[
        "machine",
        "industry",
        "cardboard",
        "packing"
    ],
    "wof:name":"No.el. Srl",
    "wof:placetype":"venue"
},
  "geometry": {"coordinates":[8.5609712601,45.4564743042],"type":"Point"}
}