{
  "type": "Feature",
  "properties": {
    "iso:country":"IT",
    "sg:address":"66034 Lanciano",
    "sg:city":"Lanciano",
    "sg:orig_category":"Servizi Per Aziende, Manifestazioni E Supporto Agli Scambi Commerciali",
    "sg:phone":"+39 0872 713586",
    "sg:postcode":"66034",
    "sg:province":"Chieti",
    "sg:website":"http://www.eventiecongressi.it",
    "wof:name":"Studio Eventi & Congressi Di Rossella Piccirilli",
    "wof:placetype":"venue"
},
  "geometry": {"coordinates":[14.39184,42.228081],"type":"Point"}
}