{
  "type": "Feature",
  "properties": {
    "addr:full":"10152 Torino Torino Torino 10152",
    "addr:postcode":"10152;10152",
    "iso:country":"IT",
    "sg:address":"10152 Torino",
    "sg:city":"Torino",
    "sg:orig_category":"Servizi E Lavori Per Edilizia E Lavori Pubblici",
    "sg:phone":"+39 011 436 5307",
    "sg:postcode":"10152",
    "sg:province":"Torino",
    "wof:name":"Eureka Di M. Gramaglia & C. Snc",
    "wof:placetype":"venue"
},
  "geometry": {"coordinates":[7.67924,45.083557],"type":"Point"}
}