{
  "type": "Feature",
  "properties": {
    "addr:full":"20093 Cologno Monzese Cologno Monzese Milano 20093",
    "addr:postcode":"20093;20093",
    "iso:country":"IT",
    "sg:address":"20093 Cologno Monzese",
    "sg:city":"Cologno Monzese",
    "sg:orig_category":"Serramenti Ed Infissi",
    "sg:phone":"+39 02 2539 0001",
    "sg:postcode":"20093",
    "sg:province":"Milano",
    "sg:website":"http://www.camepiu.it",
    "wof:name":"Came Piu' Srl",
    "wof:placetype":"venue"
},
  "geometry": {"coordinates":[9.265775,45.536423],"type":"Point"}
}