{
  "type": "Feature",
  "properties": {
    "iso:country":"IT",
    "sg:address":"64/68, V. V. Veneto 20020 Lazzate",
    "sg:city":"Lazzate",
    "sg:classifiers":[
        {
            "category":"Wholesale",
            "subcategory":"Drugs",
            "type":"Manufacturing & Wholesale Goods"
        }
    ],
    "sg:phone":"+39 39029630941",
    "sg:postcode":"20020",
    "sg:province":"Milano",
    "sg:tags":[
        "chemical",
        "pharmaceutical"
    ],
    "wof:name":"Ponzini Spa",
    "wof:placetype":"venue"
},
  "geometry": {"coordinates":[9.107994,45.687038],"type":"Point"}
}