{
  "type": "Feature",
  "properties": {
    "addr:full":"20122 Milano Milano Milano 20122",
    "addr:postcode":"20122;20122",
    "iso:country":"IT",
    "sg:address":"20122 Milano",
    "sg:city":"Milano",
    "sg:orig_category":"Ospedali E Servizi Sanitari",
    "sg:phone":"+39 02 783982",
    "sg:postcode":"20122",
    "sg:province":"Milano",
    "wof:name":"Corsi Enrico",
    "wof:placetype":"venue"
},
  "geometry": {"coordinates":[9.197203,45.465675],"type":"Point"}
}