{
  "type": "Feature",
  "properties": {
    "iso:country":"IT",
    "sg:address":"Corso Torino 90; Pinerolo",
    "sg:classifiers":[
        {
            "category":"Banks & Credit Unions",
            "subcategory":"Bank",
            "type":"Services"
        }
    ],
    "sg:phone":"+39 0121 78555",
    "wof:name":"Banca Di Roma",
    "wof:placetype":"venue"
},
  "geometry": {"coordinates":[7.33425,44.885479],"type":"Point"}
}