{
  "type": "Feature",
  "properties": {
    "iso:country":"IT",
    "sg:address":"7, Via San Martino 31020 San Zenone Degli Ezzelini",
    "sg:city":"San Zenone degli Ezzelini",
    "sg:classifiers":[
        {
            "category":"Manufacturing",
            "subcategory":"Metals",
            "type":"Manufacturing & Wholesale Goods"
        }
    ],
    "sg:phone":"+39 0423 968611",
    "sg:postcode":"31020",
    "sg:province":"Treviso",
    "sg:tags":[
        "metallurgy",
        "metalworking"
    ],
    "wof:name":"Silmec Srl",
    "wof:placetype":"venue"
},
  "geometry": {"coordinates":[11.8260231018,45.7793579102],"type":"Point"}
}