{
  "type": "Feature",
  "properties": {
    "iso:country":"IT",
    "sg:address":"20121 Milano",
    "sg:city":"Milano",
    "sg:orig_category":"Servizi Editoriali. Pubblicita', Marketing E Comunicazione",
    "sg:phone":"+39 02 805 1422",
    "sg:postcode":"20121",
    "sg:province":"Milano",
    "wof:name":"Mia (s.r.l.)",
    "wof:placetype":"venue"
},
  "geometry": {"coordinates":[9.192164,45.466145],"type":"Point"}
}