{
  "type": "Feature",
  "properties": {
    "iso:country":"IT",
    "sg:address":"20132 Milano",
    "sg:city":"Milano",
    "sg:orig_category":"Professionisti - Studi E Servizi Ed Associazioni Di Interesse Aziendale. Servizi Sociali. Associazioni Ed Organismi Di Interesse Pubblico",
    "sg:phone":"+39 02 282 8743",
    "sg:postcode":"20132",
    "sg:province":"Milano",
    "wof:name":"Cassa Per Le Pensioni Dei Dipendenti Degli Enti Locali",
    "wof:placetype":"venue"
},
  "geometry": {"coordinates":[9.2310628891,45.4924850464],"type":"Point"}
}