{
  "type": "Feature",
  "properties": {
    "addr:full":"10133 Torino Torino Torino 10133",
    "addr:postcode":"10133;10133",
    "iso:country":"IT",
    "sg:address":"10133 Torino",
    "sg:city":"Torino",
    "sg:orig_category":"Scuole E Servizi Scolastici",
    "sg:phone":"+39 011 660 2234",
    "sg:postcode":"10133",
    "sg:province":"Torino",
    "wof:name":"Saint Denis",
    "wof:placetype":"venue"
},
  "geometry": {"coordinates":[7.685918,45.009018],"type":"Point"}
}