{
  "type": "Feature",
  "properties": {
    "iso:country":"IT",
    "sg:address":"Via Monte Verena, 23 - San Zeno 36022 Cassola",
    "sg:city":"Cassola",
    "sg:classifiers":[
        {
            "category":"Shopping",
            "subcategory":"Jewelry",
            "type":"Retail Goods"
        }
    ],
    "sg:phone":"+39 0424 570353",
    "sg:postcode":"36022",
    "sg:province":"Vicenza",
    "sg:tags":[
        "gemstone",
        "jewellery"
    ],
    "wof:name":"D'orica S.r.l.",
    "wof:placetype":"venue"
},
  "geometry": {"coordinates":[11.760373,45.752712],"type":"Point"}
}