{
  "type": "Feature",
  "properties": {
    "iso:country":"IT",
    "sg:address":"11100 Aosta",
    "sg:city":"Aosta",
    "sg:orig_category":"Servizi Per Aziende, Manifestazioni E Supporto Agli Scambi Commerciali",
    "sg:phone":"+39 0165 230528",
    "sg:postcode":"11100",
    "sg:province":"Aosta",
    "sg:website":"http://www.leubage.it",
    "wof:name":"L'eubage Srl",
    "wof:placetype":"venue"
},
  "geometry": {"coordinates":[7.344876,45.741802],"type":"Point"}
}