{
  "type": "Feature",
  "properties": {
    "addr:full":"84092 Bellizzi Bellizzi Salerno 84092",
    "addr:postcode":"84092;84092",
    "addr:street":"Bellizzi",
    "iso:country":"IT",
    "sg:address":"84092 Bellizzi",
    "sg:city":"Bellizzi",
    "sg:orig_category":"Forniture Per Agricoltura E Zootecnia. Animali Domestici",
    "sg:phone":"+39 0828 52790",
    "sg:postcode":"84092",
    "sg:province":"Salerno",
    "wof:name":"Veterinaria 2000 Di Giacchetti M.",
    "wof:placetype":"venue"
},
  "geometry": {"coordinates":[14.9418058395,40.6174430847],"type":"Point"}
}