{
  "type": "Feature",
  "properties": {
    "addr:full":"Via Luigi Carrara 52 24027 Nembro Nembro Bergamo 24027",
    "addr:housenumber":"52",
    "addr:postcode":"24027;24027",
    "addr:street":"Via Luigi Carrara",
    "iso:country":"IT",
    "sg:address":"Via Luigi Carrara 52 24027 Nembro",
    "sg:city":"Nembro",
    "sg:classifiers":[
        {
            "category":"Shopping",
            "subcategory":"Crafts & Fabrics",
            "type":"Retail Goods"
        }
    ],
    "sg:phone":"+39 035 520333",
    "sg:postcode":"24027",
    "sg:province":"Bergamo",
    "sg:tags":[
        "textile",
        "machinery",
        "accessory"
    ],
    "wof:name":"Italtubetti Spa",
    "wof:placetype":"venue"
},
  "geometry": {"coordinates":[9.780752,45.74995],"type":"Point"}
}