{
  "type": "Feature",
  "properties": {
    "iso:country":"IT",
    "sg:address":"22040 Lurago D'erba",
    "sg:orig_category":"Tessuti E Stoffe. Filati E Materie Prime Tessili",
    "sg:phone":"+39 031 697454",
    "sg:postcode":"22040",
    "sg:province":"Como",
    "wof:name":"Texal Spa",
    "wof:placetype":"venue"
},
  "geometry": {"coordinates":[9.223866,45.757401],"type":"Point"}
}