{
  "type": "Feature",
  "properties": {
    "iso:country":"IT",
    "sg:address":"24029 Vertova",
    "sg:city":"Vertova",
    "sg:orig_category":"Carta, Cartone E Prodotti Primari. Forniture E Materiali Per Imballaggio E Confezionamento",
    "sg:phone":"+39 035 711001",
    "sg:postcode":"24029",
    "sg:province":"Bergamo",
    "wof:name":"Zaninoni Osvaldo",
    "wof:placetype":"venue"
},
  "geometry": {"coordinates":[9.818562,45.829792],"type":"Point"}
}