{
  "type": "Feature",
  "properties": {
    "iso:country":"IT",
    "sg:address":"15033 Casale Monferrato",
    "sg:city":"Casale Monferrato",
    "sg:orig_category":"Elettricita' Materiali - Ingrosso",
    "sg:phone":"+39 0142 436711",
    "sg:postcode":"15033",
    "sg:province":"Alessandria",
    "sg:website":"http://www.demosrl.it",
    "wof:name":"D.e.m.o. Srl",
    "wof:placetype":"venue"
},
  "geometry": {"coordinates":[8.469069,45.126301],"type":"Point"}
}