{
  "type": "Feature",
  "properties": {
    "addr:full":"Viale Stazione, 2; Moncalieri; 10024 Moncalieri Torino 10024",
    "addr:housenumber":"2",
    "addr:postcode":"10024;10024",
    "addr:street":"Viale Stazione",
    "iso:country":"IT",
    "sg:address":"Viale Stazione, 2; Moncalieri; 10024",
    "sg:city":"Moncalieri",
    "sg:classifiers":[
        {
            "category":"Banks & Credit Unions",
            "subcategory":"Bank",
            "type":"Services"
        }
    ],
    "sg:phone":"+39 011 640 7307",
    "sg:postcode":"10024",
    "sg:province":"Torino",
    "wof:name":"Banca Nazionale Dell'agricoltura",
    "wof:placetype":"venue"
},
  "geometry": {"coordinates":[7.67886,44.99876],"type":"Point"}
}