{
  "type": "Feature",
  "properties": {
    "addr:full":"Strada Statale 378 Km. 3,5 70059 Trani Trani Bari 70059",
    "addr:housenumber":"3,5",
    "addr:postcode":"70059;70059",
    "addr:street":"Strada Statale 378 Km.",
    "iso:country":"IT",
    "sg:address":"Strada Statale 378 Km. 3,5 70059 Trani",
    "sg:city":"Trani",
    "sg:orig_category":"Boys' Clothing",
    "sg:phone":"+39 0883 580606",
    "sg:postcode":"70059",
    "sg:province":"Bari",
    "sg:website":"www.conflevante.it",
    "wof:name":"Conflevante Srl",
    "wof:placetype":"venue"
},
  "geometry": {"coordinates":[16.869291,41.126053],"type":"Point"}
}