{
  "type": "Feature",
  "properties": {
    "addr:full":"62019 Recanati Recanati Macerata 62019",
    "addr:postcode":"62019;62019",
    "iso:country":"IT",
    "sg:address":"62019 Recanati",
    "sg:city":"Recanati",
    "sg:orig_category":"Articoli Da Regalo. Shopping. Regalistica Aziendale",
    "sg:phone":"+39 071 757 3701",
    "sg:postcode":"62019",
    "sg:province":"Macerata",
    "wof:name":"Gr Di Bravi Roberto & C. Snc",
    "wof:placetype":"venue"
},
  "geometry": {"coordinates":[13.5321235657,43.3946838379],"type":"Point"}
}