{
  "type": "Feature",
  "properties": {
    "iso:country":"IT",
    "sg:address":"Via Reycend Enrico 37/a 10148 Torino",
    "sg:city":"Torino",
    "sg:classifiers":[
        {
            "category":"Wholesale",
            "subcategory":"Machinery & Supplies",
            "type":"Manufacturing & Wholesale Goods"
        }
    ],
    "sg:phone":"+39 011 220 4828",
    "sg:postcode":"10148",
    "sg:province":"Torino",
    "sg:tags":[
        "pin",
        "clevis"
    ],
    "sg:website":"www.restamp.it",
    "wof:name":"Restamp Snc Di Carlo Valfre' E C.",
    "wof:placetype":"venue"
},
  "geometry": {"coordinates":[7.686619,45.07056],"type":"Point"}
}