{
  "type": "Feature",
  "properties": {
    "iso:country":"IT",
    "sg:address":"5, Via Val D'aposa 40123 Bologna",
    "sg:city":"Bologna",
    "sg:classifiers":[
        {
            "category":"Wholesale",
            "subcategory":"Drugs",
            "type":"Manufacturing & Wholesale Goods"
        }
    ],
    "sg:phone":"+39 39051263931",
    "sg:postcode":"40123",
    "sg:province":"Bologna",
    "sg:tags":[
        "chemical",
        "pharmaceutical"
    ],
    "wof:name":"Belda Ottica S.n.c. Di Daoudi Fouad E C.",
    "wof:placetype":"venue"
},
  "geometry": {"coordinates":[11.340219,44.49213],"type":"Point"}
}