{
  "type": "Feature",
  "properties": {
    "iso:country":"IT",
    "sg:address":"00198 Roma",
    "sg:city":"Roma",
    "sg:orig_category":"Pubblica Amministrazione",
    "sg:phone":"+39 06 845561",
    "sg:postcode":"00198",
    "sg:province":"Roma",
    "wof:name":"Regione Basilicata",
    "wof:placetype":"venue"
},
  "geometry": {"coordinates":[12.499912262,41.9122505188],"type":"Point"}
}