{
  "type": "Feature",
  "properties": {
    "addr:full":"Via Ciocche 1103 55047 Seravezza Seravezza Lucca 55047",
    "addr:housenumber":"1103",
    "addr:postcode":"55047;55047",
    "addr:street":"Via Ciocche",
    "iso:country":"IT",
    "sg:address":"Via Ciocche 1103 55047 Seravezza",
    "sg:city":"Seravezza",
    "sg:classifiers":[
        {
            "category":"Transit Center",
            "subcategory":"Freight",
            "type":"Transportation"
        }
    ],
    "sg:phone":"+39 0584 752305",
    "sg:postcode":"55047",
    "sg:province":"Lucca",
    "sg:tags":[
        "machining",
        "marble"
    ],
    "sg:website":"www.ntm-marble.it",
    "wof:name":"N.t.m. Srl",
    "wof:placetype":"venue"
},
  "geometry": {"coordinates":[10.179336,43.975727],"type":"Point"}
}