{
  "type": "Feature",
  "properties": {
    "addr:full":"61100 Pesaro Pesaro Pesaro E Urbino 61100",
    "addr:postcode":"61100;61100",
    "iso:country":"IT",
    "sg:address":"61100 Pesaro",
    "sg:city":"Pesaro",
    "sg:orig_category":"Fiere, Mostre E Saloni - Allestimento E Servizi",
    "sg:phone":"+39 0721 282751",
    "sg:postcode":"61100",
    "sg:province":"Pesaro E Urbino",
    "sg:website":"http://www.morinimancinelli.com",
    "wof:name":"Morini Maurizio & Mancinelli Luigi Snc",
    "wof:placetype":"venue"
},
  "geometry": {"coordinates":[12.8632154465,43.8812408447],"type":"Point"}
}