{
  "type": "Feature",
  "properties": {
    "iso:country":"IT",
    "sg:address":"22078 Turate",
    "sg:city":"Turate",
    "sg:orig_category":"Apparecchiature E Sistemi Per Imballaggio E Confezionamento",
    "sg:phone":"+39 02 968 0233",
    "sg:postcode":"22078",
    "sg:province":"Como",
    "wof:name":"Labor Di Borghi Paolo",
    "wof:placetype":"venue"
},
  "geometry": {"coordinates":[9.08521,45.803829],"type":"Point"}
}