{
  "type": "Feature",
  "properties": {
    "iso:country":"IT",
    "sg:address":"35010 Loreggia",
    "sg:city":"Loreggia",
    "sg:classifiers":[
        {
            "category":"Manufacturing",
            "subcategory":"Leather Goods",
            "type":"Manufacturing & Wholesale Goods"
        }
    ],
    "sg:phone":"+39 049 935 5207",
    "sg:postcode":"35010",
    "sg:province":"Padova",
    "sg:tags":[
        "goods",
        "clothing",
        "supply"
    ],
    "wof:name":"Bastarolo Giancarlo",
    "wof:placetype":"venue"
},
  "geometry": {"coordinates":[11.950846,45.609978],"type":"Point"}
}