{
  "type": "Feature",
  "properties": {
    "addr:full":"Via Alessandro Manzoni 25020 Flero Flero Brescia 25020",
    "addr:postcode":"25020;25020",
    "addr:street":"Via Alessandro Manzoni",
    "iso:country":"IT",
    "sg:address":"Via Alessandro Manzoni 25020 Flero",
    "sg:city":"Flero",
    "sg:classifiers":[
        {
            "category":"Professional",
            "subcategory":"Engineering",
            "type":"Services"
        }
    ],
    "sg:phone":"+39 030 268 1223",
    "sg:postcode":"25020",
    "sg:province":"Brescia",
    "sg:tags":[
        "machine",
        "-",
        "mechanical"
    ],
    "wof:name":"Fusteltecnica Di Zilioli Giuliano E. C. (s.n.c.)",
    "wof:placetype":"venue"
},
  "geometry": {"coordinates":[10.166419,45.493645],"type":"Point"}
}