{
  "type": "Feature",
  "properties": {
    "iso:country":"IT",
    "sg:address":"19126 La Spezia",
    "sg:classifiers":[
        {
            "category":"Wholesale",
            "subcategory":"Machinery & Supplies",
            "type":"Manufacturing & Wholesale Goods"
        }
    ],
    "sg:phone":"+39 0187 511474",
    "sg:province":"SP",
    "sg:tags":[
        "equipment",
        "mechanical"
    ],
    "wof:name":"Ceresa Carlo",
    "wof:placetype":"venue"
},
  "geometry": {"coordinates":[9.859933,44.107529],"type":"Point"}
}