{
  "type": "Feature",
  "properties": {
    "addr:full":"58100 Grosseto Grosseto Grosseto 58100",
    "addr:postcode":"58100;58100",
    "iso:country":"IT",
    "sg:address":"58100 Grosseto",
    "sg:city":"Grosseto",
    "sg:orig_category":"Panetterie",
    "sg:phone":"+39 0564 456251",
    "sg:postcode":"58100",
    "sg:province":"Grosseto",
    "wof:name":"Panificio G. & G. Di Grasso E Guerrini",
    "wof:placetype":"venue"
},
  "geometry": {"coordinates":[11.1071310043,42.770778656],"type":"Point"}
}