{
  "type": "Feature",
  "properties": {
    "iso:country":"IT",
    "sg:address":"00119 Roma",
    "sg:city":"Roma",
    "sg:orig_category":"Centri Di Estetica E Cosmesi E Servizi. Prodotti Cosmetici E Da Toeletta",
    "sg:phone":"+39 06 565 2431",
    "sg:postcode":"00119",
    "sg:province":"Roma",
    "wof:name":"Ceccarelli Valerio",
    "wof:placetype":"venue"
},
  "geometry": {"coordinates":[12.306305,41.775536],"type":"Point"}
}