{
  "type": "Feature",
  "properties": {
    "iso:country":"IT",
    "sg:address":"92100 Agrigento",
    "sg:city":"Agrigento",
    "sg:orig_category":"Abrasivi",
    "sg:phone":"+39 0922 21486",
    "sg:postcode":"92100",
    "sg:province":"Agrigento",
    "wof:name":"Zambuto Raimondo",
    "wof:placetype":"venue"
},
  "geometry": {"coordinates":[13.587773,37.303085],"type":"Point"}
}