{
  "type": "Feature",
  "properties": {
    "iso:country":"IT",
    "sg:address":"56040 Castellina Marittima",
    "sg:city":"Castellina Marittima",
    "sg:orig_category":"Materie Plastiche Rinforzate E Materiali Compositi",
    "sg:phone":"+39 050 699749",
    "sg:postcode":"56040",
    "sg:province":"Pisa",
    "wof:name":"Ma.ve.t Di Minutella Rizieri",
    "wof:placetype":"venue"
},
  "geometry": {"coordinates":[10.501245,43.389652],"type":"Point"}
}