{
  "type": "Feature",
  "properties": {
    "iso:country":"IT",
    "sg:address":"20123 Milano",
    "sg:city":"Milano",
    "sg:orig_category":"Imprese Di Costruzioni Civili Ed Industriali",
    "sg:phone":"+39 02 433481",
    "sg:postcode":"20123",
    "sg:province":"Milano",
    "wof:name":"Italprogetti Srl",
    "wof:placetype":"venue"
},
  "geometry": {"coordinates":[9.167419,45.464218],"type":"Point"}
}