{
  "type": "Feature",
  "properties": {
    "iso:country":"IT",
    "sg:address":"39012 Merano",
    "sg:city":"Merano",
    "sg:orig_category":"Prodotti E Manufatti In Gomma. Servizi E Lavori Industria Della Gomma. Ricambi E Componenti Dei Mezzi Di Trasporto. Riparazione Dei Mezzi Di Trasporto",
    "sg:phone":"+39 0473 230252",
    "sg:postcode":"39012",
    "sg:province":"Bolzano/Bozen",
    "sg:website":"http://www.pneustirolo.it",
    "wof:name":"Pneustirolo Srl",
    "wof:placetype":"venue"
},
  "geometry": {"coordinates":[11.3423185349,46.4900512695],"type":"Point"}
}