{
  "type": "Feature",
  "properties": {
    "iso:country":"IT",
    "sg:address":"Via Monsuello 36 25065 Lumezzane",
    "sg:city":"Lumezzane",
    "sg:orig_category":"Fittings, Valves",
    "sg:phone":"+39 030 892 2111",
    "sg:postcode":"25065",
    "sg:province":"Brescia",
    "wof:name":"Idrosanitaria Bonomi Spa",
    "wof:placetype":"venue"
},
  "geometry": {"coordinates":[10.2586536407,45.6496887207],"type":"Point"}
}