{
  "type": "Feature",
  "properties": {
    "iso:country":"IT",
    "sg:address":"20052 Monza",
    "sg:city":"Monza",
    "sg:orig_category":"Lavorazioni Metalli, Stampaggio E Saldatura",
    "sg:phone":"+39 039 742161",
    "sg:postcode":"20052",
    "sg:province":"Milano",
    "wof:name":"Ing. R. & M. Bolles & Figli",
    "wof:placetype":"venue"
},
  "geometry": {"coordinates":[9.190272,45.551537],"type":"Point"}
}