{
  "type": "Feature",
  "properties": {
    "addr:full":"20040 Briosco Briosco Milano 20040",
    "addr:postcode":"20040;20040",
    "iso:country":"IT",
    "sg:address":"20040 Briosco",
    "sg:city":"Briosco",
    "sg:orig_category":"Macchine, Impianti Ed Attrezzature Per Abbigliamento E Pelletterie. Apparecchiature Ed Attrezzature Meccaniche. Elettrotecnica Industriale, Prodotti E Apparecchiature",
    "sg:phone":"+39 036 295535",
    "sg:postcode":"20040",
    "sg:province":"Milano",
    "wof:name":"Sipro Srl",
    "wof:placetype":"venue"
},
  "geometry": {"coordinates":[9.226904,45.451729],"type":"Point"}
}