{
  "type": "Feature",
  "properties": {
    "iso:country":"IT",
    "sg:address":"00196 Roma",
    "sg:city":"Roma",
    "sg:orig_category":"Pompe",
    "sg:phone":"+39 06 320 2011",
    "sg:postcode":"00196",
    "sg:province":"Roma",
    "wof:name":"Worthington Spa",
    "wof:placetype":"venue"
},
  "geometry": {"coordinates":[12.4652137756,41.9277877808],"type":"Point"}
}