{
  "type": "Feature",
  "properties": {
    "iso:country":"IT",
    "sg:address":"Via Dell' Industria 1/l 37059 Zevio",
    "sg:city":"Zevio",
    "sg:orig_category":"Anticorrosives",
    "sg:phone":"+39 045 785 0063",
    "sg:postcode":"37059",
    "sg:province":"Verona",
    "sg:website":"www.futurarivestimenti.it",
    "wof:name":"Futura Rivestimenti Srl",
    "wof:placetype":"venue"
},
  "geometry": {"coordinates":[11.091999,45.419384],"type":"Point"}
}