{
  "type": "Feature",
  "properties": {
    "addr:full":"27, Via Della Meccanica 37139 Verona Verona Verona 37139",
    "addr:postcode":"37139;37139",
    "addr:street":"Via Della Meccanica",
    "iso:country":"IT",
    "sg:address":"27, Via Della Meccanica 37139 Verona",
    "sg:city":"Verona",
    "sg:classifiers":[
        {
            "category":"Manufacturing",
            "subcategory":"Textiles",
            "type":"Manufacturing & Wholesale Goods"
        }
    ],
    "sg:phone":"+39 045 839 3811",
    "sg:postcode":"37139",
    "sg:province":"Verona",
    "sg:tags":[
        "leather",
        "raw",
        "material",
        "-"
    ],
    "wof:name":"Despa S.p.a.",
    "wof:placetype":"venue"
},
  "geometry": {"coordinates":[10.889031,45.450752],"type":"Point"}
}