{
  "type": "Feature",
  "properties": {
    "addr:full":"60029 Ancona AN",
    "addr:postcode":"60029",
    "iso:country":"IT",
    "sg:address":"60029 Ancona",
    "sg:classifiers":[
        {
            "category":"Health Services",
            "subcategory":"Health Practitioner",
            "type":"Services"
        }
    ],
    "sg:phone":"+39 071 290 1081",
    "sg:province":"AN",
    "sg:tags":[
        "medici"
    ],
    "wof:name":"Centro Regionale Di Medicina Dello Sport Del C.o.n.i.",
    "wof:placetype":"venue"
},
  "geometry": {"coordinates":[-87.791298,42.056999],"type":"Point"}
}