{
  "type": "Feature",
  "properties": {
    "iso:country":"IT",
    "sg:address":"30121 Venezia",
    "sg:city":"Cannaregio",
    "sg:orig_category":"Trasporti E Spedizioni Merci",
    "sg:phone":"+39 041 244 0178",
    "sg:postcode":"30121",
    "sg:province":"Venezia",
    "wof:name":"Zennaro Trasporti & C. Sas",
    "wof:placetype":"venue"
},
  "geometry": {"coordinates":[12.340234,45.438961],"type":"Point"}
}