{
  "type": "Feature",
  "properties": {
    "addr:full":"Via P. Bordone 10; Taibon Agordino; 32027 Taibon Agordino Belluno 32027",
    "addr:housenumber":"10",
    "addr:postcode":"32027;32027",
    "addr:street":"Via P. Bordone;Agordino",
    "iso:country":"IT",
    "sg:address":"Via P. Bordone 10; Taibon Agordino; 32027",
    "sg:city":"Taibon Agordino",
    "sg:classifiers":[
        {
            "category":"Banks & Credit Unions",
            "subcategory":"Bank",
            "type":"Services"
        }
    ],
    "sg:phone":"+39 0437 660431",
    "sg:postcode":"32027",
    "sg:province":"Belluno",
    "wof:name":"Banca Sella Spa",
    "wof:placetype":"venue"
},
  "geometry": {"coordinates":[12.014977,46.300438],"type":"Point"}
}