{
  "type": "Feature",
  "properties": {
    "iso:country":"IT",
    "sg:address":"27040 Mezzanino",
    "sg:city":"Mezzanino",
    "sg:orig_category":"Motori Ed Organi Di Trasmissione. Ricambi E Componenti Dei Mezzi Di Trasporto",
    "sg:phone":"+39 0385 71067",
    "sg:postcode":"27040",
    "sg:province":"Pavia",
    "wof:name":"Top Cuscinetti Srl",
    "wof:placetype":"venue"
},
  "geometry": {"coordinates":[9.211388588,45.1271362305],"type":"Point"}
}