{
  "type": "Feature",
  "properties": {
    "iso:country":"IT",
    "sg:address":"34147 Trieste",
    "sg:city":"Trieste",
    "sg:orig_category":"Imprese Di Costruzioni Civili Ed Industriali",
    "sg:phone":"+39 040 380102",
    "sg:postcode":"34147",
    "sg:province":"Trieste",
    "wof:name":"Centro Edile Srl",
    "wof:placetype":"venue"
},
  "geometry": {"coordinates":[13.821258,45.598099],"type":"Point"}
}