{
  "type": "Feature",
  "properties": {
    "addr:full":"70122 Bari Bari Bari 70122",
    "addr:postcode":"70122;70122",
    "iso:country":"IT",
    "sg:address":"70122 Bari",
    "sg:city":"Bari",
    "sg:orig_category":"Scuole E Servizi Scolastici. Ricerca, Selezione E Formazione Del Personale",
    "sg:phone":"+39 080 523 7569",
    "sg:postcode":"70122",
    "sg:province":"Bari",
    "wof:name":"Oppenheimer Srl",
    "wof:placetype":"venue"
},
  "geometry": {"coordinates":[16.871471,41.11797],"type":"Point"}
}