{
  "type": "Feature",
  "properties": {
    "addr:full":"26, Via Monferrato 20098 San Giuliano Milanese San Giuliano Milanese Milano 20098",
    "addr:postcode":"20098;20098",
    "addr:street":"Via Monferrato",
    "iso:country":"IT",
    "sg:address":"26, Via Monferrato 20098 San Giuliano Milanese",
    "sg:city":"San Giuliano Milanese",
    "sg:classifiers":[
        {
            "category":"Utilities",
            "subcategory":"Electric",
            "type":"Services"
        }
    ],
    "sg:phone":"+39 39029880189",
    "sg:postcode":"20098",
    "sg:province":"Milano",
    "sg:tags":[
        "component",
        "electronic"
    ],
    "wof:name":"O E B Elettronica Srl",
    "wof:placetype":"venue"
},
  "geometry": {"coordinates":[9.259624,45.39978],"type":"Point"}
}