{
  "type": "Feature",
  "properties": {
    "addr:full":"00177 Roma Roma Roma 00177",
    "addr:postcode":"00177;00177",
    "iso:country":"IT",
    "sg:address":"00177 Roma",
    "sg:city":"Roma",
    "sg:orig_category":"Macchine, Impianti Ed Attrezzature Industria Chimica. Attrezzature E Forniture Per Officine Riparazione E Servizi Ausiliari",
    "sg:phone":"+39 06 295506",
    "sg:postcode":"00177",
    "sg:province":"Roma",
    "wof:name":"Conidi S.a.s Di Conidi Francesco Debora & C.",
    "wof:placetype":"venue"
},
  "geometry": {"coordinates":[12.884376,41.889793],"type":"Point"}
}