{
  "type": "Feature",
  "properties": {
    "iso:country":"IT",
    "sg:address":"Via Adua 24; Berbenno",
    "sg:classifiers":[
        {
            "category":"Banks & Credit Unions",
            "subcategory":"Bank",
            "type":"Services"
        }
    ],
    "sg:phone":"+39 0342 492262",
    "wof:name":"Credito Valtellines Scarl",
    "wof:placetype":"venue"
},
  "geometry": {"coordinates":[9.740953,46.168846],"type":"Point"}
}