{
  "type": "Feature",
  "properties": {
    "addr:full":"Piazza Dante 9 16121 Genova Genova Genova 16121",
    "addr:housenumber":"9",
    "addr:postcode":"16121;16121",
    "addr:street":"Piazza Dante",
    "iso:country":"IT",
    "sg:address":"Piazza Dante 9 16121 Genova",
    "sg:city":"Genova",
    "sg:classifiers":[
        {
            "category":"Home & Garden",
            "subcategory":"Carpets & Floor Coverings",
            "type":"Retail Goods"
        }
    ],
    "sg:phone":"+39 010 581698",
    "sg:postcode":"16121",
    "sg:province":"Genova",
    "sg:tags":[
        "mosaic"
    ],
    "sg:website":"www.ceramicagenova.com",
    "wof:name":"Ceramica Genova Srl",
    "wof:placetype":"venue"
},
  "geometry": {"coordinates":[8.9350805283,44.4063644409],"type":"Point"}
}