{
  "type": "Feature",
  "properties": {
    "iso:country":"IT",
    "sg:address":"51028 S.marcello Pist.",
    "sg:orig_category":"Officine Meccaniche",
    "sg:phone":"+39 0573 622549",
    "sg:postcode":"51028",
    "sg:province":"Pistoia",
    "wof:name":"F.lli Venturi Di Venturi Filippo Matteo & C. Snc",
    "wof:placetype":"venue"
},
  "geometry": {"coordinates":[10.89031,43.954372],"type":"Point"}
}