{
  "type": "Feature",
  "properties": {
    "iso:country":"IT",
    "sg:address":"3, Via Cartaia 59021 Vaiano",
    "sg:city":"Vaiano",
    "sg:classifiers":[
        {
            "category":"Shopping",
            "subcategory":"Crafts & Fabrics",
            "type":"Retail Goods"
        }
    ],
    "sg:phone":"+39 0574 984030",
    "sg:postcode":"59021",
    "sg:province":"Prato",
    "wof:name":"Fartex Srl",
    "wof:placetype":"venue"
},
  "geometry": {"coordinates":[11.1274595261,43.9267883301],"type":"Point"}
}