{
  "type": "Feature",
  "properties": {
    "addr:full":"20090 Cusago Cusago Milano 20090",
    "addr:postcode":"20090;20090",
    "iso:country":"IT",
    "sg:address":"20090 Cusago",
    "sg:city":"Cusago",
    "sg:orig_category":"Pompe. Macchine, Strumenti Ed Apparecchi Per Attivita' Industriali",
    "sg:phone":"+39 02 903 9211",
    "sg:postcode":"20090",
    "sg:province":"Milano",
    "wof:name":"S.e.i.m. Srl",
    "wof:placetype":"venue"
},
  "geometry": {"coordinates":[9.0471324921,45.4417610168],"type":"Point"}
}