{
  "type": "Feature",
  "properties": {
    "addr:full":"23, V. Crespano 31010 Fonte Fonte Treviso 31010",
    "addr:housenumber":"23",
    "addr:postcode":"31010;31010",
    "addr:street":"V. Crespano",
    "iso:country":"IT",
    "sg:address":"23, V. Crespano 31010 Fonte",
    "sg:city":"Fonte",
    "sg:classifiers":[
        {
            "category":"Professional",
            "subcategory":"Engineering",
            "type":"Services"
        }
    ],
    "sg:phone":"+39 0423 949378",
    "sg:postcode":"31010",
    "sg:province":"Treviso",
    "sg:tags":[
        "machine",
        "-",
        "mechanical"
    ],
    "sg:website":"http://www.paginegialle.it/zuccolottoautomazioni",
    "wof:name":"Zuccolotto Giuseppe",
    "wof:placetype":"venue"
},
  "geometry": {"coordinates":[11.8559865952,45.8063621521],"type":"Point"}
}