{
  "type": "Feature",
  "properties": {
    "iso:country":"IT",
    "sg:address":"2, Via Buon Pastore 40141 Bologna",
    "sg:city":"Bologna",
    "sg:classifiers":[
        {
            "category":"Professional",
            "subcategory":"Business Services",
            "type":"Services"
        }
    ],
    "sg:phone":"+39 39051474782",
    "sg:postcode":"40141",
    "sg:province":"Bologna",
    "sg:tags":[
        "advice"
    ],
    "wof:name":"Profingest",
    "wof:placetype":"venue"
},
  "geometry": {"coordinates":[11.369739,44.45953],"type":"Point"}
}