{
  "type": "Feature",
  "properties": {
    "iso:country":"IT",
    "sg:address":"24040 Osio Sopra",
    "sg:city":"Osio Sopra",
    "sg:orig_category":"Sabbiatura Metalli",
    "sg:phone":"+39 035 502128",
    "sg:postcode":"24040",
    "sg:province":"Bergamo",
    "wof:name":"Co.m.m.i. Srl",
    "wof:placetype":"venue"
},
  "geometry": {"coordinates":[9.600662,45.628159],"type":"Point"}
}