{
  "type": "Feature",
  "properties": {
    "addr:full":"26, Via Montello 23895 Nibionno Nibionno Lecco 23895",
    "addr:postcode":"23895;23895",
    "addr:street":"Via Montello",
    "iso:country":"IT",
    "sg:address":"26, Via Montello 23895 Nibionno",
    "sg:city":"Nibionno",
    "sg:classifiers":[
        {
            "category":"Shopping",
            "subcategory":"Crafts & Fabrics",
            "type":"Retail Goods"
        }
    ],
    "sg:phone":"+39 39031690895",
    "sg:postcode":"23895",
    "sg:province":"Lecco",
    "wof:name":"Donghi Enrico & Figli (s.a.s.)",
    "wof:placetype":"venue"
},
  "geometry": {"coordinates":[9.2718315125,45.7602005005],"type":"Point"}
}