{
  "type": "Feature",
  "properties": {
    "iso:country":"IT",
    "sg:address":"13, P. Xi Febbraio 24050 Zanica",
    "sg:city":"Zanica",
    "sg:classifiers":[
        {
            "category":"Parking",
            "subcategory":"Lot",
            "type":"Transportation"
        }
    ],
    "sg:phone":"+39 39035671023",
    "sg:postcode":"24050",
    "sg:province":"Bergamo",
    "sg:tags":[
        "transport",
        "road"
    ],
    "sg:website":"http://www.rottoli.it",
    "wof:name":"Autotrasporti Rottoli Snc",
    "wof:placetype":"venue"
},
  "geometry": {"coordinates":[9.669952,45.694904],"type":"Point"}
}