{
  "type": "Feature",
  "properties": {
    "iso:country":"IT",
    "sg:address":"64, Via Arno 52043 Castiglion Fiorentino",
    "sg:city":"Castiglion Fiorentino",
    "sg:classifiers":[
        {
            "category":"Personal",
            "subcategory":"Shoe Repair & Shine",
            "type":"Services"
        }
    ],
    "sg:phone":"+39 0575 680074",
    "sg:postcode":"52043",
    "sg:province":"Arezzo",
    "sg:tags":[
        "leather"
    ],
    "wof:name":"Sepam Shoes S.n.c.",
    "wof:placetype":"venue"
},
  "geometry": {"coordinates":[11.904918,43.343967],"type":"Point"}
}