{
  "type": "Feature",
  "properties": {
    "iso:country":"IT",
    "sg:address":"90146 Palermo",
    "sg:city":"Palermo",
    "sg:orig_category":"Servizi E Lavori Per Edilizia E Lavori Pubblici",
    "sg:phone":"+39 091 671 0848",
    "sg:postcode":"90146",
    "sg:province":"Palermo",
    "wof:name":"Tarantino Giovanna La Perla",
    "wof:placetype":"venue"
},
  "geometry": {"coordinates":[13.320137,38.163792],"type":"Point"}
}