{
  "type": "Feature",
  "properties": {
    "iso:country":"IT",
    "sg:address":"70, Strada St. Sempione 20028 San Vittore Olona",
    "sg:city":"San Vittore Olona",
    "sg:classifiers":[
        {
            "category":"Personal",
            "subcategory":"Shoe Repair & Shine",
            "type":"Services"
        }
    ],
    "sg:phone":"+39 0331 519054",
    "sg:postcode":"20028",
    "sg:province":"Milano",
    "sg:tags":[
        "leather"
    ],
    "wof:name":"Commissionaria Europelli Spa",
    "wof:placetype":"venue"
},
  "geometry": {"coordinates":[9.188141,45.463688],"type":"Point"}
}