{
  "type": "Feature",
  "properties": {
    "iso:country":"IT",
    "sg:address":"81100 Caserta",
    "sg:city":"Caserta",
    "sg:orig_category":"Autonoleggio",
    "sg:phone":"+39 0823 216168",
    "sg:postcode":"81100",
    "sg:province":"Caserta",
    "wof:name":"Caserta Car Service Piccola Soc.coop.r.l.",
    "wof:placetype":"venue"
},
  "geometry": {"coordinates":[14.338964,41.066372],"type":"Point"}
}