{
  "type": "Feature",
  "properties": {
    "iso:country":"IT",
    "sg:address":"10028 Trofarello",
    "sg:city":"Trofarello",
    "sg:orig_category":"Utensili Meccanici E Materiali. Forniture Per Attivita' Industriali",
    "sg:phone":"+39 011 648 1213",
    "sg:postcode":"10028",
    "sg:province":"Torino",
    "wof:name":"Diamond-lap Srl",
    "wof:placetype":"venue"
},
  "geometry": {"coordinates":[7.745366,44.975861],"type":"Point"}
}