{
  "type": "Feature",
  "properties": {
    "addr:full":"20147 Milano Milano Milano 20147",
    "addr:postcode":"20147;20147",
    "iso:country":"IT",
    "sg:address":"20147 Milano",
    "sg:city":"Milano",
    "sg:orig_category":"Prodotti Chimici Di Base",
    "sg:phone":"+39 02 419432",
    "sg:postcode":"20147",
    "sg:province":"Milano",
    "wof:name":"Chemit System S.r.l.",
    "wof:placetype":"venue"
},
  "geometry": {"coordinates":[9.1339597702,45.4593009949],"type":"Point"}
}