{
  "type": "Feature",
  "properties": {
    "iso:country":"IT",
    "sg:address":"10040 Leini'",
    "sg:orig_category":"Studi E Consulenze Amministrative, Commerciali E Aziendali. Banche E Servizi Finanziari. Agenzie D'affari E Servizi Commerciali. Consulenze Tecniche, Amministrative E Perizie",
    "sg:phone":"+39 011 998 8295",
    "sg:postcode":"10040",
    "sg:province":"Torino",
    "wof:name":"Ballor Dott. Domenico",
    "wof:placetype":"venue"
},
  "geometry": {"coordinates":[7.665225,45.153229],"type":"Point"}
}