{
  "type": "Feature",
  "properties": {
    "iso:country":"IT",
    "sg:address":"20090 Segrate",
    "sg:city":"Segrate",
    "sg:orig_category":"Attrezzature E Forniture Per Officine Riparazione E Servizi Ausiliari",
    "sg:phone":"+39 02 2695 0032",
    "sg:postcode":"20090",
    "sg:province":"Milano",
    "wof:name":"A.t. Tecnology Sas Di Trangoni A. & C.",
    "wof:placetype":"venue"
},
  "geometry": {"coordinates":[9.275015,45.497974],"type":"Point"}
}