{
  "type": "Feature",
  "properties": {
    "addr:full":"20133 Milano Milano Milano 20133",
    "addr:postcode":"20133;20133",
    "iso:country":"IT",
    "sg:address":"20133 Milano",
    "sg:city":"Milano",
    "sg:orig_category":"Arredi Ed Attrezzature Per Attivita' Commerciali Ed Artigianali",
    "sg:phone":"+39 02 7010 7389",
    "sg:postcode":"20133",
    "sg:province":"Milano",
    "wof:name":"Monimo (s.r.l.)",
    "wof:placetype":"venue"
},
  "geometry": {"coordinates":[9.233452,45.473495],"type":"Point"}
}