{
  "type": "Feature",
  "properties": {
    "addr:full":"Corso Umberto I, 1; Verzuolo; 12039 Verzuolo Cuneo 12039",
    "addr:housenumber":"1",
    "addr:postcode":"12039;12039",
    "addr:street":"Corso Umberto I",
    "iso:country":"IT",
    "sg:address":"Corso Umberto I, 1; Verzuolo; 12039",
    "sg:city":"Verzuolo",
    "sg:classifiers":[
        {
            "category":"Banks & Credit Unions",
            "subcategory":"Bank",
            "type":"Services"
        }
    ],
    "sg:phone":"+39 0175 85115",
    "sg:postcode":"12039",
    "sg:province":"Cuneo",
    "wof:name":"Banca Popolare Di Novara",
    "wof:placetype":"venue"
},
  "geometry": {"coordinates":[7.483148,44.597511],"type":"Point"}
}