{
  "type": "Feature",
  "properties": {
    "iso:country":"IT",
    "sg:address":"03029 Castelmassimo",
    "sg:city":"Castelmassimo",
    "sg:orig_category":"Manufacturers: Prefabbricati",
    "sg:phone":"+39 0775 308207",
    "sg:postcode":"03029",
    "sg:province":"Frosinone",
    "wof:name":"Santoro Fabio",
    "wof:placetype":"venue"
},
  "geometry": {"coordinates":[13.4497,41.671135],"type":"Point"}
}