{
  "type": "Feature",
  "properties": {
    "iso:country":"IT",
    "sg:address":"25030 Urago D'oglio",
    "sg:orig_category":"Servizi E Lavori Per Abbigliamento E Pelletterie",
    "sg:phone":"+39 030 717410",
    "sg:postcode":"25030",
    "sg:province":"Brescia",
    "wof:name":"Confezioni Stireria Amica",
    "wof:placetype":"venue"
},
  "geometry": {"coordinates":[9.867604,45.514008],"type":"Point"}
}