{
  "type": "Feature",
  "properties": {
    "addr:full":"20092 Cinisello Balsamo Cinisello Balsamo Milano 20092",
    "addr:postcode":"20092;20092",
    "iso:country":"IT",
    "sg:address":"20092 Cinisello Balsamo",
    "sg:city":"Cinisello Balsamo",
    "sg:classifiers":[
        {
            "category":"Shopping",
            "subcategory":"Gifts & Souvenirs",
            "type":"Retail Goods"
        }
    ],
    "sg:phone":"+39 02 2247 8765",
    "sg:postcode":"20092",
    "sg:province":"Milano",
    "sg:tags":[
        "gifts",
        "business"
    ],
    "sg:website":"http://www.altoplex.com",
    "wof:name":"Altoplex Snc",
    "wof:placetype":"venue"
},
  "geometry": {"coordinates":[9.22519,45.541859],"type":"Point"}
}