{
  "type": "Feature",
  "properties": {
    "addr:full":"Via Mario Pagano 59 20090 Trezzano Sul Naviglio Trezzano sul Naviglio Milano 20090",
    "addr:housenumber":"59",
    "addr:postcode":"20090;20090",
    "addr:street":"Via Mario Pagano",
    "iso:country":"IT",
    "sg:address":"Via Mario Pagano 59 20090 Trezzano Sul Naviglio",
    "sg:city":"Trezzano sul Naviglio",
    "sg:orig_category":"Plastic Containers For Hazardous Goods",
    "sg:phone":"+39 02 484431",
    "sg:postcode":"20090",
    "sg:province":"Milano",
    "wof:name":"Eurovetrocap Srl",
    "wof:placetype":"venue"
},
  "geometry": {"coordinates":[9.0450935364,45.4288864136],"type":"Point"}
}