{
  "type": "Feature",
  "properties": {
    "addr:full":"8, Via Barberinese 50013 Campi Bisenzio Campi Bisenzio Firenze 50013",
    "addr:postcode":"50013;50013",
    "addr:street":"Via Barberinese;Bisenzio",
    "iso:country":"IT",
    "sg:address":"8, Via Barberinese 50013 Campi Bisenzio",
    "sg:city":"Campi Bisenzio",
    "sg:classifiers":[
        {
            "category":"Shopping",
            "subcategory":"Crafts & Fabrics",
            "type":"Retail Goods"
        }
    ],
    "sg:phone":"+39 055 898 5944",
    "sg:postcode":"50013",
    "sg:province":"Firenze",
    "wof:name":"Laneco (s.p.a.)",
    "wof:placetype":"venue"
},
  "geometry": {"coordinates":[11.1292610168,43.8278388977],"type":"Point"}
}