{
  "type": "Feature",
  "properties": {
    "addr:full":"14100 Asti Asti Asti 14100",
    "addr:postcode":"14100;14100",
    "iso:country":"IT",
    "sg:address":"14100 Asti",
    "sg:city":"Asti",
    "sg:orig_category":"Petroli, Gas E Combustibili",
    "sg:phone":"+39 0141 556351",
    "sg:postcode":"14100",
    "sg:province":"Asti",
    "wof:name":"Balda Giuseppe",
    "wof:placetype":"venue"
},
  "geometry": {"coordinates":[8.1962137222,44.8998146057],"type":"Point"}
}