{
  "type": "Feature",
  "properties": {
    "addr:full":"82030 Ponte Ponte Benevento 82030",
    "addr:postcode":"82030;82030",
    "iso:country":"IT",
    "sg:address":"82030 Ponte",
    "sg:city":"Ponte",
    "sg:orig_category":"Prodotti Chimici Di Base",
    "sg:phone":"+39 0571 497108",
    "sg:postcode":"82030",
    "sg:province":"Benevento",
    "sg:website":"http://www.riverchimica.it",
    "wof:name":"River Chimica Spa",
    "wof:placetype":"venue"
},
  "geometry": {"coordinates":[14.6935396194,41.213973999],"type":"Point"}
}