{
  "type": "Feature",
  "properties": {
    "addr:full":"00192 Roma Roma Roma 00192",
    "addr:postcode":"00192;00192",
    "iso:country":"IT",
    "sg:address":"00192 Roma",
    "sg:city":"Roma",
    "sg:orig_category":"Servizi Per Lo Sport E Il Tempo Libero. Servizi Al Turismo",
    "sg:phone":"+39 06 321 5102",
    "sg:postcode":"00192",
    "sg:province":"Roma",
    "wof:name":"Iraci Srl",
    "wof:placetype":"venue"
},
  "geometry": {"coordinates":[12.465292,41.908005],"type":"Point"}
}