{
  "type": "Feature",
  "properties": {
    "iso:country":"IT",
    "sg:address":"20123 Milano",
    "sg:city":"Milano",
    "sg:orig_category":"Associazioni Ed Organismi Di Interesse Pubblico",
    "sg:phone":"+39 02 8646 4641",
    "sg:postcode":"20123",
    "sg:province":"Milano",
    "wof:name":"Mariponave",
    "wof:placetype":"venue"
},
  "geometry": {"coordinates":[9.183168,45.461914],"type":"Point"}
}