{
  "type": "Feature",
  "properties": {
    "iso:country":"IT",
    "sg:address":"14, Via Vecchia Fornace 24050 Bariano",
    "sg:city":"Bariano",
    "sg:classifiers":[
        {
            "category":"Utilities",
            "subcategory":"Electric",
            "type":"Services"
        }
    ],
    "sg:phone":"+39 036 395 7920",
    "sg:postcode":"24050",
    "sg:province":"Bergamo",
    "sg:tags":[
        "component",
        "electronic"
    ],
    "wof:name":"Ferri Giuseppina",
    "wof:placetype":"venue"
},
  "geometry": {"coordinates":[9.701587,45.523159],"type":"Point"}
}