{
  "type": "Feature",
  "properties": {
    "addr:full":"36061 Bassano Del Grappa Bassano del Grappa Vicenza 36061",
    "addr:postcode":"36061;36061",
    "iso:country":"IT",
    "sg:address":"36061 Bassano Del Grappa",
    "sg:city":"Bassano del Grappa",
    "sg:orig_category":"Materiali E Componenti Elettrotecnici",
    "sg:phone":"+39 0424 227256",
    "sg:postcode":"36061",
    "sg:province":"Vicenza",
    "wof:name":"Scramoncin Ernesto",
    "wof:placetype":"venue"
},
  "geometry": {"coordinates":[11.73493,45.760593],"type":"Point"}
}