{
  "type": "Feature",
  "properties": {
    "addr:full":"84122 Salerno Salerno Salerno 84122",
    "addr:postcode":"84122;84122",
    "iso:country":"IT",
    "sg:address":"84122 Salerno",
    "sg:city":"Salerno",
    "sg:orig_category":"Fotoriproduttori E Fotocopiatrici",
    "sg:phone":"+39 089 220773",
    "sg:postcode":"84122",
    "sg:province":"Salerno",
    "wof:name":"Battipaglia Antonio",
    "wof:placetype":"venue"
},
  "geometry": {"coordinates":[14.7647504807,40.6764335632],"type":"Point"}
}