{
  "type": "Feature",
  "properties": {
    "addr:full":"Via Seradello 237/f 25068 Sarezzo Sarezzo Brescia 25068",
    "addr:housenumber":"237 / f",
    "addr:postcode":"25068;25068",
    "addr:street":"Via Seradello",
    "iso:country":"IT",
    "sg:address":"Via Seradello 237/f 25068 Sarezzo",
    "sg:city":"Sarezzo",
    "sg:classifiers":[
        {
            "category":"Home & Garden",
            "subcategory":"Hardware",
            "type":"Retail Goods"
        }
    ],
    "sg:phone":"+39 030 832979",
    "sg:postcode":"25068",
    "sg:province":"Brescia",
    "sg:tags":[
        "small",
        "ironware",
        "item"
    ],
    "sg:website":"www.sanzogni.it",
    "wof:name":"Luigi Sanzogni & C. Snc",
    "wof:placetype":"venue"
},
  "geometry": {"coordinates":[10.222958,45.539829],"type":"Point"}
}