{
  "type": "Feature",
  "properties": {
    "addr:full":"3, Via Dei Cardi 00040 Ariccia Ariccia Roma 00040",
    "addr:postcode":"00040;roma 00040",
    "addr:street":"Via Dei Cardi",
    "iso:country":"IT",
    "sg:address":"3, Via Dei Cardi 00040 Ariccia",
    "sg:city":"Ariccia",
    "sg:classifiers":[
        {
            "category":"Communications",
            "subcategory":"Television Station",
            "type":"Services"
        }
    ],
    "sg:phone":"+39 39069340221",
    "sg:postcode":"00040",
    "sg:province":"Roma",
    "sg:tags":[
        "equipment",
        "optical",
        "instrument"
    ],
    "wof:name":"Work Team S.r.l.",
    "wof:placetype":"venue"
},
  "geometry": {"coordinates":[12.636999,41.710762],"type":"Point"}
}