{
  "type": "Feature",
  "properties": {
    "addr:full":"Via Ponte Alla; Florence; 50144 Firenze 50144",
    "addr:postcode":"50144;50144",
    "addr:street":"Via Ponte Alla Florence",
    "iso:country":"IT",
    "sg:address":"Via Ponte Alla; Florence; 50144",
    "sg:classifiers":[
        {
            "category":"Banks & Credit Unions",
            "subcategory":"Bank",
            "type":"Services"
        }
    ],
    "sg:phone":"+39 055 333621",
    "sg:postcode":"50144",
    "sg:province":"Firenze",
    "wof:name":"Credito Artigiano Spa",
    "wof:placetype":"venue"
},
  "geometry": {"coordinates":[11.234602,43.77507],"type":"Point"}
}