{
  "type": "Feature",
  "properties": {
    "iso:country":"IT",
    "sg:address":"09128 Cagliari",
    "sg:city":"Cagliari",
    "sg:orig_category":"Zootecnia E Pesca, Allevamento Piccoli Animali. Animali Domestici",
    "sg:phone":"+39 070 497051",
    "sg:postcode":"09128",
    "sg:province":"Cagliari",
    "wof:name":"L'acquario Tropicale Di Pani Amedeo Nicola",
    "wof:placetype":"venue"
},
  "geometry": {"coordinates":[9.128325,39.22216],"type":"Point"}
}