{
  "type": "Feature",
  "properties": {
    "iso:country":"IT",
    "sg:address":"24060 Rogno",
    "sg:city":"Rogno",
    "sg:orig_category":"Tempo Libero - Articoli E Forniture. Automobili E Mezzi Di Trasporto",
    "sg:phone":"+39 035 977271",
    "sg:postcode":"24060",
    "sg:province":"Bergamo",
    "wof:name":"Raggianti Battista",
    "wof:placetype":"venue"
},
  "geometry": {"coordinates":[9.730435,45.716705],"type":"Point"}
}