{
  "type": "Feature",
  "properties": {
    "addr:full":"42100 Reggio Emilia Reggio Nell'Emilia 42100",
    "addr:postcode":"42100;42100",
    "iso:country":"IT",
    "sg:address":"42100 Reggio Emilia",
    "sg:orig_category":"Arredi Ed Attrezzature Per Uffici",
    "sg:phone":"+39 0522 306501",
    "sg:postcode":"42100",
    "sg:province":"Reggio Nell'Emilia",
    "wof:name":"Afrografica S.r.l.",
    "wof:placetype":"venue"
},
  "geometry": {"coordinates":[10.617229,44.71236],"type":"Point"}
}