{
  "type": "Feature",
  "properties": {
    "iso:country":"IT",
    "sg:address":"33019 Tricesimo",
    "sg:city":"Tricesimo",
    "sg:orig_category":"Orologi Di Controllo E Sistemi Di Rilevazione Presenze",
    "sg:phone":"+39 0432 854385",
    "sg:postcode":"33019",
    "sg:province":"Udine",
    "wof:name":"Emmegi Di Mansutti Gianpietro",
    "wof:placetype":"venue"
},
  "geometry": {"coordinates":[13.220475,46.146439],"type":"Point"}
}