{
  "type": "Feature",
  "properties": {
    "iso:country":"IT",
    "sg:address":"43100 Parma",
    "sg:city":"Parma",
    "sg:classifiers":[
        {
            "category":"Retail",
            "subcategory":"Storage",
            "type":"Services"
        }
    ],
    "sg:phone":"+39 0521 771428",
    "sg:postcode":"43100",
    "sg:province":"Parma",
    "sg:tags":[
        "equipment",
        "handling",
        "system"
    ],
    "sg:website":"http://www.nicolialessandro.it",
    "wof:name":"Nicoli Alessandro Srl",
    "wof:placetype":"venue"
},
  "geometry": {"coordinates":[10.32296,44.7756],"type":"Point"}
}