{
  "type": "Feature",
  "properties": {
    "addr:full":"Via Fermi 8 20019 Settimo Milanese Settimo Milanese Milano 20019",
    "addr:housenumber":"8",
    "addr:postcode":"20019;20019",
    "addr:street":"Via Fermi",
    "iso:country":"IT",
    "sg:address":"Via Fermi 8 20019 Settimo Milanese",
    "sg:city":"Settimo Milanese",
    "sg:classifiers":[
        {
            "category":"Communications",
            "subcategory":"Film & Video Production",
            "type":"Services"
        }
    ],
    "sg:phone":"+39 02 328 7660",
    "sg:postcode":"20019",
    "sg:province":"Milano",
    "sg:tags":[
        "projector"
    ],
    "sg:website":"www.prevost.it",
    "wof:name":"Prevost Srl",
    "wof:placetype":"venue"
},
  "geometry": {"coordinates":[9.0753154755,45.4738464355],"type":"Point"}
}