{
  "type": "Feature",
  "properties": {
    "iso:country":"IT",
    "sg:address":"20064 Gorgonzola",
    "sg:city":"Gorgonzola",
    "sg:orig_category":"Macchine, Impianti Ed Attrezzature Industria Chimica. Attrezzature E Forniture Per Officine Riparazione E Servizi Ausiliari",
    "sg:phone":"+39 02 9530 1003",
    "sg:postcode":"20064",
    "sg:province":"Milano",
    "sg:website":"http://www.coralengineering.it",
    "wof:name":"Coral Engineering Srl",
    "wof:placetype":"venue"
},
  "geometry": {"coordinates":[9.084134,45.452396],"type":"Point"}
}