{
  "type": "Feature",
  "properties": {
    "iso:country":"IT",
    "sg:address":"7, Via Borea Giovanni 18038 Sanremo",
    "sg:classifiers":[
        {
            "category":"Professional",
            "subcategory":"Engineering",
            "type":"Services"
        }
    ],
    "sg:phone":"+39 0184 500632",
    "sg:postcode":"18038",
    "sg:province":"Imperia",
    "sg:tags":[
        "machine",
        "-",
        "mechanical"
    ],
    "wof:name":"Blasetta",
    "wof:placetype":"venue"
},
  "geometry": {"coordinates":[8.031564,43.887894],"type":"Point"}
}