{
  "type": "Feature",
  "properties": {
    "iso:country":"IT",
    "sg:address":"Via Rovano 25, 64023 Mosciano Sant'angelo, Te",
    "sg:classifiers":[
        {
            "category":"Banks & Credit Unions",
            "subcategory":"Bank",
            "type":"Services"
        }
    ],
    "sg:postcode":"64023",
    "sg:province":"Teramo",
    "wof:name":"Banca Di Credito Cooeprativo Val Tordino Mosciano Sant'angelo Artigiana Val Tordino",
    "wof:placetype":"venue"
},
  "geometry": {"coordinates":[13.904581,42.71497],"type":"Point"}
}