{
  "type": "Feature",
  "properties": {
    "iso:country":"IT",
    "sg:address":"Via Vittorio Veneto 20 24060 Rogno",
    "sg:city":"Rogno",
    "sg:classifiers":[
        {
            "category":"Shopping",
            "subcategory":"Clothing, Apparel, & Fashions",
            "type":"Retail Goods"
        }
    ],
    "sg:phone":"+39 035 967104",
    "sg:postcode":"24060",
    "sg:province":"Bergamo",
    "sg:tags":[
        "sportswear"
    ],
    "sg:website":"www.daritex.it",
    "wof:name":"Daritex Sport Wear Srl",
    "wof:placetype":"venue"
},
  "geometry": {"coordinates":[10.143755,45.863033],"type":"Point"}
}