{
  "type": "Feature",
  "properties": {
    "addr:full":"20125 Milano Milano Milano 20125",
    "addr:postcode":"20125;20125",
    "iso:country":"IT",
    "sg:address":"20125 Milano",
    "sg:city":"Milano",
    "sg:classifiers":[
        {
            "category":"Health Services",
            "subcategory":"Health Practitioner",
            "type":"Services"
        }
    ],
    "sg:phone":"+39 02 6707 2039",
    "sg:postcode":"20125",
    "sg:province":"Milano",
    "sg:tags":[
        "medici"
    ],
    "wof:name":"Sala Francesco",
    "wof:placetype":"venue"
},
  "geometry": {"coordinates":[9.2009601593,45.4877738953],"type":"Point"}
}