{
  "type": "Feature",
  "properties": {
    "iso:country":"IT",
    "sg:address":"80137 Napoli",
    "sg:city":"Napoli",
    "sg:orig_category":"Banche E Servizi Finanziari",
    "sg:phone":"+39 081 599 3075",
    "sg:postcode":"80137",
    "sg:province":"Napoli",
    "wof:name":"I.d.s. Italy Data System Srl Servizi All'impresa",
    "wof:placetype":"venue"
},
  "geometry": {"coordinates":[14.261397,40.862652],"type":"Point"}
}