{
  "type": "Feature",
  "properties": {
    "iso:country":"IT",
    "sg:address":"12030 Casalgrasso",
    "sg:city":"Casalgrasso",
    "sg:orig_category":"Macchine, Impianti Ed Attrezzature Per Agricoltura E Zootecnia",
    "sg:phone":"+39 011 975709",
    "sg:postcode":"12030",
    "sg:province":"Cuneo",
    "wof:name":"Saglia Mario",
    "wof:placetype":"venue"
},
  "geometry": {"coordinates":[7.632765,44.824394],"type":"Point"}
}