{
  "type": "Feature",
  "properties": {
    "iso:country":"IT",
    "sg:address":"41100 Modena",
    "sg:city":"Modena",
    "sg:orig_category":"Studi E Consulenze Tecniche E Industriali. Consulenze Tecniche, Amministrative E Perizie. Servizi Ausiliari Di Analisi, Controllo E Ricerca",
    "sg:phone":"+39 059 393757",
    "sg:postcode":"41100",
    "sg:province":"Modena",
    "wof:name":"Ing. Dr. Chinni Daniele - Studio Tecnico",
    "wof:placetype":"venue"
},
  "geometry": {"coordinates":[10.926041,44.635544],"type":"Point"}
}