{
  "type": "Feature",
  "properties": {
    "addr:full":"37136 Verona Verona Verona 37136",
    "addr:postcode":"37136;37136",
    "iso:country":"IT",
    "sg:address":"37136 Verona",
    "sg:city":"Verona",
    "sg:orig_category":"Servizi Per Aziende, Manifestazioni E Supporto Agli Scambi Commerciali",
    "sg:phone":"+39 045 862 1573",
    "sg:postcode":"37136",
    "sg:province":"Verona",
    "wof:name":"Promotion Makers Di Carr Evelyn",
    "wof:placetype":"venue"
},
  "geometry": {"coordinates":[10.959051,45.407234],"type":"Point"}
}