{
  "type": "Feature",
  "properties": {
    "addr:full":"4, Via Europa 20085 Locate Di Triulzi Locate di Triulzi Milano 20085",
    "addr:postcode":"20085;20085",
    "addr:street":"Via Europa",
    "iso:country":"IT",
    "sg:address":"4, Via Europa 20085 Locate Di Triulzi",
    "sg:city":"Locate di Triulzi",
    "sg:orig_category":"Miscellaneous Products",
    "sg:phone":"+39 02 9073 0227",
    "sg:postcode":"20085",
    "sg:province":"Milano",
    "wof:name":"General Fix (s.r.l.)",
    "wof:placetype":"venue"
},
  "geometry": {"coordinates":[9.2744369507,45.4132919312],"type":"Point"}
}