{
  "type": "Feature",
  "properties": {
    "iso:country":"IT",
    "sg:address":"90, Via Colombo Cristoforo 21054 Fagnano Olona",
    "sg:city":"Fagnano Olona",
    "sg:classifiers":[
        {
            "category":"Shopping",
            "subcategory":"Crafts & Fabrics",
            "type":"Retail Goods"
        }
    ],
    "sg:phone":"+39 0331 614057",
    "sg:postcode":"21054",
    "sg:province":"Varese",
    "wof:name":"Anteprima Srl",
    "wof:placetype":"venue"
},
  "geometry": {"coordinates":[8.8263845444,45.8176040649],"type":"Point"}
}