{
  "type": "Feature",
  "properties": {
    "addr:full":"109, Via Lgadda V Alpini 23037 Tirano Tirano Sondrio 23037",
    "addr:housenumber":"109",
    "addr:postcode":"23037;23037",
    "addr:street":"Via Lgadda V Alpini",
    "iso:country":"IT",
    "sg:address":"109, Via Lgadda V Alpini 23037 Tirano",
    "sg:city":"Tirano",
    "sg:classifiers":[
        {
            "category":"Shopping",
            "subcategory":"Crafts & Fabrics",
            "type":"Retail Goods"
        }
    ],
    "sg:phone":"+39 0342 710624",
    "sg:postcode":"23037",
    "sg:province":"Sondrio",
    "wof:name":"Si Lin Tsi S.r.l.",
    "wof:placetype":"venue"
},
  "geometry": {"coordinates":[9.8693332672,46.1712608337],"type":"Point"}
}