{
  "type": "Feature",
  "properties": {
    "iso:country":"IT",
    "sg:address":"00183 Roma",
    "sg:city":"Roma",
    "sg:orig_category":"Abbigliamento Intimo, Calze E Costumi Da Bagno",
    "sg:phone":"+39 06 7720 1874",
    "sg:postcode":"00183",
    "sg:province":"Roma",
    "wof:name":"Barba Simona",
    "wof:placetype":"venue"
},
  "geometry": {"coordinates":[12.578022,41.80909],"type":"Point"}
}