{
  "type": "Feature",
  "properties": {
    "addr:full":"22060 Cucciago Cucciago Como 22060",
    "addr:postcode":"22060;22060",
    "iso:country":"IT",
    "sg:address":"22060 Cucciago",
    "sg:city":"Cucciago",
    "sg:orig_category":"Fotoincisioni",
    "sg:phone":"+39 031 725173",
    "sg:postcode":"22060",
    "sg:province":"Como",
    "wof:name":"Foto Green Di R. Salamoni & C. Snc",
    "wof:placetype":"venue"
},
  "geometry": {"coordinates":[9.1086149216,45.7408180237],"type":"Point"}
}