{
  "type": "Feature",
  "properties": {
    "iso:country":"IT",
    "sg:address":"28100 Novara",
    "sg:city":"Novara",
    "sg:classifiers":[
        {
            "category":"Health Services",
            "subcategory":"Health Practitioner",
            "type":"Services"
        }
    ],
    "sg:phone":"+39 0321 696353",
    "sg:postcode":"28100",
    "sg:province":"Novara",
    "sg:tags":[
        "medici"
    ],
    "wof:name":"De Regibus Gianluca",
    "wof:placetype":"venue"
},
  "geometry": {"coordinates":[8.641378,45.445923],"type":"Point"}
}