{
  "type": "Feature",
  "properties": {
    "iso:country":"IT",
    "sg:address":"Via Crispi Francesco 92 80121 Napoli",
    "sg:city":"Napoli",
    "sg:classifiers":[
        {
            "category":"Wholesale",
            "subcategory":"Fruits & Vegetables",
            "type":"Manufacturing & Wholesale Goods"
        }
    ],
    "sg:phone":"+39 081 680092",
    "sg:postcode":"80121",
    "sg:province":"Napoli",
    "sg:tags":[
        "product",
        "cereal"
    ],
    "wof:name":"Rocco Giuseppe E Figli S.p.a.",
    "wof:placetype":"venue"
},
  "geometry": {"coordinates":[14.216715,40.904507],"type":"Point"}
}