{
  "type": "Feature",
  "properties": {
    "iso:country":"IT",
    "sg:address":"25125 Brescia",
    "sg:city":"Brescia",
    "sg:orig_category":"Stampaggio Materie Plastiche",
    "sg:phone":"+39 030 353 1526",
    "sg:postcode":"25125",
    "sg:province":"Brescia",
    "sg:website":"http://www.abantonelli.com",
    "wof:name":"Ab Di Antonelli Battista Srl",
    "wof:placetype":"venue"
},
  "geometry": {"coordinates":[10.194551,45.523392],"type":"Point"}
}