{
  "type": "Feature",
  "properties": {
    "iso:country":"IT",
    "sg:address":"3, Via Tartano 23020 Montagna In Valtellina",
    "sg:city":"Montagna in Valtellina",
    "sg:classifiers":[
        {
            "category":"Manufacturing",
            "subcategory":"Wood Products",
            "type":"Manufacturing & Wholesale Goods"
        }
    ],
    "sg:phone":"+39 0342 214348",
    "sg:postcode":"23020",
    "sg:province":"Sondrio",
    "sg:tags":[
        "furniture"
    ],
    "wof:name":"Berniga",
    "wof:placetype":"venue"
},
  "geometry": {"coordinates":[9.908845,46.169903],"type":"Point"}
}