{
  "type": "Feature",
  "properties": {
    "iso:country":"IT",
    "sg:address":"70027 Palo Del Colle",
    "sg:city":"Palo del Colle",
    "sg:orig_category":"Manufacturers: Prefabbricati",
    "sg:phone":"+39 080 624503",
    "sg:postcode":"70027",
    "sg:province":"Bari",
    "sg:website":"http://www.lacriola.it",
    "wof:name":"Lacriola Carlo Srl",
    "wof:placetype":"venue"
},
  "geometry": {"coordinates":[16.664501,41.045094],"type":"Point"}
}