{
  "type": "Feature",
  "properties": {
    "iso:country":"IT",
    "sg:address":"95045 Misterbianco",
    "sg:city":"Misterbianco",
    "sg:orig_category":"Ecologia - Studi Consulenza E Servizi",
    "sg:phone":"+39 095 461799",
    "sg:postcode":"95045",
    "sg:province":"Catania",
    "wof:name":"Guglielmo Giuseppe",
    "wof:placetype":"venue"
},
  "geometry": {"coordinates":[15.008554,37.517647],"type":"Point"}
}