{
  "type": "Feature",
  "properties": {
    "addr:full":"7, Via Asi 03013 Ferentino Ferentino Frosinone 03013",
    "addr:postcode":"03013;03013",
    "addr:street":"Via Asi",
    "iso:country":"IT",
    "sg:address":"7, Via Asi 03013 Ferentino",
    "sg:city":"Ferentino",
    "sg:classifiers":[
        {
            "category":"Food & Beverages",
            "subcategory":"Dairy",
            "type":"Retail Goods"
        }
    ],
    "sg:phone":"+39 0775 224484",
    "sg:postcode":"03013",
    "sg:province":"Frosinone",
    "sg:tags":[
        "product"
    ],
    "wof:name":"Pomella S.p.a.",
    "wof:placetype":"venue"
},
  "geometry": {"coordinates":[13.287987,41.615578],"type":"Point"}
}