{
  "type": "Feature",
  "properties": {
    "iso:country":"IT",
    "sg:address":"10040 Almese",
    "sg:city":"Almese",
    "sg:orig_category":"Utensili Meccanici E Materiali",
    "sg:phone":"+39 011 935 0732",
    "sg:postcode":"10040",
    "sg:province":"Torino",
    "wof:name":"Landra Srl",
    "wof:placetype":"venue"
},
  "geometry": {"coordinates":[7.903585,45.196785],"type":"Point"}
}