{
  "type": "Feature",
  "properties": {
    "iso:country":"IT",
    "sg:address":"20133 Milano",
    "sg:city":"Milano",
    "sg:orig_category":"Gioielleria, Oreficeria E Argenteria. Shopping",
    "sg:phone":"+39 02 713493",
    "sg:postcode":"20133",
    "sg:province":"Milano",
    "wof:name":"Lina Di Bakir Hussein",
    "wof:placetype":"venue"
},
  "geometry": {"coordinates":[9.23036,45.473915],"type":"Point"}
}