{
  "type": "Feature",
  "properties": {
    "iso:country":"IT",
    "sg:address":"30020 Marcon",
    "sg:city":"Marcon",
    "sg:orig_category":"Servizi Per Lo Sport E Il Tempo Libero. Alberghi E Strutture Extra Alberghiere",
    "sg:phone":"+39 041 595 2242",
    "sg:postcode":"30020",
    "sg:province":"Venezia",
    "sg:website":"http://www.aemmeimmobiliare.it",
    "wof:name":"Aemme Immobiliare Snc",
    "wof:placetype":"venue"
},
  "geometry": {"coordinates":[12.298753,45.558979],"type":"Point"}
}