{
  "type": "Feature",
  "properties": {
    "iso:country":"IT",
    "sg:address":"36050 Zermeghedo",
    "sg:city":"Zermeghedo",
    "sg:classifiers":[
        {
            "category":"Retail",
            "subcategory":"Event Space",
            "type":"Services"
        }
    ],
    "sg:phone":"+39 0444 686165",
    "sg:postcode":"36050",
    "sg:province":"Vicenza",
    "sg:tags":[
        "leather",
        "clothing",
        "goods",
        "work"
    ],
    "wof:name":"B.c.r. Di Rossetto Giandomenico & C. Snc",
    "wof:placetype":"venue"
},
  "geometry": {"coordinates":[11.370646,45.475952],"type":"Point"}
}