{
  "type": "Feature",
  "properties": {
    "iso:country":"IT",
    "sg:address":"25, Viale Dell' Industria 32040 Lozzo Di Cadore",
    "sg:city":"Lozzo di Cadore",
    "sg:classifiers":[
        {
            "category":"Manufacturing",
            "subcategory":"Metals",
            "type":"Manufacturing & Wholesale Goods"
        }
    ],
    "sg:phone":"+39 39043576571",
    "sg:postcode":"32040",
    "sg:province":"Belluno",
    "sg:tags":[
        "processing"
    ],
    "wof:name":"Colmet (s.r.l.)",
    "wof:placetype":"venue"
},
  "geometry": {"coordinates":[12.4355955124,46.4740371704],"type":"Point"}
}