{
  "type": "Feature",
  "properties": {
    "iso:country":"IT",
    "sg:address":"Via Napoli 167; Vairano Patenora",
    "sg:classifiers":[
        {
            "category":"Banks & Credit Unions",
            "subcategory":"Bank",
            "type":"Services"
        }
    ],
    "sg:phone":"+39 0823 644861",
    "wof:name":"Banca Di Roma",
    "wof:placetype":"venue"
},
  "geometry": {"coordinates":[14.110134,41.312016],"type":"Point"}
}