{
  "type": "Feature",
  "properties": {
    "addr:full":"2, V. I Maggio 20050 Ronco Briantino Ronco Briantino Milano 20050",
    "addr:housenumber":"2",
    "addr:postcode":"20050;20050",
    "addr:street":"V. I Maggio",
    "iso:country":"IT",
    "sg:address":"2, V. I Maggio 20050 Ronco Briantino",
    "sg:city":"Ronco Briantino",
    "sg:classifiers":[
        {
            "category":"Professional",
            "subcategory":"Printing & Photocopies",
            "type":"Services"
        }
    ],
    "sg:phone":"+39 039 607 9049",
    "sg:postcode":"20050",
    "sg:province":"Milano",
    "sg:website":"http://www.paginegialle.it/labriantina",
    "wof:name":"La Briantina Srl",
    "wof:placetype":"venue"
},
  "geometry": {"coordinates":[9.1881408691,45.4636878967],"type":"Point"}
}