{
  "type": "Feature",
  "properties": {
    "iso:country":"IT",
    "sg:address":"41100 Modena",
    "sg:city":"Modena",
    "sg:orig_category":"Servizi E Lavori Per Ecologia E Smaltimento Rifiuti. Servizi Ausiliari Di Sorveglianza, Manutenzione E Pulizia",
    "sg:phone":"+39 059 355041",
    "sg:postcode":"41100",
    "sg:province":"Modena",
    "sg:website":"http://www.trashbusters.it",
    "wof:name":"Consorzio Trash Busters",
    "wof:placetype":"venue"
},
  "geometry": {"coordinates":[10.937454,44.553528],"type":"Point"}
}