{
  "type": "Feature",
  "properties": {
    "iso:country":"IT",
    "sg:address":"00058 Santa Marinella",
    "sg:city":"Santa Marinella",
    "sg:orig_category":"Gioielleria, Oreficeria E Argenteria",
    "sg:phone":"+39 0766 518028",
    "sg:postcode":"00058",
    "sg:province":"Roma",
    "wof:name":"Di Giovanni Victor",
    "wof:placetype":"venue"
},
  "geometry": {"coordinates":[12.102442,41.953014],"type":"Point"}
}