{
  "type": "Feature",
  "properties": {
    "addr:full":"20090 Vimodrone Vimodrone Milano 20090",
    "addr:postcode":"20090;20090",
    "iso:country":"IT",
    "sg:address":"20090 Vimodrone",
    "sg:city":"Vimodrone",
    "sg:orig_category":"Supermercati, Grandi Magazzini E Centri Commerciali",
    "sg:phone":"+39 02 274201",
    "sg:postcode":"20090",
    "sg:province":"Milano",
    "sg:website":"http://www.unes.it",
    "wof:name":"Unes",
    "wof:placetype":"venue"
},
  "geometry": {"coordinates":[9.2852230072,45.5134925842],"type":"Point"}
}