{
  "type": "Feature",
  "properties": {
    "iso:country":"IT",
    "sg:address":"20131 Milano",
    "sg:city":"Milano",
    "sg:orig_category":"Cine-foto-ottica",
    "sg:phone":"+39 02 2940 5119",
    "sg:postcode":"20131",
    "sg:province":"Milano",
    "wof:name":"Centro Foto Cine (s.r.l.)",
    "wof:placetype":"venue"
},
  "geometry": {"coordinates":[9.215381,45.484428],"type":"Point"}
}