{
  "type": "Feature",
  "properties": {
    "addr:full":"20033 Desio Desio Milano 20033",
    "addr:postcode":"20033;20033",
    "iso:country":"IT",
    "sg:address":"20033 Desio",
    "sg:city":"Desio",
    "sg:orig_category":"Materiali Semilavorati Metallici",
    "sg:phone":"+39 036 248001",
    "sg:postcode":"20033",
    "sg:province":"Milano",
    "wof:name":"Lima Spa Lavorazione Italiana Metalli Affini",
    "wof:placetype":"venue"
},
  "geometry": {"coordinates":[9.201508,45.449837],"type":"Point"}
}