{
  "type": "Feature",
  "properties": {
    "iso:country":"IT",
    "sg:address":"Via Giulio Romano 29 20135 Milano",
    "sg:city":"Milano",
    "sg:classifiers":[
        {
            "category":"Autos & Motor Vehicles",
            "subcategory":"Boat Sales",
            "type":"Retail Goods"
        }
    ],
    "sg:phone":"+39 02 5760 9397",
    "sg:postcode":"20135",
    "sg:province":"Milano",
    "sg:tags":[
        "machine",
        "beverage",
        "vending",
        "dispensing"
    ],
    "sg:website":"www.ugolinispa.com",
    "wof:name":"Ugolini Spa",
    "wof:placetype":"venue"
},
  "geometry": {"coordinates":[9.202,45.448803],"type":"Point"}
}