{
  "type": "Feature",
  "properties": {
    "iso:country":"IT",
    "sg:address":"00159 Roma",
    "sg:city":"Roma",
    "sg:orig_category":"Servizi Culturali E Per Lo Spettacolo. Servizi Per Lo Sport E Il Tempo Libero. Servizi Per Aziende, Manifestazioni E Supporto Agli Scambi Commerciali",
    "sg:phone":"+39 06 439 1764",
    "sg:postcode":"00159",
    "sg:province":"Roma",
    "wof:name":"Happy Club",
    "wof:placetype":"venue"
},
  "geometry": {"coordinates":[12.538895,41.906906],"type":"Point"}
}