{
  "type": "Feature",
  "properties": {
    "iso:country":"IT",
    "sg:address":"31014 Colle Umberto",
    "sg:city":"Colle Umberto",
    "sg:classifiers":[
        {
            "category":"Wholesale",
            "subcategory":"Home Furnishings",
            "type":"Manufacturing & Wholesale Goods"
        }
    ],
    "sg:phone":"+39 0438 430505",
    "sg:postcode":"31014",
    "sg:province":"Treviso",
    "sg:tags":[
        "household",
        "appliance",
        "furnishings",
        "appliances",
        "kitchen"
    ],
    "sg:website":"http://www.samassrl.it",
    "wof:name":"Sa.ma.s. Srl",
    "wof:placetype":"venue"
},
  "geometry": {"coordinates":[12.3488111496,45.9475440979],"type":"Point"}
}