{
  "type": "Feature",
  "properties": {
    "iso:country":"IT",
    "sg:address":"Corso Del Popolo 25 86019 Vinchiaturo",
    "sg:city":"Vinchiaturo",
    "sg:classifiers":[
        {
            "category":"Food & Beverages",
            "subcategory":"Cheese",
            "type":"Retail Goods"
        }
    ],
    "sg:phone":"+39 0874 34157",
    "sg:postcode":"86019",
    "sg:province":"Campobasso",
    "sg:tags":[
        "cream"
    ],
    "sg:website":"www.barone.it",
    "wof:name":"Caseificio Molisano L. Barone S.n.c.",
    "wof:placetype":"venue"
},
  "geometry": {"coordinates":[14.589615,41.4939],"type":"Point"}
}