{
  "type": "Feature",
  "properties": {
    "addr:full":"1, Viale Unione Sovietica 44022 Comacchio Comacchio Ferrara 44022",
    "addr:postcode":"44022;44022",
    "addr:street":"Viale Unione Sovietica",
    "iso:country":"IT",
    "sg:address":"1, Viale Unione Sovietica 44022 Comacchio",
    "sg:city":"Comacchio",
    "sg:classifiers":[
        {
            "category":"Travel",
            "subcategory":"Travel Agent",
            "type":"Entertainment"
        }
    ],
    "sg:phone":"+39 0533 379276",
    "sg:postcode":"44022",
    "sg:province":"Ferrara",
    "sg:tags":[
        "business"
    ],
    "wof:name":"Grand Hotel Le Nazioni",
    "wof:placetype":"venue"
},
  "geometry": {"coordinates":[12.243075,44.749733],"type":"Point"}
}