{
  "type": "Feature",
  "properties": {
    "addr:full":"15033 Casale Monferrato Casale Monferrato Alessandria 15033",
    "addr:postcode":"15033;15033",
    "iso:country":"IT",
    "sg:address":"15033 Casale Monferrato",
    "sg:city":"Casale Monferrato",
    "sg:orig_category":"Imprese Di Costruzioni Civili Ed Industriali",
    "sg:phone":"+39 0142 562215",
    "sg:postcode":"15033",
    "sg:province":"Alessandria",
    "wof:name":"Pinoli Pierangelo",
    "wof:placetype":"venue"
},
  "geometry": {"coordinates":[8.443418,45.145699],"type":"Point"}
}