{
  "type": "Feature",
  "properties": {
    "iso:country":"IT",
    "sg:address":"66/3, Via Di Vittorio 41011 Campogalliano",
    "sg:city":"Campogalliano",
    "sg:classifiers":[
        {
            "category":"Shopping",
            "subcategory":"Clothing, Apparel, & Fashions",
            "type":"Retail Goods"
        }
    ],
    "sg:phone":"+39 39059527041",
    "sg:postcode":"41011",
    "sg:province":"Modena",
    "sg:tags":[
        "clothes"
    ],
    "wof:name":"Maglificio Rossetti S.r.l.",
    "wof:placetype":"venue"
},
  "geometry": {"coordinates":[10.847208,44.690956],"type":"Point"}
}