{
  "type": "Feature",
  "properties": {
    "iso:country":"IT",
    "sg:address":"12100 Cuneo",
    "sg:city":"Cuneo",
    "sg:orig_category":"Campeggio. Automobili E Mezzi Di Trasporto",
    "sg:phone":"+39 0171 411747",
    "sg:postcode":"12100",
    "sg:province":"Cuneo",
    "wof:name":"Top Car",
    "wof:placetype":"venue"
},
  "geometry": {"coordinates":[7.541013,44.427567],"type":"Point"}
}