{
  "type": "Feature",
  "properties": {
    "iso:country":"IT",
    "sg:address":"20146 Milano",
    "sg:city":"Milano",
    "sg:classifiers":[
        {
            "category":"Wholesale",
            "subcategory":"Chemicals & Plastics",
            "type":"Manufacturing & Wholesale Goods"
        }
    ],
    "sg:phone":"+39 335 675 0549",
    "sg:postcode":"20146",
    "sg:province":"Milano",
    "sg:tags":[
        "article",
        "product",
        "plastics"
    ],
    "wof:name":"Zeta Plastic Sas",
    "wof:placetype":"venue"
},
  "geometry": {"coordinates":[9.1542453766,45.4577102661],"type":"Point"}
}