{
  "type": "Feature",
  "properties": {
    "iso:country":"IT",
    "sg:address":"51, Via Magazzini Anteriori 48100 Ravenna",
    "sg:city":"Ravenna",
    "sg:classifiers":[
        {
            "category":"Marine",
            "type":"Transportation"
        }
    ],
    "sg:phone":"+39 0544 598511",
    "sg:postcode":"48100",
    "sg:province":"Ravenna",
    "sg:tags":[
        "transport",
        "sea"
    ],
    "wof:name":"Fiore - Casa Di Spedizioni S.r.l.",
    "wof:placetype":"venue"
},
  "geometry": {"coordinates":[12.225,44.363888],"type":"Point"}
}