{
  "type": "Feature",
  "properties": {
    "addr:full":"34, Via Crocevia 46046 Medole Medole Mantova 46046",
    "addr:postcode":"46046;46046",
    "addr:street":"Via Crocevia",
    "iso:country":"IT",
    "sg:address":"34, Via Crocevia 46046 Medole",
    "sg:city":"Medole",
    "sg:classifiers":[
        {
            "category":"Real Estate",
            "subcategory":"Surveying",
            "type":"Services"
        }
    ],
    "sg:phone":"+39 0376 898008",
    "sg:postcode":"46046",
    "sg:province":"Mantova",
    "sg:tags":[
        "equipment",
        "material",
        "good",
        "-",
        "handling"
    ],
    "wof:name":"Martini Prefabbricati S.p.a.",
    "wof:placetype":"venue"
},
  "geometry": {"coordinates":[10.534674,45.33017],"type":"Point"}
}