{
  "type": "Feature",
  "properties": {
    "iso:country":"IT",
    "sg:address":"30010 Cavallino - Treporti",
    "sg:orig_category":"Pubblica Amministrazione",
    "sg:phone":"+39 041 966533",
    "sg:postcode":"30010",
    "sg:province":"Venezia",
    "wof:name":"Forze Armate",
    "wof:placetype":"venue"
},
  "geometry": {"coordinates":[12.4728803635,45.4537353516],"type":"Point"}
}