{
  "type": "Feature",
  "properties": {
    "addr:full":"Traversa I Roma 80017 Melito Di Napoli Melito di Napoli Napoli 80017",
    "addr:postcode":"80017;80017",
    "addr:street":"Traversa I Roma",
    "iso:country":"IT",
    "sg:address":"Traversa I Roma 80017 Melito Di Napoli",
    "sg:city":"Melito di Napoli",
    "sg:classifiers":[
        {
            "category":"Shopping",
            "type":"Retail Goods"
        }
    ],
    "sg:phone":"+39 081 711 2622",
    "sg:postcode":"80017",
    "sg:province":"Napoli",
    "sg:tags":[
        "finished",
        "-",
        "metallic"
    ],
    "wof:name":"D.b.f. (s.r.l.)",
    "wof:placetype":"venue"
},
  "geometry": {"coordinates":[14.2319993973,40.9200401306],"type":"Point"}
}