{
  "type": "Feature",
  "properties": {
    "addr:full":"20032 Cormano Cormano Milano 20032",
    "addr:postcode":"20032;20032",
    "iso:country":"IT",
    "sg:address":"20032 Cormano",
    "sg:city":"Cormano",
    "sg:orig_category":"Prodotti Chimici Di Base. Forniture Per Attivita' Industriali",
    "sg:phone":"+39 02 6630 5060",
    "sg:postcode":"20032",
    "sg:province":"Milano",
    "wof:name":"Viba Spa",
    "wof:placetype":"venue"
},
  "geometry": {"coordinates":[9.1609220505,45.5351715088],"type":"Point"}
}