{
  "type": "Feature",
  "properties": {
    "iso:country":"IT",
    "sg:address":"41, Via Procaccini Giulio Cesare 20154 Milano",
    "sg:city":"Milano",
    "sg:classifiers":[
        {
            "category":"Wholesale",
            "subcategory":"Drugs",
            "type":"Manufacturing & Wholesale Goods"
        }
    ],
    "sg:phone":"+39 02 3360 1190",
    "sg:postcode":"20154",
    "sg:province":"Milano",
    "sg:tags":[
        "chemical",
        "pharmaceutical"
    ],
    "wof:name":"Combe Italia S.r.l.",
    "wof:placetype":"venue"
},
  "geometry": {"coordinates":[9.169801,45.483093],"type":"Point"}
}