{
  "type": "Feature",
  "properties": {
    "iso:country":"IT",
    "sg:address":"Via Del Chionso 3 42100 Reggio Emilia",
    "sg:classifiers":[
        {
            "category":"Building & Trades",
            "subcategory":"Construction",
            "type":"Services"
        }
    ],
    "sg:phone":"+39 0522 517499",
    "sg:postcode":"42100",
    "sg:province":"Reggio Nell'Emilia",
    "sg:tags":[
        "frame",
        "door",
        "constr"
    ],
    "sg:website":"www.vighi.com",
    "wof:name":"Vighi Srl",
    "wof:placetype":"venue"
},
  "geometry": {"coordinates":[10.64486,44.709965],"type":"Point"}
}