{
  "type": "Feature",
  "properties": {
    "iso:country":"IT",
    "sg:address":"310, Via Dell' Agricoltura 41058 Vignola",
    "sg:city":"Vignola",
    "sg:classifiers":[
        {
            "category":"Food & Beverages",
            "subcategory":"Groceries & Convenience Stores",
            "type":"Retail Goods"
        }
    ],
    "sg:phone":"+39 39059761992",
    "sg:postcode":"41058",
    "sg:province":"Modena",
    "sg:tags":[
        "product",
        "related"
    ],
    "wof:name":"G. Bellentani 1821 (s.p.a.)",
    "wof:placetype":"venue"
},
  "geometry": {"coordinates":[10.9924621582,44.5050888062],"type":"Point"}
}