{
  "type": "Feature",
  "properties": {
    "iso:country":"IT",
    "sg:address":"00151 Roma",
    "sg:city":"Roma",
    "sg:orig_category":"Apparecchiature Ed Attrezzature Meccaniche",
    "sg:phone":"+39 06 5820 1743",
    "sg:postcode":"00151",
    "sg:province":"Roma",
    "wof:name":"Societa' Rettifica Monteverde Srl",
    "wof:placetype":"venue"
},
  "geometry": {"coordinates":[12.447262,41.868275],"type":"Point"}
}