{
  "type": "Feature",
  "properties": {
    "addr:full":"09071 Abbasanta Abbasanta Oristano 09071",
    "addr:postcode":"09071;09071",
    "iso:country":"IT",
    "sg:address":"09071 Abbasanta",
    "sg:city":"Abbasanta",
    "sg:orig_category":"Musica",
    "sg:phone":"+39 0785 54721",
    "sg:postcode":"09071",
    "sg:province":"Oristano",
    "wof:name":"Carta Alessandro",
    "wof:placetype":"venue"
},
  "geometry": {"coordinates":[8.8192834854,40.1271286011],"type":"Point"}
}