{
  "type": "Feature",
  "properties": {
    "iso:country":"IT",
    "sg:address":"12050 Castagnito",
    "sg:city":"Castagnito",
    "sg:orig_category":"Bevande, Vini E Liquori",
    "sg:phone":"+39 0173 211261",
    "sg:postcode":"12050",
    "sg:province":"Cuneo",
    "sg:website":"http://www.vignaioli.it",
    "wof:name":"Associazione Vignaioli Piemontesi",
    "wof:placetype":"venue"
},
  "geometry": {"coordinates":[8.074887,44.745422],"type":"Point"}
}