{
  "type": "Feature",
  "properties": {
    "addr:full":"36077 Altavilla Vicentina Altavilla Vicentina Vicenza 36077",
    "addr:postcode":"36077;36077",
    "iso:country":"IT",
    "sg:address":"36077 Altavilla Vicentina",
    "sg:city":"Altavilla Vicentina",
    "sg:orig_category":"Acciaierie E Fonderie",
    "sg:phone":"+39 0444 371294",
    "sg:postcode":"36077",
    "sg:province":"Vicenza",
    "wof:name":"Ugine Savoie Italia S.r.l.",
    "wof:placetype":"venue"
},
  "geometry": {"coordinates":[11.469708,45.508312],"type":"Point"}
}