{
  "type": "Feature",
  "properties": {
    "iso:country":"IT",
    "sg:address":"8, Via Bergamo 26022 Castelverde",
    "sg:city":"Castelverde",
    "sg:classifiers":[
        {
            "category":"Manufacturing",
            "subcategory":"Rubber & Plastics",
            "type":"Manufacturing & Wholesale Goods"
        }
    ],
    "sg:phone":"+39 0372 428933",
    "sg:postcode":"26022",
    "sg:province":"Cremona",
    "wof:name":"Cappucciati (s.r.l.)",
    "wof:placetype":"venue"
},
  "geometry": {"coordinates":[10.0004291534,45.1838035583],"type":"Point"}
}