{
  "type": "Feature",
  "properties": {
    "iso:country":"IT",
    "sg:address":"50019 Sesto Fiorentino",
    "sg:city":"Sesto Fiorentino",
    "sg:orig_category":"Utensili Meccanici E Materiali",
    "sg:phone":"+39 055 420 5470",
    "sg:postcode":"50019",
    "sg:province":"Firenze",
    "sg:website":"http://www.inditel.com/aziende/sabar.html",
    "wof:name":"S.a.b.a.r. Snc",
    "wof:placetype":"venue"
},
  "geometry": {"coordinates":[11.174351,43.840054],"type":"Point"}
}