{
  "type": "Feature",
  "properties": {
    "iso:country":"IT",
    "sg:address":"84132 Salerno",
    "sg:city":"Salerno",
    "sg:orig_category":"Cinematografia E Radiotelevisione",
    "sg:phone":"+39 089 337509",
    "sg:postcode":"84132",
    "sg:province":"Salerno",
    "wof:name":"P. & P. Production Di Pacifico Pietro",
    "wof:placetype":"venue"
},
  "geometry": {"coordinates":[14.803123,40.658043],"type":"Point"}
}