{
  "type": "Feature",
  "properties": {
    "iso:country":"IT",
    "sg:address":"50013 Campi Bisenzio",
    "sg:city":"Campi Bisenzio",
    "sg:orig_category":"Apparecchiature E Sistemi Per Magazzinaggio E Movimentazione",
    "sg:phone":"+39 055 896 9170",
    "sg:postcode":"50013",
    "sg:province":"Firenze",
    "wof:name":"Centrogru S.r.l.",
    "wof:placetype":"venue"
},
  "geometry": {"coordinates":[11.160581,43.771709],"type":"Point"}
}