{
  "type": "Feature",
  "properties": {
    "iso:country":"IT",
    "sg:address":"Via Pra' Della Valle, 8/10 31040 Giavera Del Montello",
    "sg:city":"Giavera del Montello",
    "sg:classifiers":[
        {
            "category":"Building & Trades",
            "subcategory":"Locksmith",
            "type":"Services"
        }
    ],
    "sg:phone":"+39 0422 870215",
    "sg:postcode":"31040",
    "sg:province":"Treviso",
    "sg:tags":[
        "chimney"
    ],
    "wof:name":"M.t. S.r.l.",
    "wof:placetype":"venue"
},
  "geometry": {"coordinates":[12.19601,45.771214],"type":"Point"}
}