{
  "type": "Feature",
  "properties": {
    "addr:full":"12, Via Per Cadrezzate 21020 Brebbia Brebbia Varese 21020",
    "addr:postcode":"21020;21020",
    "addr:street":"Via Per Cadrezzate",
    "iso:country":"IT",
    "sg:address":"12, Via Per Cadrezzate 21020 Brebbia",
    "sg:city":"Brebbia",
    "sg:classifiers":[
        {
            "category":"Shopping",
            "subcategory":"Crafts & Fabrics",
            "type":"Retail Goods"
        }
    ],
    "sg:phone":"+39 0332 771508",
    "sg:postcode":"21020",
    "sg:province":"Varese",
    "wof:name":"Zanotex S.r.l.",
    "wof:placetype":"venue"
},
  "geometry": {"coordinates":[8.645658493,45.8208084106],"type":"Point"}
}