{
  "type": "Feature",
  "properties": {
    "iso:country":"IT",
    "sg:address":"33057 Palmanova",
    "sg:city":"Palmanova",
    "sg:orig_category":"Arredo Cucina Ed Elettrodomestici. Elettrodomestici. Apparecchi, Attrezzature E Forniture Per Centri Estetici",
    "sg:phone":"+39 0432 929577",
    "sg:postcode":"33057",
    "sg:province":"Udine",
    "wof:name":"Corrado Paolo (s.n.c.)",
    "wof:placetype":"venue"
},
  "geometry": {"coordinates":[13.317671,45.904892],"type":"Point"}
}