{
  "type": "Feature",
  "properties": {
    "addr:full":"00134 Roma Roma Roma 00134",
    "addr:postcode":"00134;00134",
    "iso:country":"IT",
    "sg:address":"00134 Roma",
    "sg:city":"Roma",
    "sg:orig_category":"Automazione E Macchine Per Ufficio. Servizi Ausiliari Di Certificati, Riproduzioni, Disegni E Foto",
    "sg:phone":"+39 06 719 7176",
    "sg:postcode":"00134",
    "sg:province":"Roma",
    "wof:name":"S.m.d. Srl",
    "wof:placetype":"venue"
},
  "geometry": {"coordinates":[12.552267,41.735699],"type":"Point"}
}