{
  "type": "Feature",
  "properties": {
    "iso:country":"IT",
    "sg:address":"97019 Vittoria",
    "sg:city":"Vittoria",
    "sg:orig_category":"Antenne Radio-televisione",
    "sg:phone":"+39 0932 863284",
    "sg:postcode":"97019",
    "sg:province":"Ragusa",
    "wof:name":"Punto Elettrodomestici Di Mangione Elio E C. Sas",
    "wof:placetype":"venue"
},
  "geometry": {"coordinates":[14.543605,36.957581],"type":"Point"}
}