{
  "type": "Feature",
  "properties": {
    "addr:full":"00178 Roma Roma Roma 00178",
    "addr:postcode":"00178;00178",
    "iso:country":"IT",
    "sg:address":"00178 Roma",
    "sg:city":"Roma",
    "sg:orig_category":"Scuole E Servizi Scolastici. Ricerca, Selezione E Formazione Del Personale",
    "sg:phone":"+39 06 764939",
    "sg:postcode":"00178",
    "sg:province":"Roma",
    "sg:website":"http://www.manzonianac.com",
    "wof:name":"Manzoni A.n.a.c.",
    "wof:placetype":"venue"
},
  "geometry": {"coordinates":[12.540474,41.866325],"type":"Point"}
}