{
  "type": "Feature",
  "properties": {
    "addr:full":"10015 Ivrea Ivrea Torino 10015",
    "addr:postcode":"10015;10015",
    "iso:country":"IT",
    "sg:address":"10015 Ivrea",
    "sg:city":"Ivrea",
    "sg:orig_category":"Musica",
    "sg:phone":"+39 0125 616800",
    "sg:postcode":"10015",
    "sg:province":"Torino",
    "sg:website":"http://www.paginegialle.it/musicstore",
    "wof:name":"Music Store Pittetti Snc Di Nepote E Pison",
    "wof:placetype":"venue"
},
  "geometry": {"coordinates":[7.8775548935,45.4596328735],"type":"Point"}
}