{
  "type": "Feature",
  "properties": {
    "addr:full":"86100 Campobasso Campobasso Campobasso 86100",
    "addr:postcode":"86100;86100",
    "iso:country":"IT",
    "sg:address":"86100 Campobasso",
    "sg:city":"Campobasso",
    "sg:classifiers":[
        {
            "category":"Insurance",
            "subcategory":"Insurance Agent",
            "type":"Services"
        }
    ],
    "sg:phone":"+39 0874 4791",
    "sg:postcode":"86100",
    "sg:province":"Campobasso",
    "sg:tags":[
        "factoring"
    ],
    "wof:name":"Finmolise Spa",
    "wof:placetype":"venue"
},
  "geometry": {"coordinates":[14.6704425812,41.5770835876],"type":"Point"}
}