{
  "type": "Feature",
  "properties": {
    "iso:country":"IT",
    "sg:address":"2679, V. Cascinare 63019 Sant'elpidio A Mare",
    "sg:city":"Cascinare",
    "sg:classifiers":[
        {
            "category":"Personal",
            "subcategory":"Shoe Repair & Shine",
            "type":"Services"
        }
    ],
    "sg:phone":"+39 0734 990469",
    "sg:postcode":"63019",
    "sg:province":"Ascoli Piceno",
    "sg:tags":[
        "leather"
    ],
    "sg:website":"http://www.sebastianomigliore.com",
    "wof:name":"Migliore Sebastiano",
    "wof:placetype":"venue"
},
  "geometry": {"coordinates":[13.712504,43.265114],"type":"Point"}
}