{
  "type": "Feature",
  "properties": {
    "iso:country":"IT",
    "sg:address":"2, Via Torre 20090 Segrate",
    "sg:city":"Segrate",
    "sg:classifiers":[
        {
            "category":"Real Estate",
            "subcategory":"Architect",
            "type":"Services"
        }
    ],
    "sg:phone":"+39 39027533191",
    "sg:postcode":"20090",
    "sg:province":"Milano",
    "sg:tags":[
        "textile",
        "clothing"
    ],
    "wof:name":"Farotex (s.p.a.)",
    "wof:placetype":"venue"
},
  "geometry": {"coordinates":[9.291769,45.494823],"type":"Point"}
}