{
  "type": "Feature",
  "properties": {
    "addr:full":"00040 Pomezia Pomezia Roma 00040",
    "addr:postcode":"00040;roma 00040",
    "iso:country":"IT",
    "sg:address":"00040 Pomezia",
    "sg:city":"Pomezia",
    "sg:orig_category":"Forniture Per Attivita' Commerciali Ed Artigianali",
    "sg:phone":"+39 06 9160 7632",
    "sg:postcode":"00040",
    "sg:province":"Roma",
    "wof:name":"Pomezia Timbri E Targhe",
    "wof:placetype":"venue"
},
  "geometry": {"coordinates":[12.4993133545,41.6728515625],"type":"Point"}
}