{
  "type": "Feature",
  "properties": {
    "iso:country":"IT",
    "sg:address":"21, Via Sicilia 40017 San Giovanni In Persiceto",
    "sg:city":"San Giovanni in Persiceto",
    "sg:classifiers":[
        {
            "category":"Manufacturing",
            "subcategory":"Glass & Minerals",
            "type":"Manufacturing & Wholesale Goods"
        }
    ],
    "sg:phone":"+39 051 681 9611",
    "sg:postcode":"40017",
    "sg:province":"Bologna",
    "sg:tags":[
        "building",
        "material"
    ],
    "wof:name":"Dado Ceramica Srl",
    "wof:placetype":"venue"
},
  "geometry": {"coordinates":[11.226522,44.70068],"type":"Point"}
}