{
  "type": "Feature",
  "properties": {
    "iso:country":"IT",
    "sg:address":"93, Strada Statale Per Voghera 15057 Tortona",
    "sg:city":"Tortona",
    "sg:classifiers":[
        {
            "category":"Manufacturing",
            "subcategory":"Metals",
            "type":"Manufacturing & Wholesale Goods"
        }
    ],
    "sg:phone":"+39 0131 814512",
    "sg:postcode":"15057",
    "sg:province":"Alessandria",
    "sg:tags":[
        "processing"
    ],
    "wof:name":"Ma.ga. Di Barbieri Gabriella & C. S.a.s.",
    "wof:placetype":"venue"
},
  "geometry": {"coordinates":[8.8829889297,44.9126396179],"type":"Point"}
}