{
  "type": "Feature",
  "properties": {
    "addr:full":"00193 Roma Roma Roma 00193",
    "addr:postcode":"00193;00193",
    "iso:country":"IT",
    "sg:address":"00193 Roma",
    "sg:city":"Roma",
    "sg:orig_category":"Pubblica Amministrazione",
    "sg:phone":"+39 06 321 8381",
    "sg:postcode":"00193",
    "sg:province":"Roma",
    "wof:name":"Consiglio Regionale Lazio",
    "wof:placetype":"venue"
},
  "geometry": {"coordinates":[12.4693346024,41.9082374573],"type":"Point"}
}