{
  "type": "Feature",
  "properties": {
    "addr:full":"V Albricci 7, 20122 Milan, Mi Milano 20122",
    "addr:housenumber":"7",
    "addr:postcode":"20122;20122",
    "addr:street":"Albricci",
    "iso:country":"IT",
    "sg:address":"V Albricci 7, 20122 Milan, Mi",
    "sg:classifiers":[
        {
            "category":"Banks & Credit Unions",
            "subcategory":"Bank",
            "type":"Services"
        }
    ],
    "sg:phone":"+39 039272000571",
    "sg:postcode":"20122",
    "sg:province":"Milano",
    "wof:name":"Bnl Fiduciaria Gestioni Sim Spa",
    "wof:placetype":"venue"
},
  "geometry": {"coordinates":[9.190097,45.460949],"type":"Point"}
}