{
  "type": "Feature",
  "properties": {
    "iso:country":"IT",
    "sg:address":"20019 Settimo Milanese",
    "sg:city":"Settimo Milanese",
    "sg:orig_category":"Prodotti Vari In Metallo. Articoli Per Imballaggio E Confezionamento",
    "sg:phone":"+39 02 328 7356",
    "sg:postcode":"20019",
    "sg:province":"Milano",
    "wof:name":"Masterinox Srl",
    "wof:placetype":"venue"
},
  "geometry": {"coordinates":[9.0697040558,45.4801902771],"type":"Point"}
}