{
  "type": "Feature",
  "properties": {
    "iso:country":"IT",
    "sg:address":"20042 Albiate",
    "sg:city":"Albiate",
    "sg:orig_category":"Articoli Per Imballaggio E Confezionamento",
    "sg:phone":"+39 036 293 2679",
    "sg:postcode":"20042",
    "sg:province":"Milano",
    "wof:name":"Saccheria Intra Antonio",
    "wof:placetype":"venue"
},
  "geometry": {"coordinates":[9.255535,45.65715],"type":"Point"}
}