{
  "type": "Feature",
  "properties": {
    "iso:country":"IT",
    "sg:address":"00181 Roma",
    "sg:city":"Roma",
    "sg:orig_category":"Automazione E Macchine Per Ufficio",
    "sg:phone":"+39 06 784 3099",
    "sg:postcode":"00181",
    "sg:province":"Roma",
    "wof:name":"Olyservice Srl",
    "wof:placetype":"venue"
},
  "geometry": {"coordinates":[12.528708,41.872307],"type":"Point"}
}