{
  "type": "Feature",
  "properties": {
    "iso:country":"IT",
    "sg:address":"50033 Firenzuola",
    "sg:city":"Firenzuola",
    "sg:classifiers":[
        {
            "category":"Home & Garden",
            "subcategory":"Building Materials",
            "type":"Retail Goods"
        }
    ],
    "sg:phone":"+39 055 819085",
    "sg:postcode":"50033",
    "sg:province":"Firenze",
    "sg:tags":[
        "stone",
        "similar",
        "marble"
    ],
    "wof:name":"La Borghigiana Srl",
    "wof:placetype":"venue"
},
  "geometry": {"coordinates":[11.365801,44.152103],"type":"Point"}
}