{
  "type": "Feature",
  "properties": {
    "iso:country":"IT",
    "sg:address":"28838 Stresa",
    "sg:city":"Stresa",
    "sg:orig_category":"Servizi Per Lo Sport E Il Tempo Libero. Servizi Al Turismo",
    "sg:phone":"+39 0323 924172",
    "sg:postcode":"28838",
    "sg:province":"Verbano-Cusio-Ossola",
    "wof:name":"Sciovie Del Mottarone S.r.l.",
    "wof:placetype":"venue"
},
  "geometry": {"coordinates":[8.45111,45.88028],"type":"Point"}
}