{
  "type": "Feature",
  "properties": {
    "addr:full":"55045 Pietrasanta Pietrasanta Lucca 55045",
    "addr:postcode":"55045;55045",
    "iso:country":"IT",
    "sg:address":"55045 Pietrasanta",
    "sg:city":"Pietrasanta",
    "sg:orig_category":"Prodotti Di Base E Forniture Per Industria Alimentare E Bevande. Macchine, Impianti Ed Attrezzature Per Industria Alimentare E Bevande. Frigotecnica, Apparecchiature E Servizi. Macchine E Impianti Per",
    "sg:phone":"+39 0584 791462",
    "sg:postcode":"55045",
    "sg:province":"Lucca",
    "wof:name":"Linea.net Milano S.r.l.",
    "wof:placetype":"venue"
},
  "geometry": {"coordinates":[10.222070694,43.959312439],"type":"Point"}
}