{
  "type": "Feature",
  "properties": {
    "addr:full":"25020 Gambara Gambara Brescia 25020",
    "addr:postcode":"25020;25020",
    "iso:country":"IT",
    "sg:address":"25020 Gambara",
    "sg:city":"Gambara",
    "sg:orig_category":"Calzaturifici E Calzolai - Forniture",
    "sg:phone":"+39 030 995 6225",
    "sg:postcode":"25020",
    "sg:province":"Brescia",
    "wof:name":"C.p.t. Srl",
    "wof:placetype":"venue"
},
  "geometry": {"coordinates":[10.294537,45.25626],"type":"Point"}
}