{
  "type": "Feature",
  "properties": {
    "iso:country":"IT",
    "sg:address":"Via Salci 03100 Frosinone",
    "sg:city":"Frosinone",
    "sg:classifiers":[
        {
            "category":"Professional",
            "subcategory":"Engineering",
            "type":"Services"
        }
    ],
    "sg:phone":"+39 0775 200653",
    "sg:postcode":"03100",
    "sg:province":"Frosinone",
    "sg:tags":[
        "machine",
        "-",
        "mechanical"
    ],
    "wof:name":"Italinox (s.r.l.)",
    "wof:placetype":"venue"
},
  "geometry": {"coordinates":[13.30666,41.650055],"type":"Point"}
}