{
  "type": "Feature",
  "properties": {
    "iso:country":"IT",
    "sg:address":"6, Via Cavarzerani 33070 Caneva",
    "sg:city":"Caneva",
    "sg:classifiers":[
        {
            "category":"Professional",
            "subcategory":"Engineering",
            "type":"Services"
        }
    ],
    "sg:phone":"+39 39043479097",
    "sg:postcode":"33070",
    "sg:province":"Pordenone",
    "sg:tags":[
        "machine",
        "-",
        "mechanical"
    ],
    "wof:name":"Polese Giovanni Automation (s.r.l.)",
    "wof:placetype":"venue"
},
  "geometry": {"coordinates":[12.437007,45.966606],"type":"Point"}
}