{
  "type": "Feature",
  "properties": {
    "addr:full":"0549 Repubblica Di San Marino SM",
    "addr:housenumber":"0549;sm",
    "addr:street":"Repubblica;San Marino",
    "iso:country":"IT",
    "sg:address":"0549 Repubblica Di San Marino",
    "sg:orig_category":"Medicinali E Prodotti Parafarmaceutici",
    "sg:phone":"+39 0549 909299",
    "sg:province":"SM",
    "wof:name":"Centro Salute Sh - Health Service",
    "wof:placetype":"venue"
},
  "geometry": {"coordinates":[12.5063285828,43.9838142395],"type":"Point"}
}