{
  "type": "Feature",
  "properties": {
    "addr:full":"93, Via Cascina California 22036 Erba Erba Como 22036",
    "addr:postcode":"22036;22036",
    "addr:street":"Via Cascina",
    "iso:country":"IT",
    "sg:address":"93, Via Cascina California 22036 Erba",
    "sg:city":"Erba",
    "sg:classifiers":[
        {
            "category":"Manufacturing",
            "subcategory":"Rubber & Plastics",
            "type":"Manufacturing & Wholesale Goods"
        }
    ],
    "sg:phone":"+39 39031640497",
    "sg:postcode":"22036",
    "sg:province":"Como",
    "wof:name":"Tecnopor (s.p.a.)",
    "wof:placetype":"venue"
},
  "geometry": {"coordinates":[9.2413349152,45.7972106934],"type":"Point"}
}