{
  "type": "Feature",
  "properties": {
    "addr:full":"98123 Messina Messina Messina 98123",
    "addr:postcode":"98123;98123",
    "iso:country":"IT",
    "sg:address":"98123 Messina",
    "sg:city":"Messina",
    "sg:orig_category":"Pompe. Elettrotecnica Industriale, Prodotti E Apparecchiature",
    "sg:phone":"+39 090 293 5140",
    "sg:postcode":"98123",
    "sg:province":"Messina",
    "wof:name":"Castelli Elio",
    "wof:placetype":"venue"
},
  "geometry": {"coordinates":[15.5554819107,38.1830253601],"type":"Point"}
}