{
  "type": "Feature",
  "properties": {
    "iso:country":"IT",
    "sg:address":"37, Via Luna 26866 Marudo",
    "sg:city":"Marudo",
    "sg:classifiers":[
        {
            "category":"Manufacturing",
            "subcategory":"Tools & Machinery",
            "type":"Manufacturing & Wholesale Goods"
        }
    ],
    "sg:phone":"+39 0371 210246",
    "sg:postcode":"26866",
    "sg:province":"Lodi",
    "sg:tags":[
        "environment",
        "equipment",
        "-"
    ],
    "wof:name":"Lodigiana Maceri (s.r.l.)",
    "wof:placetype":"venue"
},
  "geometry": {"coordinates":[9.371692,45.250408],"type":"Point"}
}