{
  "type": "Feature",
  "properties": {
    "addr:full":"17 Via Cesare Battisti, 38042 Baselga Di Pine' Trento 38042",
    "addr:postcode":"38042;38042",
    "addr:street":"Via Cesare Battisti;Di Pine ' Trento",
    "iso:country":"IT",
    "sg:address":"17 Via Cesare Battisti, 38042 Baselga Di Pine'",
    "sg:classifiers":[
        {
            "category":"Banks & Credit Unions",
            "subcategory":"Financial Services",
            "type":"Services"
        }
    ],
    "sg:phone":"+39 0461 559711",
    "sg:postcode":"38042",
    "sg:province":"Trento",
    "sg:tags":[
        "banking",
        "finance",
        "insurance"
    ],
    "wof:name":"Cassa Rurale Pinetana Fornace E Seregnano Scarl",
    "wof:placetype":"venue"
},
  "geometry": {"coordinates":[11.243973732,46.1297912598],"type":"Point"}
}