{
  "type": "Feature",
  "properties": {
    "iso:country":"IT",
    "sg:address":"34124 Trieste",
    "sg:city":"Trieste",
    "sg:classifiers":[
        {
            "category":"Sports & Exercise",
            "subcategory":"Ice Rink",
            "type":"Entertainment"
        }
    ],
    "sg:phone":"+39 040 307325",
    "sg:postcode":"34124",
    "sg:province":"Trieste",
    "sg:tags":[
        "article",
        "shopping",
        "supplies"
    ],
    "wof:name":"Avventura 2000 Snc",
    "wof:placetype":"venue"
},
  "geometry": {"coordinates":[13.767696,45.646229],"type":"Point"}
}