{
  "type": "Feature",
  "properties": {
    "addr:full":"4, Via G. Di Vittorio 40056 Crespellano Crespellano Bologna 40056",
    "addr:postcode":"40056;40056",
    "addr:street":"Via G. Di Vittorio",
    "iso:country":"IT",
    "sg:address":"4, Via G. Di Vittorio 40056 Crespellano",
    "sg:city":"Crespellano",
    "sg:classifiers":[
        {
            "category":"Shopping",
            "subcategory":"Computers & Home Electronics",
            "type":"Retail Goods"
        }
    ],
    "sg:phone":"+39 39051969460",
    "sg:postcode":"40056",
    "sg:province":"Bologna",
    "sg:tags":[
        "electronic",
        "electrical",
        "equipment"
    ],
    "wof:name":"Lipparini (s.r.l.)",
    "wof:placetype":"venue"
},
  "geometry": {"coordinates":[11.20717,44.541817],"type":"Point"}
}