{
  "type": "Feature",
  "properties": {
    "iso:country":"IT",
    "sg:address":"20090 Segrate",
    "sg:city":"Segrate",
    "sg:orig_category":"Non-classified Establishments",
    "sg:phone":"+39 02 753 1022",
    "sg:postcode":"20090",
    "sg:province":"Milano",
    "wof:name":"Huhtamaki Spa Spa",
    "wof:placetype":"venue"
},
  "geometry": {"coordinates":[9.308394,45.474106],"type":"Point"}
}