{
  "type": "Feature",
  "properties": {
    "addr:full":"31044 Montebelluna Montebelluna Treviso 31044",
    "addr:postcode":"31044;31044",
    "iso:country":"IT",
    "sg:address":"31044 Montebelluna",
    "sg:city":"Montebelluna",
    "sg:orig_category":"Detergenti Industriali",
    "sg:phone":"+39 0423 603077",
    "sg:postcode":"31044",
    "sg:province":"Treviso",
    "wof:name":"Linea Pulizie La Celeste Snc Di Bandiera Annalisa & C.",
    "wof:placetype":"venue"
},
  "geometry": {"coordinates":[12.22786,45.655521],"type":"Point"}
}