{
  "type": "Feature",
  "properties": {
    "iso:country":"IT",
    "sg:address":"5, Via Ragazzi Del 99 41043 Formigine",
    "sg:city":"Formigine",
    "sg:classifiers":[
        {
            "category":"Professional",
            "subcategory":"Advertising",
            "type":"Services"
        }
    ],
    "sg:phone":"+39 39059550501",
    "sg:postcode":"41043",
    "sg:province":"Modena",
    "sg:tags":[
        "communication",
        "medium"
    ],
    "wof:name":"Visual Photo (s.n.c.)",
    "wof:placetype":"venue"
},
  "geometry": {"coordinates":[10.848282,44.588139],"type":"Point"}
}