{
  "type": "Feature",
  "properties": {
    "iso:country":"IT",
    "sg:address":"21057 Olgiate Olona",
    "sg:city":"Olgiate Olona",
    "sg:orig_category":"Lavorazioni Metalli, Stampaggio E Saldatura",
    "sg:phone":"+39 0331 375540",
    "sg:postcode":"21057",
    "sg:province":"Varese",
    "wof:name":"Forgiatura Marcora (s.r.l.)",
    "wof:placetype":"venue"
},
  "geometry": {"coordinates":[8.882298,45.617561],"type":"Point"}
}