{
  "type": "Feature",
  "properties": {
    "iso:country":"IT",
    "sg:address":"Via Weggenstein, 36/1 39100 Bolzano",
    "sg:city":"Bolzano",
    "sg:classifiers":[
        {
            "category":"Food & Beverages",
            "subcategory":"Liquor & Beverages",
            "type":"Retail Goods"
        }
    ],
    "sg:phone":"+39 0471 972885",
    "sg:postcode":"39100",
    "sg:province":"Bolzano/Bozen",
    "sg:tags":[
        "wine",
        "italian"
    ],
    "sg:website":"www.malojer.it",
    "wof:name":"Malojer Rudolf Des Malojer Alfred",
    "wof:placetype":"venue"
},
  "geometry": {"coordinates":[11.328239,46.461643],"type":"Point"}
}