{
  "type": "Feature",
  "properties": {
    "addr:full":"60, Via Badie 24060 Castelli Calepio Castelli Calepio Bergamo 24060",
    "addr:postcode":"24060;24060",
    "addr:street":"Via Badie",
    "iso:country":"IT",
    "sg:address":"60, Via Badie 24060 Castelli Calepio",
    "sg:city":"Castelli Calepio",
    "sg:classifiers":[
        {
            "category":"Manufacturing",
            "subcategory":"Food",
            "type":"Manufacturing & Wholesale Goods"
        }
    ],
    "sg:phone":"+39 030 743 8844",
    "sg:postcode":"24060",
    "sg:province":"Bergamo",
    "sg:tags":[
        "equipment",
        "processing",
        "-",
        "machinery"
    ],
    "wof:name":"Lancini Bruno E C. (s.n.c.)",
    "wof:placetype":"venue"
},
  "geometry": {"coordinates":[9.8933935165,45.6207389832],"type":"Point"}
}