{
  "type": "Feature",
  "properties": {
    "iso:country":"IT",
    "sg:address":"66023 Francavilla Al Mare",
    "sg:city":"Francavilla al Mare",
    "sg:orig_category":"Batterie, Accumulatori E Pile - Commercio",
    "sg:phone":"+39 085 810303",
    "sg:postcode":"66023",
    "sg:province":"Chieti",
    "wof:name":"Rima Srl",
    "wof:placetype":"venue"
},
  "geometry": {"coordinates":[14.256053,42.36729],"type":"Point"}
}