{
  "type": "Feature",
  "properties": {
    "addr:full":"7/2, Via Montebello 40121 Bologna Bologna Bologna 40121",
    "addr:housenumber":"7 / 2",
    "addr:postcode":"40121;40121",
    "addr:street":"Via Montebello",
    "iso:country":"IT",
    "sg:address":"7/2, Via Montebello 40121 Bologna",
    "sg:city":"Bologna",
    "sg:classifiers":[
        {
            "category":"Shopping",
            "subcategory":"Crafts & Fabrics",
            "type":"Retail Goods"
        }
    ],
    "sg:phone":"+39 39051251352",
    "sg:postcode":"40121",
    "sg:province":"Bologna",
    "wof:name":"Avantgard Tessile (s.r.l.)",
    "wof:placetype":"venue"
},
  "geometry": {"coordinates":[11.3424062729,44.5019340515],"type":"Point"}
}