{
  "type": "Feature",
  "properties": {
    "addr:full":"48, Via Vignole 21058 Solbiate Olona Solbiate Olona Varese 21058",
    "addr:postcode":"21058;21058",
    "addr:street":"Via Vignole",
    "iso:country":"IT",
    "sg:address":"48, Via Vignole 21058 Solbiate Olona",
    "sg:city":"Solbiate Olona",
    "sg:classifiers":[
        {
            "category":"Shopping",
            "subcategory":"Clothing, Apparel, & Fashions",
            "type":"Retail Goods"
        }
    ],
    "sg:phone":"+39 0331 649140",
    "sg:postcode":"21058",
    "sg:province":"Varese",
    "sg:tags":[
        "clothes"
    ],
    "wof:name":"Tessilcompany (s.r.l.)",
    "wof:placetype":"venue"
},
  "geometry": {"coordinates":[8.880527,45.655766],"type":"Point"}
}