{
  "type": "Feature",
  "properties": {
    "addr:full":"16156 Genova Genova Genova 16156",
    "addr:housenumber":"16156",
    "addr:postcode":"16156",
    "iso:country":"IT",
    "sg:address":"16156 Genova",
    "sg:city":"Genova",
    "sg:orig_category":"Termotecnica E Riscaldamento, Apparecchiature E Servizi. Valvole E Apparecchiature Di Misura. Macchine, Strumenti Ed Apparecchi Per Attivita' Industriali",
    "sg:phone":"+39 010 698 2919",
    "sg:postcode":"16156",
    "sg:province":"Genova",
    "wof:name":"Esse.di.a. Di Risso Giuseppe S.a.s.",
    "wof:placetype":"venue"
},
  "geometry": {"coordinates":[8.811471,44.433212],"type":"Point"}
}