{
  "type": "Feature",
  "properties": {
    "iso:country":"IT",
    "sg:address":"7, V. Caduti Navicello 41030 Bomporto",
    "sg:city":"Bomporto",
    "sg:classifiers":[
        {
            "category":"Professional",
            "subcategory":"Engineering",
            "type":"Services"
        }
    ],
    "sg:phone":"+39 39059818028",
    "sg:postcode":"41030",
    "sg:province":"Modena",
    "sg:tags":[
        "machine",
        "-",
        "mechanical"
    ],
    "sg:website":"http://www.paginegialle.it/mabor",
    "wof:name":"Ma.bor. Srl",
    "wof:placetype":"venue"
},
  "geometry": {"coordinates":[11.008884,44.690529],"type":"Point"}
}