{
  "type": "Feature",
  "properties": {
    "addr:full":"83025 Montoro Inferiore Montoro Inferiore Avellino 83025",
    "addr:postcode":"83025;83025",
    "iso:country":"IT",
    "sg:address":"83025 Montoro Inferiore",
    "sg:city":"Montoro Inferiore",
    "sg:orig_category":"Manufacturers: Prefabbricati",
    "sg:phone":"+39 0825 503301",
    "sg:postcode":"83025",
    "sg:province":"Avellino",
    "wof:name":"Pellecchia Antonio",
    "wof:placetype":"venue"
},
  "geometry": {"coordinates":[14.769596,40.830997],"type":"Point"}
}