{
  "type": "Feature",
  "properties": {
    "iso:country":"IT",
    "sg:address":"54, Via Cesariano 21056 Induno Olona",
    "sg:city":"Induno Olona",
    "sg:classifiers":[
        {
            "category":"Personal",
            "subcategory":"Shoe Repair & Shine",
            "type":"Services"
        }
    ],
    "sg:phone":"+39 0332 203737",
    "sg:postcode":"21056",
    "sg:province":"Varese",
    "sg:tags":[
        "leather"
    ],
    "wof:name":"Pelletteria Portone Srl",
    "wof:placetype":"venue"
},
  "geometry": {"coordinates":[8.830888,45.840496],"type":"Point"}
}