{
  "type": "Feature",
  "properties": {
    "addr:full":"33030 Buia Udine 33030",
    "addr:postcode":"33030;33030",
    "addr:street":"Buia",
    "iso:country":"IT",
    "sg:address":"33030 Buia",
    "sg:classifiers":[
        {
            "category":"Manufacturing",
            "subcategory":"Metals",
            "type":"Manufacturing & Wholesale Goods"
        }
    ],
    "sg:phone":"+39 0432 964127",
    "sg:postcode":"33030",
    "sg:province":"Udine",
    "sg:tags":[
        "ferro"
    ],
    "sg:website":"http://www.smei-italia.com",
    "wof:name":"Smei Srl",
    "wof:placetype":"venue"
},
  "geometry": {"coordinates":[13.1621904373,46.2346496582],"type":"Point"}
}