{
  "type": "Feature",
  "properties": {
    "iso:country":"IT",
    "sg:address":"52, Via Solferino 20052 Monza",
    "sg:city":"Monza",
    "sg:classifiers":[
        {
            "category":"Communications",
            "subcategory":"Television Station",
            "type":"Services"
        }
    ],
    "sg:phone":"+39 39039212221",
    "sg:postcode":"20052",
    "sg:province":"Milano",
    "sg:tags":[
        "audio-visual"
    ],
    "wof:name":"Audio Equipment",
    "wof:placetype":"venue"
},
  "geometry": {"coordinates":[9.229824,45.533146],"type":"Point"}
}