{
  "type": "Feature",
  "properties": {
    "iso:country":"IT",
    "sg:address":"35, Via Venosta 39020 Parcines",
    "sg:city":"Parcines",
    "sg:classifiers":[
        {
            "category":"Professional",
            "subcategory":"Engineering",
            "type":"Services"
        }
    ],
    "sg:phone":"+39 0473 968242",
    "sg:postcode":"39020",
    "sg:province":"Bolzano/Bozen",
    "sg:tags":[
        "machine",
        "-",
        "mechanical"
    ],
    "wof:name":"K\u00c4lte Project (s.n.c.)",
    "wof:placetype":"venue"
},
  "geometry": {"coordinates":[11.070812,46.671654],"type":"Point"}
}