{
  "type": "Feature",
  "properties": {
    "addr:full":"12100 Cuneo Cuneo Cuneo 12100",
    "addr:postcode":"12100;12100",
    "iso:country":"IT",
    "sg:address":"12100 Cuneo",
    "sg:city":"Cuneo",
    "sg:orig_category":"Servizi E Lavori Per Industria Alimentare E Bevande",
    "sg:phone":"+39 0171 682391",
    "sg:postcode":"12100",
    "sg:province":"Cuneo",
    "wof:name":"Agrindustria Di Tecco Giuseppe",
    "wof:placetype":"venue"
},
  "geometry": {"coordinates":[7.520735,44.457615],"type":"Point"}
}