{
  "type": "Feature",
  "properties": {
    "iso:country":"IT",
    "sg:address":"20052 Monza",
    "sg:city":"Monza",
    "sg:orig_category":"Non-classified Establishments",
    "sg:phone":"+39 039 322587",
    "sg:postcode":"20052",
    "sg:province":"Milano",
    "wof:name":"Cereria Camesasca",
    "wof:placetype":"venue"
},
  "geometry": {"coordinates":[9.184217,45.452019],"type":"Point"}
}