{
  "type": "Feature",
  "properties": {
    "iso:country":"IT",
    "sg:address":"00194 Roma",
    "sg:city":"Roma",
    "sg:orig_category":"Accessori Moda D'abbigliamento. Forniture Per Abbigliamento E Pelletterie. Shopping",
    "sg:phone":"+39 06 3638 1678",
    "sg:postcode":"00194",
    "sg:province":"Roma",
    "wof:name":"Cocchi Cesare",
    "wof:placetype":"venue"
},
  "geometry": {"coordinates":[12.458319,41.946457],"type":"Point"}
}