{
  "type": "Feature",
  "properties": {
    "iso:country":"IT",
    "sg:address":"57036 Porto Azzurro",
    "sg:city":"Porto Azzurro",
    "sg:orig_category":"Autonoleggio",
    "sg:phone":"+39 0565 95112",
    "sg:postcode":"57036",
    "sg:province":"Livorno",
    "wof:name":"Spazio Mare Di Gambalunghe Snc",
    "wof:placetype":"venue"
},
  "geometry": {"coordinates":[10.307782,43.550282],"type":"Point"}
}