{
  "type": "Feature",
  "properties": {
    "iso:country":"IT",
    "sg:address":"10121 Torino",
    "sg:city":"Torino",
    "sg:classifiers":[
        {
            "category":"Shopping",
            "subcategory":"Clothing, Apparel, & Fashions",
            "type":"Retail Goods"
        }
    ],
    "sg:phone":"+39 011 540067",
    "sg:postcode":"10121",
    "sg:province":"Torino",
    "sg:tags":[
        "knitwear",
        "furs",
        "clothing"
    ],
    "wof:name":"Garb Selezione Alta Moda Spa",
    "wof:placetype":"venue"
},
  "geometry": {"coordinates":[7.57748,45.02277],"type":"Point"}
}