{
  "type": "Feature",
  "properties": {
    "iso:country":"IT",
    "sg:address":"95037 S. Giovanni La Punta",
    "sg:orig_category":"Imprese Di Costruzioni Civili Ed Industriali. Servizi E Lavori Per Ecologia E Smaltimento Rifiuti",
    "sg:phone":"+39 095 751 2424",
    "sg:postcode":"95037",
    "sg:province":"Catania",
    "wof:name":"Etna Spurgo Di Caruso Santo",
    "wof:placetype":"venue"
},
  "geometry": {"coordinates":[15.07876,37.585598],"type":"Point"}
}