{
  "type": "Feature",
  "properties": {
    "addr:full":"81020 Casapulla Casapulla Caserta 81020",
    "addr:postcode":"81020;81020",
    "iso:country":"IT",
    "sg:address":"81020 Casapulla",
    "sg:city":"Casapulla",
    "sg:orig_category":"Valvole E Apparecchiature Di Misura. Ricambi E Componenti Dei Mezzi Di Trasporto",
    "sg:phone":"+39 0823 464527",
    "sg:postcode":"81020",
    "sg:province":"Caserta",
    "wof:name":"Taddeo Pietro",
    "wof:placetype":"venue"
},
  "geometry": {"coordinates":[14.289957,41.072613],"type":"Point"}
}