{
  "type": "Feature",
  "properties": {
    "addr:full":"12084 Mondov\u00ec Gratteria Cuneo 12084",
    "addr:postcode":"12084;12084",
    "iso:country":"IT",
    "sg:address":"12084 Mondov\u00ec",
    "sg:city":"Gratteria",
    "sg:orig_category":"Fucinatura",
    "sg:phone":"+39 0174 45394",
    "sg:postcode":"12084",
    "sg:province":"Cuneo",
    "sg:website":"http://www.icsnet.it/fomec",
    "wof:name":"Fomec Spa",
    "wof:placetype":"venue"
},
  "geometry": {"coordinates":[7.7857379913,44.4720115662],"type":"Point"}
}