{
  "type": "Feature",
  "properties": {
    "iso:country":"IT",
    "sg:address":"50032 Borgo San Lorenzo",
    "sg:city":"Borgo San Lorenzo",
    "sg:classifiers":[
        {
            "category":"Organizations",
            "subcategory":"Membership Organization",
            "type":"Services"
        }
    ],
    "sg:phone":"+39 055 849 6083",
    "sg:postcode":"50032",
    "sg:province":"Firenze",
    "sg:tags":[
        "valve",
        "system",
        "packaging",
        "equipment",
        "packing",
        "measurement"
    ],
    "wof:name":"Nuova Graphopack",
    "wof:placetype":"venue"
},
  "geometry": {"coordinates":[11.368785,43.958652],"type":"Point"}
}