{
  "type": "Feature",
  "properties": {
    "iso:country":"IT",
    "sg:address":"33100 Udine",
    "sg:city":"Udine",
    "sg:orig_category":"Materiali E Componenti Elettrotecnici",
    "sg:phone":"+39 0432 522222",
    "sg:postcode":"33100",
    "sg:province":"Udine",
    "wof:name":"Elettroluce Sas Di G. & G. Moretto",
    "wof:placetype":"venue"
},
  "geometry": {"coordinates":[13.24518,46.03801],"type":"Point"}
}