{
  "type": "Feature",
  "properties": {
    "addr:full":"63024 Grottazzolina Grottazzolina Ascoli Piceno 63024",
    "addr:postcode":"63024;63024",
    "iso:country":"IT",
    "sg:address":"63024 Grottazzolina",
    "sg:city":"Grottazzolina",
    "sg:orig_category":"Calzature - Produzione E Ingrosso",
    "sg:phone":"+39 0734 631131",
    "sg:postcode":"63024",
    "sg:province":"Ascoli Piceno",
    "wof:name":"Fast Calzature Di Ferracuti Giuseppe & C. Snc",
    "wof:placetype":"venue"
},
  "geometry": {"coordinates":[13.643759,43.15361],"type":"Point"}
}