{
  "type": "Feature",
  "properties": {
    "iso:country":"IT",
    "sg:address":"23819 Primaluna",
    "sg:city":"Primaluna",
    "sg:orig_category":"Minuterie Metalliche E Ferramenta",
    "sg:phone":"+39 0341 979971",
    "sg:postcode":"23819",
    "sg:province":"Lecco",
    "wof:name":"Officine Di Cortabbio Srl",
    "wof:placetype":"venue"
},
  "geometry": {"coordinates":[9.4518918991,45.9328613281],"type":"Point"}
}