{
  "type": "Feature",
  "properties": {
    "iso:country":"IT",
    "sg:address":"61034 Fossombrone",
    "sg:city":"Fossombrone",
    "sg:orig_category":"Termotecnica E Riscaldamento, Apparecchiature E Servizi",
    "sg:phone":"+39 0721 727481",
    "sg:postcode":"61034",
    "sg:province":"Pesaro E Urbino",
    "wof:name":"T.c.v. Snc Di U. Carbonari & C.",
    "wof:placetype":"venue"
},
  "geometry": {"coordinates":[12.813778,43.691723],"type":"Point"}
}