{
  "type": "Feature",
  "properties": {
    "iso:country":"IT",
    "sg:address":"55060 Capannori",
    "sg:city":"Capannori",
    "sg:orig_category":"Utensili Meccanici E Materiali",
    "sg:phone":"+39 0583 94342",
    "sg:postcode":"55060",
    "sg:province":"Lucca",
    "wof:name":"Telti Spa",
    "wof:placetype":"venue"
},
  "geometry": {"coordinates":[10.513547,43.819672],"type":"Point"}
}