{
  "type": "Feature",
  "properties": {
    "addr:full":"50122 Firenze Firenze Firenze 50122",
    "addr:postcode":"50122;50122",
    "iso:country":"IT",
    "sg:address":"50122 Firenze",
    "sg:city":"Firenze",
    "sg:orig_category":"Musica. Shopping",
    "sg:phone":"+39 055 295101",
    "sg:postcode":"50122",
    "sg:province":"Firenze",
    "wof:name":"Nuovo Discoemporium Srl",
    "wof:placetype":"venue"
},
  "geometry": {"coordinates":[11.2579956055,43.7718849182],"type":"Point"}
}