{
  "type": "Feature",
  "properties": {
    "addr:full":"36040 Torri Di Quartesolo Torri di Quartesolo Vicenza 36040",
    "addr:postcode":"36040;36040",
    "iso:country":"IT",
    "sg:address":"36040 Torri Di Quartesolo",
    "sg:city":"Torri di Quartesolo",
    "sg:orig_category":"Macchine, Impianti Ed Attrezzature Per Abbigliamento E Pelletterie. Macchine E Impianti Per Attivita' Commerciali Ed Artigianali",
    "sg:phone":"+39 0444 380314",
    "sg:postcode":"36040",
    "sg:province":"Vicenza",
    "wof:name":"Pozzer Sergio",
    "wof:placetype":"venue"
},
  "geometry": {"coordinates":[11.608497,45.52224],"type":"Point"}
}