{
  "type": "Feature",
  "properties": {
    "addr:full":"41012 Carpi Carpi Modena 41012",
    "addr:postcode":"41012;41012",
    "iso:country":"IT",
    "sg:address":"41012 Carpi",
    "sg:city":"Carpi",
    "sg:orig_category":"Acciaierie E Fonderie",
    "sg:phone":"+39 059 694696",
    "sg:postcode":"41012",
    "sg:province":"Modena",
    "wof:name":"Fonderia Paras Snc Di Righi A. & Sarti C.",
    "wof:placetype":"venue"
},
  "geometry": {"coordinates":[10.852865,44.780903],"type":"Point"}
}