{
  "type": "Feature",
  "properties": {
    "addr:full":"Via Veneto 112 35040 Casale Di Scodosia Casale di Scodosia Padova 35040",
    "addr:housenumber":"112",
    "addr:postcode":"35040;35040",
    "addr:street":"Via Veneto",
    "iso:country":"IT",
    "sg:address":"Via Veneto 112 35040 Casale Di Scodosia",
    "sg:city":"Casale di Scodosia",
    "sg:classifiers":[
        {
            "category":"Home & Garden",
            "subcategory":"Furniture",
            "type":"Retail Goods"
        }
    ],
    "sg:phone":"+39 0429 878094",
    "sg:postcode":"35040",
    "sg:province":"Padova",
    "sg:tags":[
        "apartment"
    ],
    "wof:name":"Bei Srl",
    "wof:placetype":"venue"
},
  "geometry": {"coordinates":[11.494987,45.183956],"type":"Point"}
}