{
  "type": "Feature",
  "properties": {
    "addr:full":"84084 Fisciano Fisciano Salerno 84084",
    "addr:postcode":"84084;84084",
    "iso:country":"IT",
    "sg:address":"84084 Fisciano",
    "sg:city":"Fisciano",
    "sg:orig_category":"Abrasivi",
    "sg:phone":"+39 089 879911",
    "sg:postcode":"84084",
    "sg:province":"Salerno",
    "wof:name":"Grinding Srl",
    "wof:placetype":"venue"
},
  "geometry": {"coordinates":[14.775314,40.786888],"type":"Point"}
}