{
  "type": "Feature",
  "properties": {
    "iso:country":"IT",
    "sg:address":"00040 Ariccia",
    "sg:city":"Ariccia",
    "sg:orig_category":"Carta, Cartone E Prodotti Primari. Forniture E Materiali Per Imballaggio E Confezionamento",
    "sg:phone":"+39 06 934 4788",
    "sg:postcode":"00040",
    "sg:province":"Roma",
    "wof:name":"Ri.ca Distribuzione Srl",
    "wof:placetype":"venue"
},
  "geometry": {"coordinates":[12.674063,41.721703],"type":"Point"}
}