{
  "type": "Feature",
  "properties": {
    "iso:country":"IT",
    "sg:address":"66030 Frisa",
    "sg:city":"Frisa",
    "sg:orig_category":"Bevande, Vini E Liquori. Agricoltura, Orticoltura E Floricoltura",
    "sg:phone":"+39 0872 58128",
    "sg:postcode":"66030",
    "sg:province":"Chieti",
    "wof:name":"Cantina Sociale Colle Moro Soc.coop.r.l.",
    "wof:placetype":"venue"
},
  "geometry": {"coordinates":[14.387409,42.271595],"type":"Point"}
}