{
  "type": "Feature",
  "properties": {
    "addr:full":"10093 Collegno Collegno Torino 10093",
    "addr:postcode":"10093;10093",
    "iso:country":"IT",
    "sg:address":"10093 Collegno",
    "sg:city":"Collegno",
    "sg:orig_category":"Forniture Per Agricoltura E Zootecnia",
    "sg:phone":"+39 011 405 4158",
    "sg:postcode":"10093",
    "sg:province":"Torino",
    "wof:name":"Mussino (s.n.c.)",
    "wof:placetype":"venue"
},
  "geometry": {"coordinates":[7.5794658661,45.0864486694],"type":"Point"}
}