{
  "type": "Feature",
  "properties": {
    "addr:full":"12/a, Via Corno D'aquilio 37124 Verona Verona Verona 37124",
    "addr:housenumber":"12 / a",
    "addr:postcode":"37124;37124",
    "addr:street":"Via Corno D'Aquilio",
    "iso:country":"IT",
    "sg:address":"12/a, Via Corno D'aquilio 37124 Verona",
    "sg:city":"Verona",
    "sg:classifiers":[
        {
            "category":"Real Estate",
            "subcategory":"Surveying",
            "type":"Services"
        }
    ],
    "sg:phone":"+39 39045918133",
    "sg:postcode":"37124",
    "sg:province":"Verona",
    "sg:tags":[
        "equipment",
        "material",
        "good",
        "-",
        "handling"
    ],
    "wof:name":"Cmr Teco (s.r.l.)",
    "wof:placetype":"venue"
},
  "geometry": {"coordinates":[10.991748,45.438366],"type":"Point"}
}