{
  "type": "Feature",
  "properties": {
    "iso:country":"IT",
    "sg:address":"57125 Livorno",
    "sg:city":"Livorno",
    "sg:orig_category":"Associazioni Ed Istituti Di Previdenza Ed Assistenza",
    "sg:phone":"+39 0586 888558",
    "sg:postcode":"57125",
    "sg:province":"Livorno",
    "wof:name":"Trade Union",
    "wof:placetype":"venue"
},
  "geometry": {"coordinates":[10.318918,43.546062],"type":"Point"}
}