{
  "type": "Feature",
  "properties": {
    "iso:country":"IT",
    "sg:address":"85, Viale Delle Industrie 20040 Cambiago",
    "sg:city":"Cambiago",
    "sg:classifiers":[
        {
            "category":"Professional",
            "subcategory":"Printing & Photocopies",
            "type":"Services"
        }
    ],
    "sg:phone":"+39 02 9506 7023",
    "sg:postcode":"20040",
    "sg:province":"Milano",
    "wof:name":"Arti Grafiche A. Gallati (s.p.a.)",
    "wof:placetype":"venue"
},
  "geometry": {"coordinates":[9.4400348663,45.5812492371],"type":"Point"}
}