{
  "type": "Feature",
  "properties": {
    "iso:country":"IT",
    "sg:address":"00179 Roma",
    "sg:city":"Roma",
    "sg:orig_category":"Scuole E Servizi Scolastici. Ricerca, Selezione E Formazione Del Personale",
    "sg:phone":"+39 06 7835 9021",
    "sg:postcode":"00179",
    "sg:province":"Roma",
    "wof:name":"Di.li.eu. Diffusione Lingue Europee Snc Di Quaranta Francesca",
    "wof:placetype":"venue"
},
  "geometry": {"coordinates":[12.516816,41.875332],"type":"Point"}
}