{
  "type": "Feature",
  "properties": {
    "iso:country":"IT",
    "sg:address":"2, Via Dei Platani 41013 Castelfranco Emilia",
    "sg:city":"Castelfranco Emilia",
    "sg:classifiers":[
        {
            "category":"Shopping",
            "type":"Retail Goods"
        }
    ],
    "sg:phone":"+39 39059938152",
    "sg:postcode":"41013",
    "sg:province":"Modena",
    "sg:tags":[
        "finished",
        "-",
        "metallic"
    ],
    "wof:name":"Modelgaggio (s.n.c.)",
    "wof:placetype":"venue"
},
  "geometry": {"coordinates":[10.8677082062,44.6507530212],"type":"Point"}
}