{
  "type": "Feature",
  "properties": {
    "iso:country":"IT",
    "sg:address":"44100 Ferrara",
    "sg:city":"Ferrara",
    "sg:orig_category":"Macchine E Forniture Per Ecologia E Smaltimento Rifiuti",
    "sg:phone":"+39 0532 977897",
    "sg:postcode":"44100",
    "sg:province":"Ferrara",
    "wof:name":"Siderpol Ingegneria Srl",
    "wof:placetype":"venue"
},
  "geometry": {"coordinates":[11.641193,44.816753],"type":"Point"}
}