{
  "type": "Feature",
  "properties": {
    "iso:country":"IT",
    "sg:address":"20089 Rozzano",
    "sg:city":"Rozzano",
    "sg:orig_category":"Articoli Pulizia. Carta, Cartone E Prodotti Primari. Prodotti Cosmetici E Da Toeletta",
    "sg:phone":"+39 02 5750 6918",
    "sg:postcode":"20089",
    "sg:province":"Milano",
    "wof:name":"Bio Sac Sas Di Macchiarulo Matteo & C.",
    "wof:placetype":"venue"
},
  "geometry": {"coordinates":[9.170717,45.389835],"type":"Point"}
}