{
  "type": "Feature",
  "properties": {
    "addr:full":"00198 Roma Roma Roma 00198",
    "addr:postcode":"00198;00198",
    "iso:country":"IT",
    "sg:address":"00198 Roma",
    "sg:city":"Roma",
    "sg:orig_category":"Case Editrici",
    "sg:phone":"+39 06 841 7894",
    "sg:postcode":"00198",
    "sg:province":"Roma",
    "sg:website":"http://www.dedalo.it",
    "wof:name":"Libreria Dedalo Roma Srl",
    "wof:placetype":"venue"
},
  "geometry": {"coordinates":[12.499744,41.865868],"type":"Point"}
}