{
  "type": "Feature",
  "properties": {
    "iso:country":"IT",
    "sg:address":"37132 Verona",
    "sg:city":"Verona",
    "sg:orig_category":"Onoranze E Pompe Funebri",
    "sg:phone":"+39 045 973915",
    "sg:postcode":"37132",
    "sg:province":"Verona",
    "wof:name":"Onoranze Funebri Bona F.lli",
    "wof:placetype":"venue"
},
  "geometry": {"coordinates":[11.04975,45.431019],"type":"Point"}
}