{
  "type": "Feature",
  "properties": {
    "iso:country":"IT",
    "sg:address":"20089 Rozzano",
    "sg:city":"Rozzano",
    "sg:orig_category":"Prodotti Alimentari",
    "sg:phone":"+39 02 825 5484",
    "sg:postcode":"20089",
    "sg:province":"Milano",
    "wof:name":"Marella Rita",
    "wof:placetype":"venue"
},
  "geometry": {"coordinates":[9.1759309769,45.3818969727],"type":"Point"}
}