{
  "type": "Feature",
  "properties": {
    "addr:full":"22044 Inverigo Inverigo Como 22044",
    "addr:postcode":"22044;22044",
    "iso:country":"IT",
    "sg:address":"22044 Inverigo",
    "sg:city":"Inverigo",
    "sg:orig_category":"Materiali Edili",
    "sg:phone":"+39 031 698998",
    "sg:postcode":"22044",
    "sg:province":"Como",
    "wof:name":"Diemmeci S.r.l.",
    "wof:placetype":"venue"
},
  "geometry": {"coordinates":[9.217101,45.759335],"type":"Point"}
}