{
  "type": "Feature",
  "properties": {
    "addr:full":"20092 Cinisello Balsamo Cinisello Balsamo Milano 20092",
    "addr:postcode":"20092;20092",
    "iso:country":"IT",
    "sg:address":"20092 Cinisello Balsamo",
    "sg:city":"Cinisello Balsamo",
    "sg:orig_category":"Apparecchiature E Sistemi Per Imballaggio E Confezionamento",
    "sg:phone":"+39 02 6129 0507",
    "sg:postcode":"20092",
    "sg:province":"Milano",
    "wof:name":"F.g.z. Srl",
    "wof:placetype":"venue"
},
  "geometry": {"coordinates":[9.205515,45.561157],"type":"Point"}
}