{
  "type": "Feature",
  "properties": {
    "iso:country":"IT",
    "sg:address":"33080 Fiume Veneto",
    "sg:city":"Fiume Veneto",
    "sg:orig_category":"Brunitura Metalli",
    "sg:phone":"+39 0434 959049",
    "sg:postcode":"33080",
    "sg:province":"Pordenone",
    "wof:name":"Gobbo Oscar - Zinco Cromatura",
    "wof:placetype":"venue"
},
  "geometry": {"coordinates":[12.712812,45.943851],"type":"Point"}
}