{
  "type": "Feature",
  "properties": {
    "iso:country":"IT",
    "sg:address":"119, Via Classicana 48100 Ravenna",
    "sg:city":"Ravenna",
    "sg:classifiers":[
        {
            "category":"Utilities",
            "subcategory":"Electric",
            "type":"Services"
        }
    ],
    "sg:phone":"+39 0544 435511",
    "sg:postcode":"48100",
    "sg:province":"Ravenna",
    "sg:tags":[
        "energy"
    ],
    "wof:name":"Saipem (s.p.a.)",
    "wof:placetype":"venue"
},
  "geometry": {"coordinates":[12.225,44.363888],"type":"Point"}
}