{
  "type": "Feature",
  "properties": {
    "addr:full":"50013 Campi Bisenzio Campi Bisenzio Firenze 50013",
    "addr:postcode":"50013;50013",
    "addr:street":"Bisenzio",
    "iso:country":"IT",
    "sg:address":"50013 Campi Bisenzio",
    "sg:city":"Campi Bisenzio",
    "sg:orig_category":"Calzature, Pelletterie E Pelli",
    "sg:phone":"+39 055 896 0331",
    "sg:postcode":"50013",
    "sg:province":"Firenze",
    "wof:name":"Guido Falcini Spa",
    "wof:placetype":"venue"
},
  "geometry": {"coordinates":[11.129271,43.817513],"type":"Point"}
}