{
  "type": "Feature",
  "properties": {
    "addr:full":"80044 Ottaviano Ottaviano Napoli 80044",
    "addr:postcode":"80044;80044",
    "iso:country":"IT",
    "sg:address":"80044 Ottaviano",
    "sg:city":"Ottaviano",
    "sg:orig_category":"Tessuti E Stoffe",
    "sg:phone":"+39 081 528 8879",
    "sg:postcode":"80044",
    "sg:province":"Napoli",
    "wof:name":"Tessil Company Srl",
    "wof:placetype":"venue"
},
  "geometry": {"coordinates":[14.550258,40.841335],"type":"Point"}
}