{
  "type": "Feature",
  "properties": {
    "iso:country":"IT",
    "sg:address":"Via Melfi; Rapolla; 85027",
    "sg:city":"Rapolla",
    "sg:classifiers":[
        {
            "category":"Banks & Credit Unions",
            "subcategory":"Bank",
            "type":"Services"
        }
    ],
    "sg:phone":"+39 0972 760030",
    "sg:postcode":"85027",
    "sg:province":"Potenza",
    "wof:name":"Banca Operaia",
    "wof:placetype":"venue"
},
  "geometry": {"coordinates":[15.67134,40.978188],"type":"Point"}
}