{
  "type": "Feature",
  "properties": {
    "iso:country":"IT",
    "sg:address":"00040 Nemi",
    "sg:city":"Nemi",
    "sg:orig_category":"Macchine, Impianti Ed Attrezzature Per Industria Alimentare E Bevande. Macchine E Impianti Per Attivita' Commerciali Ed Artigianali",
    "sg:phone":"+39 06 936 2395",
    "sg:postcode":"00040",
    "sg:province":"Roma",
    "wof:name":"Orzelleca Nicola",
    "wof:placetype":"venue"
},
  "geometry": {"coordinates":[12.706259,41.69487],"type":"Point"}
}