{
  "type": "Feature",
  "properties": {
    "iso:country":"IT",
    "sg:address":"33100 Udine",
    "sg:city":"Udine",
    "sg:classifiers":[
        {
            "category":"Wholesale",
            "subcategory":"Machinery & Supplies",
            "type":"Manufacturing & Wholesale Goods"
        }
    ],
    "sg:phone":"+39 0432 531351",
    "sg:postcode":"33100",
    "sg:province":"Udine",
    "sg:tags":[
        "product",
        "industrial",
        "equipment",
        "engineering",
        "mechanical",
        "electronic"
    ],
    "wof:name":"Idraulica Srl",
    "wof:placetype":"venue"
},
  "geometry": {"coordinates":[13.226469,46.056271],"type":"Point"}
}