{
  "type": "Feature",
  "properties": {
    "iso:country":"IT",
    "sg:address":"27, Via Roma 22070 Guanzate",
    "sg:city":"Guanzate",
    "sg:classifiers":[
        {
            "category":"Shopping",
            "subcategory":"Crafts & Fabrics",
            "type":"Retail Goods"
        }
    ],
    "sg:phone":"+39 39031976042",
    "sg:postcode":"22070",
    "sg:province":"Como",
    "wof:name":"Gidaltex (s.p.a.)",
    "wof:placetype":"venue"
},
  "geometry": {"coordinates":[9.0515756607,45.7590293884],"type":"Point"}
}