{
  "type": "Feature",
  "properties": {
    "iso:country":"IT",
    "sg:address":"20154 Milano",
    "sg:city":"Milano",
    "sg:orig_category":"Cinema, Cameras, Optical Instruments",
    "sg:phone":"+39 02 345 1333",
    "sg:postcode":"20154",
    "sg:province":"Milano",
    "sg:website":"http://www.exitrental.it",
    "wof:name":"Exit Srl",
    "wof:placetype":"venue"
},
  "geometry": {"coordinates":[9.159869,45.487904],"type":"Point"}
}