{
  "type": "Feature",
  "properties": {
    "iso:country":"IT",
    "sg:address":"3, Via Corridoni 60019 Senigallia",
    "sg:city":"Senigallia",
    "sg:classifiers":[
        {
            "category":"Travel",
            "subcategory":"Travel Agent",
            "type":"Entertainment"
        }
    ],
    "sg:phone":"+39 071 792 7623",
    "sg:postcode":"60019",
    "sg:province":"Ancona",
    "sg:tags":[
        "business"
    ],
    "wof:name":"Hotel Duchi Della Rovere Srl",
    "wof:placetype":"venue"
},
  "geometry": {"coordinates":[13.221817,43.716351],"type":"Point"}
}