{
  "type": "Feature",
  "properties": {
    "addr:full":"48018 Faenza Faenza Ravenna 48018",
    "addr:postcode":"48018;48018",
    "iso:country":"IT",
    "sg:address":"48018 Faenza",
    "sg:city":"Faenza",
    "sg:orig_category":"Manufacturers: Prefabbricati. Forniture Per Edilizia E Lavori Pubblici",
    "sg:phone":"+39 0546 611155",
    "sg:postcode":"48018",
    "sg:province":"Ravenna",
    "wof:name":"Erregi Manufatti Snc",
    "wof:placetype":"venue"
},
  "geometry": {"coordinates":[11.981009,44.305965],"type":"Point"}
}