{
  "type": "Feature",
  "properties": {
    "iso:country":"IT",
    "sg:address":"96100 Siracusa",
    "sg:city":"Siracusa",
    "sg:orig_category":"Servizi Ausiliari Dei Mezzi Di Trasporto",
    "sg:phone":"+39 0931 60050",
    "sg:postcode":"96100",
    "sg:province":"Siracusa",
    "wof:name":"Autorimessa Autolavaggio Giudice",
    "wof:placetype":"venue"
},
  "geometry": {"coordinates":[15.291353,37.077969],"type":"Point"}
}