{
  "type": "Feature",
  "properties": {
    "addr:full":"20020 Ceriano Laghetto Ceriano Laghetto Milano 20020",
    "addr:postcode":"20020;20020",
    "iso:country":"IT",
    "sg:address":"20020 Ceriano Laghetto",
    "sg:city":"Ceriano Laghetto",
    "sg:orig_category":"Forniture Per Agricoltura E Zootecnia",
    "sg:phone":"+39 02 966 3183",
    "sg:postcode":"20020",
    "sg:province":"Milano",
    "wof:name":"Vismara Sergio",
    "wof:placetype":"venue"
},
  "geometry": {"coordinates":[9.0843696594,45.6337242126],"type":"Point"}
}