{
  "type": "Feature",
  "properties": {
    "iso:country":"IT",
    "sg:address":"Via Nazionale 54011 Aulla",
    "sg:city":"Aulla",
    "sg:classifiers":[
        {
            "category":"Manufacturing",
            "subcategory":"Tools & Machinery",
            "type":"Manufacturing & Wholesale Goods"
        }
    ],
    "sg:phone":"+39 0187 421650",
    "sg:postcode":"54011",
    "sg:province":"Massa-Carrara",
    "sg:tags":[
        "environment",
        "equipment",
        "-"
    ],
    "wof:name":"Lunigiana Acque S.p.a.",
    "wof:placetype":"venue"
},
  "geometry": {"coordinates":[9.967989,44.215046],"type":"Point"}
}