{
  "type": "Feature",
  "properties": {
    "iso:country":"IT",
    "sg:address":"67, Via Gardesana 25080 Prevalle",
    "sg:city":"Prevalle",
    "sg:classifiers":[
        {
            "category":"Manufacturing",
            "subcategory":"Lumber",
            "type":"Manufacturing & Wholesale Goods"
        }
    ],
    "sg:phone":"+39 39030603301",
    "sg:postcode":"25080",
    "sg:province":"Brescia",
    "sg:tags":[
        "wood"
    ],
    "wof:name":"Imbal Legno Di Scalfi Adriano E C. (s.n.c.)",
    "wof:placetype":"venue"
},
  "geometry": {"coordinates":[10.41773,45.553818],"type":"Point"}
}