{
  "type": "Feature",
  "properties": {
    "iso:country":"IT",
    "sg:address":"00172 Roma",
    "sg:city":"Roma",
    "sg:orig_category":"Editing - Agenzie E Studi",
    "sg:phone":"+39 06 242 8095",
    "sg:postcode":"00172",
    "sg:province":"Roma",
    "wof:name":"Di. Pi. Laser Snc",
    "wof:placetype":"venue"
},
  "geometry": {"coordinates":[12.572833,41.880943],"type":"Point"}
}