{
  "type": "Feature",
  "properties": {
    "addr:full":"80136 Napoli Napoli Napoli 80136",
    "addr:housenumber":"80136",
    "addr:postcode":"80136",
    "iso:country":"IT",
    "sg:address":"80136 Napoli",
    "sg:city":"Napoli",
    "sg:orig_category":"Fotografia - Servizi, Studi, Sviluppo E Stampa",
    "sg:phone":"+39 081 564 5119",
    "sg:postcode":"80136",
    "sg:province":"Napoli",
    "wof:name":"Blu Studio Di Irollo Francesco",
    "wof:placetype":"venue"
},
  "geometry": {"coordinates":[14.2736873627,40.8986816406],"type":"Point"}
}