{
  "type": "Feature",
  "properties": {
    "iso:country":"IT",
    "sg:address":"41012 Carpi",
    "sg:city":"Carpi",
    "sg:orig_category":"Accessori Moda D'abbigliamento. Shopping",
    "sg:phone":"+39 059 693014",
    "sg:postcode":"41012",
    "sg:province":"Modena",
    "wof:name":"Cappellificio Lugli Ennio & Rossi Milvia (s.n.c.)",
    "wof:placetype":"venue"
},
  "geometry": {"coordinates":[10.878419,44.657887],"type":"Point"}
}