{
  "type": "Feature",
  "properties": {
    "iso:country":"IT",
    "sg:address":"20124 Milano",
    "sg:city":"Milano",
    "sg:orig_category":"Elettrotecnica Industriale, Prodotti E Apparecchiature. Elettronica Industriale, Prodotti E Apparecchiature. Macchine, Strumenti Ed Apparecchi Per Attivita' Industriali",
    "sg:phone":"+39 02 678491",
    "sg:postcode":"20124",
    "sg:province":"Milano",
    "wof:name":"Ampere S.p.a.",
    "wof:placetype":"venue"
},
  "geometry": {"coordinates":[9.207256,45.484005],"type":"Point"}
}