{
  "type": "Feature",
  "properties": {
    "iso:country":"IT",
    "sg:address":"19, Via Pietrunto F. 86100 Campobasso",
    "sg:city":"Campobasso",
    "sg:classifiers":[
        {
            "category":"Banks & Credit Unions",
            "subcategory":"Bank",
            "type":"Services"
        }
    ],
    "sg:phone":"+39 390 874 4071",
    "sg:postcode":"86100",
    "sg:province":"Campobasso",
    "sg:tags":[
        "banking",
        "institution"
    ],
    "wof:name":"Rolo Banca 1473 (s.p.a.)",
    "wof:placetype":"venue"
},
  "geometry": {"coordinates":[14.65947,41.558994],"type":"Point"}
}