{
  "type": "Feature",
  "properties": {
    "iso:country":"IT",
    "sg:address":"00122 Lido Di Ostia",
    "sg:orig_category":"Servizi Per Lo Sport E Il Tempo Libero. Servizi Ausiliari Dei Mezzi Di Trasporto",
    "sg:phone":"+39 06 562 2959",
    "sg:postcode":"00122",
    "sg:province":"Roma",
    "wof:name":"Il Porticciolo Di Ostia Srl",
    "wof:placetype":"venue"
},
  "geometry": {"coordinates":[12.305161,41.720112],"type":"Point"}
}