{
  "type": "Feature",
  "properties": {
    "iso:country":"IT",
    "sg:address":"20060 Trezzano Rosa",
    "sg:city":"Trezzano Rosa",
    "sg:orig_category":"Scuole E Servizi Scolastici. Ospedali E Servizi Sanitari",
    "sg:phone":"+39 02 9201 0026",
    "sg:postcode":"20060",
    "sg:province":"Milano",
    "wof:name":"Coop. Sociale Castello Servizi Soc. Coop. Srl",
    "wof:placetype":"venue"
},
  "geometry": {"coordinates":[9.489611,45.583958],"type":"Point"}
}