{
  "type": "Feature",
  "properties": {
    "addr:full":"205, Via Amerina 05022 Amelia Amelia Terni 05022",
    "addr:housenumber":"205",
    "addr:postcode":"05022;05022",
    "addr:street":"Via Amerina",
    "iso:country":"IT",
    "sg:address":"205, Via Amerina 05022 Amelia",
    "sg:city":"Amelia",
    "sg:classifiers":[
        {
            "category":"Shopping",
            "type":"Retail Goods"
        }
    ],
    "sg:phone":"+39 0744 981241",
    "sg:postcode":"05022",
    "sg:province":"Terni",
    "sg:tags":[
        "finished",
        "-",
        "metallic"
    ],
    "wof:name":"Cerasi & C. S.a.s.",
    "wof:placetype":"venue"
},
  "geometry": {"coordinates":[12.4860248566,42.5382156372],"type":"Point"}
}