{
  "type": "Feature",
  "properties": {
    "addr:full":"Via Biassa 77; La Spezia; 16149 Genova 16149",
    "addr:housenumber":"77",
    "addr:postcode":"16149;16149",
    "addr:street":"Via Biassa",
    "iso:country":"IT",
    "sg:address":"Via Biassa 77; La Spezia; 16149",
    "sg:classifiers":[
        {
            "category":"Banks & Credit Unions",
            "subcategory":"Bank",
            "type":"Services"
        }
    ],
    "sg:phone":"+39 0187 33417",
    "sg:postcode":"16149",
    "sg:province":"Genova",
    "wof:name":"Cassa Di Risparmio Della Spezia",
    "wof:placetype":"venue"
},
  "geometry": {"coordinates":[8.899701,44.412285],"type":"Point"}
}