{
  "type": "Feature",
  "properties": {
    "iso:country":"IT",
    "sg:address":"27010 Giussago",
    "sg:city":"Giussago",
    "sg:orig_category":"Accessori Dei Mezzi Di Trasporto",
    "sg:phone":"+39 0382 927190",
    "sg:postcode":"27010",
    "sg:province":"Pavia",
    "wof:name":"Saccinto Paola Servauto",
    "wof:placetype":"venue"
},
  "geometry": {"coordinates":[9.122741,45.304852],"type":"Point"}
}