{
  "type": "Feature",
  "properties": {
    "addr:full":"10010 Banchette Banchette Torino 10010",
    "addr:postcode":"10010;10010",
    "iso:country":"IT",
    "sg:address":"10010 Banchette",
    "sg:city":"Banchette",
    "sg:orig_category":"Dentisti Medici Chirurghi Ed Odontoiatri",
    "sg:phone":"+39 0125 612011",
    "sg:postcode":"10010",
    "sg:province":"Torino",
    "wof:name":"Palmieri Amedeo Franco",
    "wof:placetype":"venue"
},
  "geometry": {"coordinates":[7.800634861,45.4312095642],"type":"Point"}
}