{
  "type": "Feature",
  "properties": {
    "iso:country":"IT",
    "sg:address":"21100 Varese",
    "sg:city":"Varese",
    "sg:orig_category":"Arti Grafiche",
    "sg:phone":"+39 0332 222677",
    "sg:postcode":"21100",
    "sg:province":"Varese",
    "wof:name":"Grafica Esse Zeta Snc",
    "wof:placetype":"venue"
},
  "geometry": {"coordinates":[8.815313,45.838062],"type":"Point"}
}