{
  "type": "Feature",
  "properties": {
    "iso:country":"IT",
    "sg:address":"50013 Capalle",
    "sg:city":"Capalle",
    "sg:orig_category":"Macchine, Impianti Ed Attrezzature Per Abbigliamento E Pelletterie",
    "sg:phone":"+39 055 895 2297",
    "sg:postcode":"50013",
    "sg:province":"Firenze",
    "wof:name":"O. V. Ital 92 (s.a.s.)",
    "wof:placetype":"venue"
},
  "geometry": {"coordinates":[11.259764,43.774658],"type":"Point"}
}