{
  "type": "Feature",
  "properties": {
    "iso:country":"IT",
    "sg:address":"31029 Vittorio Veneto",
    "sg:city":"Vittorio Veneto",
    "sg:orig_category":"Autotrasporti",
    "sg:phone":"+39 0438 53415",
    "sg:postcode":"31029",
    "sg:province":"Treviso",
    "wof:name":"Barel Giuseppe & Figli Srl",
    "wof:placetype":"venue"
},
  "geometry": {"coordinates":[12.291592,45.97467],"type":"Point"}
}