{
  "type": "Feature",
  "properties": {
    "iso:country":"IT",
    "sg:address":"41100 Modena",
    "sg:city":"Modena",
    "sg:orig_category":"Apparecchiature E Sistemi Per Magazzinaggio E Movimentazione",
    "sg:phone":"+39 059 363443",
    "sg:postcode":"41100",
    "sg:province":"Modena",
    "wof:name":"Ti Emme Snc",
    "wof:placetype":"venue"
},
  "geometry": {"coordinates":[10.936594,44.641979],"type":"Point"}
}