{
  "type": "Feature",
  "properties": {
    "addr:full":"40/42, Via Cavour Camillo Benso 26900 Lodi Lodi Lodi 26900",
    "addr:housenumber":"40 / 42",
    "addr:postcode":"26900;26900",
    "addr:street":"Via Cavour Camillo Benso",
    "iso:country":"IT",
    "sg:address":"40/42, Via Cavour Camillo Benso 26900 Lodi",
    "sg:city":"Lodi",
    "sg:classifiers":[
        {
            "category":"Banks & Credit Unions",
            "subcategory":"Bank",
            "type":"Services"
        }
    ],
    "sg:phone":"+39 0371 549214",
    "sg:postcode":"26900",
    "sg:province":"Lodi",
    "sg:tags":[
        "banking",
        "institution"
    ],
    "wof:name":"Banca Popolare Di Lodi Soc.coop.a R L",
    "wof:placetype":"venue"
},
  "geometry": {"coordinates":[9.505144,45.314445],"type":"Point"}
}