{
  "type": "Feature",
  "properties": {
    "addr:full":"31036 Ospedaletto Ospedaletto Treviso 31036",
    "addr:postcode":"31036;31036",
    "iso:country":"IT",
    "sg:address":"31036 Ospedaletto",
    "sg:city":"Ospedaletto",
    "sg:orig_category":"Macchine E Forniture Per Ecologia E Smaltimento Rifiuti. Ricambi E Componenti Dei Mezzi Di Trasporto",
    "sg:phone":"+39 0422 730058",
    "sg:postcode":"31036",
    "sg:province":"Treviso",
    "wof:name":"Aeroglass Filtri (s.r.l.)",
    "wof:placetype":"venue"
},
  "geometry": {"coordinates":[12.102342,45.655933],"type":"Point"}
}