{
  "type": "Feature",
  "properties": {
    "iso:country":"IT",
    "sg:address":"62012 Civitanova Marche",
    "sg:city":"Civitanova Marche",
    "sg:orig_category":"Medici Specialisti - Varie Patologie",
    "sg:phone":"+39 0733 829611",
    "sg:postcode":"62012",
    "sg:province":"Macerata",
    "wof:name":"Di Mattia Nicola",
    "wof:placetype":"venue"
},
  "geometry": {"coordinates":[13.705146,43.295986],"type":"Point"}
}