{
  "type": "Feature",
  "properties": {
    "iso:country":"IT",
    "sg:address":"Via Aldo Moro 33/a; S. Giorgio A Cremano; 80046",
    "sg:classifiers":[
        {
            "category":"Banks & Credit Unions",
            "subcategory":"Bank",
            "type":"Services"
        }
    ],
    "sg:phone":"+39 081 574 5010",
    "sg:postcode":"80046",
    "sg:province":"Napoli",
    "wof:name":"Istituto Bancario, San Paolo Di Torino Spa",
    "wof:placetype":"venue"
},
  "geometry": {"coordinates":[14.345428,40.833591],"type":"Point"}
}