{
  "type": "Feature",
  "properties": {
    "addr:full":"Via G. Galilei 80 63019 Sant'elpidio A Mare Ascoli Piceno 63019",
    "addr:housenumber":"80",
    "addr:postcode":"63019;63019",
    "addr:street":"Via G. Galilei",
    "iso:country":"IT",
    "sg:address":"Via G. Galilei 80 63019 Sant'elpidio A Mare",
    "sg:classifiers":[
        {
            "category":"Sports & Exercise",
            "subcategory":"Gym",
            "type":"Entertainment"
        }
    ],
    "sg:phone":"+39 0734 861022",
    "sg:postcode":"63019",
    "sg:province":"Ascoli Piceno",
    "sg:tags":[
        "athletic",
        "ladies'",
        "stocking"
    ],
    "sg:website":"www.robertobotticelli.it",
    "wof:name":"Errebi Spa",
    "wof:placetype":"venue"
},
  "geometry": {"coordinates":[13.574977,42.8554],"type":"Point"}
}