{
  "type": "Feature",
  "properties": {
    "iso:country":"IT",
    "sg:address":"20124 Milano",
    "sg:city":"Milano",
    "sg:orig_category":"Ecologia - Studi Consulenza E Servizi",
    "sg:phone":"+39 02 2960 1562",
    "sg:postcode":"20124",
    "sg:province":"Milano",
    "wof:name":"Newpromo Srl",
    "wof:placetype":"venue"
},
  "geometry": {"coordinates":[9.198423,45.487419],"type":"Point"}
}