{
  "type": "Feature",
  "properties": {
    "addr:full":"Piazzale Pietro Galiani Z.i. 64030 Basciano Basciano Teramo 64030",
    "addr:postcode":"64030;64030",
    "addr:street":"Piazzale Pietro Galiani",
    "iso:country":"IT",
    "sg:address":"Piazzale Pietro Galiani Z.i. 64030 Basciano",
    "sg:city":"Basciano",
    "sg:classifiers":[
        {
            "category":"Manufacturing",
            "subcategory":"Metals",
            "type":"Manufacturing & Wholesale Goods"
        }
    ],
    "sg:phone":"+39 0861 650926",
    "sg:postcode":"64030",
    "sg:province":"Teramo",
    "sg:tags":[
        "aluminium"
    ],
    "sg:website":"www.traesud.com",
    "wof:name":"Trafilerie Emiliane Sud Spa",
    "wof:placetype":"venue"
},
  "geometry": {"coordinates":[13.698531,42.66127],"type":"Point"}
}