{
  "type": "Feature",
  "properties": {
    "addr:full":"57, Via Della Viaccia 59013 Montemurlo Montemurlo Prato 59013",
    "addr:postcode":"59013;59013",
    "addr:street":"Via Della Viaccia",
    "iso:country":"IT",
    "sg:address":"57, Via Della Viaccia 59013 Montemurlo",
    "sg:city":"Montemurlo",
    "sg:classifiers":[
        {
            "category":"Professional",
            "subcategory":"Engineering",
            "type":"Services"
        }
    ],
    "sg:phone":"+39 0574 680649",
    "sg:postcode":"59013",
    "sg:province":"Prato",
    "sg:tags":[
        "machine",
        "-",
        "mechanical"
    ],
    "wof:name":"Co.me.ta Textile Machinery Sas Di E. Guidarelli &",
    "wof:placetype":"venue"
},
  "geometry": {"coordinates":[11.035811,43.902672],"type":"Point"}
}