{
  "type": "Feature",
  "properties": {
    "addr:full":"Zona Industriale Mattei E. 62019 Recanati Recanati Macerata 62019",
    "addr:postcode":"62019;62019",
    "addr:street":"Zona Industriale Mattei E.",
    "iso:country":"IT",
    "sg:address":"Zona Industriale Mattei E. 62019 Recanati",
    "sg:city":"Recanati",
    "sg:classifiers":[
        {
            "category":"Manufacturing",
            "subcategory":"Paper Products",
            "type":"Manufacturing & Wholesale Goods"
        }
    ],
    "sg:phone":"+39 071 757 0359",
    "sg:postcode":"62019",
    "sg:province":"Macerata",
    "sg:tags":[
        "cardboard"
    ],
    "wof:name":"Zara Srl",
    "wof:placetype":"venue"
},
  "geometry": {"coordinates":[13.4562616348,43.3007469177],"type":"Point"}
}