{
  "type": "Feature",
  "properties": {
    "addr:full":"23, Via Trenta Gennaio 91100 Trapani Trapani Trapani 91100",
    "addr:postcode":"91100;91100",
    "addr:street":"Via Trenta Gennaio",
    "iso:country":"IT",
    "sg:address":"23, Via Trenta Gennaio 91100 Trapani",
    "sg:city":"Trapani",
    "sg:classifiers":[
        {
            "category":"Professional",
            "subcategory":"Business Services",
            "type":"Services"
        }
    ],
    "sg:phone":"+39 39092322511",
    "sg:postcode":"91100",
    "sg:province":"Trapani",
    "sg:tags":[
        "advice"
    ],
    "wof:name":"A.p.i. Associazione Piccole E Medie Industrie Della Provincia Di Trapani",
    "wof:placetype":"venue"
},
  "geometry": {"coordinates":[12.514634,38.018589],"type":"Point"}
}