{
  "type": "Feature",
  "properties": {
    "iso:country":"IT",
    "sg:address":"20127 Milano",
    "sg:city":"Milano",
    "sg:orig_category":"Pubblicita', Marketing E Comunicazione",
    "sg:phone":"+39 02 2614 2153",
    "sg:postcode":"20127",
    "sg:province":"Milano",
    "sg:website":"http://www.freedata.it",
    "wof:name":"Freedata Srl",
    "wof:placetype":"venue"
},
  "geometry": {"coordinates":[9.2191257477,45.4909210205],"type":"Point"}
}