{
  "type": "Feature",
  "properties": {
    "iso:country":"IT",
    "sg:address":"34148 Trieste",
    "sg:city":"Trieste",
    "sg:classifiers":[
        {
            "category":"Wholesale",
            "subcategory":"Machinery & Supplies",
            "type":"Manufacturing & Wholesale Goods"
        }
    ],
    "sg:phone":"+39 040 814136",
    "sg:postcode":"34148",
    "sg:province":"Trieste",
    "sg:tags":[
        "activities",
        "industrial"
    ],
    "wof:name":"World Wide Trade Trieste Srl",
    "wof:placetype":"venue"
},
  "geometry": {"coordinates":[13.815152,45.618004],"type":"Point"}
}