{
  "type": "Feature",
  "properties": {
    "addr:full":"20090 Trezzano Naviglio Milano 20090",
    "addr:postcode":"20090;20090",
    "addr:street":"Trezzano Naviglio Milano",
    "iso:country":"IT",
    "sg:address":"20090 Trezzano Naviglio",
    "sg:orig_category":"Prodotti E Manufatti In Materie Plastiche",
    "sg:phone":"+39 02 445 3374",
    "sg:postcode":"20090",
    "sg:province":"Milano",
    "wof:name":"Femoplast",
    "wof:placetype":"venue"
},
  "geometry": {"coordinates":[9.0608549118,45.4197502136],"type":"Point"}
}