{
  "type": "Feature",
  "properties": {
    "iso:country":"IT",
    "sg:address":"Via Puccini 15 42018 San Martino In Rio",
    "sg:classifiers":[
        {
            "category":"Wholesale",
            "subcategory":"Metals & Minerals",
            "type":"Manufacturing & Wholesale Goods"
        }
    ],
    "sg:phone":"+39 0522 695129",
    "sg:postcode":"42018",
    "sg:province":"Reggio Nell'Emilia",
    "sg:tags":[
        "articles",
        "industrial"
    ],
    "sg:website":"www.salamiec.com",
    "wof:name":"Salami Silvano E C. S.n.c.",
    "wof:placetype":"venue"
},
  "geometry": {"coordinates":[10.7743520737,44.7333831787],"type":"Point"}
}