{
  "type": "Feature",
  "properties": {
    "addr:full":"6 Corso Vittorio Emanuele Iii, 67068 Scurcola Marsicana L'Aquila 67068",
    "addr:postcode":"67068;l'aquila 67068",
    "addr:street":"Corso Vittorio Emanuele Iii",
    "iso:country":"IT",
    "sg:address":"6 Corso Vittorio Emanuele Iii, 67068 Scurcola Marsicana",
    "sg:classifiers":[
        {
            "category":"Banks & Credit Unions",
            "subcategory":"Financial Services",
            "type":"Services"
        }
    ],
    "sg:phone":"+39 0863 561031",
    "sg:postcode":"67068",
    "sg:province":"L'Aquila",
    "sg:tags":[
        "banking",
        "finance",
        "insurance"
    ],
    "wof:name":"Banca Di Credito Cooperativo Di Roma",
    "wof:placetype":"venue"
},
  "geometry": {"coordinates":[13.4313716888,42.0391159058],"type":"Point"}
}