{
  "type": "Feature",
  "properties": {
    "iso:country":"IT",
    "sg:address":"35129 Padova",
    "sg:city":"Padova",
    "sg:orig_category":"Professionisti - Studi E Servizi Ed Associazioni Di Interesse Aziendale. Associazioni Ed Organismi Di Interesse Pubblico",
    "sg:phone":"+39 049 807 5088",
    "sg:postcode":"35129",
    "sg:province":"Padova",
    "sg:website":"http://www.pd.cna.it",
    "wof:name":"Cna - Confederazione Nazionale Dell'artigianato E Della Piccola E Media Impresa",
    "wof:placetype":"venue"
},
  "geometry": {"coordinates":[11.9259986877,45.4266471863],"type":"Point"}
}