{
  "type": "Feature",
  "properties": {
    "iso:country":"IT",
    "sg:address":"20127 Milano",
    "sg:city":"Milano",
    "sg:orig_category":"Servizi Vari Di Interesse Pubblico",
    "sg:phone":"+39 02 2611 1186",
    "sg:postcode":"20127",
    "sg:province":"Milano",
    "wof:name":"Astra Esoterica Di Giansanti Rita",
    "wof:placetype":"venue"
},
  "geometry": {"coordinates":[9.217298,45.495945],"type":"Point"}
}