{
  "type": "Feature",
  "properties": {
    "addr:full":"00030 S.cesareo Roma 00030",
    "addr:postcode":"00030;00030",
    "addr:street":"S.Cesareo Roma",
    "iso:country":"IT",
    "sg:address":"00030 S.cesareo",
    "sg:orig_category":"Frigotecnica, Apparecchiature E Servizi. Climatizzazione E Condizionamento, Apparecchiature E Servizi",
    "sg:phone":"+39 06 9559 9717",
    "sg:postcode":"00030",
    "sg:province":"Roma",
    "sg:website":"http://www.pmeparts.it",
    "wof:name":"P.m.e. Srl",
    "wof:placetype":"venue"
},
  "geometry": {"coordinates":[12.758348465,41.9589805603],"type":"Point"}
}