{
  "type": "Feature",
  "properties": {
    "iso:country":"IT",
    "sg:address":"12062 Cherasco",
    "sg:city":"Cherasco",
    "sg:orig_category":"Macchine E Forniture Per Arredamento E Industria Del Legno. Colori, Vernici E Smalti",
    "sg:phone":"+39 0172 489082",
    "sg:postcode":"12062",
    "sg:province":"Cuneo",
    "wof:name":"Burdisso & C. Snc",
    "wof:placetype":"venue"
},
  "geometry": {"coordinates":[7.858262,44.648556],"type":"Point"}
}