{
  "type": "Feature",
  "properties": {
    "iso:country":"IT",
    "sg:address":"44020 Ostellato",
    "sg:city":"Dogato",
    "sg:orig_category":"Elettronica Professionale E Di Consumo. Musica. Accessori Dei Mezzi Di Trasporto",
    "sg:phone":"+39 0533 651111",
    "sg:postcode":"44020",
    "sg:province":"Ferrara",
    "wof:name":"Car Stereo Di Scaranaro Gino",
    "wof:placetype":"venue"
},
  "geometry": {"coordinates":[11.871703,44.762337],"type":"Point"}
}