{
  "type": "Feature",
  "properties": {
    "addr:full":"22, Via Monte Carega 37057 San Giovanni Lupatoto San Giovanni Lupatoto Verona 37057",
    "addr:postcode":"37057;37057",
    "addr:street":"Via Monte Carega;Verona",
    "iso:country":"IT",
    "sg:address":"22, Via Monte Carega 37057 San Giovanni Lupatoto",
    "sg:city":"San Giovanni Lupatoto",
    "sg:classifiers":[
        {
            "category":"Manufacturing",
            "subcategory":"Metals",
            "type":"Manufacturing & Wholesale Goods"
        }
    ],
    "sg:phone":"+39 045 875 0032",
    "sg:postcode":"37057",
    "sg:province":"Verona",
    "sg:tags":[
        "processing"
    ],
    "wof:name":"Olma",
    "wof:placetype":"venue"
},
  "geometry": {"coordinates":[11.0282268524,45.3996963501],"type":"Point"}
}