{
  "type": "Feature",
  "properties": {
    "iso:country":"IT",
    "sg:address":"08020 Irgoli",
    "sg:city":"Irgoli",
    "sg:classifiers":[
        {
            "category":"Health Services",
            "subcategory":"Health Practitioner",
            "type":"Services"
        }
    ],
    "sg:phone":"+39 0784 979011",
    "sg:postcode":"08020",
    "sg:province":"Nuoro",
    "sg:tags":[
        "medici"
    ],
    "wof:name":"Cordone Dr. Pietro Medi Slim",
    "wof:placetype":"venue"
},
  "geometry": {"coordinates":[9.631574,40.411575],"type":"Point"}
}