{
  "type": "Feature",
  "properties": {
    "iso:country":"IT",
    "sg:address":"Via Einstein 42 70031 Andria",
    "sg:city":"Andria",
    "sg:classifiers":[
        {
            "category":"Shopping",
            "subcategory":"Clothing, Apparel, & Fashions",
            "type":"Retail Goods"
        }
    ],
    "sg:phone":"+39 0883 541183",
    "sg:postcode":"70031",
    "sg:province":"Bari",
    "sg:tags":[
        "lingerie"
    ],
    "sg:website":"www.iracorsetteria.it",
    "wof:name":"Corsetteria Ira Di Lattanzio Gaetano",
    "wof:placetype":"venue"
},
  "geometry": {"coordinates":[16.869291,41.126053],"type":"Point"}
}