{
  "type": "Feature",
  "properties": {
    "iso:country":"IT",
    "sg:address":"46044 Goito",
    "sg:city":"Goito",
    "sg:orig_category":"Elettromeccanica",
    "sg:phone":"+39 0376 604364",
    "sg:postcode":"46044",
    "sg:province":"Mantova",
    "wof:name":"Elettromeccanica Grassi Sergio",
    "wof:placetype":"venue"
},
  "geometry": {"coordinates":[10.727302,45.193909],"type":"Point"}
}