{
  "type": "Feature",
  "properties": {
    "iso:country":"IT",
    "sg:address":"38068 Rovereto",
    "sg:city":"Rovereto",
    "sg:orig_category":"Termotecnica E Riscaldamento, Apparecchiature E Servizi",
    "sg:phone":"+39 0464 494949",
    "sg:postcode":"38068",
    "sg:province":"Trento",
    "sg:website":"http://www.gentilini.it",
    "wof:name":"Gentilini Spa",
    "wof:placetype":"venue"
},
  "geometry": {"coordinates":[11.039789,45.910648],"type":"Point"}
}