{
  "type": "Feature",
  "properties": {
    "iso:country":"IT",
    "sg:address":"98055 Lipari",
    "sg:city":"Lipari",
    "sg:orig_category":"Alberghi",
    "sg:phone":"+39 090 981 2876",
    "sg:postcode":"98055",
    "sg:province":"Messina",
    "sg:website":"http://www.hotelposeidonlipari.com",
    "wof:name":"Hotel Poseidon",
    "wof:placetype":"venue"
},
  "geometry": {"coordinates":[14.927204,38.493664],"type":"Point"}
}