{
  "type": "Feature",
  "properties": {
    "iso:country":"IT",
    "sg:address":"Zona Industriale Santafiora 52037 Sansepolcro",
    "sg:city":"Sansepolcro",
    "sg:orig_category":"Ladies' Knitwear",
    "sg:phone":"+39 0575 7451",
    "sg:postcode":"52037",
    "sg:province":"Arezzo",
    "wof:name":"Cose Di Lana Spa",
    "wof:placetype":"venue"
},
  "geometry": {"coordinates":[11.863062,43.471203],"type":"Point"}
}