{
  "type": "Feature",
  "properties": {
    "iso:country":"IT",
    "sg:address":"60030 Maiolati Spontini",
    "sg:city":"Maiolati Spontini",
    "sg:orig_category":"Materiali Edili",
    "sg:phone":"+39 0731 701225",
    "sg:postcode":"60030",
    "sg:province":"Ancona",
    "wof:name":"Grondex Di Ceppi Claudio & C. Snc",
    "wof:placetype":"venue"
},
  "geometry": {"coordinates":[13.140576,43.504269],"type":"Point"}
}