{
  "type": "Feature",
  "properties": {
    "addr:full":"Via Polveriera 80035 Nola Nola Napoli 80035",
    "addr:postcode":"80035;80035",
    "addr:street":"Via Polveriera",
    "iso:country":"IT",
    "sg:address":"Via Polveriera 80035 Nola",
    "sg:city":"Nola",
    "sg:classifiers":[
        {
            "category":"Parking",
            "subcategory":"Lot",
            "type":"Transportation"
        }
    ],
    "sg:phone":"+39 081 823 8622",
    "sg:postcode":"80035",
    "sg:province":"Napoli",
    "sg:tags":[
        "transport",
        "road"
    ],
    "wof:name":"F.lli Esposito S.r.l.",
    "wof:placetype":"venue"
},
  "geometry": {"coordinates":[14.517166,40.926739],"type":"Point"}
}