{
  "type": "Feature",
  "properties": {
    "iso:country":"IT",
    "sg:address":"31011 Asolo",
    "sg:city":"Asolo",
    "sg:orig_category":"Servizi Ausiliari Di Certificati, Riproduzioni, Disegni E Foto",
    "sg:phone":"+39 0423 952830",
    "sg:postcode":"31011",
    "sg:province":"Treviso",
    "sg:website":"http://www.tipografia.com",
    "wof:name":"Tipografia Asolana Srl",
    "wof:placetype":"venue"
},
  "geometry": {"coordinates":[11.911716,45.787331],"type":"Point"}
}