{
  "type": "Feature",
  "properties": {
    "addr:full":"61013 Fratte Pesaro E Urbino 61013",
    "addr:postcode":"61013;61013",
    "iso:country":"IT",
    "sg:address":"61013 Fratte",
    "sg:orig_category":"Materiali Edili",
    "sg:phone":"+39 0541 974617",
    "sg:postcode":"61013",
    "sg:province":"Pesaro E Urbino",
    "wof:name":"Gessificio F.lli Prioli Alfonso E Lino E C.(s.n.c.)",
    "wof:placetype":"venue"
},
  "geometry": {"coordinates":[12.529803,43.633556],"type":"Point"}
}