{
  "type": "Feature",
  "properties": {
    "iso:country":"IT",
    "sg:address":"21013 Gallarate",
    "sg:city":"Gallarate",
    "sg:orig_category":"Pubblicita', Marketing E Comunicazione",
    "sg:phone":"+39 0331 701401",
    "sg:postcode":"21013",
    "sg:province":"Varese",
    "wof:name":"Pozzi Carmen",
    "wof:placetype":"venue"
},
  "geometry": {"coordinates":[8.8514957428,45.7899246216],"type":"Point"}
}