{
  "type": "Feature",
  "properties": {
    "iso:country":"IT",
    "sg:address":"06128 Perugia",
    "sg:city":"Perugia",
    "sg:orig_category":"Agricoltura, Orticoltura E Floricoltura",
    "sg:phone":"+39 075 528 0303",
    "sg:postcode":"06128",
    "sg:province":"Perugia",
    "sg:website":"http://www.lafioritapg.it",
    "wof:name":"La Fiorita",
    "wof:placetype":"venue"
},
  "geometry": {"coordinates":[12.360706,43.093658],"type":"Point"}
}