{
  "type": "Feature",
  "properties": {
    "addr:full":"53, Via I Maggio 37069 Villafranca Di Verona Villafranca di Verona Verona 37069",
    "addr:postcode":"37069;37069",
    "addr:street":"Via I Maggio;Verona",
    "iso:country":"IT",
    "sg:address":"53, Via I Maggio 37069 Villafranca Di Verona",
    "sg:city":"Villafranca di Verona",
    "sg:classifiers":[
        {
            "category":"Manufacturing",
            "subcategory":"Metals",
            "type":"Manufacturing & Wholesale Goods"
        }
    ],
    "sg:phone":"+39 045 630 2222",
    "sg:postcode":"37069",
    "sg:province":"Verona",
    "sg:tags":[
        "metallurgy",
        "metalworking"
    ],
    "wof:name":"Fover Alluminio (s.r.l.)",
    "wof:placetype":"venue"
},
  "geometry": {"coordinates":[10.9538679123,45.4220275879],"type":"Point"}
}