{
  "type": "Feature",
  "properties": {
    "iso:country":"IT",
    "sg:address":"66040 Perano",
    "sg:city":"Perano",
    "sg:orig_category":"Alberghi",
    "sg:phone":"+39 0872 898726",
    "sg:postcode":"66040",
    "sg:province":"Chieti",
    "wof:name":"Impicciatore Adriana",
    "wof:placetype":"venue"
},
  "geometry": {"coordinates":[14.395019,42.10424],"type":"Point"}
}