{
  "type": "Feature",
  "properties": {
    "iso:country":"IT",
    "sg:address":"33, Via Galoppat 33087 Pasiano Di Pordenone",
    "sg:city":"Pasiano",
    "sg:classifiers":[
        {
            "category":"Home & Garden",
            "subcategory":"Home Furnishings",
            "type":"Retail Goods"
        }
    ],
    "sg:phone":"+39 0434 629111",
    "sg:postcode":"33087",
    "sg:province":"Pordenone",
    "sg:tags":[
        "household"
    ],
    "wof:name":"Mobilificio San Giacomo S.p.a.",
    "wof:placetype":"venue"
},
  "geometry": {"coordinates":[12.614916,45.873005],"type":"Point"}
}