{
  "type": "Feature",
  "properties": {
    "iso:country":"IT",
    "sg:address":"04018 Sezze",
    "sg:city":"Sezze",
    "sg:orig_category":"Prodotti Vari In Metallo. Articoli Per Imballaggio E Confezionamento",
    "sg:phone":"+39 0773 877461",
    "sg:postcode":"04018",
    "sg:province":"Latina",
    "wof:name":"Engi & Co. Srl",
    "wof:placetype":"venue"
},
  "geometry": {"coordinates":[13.0702648163,41.4986534119],"type":"Point"}
}