{
  "type": "Feature",
  "properties": {
    "iso:country":"IT",
    "sg:address":"35127 Padova",
    "sg:city":"Padova",
    "sg:orig_category":"Macchine Utensili E Impianti",
    "sg:phone":"+39 049 870 0111",
    "sg:postcode":"35127",
    "sg:province":"Padova",
    "wof:name":"Sdp Engineering Srl",
    "wof:placetype":"venue"
},
  "geometry": {"coordinates":[11.934061,45.387646],"type":"Point"}
}