{
  "type": "Feature",
  "properties": {
    "iso:country":"IT",
    "sg:address":"20129 Milano",
    "sg:city":"Milano",
    "sg:orig_category":"Materiali E Componenti Elettronici",
    "sg:phone":"+39 02 2951 4026",
    "sg:postcode":"20129",
    "sg:province":"Milano",
    "sg:website":"http://www.ame.it",
    "wof:name":"A.m.e. Srl",
    "wof:placetype":"venue"
},
  "geometry": {"coordinates":[9.219619,45.475754],"type":"Point"}
}