{
  "type": "Feature",
  "properties": {
    "addr:full":"26900 Lodi Lodi Lodi 26900",
    "addr:postcode":"26900;26900",
    "iso:country":"IT",
    "sg:address":"26900 Lodi",
    "sg:city":"Lodi",
    "sg:orig_category":"Forniture Per Edilizia E Lavori Pubblici. Forniture Industriali Per Prevenzione, Controllo E Sicurezza",
    "sg:phone":"+39 0371 428202",
    "sg:postcode":"26900",
    "sg:province":"Lodi",
    "sg:website":"http://www.ilcartello.com",
    "wof:name":"Il Cartello Srl",
    "wof:placetype":"venue"
},
  "geometry": {"coordinates":[9.5107059479,45.3100395203],"type":"Point"}
}