{
  "type": "Feature",
  "properties": {
    "iso:country":"IT",
    "sg:address":"3, Viale Dell' Industria 20020 Busto Garolfo",
    "sg:city":"Busto Garolfo",
    "sg:classifiers":[
        {
            "category":"Shopping",
            "subcategory":"Crafts & Fabrics",
            "type":"Retail Goods"
        }
    ],
    "sg:phone":"+39 0331 569231",
    "sg:postcode":"20020",
    "sg:province":"Milano",
    "wof:name":"Euronastri S.r.l.",
    "wof:placetype":"venue"
},
  "geometry": {"coordinates":[8.8674049377,45.5597839355],"type":"Point"}
}