{
  "type": "Feature",
  "properties": {
    "iso:country":"IT",
    "sg:address":"35026 Conselve",
    "sg:city":"Conselve",
    "sg:orig_category":"Forniture Per Attivita' Industriali",
    "sg:phone":"+39 049 538 5343",
    "sg:postcode":"35026",
    "sg:province":"Padova",
    "wof:name":"La Carita (s.r.l.)",
    "wof:placetype":"venue"
},
  "geometry": {"coordinates":[11.9012060165,45.2221260071],"type":"Point"}
}