{
  "type": "Feature",
  "properties": {
    "iso:country":"IT",
    "sg:address":"20, Via Giovanni Da Procida 70033 Corato",
    "sg:city":"Corato",
    "sg:orig_category":"Miscellaneous Products",
    "sg:phone":"+39 080 872 4621",
    "sg:postcode":"70033",
    "sg:province":"Bari",
    "wof:name":"Lotito",
    "wof:placetype":"venue"
},
  "geometry": {"coordinates":[16.4141426086,41.1527252197],"type":"Point"}
}