{
  "type": "Feature",
  "properties": {
    "iso:country":"IT",
    "sg:address":"25030 Adro",
    "sg:city":"Adro",
    "sg:orig_category":"Macchine, Impianti Ed Attrezzature Per Agricoltura E Zootecnia. Forniture Per Agricoltura E Zootecnia",
    "sg:phone":"+39 030 735 6190",
    "sg:postcode":"25030",
    "sg:province":"Brescia",
    "sg:website":"http://www.valloncini.it",
    "wof:name":"Valloncini Srl",
    "wof:placetype":"venue"
},
  "geometry": {"coordinates":[9.998578,45.606014],"type":"Point"}
}