{
  "type": "Feature",
  "properties": {
    "addr:full":"37135 Verona Verona Verona 37135",
    "addr:postcode":"37135;37135",
    "iso:country":"IT",
    "sg:address":"37135 Verona",
    "sg:city":"Verona",
    "sg:orig_category":"Fiere, Mostre E Saloni - Allestimento E Servizi",
    "sg:phone":"+39 045 580011",
    "sg:postcode":"37135",
    "sg:province":"Verona",
    "wof:name":"B.p.s. Snc",
    "wof:placetype":"venue"
},
  "geometry": {"coordinates":[10.9834270477,45.4123306274],"type":"Point"}
}