{
  "type": "Feature",
  "properties": {
    "iso:country":"IT",
    "sg:address":"98064 Librizzi",
    "sg:city":"Librizzi",
    "sg:orig_category":"Ristorazione E Locali Pubblici Affini. Servizi Per Lo Sport E Il Tempo Libero. Alberghi E Strutture Extra Alberghiere. Ristoranti Ed Esercizi Affini",
    "sg:phone":"+39 0941 32390",
    "sg:postcode":"98064",
    "sg:province":"Messina",
    "wof:name":"Azienda Agricola Acquachiara",
    "wof:placetype":"venue"
},
  "geometry": {"coordinates":[14.968091,38.081032],"type":"Point"}
}