{
  "type": "Feature",
  "properties": {
    "addr:full":"Via Forli 21 20010 Canegrate Canegrate Milano 20010",
    "addr:housenumber":"21",
    "addr:postcode":"20010;20010",
    "addr:street":"Via Forli",
    "iso:country":"IT",
    "sg:address":"Via Forli 21 20010 Canegrate",
    "sg:city":"Canegrate",
    "sg:classifiers":[
        {
            "category":"Manufacturing",
            "subcategory":"Printing",
            "type":"Manufacturing & Wholesale Goods"
        }
    ],
    "sg:phone":"+39 0331 407027",
    "sg:postcode":"20010",
    "sg:province":"Milano",
    "sg:tags":[
        "plastic"
    ],
    "sg:website":"www.elpiplast.it",
    "wof:name":"Elpiplast S.r.l.",
    "wof:placetype":"venue"
},
  "geometry": {"coordinates":[8.9086017609,45.561466217],"type":"Point"}
}