{
  "type": "Feature",
  "properties": {
    "iso:country":"IT",
    "sg:address":"90133 Palermo",
    "sg:city":"Palermo",
    "sg:orig_category":"Trattamenti Termici E Superficiali Metalli, Galvanotecnica",
    "sg:phone":"+39 091 617 5422",
    "sg:postcode":"90133",
    "sg:province":"Palermo",
    "wof:name":"Carmicino Giuseppe",
    "wof:placetype":"venue"
},
  "geometry": {"coordinates":[13.363691,38.114285],"type":"Point"}
}