{
  "type": "Feature",
  "properties": {
    "iso:country":"IT",
    "sg:address":"16161 Genova",
    "sg:city":"Genova",
    "sg:orig_category":"Box Prefabbricati",
    "sg:phone":"+39 010 745 7214",
    "sg:postcode":"16161",
    "sg:province":"Genova",
    "wof:name":"Salpa Di De Paoli - Parodi & C. Sas",
    "wof:placetype":"venue"
},
  "geometry": {"coordinates":[8.891389,44.436111],"type":"Point"}
}