{
  "type": "Feature",
  "properties": {
    "iso:country":"IT",
    "sg:address":"40, Via Oreno 20049 Concorezzo",
    "sg:city":"Concorezzo",
    "sg:classifiers":[
        {
            "category":"Professional",
            "subcategory":"Engineering",
            "type":"Services"
        }
    ],
    "sg:phone":"+39 039 604 1352",
    "sg:postcode":"20049",
    "sg:province":"Milano",
    "sg:tags":[
        "machine",
        "-",
        "mechanical"
    ],
    "wof:name":"Costruz. Meccaniche F.lli Fumagalli Srl",
    "wof:placetype":"venue"
},
  "geometry": {"coordinates":[9.341319,45.599766],"type":"Point"}
}