{
  "type": "Feature",
  "properties": {
    "addr:full":"38, Via Meucci Antonio 37036 San Martino Buon Albergo San Martino Buon Albergo Verona 37036",
    "addr:postcode":"37036;buon albergo;37036",
    "addr:street":"Via Meucci Antonio",
    "iso:country":"IT",
    "sg:address":"38, Via Meucci Antonio 37036 San Martino Buon Albergo",
    "sg:city":"San Martino Buon Albergo",
    "sg:classifiers":[
        {
            "category":"Home & Garden",
            "subcategory":"Home Furnishings",
            "type":"Retail Goods"
        }
    ],
    "sg:phone":"+39 045 878 0456",
    "sg:postcode":"37036",
    "sg:province":"Verona",
    "sg:tags":[
        "household"
    ],
    "wof:name":"G.m. Arredamenti S.r.l.",
    "wof:placetype":"venue"
},
  "geometry": {"coordinates":[11.109033,45.420284],"type":"Point"}
}