{
  "type": "Feature",
  "properties": {
    "addr:full":"19, Via Soardi 47900 Rimini Rimini Rimini 47900",
    "addr:postcode":"47900;47900",
    "addr:street":"Via Soardi",
    "iso:country":"IT",
    "sg:address":"19, Via Soardi 47900 Rimini",
    "sg:city":"Rimini",
    "sg:classifiers":[
        {
            "category":"Sports & Exercise",
            "subcategory":"Playing Field",
            "type":"Entertainment"
        }
    ],
    "sg:phone":"+39 0541 785646",
    "sg:postcode":"47900",
    "sg:province":"Rimini",
    "sg:tags":[
        "game"
    ],
    "wof:name":"Galleria Fabjbasaglia-edizioni Tiperti",
    "wof:placetype":"venue"
},
  "geometry": {"coordinates":[12.468081,44.074902],"type":"Point"}
}