{
  "type": "Feature",
  "properties": {
    "addr:full":"10091 Alpignano Alpignano Torino 10091",
    "addr:postcode":"10091;10091",
    "iso:country":"IT",
    "sg:address":"10091 Alpignano",
    "sg:city":"Alpignano",
    "sg:orig_category":"Carrozzerie Automobili",
    "sg:phone":"+39 011 967 9358",
    "sg:postcode":"10091",
    "sg:province":"Torino",
    "wof:name":"Carrozzeria Borgonuovo Snc Di Elia G. & C.",
    "wof:placetype":"venue"
},
  "geometry": {"coordinates":[7.600559,45.097469],"type":"Point"}
}