{
  "type": "Feature",
  "properties": {
    "iso:country":"IT",
    "sg:address":"35040 Casale Di Scodosia",
    "sg:city":"Casale di Scodosia",
    "sg:orig_category":"Non-classified Establishments",
    "sg:phone":"+39 0429 878530",
    "sg:postcode":"35040",
    "sg:province":"Padova",
    "wof:name":"Zanin Lucio & C.",
    "wof:placetype":"venue"
},
  "geometry": {"coordinates":[11.498411,45.183933],"type":"Point"}
}