{
  "type": "Feature",
  "properties": {
    "iso:country":"IT",
    "sg:address":"00179 Roma",
    "sg:city":"Roma",
    "sg:classifiers":[
        {
            "category":"Health Services",
            "subcategory":"Health Practitioner",
            "type":"Services"
        }
    ],
    "sg:phone":"+39 06 780 0176",
    "sg:postcode":"00179",
    "sg:province":"Roma",
    "sg:tags":[
        "medici"
    ],
    "wof:name":"Cerami Fiorella Maria",
    "wof:placetype":"venue"
},
  "geometry": {"coordinates":[12.515463,41.867729],"type":"Point"}
}