{
  "type": "Feature",
  "properties": {
    "iso:country":"IT",
    "sg:address":"00040 Pomezia",
    "sg:city":"Pomezia",
    "sg:orig_category":"Automazione E Macchine Per Ufficio. Servizi Ausiliari Di Certificati, Riproduzioni, Disegni E Foto",
    "sg:phone":"+39 06 9180 1279",
    "sg:postcode":"00040",
    "sg:province":"Roma",
    "wof:name":"Italservice Srl",
    "wof:placetype":"venue"
},
  "geometry": {"coordinates":[12.499483,41.663033],"type":"Point"}
}