{
  "type": "Feature",
  "properties": {
    "addr:full":"8, Calle Pescheria 30141 Venezia Venezia Venezia 30141",
    "addr:postcode":"30141;30141",
    "addr:street":"Calle Pescheria",
    "iso:country":"IT",
    "sg:address":"8, Calle Pescheria 30141 Venezia",
    "sg:city":"Venezia",
    "sg:classifiers":[
        {
            "category":"Shopping",
            "subcategory":"Computers & Home Electronics",
            "type":"Retail Goods"
        }
    ],
    "sg:phone":"+39 39041739371",
    "sg:postcode":"30141",
    "sg:province":"Venezia",
    "sg:tags":[
        "electronic",
        "electrical",
        "equipment"
    ],
    "wof:name":"Gino Dona' Srl",
    "wof:placetype":"venue"
},
  "geometry": {"coordinates":[12.351614,45.454075],"type":"Point"}
}