{
  "type": "Feature",
  "properties": {
    "addr:full":"Po Box 1269, Via Meravigli 4, 20123 Milan, Mi Milano 20123",
    "addr:housenumber":"po;4",
    "addr:postcode":"20123;20123",
    "addr:street":"Box 1269 Via Meravigli",
    "iso:country":"IT",
    "sg:address":"Po Box 1269, Via Meravigli 4, 20123 Milan, Mi",
    "sg:classifiers":[
        {
            "category":"Banks & Credit Unions",
            "subcategory":"Bank",
            "type":"Services"
        }
    ],
    "sg:postcode":"20123",
    "sg:province":"Milano",
    "wof:name":"Bnp Leasing Spa (italy)",
    "wof:placetype":"venue"
},
  "geometry": {"coordinates":[9.18392,45.465916],"type":"Point"}
}