{
  "type": "Feature",
  "properties": {
    "addr:full":"33010 Magnano In Riviera Magnano in Riviera Udine 33010",
    "addr:postcode":"33010;33010",
    "addr:street":"Riviera",
    "iso:country":"IT",
    "sg:address":"33010 Magnano In Riviera",
    "sg:city":"Magnano in Riviera",
    "sg:orig_category":"Servizi Per Aziende, Manifestazioni E Supporto Agli Scambi Commerciali",
    "sg:phone":"+39 0432 792308",
    "sg:postcode":"33010",
    "sg:province":"Udine",
    "sg:website":"http://www.greenhotel.it",
    "wof:name":"Green Hotel",
    "wof:placetype":"venue"
},
  "geometry": {"coordinates":[13.192037,46.229389],"type":"Point"}
}