{
  "type": "Feature",
  "properties": {
    "iso:country":"IT",
    "sg:address":"20156 Milano",
    "sg:city":"Milano",
    "sg:orig_category":"Ricetrasmittenti Ed Attrezzature Per Radioamatori",
    "sg:phone":"+39 02 380761",
    "sg:postcode":"20156",
    "sg:province":"Milano",
    "wof:name":"Ical Spa",
    "wof:placetype":"venue"
},
  "geometry": {"coordinates":[9.151104,45.490414],"type":"Point"}
}