{
  "type": "Feature",
  "properties": {
    "iso:country":"IT",
    "sg:address":"3, Via Mantova 20063 Cernusco Sul Naviglio",
    "sg:city":"Cernusco sul Naviglio",
    "sg:classifiers":[
        {
            "category":"Shopping",
            "subcategory":"Computers & Home Electronics",
            "type":"Retail Goods"
        }
    ],
    "sg:phone":"+39 02 9214 0510",
    "sg:postcode":"20063",
    "sg:province":"Milano",
    "sg:tags":[
        "electronic",
        "electrical",
        "equipment"
    ],
    "wof:name":"S.e.i.s. Societa' Elettro-conduttori Isolati Speci",
    "wof:placetype":"venue"
},
  "geometry": {"coordinates":[9.343488,45.503719],"type":"Point"}
}