{
  "type": "Feature",
  "properties": {
    "addr:full":"37136 Verona Verona Verona 37136",
    "addr:postcode":"37136;37136",
    "iso:country":"IT",
    "sg:address":"37136 Verona",
    "sg:city":"Verona",
    "sg:orig_category":"Motori Elettrici E Componenti",
    "sg:phone":"+39 045 820 0741",
    "sg:postcode":"37136",
    "sg:province":"Verona",
    "wof:name":"V.i.m.e.c. Srl",
    "wof:placetype":"venue"
},
  "geometry": {"coordinates":[10.9656925201,45.4109992981],"type":"Point"}
}