{
  "type": "Feature",
  "properties": {
    "addr:full":"Via Cairoli 160 13894 Gaglianico Gaglianico Biella 13894",
    "addr:housenumber":"160",
    "addr:postcode":"13894;13894",
    "addr:street":"Via Cairoli",
    "iso:country":"IT",
    "sg:address":"Via Cairoli 160 13894 Gaglianico",
    "sg:city":"Gaglianico",
    "sg:classifiers":[
        {
            "category":"Shopping",
            "subcategory":"Clothing, Apparel, & Fashions",
            "type":"Retail Goods"
        }
    ],
    "sg:phone":"+39 015 254 5932",
    "sg:postcode":"13894",
    "sg:province":"Biella",
    "sg:tags":[
        "clothing",
        "fabric"
    ],
    "sg:website":"www.webtiscalinet.it/gremmotex",
    "wof:name":"Gremmo Tex Di Gremmo Pier Luigi",
    "wof:placetype":"venue"
},
  "geometry": {"coordinates":[8.087508,45.535496],"type":"Point"}
}