{
  "type": "Feature",
  "properties": {
    "iso:country":"IT",
    "sg:address":"Via Santa Libera, 19 31020 Fontigo",
    "sg:classifiers":[
        {
            "category":"Home & Garden",
            "subcategory":"Furniture",
            "type":"Retail Goods"
        }
    ],
    "sg:phone":"+39 0438 86567",
    "sg:postcode":"31020",
    "sg:province":"Treviso",
    "sg:tags":[
        "apartment"
    ],
    "wof:name":"Veneta Giunco Di Emilio E Valter Puppetti Snc",
    "wof:placetype":"venue"
},
  "geometry": {"coordinates":[12.242072,45.666286],"type":"Point"}
}