{
  "type": "Feature",
  "properties": {
    "addr:full":"20141 Milano Milano Milano 20141",
    "addr:postcode":"20141;20141",
    "iso:country":"IT",
    "sg:address":"20141 Milano",
    "sg:city":"Milano",
    "sg:orig_category":"Prodotti Alimentari",
    "sg:phone":"+39 02 843 5753",
    "sg:postcode":"20141",
    "sg:province":"Milano",
    "wof:name":"Campagna Gabriele Luca",
    "wof:placetype":"venue"
},
  "geometry": {"coordinates":[9.1788959503,45.4428520203],"type":"Point"}
}