{
  "type": "Feature",
  "properties": {
    "addr:full":"Regione Vernetti 10040 Caprie Caprie Torino 10040",
    "addr:postcode":"10040;10040",
    "addr:street":"Regione Vernetti",
    "iso:country":"IT",
    "sg:address":"Regione Vernetti 10040 Caprie",
    "sg:city":"Caprie",
    "sg:classifiers":[
        {
            "category":"Shopping",
            "type":"Retail Goods"
        }
    ],
    "sg:phone":"+39 011 963 2278",
    "sg:postcode":"10040",
    "sg:province":"Torino",
    "sg:tags":[
        "finished",
        "-",
        "metallic"
    ],
    "wof:name":"C.b.a.",
    "wof:placetype":"venue"
},
  "geometry": {"coordinates":[7.3881511688,45.0986557007],"type":"Point"}
}