{
  "type": "Feature",
  "properties": {
    "iso:country":"IT",
    "sg:address":"07021 Arzachena",
    "sg:city":"Arzachena",
    "sg:orig_category":"Cine-foto-ottica",
    "sg:phone":"+39 0789 82357",
    "sg:postcode":"07021",
    "sg:province":"Olbia-Tempio",
    "wof:name":"Foto Cine Ottica Di Gian Piero Piredda",
    "wof:placetype":"venue"
},
  "geometry": {"coordinates":[9.278559,40.826839],"type":"Point"}
}