{
  "type": "Feature",
  "properties": {
    "iso:country":"IT",
    "sg:address":"65, Via Ca' Nave 35013 Cittadella",
    "sg:city":"Cittadella",
    "sg:classifiers":[
        {
            "category":"Building & Trades",
            "subcategory":"Construction",
            "type":"Services"
        }
    ],
    "sg:phone":"+39 049 597 1944",
    "sg:postcode":"35013",
    "sg:province":"Padova",
    "sg:tags":[
        "work",
        "public"
    ],
    "wof:name":"Pettenon Umberto & Figlio (s.n.c.)",
    "wof:placetype":"venue"
},
  "geometry": {"coordinates":[11.782568,45.640278],"type":"Point"}
}