{
  "type": "Feature",
  "properties": {
    "iso:country":"IT",
    "sg:address":"41031 Camposanto",
    "sg:city":"Camposanto",
    "sg:classifiers":[
        {
            "category":"Banks & Credit Unions",
            "subcategory":"Investment Brokerage",
            "type":"Services"
        }
    ],
    "sg:phone":"+39 0535 88226",
    "sg:postcode":"41031",
    "sg:province":"Modena",
    "sg:tags":[
        "control",
        "climate",
        "vehicles",
        "accessory",
        "equipment",
        "conditioning",
        "motor",
        "services"
    ],
    "wof:name":"M. Clima Di Muzzioli Luciano E Luca Snc",
    "wof:placetype":"venue"
},
  "geometry": {"coordinates":[11.137759,44.79694],"type":"Point"}
}