{
  "type": "Feature",
  "properties": {
    "iso:country":"IT",
    "sg:address":"10, Via Pacinotti 41037 Mirandola",
    "sg:city":"Mirandola",
    "sg:classifiers":[
        {
            "category":"Farming",
            "subcategory":"Livestock Farm",
            "type":"Manufacturing & Wholesale Goods"
        }
    ],
    "sg:phone":"+39 39053524157",
    "sg:postcode":"41037",
    "sg:province":"Modena",
    "sg:tags":[
        "agriculture"
    ],
    "wof:name":"Siminis Italia Vegetable Seeds Srl",
    "wof:placetype":"venue"
},
  "geometry": {"coordinates":[11.062602,44.899563],"type":"Point"}
}