{
  "type": "Feature",
  "properties": {
    "iso:country":"IT",
    "sg:address":"00178 Roma",
    "sg:city":"Roma",
    "sg:orig_category":"Servizi Di Magazzinaggio E Movimentazione",
    "sg:phone":"+39 06 7128 9420",
    "sg:postcode":"00178",
    "sg:province":"Roma",
    "wof:name":"Farmaenergy Snc Del Dr. Cianci Giuseppe E Del Dr. Scanzano Leonardo Luigi",
    "wof:placetype":"venue"
},
  "geometry": {"coordinates":[12.714119,41.979832],"type":"Point"}
}