{
  "type": "Feature",
  "properties": {
    "addr:full":"00192 Roma Roma Roma 00192",
    "addr:postcode":"00192;00192",
    "iso:country":"IT",
    "sg:address":"00192 Roma",
    "sg:city":"Roma",
    "sg:classifiers":[
        {
            "category":"Home & Garden",
            "subcategory":"Carpets & Floor Coverings",
            "type":"Retail Goods"
        }
    ],
    "sg:phone":"+39 06 321 0858",
    "sg:postcode":"00192",
    "sg:province":"Roma",
    "sg:tags":[
        "curtain",
        "material",
        "fabric",
        "fabrics",
        "furnishing"
    ],
    "wof:name":"F.b. Arredamenti Srl",
    "wof:placetype":"venue"
},
  "geometry": {"coordinates":[12.4605312347,41.9098854065],"type":"Point"}
}