{
  "type": "Feature",
  "properties": {
    "iso:country":"IT",
    "sg:address":"07029 Tempio Pausania",
    "sg:city":"Tempio Pausania",
    "sg:classifiers":[
        {
            "category":"Building & Trades",
            "subcategory":"Construction",
            "type":"Services"
        }
    ],
    "sg:phone":"+39 079 673105",
    "sg:postcode":"07029",
    "sg:province":"Olbia-Tempio",
    "sg:tags":[
        "civil",
        "industry",
        "work",
        "wood",
        "furnishing",
        "works"
    ],
    "wof:name":"Sanna Benedetto Falegnameria Artigiana",
    "wof:placetype":"venue"
},
  "geometry": {"coordinates":[9.1234798431,40.8994483948],"type":"Point"}
}