{
  "type": "Feature",
  "properties": {
    "addr:full":"26, Via Andrea Brezzi 10081 Castellamonte Castellamonte Torino 10081",
    "addr:postcode":"10081;10081",
    "addr:street":"Via Andrea Brezzi",
    "iso:country":"IT",
    "sg:address":"26, Via Andrea Brezzi 10081 Castellamonte",
    "sg:city":"Castellamonte",
    "sg:classifiers":[
        {
            "category":"Manufacturing",
            "subcategory":"Metals",
            "type":"Manufacturing & Wholesale Goods"
        }
    ],
    "sg:phone":"+39 0124 513276",
    "sg:postcode":"10081",
    "sg:province":"Torino",
    "sg:tags":[
        "metallurgy",
        "metalworking"
    ],
    "wof:name":"Wolfram Carb Spa",
    "wof:placetype":"venue"
},
  "geometry": {"coordinates":[7.716776371,45.3819351196],"type":"Point"}
}