{
  "type": "Feature",
  "properties": {
    "iso:country":"IT",
    "sg:address":"9, Via Pomaroli 36030 Caldogno",
    "sg:city":"Caldogno",
    "sg:classifiers":[
        {
            "category":"Utilities",
            "subcategory":"Telephone",
            "type":"Services"
        }
    ],
    "sg:phone":"+39 0444 901000",
    "sg:postcode":"36030",
    "sg:province":"Vicenza",
    "sg:tags":[
        "telecommunication"
    ],
    "wof:name":"Autec S.r.l.",
    "wof:placetype":"venue"
},
  "geometry": {"coordinates":[11.499968,45.628479],"type":"Point"}
}