{
  "type": "Feature",
  "properties": {
    "addr:full":"11, V. Unit\u00e0 D'italia 10095 Grugliasco Grugliasco Torino 10095",
    "addr:housenumber":"11",
    "addr:postcode":"10095;10095",
    "addr:street":"V. Unita\u0300 D'Italia",
    "iso:country":"IT",
    "sg:address":"11, V. Unit\u00e0 D'italia 10095 Grugliasco",
    "sg:city":"Grugliasco",
    "sg:classifiers":[
        {
            "category":"Shopping",
            "type":"Retail Goods"
        }
    ],
    "sg:phone":"+39 011 314 9474",
    "sg:postcode":"10095",
    "sg:province":"Torino",
    "sg:tags":[
        "finished",
        "-",
        "metallic"
    ],
    "sg:website":"http://www.paginegialle.it/otocar",
    "wof:name":"O.to.car. Srl",
    "wof:placetype":"venue"
},
  "geometry": {"coordinates":[7.6031217575,45.0433769226],"type":"Point"}
}