{
  "type": "Feature",
  "properties": {
    "iso:country":"IT",
    "sg:address":"3, Piazza Quattro Novembre 20124 Milano",
    "sg:city":"Milano",
    "sg:classifiers":[
        {
            "category":"Professional",
            "subcategory":"Computer Services",
            "type":"Services"
        }
    ],
    "sg:phone":"+39 390 266 7221",
    "sg:postcode":"20124",
    "sg:province":"Milano",
    "sg:tags":[
        "information",
        "technology"
    ],
    "wof:name":"Atos Spa",
    "wof:placetype":"venue"
},
  "geometry": {"coordinates":[9.203226,45.482468],"type":"Point"}
}