{
  "type": "Feature",
  "properties": {
    "addr:full":"96100 Siracusa Siracusa Siracusa 96100",
    "addr:postcode":"96100;96100",
    "iso:country":"IT",
    "sg:address":"96100 Siracusa",
    "sg:city":"Siracusa",
    "sg:orig_category":"Agenzie Matrimoniali",
    "sg:phone":"+39 0931 412265",
    "sg:postcode":"96100",
    "sg:province":"Siracusa",
    "wof:name":"E' Amore",
    "wof:placetype":"venue"
},
  "geometry": {"coordinates":[15.288804,37.08424],"type":"Point"}
}