{
  "type": "Feature",
  "properties": {
    "iso:country":"IT",
    "sg:address":"Via Fabrizio 1 31046 Oderzo",
    "sg:city":"Oderzo",
    "sg:classifiers":[
        {
            "category":"Manufacturing",
            "subcategory":"Food",
            "type":"Manufacturing & Wholesale Goods"
        }
    ],
    "sg:phone":"+39 0422 815445",
    "sg:postcode":"31046",
    "sg:province":"Treviso",
    "sg:tags":[
        "vinegar"
    ],
    "wof:name":"Caramel Sas Di Caramel Mario & C.",
    "wof:placetype":"venue"
},
  "geometry": {"coordinates":[12.49896,45.795616],"type":"Point"}
}