{
  "type": "Feature",
  "properties": {
    "iso:country":"IT",
    "sg:address":"28021 Borgomanero",
    "sg:city":"Borgomanero",
    "sg:orig_category":"Forniture Per Edilizia E Lavori Pubblici",
    "sg:phone":"+39 0322 804482",
    "sg:postcode":"28021",
    "sg:province":"Novara",
    "wof:name":"Nuove Tecnologie Di Mora Davide",
    "wof:placetype":"venue"
},
  "geometry": {"coordinates":[8.4644107819,45.696269989],"type":"Point"}
}