{
  "type": "Feature",
  "properties": {
    "addr:full":"Via Dei Confini Di Settola 22 51100 Pistoia Pistoia Pistoia 51100",
    "addr:housenumber":"22",
    "addr:postcode":"51100;51100",
    "addr:street":"Via Dei Confini Di Settola",
    "iso:country":"IT",
    "sg:address":"Via Dei Confini Di Settola 22 51100 Pistoia",
    "sg:city":"Pistoia",
    "sg:classifiers":[
        {
            "category":"Manufacturing",
            "subcategory":"Building Materials",
            "type":"Manufacturing & Wholesale Goods"
        }
    ],
    "sg:phone":"+39 0573 934291",
    "sg:postcode":"51100",
    "sg:province":"Pistoia",
    "sg:tags":[
        "fleece",
        "fabric"
    ],
    "sg:website":"www.pratocommerz.com",
    "wof:name":"Pratocommerz Srl",
    "wof:placetype":"venue"
},
  "geometry": {"coordinates":[10.9185237885,43.9321556091],"type":"Point"}
}