{
  "type": "Feature",
  "properties": {
    "addr:full":"00060 Capena Capena Roma 00060",
    "addr:postcode":"00060;roma 00060",
    "iso:country":"IT",
    "sg:address":"00060 Capena",
    "sg:city":"Capena",
    "sg:orig_category":"Ospedali E Servizi Sanitari",
    "sg:phone":"+39 06 903 2811",
    "sg:postcode":"00060",
    "sg:province":"Roma",
    "wof:name":"Croce Rossa Italiana",
    "wof:placetype":"venue"
},
  "geometry": {"coordinates":[12.614684,42.051212],"type":"Point"}
}