{
  "type": "Feature",
  "properties": {
    "iso:country":"IT",
    "sg:address":"37020 Brentino Belluno",
    "sg:city":"Brentino Belluno",
    "sg:orig_category":"Acciai Inossidabili - Lavorazione",
    "sg:phone":"+39 045 628 4069",
    "sg:postcode":"37020",
    "sg:province":"Verona",
    "wof:name":"Metal Riv Srl",
    "wof:placetype":"venue"
},
  "geometry": {"coordinates":[10.894208,45.658344],"type":"Point"}
}