{
  "type": "Feature",
  "properties": {
    "iso:country":"IT",
    "sg:address":"26848 San Fiorano",
    "sg:city":"San Fiorano",
    "sg:orig_category":"Prodotti Di Base E Forniture Per Industria Alimentare E Bevande",
    "sg:phone":"+39 0377 53325",
    "sg:postcode":"26848",
    "sg:province":"Lodi",
    "wof:name":"Anelli Italo",
    "wof:placetype":"venue"
},
  "geometry": {"coordinates":[9.7182302475,45.1372566223],"type":"Point"}
}