{
  "type": "Feature",
  "properties": {
    "iso:country":"IT",
    "sg:address":"20121 Milano",
    "sg:city":"Milano",
    "sg:orig_category":"Servizi Al Turismo. Ambasciate Ed Enti Internazionali",
    "sg:phone":"+39 02 2906 2493",
    "sg:postcode":"20121",
    "sg:province":"Milano",
    "wof:name":"Consolato Mauritius",
    "wof:placetype":"venue"
},
  "geometry": {"coordinates":[9.192652,45.46978],"type":"Point"}
}