{
  "type": "Feature",
  "properties": {
    "iso:country":"IT",
    "sg:address":"65128 Pescara",
    "sg:city":"Pescara",
    "sg:orig_category":"Cancelli, Porte E Portoni Automatici E Telecomandati",
    "sg:phone":"+39 085 431 4875",
    "sg:postcode":"65128",
    "sg:province":"Pescara",
    "wof:name":"S.i.ca.m. Sas",
    "wof:placetype":"venue"
},
  "geometry": {"coordinates":[14.198356,42.442387],"type":"Point"}
}