{
  "type": "Feature",
  "properties": {
    "iso:country":"IT",
    "sg:address":"1, Via Don Fortuzzi 40019 Sant'agata Bolognese",
    "sg:classifiers":[
        {
            "category":"Shopping",
            "type":"Retail Goods"
        }
    ],
    "sg:phone":"+39 39051956161",
    "sg:postcode":"40019",
    "sg:province":"Bologna",
    "sg:tags":[
        "finished",
        "-",
        "metallic"
    ],
    "wof:name":"Mollificio Bo.moll Snc",
    "wof:placetype":"venue"
},
  "geometry": {"coordinates":[11.1256008148,44.6602516174],"type":"Point"}
}