{
  "type": "Feature",
  "properties": {
    "iso:country":"IT",
    "sg:address":"30, Via Triumplina 25123 Brescia",
    "sg:city":"Brescia",
    "sg:classifiers":[
        {
            "category":"Utilities",
            "subcategory":"Telephone",
            "type":"Services"
        }
    ],
    "sg:phone":"+39 39030370700",
    "sg:postcode":"25123",
    "sg:province":"Brescia",
    "sg:tags":[
        "telecommunication"
    ],
    "wof:name":"Meggiorin S.p.a.",
    "wof:placetype":"venue"
},
  "geometry": {"coordinates":[10.228352,45.561211],"type":"Point"}
}