{
  "type": "Feature",
  "properties": {
    "iso:country":"IT",
    "sg:address":"52, Via Brolo 25075 Nave",
    "sg:city":"Nave",
    "sg:classifiers":[
        {
            "category":"Professional",
            "subcategory":"Engineering",
            "type":"Services"
        }
    ],
    "sg:phone":"+39 030 253 1326",
    "sg:postcode":"25075",
    "sg:province":"Brescia",
    "sg:tags":[
        "machine",
        "-",
        "mechanical"
    ],
    "wof:name":"Battaglio Luciano & C. (s.n.c.)",
    "wof:placetype":"venue"
},
  "geometry": {"coordinates":[10.275882,45.575832],"type":"Point"}
}