{
  "type": "Feature",
  "properties": {
    "iso:country":"IT",
    "sg:address":"20135 Milano",
    "sg:city":"Milano",
    "sg:orig_category":"Gioielleria, Oreficeria E Argenteria",
    "sg:phone":"+39 02 5990 0384",
    "sg:postcode":"20135",
    "sg:province":"Milano",
    "wof:name":"S.i.b. Srl",
    "wof:placetype":"venue"
},
  "geometry": {"coordinates":[9.213831,45.458412],"type":"Point"}
}