{
  "type": "Feature",
  "properties": {
    "iso:country":"IT",
    "sg:address":"41100 Modena",
    "sg:city":"Modena",
    "sg:orig_category":"Macchine, Impianti Ed Attrezzature Per Abbigliamento E Pelletterie",
    "sg:phone":"+39 059 454010",
    "sg:postcode":"41100",
    "sg:province":"Modena",
    "wof:name":"Ansaloni Gianni",
    "wof:placetype":"venue"
},
  "geometry": {"coordinates":[10.935829,44.552532],"type":"Point"}
}