{
  "type": "Feature",
  "properties": {
    "addr:full":"38100 Trento Trento Trento 38100",
    "addr:postcode":"38100;38100",
    "iso:country":"IT",
    "sg:address":"38100 Trento",
    "sg:city":"Trento",
    "sg:orig_category":"Agenzie Immobiliari",
    "sg:phone":"+39 0461 421346",
    "sg:postcode":"38100",
    "sg:province":"Trento",
    "wof:name":"Tecnoservizi2000",
    "wof:placetype":"venue"
},
  "geometry": {"coordinates":[11.114610672,46.0762290955],"type":"Point"}
}