{
  "type": "Feature",
  "properties": {
    "addr:full":"74, Via Bergamo 26022 Castelverde Castelverde Cremona 26022",
    "addr:postcode":"26022;26022",
    "addr:street":"Via Bergamo",
    "iso:country":"IT",
    "sg:address":"74, Via Bergamo 26022 Castelverde",
    "sg:city":"Castelverde",
    "sg:classifiers":[
        {
            "category":"Professional",
            "subcategory":"Engineering",
            "type":"Services"
        }
    ],
    "sg:phone":"+39 0372 429232",
    "sg:postcode":"26022",
    "sg:province":"Cremona",
    "sg:tags":[
        "machine",
        "-",
        "mechanical"
    ],
    "wof:name":"Angelo Cremona S.p.a.",
    "wof:placetype":"venue"
},
  "geometry": {"coordinates":[10.000429,45.183804],"type":"Point"}
}