{
  "type": "Feature",
  "properties": {
    "addr:full":"00143 Roma Roma Roma 00143",
    "addr:postcode":"00143;00143",
    "iso:country":"IT",
    "sg:address":"00143 Roma",
    "sg:city":"Roma",
    "sg:orig_category":"Prodotti E Manufatti In Materie Plastiche",
    "sg:phone":"+39 06 591 3324",
    "sg:postcode":"00143",
    "sg:province":"Roma",
    "wof:name":"Tekom Srl",
    "wof:placetype":"venue"
},
  "geometry": {"coordinates":[12.481341362,41.8237800598],"type":"Point"}
}