{
  "type": "Feature",
  "properties": {
    "addr:full":"Via Lombardi 2 51031 Agliana Agliana Pistoia 51031",
    "addr:housenumber":"2",
    "addr:postcode":"51031;51031",
    "addr:street":"Via Lombardi",
    "iso:country":"IT",
    "sg:address":"Via Lombardi 2 51031 Agliana",
    "sg:city":"Agliana",
    "sg:orig_category":"Hosiery, Nightwear, Daywear",
    "sg:phone":"+39 0574 5321",
    "sg:postcode":"51031",
    "sg:province":"Pistoia",
    "wof:name":"I.m.m. Spa",
    "wof:placetype":"venue"
},
  "geometry": {"coordinates":[10.997397,43.909592],"type":"Point"}
}