{
  "type": "Feature",
  "properties": {
    "iso:country":"IT",
    "sg:address":"24038 Sant'omobono Imagna",
    "sg:orig_category":"Abbigliamento - Produzione E Ingrosso",
    "sg:phone":"+39 035 852591",
    "sg:postcode":"24038",
    "sg:province":"Bergamo",
    "wof:name":"Commerciale Pescatese Srl",
    "wof:placetype":"venue"
},
  "geometry": {"coordinates":[9.536014,45.800915],"type":"Point"}
}