{
  "type": "Feature",
  "properties": {
    "addr:full":"37030 Giazza Verona 37030",
    "addr:postcode":"37030;37030",
    "iso:country":"IT",
    "sg:address":"37030 Giazza",
    "sg:orig_category":"Servizi Per Lo Sport E Il Tempo Libero. Alberghi E Strutture Extra Alberghiere",
    "sg:phone":"+39 045 784 7011",
    "sg:postcode":"37030",
    "sg:province":"Verona",
    "wof:name":"Rifugio Passo Pertica",
    "wof:placetype":"venue"
},
  "geometry": {"coordinates":[11.006194,45.450287],"type":"Point"}
}