{
  "type": "Feature",
  "properties": {
    "iso:country":"IT",
    "sg:address":"18012 Bordighera",
    "sg:city":"Bordighera",
    "sg:orig_category":"Alberghi",
    "sg:phone":"+39 0184 261448",
    "sg:postcode":"18012",
    "sg:province":"Imperia",
    "sg:website":"http://www.savoybordighera.it",
    "wof:name":"Albergo Savoy - Ristorante Albatros",
    "wof:placetype":"venue"
},
  "geometry": {"coordinates":[7.665169,43.781223],"type":"Point"}
}