{
  "type": "Feature",
  "properties": {
    "addr:full":"24125 Bergamo Bergamo Bergamo 24125",
    "addr:postcode":"24125;24125",
    "iso:country":"IT",
    "sg:address":"24125 Bergamo",
    "sg:city":"Bergamo",
    "sg:orig_category":"Lavorazioni Meccaniche E Servizi. Riparazione Dei Mezzi Di Trasporto",
    "sg:phone":"+39 035 244129",
    "sg:postcode":"24125",
    "sg:province":"Bergamo",
    "wof:name":"Fagnani Giulio Autoforniture Bergamasche",
    "wof:placetype":"venue"
},
  "geometry": {"coordinates":[9.689726,45.692818],"type":"Point"}
}