{
  "type": "Feature",
  "properties": {
    "iso:country":"IT",
    "sg:address":"37124 Verona",
    "sg:city":"Verona",
    "sg:orig_category":"Macchine E Forniture Per Arredamento E Industria Del Legno. Utensili Meccanici E Materiali",
    "sg:phone":"+39 045 912233",
    "sg:postcode":"37124",
    "sg:province":"Verona",
    "wof:name":"Leiser",
    "wof:placetype":"venue"
},
  "geometry": {"coordinates":[10.967531,45.462555],"type":"Point"}
}