{
  "type": "Feature",
  "properties": {
    "addr:full":"24050 Zanica Zanica Bergamo 24050",
    "addr:postcode":"24050;24050",
    "iso:country":"IT",
    "sg:address":"24050 Zanica",
    "sg:city":"Zanica",
    "sg:orig_category":"Macchine, Impianti Ed Attrezzature Per Industria Alimentare E Bevande",
    "sg:phone":"+39 035 670402",
    "sg:postcode":"24050",
    "sg:province":"Bergamo",
    "wof:name":"Centrogel Di Gianluigi Alini & C. Snc",
    "wof:placetype":"venue"
},
  "geometry": {"coordinates":[9.688617,45.629791],"type":"Point"}
}