{
  "type": "Feature",
  "properties": {
    "iso:country":"IT",
    "sg:address":"7, Via Della Tecnica 40050 Argelato",
    "sg:city":"Argelato",
    "sg:classifiers":[
        {
            "category":"Professional",
            "subcategory":"Engineering",
            "type":"Services"
        }
    ],
    "sg:phone":"+39 39051892484",
    "sg:postcode":"40050",
    "sg:province":"Bologna",
    "sg:tags":[
        "machine",
        "-",
        "mechanical"
    ],
    "wof:name":"Meccanica C.g.a. (s.n.c.)",
    "wof:placetype":"venue"
},
  "geometry": {"coordinates":[11.355191,44.634037],"type":"Point"}
}