{
  "type": "Feature",
  "properties": {
    "addr:full":"54, Via Dante Alighieri 21034 Cocquio Trevisago Cocquio Varese 21034",
    "addr:postcode":"21034;21034",
    "addr:street":"Via Dante Alighieri",
    "iso:country":"IT",
    "sg:address":"54, Via Dante Alighieri 21034 Cocquio Trevisago",
    "sg:city":"Cocquio",
    "sg:classifiers":[
        {
            "category":"Shopping",
            "type":"Retail Goods"
        }
    ],
    "sg:phone":"+39 0332 700127",
    "sg:postcode":"21034",
    "sg:province":"Varese",
    "sg:tags":[
        "finished",
        "-",
        "metallic"
    ],
    "wof:name":"Stampamatic S.r.l.",
    "wof:placetype":"venue"
},
  "geometry": {"coordinates":[8.8263845444,45.8176040649],"type":"Point"}
}