{
  "type": "Feature",
  "properties": {
    "iso:country":"IT",
    "sg:address":"20129 Milano",
    "sg:city":"Milano",
    "sg:orig_category":"Automobili E Mezzi Di Trasporto",
    "sg:phone":"+39 02 2940 0653",
    "sg:postcode":"20129",
    "sg:province":"Milano",
    "wof:name":"Autocapoccia Srl",
    "wof:placetype":"venue"
},
  "geometry": {"coordinates":[9.209592,45.473286],"type":"Point"}
}