{
  "type": "Feature",
  "properties": {
    "iso:country":"IT",
    "sg:address":"11, V. Santa Giovanna D'arco 73041 Carmiano",
    "sg:city":"Carmiano",
    "sg:classifiers":[
        {
            "category":"Manufacturing",
            "subcategory":"Tools & Machinery",
            "type":"Manufacturing & Wholesale Goods"
        }
    ],
    "sg:phone":"+39 0832 607215",
    "sg:postcode":"73041",
    "sg:province":"Lecce",
    "sg:tags":[
        "environment",
        "equipment",
        "-"
    ],
    "wof:name":"Idrodinamica Spurgo Velox",
    "wof:placetype":"venue"
},
  "geometry": {"coordinates":[18.041637,40.350216],"type":"Point"}
}