{
  "type": "Feature",
  "properties": {
    "addr:full":"80034 Marigliano Marigliano Napoli 80034",
    "addr:postcode":"80034;80034",
    "iso:country":"IT",
    "sg:address":"80034 Marigliano",
    "sg:city":"Marigliano",
    "sg:orig_category":"Prodotti Alimentari",
    "sg:phone":"+39 081 841 1068",
    "sg:postcode":"80034",
    "sg:province":"Napoli",
    "wof:name":"Cereali Sud Srl",
    "wof:placetype":"venue"
},
  "geometry": {"coordinates":[14.2438735962,40.8370132446],"type":"Point"}
}