{
  "type": "Feature",
  "properties": {
    "iso:country":"IT",
    "sg:address":"60044 Fabriano",
    "sg:city":"Fabriano",
    "sg:orig_category":"Macchine Ed Impianti Per Edilizia E Lavori Pubblici. Forniture Per Edilizia E Lavori Pubblici",
    "sg:phone":"+39 0732 627683",
    "sg:postcode":"60044",
    "sg:province":"Ancona",
    "sg:website":"http://www.cacciamani.com",
    "wof:name":"Cacciamani Enrico & C. Snc",
    "wof:placetype":"venue"
},
  "geometry": {"coordinates":[12.937836,43.349064],"type":"Point"}
}