{
  "type": "Feature",
  "properties": {
    "iso:country":"IT",
    "sg:address":"98122 Messina",
    "sg:city":"Messina",
    "sg:orig_category":"Articoli Funerari",
    "sg:phone":"+39 090 393714",
    "sg:postcode":"98122",
    "sg:province":"Messina",
    "wof:name":"Lisitano Felice",
    "wof:placetype":"venue"
},
  "geometry": {"coordinates":[15.557037,38.190811],"type":"Point"}
}