{
  "type": "Feature",
  "properties": {
    "addr:full":"Via Brenta, 10/12/14 20089 Rozzano Rozzano Milano 20089",
    "addr:housenumber":"10 / 12 / 14",
    "addr:postcode":"20089;20089",
    "addr:street":"Via Brenta",
    "iso:country":"IT",
    "sg:address":"Via Brenta, 10/12/14 20089 Rozzano",
    "sg:city":"Rozzano",
    "sg:orig_category":"Wrapping Paper With Advertising Text",
    "sg:phone":"+39 02 825 0001",
    "sg:postcode":"20089",
    "sg:province":"Milano",
    "wof:name":"La Nuova Cartorama Sas",
    "wof:placetype":"venue"
},
  "geometry": {"coordinates":[9.167076,45.396996],"type":"Point"}
}