{
  "type": "Feature",
  "properties": {
    "addr:full":"35127 Padova Padova Padova 35127",
    "addr:postcode":"35127;35127",
    "iso:country":"IT",
    "sg:address":"35127 Padova",
    "sg:city":"Padova",
    "sg:classifiers":[
        {
            "category":"Professional",
            "subcategory":"Management & Consulting",
            "type":"Services"
        }
    ],
    "sg:phone":"+39 049 806 1213",
    "sg:postcode":"35127",
    "sg:province":"Padova",
    "sg:tags":[
        "information",
        "communication",
        "marketing",
        "-",
        "advertising",
        "consultant",
        "services",
        "technology"
    ],
    "sg:website":"http://www.saifo.it",
    "wof:name":"Saifo Srl",
    "wof:placetype":"venue"
},
  "geometry": {"coordinates":[11.928375,45.388134],"type":"Point"}
}