{
  "type": "Feature",
  "properties": {
    "addr:full":"37045 Legnago Legnago Verona 37045",
    "addr:postcode":"37045;37045",
    "iso:country":"IT",
    "sg:address":"37045 Legnago",
    "sg:city":"Legnago",
    "sg:orig_category":"Modelli Per Fonderie",
    "sg:phone":"+39 0442 629045",
    "sg:postcode":"37045",
    "sg:province":"Verona",
    "wof:name":"Modelleria Legnaghese Di Magri P.i. Antonio & C. Snc",
    "wof:placetype":"venue"
},
  "geometry": {"coordinates":[11.2590341568,45.1829223633],"type":"Point"}
}