{
  "type": "Feature",
  "properties": {
    "addr:full":"180, Via Crocicchio-bozzano 55054 Massarosa Bozzano Lucca 55054",
    "addr:housenumber":"180",
    "addr:postcode":"55054;55054",
    "addr:street":"Via Crocicchio-Bozzano",
    "iso:country":"IT",
    "sg:address":"180, Via Crocicchio-bozzano 55054 Massarosa",
    "sg:city":"Bozzano",
    "sg:classifiers":[
        {
            "category":"Personal",
            "subcategory":"Shoe Repair & Shine",
            "type":"Services"
        }
    ],
    "sg:phone":"+39 0584 938395",
    "sg:postcode":"55054",
    "sg:province":"Lucca",
    "sg:tags":[
        "leather"
    ],
    "wof:name":"Tomaificio Claudio Di Lucchesi Simonetta",
    "wof:placetype":"venue"
},
  "geometry": {"coordinates":[10.507994,43.843014],"type":"Point"}
}