{
  "type": "Feature",
  "properties": {
    "iso:country":"IT",
    "sg:address":"86 Corso Italia, 12037 Saluzzo",
    "sg:city":"Saluzzo",
    "sg:classifiers":[
        {
            "category":"Banks & Credit Unions",
            "subcategory":"Financial Services",
            "type":"Services"
        }
    ],
    "sg:phone":"+39 390 175 2441",
    "sg:postcode":"12037",
    "sg:province":"Cuneo",
    "sg:tags":[
        "banking",
        "finance",
        "insurance"
    ],
    "wof:name":"Cassa Di Risparmio Di Saluzzo",
    "wof:placetype":"venue"
},
  "geometry": {"coordinates":[7.4902768135,44.6459541321],"type":"Point"}
}