{
  "type": "Feature",
  "properties": {
    "iso:country":"IT",
    "sg:address":"10098 Rivoli",
    "sg:city":"Rivoli",
    "sg:orig_category":"Antenne Radio-televisione",
    "sg:phone":"+39 011 953 3181",
    "sg:postcode":"10098",
    "sg:province":"Torino",
    "wof:name":"Tecnoprogetti Sas Di Porta Roberto & C.",
    "wof:placetype":"venue"
},
  "geometry": {"coordinates":[7.571621,45.083035],"type":"Point"}
}