{
  "type": "Feature",
  "properties": {
    "iso:country":"IT",
    "sg:address":"80124 Napoli",
    "sg:city":"Napoli",
    "sg:orig_category":"Servizi Ausiliari Di Certificati, Riproduzioni, Disegni E Foto",
    "sg:phone":"+39 081 242 8565",
    "sg:postcode":"80124",
    "sg:province":"Napoli",
    "wof:name":"Alfonso Grotta",
    "wof:placetype":"venue"
},
  "geometry": {"coordinates":[14.170699,40.858997],"type":"Point"}
}