{
  "type": "Feature",
  "properties": {
    "addr:full":"30036 Santa Maria Di Sala Santa Maria di Sala Venezia 30036",
    "addr:postcode":"30036;30036",
    "addr:street":"Maria",
    "iso:country":"IT",
    "sg:address":"30036 Santa Maria Di Sala",
    "sg:city":"Santa Maria di Sala",
    "sg:orig_category":"Servizi Per Imballaggio E Confezionamento",
    "sg:phone":"+39 041 486690",
    "sg:postcode":"30036",
    "sg:province":"Venezia",
    "wof:name":"Micropac Sas",
    "wof:placetype":"venue"
},
  "geometry": {"coordinates":[12.029264,45.455738],"type":"Point"}
}