{
  "type": "Feature",
  "properties": {
    "iso:country":"IT",
    "sg:address":"9, Via Palombi 62027 San Severino Marche",
    "sg:city":"San Severino Marche",
    "sg:classifiers":[
        {
            "category":"Wholesale",
            "subcategory":"Drugs",
            "type":"Manufacturing & Wholesale Goods"
        }
    ],
    "sg:phone":"+39 0733 645112",
    "sg:postcode":"62027",
    "sg:province":"Macerata",
    "sg:tags":[
        "chemical",
        "pharmaceutical"
    ],
    "wof:name":"Kenaf S.r.l.",
    "wof:placetype":"venue"
},
  "geometry": {"coordinates":[13.4562616348,43.3007469177],"type":"Point"}
}