{
  "type": "Feature",
  "properties": {
    "addr:full":"21050 Nizzolina Varese 21050",
    "addr:housenumber":"21050",
    "addr:postcode":"21050",
    "addr:street":"Nizzolina Varese",
    "iso:country":"IT",
    "sg:address":"21050 Nizzolina",
    "sg:orig_category":"Forniture Per Attivita' Industriali",
    "sg:phone":"+39 0331 366080",
    "sg:postcode":"21050",
    "sg:province":"Varese",
    "wof:name":"Spin Di Mazza Sergio & C.",
    "wof:placetype":"venue"
},
  "geometry": {"coordinates":[8.9220209122,45.6274223328],"type":"Point"}
}