{
  "type": "Feature",
  "properties": {
    "iso:country":"IT",
    "sg:address":"15020 Serralunga Di Crea",
    "sg:city":"Serralunga di Crea",
    "sg:orig_category":"Carpenterie Metalliche",
    "sg:phone":"+39 0142 940212",
    "sg:postcode":"15020",
    "sg:province":"Alessandria",
    "sg:website":"http://www.cameltech.it",
    "wof:name":"Cameltech Srl",
    "wof:placetype":"venue"
},
  "geometry": {"coordinates":[8.28313,45.101257],"type":"Point"}
}