{
  "type": "Feature",
  "properties": {
    "iso:country":"IT",
    "sg:address":"90145 Palermo",
    "sg:city":"Palermo",
    "sg:orig_category":"Scuole E Servizi Scolastici",
    "sg:phone":"+39 091 681 4689",
    "sg:postcode":"90145",
    "sg:province":"Palermo",
    "wof:name":"Start Film Coop. Arl",
    "wof:placetype":"venue"
},
  "geometry": {"coordinates":[13.343134,38.126316],"type":"Point"}
}