{
  "type": "Feature",
  "properties": {
    "iso:country":"IT",
    "sg:address":"58019 Monte Argentario",
    "sg:city":"Monte Argentario",
    "sg:classifiers":[
        {
            "category":"Banks & Credit Unions",
            "subcategory":"Investment Brokerage",
            "type":"Services"
        }
    ],
    "sg:phone":"+39 0564 810145",
    "sg:postcode":"58019",
    "sg:province":"Grosseto",
    "sg:tags":[
        "article",
        "sport",
        "leisure",
        "supplies"
    ],
    "wof:name":"Cala Galera Diving Center",
    "wof:placetype":"venue"
},
  "geometry": {"coordinates":[11.120657,42.435669],"type":"Point"}
}