{
  "type": "Feature",
  "properties": {
    "iso:country":"IT",
    "sg:address":"36066 Sandrigo",
    "sg:city":"Sandrigo",
    "sg:orig_category":"Macchine E Forniture Per Ecologia E Smaltimento Rifiuti",
    "sg:phone":"+39 0444 657115",
    "sg:postcode":"36066",
    "sg:province":"Vicenza",
    "wof:name":"Water Brain Srl",
    "wof:placetype":"venue"
},
  "geometry": {"coordinates":[11.539094,45.544197],"type":"Point"}
}