{
  "type": "Feature",
  "properties": {
    "addr:full":"20030 Barlassina Barlassina Milano 20030",
    "addr:postcode":"20030;20030",
    "iso:country":"IT",
    "sg:address":"20030 Barlassina",
    "sg:city":"Barlassina",
    "sg:orig_category":"Antifurto",
    "sg:phone":"+39 036 256 2828",
    "sg:postcode":"20030",
    "sg:province":"Milano",
    "wof:name":"Elettrica Galuppi Snc",
    "wof:placetype":"venue"
},
  "geometry": {"coordinates":[9.179183,45.464672],"type":"Point"}
}