{
  "type": "Feature",
  "properties": {
    "iso:country":"IT",
    "sg:address":"Via Venezia 2, 73020 Melendugno, Le",
    "sg:classifiers":[
        {
            "category":"Banks & Credit Unions",
            "subcategory":"Bank",
            "type":"Services"
        }
    ],
    "sg:postcode":"73020",
    "sg:province":"Lecce",
    "wof:name":"Banca Di Credito Cooperativo Di Melendugno E Borgagne",
    "wof:placetype":"venue"
},
  "geometry": {"coordinates":[18.342121,40.19582],"type":"Point"}
}