{
  "type": "Feature",
  "properties": {
    "addr:full":"00122 Lido Di Ostia Roma 00122",
    "addr:postcode":"00122;00122",
    "addr:street":"Di Ostia Roma",
    "iso:country":"IT",
    "sg:address":"00122 Lido Di Ostia",
    "sg:orig_category":"Servizi Per Lo Sport E Il Tempo Libero. Alberghi E Strutture Extra Alberghiere",
    "sg:phone":"+39 06 5647 0100",
    "sg:postcode":"00122",
    "sg:province":"Roma",
    "wof:name":"Stab. Baln. La Bicocca Srl",
    "wof:placetype":"venue"
},
  "geometry": {"coordinates":[12.321686,41.712383],"type":"Point"}
}