{
  "type": "Feature",
  "properties": {
    "iso:country":"IT",
    "sg:address":"25069 Cogozzo",
    "sg:city":"Cogozzo",
    "sg:orig_category":"Carni, Salumi E Pesci",
    "sg:phone":"+39 030 800590",
    "sg:postcode":"25069",
    "sg:province":"Brescia",
    "wof:name":"Porta Cesare",
    "wof:placetype":"venue"
},
  "geometry": {"coordinates":[10.194245,45.641323],"type":"Point"}
}