{
  "type": "Feature",
  "properties": {
    "iso:country":"IT",
    "sg:address":"21041 Albizzate",
    "sg:city":"Albizzate",
    "sg:orig_category":"Macchine Utensili E Impianti",
    "sg:phone":"+39 0331 985581",
    "sg:postcode":"21041",
    "sg:province":"Varese",
    "wof:name":"C.i.m.a. (s.r.l.)",
    "wof:placetype":"venue"
},
  "geometry": {"coordinates":[8.829442,45.821835],"type":"Point"}
}