{
  "type": "Feature",
  "properties": {
    "iso:country":"IT",
    "sg:address":"93100 Caltanissetta",
    "sg:city":"Caltanissetta",
    "sg:orig_category":"Ascensori - Installazione E Manutenzione",
    "sg:phone":"+39 0934 584765",
    "sg:postcode":"93100",
    "sg:province":"Caltanissetta",
    "wof:name":"Unione Ascensoristi Nisseni Srl",
    "wof:placetype":"venue"
},
  "geometry": {"coordinates":[14.030454,37.454559],"type":"Point"}
}