{
  "type": "Feature",
  "properties": {
    "iso:country":"IT",
    "sg:address":"Via Ponchielli 2 26022 Castelverde",
    "sg:city":"Castelverde",
    "sg:classifiers":[
        {
            "category":"Shopping",
            "subcategory":"Used Merchandise",
            "type":"Retail Goods"
        }
    ],
    "sg:phone":"+39 0372 427347",
    "sg:postcode":"26022",
    "sg:province":"Cremona",
    "sg:tags":[
        "agricultural",
        "machinery"
    ],
    "wof:name":"Bodini Srl",
    "wof:placetype":"venue"
},
  "geometry": {"coordinates":[9.930472,45.148693],"type":"Point"}
}