{
  "type": "Feature",
  "properties": {
    "iso:country":"IT",
    "sg:address":"20037 Paderno Dugnano",
    "sg:city":"Paderno Dugnano",
    "sg:orig_category":"Arredo Cucina Ed Elettrodomestici. Elettrodomestici",
    "sg:phone":"+39 02 9108 2934",
    "sg:postcode":"20037",
    "sg:province":"Milano",
    "wof:name":"F.lli Pasqualino Srl",
    "wof:placetype":"venue"
},
  "geometry": {"coordinates":[9.180912,45.567722],"type":"Point"}
}