{
  "type": "Feature",
  "properties": {
    "addr:full":"13037 Bornate Vercelli 13037",
    "addr:housenumber":"13037",
    "addr:postcode":"13037",
    "addr:street":"Bornate Vercelli",
    "iso:country":"IT",
    "sg:address":"13037 Bornate",
    "sg:orig_category":"Cartotecnica E Servizi. Composizione, Stampa E Confezione. Servizi E Lavori Industria Delle Materie Plastiche. Servizi Per Imballaggio E Confezionamento",
    "sg:phone":"+39 0163 459985",
    "sg:postcode":"13037",
    "sg:province":"Vercelli",
    "wof:name":"Fratelli Sanges S.n.c. Di Alfredo E Sergio Sanges",
    "wof:placetype":"venue"
},
  "geometry": {"coordinates":[8.278784,45.711655],"type":"Point"}
}