{
  "type": "Feature",
  "properties": {
    "iso:country":"IT",
    "sg:address":"20141 Milano",
    "sg:city":"Milano",
    "sg:classifiers":[
        {
            "category":"Shopping",
            "subcategory":"Computers & Home Electronics",
            "type":"Retail Goods"
        }
    ],
    "sg:phone":"+39 02 539 1224",
    "sg:postcode":"20141",
    "sg:province":"Milano",
    "sg:tags":[
        "personal",
        "ed",
        "accessori"
    ],
    "sg:website":"http://web.tin.it/computerlab",
    "wof:name":"Computer Lab Snc",
    "wof:placetype":"venue"
},
  "geometry": {"coordinates":[9.1997509003,45.4239616394],"type":"Point"}
}