{
  "type": "Feature",
  "properties": {
    "iso:country":"IT",
    "sg:address":"3, Via F. Maritano 42020 Albinea",
    "sg:classifiers":[
        {
            "category":"Professional",
            "subcategory":"Engineering",
            "type":"Services"
        }
    ],
    "sg:phone":"+39 0522 597293",
    "sg:postcode":"42020",
    "sg:province":"Reggio Nell'Emilia",
    "sg:tags":[
        "machine",
        "-",
        "mechanical"
    ],
    "wof:name":"Benevelli Fratelli",
    "wof:placetype":"venue"
},
  "geometry": {"coordinates":[10.573758,44.623112],"type":"Point"}
}