{
  "type": "Feature",
  "properties": {
    "addr:full":"00019 Tivoli Tivoli Roma 00019",
    "addr:postcode":"00019;roma 00019",
    "iso:country":"IT",
    "sg:address":"00019 Tivoli",
    "sg:city":"Tivoli",
    "sg:orig_category":"Palestre",
    "sg:phone":"+39 0774 353985",
    "sg:postcode":"00019",
    "sg:province":"Roma",
    "wof:name":"A.s. Body Art",
    "wof:placetype":"venue"
},
  "geometry": {"coordinates":[12.7326841354,41.9496498108],"type":"Point"}
}