{
  "type": "Feature",
  "properties": {
    "addr:full":"118, Via Santuario Di Oropa 13900 Biella Biella Biella 13900",
    "addr:housenumber":"118",
    "addr:postcode":"13900;13900",
    "addr:street":"Via Santuario Di Oropa",
    "iso:country":"IT",
    "sg:address":"118, Via Santuario Di Oropa 13900 Biella",
    "sg:city":"Biella",
    "sg:classifiers":[
        {
            "category":"Shopping",
            "subcategory":"Crafts & Fabrics",
            "type":"Retail Goods"
        }
    ],
    "sg:phone":"+39 015 252 8600",
    "sg:postcode":"13900",
    "sg:province":"Biella",
    "wof:name":"De Martini S.p.a.",
    "wof:placetype":"venue"
},
  "geometry": {"coordinates":[8.0582695007,45.5628356934],"type":"Point"}
}