{
  "type": "Feature",
  "properties": {
    "iso:country":"IT",
    "sg:address":"80014 Giugliano In Campania",
    "sg:city":"Giugliano in Campania",
    "sg:orig_category":"Odontotecnici - Laboratori",
    "sg:phone":"+39 081 804 8575",
    "sg:postcode":"80014",
    "sg:province":"Napoli",
    "wof:name":"Regio Antonio",
    "wof:placetype":"venue"
},
  "geometry": {"coordinates":[14.09915,40.894428],"type":"Point"}
}