{
  "type": "Feature",
  "properties": {
    "addr:full":"Via Archimede 231 41010 Limidi Limidi Modena 41010",
    "addr:housenumber":"231",
    "addr:postcode":"41010;41010",
    "addr:street":"Via Archimede",
    "iso:country":"IT",
    "sg:address":"Via Archimede 231 41010 Limidi",
    "sg:city":"Limidi",
    "sg:classifiers":[
        {
            "category":"Banks & Credit Unions",
            "subcategory":"Bureau De Change",
            "type":"Services"
        }
    ],
    "sg:phone":"+39 059 561741",
    "sg:postcode":"41010",
    "sg:province":"Modena",
    "sg:tags":[
        "bag",
        "carrier",
        "nylon\u00ae"
    ],
    "wof:name":"Man Plast Srl",
    "wof:placetype":"venue"
},
  "geometry": {"coordinates":[10.905816,44.767262],"type":"Point"}
}