{
  "type": "Feature",
  "properties": {
    "iso:country":"IT",
    "sg:address":"25057 Sale Marasino",
    "sg:city":"Sale Marasino",
    "sg:orig_category":"Macchine, Impianti Ed Attrezzature Per Industria Alimentare E Bevande. Macchine, Impianti Ed Attrezzature Industria Chimica",
    "sg:phone":"+39 030 982 4456",
    "sg:postcode":"25057",
    "sg:province":"Brescia",
    "wof:name":"Buhler Spa",
    "wof:placetype":"venue"
},
  "geometry": {"coordinates":[10.129074,45.711567],"type":"Point"}
}