{
  "type": "Feature",
  "properties": {
    "addr:full":"Via Tridi 1; Torno; 22020 Torno Como 22020",
    "addr:housenumber":"1",
    "addr:postcode":"22020;22020",
    "addr:street":"Via Tridi",
    "iso:country":"IT",
    "sg:address":"Via Tridi 1; Torno; 22020",
    "sg:city":"Torno",
    "sg:classifiers":[
        {
            "category":"Banks & Credit Unions",
            "subcategory":"Bank",
            "type":"Services"
        }
    ],
    "sg:phone":"+39 011 419683",
    "sg:postcode":"22020",
    "sg:province":"Como",
    "wof:name":"Istituto Bancario, San Paolo Di Torino Spa",
    "wof:placetype":"venue"
},
  "geometry": {"coordinates":[9.11594,45.857342],"type":"Point"}
}