{
  "type": "Feature",
  "properties": {
    "iso:country":"IT",
    "sg:address":"50033 Firenzuola",
    "sg:city":"Filigare",
    "sg:orig_category":"Alberghi E Strutture Extra Alberghiere. Ospedali E Servizi Sanitari",
    "sg:phone":"+39 055 810 1271",
    "sg:postcode":"50033",
    "sg:province":"Firenze",
    "wof:name":"Nuova Villa Val Verde Srl",
    "wof:placetype":"venue"
},
  "geometry": {"coordinates":[11.333076,44.198906],"type":"Point"}
}