{
  "type": "Feature",
  "properties": {
    "addr:full":"52048 Monte S.savino Arezzo 52048",
    "addr:housenumber":"52048",
    "addr:postcode":"52048",
    "addr:street":"Monte S.Savino",
    "iso:country":"IT",
    "sg:address":"52048 Monte S.savino",
    "sg:orig_category":"Metalli E Leghe. Gioielleria, Oreficeria E Argenteria",
    "sg:phone":"+39 0575 843038",
    "sg:postcode":"52048",
    "sg:province":"Arezzo",
    "sg:website":"http://www.legioiesnc.it",
    "wof:name":"Le Gioie Snc",
    "wof:placetype":"venue"
},
  "geometry": {"coordinates":[11.8630619049,43.4712028503],"type":"Point"}
}