{
  "type": "Feature",
  "properties": {
    "addr:full":"33170 Pordenone Pordenone Pordenone 33170",
    "addr:postcode":"33170;33170",
    "iso:country":"IT",
    "sg:address":"33170 Pordenone",
    "sg:city":"Pordenone",
    "sg:orig_category":"Arredi Ed Attrezzature Per Uffici",
    "sg:phone":"+39 0434 26625",
    "sg:postcode":"33170",
    "sg:province":"Pordenone",
    "wof:name":"Eliotecnica Pordenone Di Daniela E Silvio Piuzzi Snc",
    "wof:placetype":"venue"
},
  "geometry": {"coordinates":[12.557858,45.895599],"type":"Point"}
}