{
  "type": "Feature",
  "properties": {
    "iso:country":"IT",
    "sg:address":"Via Duca D'aosta 24 10040 Caprie",
    "sg:city":"Caprie",
    "sg:classifiers":[
        {
            "category":"Banks & Credit Unions",
            "subcategory":"Investment Brokerage",
            "type":"Services"
        }
    ],
    "sg:phone":"+39 011 963 2020",
    "sg:postcode":"10040",
    "sg:province":"Torino",
    "sg:tags":[
        "machine",
        "appliance",
        "hlm",
        "disposable",
        "heart-lung"
    ],
    "sg:website":"www.smwautoblok.com",
    "wof:name":"Autoblok Spa",
    "wof:placetype":"venue"
},
  "geometry": {"coordinates":[7.350805,45.115479],"type":"Point"}
}