{
  "type": "Feature",
  "properties": {
    "iso:country":"IT",
    "sg:address":"27028 San Martino Siccomario",
    "sg:city":"San Martino Siccomario",
    "sg:orig_category":"Presse - Produzione E Commercio",
    "sg:phone":"+39 0382 559628",
    "sg:postcode":"27028",
    "sg:province":"Pavia",
    "wof:name":"Rebasti Srl",
    "wof:placetype":"venue"
},
  "geometry": {"coordinates":[9.1199331284,45.1416893005],"type":"Point"}
}