{
  "type": "Feature",
  "properties": {
    "addr:full":"20139 Milano Milano Milano 20139",
    "addr:postcode":"20139;20139",
    "iso:country":"IT",
    "sg:address":"20139 Milano",
    "sg:city":"Milano",
    "sg:classifiers":[
        {
            "category":"Social Services",
            "subcategory":"Child Care",
            "type":"Services"
        }
    ],
    "sg:phone":"+39 02 5681 6956",
    "sg:postcode":"20139",
    "sg:province":"Milano",
    "sg:tags":[
        "baby",
        "sitter",
        "-",
        "servizio"
    ],
    "sg:website":"http://www.babyworld.it",
    "wof:name":"Babyworld Srl",
    "wof:placetype":"venue"
},
  "geometry": {"coordinates":[9.227516,45.428825],"type":"Point"}
}