{
  "type": "Feature",
  "properties": {
    "addr:full":"Via Mar Lonio 2; Fossoli Di Capri; 41010 Modena 41010",
    "addr:housenumber":"2",
    "addr:postcode":"41010;41010",
    "addr:street":"Via Mar Lonio",
    "iso:country":"IT",
    "sg:address":"Via Mar Lonio 2; Fossoli Di Capri; 41010",
    "sg:classifiers":[
        {
            "category":"Banks & Credit Unions",
            "subcategory":"Bank",
            "type":"Services"
        }
    ],
    "sg:phone":"+39 059 660618",
    "sg:postcode":"41010",
    "sg:province":"Modena",
    "wof:name":"Cassa Risparmio Carpi Spa",
    "wof:placetype":"venue"
},
  "geometry": {"coordinates":[10.921619,44.76284],"type":"Point"}
}