{
  "type": "Feature",
  "properties": {
    "iso:country":"IT",
    "sg:address":"00125 Roma",
    "sg:city":"Roma",
    "sg:orig_category":"Forniture Per Agricoltura E Zootecnia",
    "sg:phone":"+39 06 5231 0023",
    "sg:postcode":"00125",
    "sg:province":"Roma",
    "wof:name":"Zootecnica Alimentare Srl",
    "wof:placetype":"venue"
},
  "geometry": {"coordinates":[12.35572052,41.7616500854],"type":"Point"}
}