{
  "type": "Feature",
  "properties": {
    "iso:country":"IT",
    "sg:address":"56017 S. Giuliano Terme",
    "sg:city":"Gello",
    "sg:orig_category":"Autoscuole",
    "sg:phone":"+39 050 820022",
    "sg:postcode":"56017",
    "sg:province":"Pisa",
    "wof:name":"Autoscuola Futura Di Logli & C.",
    "wof:placetype":"venue"
},
  "geometry": {"coordinates":[10.422337,43.751961],"type":"Point"}
}