{
  "type": "Feature",
  "properties": {
    "addr:full":"35030 Cervarese Santa Croce Cervarese Santa Croce Padova 35030",
    "addr:postcode":"35030;35030",
    "iso:country":"IT",
    "sg:address":"35030 Cervarese Santa Croce",
    "sg:city":"Cervarese Santa Croce",
    "sg:orig_category":"Servizi E Lavori Per Agricoltura E Zootecnia",
    "sg:phone":"+39 049 991 0774",
    "sg:postcode":"35030",
    "sg:province":"Padova",
    "wof:name":"Ramin Stefano",
    "wof:placetype":"venue"
},
  "geometry": {"coordinates":[11.675654,45.417816],"type":"Point"}
}