{
  "type": "Feature",
  "properties": {
    "iso:country":"IT",
    "sg:address":"20090 Pieve Emanuele",
    "sg:city":"Pieve Emanuele",
    "sg:orig_category":"Metalli E Leghe",
    "sg:phone":"+39 02 9072 3474",
    "sg:postcode":"20090",
    "sg:province":"Milano",
    "wof:name":"Fonderia Fall Di Niccolucci Elvio",
    "wof:placetype":"venue"
},
  "geometry": {"coordinates":[9.1928863525,45.3717956543],"type":"Point"}
}