{
  "type": "Feature",
  "properties": {
    "addr:full":"59100 Prato Prato Prato 59100",
    "addr:postcode":"59100;59100",
    "iso:country":"IT",
    "sg:address":"59100 Prato",
    "sg:city":"Prato",
    "sg:orig_category":"Filati - Produzione E Ingrosso",
    "sg:phone":"+39 0574 621162",
    "sg:postcode":"59100",
    "sg:province":"Prato",
    "wof:name":"Tessitura Virgola Srl",
    "wof:placetype":"venue"
},
  "geometry": {"coordinates":[11.0938081741,43.8780326843],"type":"Point"}
}