{
  "type": "Feature",
  "properties": {
    "addr:full":"50058 San Mauro A Signa San Mauro Firenze 50058",
    "addr:housenumber":"50058",
    "addr:postcode":"50058",
    "addr:street":"San Mauro A Signa",
    "iso:country":"IT",
    "sg:address":"50058 San Mauro A Signa",
    "sg:city":"San Mauro",
    "sg:orig_category":"Non-classified Establishments",
    "sg:phone":"+39 055 873 9151",
    "sg:postcode":"50058",
    "sg:province":"Firenze",
    "wof:name":"Cartei Rina Sas Di Mori G. & C.",
    "wof:placetype":"venue"
},
  "geometry": {"coordinates":[11.126682,43.794411],"type":"Point"}
}