{
  "type": "Feature",
  "properties": {
    "iso:country":"IT",
    "sg:address":"Via Monte Bianco 8 28047 Oleggio",
    "sg:city":"Oleggio",
    "sg:classifiers":[
        {
            "category":"Shopping",
            "subcategory":"Clothing, Apparel, & Fashions",
            "type":"Retail Goods"
        }
    ],
    "sg:phone":"+39 0321 91064",
    "sg:postcode":"28047",
    "sg:province":"Novara",
    "sg:tags":[
        "sportswear"
    ],
    "wof:name":"Essevi Sas Di Elena Mazzoni & C.",
    "wof:placetype":"venue"
},
  "geometry": {"coordinates":[8.627563,45.603817],"type":"Point"}
}