{
  "type": "Feature",
  "properties": {
    "iso:country":"IT",
    "sg:address":"25030 Erbusco",
    "sg:city":"Erbusco",
    "sg:orig_category":"Servizi E Lavori Per Abbigliamento E Pelletterie. Cartotecnica E Servizi. Servizi E Lavori Industria Delle Materie Plastiche",
    "sg:phone":"+39 030 770 3730",
    "sg:postcode":"25030",
    "sg:province":"Brescia",
    "wof:name":"Akkoppio S.r.l.",
    "wof:placetype":"venue"
},
  "geometry": {"coordinates":[9.971828,45.597416],"type":"Point"}
}