{
  "type": "Feature",
  "properties": {
    "iso:country":"IT",
    "sg:address":"10133 Torino",
    "sg:city":"Torino",
    "sg:orig_category":"Utensili Meccanici E Materiali",
    "sg:phone":"+39 011 661 0792",
    "sg:postcode":"10133",
    "sg:province":"Torino",
    "wof:name":"A.p.i. Di Gaia Maurizio & C Sas",
    "wof:placetype":"venue"
},
  "geometry": {"coordinates":[7.685918,45.009018],"type":"Point"}
}