{
  "type": "Feature",
  "properties": {
    "iso:country":"IT",
    "sg:address":"24050 Lurano",
    "sg:city":"Lurano",
    "sg:orig_category":"Prodotti E Manufatti In Materie Plastiche",
    "sg:phone":"+39 035 800455",
    "sg:postcode":"24050",
    "sg:province":"Bergamo",
    "wof:name":"Gam.mo. Stampi Srl",
    "wof:placetype":"venue"
},
  "geometry": {"coordinates":[9.6407060623,45.5623855591],"type":"Point"}
}