{
  "type": "Feature",
  "properties": {
    "addr:full":"12066 Monticello D'alba Cuneo 12066",
    "addr:housenumber":"12066",
    "addr:postcode":"12066",
    "addr:street":"Monticello",
    "iso:country":"IT",
    "sg:address":"12066 Monticello D'alba",
    "sg:orig_category":"Articoli Per Imballaggio E Confezionamento",
    "sg:phone":"+39 0173 441375",
    "sg:postcode":"12066",
    "sg:province":"Cuneo",
    "wof:name":"Alba Inox Srl",
    "wof:placetype":"venue"
},
  "geometry": {"coordinates":[7.88229,44.697895],"type":"Point"}
}