{
  "type": "Feature",
  "properties": {
    "addr:full":"Via Volta 21 20082 Binasco Binasco Milano 20082",
    "addr:housenumber":"21",
    "addr:postcode":"20082;20082",
    "addr:street":"Via Volta",
    "iso:country":"IT",
    "sg:address":"Via Volta 21 20082 Binasco",
    "sg:city":"Binasco",
    "sg:classifiers":[
        {
            "category":"Autos & Motor Vehicles",
            "subcategory":"Fuel & Gas Station",
            "type":"Retail Goods"
        }
    ],
    "sg:phone":"+39 02 905 5358",
    "sg:postcode":"20082",
    "sg:province":"Milano",
    "sg:tags":[
        "pump",
        "lubrication"
    ],
    "sg:website":"www.fisme.it",
    "wof:name":"Fisme Srl",
    "wof:placetype":"venue"
},
  "geometry": {"coordinates":[9.188141,45.463688],"type":"Point"}
}