{
  "type": "Feature",
  "properties": {
    "addr:full":"79, Via Milano 26013 Crema Crema Cremona 26013",
    "addr:postcode":"26013;26013",
    "addr:street":"Via Milano",
    "iso:country":"IT",
    "sg:address":"79, Via Milano 26013 Crema",
    "sg:city":"Crema",
    "sg:classifiers":[
        {
            "category":"Professional",
            "subcategory":"Printing & Photocopies",
            "type":"Services"
        }
    ],
    "sg:phone":"+39 0373 219031",
    "sg:postcode":"26013",
    "sg:province":"Cremona",
    "wof:name":"Grafin Di Cattaneo Gastone E C. Snc",
    "wof:placetype":"venue"
},
  "geometry": {"coordinates":[9.6427297592,45.359828949],"type":"Point"}
}