{
  "type": "Feature",
  "properties": {
    "iso:country":"IT",
    "sg:address":"00040 Roma",
    "sg:orig_category":"Termotecnica E Riscaldamento, Apparecchiature E Servizi",
    "sg:phone":"+39 06 7267 1964",
    "sg:postcode":"00040",
    "sg:province":"Roma",
    "wof:name":"Vabat Di De Belardini & C Snc",
    "wof:placetype":"venue"
},
  "geometry": {"coordinates":[12.622455,41.824825],"type":"Point"}
}