{
  "type": "Feature",
  "properties": {
    "iso:country":"IT",
    "sg:address":"00164 Roma",
    "sg:city":"Roma",
    "sg:orig_category":"Ceramiche: Prodotti E Lavorazioni. Articoli Da Regalo. Arte Ed Artigianato Artistico. Shopping",
    "sg:phone":"+39 06 666 3242",
    "sg:postcode":"00164",
    "sg:province":"Roma",
    "wof:name":"Paolelli Passione Ceramica Di L. Paolelli",
    "wof:placetype":"venue"
},
  "geometry": {"coordinates":[12.428073,41.879921],"type":"Point"}
}