{
  "type": "Feature",
  "properties": {
    "iso:country":"IT",
    "sg:address":"20043 Arcore",
    "sg:city":"Arcore",
    "sg:orig_category":"Tessuti E Stoffe",
    "sg:phone":"+39 039 614120",
    "sg:postcode":"20043",
    "sg:province":"Milano",
    "wof:name":"M.b. Tex Srl",
    "wof:placetype":"venue"
},
  "geometry": {"coordinates":[9.325377,45.614708],"type":"Point"}
}