{
  "type": "Feature",
  "properties": {
    "addr:full":"20016 Pero Pero Milano 20016",
    "addr:postcode":"20016;20016",
    "iso:country":"IT",
    "sg:address":"20016 Pero",
    "sg:city":"Pero",
    "sg:orig_category":"Climatizzazione E Condizionamento, Apparecchiature E Servizi. Accessori Dei Mezzi Di Trasporto",
    "sg:phone":"+39 02 3810 0376",
    "sg:postcode":"20016",
    "sg:province":"Milano",
    "wof:name":"Twin Cam Di Diego Mandelli",
    "wof:placetype":"venue"
},
  "geometry": {"coordinates":[9.092367,45.510281],"type":"Point"}
}