{
  "type": "Feature",
  "properties": {
    "iso:country":"IT",
    "sg:address":"25050 Provaglio D'iseo",
    "sg:orig_category":"Servizi E Lavori Per Edilizia E Lavori Pubblici",
    "sg:phone":"+39 030 983179",
    "sg:postcode":"25050",
    "sg:province":"Brescia",
    "wof:name":"Ferrari Paolo",
    "wof:placetype":"venue"
},
  "geometry": {"coordinates":[10.057896,45.617371],"type":"Point"}
}