{
  "type": "Feature",
  "properties": {
    "iso:country":"IT",
    "sg:address":"50018 Scandicci",
    "sg:city":"Scandicci",
    "sg:orig_category":"Pelletterie - Produzione E Ingrosso",
    "sg:phone":"+39 055 731 0465",
    "sg:postcode":"50018",
    "sg:province":"Firenze",
    "wof:name":"Pelletterie Artistiche Florence Snc",
    "wof:placetype":"venue"
},
  "geometry": {"coordinates":[11.15579319,43.7626457214],"type":"Point"}
}