{
  "type": "Feature",
  "properties": {
    "addr:full":"20035 Lissone Lissone Milano 20035",
    "addr:postcode":"20035;20035",
    "iso:country":"IT",
    "sg:address":"20035 Lissone",
    "sg:city":"Lissone",
    "sg:orig_category":"Servizi E Lavori Per Arredamento E Industria Del Legno",
    "sg:phone":"+39 039 481236",
    "sg:postcode":"20035",
    "sg:province":"Milano",
    "wof:name":"Mussi Bianchi Fossati (s.r.l.)",
    "wof:placetype":"venue"
},
  "geometry": {"coordinates":[9.151006,45.572495],"type":"Point"}
}