{
  "type": "Feature",
  "properties": {
    "iso:country":"IT",
    "sg:address":"80138 Napoli",
    "sg:city":"Napoli",
    "sg:orig_category":"Servizi Vari Di Interesse Pubblico",
    "sg:phone":"+39 081 553 6596",
    "sg:postcode":"80138",
    "sg:province":"Napoli",
    "sg:website":"http://web.tiscalinet.it/amore_amore",
    "wof:name":"Amore & Amore",
    "wof:placetype":"venue"
},
  "geometry": {"coordinates":[14.26181,40.848518],"type":"Point"}
}