{
  "type": "Feature",
  "properties": {
    "addr:full":"25064 Gussago Gussago Brescia 25064",
    "addr:postcode":"25064;25064",
    "iso:country":"IT",
    "sg:address":"25064 Gussago",
    "sg:city":"Gussago",
    "sg:orig_category":"Forniture Per Agricoltura E Zootecnia",
    "sg:phone":"+39 030 252 2000",
    "sg:postcode":"25064",
    "sg:province":"Brescia",
    "wof:name":"La Vecchia Fattoria",
    "wof:placetype":"venue"
},
  "geometry": {"coordinates":[10.1530580521,45.594455719],"type":"Point"}
}