{
  "type": "Feature",
  "properties": {
    "addr:full":"10147 Torino Torino Torino 10147",
    "addr:postcode":"10147;10147",
    "iso:country":"IT",
    "sg:address":"10147 Torino",
    "sg:city":"Torino",
    "sg:orig_category":"Forniture Per Abbigliamento E Pelletterie. Forniture E Materiali Per Imballaggio E Confezionamento",
    "sg:phone":"+39 011 221 7678",
    "sg:postcode":"10147",
    "sg:province":"Torino",
    "wof:name":"Scrofano Carmelo",
    "wof:placetype":"venue"
},
  "geometry": {"coordinates":[7.6784529686,45.1004486084],"type":"Point"}
}