{
  "type": "Feature",
  "properties": {
    "iso:country":"IT",
    "sg:address":"95030 Mascalucia",
    "sg:city":"Mascalucia",
    "sg:orig_category":"Studi E Consulenze Tecniche E Industriali. Consulenze Tecniche, Amministrative E Perizie. Professionisti - Studi E Servizi Ed Associazioni Di Interesse Aziendale",
    "sg:phone":"+39 095 727 0298",
    "sg:postcode":"95030",
    "sg:province":"Catania",
    "wof:name":"Distefano Maurizio",
    "wof:placetype":"venue"
},
  "geometry": {"coordinates":[15.032393,37.567348],"type":"Point"}
}