{
  "type": "Feature",
  "properties": {
    "iso:country":"IT",
    "sg:address":"Corso Borsalino 46; Alessandria; 15100",
    "sg:city":"Alessandria",
    "sg:classifiers":[
        {
            "category":"Banks & Credit Unions",
            "subcategory":"Bank",
            "type":"Services"
        }
    ],
    "sg:phone":"+39 0131 236040",
    "sg:postcode":"15100",
    "sg:province":"Alessandria",
    "wof:name":"Banca Carige Spa",
    "wof:placetype":"venue"
},
  "geometry": {"coordinates":[8.617095,44.907722],"type":"Point"}
}