{
  "type": "Feature",
  "properties": {
    "addr:full":"17026 Noli Noli Savona 17026",
    "addr:postcode":"17026;17026",
    "iso:country":"IT",
    "sg:address":"17026 Noli",
    "sg:city":"Noli",
    "sg:orig_category":"Alberghi E Strutture Extra Alberghiere. Ospedali E Servizi Sanitari",
    "sg:phone":"+39 019 748924",
    "sg:postcode":"17026",
    "sg:province":"Savona",
    "wof:name":"Citta' Di Torino",
    "wof:placetype":"venue"
},
  "geometry": {"coordinates":[8.415492,44.223492],"type":"Point"}
}