{
  "type": "Feature",
  "properties": {
    "iso:country":"IT",
    "sg:address":"27047 Santa Maria Della Versa",
    "sg:city":"Santa Maria della Versa",
    "sg:orig_category":"Imprese Di Costruzioni Civili Ed Industriali",
    "sg:phone":"+39 0385 79526",
    "sg:postcode":"27047",
    "sg:province":"Pavia",
    "wof:name":"Bruciamonti Alberto",
    "wof:placetype":"venue"
},
  "geometry": {"coordinates":[9.29737,44.990166],"type":"Point"}
}