{
  "type": "Feature",
  "properties": {
    "iso:country":"IT",
    "sg:address":"88100 Catanzaro",
    "sg:city":"Catanzaro",
    "sg:orig_category":"Forniture Per Uffici",
    "sg:phone":"+39 0961 33572",
    "sg:postcode":"88100",
    "sg:province":"Catanzaro",
    "wof:name":"La Sfera Di Albano Fabrizio & C. Sas",
    "wof:placetype":"venue"
},
  "geometry": {"coordinates":[16.6108322144,38.8193130493],"type":"Point"}
}