{
  "type": "Feature",
  "properties": {
    "iso:country":"IT",
    "sg:address":"36060 Molvena",
    "sg:city":"Molvena",
    "sg:orig_category":"Legno E Semilavorati",
    "sg:phone":"+39 0424 470304",
    "sg:postcode":"36060",
    "sg:province":"Vicenza",
    "wof:name":"Mozzato Saverino & Roberto",
    "wof:placetype":"venue"
},
  "geometry": {"coordinates":[11.615138,45.737953],"type":"Point"}
}