{
  "type": "Feature",
  "properties": {
    "addr:full":"20090 Buccinasco Buccinasco Milano 20090",
    "addr:postcode":"20090;20090",
    "iso:country":"IT",
    "sg:address":"20090 Buccinasco",
    "sg:city":"Buccinasco",
    "sg:orig_category":"Minuterie Metalliche E Ferramenta",
    "sg:phone":"+39 02 4570 0208",
    "sg:postcode":"20090",
    "sg:province":"Milano",
    "wof:name":"Derk (s.p.a.)",
    "wof:placetype":"venue"
},
  "geometry": {"coordinates":[9.115319252,45.4168586731],"type":"Point"}
}