{
  "type": "Feature",
  "properties": {
    "iso:country":"IT",
    "sg:address":"33040 Corno Di Rosazzo",
    "sg:city":"Corno di Rosazzo",
    "sg:orig_category":"Lavorazioni Meccaniche E Servizi",
    "sg:phone":"+39 0432 753338",
    "sg:postcode":"33040",
    "sg:province":"Udine",
    "sg:website":"http://www.eurofriuli.com/bl/index.htm",
    "wof:name":"B.l. Snc Di Blancuzzi M. & Lemme G.",
    "wof:placetype":"venue"
},
  "geometry": {"coordinates":[13.441377,45.994537],"type":"Point"}
}