{
  "type": "Feature",
  "properties": {
    "iso:country":"IT",
    "sg:address":"27, Via Foggia 70014 Conversano",
    "sg:city":"Conversano",
    "sg:classifiers":[
        {
            "category":"Utilities",
            "subcategory":"Telephone",
            "type":"Services"
        }
    ],
    "sg:phone":"+39 080 495 2020",
    "sg:postcode":"70014",
    "sg:province":"Bari",
    "sg:tags":[
        "telecommunication"
    ],
    "wof:name":"Videopuglia (s.r.l.)",
    "wof:placetype":"venue"
},
  "geometry": {"coordinates":[17.110308,40.970886],"type":"Point"}
}