{
  "type": "Feature",
  "properties": {
    "addr:full":"70026 Modugno Modugno Bari 70026",
    "addr:postcode":"70026;70026",
    "iso:country":"IT",
    "sg:address":"70026 Modugno",
    "sg:city":"Modugno",
    "sg:orig_category":"Trasporti E Spedizioni Merci",
    "sg:phone":"+39 080 531 4220",
    "sg:postcode":"70026",
    "sg:province":"Bari",
    "sg:website":"http://www.arcotrans.com",
    "wof:name":"Arcotrans Spa",
    "wof:placetype":"venue"
},
  "geometry": {"coordinates":[16.790714,41.115612],"type":"Point"}
}