{
  "type": "Feature",
  "properties": {
    "addr:full":"70051 Barletta Barletta Bari 70051",
    "addr:postcode":"70051;70051",
    "iso:country":"IT",
    "sg:address":"70051 Barletta",
    "sg:city":"Barletta",
    "sg:orig_category":"Prodotti Alimentari",
    "sg:phone":"+39 0883 515025",
    "sg:postcode":"70051",
    "sg:province":"Bari",
    "wof:name":"Cogipal Di Lionetti Concetta E Giuseppe (s.n.c.)",
    "wof:placetype":"venue"
},
  "geometry": {"coordinates":[16.2769832611,41.3169670105],"type":"Point"}
}