{
  "type": "Feature",
  "properties": {
    "addr:full":"Via Froner 3, 38050 Roncegno, Tn Roncegno Trento 38050",
    "addr:housenumber":"3",
    "addr:postcode":"38050;38050",
    "addr:street":"Via Froner;Trento",
    "iso:country":"IT",
    "sg:address":"Via Froner 3, 38050 Roncegno, Tn",
    "sg:city":"Roncegno",
    "sg:classifiers":[
        {
            "category":"Banks & Credit Unions",
            "subcategory":"Bank",
            "type":"Services"
        }
    ],
    "sg:postcode":"38050",
    "sg:province":"Trento",
    "wof:name":"Cassa Rurale Di Roncegno-banca Di Credito Cooperativo Scarl",
    "wof:placetype":"venue"
},
  "geometry": {"coordinates":[11.411589,46.053055],"type":"Point"}
}