{
  "type": "Feature",
  "properties": {
    "iso:country":"IT",
    "sg:address":"2, Via Appia 72015 Fasano",
    "sg:city":"Fasano",
    "sg:classifiers":[
        {
            "category":"Travel",
            "subcategory":"Travel Agent",
            "type":"Entertainment"
        }
    ],
    "sg:phone":"+39 080 482 0133",
    "sg:postcode":"72015",
    "sg:province":"Brindisi",
    "sg:tags":[
        "business"
    ],
    "wof:name":"Il Grand Hotel Di Torre Canne - Terme",
    "wof:placetype":"venue"
},
  "geometry": {"coordinates":[17.413584,40.870277],"type":"Point"}
}