{
  "type": "Feature",
  "properties": {
    "iso:country":"IT",
    "sg:address":"84013 Cava De'tirreni",
    "sg:orig_category":"Servizi E Lavori Per Ecologia E Smaltimento Rifiuti. Servizi Ausiliari Di Analisi, Controllo E Ricerca",
    "sg:phone":"+39 089 340033",
    "sg:postcode":"84013",
    "sg:province":"Salerno",
    "wof:name":"La.sp.ed. Tirreno Srl",
    "wof:placetype":"venue"
},
  "geometry": {"coordinates":[14.693768,40.706985],"type":"Point"}
}