{
  "type": "Feature",
  "properties": {
    "iso:country":"IT",
    "sg:address":"17100 Savona",
    "sg:city":"Savona",
    "sg:orig_category":"Servizi E Lavori Per Abbigliamento E Pelletterie",
    "sg:phone":"+39 019 833 5208",
    "sg:postcode":"17100",
    "sg:province":"Savona",
    "wof:name":"Traina Antonino",
    "wof:placetype":"venue"
},
  "geometry": {"coordinates":[8.479088,44.307587],"type":"Point"}
}