{
  "type": "Feature",
  "properties": {
    "addr:full":"Via Cervi Fratelli 50013 Campi Bisenzio Campi Bisenzio Firenze 50013",
    "addr:postcode":"50013;50013",
    "addr:street":"Via Cervi;Bisenzio",
    "iso:country":"IT",
    "sg:address":"Via Cervi Fratelli 50013 Campi Bisenzio",
    "sg:city":"Campi Bisenzio",
    "sg:classifiers":[
        {
            "category":"Manufacturing",
            "subcategory":"Motor Vehicles & Parts",
            "type":"Manufacturing & Wholesale Goods"
        }
    ],
    "sg:phone":"+39 390 558 9431",
    "sg:postcode":"50013",
    "sg:province":"Firenze",
    "sg:tags":[
        "engine"
    ],
    "wof:name":"Gkn Componenti Firenze Spa",
    "wof:placetype":"venue"
},
  "geometry": {"coordinates":[11.256902,43.768734],"type":"Point"}
}