{
  "type": "Feature",
  "properties": {
    "addr:full":"4/b, Via Rossa Guido 21012 Cassano Magnago Cassano Magnago Varese 21012",
    "addr:housenumber":"4 / b",
    "addr:postcode":"21012;21012",
    "addr:street":"Via Rossa Guido",
    "iso:country":"IT",
    "sg:address":"4/b, Via Rossa Guido 21012 Cassano Magnago",
    "sg:city":"Cassano Magnago",
    "sg:classifiers":[
        {
            "category":"Shopping",
            "subcategory":"Crafts & Fabrics",
            "type":"Retail Goods"
        }
    ],
    "sg:phone":"+39 0331 282260",
    "sg:postcode":"21012",
    "sg:province":"Varese",
    "wof:name":"Sammartini Snc Di Sammartini Giuseppe & C",
    "wof:placetype":"venue"
},
  "geometry": {"coordinates":[8.8263845444,45.8176040649],"type":"Point"}
}