{
  "type": "Feature",
  "properties": {
    "iso:country":"IT",
    "sg:address":"50142 Firenze",
    "sg:city":"Firenze",
    "sg:orig_category":"Attrezzature E Forniture Per Officine Riparazione E Servizi Ausiliari",
    "sg:phone":"+39 055 714784",
    "sg:postcode":"50142",
    "sg:province":"Firenze",
    "wof:name":"Ti - Erre & C. S.n.c.",
    "wof:placetype":"venue"
},
  "geometry": {"coordinates":[11.217177,43.77351],"type":"Point"}
}