{
  "type": "Feature",
  "properties": {
    "iso:country":"IT",
    "sg:address":"23900 Lecco",
    "sg:city":"Lecco",
    "sg:orig_category":"Abbigliamento Esterno, Maglierie E Pelliccerie. Shopping",
    "sg:phone":"+39 0341 350185",
    "sg:postcode":"23900",
    "sg:province":"Lecco",
    "wof:name":"Classique Srl",
    "wof:placetype":"venue"
},
  "geometry": {"coordinates":[9.415548,45.849552],"type":"Point"}
}