{
  "type": "Feature",
  "properties": {
    "iso:country":"IT",
    "sg:address":"23808 Vercurago",
    "sg:city":"Vercurago",
    "sg:orig_category":"Materiali Semilavorati Metallici",
    "sg:phone":"+39 0341 420137",
    "sg:postcode":"23808",
    "sg:province":"Lecco",
    "wof:name":"Safilo Spa",
    "wof:placetype":"venue"
},
  "geometry": {"coordinates":[9.424092,45.812943],"type":"Point"}
}