{
  "type": "Feature",
  "properties": {
    "iso:country":"IT",
    "sg:address":"10087 Valperga",
    "sg:city":"Valperga",
    "sg:orig_category":"Motori Ed Organi Di Trasmissione. Ricambi E Componenti Dei Mezzi Di Trasporto",
    "sg:phone":"+39 0124 617303",
    "sg:postcode":"10087",
    "sg:province":"Torino",
    "wof:name":"Trioneuro S.p.a.",
    "wof:placetype":"venue"
},
  "geometry": {"coordinates":[7.655933857,45.3429794312],"type":"Point"}
}