{
  "type": "Feature",
  "properties": {
    "addr:full":"24050 Zanica Zanica Bergamo 24050",
    "addr:postcode":"24050;24050",
    "iso:country":"IT",
    "sg:address":"24050 Zanica",
    "sg:city":"Zanica",
    "sg:orig_category":"Caravans, Campers, Roulottes E Accessori",
    "sg:phone":"+39 035 671505",
    "sg:postcode":"24050",
    "sg:province":"Bergamo",
    "wof:name":"Camper Berghem S.s. Snc",
    "wof:placetype":"venue"
},
  "geometry": {"coordinates":[9.680524,45.641747],"type":"Point"}
}