{
  "type": "Feature",
  "properties": {
    "addr:full":"10090 Villarbasse Villarbasse Torino 10090",
    "addr:postcode":"10090;10090",
    "iso:country":"IT",
    "sg:address":"10090 Villarbasse",
    "sg:city":"Villarbasse",
    "sg:orig_category":"Campeggio. Automobili E Mezzi Di Trasporto",
    "sg:phone":"+39 011 952066",
    "sg:postcode":"10090",
    "sg:province":"Torino",
    "wof:name":"Trasfotec Srl",
    "wof:placetype":"venue"
},
  "geometry": {"coordinates":[7.492161,45.047428],"type":"Point"}
}