{
  "type": "Feature",
  "properties": {
    "addr:full":"95128 Catania Catania Catania 95128",
    "addr:postcode":"95128;95128",
    "iso:country":"IT",
    "sg:address":"95128 Catania",
    "sg:city":"Catania",
    "sg:orig_category":"Articoli Regalo - Vendita Al Dettaglio",
    "sg:phone":"+39 095 446022",
    "sg:postcode":"95128",
    "sg:province":"Catania",
    "wof:name":"Motta Cartapiu'",
    "wof:placetype":"venue"
},
  "geometry": {"coordinates":[15.091149,37.517288],"type":"Point"}
}