{
  "type": "Feature",
  "properties": {
    "addr:full":"C.so Fogazzaro, 37; Vicenza; 36100 Vicenza Vicenza 36100",
    "addr:housenumber":"37",
    "addr:postcode":"36100;36100",
    "addr:street":"C.So Fogazzaro",
    "iso:country":"IT",
    "sg:address":"C.so Fogazzaro, 37; Vicenza; 36100",
    "sg:city":"Vicenza",
    "sg:classifiers":[
        {
            "category":"Shopping",
            "subcategory":"Computers & Home Electronics",
            "type":"Retail Goods"
        }
    ],
    "sg:phone":"+39 0444 994811",
    "sg:postcode":"36100",
    "sg:province":"Vicenza",
    "sg:tags":[
        "chamber",
        "commerce"
    ],
    "sg:website":"www.vi.camcom.it",
    "wof:name":"Vicenza Chamber Of Commerce & Industry",
    "wof:placetype":"venue"
},
  "geometry": {"coordinates":[11.543074,45.548069],"type":"Point"}
}