{
  "type": "Feature",
  "properties": {
    "iso:country":"IT",
    "sg:address":"Via Stazione, Km 1 74020 Avetrana",
    "sg:city":"Avetrana",
    "sg:classifiers":[
        {
            "category":"Food & Beverages",
            "subcategory":"Liquor & Beverages",
            "type":"Retail Goods"
        }
    ],
    "sg:phone":"+39 099 970 4513",
    "sg:postcode":"74020",
    "sg:province":"Taranto",
    "sg:tags":[
        "wine",
        "italian"
    ],
    "sg:website":"www.oliodepadova.it",
    "wof:name":"Francesco De Padova Srl",
    "wof:placetype":"venue"
},
  "geometry": {"coordinates":[17.240009,40.469238],"type":"Point"}
}