{
  "type": "Feature",
  "properties": {
    "iso:country":"IT",
    "sg:address":"10147 Torino",
    "sg:city":"Torino",
    "sg:orig_category":"Tende E Tendaggi - Vendita Al Dettaglio",
    "sg:phone":"+39 011 296607",
    "sg:postcode":"10147",
    "sg:province":"Torino",
    "wof:name":"Telerie E Arredamenti Di Masera",
    "wof:placetype":"venue"
},
  "geometry": {"coordinates":[7.675841,45.100243],"type":"Point"}
}