{
  "type": "Feature",
  "properties": {
    "addr:full":"2, Piazza Andria 00132 Roma Roma Roma 00132",
    "addr:postcode":"00132;00132",
    "addr:street":"Piazza Andria",
    "iso:country":"IT",
    "sg:address":"2, Piazza Andria 00132 Roma",
    "sg:city":"Roma",
    "sg:classifiers":[
        {
            "category":"Parking",
            "subcategory":"Lot",
            "type":"Transportation"
        }
    ],
    "sg:phone":"+39 06 2244 6693",
    "sg:postcode":"00132",
    "sg:province":"Roma",
    "sg:tags":[
        "transport",
        "road"
    ],
    "wof:name":"Picillo Snc",
    "wof:placetype":"venue"
},
  "geometry": {"coordinates":[12.663923,41.890182],"type":"Point"}
}