{
  "type": "Feature",
  "properties": {
    "iso:country":"IT",
    "sg:address":"41100 Modena",
    "sg:city":"Modena",
    "sg:orig_category":"Non-classified Establishments",
    "sg:phone":"+39 059 450557",
    "sg:postcode":"41100",
    "sg:province":"Modena",
    "sg:website":"http://www.casadelbambu.modena.it",
    "wof:name":"Castagnoli Massimo",
    "wof:placetype":"venue"
},
  "geometry": {"coordinates":[10.899542,44.648563],"type":"Point"}
}