{
  "type": "Feature",
  "properties": {
    "addr:full":"Via Don Carlo Barison 14e 35010 Onara Padova 35010",
    "addr:housenumber":"14e",
    "addr:postcode":"35010;35010",
    "addr:street":"Via Don Carlo Barison",
    "iso:country":"IT",
    "sg:address":"Via Don Carlo Barison 14e 35010 Onara",
    "sg:classifiers":[
        {
            "category":"Manufacturing",
            "subcategory":"Rubber & Plastics",
            "type":"Manufacturing & Wholesale Goods"
        }
    ],
    "sg:phone":"+39 049 599 3080",
    "sg:postcode":"35010",
    "sg:province":"Padova",
    "sg:tags":[
        "galosh",
        "boot",
        "boots",
        "polyvinyl",
        "pvc",
        "chloride"
    ],
    "wof:name":"Calzaturificio Zecchin Srl",
    "wof:placetype":"venue"
},
  "geometry": {"coordinates":[11.876589,45.409569],"type":"Point"}
}