{
  "type": "Feature",
  "properties": {
    "iso:country":"IT",
    "sg:address":"Ctr Macchione 14/10 Ex 10 70052 Bisceglie",
    "sg:city":"Bisceglie",
    "sg:classifiers":[
        {
            "category":"Shopping",
            "subcategory":"Clothing, Apparel, & Fashions",
            "type":"Retail Goods"
        }
    ],
    "sg:phone":"+39 080 395 8245",
    "sg:postcode":"70052",
    "sg:province":"Bari",
    "sg:tags":[
        "image",
        "clothing",
        "basic"
    ],
    "sg:website":"www.unoelle.it",
    "wof:name":"1 L'unoelle Di Lampedecchia Pasquale",
    "wof:placetype":"venue"
},
  "geometry": {"coordinates":[16.869291,41.126053],"type":"Point"}
}