{
  "type": "Feature",
  "properties": {
    "iso:country":"IT",
    "sg:address":"40033 Casalecchio Di Reno",
    "sg:city":"Casalecchio di Reno",
    "sg:orig_category":"Officine Meccaniche",
    "sg:phone":"+39 051 750528",
    "sg:postcode":"40033",
    "sg:province":"Bologna",
    "wof:name":"F.lli Santi",
    "wof:placetype":"venue"
},
  "geometry": {"coordinates":[11.251216,44.491364],"type":"Point"}
}