{
  "type": "Feature",
  "properties": {
    "iso:country":"IT",
    "sg:address":"25124 Brescia",
    "sg:city":"Brescia",
    "sg:orig_category":"Materiali E Componenti Elettronici",
    "sg:phone":"+39 030 226272",
    "sg:postcode":"25124",
    "sg:province":"Brescia",
    "wof:name":"Delta Elettronica Di G. Marchioro",
    "wof:placetype":"venue"
},
  "geometry": {"coordinates":[10.220579,45.524181],"type":"Point"}
}