{
  "type": "Feature",
  "properties": {
    "addr:full":"Via Della Liberta' 51 10095 Grugliasco Grugliasco Torino 10095",
    "addr:housenumber":"51",
    "addr:postcode":"10095;10095",
    "addr:street":"Via Della Liberta '",
    "iso:country":"IT",
    "sg:address":"Via Della Liberta' 51 10095 Grugliasco",
    "sg:city":"Grugliasco",
    "sg:orig_category":"Fruits, Dried",
    "sg:phone":"+39 011 780 4336",
    "sg:postcode":"10095",
    "sg:province":"Torino",
    "sg:website":"www.exica.it",
    "wof:name":"Exica Italia S.r.l.",
    "wof:placetype":"venue"
},
  "geometry": {"coordinates":[7.5890302658,45.0441169739],"type":"Point"}
}