{
  "type": "Feature",
  "properties": {
    "iso:country":"IT",
    "sg:address":"71/r., Via Ayroli 16143 Genova",
    "sg:city":"Genova",
    "sg:classifiers":[
        {
            "category":"Shopping",
            "subcategory":"Computers & Home Electronics",
            "type":"Retail Goods"
        }
    ],
    "sg:phone":"+39 39010877962",
    "sg:postcode":"16143",
    "sg:province":"Genova",
    "sg:tags":[
        "electronic",
        "electrical",
        "equipment"
    ],
    "wof:name":"De Barbieri (s.p.a.)",
    "wof:placetype":"venue"
},
  "geometry": {"coordinates":[8.933989,44.407063],"type":"Point"}
}