{
  "type": "Feature",
  "properties": {
    "iso:country":"IT",
    "sg:address":"Via Fontanive 40 33080 Zoppola",
    "sg:city":"Zoppola",
    "sg:classifiers":[
        {
            "category":"Communications",
            "subcategory":"Film & Video Production",
            "type":"Services"
        }
    ],
    "sg:phone":"+39 0434 97147",
    "sg:postcode":"33080",
    "sg:province":"Pordenone",
    "sg:tags":[
        "wooden",
        "frame"
    ],
    "wof:name":"Falegnameria Pellegrini Srl",
    "wof:placetype":"venue"
},
  "geometry": {"coordinates":[12.809561,45.97628],"type":"Point"}
}