{
  "type": "Feature",
  "properties": {
    "addr:full":"57023 Cecina Cecina Livorno 57023",
    "addr:postcode":"57023;57023",
    "iso:country":"IT",
    "sg:address":"57023 Cecina",
    "sg:city":"Cecina",
    "sg:orig_category":"Cine-foto-ottica. Shopping",
    "sg:phone":"+39 0586 620375",
    "sg:postcode":"57023",
    "sg:province":"Livorno",
    "wof:name":"Liberati Alessandro",
    "wof:placetype":"venue"
},
  "geometry": {"coordinates":[10.32608,43.559517],"type":"Point"}
}