{
  "type": "Feature",
  "properties": {
    "iso:country":"IT",
    "sg:address":"73024 Maglie",
    "sg:city":"Maglie",
    "sg:classifiers":[
        {
            "category":"Professional",
            "type":"Services"
        }
    ],
    "sg:phone":"+39 0836 460221",
    "sg:postcode":"73024",
    "sg:province":"Lecce",
    "sg:tags":[
        "auxiliary",
        "entertainment",
        "premises",
        "related",
        "catering",
        "public",
        "restaurants"
    ],
    "sg:website":"http://www.cioccolatomaglio.it",
    "wof:name":"Vincenzo Maglio Srl",
    "wof:placetype":"venue"
},
  "geometry": {"coordinates":[18.29707,40.120602],"type":"Point"}
}