{
  "type": "Feature",
  "properties": {
    "iso:country":"IT",
    "sg:address":"22, Via S. Martino 25020 San Paolo",
    "sg:city":"San Paolo",
    "sg:classifiers":[
        {
            "category":"Shopping",
            "subcategory":"Stationery & Office Supplies",
            "type":"Retail Goods"
        }
    ],
    "sg:phone":"+39 030 997 0217",
    "sg:postcode":"25020",
    "sg:province":"Brescia",
    "sg:tags":[
        "professional"
    ],
    "wof:name":"Zeta E P. Di Zacchi G. E Pelucchi F. (s.n.c.)",
    "wof:placetype":"venue"
},
  "geometry": {"coordinates":[9.6142473221,45.6404151917],"type":"Point"}
}