{
  "type": "Feature",
  "properties": {
    "addr:full":"11/a, Piazza Stazione S. Lorenzo 90146 Palermo Palermo Palermo 90146",
    "addr:housenumber":"11 / a",
    "addr:postcode":"90146;90146",
    "addr:street":"Piazza Stazione S. Lorenzo",
    "iso:country":"IT",
    "sg:address":"11/a, Piazza Stazione S. Lorenzo 90146 Palermo",
    "sg:city":"Palermo",
    "sg:classifiers":[
        {
            "category":"Wholesale",
            "subcategory":"Drugs",
            "type":"Manufacturing & Wholesale Goods"
        }
    ],
    "sg:phone":"+39 091 671 7772",
    "sg:postcode":"90146",
    "sg:province":"Palermo",
    "sg:tags":[
        "chemical",
        "pharmaceutical"
    ],
    "wof:name":"Sicilgas S.r.l.",
    "wof:placetype":"venue"
},
  "geometry": {"coordinates":[12.941817,37.914299],"type":"Point"}
}