{
  "type": "Feature",
  "properties": {
    "addr:full":"52100 Arezzo Arezzo Arezzo 52100",
    "addr:postcode":"52100;52100",
    "iso:country":"IT",
    "sg:address":"52100 Arezzo",
    "sg:city":"Arezzo",
    "sg:orig_category":"Prodotti Chimici Di Base",
    "sg:phone":"+39 0575 382381",
    "sg:postcode":"52100",
    "sg:province":"Arezzo",
    "wof:name":"Acquasystem Srl",
    "wof:placetype":"venue"
},
  "geometry": {"coordinates":[11.8573694229,43.4770355225],"type":"Point"}
}