{
  "type": "Feature",
  "properties": {
    "iso:country":"IT",
    "sg:address":"16014 Campomorone",
    "sg:city":"Campomorone",
    "sg:orig_category":"Non-classified Establishments",
    "sg:phone":"+39 010 782862",
    "sg:postcode":"16014",
    "sg:province":"Genova",
    "sg:website":"http://www.chateaudax-liguria.com",
    "wof:name":"Nuova Parodi Arredamenti Srl",
    "wof:placetype":"venue"
},
  "geometry": {"coordinates":[8.87419,44.518345],"type":"Point"}
}