{
  "type": "Feature",
  "properties": {
    "iso:country":"IT",
    "sg:address":"Viii Sda Macchiareddu 09010 Uta",
    "sg:city":"Uta",
    "sg:classifiers":[
        {
            "category":"Wholesale",
            "subcategory":"Motor Vehicles",
            "type":"Manufacturing & Wholesale Goods"
        }
    ],
    "sg:phone":"+39 070 247171",
    "sg:postcode":"09010",
    "sg:province":"Cagliari",
    "sg:tags":[
        "tube",
        "inner",
        "tyre"
    ],
    "sg:website":"www.irp.it",
    "wof:name":"Irp Industria Ricostruzione Pneumatici Spa",
    "wof:placetype":"venue"
},
  "geometry": {"coordinates":[8.952751,39.290066],"type":"Point"}
}