{
  "type": "Feature",
  "properties": {
    "iso:country":"IT",
    "sg:address":"57, Via Nemorense 00199 Roma",
    "sg:city":"Roma",
    "sg:classifiers":[
        {
            "category":"Food & Beverages",
            "subcategory":"Groceries & Convenience Stores",
            "type":"Retail Goods"
        }
    ],
    "sg:phone":"+39 06 8620 6616",
    "sg:postcode":"00199",
    "sg:province":"Roma",
    "sg:tags":[
        "drink"
    ],
    "wof:name":"C.v.a. Centro Vini Arcioni (s.r.l.)",
    "wof:placetype":"venue"
},
  "geometry": {"coordinates":[12.510381,41.926865],"type":"Point"}
}