{
  "type": "Feature",
  "properties": {
    "addr:full":"34122 Trieste Trieste Trieste 34122",
    "addr:postcode":"34122;34122",
    "iso:country":"IT",
    "sg:address":"34122 Trieste",
    "sg:city":"Trieste",
    "sg:orig_category":"Casseforti E Armadi Blindati",
    "sg:phone":"+39 040 630884",
    "sg:postcode":"34122",
    "sg:province":"Trieste",
    "wof:name":"Sapienza & Ponte Snc Di P. Carboncich & F. Valenta",
    "wof:placetype":"venue"
},
  "geometry": {"coordinates":[13.775008,45.651356],"type":"Point"}
}