{
  "type": "Feature",
  "properties": {
    "addr:full":"72, Via Roma 20020 Lazzate Lazzate Milano 20020",
    "addr:postcode":"20020;20020",
    "addr:street":"Via Roma",
    "iso:country":"IT",
    "sg:address":"72, Via Roma 20020 Lazzate",
    "sg:city":"Lazzate",
    "sg:classifiers":[
        {
            "category":"Professional",
            "subcategory":"Engineering",
            "type":"Services"
        }
    ],
    "sg:phone":"+39 02 9632 0152",
    "sg:postcode":"20020",
    "sg:province":"Milano",
    "sg:tags":[
        "machine",
        "-",
        "mechanical"
    ],
    "wof:name":"Monti Impianti (s.r.l.)",
    "wof:placetype":"venue"
},
  "geometry": {"coordinates":[9.082751,45.668259],"type":"Point"}
}