{
  "type": "Feature",
  "properties": {
    "iso:country":"IT",
    "sg:address":"66, Via Bolladore 23035 Sondalo",
    "sg:city":"Sondalo",
    "sg:classifiers":[
        {
            "category":"Shopping",
            "type":"Retail Goods"
        }
    ],
    "sg:phone":"+39 0342 801676",
    "sg:postcode":"23035",
    "sg:province":"Sondrio",
    "sg:tags":[
        "finished",
        "-",
        "metallic"
    ],
    "wof:name":"O.m.c. S.r.l.",
    "wof:placetype":"venue"
},
  "geometry": {"coordinates":[10.3275346756,46.32604599],"type":"Point"}
}