{
  "type": "Feature",
  "properties": {
    "addr:full":"Via Larga 15/8l 40138 Bologna Bologna Bologna 40138",
    "addr:housenumber":"15 / 8l",
    "addr:postcode":"40138;40138",
    "addr:street":"Via Larga",
    "iso:country":"IT",
    "sg:address":"Via Larga 15/8l 40138 Bologna",
    "sg:city":"Bologna",
    "sg:classifiers":[
        {
            "category":"Utilities",
            "subcategory":"Fuel Oil & Lpg",
            "type":"Services"
        }
    ],
    "sg:phone":"+39 051 534834",
    "sg:postcode":"40138",
    "sg:province":"Bologna",
    "sg:tags":[
        "fluid",
        "mechanic"
    ],
    "sg:website":"www.vivoil.com",
    "wof:name":"Vivoil Oleodinamica Vivolo Srl",
    "wof:placetype":"venue"
},
  "geometry": {"coordinates":[11.3464813232,44.4942207336],"type":"Point"}
}