{
  "type": "Feature",
  "properties": {
    "iso:country":"IT",
    "sg:address":"Via Fiori Chiari 32 20121 Milano",
    "sg:city":"Milano",
    "sg:classifiers":[
        {
            "category":"Professional",
            "subcategory":"Management & Consulting",
            "type":"Services"
        }
    ],
    "sg:phone":"+39 02 721341",
    "sg:postcode":"20121",
    "sg:province":"Milano",
    "sg:tags":[
        "consultancy"
    ],
    "sg:website":"www.gianfrancoferre.com",
    "wof:name":"Gianfranco Ferre' Spa",
    "wof:placetype":"venue"
},
  "geometry": {"coordinates":[9.184542,45.471786],"type":"Point"}
}