{
  "type": "Feature",
  "properties": {
    "addr:full":"Via Castello 57; Rodengo Saiano; 25050 Brescia 25050",
    "addr:housenumber":"57",
    "addr:postcode":"25050;25050",
    "addr:street":"Via Castello",
    "iso:country":"IT",
    "sg:address":"Via Castello 57; Rodengo Saiano; 25050",
    "sg:classifiers":[
        {
            "category":"Banks & Credit Unions",
            "subcategory":"Bank",
            "type":"Services"
        }
    ],
    "sg:phone":"+39 030 611361",
    "sg:postcode":"25050",
    "sg:province":"Brescia",
    "wof:name":"Credito Bergamasco Spa",
    "wof:placetype":"venue"
},
  "geometry": {"coordinates":[10.10371,45.597084],"type":"Point"}
}