{
  "type": "Feature",
  "properties": {
    "iso:country":"IT",
    "sg:address":"06073 Corciano",
    "sg:city":"Corciano",
    "sg:orig_category":"Non-classified Establishments",
    "sg:phone":"+39 075 515 9076",
    "sg:postcode":"06073",
    "sg:province":"Perugia",
    "wof:name":"Casa Del Bambu Sas Di Pizzingrilli Renato",
    "wof:placetype":"venue"
},
  "geometry": {"coordinates":[12.31638,43.074734],"type":"Point"}
}