{
  "type": "Feature",
  "properties": {
    "iso:country":"IT",
    "sg:address":"70033 Corato",
    "sg:city":"Corato",
    "sg:orig_category":"Articoli Da Regalo. Tempo Libero - Articoli E Forniture. Regalistica Aziendale",
    "sg:phone":"+39 080 898 3652",
    "sg:postcode":"70033",
    "sg:province":"Bari",
    "wof:name":"Mazzilli Cataldo",
    "wof:placetype":"venue"
},
  "geometry": {"coordinates":[16.870493,41.072529],"type":"Point"}
}