{
  "type": "Feature",
  "properties": {
    "iso:country":"IT",
    "sg:address":"Via Benedetto Virgilio 67030 Villetta Barrea",
    "sg:classifiers":[
        {
            "category":"Travel",
            "subcategory":"Travel Agent",
            "type":"Entertainment"
        }
    ],
    "sg:phone":"+39 39086489274",
    "sg:postcode":"67030",
    "sg:province":"L\\\\\\\\\\\\\\\\\\\\\\\\\\\\'Aquila",
    "sg:tags":[
        "business"
    ],
    "wof:name":"Hotel Il Vecchio Pescatore",
    "wof:placetype":"venue"
},
  "geometry": {"coordinates":[13.932008,41.776112],"type":"Point"}
}