{
  "type": "Feature",
  "properties": {
    "iso:country":"IT",
    "sg:address":"00196 Roma",
    "sg:city":"Roma",
    "sg:orig_category":"Centri Di Estetica E Cosmesi E Servizi",
    "sg:phone":"+39 06 322 2868",
    "sg:postcode":"00196",
    "sg:province":"Roma",
    "wof:name":"Black And White",
    "wof:placetype":"venue"
},
  "geometry": {"coordinates":[12.473819,41.912548],"type":"Point"}
}