{
  "type": "Feature",
  "properties": {
    "iso:country":"IT",
    "sg:address":"Via Feltrina 17 31050 Onigo",
    "sg:classifiers":[
        {
            "category":"Banks & Credit Unions",
            "subcategory":"Investment Brokerage",
            "type":"Services"
        }
    ],
    "sg:phone":"+39 0423 648137",
    "sg:postcode":"31050",
    "sg:province":"Treviso",
    "sg:tags":[
        "picture",
        "frame",
        "moulding"
    ],
    "sg:website":"www.ceccatocornici.it",
    "wof:name":"Ceccato Pierino S.n.c.",
    "wof:placetype":"venue"
},
  "geometry": {"coordinates":[12.2420721054,45.6662864685],"type":"Point"}
}