{
  "type": "Feature",
  "properties": {
    "iso:country":"IT",
    "sg:address":"34, Via Plinio 22030 Lipomo",
    "sg:city":"Lipomo",
    "sg:classifiers":[
        {
            "category":"Professional",
            "subcategory":"Engineering",
            "type":"Services"
        }
    ],
    "sg:phone":"+39 39031557011",
    "sg:postcode":"22030",
    "sg:province":"Como",
    "sg:tags":[
        "machine",
        "-",
        "mechanical"
    ],
    "wof:name":"Stamperia Alatex Snc",
    "wof:placetype":"venue"
},
  "geometry": {"coordinates":[9.161473,45.784973],"type":"Point"}
}