{
  "type": "Feature",
  "properties": {
    "iso:country":"IT",
    "sg:address":"22100 Como",
    "sg:city":"Como",
    "sg:orig_category":"Servizi E Lavori Per Abbigliamento E Pelletterie",
    "sg:phone":"+39 031 523473",
    "sg:postcode":"22100",
    "sg:province":"Como",
    "wof:name":"Crivelli Marco",
    "wof:placetype":"venue"
},
  "geometry": {"coordinates":[9.062906,45.792866],"type":"Point"}
}