{
  "type": "Feature",
  "properties": {
    "iso:country":"IT",
    "sg:address":"81020 San Marco Evangelista",
    "sg:city":"San Marco Evangelista",
    "sg:orig_category":"Forniture Per Agricoltura E Zootecnia. Animali Domestici",
    "sg:phone":"+39 0823 451445",
    "sg:postcode":"81020",
    "sg:province":"Caserta",
    "wof:name":"Ferraiuolo Antonio - Dolce & Salato",
    "wof:placetype":"venue"
},
  "geometry": {"coordinates":[14.3398866653,41.0360221863],"type":"Point"}
}