{
  "type": "Feature",
  "properties": {
    "addr:full":"162, Viale Aguggiari 21100 Varese Varese Varese 21100",
    "addr:postcode":"21100;21100",
    "addr:street":"Viale Aguggiari",
    "iso:country":"IT",
    "sg:address":"162, Viale Aguggiari 21100 Varese",
    "sg:city":"Varese",
    "sg:classifiers":[
        {
            "category":"Wholesale",
            "subcategory":"Drugs",
            "type":"Manufacturing & Wholesale Goods"
        }
    ],
    "sg:phone":"+39 0332 223286",
    "sg:postcode":"21100",
    "sg:province":"Varese",
    "sg:tags":[
        "chemical",
        "pharmaceutical"
    ],
    "wof:name":"Termoraggi S.p.a.",
    "wof:placetype":"venue"
},
  "geometry": {"coordinates":[8.816957,45.837639],"type":"Point"}
}