{
  "type": "Feature",
  "properties": {
    "iso:country":"IT",
    "sg:address":"Via Mazzini 1/a; Spilimbergo; 33097",
    "sg:city":"Spilimbergo",
    "sg:classifiers":[
        {
            "category":"Banks & Credit Unions",
            "subcategory":"Bank",
            "type":"Services"
        }
    ],
    "sg:phone":"+39 0427 50490",
    "sg:postcode":"33097",
    "sg:province":"Pordenone",
    "wof:name":"Banco Ambrosiano Veneto Spa",
    "wof:placetype":"venue"
},
  "geometry": {"coordinates":[12.899923,46.109028],"type":"Point"}
}