{
  "type": "Feature",
  "properties": {
    "iso:country":"IT",
    "sg:address":"00153 Roma",
    "sg:city":"Roma",
    "sg:orig_category":"Articoli Per Imballaggio E Confezionamento",
    "sg:phone":"+39 06 6500 2920",
    "sg:postcode":"00153",
    "sg:province":"Roma",
    "wof:name":"Imball Center Srl",
    "wof:placetype":"venue"
},
  "geometry": {"coordinates":[12.45293,41.862167],"type":"Point"}
}