{
  "type": "Feature",
  "properties": {
    "iso:country":"IT",
    "sg:address":"43012 Fontanellato",
    "sg:city":"Fontanellato",
    "sg:orig_category":"Lavorazioni Metalli, Stampaggio E Saldatura",
    "sg:phone":"+39 0521 821323",
    "sg:postcode":"43012",
    "sg:province":"Parma",
    "wof:name":"Intermarket Snc Di Masetti, Parma E Armani",
    "wof:placetype":"venue"
},
  "geometry": {"coordinates":[10.146071,44.882523],"type":"Point"}
}