{
  "type": "Feature",
  "properties": {
    "iso:country":"IT",
    "sg:address":"Via Ferraris Galileo 31 20010 Cusago",
    "sg:classifiers":[
        {
            "category":"Shopping",
            "subcategory":"Pharmacy",
            "type":"Retail Goods"
        }
    ],
    "sg:phone":"+39 02 9039 0038",
    "sg:postcode":"20010",
    "sg:province":"Milano",
    "sg:tags":[
        "preparation",
        "pharmaceutical"
    ],
    "sg:website":"www.sanicare.it",
    "wof:name":"Sanico Srl",
    "wof:placetype":"venue"
},
  "geometry": {"coordinates":[9.0509471893,45.4372520447],"type":"Point"}
}