{
  "type": "Feature",
  "properties": {
    "iso:country":"IT",
    "sg:address":"03022 Boville Ernica",
    "sg:city":"Boville Ernica",
    "sg:classifiers":[
        {
            "category":"Health Services",
            "subcategory":"Health Practitioner",
            "type":"Services"
        }
    ],
    "sg:phone":"+39 0775 356760",
    "sg:postcode":"03022",
    "sg:province":"Frosinone",
    "sg:tags":[
        "medici"
    ],
    "wof:name":"Veronesi Massimo",
    "wof:placetype":"venue"
},
  "geometry": {"coordinates":[13.4565858841,41.6241607666],"type":"Point"}
}