{
  "type": "Feature",
  "properties": {
    "iso:country":"IT",
    "sg:address":"20132 Milano",
    "sg:city":"Milano",
    "sg:orig_category":"Servizi Per Aziende, Manifestazioni E Supporto Agli Scambi Commerciali",
    "sg:phone":"+39 02 256 5410",
    "sg:postcode":"20132",
    "sg:province":"Milano",
    "wof:name":"Nuova Arte Vetrina S.n.c. Di Mercadante Peter E Di Rocco Andrea",
    "wof:placetype":"venue"
},
  "geometry": {"coordinates":[9.246399,45.50668],"type":"Point"}
}