{
  "type": "Feature",
  "properties": {
    "addr:full":"09040 San Nicolo'gerrei Cagliari 09040",
    "addr:postcode":"09040;09040",
    "addr:street":"Nicolo'Gerrei",
    "iso:country":"IT",
    "sg:address":"09040 San Nicolo'gerrei",
    "sg:orig_category":"Pubblica Amministrazione",
    "sg:phone":"+39 070 950056",
    "sg:postcode":"09040",
    "sg:province":"Cagliari",
    "wof:name":"Uffici Giudiziari",
    "wof:placetype":"venue"
},
  "geometry": {"coordinates":[9.3081293106,39.4986114502],"type":"Point"}
}