{
  "type": "Feature",
  "properties": {
    "iso:country":"IT",
    "sg:address":"10080 Ozegna",
    "sg:city":"Feletto",
    "sg:orig_category":"Servizi Ausiliari Dei Mezzi Di Trasporto",
    "sg:phone":"+39 0124 29893",
    "sg:postcode":"10080",
    "sg:province":"Torino",
    "wof:name":"Di Pietro Armando",
    "wof:placetype":"venue"
},
  "geometry": {"coordinates":[7.768148,45.368149],"type":"Point"}
}