{
  "type": "Feature",
  "properties": {
    "iso:country":"IT",
    "sg:address":"Via Del Bravo 18 54033 Carrara",
    "sg:city":"Carrara",
    "sg:classifiers":[
        {
            "category":"Home & Garden",
            "subcategory":"Building Materials",
            "type":"Retail Goods"
        }
    ],
    "sg:phone":"+39 0585 857848",
    "sg:postcode":"54033",
    "sg:province":"Massa-Carrara",
    "sg:tags":[
        "slab",
        "marble"
    ],
    "sg:website":"www.mirkomenconimarmi.it",
    "wof:name":"Mirko Menconi Marmi Srl",
    "wof:placetype":"venue"
},
  "geometry": {"coordinates":[10.068971,44.051468],"type":"Point"}
}