{
  "type": "Feature",
  "properties": {
    "iso:country":"IT",
    "sg:address":"39040 Aldino",
    "sg:city":"Aldino",
    "sg:orig_category":"Valvole E Apparecchiature Di Misura. Ricambi E Componenti Dei Mezzi Di Trasporto",
    "sg:phone":"+39 0471 886019",
    "sg:postcode":"39040",
    "sg:province":"Bolzano/Bozen",
    "wof:name":"Stuerz Stefan",
    "wof:placetype":"venue"
},
  "geometry": {"coordinates":[11.331881,46.504513],"type":"Point"}
}