{
  "type": "Feature",
  "properties": {
    "iso:country":"IT",
    "sg:address":"32, Via Ca' Silvestre 36024 Nanto",
    "sg:city":"Nanto",
    "sg:classifiers":[
        {
            "category":"Manufacturing",
            "subcategory":"Rubber & Plastics",
            "type":"Manufacturing & Wholesale Goods"
        }
    ],
    "sg:phone":"+39 0444 730140",
    "sg:postcode":"36024",
    "sg:province":"Vicenza",
    "wof:name":"Sitland S.p.a.",
    "wof:placetype":"venue"
},
  "geometry": {"coordinates":[11.6001815796,45.4253463745],"type":"Point"}
}