{
  "type": "Feature",
  "properties": {
    "iso:country":"IT",
    "sg:address":"7, Corso Promessi Sposi 23900 Lecco",
    "sg:city":"Lecco",
    "sg:classifiers":[
        {
            "category":"Home & Garden",
            "subcategory":"Home Furnishings",
            "type":"Retail Goods"
        }
    ],
    "sg:phone":"+39 0341 285595",
    "sg:postcode":"23900",
    "sg:province":"Lecco",
    "sg:tags":[
        "household"
    ],
    "wof:name":"Acciaitubi Spa",
    "wof:placetype":"venue"
},
  "geometry": {"coordinates":[9.403128,45.854862],"type":"Point"}
}