{
  "type": "Feature",
  "properties": {
    "iso:country":"IT",
    "sg:address":"20149 Milano",
    "sg:city":"Milano",
    "sg:orig_category":"Bronzine",
    "sg:phone":"+39 02 3921 7451",
    "sg:postcode":"20149",
    "sg:province":"Milano",
    "wof:name":"C.p.s. Di Cesare & Luigi Guffanti Snc",
    "wof:placetype":"venue"
},
  "geometry": {"coordinates":[9.147249,45.491131],"type":"Point"}
}