{
  "type": "Feature",
  "properties": {
    "addr:full":"20098 S. Giuliano Milanese Milano 20098",
    "addr:housenumber":"20098",
    "addr:postcode":"20098",
    "addr:street":"S. Giuliano Milanese",
    "iso:country":"IT",
    "sg:address":"20098 S. Giuliano Milanese",
    "sg:orig_category":"Automazione E Robotica - Apparecchiature E Componenti",
    "sg:phone":"+39 02 9828 1013",
    "sg:postcode":"20098",
    "sg:province":"Milano",
    "sg:website":"http://www.tumac.it",
    "wof:name":"Tumac Spa",
    "wof:placetype":"venue"
},
  "geometry": {"coordinates":[9.264246,45.401676],"type":"Point"}
}