{
  "type": "Feature",
  "properties": {
    "iso:country":"IT",
    "sg:address":"Via Roma 40; Montecchia Di Crosara; 37030",
    "sg:city":"Montecchia di Crosara",
    "sg:classifiers":[
        {
            "category":"Banks & Credit Unions",
            "subcategory":"Bank",
            "type":"Services"
        }
    ],
    "sg:phone":"+39 045 745 0460",
    "sg:postcode":"37030",
    "sg:province":"Verona",
    "wof:name":"Cariverona Banca Spa",
    "wof:placetype":"venue"
},
  "geometry": {"coordinates":[11.255637,45.485313],"type":"Point"}
}