{
  "type": "Feature",
  "properties": {
    "addr:full":"54, Via Roma 70058 Spinazzola Spinazzola Bari 70058",
    "addr:postcode":"70058;70058",
    "addr:street":"Via Roma",
    "iso:country":"IT",
    "sg:address":"54, Via Roma 70058 Spinazzola",
    "sg:city":"Spinazzola",
    "sg:classifiers":[
        {
            "category":"Shopping",
            "subcategory":"Clothing, Apparel, & Fashions",
            "type":"Retail Goods"
        }
    ],
    "sg:phone":"+39 0883 683410",
    "sg:postcode":"70058",
    "sg:province":"Bari",
    "sg:tags":[
        "clothes"
    ],
    "wof:name":"Esseci (s.r.l.)",
    "wof:placetype":"venue"
},
  "geometry": {"coordinates":[15.980881,40.930374],"type":"Point"}
}