{
  "type": "Feature",
  "properties": {
    "iso:country":"IT",
    "sg:address":"16154 Genova",
    "sg:city":"Genova",
    "sg:orig_category":"Prodotti E Manufatti In Gomma. Servizi E Lavori Industria Della Gomma. Ricambi E Componenti Dei Mezzi Di Trasporto. Riparazione Dei Mezzi Di Trasporto",
    "sg:phone":"+39 010 650 9216",
    "sg:postcode":"16154",
    "sg:province":"Genova",
    "sg:website":"http://www.sestrigomma.it",
    "wof:name":"Sestri Gomma Sas",
    "wof:placetype":"venue"
},
  "geometry": {"coordinates":[8.8417892456,44.4378852844],"type":"Point"}
}