{
  "type": "Feature",
  "properties": {
    "addr:full":"00136 Roma Roma Roma 00136",
    "addr:postcode":"00136;00136",
    "iso:country":"IT",
    "sg:address":"00136 Roma",
    "sg:city":"Roma",
    "sg:orig_category":"Banche E Servizi Finanziari",
    "sg:phone":"+39 06 3972 2838",
    "sg:postcode":"00136",
    "sg:province":"Roma",
    "wof:name":"Romana Factoring S.r.l.",
    "wof:placetype":"venue"
},
  "geometry": {"coordinates":[12.437251,41.909256],"type":"Point"}
}