{
  "type": "Feature",
  "properties": {
    "addr:full":"36, Viale Piceno 20129 Milano Milano Milano 20129",
    "addr:housenumber":"36",
    "addr:postcode":"20129;20129",
    "addr:street":"Viale Piceno",
    "iso:country":"IT",
    "sg:address":"36, Viale Piceno 20129 Milano",
    "sg:city":"Milano",
    "sg:classifiers":[
        {
            "category":"Shopping",
            "subcategory":"Clothing, Apparel, & Fashions",
            "type":"Retail Goods"
        }
    ],
    "sg:phone":"+39 02 7010 0201",
    "sg:postcode":"20129",
    "sg:province":"Milano",
    "sg:tags":[
        "clothing",
        "accessory"
    ],
    "wof:name":"Eq Design Srl",
    "wof:placetype":"venue"
},
  "geometry": {"coordinates":[9.203226,45.482468],"type":"Point"}
}