{
  "type": "Feature",
  "properties": {
    "iso:country":"IT",
    "sg:address":"128, Via Statale 25011 Calcinato",
    "sg:city":"Calcinato",
    "sg:classifiers":[
        {
            "category":"Manufacturing",
            "subcategory":"Printing",
            "type":"Manufacturing & Wholesale Goods"
        }
    ],
    "sg:phone":"+39 030 998 0388",
    "sg:postcode":"25011",
    "sg:province":"Brescia",
    "sg:tags":[
        "publishing"
    ],
    "wof:name":"C 3 F Di Chittolina Evaristo E C.(s.n.c.)",
    "wof:placetype":"venue"
},
  "geometry": {"coordinates":[10.414765358,45.4750175476],"type":"Point"}
}