{
  "type": "Feature",
  "properties": {
    "addr:full":"13 Via Umberto I, 64034 Castiglione Messer Raimondo Castiglione Messer Raimondo Teramo 64034",
    "addr:postcode":"64034;64034",
    "addr:street":"Via Umberto I;Messer Raimondo",
    "iso:country":"IT",
    "sg:address":"13 Via Umberto I, 64034 Castiglione Messer Raimondo",
    "sg:city":"Castiglione Messer Raimondo",
    "sg:classifiers":[
        {
            "category":"Banks & Credit Unions",
            "subcategory":"Financial Services",
            "type":"Services"
        }
    ],
    "sg:phone":"+39 390 861 9941",
    "sg:postcode":"64034",
    "sg:province":"Teramo",
    "sg:tags":[
        "banking",
        "finance",
        "insurance"
    ],
    "wof:name":"Banca Credcoop Castiglione Mr E Pianella",
    "wof:placetype":"venue"
},
  "geometry": {"coordinates":[13.8778104782,42.5327529907],"type":"Point"}
}