{
  "type": "Feature",
  "properties": {
    "iso:country":"IT",
    "sg:address":"80067 Sorrento",
    "sg:city":"Sorrento",
    "sg:orig_category":"Servizi Per Aziende, Manifestazioni E Supporto Agli Scambi Commerciali",
    "sg:phone":"+39 081 534 1050",
    "sg:postcode":"80067",
    "sg:province":"Napoli",
    "wof:name":"Sorrento Congressi International",
    "wof:placetype":"venue"
},
  "geometry": {"coordinates":[14.307229,40.840538],"type":"Point"}
}