{
  "type": "Feature",
  "properties": {
    "iso:country":"IT",
    "sg:address":"66015 Fara San Martino",
    "sg:city":"Fara San Martino",
    "sg:orig_category":"Paste Alimentari - Produzione E Ingrosso",
    "sg:phone":"+39 0872 984121",
    "sg:postcode":"66015",
    "sg:province":"Chieti",
    "wof:name":"Pastificio Artigiano Cav. Giuseppe Cocco Fara San Martino Snc",
    "wof:placetype":"venue"
},
  "geometry": {"coordinates":[14.1582250595,42.0904998779],"type":"Point"}
}