{
  "type": "Feature",
  "properties": {
    "addr:full":"Piazza Vittorio; Villalba; 93010 Villalba Caltanissetta 93010",
    "addr:postcode":"93010;93010",
    "addr:street":"Piazza Vittorio Villalba",
    "iso:country":"IT",
    "sg:address":"Piazza Vittorio; Villalba; 93010",
    "sg:city":"Villalba",
    "sg:classifiers":[
        {
            "category":"Banks & Credit Unions",
            "subcategory":"Bank",
            "type":"Services"
        }
    ],
    "sg:phone":"+39 0934 911054",
    "sg:postcode":"93010",
    "sg:province":"Caltanissetta",
    "wof:name":"Banco Di Sicilia Spa",
    "wof:placetype":"venue"
},
  "geometry": {"coordinates":[13.843205,37.654598],"type":"Point"}
}