{
  "type": "Feature",
  "properties": {
    "iso:country":"IT",
    "sg:address":"100, Corso Riccardi Domenico 80040 Cercola",
    "sg:city":"Cercola",
    "sg:classifiers":[
        {
            "category":"Professional",
            "subcategory":"Engineering",
            "type":"Services"
        }
    ],
    "sg:phone":"+39 081 555 0775",
    "sg:postcode":"80040",
    "sg:province":"Napoli",
    "sg:tags":[
        "machine",
        "-",
        "mechanical"
    ],
    "wof:name":"I.s.i. S.r.l.",
    "wof:placetype":"venue"
},
  "geometry": {"coordinates":[14.356344,40.858387],"type":"Point"}
}