{
  "type": "Feature",
  "properties": {
    "addr:full":"24033 Calusco D'adda Bergamo 24033",
    "addr:postcode":"24033;24033",
    "iso:country":"IT",
    "sg:address":"24033 Calusco D'adda",
    "sg:orig_category":"Prodotti Vari In Metallo. Articoli Per Imballaggio E Confezionamento",
    "sg:phone":"+39 035 438 0061",
    "sg:postcode":"24033",
    "sg:province":"Bergamo",
    "wof:name":"Cmt Inox Srl",
    "wof:placetype":"venue"
},
  "geometry": {"coordinates":[9.4799585342,45.6902046204],"type":"Point"}
}