{
  "type": "Feature",
  "properties": {
    "iso:country":"IT",
    "sg:address":"Via Antonio Facinotti 2m 50054 Fucecchio",
    "sg:city":"Fucecchio",
    "sg:orig_category":"Soles, Heels",
    "sg:phone":"+39 0571 260677",
    "sg:postcode":"50054",
    "sg:province":"Firenze",
    "wof:name":"Apam International S.p.a",
    "wof:placetype":"venue"
},
  "geometry": {"coordinates":[11.256902,43.768734],"type":"Point"}
}