{
  "type": "Feature",
  "properties": {
    "iso:country":"IT",
    "sg:address":"66100 Chieti, Brecciarola",
    "sg:city":"Brecciarola",
    "sg:classifiers":[
        {
            "category":"Restaurant",
            "type":"Food & Drink"
        }
    ],
    "sg:phone":"+39 0871 684510",
    "sg:postcode":"66100",
    "sg:province":"Chieti",
    "sg:tags":[
        "auxiliary",
        "entertainment",
        "premises",
        "related",
        "catering",
        "similar",
        "public",
        "restaurants"
    ],
    "wof:name":"Ristorante Bar Aceto",
    "wof:placetype":"venue"
},
  "geometry": {"coordinates":[14.116676,42.331669],"type":"Point"}
}