{
  "type": "Feature",
  "properties": {
    "iso:country":"IT",
    "sg:address":"05035 Narni",
    "sg:city":"Narni",
    "sg:orig_category":"Caminetti, Forni Da Giardino E Barbecues",
    "sg:phone":"+39 0744 737906",
    "sg:postcode":"05035",
    "sg:province":"Terni",
    "wof:name":"Edilmarmi Snc",
    "wof:placetype":"venue"
},
  "geometry": {"coordinates":[12.515122,42.532551],"type":"Point"}
}