{
  "type": "Feature",
  "properties": {
    "addr:full":"28100 Novara Novara Novara 28100",
    "addr:postcode":"28100;28100",
    "iso:country":"IT",
    "sg:address":"28100 Novara",
    "sg:city":"Novara",
    "sg:classifiers":[
        {
            "category":"Health Services",
            "subcategory":"Nursing And Care Facility",
            "type":"Services"
        }
    ],
    "sg:phone":"+39 0321 636774",
    "sg:postcode":"28100",
    "sg:province":"Novara",
    "sg:tags":[
        "case",
        "riposo",
        "di"
    ],
    "wof:name":"Fondazione Santa Maria",
    "wof:placetype":"venue"
},
  "geometry": {"coordinates":[8.673697,45.46032],"type":"Point"}
}