{
  "type": "Feature",
  "properties": {
    "iso:country":"IT",
    "sg:address":"1, Piazza Dante Alighieri 56126 Pisa",
    "sg:city":"Pisa",
    "sg:classifiers":[
        {
            "category":"Banks & Credit Unions",
            "subcategory":"Bank",
            "type":"Services"
        }
    ],
    "sg:phone":"+39 39050591111",
    "sg:postcode":"56126",
    "sg:province":"Pisa",
    "sg:tags":[
        "banking",
        "institution"
    ],
    "wof:name":"Cassa Di Risparmio Di Pisa Spa",
    "wof:placetype":"venue"
},
  "geometry": {"coordinates":[10.398124,43.717659],"type":"Point"}
}