{
  "type": "Feature",
  "properties": {
    "iso:country":"IT",
    "sg:address":"20017 Rho",
    "sg:city":"Rho",
    "sg:orig_category":"Apparecchiature Ed Attrezzature Meccaniche",
    "sg:phone":"+39 02 9316 9269",
    "sg:postcode":"20017",
    "sg:province":"Milano",
    "wof:name":"Tubi Italflex (s.r.l.)",
    "wof:placetype":"venue"
},
  "geometry": {"coordinates":[9.045074,45.520435],"type":"Point"}
}