{
  "type": "Feature",
  "properties": {
    "addr:full":"Via Roma 80; Vigolzone; 29020 Vigolzone Piacenza 29020",
    "addr:housenumber":"80",
    "addr:postcode":"29020;29020",
    "addr:street":"Via Roma",
    "iso:country":"IT",
    "sg:address":"Via Roma 80; Vigolzone; 29020",
    "sg:city":"Vigolzone",
    "sg:classifiers":[
        {
            "category":"Banks & Credit Unions",
            "subcategory":"Bank",
            "type":"Services"
        }
    ],
    "sg:phone":"+39 0523 879024",
    "sg:postcode":"29020",
    "sg:province":"Piacenza",
    "wof:name":"Cassa Di Risparmio, Di Parma E Piacenza Spa",
    "wof:placetype":"venue"
},
  "geometry": {"coordinates":[9.668886,44.914082],"type":"Point"}
}