{
  "type": "Feature",
  "properties": {
    "iso:country":"IT",
    "sg:address":"80126 Napoli",
    "sg:city":"Napoli",
    "sg:orig_category":"Carni, Salumi E Pesci",
    "sg:phone":"+39 081 726 5707",
    "sg:postcode":"80126",
    "sg:province":"Napoli",
    "wof:name":"La Golden Fish Sas Di Carrella Giuseppina & C.",
    "wof:placetype":"venue"
},
  "geometry": {"coordinates":[14.175657,40.857288],"type":"Point"}
}