{
  "type": "Feature",
  "properties": {
    "iso:country":"IT",
    "sg:address":"10025 Pino Torinese",
    "sg:city":"Pino Torinese",
    "sg:orig_category":"Apparecchiature Ed Attrezzature Meccaniche",
    "sg:phone":"+39 011 811 9249",
    "sg:postcode":"10025",
    "sg:province":"Torino",
    "wof:name":"Ivaldi Roberto",
    "wof:placetype":"venue"
},
  "geometry": {"coordinates":[7.781507,45.042271],"type":"Point"}
}