{
  "type": "Feature",
  "properties": {
    "addr:full":"Via Abbadia 9 60021 Camerano Camerano Ancona 60021",
    "addr:housenumber":"9",
    "addr:postcode":"60021;60021",
    "addr:street":"Via Abbadia",
    "iso:country":"IT",
    "sg:address":"Via Abbadia 9 60021 Camerano",
    "sg:city":"Camerano",
    "sg:orig_category":"Chemico-technical Articles",
    "sg:phone":"+39 071 730011",
    "sg:postcode":"60021",
    "sg:province":"Ancona",
    "sg:website":"www.turboair.com",
    "wof:name":"Osma Spa",
    "wof:placetype":"venue"
},
  "geometry": {"coordinates":[13.542355,43.514648],"type":"Point"}
}