{
  "type": "Feature",
  "properties": {
    "iso:country":"IT",
    "sg:address":"65, Via Cal Larga 31010 Mareno Di Piave",
    "sg:city":"Mareno di Piave",
    "sg:classifiers":[
        {
            "category":"Professional",
            "subcategory":"Engineering",
            "type":"Services"
        }
    ],
    "sg:phone":"+39 0438 308846",
    "sg:postcode":"31010",
    "sg:province":"Treviso",
    "sg:tags":[
        "machine",
        "-",
        "mechanical"
    ],
    "wof:name":"Ar. Tech. Di A. Lovisotto",
    "wof:placetype":"venue"
},
  "geometry": {"coordinates":[12.342207,45.835316],"type":"Point"}
}