{
  "type": "Feature",
  "properties": {
    "addr:full":"90046 Monreale Monreale Palermo 90046",
    "addr:postcode":"90046;90046",
    "iso:country":"IT",
    "sg:address":"90046 Monreale",
    "sg:city":"Monreale",
    "sg:orig_category":"Dolciumi E Gelati",
    "sg:phone":"+39 091 640 2216",
    "sg:postcode":"90046",
    "sg:province":"Palermo",
    "wof:name":"Apicoltura Michelucci Pietro",
    "wof:placetype":"venue"
},
  "geometry": {"coordinates":[13.296109,38.086151],"type":"Point"}
}