{
  "type": "Feature",
  "properties": {
    "iso:country":"IT",
    "sg:address":"20091 Bresso",
    "sg:city":"Bresso",
    "sg:orig_category":"Materiali E Componenti Elettrotecnici. Elettrotecnica Industriale, Prodotti E Apparecchiature",
    "sg:phone":"+39 02 610 0850",
    "sg:postcode":"20091",
    "sg:province":"Milano",
    "wof:name":"Lombarda Trasformatori Sas Di Bassani G.franco & C",
    "wof:placetype":"venue"
},
  "geometry": {"coordinates":[9.18775,45.541325],"type":"Point"}
}