{
  "type": "Feature",
  "properties": {
    "iso:country":"IT",
    "sg:address":"18, Via Cavallo Giuseppe 10078 Venaria",
    "sg:classifiers":[
        {
            "category":"Shopping",
            "type":"Retail Goods"
        }
    ],
    "sg:phone":"+39 39011495621",
    "sg:postcode":"10078",
    "sg:province":"Torino",
    "sg:tags":[
        "finished",
        "-",
        "metallic"
    ],
    "wof:name":"Pontrandolfo Srl Unipersonale",
    "wof:placetype":"venue"
},
  "geometry": {"coordinates":[7.6309247017,45.1352462769],"type":"Point"}
}