{
  "type": "Feature",
  "properties": {
    "iso:country":"IT",
    "sg:address":"40050 Argelato",
    "sg:city":"Argelato",
    "sg:orig_category":"Attrezzature E Forniture Per Officine Riparazione E Servizi Ausiliari",
    "sg:phone":"+39 051 664 6282",
    "sg:postcode":"40050",
    "sg:province":"Bologna",
    "wof:name":"Scama Spa",
    "wof:placetype":"venue"
},
  "geometry": {"coordinates":[11.367518,44.594555],"type":"Point"}
}