{
  "type": "Feature",
  "properties": {
    "iso:country":"IT",
    "sg:address":"00054 Fiumicino",
    "sg:city":"Fiumicino",
    "sg:orig_category":"Servizi Per Lo Sport E Il Tempo Libero. Alberghi E Strutture Extra Alberghiere",
    "sg:phone":"+39 06 652 2594",
    "sg:postcode":"00054",
    "sg:province":"Roma",
    "wof:name":"Soc. Venere S.r.l.",
    "wof:placetype":"venue"
},
  "geometry": {"coordinates":[12.223427,41.767216],"type":"Point"}
}