{
  "type": "Feature",
  "properties": {
    "iso:country":"IT",
    "sg:address":"40033 Casalecchio Di Reno",
    "sg:city":"Casalecchio di Reno",
    "sg:orig_category":"Scuole E Servizi Scolastici",
    "sg:phone":"+39 051 571681",
    "sg:postcode":"40033",
    "sg:province":"Bologna",
    "wof:name":"Associazione Culturale E Ricreativa La Coccinella Club",
    "wof:placetype":"venue"
},
  "geometry": {"coordinates":[11.26078,44.485825],"type":"Point"}
}