{
  "type": "Feature",
  "properties": {
    "iso:country":"IT",
    "sg:address":"Via Del Molo 1, Pertegada, 33050 Latisana, Ud",
    "sg:city":"Latisana",
    "sg:classifiers":[
        {
            "category":"Banks & Credit Unions",
            "subcategory":"Bank",
            "type":"Services"
        }
    ],
    "sg:postcode":"33050",
    "sg:province":"Udine",
    "wof:name":"Banca Di Credito Cooperativo Sud Friuli-latisana Scrl",
    "wof:placetype":"venue"
},
  "geometry": {"coordinates":[13.230724,46.064941],"type":"Point"}
}