{
  "type": "Feature",
  "properties": {
    "addr:full":"24125 Bergamo Bergamo Bergamo 24125",
    "addr:postcode":"24125;24125",
    "iso:country":"IT",
    "sg:address":"24125 Bergamo",
    "sg:city":"Bergamo",
    "sg:orig_category":"Climatizzazione E Condizionamento, Apparecchiature E Servizi. Accessori Dei Mezzi Di Trasporto",
    "sg:phone":"+39 035 313230",
    "sg:postcode":"24125",
    "sg:province":"Bergamo",
    "wof:name":"Elettrauto Fratelli Vanotti Ivan & Gianluca Snc",
    "wof:placetype":"venue"
},
  "geometry": {"coordinates":[9.690181,45.690006],"type":"Point"}
}