{
  "type": "Feature",
  "properties": {
    "iso:country":"IT",
    "sg:address":"Via Faiteria 13 15048 Valenza",
    "sg:city":"Valenza",
    "sg:orig_category":"Ladies' Shoes",
    "sg:phone":"+39 0131 947720",
    "sg:postcode":"15048",
    "sg:province":"Alessandria",
    "wof:name":"D'angelo Di Angelo Accatino Srl",
    "wof:placetype":"venue"
},
  "geometry": {"coordinates":[8.640973,45.017189],"type":"Point"}
}