{
  "type": "Feature",
  "properties": {
    "addr:full":"Via Faiteria 13 15048 Valenza Valenza Alessandria 15048",
    "addr:housenumber":"13",
    "addr:postcode":"15048;15048",
    "addr:street":"Via Faiteria",
    "iso:country":"IT",
    "sg:address":"Via Faiteria 13 15048 Valenza",
    "sg:city":"Valenza",
    "sg:orig_category":"Ladies' Shoes",
    "sg:phone":"+39 0131 947720",
    "sg:postcode":"15048",
    "sg:province":"Alessandria",
    "wof:name":"D'angelo Di Angelo Accatino Srl",
    "wof:placetype":"venue"
},
  "geometry": {"coordinates":[8.640973,45.017189],"type":"Point"}
}