{
  "type": "Feature",
  "properties": {
    "addr:full":"20144 Milano Milano Milano 20144",
    "addr:postcode":"20144;20144",
    "iso:country":"IT",
    "sg:address":"20144 Milano",
    "sg:city":"Milano",
    "sg:orig_category":"Avvocati, Notai E Servizi Legali. Consulenze Tecniche, Amministrative E Perizie",
    "sg:phone":"+39 02 480681",
    "sg:postcode":"20144",
    "sg:province":"Milano",
    "sg:website":"http://www.racheli.it",
    "wof:name":"Racheli & C. Spa",
    "wof:placetype":"venue"
},
  "geometry": {"coordinates":[9.164631,45.465504],"type":"Point"}
}