{
  "type": "Feature",
  "properties": {
    "iso:country":"IT",
    "sg:address":"20019 Settimo Milanese",
    "sg:city":"Settimo Milanese",
    "sg:orig_category":"Cine-foto-ottica",
    "sg:phone":"+39 02 3350 1204",
    "sg:postcode":"20019",
    "sg:province":"Milano",
    "wof:name":"Hostert Fotomata Italia (s.r.l.)",
    "wof:placetype":"venue"
},
  "geometry": {"coordinates":[9.065562,45.487263],"type":"Point"}
}