{
  "type": "Feature",
  "properties": {
    "iso:country":"IT",
    "sg:address":"20020 Cogliate",
    "sg:city":"Cogliate",
    "sg:orig_category":"Valvole E Apparecchiature Di Misura",
    "sg:phone":"+39 02 9646 1285",
    "sg:postcode":"20020",
    "sg:province":"Milano",
    "wof:name":"Marini Luigi",
    "wof:placetype":"venue"
},
  "geometry": {"coordinates":[9.225666,45.477123],"type":"Point"}
}