{
  "type": "Feature",
  "properties": {
    "addr:full":"20, Via Maestra Grande-dodici Morelli 44042 Cento Cento Ferrara 44042",
    "addr:postcode":"44042;44042",
    "addr:street":"Via Maestra Grande-Dodici Morelli",
    "iso:country":"IT",
    "sg:address":"20, Via Maestra Grande-dodici Morelli 44042 Cento",
    "sg:city":"Cento",
    "sg:classifiers":[
        {
            "category":"Manufacturing",
            "subcategory":"Food",
            "type":"Manufacturing & Wholesale Goods"
        }
    ],
    "sg:phone":"+39 051 684 2166",
    "sg:postcode":"44042",
    "sg:province":"Ferrara",
    "sg:tags":[
        "equipment",
        "processing",
        "-",
        "machinery"
    ],
    "wof:name":"Axor (s.r.l.)",
    "wof:placetype":"venue"
},
  "geometry": {"coordinates":[11.295753479,44.7900314331],"type":"Point"}
}