{
  "type": "Feature",
  "properties": {
    "iso:country":"IT",
    "sg:address":"73050 Secl\u00ec",
    "sg:orig_category":"Metalli E Leghe",
    "sg:phone":"+39 0836 554225",
    "sg:postcode":"73050",
    "sg:province":"Lecce",
    "wof:name":"Escelsior Giovanni",
    "wof:placetype":"venue"
},
  "geometry": {"coordinates":[18.1018295288,40.1308631897],"type":"Point"}
}