{
  "type": "Feature",
  "properties": {
    "addr:full":"25, Via Lavoratori 20092 Cinisello Balsamo Cinisello Balsamo Milano 20092",
    "addr:postcode":"20092;20092",
    "addr:street":"Via Lavoratori",
    "iso:country":"IT",
    "sg:address":"25, Via Lavoratori 20092 Cinisello Balsamo",
    "sg:city":"Cinisello Balsamo",
    "sg:classifiers":[
        {
            "category":"Professional",
            "subcategory":"Engineering",
            "type":"Services"
        }
    ],
    "sg:phone":"+39 39026608171",
    "sg:postcode":"20092",
    "sg:province":"Milano",
    "sg:tags":[
        "machine",
        "-",
        "mechanical"
    ],
    "wof:name":"Branson Ultrasuoni S.p.a.",
    "wof:placetype":"venue"
},
  "geometry": {"coordinates":[9.2303,45.557041],"type":"Point"}
}