{
  "type": "Feature",
  "properties": {
    "iso:country":"IT",
    "sg:address":"Via Chizzalunga 8 36066 Sandrigo",
    "sg:city":"Sandrigo",
    "sg:classifiers":[
        {
            "category":"Building & Trades",
            "subcategory":"Construction",
            "type":"Services"
        }
    ],
    "sg:phone":"+39 0444 666100",
    "sg:postcode":"36066",
    "sg:province":"Vicenza",
    "sg:tags":[
        "control",
        "electric",
        "equipment",
        "hoist",
        "systems",
        "crane",
        "switching",
        "lifting"
    ],
    "wof:name":"Omis Service S.r.l.",
    "wof:placetype":"venue"
},
  "geometry": {"coordinates":[11.580306,45.660103],"type":"Point"}
}