{
  "type": "Feature",
  "properties": {
    "addr:full":"41/43, Via I Maggio 75100 Matera Matera Matera 75100",
    "addr:housenumber":"41 / 43",
    "addr:postcode":"75100;75100",
    "addr:street":"Via I Maggio",
    "iso:country":"IT",
    "sg:address":"41/43, Via I Maggio 75100 Matera",
    "sg:city":"Matera",
    "sg:classifiers":[
        {
            "category":"Shopping",
            "subcategory":"Computers & Home Electronics",
            "type":"Retail Goods"
        }
    ],
    "sg:phone":"+39 0835 388174",
    "sg:postcode":"75100",
    "sg:province":"Matera",
    "sg:tags":[
        "electronic",
        "electrical",
        "equipment"
    ],
    "wof:name":"Elettromeccanica Giovanni Azzone Snc Di Domenico & Antonio Azzone",
    "wof:placetype":"venue"
},
  "geometry": {"coordinates":[16.606087,40.668652],"type":"Point"}
}