{
  "type": "Feature",
  "properties": {
    "iso:country":"IT",
    "sg:address":"24059 Urgnano",
    "sg:city":"Urgnano",
    "sg:orig_category":"Apparecchiature E Sistemi Per Imballaggio E Confezionamento",
    "sg:phone":"+39 035 893135",
    "sg:postcode":"24059",
    "sg:province":"Bergamo",
    "sg:website":"http://www.tgm.it",
    "wof:name":"Tgm - Tecnomachines Srl",
    "wof:placetype":"venue"
},
  "geometry": {"coordinates":[9.704121,45.600716],"type":"Point"}
}