{
  "type": "Feature",
  "properties": {
    "addr:full":"00192 Roma Roma Roma 00192",
    "addr:postcode":"00192;00192",
    "iso:country":"IT",
    "sg:address":"00192 Roma",
    "sg:city":"Roma",
    "sg:orig_category":"Petroli, Gas E Combustibili",
    "sg:phone":"+39 06 3972 0709",
    "sg:postcode":"00192",
    "sg:province":"Roma",
    "wof:name":"Giovannetti Ilario",
    "wof:placetype":"venue"
},
  "geometry": {"coordinates":[12.4518690109,41.9078521729],"type":"Point"}
}