{
  "type": "Feature",
  "properties": {
    "addr:full":"1, Via Pasubio 36020 Albettone Albettone Vicenza 36020",
    "addr:postcode":"36020;36020",
    "addr:street":"Via Pasubio",
    "iso:country":"IT",
    "sg:address":"1, Via Pasubio 36020 Albettone",
    "sg:city":"Albettone",
    "sg:classifiers":[
        {
            "category":"Home & Garden",
            "subcategory":"Home Furnishings",
            "type":"Retail Goods"
        }
    ],
    "sg:phone":"+39 0444 790005",
    "sg:postcode":"36020",
    "sg:province":"Vicenza",
    "sg:tags":[
        "household"
    ],
    "wof:name":"Perdoncin Di Perdoncin Lorenzo E Aldo (s.n.c.)",
    "wof:placetype":"venue"
},
  "geometry": {"coordinates":[11.580505,45.358551],"type":"Point"}
}