{
  "type": "Feature",
  "properties": {
    "addr:full":"165, Via Quarantadue Martiri 28924 Verbania Verbania Verbano-Cusio-Ossola 28924",
    "addr:housenumber":"165",
    "addr:postcode":"28924;28924",
    "addr:street":"Via Quarantadue Martiri",
    "iso:country":"IT",
    "sg:address":"165, Via Quarantadue Martiri 28924 Verbania",
    "sg:city":"Verbania",
    "sg:classifiers":[
        {
            "category":"Communications",
            "subcategory":"Newspaper",
            "type":"Services"
        }
    ],
    "sg:phone":"+39 0323 585311",
    "sg:postcode":"28924",
    "sg:province":"Verbano-Cusio-Ossola",
    "sg:tags":[
        "advertising"
    ],
    "wof:name":"Co-ver Impiantistica Srl",
    "wof:placetype":"venue"
},
  "geometry": {"coordinates":[8.471264,45.942734],"type":"Point"}
}