{
  "type": "Feature",
  "properties": {
    "iso:country":"IT",
    "sg:address":"35012 Camposampiero",
    "sg:city":"Camposampiero",
    "sg:classifiers":[
        {
            "category":"Health Services",
            "subcategory":"Health Practitioner",
            "type":"Services"
        }
    ],
    "sg:phone":"+39 049 930 1675",
    "sg:postcode":"35012",
    "sg:province":"Padova",
    "sg:tags":[
        "medici"
    ],
    "wof:name":"Grigio Maurizio",
    "wof:placetype":"venue"
},
  "geometry": {"coordinates":[11.873277,45.40868],"type":"Point"}
}