{
  "type": "Feature",
  "properties": {
    "iso:country":"IT",
    "sg:address":"Str. Per Felizzano 18 15043 Fubine",
    "sg:city":"Fubine",
    "sg:classifiers":[
        {
            "category":"Manufacturing",
            "subcategory":"Tools & Machinery",
            "type":"Manufacturing & Wholesale Goods"
        }
    ],
    "sg:phone":"+39 0131 792711",
    "sg:postcode":"15043",
    "sg:province":"Alessandria",
    "sg:tags":[
        "machine"
    ],
    "sg:website":"www.mecal.net",
    "wof:name":"Mecal Srl",
    "wof:placetype":"venue"
},
  "geometry": {"coordinates":[8.44128,44.949062],"type":"Point"}
}