{
  "type": "Feature",
  "properties": {
    "iso:country":"IT",
    "sg:address":"12, Via Dell' Industria 35020 Brugine",
    "sg:city":"Brugine",
    "sg:classifiers":[
        {
            "category":"Communications",
            "subcategory":"Television Station",
            "type":"Services"
        }
    ],
    "sg:phone":"+39 049 973 0124",
    "sg:postcode":"35020",
    "sg:province":"Padova",
    "sg:tags":[
        "audio-visual"
    ],
    "wof:name":"Samos (s.r.l.)",
    "wof:placetype":"venue"
},
  "geometry": {"coordinates":[11.876589,45.409569],"type":"Point"}
}