{
  "type": "Feature",
  "properties": {
    "addr:full":"00133 Roma Roma Roma 00133",
    "addr:postcode":"00133;00133",
    "iso:country":"IT",
    "sg:address":"00133 Roma",
    "sg:city":"Roma",
    "sg:orig_category":"Servizi Al Turismo. Trasporto Pubblico E Privato. Acqua, Luce, Gas E Societa' Di Esercizio Pubblico",
    "sg:phone":"+39 06 2043 4335",
    "sg:postcode":"00133",
    "sg:province":"Roma",
    "wof:name":"Torbellamonaca Busdi De Angelis G. & C. Sas",
    "wof:placetype":"venue"
},
  "geometry": {"coordinates":[12.650995,41.871277],"type":"Point"}
}