{
  "type": "Feature",
  "properties": {
    "addr:full":"19, Via Degli Astalli 00186 Roma Roma Roma 00186",
    "addr:postcode":"00186;00186",
    "addr:street":"Via Degli Astalli",
    "iso:country":"IT",
    "sg:address":"19, Via Degli Astalli 00186 Roma",
    "sg:city":"Roma",
    "sg:classifiers":[
        {
            "category":"Shopping",
            "subcategory":"Clothing, Apparel, & Fashions",
            "type":"Retail Goods"
        }
    ],
    "sg:phone":"+39 39066789507",
    "sg:postcode":"00186",
    "sg:province":"Roma",
    "sg:tags":[
        "clothes"
    ],
    "wof:name":"Le Camicie Di S.r.l.",
    "wof:placetype":"venue"
},
  "geometry": {"coordinates":[12.480149,41.896458],"type":"Point"}
}