{
  "type": "Feature",
  "properties": {
    "addr:full":"2, Via Dell' Artigianato 41039 San Possidonio San Possidonio Modena 41039",
    "addr:postcode":"41039;possidonio;41039",
    "addr:street":"Via Dell ' Artigianato",
    "iso:country":"IT",
    "sg:address":"2, Via Dell' Artigianato 41039 San Possidonio",
    "sg:city":"San Possidonio",
    "sg:classifiers":[
        {
            "category":"Sports & Exercise",
            "subcategory":"Playing Field",
            "type":"Entertainment"
        }
    ],
    "sg:phone":"+39 39053530210",
    "sg:postcode":"41039",
    "sg:province":"Modena",
    "sg:tags":[
        "game"
    ],
    "wof:name":"La Bottega Degli Antichi Mestieri S.n.c.",
    "wof:placetype":"venue"
},
  "geometry": {"coordinates":[10.92522,44.647079],"type":"Point"}
}