{
  "type": "Feature",
  "properties": {
    "addr:full":"00010 Roma Roma 00010",
    "addr:postcode":"00010;00010",
    "iso:country":"IT",
    "sg:address":"00010 Roma",
    "sg:orig_category":"Servizi E Lavori Per Ecologia E Smaltimento Rifiuti. Servizi Ausiliari Di Sorveglianza, Manutenzione E Pulizia",
    "sg:phone":"+39 06 502 0182",
    "sg:postcode":"00010",
    "sg:province":"Roma",
    "sg:website":"http://www.paginegialle.it/labruzzesepulizie",
    "wof:name":"Cooperativa L'abruzzese Soc.coop.ar.l.",
    "wof:placetype":"venue"
},
  "geometry": {"coordinates":[12.631426,41.892765],"type":"Point"}
}