{
  "type": "Feature",
  "properties": {
    "iso:country":"IT",
    "sg:address":"47900 Rimini",
    "sg:city":"Rimini",
    "sg:orig_category":"Servizi Culturali E Per Lo Spettacolo. Servizi Per Lo Sport E Il Tempo Libero. Associazioni Ed Organismi Di Interesse Pubblico",
    "sg:phone":"+39 0541 780153",
    "sg:postcode":"47900",
    "sg:province":"Rimini",
    "wof:name":"Circolo Minnesota Fats",
    "wof:placetype":"venue"
},
  "geometry": {"coordinates":[12.562764,44.05896],"type":"Point"}
}