{
  "type": "Feature",
  "properties": {
    "addr:full":"20019 Settimo Milanese Settimo Milanese Milano 20019",
    "addr:postcode":"20019;20019",
    "iso:country":"IT",
    "sg:address":"20019 Settimo Milanese",
    "sg:city":"Settimo Milanese",
    "sg:orig_category":"Prodotti Chimici Secondari. Prodotti Cosmetici E Da Toeletta",
    "sg:phone":"+39 02 3350 1000",
    "sg:postcode":"20019",
    "sg:province":"Milano",
    "wof:name":"Eurosirel S.r.l.",
    "wof:placetype":"venue"
},
  "geometry": {"coordinates":[9.0754966736,45.4753799438],"type":"Point"}
}