{
  "type": "Feature",
  "properties": {
    "addr:full":"66100 Chieti Chieti Chieti 66100",
    "addr:postcode":"66100;66100",
    "iso:country":"IT",
    "sg:address":"66100 Chieti",
    "sg:city":"Chieti",
    "sg:orig_category":"Petroli, Gas E Combustibili. Materiali Edili",
    "sg:phone":"+39 0871 574041",
    "sg:postcode":"66100",
    "sg:province":"Chieti",
    "wof:name":"Icobit Srl",
    "wof:placetype":"venue"
},
  "geometry": {"coordinates":[14.1404342651,42.3751831055],"type":"Point"}
}