{
  "type": "Feature",
  "properties": {
    "iso:country":"IT",
    "sg:address":"64024 Notaresco",
    "sg:city":"Notaresco",
    "sg:orig_category":"Marmitte Per Motori",
    "sg:phone":"+39 085 898353",
    "sg:postcode":"64024",
    "sg:province":"Teramo",
    "wof:name":"C.m.a. Srl",
    "wof:placetype":"venue"
},
  "geometry": {"coordinates":[14.005944,42.65189],"type":"Point"}
}