{
  "type": "Feature",
  "properties": {
    "addr:full":"10080 Feletto Feletto Torino 10080",
    "addr:postcode":"10080;10080",
    "iso:country":"IT",
    "sg:address":"10080 Feletto",
    "sg:city":"Feletto",
    "sg:orig_category":"Vetro: Prodotti E Lavorazioni",
    "sg:phone":"+39 0124 490554",
    "sg:postcode":"10080",
    "sg:province":"Torino",
    "wof:name":"Ferro Angelo",
    "wof:placetype":"venue"
},
  "geometry": {"coordinates":[7.746778,45.298122],"type":"Point"}
}