{
  "type": "Feature",
  "properties": {
    "iso:country":"IT",
    "sg:address":"20052 Monza",
    "sg:city":"Monza",
    "sg:orig_category":"Climatizzazione E Condizionamento, Apparecchiature E Servizi",
    "sg:phone":"+39 039 200 7173",
    "sg:postcode":"20052",
    "sg:province":"Milano",
    "wof:name":"Ma.pi Maurizio Mattera Sas",
    "wof:placetype":"venue"
},
  "geometry": {"coordinates":[9.186015,45.45253],"type":"Point"}
}