{
  "type": "Feature",
  "properties": {
    "iso:country":"IT",
    "sg:address":"21047 Saronno",
    "sg:city":"Saronno",
    "sg:orig_category":"Informatica - Consulenza E Servizi. Servizi Ausiliari Di Analisi, Controllo E Ricerca. Servizi Per Aziende, Manifestazioni E Supporto Agli Scambi Commerciali",
    "sg:phone":"+39 02 9670 2458",
    "sg:postcode":"21047",
    "sg:province":"Varese",
    "sg:website":"http://www.3gsrl.net",
    "wof:name":"3 G Srl",
    "wof:placetype":"venue"
},
  "geometry": {"coordinates":[9.030049,45.626217],"type":"Point"}
}