{
  "type": "Feature",
  "properties": {
    "iso:country":"IT",
    "sg:address":"2, Via Italia 23885 Calco",
    "sg:city":"Calco",
    "sg:classifiers":[
        {
            "category":"Professional",
            "subcategory":"Advertising",
            "type":"Services"
        }
    ],
    "sg:phone":"+39 39039508435",
    "sg:postcode":"23885",
    "sg:province":"Lecco",
    "sg:tags":[
        "communication",
        "medium"
    ],
    "wof:name":"Fotomar Di Alfonso Marchese & C. (s.n.c.)",
    "wof:placetype":"venue"
},
  "geometry": {"coordinates":[9.428791,45.725906],"type":"Point"}
}