{
  "type": "Feature",
  "properties": {
    "addr:full":"10/a, Via Giardini 33076 Pravisdomini Pravisdomini Pordenone 33076",
    "addr:housenumber":"10 / a",
    "addr:postcode":"33076;33076",
    "addr:street":"Via Giardini",
    "iso:country":"IT",
    "sg:address":"10/a, Via Giardini 33076 Pravisdomini",
    "sg:city":"Pravisdomini",
    "sg:classifiers":[
        {
            "category":"Manufacturing",
            "subcategory":"Lumber",
            "type":"Manufacturing & Wholesale Goods"
        }
    ],
    "sg:phone":"+39 0434 644286",
    "sg:postcode":"33076",
    "sg:province":"Pordenone",
    "sg:tags":[
        "wood"
    ],
    "wof:name":"Nuova Emmebi (s.r.l.)",
    "wof:placetype":"venue"
},
  "geometry": {"coordinates":[12.655044,45.96265],"type":"Point"}
}