{
  "type": "Feature",
  "properties": {
    "iso:country":"IT",
    "sg:address":"56038 Ponsacco",
    "sg:city":"Ponsacco",
    "sg:orig_category":"Poltrone E Divani - Vendita Al Dettaglio",
    "sg:phone":"+39 0587 731448",
    "sg:postcode":"56038",
    "sg:province":"Pisa",
    "wof:name":"Cionini Romano",
    "wof:placetype":"venue"
},
  "geometry": {"coordinates":[10.6365480423,43.6141777039],"type":"Point"}
}