{
  "type": "Feature",
  "properties": {
    "iso:country":"IT",
    "sg:address":"63, Viale Delle Alpi 90144 Palermo",
    "sg:city":"Palermo",
    "sg:classifiers":[
        {
            "category":"Professional",
            "subcategory":"Engineering",
            "type":"Services"
        }
    ],
    "sg:phone":"+39 39091201117",
    "sg:postcode":"90144",
    "sg:province":"Palermo",
    "sg:tags":[
        "machine",
        "-",
        "mechanical"
    ],
    "wof:name":"Ediltecno Clima Srl",
    "wof:placetype":"venue"
},
  "geometry": {"coordinates":[13.33578,38.140659],"type":"Point"}
}