{
  "type": "Feature",
  "properties": {
    "iso:country":"IT",
    "sg:address":"35019 Tombolo",
    "sg:city":"Tombolo",
    "sg:orig_category":"Dolciumi E Gelati",
    "sg:phone":"+39 049 947 1036",
    "sg:postcode":"35019",
    "sg:province":"Padova",
    "wof:name":"Rebisco S.p.a.",
    "wof:placetype":"venue"
},
  "geometry": {"coordinates":[11.875237,45.399239],"type":"Point"}
}