{
  "type": "Feature",
  "properties": {
    "iso:country":"IT",
    "sg:address":"168, Via Madonna Pellegrina 20010 Bareggio",
    "sg:city":"Bareggio",
    "sg:classifiers":[
        {
            "category":"Professional",
            "subcategory":"Engineering",
            "type":"Services"
        }
    ],
    "sg:phone":"+39 02 9036 1667",
    "sg:postcode":"20010",
    "sg:province":"Milano",
    "sg:tags":[
        "machine",
        "-",
        "mechanical"
    ],
    "wof:name":"Prinox S.r.l",
    "wof:placetype":"venue"
},
  "geometry": {"coordinates":[9.008738,45.484119],"type":"Point"}
}