{
  "type": "Feature",
  "properties": {
    "addr:full":"Via Ragazzi Del'99 12; Sondrio; 23100 Sondrio Sondrio 23100",
    "addr:housenumber":"del'99 12",
    "addr:postcode":"23100;23100",
    "addr:street":"Via Ragazzi",
    "iso:country":"IT",
    "sg:address":"Via Ragazzi Del'99 12; Sondrio; 23100",
    "sg:city":"Sondrio",
    "sg:classifiers":[
        {
            "category":"Banks & Credit Unions",
            "subcategory":"Bank",
            "type":"Services"
        }
    ],
    "sg:phone":"+39 0342 522508",
    "sg:postcode":"23100",
    "sg:province":"Sondrio",
    "wof:name":"Credito Artigiano Spa",
    "wof:placetype":"venue"
},
  "geometry": {"coordinates":[9.870386,46.170292],"type":"Point"}
}