{
  "type": "Feature",
  "properties": {
    "iso:country":"IT",
    "sg:address":"52040 Civitella",
    "sg:orig_category":"Materiali Edili",
    "sg:phone":"+39 0575 441415",
    "sg:province":"AR",
    "wof:name":"Tecnocal Spa",
    "wof:placetype":"venue"
},
  "geometry": {"coordinates":[11.773611,43.433777],"type":"Point"}
}