{
  "type": "Feature",
  "properties": {
    "iso:country":"IT",
    "sg:address":"110, Localita' Signayes Clou 11100 Aosta",
    "sg:city":"Aosta",
    "sg:classifiers":[
        {
            "category":"Travel",
            "subcategory":"Travel Agent",
            "type":"Entertainment"
        }
    ],
    "sg:phone":"+39 0165 262426",
    "sg:postcode":"11100",
    "sg:province":"Aosta",
    "sg:tags":[
        "business"
    ],
    "wof:name":"Albergo La Roche",
    "wof:placetype":"venue"
},
  "geometry": {"coordinates":[7.315921,45.757248],"type":"Point"}
}