{
  "type": "Feature",
  "properties": {
    "iso:country":"IT",
    "sg:address":"84098 Pontecagnano Faiano",
    "sg:city":"Faiano",
    "sg:orig_category":"Scuole E Servizi Scolastici. Centri Di Estetica E Cosmesi E Servizi. Ricerca, Selezione E Formazione Del Personale",
    "sg:phone":"+39 089 384480",
    "sg:postcode":"84098",
    "sg:province":"Salerno",
    "wof:name":"First Lady",
    "wof:placetype":"venue"
},
  "geometry": {"coordinates":[14.88063,40.640312],"type":"Point"}
}