{
  "type": "Feature",
  "properties": {
    "addr:full":"22079 Villa Guardia Villa Guardia Como 22079",
    "addr:housenumber":"22079;guardia",
    "addr:postcode":"22079",
    "addr:street":"Villa Guardia",
    "iso:country":"IT",
    "sg:address":"22079 Villa Guardia",
    "sg:city":"Villa Guardia",
    "sg:orig_category":"Cravatte, Sciarpe E Foulards",
    "sg:phone":"+39 031 563646",
    "sg:postcode":"22079",
    "sg:province":"Como",
    "wof:name":"Tessitura Attilio Bottinelli Srl",
    "wof:placetype":"venue"
},
  "geometry": {"coordinates":[9.021589,45.772205],"type":"Point"}
}