{
  "type": "Feature",
  "properties": {
    "iso:country":"IT",
    "sg:address":"20122 Milano",
    "sg:city":"Milano",
    "sg:orig_category":"Abbigliamento Esterno, Maglierie E Pelliccerie. Calzature, Pelletterie E Pelli",
    "sg:phone":"+39 02 8646 0439",
    "sg:postcode":"20122",
    "sg:province":"Milano",
    "wof:name":"Brambilla Ambrogio",
    "wof:placetype":"venue"
},
  "geometry": {"coordinates":[9.193,45.462151],"type":"Point"}
}