{
  "type": "Feature",
  "properties": {
    "addr:full":"Via Roma 186; Martinsicuro; 64014 Martinsicuro Teramo 64014",
    "addr:housenumber":"186",
    "addr:postcode":"64014;64014",
    "addr:street":"Via Roma",
    "iso:country":"IT",
    "sg:address":"Via Roma 186; Martinsicuro; 64014",
    "sg:city":"Martinsicuro",
    "sg:classifiers":[
        {
            "category":"Banks & Credit Unions",
            "subcategory":"Bank",
            "type":"Services"
        }
    ],
    "sg:phone":"+39 0861 761688",
    "sg:postcode":"64014",
    "sg:province":"Teramo",
    "wof:name":"Banca Toscana Spa",
    "wof:placetype":"venue"
},
  "geometry": {"coordinates":[13.921185,42.864502],"type":"Point"}
}