{
  "type": "Feature",
  "properties": {
    "iso:country":"IT",
    "sg:address":"04012 Cisterna Di Latina",
    "sg:city":"Cisterna di Latina",
    "sg:orig_category":"Macchine, Impianti Ed Attrezzature Per Agricoltura E Zootecnia",
    "sg:phone":"+39 06 968 1381",
    "sg:postcode":"04012",
    "sg:province":"Latina",
    "wof:name":"Refa Di Chiarucci Fabrizio & C. Sas",
    "wof:placetype":"venue"
},
  "geometry": {"coordinates":[12.828477,41.575401],"type":"Point"}
}