{
  "type": "Feature",
  "properties": {
    "addr:full":"60, Via Fermi 10093 Collegno Collegno Torino 10093",
    "addr:postcode":"10093;10093",
    "addr:street":"Via Fermi",
    "iso:country":"IT",
    "sg:address":"60, Via Fermi 10093 Collegno",
    "sg:city":"Collegno",
    "sg:classifiers":[
        {
            "category":"Manufacturing",
            "subcategory":"Rubber & Plastics",
            "type":"Manufacturing & Wholesale Goods"
        }
    ],
    "sg:phone":"+39 011 411 1342",
    "sg:postcode":"10093",
    "sg:province":"Torino",
    "wof:name":"Vadoplast (s.r.l.)",
    "wof:placetype":"venue"
},
  "geometry": {"coordinates":[7.5925579071,45.0796585083],"type":"Point"}
}