{
  "type": "Feature",
  "properties": {
    "iso:country":"IT",
    "sg:address":"Via Del Bosco 33 56029 Santa Croce Sull'arno",
    "sg:classifiers":[
        {
            "category":"Banks & Credit Unions",
            "subcategory":"Bureau De Change",
            "type":"Services"
        }
    ],
    "sg:phone":"+39 0571 31730",
    "sg:postcode":"56029",
    "sg:province":"Pisa",
    "sg:tags":[
        "punching",
        "series",
        "press"
    ],
    "wof:name":"Flamarstampi Srl",
    "wof:placetype":"venue"
},
  "geometry": {"coordinates":[10.778507,43.713463],"type":"Point"}
}