{
  "type": "Feature",
  "properties": {
    "addr:full":"80020 Frattaminore Frattaminore Napoli 80020",
    "addr:postcode":"80020;80020",
    "iso:country":"IT",
    "sg:address":"80020 Frattaminore",
    "sg:city":"Frattaminore",
    "sg:orig_category":"Forniture Per Agricoltura E Zootecnia. Animali Domestici",
    "sg:phone":"+39 081 831 7327",
    "sg:postcode":"80020",
    "sg:province":"Napoli",
    "wof:name":"Centro Veterinario Barbuto",
    "wof:placetype":"venue"
},
  "geometry": {"coordinates":[14.2483081818,40.8627319336],"type":"Point"}
}