{
  "type": "Feature",
  "properties": {
    "iso:country":"IT",
    "sg:address":"23, Via Delle Industrie 30020 Marcon",
    "sg:city":"Marcon",
    "sg:classifiers":[
        {
            "category":"Manufacturing",
            "subcategory":"Metals",
            "type":"Manufacturing & Wholesale Goods"
        }
    ],
    "sg:phone":"+39 041 456 7644",
    "sg:postcode":"30020",
    "sg:province":"Venezia",
    "sg:tags":[
        "metallurgy",
        "metalworking"
    ],
    "wof:name":"Faces (s.p.a.)",
    "wof:placetype":"venue"
},
  "geometry": {"coordinates":[12.291970253,45.5462188721],"type":"Point"}
}