{
  "type": "Feature",
  "properties": {
    "addr:full":"16121 Genova Genova Genova 16121",
    "addr:postcode":"16121;16121",
    "iso:country":"IT",
    "sg:address":"16121 Genova",
    "sg:city":"Genova",
    "sg:orig_category":"Servizi Ausiliari Per Il Trasporto. Agenzie D'affari E Servizi Commerciali",
    "sg:phone":"+39 010 540869",
    "sg:postcode":"16121",
    "sg:province":"Genova",
    "wof:name":"Revello Massimo",
    "wof:placetype":"venue"
},
  "geometry": {"coordinates":[8.888069,44.967991],"type":"Point"}
}