{
  "type": "Feature",
  "properties": {
    "iso:country":"IT",
    "sg:address":"00148 Roma",
    "sg:city":"Roma",
    "sg:orig_category":"Servizi Ausiliari Di Analisi, Controllo E Ricerca",
    "sg:phone":"+39 06 653 9210",
    "sg:postcode":"00148",
    "sg:province":"Roma",
    "wof:name":"Cnd Service Srl",
    "wof:placetype":"venue"
},
  "geometry": {"coordinates":[12.438383,41.833645],"type":"Point"}
}