{
  "type": "Feature",
  "properties": {
    "addr:full":"16123 Genova Genova Genova 16123",
    "addr:postcode":"16123;16123",
    "iso:country":"IT",
    "sg:address":"16123 Genova",
    "sg:city":"Genova",
    "sg:orig_category":"Lavorazioni Meccaniche E Servizi. Riparazione Dei Mezzi Di Trasporto",
    "sg:phone":"+39 010 251 2618",
    "sg:postcode":"16123",
    "sg:province":"Genova",
    "wof:name":"Tubo Montaggi",
    "wof:placetype":"venue"
},
  "geometry": {"coordinates":[8.931434,44.408623],"type":"Point"}
}