{
  "type": "Feature",
  "properties": {
    "addr:full":"10093 Collegno Collegno Torino 10093",
    "addr:postcode":"10093;10093",
    "iso:country":"IT",
    "sg:address":"10093 Collegno",
    "sg:city":"Collegno",
    "sg:orig_category":"Climatizzazione E Condizionamento, Apparecchiature E Servizi",
    "sg:phone":"+39 011 424 0733",
    "sg:postcode":"10093",
    "sg:province":"Torino",
    "sg:website":"http://www.tecnologieimpiantistiche.it",
    "wof:name":"Tecnologie Impiantistiche Srl",
    "wof:placetype":"venue"
},
  "geometry": {"coordinates":[7.601273,45.097523],"type":"Point"}
}