{
  "type": "Feature",
  "properties": {
    "iso:country":"IT",
    "sg:address":"52, Via Circonvallazione 20040 Cornate D'adda",
    "sg:classifiers":[
        {
            "category":"Real Estate",
            "subcategory":"Architect",
            "type":"Services"
        }
    ],
    "sg:phone":"+39 039 692 6523",
    "sg:postcode":"20040",
    "sg:province":"Milano",
    "sg:tags":[
        "textile",
        "clothing"
    ],
    "wof:name":"Imba Di G. Biffi & C. (s.n.c.)",
    "wof:placetype":"venue"
},
  "geometry": {"coordinates":[9.461792,45.65094],"type":"Point"}
}