{
  "type": "Feature",
  "properties": {
    "addr:full":"17011 Albisola Superiore Albisola Superiore Savona 17011",
    "addr:postcode":"17011;17011",
    "iso:country":"IT",
    "sg:address":"17011 Albisola Superiore",
    "sg:city":"Albisola Superiore",
    "sg:orig_category":"Animali Domestici - Allevamento E Addestramento",
    "sg:phone":"+39 347 275 7319",
    "sg:postcode":"17011",
    "sg:province":"Savona",
    "wof:name":"Addestramento Cani Fabiano G.",
    "wof:placetype":"venue"
},
  "geometry": {"coordinates":[8.502455,44.339622],"type":"Point"}
}