{
  "type": "Feature",
  "properties": {
    "addr:full":"59100 Prato Prato Prato 59100",
    "addr:postcode":"59100;59100",
    "iso:country":"IT",
    "sg:address":"59100 Prato",
    "sg:city":"Prato",
    "sg:classifiers":[
        {
            "category":"Home & Garden",
            "subcategory":"Building Materials",
            "type":"Retail Goods"
        }
    ],
    "sg:phone":"+39 0574 595556",
    "sg:postcode":"59100",
    "sg:province":"Prato",
    "sg:tags":[
        "window",
        "door",
        "frame"
    ],
    "wof:name":"Puggelli Franco & C. Srl",
    "wof:placetype":"venue"
},
  "geometry": {"coordinates":[11.095904,43.855999],"type":"Point"}
}