{
  "type": "Feature",
  "properties": {
    "iso:country":"IT",
    "sg:address":"30015 Chioggia",
    "sg:city":"Chioggia",
    "sg:orig_category":"Bruciatori Nafta, Gasolio E Kerosene - Installazione E Manutenzione",
    "sg:phone":"+39 041 554 3359",
    "sg:postcode":"30015",
    "sg:province":"Venezia",
    "wof:name":"Airservice Sas",
    "wof:placetype":"venue"
},
  "geometry": {"coordinates":[12.292395,45.217369],"type":"Point"}
}