{
  "type": "Feature",
  "properties": {
    "addr:full":"20060 Gessate Gessate Milano 20060",
    "addr:postcode":"20060;20060",
    "iso:country":"IT",
    "sg:address":"20060 Gessate",
    "sg:city":"Gessate",
    "sg:orig_category":"Forniture Per Edilizia E Lavori Pubblici",
    "sg:phone":"+39 02 9578 1560",
    "sg:postcode":"20060",
    "sg:province":"Milano",
    "wof:name":"Marini Terenzio",
    "wof:placetype":"venue"
},
  "geometry": {"coordinates":[9.4624967575,45.5670967102],"type":"Point"}
}