{
  "type": "Feature",
  "properties": {
    "iso:country":"IT",
    "sg:address":"Via Anagnina, 203 C.p. 4197; Rome; 00100",
    "sg:classifiers":[
        {
            "category":"Industrial Area",
            "type":"Public Place"
        }
    ],
    "sg:phone":"+39 390 672 581",
    "sg:tags":[
        "large",
        "private"
    ],
    "sg:website":"www.ericsson.it",
    "wof:name":"Ericsson Spa",
    "wof:placetype":"venue"
},
  "geometry": {"coordinates":[12.5959472656,41.8321342468],"type":"Point"}
}