{
  "type": "Feature",
  "properties": {
    "iso:country":"IT",
    "sg:address":"20121 Milano",
    "sg:city":"Milano",
    "sg:orig_category":"Tessuti E Stoffe. Tessuti Arredamento, Tende E Tappeti. Shopping",
    "sg:phone":"+39 02 876290",
    "sg:postcode":"20121",
    "sg:province":"Milano",
    "wof:name":"Belgir Carlo",
    "wof:placetype":"venue"
},
  "geometry": {"coordinates":[9.184934,45.466206],"type":"Point"}
}