{
  "type": "Feature",
  "properties": {
    "iso:country":"IT",
    "sg:address":"Via O. Da Gubbio, 166; Roma",
    "sg:classifiers":[
        {
            "category":"Banks & Credit Unions",
            "subcategory":"Bank",
            "type":"Services"
        }
    ],
    "sg:phone":"+39 06 558 6741",
    "wof:name":"Cassa Di Risparmio Di Roma",
    "wof:placetype":"venue"
},
  "geometry": {"coordinates":[12.465095,41.865051],"type":"Point"}
}