{
  "type": "Feature",
  "properties": {
    "iso:country":"IT",
    "sg:address":"20090 Assago",
    "sg:city":"Assago",
    "sg:orig_category":"Carpenterie Ferro",
    "sg:phone":"+39 02 488 0397",
    "sg:postcode":"20090",
    "sg:province":"Milano",
    "sg:website":"http://www.agl-acquati.com",
    "wof:name":"A.g.l. Snc",
    "wof:placetype":"venue"
},
  "geometry": {"coordinates":[9.121845,45.405018],"type":"Point"}
}