{
  "type": "Feature",
  "properties": {
    "iso:country":"IT",
    "sg:address":"Via Trieste 3; Gorizia; 34170",
    "sg:city":"Gorizia",
    "sg:classifiers":[
        {
            "category":"Banks & Credit Unions",
            "subcategory":"Bank",
            "type":"Services"
        }
    ],
    "sg:phone":"+39 0481 522530",
    "sg:postcode":"34170",
    "sg:province":"Gorizia",
    "wof:name":"Cassamarca Spa",
    "wof:placetype":"venue"
},
  "geometry": {"coordinates":[13.613397,45.920792],"type":"Point"}
}