{
  "type": "Feature",
  "properties": {
    "addr:full":"2, Via Piave 33032 Bertiolo Bertiolo Udine 33032",
    "addr:postcode":"33032;33032",
    "addr:street":"Via Piave",
    "iso:country":"IT",
    "sg:address":"2, Via Piave 33032 Bertiolo",
    "sg:city":"Bertiolo",
    "sg:classifiers":[
        {
            "category":"Farming",
            "subcategory":"Livestock Farm",
            "type":"Manufacturing & Wholesale Goods"
        }
    ],
    "sg:phone":"+39 0432 917093",
    "sg:postcode":"33032",
    "sg:province":"Udine",
    "sg:tags":[
        "agriculture"
    ],
    "wof:name":"Eraclit Venier (s.p.a.)",
    "wof:placetype":"venue"
},
  "geometry": {"coordinates":[13.050303,45.904697],"type":"Point"}
}