{
  "type": "Feature",
  "properties": {
    "addr:full":"Contrada Santoro 87020 Santa Maria Del Cedro Santa Maria del Cedro Cosenza 87020",
    "addr:postcode":"87020;87020",
    "addr:street":"Contrada Santoro;Del Cedro",
    "iso:country":"IT",
    "sg:address":"Contrada Santoro 87020 Santa Maria Del Cedro",
    "sg:city":"Santa Maria del Cedro",
    "sg:classifiers":[
        {
            "category":"Manufacturing",
            "subcategory":"Metals",
            "type":"Manufacturing & Wholesale Goods"
        }
    ],
    "sg:phone":"+39 390 985 5359",
    "sg:postcode":"87020",
    "sg:province":"Cosenza",
    "sg:tags":[
        "metallurgy",
        "metalworking"
    ],
    "wof:name":"For.man.snc Di Mandato Osvaldo & C.",
    "wof:placetype":"venue"
},
  "geometry": {"coordinates":[15.8238534927,39.7423553467],"type":"Point"}
}