{
  "type": "Feature",
  "properties": {
    "iso:country":"IT",
    "sg:address":"31010 Ormelle",
    "sg:orig_category":"Manufacturers: Prefabbricati",
    "sg:phone":"+39 0422 745387",
    "sg:postcode":"31010",
    "sg:province":"Treviso",
    "wof:name":"Daniel Luigino",
    "wof:placetype":"venue"
},
  "geometry": {"coordinates":[12.466408,45.763779],"type":"Point"}
}