{
  "type": "Feature",
  "properties": {
    "addr:full":"31010 Mareno Di Piave Mareno di Piave Treviso 31010",
    "addr:housenumber":"di piave",
    "addr:postcode":"31010;31010",
    "iso:country":"IT",
    "sg:address":"31010 Mareno Di Piave",
    "sg:city":"Mareno di Piave",
    "sg:orig_category":"Prodotti Di Base E Forniture Per Industria Alimentare E Bevande. Vetro: Prodotti E Lavorazioni. Articoli Per Imballaggio E Confezionamento",
    "sg:phone":"+39 0438 28475",
    "sg:postcode":"31010",
    "sg:province":"Treviso",
    "wof:name":"Facchin Luigi",
    "wof:placetype":"venue"
},
  "geometry": {"coordinates":[12.3102455139,45.8235435486],"type":"Point"}
}