{
  "type": "Feature",
  "properties": {
    "addr:full":"09048 Sinnai Sinnai Cagliari 09048",
    "addr:postcode":"09048;09048",
    "iso:country":"IT",
    "sg:address":"09048 Sinnai",
    "sg:city":"Sinnai",
    "sg:classifiers":[
        {
            "category":"Health Services",
            "subcategory":"Health Practitioner",
            "type":"Services"
        }
    ],
    "sg:phone":"+39 070 768056",
    "sg:postcode":"09048",
    "sg:province":"Cagliari",
    "sg:tags":[
        "medici"
    ],
    "wof:name":"Loi Giuseppe",
    "wof:placetype":"venue"
},
  "geometry": {"coordinates":[9.300736,39.341503],"type":"Point"}
}