{
  "type": "Feature",
  "properties": {
    "iso:country":"IT",
    "sg:address":"62029 Tolentino",
    "sg:city":"Tolentino",
    "sg:orig_category":"Tintorie Filati E Tessuti",
    "sg:phone":"+39 0733 966660",
    "sg:postcode":"62029",
    "sg:province":"Macerata",
    "wof:name":"La Fenice Srl",
    "wof:placetype":"venue"
},
  "geometry": {"coordinates":[13.456524,43.293613],"type":"Point"}
}