{
  "type": "Feature",
  "properties": {
    "iso:country":"IT",
    "sg:address":"Via Paolo Sarpi 54; Milano; 20154",
    "sg:city":"Milano",
    "sg:classifiers":[
        {
            "category":"Banks & Credit Unions",
            "subcategory":"Bank",
            "type":"Services"
        }
    ],
    "sg:phone":"+39 02 384650",
    "sg:postcode":"20154",
    "sg:province":"Milano",
    "wof:name":"Banca Agricola Milanese Spa",
    "wof:placetype":"venue"
},
  "geometry": {"coordinates":[9.171959,45.481091],"type":"Point"}
}