{
  "type": "Feature",
  "properties": {
    "iso:country":"IT",
    "sg:address":"21100 Varese",
    "sg:city":"Varese",
    "sg:orig_category":"Studi E Consulenze Amministrative, Commerciali E Aziendali. Consulenze Tecniche, Amministrative E Perizie. Professionisti - Studi E Servizi Ed Associazioni Di Interesse Aziendale",
    "sg:phone":"+39 0332 224031",
    "sg:postcode":"21100",
    "sg:province":"Varese",
    "sg:website":"http://www.studiocarbone.it",
    "wof:name":"Studio Di Economia E Diritto Aziendale Carbone & Associati",
    "wof:placetype":"venue"
},
  "geometry": {"coordinates":[8.818517,45.820881],"type":"Point"}
}