{
  "type": "Feature",
  "properties": {
    "addr:full":"33010 Cassacco Cassacco Udine 33010",
    "addr:postcode":"33010;33010",
    "iso:country":"IT",
    "sg:address":"33010 Cassacco",
    "sg:city":"Cassacco",
    "sg:orig_category":"Prodotti E Manufatti In Materie Plastiche",
    "sg:phone":"+39 0432 851296",
    "sg:postcode":"33010",
    "sg:province":"Udine",
    "sg:website":"http://www.mininiplastic.it",
    "wof:name":"Minini & C. Snc",
    "wof:placetype":"venue"
},
  "geometry": {"coordinates":[13.1816015244,46.1196975708],"type":"Point"}
}