{
  "type": "Feature",
  "properties": {
    "iso:country":"IT",
    "sg:address":"89133 Reggio Calabria",
    "sg:orig_category":"Calzature, Pelletterie E Pelli",
    "sg:phone":"+39 0965 598699",
    "sg:province":"RC",
    "wof:name":"Jo.na.than Di Annita Blatnik",
    "wof:placetype":"venue"
},
  "geometry": {"coordinates":[15.7233810425,38.0991821289],"type":"Point"}
}