{
  "type": "Feature",
  "properties": {
    "addr:full":"00193 Roma Roma Roma 00193",
    "addr:postcode":"00193;00193",
    "iso:country":"IT",
    "sg:address":"00193 Roma",
    "sg:city":"Roma",
    "sg:orig_category":"Banche E Servizi Finanziari",
    "sg:phone":"+39 06 322 2360",
    "sg:postcode":"00193",
    "sg:province":"Roma",
    "wof:name":"Cofactor S.p.a.",
    "wof:placetype":"venue"
},
  "geometry": {"coordinates":[12.89038,41.88932],"type":"Point"}
}