{
  "type": "Feature",
  "properties": {
    "iso:country":"IT",
    "sg:address":"80044 Ottaviano",
    "sg:city":"Ottaviano",
    "sg:orig_category":"Abbigliamento Esterno, Maglierie E Pelliccerie",
    "sg:phone":"+39 081 528 8816",
    "sg:postcode":"80044",
    "sg:province":"Napoli",
    "sg:website":"http://www.kocca.it/",
    "wof:name":"Germani Srl",
    "wof:placetype":"venue"
},
  "geometry": {"coordinates":[14.478153,40.838894],"type":"Point"}
}