{
  "type": "Feature",
  "properties": {
    "iso:country":"IT",
    "sg:address":"Via Cedegolo 25051 Cedegolo",
    "sg:city":"Cedegolo",
    "sg:classifiers":[
        {
            "category":"Real Estate",
            "subcategory":"Architect",
            "type":"Services"
        }
    ],
    "sg:phone":"+39 036 463 0373",
    "sg:postcode":"25051",
    "sg:province":"Brescia",
    "sg:tags":[
        "textile",
        "clothing"
    ],
    "wof:name":"Scom",
    "wof:placetype":"venue"
},
  "geometry": {"coordinates":[10.352887,46.071827],"type":"Point"}
}