{
  "type": "Feature",
  "properties": {
    "addr:full":"250, Corso Genova 27029 Vigevano Vigevano Pavia 27029",
    "addr:postcode":"27029;27029",
    "addr:street":"Corso Genova",
    "iso:country":"IT",
    "sg:address":"250, Corso Genova 27029 Vigevano",
    "sg:city":"Vigevano",
    "sg:classifiers":[
        {
            "category":"Personal",
            "subcategory":"Shoe Repair & Shine",
            "type":"Services"
        }
    ],
    "sg:phone":"+39 0381 346095",
    "sg:postcode":"27029",
    "sg:province":"Pavia",
    "sg:tags":[
        "leather"
    ],
    "wof:name":"Repa S.r.l.",
    "wof:placetype":"venue"
},
  "geometry": {"coordinates":[8.854091,45.282822],"type":"Point"}
}