{
  "type": "Feature",
  "properties": {
    "iso:country":"IT",
    "sg:address":"10, Via Amalfi 41034 Finale Emilia",
    "sg:city":"Finale Emilia",
    "sg:classifiers":[
        {
            "category":"Manufacturing",
            "subcategory":"Tools & Machinery",
            "type":"Manufacturing & Wholesale Goods"
        }
    ],
    "sg:phone":"+39 39053598202",
    "sg:postcode":"41034",
    "sg:province":"Modena",
    "sg:tags":[
        "environment",
        "equipment",
        "-"
    ],
    "wof:name":"P.r.t. (s.r.l.)",
    "wof:placetype":"venue"
},
  "geometry": {"coordinates":[11.250034,44.82946],"type":"Point"}
}