{
  "type": "Feature",
  "properties": {
    "iso:country":"IT",
    "sg:address":"24124 Bergamo",
    "sg:city":"Bergamo",
    "sg:orig_category":"Servizi Editoriali",
    "sg:phone":"+39 035 238751",
    "sg:postcode":"24124",
    "sg:province":"Bergamo",
    "wof:name":"Ranica Augusto",
    "wof:placetype":"venue"
},
  "geometry": {"coordinates":[9.678043,45.70351],"type":"Point"}
}