{
  "type": "Feature",
  "properties": {
    "addr:full":"19, Via Giovanni Da Verrazzano 90142 Palermo Palermo Palermo 90142",
    "addr:postcode":"90142;90142",
    "addr:street":"Via Giovanni Da Verrazzano",
    "iso:country":"IT",
    "sg:address":"19, Via Giovanni Da Verrazzano 90142 Palermo",
    "sg:city":"Palermo",
    "sg:classifiers":[
        {
            "category":"Autos & Motor Vehicles",
            "subcategory":"Boat Sales",
            "type":"Retail Goods"
        }
    ],
    "sg:phone":"+39 39091546067",
    "sg:postcode":"90142",
    "sg:province":"Palermo",
    "wof:name":"Na.te.r. S.r.l.",
    "wof:placetype":"venue"
},
  "geometry": {"coordinates":[13.361376,38.11562],"type":"Point"}
}