{
  "type": "Feature",
  "properties": {
    "iso:country":"IT",
    "sg:address":"92024 Canicatti'",
    "sg:orig_category":"Prodotti Alimentari",
    "sg:phone":"+39 0922 735000",
    "sg:postcode":"92024",
    "sg:province":"Agrigento",
    "wof:name":"Ce. Di. Al Srl",
    "wof:placetype":"venue"
},
  "geometry": {"coordinates":[13.8332195282,37.362953186],"type":"Point"}
}