{
  "type": "Feature",
  "properties": {
    "iso:country":"IT",
    "sg:address":"Via Sant' Ambrogio 74 20050 Triuggio",
    "sg:city":"Triuggio",
    "sg:classifiers":[
        {
            "category":"Communications",
            "subcategory":"Television Station",
            "type":"Services"
        }
    ],
    "sg:phone":"+39 036 291 9633",
    "sg:postcode":"20050",
    "sg:province":"Milano",
    "sg:tags":[
        "curtain",
        "black-out"
    ],
    "sg:website":"www.lodovici.it",
    "wof:name":"Manifattura Lodovici E C. Spa",
    "wof:placetype":"venue"
},
  "geometry": {"coordinates":[9.289638,45.681831],"type":"Point"}
}