{
  "type": "Feature",
  "properties": {
    "iso:country":"IT",
    "sg:address":"33080 Fiume Veneto",
    "sg:city":"Fiume Veneto",
    "sg:orig_category":"Giardinaggio - Macchine Ed Attrezzi",
    "sg:phone":"+39 0434 958836",
    "sg:postcode":"33080",
    "sg:province":"Pordenone",
    "sg:website":"http://www.claber.com",
    "wof:name":"Claber Spa",
    "wof:placetype":"venue"
},
  "geometry": {"coordinates":[12.714156,45.933537],"type":"Point"}
}