{
  "type": "Feature",
  "properties": {
    "iso:country":"IT",
    "sg:address":"Via Delle Piagge 15 55014 Marlia",
    "sg:city":"Marlia",
    "sg:orig_category":"Ladies' Shoes",
    "sg:phone":"+39 0583 407233",
    "sg:postcode":"55014",
    "sg:province":"Lucca",
    "sg:website":"www.toscanoshoes.it",
    "wof:name":"Calzaturificio Toscano Shoes S.r.l.",
    "wof:placetype":"venue"
},
  "geometry": {"coordinates":[10.538775,43.885029],"type":"Point"}
}