{
  "type": "Feature",
  "properties": {
    "addr:full":"3, Via Degli Artigiani 33020 Verzegnis Verzegnis Udine 33020",
    "addr:postcode":"33020;33020",
    "addr:street":"Via Degli Artigiani",
    "iso:country":"IT",
    "sg:address":"3, Via Degli Artigiani 33020 Verzegnis",
    "sg:city":"Verzegnis",
    "sg:classifiers":[
        {
            "category":"Manufacturing",
            "subcategory":"Metals",
            "type":"Manufacturing & Wholesale Goods"
        }
    ],
    "sg:phone":"+39 39043343321",
    "sg:postcode":"33020",
    "sg:province":"Udine",
    "sg:tags":[
        "processing"
    ],
    "wof:name":"De Stalis Michele & C. S.n.c.",
    "wof:placetype":"venue"
},
  "geometry": {"coordinates":[13.0320415497,46.3907928467],"type":"Point"}
}