{
  "type": "Feature",
  "properties": {
    "iso:country":"IT",
    "sg:address":"24060 Rogno",
    "sg:city":"Rogno",
    "sg:orig_category":"Dolciumi E Gelati",
    "sg:phone":"+39 035 967605",
    "sg:postcode":"24060",
    "sg:province":"Bergamo",
    "wof:name":"Le Delizie Dell'alveare Sas Di Torri",
    "wof:placetype":"venue"
},
  "geometry": {"coordinates":[9.730435,45.716705],"type":"Point"}
}