{
  "type": "Feature",
  "properties": {
    "iso:country":"IT",
    "sg:address":"Via Fabi Armando 03100 Frosinone",
    "sg:city":"Frosinone",
    "sg:classifiers":[
        {
            "category":"Parking",
            "subcategory":"Lot",
            "type":"Transportation"
        }
    ],
    "sg:phone":"+39 0775 888064",
    "sg:postcode":"03100",
    "sg:province":"Frosinone",
    "sg:tags":[
        "transport",
        "road"
    ],
    "wof:name":"Cianfrocca Trasporti Srl",
    "wof:placetype":"venue"
},
  "geometry": {"coordinates":[13.316617,41.639259],"type":"Point"}
}