{
  "type": "Feature",
  "properties": {
    "addr:full":"Via Laurentina Km 26500 00040 Pomezia Pomezia Roma 00040",
    "addr:housenumber":"km",
    "addr:postcode":"00040;roma 00040",
    "addr:street":"Via Laurentina;26500",
    "iso:country":"IT",
    "sg:address":"Via Laurentina Km 26500 00040 Pomezia",
    "sg:city":"Pomezia",
    "sg:orig_category":"Bags Of Neoprene",
    "sg:phone":"+39 06 919601",
    "sg:postcode":"00040",
    "sg:province":"Roma",
    "sg:website":"www.morettigroup.com",
    "wof:name":"Moretti Group International Spa",
    "wof:placetype":"venue"
},
  "geometry": {"coordinates":[12.501794,41.669292],"type":"Point"}
}