{
  "type": "Feature",
  "properties": {
    "iso:country":"IT",
    "sg:address":"10, Via Dell' Artigianato 48011 Alfonsine",
    "sg:city":"Alfonsine",
    "sg:classifiers":[
        {
            "category":"Professional",
            "subcategory":"Engineering",
            "type":"Services"
        }
    ],
    "sg:phone":"+39 39054482357",
    "sg:postcode":"48011",
    "sg:province":"Ravenna",
    "sg:tags":[
        "machine",
        "-",
        "mechanical"
    ],
    "wof:name":"Fratelli Montanari Daniele & Domenico S.n.c.",
    "wof:placetype":"venue"
},
  "geometry": {"coordinates":[12.019485,44.506672],"type":"Point"}
}