{
  "type": "Feature",
  "properties": {
    "iso:country":"IT",
    "sg:address":"94, Viale S. Bernardino 71016 San Severo",
    "sg:city":"San Severo",
    "sg:classifiers":[
        {
            "category":"Food & Beverages",
            "subcategory":"Groceries & Convenience Stores",
            "type":"Retail Goods"
        }
    ],
    "sg:phone":"+39 0882 221125",
    "sg:postcode":"71016",
    "sg:province":"Foggia",
    "sg:tags":[
        "drink"
    ],
    "wof:name":"Cantina Sociale Cooperativa",
    "wof:placetype":"venue"
},
  "geometry": {"coordinates":[15.5447,41.462334],"type":"Point"}
}