{
  "type": "Feature",
  "properties": {
    "iso:country":"IT",
    "sg:address":"Piazza Edison, 3; Milano; 20123",
    "sg:city":"Milano",
    "sg:classifiers":[
        {
            "category":"Banks & Credit Unions",
            "subcategory":"Bank",
            "type":"Services"
        }
    ],
    "sg:phone":"+39 0285921",
    "sg:postcode":"20123",
    "sg:province":"Milano",
    "wof:name":"Banca D'italia",
    "wof:placetype":"venue"
},
  "geometry": {"coordinates":[9.184804,45.464279],"type":"Point"}
}