{
  "type": "Feature",
  "properties": {
    "addr:full":"80125 Napoli Napoli Napoli 80125",
    "addr:housenumber":"80125",
    "addr:postcode":"80125",
    "iso:country":"IT",
    "sg:address":"80125 Napoli",
    "sg:city":"Napoli",
    "sg:classifiers":[
        {
            "category":"Manufacturing",
            "subcategory":"Motor Vehicles & Parts",
            "type":"Manufacturing & Wholesale Goods"
        }
    ],
    "sg:phone":"+39 081 570 5300",
    "sg:postcode":"80125",
    "sg:province":"Napoli",
    "sg:tags":[
        "spare",
        "vehicles",
        "component"
    ],
    "sg:website":"http://www.meam.it",
    "wof:name":"M.e.a.m. Srl",
    "wof:placetype":"venue"
},
  "geometry": {"coordinates":[14.162399292,40.833568573],"type":"Point"}
}