{
  "type": "Feature",
  "properties": {
    "iso:country":"IT",
    "sg:address":"1, Via Altivole 31031 Caerano Di San Marco",
    "sg:city":"Caerano di San Marco",
    "sg:classifiers":[
        {
            "category":"Shopping",
            "subcategory":"Crafts & Fabrics",
            "type":"Retail Goods"
        }
    ],
    "sg:phone":"+39 0423 859185",
    "sg:postcode":"31031",
    "sg:province":"Treviso",
    "wof:name":"Filatura Di Caerano (s.p.a.)",
    "wof:placetype":"venue"
},
  "geometry": {"coordinates":[11.9893226624,45.7592697144],"type":"Point"}
}