{
  "type": "Feature",
  "properties": {
    "iso:country":"IT",
    "sg:address":"20128 Milano",
    "sg:city":"Milano",
    "sg:orig_category":"Prodotti Chimici Di Base",
    "sg:phone":"+39 02 255 0237",
    "sg:postcode":"20128",
    "sg:province":"Milano",
    "wof:name":"Tecnocor S.r.l.",
    "wof:placetype":"venue"
},
  "geometry": {"coordinates":[9.2322950363,45.5118026733],"type":"Point"}
}