{
  "type": "Feature",
  "properties": {
    "iso:country":"IT",
    "sg:address":"00197 Roma",
    "sg:city":"Roma",
    "sg:orig_category":"Servizi Al Turismo. Ambasciate Ed Enti Internazionali",
    "sg:phone":"+39 06 808 4423",
    "sg:postcode":"00197",
    "sg:province":"Roma",
    "wof:name":"Consolato Romania",
    "wof:placetype":"venue"
},
  "geometry": {"coordinates":[12.488273,41.924488],"type":"Point"}
}