{
  "type": "Feature",
  "properties": {
    "iso:country":"IT",
    "sg:address":"43010 Roccabianca",
    "sg:city":"Roccabianca",
    "sg:orig_category":"Assemblaggio Conto Terzi",
    "sg:phone":"+39 0521 870321",
    "sg:postcode":"43010",
    "sg:province":"Parma",
    "wof:name":"Tecno.co.me. Snc",
    "wof:placetype":"venue"
},
  "geometry": {"coordinates":[10.2584228516,44.927947998],"type":"Point"}
}