{
  "type": "Feature",
  "properties": {
    "addr:full":"Via Enrico Mattei 10 53041 Asciano Asciano Siena 53041",
    "addr:housenumber":"10",
    "addr:postcode":"53041;53041",
    "addr:street":"Via Enrico Mattei",
    "iso:country":"IT",
    "sg:address":"Via Enrico Mattei 10 53041 Asciano",
    "sg:city":"Asciano",
    "sg:classifiers":[
        {
            "category":"Home & Garden",
            "subcategory":"Home Furnishings",
            "type":"Retail Goods"
        }
    ],
    "sg:phone":"+39 0577 718293",
    "sg:postcode":"53041",
    "sg:province":"Siena",
    "sg:tags":[
        "bathroom",
        "wc",
        "fitting"
    ],
    "sg:website":"www.rubinetterie3m.it",
    "wof:name":"Rubinetterie 3m Srl",
    "wof:placetype":"venue"
},
  "geometry": {"coordinates":[11.582077,43.2383],"type":"Point"}
}