{
  "type": "Feature",
  "properties": {
    "addr:full":"23877 Paderno D'adda Lecco 23877",
    "addr:postcode":"23877;23877",
    "iso:country":"IT",
    "sg:address":"23877 Paderno D'adda",
    "sg:orig_category":"Forniture Per Abbigliamento E Pelletterie. Complementi Di Arredamento",
    "sg:phone":"+39 039 951 5534",
    "sg:postcode":"23877",
    "sg:province":"Lecco",
    "wof:name":"Passamaneria Viky Snc",
    "wof:placetype":"venue"
},
  "geometry": {"coordinates":[9.4445543289,45.6835784912],"type":"Point"}
}