{
  "type": "Feature",
  "properties": {
    "addr:full":"20010 Santo Stefano Ticino Santo Stefano Ticino Milano 20010",
    "addr:postcode":"20010;20010",
    "iso:country":"IT",
    "sg:address":"20010 Santo Stefano Ticino",
    "sg:city":"Santo Stefano Ticino",
    "sg:orig_category":"Valvole E Apparecchiature Di Misura. Forniture Per Attivita' Industriali",
    "sg:phone":"+39 02 974 8421",
    "sg:postcode":"20010",
    "sg:province":"Milano",
    "wof:name":"Adler Srl",
    "wof:placetype":"venue"
},
  "geometry": {"coordinates":[8.919097,45.488731],"type":"Point"}
}