{
  "type": "Feature",
  "properties": {
    "addr:full":"Via G. Alghisi 31/b 41012 Carpi Carpi Modena 41012",
    "addr:housenumber":"31 / b",
    "addr:postcode":"41012;41012",
    "addr:street":"Via G. Alghisi",
    "iso:country":"IT",
    "sg:address":"Via G. Alghisi 31/b 41012 Carpi",
    "sg:city":"Carpi",
    "sg:orig_category":"Hoisiery Goods",
    "sg:phone":"+39 059 697361",
    "sg:postcode":"41012",
    "sg:province":"Modena",
    "wof:name":"Maglierie Portioli Di Portioli O. E C. Sas",
    "wof:placetype":"venue"
},
  "geometry": {"coordinates":[10.891506,44.780651],"type":"Point"}
}