{
  "type": "Feature",
  "properties": {
    "iso:country":"IT",
    "sg:address":"Loc. Campiaro 40030 Grizzana Morandi",
    "sg:city":"Grizzana Morandi",
    "sg:orig_category":"Brushes, Special, For Technical Purposes",
    "sg:phone":"+39 051 673 0004",
    "sg:postcode":"40030",
    "sg:province":"Bologna",
    "sg:website":"www.lippert-unipol.it",
    "wof:name":"Lippert Unipol (i) Srl",
    "wof:placetype":"venue"
},
  "geometry": {"coordinates":[11.346481,44.494221],"type":"Point"}
}