{
  "type": "Feature",
  "properties": {
    "addr:full":"12100 Madonna Delle Grazie Madonna delle Grazie Cuneo 12100",
    "addr:postcode":"12100;12100",
    "addr:street":"Delle Grazie",
    "iso:country":"IT",
    "sg:address":"12100 Madonna Delle Grazie",
    "sg:city":"Madonna delle Grazie",
    "sg:orig_category":"Motori Ed Organi Di Trasmissione. Ricambi E Componenti Dei Mezzi Di Trasporto",
    "sg:phone":"+39 0171 403583",
    "sg:postcode":"12100",
    "sg:province":"Cuneo",
    "wof:name":"Broglia Andrea",
    "wof:placetype":"venue"
},
  "geometry": {"coordinates":[7.5649733543,44.3927154541],"type":"Point"}
}