{
  "type": "Feature",
  "properties": {
    "iso:country":"IT",
    "sg:address":"24040 Bottanuco",
    "sg:city":"Bottanuco",
    "sg:orig_category":"Macchine Ed Impianti Per Edilizia E Lavori Pubblici",
    "sg:phone":"+39 035 499 2060",
    "sg:postcode":"24040",
    "sg:province":"Bergamo",
    "wof:name":"Vecos Srl",
    "wof:placetype":"venue"
},
  "geometry": {"coordinates":[9.503472,45.640617],"type":"Point"}
}