{
  "type": "Feature",
  "properties": {
    "iso:country":"IT",
    "sg:address":"2, Via Del Popolo 05029 Sangemini",
    "sg:classifiers":[
        {
            "category":"Sports & Exercise",
            "subcategory":"Playing Field",
            "type":"Entertainment"
        }
    ],
    "sg:phone":"+39 0744 630590",
    "sg:postcode":"05029",
    "sg:province":"Terni",
    "sg:tags":[
        "game"
    ],
    "wof:name":"R.b. Diffusion S.r.l.",
    "wof:placetype":"venue"
},
  "geometry": {"coordinates":[12.646781,42.560219],"type":"Point"}
}