{
  "type": "Feature",
  "properties": {
    "iso:country":"IT",
    "sg:address":"28, Via Benzoni Girolamo 00154 Roma",
    "sg:city":"Roma",
    "sg:classifiers":[
        {
            "category":"Shopping",
            "subcategory":"Clothing, Apparel, & Fashions",
            "type":"Retail Goods"
        }
    ],
    "sg:phone":"+39 39065759061",
    "sg:postcode":"00154",
    "sg:province":"Roma",
    "sg:tags":[
        "clothes"
    ],
    "wof:name":"Biban Atelier Srl",
    "wof:placetype":"venue"
},
  "geometry": {"coordinates":[12.484741,41.868095],"type":"Point"}
}