{
  "type": "Feature",
  "properties": {
    "iso:country":"IT",
    "sg:address":"24068 Seriate",
    "sg:city":"Cassinone",
    "sg:orig_category":"Lavorazioni Metalli, Stampaggio E Saldatura",
    "sg:phone":"+39 035 293302",
    "sg:postcode":"24068",
    "sg:province":"Bergamo",
    "sg:website":"http://www.ranica.org",
    "wof:name":"Carpenterie Metalliche Ranica Snc",
    "wof:placetype":"venue"
},
  "geometry": {"coordinates":[9.739264,45.659187],"type":"Point"}
}