{
  "type": "Feature",
  "properties": {
    "iso:country":"IT",
    "sg:address":"Loc Ghisella 2 26812 Borghetto Lodigiano",
    "sg:city":"Borghetto Lodigiano",
    "sg:classifiers":[
        {
            "category":"Wholesale",
            "subcategory":"Groceries",
            "type":"Manufacturing & Wholesale Goods"
        }
    ],
    "sg:phone":"+39 0371 897532",
    "sg:postcode":"26812",
    "sg:province":"Lodi",
    "sg:tags":[
        "rice"
    ],
    "sg:website":"www.risodragoni.it",
    "wof:name":"Riso Dragoni Di Dragoni Giovanni E C Snc",
    "wof:placetype":"venue"
},
  "geometry": {"coordinates":[9.49785,45.312878],"type":"Point"}
}