{
  "type": "Feature",
  "properties": {
    "iso:country":"IT",
    "sg:address":"20145 Milano",
    "sg:city":"Milano",
    "sg:orig_category":"Cartolerie",
    "sg:phone":"+39 02 4800 3342",
    "sg:postcode":"20145",
    "sg:province":"Milano",
    "wof:name":"Parenti & Agostinelli",
    "wof:placetype":"venue"
},
  "geometry": {"coordinates":[9.164727,45.466251],"type":"Point"}
}