{
  "type": "Feature",
  "properties": {
    "iso:country":"IT",
    "sg:address":"36, Via Armando Diaz 20020 Magnago",
    "sg:city":"Magnago",
    "sg:classifiers":[
        {
            "category":"Utilities",
            "subcategory":"Electric",
            "type":"Services"
        }
    ],
    "sg:phone":"+39 0331 659798",
    "sg:postcode":"20020",
    "sg:province":"Milano",
    "sg:tags":[
        "component",
        "electronic"
    ],
    "wof:name":"Linear (s.r.l.)",
    "wof:placetype":"venue"
},
  "geometry": {"coordinates":[8.813379,45.576996],"type":"Point"}
}