{
  "type": "Feature",
  "properties": {
    "iso:country":"IT",
    "sg:address":"10036 Settimo Torinese",
    "sg:city":"Settimo Torinese",
    "sg:orig_category":"Prodotti Vari In Metallo",
    "sg:phone":"+39 011 895 5884",
    "sg:postcode":"10036",
    "sg:province":"Torino",
    "wof:name":"Load Lok Italia Srl",
    "wof:placetype":"venue"
},
  "geometry": {"coordinates":[7.7489151955,45.1250839233],"type":"Point"}
}