{
  "type": "Feature",
  "properties": {
    "iso:country":"IT",
    "sg:address":"20060 Triginto",
    "sg:city":"Triginto",
    "sg:orig_category":"Scuole E Servizi Scolastici. Servizi Vari Di Interesse Pubblico",
    "sg:phone":"+39 02 906 2354",
    "sg:postcode":"20060",
    "sg:province":"Milano",
    "wof:name":"Asilo Nido - Biblioteca Civica",
    "wof:placetype":"venue"
},
  "geometry": {"coordinates":[9.21024,45.47076],"type":"Point"}
}