{
  "type": "Feature",
  "properties": {
    "addr:full":"00154 Roma Roma Roma 00154",
    "addr:postcode":"00154;00154",
    "iso:country":"IT",
    "sg:address":"00154 Roma",
    "sg:city":"Roma",
    "sg:orig_category":"Valvole E Apparecchiature Di Misura. Forniture Per Attivita' Industriali",
    "sg:phone":"+39 06 578 0759",
    "sg:postcode":"00154",
    "sg:province":"Roma",
    "wof:name":"Pucci Mario",
    "wof:placetype":"venue"
},
  "geometry": {"coordinates":[12.481447,41.874138],"type":"Point"}
}