{
  "type": "Feature",
  "properties": {
    "iso:country":"IT",
    "sg:address":"Regione Mesu E Jagas 07047 Thiesi",
    "sg:city":"Thiesi",
    "sg:classifiers":[
        {
            "category":"Food & Beverages",
            "subcategory":"Dairy",
            "type":"Retail Goods"
        }
    ],
    "sg:phone":"+39 39079886829",
    "sg:postcode":"07047",
    "sg:province":"Sassari",
    "sg:tags":[
        "product"
    ],
    "wof:name":"Cossu Demetrio Ind.casearia S.a.s. Di Rita Cossu & C.",
    "wof:placetype":"venue"
},
  "geometry": {"coordinates":[8.558469,40.727165],"type":"Point"}
}