{
  "type": "Feature",
  "properties": {
    "iso:country":"IT",
    "sg:address":"00049 Velletri",
    "sg:city":"Velletri",
    "sg:orig_category":"Arredo Camera Letto E Complementi. Servizi E Lavori Per Arredamento E Industria Del Legno",
    "sg:phone":"+39 06 963 2054",
    "sg:postcode":"00049",
    "sg:province":"Roma",
    "wof:name":"Matera Riccardo",
    "wof:placetype":"venue"
},
  "geometry": {"coordinates":[12.77608,41.689743],"type":"Point"}
}