{
  "type": "Feature",
  "properties": {
    "addr:full":"1, Via Liguria 24052 Azzano San Paolo Azzano San Paolo Bergamo 24052",
    "addr:postcode":"24052;24052",
    "addr:street":"Via Liguria",
    "iso:country":"IT",
    "sg:address":"1, Via Liguria 24052 Azzano San Paolo",
    "sg:city":"Azzano San Paolo",
    "sg:classifiers":[
        {
            "category":"Shopping",
            "subcategory":"Crafts & Fabrics",
            "type":"Retail Goods"
        }
    ],
    "sg:phone":"+39 39035320445",
    "sg:postcode":"24052",
    "sg:province":"Bergamo",
    "wof:name":"Seristir (s.n.c.)",
    "wof:placetype":"venue"
},
  "geometry": {"coordinates":[9.6991500854,45.6613960266],"type":"Point"}
}