{
  "type": "Feature",
  "properties": {
    "addr:full":"70010 Adelfia Adelfia Bari 70010",
    "addr:postcode":"70010;70010",
    "iso:country":"IT",
    "sg:address":"70010 Adelfia",
    "sg:city":"Adelfia",
    "sg:orig_category":"Servizi E Lavori Per Agricoltura E Zootecnia. Animali Domestici",
    "sg:phone":"+39 080 459 6058",
    "sg:postcode":"70010",
    "sg:province":"Bari",
    "wof:name":"Borino Dott. Leandro",
    "wof:placetype":"venue"
},
  "geometry": {"coordinates":[16.862436,41.004753],"type":"Point"}
}