{
  "type": "Feature",
  "properties": {
    "addr:full":"40064 Ozzano Dell'emilia Mercatale Bologna 40064",
    "addr:postcode":"40064;mercatale bologna 40064",
    "iso:country":"IT",
    "sg:address":"40064 Ozzano Dell'emilia",
    "sg:city":"Mercatale",
    "sg:orig_category":"Servizi E Lavori Per Agricoltura E Zootecnia",
    "sg:phone":"+39 051 651 5353",
    "sg:postcode":"40064",
    "sg:province":"Bologna",
    "wof:name":"Co.pro.zoo. Cooperativa Produttori Zootecnici (s.r.l.)",
    "wof:placetype":"venue"
},
  "geometry": {"coordinates":[11.449482,44.392185],"type":"Point"}
}