{
  "type": "Feature",
  "properties": {
    "addr:full":"10093 Collegno Collegno Torino 10093",
    "addr:postcode":"10093;10093",
    "iso:country":"IT",
    "sg:address":"10093 Collegno",
    "sg:city":"Collegno",
    "sg:orig_category":"Materiali E Componenti Elettronici",
    "sg:phone":"+39 011 411 3315",
    "sg:postcode":"10093",
    "sg:province":"Torino",
    "wof:name":"C.e.a.r.t.",
    "wof:placetype":"venue"
},
  "geometry": {"coordinates":[7.604176,45.074081],"type":"Point"}
}