{
  "type": "Feature",
  "properties": {
    "iso:country":"IT",
    "sg:address":"209, Via Maccani Ezio 38100 Trento",
    "sg:city":"Trento",
    "sg:classifiers":[
        {
            "category":"Utilities",
            "subcategory":"Electric",
            "type":"Services"
        }
    ],
    "sg:phone":"+39 0461 827050",
    "sg:postcode":"38100",
    "sg:province":"Trento",
    "sg:tags":[
        "component",
        "electronic"
    ],
    "wof:name":"Foxel (s.r.l.)",
    "wof:placetype":"venue"
},
  "geometry": {"coordinates":[11.106182,46.093235],"type":"Point"}
}