{
  "type": "Feature",
  "properties": {
    "iso:country":"IT",
    "sg:address":"25024 Leno",
    "sg:city":"Leno",
    "sg:orig_category":"Macchine, Impianti Ed Attrezzature Industria Delle Materie Plastiche E Gomma",
    "sg:phone":"+39 030 903 9036",
    "sg:postcode":"25024",
    "sg:province":"Brescia",
    "wof:name":"Bianchetti Fabio",
    "wof:placetype":"venue"
},
  "geometry": {"coordinates":[10.167614,45.499928],"type":"Point"}
}