{
  "type": "Feature",
  "properties": {
    "iso:country":"IT",
    "sg:address":"10098 Cascine Vica",
    "sg:city":"Cascine vica",
    "sg:orig_category":"Apparecchiature Ed Attrezzature Meccaniche. Ricambi E Componenti Dei Mezzi Di Trasporto",
    "sg:phone":"+39 011 959 4717",
    "sg:postcode":"10098",
    "sg:province":"Torino",
    "wof:name":"Caber S.r.l.",
    "wof:placetype":"venue"
},
  "geometry": {"coordinates":[7.560495,45.06292],"type":"Point"}
}