{
  "type": "Feature",
  "properties": {
    "iso:country":"IT",
    "sg:address":"81010 Ciorlano",
    "sg:city":"Ciorlano",
    "sg:orig_category":"Metalli E Leghe",
    "sg:phone":"+39 0823 944108",
    "sg:postcode":"81010",
    "sg:province":"Caserta",
    "wof:name":"Fortini Antonio",
    "wof:placetype":"venue"
},
  "geometry": {"coordinates":[14.158908844,41.4507408142],"type":"Point"}
}