{
  "type": "Feature",
  "properties": {
    "iso:country":"IT",
    "sg:address":"93012 Gela",
    "sg:city":"Gela",
    "sg:orig_category":"Scuole E Servizi Scolastici. Centri Di Estetica E Cosmesi E Servizi. Ricerca, Selezione E Formazione Del Personale",
    "sg:phone":"+39 0933 918204",
    "sg:postcode":"93012",
    "sg:province":"Caltanissetta",
    "sg:website":"http://www.extremetrendmalu.it",
    "wof:name":"Extreme Trend Mal\u00d9",
    "wof:placetype":"venue"
},
  "geometry": {"coordinates":[14.309376,37.08503],"type":"Point"}
}