{
  "type": "Feature",
  "properties": {
    "addr:full":"Via Sacconi Giuseppe 33 06132 Perugia Perugia Perugia 06132",
    "addr:housenumber":"33",
    "addr:postcode":"06132;06132",
    "addr:street":"Via Sacconi Giuseppe",
    "iso:country":"IT",
    "sg:address":"Via Sacconi Giuseppe 33 06132 Perugia",
    "sg:city":"Perugia",
    "sg:classifiers":[
        {
            "category":"Government",
            "subcategory":"Department Of Motor Vehicles",
            "type":"Public Place"
        }
    ],
    "sg:phone":"+39 075 528 9583",
    "sg:postcode":"06132",
    "sg:province":"Perugia",
    "sg:tags":[
        "machine",
        "closing",
        "vacuum"
    ],
    "wof:name":"Automazioni Meccaniche Srl",
    "wof:placetype":"venue"
},
  "geometry": {"coordinates":[12.389172,43.110703],"type":"Point"}
}