{
  "type": "Feature",
  "properties": {
    "iso:country":"IT",
    "sg:address":"39054 Collalbo",
    "sg:city":"Collalbo",
    "sg:orig_category":"Servizi E Lavori Per Ecologia E Smaltimento Rifiuti. Termotecnica E Riscaldamento, Apparecchiature E Servizi. Servizi Ausiliari Di Sorveglianza, Manutenzione E Pulizia",
    "sg:phone":"+39 0471 356342",
    "sg:postcode":"39054",
    "sg:province":"Bolzano/Bozen",
    "wof:name":"Fischer Franz",
    "wof:placetype":"venue"
},
  "geometry": {"coordinates":[11.468043,46.536686],"type":"Point"}
}