{
  "type": "Feature",
  "properties": {
    "iso:country":"IT",
    "sg:address":"22, Via Bonazzi 40013 Castel Maggiore",
    "sg:city":"Castel Maggiore",
    "sg:classifiers":[
        {
            "category":"Shopping",
            "subcategory":"Computers & Home Electronics",
            "type":"Retail Goods"
        }
    ],
    "sg:phone":"+39 39051700321",
    "sg:postcode":"40013",
    "sg:province":"Bologna",
    "sg:tags":[
        "electronic",
        "electrical",
        "equipment"
    ],
    "wof:name":"Sati Trading (s.r.l.)",
    "wof:placetype":"venue"
},
  "geometry": {"coordinates":[11.370284,44.559704],"type":"Point"}
}