{
  "type": "Feature",
  "properties": {
    "iso:country":"IT",
    "sg:address":"18038 Sanremo",
    "sg:orig_category":"Barche, Canotti Pneumatici E Motoscafi - Vendita Al Dettaglio",
    "sg:phone":"+39 0184 505806",
    "sg:postcode":"18038",
    "sg:province":"Imperia",
    "wof:name":"Sanremo Ship Srl",
    "wof:placetype":"venue"
},
  "geometry": {"coordinates":[7.77427,43.841179],"type":"Point"}
}