{
  "type": "Feature",
  "properties": {
    "iso:country":"IT",
    "sg:address":"55049 Viareggio",
    "sg:city":"Viareggio",
    "sg:orig_category":"Centri Di Estetica E Cosmesi E Servizi. Prodotti Cosmetici E Da Toeletta",
    "sg:phone":"+39 0584 46549",
    "sg:postcode":"55049",
    "sg:province":"Lucca",
    "wof:name":"Vanelli Stefano",
    "wof:placetype":"venue"
},
  "geometry": {"coordinates":[10.27123,43.851627],"type":"Point"}
}