{
  "type": "Feature",
  "properties": {
    "addr:full":"67039 Sulmona L'Aquila 67039",
    "addr:postcode":"67039;67039",
    "iso:country":"IT",
    "sg:address":"67039 Sulmona",
    "sg:orig_category":"Arredo Camera Letto E Complementi",
    "sg:phone":"+39 0864 50584",
    "sg:postcode":"67039",
    "sg:province":"L'Aquila",
    "wof:name":"Tricarico Sebastiano",
    "wof:placetype":"venue"
},
  "geometry": {"coordinates":[13.399934,42.350697],"type":"Point"}
}