{
  "type": "Feature",
  "properties": {
    "iso:country":"IT",
    "sg:address":"25, Viale Letizia 80131 Napoli",
    "sg:city":"Napoli",
    "sg:classifiers":[
        {
            "category":"Real Estate",
            "subcategory":"Surveying",
            "type":"Services"
        }
    ],
    "sg:phone":"+39 081 546 7397",
    "sg:postcode":"80131",
    "sg:province":"Napoli",
    "sg:tags":[
        "equipment",
        "material",
        "good",
        "-",
        "handling"
    ],
    "wof:name":"Buccilli G. & G. Di Buccilli Gabriella - Sas",
    "wof:placetype":"venue"
},
  "geometry": {"coordinates":[14.244994,40.869785],"type":"Point"}
}