{
  "type": "Feature",
  "properties": {
    "iso:country":"IT",
    "sg:address":"28881 Casale Corte Cerro",
    "sg:city":"Casale Corte Cerro",
    "sg:orig_category":"Prodotti Di Base E Forniture Per Industria Alimentare E Bevande",
    "sg:phone":"+39 0323 60726",
    "sg:postcode":"28881",
    "sg:province":"Verbano-Cusio-Ossola",
    "wof:name":"Togno Giuseppe",
    "wof:placetype":"venue"
},
  "geometry": {"coordinates":[8.4187870026,45.9078216553],"type":"Point"}
}