{
  "type": "Feature",
  "properties": {
    "addr:full":"10095 Grugliasco Grugliasco Torino 10095",
    "addr:postcode":"10095;10095",
    "iso:country":"IT",
    "sg:address":"10095 Grugliasco",
    "sg:city":"Grugliasco",
    "sg:orig_category":"Carta Da Macero",
    "sg:phone":"+39 011 311 3653",
    "sg:postcode":"10095",
    "sg:province":"Torino",
    "wof:name":"Scelzi Srl",
    "wof:placetype":"venue"
},
  "geometry": {"coordinates":[7.59077,45.043022],"type":"Point"}
}