{
  "type": "Feature",
  "properties": {
    "iso:country":"IT",
    "sg:address":"Via Per Sassuolo 1933 41058 Vignola",
    "sg:city":"Vignola",
    "sg:orig_category":"Stretch Film Packing Plants And Machines",
    "sg:phone":"+39 059 772780",
    "sg:postcode":"41058",
    "sg:province":"Modena",
    "sg:website":"www.gruppofabbri.com",
    "wof:name":"Automac Spa",
    "wof:placetype":"venue"
},
  "geometry": {"coordinates":[10.994482,44.49353],"type":"Point"}
}