{
  "type": "Feature",
  "properties": {
    "iso:country":"IT",
    "sg:address":"50145 Firenze",
    "sg:city":"Firenze",
    "sg:classifiers":[
        {
            "category":"Health Services",
            "subcategory":"Health Practitioner",
            "type":"Services"
        }
    ],
    "sg:phone":"+39 055 302 4364",
    "sg:postcode":"50145",
    "sg:province":"Firenze",
    "sg:tags":[
        "medici"
    ],
    "wof:name":"Intes S.r.l.",
    "wof:placetype":"venue"
},
  "geometry": {"coordinates":[11.192209,43.800419],"type":"Point"}
}