{
  "type": "Feature",
  "properties": {
    "iso:country":"IT",
    "sg:address":"50013 San Donnino",
    "sg:city":"San Donnino",
    "sg:orig_category":"Prodotti E Manufatti In Materie Plastiche",
    "sg:phone":"+39 055 896 2551",
    "sg:postcode":"50013",
    "sg:province":"Firenze",
    "wof:name":"Siland (s.r.l.)",
    "wof:placetype":"venue"
},
  "geometry": {"coordinates":[11.144405365,43.7886276245],"type":"Point"}
}