{
  "type": "Feature",
  "properties": {
    "addr:full":"25032 Chiari Chiari Brescia 25032",
    "addr:postcode":"25032;25032",
    "iso:country":"IT",
    "sg:address":"25032 Chiari",
    "sg:city":"Chiari",
    "sg:orig_category":"Servizi E Lavori Industria Chimica",
    "sg:phone":"+39 030 700 2575",
    "sg:postcode":"25032",
    "sg:province":"Brescia",
    "wof:name":"Ilar Verniciature S.r.l.",
    "wof:placetype":"venue"
},
  "geometry": {"coordinates":[9.912815,45.53157],"type":"Point"}
}