{
  "type": "Feature",
  "properties": {
    "iso:country":"IT",
    "sg:address":"19, Via Mario Alberto 20149 Milano",
    "sg:city":"Milano",
    "sg:classifiers":[
        {
            "category":"Professional",
            "subcategory":"Engineering",
            "type":"Services"
        }
    ],
    "sg:phone":"+39 39024986751",
    "sg:postcode":"20149",
    "sg:province":"Milano",
    "sg:tags":[
        "machine",
        "-",
        "mechanical"
    ],
    "wof:name":"Fluxa Filtri (s.p.a.)",
    "wof:placetype":"venue"
},
  "geometry": {"coordinates":[9.150016,45.47084],"type":"Point"}
}