{
  "type": "Feature",
  "properties": {
    "addr:full":"Via Vendipiano 98070 Longi Longi Messina 98070",
    "addr:postcode":"98070;98070",
    "addr:street":"Via Vendipiano",
    "iso:country":"IT",
    "sg:address":"Via Vendipiano 98070 Longi",
    "sg:city":"Longi",
    "sg:classifiers":[
        {
            "category":"Real Estate",
            "subcategory":"Architect",
            "type":"Services"
        }
    ],
    "sg:phone":"+39 0941 485083",
    "sg:postcode":"98070",
    "sg:province":"Messina",
    "sg:tags":[
        "textile",
        "clothing"
    ],
    "wof:name":"Edelina Castano Srl",
    "wof:placetype":"venue"
},
  "geometry": {"coordinates":[14.753284,38.028618],"type":"Point"}
}