{
  "type": "Feature",
  "properties": {
    "iso:country":"IT",
    "sg:address":"Via Monte Castello 53 13037 Serravalle Sesia",
    "sg:city":"Serravalle Sesia",
    "sg:classifiers":[
        {
            "category":"Building & Trades",
            "subcategory":"Construction",
            "type":"Services"
        }
    ],
    "sg:phone":"+39 0163 452600",
    "sg:postcode":"13037",
    "sg:province":"Vercelli",
    "sg:tags":[
        "valve"
    ],
    "sg:website":"www.mival.it",
    "wof:name":"Mival Srl",
    "wof:placetype":"venue"
},
  "geometry": {"coordinates":[8.426394,45.32106],"type":"Point"}
}