{
  "type": "Feature",
  "properties": {
    "addr:full":"27, Viale Enrico Mattei 24060 Entratico Entratico Bergamo 24060",
    "addr:housenumber":"27",
    "addr:postcode":"24060;24060",
    "addr:street":"Viale Enrico Mattei",
    "iso:country":"IT",
    "sg:address":"27, Viale Enrico Mattei 24060 Entratico",
    "sg:city":"Entratico",
    "sg:classifiers":[
        {
            "category":"Real Estate",
            "subcategory":"Architect",
            "type":"Services"
        }
    ],
    "sg:phone":"+39 39035945420",
    "sg:postcode":"24060",
    "sg:province":"Bergamo",
    "sg:tags":[
        "textile",
        "clothing"
    ],
    "wof:name":"I Pinco Pallino S.p.a.",
    "wof:placetype":"venue"
},
  "geometry": {"coordinates":[9.8654928207,45.7049713135],"type":"Point"}
}