{
  "type": "Feature",
  "properties": {
    "addr:full":"16145 Genova Genova Genova 16145",
    "addr:postcode":"16145;16145",
    "iso:country":"IT",
    "sg:address":"16145 Genova",
    "sg:city":"Genova",
    "sg:orig_category":"Pubblica Amministrazione",
    "sg:phone":"+39 010 315046",
    "sg:postcode":"16145",
    "sg:province":"Genova",
    "wof:name":"C.i.f. Regionale",
    "wof:placetype":"venue"
},
  "geometry": {"coordinates":[8.9593353271,44.3953933716],"type":"Point"}
}