{
  "type": "Feature",
  "properties": {
    "addr:full":"171, V. Roma 80040 Poggiomarino Poggiomarino Napoli 80040",
    "addr:housenumber":"171",
    "addr:postcode":"80040;80040",
    "addr:street":"V. Roma",
    "iso:country":"IT",
    "sg:address":"171, V. Roma 80040 Poggiomarino",
    "sg:city":"Poggiomarino",
    "sg:classifiers":[
        {
            "category":"Shopping",
            "subcategory":"Crafts & Fabrics",
            "type":"Retail Goods"
        }
    ],
    "sg:phone":"+39 081 865 1993",
    "sg:postcode":"80040",
    "sg:province":"Napoli",
    "sg:tags":[
        "linen"
    ],
    "sg:website":"http://www.paginegialle.it/bemar-02",
    "wof:name":"Bemar Srl",
    "wof:placetype":"venue"
},
  "geometry": {"coordinates":[14.5739526749,40.8132591248],"type":"Point"}
}