{
  "type": "Feature",
  "properties": {
    "iso:country":"IT",
    "sg:address":"00185 Roma",
    "sg:city":"Roma",
    "sg:orig_category":"Servizi Per Lo Sport E Il Tempo Libero. Servizi Al Turismo",
    "sg:phone":"+39 06 445 0872",
    "sg:postcode":"00185",
    "sg:province":"Roma",
    "wof:name":"Lupi Sergio",
    "wof:placetype":"venue"
},
  "geometry": {"coordinates":[12.505733,41.905514],"type":"Point"}
}