{
  "type": "Feature",
  "properties": {
    "iso:country":"IT",
    "sg:address":"00144 Roma",
    "sg:city":"Roma",
    "sg:orig_category":"Servizi Al Turismo. Trasporto Pubblico E Privato",
    "sg:phone":"+39 06 591 2890",
    "sg:postcode":"00144",
    "sg:province":"Roma",
    "wof:name":"Vemar Srl",
    "wof:placetype":"venue"
},
  "geometry": {"coordinates":[12.473068,41.823086],"type":"Point"}
}