{
  "type": "Feature",
  "properties": {
    "iso:country":"IT",
    "sg:address":"41043 Formigine",
    "sg:city":"Formigine",
    "sg:orig_category":"Elettromeccanica",
    "sg:phone":"+39 059 570708",
    "sg:postcode":"41043",
    "sg:province":"Modena",
    "wof:name":"Cablocavi Srl",
    "wof:placetype":"venue"
},
  "geometry": {"coordinates":[10.854124,44.560726],"type":"Point"}
}