{
  "type": "Feature",
  "properties": {
    "addr:full":"27020 Dorno Dorno Pavia 27020",
    "addr:postcode":"27020;27020",
    "iso:country":"IT",
    "sg:address":"27020 Dorno",
    "sg:city":"Dorno",
    "sg:orig_category":"Servizi Per Lo Sport E Il Tempo Libero. Servizi Al Turismo. Acqua, Luce, Gas E Societa' Di Esercizio Pubblico",
    "sg:phone":"+39 0382 84054",
    "sg:postcode":"27020",
    "sg:province":"Pavia",
    "wof:name":"Riserva Di Caccia Boschetto",
    "wof:placetype":"venue"
},
  "geometry": {"coordinates":[8.937056,45.159222],"type":"Point"}
}