{
  "type": "Feature",
  "properties": {
    "iso:country":"IT",
    "sg:address":"50014 Fiesole",
    "sg:city":"Fiesole",
    "sg:orig_category":"Petroli, Gas E Combustibili",
    "sg:phone":"+39 055 59492",
    "sg:postcode":"50014",
    "sg:province":"Firenze",
    "wof:name":"Travelli Egisto",
    "wof:placetype":"venue"
},
  "geometry": {"coordinates":[11.3014936447,43.8074073792],"type":"Point"}
}