{
  "type": "Feature",
  "properties": {
    "iso:country":"IT",
    "sg:address":"14, V. Artigiana 25030 Torbiato Di Adro",
    "sg:city":"Adro",
    "sg:classifiers":[
        {
            "category":"Sports & Exercise",
            "subcategory":"Playing Field",
            "type":"Entertainment"
        }
    ],
    "sg:phone":"+39 030 745 0700",
    "sg:postcode":"25030",
    "sg:province":"Brescia",
    "sg:tags":[
        "game"
    ],
    "sg:website":"http://www.brestil.it",
    "wof:name":"Brestil Srl",
    "wof:placetype":"venue"
},
  "geometry": {"coordinates":[10.222958,45.539829],"type":"Point"}
}