{
  "type": "Feature",
  "properties": {
    "iso:country":"IT",
    "sg:address":"35010 San Giorgio In Bosco",
    "sg:city":"San Giorgio in Bosco",
    "sg:orig_category":"Audiovisivi Filmati, Spot E Multimediali - Realizzazione E Duplicazione",
    "sg:phone":"+39 049 945 0784",
    "sg:postcode":"35010",
    "sg:province":"Padova",
    "wof:name":"Eos Comunicazione Srl",
    "wof:placetype":"venue"
},
  "geometry": {"coordinates":[11.656878,44.977913],"type":"Point"}
}