{
  "type": "Feature",
  "properties": {
    "iso:country":"IT",
    "sg:address":"62029 Tolentino",
    "sg:city":"Tolentino",
    "sg:orig_category":"Alberghi E Strutture Extra Alberghiere. Servizi Per Aziende, Manifestazioni E Supporto Agli Scambi Commerciali",
    "sg:phone":"+39 0733 201049",
    "sg:postcode":"62029",
    "sg:province":"Macerata",
    "wof:name":"Fondazione Giustiniani Bandini",
    "wof:placetype":"venue"
},
  "geometry": {"coordinates":[13.402905,43.221031],"type":"Point"}
}