{
  "type": "Feature",
  "properties": {
    "addr:full":"20090 Vimodrone Vimodrone Milano 20090",
    "addr:postcode":"20090;20090",
    "iso:country":"IT",
    "sg:address":"20090 Vimodrone",
    "sg:city":"Vimodrone",
    "sg:orig_category":"Forniture Alle Strutture Ricettive. Macchine E Impianti Per Attivita' Commerciali Ed Artigianali",
    "sg:phone":"+39 02 250 2030",
    "sg:postcode":"20090",
    "sg:province":"Milano",
    "wof:name":"Eurobar (s.r.l.)",
    "wof:placetype":"venue"
},
  "geometry": {"coordinates":[9.2739810944,45.5142822266],"type":"Point"}
}