{
  "type": "Feature",
  "properties": {
    "iso:country":"IT",
    "sg:address":"22012 Cernobbio",
    "sg:city":"Cernobbio",
    "sg:orig_category":"Servizi E Lavori Per Abbigliamento E Pelletterie",
    "sg:phone":"+39 031 510021",
    "sg:postcode":"22012",
    "sg:province":"Como",
    "wof:name":"Sala Loredana",
    "wof:placetype":"venue"
},
  "geometry": {"coordinates":[9.077407,45.842026],"type":"Point"}
}