{
  "type": "Feature",
  "properties": {
    "iso:country":"IT",
    "sg:address":"Via Paolo Ercole 37; Felizzano; 15023",
    "sg:city":"Felizzano",
    "sg:classifiers":[
        {
            "category":"Banks & Credit Unions",
            "subcategory":"Bank",
            "type":"Services"
        }
    ],
    "sg:phone":"+39 0131 772698",
    "sg:postcode":"15023",
    "sg:province":"Alessandria",
    "wof:name":"Istituto Bancario, San Paolo Di Torino Spa",
    "wof:placetype":"venue"
},
  "geometry": {"coordinates":[8.436849,44.898319],"type":"Point"}
}