{
  "type": "Feature",
  "properties": {
    "iso:country":"IT",
    "sg:address":"95030 Gravina Di Catania",
    "sg:city":"Gravina di Catania",
    "sg:orig_category":"Forniture Ospedaliere",
    "sg:phone":"+39 095 243526",
    "sg:postcode":"95030",
    "sg:province":"Catania",
    "wof:name":"Promex Srl",
    "wof:placetype":"venue"
},
  "geometry": {"coordinates":[15.0664596558,37.5441207886],"type":"Point"}
}