{
  "type": "Feature",
  "properties": {
    "iso:country":"IT",
    "sg:address":"00197 Roma",
    "sg:city":"Roma",
    "sg:orig_category":"Banche E Servizi Finanziari",
    "sg:phone":"+39 06 8069 0017",
    "sg:postcode":"00197",
    "sg:province":"Roma",
    "wof:name":"Ugolini Roberto",
    "wof:placetype":"venue"
},
  "geometry": {"coordinates":[12.486273,41.927635],"type":"Point"}
}