{
  "type": "Feature",
  "properties": {
    "addr:full":"15062 Bosco Marengo Bosco Marengo Alessandria 15062",
    "addr:postcode":"15062;15062",
    "iso:country":"IT",
    "sg:address":"15062 Bosco Marengo",
    "sg:city":"Bosco Marengo",
    "sg:orig_category":"Abiti Da Sposa E Cerimonia",
    "sg:phone":"+39 0131 298162",
    "sg:postcode":"15062",
    "sg:province":"Alessandria",
    "sg:website":"http://www.erossposi.it",
    "wof:name":"Eros Di Ponzano Vincenzo R. & C. Snc",
    "wof:placetype":"venue"
},
  "geometry": {"coordinates":[8.736715,44.834824],"type":"Point"}
}