{
  "type": "Feature",
  "properties": {
    "addr:full":"00196 Roma Roma Roma 00196",
    "addr:postcode":"00196;00196",
    "iso:country":"IT",
    "sg:address":"00196 Roma",
    "sg:city":"Roma",
    "sg:orig_category":"Elettronica Professionale E Di Consumo. Tempo Libero - Articoli E Forniture",
    "sg:phone":"+39 06 361 1585",
    "sg:postcode":"00196",
    "sg:province":"Roma",
    "wof:name":"Prisco Edoardo",
    "wof:placetype":"venue"
},
  "geometry": {"coordinates":[12.475513,41.912525],"type":"Point"}
}