{
  "type": "Feature",
  "properties": {
    "iso:country":"IT",
    "sg:address":"34, Via Eugubina 06022 Fossato Di Vico",
    "sg:city":"Fossato di Vico",
    "sg:classifiers":[
        {
            "category":"Shopping",
            "subcategory":"Crafts & Fabrics",
            "type":"Retail Goods"
        }
    ],
    "sg:phone":"+39 39075919621",
    "sg:postcode":"06022",
    "sg:province":"Perugia",
    "sg:tags":[
        "ceramic"
    ],
    "wof:name":"Wald (s.r.l.)",
    "wof:placetype":"venue"
},
  "geometry": {"coordinates":[12.746717,43.290821],"type":"Point"}
}