{
  "type": "Feature",
  "properties": {
    "addr:full":"35, Via Biban 31030 Carbonera Carbonera Treviso 31030",
    "addr:postcode":"31030;31030",
    "addr:street":"Via Biban",
    "iso:country":"IT",
    "sg:address":"35, Via Biban 31030 Carbonera",
    "sg:city":"Carbonera",
    "sg:classifiers":[
        {
            "category":"Manufacturing",
            "subcategory":"Rubber & Plastics",
            "type":"Manufacturing & Wholesale Goods"
        }
    ],
    "sg:phone":"+39 0422 445459",
    "sg:postcode":"31030",
    "sg:province":"Treviso",
    "wof:name":"Cartoplastica (s.r.l.)",
    "wof:placetype":"venue"
},
  "geometry": {"coordinates":[12.2812385559,45.6913871765],"type":"Point"}
}