{
  "type": "Feature",
  "properties": {
    "addr:full":"Via Bonzanini 25 37058 Sanguinetto Sanguinetto Verona 37058",
    "addr:housenumber":"25",
    "addr:postcode":"37058;37058",
    "addr:street":"Via Bonzanini",
    "iso:country":"IT",
    "sg:address":"Via Bonzanini 25 37058 Sanguinetto",
    "sg:city":"Sanguinetto",
    "sg:classifiers":[
        {
            "category":"Home & Garden",
            "subcategory":"Home Furnishings",
            "type":"Retail Goods"
        }
    ],
    "sg:phone":"+39 0442 398511",
    "sg:postcode":"37058",
    "sg:province":"Verona",
    "sg:tags":[
        "premise"
    ],
    "sg:website":"www.mobilbracco.it",
    "wof:name":"Mobilbracco Srl",
    "wof:placetype":"venue"
},
  "geometry": {"coordinates":[11.1593770981,45.1644821167],"type":"Point"}
}