{
  "type": "Feature",
  "properties": {
    "addr:full":"16, Via Marco Polo Ca' Vio 30010 Cavallino - Treporti Venezia 30010",
    "addr:postcode":"30010;30010",
    "addr:street":"Via Marco Polo Ca ' Vio",
    "iso:country":"IT",
    "sg:address":"16, Via Marco Polo Ca' Vio 30010 Cavallino - Treporti",
    "sg:classifiers":[
        {
            "category":"Professional",
            "subcategory":"Engineering",
            "type":"Services"
        }
    ],
    "sg:phone":"+39 39041966034",
    "sg:postcode":"30010",
    "sg:province":"Venezia",
    "sg:tags":[
        "machine",
        "-",
        "mechanical"
    ],
    "wof:name":"Bacciolo Gelsomino & Figli Srl",
    "wof:placetype":"venue"
},
  "geometry": {"coordinates":[12.338784,45.434338],"type":"Point"}
}