{
  "type": "Feature",
  "properties": {
    "addr:full":"10023 Chieri Chieri Torino 10023",
    "addr:postcode":"10023;10023",
    "iso:country":"IT",
    "sg:address":"10023 Chieri",
    "sg:city":"Chieri",
    "sg:orig_category":"Forniture Per Abbigliamento E Pelletterie. Complementi Di Arredamento",
    "sg:phone":"+39 011 942 2460",
    "sg:postcode":"10023",
    "sg:province":"Torino",
    "wof:name":"Ar.na(s.n.c.)",
    "wof:placetype":"venue"
},
  "geometry": {"coordinates":[7.8025064468,45.0258827209],"type":"Point"}
}