{
  "type": "Feature",
  "properties": {
    "iso:country":"IT",
    "sg:address":"70043 Monopoli",
    "sg:city":"Monopoli",
    "sg:orig_category":"Prodotti Vari In Metallo. Articoli Per Imballaggio E Confezionamento",
    "sg:phone":"+39 080 887 2977",
    "sg:postcode":"70043",
    "sg:province":"Bari",
    "wof:name":"Rotondo Antonio",
    "wof:placetype":"venue"
},
  "geometry": {"coordinates":[17.2666397095,40.905090332],"type":"Point"}
}