{
  "type": "Feature",
  "properties": {
    "addr:full":"95121 Catania Catania Catania 95121",
    "addr:postcode":"95121;95121",
    "iso:country":"IT",
    "sg:address":"95121 Catania",
    "sg:city":"Catania",
    "sg:orig_category":"Caccia E Pesca Articoli - Produzione E Ingrosso",
    "sg:phone":"+39 095 345670",
    "sg:postcode":"95121",
    "sg:province":"Catania",
    "wof:name":"Milone Matteo",
    "wof:placetype":"venue"
},
  "geometry": {"coordinates":[15.106206,37.543999],"type":"Point"}
}