{
  "type": "Feature",
  "properties": {
    "iso:country":"IT",
    "sg:address":"109, Via Caraglio 10141 Torino",
    "sg:city":"Torino",
    "sg:classifiers":[
        {
            "category":"Shopping",
            "type":"Retail Goods"
        }
    ],
    "sg:phone":"+39 39011331886",
    "sg:postcode":"10141",
    "sg:province":"Torino",
    "sg:tags":[
        "finished",
        "-",
        "metallic"
    ],
    "wof:name":"Punto 73 (s.r.l.)",
    "wof:placetype":"venue"
},
  "geometry": {"coordinates":[7.6419897079,45.0581626892],"type":"Point"}
}