{
  "type": "Feature",
  "properties": {
    "addr:full":"7, Via Degli Artigiani 31035 Crocetta Del Montello Crocetta del Montello Treviso 31035",
    "addr:postcode":"31035;31035",
    "addr:street":"Via Degli Artigiani",
    "iso:country":"IT",
    "sg:address":"7, Via Degli Artigiani 31035 Crocetta Del Montello",
    "sg:city":"Crocetta del Montello",
    "sg:classifiers":[
        {
            "category":"Manufacturing",
            "subcategory":"Metals",
            "type":"Manufacturing & Wholesale Goods"
        }
    ],
    "sg:phone":"+39 390 423 8228",
    "sg:postcode":"31035",
    "sg:province":"Treviso",
    "sg:tags":[
        "processing"
    ],
    "wof:name":"Everest S.p.a.",
    "wof:placetype":"venue"
},
  "geometry": {"coordinates":[12.025387764,45.8128700256],"type":"Point"}
}