{
  "type": "Feature",
  "properties": {
    "addr:full":"06100 Perugia PG",
    "addr:postcode":"06100",
    "addr:street":"Pg",
    "iso:country":"IT",
    "sg:address":"06100 Perugia",
    "sg:orig_category":"Legno E Semilavorati. Manufatti Edili E Prefabbricati",
    "sg:phone":"+39 075 514 9064",
    "sg:province":"PG",
    "wof:name":"Cml Srl",
    "wof:placetype":"venue"
},
  "geometry": {"coordinates":[12.330222,43.052582],"type":"Point"}
}