{
  "type": "Feature",
  "properties": {
    "iso:country":"IT",
    "sg:address":"145, C. Freda 81030 Cellole",
    "sg:city":"Cellole",
    "sg:classifiers":[
        {
            "category":"Sports & Exercise",
            "subcategory":"Playing Field",
            "type":"Entertainment"
        }
    ],
    "sg:postcode":"81030",
    "sg:province":"Caserta",
    "sg:tags":[
        "game"
    ],
    "sg:website":"http://www.paginegialle.it/",
    "wof:name":"Unlikesun Di Taka'cs Eloise",
    "wof:placetype":"venue"
},
  "geometry": {"coordinates":[13.855331,41.204876],"type":"Point"}
}