{
  "type": "Feature",
  "properties": {
    "iso:country":"IT",
    "sg:address":"80030 Liveri",
    "sg:city":"Liveri",
    "sg:orig_category":"Prodotti Chimici Di Base. Forniture Per Attivita' Industriali",
    "sg:phone":"+39 081 825 5259",
    "sg:postcode":"80030",
    "sg:province":"Napoli",
    "wof:name":"Bellomo Oscar Cereria",
    "wof:placetype":"venue"
},
  "geometry": {"coordinates":[14.2739524841,40.8561706543],"type":"Point"}
}