{
  "type": "Feature",
  "properties": {
    "iso:country":"IT",
    "sg:address":"73020 Cursi",
    "sg:city":"Cursi",
    "sg:orig_category":"Marmo, Pietre Ed Affini",
    "sg:phone":"+39 0836 421375",
    "sg:postcode":"73020",
    "sg:province":"Lecce",
    "wof:name":"F. Lli Pitardi Di Benito Ed Egidio Snc",
    "wof:placetype":"venue"
},
  "geometry": {"coordinates":[18.336189,40.193462],"type":"Point"}
}