{
  "type": "Feature",
  "properties": {
    "addr:full":"53036 Poggibonsi Poggibonsi Siena 53036",
    "addr:postcode":"53036;53036",
    "iso:country":"IT",
    "sg:address":"53036 Poggibonsi",
    "sg:city":"Poggibonsi",
    "sg:orig_category":"Materiali E Componenti Elettrotecnici. Elettrotecnica Industriale, Prodotti E Apparecchiature",
    "sg:phone":"+39 0577 979681",
    "sg:postcode":"53036",
    "sg:province":"Siena",
    "wof:name":"Newton Industrie Trasformatori Srl",
    "wof:placetype":"venue"
},
  "geometry": {"coordinates":[11.184389,43.452106],"type":"Point"}
}