{
  "type": "Feature",
  "properties": {
    "iso:country":"IT",
    "sg:address":"Via Felice Cavalloti 5; Monza; 20052",
    "sg:city":"Monza",
    "sg:classifiers":[
        {
            "category":"Banks & Credit Unions",
            "subcategory":"Bank",
            "type":"Services"
        }
    ],
    "sg:phone":"+39 039 73931",
    "sg:postcode":"20052",
    "sg:province":"Milano",
    "wof:name":"Banca Commerciale Italiana Spa",
    "wof:placetype":"venue"
},
  "geometry": {"coordinates":[9.270881,45.582134],"type":"Point"}
}