{
  "type": "Feature",
  "properties": {
    "iso:country":"IT",
    "sg:address":"61100 Pesaro",
    "sg:city":"Pesaro",
    "sg:orig_category":"Medicali Ed Elettromedicali Impianti Ed Apparecchi - Produzione",
    "sg:phone":"+39 0721 21888",
    "sg:postcode":"61100",
    "sg:province":"Pesaro E Urbino",
    "wof:name":"Salus And Beauty Di Bonazzelli G. & C. Sas",
    "wof:placetype":"venue"
},
  "geometry": {"coordinates":[12.901795,43.91259],"type":"Point"}
}