{
  "type": "Feature",
  "properties": {
    "iso:country":"IT",
    "sg:address":"25049 Iseo",
    "sg:city":"Iseo",
    "sg:orig_category":"Servizi Per Aziende, Manifestazioni E Supporto Agli Scambi Commerciali",
    "sg:phone":"+39 030 9822 2231",
    "sg:postcode":"25049",
    "sg:province":"Brescia",
    "wof:name":"Consoli Pier Luigi",
    "wof:placetype":"venue"
},
  "geometry": {"coordinates":[10.064176,45.628212],"type":"Point"}
}