{
  "type": "Feature",
  "properties": {
    "iso:country":"IT",
    "sg:address":"57122 Livorno",
    "sg:city":"Livorno",
    "sg:orig_category":"Serramenti Ed Infissi",
    "sg:phone":"+39 0586 410598",
    "sg:postcode":"57122",
    "sg:province":"Livorno",
    "wof:name":"Lepori Srl",
    "wof:placetype":"venue"
},
  "geometry": {"coordinates":[10.322499,43.561913],"type":"Point"}
}