{
  "type": "Feature",
  "properties": {
    "addr:full":"50123 Firenze Firenze Firenze 50123",
    "addr:postcode":"50123;50123",
    "iso:country":"IT",
    "sg:address":"50123 Firenze",
    "sg:city":"Firenze",
    "sg:orig_category":"Ospedali E Servizi Sanitari. Servizi Sociali. Associazioni Ed Organismi Di Interesse Pubblico",
    "sg:phone":"+39 055 27921",
    "sg:postcode":"50123",
    "sg:province":"Firenze",
    "wof:name":"Lega Regionale Toscana Cooperative E Mutue",
    "wof:placetype":"venue"
},
  "geometry": {"coordinates":[11.249545,43.775291],"type":"Point"}
}