{
  "type": "Feature",
  "properties": {
    "addr:full":"Piazza Mercanzia 4 - Pal. Mercanzia; Bologna; 40125 Bologna Bologna 40125",
    "addr:housenumber":"4",
    "addr:postcode":"40125;40125",
    "addr:street":"Piazza Mercanzia;Mercanzia",
    "iso:country":"IT",
    "sg:address":"Piazza Mercanzia 4 - Pal. Mercanzia; Bologna; 40125",
    "sg:city":"Bologna",
    "sg:classifiers":[
        {
            "category":"Shopping",
            "subcategory":"Computers & Home Electronics",
            "type":"Retail Goods"
        }
    ],
    "sg:postcode":"40125",
    "sg:province":"Bologna",
    "sg:tags":[
        "chamber",
        "commerce"
    ],
    "sg:website":"www.bo.camcom.it",
    "wof:name":"Bologna Chamber Of Commerce And Industry",
    "wof:placetype":"venue"
},
  "geometry": {"coordinates":[11.352383,44.491131],"type":"Point"}
}