{
  "type": "Feature",
  "properties": {
    "addr:full":"35131 Padova Padova Padova 35131",
    "addr:postcode":"35131;35131",
    "iso:country":"IT",
    "sg:address":"35131 Padova",
    "sg:city":"Padova",
    "sg:orig_category":"Ristorazione E Locali Pubblici Affini. Servizi Per Lo Sport E Il Tempo Libero. Alberghi E Strutture Extra Alberghiere. Ristoranti Ed Esercizi Affini",
    "sg:phone":"+39 049 877 6322",
    "sg:postcode":"35131",
    "sg:province":"Padova",
    "sg:website":"http://www.inforjob.it",
    "wof:name":"Le Mille & Una Casa \u00ae Srl",
    "wof:placetype":"venue"
},
  "geometry": {"coordinates":[11.892819,45.413452],"type":"Point"}
}