{
  "type": "Feature",
  "properties": {
    "addr:full":"20056 Trezzo Sull'adda Milano 20056",
    "addr:postcode":"20056;20056",
    "iso:country":"IT",
    "sg:address":"20056 Trezzo Sull'adda",
    "sg:orig_category":"Elettrotecnica Professionale E Di Consumo. Forniture Per Attivita' Commerciali Ed Artigianali",
    "sg:phone":"+39 02 909 3681",
    "sg:postcode":"20056",
    "sg:province":"Milano",
    "sg:website":"http://www.visualcolor.it",
    "wof:name":"Visualcolor Snc Di Delucchi E Valtorta",
    "wof:placetype":"venue"
},
  "geometry": {"coordinates":[9.507312,45.598961],"type":"Point"}
}