{
  "type": "Feature",
  "properties": {
    "iso:country":"IT",
    "sg:address":"Str. St. 106 88817 Torre Melissa",
    "sg:classifiers":[
        {
            "category":"Real Estate",
            "subcategory":"Surveying",
            "type":"Services"
        }
    ],
    "sg:phone":"+39 0962 865184",
    "sg:postcode":"88817",
    "sg:province":"Crotone",
    "sg:tags":[
        "equipment",
        "material",
        "good",
        "-",
        "handling"
    ],
    "sg:website":"http://www.paginegialle.it/defrancescovittoria",
    "wof:name":"De Francesco Vittoria",
    "wof:placetype":"venue"
},
  "geometry": {"coordinates":[17.127079,39.080738],"type":"Point"}
}