{
  "type": "Feature",
  "properties": {
    "iso:country":"IT",
    "sg:address":"10, Via Filodrammatici 20121 Milano",
    "sg:city":"Milano",
    "sg:classifiers":[
        {
            "category":"Banks & Credit Unions",
            "subcategory":"Bank",
            "type":"Services"
        }
    ],
    "sg:phone":"+39 39800445577",
    "sg:postcode":"20121",
    "sg:province":"Milano",
    "sg:tags":[
        "banking",
        "institution"
    ],
    "wof:name":"Mediobanca Spa",
    "wof:placetype":"venue"
},
  "geometry": {"coordinates":[9.187983,45.467617],"type":"Point"}
}