{
  "type": "Feature",
  "properties": {
    "iso:country":"IT",
    "sg:address":"10, Via Primo Maggio 25035 Ospitaletto",
    "sg:city":"Ospitaletto",
    "sg:classifiers":[
        {
            "category":"Manufacturing",
            "subcategory":"Metals",
            "type":"Manufacturing & Wholesale Goods"
        }
    ],
    "sg:phone":"+39 39030641182",
    "sg:postcode":"25035",
    "sg:province":"Brescia",
    "sg:tags":[
        "processing"
    ],
    "wof:name":"Bertoletti Meccanica S.r.l.",
    "wof:placetype":"venue"
},
  "geometry": {"coordinates":[10.1140289307,45.5588874817],"type":"Point"}
}