{
  "type": "Feature",
  "properties": {
    "iso:country":"IT",
    "sg:address":"3, Strada Romana Nord 46027 San Benedetto Po",
    "sg:city":"San Benedetto Po",
    "sg:classifiers":[
        {
            "category":"Manufacturing",
            "subcategory":"Rubber & Plastics",
            "type":"Manufacturing & Wholesale Goods"
        }
    ],
    "sg:phone":"+39 0376 620746",
    "sg:postcode":"46027",
    "sg:province":"Mantova",
    "wof:name":"Poliplast Di Maduzzi Gianni E C. Snc",
    "wof:placetype":"venue"
},
  "geometry": {"coordinates":[10.9302148819,45.0522499084],"type":"Point"}
}