{
  "type": "Feature",
  "properties": {
    "iso:country":"IT",
    "sg:address":"23900 Lecco",
    "sg:city":"Lecco",
    "sg:orig_category":"Utensili Meccanici E Materiali",
    "sg:phone":"+39 0341 283543",
    "sg:postcode":"23900",
    "sg:province":"Lecco",
    "sg:website":"http://www.theinternationalagency.com",
    "wof:name":"Simone - Kramer Badoni",
    "wof:placetype":"venue"
},
  "geometry": {"coordinates":[9.397378,45.859402],"type":"Point"}
}