{
  "type": "Feature",
  "properties": {
    "addr:full":"81020 San Marco Evangelista San Marco Evangelista Caserta 81020",
    "addr:housenumber":"81020",
    "addr:postcode":"81020",
    "addr:street":"San",
    "iso:country":"IT",
    "sg:address":"81020 San Marco Evangelista",
    "sg:city":"San Marco Evangelista",
    "sg:orig_category":"Macchine, Impianti Ed Attrezzature Per Industria Alimentare E Bevande",
    "sg:phone":"+39 0823 452240",
    "sg:postcode":"81020",
    "sg:province":"Caserta",
    "wof:name":"Gel Up Snc",
    "wof:placetype":"venue"
},
  "geometry": {"coordinates":[14.329155,41.036995],"type":"Point"}
}