{
  "type": "Feature",
  "properties": {
    "addr:full":"40055 Castenaso Castenaso Bologna 40055",
    "addr:postcode":"40055;40055",
    "iso:country":"IT",
    "sg:address":"40055 Castenaso",
    "sg:city":"Castenaso",
    "sg:orig_category":"Apparecchiature Ed Attrezzature Meccaniche",
    "sg:phone":"+39 051 780081",
    "sg:postcode":"40055",
    "sg:province":"Bologna",
    "sg:website":"http://www.cedit.it",
    "wof:name":"Cedit Srl",
    "wof:placetype":"venue"
},
  "geometry": {"coordinates":[11.444955,44.502689],"type":"Point"}
}