{
  "type": "Feature",
  "properties": {
    "iso:country":"IT",
    "sg:address":"Via Santa Margherita 123 20047 Brugherio",
    "sg:city":"Brugherio",
    "sg:classifiers":[
        {
            "category":"Manufacturing",
            "subcategory":"Motor Vehicles & Parts",
            "type":"Manufacturing & Wholesale Goods"
        }
    ],
    "sg:phone":"+39 039 28901",
    "sg:postcode":"20047",
    "sg:province":"Milano",
    "sg:tags":[
        "pneumatic",
        "component",
        "accessory"
    ],
    "sg:website":"www.ape-automazione.it",
    "wof:name":"Ape Automazione Srl",
    "wof:placetype":"venue"
},
  "geometry": {"coordinates":[9.2799,45.527004],"type":"Point"}
}