{
  "type": "Feature",
  "properties": {
    "iso:country":"IT",
    "sg:address":"91011 Alcamo",
    "sg:city":"Alcamo",
    "sg:orig_category":"Condizionamento Aria Impianti - Installazione E Manutenzione",
    "sg:phone":"+39 0924 514568",
    "sg:postcode":"91011",
    "sg:province":"Trapani",
    "wof:name":"Elettrica Di Coraci Vincenzo",
    "wof:placetype":"venue"
},
  "geometry": {"coordinates":[12.966582,37.954071],"type":"Point"}
}