{
  "type": "Feature",
  "properties": {
    "iso:country":"IT",
    "sg:address":"21013 Gallarate",
    "sg:city":"Gallarate",
    "sg:orig_category":"Macchine, Impianti Ed Attrezzature Per Abbigliamento E Pelletterie",
    "sg:phone":"+39 0331 797550",
    "sg:postcode":"21013",
    "sg:province":"Varese",
    "wof:name":"Tomasi Renato",
    "wof:placetype":"venue"
},
  "geometry": {"coordinates":[8.994537,45.634224],"type":"Point"}
}