{
  "type": "Feature",
  "properties": {
    "iso:country":"IT",
    "sg:address":"Via Giacomo Brodolini, 25/27 20054 Nova Milanese",
    "sg:city":"Nova Milanese",
    "sg:classifiers":[
        {
            "category":"Shopping",
            "subcategory":"Stationery & Office Supplies",
            "type":"Retail Goods"
        }
    ],
    "sg:phone":"+39 036 236 8510",
    "sg:postcode":"20054",
    "sg:province":"Milano",
    "sg:tags":[
        "furniture"
    ],
    "sg:website":"www.caimi.com",
    "wof:name":"Caimi Brevetti Spa",
    "wof:placetype":"venue"
},
  "geometry": {"coordinates":[9.188141,45.463688],"type":"Point"}
}