{
  "type": "Feature",
  "properties": {
    "iso:country":"IT",
    "sg:address":"Strada Vicinale Dell' Osteria 06073 Corciano",
    "sg:city":"Corciano",
    "sg:classifiers":[
        {
            "category":"Travel",
            "subcategory":"Travel Agent",
            "type":"Entertainment"
        }
    ],
    "sg:phone":"+39 075 697 8464",
    "sg:postcode":"06073",
    "sg:province":"Perugia",
    "sg:tags":[
        "business"
    ],
    "wof:name":"El Patio (s.n.c.)",
    "wof:placetype":"venue"
},
  "geometry": {"coordinates":[12.389172,43.110703],"type":"Point"}
}