{
  "type": "Feature",
  "properties": {
    "iso:country":"IT",
    "sg:address":"66034 Lanciano",
    "sg:city":"Lanciano",
    "sg:orig_category":"Macchine, Impianti Ed Attrezzature Per Industria Alimentare E Bevande",
    "sg:phone":"+39 0872 710401",
    "sg:postcode":"66034",
    "sg:province":"Chieti",
    "wof:name":"Nasuti Mario",
    "wof:placetype":"venue"
},
  "geometry": {"coordinates":[14.353493,42.232113],"type":"Point"}
}