{
  "type": "Feature",
  "properties": {
    "iso:country":"IT",
    "sg:address":"41043 Formigine",
    "sg:city":"Formigine",
    "sg:orig_category":"Prodotti Finiti Stampati. Forniture Per Attivita' Commerciali Ed Artigianali",
    "sg:phone":"+39 059 570595",
    "sg:postcode":"41043",
    "sg:province":"Modena",
    "wof:name":"Mondialker Italia S.r.l.",
    "wof:placetype":"venue"
},
  "geometry": {"coordinates":[10.8442077637,44.5602264404],"type":"Point"}
}