{
  "type": "Feature",
  "properties": {
    "iso:country":"IT",
    "sg:address":"60022 Castelfidardo",
    "sg:city":"Castelfidardo",
    "sg:orig_category":"Musica",
    "sg:phone":"+39 071 782 2795",
    "sg:postcode":"60022",
    "sg:province":"Ancona",
    "wof:name":"Fisart Di Vignoni & Pigini",
    "wof:placetype":"venue"
},
  "geometry": {"coordinates":[13.5448656082,43.4960441589],"type":"Point"}
}