{
  "type": "Feature",
  "properties": {
    "addr:full":"20124 Milano Milano Milano 20124",
    "addr:postcode":"20124;20124",
    "iso:country":"IT",
    "sg:address":"20124 Milano",
    "sg:city":"Milano",
    "sg:orig_category":"Penne Stilografiche Ed Articoli Scrittura",
    "sg:phone":"+39 02 2940 5604",
    "sg:postcode":"20124",
    "sg:province":"Milano",
    "wof:name":"La Stilografica Srl",
    "wof:placetype":"venue"
},
  "geometry": {"coordinates":[9.2124538422,45.4818954468],"type":"Point"}
}