{
  "type": "Feature",
  "properties": {
    "addr:full":"56021 Cascina Cascina Pisa 56021",
    "addr:postcode":"56021;56021",
    "addr:street":"Cascina Pisa",
    "iso:country":"IT",
    "sg:address":"56021 Cascina",
    "sg:city":"Cascina",
    "sg:orig_category":"Forniture Per Abbigliamento E Pelletterie. Complementi Di Arredamento",
    "sg:phone":"+39 050 701523",
    "sg:postcode":"56021",
    "sg:province":"Pisa",
    "wof:name":"Caciagli Alessandro",
    "wof:placetype":"venue"
},
  "geometry": {"coordinates":[10.5345163345,43.6868858337],"type":"Point"}
}