{
  "type": "Feature",
  "properties": {
    "iso:country":"IT",
    "sg:address":"65121 Pescara",
    "sg:city":"Pescara",
    "sg:orig_category":"Forniture Per Attivita' Commerciali Ed Artigianali",
    "sg:phone":"+39 085 422 4088",
    "sg:postcode":"65121",
    "sg:province":"Pescara",
    "wof:name":"Incisoria Meccanica Abruzzese Di Di Silvestri Franco",
    "wof:placetype":"venue"
},
  "geometry": {"coordinates":[14.2142047882,42.466796875],"type":"Point"}
}