{
  "type": "Feature",
  "properties": {
    "iso:country":"IT",
    "sg:address":"51018 Pieve A Nievole",
    "sg:city":"Pieve a Nievole",
    "sg:orig_category":"Tipografie",
    "sg:phone":"+39 0572 954312",
    "sg:postcode":"51018",
    "sg:province":"Pistoia",
    "sg:website":"http://www.nuovoufficiostampa.it",
    "wof:name":"Nuovo Ufficio Stampa Di Sergio Grasso",
    "wof:placetype":"venue"
},
  "geometry": {"coordinates":[10.796816,43.882629],"type":"Point"}
}