{
  "type": "Feature",
  "properties": {
    "addr:full":"21040 Uboldo Uboldo Varese 21040",
    "addr:postcode":"21040;21040",
    "iso:country":"IT",
    "sg:address":"21040 Uboldo",
    "sg:city":"Uboldo",
    "sg:orig_category":"Motocicli E Motocarri Accessori E Parti - Produzione E Ingrosso",
    "sg:phone":"+39 02 9678 1170",
    "sg:postcode":"21040",
    "sg:province":"Varese",
    "wof:name":"Motortimes Srl",
    "wof:placetype":"venue"
},
  "geometry": {"coordinates":[9.0122480392,45.6162147522],"type":"Point"}
}