{
  "type": "Feature",
  "properties": {
    "iso:country":"IT",
    "sg:address":"10137 Torino",
    "sg:city":"Torino",
    "sg:orig_category":"Macchine, Impianti Ed Attrezzature Industria Chimica. Attrezzature E Forniture Per Officine Riparazione E Servizi Ausiliari",
    "sg:phone":"+39 011 301 2211",
    "sg:postcode":"10137",
    "sg:province":"Torino",
    "wof:name":"Abb Synergia S.r.l.",
    "wof:placetype":"venue"
},
  "geometry": {"coordinates":[7.592778,45.025333],"type":"Point"}
}