{
  "type": "Feature",
  "properties": {
    "addr:full":"Corso Roma 13; Montecatini; 51016 Pistoia 51016",
    "addr:housenumber":"13",
    "addr:postcode":"51016;51016",
    "addr:street":"Corso Roma",
    "iso:country":"IT",
    "sg:address":"Corso Roma 13; Montecatini; 51016",
    "sg:classifiers":[
        {
            "category":"Banks & Credit Unions",
            "subcategory":"Bank",
            "type":"Services"
        }
    ],
    "sg:phone":"+39 0572 70181",
    "sg:postcode":"51016",
    "sg:province":"Pistoia",
    "wof:name":"Banca Nazionale Del Lavoro Spa",
    "wof:placetype":"venue"
},
  "geometry": {"coordinates":[10.769795,43.883747],"type":"Point"}
}