{
  "type": "Feature",
  "properties": {
    "iso:country":"IT",
    "sg:address":"62010 Montefano",
    "sg:city":"Montefano",
    "sg:orig_category":"Abbigliamento Sportivo - Produzione E Ingrosso",
    "sg:phone":"+39 0737 850174",
    "sg:postcode":"62010",
    "sg:province":"Macerata",
    "wof:name":"Linea Luti Spa",
    "wof:placetype":"venue"
},
  "geometry": {"coordinates":[13.462263,43.357498],"type":"Point"}
}