{
  "type": "Feature",
  "properties": {
    "iso:country":"IT",
    "sg:address":"28100 Novara",
    "sg:city":"Novara",
    "sg:orig_category":"Lame Industriali",
    "sg:phone":"+39 0321 392255",
    "sg:postcode":"28100",
    "sg:province":"Novara",
    "wof:name":"Cecchetti Mirko",
    "wof:placetype":"venue"
},
  "geometry": {"coordinates":[8.604927,45.449795],"type":"Point"}
}