{
  "type": "Feature",
  "properties": {
    "addr:full":"Via E. Filiberto, 34; Padova; 35122 Padova Padova 35122",
    "addr:housenumber":"34",
    "addr:postcode":"35122;35122",
    "addr:street":"Via E. Filiberto",
    "iso:country":"IT",
    "sg:address":"Via E. Filiberto, 34; Padova; 35122",
    "sg:city":"Padova",
    "sg:classifiers":[
        {
            "category":"Shopping",
            "subcategory":"Computers & Home Electronics",
            "type":"Retail Goods"
        }
    ],
    "sg:phone":"+39 049 820 8111",
    "sg:postcode":"35122",
    "sg:province":"Padova",
    "sg:tags":[
        "chamber",
        "commerce"
    ],
    "sg:website":"www.pd.camcom.it",
    "wof:name":"Padova Chamber Of Commerce & Industry",
    "wof:placetype":"venue"
},
  "geometry": {"coordinates":[11.876138,45.409271],"type":"Point"}
}