{
  "type": "Feature",
  "properties": {
    "iso:country":"IT",
    "sg:address":"10127 Torino",
    "sg:city":"Torino",
    "sg:orig_category":"Mobili Metallici",
    "sg:phone":"+39 011 606 0519",
    "sg:postcode":"10127",
    "sg:province":"Torino",
    "wof:name":"Comisso F. & C. Snc",
    "wof:placetype":"venue"
},
  "geometry": {"coordinates":[7.6581630707,45.0142593384],"type":"Point"}
}