{
  "type": "Feature",
  "properties": {
    "iso:country":"IT",
    "sg:address":"Vle Druso 86a 39100 Bolzano",
    "sg:city":"Bolzano",
    "sg:classifiers":[
        {
            "category":"Juice Bar",
            "subcategory":"None",
            "type":"Food & Drink"
        }
    ],
    "sg:phone":"+39 0471 204400",
    "sg:postcode":"39100",
    "sg:province":"Bolzano/Bozen",
    "sg:tags":[
        "granite",
        "slab"
    ],
    "sg:website":"www.sparber.it",
    "wof:name":"Inter Pietre Sparber Srl",
    "wof:placetype":"venue"
},
  "geometry": {"coordinates":[11.328239,46.461643],"type":"Point"}
}