{
  "type": "Feature",
  "properties": {
    "iso:country":"IT",
    "sg:address":"20090 Cesano Boscone",
    "sg:city":"Cesano Boscone",
    "sg:orig_category":"Elettrotecnica Industriale, Prodotti E Apparecchiature. Elettrotecnica Professionale E Di Consumo",
    "sg:phone":"+39 02 458 1883",
    "sg:postcode":"20090",
    "sg:province":"Milano",
    "wof:name":"New E B M Srl",
    "wof:placetype":"venue"
},
  "geometry": {"coordinates":[9.084471,45.44746],"type":"Point"}
}