{
  "type": "Feature",
  "properties": {
    "iso:country":"IT",
    "sg:address":"25018 Montichiari",
    "sg:city":"Montichiari",
    "sg:orig_category":"Servizi Al Turismo. Trasporto Pubblico E Privato",
    "sg:phone":"+39 030 996 1241",
    "sg:postcode":"25018",
    "sg:province":"Brescia",
    "wof:name":"Aereo Servizi Bresciana Srl",
    "wof:placetype":"venue"
},
  "geometry": {"coordinates":[10.325848,45.424805],"type":"Point"}
}