{
  "type": "Feature",
  "properties": {
    "iso:country":"IT",
    "sg:address":"Via Domenico Cimarosa 33 40033 Casalecchio Di Reno",
    "sg:city":"Casalecchio di Reno",
    "sg:classifiers":[
        {
            "category":"Food & Beverages",
            "subcategory":"Fruits & Vegetables",
            "type":"Retail Goods"
        }
    ],
    "sg:phone":"+39 051 613 2910",
    "sg:postcode":"40033",
    "sg:province":"Bologna",
    "sg:tags":[
        "paste"
    ],
    "sg:website":"www.geldue.it",
    "wof:name":"Geldue Srl",
    "wof:placetype":"venue"
},
  "geometry": {"coordinates":[11.2724590302,44.4611053467],"type":"Point"}
}