{
  "type": "Feature",
  "properties": {
    "addr:full":"3, Via Anticoli Corrado 00156 Roma Roma Roma 00156",
    "addr:postcode":"00156;00156",
    "addr:street":"Via Anticoli Corrado",
    "iso:country":"IT",
    "sg:address":"3, Via Anticoli Corrado 00156 Roma",
    "sg:city":"Roma",
    "sg:classifiers":[
        {
            "category":"Shopping",
            "subcategory":"Clothing, Apparel, & Fashions",
            "type":"Retail Goods"
        }
    ],
    "sg:phone":"+39 39064100716",
    "sg:postcode":"00156",
    "sg:province":"Roma",
    "sg:tags":[
        "clothes"
    ],
    "wof:name":"Selmau Srl",
    "wof:placetype":"venue"
},
  "geometry": {"coordinates":[12.593668,41.932976],"type":"Point"}
}