{
  "type": "Feature",
  "properties": {
    "addr:full":"48, Via Vallina Orticella 31030 Borso Del Grappa Borso del Grappa Treviso 31030",
    "addr:postcode":"31030;31030",
    "addr:street":"Via Vallina Orticella",
    "iso:country":"IT",
    "sg:address":"48, Via Vallina Orticella 31030 Borso Del Grappa",
    "sg:city":"Borso del Grappa",
    "sg:classifiers":[
        {
            "category":"Manufacturing",
            "subcategory":"Glass & Minerals",
            "type":"Manufacturing & Wholesale Goods"
        }
    ],
    "sg:phone":"+39 0423 910076",
    "sg:postcode":"31030",
    "sg:province":"Treviso",
    "sg:tags":[
        "building",
        "material"
    ],
    "wof:name":"Decoratori Bassanesi (s.n.c.)",
    "wof:placetype":"venue"
},
  "geometry": {"coordinates":[11.805669,45.814335],"type":"Point"}
}