{
  "type": "Feature",
  "properties": {
    "iso:country":"IT",
    "sg:address":"41012 Carpi",
    "sg:city":"Carpi",
    "sg:orig_category":"Etichette Autoadesive",
    "sg:phone":"+39 059 652520",
    "sg:postcode":"41012",
    "sg:province":"Modena",
    "wof:name":"Emilabel Srl",
    "wof:placetype":"venue"
},
  "geometry": {"coordinates":[10.893876,44.795925],"type":"Point"}
}