{
  "type": "Feature",
  "properties": {
    "addr:full":"4, Via Verdi Giuseppe 29100 Piacenza Piacenza Piacenza 29100",
    "addr:postcode":"29100;29100",
    "addr:street":"Via Verdi Giuseppe",
    "iso:country":"IT",
    "sg:address":"4, Via Verdi Giuseppe 29100 Piacenza",
    "sg:city":"Piacenza",
    "sg:classifiers":[
        {
            "category":"Communications",
            "subcategory":"Newspaper",
            "type":"Services"
        }
    ],
    "sg:phone":"+39 0523 338245",
    "sg:postcode":"29100",
    "sg:province":"Piacenza",
    "sg:tags":[
        "advertising"
    ],
    "wof:name":"Publisi'(s.r.l.)",
    "wof:placetype":"venue"
},
  "geometry": {"coordinates":[9.695142,45.053772],"type":"Point"}
}