{
  "type": "Feature",
  "properties": {
    "iso:country":"IT",
    "sg:address":"Via Vittorio Emanuele 33 50041 Calenzano",
    "sg:city":"Calenzano",
    "sg:classifiers":[
        {
            "category":"Manufacturing",
            "subcategory":"Motor Vehicles & Parts",
            "type":"Manufacturing & Wholesale Goods"
        }
    ],
    "sg:phone":"+39 055 881 1184",
    "sg:postcode":"50041",
    "sg:province":"Firenze",
    "sg:tags":[
        "wheel",
        "wheel-sets"
    ],
    "sg:website":"www.casadellaruota.it",
    "wof:name":"Casa Della Ruota Di Carla Ghigliazza Sas",
    "wof:placetype":"venue"
},
  "geometry": {"coordinates":[11.175839,43.846958],"type":"Point"}
}