{
  "type": "Feature",
  "properties": {
    "iso:country":"IT",
    "sg:address":"04011 Aprilia",
    "sg:city":"Aprilia",
    "sg:orig_category":"Articoli Da Regalo. Arte Ed Artigianato Artistico. Shopping. Regalistica Aziendale",
    "sg:phone":"+39 06 927 6932",
    "sg:postcode":"04011",
    "sg:province":"Latina",
    "wof:name":"Fanucci Isidoro",
    "wof:placetype":"venue"
},
  "geometry": {"coordinates":[12.690533,41.551586],"type":"Point"}
}