{
  "type": "Feature",
  "properties": {
    "iso:country":"IT",
    "sg:address":"2, Viale Della Repubblica 20077 Melegnano",
    "sg:city":"Melegnano",
    "sg:classifiers":[
        {
            "category":"Manufacturing",
            "subcategory":"Metals",
            "type":"Manufacturing & Wholesale Goods"
        }
    ],
    "sg:phone":"+39 39029830178",
    "sg:postcode":"20077",
    "sg:province":"Milano",
    "sg:tags":[
        "metallurgy",
        "metalworking"
    ],
    "wof:name":"Altieri A. (s.r.l.)",
    "wof:placetype":"venue"
},
  "geometry": {"coordinates":[9.3172340393,45.3565597534],"type":"Point"}
}