{
  "type": "Feature",
  "properties": {
    "addr:full":"70053 Canosa Di Puglia Canosa di Puglia Bari 70053",
    "addr:postcode":"70053;70053",
    "addr:street":"Di Puglia",
    "iso:country":"IT",
    "sg:address":"70053 Canosa Di Puglia",
    "sg:city":"Canosa di Puglia",
    "sg:orig_category":"Pelliccerie",
    "sg:phone":"+39 0883 611144",
    "sg:postcode":"70053",
    "sg:province":"Bari",
    "wof:name":"Pellicceria Fedi",
    "wof:placetype":"venue"
},
  "geometry": {"coordinates":[16.0875320435,41.2369232178],"type":"Point"}
}