{
  "type": "Feature",
  "properties": {
    "addr:full":"00128 Roma Roma Roma 00128",
    "addr:postcode":"00128;00128",
    "iso:country":"IT",
    "sg:address":"00128 Roma",
    "sg:city":"Roma",
    "sg:orig_category":"Servizi E Lavori Per Agricoltura E Zootecnia. Servizi E Lavori Per Ecologia E Smaltimento Rifiuti",
    "sg:phone":"+39 06 5065 4106",
    "sg:postcode":"00128",
    "sg:province":"Roma",
    "wof:name":"San Giorgio Bonifiche Srl",
    "wof:placetype":"venue"
},
  "geometry": {"coordinates":[12.479835,41.772736],"type":"Point"}
}