{
  "type": "Feature",
  "properties": {
    "iso:country":"IT",
    "sg:address":"20090 Segrate",
    "sg:city":"Segrate",
    "sg:orig_category":"Chiese Ed Associazioni Religiose",
    "sg:phone":"+39 02 213 5631",
    "sg:postcode":"20090",
    "sg:province":"Milano",
    "wof:name":"Parrocchia Madonna Del Rosario App.suore",
    "wof:placetype":"venue"
},
  "geometry": {"coordinates":[9.267747,45.480106],"type":"Point"}
}