{
  "type": "Feature",
  "properties": {
    "addr:full":"Piazza Amendola 12; Siena; 53100 Siena Siena 53100",
    "addr:housenumber":"12",
    "addr:postcode":"53100;53100",
    "addr:street":"Piazza Amendola",
    "iso:country":"IT",
    "sg:address":"Piazza Amendola 12; Siena; 53100",
    "sg:city":"Siena",
    "sg:classifiers":[
        {
            "category":"Banks & Credit Unions",
            "subcategory":"Bank",
            "type":"Services"
        }
    ],
    "sg:phone":"+39 0577 28901",
    "sg:postcode":"53100",
    "sg:province":"Siena",
    "wof:name":"Banca Monte Dei Paschi Di Siena",
    "wof:placetype":"venue"
},
  "geometry": {"coordinates":[11.322111,43.327831],"type":"Point"}
}