{
  "type": "Feature",
  "properties": {
    "iso:country":"IT",
    "sg:address":"67039 Sulmona",
    "sg:orig_category":"Biliardi Ed Accessori",
    "sg:phone":"+39 0864 32029",
    "sg:postcode":"67039",
    "sg:province":"L'Aquila",
    "wof:name":"D'agostino Claudio",
    "wof:placetype":"venue"
},
  "geometry": {"coordinates":[13.925905,42.045109],"type":"Point"}
}