{
  "type": "Feature",
  "properties": {
    "iso:country":"IT",
    "sg:address":"59028 Vaiano",
    "sg:orig_category":"Filtri - Produzione E Commercio",
    "sg:phone":"+39 0574 984477",
    "sg:province":"PO",
    "wof:name":"Texwell Italiana Srl",
    "wof:placetype":"venue"
},
  "geometry": {"coordinates":[11.1281290054,43.9390335083],"type":"Point"}
}