{
  "type": "Feature",
  "properties": {
    "addr:full":"30175 Mestre Mestre Venezia 30175",
    "addr:postcode":"30175;30175",
    "addr:street":"Mestre Mestre Venezia",
    "iso:country":"IT",
    "sg:address":"30175 Mestre",
    "sg:city":"Mestre",
    "sg:orig_category":"Alberghi E Strutture Extra Alberghiere. Ospedali E Servizi Sanitari",
    "sg:phone":"+39 041 920979",
    "sg:postcode":"30175",
    "sg:province":"Venezia",
    "wof:name":"Colonia Alpina S. Marco Venezia",
    "wof:placetype":"venue"
},
  "geometry": {"coordinates":[12.232218,45.482853],"type":"Point"}
}