{
  "type": "Feature",
  "properties": {
    "iso:country":"IT",
    "sg:address":"20016 Pero",
    "sg:city":"Pero",
    "sg:orig_category":"Impianti, Attrezzature E Forniture Sanitarie Ed Ospedaliere",
    "sg:phone":"+39 02 3810 0273",
    "sg:postcode":"20016",
    "sg:province":"Milano",
    "wof:name":"O.m.a. Snc Fratelli Berardi",
    "wof:placetype":"venue"
},
  "geometry": {"coordinates":[9.077485,45.503296],"type":"Point"}
}