{
  "type": "Feature",
  "properties": {
    "addr:full":"14, Localita' Vanzelle 15060 Vignole Borbera Vignole Borbera Alessandria 15060",
    "addr:postcode":"15060;15060",
    "addr:street":"Localita ' Vanzelle",
    "iso:country":"IT",
    "sg:address":"14, Localita' Vanzelle 15060 Vignole Borbera",
    "sg:city":"Vignole Borbera",
    "sg:classifiers":[
        {
            "category":"Wholesale",
            "subcategory":"Drugs",
            "type":"Manufacturing & Wholesale Goods"
        }
    ],
    "sg:phone":"+39 0143 677767",
    "sg:postcode":"15060",
    "sg:province":"Alessandria",
    "sg:tags":[
        "chemical",
        "pharmaceutical"
    ],
    "wof:name":"S.l.i. Sociata' Internazionale Lubrificanti S.p.a.",
    "wof:placetype":"venue"
},
  "geometry": {"coordinates":[8.912932,44.712135],"type":"Point"}
}