{
  "type": "Feature",
  "properties": {
    "iso:country":"IT",
    "sg:address":"Via Fabio Filzi 30024 Musile Di Piave",
    "sg:city":"Musile di Piave",
    "sg:classifiers":[
        {
            "category":"Farming",
            "subcategory":"Livestock Farm",
            "type":"Manufacturing & Wholesale Goods"
        }
    ],
    "sg:phone":"+39 39042152880",
    "sg:postcode":"30024",
    "sg:province":"Venezia",
    "sg:tags":[
        "agriculture"
    ],
    "wof:name":"Bisiol",
    "wof:placetype":"venue"
},
  "geometry": {"coordinates":[12.549725,45.627327],"type":"Point"}
}