{
  "type": "Feature",
  "properties": {
    "addr:full":"Via Gora Del Pero 53 59100 Prato Prato Prato 59100",
    "addr:housenumber":"53",
    "addr:postcode":"59100;59100",
    "addr:street":"Via Gora Del Pero",
    "iso:country":"IT",
    "sg:address":"Via Gora Del Pero 53 59100 Prato",
    "sg:city":"Prato",
    "sg:classifiers":[
        {
            "category":"Shopping",
            "subcategory":"Clothing, Apparel, & Fashions",
            "type":"Retail Goods"
        }
    ],
    "sg:phone":"+39 0574 620574",
    "sg:postcode":"59100",
    "sg:province":"Prato",
    "sg:tags":[
        "clothing",
        "fabric"
    ],
    "wof:name":"Lanificio Becherucci Spa",
    "wof:placetype":"venue"
},
  "geometry": {"coordinates":[11.05648,43.855164],"type":"Point"}
}