{
  "type": "Feature",
  "properties": {
    "iso:country":"IT",
    "sg:address":"25135 Brescia",
    "sg:city":"Brescia",
    "sg:orig_category":"Macchine, Impianti Ed Attrezzature Per Industria Alimentare E Bevande",
    "sg:phone":"+39 030 336 6321",
    "sg:postcode":"25135",
    "sg:province":"Brescia",
    "wof:name":"Arte Bianca S.r.l.",
    "wof:placetype":"venue"
},
  "geometry": {"coordinates":[10.280022,45.510227],"type":"Point"}
}