{
  "type": "Feature",
  "properties": {
    "addr:full":"98066 Patti Patti Messina 98066",
    "addr:postcode":"98066;98066",
    "iso:country":"IT",
    "sg:address":"98066 Patti",
    "sg:city":"Patti",
    "sg:orig_category":"Articoli Da Regalo. Shopping. Regalistica Aziendale",
    "sg:phone":"+39 339 394 9475",
    "sg:postcode":"98066",
    "sg:province":"Messina",
    "wof:name":"Pathirana Hewage Sriyani",
    "wof:placetype":"venue"
},
  "geometry": {"coordinates":[14.997303,38.134094],"type":"Point"}
}