{
  "type": "Feature",
  "properties": {
    "addr:full":"20136 Milano Milano Milano 20136",
    "addr:postcode":"20136;20136",
    "iso:country":"IT",
    "sg:address":"20136 Milano",
    "sg:city":"Milano",
    "sg:orig_category":"Serramenti Ed Infissi",
    "sg:phone":"+39 02 837 2071",
    "sg:postcode":"20136",
    "sg:province":"Milano",
    "wof:name":"B.g. Di Bergamaschi A. & C. Snc",
    "wof:placetype":"venue"
},
  "geometry": {"coordinates":[9.179873,45.450176],"type":"Point"}
}