{
  "type": "Feature",
  "properties": {
    "iso:country":"IT",
    "sg:address":"Via V. Vento, 90; Belluno; 32100",
    "sg:city":"Belluno",
    "sg:classifiers":[
        {
            "category":"Banks & Credit Unions",
            "subcategory":"Bank",
            "type":"Services"
        }
    ],
    "sg:phone":"+39 0437 930133",
    "sg:postcode":"32100",
    "sg:province":"Belluno",
    "wof:name":"Banca Sella",
    "wof:placetype":"venue"
},
  "geometry": {"coordinates":[12.223274,46.145752],"type":"Point"}
}