{
  "type": "Feature",
  "properties": {
    "addr:full":"Corso Borsalino 56; Alessandria; 15100 Alessandria Alessandria 15100",
    "addr:housenumber":"56",
    "addr:postcode":"15100;15100",
    "addr:street":"Corso Borsalino",
    "iso:country":"IT",
    "sg:address":"Corso Borsalino 56; Alessandria; 15100",
    "sg:city":"Alessandria",
    "sg:classifiers":[
        {
            "category":"Banks & Credit Unions",
            "subcategory":"Bank",
            "type":"Services"
        }
    ],
    "sg:phone":"+39 0131 231555",
    "sg:postcode":"15100",
    "sg:province":"Alessandria",
    "wof:name":"Banca Cariplo",
    "wof:placetype":"venue"
},
  "geometry": {"coordinates":[8.61491,44.907574],"type":"Point"}
}