{
  "type": "Feature",
  "properties": {
    "iso:country":"IT",
    "sg:address":"5, V. Smeraldo 40138 Bologna",
    "sg:city":"Bologna",
    "sg:classifiers":[
        {
            "category":"Shopping",
            "subcategory":"Clothing, Apparel, & Fashions",
            "type":"Retail Goods"
        }
    ],
    "sg:phone":"+39 39051390058",
    "sg:postcode":"40138",
    "sg:province":"Bologna",
    "sg:tags":[
        "clothing",
        "accessory"
    ],
    "sg:website":"http://www.vivolo.com",
    "wof:name":"A-vivolo Srl",
    "wof:placetype":"venue"
},
  "geometry": {"coordinates":[11.373979,44.490753],"type":"Point"}
}