{
  "type": "Feature",
  "properties": {
    "addr:full":"Km. 18.300, Via Nettunense 00040 Lanuvio Lanuvio Roma 00040",
    "addr:postcode":"00040;roma 00040",
    "addr:street":"Km. 18.300 Via Nettunense",
    "iso:country":"IT",
    "sg:address":"Km. 18.300, Via Nettunense 00040 Lanuvio",
    "sg:city":"Lanuvio",
    "sg:classifiers":[
        {
            "category":"Bars & Pubs",
            "subcategory":"Nightclub",
            "type":"Food & Drink"
        }
    ],
    "sg:phone":"+39 39069374475",
    "sg:postcode":"00040",
    "sg:province":"Roma",
    "sg:tags":[
        "cake",
        "bread"
    ],
    "wof:name":"Dolmont S.r.l.",
    "wof:placetype":"venue"
},
  "geometry": {"coordinates":[12.482325,41.895466],"type":"Point"}
}