{
  "type": "Feature",
  "properties": {
    "iso:country":"IT",
    "sg:address":"90134 Palermo",
    "sg:city":"Palermo",
    "sg:orig_category":"Articoli Natalizi",
    "sg:phone":"+39 091 651 2787",
    "sg:postcode":"90134",
    "sg:province":"Palermo",
    "sg:website":"http://www.tripi.it",
    "wof:name":"Sicily's Folk Di Angela Tripi & C. Snc",
    "wof:placetype":"venue"
},
  "geometry": {"coordinates":[13.3572349548,38.1139373779],"type":"Point"}
}