{
  "type": "Feature",
  "properties": {
    "iso:country":"IT",
    "sg:address":"20091 Bresso",
    "sg:city":"Bresso",
    "sg:orig_category":"Automobili E Mezzi Di Trasporto",
    "sg:phone":"+39 02 610 2316",
    "sg:postcode":"20091",
    "sg:province":"Milano",
    "wof:name":"Pozzi Avio (s.r.l.)",
    "wof:placetype":"venue"
},
  "geometry": {"coordinates":[9.196669,45.543579],"type":"Point"}
}