{
  "type": "Feature",
  "properties": {
    "addr:full":"42, Via Galignani 25036 Palazzolo Sull'oglio Brescia 25036",
    "addr:postcode":"25036;25036",
    "addr:street":"Via Galignani",
    "iso:country":"IT",
    "sg:address":"42, Via Galignani 25036 Palazzolo Sull'oglio",
    "sg:classifiers":[
        {
            "category":"Manufacturing",
            "subcategory":"Rubber & Plastics",
            "type":"Manufacturing & Wholesale Goods"
        }
    ],
    "sg:phone":"+39 39030731815",
    "sg:postcode":"25036",
    "sg:province":"Brescia",
    "wof:name":"Stampilite Di Villa Francesco & C. (s.n.c.)",
    "wof:placetype":"venue"
},
  "geometry": {"coordinates":[9.884057045,45.6013717651],"type":"Point"}
}