{
  "type": "Feature",
  "properties": {
    "addr:full":"01100 Viterbo Viterbo Viterbo 01100",
    "addr:postcode":"01100;01100",
    "iso:country":"IT",
    "sg:address":"01100 Viterbo",
    "sg:city":"Viterbo",
    "sg:classifiers":[
        {
            "category":"Manufacturing",
            "subcategory":"Furniture",
            "type":"Manufacturing & Wholesale Goods"
        }
    ],
    "sg:phone":"+39 0761 263538",
    "sg:postcode":"01100",
    "sg:province":"Viterbo",
    "sg:tags":[
        "wood",
        "industry",
        "work",
        "furnishing"
    ],
    "wof:name":"Idee In Pietra Di Errichiello Arcangelo",
    "wof:placetype":"venue"
},
  "geometry": {"coordinates":[12.0489788055,42.4415359497],"type":"Point"}
}