{
  "type": "Feature",
  "properties": {
    "iso:country":"IT",
    "sg:address":"9, Via Foggia 63018 Porto Sant'elpidio",
    "sg:classifiers":[
        {
            "category":"Personal",
            "subcategory":"Shoe Repair & Shine",
            "type":"Services"
        }
    ],
    "sg:phone":"+39 0734 902082",
    "sg:postcode":"63018",
    "sg:province":"Ascoli Piceno",
    "sg:tags":[
        "leather"
    ],
    "wof:name":"Calzaturificio Mignani Di Mignani Roberto & C Sas",
    "wof:placetype":"venue"
},
  "geometry": {"coordinates":[13.76576,43.240143],"type":"Point"}
}