{
  "type": "Feature",
  "properties": {
    "iso:country":"IT",
    "sg:address":"81100 Falciano",
    "sg:city":"Falciano",
    "sg:orig_category":"Elettronica Professionale E Di Consumo. Automazione E Macchine Per Ufficio",
    "sg:phone":"+39 0823 325388",
    "sg:postcode":"81100",
    "sg:province":"Caserta",
    "wof:name":"Willett S.p.a.",
    "wof:placetype":"venue"
},
  "geometry": {"coordinates":[14.350809,41.065826],"type":"Point"}
}