{
  "type": "Feature",
  "properties": {
    "addr:full":"44033 Berra Berra Ferrara 44033",
    "addr:postcode":"44033;44033",
    "iso:country":"IT",
    "sg:address":"44033 Berra",
    "sg:city":"Berra",
    "sg:orig_category":"Non-classified Establishments",
    "sg:phone":"+39 0532 831165",
    "sg:postcode":"44033",
    "sg:province":"Ferrara",
    "sg:website":"http://www.macagnoarredi.com",
    "wof:name":"Alberto Macagno Arredi",
    "wof:placetype":"venue"
},
  "geometry": {"coordinates":[11.975743,44.97324],"type":"Point"}
}