{
  "type": "Feature",
  "properties": {
    "iso:country":"IT",
    "sg:address":"20, Via Albani Francesco 20149 Milano",
    "sg:city":"Milano",
    "sg:classifiers":[
        {
            "category":"Sports & Exercise",
            "subcategory":"Playing Field",
            "type":"Entertainment"
        }
    ],
    "sg:phone":"+39 02 4800 6109",
    "sg:postcode":"20149",
    "sg:province":"Milano",
    "sg:tags":[
        "game"
    ],
    "wof:name":"O.m.e.a. (s.r.l.)",
    "wof:placetype":"venue"
},
  "geometry": {"coordinates":[9.147843,45.479721],"type":"Point"}
}