{
  "type": "Feature",
  "properties": {
    "iso:country":"IT",
    "sg:address":"95128 Catania",
    "sg:city":"Catania",
    "sg:orig_category":"Motocicli E Motocarri - Commercio E Riparazione",
    "sg:phone":"+39 095 502868",
    "sg:postcode":"95128",
    "sg:province":"Catania",
    "wof:name":"Drive Srl",
    "wof:placetype":"venue"
},
  "geometry": {"coordinates":[15.0879058838,37.5143470764],"type":"Point"}
}