{
  "type": "Feature",
  "properties": {
    "addr:full":"36027 Ros\u00e0 Vicenza 36027",
    "addr:postcode":"36027;36027",
    "iso:country":"IT",
    "sg:address":"36027 Ros\u00e0",
    "sg:classifiers":[
        {
            "category":"Shopping",
            "subcategory":"Stationery & Office Supplies",
            "type":"Retail Goods"
        }
    ],
    "sg:phone":"+39 0424 560785",
    "sg:postcode":"36027",
    "sg:province":"Vicenza",
    "sg:tags":[
        "equipment",
        "furniture",
        "furnishing",
        "professional"
    ],
    "sg:website":"http://www.tosingraf.com",
    "wof:name":"Tosingraf Srl",
    "wof:placetype":"venue"
},
  "geometry": {"coordinates":[11.5195684433,45.5319633484],"type":"Point"}
}