{
  "type": "Feature",
  "properties": {
    "iso:country":"IT",
    "sg:address":"Cso Garibaldi 130 15048 Valenza",
    "sg:city":"Valenza",
    "sg:classifiers":[
        {
            "category":"Manufacturing",
            "subcategory":"Jewelry",
            "type":"Manufacturing & Wholesale Goods"
        }
    ],
    "sg:phone":"+39 0131 947244",
    "sg:postcode":"15048",
    "sg:province":"Alessandria",
    "sg:tags":[
        "jewel"
    ],
    "sg:website":"www.orogi.it",
    "wof:name":"Orogi - S.r.l.",
    "wof:placetype":"venue"
},
  "geometry": {"coordinates":[8.643589,45.011208],"type":"Point"}
}