{
  "type": "Feature",
  "properties": {
    "iso:country":"IT",
    "sg:address":"56, Via Cal Larga 31010 Mareno Di Piave",
    "sg:city":"Mareno di Piave",
    "sg:classifiers":[
        {
            "category":"Home & Garden",
            "subcategory":"Home Furnishings",
            "type":"Retail Goods"
        }
    ],
    "sg:phone":"+39 0438 492506",
    "sg:postcode":"31010",
    "sg:province":"Treviso",
    "sg:tags":[
        "household"
    ],
    "wof:name":"Old Line Arredamenti (s.r.l.)",
    "wof:placetype":"venue"
},
  "geometry": {"coordinates":[12.339767,45.83379],"type":"Point"}
}