{
  "type": "Feature",
  "properties": {
    "iso:country":"IT",
    "sg:address":"70044 Polignano A Mare",
    "sg:city":"Polignano a Mare",
    "sg:orig_category":"Agricoltura, Orticoltura E Floricoltura",
    "sg:phone":"+39 080 424 0377",
    "sg:postcode":"70044",
    "sg:province":"Bari",
    "wof:name":"Frutta Italia Di Montalbo' V. & C. Snc",
    "wof:placetype":"venue"
},
  "geometry": {"coordinates":[17.183903,40.966835],"type":"Point"}
}