{
  "type": "Feature",
  "properties": {
    "iso:country":"IT",
    "sg:address":"21047 Saronno",
    "sg:city":"Saronno",
    "sg:orig_category":"Campeggio",
    "sg:phone":"+39 02 962 1261",
    "sg:postcode":"21047",
    "sg:province":"Varese",
    "wof:name":"Tassoni Corrado",
    "wof:placetype":"venue"
},
  "geometry": {"coordinates":[9.021383,45.617058],"type":"Point"}
}