{
  "type": "Feature",
  "properties": {
    "iso:country":"IT",
    "sg:address":"33050 Trivignano Udinese",
    "sg:city":"Rivignano",
    "sg:orig_category":"Climatizzazione E Condizionamento, Apparecchiature E Servizi",
    "sg:phone":"+39 0432 999012",
    "sg:postcode":"33050",
    "sg:province":"Udine",
    "wof:name":"Colavini Snc Di Marco Colavini & C.",
    "wof:placetype":"venue"
},
  "geometry": {"coordinates":[13.338255,45.954475],"type":"Point"}
}