{
  "type": "Feature",
  "properties": {
    "iso:country":"IT",
    "sg:address":"39042 Bressanone",
    "sg:city":"Bressanone",
    "sg:orig_category":"Architetti - Studi",
    "sg:phone":"+39 0472 831112",
    "sg:postcode":"39042",
    "sg:province":"Bolzano/Bozen",
    "wof:name":"Costazza Dr. Arch. Paul",
    "wof:placetype":"venue"
},
  "geometry": {"coordinates":[11.353288,46.496807],"type":"Point"}
}