{
  "type": "Feature",
  "properties": {
    "addr:full":"10048 Vinovo Vinovo Torino 10048",
    "addr:housenumber":"10048",
    "addr:postcode":"10048",
    "addr:street":"Vinovo",
    "iso:country":"IT",
    "sg:address":"10048 Vinovo",
    "sg:city":"Vinovo",
    "sg:orig_category":"Agenzie D'affari E Servizi Commerciali. Servizi Per Aziende, Manifestazioni E Supporto Agli Scambi Commerciali",
    "sg:phone":"+39 011 965 4128",
    "sg:postcode":"10048",
    "sg:province":"Torino",
    "wof:name":"Studio Miele Sas",
    "wof:placetype":"venue"
},
  "geometry": {"coordinates":[7.618076,44.974865],"type":"Point"}
}