{
  "type": "Feature",
  "properties": {
    "addr:full":"30036 Santa Maria Di Sala Santa Maria di Sala Venezia 30036",
    "addr:postcode":"30036;30036",
    "addr:street":"Maria",
    "iso:country":"IT",
    "sg:address":"30036 Santa Maria Di Sala",
    "sg:city":"Santa Maria di Sala",
    "sg:orig_category":"Frigotecnica, Apparecchiature E Servizi. Servizi Di Magazzinaggio E Movimentazione",
    "sg:phone":"+39 041 576 0401",
    "sg:postcode":"30036",
    "sg:province":"Venezia",
    "wof:name":"Frigoscandia Spa",
    "wof:placetype":"venue"
},
  "geometry": {"coordinates":[12.0293865204,45.4557228088],"type":"Point"}
}