{
  "type": "Feature",
  "properties": {
    "iso:country":"IT",
    "sg:address":"12, Via Provinciale Per Reggio 42018 San Martino In Rio",
    "sg:classifiers":[
        {
            "category":"Professional",
            "subcategory":"Engineering",
            "type":"Services"
        }
    ],
    "sg:phone":"+39 0522 695270",
    "sg:postcode":"42018",
    "sg:province":"Reggio Nell'Emilia",
    "sg:tags":[
        "machine",
        "-",
        "mechanical"
    ],
    "wof:name":"Casoli & Losi (s.n.c.)",
    "wof:placetype":"venue"
},
  "geometry": {"coordinates":[10.767587,44.725502],"type":"Point"}
}