{
  "type": "Feature",
  "properties": {
    "iso:country":"IT",
    "sg:address":"35027 Noventa Padovana",
    "sg:city":"Noventa Padovana",
    "sg:orig_category":"Materassi - Produzione E Ingrosso",
    "sg:phone":"+39 049 808 9057",
    "sg:postcode":"35027",
    "sg:province":"Padova",
    "wof:name":"Hurry Up Srl",
    "wof:placetype":"venue"
},
  "geometry": {"coordinates":[11.929816,45.408684],"type":"Point"}
}