{
  "type": "Feature",
  "properties": {
    "iso:country":"IT",
    "sg:address":"12, Via Fermi Enrico 37026 Pescantina",
    "sg:city":"Pescantina",
    "sg:classifiers":[
        {
            "category":"Wholesale",
            "subcategory":"Drugs",
            "type":"Manufacturing & Wholesale Goods"
        }
    ],
    "sg:phone":"+39 045 715 7763",
    "sg:postcode":"37026",
    "sg:province":"Verona",
    "sg:tags":[
        "chemical",
        "pharmaceutical"
    ],
    "wof:name":"Far (s.r.l.)",
    "wof:placetype":"venue"
},
  "geometry": {"coordinates":[10.906265,45.479984],"type":"Point"}
}