{
  "type": "Feature",
  "properties": {
    "iso:country":"IT",
    "sg:address":"10073 Cirie'",
    "sg:orig_category":"Servizi E Lavori Per Industria Alimentare E Bevande",
    "sg:phone":"+39 011 921 4063",
    "sg:postcode":"10073",
    "sg:province":"Torino",
    "wof:name":"Ballesio Renato",
    "wof:placetype":"venue"
},
  "geometry": {"coordinates":[7.608222,45.233284],"type":"Point"}
}