{
  "type": "Feature",
  "properties": {
    "iso:country":"IT",
    "sg:address":"Km. 1.300, Strada Provinciale 54 09170 Oristano",
    "sg:city":"Oristano",
    "sg:classifiers":[
        {
            "category":"Professional",
            "subcategory":"Engineering",
            "type":"Services"
        }
    ],
    "sg:phone":"+39 39078333955",
    "sg:postcode":"09170",
    "sg:province":"Oristano",
    "sg:tags":[
        "machine",
        "-",
        "mechanical"
    ],
    "wof:name":"Nuova F.r.c.i. Srl",
    "wof:placetype":"venue"
},
  "geometry": {"coordinates":[8.596333,39.905273],"type":"Point"}
}