{
  "type": "Feature",
  "properties": {
    "addr:full":"06089 Torgiano Torgiano Perugia 06089",
    "addr:postcode":"06089;06089",
    "iso:country":"IT",
    "sg:address":"06089 Torgiano",
    "sg:city":"Torgiano",
    "sg:classifiers":[
        {
            "category":"Manufacturing",
            "subcategory":"Metals",
            "type":"Manufacturing & Wholesale Goods"
        }
    ],
    "sg:phone":"+39 075 988 9038",
    "sg:postcode":"06089",
    "sg:province":"Perugia",
    "sg:tags":[
        "ferro"
    ],
    "wof:name":"Wilsider Srl",
    "wof:placetype":"venue"
},
  "geometry": {"coordinates":[12.4365005493,43.0262107849],"type":"Point"}
}