{
  "type": "Feature",
  "properties": {
    "addr:full":"Via Meucci Int. Chatillon 13100 Vercelli Vercelli Vercelli 13100",
    "addr:postcode":"13100;13100",
    "addr:street":"Via Meucci Int. Chatillon",
    "iso:country":"IT",
    "sg:address":"Via Meucci Int. Chatillon 13100 Vercelli",
    "sg:city":"Vercelli",
    "sg:classifiers":[
        {
            "category":"Communications",
            "subcategory":"Film & Video Production",
            "type":"Services"
        }
    ],
    "sg:phone":"+39 0161 215333",
    "sg:postcode":"13100",
    "sg:province":"Vercelli",
    "sg:tags":[
        "hair",
        "ware"
    ],
    "sg:website":"www.fabyline.it",
    "wof:name":"Faby Line Srl",
    "wof:placetype":"venue"
},
  "geometry": {"coordinates":[8.426394,45.32106],"type":"Point"}
}