{
  "type": "Feature",
  "properties": {
    "addr:full":"Bastioni Di Porta Volta 13 20121 Milano Milano Milano 20121",
    "addr:housenumber":"13",
    "addr:postcode":"20121;20121",
    "addr:street":"Bastioni Di Porta Volta",
    "iso:country":"IT",
    "sg:address":"Bastioni Di Porta Volta 13 20121 Milano",
    "sg:city":"Milano",
    "sg:classifiers":[
        {
            "category":"Real Estate",
            "subcategory":"Architect",
            "type":"Services"
        }
    ],
    "sg:phone":"+39 02 659 0932",
    "sg:postcode":"20121",
    "sg:province":"Milano",
    "sg:tags":[
        "paving"
    ],
    "wof:name":"Gere Srl",
    "wof:placetype":"venue"
},
  "geometry": {"coordinates":[9.1816883087,45.4787445068],"type":"Point"}
}