{
  "type": "Feature",
  "properties": {
    "iso:country":"IT",
    "sg:address":"20060 Cassina De'pecchi",
    "sg:orig_category":"Riparazione Dei Mezzi Di Trasporto. Servizi Ausiliari Dei Mezzi Di Trasporto",
    "sg:phone":"+39 02 9529 9075",
    "sg:postcode":"20060",
    "sg:province":"Milano",
    "wof:name":"Autofficina Effegi Di Facetti Virgilio",
    "wof:placetype":"venue"
},
  "geometry": {"coordinates":[9.323892,45.492157],"type":"Point"}
}