{
  "type": "Feature",
  "properties": {
    "iso:country":"IT",
    "sg:address":"24060 Bagnatica",
    "sg:city":"Bagnatica",
    "sg:orig_category":"Abbigliamento Industria - Forniture Ed Accessori",
    "sg:phone":"+39 035 681814",
    "sg:postcode":"24060",
    "sg:province":"Bergamo",
    "sg:website":"http://www.knowh.it",
    "wof:name":"Know How Di Omodei Luciano Sas",
    "wof:placetype":"venue"
},
  "geometry": {"coordinates":[9.782194,45.661896],"type":"Point"}
}