{
  "type": "Feature",
  "properties": {
    "iso:country":"IT",
    "sg:address":"70032 Bitonto",
    "sg:city":"Bitonto",
    "sg:orig_category":"Automazione E Macchine Per Ufficio",
    "sg:phone":"+39 080 371 5071",
    "sg:postcode":"70032",
    "sg:province":"Bari",
    "wof:name":"Minenna Michele",
    "wof:placetype":"venue"
},
  "geometry": {"coordinates":[16.777351,41.085213],"type":"Point"}
}