{
  "type": "Feature",
  "properties": {
    "iso:country":"IT",
    "sg:address":"20122 Milano",
    "sg:city":"Milano",
    "sg:orig_category":"Banche E Servizi Finanziari",
    "sg:phone":"+39 02 7639 0776",
    "sg:postcode":"20122",
    "sg:province":"Milano",
    "wof:name":"Fid Fiduciaria Investimenti Spa",
    "wof:placetype":"venue"
},
  "geometry": {"coordinates":[9.195952,45.462593],"type":"Point"}
}