{
  "type": "Feature",
  "properties": {
    "iso:country":"IT",
    "sg:address":"Via Porru Bonelli 81; Gonnosfanadiga; 09035",
    "sg:city":"Gonnosfanadiga",
    "sg:classifiers":[
        {
            "category":"Banks & Credit Unions",
            "subcategory":"Bank",
            "type":"Services"
        }
    ],
    "sg:phone":"+39 070 979 9020",
    "sg:postcode":"09035",
    "sg:province":"Medio Campidano",
    "wof:name":"Banco Di Napoli Spa",
    "wof:placetype":"venue"
},
  "geometry": {"coordinates":[8.661477,39.493382],"type":"Point"}
}