{
  "type": "Feature",
  "properties": {
    "iso:country":"IT",
    "sg:address":"25018 Montichiari",
    "sg:city":"Montichiari",
    "sg:orig_category":"Carrozzerie Autoveicoli Industriali E Speciali",
    "sg:phone":"+39 030 996 1741",
    "sg:postcode":"25018",
    "sg:province":"Brescia",
    "sg:website":"http://www.comear.it",
    "wof:name":"Co.me.ar Molinari Spa",
    "wof:placetype":"venue"
},
  "geometry": {"coordinates":[10.367213,45.413536],"type":"Point"}
}