{
  "type": "Feature",
  "properties": {
    "iso:country":"IT",
    "sg:address":"167, Via Case Sparse 22013 Domaso",
    "sg:city":"Domaso",
    "sg:classifiers":[
        {
            "category":"Shopping",
            "type":"Retail Goods"
        }
    ],
    "sg:phone":"+39 39034496019",
    "sg:postcode":"22013",
    "sg:province":"Como",
    "sg:tags":[
        "finished",
        "-",
        "metallic"
    ],
    "wof:name":"Sider Lario (s.r.l.)",
    "wof:placetype":"venue"
},
  "geometry": {"coordinates":[9.3330211639,46.1536903381],"type":"Point"}
}