{
  "type": "Feature",
  "properties": {
    "addr:full":"95030 Sant'agata Li Battiati Catania 95030",
    "addr:postcode":"95030;95030",
    "iso:country":"IT",
    "sg:address":"95030 Sant'agata Li Battiati",
    "sg:orig_category":"Ceramiche Per Pavimenti E Rivestimenti - Produzione E Ingrosso",
    "sg:phone":"+39 095 411018",
    "sg:postcode":"95030",
    "sg:province":"Catania",
    "wof:name":"Torre Rappresentanze Sas",
    "wof:placetype":"venue"
},
  "geometry": {"coordinates":[15.07721,37.548286],"type":"Point"}
}