{
  "type": "Feature",
  "properties": {
    "iso:country":"IT",
    "sg:address":"37024 Negrar",
    "sg:city":"Arbizzano",
    "sg:orig_category":"Elettrotecnica Industriale, Prodotti E Apparecchiature",
    "sg:phone":"+39 045 751 3531",
    "sg:postcode":"37024",
    "sg:province":"Verona",
    "wof:name":"Elettromontaggi Snc Di Masotto M. & C",
    "wof:placetype":"venue"
},
  "geometry": {"coordinates":[10.933613,45.486622],"type":"Point"}
}