{
  "type": "Feature",
  "properties": {
    "addr:full":"31020 San Zenone Degli Ezzelini San Zenone degli Ezzelini Treviso 31020",
    "addr:housenumber":"31020",
    "addr:postcode":"31020",
    "addr:street":"San",
    "iso:country":"IT",
    "sg:address":"31020 San Zenone Degli Ezzelini",
    "sg:city":"San Zenone degli Ezzelini",
    "sg:orig_category":"Gioielleria, Oreficeria E Argenteria",
    "sg:phone":"+39 0423 968508",
    "sg:postcode":"31020",
    "sg:province":"Treviso",
    "wof:name":"Evan Srl",
    "wof:placetype":"venue"
},
  "geometry": {"coordinates":[11.825712,45.776421],"type":"Point"}
}