{
  "type": "Feature",
  "properties": {
    "iso:country":"IT",
    "sg:address":"15048 Valenza",
    "sg:city":"Valenza",
    "sg:orig_category":"Trattamenti Termici E Superficiali Metalli, Galvanotecnica",
    "sg:phone":"+39 0131 950916",
    "sg:postcode":"15048",
    "sg:province":"Alessandria",
    "wof:name":"Maggio E Damianacos Snc",
    "wof:placetype":"venue"
},
  "geometry": {"coordinates":[8.608051,44.912334],"type":"Point"}
}