{
  "type": "Feature",
  "properties": {
    "iso:country":"IT",
    "sg:address":"20020 Lainate",
    "sg:city":"Lainate",
    "sg:orig_category":"Apparecchiature Ed Attrezzature Meccaniche. Elettronica Industriale, Prodotti E Apparecchiature. Impianti, Attrezzature E Forniture Sanitarie Ed Ospedaliere. Apparecchi, Attrezzature E Forniture Per C",
    "sg:phone":"+39 02 937 1038",
    "sg:postcode":"20020",
    "sg:province":"Milano",
    "wof:name":"Vidalaser Di Angela Paleari & C. S.a.s.",
    "wof:placetype":"venue"
},
  "geometry": {"coordinates":[9.012868,45.511997],"type":"Point"}
}