{
  "type": "Feature",
  "properties": {
    "addr:full":"20019 Settimo Milanese Settimo Milanese Milano 20019",
    "addr:postcode":"20019;20019",
    "iso:country":"IT",
    "sg:address":"20019 Settimo Milanese",
    "sg:city":"Settimo Milanese",
    "sg:orig_category":"Metalli E Leghe. Gioielleria, Oreficeria E Argenteria",
    "sg:phone":"+39 02 328 2018",
    "sg:postcode":"20019",
    "sg:province":"Milano",
    "wof:name":"Comepre (s.r.l.)",
    "wof:placetype":"venue"
},
  "geometry": {"coordinates":[9.0743579865,45.4712944031],"type":"Point"}
}