{
  "type": "Feature",
  "properties": {
    "iso:country":"IT",
    "sg:address":"73044 Galatone",
    "sg:city":"Galatone",
    "sg:orig_category":"Aspirazione Impianti",
    "sg:phone":"+39 0833 867900",
    "sg:postcode":"73044",
    "sg:province":"Lecce",
    "wof:name":"Tecnometal Srl",
    "wof:placetype":"venue"
},
  "geometry": {"coordinates":[18.059866,40.13916],"type":"Point"}
}