{
  "type": "Feature",
  "properties": {
    "iso:country":"IT",
    "sg:address":"00139 Roma",
    "sg:city":"Roma",
    "sg:orig_category":"Condizionatori Aria - Commercio",
    "sg:phone":"+39 06 818 4647",
    "sg:postcode":"00139",
    "sg:province":"Roma",
    "wof:name":"Expert R.t.e. Color Srl",
    "wof:placetype":"venue"
},
  "geometry": {"coordinates":[12.564226,41.986916],"type":"Point"}
}