{
  "type": "Feature",
  "properties": {
    "addr:full":"Via L. Einaudi 14 36056 Tezze Sul Brenta Tezze sul Brenta Vicenza 36056",
    "addr:housenumber":"14",
    "addr:postcode":"36056;36056",
    "addr:street":"Via L. Einaudi",
    "iso:country":"IT",
    "sg:address":"Via L. Einaudi 14 36056 Tezze Sul Brenta",
    "sg:city":"Tezze sul Brenta",
    "sg:classifiers":[
        {
            "category":"Organizations",
            "subcategory":"Community Association",
            "type":"Services"
        }
    ],
    "sg:phone":"+39 0424 539216",
    "sg:postcode":"36056",
    "sg:province":"Vicenza",
    "sg:tags":[
        "medal"
    ],
    "wof:name":"Agf Snc",
    "wof:placetype":"venue"
},
  "geometry": {"coordinates":[11.540307,45.545906],"type":"Point"}
}