{
  "type": "Feature",
  "properties": {
    "addr:full":"41100 Modena Modena Modena 41100",
    "addr:postcode":"41100;41100",
    "iso:country":"IT",
    "sg:address":"41100 Modena",
    "sg:city":"Modena",
    "sg:orig_category":"Campeggio",
    "sg:phone":"+39 059 450557",
    "sg:postcode":"41100",
    "sg:province":"Modena",
    "wof:name":"Casa Del Bambu' Di Castagnoli Massimo",
    "wof:placetype":"venue"
},
  "geometry": {"coordinates":[10.899542,44.648563],"type":"Point"}
}