{
  "type": "Feature",
  "properties": {
    "iso:country":"IT",
    "sg:address":"00159 Roma",
    "sg:city":"Roma",
    "sg:orig_category":"Scuole E Servizi Scolastici",
    "sg:phone":"+39 06 407 6331",
    "sg:postcode":"00159",
    "sg:province":"Roma",
    "wof:name":"Scuola Elementare Parificata Suore Sacramentine",
    "wof:placetype":"venue"
},
  "geometry": {"coordinates":[12.562938,41.908676],"type":"Point"}
}