{
  "type": "Feature",
  "properties": {
    "iso:country":"IT",
    "sg:address":"20, Via Trebbia 23868 Valmadrera",
    "sg:city":"Valmadrera",
    "sg:classifiers":[
        {
            "category":"Shopping",
            "subcategory":"Computers & Home Electronics",
            "type":"Retail Goods"
        }
    ],
    "sg:phone":"+39 0341 550560",
    "sg:postcode":"23868",
    "sg:province":"Lecco",
    "sg:tags":[
        "electronic",
        "electrical",
        "equipment"
    ],
    "wof:name":"Elettromeccanica Valmadrerese Di Di Attilio Anghil",
    "wof:placetype":"venue"
},
  "geometry": {"coordinates":[9.345197,45.838757],"type":"Point"}
}