{
  "type": "Feature",
  "properties": {
    "addr:full":"06012 Citt\u00e0 Di Castello Perugia 06012",
    "addr:postcode":"06012;06012",
    "iso:country":"IT",
    "sg:address":"06012 Citt\u00e0 Di Castello",
    "sg:orig_category":"Arredamenti - Produzione E Ingrosso",
    "sg:phone":"+39 075 851 1566",
    "sg:postcode":"06012",
    "sg:province":"Perugia",
    "wof:name":"Country House Srl",
    "wof:placetype":"venue"
},
  "geometry": {"coordinates":[12.222097,43.49136],"type":"Point"}
}