{
  "type": "Feature",
  "properties": {
    "iso:country":"IT",
    "sg:address":"56025 Pontedera",
    "sg:city":"Pontedera",
    "sg:orig_category":"Metalli E Leghe",
    "sg:phone":"+39 0587 484232",
    "sg:postcode":"56025",
    "sg:province":"Pisa",
    "wof:name":"Mansider Di Boschi Luca & C. Sas",
    "wof:placetype":"venue"
},
  "geometry": {"coordinates":[10.5277633667,43.6788215637],"type":"Point"}
}