{
  "type": "Feature",
  "properties": {
    "addr:full":"89127 Reggio Calabria RC",
    "addr:postcode":"89127",
    "iso:country":"IT",
    "sg:address":"89127 Reggio Calabria",
    "sg:orig_category":"Essenze, Estratti E Prodotti Aromatici Per Alimentari",
    "sg:phone":"+39 0965 892473",
    "sg:province":"RC",
    "wof:name":"Fiori Di Calabria Sdf",
    "wof:placetype":"venue"
},
  "geometry": {"coordinates":[15.639787,38.10413],"type":"Point"}
}