{
  "type": "Feature",
  "properties": {
    "addr:full":"20156 Milano Milano Milano 20156",
    "addr:postcode":"20156;20156",
    "iso:country":"IT",
    "sg:address":"20156 Milano",
    "sg:city":"Milano",
    "sg:orig_category":"Servizi Ausiliari Dei Mezzi Di Trasporto",
    "sg:phone":"+39 02 308 4516",
    "sg:postcode":"20156",
    "sg:province":"Milano",
    "wof:name":"Agnelli Pasquale",
    "wof:placetype":"venue"
},
  "geometry": {"coordinates":[9.148128,45.494827],"type":"Point"}
}