{
  "type": "Feature",
  "properties": {
    "iso:country":"IT",
    "sg:address":"131, Via Val Della Torre 10040 Caselette",
    "sg:city":"Caselette",
    "sg:classifiers":[
        {
            "category":"Autos & Motor Vehicles",
            "subcategory":"Automobile Sales",
            "type":"Retail Goods"
        }
    ],
    "sg:phone":"+39 011 968 7051",
    "sg:postcode":"10040",
    "sg:province":"Torino",
    "sg:tags":[
        "motor-cars"
    ],
    "wof:name":"Kostal Italia S.r.l.",
    "wof:placetype":"venue"
},
  "geometry": {"coordinates":[7.4870114326,45.1169662476],"type":"Point"}
}