{
  "type": "Feature",
  "properties": {
    "iso:country":"IT",
    "sg:address":"6, Via Della Repubblica 33050 Pavia Di Udine",
    "sg:city":"Pavia di Udine",
    "sg:classifiers":[
        {
            "category":"Shopping",
            "subcategory":"Stationery & Office Supplies",
            "type":"Retail Goods"
        }
    ],
    "sg:phone":"+39 0432 676680",
    "sg:postcode":"33050",
    "sg:province":"Udine",
    "sg:tags":[
        "professional"
    ],
    "wof:name":"Cobar Srl",
    "wof:placetype":"venue"
},
  "geometry": {"coordinates":[13.3039131165,46.0351524353],"type":"Point"}
}