{
  "type": "Feature",
  "properties": {
    "iso:country":"IT",
    "sg:address":"50032 Borgo San Lorenzo",
    "sg:city":"Borgo San Lorenzo",
    "sg:orig_category":"Articoli Da Regalo. Regalistica Aziendale",
    "sg:phone":"+39 055 849 5153",
    "sg:postcode":"50032",
    "sg:province":"Firenze",
    "wof:name":"Gianna Di Chiarugi Silvano",
    "wof:placetype":"venue"
},
  "geometry": {"coordinates":[11.217108,43.709515],"type":"Point"}
}