{
  "type": "Feature",
  "properties": {
    "addr:full":"Strada 317 Per Agello Solomeo 06073 Corciano Corciano Perugia 06073",
    "addr:postcode":"06073;06073",
    "addr:street":"Strada 317 Per Agello Solomeo",
    "iso:country":"IT",
    "sg:address":"Strada 317 Per Agello Solomeo 06073 Corciano",
    "sg:city":"Corciano",
    "sg:classifiers":[
        {
            "category":"Wholesale",
            "subcategory":"Drugs",
            "type":"Manufacturing & Wholesale Goods"
        }
    ],
    "sg:phone":"+39 075 529 3471",
    "sg:postcode":"06073",
    "sg:province":"Perugia",
    "sg:tags":[
        "chemical",
        "pharmaceutical"
    ],
    "wof:name":"S.n.i.f.f. Italia (s.p.a.)",
    "wof:placetype":"venue"
},
  "geometry": {"coordinates":[12.389172,43.110703],"type":"Point"}
}