{
  "type": "Feature",
  "properties": {
    "addr:full":"Ctr. Fiastra 27/d 62014 Petriolo Petriolo Macerata 62014",
    "addr:housenumber":"27 / d",
    "addr:postcode":"62014;62014",
    "addr:street":"Fiastra",
    "iso:country":"IT",
    "sg:address":"Ctr. Fiastra 27/d 62014 Petriolo",
    "sg:city":"Petriolo",
    "sg:classifiers":[
        {
            "category":"Sports & Exercise",
            "subcategory":"Gym",
            "type":"Entertainment"
        }
    ],
    "sg:phone":"+39 0733 550222",
    "sg:postcode":"62014",
    "sg:province":"Macerata",
    "sg:tags":[
        "athletic",
        "ladies'",
        "stocking"
    ],
    "sg:website":"www.albertofermani.com",
    "wof:name":"Aeffe Srl",
    "wof:placetype":"venue"
},
  "geometry": {"coordinates":[13.456262,43.300747],"type":"Point"}
}