{
  "type": "Feature",
  "properties": {
    "addr:full":"78, Via Depretis Agostino 80133 Napoli Napoli Napoli 80133",
    "addr:postcode":"80133;80133",
    "addr:street":"Via Depretis Agostino",
    "iso:country":"IT",
    "sg:address":"78, Via Depretis Agostino 80133 Napoli",
    "sg:city":"Napoli",
    "sg:classifiers":[
        {
            "category":"Marine",
            "type":"Transportation"
        }
    ],
    "sg:phone":"+39 081 551 2109",
    "sg:postcode":"80133",
    "sg:province":"Napoli",
    "sg:tags":[
        "transport",
        "sea"
    ],
    "wof:name":"Agenzia Genovese Srl",
    "wof:placetype":"venue"
},
  "geometry": {"coordinates":[14.251636,40.840096],"type":"Point"}
}