{
  "type": "Feature",
  "properties": {
    "iso:country":"IT",
    "sg:address":"19, Via Tanaro 20015 Parabiago",
    "sg:city":"Parabiago",
    "sg:classifiers":[
        {
            "category":"Shopping",
            "subcategory":"Computers & Home Electronics",
            "type":"Retail Goods"
        }
    ],
    "sg:phone":"+39 0331 491770",
    "sg:postcode":"20015",
    "sg:province":"Milano",
    "sg:tags":[
        "electronic",
        "electrical",
        "equipment"
    ],
    "wof:name":"Ramcro S.r.l.",
    "wof:placetype":"venue"
},
  "geometry": {"coordinates":[8.958478,45.54353],"type":"Point"}
}