{
  "type": "Feature",
  "properties": {
    "addr:full":"10090 Castiglione Torinese Castiglione Torinese Torino 10090",
    "addr:postcode":"10090;10090",
    "iso:country":"IT",
    "sg:address":"10090 Castiglione Torinese",
    "sg:city":"Castiglione Torinese",
    "sg:orig_category":"Forniture Per Uffici. Regalistica Aziendale",
    "sg:phone":"+39 011 960 0370",
    "sg:postcode":"10090",
    "sg:province":"Torino",
    "wof:name":"Cromolux (s.r.l.)",
    "wof:placetype":"venue"
},
  "geometry": {"coordinates":[8.3989200592,45.4623451233],"type":"Point"}
}