{
  "type": "Feature",
  "properties": {
    "iso:country":"IT",
    "sg:address":"42100 Sesso",
    "sg:orig_category":"Macchine Utensili E Impianti",
    "sg:phone":"+39 0522 531721",
    "sg:postcode":"42100",
    "sg:province":"Reggio Nell'Emilia",
    "wof:name":"Officina Meccanica Cucchi Aurelio Di Cucchi Luciano E C. Snc",
    "wof:placetype":"venue"
},
  "geometry": {"coordinates":[10.614469,44.737251],"type":"Point"}
}