{
  "type": "Feature",
  "properties": {
    "iso:country":"IT",
    "sg:address":"20021 Bollate",
    "sg:city":"Bollate",
    "sg:orig_category":"Non-classified Establishments",
    "sg:phone":"+39 02 3830 6027",
    "sg:postcode":"20021",
    "sg:province":"Milano",
    "wof:name":"Lapo-gel Di Paganoni Stefania",
    "wof:placetype":"venue"
},
  "geometry": {"coordinates":[9.115255,45.543343],"type":"Point"}
}