{
  "type": "Feature",
  "properties": {
    "iso:country":"IT",
    "sg:address":"3, V. Cimarosa 36071 Arzignano",
    "sg:city":"Arzignano",
    "sg:classifiers":[
        {
            "category":"Manufacturing",
            "subcategory":"Textiles",
            "type":"Manufacturing & Wholesale Goods"
        }
    ],
    "sg:phone":"+39 0444 670244",
    "sg:postcode":"36071",
    "sg:province":"Vicenza",
    "sg:tags":[
        "leather",
        "raw",
        "material",
        "-"
    ],
    "sg:website":"http://www.olivieripellami.it",
    "wof:name":"Olivieri Pellami",
    "wof:placetype":"venue"
},
  "geometry": {"coordinates":[11.338365,45.527924],"type":"Point"}
}