{
  "type": "Feature",
  "properties": {
    "iso:country":"IT",
    "sg:address":"Via Milano 25 25126 Brescia",
    "sg:city":"Brescia",
    "sg:classifiers":[
        {
            "category":"Real Estate",
            "subcategory":"Real Estate Agent",
            "type":"Services"
        }
    ],
    "sg:phone":"+39 030 315522",
    "sg:postcode":"25126",
    "sg:province":"Brescia",
    "sg:tags":[
        "lacquer"
    ],
    "sg:website":"www.colorificiosifra.it",
    "wof:name":"Colorificio Sifra Sas",
    "wof:placetype":"venue"
},
  "geometry": {"coordinates":[9.614247,45.640415],"type":"Point"}
}