{
  "type": "Feature",
  "properties": {
    "iso:country":"IT",
    "sg:address":"Via Nazionale 93 24068 Seriate",
    "sg:city":"Seriate",
    "sg:classifiers":[
        {
            "category":"Parking",
            "subcategory":"Lot",
            "type":"Transportation"
        }
    ],
    "sg:phone":"+39 39035298457",
    "sg:postcode":"24068",
    "sg:province":"Bergamo",
    "sg:tags":[
        "transport",
        "road"
    ],
    "wof:name":"Panigada Trasporti Srl",
    "wof:placetype":"venue"
},
  "geometry": {"coordinates":[9.739511,45.68689],"type":"Point"}
}