{
  "type": "Feature",
  "properties": {
    "addr:full":"26, Viale Lazio 20135 Milano Milano Milano 20135",
    "addr:housenumber":"26",
    "addr:postcode":"20135;20135",
    "addr:street":"Viale Lazio",
    "iso:country":"IT",
    "sg:address":"26, Viale Lazio 20135 Milano",
    "sg:city":"Milano",
    "sg:classifiers":[
        {
            "category":"Shopping",
            "subcategory":"Computers & Home Electronics",
            "type":"Retail Goods"
        }
    ],
    "sg:phone":"+39 390 254 1941",
    "sg:postcode":"20135",
    "sg:province":"Milano",
    "sg:tags":[
        "electronic",
        "electrical",
        "equipment"
    ],
    "wof:name":"Tritecnica S.r.l.",
    "wof:placetype":"venue"
},
  "geometry": {"coordinates":[9.162553,45.385666],"type":"Point"}
}