{
  "type": "Feature",
  "properties": {
    "iso:country":"IT",
    "sg:address":"74011 Castellaneta",
    "sg:city":"Castellaneta",
    "sg:orig_category":"Macchine Ed Impianti Per Edilizia E Lavori Pubblici",
    "sg:phone":"+39 099 849 1701",
    "sg:postcode":"74011",
    "sg:province":"Taranto",
    "wof:name":"Todisco Michele Angelo",
    "wof:placetype":"venue"
},
  "geometry": {"coordinates":[16.888643,40.568573],"type":"Point"}
}