{
  "type": "Feature",
  "properties": {
    "iso:country":"IT",
    "sg:address":"38/e, Via Colombo Cristoforo 24046 Osio Sotto",
    "sg:city":"Osio Sotto",
    "sg:classifiers":[
        {
            "category":"Manufacturing",
            "subcategory":"Rubber & Plastics",
            "type":"Manufacturing & Wholesale Goods"
        }
    ],
    "sg:phone":"+39 39035807737",
    "sg:postcode":"24046",
    "sg:province":"Bergamo",
    "wof:name":"Utentor (s.r.l.)",
    "wof:placetype":"venue"
},
  "geometry": {"coordinates":[9.6581945419,45.6471786499],"type":"Point"}
}