{
  "type": "Feature",
  "properties": {
    "iso:country":"IT",
    "sg:address":"130, V. S. Marco 72020 Cellino S. Marco",
    "sg:classifiers":[
        {
            "category":"Food & Beverages",
            "subcategory":"Groceries & Convenience Stores",
            "type":"Retail Goods"
        }
    ],
    "sg:phone":"+39 0831 617865",
    "sg:postcode":"72020",
    "sg:province":"Brindisi",
    "sg:tags":[
        "drink"
    ],
    "sg:website":"http://www.cantineduepalme.it",
    "wof:name":"Cantine Due Palme Soc. Coop. A Rl",
    "wof:placetype":"venue"
},
  "geometry": {"coordinates":[17.954628,40.468349],"type":"Point"}
}