{
  "type": "Feature",
  "properties": {
    "iso:country":"IT",
    "sg:address":"7, Via Puia 33070 Brugnera",
    "sg:city":"Brugnera",
    "sg:classifiers":[
        {
            "category":"Home & Garden",
            "subcategory":"Home Furnishings",
            "type":"Retail Goods"
        }
    ],
    "sg:phone":"+39 0434 618111",
    "sg:postcode":"33070",
    "sg:province":"Pordenone",
    "sg:tags":[
        "household"
    ],
    "wof:name":"Presotto Industrie Mobili S.r.l.",
    "wof:placetype":"venue"
},
  "geometry": {"coordinates":[12.560739,45.885666],"type":"Point"}
}