{
  "type": "Feature",
  "properties": {
    "iso:country":"IT",
    "sg:address":"Via Umbria 35 10099 San Mauro Torinese",
    "sg:city":"San Mauro Torinese",
    "sg:orig_category":"Steel Bar Blanks",
    "sg:phone":"+39 011 223 6824",
    "sg:postcode":"10099",
    "sg:province":"Torino",
    "sg:website":"www.flainox.com",
    "wof:name":"Fla Spa",
    "wof:placetype":"venue"
},
  "geometry": {"coordinates":[7.747519,45.118061],"type":"Point"}
}