{
  "type": "Feature",
  "properties": {
    "iso:country":"IT",
    "sg:address":"10030 Vische",
    "sg:city":"Vische",
    "sg:orig_category":"Servizi E Lavori Per Arredamento E Industria Del Legno",
    "sg:phone":"+39 011 983 7506",
    "sg:postcode":"10030",
    "sg:province":"Torino",
    "wof:name":"Lasagna Savino",
    "wof:placetype":"venue"
},
  "geometry": {"coordinates":[7.945944,45.335201],"type":"Point"}
}