{
  "type": "Feature",
  "properties": {
    "iso:country":"IT",
    "sg:address":"Via Bergonzoli Giulio 1/5 20127 Milano",
    "sg:city":"Milano",
    "sg:classifiers":[
        {
            "category":"Sports & Exercise",
            "subcategory":"Playing Field",
            "type":"Entertainment"
        }
    ],
    "sg:phone":"+39 02 283151",
    "sg:postcode":"20127",
    "sg:province":"Milano",
    "sg:tags":[
        "cd-rom",
        "database"
    ],
    "sg:website":"www.ie-online.it",
    "wof:name":"Informazioni Editoriali I.e. Spa",
    "wof:placetype":"venue"
},
  "geometry": {"coordinates":[9.214708,45.48912],"type":"Point"}
}