{
  "type": "Feature",
  "properties": {
    "addr:full":"15, Via Per Gattinara 13851 Castelletto Cervo Castelletto Cervo Biella 13851",
    "addr:postcode":"13851;13851",
    "addr:street":"Via Per Gattinara",
    "iso:country":"IT",
    "sg:address":"15, Via Per Gattinara 13851 Castelletto Cervo",
    "sg:city":"Castelletto Cervo",
    "sg:classifiers":[
        {
            "category":"Manufacturing",
            "subcategory":"Rubber & Plastics",
            "type":"Manufacturing & Wholesale Goods"
        }
    ],
    "sg:phone":"+39 0161 859331",
    "sg:postcode":"13851",
    "sg:province":"Biella",
    "wof:name":"David S.r.l.",
    "wof:placetype":"venue"
},
  "geometry": {"coordinates":[8.2410125732,45.5248947144],"type":"Point"}
}