{
  "type": "Feature",
  "properties": {
    "iso:country":"IT",
    "sg:address":"1, Via Fagagna 33038 San Daniele Del Friuli",
    "sg:city":"San Daniele del Friuli",
    "sg:classifiers":[
        {
            "category":"Personal",
            "subcategory":"Shoe Repair & Shine",
            "type":"Services"
        }
    ],
    "sg:phone":"+39 0432 957341",
    "sg:postcode":"33038",
    "sg:province":"Udine",
    "sg:tags":[
        "leather"
    ],
    "wof:name":"Zapas (s.r.l.)",
    "wof:placetype":"venue"
},
  "geometry": {"coordinates":[13.016047,46.156227],"type":"Point"}
}