{
  "type": "Feature",
  "properties": {
    "iso:country":"IT",
    "sg:address":"24025 Gazzaniga",
    "sg:city":"Gazzaniga",
    "sg:orig_category":"Non-classified Establishments",
    "sg:phone":"+39 035 712314",
    "sg:postcode":"24025",
    "sg:province":"Bergamo",
    "wof:name":"Mobilificio Fattorini Srl",
    "wof:placetype":"venue"
},
  "geometry": {"coordinates":[9.677732,45.702732],"type":"Point"}
}