{
  "type": "Feature",
  "properties": {
    "iso:country":"IT",
    "sg:address":"73100 Lecce",
    "sg:city":"Lecce",
    "sg:orig_category":"Impiantistica E Prodotti Tecnologici Per Edilizia. Forniture Industriali Per Prevenzione, Controllo E Sicurezza",
    "sg:phone":"+39 0832 315171",
    "sg:postcode":"73100",
    "sg:province":"Lecce",
    "wof:name":"Le.li. Estintori",
    "wof:placetype":"venue"
},
  "geometry": {"coordinates":[18.185593,40.361286],"type":"Point"}
}