{
  "type": "Feature",
  "properties": {
    "iso:country":"IT",
    "sg:address":"57037 Portoferraio",
    "sg:city":"Portoferraio",
    "sg:orig_category":"Agenzie Marittime",
    "sg:phone":"+39 0565 930222",
    "sg:postcode":"57037",
    "sg:province":"Livorno",
    "wof:name":"Agenzia Viaggi E Turismo Tesi",
    "wof:placetype":"venue"
},
  "geometry": {"coordinates":[10.315622,42.812511],"type":"Point"}
}