{
  "type": "Feature",
  "properties": {
    "iso:country":"IT",
    "sg:address":"Via Toscana 9 46041 Asola",
    "sg:city":"Asola",
    "sg:classifiers":[
        {
            "category":"Shopping",
            "subcategory":"Baby Store",
            "type":"Retail Goods"
        }
    ],
    "sg:phone":"+39 0376 729521",
    "sg:postcode":"46041",
    "sg:province":"Mantova",
    "sg:tags":[
        "children's",
        "tights"
    ],
    "wof:name":"Verbena Srl",
    "wof:placetype":"venue"
},
  "geometry": {"coordinates":[10.397911,45.218876],"type":"Point"}
}