{
  "type": "Feature",
  "properties": {
    "iso:country":"IT",
    "sg:address":"Zona Industriale 66040 Piazzano Di Atessa",
    "sg:classifiers":[
        {
            "category":"Autos & Motor Vehicles",
            "subcategory":"Motorcycle Sales",
            "type":"Retail Goods"
        }
    ],
    "sg:phone":"+39 0872 8991",
    "sg:postcode":"66040",
    "sg:province":"Chieti",
    "sg:website":"www.hondaitalia.it",
    "wof:name":"Honda Italia Industriale Spa",
    "wof:placetype":"venue"
},
  "geometry": {"coordinates":[14.1671514511,42.3517913818],"type":"Point"}
}