{
  "type": "Feature",
  "properties": {
    "iso:country":"IT",
    "sg:address":"16152 Genova",
    "sg:city":"Genova",
    "sg:orig_category":"Lavorazioni Meccaniche E Servizi",
    "sg:phone":"+39 010 650 7131",
    "sg:postcode":"16152",
    "sg:province":"Genova",
    "wof:name":"Utensilfila (s.n.c.)",
    "wof:placetype":"venue"
},
  "geometry": {"coordinates":[8.868962,44.41518],"type":"Point"}
}