{
  "type": "Feature",
  "properties": {
    "iso:country":"IT",
    "sg:address":"80147 San Giorgio A Cremano",
    "sg:orig_category":"Prodotti Vari In Metallo",
    "sg:phone":"+39 081 596 9556",
    "sg:postcode":"80147",
    "sg:province":"Napoli",
    "wof:name":"Campania Funi",
    "wof:placetype":"venue"
},
  "geometry": {"coordinates":[14.3399133682,40.8427734375],"type":"Point"}
}