{
  "type": "Feature",
  "properties": {
    "iso:country":"IT",
    "sg:address":"36100 Vicenza",
    "sg:city":"Vicenza",
    "sg:orig_category":"Servizi Di Magazzinaggio E Movimentazione. Servizi Ausiliari Di Sorveglianza, Manutenzione E Pulizia. Servizi Per Aziende, Manifestazioni E Supporto Agli Scambi Commerciali",
    "sg:phone":"+39 0444 962010",
    "sg:postcode":"36100",
    "sg:province":"Vicenza",
    "wof:name":"Cegalin Pulizie E Servizi Soc. Coop. Arl",
    "wof:placetype":"venue"
},
  "geometry": {"coordinates":[11.561045,45.53619],"type":"Point"}
}