{
  "type": "Feature",
  "properties": {
    "addr:full":"25015 Desenzano Del Garda Desenzano del Garda Brescia 25015",
    "addr:postcode":"25015;25015",
    "iso:country":"IT",
    "sg:address":"25015 Desenzano Del Garda",
    "sg:city":"Desenzano del Garda",
    "sg:orig_category":"Prodotti Finiti Stampati. Shopping. Regalistica Aziendale",
    "sg:phone":"+39 030 914 4688",
    "sg:postcode":"25015",
    "sg:province":"Brescia",
    "wof:name":"Al-ani Manar",
    "wof:placetype":"venue"
},
  "geometry": {"coordinates":[10.5346260071,45.4659500122],"type":"Point"}
}