{
  "type": "Feature",
  "properties": {
    "iso:country":"IT",
    "sg:address":"4, Piazza Del Carmine 20121 Milano",
    "sg:city":"Milano",
    "sg:classifiers":[
        {
            "category":"Marine",
            "type":"Transportation"
        }
    ],
    "sg:phone":"+39 39028068151",
    "sg:postcode":"20121",
    "sg:province":"Milano",
    "sg:tags":[
        "transport",
        "sea"
    ],
    "wof:name":"Agenzia Marittima Prosper S.r.l.",
    "wof:placetype":"venue"
},
  "geometry": {"coordinates":[9.185421,45.470421],"type":"Point"}
}