{
  "type": "Feature",
  "properties": {
    "addr:full":"2/a, Via Fenzoni 48018 Faenza Faenza Ravenna 48018",
    "addr:housenumber":"2 / a",
    "addr:postcode":"48018;48018",
    "addr:street":"Via Fenzoni",
    "iso:country":"IT",
    "sg:address":"2/a, Via Fenzoni 48018 Faenza",
    "sg:city":"Faenza",
    "sg:classifiers":[
        {
            "category":"Shopping",
            "subcategory":"Crafts & Fabrics",
            "type":"Retail Goods"
        }
    ],
    "sg:phone":"+39 39054633027",
    "sg:postcode":"48018",
    "sg:province":"Ravenna",
    "sg:tags":[
        "linen"
    ],
    "wof:name":"Azzurra S.n.c. Di Guidi Walter E C.",
    "wof:placetype":"venue"
},
  "geometry": {"coordinates":[12.1965713501,44.4157295227],"type":"Point"}
}