{
  "type": "Feature",
  "properties": {
    "iso:country":"IT",
    "sg:address":"20090 Settala",
    "sg:city":"Settala",
    "sg:orig_category":"Prodotti Chimici Secondari. Medicinali E Prodotti Parafarmaceutici",
    "sg:phone":"+39 02 952451",
    "sg:postcode":"20090",
    "sg:province":"Milano",
    "wof:name":"Nuclear Laser Medicine Srl",
    "wof:placetype":"venue"
},
  "geometry": {"coordinates":[9.385679245,45.4442024231],"type":"Point"}
}