{
  "type": "Feature",
  "properties": {
    "addr:full":"Via Fontanili 26012 Castelleone Castelleone Cremona 26012",
    "addr:postcode":"26012;26012",
    "addr:street":"Via Fontanili",
    "iso:country":"IT",
    "sg:address":"Via Fontanili 26012 Castelleone",
    "sg:city":"Castelleone",
    "sg:classifiers":[
        {
            "category":"Building & Trades",
            "subcategory":"Construction",
            "type":"Services"
        }
    ],
    "sg:phone":"+39 0374 56003",
    "sg:postcode":"26012",
    "sg:province":"Cremona",
    "sg:tags":[
        "valve"
    ],
    "wof:name":"Rubival Inox Srl",
    "wof:placetype":"venue"
},
  "geometry": {"coordinates":[9.750232,45.294064],"type":"Point"}
}