{
  "type": "Feature",
  "properties": {
    "iso:country":"IT",
    "sg:address":"20131 Milano",
    "sg:city":"Milano",
    "sg:orig_category":"Prodotti Alimentari",
    "sg:phone":"+39 02 282 4977",
    "sg:postcode":"20131",
    "sg:province":"Milano",
    "wof:name":"Gatti Mario",
    "wof:placetype":"venue"
},
  "geometry": {"coordinates":[9.231595993,45.4879646301],"type":"Point"}
}