{
  "type": "Feature",
  "properties": {
    "addr:full":"12, Via Rossini Fr. Bariano 23873 Missaglia Missaglia Lecco 23873",
    "addr:postcode":"23873;23873",
    "addr:street":"Via Rossini Fr. Bariano",
    "iso:country":"IT",
    "sg:address":"12, Via Rossini Fr. Bariano 23873 Missaglia",
    "sg:city":"Missaglia",
    "sg:classifiers":[
        {
            "category":"Manufacturing",
            "subcategory":"Metals",
            "type":"Manufacturing & Wholesale Goods"
        }
    ],
    "sg:phone":"+39 039 920 1182",
    "sg:postcode":"23873",
    "sg:province":"Lecco",
    "sg:tags":[
        "metallurgy",
        "metalworking"
    ],
    "wof:name":"Casiraghi Giuseppe (s.r.l.)",
    "wof:placetype":"venue"
},
  "geometry": {"coordinates":[9.3900709152,45.8529815674],"type":"Point"}
}