{
  "type": "Feature",
  "properties": {
    "iso:country":"IT",
    "sg:address":"17027 Pietra Ligure",
    "sg:city":"Pietra Ligure",
    "sg:orig_category":"Abbigliamento Intimo, Calze E Costumi Da Bagno",
    "sg:phone":"+39 019 629000",
    "sg:postcode":"17027",
    "sg:province":"Savona",
    "wof:name":"Ninfea Snc",
    "wof:placetype":"venue"
},
  "geometry": {"coordinates":[8.28271,44.148861],"type":"Point"}
}