{
  "type": "Feature",
  "properties": {
    "iso:country":"IT",
    "sg:address":"23/a, Via Barsanti Eugenio 37139 Verona",
    "sg:city":"Verona",
    "sg:classifiers":[
        {
            "category":"Manufacturing",
            "subcategory":"Textiles",
            "type":"Manufacturing & Wholesale Goods"
        }
    ],
    "sg:phone":"+39 045 851 1013",
    "sg:postcode":"37139",
    "sg:province":"Verona",
    "sg:tags":[
        "leather",
        "raw",
        "material",
        "-"
    ],
    "wof:name":"Eurofoven S.r.l.",
    "wof:placetype":"venue"
},
  "geometry": {"coordinates":[10.991748,45.438366],"type":"Point"}
}