{
  "type": "Feature",
  "properties": {
    "addr:full":"40139 Bologna Bologna Bologna 40139",
    "addr:postcode":"40139;40139",
    "iso:country":"IT",
    "sg:address":"40139 Bologna",
    "sg:city":"Bologna",
    "sg:orig_category":"Pubblica Amministrazione",
    "sg:phone":"+39 051 450439",
    "sg:postcode":"40139",
    "sg:province":"Bologna",
    "wof:name":"Forze Armate/esercito/121 Reggimento Art.c Caserma Viali",
    "wof:placetype":"venue"
},
  "geometry": {"coordinates":[11.3938875198,44.4823875427],"type":"Point"}
}