{
  "type": "Feature",
  "properties": {
    "iso:country":"IT",
    "sg:address":"59013 Montemurlo",
    "sg:city":"Montemurlo",
    "sg:orig_category":"Bottoni",
    "sg:phone":"+39 0574 682505",
    "sg:postcode":"59013",
    "sg:province":"Prato",
    "wof:name":"Bottonificio Pratese Sas Di Salimbeni A. & C.",
    "wof:placetype":"venue"
},
  "geometry": {"coordinates":[11.059862,43.928516],"type":"Point"}
}