{
  "type": "Feature",
  "properties": {
    "addr:full":"66, Via Vittorio Veneto 37053 Cerea Cerea Verona 37053",
    "addr:postcode":"37053;37053",
    "addr:street":"Via Vittorio Veneto",
    "iso:country":"IT",
    "sg:address":"66, Via Vittorio Veneto 37053 Cerea",
    "sg:city":"Cerea",
    "sg:classifiers":[
        {
            "category":"Autos & Motor Vehicles",
            "subcategory":"Automobile Sales",
            "type":"Retail Goods"
        }
    ],
    "sg:phone":"+39 39044280377",
    "sg:postcode":"37053",
    "sg:province":"Verona",
    "sg:tags":[
        "industrial"
    ],
    "wof:name":"Officine Mirandola Veicoli Industriali (s.p.a.)",
    "wof:placetype":"venue"
},
  "geometry": {"coordinates":[11.219488,45.188499],"type":"Point"}
}