{
  "type": "Feature",
  "properties": {
    "addr:full":"00179 Roma Roma Roma 00179",
    "addr:postcode":"00179;00179",
    "iso:country":"IT",
    "sg:address":"00179 Roma",
    "sg:city":"Roma",
    "sg:orig_category":"Servizi Editoriali",
    "sg:phone":"+39 06 780 2912",
    "sg:postcode":"00179",
    "sg:province":"Roma",
    "wof:name":"Citta' Nuova Roma",
    "wof:placetype":"venue"
},
  "geometry": {"coordinates":[12.501509,41.857262],"type":"Point"}
}