{
  "type": "Feature",
  "properties": {
    "addr:full":"62100 Macerata Macerata Macerata 62100",
    "addr:postcode":"62100;62100",
    "iso:country":"IT",
    "sg:address":"62100 Macerata",
    "sg:city":"Macerata",
    "sg:orig_category":"Articoli Da Regalo. Regalistica Aziendale",
    "sg:phone":"+39 0733 281215",
    "sg:postcode":"62100",
    "sg:province":"Macerata",
    "wof:name":"Palmieri & Turchetto Sas",
    "wof:placetype":"venue"
},
  "geometry": {"coordinates":[13.487078,43.281216],"type":"Point"}
}