{
  "type": "Feature",
  "properties": {
    "addr:full":"17100 Savona Savona Savona 17100",
    "addr:postcode":"17100;17100",
    "iso:country":"IT",
    "sg:address":"17100 Savona",
    "sg:city":"Savona",
    "sg:orig_category":"Banche E Servizi Finanziari. Acqua, Luce, Gas E Societa' Di Esercizio Pubblico. Pubblica Amministrazione",
    "sg:phone":"+39 019 807754",
    "sg:postcode":"17100",
    "sg:province":"Savona",
    "wof:name":"Uffici Finanziari/sezioni Catastali",
    "wof:placetype":"venue"
},
  "geometry": {"coordinates":[7.779292,44.641384],"type":"Point"}
}