{
  "type": "Feature",
  "properties": {
    "iso:country":"IT",
    "sg:address":"57122 Livorno",
    "sg:city":"Livorno",
    "sg:orig_category":"Trasporti E Spedizioni Merci",
    "sg:phone":"+39 0586 837411",
    "sg:postcode":"57122",
    "sg:province":"Livorno",
    "wof:name":"Transalpe Srl",
    "wof:placetype":"venue"
},
  "geometry": {"coordinates":[10.310013,43.558689],"type":"Point"}
}