{
  "type": "Feature",
  "properties": {
    "addr:full":"175/177/r, Via Senese 50124 Firenze Firenze Firenze 50124",
    "addr:housenumber":"175 / 177 / r",
    "addr:postcode":"50124;50124",
    "addr:street":"Via Senese",
    "iso:country":"IT",
    "sg:address":"175/177/r, Via Senese 50124 Firenze",
    "sg:city":"Firenze",
    "sg:classifiers":[
        {
            "category":"Autos & Motor Vehicles",
            "subcategory":"Automobile Sales",
            "type":"Retail Goods"
        }
    ],
    "sg:phone":"+39 055 232 0235",
    "sg:postcode":"50124",
    "sg:province":"Firenze",
    "sg:tags":[
        "equipment",
        "transport"
    ],
    "wof:name":"Velmotor 2000 (s.r.l.)",
    "wof:placetype":"venue"
},
  "geometry": {"coordinates":[11.256902,43.768734],"type":"Point"}
}