{
  "type": "Feature",
  "properties": {
    "iso:country":"IT",
    "sg:address":"6, Corso Buenos Aires 16129 Genova",
    "sg:city":"Genova",
    "sg:classifiers":[
        {
            "category":"Banks & Credit Unions",
            "subcategory":"Investment Brokerage",
            "type":"Services"
        }
    ],
    "sg:phone":"+39 39010562844",
    "sg:postcode":"16129",
    "sg:province":"Genova",
    "sg:tags":[
        "-",
        "transport",
        "related"
    ],
    "wof:name":"Oliva Spedizioni Spa",
    "wof:placetype":"venue"
},
  "geometry": {"coordinates":[8.950065,44.403214],"type":"Point"}
}