{
  "type": "Feature",
  "properties": {
    "addr:full":"18038 Sanremo Imperia 18038",
    "addr:postcode":"18038;18038",
    "iso:country":"IT",
    "sg:address":"18038 Sanremo",
    "sg:orig_category":"Abbigliamento Intimo, Calze E Costumi Da Bagno",
    "sg:phone":"+39 0184 515022",
    "sg:postcode":"18038",
    "sg:province":"Imperia",
    "wof:name":"Sirena Di Alberto Appicciutoli",
    "wof:placetype":"venue"
},
  "geometry": {"coordinates":[7.807105,43.826218],"type":"Point"}
}