{
  "type": "Feature",
  "properties": {
    "addr:full":"20020 Cogliate Cogliate Milano 20020",
    "addr:postcode":"20020;20020",
    "iso:country":"IT",
    "sg:address":"20020 Cogliate",
    "sg:city":"Cogliate",
    "sg:orig_category":"Carni, Salumi E Pesci",
    "sg:phone":"+39 02 966 1289",
    "sg:postcode":"20020",
    "sg:province":"Milano",
    "wof:name":"Ruggeri Giosue'",
    "wof:placetype":"venue"
},
  "geometry": {"coordinates":[9.103828,45.643845],"type":"Point"}
}