{
  "type": "Feature",
  "properties": {
    "addr:full":"95131 Catania Catania Catania 95131",
    "addr:postcode":"95131;95131",
    "iso:country":"IT",
    "sg:address":"95131 Catania",
    "sg:city":"Catania",
    "sg:orig_category":"Lotto, Ricevitorie Concorsi E Giocate",
    "sg:phone":"+39 095 325248",
    "sg:postcode":"95131",
    "sg:province":"Catania",
    "wof:name":"Totoricevitoria Zappala' Snc Di Pappalardo Marcello E Pappalardo Alessandro",
    "wof:placetype":"venue"
},
  "geometry": {"coordinates":[15.1013565063,37.5096168518],"type":"Point"}
}