{
  "type": "Feature",
  "properties": {
    "addr:full":"46, V. Leonetti 81100 Caserta Caserta Caserta 81100",
    "addr:housenumber":"46",
    "addr:postcode":"81100;81100",
    "addr:street":"V. Leonetti",
    "iso:country":"IT",
    "sg:address":"46, V. Leonetti 81100 Caserta",
    "sg:city":"Caserta",
    "sg:classifiers":[
        {
            "category":"Wholesale",
            "subcategory":"Drugs",
            "type":"Manufacturing & Wholesale Goods"
        }
    ],
    "sg:phone":"+39 0823 321182",
    "sg:postcode":"81100",
    "sg:province":"Caserta",
    "sg:tags":[
        "chemical",
        "pharmaceutical"
    ],
    "sg:website":"http://www.ripar.com",
    "wof:name":"Ripar Cosmetici",
    "wof:placetype":"venue"
},
  "geometry": {"coordinates":[14.332834,41.076344],"type":"Point"}
}