{
  "type": "Feature",
  "properties": {
    "addr:full":"2, Via Ploner Pietro 46100 Mantova Mantova Mantova 46100",
    "addr:postcode":"46100;46100",
    "addr:street":"Via Ploner Pietro",
    "iso:country":"IT",
    "sg:address":"2, Via Ploner Pietro 46100 Mantova",
    "sg:city":"Mantova",
    "sg:classifiers":[
        {
            "category":"Manufacturing",
            "subcategory":"Wood Products",
            "type":"Manufacturing & Wholesale Goods"
        }
    ],
    "sg:phone":"+39 0376 374213",
    "sg:postcode":"46100",
    "sg:province":"Mantova",
    "sg:tags":[
        "furniture"
    ],
    "wof:name":"Agape (s.p.a.)",
    "wof:placetype":"venue"
},
  "geometry": {"coordinates":[10.84667,45.138367],"type":"Point"}
}