{
  "type": "Feature",
  "properties": {
    "iso:country":"IT",
    "sg:address":"2, Via Varese 21047 Saronno",
    "sg:city":"Saronno",
    "sg:classifiers":[
        {
            "category":"Food & Beverages",
            "subcategory":"Groceries & Convenience Stores",
            "type":"Retail Goods"
        }
    ],
    "sg:phone":"+39 02 9670 0866",
    "sg:postcode":"21047",
    "sg:province":"Varese",
    "sg:tags":[
        "product",
        "related"
    ],
    "wof:name":"Silca (s.p.a.)",
    "wof:placetype":"venue"
},
  "geometry": {"coordinates":[9.0354690552,45.6119995117],"type":"Point"}
}