{
  "type": "Feature",
  "properties": {
    "addr:full":"10080 Rivara Rivara Torino 10080",
    "addr:postcode":"10080;10080",
    "iso:country":"IT",
    "sg:address":"10080 Rivara",
    "sg:city":"Rivara",
    "sg:orig_category":"Pubblica Amministrazione",
    "sg:phone":"+39 0124 474716",
    "sg:postcode":"10080",
    "sg:province":"Torino",
    "wof:name":"Comunita' Montana Alto Canavese",
    "wof:placetype":"venue"
},
  "geometry": {"coordinates":[7.6252450943,45.3334770203],"type":"Point"}
}