{
  "type": "Feature",
  "properties": {
    "iso:country":"IT",
    "sg:address":"19034 Ortonovo",
    "sg:city":"Ortonovo",
    "sg:orig_category":"Banche E Servizi Finanziari",
    "sg:phone":"+39 0187 66540",
    "sg:postcode":"19034",
    "sg:province":"La Spezia",
    "wof:name":"Cassa Di Risparmio Della Spezia",
    "wof:placetype":"venue"
},
  "geometry": {"coordinates":[9.768391,44.145016],"type":"Point"}
}