{
  "type": "Feature",
  "properties": {
    "iso:country":"IT",
    "sg:address":"Via Metauro 11 61033 Fermignano",
    "sg:city":"Fermignano",
    "sg:classifiers":[
        {
            "category":"Industrial Area",
            "type":"Public Place"
        }
    ],
    "sg:phone":"+39 0722 330048",
    "sg:postcode":"61033",
    "sg:province":"Pesaro E Urbino",
    "sg:tags":[
        "shed"
    ],
    "sg:website":"www.amdpaolini.com",
    "wof:name":"Comepa Srl",
    "wof:placetype":"venue"
},
  "geometry": {"coordinates":[12.59753,43.652134],"type":"Point"}
}