{
  "type": "Feature",
  "properties": {
    "iso:country":"IT",
    "sg:address":"70023 Gioia Del Colle",
    "sg:city":"Gioia del Colle",
    "sg:orig_category":"Lattiero Casearia Industria - Macchine",
    "sg:phone":"+39 080 343 2036",
    "sg:postcode":"70023",
    "sg:province":"Bari",
    "wof:name":"Alfa Impianti Di Nicola Capurso & C. Snc",
    "wof:placetype":"venue"
},
  "geometry": {"coordinates":[16.930853,40.795818],"type":"Point"}
}