{
  "type": "Feature",
  "properties": {
    "iso:country":"IT",
    "sg:address":"1, Via Castellano 63019 Sant'elpidio A Mare",
    "sg:city":"Castellano",
    "sg:classifiers":[
        {
            "category":"Manufacturing",
            "subcategory":"Textiles",
            "type":"Manufacturing & Wholesale Goods"
        }
    ],
    "sg:phone":"+39 0734 990724",
    "sg:postcode":"63019",
    "sg:province":"Ascoli Piceno",
    "sg:tags":[
        "leather",
        "raw",
        "material",
        "-"
    ],
    "wof:name":"Lattanzi Macchine (s.p.a.)",
    "wof:placetype":"venue"
},
  "geometry": {"coordinates":[13.746009,43.275272],"type":"Point"}
}