{
  "type": "Feature",
  "properties": {
    "iso:country":"IT",
    "sg:address":"Via Valchiampo 5 36050 Zermeghedo",
    "sg:city":"Zermeghedo",
    "sg:classifiers":[
        {
            "category":"Manufacturing",
            "subcategory":"Leather Goods",
            "type":"Manufacturing & Wholesale Goods"
        }
    ],
    "sg:phone":"+39 0444 484233",
    "sg:postcode":"36050",
    "sg:province":"Vicenza",
    "sg:tags":[
        "synthetic",
        "series",
        "product",
        "production",
        "customized"
    ],
    "sg:website":"www.conceriasada.com",
    "wof:name":"Sa.da. S.p.a.",
    "wof:placetype":"venue"
},
  "geometry": {"coordinates":[11.540307,45.545906],"type":"Point"}
}