{
  "type": "Feature",
  "properties": {
    "iso:country":"IT",
    "sg:address":"74100 Taranto",
    "sg:city":"Taranto",
    "sg:orig_category":"Automobili E Mezzi Di Trasporto. Riparazione Dei Mezzi Di Trasporto",
    "sg:phone":"+39 099 779 1771",
    "sg:postcode":"74100",
    "sg:province":"Taranto",
    "sg:website":"http://www.puntogommeta.it",
    "wof:name":"Puntogomme Taranto Srl",
    "wof:placetype":"venue"
},
  "geometry": {"coordinates":[17.313931,40.503941],"type":"Point"}
}