{
  "type": "Feature",
  "properties": {
    "addr:full":"62, Via Trani 70051 Barletta Barletta Bari 70051",
    "addr:postcode":"70051;70051",
    "addr:street":"Via Trani",
    "iso:country":"IT",
    "sg:address":"62, Via Trani 70051 Barletta",
    "sg:city":"Barletta",
    "sg:classifiers":[
        {
            "category":"Manufacturing",
            "subcategory":"Rubber & Plastics",
            "type":"Manufacturing & Wholesale Goods"
        }
    ],
    "sg:phone":"+39 0883 348190",
    "sg:postcode":"70051",
    "sg:province":"Bari",
    "sg:tags":[
        "packaging",
        "material",
        "-"
    ],
    "wof:name":"Fil Plastic Di Filannino Giuseppe",
    "wof:placetype":"venue"
},
  "geometry": {"coordinates":[16.316192627,41.306427002],"type":"Point"}
}