{
  "type": "Feature",
  "properties": {
    "addr:full":"09045 Quartu S.elena Cagliari 09045",
    "addr:postcode":"09045;09045",
    "addr:street":"S.Elena Cagliari",
    "iso:country":"IT",
    "sg:address":"09045 Quartu S.elena",
    "sg:orig_category":"Autoaccessori - Commercio",
    "sg:phone":"+39 070 810772",
    "sg:postcode":"09045",
    "sg:province":"Cagliari",
    "wof:name":"Sariel",
    "wof:placetype":"venue"
},
  "geometry": {"coordinates":[9.189857,39.246136],"type":"Point"}
}