{
  "type": "Feature",
  "properties": {
    "iso:country":"IT",
    "sg:address":"26867 Somaglia",
    "sg:city":"Somaglia",
    "sg:orig_category":"Prodotti E Manufatti In Materie Plastiche. Articoli Per Imballaggio E Confezionamento",
    "sg:phone":"+39 0377 570190",
    "sg:postcode":"26867",
    "sg:province":"Lodi",
    "wof:name":"Euro - Tank Nord S.r.l.",
    "wof:placetype":"venue"
},
  "geometry": {"coordinates":[9.6351232529,45.1553497314],"type":"Point"}
}