{
  "type": "Feature",
  "properties": {
    "iso:country":"IT",
    "sg:address":"00187 Roma",
    "sg:city":"Roma",
    "sg:orig_category":"Istituti Di Bellezza",
    "sg:phone":"+39 06 474 6072",
    "sg:postcode":"00187",
    "sg:province":"Roma",
    "wof:name":"Modafferi",
    "wof:placetype":"venue"
},
  "geometry": {"coordinates":[12.383075,42.134842],"type":"Point"}
}