{
  "type": "Feature",
  "properties": {
    "iso:country":"IT",
    "sg:address":"Via G. Garibaldi 68 40066 Pieve Di Cento",
    "sg:city":"Pieve di Cento",
    "sg:classifiers":[
        {
            "category":"Home & Garden",
            "subcategory":"Building Materials",
            "type":"Retail Goods"
        }
    ],
    "sg:phone":"+39 051 975050",
    "sg:postcode":"40066",
    "sg:province":"Bologna",
    "sg:tags":[
        "cord",
        "packing"
    ],
    "wof:name":"Campanini Ugo Spa",
    "wof:placetype":"venue"
},
  "geometry": {"coordinates":[11.3464813232,44.4942207336],"type":"Point"}
}