{
  "type": "Feature",
  "properties": {
    "iso:country":"IT",
    "sg:address":"Via L. Da Vinci 24-z.i. 63030 Acquaviva Picena",
    "sg:city":"Acquaviva Picena",
    "sg:orig_category":"Wire Rope Cores",
    "sg:phone":"+39 0735 582556",
    "sg:postcode":"63030",
    "sg:province":"Ascoli Piceno",
    "sg:website":"www.eurofuni.com",
    "wof:name":"Eurofuni Srl",
    "wof:placetype":"venue"
},
  "geometry": {"coordinates":[13.844181,42.954266],"type":"Point"}
}