{
  "type": "Feature",
  "properties": {
    "addr:full":"20123 Milano Milano Milano 20123",
    "addr:postcode":"20123;20123",
    "iso:country":"IT",
    "sg:address":"20123 Milano",
    "sg:city":"Milano",
    "sg:orig_category":"Servizi Ausiliari Di Analisi, Controllo E Ricerca",
    "sg:phone":"+39 02 481 5718",
    "sg:postcode":"20123",
    "sg:province":"Milano",
    "wof:name":"Centro Ricerche Progetti",
    "wof:placetype":"venue"
},
  "geometry": {"coordinates":[9.173666,45.468052],"type":"Point"}
}