{
  "type": "Feature",
  "properties": {
    "iso:country":"IT",
    "sg:address":"Via Cagnola 35a 20081 Abbiategrasso",
    "sg:city":"Abbiategrasso",
    "sg:classifiers":[
        {
            "category":"Manufacturing",
            "subcategory":"Glass & Minerals",
            "type":"Manufacturing & Wholesale Goods"
        }
    ],
    "sg:phone":"+39 02 9496 0368",
    "sg:postcode":"20081",
    "sg:province":"Milano",
    "sg:tags":[
        "machine",
        "tool",
        "working"
    ],
    "wof:name":"Delta Srl",
    "wof:placetype":"venue"
},
  "geometry": {"coordinates":[8.919808,45.385742],"type":"Point"}
}