{
  "type": "Feature",
  "properties": {
    "iso:country":"IT",
    "sg:address":"31050 Vedelago",
    "sg:city":"Vedelago",
    "sg:orig_category":"Abbigliamento - Vendita Al Dettaglio",
    "sg:phone":"+39 0423 400276",
    "sg:postcode":"31050",
    "sg:province":"Treviso",
    "wof:name":"Gerolimetto Abbigliamento Sas Di Gerolimetto Maurizio & C.",
    "wof:placetype":"venue"
},
  "geometry": {"coordinates":[12.237485,45.65144],"type":"Point"}
}