{
  "type": "Feature",
  "properties": {
    "addr:full":"20050 Lesmo Lesmo Milano 20050",
    "addr:postcode":"20050;20050",
    "iso:country":"IT",
    "sg:address":"20050 Lesmo",
    "sg:city":"Lesmo",
    "sg:orig_category":"Trattamenti Termici E Superficiali Metalli, Galvanotecnica",
    "sg:phone":"+39 039 688 8052",
    "sg:postcode":"20050",
    "sg:province":"Milano",
    "wof:name":"Eurocoating Sas Di Martini Carlo & C.",
    "wof:placetype":"venue"
},
  "geometry": {"coordinates":[9.176076,45.463623],"type":"Point"}
}