{
  "type": "Feature",
  "properties": {
    "addr:full":"00062 Bracciano Bracciano Roma 00062",
    "addr:postcode":"00062;roma 00062",
    "iso:country":"IT",
    "sg:address":"00062 Bracciano",
    "sg:city":"Bracciano",
    "sg:orig_category":"Automobili E Mezzi Di Trasporto",
    "sg:phone":"+39 06 998 4101",
    "sg:postcode":"00062",
    "sg:province":"Roma",
    "wof:name":"Alenia Aerospazio Div.spazio",
    "wof:placetype":"venue"
},
  "geometry": {"coordinates":[12.167665,42.100262],"type":"Point"}
}