{
  "type": "Feature",
  "properties": {
    "addr:full":"26034 Piadena Piadena Cremona 26034",
    "addr:postcode":"26034;26034",
    "iso:country":"IT",
    "sg:address":"26034 Piadena",
    "sg:city":"Piadena",
    "sg:orig_category":"Elettrotecnica Industriale, Prodotti E Apparecchiature",
    "sg:phone":"+39 0375 380260",
    "sg:postcode":"26034",
    "sg:province":"Cremona",
    "wof:name":"Info Project S.r.l.",
    "wof:placetype":"venue"
},
  "geometry": {"coordinates":[10.02235,45.131363],"type":"Point"}
}