{
  "type": "Feature",
  "properties": {
    "addr:full":"9, Via Tiziano Vecellio 31025 Santa Lucia Di Piave Santa Lucia di Piave Treviso 31025",
    "addr:postcode":"31025;31025",
    "addr:street":"Via Tiziano Vecellio",
    "iso:country":"IT",
    "sg:address":"9, Via Tiziano Vecellio 31025 Santa Lucia Di Piave",
    "sg:city":"Santa Lucia di Piave",
    "sg:classifiers":[
        {
            "category":"Manufacturing",
            "subcategory":"Metals",
            "type":"Manufacturing & Wholesale Goods"
        }
    ],
    "sg:phone":"+39 0438 460676",
    "sg:postcode":"31025",
    "sg:province":"Treviso",
    "sg:tags":[
        "processing"
    ],
    "wof:name":"Tecnometal (s.n.c.)",
    "wof:placetype":"venue"
},
  "geometry": {"coordinates":[12.2979679108,45.8584365845],"type":"Point"}
}