{
  "type": "Feature",
  "properties": {
    "addr:full":"Via Priverno 20; Latina; 04100 Latina Latina 04100",
    "addr:housenumber":"20",
    "addr:postcode":"04100;04100",
    "addr:street":"Via Priverno",
    "iso:country":"IT",
    "sg:address":"Via Priverno 20; Latina; 04100",
    "sg:city":"Latina",
    "sg:classifiers":[
        {
            "category":"Banks & Credit Unions",
            "subcategory":"Bank",
            "type":"Services"
        }
    ],
    "sg:phone":"+39 0773 6741",
    "sg:postcode":"04100",
    "sg:province":"Latina",
    "wof:name":"Banco Di Napoli Spa",
    "wof:placetype":"venue"
},
  "geometry": {"coordinates":[12.908578,41.45591],"type":"Point"}
}