{
  "type": "Feature",
  "properties": {
    "addr:full":"37021 Bosco Chiesanuova Bosco Chiesanuova Verona 37021",
    "addr:postcode":"37021;37021",
    "iso:country":"IT",
    "sg:address":"37021 Bosco Chiesanuova",
    "sg:city":"Bosco Chiesanuova",
    "sg:orig_category":"Pubblica Amministrazione",
    "sg:phone":"+39 045 705 0730",
    "sg:postcode":"37021",
    "sg:province":"Verona",
    "wof:name":"Corpo Forestale Dello Stato",
    "wof:placetype":"venue"
},
  "geometry": {"coordinates":[10.9940252304,45.4374809265],"type":"Point"}
}