{
  "type": "Feature",
  "properties": {
    "addr:full":"41012 Carpi Carpi Modena 41012",
    "addr:postcode":"41012;41012",
    "iso:country":"IT",
    "sg:address":"41012 Carpi",
    "sg:city":"Carpi",
    "sg:orig_category":"Prodotti E Manufatti In Materie Plastiche. Forniture Per Attivita' Industriali",
    "sg:phone":"+39 059 654514",
    "sg:postcode":"41012",
    "sg:province":"Modena",
    "wof:name":"Eurocom Srl",
    "wof:placetype":"venue"
},
  "geometry": {"coordinates":[10.9289970398,44.6566467285],"type":"Point"}
}