{
  "type": "Feature",
  "properties": {
    "addr:full":"35020 Casalserugo Casalserugo Padova 35020",
    "addr:postcode":"35020;35020",
    "iso:country":"IT",
    "sg:address":"35020 Casalserugo",
    "sg:city":"Casalserugo",
    "sg:orig_category":"Abbigliamento Esterno, Maglierie E Pelliccerie",
    "sg:phone":"+39 049 874 0299",
    "sg:postcode":"35020",
    "sg:province":"Padova",
    "wof:name":"Manifattura Corona (s.p.a.)",
    "wof:placetype":"venue"
},
  "geometry": {"coordinates":[11.909154,45.314991],"type":"Point"}
}