{
  "type": "Feature",
  "properties": {
    "iso:country":"IT",
    "sg:address":"63033 Monteprandone",
    "sg:city":"Monteprandone",
    "sg:orig_category":"Agricoltura, Orticoltura E Floricoltura",
    "sg:phone":"+39 0735 704051",
    "sg:postcode":"63033",
    "sg:province":"Ascoli Piceno",
    "wof:name":"Orsini Gino Damiani Filippo Sas",
    "wof:placetype":"venue"
},
  "geometry": {"coordinates":[13.833565,42.920437],"type":"Point"}
}