{
  "type": "Feature",
  "properties": {
    "iso:country":"IT",
    "sg:address":"70121 Bari",
    "sg:city":"Bari",
    "sg:orig_category":"Scuole E Servizi Scolastici. Ricerca, Selezione E Formazione Del Personale",
    "sg:phone":"+39 080 521 5800",
    "sg:postcode":"70121",
    "sg:province":"Bari",
    "sg:website":"http://www.euroaccademia.it",
    "wof:name":"Euroaccademiabari Sas",
    "wof:placetype":"venue"
},
  "geometry": {"coordinates":[16.871294,41.119968],"type":"Point"}
}