{
  "type": "Feature",
  "properties": {
    "addr:full":"16146 Genova Genova Genova 16146",
    "addr:postcode":"16146;16146",
    "iso:country":"IT",
    "sg:address":"16146 Genova",
    "sg:city":"Genova",
    "sg:classifiers":[
        {
            "category":"Health Services",
            "subcategory":"Health Practitioner",
            "type":"Services"
        }
    ],
    "sg:phone":"+39 010 386418",
    "sg:postcode":"16146",
    "sg:province":"Genova",
    "sg:tags":[
        "medici"
    ],
    "wof:name":"Rescalli Guido",
    "wof:placetype":"venue"
},
  "geometry": {"coordinates":[8.9757328033,44.3953132629],"type":"Point"}
}