{
  "type": "Feature",
  "properties": {
    "addr:full":"35, Via Crimea 62012 Civitanova Marche Civitanova Marche Macerata 62012",
    "addr:postcode":"62012;62012",
    "addr:street":"Via Crimea",
    "iso:country":"IT",
    "sg:address":"35, Via Crimea 62012 Civitanova Marche",
    "sg:city":"Civitanova Marche",
    "sg:classifiers":[
        {
            "category":"Personal",
            "subcategory":"Shoe Repair & Shine",
            "type":"Services"
        }
    ],
    "sg:phone":"+39 0733 816046",
    "sg:postcode":"62012",
    "sg:province":"Macerata",
    "sg:tags":[
        "leather"
    ],
    "wof:name":"Mario Rapagnani (srl)",
    "wof:placetype":"venue"
},
  "geometry": {"coordinates":[13.728028,43.29958],"type":"Point"}
}