{
  "type": "Feature",
  "properties": {
    "addr:full":"Via Pio La Torre 4 60022 Castelfidardo Castelfidardo Ancona 60022",
    "addr:housenumber":"4",
    "addr:postcode":"60022;60022",
    "addr:street":"Via Pio La Torre",
    "iso:country":"IT",
    "sg:address":"Via Pio La Torre 4 60022 Castelfidardo",
    "sg:city":"Castelfidardo",
    "sg:classifiers":[
        {
            "category":"Military Area",
            "subcategory":"Air Force Base",
            "type":"Public Place"
        }
    ],
    "sg:phone":"+39 071 780450",
    "sg:postcode":"60022",
    "sg:province":"Ancona",
    "sg:tags":[
        "case",
        "box",
        "jewellery"
    ],
    "sg:website":"www.fraba.it",
    "wof:name":"Fra.ba Di Bambozzi A. & A.snc",
    "wof:placetype":"venue"
},
  "geometry": {"coordinates":[13.543146,43.455254],"type":"Point"}
}