{
  "type": "Feature",
  "properties": {
    "addr:full":"44042 Cento Cento Ferrara 44042",
    "addr:postcode":"44042;44042",
    "iso:country":"IT",
    "sg:address":"44042 Cento",
    "sg:city":"Cento",
    "sg:classifiers":[
        {
            "category":"Health Services",
            "subcategory":"Health Practitioner",
            "type":"Services"
        }
    ],
    "sg:phone":"+39 051 902008",
    "sg:postcode":"44042",
    "sg:province":"Ferrara",
    "sg:tags":[
        "medici"
    ],
    "wof:name":"Pirani Alessandro",
    "wof:placetype":"venue"
},
  "geometry": {"coordinates":[11.6068162918,44.8583564758],"type":"Point"}
}