{
  "type": "Feature",
  "properties": {
    "addr:full":"2, Via F.lli Rosselli 15079 Sezzadio Sezzadio Alessandria 15079",
    "addr:postcode":"15079;15079",
    "addr:street":"Via F.Lli Rosselli",
    "iso:country":"IT",
    "sg:address":"2, Via F.lli Rosselli 15079 Sezzadio",
    "sg:city":"Sezzadio",
    "sg:classifiers":[
        {
            "category":"Wholesale",
            "subcategory":"Machinery & Supplies",
            "type":"Manufacturing & Wholesale Goods"
        }
    ],
    "sg:phone":"+39 0131 703117",
    "sg:postcode":"15079",
    "sg:province":"Alessandria",
    "sg:tags":[
        "-",
        "agriculture",
        "equipment"
    ],
    "wof:name":"Abbriata Giovanni S.r.l.",
    "wof:placetype":"venue"
},
  "geometry": {"coordinates":[8.616951,44.913216],"type":"Point"}
}