{
  "type": "Feature",
  "properties": {
    "addr:full":"Via Galilei, 171 - Fossatone 40059 Medicina Medicina Bologna 40059",
    "addr:housenumber":"171",
    "addr:postcode":"40059;40059",
    "addr:street":"Via Galilei;Fossatone",
    "iso:country":"IT",
    "sg:address":"Via Galilei, 171 - Fossatone 40059 Medicina",
    "sg:city":"Medicina",
    "sg:orig_category":"Petrol Flaps For Cars",
    "sg:phone":"+39 051 856324",
    "sg:postcode":"40059",
    "sg:province":"Bologna",
    "sg:website":"www.farmagroup.it",
    "wof:name":"Nuova F.a.a.b. Srl",
    "wof:placetype":"venue"
},
  "geometry": {"coordinates":[11.3464813232,44.4942207336],"type":"Point"}
}