{
  "type": "Feature",
  "properties": {
    "iso:country":"IT",
    "sg:address":"00187 Roma",
    "sg:city":"Roma",
    "sg:orig_category":"Articoli Regalo - Vendita Al Dettaglio",
    "sg:phone":"+39 06 445 2389",
    "sg:postcode":"00187",
    "sg:province":"Roma",
    "sg:website":"http://www.rinaldipens.com",
    "wof:name":"Rinaldi",
    "wof:placetype":"venue"
},
  "geometry": {"coordinates":[12.4468,42.105164],"type":"Point"}
}