{
  "type": "Feature",
  "properties": {
    "iso:country":"IT",
    "sg:address":"20144 Milano",
    "sg:city":"Milano",
    "sg:orig_category":"Servizi E Lavori Per Abbigliamento E Pelletterie",
    "sg:phone":"+39 02 4895 2231",
    "sg:postcode":"20144",
    "sg:province":"Milano",
    "wof:name":"Loria Frigoriferi (s.r.l.)",
    "wof:placetype":"venue"
},
  "geometry": {"coordinates":[9.160146,45.455471],"type":"Point"}
}