{
  "type": "Feature",
  "properties": {
    "iso:country":"IT",
    "sg:address":"23883 Brivio",
    "sg:city":"Brivio",
    "sg:orig_category":"Pompe",
    "sg:phone":"+39 039 532 1096",
    "sg:postcode":"23883",
    "sg:province":"Lecco",
    "wof:name":"Pressitalia Snc",
    "wof:placetype":"venue"
},
  "geometry": {"coordinates":[9.4253149033,45.7548522949],"type":"Point"}
}