{
  "type": "Feature",
  "properties": {
    "iso:country":"IT",
    "sg:address":"73043 Copertino",
    "sg:city":"Copertino",
    "sg:orig_category":"Macchine E Forniture Per Ecologia E Smaltimento Rifiuti. Termotecnica E Riscaldamento, Apparecchiature E Servizi",
    "sg:phone":"+39 0832 948450",
    "sg:postcode":"73043",
    "sg:province":"Lecce",
    "wof:name":"Tecnoconfort Di Tarantino P. & M. Snc",
    "wof:placetype":"venue"
},
  "geometry": {"coordinates":[18.039917,40.271496],"type":"Point"}
}