{
  "type": "Feature",
  "properties": {
    "addr:full":"98121 Messina Messina Messina 98121",
    "addr:postcode":"98121;98121",
    "iso:country":"IT",
    "sg:address":"98121 Messina",
    "sg:city":"Messina",
    "sg:orig_category":"Servizi Culturali E Per Lo Spettacolo. Musica",
    "sg:phone":"+39 090 51558",
    "sg:postcode":"98121",
    "sg:province":"Messina",
    "sg:website":"http://www.piparomusica.it",
    "wof:name":"Piparo Sas Di Alessandro E Gabriella Piparo E C.",
    "wof:placetype":"venue"
},
  "geometry": {"coordinates":[15.55795,38.20248],"type":"Point"}
}