{
  "type": "Feature",
  "properties": {
    "addr:full":"190, Via Spilimbergo 33034 Fagagna Fagagna Udine 33034",
    "addr:housenumber":"190",
    "addr:postcode":"33034;33034",
    "addr:street":"Via Spilimbergo",
    "iso:country":"IT",
    "sg:address":"190, Via Spilimbergo 33034 Fagagna",
    "sg:city":"Fagagna",
    "sg:classifiers":[
        {
            "category":"Professional",
            "subcategory":"Engineering",
            "type":"Services"
        }
    ],
    "sg:phone":"+39 0432 801276",
    "sg:postcode":"33034",
    "sg:province":"Udine",
    "sg:tags":[
        "machine",
        "-",
        "mechanical"
    ],
    "wof:name":"Berton Calortecnica S.r.l.",
    "wof:placetype":"venue"
},
  "geometry": {"coordinates":[13.155867,46.08717],"type":"Point"}
}