{
  "type": "Feature",
  "properties": {
    "iso:country":"IT",
    "sg:address":"21049 Tradate",
    "sg:city":"Tradate",
    "sg:orig_category":"Tessuti Arredamento, Tende E Tappeti. Forniture Per Edilizia E Lavori Pubblici",
    "sg:phone":"+39 0331 845540",
    "sg:postcode":"21049",
    "sg:province":"Varese",
    "wof:name":"Linea Casa Snc Di Chiarotto Gabriella & C.",
    "wof:placetype":"venue"
},
  "geometry": {"coordinates":[8.91902,45.712749],"type":"Point"}
}