{
  "type": "Feature",
  "properties": {
    "addr:full":"90151 Palermo Palermo Palermo 90151",
    "addr:postcode":"90151;90151",
    "iso:country":"IT",
    "sg:address":"90151 Palermo",
    "sg:city":"Palermo",
    "sg:orig_category":"Bevande, Vini E Liquori",
    "sg:phone":"+39 091 530517",
    "sg:postcode":"90151",
    "sg:province":"Palermo",
    "wof:name":"C.i.a. Srl Commercio Ingrosso Alimentari",
    "wof:placetype":"venue"
},
  "geometry": {"coordinates":[13.307821,38.19302],"type":"Point"}
}