{
  "type": "Feature",
  "properties": {
    "iso:country":"IT",
    "sg:address":"Viale Dante 24 15048 Valenza",
    "sg:city":"Valenza",
    "sg:classifiers":[
        {
            "category":"Manufacturing",
            "subcategory":"Jewelry",
            "type":"Manufacturing & Wholesale Goods"
        }
    ],
    "sg:phone":"+39 0131 945296",
    "sg:postcode":"15048",
    "sg:province":"Alessandria",
    "sg:tags":[
        "jewel"
    ],
    "sg:website":"www.crivelligioielli.com",
    "wof:name":"Crivelli - S.r.l.",
    "wof:placetype":"venue"
},
  "geometry": {"coordinates":[8.64107,45.010155],"type":"Point"}
}