{
  "type": "Feature",
  "properties": {
    "iso:country":"IT",
    "sg:address":"21050 Castelseprio",
    "sg:city":"Castelseprio",
    "sg:orig_category":"Prodotti E Manufatti In Materie Plastiche",
    "sg:phone":"+39 0331 820991",
    "sg:postcode":"21050",
    "sg:province":"Varese",
    "wof:name":"Themis Di Silvestri Lucia Anna",
    "wof:placetype":"venue"
},
  "geometry": {"coordinates":[8.8626022339,45.7079620361],"type":"Point"}
}