{
  "type": "Feature",
  "properties": {
    "addr:full":"24, Via Alfred Ammon 39042 Bressanone Bressanone Bolzano/Bozen 39042",
    "addr:postcode":"39042;39042",
    "addr:street":"Via Alfred Ammon",
    "iso:country":"IT",
    "sg:address":"24, Via Alfred Ammon 39042 Bressanone",
    "sg:city":"Bressanone",
    "sg:classifiers":[
        {
            "category":"Professional",
            "subcategory":"Printing & Photocopies",
            "type":"Services"
        }
    ],
    "sg:phone":"+39 0472 835435",
    "sg:postcode":"39042",
    "sg:province":"Bolzano/Bozen",
    "wof:name":"Serima Di Oberrauch Martin & C. S.a.s.",
    "wof:placetype":"venue"
},
  "geometry": {"coordinates":[11.6387796402,46.6878128052],"type":"Point"}
}