{
  "type": "Feature",
  "properties": {
    "iso:country":"IT",
    "sg:address":"36053 Gambellara",
    "sg:city":"Gambellara",
    "sg:orig_category":"Acciaierie E Fonderie. Arte Ed Artigianato Artistico",
    "sg:postcode":"36053",
    "sg:province":"Vicenza",
    "wof:name":"Fonderia Artistica In Bronzo Di Guastini Cav. Primo & C. (s.n.c.)",
    "wof:placetype":"venue"
},
  "geometry": {"coordinates":[11.346922,45.431015],"type":"Point"}
}