{
  "type": "Feature",
  "properties": {
    "iso:country":"IT",
    "sg:address":"20128 Milano",
    "sg:city":"Milano",
    "sg:orig_category":"Materiali E Componenti Elettrotecnici",
    "sg:phone":"+39 02 2600 0377",
    "sg:postcode":"20128",
    "sg:province":"Milano",
    "wof:name":"Baldrighi Angelo",
    "wof:placetype":"venue"
},
  "geometry": {"coordinates":[9.227921,45.51852],"type":"Point"}
}