{
  "type": "Feature",
  "properties": {
    "addr:full":"20149 Milano Milano Milano 20149",
    "addr:postcode":"20149;20149",
    "iso:country":"IT",
    "sg:address":"20149 Milano",
    "sg:city":"Milano",
    "sg:orig_category":"Agenzie Ed Enti Turistici. Consulenze Tecniche, Amministrative E Perizie",
    "sg:phone":"+39 02 4399 5217",
    "sg:postcode":"20149",
    "sg:province":"Milano",
    "wof:name":"Sygroup Srl",
    "wof:placetype":"venue"
},
  "geometry": {"coordinates":[9.148857,45.476284],"type":"Point"}
}