{
  "type": "Feature",
  "properties": {
    "iso:country":"IT",
    "sg:address":"30016 Jesolo",
    "sg:orig_category":"Alberghi E Strutture Extra Alberghiere",
    "sg:phone":"+39 0421 91979",
    "sg:postcode":"30016",
    "sg:province":"Venezia",
    "wof:name":"Hotel Sofia",
    "wof:placetype":"venue"
},
  "geometry": {"coordinates":[12.196239,45.474331],"type":"Point"}
}