{
  "type": "Feature",
  "properties": {
    "iso:country":"IT",
    "sg:address":"Via Belbrolo 46045 Marmirolo",
    "sg:city":"Marmirolo",
    "sg:classifiers":[
        {
            "category":"Food & Beverages",
            "subcategory":"Dairy",
            "type":"Retail Goods"
        }
    ],
    "sg:phone":"+39 0376 466258",
    "sg:postcode":"46045",
    "sg:province":"Mantova",
    "sg:tags":[
        "product"
    ],
    "wof:name":"Latteria Agricola Di Marmirolo",
    "wof:placetype":"venue"
},
  "geometry": {"coordinates":[10.731398,45.21619],"type":"Point"}
}