{
  "type": "Feature",
  "properties": {
    "iso:country":"IT",
    "sg:address":"00149 Roma",
    "sg:city":"Roma",
    "sg:orig_category":"Antifurto",
    "sg:phone":"+39 06 559 4493",
    "sg:postcode":"00149",
    "sg:province":"Roma",
    "wof:name":"Meyer Security Srl",
    "wof:placetype":"venue"
},
  "geometry": {"coordinates":[12.452163,41.860443],"type":"Point"}
}