{
  "type": "Feature",
  "properties": {
    "addr:full":"53014 Monteroni D'arbia Siena 53014",
    "addr:postcode":"53014;53014",
    "iso:country":"IT",
    "sg:address":"53014 Monteroni D'arbia",
    "sg:orig_category":"Servizi E Lavori Industria Chimica. Trattamenti Termici E Superficiali Metalli, Galvanotecnica",
    "sg:phone":"+39 0577 375641",
    "sg:postcode":"53014",
    "sg:province":"Siena",
    "wof:name":"Verniciatura Metalli Snc",
    "wof:placetype":"venue"
},
  "geometry": {"coordinates":[11.420318,43.233494],"type":"Point"}
}