{
  "type": "Feature",
  "properties": {
    "addr:full":"00157 Roma Roma Roma 00157",
    "addr:postcode":"00157;00157",
    "iso:country":"IT",
    "sg:address":"00157 Roma",
    "sg:city":"Roma",
    "sg:orig_category":"Prodotti Chimici Di Base. Macchine E Forniture Per Ecologia E Smaltimento Rifiuti",
    "sg:phone":"+39 06 4173 4297",
    "sg:postcode":"00157",
    "sg:province":"Roma",
    "sg:website":"http://www.intuneweb.com/bmd",
    "wof:name":"B.m.d. Srl",
    "wof:placetype":"venue"
},
  "geometry": {"coordinates":[12.5451488495,41.9191513062],"type":"Point"}
}