{
  "type": "Feature",
  "properties": {
    "addr:full":"41, Via Luigi Cadorna 23895 Nibionno Nibionno Lecco 23895",
    "addr:postcode":"23895;23895",
    "addr:street":"Via Luigi Cadorna",
    "iso:country":"IT",
    "sg:address":"41, Via Luigi Cadorna 23895 Nibionno",
    "sg:city":"Nibionno",
    "sg:classifiers":[
        {
            "category":"Shopping",
            "subcategory":"Crafts & Fabrics",
            "type":"Retail Goods"
        }
    ],
    "sg:phone":"+39 39031692222",
    "sg:postcode":"23895",
    "sg:province":"Lecco",
    "wof:name":"Imatex Spa",
    "wof:placetype":"venue"
},
  "geometry": {"coordinates":[9.3900709152,45.8529815674],"type":"Point"}
}