{
  "type": "Feature",
  "properties": {
    "addr:full":"54100 Massa Massa Massa-Carrara 54100",
    "addr:postcode":"54100;54100",
    "iso:country":"IT",
    "sg:address":"54100 Massa",
    "sg:city":"Massa",
    "sg:orig_category":"Petroli, Gas E Combustibili",
    "sg:phone":"+39 0585 250333",
    "sg:postcode":"54100",
    "sg:province":"Massa-Carrara",
    "wof:name":"L.o.m. Petrolchimici S.r.l.",
    "wof:placetype":"venue"
},
  "geometry": {"coordinates":[10.1071996689,44.0272064209],"type":"Point"}
}