{
  "type": "Feature",
  "properties": {
    "iso:country":"IT",
    "sg:address":"Piazza Cecco D'ascoli 25/a; Ascoli Satriano; 71022",
    "sg:city":"Ascoli Satriano",
    "sg:classifiers":[
        {
            "category":"Banks & Credit Unions",
            "subcategory":"Bank",
            "type":"Services"
        }
    ],
    "sg:phone":"+39 0885 61001",
    "sg:postcode":"71022",
    "sg:province":"Foggia",
    "wof:name":"Banco Di Napoli Spa",
    "wof:placetype":"venue"
},
  "geometry": {"coordinates":[15.561768,41.206116],"type":"Point"}
}