{
  "type": "Feature",
  "properties": {
    "addr:full":"59100 Prato Prato Prato 59100",
    "addr:postcode":"59100;59100",
    "iso:country":"IT",
    "sg:address":"59100 Prato",
    "sg:city":"Prato",
    "sg:orig_category":"Arte Ed Artigianato Artistico",
    "sg:phone":"+39 0574 572324",
    "sg:postcode":"59100",
    "sg:province":"Prato",
    "wof:name":"Sir.co. Sas",
    "wof:placetype":"venue"
},
  "geometry": {"coordinates":[11.09683,43.867825],"type":"Point"}
}