{
  "type": "Feature",
  "properties": {
    "iso:country":"IT",
    "sg:address":"41100 San Damaso",
    "sg:city":"San damaso",
    "sg:orig_category":"Accessori Dei Mezzi Di Trasporto",
    "sg:phone":"+39 059 146 8848",
    "sg:postcode":"41100",
    "sg:province":"Modena",
    "sg:website":"http://www.interbike.it",
    "wof:name":"Interbike Di Benassi Marco",
    "wof:placetype":"venue"
},
  "geometry": {"coordinates":[10.969126,44.603626],"type":"Point"}
}