{
  "type": "Feature",
  "properties": {
    "iso:country":"IT",
    "sg:address":"10070 Robassomero",
    "sg:city":"Robassomero",
    "sg:orig_category":"Elettrotecnica Industriale, Prodotti E Apparecchiature",
    "sg:phone":"+39 011 923 5222",
    "sg:postcode":"10070",
    "sg:province":"Torino",
    "wof:name":"C.i.e.t. Srl",
    "wof:placetype":"venue"
},
  "geometry": {"coordinates":[7.56858,45.200741],"type":"Point"}
}