{
  "type": "Feature",
  "properties": {
    "iso:country":"IT",
    "sg:address":"Zona Industriale 32034 Pedavena",
    "sg:city":"Pedavena",
    "sg:classifiers":[
        {
            "category":"Manufacturing",
            "subcategory":"Rubber & Plastics",
            "type":"Manufacturing & Wholesale Goods"
        }
    ],
    "sg:phone":"+39 0439 301150",
    "sg:postcode":"32034",
    "sg:province":"Belluno",
    "wof:name":"Dolmap (s.r.l.)",
    "wof:placetype":"venue"
},
  "geometry": {"coordinates":[11.9207687378,46.0227737427],"type":"Point"}
}