{
  "type": "Feature",
  "properties": {
    "iso:country":"IT",
    "sg:address":"48100 Ravenna",
    "sg:city":"Ravenna",
    "sg:orig_category":"Automobili E Mezzi Di Trasporto",
    "sg:phone":"+39 0544 500140",
    "sg:postcode":"48100",
    "sg:province":"Ravenna",
    "sg:website":"http://www.autovogue.it",
    "wof:name":"Autovogue Srl",
    "wof:placetype":"venue"
},
  "geometry": {"coordinates":[12.224458,44.380314],"type":"Point"}
}