{
  "type": "Feature",
  "properties": {
    "iso:country":"IT",
    "sg:address":"64026 Roseto Degli Abruzzi",
    "sg:city":"Roseto degli Abruzzi",
    "sg:orig_category":"Motocicli E Motocarri - Commercio E Riparazione",
    "sg:phone":"+39 085 893 0388",
    "sg:postcode":"64026",
    "sg:province":"Teramo",
    "wof:name":"Del Gaone Roberto",
    "wof:placetype":"venue"
},
  "geometry": {"coordinates":[13.9724140167,42.6925392151],"type":"Point"}
}