{
  "type": "Feature",
  "properties": {
    "iso:country":"IT",
    "sg:address":"4, C. Allamano",
    "sg:city":"Grugliasco",
    "sg:classifiers":[
        {
            "category":"Autos & Motor Vehicles",
            "subcategory":"Automobile Sales",
            "type":"Retail Goods"
        }
    ],
    "sg:phone":"+39 011 780 5317",
    "sg:postcode":"10095",
    "sg:province":"Torino",
    "sg:tags":[
        "industrial"
    ],
    "sg:website":"http://www.nuovademolizione.it",
    "wof:name":"Nuova Demolizione Auto",
    "wof:placetype":"venue"
},
  "geometry": {"coordinates":[7.686619,45.07056],"type":"Point"}
}