{
  "type": "Feature",
  "properties": {
    "addr:full":"47900 Rimini Rimini Rimini 47900",
    "addr:postcode":"47900;47900",
    "iso:country":"IT",
    "sg:address":"47900 Rimini",
    "sg:city":"Rimini",
    "sg:orig_category":"Musica. Shopping",
    "sg:phone":"+39 0541 23624",
    "sg:postcode":"47900",
    "sg:province":"Rimini",
    "wof:name":"Libreria Il Libro E La Vela",
    "wof:placetype":"venue"
},
  "geometry": {"coordinates":[12.5527505875,44.0264587402],"type":"Point"}
}