{
  "type": "Feature",
  "properties": {
    "iso:country":"IT",
    "sg:address":"20132 Milano",
    "sg:city":"Milano",
    "sg:orig_category":"Macchine, Impianti Ed Attrezzature Per Industria Alimentare E Bevande",
    "sg:phone":"+39 0228391",
    "sg:postcode":"20132",
    "sg:province":"Milano",
    "wof:name":"O.m.i. Organizzazione Macchine Industriali (s.p.a.)",
    "wof:placetype":"venue"
},
  "geometry": {"coordinates":[9.232844,45.493416],"type":"Point"}
}