{
  "type": "Feature",
  "properties": {
    "addr:full":"20154 Milano Milano Milano 20154",
    "addr:postcode":"20154;20154",
    "iso:country":"IT",
    "sg:address":"20154 Milano",
    "sg:city":"Milano",
    "sg:orig_category":"Servizi E Lavori Per Arredamento E Industria Del Legno",
    "sg:phone":"+39 02 344100",
    "sg:postcode":"20154",
    "sg:province":"Milano",
    "wof:name":"Carminati Duilio",
    "wof:placetype":"venue"
},
  "geometry": {"coordinates":[9.181097,45.480095],"type":"Point"}
}