{
  "type": "Feature",
  "properties": {
    "iso:country":"IT",
    "sg:address":"71, Via Po 09032 Assemini",
    "sg:city":"Assemini",
    "sg:classifiers":[
        {
            "category":"Shopping",
            "subcategory":"Crafts & Fabrics",
            "type":"Retail Goods"
        }
    ],
    "sg:phone":"+39 39070940621",
    "sg:postcode":"09032",
    "sg:province":"Cagliari",
    "wof:name":"Ciemme S.r.l.",
    "wof:placetype":"venue"
},
  "geometry": {"coordinates":[9.0043754578,39.2959365845],"type":"Point"}
}