{
  "type": "Feature",
  "properties": {
    "iso:country":"IT",
    "sg:address":"Zona Industriale Squartabue 62019 Recanati",
    "sg:city":"Recanati",
    "sg:classifiers":[
        {
            "category":"Structure",
            "subcategory":"Tower",
            "type":"Public Place"
        }
    ],
    "sg:phone":"+39 071 750 6105",
    "sg:postcode":"62019",
    "sg:province":"Macerata",
    "sg:tags":[
        "intercom"
    ],
    "sg:website":"www.esse-ti.it",
    "wof:name":"Esse-ti Srl",
    "wof:placetype":"venue"
},
  "geometry": {"coordinates":[13.456262,43.300747],"type":"Point"}
}