{
  "type": "Feature",
  "properties": {
    "iso:country":"IT",
    "sg:address":"20122 Milano",
    "sg:city":"Milano",
    "sg:classifiers":[
        {
            "category":"Shopping",
            "subcategory":"Stationery & Office Supplies",
            "type":"Retail Goods"
        }
    ],
    "sg:phone":"+39 02 799773",
    "sg:postcode":"20122",
    "sg:province":"Milano",
    "sg:tags":[
        "equipment",
        "furniture",
        "furnishing",
        "professional"
    ],
    "wof:name":"Multiform Srl",
    "wof:placetype":"venue"
},
  "geometry": {"coordinates":[9.1968250275,45.4654693604],"type":"Point"}
}