{
  "type": "Feature",
  "properties": {
    "iso:country":"IT",
    "sg:address":"Corso Vittorio Emanuele Ii 15 20122 Milano",
    "sg:city":"Milano",
    "sg:classifiers":[
        {
            "category":"Education",
            "subcategory":"School",
            "type":"Public Place"
        }
    ],
    "sg:phone":"+39 02 795535",
    "sg:postcode":"20122",
    "sg:province":"Milano",
    "sg:tags":[
        "breeding",
        "livestock",
        "cattle"
    ],
    "sg:website":"www.sadia.com",
    "wof:name":"Sadia Italia Srl",
    "wof:placetype":"venue"
},
  "geometry": {"coordinates":[9.196226,45.465683],"type":"Point"}
}