{
  "type": "Feature",
  "properties": {
    "iso:country":"IT",
    "sg:address":"98122 Messina",
    "sg:city":"Messina",
    "sg:orig_category":"Impianti, Attrezzature E Forniture Sanitarie Ed Ospedaliere",
    "sg:phone":"+39 090 47200",
    "sg:postcode":"98122",
    "sg:province":"Messina",
    "wof:name":"Chirmedical Snc",
    "wof:placetype":"venue"
},
  "geometry": {"coordinates":[15.538645,38.199047],"type":"Point"}
}