{
  "type": "Feature",
  "properties": {
    "iso:country":"IT",
    "sg:address":"35010 Vigonza",
    "sg:city":"Vigonza",
    "sg:orig_category":"Macchine, Impianti Ed Attrezzature Industria Chimica. Attrezzature E Forniture Per Officine Riparazione E Servizi Ausiliari",
    "sg:phone":"+39 049 626912",
    "sg:postcode":"35010",
    "sg:province":"Padova",
    "wof:name":"Sartec Srl",
    "wof:placetype":"venue"
},
  "geometry": {"coordinates":[11.954478,45.435238],"type":"Point"}
}