{
  "type": "Feature",
  "properties": {
    "iso:country":"IT",
    "sg:address":"240, Corso Europa 23801 Calolziocorte",
    "sg:city":"Calolziocorte",
    "sg:classifiers":[
        {
            "category":"Manufacturing",
            "subcategory":"Metals",
            "type":"Manufacturing & Wholesale Goods"
        }
    ],
    "sg:phone":"+39 0341 634814",
    "sg:postcode":"23801",
    "sg:province":"Lecco",
    "sg:tags":[
        "metallurgy",
        "metalworking"
    ],
    "wof:name":"Mi.me.af (s.p.a.)",
    "wof:placetype":"venue"
},
  "geometry": {"coordinates":[9.4390220642,45.7902908325],"type":"Point"}
}