{
  "type": "Feature",
  "properties": {
    "iso:country":"IT",
    "sg:address":"48 Via Stradone, 06062 Citta' Della Pieve",
    "sg:classifiers":[
        {
            "category":"Banks & Credit Unions",
            "subcategory":"Financial Services",
            "type":"Services"
        }
    ],
    "sg:phone":"+39 390 578 2951",
    "sg:postcode":"06062",
    "sg:province":"Perugia",
    "sg:tags":[
        "banking",
        "finance",
        "insurance"
    ],
    "wof:name":"Banca Di Credito Cooperativo Del Trasimeno Scrl",
    "wof:placetype":"venue"
},
  "geometry": {"coordinates":[12.0155315399,43.0128059387],"type":"Point"}
}