{
  "type": "Feature",
  "properties": {
    "iso:country":"IT",
    "sg:address":"20035 Lissone",
    "sg:city":"Lissone",
    "sg:orig_category":"Ceramiche Per Pavimenti E Rivestimenti - Produzione E Ingrosso",
    "sg:phone":"+39 039 484602",
    "sg:postcode":"20035",
    "sg:province":"Milano",
    "wof:name":"Acr Srl",
    "wof:placetype":"venue"
},
  "geometry": {"coordinates":[9.24033,45.603943],"type":"Point"}
}