{
  "type": "Feature",
  "properties": {
    "addr:full":"272, Via S. Paolo 59100 Prato Prato Prato 59100",
    "addr:housenumber":"272",
    "addr:postcode":"59100;59100",
    "addr:street":"Via S. Paolo",
    "iso:country":"IT",
    "sg:address":"272, Via S. Paolo 59100 Prato",
    "sg:city":"Prato",
    "sg:classifiers":[
        {
            "category":"Shopping",
            "subcategory":"Crafts & Fabrics",
            "type":"Retail Goods"
        }
    ],
    "sg:phone":"+39 39057437078",
    "sg:postcode":"59100",
    "sg:province":"Prato",
    "wof:name":"Super - Fil (s.r.l.)",
    "wof:placetype":"venue"
},
  "geometry": {"coordinates":[11.0937786102,43.904510498],"type":"Point"}
}