{
  "type": "Feature",
  "properties": {
    "iso:country":"IT",
    "sg:address":"4, Via Marsala 36027 Rosa'",
    "sg:classifiers":[
        {
            "category":"Professional",
            "subcategory":"Engineering",
            "type":"Services"
        }
    ],
    "sg:phone":"+39 0424 581029",
    "sg:postcode":"36027",
    "sg:province":"Vicenza",
    "sg:tags":[
        "machine",
        "-",
        "mechanical"
    ],
    "wof:name":"Tecnolegno High-tech S.r.l.",
    "wof:placetype":"venue"
},
  "geometry": {"coordinates":[11.770404,45.724472],"type":"Point"}
}