{
  "type": "Feature",
  "properties": {
    "addr:full":"10122 Torino Torino Torino 10122",
    "addr:housenumber":"10122",
    "addr:postcode":"10122",
    "iso:country":"IT",
    "sg:address":"10122 Torino",
    "sg:city":"Torino",
    "sg:orig_category":"Servizi Culturali E Per Lo Spettacolo. Servizi Al Turismo. Acqua, Luce, Gas E Societa' Di Esercizio Pubblico",
    "sg:phone":"+39 011 549523",
    "sg:postcode":"10122",
    "sg:province":"Torino",
    "wof:name":"Istituto Piemontese Per La Storia Della Resistenza E Della Soc.contemporanea",
    "wof:placetype":"venue"
},
  "geometry": {"coordinates":[7.674809,45.073219],"type":"Point"}
}