{
  "type": "Feature",
  "properties": {
    "iso:country":"IT",
    "sg:address":"00034 Colleferro",
    "sg:city":"Colleferro",
    "sg:orig_category":"Termotecnica E Riscaldamento, Apparecchiature E Servizi",
    "sg:phone":"+39 06 9723 6901",
    "sg:postcode":"00034",
    "sg:province":"Roma",
    "sg:website":"http://www.risen.it",
    "wof:name":"Ris.en Sas",
    "wof:placetype":"venue"
},
  "geometry": {"coordinates":[13.010571,41.722286],"type":"Point"}
}