{
  "type": "Feature",
  "properties": {
    "addr:full":"565, Frazione S. Valburga 39016 Ultimo Ultimo Bolzano/Bozen 39016",
    "addr:postcode":"39016;39016",
    "addr:street":"Frazione S. Valburga",
    "iso:country":"IT",
    "sg:address":"565, Frazione S. Valburga 39016 Ultimo",
    "sg:city":"Ultimo",
    "sg:classifiers":[
        {
            "category":"Professional",
            "subcategory":"Engineering",
            "type":"Services"
        }
    ],
    "sg:phone":"+39 0473 795390",
    "sg:postcode":"39016",
    "sg:province":"Bolzano/Bozen",
    "sg:tags":[
        "machine",
        "-",
        "mechanical"
    ],
    "wof:name":"Sciovie E Seggiovie Di Val D'ultimo (s.r.l.)",
    "wof:placetype":"venue"
},
  "geometry": {"coordinates":[11.358005,46.496716],"type":"Point"}
}