{
  "type": "Feature",
  "properties": {
    "iso:country":"IT",
    "sg:address":"39034 Dobbiaco",
    "sg:city":"Dobbiaco",
    "sg:orig_category":"Servizi E Lavori Per Ecologia E Smaltimento Rifiuti. Termotecnica E Riscaldamento, Apparecchiature E Servizi. Servizi Ausiliari Di Sorveglianza, Manutenzione E Pulizia",
    "sg:phone":"+39 0474 972484",
    "sg:postcode":"39034",
    "sg:province":"Bolzano/Bozen",
    "wof:name":"Mair Wolfgang Herbert & Co. S.n.c.",
    "wof:placetype":"venue"
},
  "geometry": {"coordinates":[12.227074,46.73772],"type":"Point"}
}