{
  "type": "Feature",
  "properties": {
    "addr:full":"Via Ariosto Ludovico 10 20052 Monza Monza Milano 20052",
    "addr:housenumber":"10",
    "addr:postcode":"20052;20052",
    "addr:street":"Via Ariosto Ludovico",
    "iso:country":"IT",
    "sg:address":"Via Ariosto Ludovico 10 20052 Monza",
    "sg:city":"Monza",
    "sg:orig_category":"Wooden Panel Separation Sawing Machines And Automatic Sawing Machines",
    "sg:phone":"+39 039 202 6321",
    "sg:postcode":"20052",
    "sg:province":"Milano",
    "wof:name":"Ferdinando Visconti Snc",
    "wof:placetype":"venue"
},
  "geometry": {"coordinates":[9.28508,45.535164],"type":"Point"}
}