{
  "type": "Feature",
  "properties": {
    "addr:full":"Piazzale De Matthaeis 41, 03100 Frosinone, Fr Frosinone Frosinone 03100",
    "addr:housenumber":"41",
    "addr:postcode":"03100;03100",
    "addr:street":"Piazzale De Matthaeis",
    "iso:country":"IT",
    "sg:address":"Piazzale De Matthaeis 41, 03100 Frosinone, Fr",
    "sg:city":"Frosinone",
    "sg:classifiers":[
        {
            "category":"Banks & Credit Unions",
            "subcategory":"Bank",
            "type":"Services"
        }
    ],
    "sg:postcode":"03100",
    "sg:province":"Frosinone",
    "wof:name":"Consorzio Per I'area Di Sviluppo Industriale Della Prov Di Frosinone",
    "wof:placetype":"venue"
},
  "geometry": {"coordinates":[13.348705,41.646919],"type":"Point"}
}