{
  "type": "Feature",
  "properties": {
    "iso:country":"IT",
    "sg:address":"39, Via Figino 22020 San Fermo Della Battaglia",
    "sg:city":"San Fermo della Battaglia",
    "sg:classifiers":[
        {
            "category":"Manufacturing",
            "subcategory":"Printing",
            "type":"Manufacturing & Wholesale Goods"
        }
    ],
    "sg:phone":"+39 39031210554",
    "sg:postcode":"22020",
    "sg:province":"Como",
    "sg:tags":[
        "publishing"
    ],
    "wof:name":"Brunati Arti Grafiche (s.r.l.)",
    "wof:placetype":"venue"
},
  "geometry": {"coordinates":[9.0454902649,45.8055839539],"type":"Point"}
}