{
  "type": "Feature",
  "properties": {
    "addr:full":"19, Via Schio 36030 Sarcedo Sarcedo Vicenza 36030",
    "addr:postcode":"36030;36030",
    "addr:street":"Via Schio",
    "iso:country":"IT",
    "sg:address":"19, Via Schio 36030 Sarcedo",
    "sg:city":"Sarcedo",
    "sg:classifiers":[
        {
            "category":"Manufacturing",
            "subcategory":"Metals",
            "type":"Manufacturing & Wholesale Goods"
        }
    ],
    "sg:phone":"+39 0445 884399",
    "sg:postcode":"36030",
    "sg:province":"Vicenza",
    "sg:tags":[
        "processing"
    ],
    "wof:name":"S.p.f. Chilo' (s.r.l.)",
    "wof:placetype":"venue"
},
  "geometry": {"coordinates":[11.540307045,45.5459060669],"type":"Point"}
}