{
  "type": "Feature",
  "properties": {
    "iso:country":"IT",
    "sg:address":"22100 Como",
    "sg:city":"Como",
    "sg:orig_category":"Servizi E Lavori Per Abbigliamento E Pelletterie",
    "sg:phone":"+39 031 240151",
    "sg:postcode":"22100",
    "sg:province":"Como",
    "wof:name":"Nuvo' (s.n.c.)",
    "wof:placetype":"venue"
},
  "geometry": {"coordinates":[9.083227,45.808002],"type":"Point"}
}