{
  "type": "Feature",
  "properties": {
    "iso:country":"IT",
    "sg:address":"Ctr. Traverso",
    "sg:city":"Buonalbergo",
    "sg:classifiers":[
        {
            "category":"Shopping",
            "subcategory":"Clothing, Apparel, & Fashions",
            "type":"Retail Goods"
        }
    ],
    "sg:phone":"+39 0824 929815",
    "sg:postcode":"82020",
    "sg:province":"Benevento",
    "sg:tags":[
        "clothing",
        "accessory"
    ],
    "sg:website":"http://www.danycharls.com",
    "wof:name":"Dany Charls Sas",
    "wof:placetype":"venue"
},
  "geometry": {"coordinates":[14.781174,41.130447],"type":"Point"}
}