{
  "type": "Feature",
  "properties": {
    "iso:country":"IT",
    "sg:address":"41, Via Pastore Giulio 47900 Rimini",
    "sg:city":"Rimini",
    "sg:classifiers":[
        {
            "category":"Personal",
            "subcategory":"Shoe Repair & Shine",
            "type":"Services"
        }
    ],
    "sg:phone":"+39 0541 734375",
    "sg:postcode":"47900",
    "sg:province":"Rimini",
    "sg:tags":[
        "leather"
    ],
    "wof:name":"Rossanti Di Magianti Maurizio",
    "wof:placetype":"venue"
},
  "geometry": {"coordinates":[12.566257,44.06078],"type":"Point"}
}