{
  "type": "Feature",
  "properties": {
    "iso:country":"IT",
    "sg:address":"222, Via Roma 35040 Casale Di Scodosia",
    "sg:city":"Casale di Scodosia",
    "sg:classifiers":[
        {
            "category":"Home & Garden",
            "subcategory":"Home Furnishings",
            "type":"Retail Goods"
        }
    ],
    "sg:phone":"+39 39042987354",
    "sg:postcode":"35040",
    "sg:province":"Padova",
    "sg:tags":[
        "household"
    ],
    "wof:name":"Morello Fratelli Di Morello Gianluca & C. (s.n.c.)",
    "wof:placetype":"venue"
},
  "geometry": {"coordinates":[11.469589,45.187717],"type":"Point"}
}