{
  "type": "Feature",
  "properties": {
    "addr:full":"20046 Biassono Biassono Milano 20046",
    "addr:postcode":"20046;20046",
    "iso:country":"IT",
    "sg:address":"20046 Biassono",
    "sg:city":"Biassono",
    "sg:orig_category":"Argentatura, Doratura, Platinatura E Rodiatura",
    "sg:phone":"+39 039 275 2788",
    "sg:postcode":"20046",
    "sg:province":"Milano",
    "wof:name":"F.lli Re Sas",
    "wof:placetype":"venue"
},
  "geometry": {"coordinates":[9.226521,45.58849],"type":"Point"}
}