{
  "type": "Feature",
  "properties": {
    "iso:country":"IT",
    "sg:address":"56, Via Dell' Industria 20083 Gaggiano",
    "sg:city":"Gaggiano",
    "sg:classifiers":[
        {
            "category":"Shopping",
            "subcategory":"Computers & Home Electronics",
            "type":"Retail Goods"
        }
    ],
    "sg:phone":"+39 39029086617",
    "sg:postcode":"20083",
    "sg:province":"Milano",
    "sg:tags":[
        "electronic",
        "electrical",
        "equipment"
    ],
    "wof:name":"E. T. S. Sistemi Industriali Srl",
    "wof:placetype":"venue"
},
  "geometry": {"coordinates":[9.100558,45.41124],"type":"Point"}
}