{
  "type": "Feature",
  "properties": {
    "addr:full":"21013 Gallarate Gallarate Varese 21013",
    "addr:postcode":"21013;21013",
    "iso:country":"IT",
    "sg:address":"21013 Gallarate",
    "sg:city":"Gallarate",
    "sg:orig_category":"Forniture Per Abbigliamento E Pelletterie",
    "sg:phone":"+39 0331 792743",
    "sg:postcode":"21013",
    "sg:province":"Varese",
    "wof:name":"Manifattura Sandro Graziina Srl",
    "wof:placetype":"venue"
},
  "geometry": {"coordinates":[8.7771978378,45.6726799011],"type":"Point"}
}