{
  "type": "Feature",
  "properties": {
    "addr:full":"89861 Tropea Tropea Vibo Valentia 89861",
    "addr:postcode":"89861;89861",
    "addr:street":"Valentia",
    "iso:country":"IT",
    "sg:address":"89861 Tropea",
    "sg:city":"Tropea",
    "sg:classifiers":[
        {
            "category":"Bars & Pubs",
            "subcategory":"Biergarten",
            "type":"Food & Drink"
        }
    ],
    "sg:phone":"+39 0963 61570",
    "sg:postcode":"89861",
    "sg:province":"Vibo Valentia",
    "sg:tags":[
        "birrerie",
        "e"
    ],
    "wof:name":"Cricelli Giovanbattista",
    "wof:placetype":"venue"
},
  "geometry": {"coordinates":[15.893003,38.675518],"type":"Point"}
}