{
  "type": "Feature",
  "properties": {
    "iso:country":"IT",
    "sg:address":"9/11, Via Falzarego 20021 Bollate",
    "sg:city":"Bollate",
    "sg:classifiers":[
        {
            "category":"Wholesale",
            "subcategory":"Machinery & Supplies",
            "type":"Manufacturing & Wholesale Goods"
        }
    ],
    "sg:phone":"+39 390 233 3371",
    "sg:postcode":"20021",
    "sg:province":"Milano",
    "sg:tags":[
        "equipment",
        "-",
        "instrument",
        "measurement"
    ],
    "wof:name":"Ascon (s.p.a.)",
    "wof:placetype":"venue"
},
  "geometry": {"coordinates":[9.103297,45.531883],"type":"Point"}
}