{
  "type": "Feature",
  "properties": {
    "iso:country":"IT",
    "sg:address":"138, Via Marx Carlo 41012 Carpi",
    "sg:city":"Carpi",
    "sg:classifiers":[
        {
            "category":"Shopping",
            "type":"Retail Goods"
        }
    ],
    "sg:phone":"+39 39059641830",
    "sg:postcode":"41012",
    "sg:province":"Modena",
    "sg:tags":[
        "finished",
        "-",
        "metallic"
    ],
    "wof:name":"Zadi Spa",
    "wof:placetype":"venue"
},
  "geometry": {"coordinates":[10.8725280762,44.7585906982],"type":"Point"}
}