{
  "type": "Feature",
  "properties": {
    "addr:full":"Via Della Scala 85; Firenze; 50123 Firenze Firenze 50123",
    "addr:housenumber":"85",
    "addr:postcode":"50123;50123",
    "addr:street":"Via Della Scala",
    "iso:country":"IT",
    "sg:address":"Via Della Scala 85; Firenze; 50123",
    "sg:city":"Firenze",
    "sg:classifiers":[
        {
            "category":"Banks & Credit Unions",
            "subcategory":"Bank",
            "type":"Services"
        }
    ],
    "sg:phone":"+39 055 210347",
    "sg:postcode":"50123",
    "sg:province":"Firenze",
    "wof:name":"Cassa Di Risparmio Di Pisa",
    "wof:placetype":"venue"
},
  "geometry": {"coordinates":[11.244741,43.776119],"type":"Point"}
}