{
  "type": "Feature",
  "properties": {
    "iso:country":"IT",
    "sg:address":"40068 San Lazzaro Di Savena",
    "sg:city":"San Lazzaro",
    "sg:orig_category":"Servizi Vari Di Interesse Pubblico",
    "sg:phone":"+39 051 625 9584",
    "sg:postcode":"40068",
    "sg:province":"Bologna",
    "wof:name":"Milanesi Maria Grazia",
    "wof:placetype":"venue"
},
  "geometry": {"coordinates":[11.445734,44.455566],"type":"Point"}
}