{
  "type": "Feature",
  "properties": {
    "iso:country":"IT",
    "sg:address":"43100 Parma",
    "sg:city":"Parma",
    "sg:orig_category":"Agitatori, Emulsionatori Ed Omogeneizzatori",
    "sg:phone":"+39 0521 291516",
    "sg:postcode":"43100",
    "sg:province":"Parma",
    "wof:name":"Bertoli Omogeneizzatori Srl",
    "wof:placetype":"venue"
},
  "geometry": {"coordinates":[10.257689,44.784882],"type":"Point"}
}