{
  "type": "Feature",
  "properties": {
    "addr:full":"24040 Zingonia Zingonia Bergamo 24040",
    "addr:postcode":"24040;24040",
    "iso:country":"IT",
    "sg:address":"24040 Zingonia",
    "sg:city":"Zingonia",
    "sg:orig_category":"Cavi E Conduttori Elettrici E Telefonici",
    "sg:phone":"+39 035 883359",
    "sg:postcode":"24040",
    "sg:province":"Bergamo",
    "wof:name":"Flamar Cavi Elettrici Srl",
    "wof:placetype":"venue"
},
  "geometry": {"coordinates":[9.613678,45.595688],"type":"Point"}
}