{
  "type": "Feature",
  "properties": {
    "iso:country":"IT",
    "sg:address":"50133 Firenze",
    "sg:city":"Firenze",
    "sg:orig_category":"Trattamenti Termici E Superficiali Metalli, Galvanotecnica",
    "sg:phone":"+39 055 486168",
    "sg:postcode":"50133",
    "sg:province":"Firenze",
    "wof:name":"Sama Cromo Di Iacovino Luigi & C. Snc",
    "wof:placetype":"venue"
},
  "geometry": {"coordinates":[11.277887,43.796101],"type":"Point"}
}