{
  "type": "Feature",
  "properties": {
    "iso:country":"IT",
    "sg:address":"Via A. Moro 18 20060 Pessano Con Bornago",
    "sg:city":"Ornago",
    "sg:classifiers":[
        {
            "category":"Building & Trades",
            "subcategory":"Construction",
            "type":"Services"
        }
    ],
    "sg:phone":"+39 02 9574 2804",
    "sg:postcode":"20060",
    "sg:province":"Milano",
    "sg:tags":[
        "carpenter's",
        "work",
        "supraregional"
    ],
    "sg:website":"www.cpsrl.it",
    "wof:name":"Carpenteria Pessano Srl",
    "wof:placetype":"venue"
},
  "geometry": {"coordinates":[9.188141,45.463688],"type":"Point"}
}