{
  "type": "Feature",
  "properties": {
    "iso:country":"IT",
    "sg:address":"17, Via Europa 24030 Medolago",
    "sg:city":"Medolago",
    "sg:classifiers":[
        {
            "category":"Professional",
            "subcategory":"Computer Services",
            "type":"Services"
        }
    ],
    "sg:phone":"+39 035 494 8856",
    "sg:postcode":"24030",
    "sg:province":"Bergamo",
    "sg:tags":[
        "information",
        "technology"
    ],
    "wof:name":"Pernice Informatica Di Fontana E Airoldi Snc",
    "wof:placetype":"venue"
},
  "geometry": {"coordinates":[9.493914,45.672443],"type":"Point"}
}