{
  "type": "Feature",
  "properties": {
    "addr:full":"198/c, Via Pisa 20099 Sesto San Giovanni Sesto San Giovanni Milano 20099",
    "addr:housenumber":"198 / c",
    "addr:postcode":"20099;20099",
    "addr:street":"Via Pisa",
    "iso:country":"IT",
    "sg:address":"198/c, Via Pisa 20099 Sesto San Giovanni",
    "sg:city":"Sesto San Giovanni",
    "sg:classifiers":[
        {
            "category":"Manufacturing",
            "subcategory":"Metals",
            "type":"Manufacturing & Wholesale Goods"
        }
    ],
    "sg:phone":"+39 39022484070",
    "sg:postcode":"20099",
    "sg:province":"Milano",
    "sg:tags":[
        "metallurgy",
        "metalworking"
    ],
    "wof:name":"Fusi (s.r.l.)",
    "wof:placetype":"venue"
},
  "geometry": {"coordinates":[9.2582798004,45.5294570923],"type":"Point"}
}