{
  "type": "Feature",
  "properties": {
    "addr:full":"41026 Pavullo Nel Frignano Pavullo nel Frignano Modena 41026",
    "addr:postcode":"41026;41026",
    "addr:street":"Nel Frignano",
    "iso:country":"IT",
    "sg:address":"41026 Pavullo Nel Frignano",
    "sg:city":"Pavullo nel Frignano",
    "sg:classifiers":[
        {
            "category":"Health Services",
            "subcategory":"Health Practitioner",
            "type":"Services"
        }
    ],
    "sg:phone":"+39 0536 324108",
    "sg:postcode":"41026",
    "sg:province":"Modena",
    "sg:tags":[
        "medici"
    ],
    "wof:name":"Stradi Claudio",
    "wof:placetype":"venue"
},
  "geometry": {"coordinates":[10.8677253723,44.3508529663],"type":"Point"}
}