{
  "type": "Feature",
  "properties": {
    "addr:full":"35028 Corte Corte Padova 35028",
    "addr:housenumber":"35028",
    "addr:postcode":"35028",
    "addr:street":"Corte Corte Padova",
    "iso:country":"IT",
    "sg:address":"35028 Corte",
    "sg:city":"Corte",
    "sg:orig_category":"Servizi E Lavori Per Agricoltura E Zootecnia",
    "sg:phone":"+39 049 585 6086",
    "sg:postcode":"35028",
    "sg:province":"Padova",
    "wof:name":"Da Re Luciano",
    "wof:placetype":"venue"
},
  "geometry": {"coordinates":[12.075648,45.308445],"type":"Point"}
}