{
  "type": "Feature",
  "properties": {
    "addr:full":"91022 Castelvetrano Castelvetrano Trapani 91022",
    "addr:postcode":"91022;91022",
    "iso:country":"IT",
    "sg:address":"91022 Castelvetrano",
    "sg:city":"Castelvetrano",
    "sg:orig_category":"Studi E Consulenze Amministrative, Commerciali E Aziendali. Banche E Servizi Finanziari. Agenzie D'affari E Servizi Commerciali. Consulenze Tecniche, Amministrative E Perizie",
    "sg:phone":"+39 0924 45546",
    "sg:postcode":"91022",
    "sg:province":"Trapani",
    "wof:name":"Alfa Omega Di A.m. Marchese Snc",
    "wof:placetype":"venue"
},
  "geometry": {"coordinates":[12.795444,37.681744],"type":"Point"}
}