{
  "type": "Feature",
  "properties": {
    "iso:country":"IT",
    "sg:address":"39100 Bolzano",
    "sg:city":"Bolzano",
    "sg:orig_category":"Pubblicita', Marketing E Comunicazione",
    "sg:phone":"+39 0471 279311",
    "sg:postcode":"39100",
    "sg:province":"Bolzano/Bozen",
    "sg:website":"http://www.tuttotarghe.it",
    "wof:name":"Tuttotarghe Di Nardelli Mauro - Luca & C. Snc",
    "wof:placetype":"venue"
},
  "geometry": {"coordinates":[11.35800457,46.4967155457],"type":"Point"}
}