{
  "type": "Feature",
  "properties": {
    "iso:country":"IT",
    "sg:address":"361, Piazza Colonna 00187 Roma",
    "sg:city":"Roma",
    "sg:classifiers":[
        {
            "category":"Banks & Credit Unions",
            "subcategory":"Investment Brokerage",
            "type":"Services"
        }
    ],
    "sg:phone":"+39 06 6920 0265",
    "sg:postcode":"00187",
    "sg:province":"Roma",
    "sg:tags":[
        "-",
        "transport",
        "related"
    ],
    "wof:name":"Parrini E C S.p.a.",
    "wof:placetype":"venue"
},
  "geometry": {"coordinates":[12.757081,41.821785],"type":"Point"}
}