{
  "type": "Feature",
  "properties": {
    "addr:full":"194, Via Sempione 21052 Busto Arsizio Busto Arsizio Varese 21052",
    "addr:housenumber":"194",
    "addr:postcode":"21052;21052",
    "addr:street":"Via Sempione",
    "iso:country":"IT",
    "sg:address":"194, Via Sempione 21052 Busto Arsizio",
    "sg:city":"Busto Arsizio",
    "sg:classifiers":[
        {
            "category":"Shopping",
            "subcategory":"Crafts & Fabrics",
            "type":"Retail Goods"
        }
    ],
    "sg:phone":"+39 0331 680285",
    "sg:postcode":"21052",
    "sg:province":"Varese",
    "wof:name":"Mizar (s.p.a.)",
    "wof:placetype":"venue"
},
  "geometry": {"coordinates":[8.8326301575,45.634311676],"type":"Point"}
}