{
  "type": "Feature",
  "properties": {
    "iso:country":"IT",
    "sg:address":"46100 Mantova",
    "sg:city":"Mantova",
    "sg:orig_category":"Assicurazioni",
    "sg:phone":"+39 0376 223636",
    "sg:postcode":"46100",
    "sg:province":"Mantova",
    "wof:name":"Solci Srl",
    "wof:placetype":"venue"
},
  "geometry": {"coordinates":[10.791225,45.155468],"type":"Point"}
}