{
  "type": "Feature",
  "properties": {
    "iso:country":"IT",
    "sg:address":"Via Cremona 26015 Soresina",
    "sg:city":"Soresina",
    "sg:classifiers":[
        {
            "category":"Bars & Pubs",
            "subcategory":"Nightclub",
            "type":"Food & Drink"
        }
    ],
    "sg:phone":"+39 0374 343711",
    "sg:postcode":"26015",
    "sg:province":"Cremona",
    "sg:tags":[
        "cake",
        "bread"
    ],
    "wof:name":"Dolciaria Salini F.lli Di Regoldi Luigi & C. S.n.c",
    "wof:placetype":"venue"
},
  "geometry": {"coordinates":[9.868414,45.286797],"type":"Point"}
}