{
  "type": "Feature",
  "properties": {
    "iso:country":"IT",
    "sg:address":"00192 Roma",
    "sg:city":"Roma",
    "sg:orig_category":"Servizi E Lavori Per Arredamento E Industria Del Legno. Forniture Per Congressi, Fiere E Manifestazioni. Servizi Per Aziende, Manifestazioni E Supporto Agli Scambi Commerciali",
    "sg:phone":"+39 06 3975 0818",
    "sg:postcode":"00192",
    "sg:province":"Roma",
    "wof:name":"Le Spose Di Dat\u00cd",
    "wof:placetype":"venue"
},
  "geometry": {"coordinates":[12.459567,41.908146],"type":"Point"}
}