{
  "type": "Feature",
  "properties": {
    "addr:full":"Contrada Sabbione 74100 Taranto Taranto Taranto 74100",
    "addr:postcode":"74100;74100",
    "addr:street":"Contrada Sabbione",
    "iso:country":"IT",
    "sg:address":"Contrada Sabbione 74100 Taranto",
    "sg:city":"Taranto",
    "sg:classifiers":[
        {
            "category":"Autos & Motor Vehicles",
            "subcategory":"Boat Sales",
            "type":"Retail Goods"
        }
    ],
    "sg:phone":"+39 099 733 1140",
    "sg:postcode":"74100",
    "sg:province":"Taranto",
    "wof:name":"Cantiere Navale Greco",
    "wof:placetype":"venue"
},
  "geometry": {"coordinates":[17.240009,40.469238],"type":"Point"}
}