{
  "type": "Feature",
  "properties": {
    "iso:country":"IT",
    "sg:address":"22060 Figino Serenza",
    "sg:city":"Figino Serenza",
    "sg:orig_category":"Materiali Edili",
    "sg:phone":"+39 031 726431",
    "sg:postcode":"22060",
    "sg:province":"Como",
    "wof:name":"Co.pre Snc",
    "wof:placetype":"venue"
},
  "geometry": {"coordinates":[9.135368,45.702816],"type":"Point"}
}