{
  "type": "Feature",
  "properties": {
    "addr:full":"55049 Viareggio Viareggio Lucca 55049",
    "addr:postcode":"55049;55049",
    "iso:country":"IT",
    "sg:address":"55049 Viareggio",
    "sg:city":"Viareggio",
    "sg:orig_category":"Dentisti Medici Chirurghi Ed Odontoiatri",
    "sg:phone":"+39 0584 53500",
    "sg:postcode":"55049",
    "sg:province":"Lucca",
    "wof:name":"Dr. Cesare Paoleschi",
    "wof:placetype":"venue"
},
  "geometry": {"coordinates":[10.299923,43.95266],"type":"Point"}
}