{
  "type": "Feature",
  "properties": {
    "iso:country":"IT",
    "sg:address":"10036 Settimo Torinese",
    "sg:city":"Settimo Torinese",
    "sg:orig_category":"Calzature, Pelletterie E Pelli. Shopping",
    "sg:phone":"+39 011 895 7425",
    "sg:postcode":"10036",
    "sg:province":"Torino",
    "wof:name":"Center Bag 2000 Di Cardace Antonio & C. Sas",
    "wof:placetype":"venue"
},
  "geometry": {"coordinates":[7.742941,45.128586],"type":"Point"}
}