{
  "type": "Feature",
  "properties": {
    "addr:full":"54100 Massa Massa Massa-Carrara 54100",
    "addr:postcode":"54100;54100",
    "iso:country":"IT",
    "sg:address":"54100 Massa",
    "sg:city":"Massa",
    "sg:orig_category":"Calzature, Pelletterie E Pelli. Shopping",
    "sg:phone":"+39 0585 40740",
    "sg:postcode":"54100",
    "sg:province":"Massa-Carrara",
    "wof:name":"Lazzarelli Srl",
    "wof:placetype":"venue"
},
  "geometry": {"coordinates":[10.035966,44.221401],"type":"Point"}
}