{
  "type": "Feature",
  "properties": {
    "iso:country":"IT",
    "sg:address":"Via Colzano 32 25030 Adro",
    "sg:city":"Adro",
    "sg:classifiers":[
        {
            "category":"Winery",
            "type":"Food & Drink"
        }
    ],
    "sg:phone":"+39 030 745 0126",
    "sg:postcode":"25030",
    "sg:province":"Brescia",
    "sg:tags":[
        "wine",
        "top-class"
    ],
    "sg:website":"www.contadicastaldi.it",
    "wof:name":"Contadi Castaldi Srl",
    "wof:placetype":"venue"
},
  "geometry": {"coordinates":[9.953164,45.630558],"type":"Point"}
}