{
  "type": "Feature",
  "properties": {
    "iso:country":"IT",
    "sg:address":"14, Via Austria 41100 Modena",
    "sg:city":"Modena",
    "sg:classifiers":[
        {
            "category":"Professional",
            "subcategory":"Engineering",
            "type":"Services"
        }
    ],
    "sg:phone":"+39 059 213 0711",
    "sg:postcode":"41100",
    "sg:province":"Modena",
    "sg:tags":[
        "machine",
        "-",
        "mechanical"
    ],
    "wof:name":"A.t.p. S.p.a.",
    "wof:placetype":"venue"
},
  "geometry": {"coordinates":[10.935766,44.668438],"type":"Point"}
}