{
  "type": "Feature",
  "properties": {
    "addr:full":"Corso Vittorio Emanuele Ii 105 10128 Torino Torino Torino 10128",
    "addr:housenumber":"105",
    "addr:postcode":"10128;10128",
    "addr:street":"Corso Vittorio Emanuele Ii",
    "iso:country":"IT",
    "sg:address":"Corso Vittorio Emanuele Ii 105 10128 Torino",
    "sg:city":"Torino",
    "sg:orig_category":"Precast Concrete Components For Bridge Building",
    "sg:phone":"+39 011 517 0124",
    "sg:postcode":"10128",
    "sg:province":"Torino",
    "wof:name":"Tensiter Spa",
    "wof:placetype":"venue"
},
  "geometry": {"coordinates":[7.6668772697,45.066860199],"type":"Point"}
}