{
  "type": "Feature",
  "properties": {
    "addr:full":"81022 Casagiove Casagiove Caserta 81022",
    "addr:postcode":"81022;81022",
    "iso:country":"IT",
    "sg:address":"81022 Casagiove",
    "sg:city":"Casagiove",
    "sg:orig_category":"Macchine, Strumenti Ed Apparecchi Per Attivita' Industriali",
    "sg:phone":"+39 0823 492869",
    "sg:postcode":"81022",
    "sg:province":"Caserta",
    "sg:website":"http://www.elmeg.caserta.it",
    "wof:name":"Elmeg Di Iovino Vincenzo",
    "wof:placetype":"venue"
},
  "geometry": {"coordinates":[14.311851,41.074863],"type":"Point"}
}