{
  "type": "Feature",
  "properties": {
    "addr:full":"70020 Bitritto Bitritto Bari 70020",
    "addr:postcode":"70020;70020",
    "iso:country":"IT",
    "sg:address":"70020 Bitritto",
    "sg:city":"Bitritto",
    "sg:orig_category":"Nautica. Forniture Per Attivita' Commerciali Ed Artigianali",
    "sg:phone":"+39 080 637109",
    "sg:postcode":"70020",
    "sg:province":"Bari",
    "wof:name":"Cordami S.r.l.",
    "wof:placetype":"venue"
},
  "geometry": {"coordinates":[16.829161,41.04213],"type":"Point"}
}