{
  "type": "Feature",
  "properties": {
    "addr:full":"2, Via Corazzi 26100 Cremona Cremona Cremona 26100",
    "addr:postcode":"26100;26100",
    "addr:street":"Via Corazzi",
    "iso:country":"IT",
    "sg:address":"2, Via Corazzi 26100 Cremona",
    "sg:city":"Cremona",
    "sg:orig_category":"Miscellaneous Products",
    "sg:phone":"+39 39037240481",
    "sg:postcode":"26100",
    "sg:province":"Cremona",
    "wof:name":"Corazzi Paolo Fibre S.r.l.",
    "wof:placetype":"venue"
},
  "geometry": {"coordinates":[9.9898071289,45.1448478699],"type":"Point"}
}