{
  "type": "Feature",
  "properties": {
    "iso:country":"IT",
    "sg:address":"96010 Melilli",
    "sg:city":"Melilli",
    "sg:orig_category":"Macchine, Impianti Ed Attrezzature Per Agricoltura E Zootecnia",
    "sg:phone":"+39 0931 761330",
    "sg:postcode":"96010",
    "sg:province":"Siracusa",
    "wof:name":"Mangione Provvidenza - Sicilcorde",
    "wof:placetype":"venue"
},
  "geometry": {"coordinates":[15.126534,37.180744],"type":"Point"}
}