{
  "type": "Feature",
  "properties": {
    "iso:country":"IT",
    "sg:address":"Via Oberdan ,37/39 45037 Melara",
    "sg:city":"Melara",
    "sg:orig_category":"Screw Conveyors",
    "sg:phone":"+39 0425 89000",
    "sg:postcode":"45037",
    "sg:province":"Rovigo",
    "sg:website":"www.pofer.it",
    "wof:name":"Pofer Srl",
    "wof:placetype":"venue"
},
  "geometry": {"coordinates":[11.789797,45.070736],"type":"Point"}
}