{
  "type": "Feature",
  "properties": {
    "iso:country":"IT",
    "sg:address":"Via Cestari 10; Montesano; 84033",
    "sg:classifiers":[
        {
            "category":"Banks & Credit Unions",
            "subcategory":"Bank",
            "type":"Services"
        }
    ],
    "sg:phone":"+39 0975 865043",
    "sg:postcode":"84033",
    "sg:province":"Salerno",
    "wof:name":"Banco Di Napoli Spa",
    "wof:placetype":"venue"
},
  "geometry": {"coordinates":[15.702699,40.27562],"type":"Point"}
}