{
  "type": "Feature",
  "properties": {
    "addr:full":"16129 Genova Genova Genova 16129",
    "addr:postcode":"16129;16129",
    "iso:country":"IT",
    "sg:address":"16129 Genova",
    "sg:city":"Genova",
    "sg:orig_category":"Musica",
    "sg:phone":"+39 010 564212",
    "sg:postcode":"16129",
    "sg:province":"Genova",
    "wof:name":"Rizzo Aldo",
    "wof:placetype":"venue"
},
  "geometry": {"coordinates":[8.9446115494,44.3967208862],"type":"Point"}
}