{
  "type": "Feature",
  "properties": {
    "addr:full":"20146 Milano Milano Milano 20146",
    "addr:postcode":"20146;20146",
    "iso:country":"IT",
    "sg:address":"20146 Milano",
    "sg:city":"Milano",
    "sg:orig_category":"Chiese Ed Associazioni Religiose",
    "sg:phone":"+39 02 422 3844",
    "sg:postcode":"20146",
    "sg:province":"Milano",
    "wof:name":"Chiesa Cattolica Parrocchiale S. Curato D'ars",
    "wof:placetype":"venue"
},
  "geometry": {"coordinates":[9.136298,45.446564],"type":"Point"}
}