{
  "type": "Feature",
  "properties": {
    "iso:country":"IT",
    "sg:address":"70126 Bari",
    "sg:city":"Bari",
    "sg:orig_category":"Scuole E Servizi Scolastici. Servizi Vari Di Interesse Pubblico",
    "sg:phone":"+39 080 553 7004",
    "sg:postcode":"70126",
    "sg:province":"Bari",
    "wof:name":"Il Bruco Bebe' Srl",
    "wof:placetype":"venue"
},
  "geometry": {"coordinates":[16.891588,41.11747],"type":"Point"}
}