{
  "type": "Feature",
  "properties": {
    "addr:full":"29100 Piacenza Piacenza Piacenza 29100",
    "addr:postcode":"29100;29100",
    "iso:country":"IT",
    "sg:address":"29100 Piacenza",
    "sg:city":"Piacenza",
    "sg:orig_category":"Pubblicita', Marketing E Comunicazione",
    "sg:phone":"+39 0523 385926",
    "sg:postcode":"29100",
    "sg:province":"Piacenza",
    "sg:website":"http://www.davidegalli.com",
    "wof:name":"Galli Davide Davide & Galli",
    "wof:placetype":"venue"
},
  "geometry": {"coordinates":[9.6947822571,45.0509223938],"type":"Point"}
}