{
  "type": "Feature",
  "properties": {
    "addr:full":"4, V. Santuario20090 Limito Milano 20090",
    "addr:housenumber":"4",
    "addr:postcode":"20090",
    "addr:street":"V. Santuario20090 Limito",
    "iso:country":"IT",
    "sg:address":"4, V. Santuario20090 Limito",
    "sg:classifiers":[
        {
            "category":"Shopping",
            "subcategory":"Crafts & Fabrics",
            "type":"Retail Goods"
        }
    ],
    "sg:phone":"+39 390 292 1641",
    "sg:postcode":"20090",
    "sg:province":"Milano",
    "sg:website":"http://www.itamgroup.com:ws_end: :mark:ws:http://www.paginegialle.it/itam",
    "wof:name":"Itam Spa",
    "wof:placetype":"venue"
},
  "geometry": {"coordinates":[9.3264703751,45.4880180359],"type":"Point"}
}