{
  "type": "Feature",
  "properties": {
    "addr:full":"Via Boccaccio 25080 Mazzano Mazzano Brescia 25080",
    "addr:postcode":"25080;25080",
    "addr:street":"Via Boccaccio",
    "iso:country":"IT",
    "sg:address":"Via Boccaccio 25080 Mazzano",
    "sg:city":"Mazzano",
    "sg:classifiers":[
        {
            "category":"Professional",
            "subcategory":"Engineering",
            "type":"Services"
        }
    ],
    "sg:phone":"+39 030 262 0865",
    "sg:postcode":"25080",
    "sg:province":"Brescia",
    "sg:tags":[
        "machine",
        "-",
        "mechanical"
    ],
    "wof:name":"Officina Meccanica Coccoli Di Coccoli Lucio E C. (",
    "wof:placetype":"venue"
},
  "geometry": {"coordinates":[10.222958,45.539829],"type":"Point"}
}