{
  "type": "Feature",
  "properties": {
    "addr:full":"22063 Cantu' Como 22063",
    "addr:postcode":"22063;22063",
    "addr:street":"Cantu ' Como",
    "iso:country":"IT",
    "sg:address":"22063 Cantu'",
    "sg:orig_category":"Petroli, Gas E Combustibili. Servizi E Lavori Industria Chimica. Servizi E Lavori Per Edilizia E Lavori Pubblici. Acqua, Luce, Gas E Societa' Di Esercizio Pubblico",
    "sg:phone":"+39 031 712113",
    "sg:postcode":"22063",
    "sg:province":"Como",
    "sg:website":"http://www.canturinaservizi.it",
    "wof:name":"Canturina Servizi Spa",
    "wof:placetype":"venue"
},
  "geometry": {"coordinates":[9.1296415329,45.7532424927],"type":"Point"}
}