{
  "type": "Feature",
  "properties": {
    "iso:country":"IT",
    "sg:address":"80143 Napoli",
    "sg:city":"Napoli",
    "sg:classifiers":[
        {
            "category":"Professional",
            "subcategory":"Management & Consulting",
            "type":"Services"
        }
    ],
    "sg:phone":"+39 081 200960",
    "sg:postcode":"80143",
    "sg:province":"Napoli",
    "sg:tags":[
        "business",
        "technical",
        "consultant",
        "administration",
        "consultancies",
        "administrative",
        "appraiser"
    ],
    "wof:name":"Scarpati Dr. Romano",
    "wof:placetype":"venue"
},
  "geometry": {"coordinates":[14.286764,40.899895],"type":"Point"}
}