{
  "type": "Feature",
  "properties": {
    "iso:country":"IT",
    "sg:address":"Via Sra 170 Colognola Ai Colii 37030 Velo Veronese",
    "sg:city":"Velo Veronese",
    "sg:classifiers":[
        {
            "category":"Manufacturing",
            "subcategory":"Motor Vehicles & Parts",
            "type":"Manufacturing & Wholesale Goods"
        }
    ],
    "sg:phone":"+39 045 615 9011",
    "sg:postcode":"37030",
    "sg:province":"Verona",
    "sg:tags":[
        "industry",
        "metallurgical",
        "spare"
    ],
    "wof:name":"Metall Steel Srl",
    "wof:placetype":"venue"
},
  "geometry": {"coordinates":[10.991748,45.438366],"type":"Point"}
}