{
  "type": "Feature",
  "properties": {
    "addr:full":"12, Via Raso 25036 Palazzolo Sull'oglio Brescia 25036",
    "addr:postcode":"25036;25036",
    "addr:street":"Via Raso",
    "iso:country":"IT",
    "sg:address":"12, Via Raso 25036 Palazzolo Sull'oglio",
    "sg:classifiers":[
        {
            "category":"Shopping",
            "subcategory":"Crafts & Fabrics",
            "type":"Retail Goods"
        }
    ],
    "sg:phone":"+39 030 730 0969",
    "sg:postcode":"25036",
    "sg:province":"Brescia",
    "wof:name":"Gasatura E Aspatura Di Belotti Bruno & C. (s.n.c.)",
    "wof:placetype":"venue"
},
  "geometry": {"coordinates":[9.8896932602,45.5848731995],"type":"Point"}
}