{
  "type": "Feature",
  "properties": {
    "iso:country":"IT",
    "sg:address":"37139 Verona",
    "sg:city":"Verona",
    "sg:orig_category":"Centri Di Estetica E Cosmesi E Servizi",
    "sg:phone":"+39 045 800 8889",
    "sg:postcode":"37139",
    "sg:province":"Verona",
    "wof:name":"Beauty Time Snc",
    "wof:placetype":"venue"
},
  "geometry": {"coordinates":[10.950445,45.440048],"type":"Point"}
}