{
  "type": "Feature",
  "properties": {
    "iso:country":"IT",
    "sg:address":"20149 Milano",
    "sg:city":"Milano",
    "sg:orig_category":"Servizi Vari Di Interesse Pubblico",
    "sg:phone":"+39 02 3453 7054",
    "sg:postcode":"20149",
    "sg:province":"Milano",
    "wof:name":"Flores Sergio",
    "wof:placetype":"venue"
},
  "geometry": {"coordinates":[9.155325,45.487125],"type":"Point"}
}