{
  "type": "Feature",
  "properties": {
    "iso:country":"IT",
    "sg:address":"89900 Vibo Valentia",
    "sg:city":"Vibo Valentia",
    "sg:orig_category":"Petroli, Gas E Combustibili. Servizi E Lavori Industria Chimica. Servizi E Lavori Per Edilizia E Lavori Pubblici. Acqua, Luce, Gas E Societa' Di Esercizio Pubblico",
    "sg:phone":"+39 0963 571850",
    "sg:postcode":"89900",
    "sg:province":"Vibo Valentia",
    "wof:name":"Instem Di Carenza Vincenza",
    "wof:placetype":"venue"
},
  "geometry": {"coordinates":[16.1271018982,38.713760376],"type":"Point"}
}