{
  "type": "Feature",
  "properties": {
    "addr:full":"14, Via Lama 41012 Carpi Carpi Modena 41012",
    "addr:postcode":"41012;41012",
    "addr:street":"Via Lama",
    "iso:country":"IT",
    "sg:address":"14, Via Lama 41012 Carpi",
    "sg:city":"Carpi",
    "sg:classifiers":[
        {
            "category":"Shopping",
            "subcategory":"Clothing, Apparel, & Fashions",
            "type":"Retail Goods"
        }
    ],
    "sg:phone":"+39 39059643771",
    "sg:postcode":"41012",
    "sg:province":"Modena",
    "sg:tags":[
        "clothes"
    ],
    "wof:name":"Maglificio Noemi (s.r.l.)",
    "wof:placetype":"venue"
},
  "geometry": {"coordinates":[10.855998,44.715462],"type":"Point"}
}