{
  "type": "Feature",
  "properties": {
    "addr:full":"Viale Espinasse Carlo 41 20156 Milano Milano Milano 20156",
    "addr:housenumber":"41",
    "addr:postcode":"20156;20156",
    "addr:street":"Viale Espinasse Carlo",
    "iso:country":"IT",
    "sg:address":"Viale Espinasse Carlo 41 20156 Milano",
    "sg:city":"Milano",
    "sg:classifiers":[
        {
            "category":"Banks & Credit Unions",
            "subcategory":"Investment Brokerage",
            "type":"Services"
        }
    ],
    "sg:phone":"+39 02 324746",
    "sg:postcode":"20156",
    "sg:province":"Milano",
    "sg:tags":[
        "aid"
    ],
    "sg:website":"www.spal-srl.com",
    "wof:name":"Spal Srl",
    "wof:placetype":"venue"
},
  "geometry": {"coordinates":[9.203226,45.482468],"type":"Point"}
}