{
  "type": "Feature",
  "properties": {
    "iso:country":"IT",
    "sg:address":"85100 Potenza",
    "sg:city":"Potenza",
    "sg:orig_category":"Prodotti Di Base E Forniture Per Industria Alimentare E Bevande",
    "sg:phone":"+39 0971 52127",
    "sg:postcode":"85100",
    "sg:province":"Potenza",
    "wof:name":"Velini Donato",
    "wof:placetype":"venue"
},
  "geometry": {"coordinates":[15.7884235382,40.6328201294],"type":"Point"}
}