{
  "type": "Feature",
  "properties": {
    "iso:country":"IT",
    "sg:address":"42020 San Polo D'enza",
    "sg:orig_category":"Non-classified Establishments",
    "sg:phone":"+39 0522 873018",
    "sg:postcode":"42020",
    "sg:province":"Reggio Nell'Emilia",
    "wof:name":"Centro Gis (s.r.l.)",
    "wof:placetype":"venue"
},
  "geometry": {"coordinates":[10.472659,44.644485],"type":"Point"}
}