{
  "type": "Feature",
  "properties": {
    "iso:country":"IT",
    "sg:address":"115, Via S. Polo 34074 Monfalcone",
    "sg:city":"Monfalcone",
    "sg:classifiers":[
        {
            "category":"Autos & Motor Vehicles",
            "subcategory":"Boat Sales",
            "type":"Retail Goods"
        }
    ],
    "sg:phone":"+39 0481 413472",
    "sg:postcode":"34074",
    "sg:province":"Gorizia",
    "wof:name":"Vindigni Srl",
    "wof:placetype":"venue"
},
  "geometry": {"coordinates":[13.6215457916,45.9413032532],"type":"Point"}
}