{
  "type": "Feature",
  "properties": {
    "iso:country":"IT",
    "sg:address":"88100 Catanzaro",
    "sg:city":"Catanzaro",
    "sg:orig_category":"Certificazione Qualita', Sicurezza Ed Ambiente",
    "sg:phone":"+39 0961 777713",
    "sg:postcode":"88100",
    "sg:province":"Catanzaro",
    "sg:website":"http://www.sialservice.interfree.it",
    "wof:name":"S.i.a.l. Service Srl Sicurezza-igiene-ambiente Lavoro",
    "wof:placetype":"venue"
},
  "geometry": {"coordinates":[16.581646,38.904099],"type":"Point"}
}