{
  "type": "Feature",
  "properties": {
    "addr:full":"39, Strada Antica Fornace 14053 Canelli Canelli Asti 14053",
    "addr:postcode":"14053;14053",
    "addr:street":"Strada Antica Fornace",
    "iso:country":"IT",
    "sg:address":"39, Strada Antica Fornace 14053 Canelli",
    "sg:city":"Canelli",
    "sg:classifiers":[
        {
            "category":"Manufacturing",
            "subcategory":"Food",
            "type":"Manufacturing & Wholesale Goods"
        }
    ],
    "sg:phone":"+39 0141 821511",
    "sg:postcode":"14053",
    "sg:province":"Asti",
    "sg:tags":[
        "equipment",
        "processing",
        "-",
        "machinery"
    ],
    "wof:name":"Intercap Srl",
    "wof:placetype":"venue"
},
  "geometry": {"coordinates":[8.3047637939,44.7302780151],"type":"Point"}
}