{
  "type": "Feature",
  "properties": {
    "iso:country":"IT",
    "sg:address":"3/5, Via Peschiera 33020 Sutrio",
    "sg:city":"Sutrio",
    "sg:classifiers":[
        {
            "category":"Manufacturing",
            "subcategory":"Lumber",
            "type":"Manufacturing & Wholesale Goods"
        }
    ],
    "sg:phone":"+39 0433 778762",
    "sg:postcode":"33020",
    "sg:province":"Udine",
    "sg:tags":[
        "wood"
    ],
    "wof:name":"Stratex S.p.a.",
    "wof:placetype":"venue"
},
  "geometry": {"coordinates":[12.998791,46.507843],"type":"Point"}
}