{
  "type": "Feature",
  "properties": {
    "addr:full":"Via Palazzo 12 24047 Treviglio Treviglio Bergamo 24047",
    "addr:housenumber":"12",
    "addr:postcode":"24047;24047",
    "addr:street":"Via Palazzo",
    "iso:country":"IT",
    "sg:address":"Via Palazzo 12 24047 Treviglio",
    "sg:city":"Treviglio",
    "sg:classifiers":[
        {
            "category":"Manufacturing",
            "subcategory":"Glass & Minerals",
            "type":"Manufacturing & Wholesale Goods"
        }
    ],
    "sg:phone":"+39 036 348855",
    "sg:postcode":"24047",
    "sg:province":"Bergamo",
    "sg:tags":[
        "industry",
        "machinery"
    ],
    "sg:website":"www.ariste.it",
    "wof:name":"Ariste Srl",
    "wof:placetype":"venue"
},
  "geometry": {"coordinates":[9.582809,45.507175],"type":"Point"}
}