{
  "type": "Feature",
  "properties": {
    "addr:full":"Strada Vic. Sant'angelo 70017 Putignano Putignano Bari 70017",
    "addr:postcode":"70017;70017",
    "addr:street":"Strada Vic.",
    "iso:country":"IT",
    "sg:address":"Strada Vic. Sant'angelo 70017 Putignano",
    "sg:city":"Putignano",
    "sg:classifiers":[
        {
            "category":"Food & Beverages",
            "subcategory":"Dairy",
            "type":"Retail Goods"
        }
    ],
    "sg:phone":"+39 080 405 1410",
    "sg:postcode":"70017",
    "sg:province":"Bari",
    "sg:tags":[
        "product"
    ],
    "wof:name":"Caseificio Palazzo S.p.a.",
    "wof:placetype":"venue"
},
  "geometry": {"coordinates":[16.869291,41.126053],"type":"Point"}
}