{
  "type": "Feature",
  "properties": {
    "iso:country":"IT",
    "sg:address":"Via Mercadante Saverio 15 20124 Milano",
    "sg:city":"Milano",
    "sg:classifiers":[
        {
            "category":"Wholesale",
            "subcategory":"Medical Equipment & Supplies",
            "type":"Manufacturing & Wholesale Goods"
        }
    ],
    "sg:phone":"+39 02 669 3481",
    "sg:postcode":"20124",
    "sg:province":"Milano",
    "sg:tags":[
        "instrument",
        "surgical"
    ],
    "wof:name":"Medicalplastic Srl",
    "wof:placetype":"venue"
},
  "geometry": {"coordinates":[9.213091,45.483814],"type":"Point"}
}