{
  "type": "Feature",
  "properties": {
    "iso:country":"IT",
    "sg:address":"42048 Rubiera",
    "sg:orig_category":"Prodotti E Manufatti In Materie Plastiche. Articoli Per Imballaggio E Confezionamento",
    "sg:postcode":"42048",
    "sg:province":"Reggio Nell'Emilia",
    "wof:name":"Pagani - Hilary's Pagani (s.r.l.)",
    "wof:placetype":"venue"
},
  "geometry": {"coordinates":[10.7660551071,44.657119751],"type":"Point"}
}