{
  "type": "Feature",
  "properties": {
    "iso:country":"IT",
    "sg:address":"00174 Roma",
    "sg:city":"Roma",
    "sg:orig_category":"Servizi E Lavori Per Arredamento E Industria Del Legno. Vetro: Prodotti E Lavorazioni",
    "sg:phone":"+39 06 748 1627",
    "sg:postcode":"00174",
    "sg:province":"Roma",
    "wof:name":"Vetreria Piombarolo Francesco",
    "wof:placetype":"venue"
},
  "geometry": {"coordinates":[12.557054,41.857018],"type":"Point"}
}