{
  "type": "Feature",
  "properties": {
    "iso:country":"IT",
    "sg:address":"3, V. Barberini 00187 Roma",
    "sg:city":"Roma",
    "sg:classifiers":[
        {
            "category":"Banks & Credit Unions",
            "subcategory":"Financial Services",
            "type":"Services"
        }
    ],
    "sg:phone":"+39 39064819595",
    "sg:postcode":"00187",
    "sg:province":"Roma",
    "sg:tags":[
        "banking",
        "finance",
        "insurance"
    ],
    "wof:name":"Guttieres Avv. Mario Remiddi Avv. Laura E Associati",
    "wof:placetype":"venue"
},
  "geometry": {"coordinates":[12.489099,41.903732],"type":"Point"}
}