{
  "type": "Feature",
  "properties": {
    "addr:full":"51039 Quarrata Quarrata Pistoia 51039",
    "addr:postcode":"51039;51039",
    "iso:country":"IT",
    "sg:address":"51039 Quarrata",
    "sg:city":"Quarrata",
    "sg:orig_category":"Salotti, Poltrone, Sedie E Tavoli",
    "sg:phone":"+39 0573 738524",
    "sg:postcode":"51039",
    "sg:province":"Pistoia",
    "wof:name":"Cangioloni Imolo",
    "wof:placetype":"venue"
},
  "geometry": {"coordinates":[10.974707,43.858826],"type":"Point"}
}