{
  "type": "Feature",
  "properties": {
    "iso:country":"IT",
    "sg:address":"39012 Merano",
    "sg:city":"Merano",
    "sg:orig_category":"Articoli Sportivi - Produzione E Ingrosso",
    "sg:phone":"+39 0473 204300",
    "sg:postcode":"39012",
    "sg:province":"Bolzano/Bozen",
    "wof:name":"Huber Srl",
    "wof:placetype":"venue"
},
  "geometry": {"coordinates":[11.157018,46.653404],"type":"Point"}
}