{
  "type": "Feature",
  "properties": {
    "iso:country":"IT",
    "sg:address":"48, Via Buffolareccia 60025 Loreto",
    "sg:city":"Loreto",
    "sg:classifiers":[
        {
            "category":"Professional",
            "subcategory":"Engineering",
            "type":"Services"
        }
    ],
    "sg:phone":"+39 071 750 0217",
    "sg:postcode":"60025",
    "sg:province":"Ancona",
    "sg:tags":[
        "machine",
        "-",
        "mechanical"
    ],
    "wof:name":"Lo.met. Loreto Metalli Spa",
    "wof:placetype":"venue"
},
  "geometry": {"coordinates":[13.620826,43.440475],"type":"Point"}
}