{
  "type": "Feature",
  "properties": {
    "iso:country":"IT",
    "sg:address":"52022 Cavriglia",
    "sg:city":"Cavriglia",
    "sg:orig_category":"Articoli Medico-sanitari Ed Ortopedici. Impianti, Attrezzature E Forniture Sanitarie Ed Ospedaliere",
    "sg:phone":"+39 055 961746",
    "sg:postcode":"52022",
    "sg:province":"Arezzo",
    "wof:name":"Me.tec. Srl",
    "wof:placetype":"venue"
},
  "geometry": {"coordinates":[11.487982,43.521259],"type":"Point"}
}