{
  "type": "Feature",
  "properties": {
    "iso:country":"IT",
    "sg:address":"15/canc, Via Barchetta 16162 Genova",
    "sg:city":"Genova",
    "sg:classifiers":[
        {
            "category":"Food & Beverages",
            "subcategory":"Groceries & Convenience Stores",
            "type":"Retail Goods"
        }
    ],
    "sg:phone":"+39 010 745 3651",
    "sg:postcode":"16162",
    "sg:province":"Genova",
    "sg:tags":[
        "product",
        "related"
    ],
    "wof:name":"Soripesca (s.n.c.)",
    "wof:placetype":"venue"
},
  "geometry": {"coordinates":[8.9339885712,44.4070625305],"type":"Point"}
}