{
  "type": "Feature",
  "properties": {
    "iso:country":"IT",
    "sg:address":"27045 Casteggio",
    "sg:city":"Casteggio",
    "sg:orig_category":"Bevande, Vini E Liquori",
    "sg:phone":"+39 0383 82744",
    "sg:postcode":"27045",
    "sg:province":"Pavia",
    "wof:name":"Garagiola Giancarlo",
    "wof:placetype":"venue"
},
  "geometry": {"coordinates":[9.120109,45.011215],"type":"Point"}
}