{
  "type": "Feature",
  "properties": {
    "iso:country":"IT",
    "sg:address":"Via Crispi, 110/b; Bari; 70100",
    "sg:classifiers":[
        {
            "category":"Banks & Credit Unions",
            "subcategory":"Bank",
            "type":"Services"
        }
    ],
    "sg:phone":"+39 080 349175",
    "wof:name":"Banca Nazionale Dell' Agricoltura",
    "wof:placetype":"venue"
},
  "geometry": {"coordinates":[16.855505,41.123363],"type":"Point"}
}