{
  "type": "Feature",
  "properties": {
    "addr:full":"20090 Cesano Boscone Cesano Boscone Milano 20090",
    "addr:postcode":"20090;20090",
    "iso:country":"IT",
    "sg:address":"20090 Cesano Boscone",
    "sg:city":"Cesano Boscone",
    "sg:orig_category":"Lavanderie - Impianti E Macchine",
    "sg:phone":"+39 02 447 0408",
    "sg:postcode":"20090",
    "sg:province":"Milano",
    "wof:name":"Tecnowash Srl",
    "wof:placetype":"venue"
},
  "geometry": {"coordinates":[9.09132,45.427402],"type":"Point"}
}