{
  "type": "Feature",
  "properties": {
    "addr:full":"39023 Lasa Lasa Bolzano/Bozen 39023",
    "addr:postcode":"39023;39023",
    "iso:country":"IT",
    "sg:address":"39023 Lasa",
    "sg:city":"Lasa",
    "sg:orig_category":"Lampadari - Produzione E Ingrosso",
    "sg:phone":"+39 0473 739788",
    "sg:postcode":"39023",
    "sg:province":"Bolzano/Bozen",
    "sg:website":"http://www.paginegialle.it/ancoleuchten",
    "wof:name":"Anco Leuchten - Oris",
    "wof:placetype":"venue"
},
  "geometry": {"coordinates":[11.35800457,46.4967155457],"type":"Point"}
}