{
  "type": "Feature",
  "properties": {
    "addr:full":"22, Via Gramsci 46027 San Benedetto Po San Benedetto Po Mantova 46027",
    "addr:postcode":"46027;46027",
    "addr:street":"Via Gramsci;Po",
    "iso:country":"IT",
    "sg:address":"22, Via Gramsci 46027 San Benedetto Po",
    "sg:city":"San Benedetto Po",
    "sg:classifiers":[
        {
            "category":"Retail",
            "subcategory":"Animal Services",
            "type":"Services"
        }
    ],
    "sg:phone":"+39 0376 615352",
    "sg:postcode":"46027",
    "sg:province":"Mantova",
    "sg:tags":[
        "breeding"
    ],
    "wof:name":"Molini Landucci (s.r.l.)",
    "wof:placetype":"venue"
},
  "geometry": {"coordinates":[10.797698,45.160366],"type":"Point"}
}