{
  "type": "Feature",
  "properties": {
    "addr:full":"20090 Assago Assago Milano 20090",
    "addr:postcode":"20090;20090",
    "addr:street":"Assago",
    "iso:country":"IT",
    "sg:address":"20090 Assago",
    "sg:city":"Assago",
    "sg:orig_category":"Prodotti Alimentari",
    "sg:phone":"+39 02 488 0287",
    "sg:postcode":"20090",
    "sg:province":"Milano",
    "wof:name":"Humana Italia S.p.a.",
    "wof:placetype":"venue"
},
  "geometry": {"coordinates":[9.1206264496,45.4035873413],"type":"Point"}
}