{
  "type": "Feature",
  "properties": {
    "addr:full":"36065 Mussolente Mussolente Vicenza 36065",
    "addr:postcode":"36065;36065",
    "iso:country":"IT",
    "sg:address":"36065 Mussolente",
    "sg:city":"Mussolente",
    "sg:orig_category":"Macchine, Impianti Ed Attrezzature Industria Chimica",
    "sg:phone":"+39 0424 573839",
    "sg:postcode":"36065",
    "sg:province":"Vicenza",
    "wof:name":"Dal Molin Guerrino",
    "wof:placetype":"venue"
},
  "geometry": {"coordinates":[11.79038,45.739555],"type":"Point"}
}