{
  "type": "Feature",
  "properties": {
    "iso:country":"IT",
    "sg:address":"Via Baroggi 10; Maccagno",
    "sg:classifiers":[
        {
            "category":"Banks & Credit Unions",
            "subcategory":"Bank",
            "type":"Services"
        }
    ],
    "sg:phone":"+39 0332 561088",
    "wof:name":"Banca Populare Di Luino, E Di Varese",
    "wof:placetype":"venue"
},
  "geometry": {"coordinates":[8.738553,46.043957],"type":"Point"}
}