{
  "type": "Feature",
  "properties": {
    "iso:country":"IT",
    "sg:address":"30035 Mirano",
    "sg:city":"Mirano",
    "sg:orig_category":"Servizi Vari Di Interesse Pubblico",
    "sg:phone":"+39 041 570 2682",
    "sg:postcode":"30035",
    "sg:province":"Venezia",
    "wof:name":"Centro Terapie Naturali",
    "wof:placetype":"venue"
},
  "geometry": {"coordinates":[12.078761,45.482025],"type":"Point"}
}