{
  "type": "Feature",
  "properties": {
    "iso:country":"IT",
    "sg:address":"Via Vittorio Emanuele Ii 73040 Alliste",
    "sg:city":"Alliste",
    "sg:orig_category":"Flacons",
    "sg:phone":"+39 0833 584409",
    "sg:postcode":"73040",
    "sg:province":"Lecce",
    "wof:name":"Allplast Srl",
    "wof:placetype":"venue"
},
  "geometry": {"coordinates":[18.0891685486,39.9458770752],"type":"Point"}
}