{
  "type": "Feature",
  "properties": {
    "iso:country":"IT",
    "sg:address":"74015 Martina Franca",
    "sg:city":"Martina Franca",
    "sg:orig_category":"Pubblica Amministrazione",
    "sg:phone":"+39 080 480 1610",
    "sg:postcode":"74015",
    "sg:province":"Taranto",
    "wof:name":"Carabinieri",
    "wof:placetype":"venue"
},
  "geometry": {"coordinates":[17.4759502411,40.5818710327],"type":"Point"}
}