{
  "type": "Feature",
  "properties": {
    "iso:country":"IT",
    "sg:address":"Via Circonvallazione Est 25 31033 Castelfranco Veneto",
    "sg:city":"Castelfranco Veneto",
    "sg:classifiers":[
        {
            "category":"Banks & Credit Unions",
            "subcategory":"Investment Brokerage",
            "type":"Services"
        }
    ],
    "sg:phone":"+39 0423 490718",
    "sg:postcode":"31033",
    "sg:province":"Treviso",
    "sg:tags":[
        "lift",
        "truck"
    ],
    "sg:website":"www.zandona.it",
    "wof:name":"Zandona' Luigi S.r.l.",
    "wof:placetype":"venue"
},
  "geometry": {"coordinates":[11.96002,45.685497],"type":"Point"}
}