{
  "type": "Feature",
  "properties": {
    "iso:country":"IT",
    "sg:address":"17012 Albisola Marina",
    "sg:orig_category":"Macchine E Forniture Per Ecologia E Smaltimento Rifiuti. Macchine, Strumenti Ed Apparecchi Per Attivita' Industriali",
    "sg:phone":"+39 019 483034",
    "sg:postcode":"17012",
    "sg:province":"Savona",
    "sg:website":"http://www.comliguria.com",
    "wof:name":"Com Di Quafa Abderrahman",
    "wof:placetype":"venue"
},
  "geometry": {"coordinates":[8.497266,44.337635],"type":"Point"}
}