{
  "type": "Feature",
  "properties": {
    "iso:country":"IT",
    "sg:address":"16162 Genova",
    "sg:city":"Genova",
    "sg:orig_category":"Caminetti, Forni Da Giardino E Barbecues",
    "sg:phone":"+39 010 745 0048",
    "sg:postcode":"16162",
    "sg:province":"Genova",
    "wof:name":"Mondialcasa Sas",
    "wof:placetype":"venue"
},
  "geometry": {"coordinates":[8.907978,44.460815],"type":"Point"}
}