{
  "type": "Feature",
  "properties": {
    "iso:country":"IT",
    "sg:address":"36050 Pozzoleone",
    "sg:city":"Pozzoleone",
    "sg:orig_category":"Ceramiche: Prodotti E Lavorazioni. Articoli Da Regalo. Arte Ed Artigianato Artistico. Shopping",
    "sg:phone":"+39 0444 668144",
    "sg:postcode":"36050",
    "sg:province":"Vicenza",
    "wof:name":"Ceramiche San Valentino Sas Di Rigo Domenico",
    "wof:placetype":"venue"
},
  "geometry": {"coordinates":[11.679248,45.648899],"type":"Point"}
}