{
  "type": "Feature",
  "properties": {
    "iso:country":"IT",
    "sg:address":"54, Via Gramsci 40050 Argelato",
    "sg:city":"Argelato",
    "sg:classifiers":[
        {
            "category":"Professional",
            "subcategory":"Engineering",
            "type":"Services"
        }
    ],
    "sg:phone":"+39 39051860770",
    "sg:postcode":"40050",
    "sg:province":"Bologna",
    "sg:tags":[
        "machine",
        "-",
        "mechanical"
    ],
    "wof:name":"Giorgi Oriano & C. Srl",
    "wof:placetype":"venue"
},
  "geometry": {"coordinates":[11.364442,44.576141],"type":"Point"}
}