{
  "type": "Feature",
  "properties": {
    "iso:country":"IT",
    "sg:address":"Via Ing. C. Luda, 11/13 10022 Carmagnola",
    "sg:city":"Carmagnola",
    "sg:classifiers":[
        {
            "category":"Banks & Credit Unions",
            "subcategory":"Investment Brokerage",
            "type":"Services"
        }
    ],
    "sg:phone":"+39 011 972 1336",
    "sg:postcode":"10022",
    "sg:province":"Torino",
    "sg:tags":[
        "women's",
        "clothing",
        "accessory"
    ],
    "sg:website":"www.offersrl.it",
    "wof:name":"Offer Srl",
    "wof:placetype":"venue"
},
  "geometry": {"coordinates":[7.686619,45.07056],"type":"Point"}
}