{
  "type": "Feature",
  "properties": {
    "iso:country":"IT",
    "sg:address":"31057 Silea",
    "sg:city":"Cendon",
    "sg:orig_category":"Servizi E Lavori Per Ecologia E Smaltimento Rifiuti. Macchine E Forniture Per Ecologia E Smaltimento Rifiuti",
    "sg:phone":"+39 0422 361960",
    "sg:postcode":"31057",
    "sg:province":"Treviso",
    "wof:name":"S.ve.d.a. Srl",
    "wof:placetype":"venue"
},
  "geometry": {"coordinates":[12.308406,45.643776],"type":"Point"}
}