{
  "type": "Feature",
  "properties": {
    "iso:country":"IT",
    "sg:address":"47020 Longiano",
    "sg:city":"Longiano",
    "sg:orig_category":"Legno E Semilavorati. Manufatti Edili E Prefabbricati",
    "sg:phone":"+39 0547 652111",
    "sg:postcode":"47020",
    "sg:province":"Forl\u00ec-Cesena",
    "sg:website":"http://www.neridomenico.com",
    "wof:name":"Neri Spa",
    "wof:placetype":"venue"
},
  "geometry": {"coordinates":[12.32827,44.075146],"type":"Point"}
}