{
  "type": "Feature",
  "properties": {
    "addr:full":"24040 Boltiere Boltiere Bergamo 24040",
    "addr:postcode":"24040;24040",
    "iso:country":"IT",
    "sg:address":"24040 Boltiere",
    "sg:city":"Boltiere",
    "sg:classifiers":[
        {
            "category":"Bars & Pubs",
            "subcategory":"Champagne Bar",
            "type":"Food & Drink"
        }
    ],
    "sg:phone":"+39 035 881260",
    "sg:postcode":"24040",
    "sg:province":"Bergamo",
    "sg:tags":[
        "caffe'",
        "e"
    ],
    "wof:name":"Il Caffe' Del Mulino",
    "wof:placetype":"venue"
},
  "geometry": {"coordinates":[9.670644,45.696178],"type":"Point"}
}