{
  "type": "Feature",
  "properties": {
    "addr:full":"Via D.luigi Sturzo 75015 Pisticci Pisticci Matera 75015",
    "addr:postcode":"75015;75015",
    "addr:street":"Via D.Luigi Sturzo",
    "iso:country":"IT",
    "sg:address":"Via D.luigi Sturzo 75015 Pisticci",
    "sg:city":"Pisticci",
    "sg:classifiers":[
        {
            "category":"Professional",
            "subcategory":"Engineering",
            "type":"Services"
        }
    ],
    "sg:phone":"+39 0835 411734",
    "sg:postcode":"75015",
    "sg:province":"Matera",
    "sg:tags":[
        "machine",
        "-",
        "mechanical"
    ],
    "wof:name":"A.p.m.assistenza Progettazione Montaggi Srl",
    "wof:placetype":"venue"
},
  "geometry": {"coordinates":[16.606087,40.668652],"type":"Point"}
}