{
  "type": "Feature",
  "properties": {
    "addr:full":"Via Maruti 24 26012 Castelleone Castelleone Cremona 26012",
    "addr:housenumber":"24",
    "addr:postcode":"26012;26012",
    "addr:street":"Via Maruti",
    "iso:country":"IT",
    "sg:address":"Via Maruti 24 26012 Castelleone",
    "sg:city":"Castelleone",
    "sg:classifiers":[
        {
            "category":"Manufacturing",
            "subcategory":"Rubber & Plastics",
            "type":"Manufacturing & Wholesale Goods"
        }
    ],
    "sg:phone":"+39 0374 58479",
    "sg:postcode":"26012",
    "sg:province":"Cremona",
    "sg:tags":[
        "technical",
        "item",
        "us"
    ],
    "wof:name":"Leongomma Snc",
    "wof:placetype":"venue"
},
  "geometry": {"coordinates":[9.76495,45.30331],"type":"Point"}
}