{
  "type": "Feature",
  "properties": {
    "addr:full":"Via Bari 14 73010 Surbo Surbo Lecce 73010",
    "addr:housenumber":"14",
    "addr:postcode":"73010;73010",
    "addr:street":"Via Bari",
    "iso:country":"IT",
    "sg:address":"Via Bari 14 73010 Surbo",
    "sg:city":"Surbo",
    "sg:classifiers":[
        {
            "category":"Health Services",
            "subcategory":"Medical Lab",
            "type":"Services"
        }
    ],
    "sg:phone":"+39 0832 365556",
    "sg:postcode":"73010",
    "sg:province":"Lecce",
    "sg:tags":[
        "article",
        "disposable"
    ],
    "wof:name":"Euro.me.d. Societa' Cooperativa A.r.l.",
    "wof:placetype":"venue"
},
  "geometry": {"coordinates":[18.147476,40.388596],"type":"Point"}
}