{
  "type": "Feature",
  "properties": {
    "iso:country":"IT",
    "sg:address":"00141 Roma",
    "sg:city":"Roma",
    "sg:orig_category":"Agricoltura, Orticoltura E Floricoltura",
    "sg:phone":"+39 06 818 9711",
    "sg:postcode":"00141",
    "sg:province":"Roma",
    "wof:name":"Mariotti Paolo",
    "wof:placetype":"venue"
},
  "geometry": {"coordinates":[12.471405,41.816082],"type":"Point"}
}