{
  "type": "Feature",
  "properties": {
    "iso:country":"IT",
    "sg:address":"98121 Messina",
    "sg:city":"Messina",
    "sg:orig_category":"Servizi E Lavori Per Agricoltura E Zootecnia. Consulenze Tecniche, Amministrative E Perizie",
    "sg:phone":"+39 090 41085",
    "sg:postcode":"98121",
    "sg:province":"Messina",
    "wof:name":"Associazione Professionale 'emmeti'",
    "wof:placetype":"venue"
},
  "geometry": {"coordinates":[15.55689,38.201038],"type":"Point"}
}