{
  "type": "Feature",
  "properties": {
    "iso:country":"IT",
    "sg:address":"63033 Centobuchi",
    "sg:city":"Centobuchi",
    "sg:orig_category":"Abbigliamento Esterno, Maglierie E Pelliccerie. Calzature, Pelletterie E Pelli",
    "sg:phone":"+39 0735 701817",
    "sg:postcode":"63033",
    "sg:province":"Ascoli Piceno",
    "wof:name":"C.c.c.p. Di Cameli D. & Paoloni G. & C. S.r.l.",
    "wof:placetype":"venue"
},
  "geometry": {"coordinates":[13.588907,43.125168],"type":"Point"}
}