{
  "type": "Feature",
  "properties": {
    "iso:country":"IT",
    "sg:address":"00011 Bagni Di Tivoli",
    "sg:city":"Tivoli",
    "sg:orig_category":"Prodotti E Manufatti In Materie Plastiche",
    "sg:phone":"+39 0774 353372",
    "sg:postcode":"00011",
    "sg:province":"Roma",
    "wof:name":"Compagnia Industrie E Servizi Srl",
    "wof:placetype":"venue"
},
  "geometry": {"coordinates":[12.7315263748,41.9493484497],"type":"Point"}
}