{
  "type": "Feature",
  "properties": {
    "iso:country":"IT",
    "sg:address":"Via San Pio Decimo; Porto Di Legnago; 37045",
    "sg:city":"Legnago",
    "sg:classifiers":[
        {
            "category":"Banks & Credit Unions",
            "subcategory":"Bank",
            "type":"Services"
        }
    ],
    "sg:phone":"+39 0442 25500",
    "sg:postcode":"37045",
    "sg:province":"Verona",
    "wof:name":"Cariverona Banca Spa",
    "wof:placetype":"venue"
},
  "geometry": {"coordinates":[11.312437,45.161705],"type":"Point"}
}