{
  "type": "Feature",
  "properties": {
    "addr:full":"20025 Legnano Legnano Milano 20025",
    "addr:postcode":"20025;20025",
    "iso:country":"IT",
    "sg:address":"20025 Legnano",
    "sg:city":"Legnano",
    "sg:orig_category":"Motori Ed Organi Di Trasmissione. Ricambi E Componenti Dei Mezzi Di Trasporto",
    "sg:phone":"+39 0331 469999",
    "sg:postcode":"20025",
    "sg:province":"Milano",
    "wof:name":"Rosa Sistemi S.p.a.",
    "wof:placetype":"venue"
},
  "geometry": {"coordinates":[9.262512207,45.402015686],"type":"Point"}
}