{
  "type": "Feature",
  "properties": {
    "iso:country":"IT",
    "sg:address":"Via Regione Siciliana 27 96016 Lentini",
    "sg:city":"Lentini",
    "sg:classifiers":[
        {
            "category":"Food & Beverages",
            "subcategory":"Fruits & Vegetables",
            "type":"Retail Goods"
        }
    ],
    "sg:phone":"+39 095 901324",
    "sg:postcode":"96016",
    "sg:province":"Siracusa",
    "wof:name":"Ragazzi Coop. Agricola A.r.l.",
    "wof:placetype":"venue"
},
  "geometry": {"coordinates":[14.9936828613,37.2974205017],"type":"Point"}
}