{
  "type": "Feature",
  "properties": {
    "iso:country":"IT",
    "sg:address":"20121 Milano",
    "sg:city":"Milano",
    "sg:orig_category":"Arredamenti E Mobili Professionali. Complementi Di Arredamento",
    "sg:phone":"+39 02 804361",
    "sg:postcode":"20121",
    "sg:province":"Milano",
    "wof:name":"Creperio Pino",
    "wof:placetype":"venue"
},
  "geometry": {"coordinates":[9.186647,45.470371],"type":"Point"}
}