{
  "type": "Feature",
  "properties": {
    "addr:full":"86, Frazione Cares 38071 Bleggio Inferiore Bleggio Inferiore Trento 38071",
    "addr:postcode":"38071;38071",
    "addr:street":"Frazione Cares",
    "iso:country":"IT",
    "sg:address":"86, Frazione Cares 38071 Bleggio Inferiore",
    "sg:city":"Bleggio Inferiore",
    "sg:classifiers":[
        {
            "category":"Shopping",
            "subcategory":"Crafts & Fabrics",
            "type":"Retail Goods"
        }
    ],
    "sg:phone":"+39 0465 709011",
    "sg:postcode":"38071",
    "sg:province":"Trento",
    "wof:name":"Tessilquattro Spa",
    "wof:placetype":"venue"
},
  "geometry": {"coordinates":[10.8621101379,46.0327377319],"type":"Point"}
}