{
  "type": "Feature",
  "properties": {
    "iso:country":"IT",
    "sg:address":"13, Via Correnti Cesare 20123 Milano",
    "sg:city":"Milano",
    "sg:classifiers":[
        {
            "category":"Travel",
            "subcategory":"Travel Agent",
            "type":"Entertainment"
        }
    ],
    "sg:phone":"+39 02 5810 6913",
    "sg:postcode":"20123",
    "sg:province":"Milano",
    "sg:tags":[
        "business"
    ],
    "wof:name":"Hotel Regina",
    "wof:placetype":"venue"
},
  "geometry": {"coordinates":[9.179479,45.459541],"type":"Point"}
}