{
  "type": "Feature",
  "properties": {
    "iso:country":"IT",
    "sg:address":"00197 Roma",
    "sg:city":"Roma",
    "sg:classifiers":[
        {
            "category":"Health Services",
            "subcategory":"Health Practitioner",
            "type":"Services"
        }
    ],
    "sg:phone":"+39 06 808 2264",
    "sg:postcode":"00197",
    "sg:province":"Roma",
    "sg:tags":[
        "medici"
    ],
    "wof:name":"Marcellini Hercolani Gaddi Prof. Gianfranco",
    "wof:placetype":"venue"
},
  "geometry": {"coordinates":[12.486789,41.924664],"type":"Point"}
}