{
  "type": "Feature",
  "properties": {
    "addr:full":"10043 Orbassano Orbassano Torino 10043",
    "addr:postcode":"10043;10043",
    "iso:country":"IT",
    "sg:address":"10043 Orbassano",
    "sg:city":"Orbassano",
    "sg:orig_category":"Utensili Meccanici E Materiali",
    "sg:phone":"+39 011 904 0943",
    "sg:postcode":"10043",
    "sg:province":"Torino",
    "wof:name":"Neotech Di Laura Sennarica & C. Snc",
    "wof:placetype":"venue"
},
  "geometry": {"coordinates":[7.547873,45.008419],"type":"Point"}
}