{
  "type": "Feature",
  "properties": {
    "addr:full":"00175 Roma Roma Roma 00175",
    "addr:postcode":"00175;00175",
    "iso:country":"IT",
    "sg:address":"00175 Roma",
    "sg:city":"Roma",
    "sg:orig_category":"Casellari E Cassette Postali, Bacheche",
    "sg:phone":"+39 06 761 0751",
    "sg:postcode":"00175",
    "sg:province":"Roma",
    "wof:name":"Leggi Armando",
    "wof:placetype":"venue"
},
  "geometry": {"coordinates":[12.546618,41.866718],"type":"Point"}
}