{
  "type": "Feature",
  "properties": {
    "iso:country":"IT",
    "sg:address":"272, Via Pesciatina 55012 Capannori",
    "sg:city":"Capannori",
    "sg:classifiers":[
        {
            "category":"Shopping",
            "subcategory":"Computers & Home Electronics",
            "type":"Retail Goods"
        }
    ],
    "sg:phone":"+39 0583 429430",
    "sg:postcode":"55012",
    "sg:province":"Lucca",
    "sg:tags":[
        "electronic",
        "electrical",
        "equipment"
    ],
    "wof:name":"Cacini & C. (s.p.a.)",
    "wof:placetype":"venue"
},
  "geometry": {"coordinates":[10.588737,43.858521],"type":"Point"}
}