{
  "type": "Feature",
  "properties": {
    "iso:country":"IT",
    "sg:address":"Via Perrone 4 10023 Chieri",
    "sg:city":"Chieri",
    "sg:classifiers":[
        {
            "category":"Banks & Credit Unions",
            "subcategory":"Financial Services",
            "type":"Services"
        }
    ],
    "sg:phone":"+39 011 947 2656",
    "sg:postcode":"10023",
    "sg:province":"Torino",
    "sg:tags":[
        "decorative",
        "trim"
    ],
    "sg:website":"www.passamaneriapersico.com",
    "wof:name":"Persico Alessandro & C. Snc",
    "wof:placetype":"venue"
},
  "geometry": {"coordinates":[7.817961,45.0056],"type":"Point"}
}