{
  "type": "Feature",
  "properties": {
    "addr:full":"Via Pesciatina 445 55010 Camigliano Santa Gemma Camigliano Santa gemma Lucca 55010",
    "addr:housenumber":"445",
    "addr:postcode":"55010;55010",
    "addr:street":"Via Pesciatina;Santa",
    "iso:country":"IT",
    "sg:address":"Via Pesciatina 445 55010 Camigliano Santa Gemma",
    "sg:city":"Camigliano Santa gemma",
    "sg:orig_category":"Ladies' Shoes",
    "sg:phone":"+39 0583 920380",
    "sg:postcode":"55010",
    "sg:province":"Lucca",
    "sg:website":"www.monicashoes.com",
    "wof:name":"Monica Shoes S.r.l.",
    "wof:placetype":"venue"
},
  "geometry": {"coordinates":[10.507994,43.843014],"type":"Point"}
}