{
  "type": "Feature",
  "properties": {
    "iso:country":"IT",
    "sg:address":"Via S. Paternostro 88900 Crotone",
    "sg:city":"Crotone",
    "sg:classifiers":[
        {
            "category":"Shopping",
            "subcategory":"Jewelry",
            "type":"Retail Goods"
        }
    ],
    "sg:phone":"+39 0962 20661",
    "sg:postcode":"88900",
    "sg:province":"Crotone",
    "sg:tags":[
        "gemstone",
        "jewellery"
    ],
    "sg:website":"www.gerardosacco.com",
    "wof:name":"Gerardo Sacco Srl",
    "wof:placetype":"venue"
},
  "geometry": {"coordinates":[17.126921,39.079685],"type":"Point"}
}