{
  "type": "Feature",
  "properties": {
    "addr:full":"36065 Mussolente Casoni Vicenza 36065",
    "addr:postcode":"36065;36065",
    "iso:country":"IT",
    "sg:address":"36065 Mussolente",
    "sg:city":"Casoni",
    "sg:classifiers":[
        {
            "category":"Manufacturing",
            "subcategory":"Wood Products",
            "type":"Manufacturing & Wholesale Goods"
        }
    ],
    "sg:phone":"+39 0424 574054",
    "sg:postcode":"36065",
    "sg:province":"Vicenza",
    "sg:tags":[
        "decorative",
        "building",
        "furnishings",
        "semi-finished",
        "industry",
        "objects",
        "article"
    ],
    "sg:website":"http://www.stradiotto.it",
    "wof:name":"Stradiotto Di Zonta Carla",
    "wof:placetype":"venue"
},
  "geometry": {"coordinates":[11.7885494232,45.7392654419],"type":"Point"}
}