{
  "type": "Feature",
  "properties": {
    "iso:country":"IT",
    "sg:address":"20052 Monza",
    "sg:city":"Monza",
    "sg:orig_category":"Macchine Utensili E Impianti. Utensili Meccanici E Materiali",
    "sg:phone":"+39 039 230 1343",
    "sg:postcode":"20052",
    "sg:province":"Milano",
    "sg:website":"http://www.utenmec.it",
    "wof:name":"Uten Mec Srl",
    "wof:placetype":"venue"
},
  "geometry": {"coordinates":[9.204403,45.47707],"type":"Point"}
}