{
  "type": "Feature",
  "properties": {
    "addr:full":"Via Delle Monachelle 66 00040 Pomezia Pomezia Roma 00040",
    "addr:housenumber":"66",
    "addr:postcode":"00040;roma 00040",
    "addr:street":"Via Delle Monachelle",
    "iso:country":"IT",
    "sg:address":"Via Delle Monachelle 66 00040 Pomezia",
    "sg:city":"Pomezia",
    "sg:classifiers":[
        {
            "category":"Utilities",
            "subcategory":"Mobile Phone",
            "type":"Services"
        }
    ],
    "sg:phone":"+39 06 910 5755",
    "sg:postcode":"00040",
    "sg:province":"Roma",
    "sg:tags":[
        "battery",
        "charger"
    ],
    "sg:website":"www.med-el.com",
    "wof:name":"Medel Srl",
    "wof:placetype":"venue"
},
  "geometry": {"coordinates":[12.543641,41.686451],"type":"Point"}
}