{
  "type": "Feature",
  "properties": {
    "iso:country":"IT",
    "sg:address":"70022 Altamura",
    "sg:city":"Altamura",
    "sg:orig_category":"Alberghi E Strutture Extra Alberghiere. Servizi Per Aziende, Manifestazioni E Supporto Agli Scambi Commerciali",
    "sg:phone":"+39 080 314 7407",
    "sg:postcode":"70022",
    "sg:province":"Bari",
    "wof:name":"Villa Belvedere",
    "wof:placetype":"venue"
},
  "geometry": {"coordinates":[16.410748,41.153122],"type":"Point"}
}