{
  "type": "Feature",
  "properties": {
    "iso:country":"IT",
    "sg:address":"67, Via Di Vittorio Giuseppe 43044 Collecchio",
    "sg:city":"Collecchio",
    "sg:classifiers":[
        {
            "category":"Manufacturing",
            "subcategory":"Food",
            "type":"Manufacturing & Wholesale Goods"
        }
    ],
    "sg:phone":"+39 0521 304358",
    "sg:postcode":"43044",
    "sg:province":"Parma",
    "sg:tags":[
        "equipment",
        "processing",
        "-",
        "machinery"
    ],
    "wof:name":"Prima S.r.l.",
    "wof:placetype":"venue"
},
  "geometry": {"coordinates":[10.2627687454,44.7716255188],"type":"Point"}
}