{
  "type": "Feature",
  "properties": {
    "iso:country":"IT",
    "sg:address":"14, Via Xxv Luglio 82100 Benevento",
    "sg:city":"Benevento",
    "sg:classifiers":[
        {
            "category":"Shopping",
            "subcategory":"Gifts & Souvenirs",
            "type":"Retail Goods"
        }
    ],
    "sg:phone":"+39 39082421133",
    "sg:postcode":"82100",
    "sg:province":"Benevento",
    "wof:name":"Consorzio Agrario Provinciale",
    "wof:placetype":"venue"
},
  "geometry": {"coordinates":[14.781174,41.130447],"type":"Point"}
}