{
  "type": "Feature",
  "properties": {
    "addr:full":"22100 Como Como Como 22100",
    "addr:postcode":"22100;22100",
    "iso:country":"IT",
    "sg:address":"22100 Como",
    "sg:city":"Como",
    "sg:orig_category":"Accessori Moda D'abbigliamento",
    "sg:phone":"+39 031 505147",
    "sg:postcode":"22100",
    "sg:province":"Como",
    "wof:name":"Euroseta Srl",
    "wof:placetype":"venue"
},
  "geometry": {"coordinates":[9.081401,45.789112],"type":"Point"}
}