{
  "type": "Feature",
  "properties": {
    "iso:country":"IT",
    "sg:address":"Via Camaldoli 32 20138 Milano",
    "sg:city":"Milano",
    "sg:classifiers":[
        {
            "category":"Professional",
            "subcategory":"Printing & Photocopies",
            "type":"Services"
        }
    ],
    "sg:phone":"+39 02 5518 1022",
    "sg:postcode":"20138",
    "sg:province":"Milano",
    "sg:tags":[
        "paper"
    ],
    "sg:website":"www.kores.it",
    "wof:name":"Kores Spa",
    "wof:placetype":"venue"
},
  "geometry": {"coordinates":[9.2660837173,45.439655304],"type":"Point"}
}