{
  "type": "Feature",
  "properties": {
    "iso:country":"IT",
    "sg:address":"20123 Milano",
    "sg:city":"Milano",
    "sg:orig_category":"Non-classified Establishments",
    "sg:phone":"+39 02 8646 1409",
    "sg:postcode":"20123",
    "sg:province":"Milano",
    "wof:name":"Kikky Alliney Srl",
    "wof:placetype":"venue"
},
  "geometry": {"coordinates":[9.176371,45.460648],"type":"Point"}
}