{
  "type": "Feature",
  "properties": {
    "addr:full":"Via Galimberti 3 10032 Brandizzo Brandizzo Torino 10032",
    "addr:housenumber":"3",
    "addr:postcode":"10032;10032",
    "addr:street":"Via Galimberti",
    "iso:country":"IT",
    "sg:address":"Via Galimberti 3 10032 Brandizzo",
    "sg:city":"Brandizzo",
    "sg:classifiers":[
        {
            "category":"Community Center",
            "subcategory":"Senior",
            "type":"Public Place"
        }
    ],
    "sg:phone":"+39 011 913 9964",
    "sg:postcode":"10032",
    "sg:province":"Torino",
    "sg:tags":[
        "pen",
        "ball",
        "point"
    ],
    "sg:website":"www.demapen.it",
    "wof:name":"Dema Di Donetti Dontin Mariangela & C",
    "wof:placetype":"venue"
},
  "geometry": {"coordinates":[7.827321,45.170418],"type":"Point"}
}