{
  "type": "Feature",
  "properties": {
    "iso:country":"IT",
    "sg:address":"20099 Sesto San Giovanni",
    "sg:city":"Sesto San Giovanni",
    "sg:orig_category":"Professionisti - Studi E Servizi Ed Associazioni Di Interesse Aziendale. Associazioni Ed Organismi Di Interesse Pubblico",
    "sg:phone":"+39 02 240 6886",
    "sg:postcode":"20099",
    "sg:province":"Milano",
    "wof:name":"Associazione Sconfinando",
    "wof:placetype":"venue"
},
  "geometry": {"coordinates":[9.2404880524,45.5349082947],"type":"Point"}
}