{
  "type": "Feature",
  "properties": {
    "iso:country":"IT",
    "sg:address":"Via Cutolo 80039 Saviano",
    "sg:city":"Saviano",
    "sg:classifiers":[
        {
            "category":"Parking",
            "subcategory":"Lot",
            "type":"Transportation"
        }
    ],
    "sg:phone":"+39 081 511 5682",
    "sg:postcode":"80039",
    "sg:province":"Napoli",
    "sg:tags":[
        "transport",
        "road"
    ],
    "wof:name":"Dello Iacono Trasporti S.r.l.",
    "wof:placetype":"venue"
},
  "geometry": {"coordinates":[14.505716,40.885647],"type":"Point"}
}