{
  "type": "Feature",
  "properties": {
    "iso:country":"IT",
    "sg:address":"Piazza Dei Martiri, 29; Belluno; 32100",
    "sg:city":"Belluno",
    "sg:classifiers":[
        {
            "category":"Banks & Credit Unions",
            "subcategory":"Bank",
            "type":"Services"
        }
    ],
    "sg:phone":"+39 0437 28347",
    "sg:postcode":"32100",
    "sg:province":"Belluno",
    "wof:name":"Banca D'italia",
    "wof:placetype":"venue"
},
  "geometry": {"coordinates":[12.215184,46.139454],"type":"Point"}
}