{
  "type": "Feature",
  "properties": {
    "iso:country":"IT",
    "sg:address":"31030 Paese",
    "sg:orig_category":"Elettrotecnica Industriale, Prodotti E Apparecchiature",
    "sg:phone":"+39 0422 4575",
    "sg:postcode":"31030",
    "sg:province":"Treviso",
    "sg:website":"http://www.lagunalight.com",
    "wof:name":"Laguna Light Srl",
    "wof:placetype":"venue"
},
  "geometry": {"coordinates":[12.132405,45.674927],"type":"Point"}
}