{
  "type": "Feature",
  "properties": {
    "addr:full":"26100 Cremona Cremona Cremona 26100",
    "addr:postcode":"26100;26100",
    "iso:country":"IT",
    "sg:address":"26100 Cremona",
    "sg:city":"Cremona",
    "sg:orig_category":"Forniture Per Edilizia E Lavori Pubblici. Forniture Per Attivita' Industriali",
    "sg:phone":"+39 0372 25254",
    "sg:postcode":"26100",
    "sg:province":"Cremona",
    "wof:name":"Studio Storti",
    "wof:placetype":"venue"
},
  "geometry": {"coordinates":[10.0325498581,45.1404190063],"type":"Point"}
}