{
  "type": "Feature",
  "properties": {
    "addr:full":"Via Milano 3 25034 Orzinuovi Orzinuovi Brescia 25034",
    "addr:housenumber":"3",
    "addr:postcode":"25034;25034",
    "addr:street":"Via Milano",
    "iso:country":"IT",
    "sg:address":"Via Milano 3 25034 Orzinuovi",
    "sg:city":"Orzinuovi",
    "sg:classifiers":[
        {
            "category":"Home & Garden",
            "subcategory":"Kitchen Supply",
            "type":"Retail Goods"
        }
    ],
    "sg:phone":"+39 030 941761",
    "sg:postcode":"25034",
    "sg:province":"Brescia",
    "sg:tags":[
        "margarine"
    ],
    "wof:name":"I.g.o.r. Industria Grassi Olii Raffinati Spa",
    "wof:placetype":"venue"
},
  "geometry": {"coordinates":[9.903624,45.400555],"type":"Point"}
}