{
  "type": "Feature",
  "properties": {
    "addr:full":"42010 Rio Saliceto Reggio Nell'Emilia 42010",
    "addr:housenumber":"42010",
    "addr:postcode":"42010",
    "iso:country":"IT",
    "sg:address":"42010 Rio Saliceto",
    "sg:orig_category":"Macchine, Impianti Ed Attrezzature Industria Delle Materie Plastiche E Gomma",
    "sg:phone":"+39 0522 699187",
    "sg:postcode":"42010",
    "sg:province":"Reggio Nell'Emilia",
    "wof:name":"Meca",
    "wof:placetype":"venue"
},
  "geometry": {"coordinates":[10.651519,44.919292],"type":"Point"}
}