{
  "type": "Feature",
  "properties": {
    "iso:country":"IT",
    "sg:address":"48024 Massa Lombarda",
    "sg:city":"Massa Lombarda",
    "sg:orig_category":"Informatica - Consulenza E Servizi. Servizi Ausiliari Di Analisi, Controllo E Ricerca. Servizi Per Aziende, Manifestazioni E Supporto Agli Scambi Commerciali",
    "sg:phone":"+39 0545 971288",
    "sg:postcode":"48024",
    "sg:province":"Ravenna",
    "wof:name":"Toner Image Snc Di Natale Marincolo & C.",
    "wof:placetype":"venue"
},
  "geometry": {"coordinates":[11.809352,44.453411],"type":"Point"}
}