{
  "type": "Feature",
  "properties": {
    "addr:full":"24012 Brembilla Brembilla Bergamo 24012",
    "addr:postcode":"24012;24012",
    "iso:country":"IT",
    "sg:address":"24012 Brembilla",
    "sg:city":"Brembilla",
    "sg:classifiers":[
        {
            "category":"Home & Garden",
            "subcategory":"Garden Supply",
            "type":"Retail Goods"
        }
    ],
    "sg:phone":"+39 0345 98146",
    "sg:postcode":"24012",
    "sg:province":"Bergamo",
    "sg:tags":[
        "article",
        "leisure",
        "gift",
        "business",
        "supplies"
    ],
    "wof:name":"Scaglia Ettore & C. Sas",
    "wof:placetype":"venue"
},
  "geometry": {"coordinates":[9.597236,45.815731],"type":"Point"}
}