{
  "type": "Feature",
  "properties": {
    "iso:country":"IT",
    "sg:address":"98050 Terme Vigliatore",
    "sg:city":"Terme Vigliatore",
    "sg:orig_category":"Ospedali E Servizi Sanitari",
    "sg:phone":"+39 090 974 0071",
    "sg:postcode":"98050",
    "sg:province":"Messina",
    "wof:name":"Triolo Rosaria",
    "wof:placetype":"venue"
},
  "geometry": {"coordinates":[15.130237,38.122227],"type":"Point"}
}