{
  "type": "Feature",
  "properties": {
    "addr:full":"25012 Brescia Brescia 25012",
    "addr:postcode":"25012;25012",
    "iso:country":"IT",
    "sg:address":"25012 Brescia",
    "sg:orig_category":"Macchine Utensili E Impianti",
    "sg:phone":"+39 030 358 2063",
    "sg:postcode":"25012",
    "sg:province":"Brescia",
    "wof:name":"Airgas Srl",
    "wof:placetype":"venue"
},
  "geometry": {"coordinates":[10.222958,45.539829],"type":"Point"}
}