{
  "type": "Feature",
  "properties": {
    "iso:country":"IT",
    "sg:address":"40017 San Giovanni In Persiceto",
    "sg:city":"San Giovanni in Persiceto",
    "sg:orig_category":"Fotocomposizione",
    "sg:phone":"+39 051 823011",
    "sg:postcode":"40017",
    "sg:province":"Bologna",
    "wof:name":"Tipolitografia Il Torchio",
    "wof:placetype":"venue"
},
  "geometry": {"coordinates":[11.1735429764,44.6317138672],"type":"Point"}
}