{
  "type": "Feature",
  "properties": {
    "iso:country":"IT",
    "sg:address":"65015 Montesilvano",
    "sg:city":"Montesilvano",
    "sg:orig_category":"Legno E Semilavorati",
    "sg:phone":"+39 085 835661",
    "sg:postcode":"65015",
    "sg:province":"Pescara",
    "wof:name":"Mantiniarreda",
    "wof:placetype":"venue"
},
  "geometry": {"coordinates":[14.149879,42.516544],"type":"Point"}
}