{
  "type": "Feature",
  "properties": {
    "iso:country":"IT",
    "sg:address":"20146 Milano",
    "sg:city":"Milano",
    "sg:orig_category":"Servizi Editoriali",
    "sg:phone":"+39 02 410187",
    "sg:postcode":"20146",
    "sg:province":"Milano",
    "wof:name":"Fornara Luigi Marcello",
    "wof:placetype":"venue"
},
  "geometry": {"coordinates":[9.142772,45.454659],"type":"Point"}
}