{
  "type": "Feature",
  "properties": {
    "iso:country":"IT",
    "sg:address":"20020 Arese",
    "sg:city":"Arese",
    "sg:classifiers":[
        {
            "category":"Government",
            "subcategory":"Office",
            "type":"Public Place"
        }
    ],
    "sg:phone":"+39 02 938 3299",
    "sg:postcode":"20020",
    "sg:province":"Milano",
    "sg:tags":[
        "e",
        "lo",
        "tempo",
        "libero",
        "per",
        "spettacolo",
        "servizi",
        "culturali",
        "sport",
        "il"
    ],
    "wof:name":"Ass.orchestra Lirico Sinfonica Carlo Coccia",
    "wof:placetype":"venue"
},
  "geometry": {"coordinates":[9.078259,45.544106],"type":"Point"}
}