{
  "type": "Feature",
  "properties": {
    "iso:country":"IT",
    "sg:address":"20154 Milano",
    "sg:city":"Milano",
    "sg:orig_category":"Cinematografia E Radiotelevisione",
    "sg:phone":"+39 02 3360 8633",
    "sg:postcode":"20154",
    "sg:province":"Milano",
    "wof:name":"Pro.post.a",
    "wof:placetype":"venue"
},
  "geometry": {"coordinates":[9.173891,45.482258],"type":"Point"}
}