{
  "type": "Feature",
  "properties": {
    "addr:full":"90135 Palermo Palermo Palermo 90135",
    "addr:postcode":"90135;90135",
    "iso:country":"IT",
    "sg:address":"90135 Palermo",
    "sg:city":"Palermo",
    "sg:orig_category":"Informatica - Consulenza E Software",
    "sg:phone":"+39 091 676 5629",
    "sg:postcode":"90135",
    "sg:province":"Palermo",
    "wof:name":"Nab Sas Di Giancarlo Di Vita",
    "wof:placetype":"venue"
},
  "geometry": {"coordinates":[13.331511,38.118137],"type":"Point"}
}