{
  "type": "Feature",
  "properties": {
    "iso:country":"IT",
    "sg:address":"09010 Pula",
    "sg:city":"Pula",
    "sg:orig_category":"Arredamenti - Materiali",
    "sg:phone":"+39 070 920 9432",
    "sg:postcode":"09010",
    "sg:province":"Cagliari",
    "wof:name":"Tappezzeria La Veneta Di Merlin Renza",
    "wof:placetype":"venue"
},
  "geometry": {"coordinates":[9.002666,39.00861],"type":"Point"}
}