{
  "type": "Feature",
  "properties": {
    "iso:country":"IT",
    "sg:address":"3, Via Del Ponte 53037 San Gimignano",
    "sg:city":"San Gimignano",
    "sg:classifiers":[
        {
            "category":"Professional",
            "subcategory":"Engineering",
            "type":"Services"
        }
    ],
    "sg:phone":"+39 0577 944788",
    "sg:postcode":"53037",
    "sg:province":"Siena",
    "sg:tags":[
        "machine",
        "-",
        "mechanical"
    ],
    "wof:name":"Desipak Service Srl",
    "wof:placetype":"venue"
},
  "geometry": {"coordinates":[11.034896,43.535568],"type":"Point"}
}