{
  "type": "Feature",
  "properties": {
    "iso:country":"IT",
    "sg:address":"50, Via Simioli E. 10098 Rivoli",
    "sg:city":"Rivoli",
    "sg:classifiers":[
        {
            "category":"Professional",
            "subcategory":"Engineering",
            "type":"Services"
        }
    ],
    "sg:phone":"+39 011 959 5076",
    "sg:postcode":"10098",
    "sg:province":"Torino",
    "sg:tags":[
        "machine",
        "-",
        "mechanical"
    ],
    "wof:name":"Sossella Joint System S.a.s.",
    "wof:placetype":"venue"
},
  "geometry": {"coordinates":[7.537329,45.064373],"type":"Point"}
}