{
  "type": "Feature",
  "properties": {
    "iso:country":"IT",
    "sg:address":"Viale Aldo Moro 18, 40127 Bologna, Bo",
    "sg:city":"Bologna",
    "sg:classifiers":[
        {
            "category":"Banks & Credit Unions",
            "subcategory":"Bank",
            "type":"Services"
        }
    ],
    "sg:postcode":"40127",
    "sg:province":"Bologna",
    "wof:name":"Carimonte Banca Spa",
    "wof:placetype":"venue"
},
  "geometry": {"coordinates":[11.362365,44.509109],"type":"Point"}
}