{
  "type": "Feature",
  "properties": {
    "addr:full":"16, Via Trieste 22063 Cantu' Como 22063",
    "addr:postcode":"22063;22063",
    "addr:street":"Via Trieste;Cantu ' Como",
    "iso:country":"IT",
    "sg:address":"16, Via Trieste 22063 Cantu'",
    "sg:classifiers":[
        {
            "category":"Professional",
            "subcategory":"Printing & Photocopies",
            "type":"Services"
        }
    ],
    "sg:phone":"+39 39031712723",
    "sg:postcode":"22063",
    "sg:province":"Como",
    "wof:name":"Scalzini Cliche' (s.n.c.)",
    "wof:placetype":"venue"
},
  "geometry": {"coordinates":[9.1336269379,45.7438201904],"type":"Point"}
}