{
  "type": "Feature",
  "properties": {
    "addr:full":"28, Via Stazione 39010 Gargazzone Gargazzone Bolzano/Bozen 39010",
    "addr:postcode":"39010;39010",
    "addr:street":"Via Stazione",
    "iso:country":"IT",
    "sg:address":"28, Via Stazione 39010 Gargazzone",
    "sg:city":"Gargazzone",
    "sg:classifiers":[
        {
            "category":"Building & Trades",
            "subcategory":"Construction",
            "type":"Services"
        }
    ],
    "sg:phone":"+39 0473 291060",
    "sg:postcode":"39010",
    "sg:province":"Bolzano/Bozen",
    "sg:tags":[
        "work",
        "public"
    ],
    "wof:name":"Stebo Ambiente (s.r.l.)",
    "wof:placetype":"venue"
},
  "geometry": {"coordinates":[11.201276,46.580704],"type":"Point"}
}