{
  "type": "Feature",
  "properties": {
    "addr:full":"14018 Villafranca D'asti Asti 14018",
    "addr:postcode":"14018;14018",
    "iso:country":"IT",
    "sg:address":"14018 Villafranca D'asti",
    "sg:orig_category":"Pneumatici - Produzione E Ricostruzione",
    "sg:phone":"+39 0141 943508",
    "sg:postcode":"14018",
    "sg:province":"Asti",
    "wof:name":"Tosgomma",
    "wof:placetype":"venue"
},
  "geometry": {"coordinates":[8.0328330994,44.9129829407],"type":"Point"}
}