{
  "type": "Feature",
  "properties": {
    "addr:full":"80041 Boscoreale Boscoreale Napoli 80041",
    "addr:postcode":"80041;80041",
    "iso:country":"IT",
    "sg:address":"80041 Boscoreale",
    "sg:city":"Boscoreale",
    "sg:orig_category":"Utensili Meccanici E Materiali. Forniture Per Attivita' Industriali",
    "sg:phone":"+39 081 862 6704",
    "sg:postcode":"80041",
    "sg:province":"Napoli",
    "wof:name":"V.t.l. Di Vitulano Luigi",
    "wof:placetype":"venue"
},
  "geometry": {"coordinates":[14.470974,40.77116],"type":"Point"}
}