{
  "type": "Feature",
  "properties": {
    "addr:full":"35030 Vo Padova 35030",
    "addr:postcode":"35030;35030",
    "iso:country":"IT",
    "sg:address":"35030 Vo",
    "sg:orig_category":"Scultori D'arte - Studi",
    "sg:phone":"+39 049 994 0260",
    "sg:postcode":"35030",
    "sg:province":"Padova",
    "wof:name":"Longhin Roberto",
    "wof:placetype":"venue"
},
  "geometry": {"coordinates":[11.6425,45.329224],"type":"Point"}
}