{
  "type": "Feature",
  "properties": {
    "addr:full":"45014 Porto Viro Porto Viro Rovigo 45014",
    "addr:housenumber":"45014",
    "addr:postcode":"45014",
    "addr:street":"Viro",
    "iso:country":"IT",
    "sg:address":"45014 Porto Viro",
    "sg:city":"Porto Viro",
    "sg:orig_category":"Dolciumi E Gelati. Condimenti, Spezie, Infusi E Caffe'",
    "sg:phone":"+39 0426 633720",
    "sg:postcode":"45014",
    "sg:province":"Rovigo",
    "wof:name":"Cerestar Spa",
    "wof:placetype":"venue"
},
  "geometry": {"coordinates":[12.242658,45.036316],"type":"Point"}
}