{
  "type": "Feature",
  "properties": {
    "iso:country":"IT",
    "sg:address":"386, Via Consolare Antica 98071 Capo D'orlando",
    "sg:classifiers":[
        {
            "category":"Farming",
            "subcategory":"Livestock Farm",
            "type":"Manufacturing & Wholesale Goods"
        }
    ],
    "sg:phone":"+39 0941 901400",
    "sg:postcode":"98071",
    "sg:province":"Messina",
    "sg:tags":[
        "agriculture"
    ],
    "wof:name":"Cooperativa Esportatori Produttori Agricoli",
    "wof:placetype":"venue"
},
  "geometry": {"coordinates":[14.741499,38.15406],"type":"Point"}
}