{
  "type": "Feature",
  "properties": {
    "iso:country":"IT",
    "sg:address":"23, Via Brughetti 20030 Bovisio Masciago",
    "sg:city":"Bovisio",
    "sg:classifiers":[
        {
            "category":"Home & Garden",
            "subcategory":"Home Furnishings",
            "type":"Retail Goods"
        }
    ],
    "sg:phone":"+39 036 259 3588",
    "sg:postcode":"20030",
    "sg:province":"Milano",
    "sg:tags":[
        "household"
    ],
    "wof:name":"Travagin",
    "wof:placetype":"venue"
},
  "geometry": {"coordinates":[9.161153,45.615917],"type":"Point"}
}