{
  "type": "Feature",
  "properties": {
    "iso:country":"IT",
    "sg:address":"Via Campolongo -loc Ferretelle 84025 Eboli",
    "sg:city":"Eboli",
    "sg:orig_category":"Fresh Vegetables, Lettuces, And Potatoes",
    "sg:phone":"+39 0828 691275",
    "sg:postcode":"84025",
    "sg:province":"Salerno",
    "wof:name":"Ortocampagna S.c.r.l.",
    "wof:placetype":"venue"
},
  "geometry": {"coordinates":[14.765912056,40.6779556274],"type":"Point"}
}