{
  "type": "Feature",
  "properties": {
    "addr:full":"Str. St. 275 73031 Alessano Alessano Lecce 73031",
    "addr:housenumber":"275",
    "addr:postcode":"73031;73031",
    "addr:street":"Str. St.",
    "iso:country":"IT",
    "sg:address":"Str. St. 275 73031 Alessano",
    "sg:city":"Alessano",
    "sg:classifiers":[
        {
            "category":"Shopping",
            "subcategory":"Crafts & Fabrics",
            "type":"Retail Goods"
        }
    ],
    "sg:phone":"+39 0833 522081",
    "sg:postcode":"73031",
    "sg:province":"Lecce",
    "sg:website":"http://www.paginegialle.it/marcop",
    "wof:name":"Mar.cop. Industrie",
    "wof:placetype":"venue"
},
  "geometry": {"coordinates":[18.1740150452,40.3532905579],"type":"Point"}
}