{
  "type": "Feature",
  "properties": {
    "iso:country":"IT",
    "sg:address":"18018 Taggia",
    "sg:city":"Taggia",
    "sg:orig_category":"Audiovisivi Apparecchi Ed Impianti - Produzione, Commercio E Noleggio",
    "sg:phone":"+39 0184 448651",
    "sg:postcode":"18018",
    "sg:province":"Imperia",
    "wof:name":"Elle V Elettronica P.s. Coop A R.l.",
    "wof:placetype":"venue"
},
  "geometry": {"coordinates":[7.853765,43.838234],"type":"Point"}
}