{
  "type": "Feature",
  "properties": {
    "iso:country":"IT",
    "sg:address":"00195 Roma",
    "sg:city":"Roma",
    "sg:orig_category":"Audiovisivi Filmati, Spot E Multimediali - Realizzazione E Duplicazione",
    "sg:phone":"+39 06 3750 0060",
    "sg:postcode":"00195",
    "sg:province":"Roma",
    "sg:website":"http://www.invideo.it",
    "wof:name":"Invideo Srl",
    "wof:placetype":"venue"
},
  "geometry": {"coordinates":[12.45448,41.912159],"type":"Point"}
}