{
  "type": "Feature",
  "properties": {
    "addr:full":"52044 Cortona Camucia Arezzo 52044",
    "addr:postcode":"52044;52044",
    "iso:country":"IT",
    "sg:address":"52044 Cortona",
    "sg:city":"Camucia",
    "sg:orig_category":"Elettrotecnica Industriale, Prodotti E Apparecchiature. Elettronica Industriale, Prodotti E Apparecchiature",
    "sg:phone":"+39 0575 604854",
    "sg:postcode":"52044",
    "sg:province":"Arezzo",
    "sg:website":"http://www.mbelettronica.com",
    "wof:name":"M.b. Elettronica Snc",
    "wof:placetype":"venue"
},
  "geometry": {"coordinates":[11.976574,43.260483],"type":"Point"}
}