{
  "type": "Feature",
  "properties": {
    "addr:full":"20127 Milano Milano Milano 20127",
    "addr:postcode":"20127;20127",
    "iso:country":"IT",
    "sg:address":"20127 Milano",
    "sg:city":"Milano",
    "sg:orig_category":"Macchine, Strumenti Ed Apparecchi Per Attivita' Industriali",
    "sg:phone":"+39 02 2630 6259",
    "sg:postcode":"20127",
    "sg:province":"Milano",
    "sg:website":"http://www.prelectronics.it",
    "wof:name":"Pr Electronics Italy Srl",
    "wof:placetype":"venue"
},
  "geometry": {"coordinates":[9.238941,45.505081],"type":"Point"}
}