{
  "type": "Feature",
  "properties": {
    "iso:country":"IT",
    "sg:address":"8, Via Pastore G. 60035 Jesi",
    "sg:city":"Jesi",
    "sg:classifiers":[
        {
            "category":"Parking",
            "subcategory":"Lot",
            "type":"Transportation"
        }
    ],
    "sg:phone":"+39 0731 605762",
    "sg:postcode":"60035",
    "sg:province":"Ancona",
    "sg:tags":[
        "transport",
        "road"
    ],
    "wof:name":"Consorzio Autotrasportatori Marchigiani",
    "wof:placetype":"venue"
},
  "geometry": {"coordinates":[13.518757,43.615856],"type":"Point"}
}