{
  "type": "Feature",
  "properties": {
    "iso:country":"IT",
    "sg:address":"9, Piazza Del Popolo 22100 Como",
    "sg:city":"Como",
    "sg:classifiers":[
        {
            "category":"Professional",
            "subcategory":"Business Services",
            "type":"Services"
        }
    ],
    "sg:phone":"+39 39031303535",
    "sg:postcode":"22100",
    "sg:province":"Como",
    "sg:tags":[
        "advice"
    ],
    "wof:name":"Green Design Srl",
    "wof:placetype":"venue"
},
  "geometry": {"coordinates":[9.086346,45.81147],"type":"Point"}
}