{
  "type": "Feature",
  "properties": {
    "iso:country":"IT",
    "sg:address":"20063 Cernusco Sul Naviglio",
    "sg:city":"Cernusco sul Naviglio",
    "sg:orig_category":"Macchine E Forniture Per Arredamento E Industria Del Legno. Forniture Per Edilizia E Lavori Pubblici",
    "sg:phone":"+39 02 923 5330",
    "sg:postcode":"20063",
    "sg:province":"Milano",
    "wof:name":"Smart Service Di Sergio Marongiu",
    "wof:placetype":"venue"
},
  "geometry": {"coordinates":[9.324418,45.579983],"type":"Point"}
}