{
  "type": "Feature",
  "properties": {
    "addr:full":"55012 Capannori Capannori Lucca 55012",
    "addr:postcode":"55012;55012",
    "iso:country":"IT",
    "sg:address":"55012 Capannori",
    "sg:city":"Capannori",
    "sg:orig_category":"Legno E Semilavorati. Apparecchiature E Sistemi Per Magazzinaggio E Movimentazione",
    "sg:phone":"+39 0583 979015",
    "sg:postcode":"55012",
    "sg:province":"Lucca",
    "sg:website":"http://www.etruriapancali.com",
    "wof:name":"Etruria Star",
    "wof:placetype":"venue"
},
  "geometry": {"coordinates":[10.6110610962,43.7647018433],"type":"Point"}
}