{
  "type": "Feature",
  "properties": {
    "iso:country":"IT",
    "sg:address":"Via Dante Alighieri 321; Lozzo Di Cadore; 32040",
    "sg:city":"Lozzo di Cadore",
    "sg:classifiers":[
        {
            "category":"Banks & Credit Unions",
            "subcategory":"Bank",
            "type":"Services"
        }
    ],
    "sg:phone":"+39 0435 768020",
    "sg:postcode":"32040",
    "sg:province":"Belluno",
    "wof:name":"Cariverona Banca Spa",
    "wof:placetype":"venue"
},
  "geometry": {"coordinates":[12.443911,46.484966],"type":"Point"}
}