{
  "type": "Feature",
  "properties": {
    "iso:country":"IT",
    "sg:address":"60027 Osimo",
    "sg:city":"Osimo",
    "sg:orig_category":"Termotecnica E Riscaldamento, Apparecchiature E Servizi",
    "sg:phone":"+39 071 721061",
    "sg:postcode":"60027",
    "sg:province":"Ancona",
    "sg:website":"http://www.marvit.it",
    "wof:name":"Marvit Spa",
    "wof:placetype":"venue"
},
  "geometry": {"coordinates":[13.531453,43.503311],"type":"Point"}
}