{
  "type": "Feature",
  "properties": {
    "iso:country":"IT",
    "sg:address":"26, Via Del Tornitore 40138 Bologna",
    "sg:city":"Bologna",
    "sg:classifiers":[
        {
            "category":"Shopping",
            "type":"Retail Goods"
        }
    ],
    "sg:phone":"+39 39051530371",
    "sg:postcode":"40138",
    "sg:province":"Bologna",
    "sg:tags":[
        "finished",
        "-",
        "metallic"
    ],
    "wof:name":"In.ra.bo. (s.r.l.)",
    "wof:placetype":"venue"
},
  "geometry": {"coordinates":[11.416885376,44.5001449585],"type":"Point"}
}