{
  "type": "Feature",
  "properties": {
    "iso:country":"IT",
    "sg:address":"21013 Gallarate",
    "sg:city":"Gallarate",
    "sg:orig_category":"Scuole E Servizi Scolastici",
    "sg:phone":"+39 0331 200416",
    "sg:postcode":"21013",
    "sg:province":"Varese",
    "wof:name":"Istituti F. Cavallotti Srl",
    "wof:placetype":"venue"
},
  "geometry": {"coordinates":[8.80476,45.824413],"type":"Point"}
}