{
  "type": "Feature",
  "properties": {
    "addr:full":"227 Viale Della Repubblica, 59100 Prato Prato Prato 59100",
    "addr:postcode":"59100;59100",
    "addr:street":"Viale Della Repubblica",
    "iso:country":"IT",
    "sg:address":"227 Viale Della Repubblica, 59100 Prato",
    "sg:city":"Prato",
    "sg:classifiers":[
        {
            "category":"Banks & Credit Unions",
            "subcategory":"Financial Services",
            "type":"Services"
        }
    ],
    "sg:phone":"+39 390 574 5794",
    "sg:postcode":"59100",
    "sg:province":"Prato",
    "sg:tags":[
        "banking",
        "finance",
        "insurance"
    ],
    "wof:name":"Merchant Leasing & Factoring Spa",
    "wof:placetype":"venue"
},
  "geometry": {"coordinates":[11.1263513565,43.9359703064],"type":"Point"}
}