{
  "type": "Feature",
  "properties": {
    "addr:full":"S.s. Flaminia Km 41,400 00068 Rignano Flaminio Rignano Flaminio Roma 00068",
    "addr:housenumber":"km 41,400",
    "addr:postcode":"00068;roma 00068",
    "iso:country":"IT",
    "sg:address":"S.s. Flaminia Km 41,400 00068 Rignano Flaminio",
    "sg:city":"Rignano Flaminio",
    "sg:classifiers":[
        {
            "category":"Manufacturing",
            "subcategory":"Building Materials",
            "type":"Manufacturing & Wholesale Goods"
        }
    ],
    "sg:phone":"+39 0761 507893",
    "sg:postcode":"00068",
    "sg:province":"Roma",
    "sg:tags":[
        "machine",
        "industry",
        "special"
    ],
    "sg:website":"www.marmoelettro.it",
    "wof:name":"Marmoelettromeccanica Srl",
    "wof:placetype":"venue"
},
  "geometry": {"coordinates":[12.482325,41.895466],"type":"Point"}
}