{
  "type": "Feature",
  "properties": {
    "iso:country":"IT",
    "sg:address":"20090 Assago",
    "sg:city":"Assago",
    "sg:orig_category":"Campeggio. Accessori Dei Mezzi Di Trasporto",
    "sg:phone":"+39 02 4884 4281",
    "sg:postcode":"20090",
    "sg:province":"Milano",
    "wof:name":"Bianchi Paolo Srl",
    "wof:placetype":"venue"
},
  "geometry": {"coordinates":[9.120116,45.40873],"type":"Point"}
}