{
  "type": "Feature",
  "properties": {
    "iso:country":"IT",
    "sg:address":"40134 Bologna",
    "sg:city":"Bologna",
    "sg:orig_category":"Carta, Cartone E Prodotti Primari. Forniture Per Attivita' Commerciali Ed Artigianali",
    "sg:phone":"+39 051 614 2408",
    "sg:postcode":"40134",
    "sg:province":"Bologna",
    "sg:website":"http://www.borianicarta.it",
    "wof:name":"Ditta Ivo Boriani Di Elisabetta Boriani & C. Sas",
    "wof:placetype":"venue"
},
  "geometry": {"coordinates":[11.318292,44.494549],"type":"Point"}
}