{
  "type": "Feature",
  "properties": {
    "iso:country":"IT",
    "sg:address":"18, Via Pedeguarda 31051 Follina",
    "sg:city":"Follina",
    "sg:classifiers":[
        {
            "category":"Shopping",
            "subcategory":"Crafts & Fabrics",
            "type":"Retail Goods"
        }
    ],
    "sg:phone":"+39 0438 842409",
    "sg:postcode":"31051",
    "sg:province":"Treviso",
    "wof:name":"Setaveneta (s.r.l.)",
    "wof:placetype":"venue"
},
  "geometry": {"coordinates":[12.1516809464,45.9285469055],"type":"Point"}
}