{
  "type": "Feature",
  "properties": {
    "iso:country":"IT",
    "sg:address":"4, Via Newton 20016 Pero",
    "sg:city":"Pero",
    "sg:classifiers":[
        {
            "category":"Wholesale",
            "subcategory":"Drugs",
            "type":"Manufacturing & Wholesale Goods"
        }
    ],
    "sg:phone":"+39 390 233 9271",
    "sg:postcode":"20016",
    "sg:province":"Milano",
    "sg:tags":[
        "chemical",
        "pharmaceutical"
    ],
    "wof:name":"Pti Spa",
    "wof:placetype":"venue"
},
  "geometry": {"coordinates":[9.081513,45.502605],"type":"Point"}
}