{
  "type": "Feature",
  "properties": {
    "addr:full":"37, Via Piani Savelli Pavona 00041 Albano Laziale Albano Laziale Roma 00041",
    "addr:postcode":"00041;00041",
    "addr:street":"Via Piani Savelli Pavona;Roma",
    "iso:country":"IT",
    "sg:address":"37, Via Piani Savelli Pavona 00041 Albano Laziale",
    "sg:city":"Albano Laziale",
    "sg:classifiers":[
        {
            "category":"Wholesale",
            "subcategory":"Medical Equipment & Supplies",
            "type":"Manufacturing & Wholesale Goods"
        }
    ],
    "sg:phone":"+39 39069315492",
    "sg:postcode":"00041",
    "sg:province":"Roma",
    "sg:tags":[
        "-",
        "health",
        "instrument"
    ],
    "wof:name":"Cosmed Srl",
    "wof:placetype":"venue"
},
  "geometry": {"coordinates":[12.611259,41.719006],"type":"Point"}
}