{
  "type": "Feature",
  "properties": {
    "addr:full":"4, Via Cristina 44026 Mesola Mesola Ferrara 44026",
    "addr:postcode":"44026;44026",
    "addr:street":"Via Cristina",
    "iso:country":"IT",
    "sg:address":"4, Via Cristina 44026 Mesola",
    "sg:city":"Mesola",
    "sg:classifiers":[
        {
            "category":"Shopping",
            "subcategory":"Crafts & Fabrics",
            "type":"Retail Goods"
        }
    ],
    "sg:phone":"+39 0533 794878",
    "sg:postcode":"44026",
    "sg:province":"Ferrara",
    "wof:name":"A. Benvenuti S.n.c.",
    "wof:placetype":"venue"
},
  "geometry": {"coordinates":[12.2292346954,44.8766059875],"type":"Point"}
}