{
  "type": "Feature",
  "properties": {
    "addr:full":"20123 Milano Milano Milano 20123",
    "addr:postcode":"20123;20123",
    "iso:country":"IT",
    "sg:address":"20123 Milano",
    "sg:city":"Milano",
    "sg:classifiers":[
        {
            "category":"Health Services",
            "subcategory":"Health Practitioner",
            "type":"Services"
        }
    ],
    "sg:phone":"+39 02 469 4878",
    "sg:postcode":"20123",
    "sg:province":"Milano",
    "sg:tags":[
        "medici"
    ],
    "wof:name":"Saraval Anteo",
    "wof:placetype":"venue"
},
  "geometry": {"coordinates":[9.1707725525,45.4676742554],"type":"Point"}
}