{
  "type": "Feature",
  "properties": {
    "iso:country":"IT",
    "sg:address":"2, Contrada Frassineto 85050 Paterno",
    "sg:city":"Paterno",
    "sg:classifiers":[
        {
            "category":"Real Estate",
            "subcategory":"Surveying",
            "type":"Services"
        }
    ],
    "sg:phone":"+39 0975 340105",
    "sg:postcode":"85050",
    "sg:province":"Potenza",
    "sg:tags":[
        "equipment",
        "material",
        "good",
        "-",
        "handling"
    ],
    "wof:name":"Paterlegno Snc",
    "wof:placetype":"venue"
},
  "geometry": {"coordinates":[15.802221,40.637241],"type":"Point"}
}