{
  "type": "Feature",
  "properties": {
    "iso:country":"IT",
    "sg:address":"20131 Milano",
    "sg:city":"Milano",
    "sg:orig_category":"Articoli Medico-sanitari Ed Ortopedici",
    "sg:phone":"+39 02 282 9275",
    "sg:postcode":"20131",
    "sg:province":"Milano",
    "wof:name":"Audire Di Angiola M. Scibona",
    "wof:placetype":"venue"
},
  "geometry": {"coordinates":[9.223392,45.490303],"type":"Point"}
}