{
  "type": "Feature",
  "properties": {
    "addr:full":"20126 Milano Milano Milano 20126",
    "addr:postcode":"20126;20126",
    "iso:country":"IT",
    "sg:address":"20126 Milano",
    "sg:city":"Milano",
    "sg:orig_category":"Servizi E Lavori Per Ecologia E Smaltimento Rifiuti. Macchine E Forniture Per Ecologia E Smaltimento Rifiuti",
    "sg:phone":"+39 02 270 7181",
    "sg:postcode":"20126",
    "sg:province":"Milano",
    "wof:name":"Imeco Srl",
    "wof:placetype":"venue"
},
  "geometry": {"coordinates":[9.224881,45.518158],"type":"Point"}
}