{
  "type": "Feature",
  "properties": {
    "addr:full":"00178 Roma Roma Roma 00178",
    "addr:postcode":"00178;00178",
    "iso:country":"IT",
    "sg:address":"00178 Roma",
    "sg:city":"Roma",
    "sg:orig_category":"Ristorazione E Locali Pubblici Affini. Ristoranti Ed Esercizi Affini. Servizi Ausiliari Di Ristorazione E Di Intrattenimento",
    "sg:phone":"+39 06 519 2786",
    "sg:postcode":"00178",
    "sg:province":"Roma",
    "sg:website":"http://www.anthonyclub.it",
    "wof:name":"Anthony Club Srl",
    "wof:placetype":"venue"
},
  "geometry": {"coordinates":[12.519298,41.8307],"type":"Point"}
}