{
  "type": "Feature",
  "properties": {
    "addr:full":"20121 Milano Milano Milano 20121",
    "addr:postcode":"20121;20121",
    "iso:country":"IT",
    "sg:address":"20121 Milano",
    "sg:city":"Milano",
    "sg:orig_category":"Petroli, Gas E Combustibili. Servizi E Lavori Industria Chimica. Servizi E Lavori Per Edilizia E Lavori Pubblici. Acqua, Luce, Gas E Societa' Di Esercizio Pubblico",
    "sg:phone":"+39 02 777941",
    "sg:postcode":"20121",
    "sg:province":"Milano",
    "wof:name":"British Gas Rimi",
    "wof:placetype":"venue"
},
  "geometry": {"coordinates":[9.1955909729,45.4723815918],"type":"Point"}
}