{
  "type": "Feature",
  "properties": {
    "iso:country":"IT",
    "sg:address":"76, Via Martiri Del Xxi 10064 Pinerolo",
    "sg:city":"Pinerolo",
    "sg:classifiers":[
        {
            "category":"Professional",
            "subcategory":"Engineering",
            "type":"Services"
        }
    ],
    "sg:phone":"+39 390 121 2311",
    "sg:postcode":"10064",
    "sg:province":"Torino",
    "sg:tags":[
        "machine",
        "-",
        "mechanical"
    ],
    "wof:name":"Pmt Italia S.p.a",
    "wof:placetype":"venue"
},
  "geometry": {"coordinates":[7.686619,45.07056],"type":"Point"}
}