{
  "type": "Feature",
  "properties": {
    "iso:country":"IT",
    "sg:address":"9, Via Dell' Artigiano 32026 Mel",
    "sg:city":"Mel",
    "sg:classifiers":[
        {
            "category":"Professional",
            "subcategory":"Engineering",
            "type":"Services"
        }
    ],
    "sg:phone":"+39 0437 753945",
    "sg:postcode":"32026",
    "sg:province":"Belluno",
    "sg:tags":[
        "machine",
        "-",
        "mechanical"
    ],
    "wof:name":"Moret Nerino",
    "wof:placetype":"venue"
},
  "geometry": {"coordinates":[12.106293,46.07021],"type":"Point"}
}