{
  "type": "Feature",
  "properties": {
    "iso:country":"IT",
    "sg:address":"Via Flaminia 06023 Gualdo Tadino",
    "sg:city":"Gualdo Tadino",
    "sg:classifiers":[
        {
            "category":"Professional",
            "subcategory":"Engineering",
            "type":"Services"
        }
    ],
    "sg:phone":"+39 075 914 0435",
    "sg:postcode":"06023",
    "sg:province":"Perugia",
    "sg:tags":[
        "machine",
        "-",
        "mechanical"
    ],
    "wof:name":"Viventi Rosmundo S.r.l.",
    "wof:placetype":"venue"
},
  "geometry": {"coordinates":[12.779157,43.230736],"type":"Point"}
}