{
  "type": "Feature",
  "properties": {
    "iso:country":"IT",
    "sg:address":"21010 Arsago Seprio",
    "sg:city":"Arsago Seprio",
    "sg:orig_category":"Cartotecnica E Servizi. Forniture Per Uffici",
    "sg:phone":"+39 0331 768690",
    "sg:postcode":"21010",
    "sg:province":"Varese",
    "wof:name":"Cartoleria Vanoni Di Piantanida Luciano",
    "wof:placetype":"venue"
},
  "geometry": {"coordinates":[8.774903,45.6464],"type":"Point"}
}