{
  "type": "Feature",
  "properties": {
    "iso:country":"IT",
    "sg:address":"Via L. Perosi 5 31020 Ca' Rainati",
    "sg:classifiers":[
        {
            "category":"Arts & Performance",
            "subcategory":"Dance",
            "type":"Entertainment"
        }
    ],
    "sg:phone":"+39 0423 484325",
    "sg:postcode":"31020",
    "sg:province":"Treviso",
    "sg:tags":[
        "nouveau",
        "lamp"
    ],
    "sg:website":"www.elegantlight.com",
    "wof:name":"Elegant Light Sas",
    "wof:placetype":"venue"
},
  "geometry": {"coordinates":[12.242072,45.666286],"type":"Point"}
}