{
  "type": "Feature",
  "properties": {
    "iso:country":"IT",
    "sg:address":"80040 S.sebastiano Vesuvio",
    "sg:orig_category":"Forniture Per Attivita' Industriali",
    "sg:phone":"+39 081 574 7090",
    "sg:postcode":"80040",
    "sg:province":"Napoli",
    "wof:name":"D. & T. Tex Sas",
    "wof:placetype":"venue"
},
  "geometry": {"coordinates":[14.3578090668,40.8465232849],"type":"Point"}
}