{
  "type": "Feature",
  "properties": {
    "iso:country":"IT",
    "sg:address":"14100 Asti",
    "sg:city":"Asti",
    "sg:orig_category":"Macchine, Impianti E Forniture Per Industria Grafica, Cartaria E Cartotecnica. Forniture Per Uffici",
    "sg:phone":"+39 0141 593936",
    "sg:postcode":"14100",
    "sg:province":"Asti",
    "wof:name":"Crosetti Roberto",
    "wof:placetype":"venue"
},
  "geometry": {"coordinates":[8.209192,44.900806],"type":"Point"}
}