{
  "type": "Feature",
  "properties": {
    "iso:country":"IT",
    "sg:address":"Via Monte Grappa 46 22069 Rovellasca",
    "sg:city":"Rovellasca",
    "sg:classifiers":[
        {
            "category":"Military Area",
            "subcategory":"Coast Guard Base",
            "type":"Public Place"
        }
    ],
    "sg:phone":"+39 02 9674 0420",
    "sg:postcode":"22069",
    "sg:province":"Como",
    "sg:tags":[
        "lock",
        "door"
    ],
    "sg:website":"www.fiamserrature.it",
    "wof:name":"Fiam Industria Serrature Spa",
    "wof:placetype":"venue"
},
  "geometry": {"coordinates":[9.056433,45.663723],"type":"Point"}
}