{
  "type": "Feature",
  "properties": {
    "iso:country":"IT",
    "sg:address":"08100 Nuoro",
    "sg:city":"Nuoro",
    "sg:orig_category":"Arredamento Bar E Ristoranti",
    "sg:phone":"+39 0784 33266",
    "sg:postcode":"08100",
    "sg:province":"Nuoro",
    "wof:name":"Berretta & C. Di Berretta Antonio Snc",
    "wof:placetype":"venue"
},
  "geometry": {"coordinates":[9.328831,40.317997],"type":"Point"}
}