{
  "type": "Feature",
  "properties": {
    "iso:country":"IT",
    "sg:address":"20010 Cornaredo",
    "sg:city":"Cornaredo",
    "sg:orig_category":"Impianti, Attrezzature E Forniture Sanitarie Ed Ospedaliere. Macchine, Strumenti Ed Apparecchi Per Attivita' Industriali",
    "sg:phone":"+39 02 939911",
    "sg:postcode":"20010",
    "sg:province":"Milano",
    "wof:name":"Dasit Spa",
    "wof:placetype":"venue"
},
  "geometry": {"coordinates":[9.033037,45.483765],"type":"Point"}
}