{
  "type": "Feature",
  "properties": {
    "iso:country":"IT",
    "sg:address":"20124 Milano",
    "sg:city":"Milano",
    "sg:classifiers":[
        {
            "category":"Health Services",
            "subcategory":"Health Practitioner",
            "type":"Services"
        }
    ],
    "sg:phone":"+39 02 655 1342",
    "sg:postcode":"20124",
    "sg:province":"Milano",
    "sg:tags":[
        "medici"
    ],
    "wof:name":"Donati Emilio",
    "wof:placetype":"venue"
},
  "geometry": {"coordinates":[9.199023,45.477524],"type":"Point"}
}