{
  "type": "Feature",
  "properties": {
    "iso:country":"IT",
    "sg:address":"146, Viale Lombardia 20093 Cologno Monzese",
    "sg:city":"Cologno Monzese",
    "sg:classifiers":[
        {
            "category":"Professional",
            "subcategory":"Engineering",
            "type":"Services"
        }
    ],
    "sg:phone":"+39 39022547630",
    "sg:postcode":"20093",
    "sg:province":"Milano",
    "sg:tags":[
        "machine",
        "-",
        "mechanical"
    ],
    "wof:name":"Bianchi Fratelli (s.r.l.)",
    "wof:placetype":"venue"
},
  "geometry": {"coordinates":[9.274576,45.545719],"type":"Point"}
}