{
  "type": "Feature",
  "properties": {
    "addr:full":"Via Borgo Di; Roma",
    "addr:street":"Via Borgo Di Roma",
    "iso:country":"IT",
    "sg:address":"Via Borgo Di; Roma",
    "sg:classifiers":[
        {
            "category":"Banks & Credit Unions",
            "subcategory":"Bank",
            "type":"Services"
        }
    ],
    "sg:phone":"+39 06 6830 0663",
    "wof:name":"Banca Di Roma",
    "wof:placetype":"venue"
},
  "geometry": {"coordinates":[12.373002,41.918617],"type":"Point"}
}