{
  "type": "Feature",
  "properties": {
    "iso:country":"IT",
    "sg:address":"33030 Maiano",
    "sg:orig_category":"Non-classified Establishments",
    "sg:phone":"+39 0432 959252",
    "sg:postcode":"33030",
    "sg:province":"Udine",
    "sg:website":"http://www.mobilisnaidero.it",
    "wof:name":"Mobilsnaidero Srl",
    "wof:placetype":"venue"
},
  "geometry": {"coordinates":[13.054638,46.189445],"type":"Point"}
}