{
  "type": "Feature",
  "properties": {
    "iso:country":"IT",
    "sg:address":"81, Via Battifollo Romito Magra Romito Magra 19021 Arcola",
    "sg:city":"Arcola",
    "sg:classifiers":[
        {
            "category":"Shopping",
            "type":"Retail Goods"
        }
    ],
    "sg:phone":"+39 0187 622516",
    "sg:postcode":"19021",
    "sg:province":"La Spezia",
    "sg:tags":[
        "finished",
        "-",
        "metallic"
    ],
    "wof:name":"F.a.s.a.l. Di Brotini E Posterli",
    "wof:placetype":"venue"
},
  "geometry": {"coordinates":[9.8292188644,44.1067352295],"type":"Point"}
}