{
  "type": "Feature",
  "properties": {
    "addr:full":"Via Verga 1 20045 Besana In Brianza Besana in Brianza Milano 20045",
    "addr:housenumber":"1",
    "addr:postcode":"20045;20045",
    "addr:street":"Via Verga",
    "iso:country":"IT",
    "sg:address":"Via Verga 1 20045 Besana In Brianza",
    "sg:city":"Besana in Brianza",
    "sg:classifiers":[
        {
            "category":"Manufacturing",
            "subcategory":"Rubber & Plastics",
            "type":"Manufacturing & Wholesale Goods"
        }
    ],
    "sg:phone":"+39 036 299 4943",
    "sg:postcode":"20045",
    "sg:province":"Milano",
    "sg:tags":[
        "machine",
        "bag",
        "sealing"
    ],
    "sg:website":"www.fapitaly.com",
    "wof:name":"Fap Srl",
    "wof:placetype":"venue"
},
  "geometry": {"coordinates":[9.1881408691,45.4636878967],"type":"Point"}
}