{
  "type": "Feature",
  "properties": {
    "iso:country":"IT",
    "sg:address":"12040 Morozzo",
    "sg:city":"Morozzo",
    "sg:orig_category":"Prodotti Alimentari",
    "sg:phone":"+39 0171 772008",
    "sg:postcode":"12040",
    "sg:province":"Cuneo",
    "wof:name":"Lovovo Agroalimentare Srl",
    "wof:placetype":"venue"
},
  "geometry": {"coordinates":[7.7096004486,44.4244995117],"type":"Point"}
}