{
  "type": "Feature",
  "properties": {
    "addr:full":"35030 Veggiano Veggiano Padova 35030",
    "addr:postcode":"35030;35030",
    "iso:country":"IT",
    "sg:address":"35030 Veggiano",
    "sg:city":"Veggiano",
    "sg:orig_category":"Pronto Soccorso",
    "sg:phone":"+39 049 900 3224",
    "sg:postcode":"35030",
    "sg:province":"Padova",
    "wof:name":"Croce Bianca Associazione Di Volontariato",
    "wof:placetype":"venue"
},
  "geometry": {"coordinates":[11.1159410477,45.4183425903],"type":"Point"}
}