{
  "type": "Feature",
  "properties": {
    "iso:country":"IT",
    "sg:address":"73044 Galatone",
    "sg:city":"Galatone",
    "sg:orig_category":"Macchine E Forniture Per Arredamento E Industria Del Legno",
    "sg:phone":"+39 0833 832129",
    "sg:postcode":"73044",
    "sg:province":"Lecce",
    "wof:name":"I.m.a. Srl",
    "wof:placetype":"venue"
},
  "geometry": {"coordinates":[18.059866,40.13916],"type":"Point"}
}