{
  "type": "Feature",
  "properties": {
    "addr:full":"20090 Vimodrone Vimodrone Milano 20090",
    "addr:postcode":"20090;20090",
    "iso:country":"IT",
    "sg:address":"20090 Vimodrone",
    "sg:city":"Vimodrone",
    "sg:orig_category":"Spedizioni Aeree, Marittime E Terrestri",
    "sg:phone":"+39 02 250 7191",
    "sg:postcode":"20090",
    "sg:province":"Milano",
    "sg:website":"http://www.targetitaly.it",
    "wof:name":"Target Italia Srl",
    "wof:placetype":"venue"
},
  "geometry": {"coordinates":[9.285223,45.513493],"type":"Point"}
}