{
  "type": "Feature",
  "properties": {
    "iso:country":"IT",
    "sg:address":"10051 Avigliana",
    "sg:city":"Avigliana",
    "sg:orig_category":"Nautica. Automobili E Mezzi Di Trasporto",
    "sg:phone":"+39 011 936 9362",
    "sg:postcode":"10051",
    "sg:province":"Torino",
    "wof:name":"Azimut Spa",
    "wof:placetype":"venue"
},
  "geometry": {"coordinates":[7.381818,45.083744],"type":"Point"}
}