{
  "type": "Feature",
  "properties": {
    "iso:country":"IT",
    "sg:address":"20020 Arconate",
    "sg:city":"Arconate",
    "sg:orig_category":"Tessuti E Stoffe. Forniture Per Attivita' Industriali",
    "sg:phone":"+39 0331 461218",
    "sg:postcode":"20020",
    "sg:province":"Milano",
    "wof:name":"Tessitura Calloni Lino & C. S.n.c.",
    "wof:placetype":"venue"
},
  "geometry": {"coordinates":[9.076509,45.544132],"type":"Point"}
}