{
  "type": "Feature",
  "properties": {
    "iso:country":"IT",
    "sg:address":"12, Via Maestri Del Lavoro 35016 Piazzola Sul Brenta",
    "sg:city":"Piazzola sul Brenta",
    "sg:classifiers":[
        {
            "category":"Manufacturing",
            "subcategory":"Tools & Machinery",
            "type":"Manufacturing & Wholesale Goods"
        }
    ],
    "sg:phone":"+39 049 559 0813",
    "sg:postcode":"35016",
    "sg:province":"Padova",
    "sg:tags":[
        "environment",
        "equipment",
        "-"
    ],
    "wof:name":"Biasio Walter",
    "wof:placetype":"venue"
},
  "geometry": {"coordinates":[11.876589,45.409569],"type":"Point"}
}