{
  "type": "Feature",
  "properties": {
    "iso:country":"IT",
    "sg:address":"20094 Corsico",
    "sg:city":"Corsico",
    "sg:classifiers":[
        {
            "category":"Health Services",
            "subcategory":"Health Practitioner",
            "type":"Services"
        }
    ],
    "sg:phone":"+39 02 440 6859",
    "sg:postcode":"20094",
    "sg:province":"Milano",
    "sg:tags":[
        "medici"
    ],
    "wof:name":"Zingales Maria",
    "wof:placetype":"venue"
},
  "geometry": {"coordinates":[9.1154937744,45.4310569763],"type":"Point"}
}