{
  "type": "Feature",
  "properties": {
    "addr:full":"65127 Pescara Pescara Pescara 65127",
    "addr:postcode":"65127;65127",
    "iso:country":"IT",
    "sg:address":"65127 Pescara",
    "sg:city":"Pescara",
    "sg:orig_category":"Abbigliamento Esterno, Maglierie E Pelliccerie",
    "sg:phone":"+39 085 63977",
    "sg:postcode":"65127",
    "sg:province":"Pescara",
    "sg:website":"http://www.snccosenza.com",
    "wof:name":"Cosenza Di Baroni & Cipollone",
    "wof:placetype":"venue"
},
  "geometry": {"coordinates":[14.216056,42.4603],"type":"Point"}
}