{
  "type": "Feature",
  "properties": {
    "addr:full":"15100 Alessandria Alessandria Alessandria 15100",
    "addr:postcode":"15100;15100",
    "iso:country":"IT",
    "sg:address":"15100 Alessandria",
    "sg:city":"Alessandria",
    "sg:classifiers":[
        {
            "category":"Utilities",
            "subcategory":"Natural Gas",
            "type":"Services"
        }
    ],
    "sg:phone":"+39 0131 254600",
    "sg:postcode":"15100",
    "sg:province":"Alessandria",
    "sg:tags":[
        "bruciatori",
        "e",
        "carbone"
    ],
    "wof:name":"Energas Snc Di Capuzzo & Bellinazzo",
    "wof:placetype":"venue"
},
  "geometry": {"coordinates":[8.805001,44.89278],"type":"Point"}
}