{
  "type": "Feature",
  "properties": {
    "addr:full":"Cda Manferrara Soprana Zona Pip 75016 Pomarico Pomarico Matera 75016",
    "addr:postcode":"75016;75016",
    "addr:street":"Pip",
    "iso:country":"IT",
    "sg:address":"Cda Manferrara Soprana Zona Pip 75016 Pomarico",
    "sg:city":"Pomarico",
    "sg:classifiers":[
        {
            "category":"Manufacturing",
            "subcategory":"Textiles",
            "type":"Manufacturing & Wholesale Goods"
        }
    ],
    "sg:phone":"+39 0835 552376",
    "sg:postcode":"75016",
    "sg:province":"Matera",
    "sg:tags":[
        "knitted",
        "industry"
    ],
    "wof:name":"Vimes Srl",
    "wof:placetype":"venue"
},
  "geometry": {"coordinates":[16.606087,40.668652],"type":"Point"}
}