{
  "type": "Feature",
  "properties": {
    "iso:country":"IT",
    "sg:address":"Via Firenze 1/e; Lucera; 71036",
    "sg:city":"Lucera",
    "sg:classifiers":[
        {
            "category":"Banks & Credit Unions",
            "subcategory":"Bank",
            "type":"Services"
        }
    ],
    "sg:phone":"+39 0881 522825",
    "sg:postcode":"71036",
    "sg:province":"Foggia",
    "wof:name":"Credito Italiano Spa",
    "wof:placetype":"venue"
},
  "geometry": {"coordinates":[15.330979,41.508961],"type":"Point"}
}