{
  "type": "Feature",
  "properties": {
    "addr:full":"38068 Rovereto Rovereto Trento 38068",
    "addr:postcode":"38068;38068",
    "iso:country":"IT",
    "sg:address":"38068 Rovereto",
    "sg:city":"Rovereto",
    "sg:orig_category":"Servizi Per Aziende, Manifestazioni E Supporto Agli Scambi Commerciali",
    "sg:phone":"+39 0464 437474",
    "sg:postcode":"38068",
    "sg:province":"Trento",
    "sg:website":"http://www.martinipubblicita.com",
    "wof:name":"Martini Pubblicit\u00c0 Srl",
    "wof:placetype":"venue"
},
  "geometry": {"coordinates":[11.039661,45.889877],"type":"Point"}
}