{
  "type": "Feature",
  "properties": {
    "addr:full":"20016 Pero Pero Milano 20016",
    "addr:postcode":"20016;20016",
    "iso:country":"IT",
    "sg:address":"20016 Pero",
    "sg:city":"Pero",
    "sg:orig_category":"Prodotti Chimici Secondari. Prodotti Cosmetici E Da Toeletta",
    "sg:phone":"+39 02 353 5098",
    "sg:postcode":"20016",
    "sg:province":"Milano",
    "wof:name":"Josette France Sas Di Mazzilli Domenico E C.",
    "wof:placetype":"venue"
},
  "geometry": {"coordinates":[9.0797119141,45.5119552612],"type":"Point"}
}