{
  "type": "Feature",
  "properties": {
    "iso:country":"IT",
    "sg:address":"7, Via De Carli 22036 Erba",
    "sg:city":"Erba",
    "sg:classifiers":[
        {
            "category":"Professional",
            "subcategory":"Engineering",
            "type":"Services"
        }
    ],
    "sg:phone":"+39 39031641524",
    "sg:postcode":"22036",
    "sg:province":"Como",
    "sg:tags":[
        "machine",
        "-",
        "mechanical"
    ],
    "wof:name":"O.e.t.",
    "wof:placetype":"venue"
},
  "geometry": {"coordinates":[9.218295,45.811153],"type":"Point"}
}