{
  "type": "Feature",
  "properties": {
    "iso:country":"IT",
    "sg:address":"20093 Cologno Monzese",
    "sg:city":"Cologno Monzese",
    "sg:classifiers":[
        {
            "category":"Manufacturing",
            "subcategory":"Chemicals & Compounds",
            "type":"Manufacturing & Wholesale Goods"
        }
    ],
    "sg:phone":"+39 02 2539 6614",
    "sg:postcode":"20093",
    "sg:province":"Milano",
    "sg:tags":[
        "equipment",
        "industry",
        "machinery"
    ],
    "wof:name":"Stevenazzi Packaging Srl",
    "wof:placetype":"venue"
},
  "geometry": {"coordinates":[9.268953,45.525219],"type":"Point"}
}