{
  "type": "Feature",
  "properties": {
    "iso:country":"IT",
    "sg:address":"16030 Pieve Ligure",
    "sg:city":"Pieve Ligure",
    "sg:classifiers":[
        {
            "category":"Health Services",
            "subcategory":"Health Practitioner",
            "type":"Services"
        }
    ],
    "sg:phone":"+39 010 346 0174",
    "sg:postcode":"16030",
    "sg:province":"Genova",
    "sg:tags":[
        "medici"
    ],
    "wof:name":"Giugiario Patrizia",
    "wof:placetype":"venue"
},
  "geometry": {"coordinates":[9.077716,44.377934],"type":"Point"}
}