{
  "type": "Feature",
  "properties": {
    "iso:country":"IT",
    "sg:address":"Via Per Turbigo, 1/3 20022 Castano Primo",
    "sg:city":"Castano Primo",
    "sg:classifiers":[
        {
            "category":"Personal",
            "subcategory":"Tanning Parlor",
            "type":"Services"
        }
    ],
    "sg:phone":"+39 0331 881364",
    "sg:postcode":"20022",
    "sg:province":"Milano",
    "sg:tags":[
        "hide"
    ],
    "wof:name":"Maitem Srl",
    "wof:placetype":"venue"
},
  "geometry": {"coordinates":[8.76946,45.546768],"type":"Point"}
}