{
  "type": "Feature",
  "properties": {
    "addr:full":"00013 Tor Lupara Tor lupara Roma 00013",
    "addr:postcode":"00013;00013",
    "addr:street":"Tor Lupara Tor;Roma",
    "iso:country":"IT",
    "sg:address":"00013 Tor Lupara",
    "sg:city":"Tor lupara",
    "sg:orig_category":"Arte Ed Artigianato Artistico",
    "sg:phone":"+39 06 906 3312",
    "sg:postcode":"00013",
    "sg:province":"Roma",
    "wof:name":"Battiston Massimo",
    "wof:placetype":"venue"
},
  "geometry": {"coordinates":[12.621252,41.998074],"type":"Point"}
}