{
  "type": "Feature",
  "properties": {
    "addr:full":"90145 Palermo Palermo Palermo 90145",
    "addr:postcode":"90145;90145",
    "iso:country":"IT",
    "sg:address":"90145 Palermo",
    "sg:city":"Palermo",
    "sg:orig_category":"Pompe",
    "sg:phone":"+39 091 676 3517",
    "sg:postcode":"90145",
    "sg:province":"Palermo",
    "wof:name":"Chiappara Geom. Vincenzo",
    "wof:placetype":"venue"
},
  "geometry": {"coordinates":[13.3242692947,38.1254959106],"type":"Point"}
}