{
  "type": "Feature",
  "properties": {
    "iso:country":"IT",
    "sg:address":"17031 Albenga",
    "sg:city":"Albenga",
    "sg:orig_category":"Servizi Per Aziende, Manifestazioni E Supporto Agli Scambi Commerciali",
    "sg:phone":"+39 0182 52637",
    "sg:postcode":"17031",
    "sg:province":"Savona",
    "wof:name":"Bertone Piergiorgio",
    "wof:placetype":"venue"
},
  "geometry": {"coordinates":[8.474292,44.317181],"type":"Point"}
}