{
  "type": "Feature",
  "properties": {
    "addr:full":"20017 Rho Rho Milano 20017",
    "addr:postcode":"20017;20017",
    "iso:country":"IT",
    "sg:address":"20017 Rho",
    "sg:city":"Rho",
    "sg:orig_category":"Scuole E Servizi Scolastici. Servizi Per Lo Sport E Il Tempo Libero",
    "sg:phone":"+39 02 930 8046",
    "sg:postcode":"20017",
    "sg:province":"Milano",
    "wof:name":"Associazione Iniziative Culturali Artistiche",
    "wof:placetype":"venue"
},
  "geometry": {"coordinates":[9.041754,45.529324],"type":"Point"}
}