{
  "type": "Feature",
  "properties": {
    "iso:country":"IT",
    "sg:address":"00193 Roma",
    "sg:city":"Roma",
    "sg:orig_category":"Informatica - Consulenza E Servizi. Automazione E Macchine Per Ufficio. Servizi Ausiliari Di Analisi, Controllo E Ricerca. Servizi Per Aziende, Manifestazioni E Supporto Agli Scambi Commerciali",
    "sg:phone":"+39 06 320 4944",
    "sg:postcode":"00193",
    "sg:province":"Roma",
    "sg:website":"http://www.pml.it",
    "wof:name":"Pml Telematica E Telecomunicazioni Srl",
    "wof:placetype":"venue"
},
  "geometry": {"coordinates":[12.417894,41.844124],"type":"Point"}
}