{
  "type": "Feature",
  "properties": {
    "addr:full":"20096 Pioltello Pioltello Milano 20096",
    "addr:postcode":"20096;20096",
    "iso:country":"IT",
    "sg:address":"20096 Pioltello",
    "sg:city":"Pioltello",
    "sg:orig_category":"Forniture Per Attivita' Industriali",
    "sg:phone":"+39 02 926 6155",
    "sg:postcode":"20096",
    "sg:province":"Milano",
    "wof:name":"Tecnigrafite Srl",
    "wof:placetype":"venue"
},
  "geometry": {"coordinates":[9.3241529465,45.4933052063],"type":"Point"}
}