{
  "type": "Feature",
  "properties": {
    "iso:country":"IT",
    "sg:address":"00151 Roma",
    "sg:city":"Roma",
    "sg:orig_category":"Telecomunicazioni E Telefonia, Impianti, Apparecchi E Servizi",
    "sg:phone":"+39 06 6574 0004",
    "sg:postcode":"00151",
    "sg:province":"Roma",
    "wof:name":"Logatek Srl",
    "wof:placetype":"venue"
},
  "geometry": {"coordinates":[12.446565,41.86578],"type":"Point"}
}