{
  "type": "Feature",
  "properties": {
    "iso:country":"IT",
    "sg:address":"41012 Carpi",
    "sg:city":"Carpi",
    "sg:orig_category":"Trasporti E Spedizioni Merci",
    "sg:phone":"+39 059 632 2511",
    "sg:postcode":"41012",
    "sg:province":"Modena",
    "wof:name":"Punto System",
    "wof:placetype":"venue"
},
  "geometry": {"coordinates":[10.8762950897,44.7831535339],"type":"Point"}
}