{
  "type": "Feature",
  "properties": {
    "iso:country":"IT",
    "sg:address":"10147 Torino",
    "sg:city":"Torino",
    "sg:orig_category":"Prodotti Di Base E Forniture Per Industria Alimentare E Bevande. Prodotti Chimici Di Base",
    "sg:phone":"+39 011 221 2211",
    "sg:postcode":"10147",
    "sg:province":"Torino",
    "wof:name":"San Giorgio Flavors S.p.a.",
    "wof:placetype":"venue"
},
  "geometry": {"coordinates":[7.6850442886,45.0998268127],"type":"Point"}
}