{
  "type": "Feature",
  "properties": {
    "iso:country":"IT",
    "sg:address":"12030 Cavallerleone",
    "sg:city":"Cavallerleone",
    "sg:orig_category":"Non-classified Establishments",
    "sg:phone":"+39 0172 85897",
    "sg:postcode":"12030",
    "sg:province":"Cuneo",
    "wof:name":"Arredamenti 2 G Di Giordana Giuseppe & C. Snc",
    "wof:placetype":"venue"
},
  "geometry": {"coordinates":[8.072266,44.577995],"type":"Point"}
}