{
  "type": "Feature",
  "properties": {
    "addr:full":"36063 Marostica Marostica Vicenza 36063",
    "addr:postcode":"36063;36063",
    "iso:country":"IT",
    "sg:address":"36063 Marostica",
    "sg:city":"Marostica",
    "sg:orig_category":"Torrefazione Di Caffe' Ed Affini - Lavorazione E Ingrosso",
    "sg:phone":"+39 0424 72117",
    "sg:postcode":"36063",
    "sg:province":"Vicenza",
    "wof:name":"Marosticana Caff\u00c8 Srl",
    "wof:placetype":"venue"
},
  "geometry": {"coordinates":[11.651682,45.756786],"type":"Point"}
}