{
  "type": "Feature",
  "properties": {
    "iso:country":"IT",
    "sg:address":"41012 Fossoli",
    "sg:city":"Budrione",
    "sg:orig_category":"Macchine, Impianti Ed Attrezzature Per Abbigliamento E Pelletterie",
    "sg:phone":"+39 059 660523",
    "sg:postcode":"41012",
    "sg:province":"Modena",
    "wof:name":"Ferrari Mario & C. (s.n.c.)",
    "wof:placetype":"venue"
},
  "geometry": {"coordinates":[10.88503,44.818676],"type":"Point"}
}