{
  "type": "Feature",
  "properties": {
    "iso:country":"IT",
    "sg:address":"117, Via Orzinuovi 25125 Brescia",
    "sg:city":"Brescia",
    "sg:classifiers":[
        {
            "category":"Shopping",
            "subcategory":"Clothing, Apparel, & Fashions",
            "type":"Retail Goods"
        }
    ],
    "sg:phone":"+39 39030348761",
    "sg:postcode":"25125",
    "sg:province":"Brescia",
    "sg:tags":[
        "clothes"
    ],
    "wof:name":"Cronert Italiana (s.p.a.)",
    "wof:placetype":"venue"
},
  "geometry": {"coordinates":[10.185384,45.5303],"type":"Point"}
}