{
  "type": "Feature",
  "properties": {
    "iso:country":"IT",
    "sg:address":"55100 Lucca",
    "sg:city":"Lucca",
    "sg:orig_category":"Zincatura A Caldo E A Spruzzo",
    "sg:phone":"+39 0583 406363",
    "sg:postcode":"55100",
    "sg:province":"Lucca",
    "wof:name":"Italzinc Srl",
    "wof:placetype":"venue"
},
  "geometry": {"coordinates":[10.532744,43.907997],"type":"Point"}
}