{
  "type": "Feature",
  "properties": {
    "addr:full":"59100 Prato Prato Prato 59100",
    "addr:postcode":"59100;59100",
    "iso:country":"IT",
    "sg:address":"59100 Prato",
    "sg:city":"Prato",
    "sg:orig_category":"Valvole E Apparecchiature Di Misura",
    "sg:phone":"+39 0574 597438",
    "sg:postcode":"59100",
    "sg:province":"Prato",
    "wof:name":"Baldi Sandro",
    "wof:placetype":"venue"
},
  "geometry": {"coordinates":[11.115015,43.859787],"type":"Point"}
}