{
  "type": "Feature",
  "properties": {
    "addr:full":"Via C. Grassi, 19; Erchie; 72020 Erchie Brindisi 72020",
    "addr:housenumber":"19",
    "addr:postcode":"72020;72020",
    "addr:street":"Via C. Grassi",
    "iso:country":"IT",
    "sg:address":"Via C. Grassi, 19; Erchie; 72020",
    "sg:city":"Erchie",
    "sg:classifiers":[
        {
            "category":"Banks & Credit Unions",
            "subcategory":"Bank",
            "type":"Services"
        }
    ],
    "sg:phone":"+39 0831 757009",
    "sg:postcode":"72020",
    "sg:province":"Brindisi",
    "wof:name":"Cassa Di Risparmio Di Puglia",
    "wof:placetype":"venue"
},
  "geometry": {"coordinates":[17.734823,40.43615],"type":"Point"}
}