{
  "type": "Feature",
  "properties": {
    "addr:full":"20154 Milano Milano Milano 20154",
    "addr:postcode":"20154;20154",
    "iso:country":"IT",
    "sg:address":"20154 Milano",
    "sg:city":"Milano",
    "sg:orig_category":"Materiali E Componenti Elettrotecnici",
    "sg:phone":"+39 02 655 1198",
    "sg:postcode":"20154",
    "sg:province":"Milano",
    "wof:name":"La Resistenza (s.r.l.)",
    "wof:placetype":"venue"
},
  "geometry": {"coordinates":[9.182794,45.483765],"type":"Point"}
}