{
  "type": "Feature",
  "properties": {
    "iso:country":"IT",
    "sg:address":"42017 Novellara",
    "sg:orig_category":"Minuterie Metalliche E Ferramenta",
    "sg:phone":"+39 0522 655611",
    "sg:postcode":"42017",
    "sg:province":"Reggio Nell'Emilia",
    "wof:name":"Viterie Mirabello (s.r.l.)",
    "wof:placetype":"venue"
},
  "geometry": {"coordinates":[10.6781311035,44.7689323425],"type":"Point"}
}