{
  "type": "Feature",
  "properties": {
    "iso:country":"IT",
    "sg:address":"80069 Vico Equense",
    "sg:city":"Vico Equense",
    "sg:classifiers":[
        {
            "category":"Travel",
            "subcategory":"Hotels & Motels",
            "type":"Entertainment"
        }
    ],
    "sg:phone":"+39 081 801 5522",
    "sg:postcode":"80069",
    "sg:province":"Napoli",
    "sg:tags":[
        "hotels",
        "facility"
    ],
    "wof:name":"Hotel Oriente G.i.t.a. Srl",
    "wof:placetype":"venue"
},
  "geometry": {"coordinates":[14.431727,40.667301],"type":"Point"}
}