{
  "type": "Feature",
  "properties": {
    "addr:full":"20144 Milano Milano Milano 20144",
    "addr:postcode":"20144;20144",
    "iso:country":"IT",
    "sg:address":"20144 Milano",
    "sg:city":"Milano",
    "sg:orig_category":"Metalli E Leghe. Gioielleria, Oreficeria E Argenteria",
    "sg:postcode":"20144",
    "sg:province":"Milano",
    "wof:name":"La Duo S.r.l.",
    "wof:placetype":"venue"
},
  "geometry": {"coordinates":[9.1586284637,45.4538955688],"type":"Point"}
}