{
  "type": "Feature",
  "properties": {
    "iso:country":"IT",
    "sg:address":"80053 Castellammare Di Stabia",
    "sg:city":"Castellammare di Stabia",
    "sg:orig_category":"Zootecnia E Pesca, Allevamento Piccoli Animali. Animali Domestici",
    "sg:phone":"+39 081 871 1358",
    "sg:postcode":"80053",
    "sg:province":"Napoli",
    "wof:name":"La Casa Degli Uccelli S.a.s",
    "wof:placetype":"venue"
},
  "geometry": {"coordinates":[14.4898,40.698475],"type":"Point"}
}