{
  "type": "Feature",
  "properties": {
    "addr:full":"57015 Cecina LI",
    "addr:postcode":"57015",
    "iso:country":"IT",
    "sg:address":"57015 Cecina",
    "sg:orig_category":"Manufacturers: Prefabbricati",
    "sg:phone":"+39 0586 680016",
    "sg:province":"LI",
    "wof:name":"Andrei Fratelli Snc",
    "wof:placetype":"venue"
},
  "geometry": {"coordinates":[-96.985344,43.405182],"type":"Point"}
}