{
  "type": "Feature",
  "properties": {
    "iso:country":"IT",
    "sg:address":"Pl Aldo Moro 1; Agrigento; 92100",
    "sg:city":"Agrigento",
    "sg:classifiers":[
        {
            "category":"Banks & Credit Unions",
            "subcategory":"Bank",
            "type":"Services"
        }
    ],
    "sg:phone":"+39 0922 481111",
    "sg:postcode":"92100",
    "sg:province":"Agrigento",
    "wof:name":"Banco Di Sicilia Spa",
    "wof:placetype":"venue"
},
  "geometry": {"coordinates":[13.58551,37.310432],"type":"Point"}
}