{
  "type": "Feature",
  "properties": {
    "addr:full":"196, Via Tiburtina 00185 Roma Roma Roma 00185",
    "addr:housenumber":"196",
    "addr:postcode":"00185;00185",
    "addr:street":"Via Tiburtina",
    "iso:country":"IT",
    "sg:address":"196, Via Tiburtina 00185 Roma",
    "sg:city":"Roma",
    "sg:classifiers":[
        {
            "category":"Professional",
            "subcategory":"Printing & Photocopies",
            "type":"Services"
        }
    ],
    "sg:phone":"+39 39064469905",
    "sg:postcode":"00185",
    "sg:province":"Roma",
    "wof:name":"Linotipia Velox (s.r.l.)",
    "wof:placetype":"venue"
},
  "geometry": {"coordinates":[12.5161142349,41.8993110657],"type":"Point"}
}