{
  "type": "Feature",
  "properties": {
    "iso:country":"IT",
    "sg:address":"81022 Casagiove",
    "sg:city":"Casagiove",
    "sg:orig_category":"Macchine Utensili E Impianti",
    "sg:phone":"+39 0823 494133",
    "sg:postcode":"81022",
    "sg:province":"Caserta",
    "wof:name":"General Rettifiche",
    "wof:placetype":"venue"
},
  "geometry": {"coordinates":[14.291843,41.07346],"type":"Point"}
}