{
  "type": "Feature",
  "properties": {
    "iso:country":"IT",
    "sg:address":"31056 Vallio",
    "sg:orig_category":"Macchine Ed Impianti Per Edilizia E Lavori Pubblici. Macchine, Strumenti Ed Apparecchi Per Attivita' Industriali",
    "sg:phone":"+39 0422 840507",
    "sg:postcode":"31056",
    "sg:province":"Treviso",
    "wof:name":"For.el. S.p.a.",
    "wof:placetype":"venue"
},
  "geometry": {"coordinates":[12.417277,45.637142],"type":"Point"}
}