{
  "type": "Feature",
  "properties": {
    "iso:country":"IT",
    "sg:address":"Via Mario Pagano 56 20090 Trezzano Sul Naviglio",
    "sg:city":"Trezzano sul Naviglio",
    "sg:classifiers":[
        {
            "category":"Building & Trades",
            "subcategory":"Landscaping Services",
            "type":"Services"
        }
    ],
    "sg:phone":"+39 02 445 0603",
    "sg:postcode":"20090",
    "sg:province":"Milano",
    "sg:tags":[
        "import",
        "oriental"
    ],
    "wof:name":"Italchina Sas Di Marcora Paolo & C.",
    "wof:placetype":"venue"
},
  "geometry": {"coordinates":[9.044973,45.428886],"type":"Point"}
}