{
  "type": "Feature",
  "properties": {
    "iso:country":"IT",
    "sg:address":"09128 Cagliari",
    "sg:city":"Cagliari",
    "sg:orig_category":"Automobili - Commercio",
    "sg:phone":"+39 070 499310",
    "sg:postcode":"09128",
    "sg:province":"Cagliari",
    "wof:name":"L'automobile Srl",
    "wof:placetype":"venue"
},
  "geometry": {"coordinates":[9.12254,39.223331],"type":"Point"}
}