{
  "type": "Feature",
  "properties": {
    "addr:full":"00198 Roma Roma Roma 00198",
    "addr:postcode":"00198;00198",
    "iso:country":"IT",
    "sg:address":"00198 Roma",
    "sg:city":"Roma",
    "sg:orig_category":"Forniture Per Edilizia E Lavori Pubblici. Prodotti Vari In Metallo",
    "sg:phone":"+39 06 884 1225",
    "sg:postcode":"00198",
    "sg:province":"Roma",
    "wof:name":"Metalmeccanica Fracasso Spa",
    "wof:placetype":"venue"
},
  "geometry": {"coordinates":[12.5013036728,41.9127807617],"type":"Point"}
}