{
  "type": "Feature",
  "properties": {
    "addr:full":"Via Roma 3 33070 Polcenigo Polcenigo Pordenone 33070",
    "addr:housenumber":"3",
    "addr:postcode":"33070;33070",
    "addr:street":"Via Roma",
    "iso:country":"IT",
    "sg:address":"Via Roma 3 33070 Polcenigo",
    "sg:city":"Polcenigo",
    "sg:classifiers":[
        {
            "category":"Real Estate",
            "subcategory":"Real Estate Operator",
            "type":"Services"
        }
    ],
    "sg:phone":"+39 0434 74072",
    "sg:postcode":"33070",
    "sg:province":"Pordenone",
    "sg:tags":[
        "flat",
        "working",
        "glass"
    ],
    "sg:website":"www.eot.it",
    "wof:name":"E.o.t. Impresa Individuale",
    "wof:placetype":"venue"
},
  "geometry": {"coordinates":[12.655043602,45.9626502991],"type":"Point"}
}