{
  "type": "Feature",
  "properties": {
    "addr:full":"35030 Selvazzano Dentro Selvazzano Dentro Padova 35030",
    "addr:postcode":"35030;35030",
    "iso:country":"IT",
    "sg:address":"35030 Selvazzano Dentro",
    "sg:city":"Selvazzano Dentro",
    "sg:orig_category":"Prodotti E Manufatti In Gomma. Forniture Per Attivita' Industriali",
    "sg:phone":"+39 049 630646",
    "sg:postcode":"35030",
    "sg:province":"Padova",
    "wof:name":"Nuova Singum Srl",
    "wof:placetype":"venue"
},
  "geometry": {"coordinates":[11.8156881332,45.4037818909],"type":"Point"}
}