{
  "type": "Feature",
  "properties": {
    "iso:country":"IT",
    "sg:address":"6, Via Ugo La Malfa 43013 Langhirano",
    "sg:city":"Langhirano",
    "sg:classifiers":[
        {
            "category":"Wholesale",
            "subcategory":"Medical Equipment & Supplies",
            "type":"Manufacturing & Wholesale Goods"
        }
    ],
    "sg:phone":"+39 0521 637133",
    "sg:postcode":"43013",
    "sg:province":"Parma",
    "sg:tags":[
        "-",
        "health",
        "instrument"
    ],
    "wof:name":"Ca.mi. (s.n.c.)",
    "wof:placetype":"venue"
},
  "geometry": {"coordinates":[10.290971,44.682995],"type":"Point"}
}