{
  "type": "Feature",
  "properties": {
    "iso:country":"IT",
    "sg:address":"20147 Milano",
    "sg:city":"Milano",
    "sg:orig_category":"Automobili E Mezzi Di Trasporto",
    "sg:phone":"+39 02 418741",
    "sg:postcode":"20147",
    "sg:province":"Milano",
    "sg:website":"http://www.ambros-saro.bmw.it",
    "wof:name":"Ambros Saro Spa",
    "wof:placetype":"venue"
},
  "geometry": {"coordinates":[9.136154,45.459866],"type":"Point"}
}