{
  "type": "Feature",
  "properties": {
    "iso:country":"IT",
    "sg:address":"36016 Thiene",
    "sg:city":"Thiene",
    "sg:orig_category":"Servizi Ausiliari Dei Mezzi Di Trasporto",
    "sg:phone":"+39 0445 362090",
    "sg:postcode":"36016",
    "sg:province":"Vicenza",
    "wof:name":"Gas Auto Perdoncin Domenico",
    "wof:placetype":"venue"
},
  "geometry": {"coordinates":[11.466057,45.72702],"type":"Point"}
}