{
  "type": "Feature",
  "properties": {
    "addr:full":"20121 Milano Milano Milano 20121",
    "addr:postcode":"20121;20121",
    "iso:country":"IT",
    "sg:address":"20121 Milano",
    "sg:city":"Milano",
    "sg:orig_category":"Scuole E Servizi Scolastici. Alberghi E Strutture Extra Alberghiere",
    "sg:phone":"+39 02 2900 0164",
    "sg:postcode":"20121",
    "sg:province":"Milano",
    "wof:name":"Acisjf Protezione Della Giovane",
    "wof:placetype":"venue"
},
  "geometry": {"coordinates":[9.186108,45.479572],"type":"Point"}
}