{
  "type": "Feature",
  "properties": {
    "iso:country":"IT",
    "sg:address":"70023 Gioia Del Colle",
    "sg:city":"Gioia del Colle",
    "sg:orig_category":"Lattiero Casearia Industria - Macchine",
    "sg:phone":"+39 080 348 2194",
    "sg:postcode":"70023",
    "sg:province":"Bari",
    "wof:name":"Teknomilk Srl",
    "wof:placetype":"venue"
},
  "geometry": {"coordinates":[16.888643,40.765903],"type":"Point"}
}