{
  "type": "Feature",
  "properties": {
    "iso:country":"IT",
    "sg:address":"08100 Nuoro",
    "sg:city":"Nuoro",
    "sg:orig_category":"Macchine, Impianti E Forniture Per Industria Grafica, Cartaria E Cartotecnica. Automazione E Macchine Per Ufficio",
    "sg:phone":"+39 0784 35104",
    "sg:postcode":"08100",
    "sg:province":"Nuoro",
    "wof:name":"Eliografia Tore",
    "wof:placetype":"venue"
},
  "geometry": {"coordinates":[9.300736,40.321114],"type":"Point"}
}