{
  "type": "Feature",
  "properties": {
    "iso:country":"IT",
    "sg:address":"11, V. Donatello 10071 Borgaro",
    "sg:classifiers":[
        {
            "category":"Manufacturing",
            "subcategory":"Metals",
            "type":"Manufacturing & Wholesale Goods"
        }
    ],
    "sg:phone":"+39 011 222 2096",
    "sg:postcode":"10071",
    "sg:province":"Torino",
    "sg:tags":[
        "metallurgy",
        "metalworking"
    ],
    "sg:website":"http://www.paginegialle.it/deltaacciai",
    "wof:name":"Delta Acciai Inox",
    "wof:placetype":"venue"
},
  "geometry": {"coordinates":[7.6877675056,45.13489151],"type":"Point"}
}