{
  "type": "Feature",
  "properties": {
    "addr:full":"00192 Roma Roma Roma 00192",
    "addr:postcode":"00192;00192",
    "iso:country":"IT",
    "sg:address":"00192 Roma",
    "sg:city":"Roma",
    "sg:orig_category":"Cine-foto-ottica. Articoli Medico-sanitari Ed Ortopedici",
    "sg:phone":"+39 06 3600 3291",
    "sg:postcode":"00192",
    "sg:province":"Roma",
    "wof:name":"Mito Di P. Ciocari",
    "wof:placetype":"venue"
},
  "geometry": {"coordinates":[12.469826,41.909081],"type":"Point"}
}