{
  "type": "Feature",
  "properties": {
    "iso:country":"IT",
    "sg:address":"53042 Chianciano Terme",
    "sg:city":"Chianciano Terme",
    "sg:orig_category":"Alberghi E Strutture Extra Alberghiere. Ospedali E Servizi Sanitari",
    "sg:phone":"+39 0578 63434",
    "sg:postcode":"53042",
    "sg:province":"Siena",
    "wof:name":"Albergo La Primula",
    "wof:placetype":"venue"
},
  "geometry": {"coordinates":[11.817022,43.048016],"type":"Point"}
}