{
  "type": "Feature",
  "properties": {
    "addr:full":"10015 Ivrea Ivrea Torino 10015",
    "addr:postcode":"10015;10015",
    "iso:country":"IT",
    "sg:address":"10015 Ivrea",
    "sg:city":"Ivrea",
    "sg:orig_category":"Pubblica Amministrazione",
    "sg:phone":"+39 0125 48096",
    "sg:postcode":"10015",
    "sg:province":"Torino",
    "wof:name":"Comune Di Ivrea",
    "wof:placetype":"venue"
},
  "geometry": {"coordinates":[7.9038648605,45.4502830505],"type":"Point"}
}