{
  "type": "Feature",
  "properties": {
    "addr:full":"00142 Roma Roma Roma 00142",
    "addr:postcode":"00142;00142",
    "iso:country":"IT",
    "sg:address":"00142 Roma",
    "sg:city":"Roma",
    "sg:orig_category":"Forniture Per Agricoltura E Zootecnia. Animali Domestici",
    "sg:phone":"+39 06 519 2206",
    "sg:postcode":"00142",
    "sg:province":"Roma",
    "wof:name":"Animal Store Di De Vivo Michela",
    "wof:placetype":"venue"
},
  "geometry": {"coordinates":[12.487323761,41.8276519775],"type":"Point"}
}