{
  "type": "Feature",
  "properties": {
    "iso:country":"IT",
    "sg:address":"27100 Pavia",
    "sg:city":"Pavia",
    "sg:orig_category":"Ingrassatori E Oliatori",
    "sg:phone":"+39 0382 575996",
    "sg:postcode":"27100",
    "sg:province":"Pavia",
    "sg:website":"http://www.junior-plast.it",
    "wof:name":"Junior Plast Snc Di Durio Franco & C.",
    "wof:placetype":"venue"
},
  "geometry": {"coordinates":[9.172483,45.202644],"type":"Point"}
}