{
  "type": "Feature",
  "properties": {
    "iso:country":"IT",
    "sg:address":"Via Bizzarri Loc.bargellino 21 40012 Calderara Di Reno",
    "sg:city":"Bargellino",
    "sg:orig_category":"Fittings For Ventilating Pipes",
    "sg:postcode":"40012",
    "sg:province":"Bologna",
    "sg:website":"www.manuli.it",
    "wof:name":"Manuli Refrigeration Connectors Spa",
    "wof:placetype":"venue"
},
  "geometry": {"coordinates":[11.3464813232,44.4942207336],"type":"Point"}
}