{
  "type": "Feature",
  "properties": {
    "addr:full":"Via Consorziale Traversa 22074 Lomazzo Lomazzo Como 22074",
    "addr:postcode":"22074;22074",
    "addr:street":"Via Consorziale Traversa",
    "iso:country":"IT",
    "sg:address":"Via Consorziale Traversa 22074 Lomazzo",
    "sg:city":"Lomazzo",
    "sg:classifiers":[
        {
            "category":"Shopping",
            "subcategory":"Stationery & Office Supplies",
            "type":"Retail Goods"
        }
    ],
    "sg:phone":"+39 02 9677 9085",
    "sg:postcode":"22074",
    "sg:province":"Como",
    "sg:tags":[
        "professional"
    ],
    "wof:name":"C.i.f.a. (s.r.l.)",
    "wof:placetype":"venue"
},
  "geometry": {"coordinates":[9.0854558945,45.8119659424],"type":"Point"}
}