{
  "type": "Feature",
  "properties": {
    "iso:country":"IT",
    "sg:address":"15059 Monleale",
    "sg:city":"Monleale",
    "sg:orig_category":"Bagno - Accessori E Mobili",
    "sg:phone":"+39 0131 80337",
    "sg:postcode":"15059",
    "sg:province":"Alessandria",
    "wof:name":"Ceramiche Davico",
    "wof:placetype":"venue"
},
  "geometry": {"coordinates":[8.975,44.885315],"type":"Point"}
}