{
  "type": "Feature",
  "properties": {
    "addr:full":"10139 Torino Torino Torino 10139",
    "addr:postcode":"10139;10139",
    "iso:country":"IT",
    "sg:address":"10139 Torino",
    "sg:city":"Torino",
    "sg:orig_category":"Prodotti Chimici Di Base. Forniture Per Attivita' Industriali",
    "sg:phone":"+39 011 748465",
    "sg:postcode":"10139",
    "sg:province":"Torino",
    "wof:name":"Mac Spa",
    "wof:placetype":"venue"
},
  "geometry": {"coordinates":[7.6414279938,45.0708465576],"type":"Point"}
}