{
  "type": "Feature",
  "properties": {
    "addr:full":"25121 Brescia Brescia Brescia 25121",
    "addr:postcode":"25121;25121",
    "iso:country":"IT",
    "sg:address":"25121 Brescia",
    "sg:city":"Brescia",
    "sg:orig_category":"Arredamenti E Mobili Professionali. Complementi Di Arredamento",
    "sg:phone":"+39 030 44510",
    "sg:postcode":"25121",
    "sg:province":"Brescia",
    "sg:website":"http://www.novalibandiere.it",
    "wof:name":"Novali Egidio Di Novali A. & C. Snc",
    "wof:placetype":"venue"
},
  "geometry": {"coordinates":[10.223327,45.537201],"type":"Point"}
}