{
  "type": "Feature",
  "properties": {
    "iso:country":"IT",
    "sg:address":"20144 Milano",
    "sg:city":"Milano",
    "sg:orig_category":"Materiali Edili",
    "sg:phone":"+39 02 2641 2508",
    "sg:postcode":"20144",
    "sg:province":"Milano",
    "wof:name":"Acim Srl",
    "wof:placetype":"venue"
},
  "geometry": {"coordinates":[9.163064,45.460228],"type":"Point"}
}