{
  "type": "Feature",
  "properties": {
    "addr:full":"48012 Bagnacavallo Bagnacavallo Ravenna 48012",
    "addr:postcode":"48012;48012",
    "iso:country":"IT",
    "sg:address":"48012 Bagnacavallo",
    "sg:city":"Bagnacavallo",
    "sg:orig_category":"Cavi E Conduttori Elettrici E Telefonici",
    "sg:phone":"+39 0545 60470",
    "sg:postcode":"48012",
    "sg:province":"Ravenna",
    "wof:name":"I.t.c. Industria Tecnica Cavi Srl",
    "wof:placetype":"venue"
},
  "geometry": {"coordinates":[11.999666,44.409924],"type":"Point"}
}