{
  "type": "Feature",
  "properties": {
    "addr:full":"Raiano; 67027 L'Aquila 67027",
    "addr:postcode":"67027;67027",
    "iso:country":"IT",
    "sg:address":"Raiano; 67027",
    "sg:classifiers":[
        {
            "category":"Banks & Credit Unions",
            "subcategory":"Bank",
            "type":"Services"
        }
    ],
    "sg:phone":"+39 0864 72284",
    "sg:postcode":"67027",
    "sg:province":"L'Aquila",
    "wof:name":"Cassa Di Risparmio Della, Provincia Dell'aquila",
    "wof:placetype":"venue"
},
  "geometry": {"coordinates":[13.810034,42.094814],"type":"Point"}
}