{
  "type": "Feature",
  "properties": {
    "iso:country":"IT",
    "sg:address":"00176 Roma",
    "sg:city":"Roma",
    "sg:orig_category":"Ospedali E Servizi Sanitari",
    "sg:phone":"+39 06 275 1689",
    "sg:postcode":"00176",
    "sg:province":"Roma",
    "wof:name":"Ve. Di. Radiologia Srl",
    "wof:placetype":"venue"
},
  "geometry": {"coordinates":[12.53472,41.883167],"type":"Point"}
}