{
  "type": "Feature",
  "properties": {
    "addr:full":"00191 Roma Roma Roma 00191",
    "addr:postcode":"00191;00191",
    "iso:country":"IT",
    "sg:address":"00191 Roma",
    "sg:city":"Roma",
    "sg:orig_category":"Alimentari - Vendita Al Dettaglio",
    "sg:phone":"+39 06 333 2971",
    "sg:postcode":"00191",
    "sg:province":"Roma",
    "wof:name":"Saporid\u00cc Srl",
    "wof:placetype":"venue"
},
  "geometry": {"coordinates":[12.476867,41.947872],"type":"Point"}
}