{
  "type": "Feature",
  "properties": {
    "addr:full":"Via Vittorio Veneto 50; Brugherio; 20047 Brugherio Milano 20047",
    "addr:housenumber":"50",
    "addr:postcode":"20047;20047",
    "addr:street":"Via Vittorio Veneto",
    "iso:country":"IT",
    "sg:address":"Via Vittorio Veneto 50; Brugherio; 20047",
    "sg:city":"Brugherio",
    "sg:classifiers":[
        {
            "category":"Banks & Credit Unions",
            "subcategory":"Bank",
            "type":"Services"
        }
    ],
    "sg:phone":"+39 039 287 3303",
    "sg:postcode":"20047",
    "sg:province":"Milano",
    "wof:name":"Istituto Bancario, San Paolo Di Torino Spa",
    "wof:placetype":"venue"
},
  "geometry": {"coordinates":[9.29889,45.553009],"type":"Point"}
}