{
  "type": "Feature",
  "properties": {
    "iso:country":"IT",
    "sg:address":"00148 Roma",
    "sg:city":"Roma",
    "sg:orig_category":"Trasporti E Spedizioni Merci",
    "sg:phone":"+39 06 6567 0582",
    "sg:postcode":"00148",
    "sg:province":"Roma",
    "wof:name":"Goeldlin Transport Srl",
    "wof:placetype":"venue"
},
  "geometry": {"coordinates":[12.4086227417,41.8217468262],"type":"Point"}
}