{
  "type": "Feature",
  "properties": {
    "addr:full":"Via Delle Suore 305 41100 Modena Modena Modena 41100",
    "addr:housenumber":"305",
    "addr:postcode":"41100;41100",
    "addr:street":"Via Delle Suore",
    "iso:country":"IT",
    "sg:address":"Via Delle Suore 305 41100 Modena",
    "sg:city":"Modena",
    "sg:classifiers":[
        {
            "category":"Airport",
            "type":"Transportation"
        }
    ],
    "sg:phone":"+39 059 314101",
    "sg:postcode":"41100",
    "sg:province":"Modena",
    "sg:tags":[
        "device",
        "equipment"
    ],
    "sg:website":"www.ata-modena.com",
    "wof:name":"Ata Srl",
    "wof:placetype":"venue"
},
  "geometry": {"coordinates":[10.916505,44.66304],"type":"Point"}
}