{
  "type": "Feature",
  "properties": {
    "addr:full":"32, Via Veclezio 47100 Forli' Forl\u00ec-Cesena 47100",
    "addr:postcode":"47100;47100",
    "addr:street":"Via Veclezio;Forli ' Forli\u0300-Cesena",
    "iso:country":"IT",
    "sg:address":"32, Via Veclezio 47100 Forli'",
    "sg:classifiers":[
        {
            "category":"Personal",
            "subcategory":"Shoe Repair & Shine",
            "type":"Services"
        }
    ],
    "sg:phone":"+39 39054386314",
    "sg:postcode":"47100",
    "sg:province":"Forl\u00ec-Cesena",
    "sg:tags":[
        "leather"
    ],
    "wof:name":"Gardini",
    "wof:placetype":"venue"
},
  "geometry": {"coordinates":[12.020473,44.192474],"type":"Point"}
}