{
  "type": "Feature",
  "properties": {
    "addr:full":"00155 Roma Roma Roma 00155",
    "addr:postcode":"00155;00155",
    "iso:country":"IT",
    "sg:address":"00155 Roma",
    "sg:city":"Roma",
    "sg:orig_category":"Pubblicita', Marketing E Comunicazione",
    "sg:phone":"+39 06 4080 2412",
    "sg:postcode":"00155",
    "sg:province":"Roma",
    "wof:name":"Padovani Service S.r.l.",
    "wof:placetype":"venue"
},
  "geometry": {"coordinates":[12.5716571808,41.9106063843],"type":"Point"}
}