{
  "type": "Feature",
  "properties": {
    "iso:country":"IT",
    "sg:address":"13, Strada Del Pascolo 10156 Torino",
    "sg:city":"Torino",
    "sg:classifiers":[
        {
            "category":"Shopping",
            "subcategory":"Computers & Home Electronics",
            "type":"Retail Goods"
        }
    ],
    "sg:phone":"+39 011 273 4576",
    "sg:postcode":"10156",
    "sg:province":"Torino",
    "sg:tags":[
        "electronic",
        "electrical",
        "equipment"
    ],
    "wof:name":"Coragliotto Elettronica Automazione Di L. Coragliotto & C. (s.a.s.)",
    "wof:placetype":"venue"
},
  "geometry": {"coordinates":[7.724811,45.099243],"type":"Point"}
}