{
  "type": "Feature",
  "properties": {
    "addr:full":"09070 Bauladu Bauladu Oristano 09070",
    "addr:postcode":"09070;09070",
    "iso:country":"IT",
    "sg:address":"09070 Bauladu",
    "sg:city":"Bauladu",
    "sg:orig_category":"Materiali Edili",
    "sg:phone":"+39 0783 67503",
    "sg:postcode":"09070",
    "sg:province":"Oristano",
    "wof:name":"Arte Pietra Di Agus S. E C. Snc",
    "wof:placetype":"venue"
},
  "geometry": {"coordinates":[8.671849,40.02047],"type":"Point"}
}