{
  "type": "Feature",
  "properties": {
    "iso:country":"IT",
    "sg:address":"00161 Roma",
    "sg:city":"Roma",
    "sg:orig_category":"Cinematografia E Radiotelevisione",
    "sg:phone":"+39 06 4424 3039",
    "sg:postcode":"00161",
    "sg:province":"Roma",
    "wof:name":"S.e.fi.t. S.r.l.",
    "wof:placetype":"venue"
},
  "geometry": {"coordinates":[12.679975,41.702854],"type":"Point"}
}