{
  "type": "Feature",
  "properties": {
    "addr:full":"Via Xx Settembre 1; Terricciola; 56030 Terricciola Pisa 56030",
    "addr:housenumber":"1",
    "addr:postcode":"56030;56030",
    "addr:street":"Via Xx Settembre",
    "iso:country":"IT",
    "sg:address":"Via Xx Settembre 1; Terricciola; 56030",
    "sg:city":"Terricciola",
    "sg:classifiers":[
        {
            "category":"Banks & Credit Unions",
            "subcategory":"Bank",
            "type":"Services"
        }
    ],
    "sg:phone":"+39 0587 658520",
    "sg:postcode":"56030",
    "sg:province":"Pisa",
    "wof:name":"Banca Toscana Spa",
    "wof:placetype":"venue"
},
  "geometry": {"coordinates":[10.676411,43.523922],"type":"Point"}
}