{
  "type": "Feature",
  "properties": {
    "iso:country":"IT",
    "sg:address":"25055 Pisogne",
    "sg:city":"Pisogne",
    "sg:orig_category":"Materiali Edili",
    "sg:phone":"+39 036 488 0430",
    "sg:postcode":"25055",
    "sg:province":"Brescia",
    "wof:name":"Lavorazione Gessi Speciali La.ge.s. S.p.a.",
    "wof:placetype":"venue"
},
  "geometry": {"coordinates":[10.204579,45.566635],"type":"Point"}
}