{
  "type": "Feature",
  "properties": {
    "iso:country":"IT",
    "sg:address":"22079 Villa Guardia",
    "sg:city":"Villa Guardia",
    "sg:orig_category":"Servizi E Lavori Per Abbigliamento E Pelletterie",
    "sg:phone":"+39 031 480768",
    "sg:postcode":"22079",
    "sg:province":"Como",
    "wof:name":"Biondi Claudio",
    "wof:placetype":"venue"
},
  "geometry": {"coordinates":[9.026309,45.775028],"type":"Point"}
}