{
  "type": "Feature",
  "properties": {
    "iso:country":"IT",
    "sg:address":"37045 Legnago",
    "sg:city":"Legnago",
    "sg:orig_category":"Materiali E Componenti Elettrotecnici",
    "sg:phone":"+39 0442 25428",
    "sg:postcode":"37045",
    "sg:province":"Verona",
    "wof:name":"Elettrocablo Di Menegazzi C. & M. Snc",
    "wof:placetype":"venue"
},
  "geometry": {"coordinates":[11.338432,45.200233],"type":"Point"}
}