{
  "type": "Feature",
  "properties": {
    "addr:full":"41100 Modena Modena Modena 41100",
    "addr:postcode":"41100;41100",
    "iso:country":"IT",
    "sg:address":"41100 Modena",
    "sg:city":"Modena",
    "sg:orig_category":"Forniture Per Edilizia E Lavori Pubblici. Forniture Per Attivita' Industriali",
    "sg:phone":"+39 059 251364",
    "sg:postcode":"41100",
    "sg:province":"Modena",
    "wof:name":"Modelleria Fratelli Bagatti Di Bagatti Evelino E C. Snc",
    "wof:placetype":"venue"
},
  "geometry": {"coordinates":[10.9244880676,44.5478820801],"type":"Point"}
}