{
  "type": "Feature",
  "properties": {
    "iso:country":"IT",
    "sg:address":"70122 Bari",
    "sg:city":"Bari",
    "sg:orig_category":"Dentisti Medici Chirurghi Ed Odontoiatri",
    "sg:phone":"+39 080 524 2939",
    "sg:postcode":"70122",
    "sg:province":"Bari",
    "wof:name":"Gadaleta Patrizia",
    "wof:placetype":"venue"
},
  "geometry": {"coordinates":[16.865681,41.120262],"type":"Point"}
}