{
  "type": "Feature",
  "properties": {
    "addr:full":"Piazza Venticinque Aprile 1 20121 Milano Milano Milano 20121",
    "addr:housenumber":"1",
    "addr:postcode":"20121;20121",
    "addr:street":"Piazza Venticinque Aprile",
    "iso:country":"IT",
    "sg:address":"Piazza Venticinque Aprile 1 20121 Milano",
    "sg:city":"Milano",
    "sg:classifiers":[
        {
            "category":"Military Area",
            "subcategory":"Air Force Base",
            "type":"Public Place"
        }
    ],
    "sg:phone":"+39 02 659 8282",
    "sg:postcode":"20121",
    "sg:province":"Milano",
    "sg:tags":[
        "equipment",
        "safety",
        "system"
    ],
    "sg:website":"www.rapitron.it",
    "wof:name":"Rapitron Srl",
    "wof:placetype":"venue"
},
  "geometry": {"coordinates":[9.203226,45.482468],"type":"Point"}
}