{
  "type": "Feature",
  "properties": {
    "addr:full":"80049 Somma Vesuviana Somma Vesuviana Napoli 80049",
    "addr:postcode":"80049;80049",
    "iso:country":"IT",
    "sg:address":"80049 Somma Vesuviana",
    "sg:city":"Somma Vesuviana",
    "sg:orig_category":"Articoli Medico-sanitari Ed Ortopedici",
    "sg:phone":"+39 081 899 2166",
    "sg:postcode":"80049",
    "sg:province":"Napoli",
    "wof:name":"Coppola Antonio - Guido Simplex",
    "wof:placetype":"venue"
},
  "geometry": {"coordinates":[14.431424,40.872128],"type":"Point"}
}