{
  "type": "Feature",
  "properties": {
    "addr:full":"10127 Torino Torino Torino 10127",
    "addr:postcode":"10127;10127",
    "iso:country":"IT",
    "sg:address":"10127 Torino",
    "sg:city":"Torino",
    "sg:orig_category":"Forniture Per Attivita' Industriali",
    "sg:phone":"+39 011 667 0145",
    "sg:postcode":"10127",
    "sg:province":"Torino",
    "wof:name":"Star",
    "wof:placetype":"venue"
},
  "geometry": {"coordinates":[7.6610913277,45.0220832825],"type":"Point"}
}