{
  "type": "Feature",
  "properties": {
    "addr:full":"Strada Provinciale 135 84091 Battipaglia Battipaglia Salerno 84091",
    "addr:housenumber":"135",
    "addr:postcode":"84091;84091",
    "addr:street":"Strada Provinciale",
    "iso:country":"IT",
    "sg:address":"Strada Provinciale 135 84091 Battipaglia",
    "sg:city":"Battipaglia",
    "sg:classifiers":[
        {
            "category":"Shopping",
            "subcategory":"Computers & Home Electronics",
            "type":"Retail Goods"
        }
    ],
    "sg:phone":"+39 0828 370555",
    "sg:postcode":"84091",
    "sg:province":"Salerno",
    "sg:tags":[
        "electronic",
        "electrical",
        "equipment"
    ],
    "wof:name":"Fibre Ottiche Sud (s.p.a.)",
    "wof:placetype":"venue"
},
  "geometry": {"coordinates":[14.765912,40.677956],"type":"Point"}
}