{
  "type": "Feature",
  "properties": {
    "iso:country":"IT",
    "sg:address":"20123 Milano",
    "sg:city":"Milano",
    "sg:orig_category":"Ricerca, Selezione E Formazione Del Personale",
    "sg:phone":"+39 02 8645 0077",
    "sg:postcode":"20123",
    "sg:province":"Milano",
    "sg:website":"http://www.iocap.it",
    "wof:name":"Iocap Srl",
    "wof:placetype":"venue"
},
  "geometry": {"coordinates":[9.184038,45.46003],"type":"Point"}
}