{
  "type": "Feature",
  "properties": {
    "addr:full":"80131 Napoli Napoli Napoli 80131",
    "addr:housenumber":"80131",
    "addr:postcode":"80131",
    "iso:country":"IT",
    "sg:address":"80131 Napoli",
    "sg:city":"Napoli",
    "sg:orig_category":"Non-classified Establishments",
    "sg:phone":"+39 081 743 3124",
    "sg:postcode":"80131",
    "sg:province":"Napoli",
    "wof:name":"Cadema Carta Da Parati",
    "wof:placetype":"venue"
},
  "geometry": {"coordinates":[14.236,40.868546],"type":"Point"}
}