{
  "type": "Feature",
  "properties": {
    "iso:country":"IT",
    "sg:address":"59013 Montemurlo",
    "sg:city":"Montemurlo",
    "sg:classifiers":[
        {
            "category":"Manufacturing",
            "subcategory":"Tools & Machinery",
            "type":"Manufacturing & Wholesale Goods"
        }
    ],
    "sg:phone":"+39 0574 683090",
    "sg:postcode":"59013",
    "sg:province":"Prato",
    "sg:tags":[
        "leather",
        "equipment",
        "goods",
        "clothing"
    ],
    "wof:name":"S.b.r. Srl",
    "wof:placetype":"venue"
},
  "geometry": {"coordinates":[11.035792,43.906815],"type":"Point"}
}