{
  "type": "Feature",
  "properties": {
    "addr:full":"45, Via Sotto Rive 33048 San Giovanni Al Natisone San Giovanni al Natisone Udine 33048",
    "addr:postcode":"33048;33048",
    "addr:street":"Via Sotto Rive",
    "iso:country":"IT",
    "sg:address":"45, Via Sotto Rive 33048 San Giovanni Al Natisone",
    "sg:city":"San Giovanni al Natisone",
    "sg:classifiers":[
        {
            "category":"Home & Garden",
            "subcategory":"Home Furnishings",
            "type":"Retail Goods"
        }
    ],
    "sg:phone":"+39 0432 756348",
    "sg:postcode":"33048",
    "sg:province":"Udine",
    "sg:tags":[
        "household"
    ],
    "wof:name":"B.b.c. Di Bosco E Caucig (s.n.c.)",
    "wof:placetype":"venue"
},
  "geometry": {"coordinates":[13.421333,45.976002],"type":"Point"}
}