{
  "type": "Feature",
  "properties": {
    "iso:country":"IT",
    "sg:address":"20/22, V. Badia 25060 Cellatica",
    "sg:city":"Cellatica",
    "sg:classifiers":[
        {
            "category":"Food & Beverages",
            "subcategory":"Groceries & Convenience Stores",
            "type":"Retail Goods"
        }
    ],
    "sg:phone":"+39 030 373 0298",
    "sg:postcode":"25060",
    "sg:province":"Brescia",
    "sg:tags":[
        "drink"
    ],
    "sg:website":"http://www.gmariani.it",
    "wof:name":"Mariani G. & C. Srl",
    "wof:placetype":"venue"
},
  "geometry": {"coordinates":[10.168253,45.557659],"type":"Point"}
}