{
  "type": "Feature",
  "properties": {
    "addr:full":"1, Via Papini Giovanni 51037 Montale Montale Pistoia 51037",
    "addr:postcode":"51037;51037",
    "addr:street":"Via Papini Giovanni",
    "iso:country":"IT",
    "sg:address":"1, Via Papini Giovanni 51037 Montale",
    "sg:city":"Montale",
    "sg:classifiers":[
        {
            "category":"Shopping",
            "subcategory":"Crafts & Fabrics",
            "type":"Retail Goods"
        }
    ],
    "sg:phone":"+39 39057355275",
    "sg:postcode":"51037",
    "sg:province":"Pistoia",
    "wof:name":"Sifim Di Lenzi E C Snc",
    "wof:placetype":"venue"
},
  "geometry": {"coordinates":[10.9185237885,43.9321556091],"type":"Point"}
}