{
  "type": "Feature",
  "properties": {
    "iso:country":"IT",
    "sg:address":"22063 Cantu'",
    "sg:orig_category":"Accessori Moda D'abbigliamento. Forniture Per Abbigliamento E Pelletterie",
    "sg:phone":"+39 031 712265",
    "sg:postcode":"22063",
    "sg:province":"Como",
    "wof:name":"Cooperativa Produzione Merletti",
    "wof:placetype":"venue"
},
  "geometry": {"coordinates":[9.126745,45.737209],"type":"Point"}
}