{
  "type": "Feature",
  "properties": {
    "iso:country":"IT",
    "sg:address":"24049 Verdello",
    "sg:city":"Verdello",
    "sg:orig_category":"Bagno - Accessori E Mobili",
    "sg:phone":"+39 035 884622",
    "sg:postcode":"24049",
    "sg:province":"Bergamo",
    "sg:website":"http://www.dielleceramiche.it",
    "wof:name":"Dielle Ceramiche Spa",
    "wof:placetype":"venue"
},
  "geometry": {"coordinates":[9.628035,45.648403],"type":"Point"}
}