{
  "type": "Feature",
  "properties": {
    "iso:country":"IT",
    "sg:address":"56025 Pontedera",
    "sg:city":"Pontedera",
    "sg:orig_category":"Arredo Bagno Ed Idrosanitari. Complementi Di Arredamento. Vetro: Prodotti E Lavorazioni",
    "sg:phone":"+39 0587 59280",
    "sg:postcode":"56025",
    "sg:province":"Pisa",
    "wof:name":"Ferrini Rossana",
    "wof:placetype":"venue"
},
  "geometry": {"coordinates":[10.395515,43.714615],"type":"Point"}
}