{
  "type": "Feature",
  "properties": {
    "iso:country":"IT",
    "sg:address":"70123 Palese Macchie",
    "sg:city":"Bari",
    "sg:orig_category":"Non-classified Establishments",
    "sg:phone":"+39 080 531 4132",
    "sg:postcode":"70123",
    "sg:province":"Bari",
    "wof:name":"Sanigen (s.p.a.)",
    "wof:placetype":"venue"
},
  "geometry": {"coordinates":[16.835537,41.122498],"type":"Point"}
}