{
  "type": "Feature",
  "properties": {
    "iso:country":"IT",
    "sg:address":"96100 Siracusa",
    "sg:city":"Siracusa",
    "sg:orig_category":"Agenzie Ed Enti Turistici. Consulenze Tecniche, Amministrative E Perizie",
    "sg:phone":"+39 0931 414123",
    "sg:postcode":"96100",
    "sg:province":"Siracusa",
    "wof:name":"Signorello Prof. Vito",
    "wof:placetype":"venue"
},
  "geometry": {"coordinates":[15.280898,37.080635],"type":"Point"}
}