{
  "type": "Feature",
  "properties": {
    "iso:country":"IT",
    "sg:address":"3, Via Trivulzio Antonio Tolomeo 20146 Milano",
    "sg:city":"Milano",
    "sg:classifiers":[
        {
            "category":"Parking",
            "subcategory":"Lot",
            "type":"Transportation"
        }
    ],
    "sg:phone":"+39 39024385061",
    "sg:postcode":"20146",
    "sg:province":"Milano",
    "sg:tags":[
        "transport",
        "road"
    ],
    "wof:name":"Actom Srl",
    "wof:placetype":"venue"
},
  "geometry": {"coordinates":[9.147508,45.466228],"type":"Point"}
}