{
  "type": "Feature",
  "properties": {
    "iso:country":"IT",
    "sg:address":"00040 Pomezia",
    "sg:city":"Pomezia",
    "sg:orig_category":"Archeologia E Beni Culturali - Servizi E Lavori",
    "sg:phone":"+39 06 912 3222",
    "sg:postcode":"00040",
    "sg:province":"Roma",
    "wof:name":"Office System Srl",
    "wof:placetype":"venue"
},
  "geometry": {"coordinates":[12.495059,41.690483],"type":"Point"}
}