{
  "type": "Feature",
  "properties": {
    "addr:full":"Via Monte Bianco 14 22079 Villa Guardia Villa Guardia Como 22079",
    "addr:housenumber":"14;guardia",
    "addr:postcode":"22079;22079",
    "addr:street":"Via Monte Bianco;Guardia",
    "iso:country":"IT",
    "sg:address":"Via Monte Bianco 14 22079 Villa Guardia",
    "sg:city":"Villa Guardia",
    "sg:classifiers":[
        {
            "category":"Manufacturing",
            "subcategory":"Textiles",
            "type":"Manufacturing & Wholesale Goods"
        }
    ],
    "sg:phone":"+39 031 480162",
    "sg:postcode":"22079",
    "sg:province":"Como",
    "sg:tags":[
        "non-woven",
        "industrial",
        "fabric",
        "processing"
    ],
    "wof:name":"Leucadia Spa",
    "wof:placetype":"venue"
},
  "geometry": {"coordinates":[9.014606,45.767525],"type":"Point"}
}