{
  "type": "Feature",
  "properties": {
    "addr:full":"4, Via Bonsignora 21052 Busto Arsizio Busto Arsizio Varese 21052",
    "addr:postcode":"21052;21052",
    "addr:street":"Via Bonsignora",
    "iso:country":"IT",
    "sg:address":"4, Via Bonsignora 21052 Busto Arsizio",
    "sg:city":"Busto Arsizio",
    "sg:classifiers":[
        {
            "category":"Manufacturing",
            "subcategory":"Glass & Minerals",
            "type":"Manufacturing & Wholesale Goods"
        }
    ],
    "sg:phone":"+39 0331 635001",
    "sg:postcode":"21052",
    "sg:province":"Varese",
    "sg:tags":[
        "building",
        "material"
    ],
    "wof:name":"Crivelli Giovanni (s.r.l.)",
    "wof:placetype":"venue"
},
  "geometry": {"coordinates":[8.822425,45.60722],"type":"Point"}
}