{
  "type": "Feature",
  "properties": {
    "iso:country":"IT",
    "sg:address":"67051 Avezzano",
    "sg:orig_category":"Servizi E Lavori Per Edilizia E Lavori Pubblici",
    "sg:phone":"+39 0863 415643",
    "sg:postcode":"67051",
    "sg:province":"L'Aquila",
    "wof:name":"Archeores Sas",
    "wof:placetype":"venue"
},
  "geometry": {"coordinates":[13.925507,42.044315],"type":"Point"}
}