{
  "type": "Feature",
  "properties": {
    "iso:country":"IT",
    "sg:address":"Via Roma, 39-41; Baricella; 40052",
    "sg:city":"Baricella",
    "sg:classifiers":[
        {
            "category":"Banks & Credit Unions",
            "subcategory":"Bank",
            "type":"Services"
        }
    ],
    "sg:phone":"+39 051 879133",
    "sg:postcode":"40052",
    "sg:province":"Bologna",
    "wof:name":"Banca Del Monte",
    "wof:placetype":"venue"
},
  "geometry": {"coordinates":[11.532137,44.645824],"type":"Point"}
}