{
  "type": "Feature",
  "properties": {
    "iso:country":"IT",
    "sg:address":"09124 Cagliari",
    "sg:city":"Cagliari",
    "sg:orig_category":"Non-classified Establishments",
    "sg:phone":"+39 070 669499",
    "sg:postcode":"09124",
    "sg:province":"Cagliari",
    "wof:name":"De Martini Antiquariato Di De Martini G. E C. Snc",
    "wof:placetype":"venue"
},
  "geometry": {"coordinates":[9.116068,39.218616],"type":"Point"}
}