{
  "type": "Feature",
  "properties": {
    "iso:country":"IT",
    "sg:address":"24, Via Duca D'aosta 10040 Caprie",
    "sg:city":"Caprie",
    "sg:classifiers":[
        {
            "category":"Professional",
            "subcategory":"Engineering",
            "type":"Services"
        }
    ],
    "sg:phone":"+39 011 963 2313",
    "sg:postcode":"10040",
    "sg:province":"Torino",
    "sg:tags":[
        "machine",
        "-",
        "mechanical"
    ],
    "wof:name":"I.c.m.a. (s.p.a.)",
    "wof:placetype":"venue"
},
  "geometry": {"coordinates":[7.350805,45.115479],"type":"Point"}
}