{
  "type": "Feature",
  "properties": {
    "iso:country":"IT",
    "sg:address":"31033 Castelfranco Veneto",
    "sg:city":"Castelfranco Veneto",
    "sg:orig_category":"Legno E Semilavorati",
    "sg:phone":"+39 0423 496047",
    "sg:postcode":"31033",
    "sg:province":"Treviso",
    "wof:name":"Marin Gino Spa",
    "wof:placetype":"venue"
},
  "geometry": {"coordinates":[11.927566,45.691593],"type":"Point"}
}