{
  "type": "Feature",
  "properties": {
    "addr:full":"40050 Argelato Argelato Bologna 40050",
    "addr:postcode":"40050;40050",
    "iso:country":"IT",
    "sg:address":"40050 Argelato",
    "sg:city":"Argelato",
    "sg:orig_category":"Verniciatura A Fuoco E A Forno",
    "sg:phone":"+39 051 861407",
    "sg:postcode":"40050",
    "sg:province":"Bologna",
    "wof:name":"Bianchi Srl",
    "wof:placetype":"venue"
},
  "geometry": {"coordinates":[11.348926,44.642502],"type":"Point"}
}