{
  "type": "Feature",
  "properties": {
    "iso:country":"IT",
    "sg:address":"20050 Sovico",
    "sg:city":"Sovico",
    "sg:orig_category":"Molle - Produzione E Commercio",
    "sg:phone":"+39 039 201 3606",
    "sg:postcode":"20050",
    "sg:province":"Milano",
    "wof:name":"Mollificio Mariani Di Mariani & C. Sas",
    "wof:placetype":"venue"
},
  "geometry": {"coordinates":[9.195526123,45.4615898132],"type":"Point"}
}