{
  "type": "Feature",
  "properties": {
    "addr:full":"49, Strada Torino 10043 Orbassano Orbassano Torino 10043",
    "addr:postcode":"10043;10043",
    "addr:street":"Strada Torino",
    "iso:country":"IT",
    "sg:address":"49, Strada Torino 10043 Orbassano",
    "sg:city":"Orbassano",
    "sg:classifiers":[
        {
            "category":"Manufacturing",
            "subcategory":"Metals",
            "type":"Manufacturing & Wholesale Goods"
        }
    ],
    "sg:phone":"+39 011 903 2092",
    "sg:postcode":"10043",
    "sg:province":"Torino",
    "sg:tags":[
        "metallurgy",
        "metalworking"
    ],
    "wof:name":"Metfon Di Battistelli Luciano & C. (s.n.c.)",
    "wof:placetype":"venue"
},
  "geometry": {"coordinates":[7.5478730202,45.0084190369],"type":"Point"}
}