{
  "type": "Feature",
  "properties": {
    "iso:country":"IT",
    "sg:address":"Via Avogadro 3 70031 Andria",
    "sg:city":"Andria",
    "sg:classifiers":[
        {
            "category":"Shopping",
            "subcategory":"Clothing, Apparel, & Fashions",
            "type":"Retail Goods"
        }
    ],
    "sg:phone":"+39 0883 543011",
    "sg:postcode":"70031",
    "sg:province":"Bari",
    "sg:tags":[
        "shirt"
    ],
    "wof:name":"Fratelli Zingaro S.r.l.",
    "wof:placetype":"venue"
},
  "geometry": {"coordinates":[16.300745,41.219044],"type":"Point"}
}