{
  "type": "Feature",
  "properties": {
    "iso:country":"IT",
    "sg:address":"Via S. Micheli 43030 Torrile",
    "sg:classifiers":[
        {
            "category":"Manufacturing",
            "subcategory":"Glass & Minerals",
            "type":"Manufacturing & Wholesale Goods"
        }
    ],
    "sg:phone":"+39 0521 819723",
    "sg:postcode":"43030",
    "sg:province":"Parma",
    "wof:name":"Furlotti",
    "wof:placetype":"venue"
},
  "geometry": {"coordinates":[10.359793,44.88485],"type":"Point"}
}