{
  "type": "Feature",
  "properties": {
    "iso:country":"IT",
    "sg:address":"62014 Corridonia",
    "sg:city":"Corridonia",
    "sg:orig_category":"Calcestruzzo Preconfezionato",
    "sg:phone":"+39 0733 283130",
    "sg:postcode":"62014",
    "sg:province":"Macerata",
    "wof:name":"Concrete Service Srl",
    "wof:placetype":"venue"
},
  "geometry": {"coordinates":[13.482093,43.266571],"type":"Point"}
}