{
  "type": "Feature",
  "properties": {
    "iso:country":"IT",
    "sg:address":"Via Faini 11 25073 Bovezzo",
    "sg:city":"Bovezzo",
    "sg:classifiers":[
        {
            "category":"Government",
            "subcategory":"Post Office",
            "type":"Public Place"
        }
    ],
    "sg:phone":"+39 030 271 1218",
    "sg:postcode":"25073",
    "sg:province":"Brescia",
    "sg:tags":[
        "thermoformed",
        "parts",
        "plastic"
    ],
    "sg:website":"www.rosaplast.com",
    "wof:name":"Rosa Plast S.r.l.",
    "wof:placetype":"venue"
},
  "geometry": {"coordinates":[10.2460708618,45.5865325928],"type":"Point"}
}