{
  "type": "Feature",
  "properties": {
    "iso:country":"IT",
    "sg:address":"18/a, V. Collamarini 40138 Bologna",
    "sg:city":"Bologna",
    "sg:classifiers":[
        {
            "category":"Professional",
            "subcategory":"Engineering",
            "type":"Services"
        }
    ],
    "sg:phone":"+39 051 601 4842",
    "sg:postcode":"40138",
    "sg:province":"Bologna",
    "sg:tags":[
        "machine",
        "-",
        "mechanical"
    ],
    "sg:website":"http://www.tpack.it",
    "wof:name":"T Pack Srl",
    "wof:placetype":"venue"
},
  "geometry": {"coordinates":[11.398866,44.496426],"type":"Point"}
}