{
  "type": "Feature",
  "properties": {
    "iso:country":"IT",
    "sg:address":"33048 San Giovanni Natisone",
    "sg:orig_category":"Salotti, Poltrone, Sedie E Tavoli",
    "sg:phone":"+39 0432 758014",
    "sg:postcode":"33048",
    "sg:province":"Udine",
    "sg:website":"http://www.3emme.it",
    "wof:name":"Tre Emme Di Magrino & C. Sas",
    "wof:placetype":"venue"
},
  "geometry": {"coordinates":[13.166289,46.140797],"type":"Point"}
}