{
  "type": "Feature",
  "properties": {
    "addr:full":"20123 Milano Milano Milano 20123",
    "addr:postcode":"20123;20123",
    "iso:country":"IT",
    "sg:address":"20123 Milano",
    "sg:city":"Milano",
    "sg:orig_category":"Automazione E Macchine Per Ufficio",
    "sg:phone":"+39 02 4331 9036",
    "sg:postcode":"20123",
    "sg:province":"Milano",
    "wof:name":"I.p.s. Idee Progetti Soluzioni Srl",
    "wof:placetype":"venue"
},
  "geometry": {"coordinates":[9.169645,45.470371],"type":"Point"}
}