{
  "type": "Feature",
  "properties": {
    "addr:full":"32, Via Marenco Carlo 10126 Torino Torino Torino 10126",
    "addr:postcode":"10126;10126",
    "addr:street":"Via Marenco Carlo",
    "iso:country":"IT",
    "sg:address":"32, Via Marenco Carlo 10126 Torino",
    "sg:city":"Torino",
    "sg:classifiers":[
        {
            "category":"Manufacturing",
            "subcategory":"Printing",
            "type":"Manufacturing & Wholesale Goods"
        }
    ],
    "sg:phone":"+39 011 664 5601",
    "sg:postcode":"10126",
    "sg:province":"Torino",
    "sg:tags":[
        "publishing"
    ],
    "wof:name":"Editrice La Stampa S.p.a.",
    "wof:placetype":"venue"
},
  "geometry": {"coordinates":[7.6866188049,45.0705604553],"type":"Point"}
}