{
  "type": "Feature",
  "properties": {
    "addr:full":"Via Europa 37 25040 Monticelli Brusati Monticelli Brusati Brescia 25040",
    "addr:housenumber":"37",
    "addr:postcode":"25040;brusati;25040",
    "addr:street":"Via Europa;Brescia",
    "iso:country":"IT",
    "sg:address":"Via Europa 37 25040 Monticelli Brusati",
    "sg:city":"Monticelli Brusati",
    "sg:orig_category":"Cable Harness Layout Systems",
    "sg:phone":"+39 030 685 0351",
    "sg:postcode":"25040",
    "sg:province":"Brescia",
    "sg:website":"www.cfcablaggi.it",
    "wof:name":"Cf Cablaggi Snc",
    "wof:placetype":"venue"
},
  "geometry": {"coordinates":[10.076724,45.615864],"type":"Point"}
}