{
  "type": "Feature",
  "properties": {
    "iso:country":"IT",
    "sg:address":"17/a, Z.i. La Martella",
    "sg:city":"La Martella",
    "sg:classifiers":[
        {
            "category":"Home & Garden",
            "subcategory":"Home Furnishings",
            "type":"Retail Goods"
        }
    ],
    "sg:phone":"+39 0835 302211",
    "sg:postcode":"75100",
    "sg:province":"Matera",
    "sg:tags":[
        "household"
    ],
    "sg:website":"http://www.interlineitalia.com",
    "wof:name":"Interline Italia",
    "wof:placetype":"venue"
},
  "geometry": {"coordinates":[16.58198,40.673416],"type":"Point"}
}