{
  "type": "Feature",
  "properties": {
    "iso:country":"IT",
    "sg:address":"20017 Rho",
    "sg:city":"Rho",
    "sg:orig_category":"Abbigliamento Esterno, Maglierie E Pelliccerie",
    "sg:phone":"+39 02 931 6858",
    "sg:postcode":"20017",
    "sg:province":"Milano",
    "wof:name":"Carmen (s.n.c.)",
    "wof:placetype":"venue"
},
  "geometry": {"coordinates":[9.037096,45.527443],"type":"Point"}
}