{
  "type": "Feature",
  "properties": {
    "addr:full":"Via S. Lorenzo 01028 Orte Orte Viterbo 01028",
    "addr:postcode":"01028;01028",
    "addr:street":"Via S. Lorenzo",
    "iso:country":"IT",
    "sg:address":"Via S. Lorenzo 01028 Orte",
    "sg:city":"Orte",
    "sg:classifiers":[
        {
            "category":"Shopping",
            "subcategory":"Clothing, Apparel, & Fashions",
            "type":"Retail Goods"
        }
    ],
    "sg:phone":"+39 0761 402486",
    "sg:postcode":"01028",
    "sg:province":"Viterbo",
    "sg:tags":[
        "clothes"
    ],
    "wof:name":"Testa Teresa",
    "wof:placetype":"venue"
},
  "geometry": {"coordinates":[12.104854,42.417381],"type":"Point"}
}