{
  "type": "Feature",
  "properties": {
    "addr:full":"53100 Siena Siena Siena 53100",
    "addr:postcode":"53100;53100",
    "iso:country":"IT",
    "sg:address":"53100 Siena",
    "sg:city":"Siena",
    "sg:orig_category":"Lavorazioni Meccaniche E Servizi. Riparazione Dei Mezzi Di Trasporto",
    "sg:phone":"+39 0577 284281",
    "sg:postcode":"53100",
    "sg:province":"Siena",
    "wof:name":"Tecnorettifica Senese Snc",
    "wof:placetype":"venue"
},
  "geometry": {"coordinates":[11.365801,43.31971],"type":"Point"}
}