{
  "type": "Feature",
  "properties": {
    "iso:country":"IT",
    "sg:address":"Contrada Isca 85050 Sant'angelo Le Fratte",
    "sg:classifiers":[
        {
            "category":"Manufacturing",
            "subcategory":"Tools & Machinery",
            "type":"Manufacturing & Wholesale Goods"
        }
    ],
    "sg:phone":"+39 0975 386424",
    "sg:postcode":"85050",
    "sg:province":"Potenza",
    "sg:tags":[
        "environment",
        "equipment",
        "-"
    ],
    "wof:name":"Tecnoplastica Lucana",
    "wof:placetype":"venue"
},
  "geometry": {"coordinates":[15.578319,40.543209],"type":"Point"}
}