{
  "type": "Feature",
  "properties": {
    "iso:country":"IT",
    "sg:address":"Via Cagliari 09030 Samassi",
    "sg:classifiers":[
        {
            "category":"Food & Beverages",
            "subcategory":"Groceries & Convenience Stores",
            "type":"Retail Goods"
        }
    ],
    "sg:phone":"+39 070 938 8003",
    "sg:postcode":"09030",
    "sg:province":"Cagliari",
    "sg:tags":[
        "product",
        "related"
    ],
    "wof:name":"Pomo Sarda",
    "wof:placetype":"venue"
},
  "geometry": {"coordinates":[8.9110832214,39.475151062],"type":"Point"}
}