{
  "type": "Feature",
  "properties": {
    "iso:country":"IT",
    "sg:address":"23852 Garlate",
    "sg:city":"Garlate",
    "sg:orig_category":"Elettrotecnica Industriale, Prodotti E Apparecchiature. Elettrotecnica Professionale E Di Consumo",
    "sg:phone":"+39 0341 680631",
    "sg:postcode":"23852",
    "sg:province":"Lecco",
    "sg:website":"http://www.seisrl.it",
    "wof:name":"S.e.i. Srl",
    "wof:placetype":"venue"
},
  "geometry": {"coordinates":[9.39808,45.808842],"type":"Point"}
}