{
  "type": "Feature",
  "properties": {
    "iso:country":"IT",
    "sg:address":"435, Via Del Corso 00186 Roma",
    "sg:city":"Roma",
    "sg:classifiers":[
        {
            "category":"Shopping",
            "subcategory":"Crafts & Fabrics",
            "type":"Retail Goods"
        }
    ],
    "sg:phone":"+39 39066878530",
    "sg:postcode":"00186",
    "sg:province":"Roma",
    "wof:name":"Home Sweet Home Srl",
    "wof:placetype":"venue"
},
  "geometry": {"coordinates":[12.7847585678,41.8179969788],"type":"Point"}
}