{
  "type": "Feature",
  "properties": {
    "addr:full":"12, V. Romagna 63013 Grottammare Grottammare Ascoli Piceno 63013",
    "addr:housenumber":"12",
    "addr:postcode":"63013;63013",
    "addr:street":"V. Romagna",
    "iso:country":"IT",
    "sg:address":"12, V. Romagna 63013 Grottammare",
    "sg:city":"Grottammare",
    "sg:classifiers":[
        {
            "category":"Shopping",
            "subcategory":"Stationery & Office Supplies",
            "type":"Retail Goods"
        }
    ],
    "sg:phone":"+39 0735 583318",
    "sg:postcode":"63013",
    "sg:province":"Ascoli Piceno",
    "sg:tags":[
        "professional"
    ],
    "sg:website":"http://www.paginegialle.it/teknica",
    "wof:name":"Teknica Arredamenti",
    "wof:placetype":"venue"
},
  "geometry": {"coordinates":[13.8752651215,42.9714164734],"type":"Point"}
}