{
  "type": "Feature",
  "properties": {
    "addr:full":"36070 Nogarole Vicentino Nogarole Vicentino Vicenza 36070",
    "addr:postcode":"36070;36070",
    "addr:street":"Vicentino",
    "iso:country":"IT",
    "sg:address":"36070 Nogarole Vicentino",
    "sg:city":"Nogarole Vicentino",
    "sg:orig_category":"Calzature, Pelletterie E Pelli",
    "sg:phone":"+39 0444 427282",
    "sg:postcode":"36070",
    "sg:province":"Vicenza",
    "wof:name":"Teno Di Cortivo Dario",
    "wof:placetype":"venue"
},
  "geometry": {"coordinates":[11.283199,45.564285],"type":"Point"}
}