{
  "type": "Feature",
  "properties": {
    "addr:full":"24038 Sant'omobono Imagna Bergamo 24038",
    "addr:postcode":"24038;24038",
    "iso:country":"IT",
    "sg:address":"24038 Sant'omobono Imagna",
    "sg:orig_category":"Macchine E Forniture Per Arredamento E Industria Del Legno",
    "sg:phone":"+39 035 851686",
    "sg:postcode":"24038",
    "sg:province":"Bergamo",
    "wof:name":"Meccanica Salvi Di Salvi Sergio & Gianmario (s.n.c.)",
    "wof:placetype":"venue"
},
  "geometry": {"coordinates":[9.53451,45.810677],"type":"Point"}
}