{
  "type": "Feature",
  "properties": {
    "iso:country":"IT",
    "sg:address":"31015 Conegliano",
    "sg:city":"Conegliano",
    "sg:orig_category":"Telecomunicazioni E Telefonia, Impianti, Apparecchi E Servizi. Automazione E Macchine Per Ufficio",
    "sg:phone":"+39 0438 32248",
    "sg:postcode":"31015",
    "sg:province":"Treviso",
    "wof:name":"Sitel Srl",
    "wof:placetype":"venue"
},
  "geometry": {"coordinates":[12.300652504,45.8804321289],"type":"Point"}
}