{
  "type": "Feature",
  "properties": {
    "addr:full":"95131 Catania Catania Catania 95131",
    "addr:postcode":"95131;95131",
    "iso:country":"IT",
    "sg:address":"95131 Catania",
    "sg:city":"Catania",
    "sg:orig_category":"Materiali Semilavorati Metallici",
    "sg:phone":"+39 095 534945",
    "sg:postcode":"95131",
    "sg:province":"Catania",
    "wof:name":"Brodbeck Srl",
    "wof:placetype":"venue"
},
  "geometry": {"coordinates":[15.098008,37.509686],"type":"Point"}
}