{
  "type": "Feature",
  "properties": {
    "iso:country":"IT",
    "sg:address":"Via Gran Bretagna 38 63015 Monte Urano",
    "sg:city":"Monte Urano",
    "sg:classifiers":[
        {
            "category":"Shopping",
            "subcategory":"Shoes",
            "type":"Retail Goods"
        }
    ],
    "sg:phone":"+39 0734 841954",
    "sg:postcode":"63015",
    "sg:province":"Ascoli Piceno",
    "sg:tags":[
        "fitting"
    ],
    "wof:name":"Emmedue Srl",
    "wof:placetype":"venue"
},
  "geometry": {"coordinates":[13.661615,43.191841],"type":"Point"}
}