{
  "type": "Feature",
  "properties": {
    "iso:country":"IT",
    "sg:address":"35128 Padova",
    "sg:city":"Padova",
    "sg:orig_category":"Servizi E Lavori Per Arredamento E Industria Del Legno",
    "sg:phone":"+39 049 750606",
    "sg:postcode":"35128",
    "sg:province":"Padova",
    "wof:name":"Cappelletto Francesco",
    "wof:placetype":"venue"
},
  "geometry": {"coordinates":[11.926522,45.344589],"type":"Point"}
}