{
  "type": "Feature",
  "properties": {
    "addr:full":"20089 Rozzano Rozzano Milano 20089",
    "addr:postcode":"20089;20089",
    "iso:country":"IT",
    "sg:address":"20089 Rozzano",
    "sg:city":"Rozzano",
    "sg:orig_category":"Arredi Ed Attrezzature Per Attivita' Commerciali Ed Artigianali",
    "sg:phone":"+39 02 5751 4723",
    "sg:postcode":"20089",
    "sg:province":"Milano",
    "wof:name":"Europac S.r.l.",
    "wof:placetype":"venue"
},
  "geometry": {"coordinates":[9.164368,45.39286],"type":"Point"}
}