{
  "type": "Feature",
  "properties": {
    "iso:country":"IT",
    "sg:address":"80045 Pompei",
    "sg:city":"Pompei",
    "sg:classifiers":[
        {
            "category":"Manufacturing",
            "subcategory":"Wood Products",
            "type":"Manufacturing & Wholesale Goods"
        }
    ],
    "sg:phone":"+39 081 863 9188",
    "sg:postcode":"80045",
    "sg:province":"Napoli",
    "sg:tags":[
        "semi-finished"
    ],
    "wof:name":"Zeno Ciro & Zeno Pasquale Snc",
    "wof:placetype":"venue"
},
  "geometry": {"coordinates":[14.266722,40.850288],"type":"Point"}
}