{
  "type": "Feature",
  "properties": {
    "iso:country":"IT",
    "sg:address":"58, Via I. Nievo 33079 Sesto Al Reghena",
    "sg:city":"Sesto al Reghena",
    "sg:classifiers":[
        {
            "category":"Food & Beverages",
            "subcategory":"Dairy",
            "type":"Retail Goods"
        }
    ],
    "sg:phone":"+39 0434 690333",
    "sg:postcode":"33079",
    "sg:province":"Pordenone",
    "sg:tags":[
        "product"
    ],
    "wof:name":"Venchiaredo - Caseificio Sociale (soc. Coop. R.l.)",
    "wof:placetype":"venue"
},
  "geometry": {"coordinates":[12.655044,45.96265],"type":"Point"}
}