{
  "type": "Feature",
  "properties": {
    "iso:country":"IT",
    "sg:address":"51017 Pescia",
    "sg:city":"Pescia",
    "sg:orig_category":"Vivai Piante E Fiori",
    "sg:phone":"+39 0572 440291",
    "sg:postcode":"51017",
    "sg:province":"Pistoia",
    "sg:website":"http://www.vivaipacini.it",
    "wof:name":"Pacini Pietro E C. Sas",
    "wof:placetype":"venue"
},
  "geometry": {"coordinates":[10.687931,43.894962],"type":"Point"}
}