{
  "type": "Feature",
  "properties": {
    "iso:country":"IT",
    "sg:address":"20151 Milano",
    "sg:city":"Milano",
    "sg:orig_category":"Zootecnia E Pesca, Allevamento Piccoli Animali. Servizi Per Lo Sport E Il Tempo Libero",
    "sg:phone":"+39 02 4820 1721",
    "sg:postcode":"20151",
    "sg:province":"Milano",
    "wof:name":"Societa' Trenno S.p.a.",
    "wof:placetype":"venue"
},
  "geometry": {"coordinates":[9.282507,45.467201],"type":"Point"}
}