{
  "type": "Feature",
  "properties": {
    "iso:country":"IT",
    "sg:address":"18, Via Sorti 25050 Pian Camuno",
    "sg:city":"Pian Camuno",
    "sg:classifiers":[
        {
            "category":"Shopping",
            "type":"Retail Goods"
        }
    ],
    "sg:phone":"+39 036 459 0308",
    "sg:postcode":"25050",
    "sg:province":"Brescia",
    "sg:tags":[
        "finished",
        "-",
        "metallic"
    ],
    "wof:name":"Minus Mole Di Bonfadini W. & C. S.n.c.",
    "wof:placetype":"venue"
},
  "geometry": {"coordinates":[10.141954422,45.8462219238],"type":"Point"}
}