{
  "type": "Feature",
  "properties": {
    "iso:country":"IT",
    "sg:address":"70031 Andria",
    "sg:city":"Andria",
    "sg:orig_category":"Biancheria Intima Ed Abbigliamento Intimo - Produzione E Ingrosso",
    "sg:phone":"+39 0883 551259",
    "sg:postcode":"70031",
    "sg:province":"Bari",
    "wof:name":"Confezioni Nice Di D'oria Riccardo & C. Snc",
    "wof:placetype":"venue"
},
  "geometry": {"coordinates":[16.288357,41.238071],"type":"Point"}
}