{
  "type": "Feature",
  "properties": {
    "addr:full":"198, Via S. Polo 35020 Sant'angelo Di Piove Di Sacco Padova 35020",
    "addr:housenumber":"198",
    "addr:postcode":"35020;35020",
    "addr:street":"Via S. Polo",
    "iso:country":"IT",
    "sg:address":"198, Via S. Polo 35020 Sant'angelo Di Piove Di Sacco",
    "sg:classifiers":[
        {
            "category":"Personal",
            "subcategory":"Shoe Repair & Shine",
            "type":"Services"
        }
    ],
    "sg:phone":"+39 049 979 0300",
    "sg:postcode":"35020",
    "sg:province":"Padova",
    "sg:tags":[
        "leather"
    ],
    "wof:name":"Mazzucco",
    "wof:placetype":"venue"
},
  "geometry": {"coordinates":[11.958503,45.365257],"type":"Point"}
}