{
  "type": "Feature",
  "properties": {
    "iso:country":"IT",
    "sg:address":"25, Via Dell' Artigianato 35010 Vigonza",
    "sg:city":"Vigonza",
    "sg:classifiers":[
        {
            "category":"Wholesale",
            "subcategory":"Drugs",
            "type":"Manufacturing & Wholesale Goods"
        }
    ],
    "sg:phone":"+39 049 893 2391",
    "sg:postcode":"35010",
    "sg:province":"Padova",
    "sg:tags":[
        "chemical",
        "pharmaceutical"
    ],
    "wof:name":"Interchem Italia S.r.l.",
    "wof:placetype":"venue"
},
  "geometry": {"coordinates":[11.952312,45.433052],"type":"Point"}
}