{
  "type": "Feature",
  "properties": {
    "iso:country":"IT",
    "sg:address":"10128 Torino",
    "sg:city":"Torino",
    "sg:orig_category":"Viterie Di Precisione",
    "sg:phone":"+39 011 568 1749",
    "sg:postcode":"10128",
    "sg:province":"Torino",
    "wof:name":"Maurer",
    "wof:placetype":"venue"
},
  "geometry": {"coordinates":[7.670135,45.058353],"type":"Point"}
}