{
  "type": "Feature",
  "properties": {
    "iso:country":"IT",
    "sg:address":"25023 Gottolengo",
    "sg:city":"Gottolengo",
    "sg:orig_category":"Prodotti Alimentari",
    "sg:phone":"+39 030 951452",
    "sg:postcode":"25023",
    "sg:province":"Brescia",
    "wof:name":"Eredi Lampugnani Mario",
    "wof:placetype":"venue"
},
  "geometry": {"coordinates":[10.263428688,45.2956199646],"type":"Point"}
}