{
  "type": "Feature",
  "properties": {
    "iso:country":"IT",
    "sg:address":"27/33, Via Einstein Albert 70124 Bari",
    "sg:city":"Bari",
    "sg:classifiers":[
        {
            "category":"Shopping",
            "subcategory":"Computers & Home Electronics",
            "type":"Retail Goods"
        }
    ],
    "sg:phone":"+39 080 536 3322",
    "sg:postcode":"70124",
    "sg:province":"Bari",
    "sg:tags":[
        "electronic",
        "electrical",
        "equipment"
    ],
    "wof:name":"Ge Medical Systems Italia S.p.a.",
    "wof:placetype":"venue"
},
  "geometry": {"coordinates":[16.829243,41.042393],"type":"Point"}
}