{
  "type": "Feature",
  "properties": {
    "iso:country":"IT",
    "sg:address":"Via Gaetano Negri 10, 20121 Milan, Mi",
    "sg:classifiers":[
        {
            "category":"Banks & Credit Unions",
            "subcategory":"Bank",
            "type":"Services"
        }
    ],
    "sg:postcode":"20121",
    "sg:province":"Milano",
    "wof:name":"Auriga Immobiliare Spa",
    "wof:placetype":"venue"
},
  "geometry": {"coordinates":[9.183643,45.465042],"type":"Point"}
}