{
  "type": "Feature",
  "properties": {
    "iso:country":"IT",
    "sg:address":"32, Via Goito 10042 Nichelino",
    "sg:city":"Nichelino",
    "sg:classifiers":[
        {
            "category":"Shopping",
            "type":"Retail Goods"
        }
    ],
    "sg:phone":"+39 011 627 1169",
    "sg:postcode":"10042",
    "sg:province":"Torino",
    "sg:tags":[
        "finished",
        "-",
        "metallic"
    ],
    "wof:name":"Ag Industrie S.r.l.",
    "wof:placetype":"venue"
},
  "geometry": {"coordinates":[7.6384644508,44.9765281677],"type":"Point"}
}