{
  "type": "Feature",
  "properties": {
    "iso:country":"IT",
    "sg:address":"37, Via Marco Emilio Lepido 40132 Bologna",
    "sg:city":"Bologna",
    "sg:classifiers":[
        {
            "category":"Wholesale",
            "subcategory":"Drugs",
            "type":"Manufacturing & Wholesale Goods"
        }
    ],
    "sg:phone":"+39 39051400016",
    "sg:postcode":"40132",
    "sg:province":"Bologna",
    "sg:tags":[
        "chemical",
        "pharmaceutical"
    ],
    "wof:name":"Amedeo Bonfiglioli (s.r.l.)",
    "wof:placetype":"venue"
},
  "geometry": {"coordinates":[11.27676,44.516972],"type":"Point"}
}