{
  "type": "Feature",
  "properties": {
    "addr:full":"20092 Cinisello Balsamo Cinisello Balsamo Milano 20092",
    "addr:postcode":"20092;20092",
    "iso:country":"IT",
    "sg:address":"20092 Cinisello Balsamo",
    "sg:city":"Cinisello Balsamo",
    "sg:orig_category":"Palestre",
    "sg:phone":"+39 02 6601 2221",
    "sg:postcode":"20092",
    "sg:province":"Milano",
    "wof:name":"Associazione Sportiva Kung Fu Chang",
    "wof:placetype":"venue"
},
  "geometry": {"coordinates":[9.1993045807,45.5485115051],"type":"Point"}
}