{
  "type": "Feature",
  "properties": {
    "iso:country":"IT",
    "sg:address":"Km. 22.150, Strada St. Sannitica 81020 Capodrise",
    "sg:city":"Capodrise",
    "sg:classifiers":[
        {
            "category":"Travel",
            "subcategory":"Travel Agent",
            "type":"Entertainment"
        }
    ],
    "sg:phone":"+39 0823 826553",
    "sg:postcode":"81020",
    "sg:province":"Caserta",
    "sg:tags":[
        "business"
    ],
    "wof:name":"Novotel Caserta Sud Srl",
    "wof:placetype":"venue"
},
  "geometry": {"coordinates":[14.332194,41.075417],"type":"Point"}
}