{
  "type": "Feature",
  "properties": {
    "iso:country":"IT",
    "sg:address":"33049 San Pietro Al Natisone",
    "sg:city":"San Pietro al Natisone",
    "sg:orig_category":"Macchine, Impianti Ed Attrezzature Per Agricoltura E Zootecnia. Macchine, Impianti Ed Attrezzature Industria Chimica. Macchine Utensili E Impianti",
    "sg:phone":"+39 0432 727750",
    "sg:postcode":"33049",
    "sg:province":"Udine",
    "wof:name":"Dorbolo' Michele",
    "wof:placetype":"venue"
},
  "geometry": {"coordinates":[13.492221,46.136234],"type":"Point"}
}