{
  "type": "Feature",
  "properties": {
    "iso:country":"IT",
    "sg:address":"Corso Italia 13 20122 Milano",
    "sg:city":"Milano",
    "sg:classifiers":[
        {
            "category":"Organizations",
            "subcategory":"Professional Association",
            "type":"Services"
        }
    ],
    "sg:phone":"+39 02 8020 6620",
    "sg:postcode":"20122",
    "sg:province":"Milano",
    "sg:tags":[
        "publisher",
        "literature"
    ],
    "sg:website":"www.longanesi.it",
    "wof:name":"Longanesi & C. Spa",
    "wof:placetype":"venue"
},
  "geometry": {"coordinates":[9.1879091263,45.4581298828],"type":"Point"}
}