{
  "type": "Feature",
  "properties": {
    "iso:country":"IT",
    "sg:address":"16123 Genova",
    "sg:city":"Genova",
    "sg:classifiers":[
        {
            "category":"Shopping",
            "subcategory":"Clothing, Apparel, & Fashions",
            "type":"Retail Goods"
        }
    ],
    "sg:phone":"+39 010 247 1709",
    "sg:postcode":"16123",
    "sg:province":"Genova",
    "sg:tags":[
        "knitwear",
        "furs",
        "clothing"
    ],
    "wof:name":"Manifattura Carignano - Camicie Laura",
    "wof:placetype":"venue"
},
  "geometry": {"coordinates":[8.930902,44.407333],"type":"Point"}
}