{
  "type": "Feature",
  "properties": {
    "addr:full":"74100 Taranto Taranto Taranto 74100",
    "addr:postcode":"74100;74100",
    "iso:country":"IT",
    "sg:address":"74100 Taranto",
    "sg:city":"Taranto",
    "sg:orig_category":"Non-classified Establishments",
    "sg:phone":"+39 099 7366 5596",
    "sg:postcode":"74100",
    "sg:province":"Taranto",
    "wof:name":"Il Mercatino Dell'affare",
    "wof:placetype":"venue"
},
  "geometry": {"coordinates":[17.259628,40.456577],"type":"Point"}
}