{
  "type": "Feature",
  "properties": {
    "addr:full":"108/b, V. S. Lucia 10075 Mathi Mathi Torino 10075",
    "addr:housenumber":"108 / b v. s.",
    "addr:postcode":"10075;10075",
    "addr:street":"Lucia",
    "iso:country":"IT",
    "sg:address":"108/b, V. S. Lucia 10075 Mathi",
    "sg:city":"Mathi",
    "sg:classifiers":[
        {
            "category":"Wholesale",
            "subcategory":"Drugs",
            "type":"Manufacturing & Wholesale Goods"
        }
    ],
    "sg:phone":"+39 011 926 8113",
    "sg:postcode":"10075",
    "sg:province":"Torino",
    "sg:tags":[
        "chemical",
        "pharmaceutical"
    ],
    "sg:website":"http://www.mistermitt.it",
    "wof:name":"Mdd Di Maddaleno M.",
    "wof:placetype":"venue"
},
  "geometry": {"coordinates":[7.686619,45.07056],"type":"Point"}
}