{
  "type": "Feature",
  "properties": {
    "addr:full":"3, Via Sozzi Gastone 56029 Santa Croce Sull'arno Pisa 56029",
    "addr:postcode":"56029;56029",
    "addr:street":"Via Sozzi Gastone",
    "iso:country":"IT",
    "sg:address":"3, Via Sozzi Gastone 56029 Santa Croce Sull'arno",
    "sg:orig_category":"Miscellaneous Products",
    "sg:phone":"+39 0571 366502",
    "sg:postcode":"56029",
    "sg:province":"Pisa",
    "wof:name":"Penta Trading S.p.a",
    "wof:placetype":"venue"
},
  "geometry": {"coordinates":[10.3965845108,43.7161369324],"type":"Point"}
}