{
  "type": "Feature",
  "properties": {
    "iso:country":"IT",
    "sg:address":"12, C. Re Ruggero 90134 Palermo",
    "sg:city":"Palermo",
    "sg:classifiers":[
        {
            "category":"Professional",
            "subcategory":"Computer Services",
            "type":"Services"
        }
    ],
    "sg:phone":"+39 091 656 3560",
    "sg:postcode":"90134",
    "sg:province":"Palermo",
    "sg:tags":[
        "information",
        "technology"
    ],
    "sg:website":"http://www.cwgrafic.com",
    "wof:name":"Cw Grafic",
    "wof:placetype":"venue"
},
  "geometry": {"coordinates":[13.354556,38.108341],"type":"Point"}
}