{
  "type": "Feature",
  "properties": {
    "iso:country":"IT",
    "sg:address":"Via Cassa Di Risparmio 8; Merano",
    "sg:classifiers":[
        {
            "category":"Banks & Credit Unions",
            "subcategory":"Bank",
            "type":"Services"
        }
    ],
    "sg:phone":"+39 0473 230640",
    "wof:name":"Cassa Di Risparmio Di Bolzano Spa",
    "wof:placetype":"venue"
},
  "geometry": {"coordinates":[11.161834,46.670963],"type":"Point"}
}