{
  "type": "Feature",
  "properties": {
    "iso:country":"IT",
    "sg:address":"Via Gaspare Pedone 20 26100 Cremona",
    "sg:city":"Cremona",
    "sg:classifiers":[
        {
            "category":"Building & Trades",
            "subcategory":"Construction",
            "type":"Services"
        }
    ],
    "sg:phone":"+39 0372 460142",
    "sg:postcode":"26100",
    "sg:province":"Cremona",
    "sg:tags":[
        "exhibition"
    ],
    "wof:name":"Cremona Export Group Srl Trading Co",
    "wof:placetype":"venue"
},
  "geometry": {"coordinates":[10.032647,45.131958],"type":"Point"}
}