{
  "type": "Feature",
  "properties": {
    "addr:full":"80142 Napoli Napoli Napoli 80142",
    "addr:housenumber":"80142",
    "addr:postcode":"80142",
    "iso:country":"IT",
    "sg:address":"80142 Napoli",
    "sg:city":"Napoli",
    "sg:orig_category":"Scuole E Servizi Scolastici. Centri Di Estetica E Cosmesi E Servizi. Ricerca, Selezione E Formazione Del Personale",
    "sg:phone":"+39 081 563 0584",
    "sg:postcode":"80142",
    "sg:province":"Napoli",
    "wof:name":"Cinecitta' Forniture Per L'estetica Sas",
    "wof:placetype":"venue"
},
  "geometry": {"coordinates":[14.277389,40.847008],"type":"Point"}
}