{
  "type": "Feature",
  "properties": {
    "addr:full":"36031 Dueville Dueville Vicenza 36031",
    "addr:postcode":"36031;36031",
    "iso:country":"IT",
    "sg:address":"36031 Dueville",
    "sg:city":"Dueville",
    "sg:orig_category":"Ceramiche: Prodotti E Lavorazioni",
    "sg:phone":"+39 0444 594333",
    "sg:postcode":"36031",
    "sg:province":"Vicenza",
    "sg:website":"http://web.tiscali.it/paviteam",
    "wof:name":"Paviteam Srl",
    "wof:placetype":"venue"
},
  "geometry": {"coordinates":[11.5527124405,45.6391677856],"type":"Point"}
}