{
  "type": "Feature",
  "properties": {
    "iso:country":"IT",
    "sg:address":"Via Dei Carretti 18 25040 Cortefranca",
    "sg:classifiers":[
        {
            "category":"Government",
            "subcategory":"Court House",
            "type":"Public Place"
        }
    ],
    "sg:phone":"+39 030 982 8380",
    "sg:postcode":"25040",
    "sg:province":"Brescia",
    "sg:tags":[
        "cable",
        "special-purpose"
    ],
    "sg:website":"www.ats.it",
    "wof:name":"Atiesse S.r.l.",
    "wof:placetype":"venue"
},
  "geometry": {"coordinates":[10.000392,45.646603],"type":"Point"}
}