{
  "type": "Feature",
  "properties": {
    "iso:country":"IT",
    "sg:address":"00195 Roma",
    "sg:city":"Roma",
    "sg:orig_category":"Sport - Articoli E Forniture",
    "sg:phone":"+39 06 3973 3313",
    "sg:postcode":"00195",
    "sg:province":"Roma",
    "wof:name":"Ara Mario",
    "wof:placetype":"venue"
},
  "geometry": {"coordinates":[12.450661,41.910034],"type":"Point"}
}