{
  "type": "Feature",
  "properties": {
    "iso:country":"IT",
    "sg:address":"28, Strada Comunale Dei Boschi 10092 Beinasco",
    "sg:city":"Beinasco",
    "sg:classifiers":[
        {
            "category":"Professional",
            "subcategory":"Engineering",
            "type":"Services"
        }
    ],
    "sg:phone":"+39 011 349 9234",
    "sg:postcode":"10092",
    "sg:province":"Torino",
    "sg:tags":[
        "machine",
        "-",
        "mechanical"
    ],
    "wof:name":"O.m.c.a. Srl",
    "wof:placetype":"venue"
},
  "geometry": {"coordinates":[7.574721,45.010536],"type":"Point"}
}