{
  "type": "Feature",
  "properties": {
    "iso:country":"IT",
    "sg:address":"22060 Figino Serenza",
    "sg:city":"Figino Serenza",
    "sg:orig_category":"Legno E Semilavorati",
    "sg:phone":"+39 031 781475",
    "sg:postcode":"22060",
    "sg:province":"Como",
    "wof:name":"Carpani Roberto",
    "wof:placetype":"venue"
},
  "geometry": {"coordinates":[9.130539,45.71397],"type":"Point"}
}