{
  "type": "Feature",
  "properties": {
    "addr:full":"Via Vitt. Emanuele, 20; Parabita; 73052 Parabita Lecce 73052",
    "addr:housenumber":"20",
    "addr:postcode":"73052;73052",
    "addr:street":"Via Vitt. Emanuele",
    "iso:country":"IT",
    "sg:address":"Via Vitt. Emanuele, 20; Parabita; 73052",
    "sg:city":"Parabita",
    "sg:classifiers":[
        {
            "category":"Banks & Credit Unions",
            "subcategory":"Bank",
            "type":"Services"
        }
    ],
    "sg:phone":"+39 0833 325295",
    "sg:postcode":"73052",
    "sg:province":"Lecce",
    "wof:name":"Banca Vincenzo Tamorino",
    "wof:placetype":"venue"
},
  "geometry": {"coordinates":[18.125078,40.054264],"type":"Point"}
}