{
  "type": "Feature",
  "properties": {
    "iso:country":"IT",
    "sg:address":"90040 Isola Delle Femmine",
    "sg:city":"Isola delle Femmine",
    "sg:orig_category":"Apparecchiature Ed Attrezzature Meccaniche",
    "sg:phone":"+39 091 867 7500",
    "sg:postcode":"90040",
    "sg:province":"Palermo",
    "wof:name":"Bottegoni Snc",
    "wof:placetype":"venue"
},
  "geometry": {"coordinates":[13.254573,38.197365],"type":"Point"}
}