{
  "type": "Feature",
  "properties": {
    "iso:country":"IT",
    "sg:address":"37131 Verona",
    "sg:city":"Verona",
    "sg:orig_category":"Arredamenti E Mobili Professionali. Apparecchi, Attrezzature E Forniture Per Centri Estetici. Arredi Ed Attrezzature Per Attivita' Commerciali Ed Artigianali",
    "sg:phone":"+39 045 529488",
    "sg:postcode":"37131",
    "sg:province":"Verona",
    "wof:name":"Luxor (s.r.l.)",
    "wof:placetype":"venue"
},
  "geometry": {"coordinates":[11.016517,45.444767],"type":"Point"}
}