{
  "type": "Feature",
  "properties": {
    "iso:country":"IT",
    "sg:address":"10093 Collegno",
    "sg:city":"Collegno",
    "sg:orig_category":"Banche E Servizi Finanziari. Acqua, Luce, Gas E Societa' Di Esercizio Pubblico",
    "sg:phone":"+39 011 403 8763",
    "sg:postcode":"10093",
    "sg:province":"Torino",
    "wof:name":"Ica S.p.a.",
    "wof:placetype":"venue"
},
  "geometry": {"coordinates":[7.598966,45.072086],"type":"Point"}
}