{
  "type": "Feature",
  "properties": {
    "iso:country":"IT",
    "sg:address":"61, Via Bucci 47833 Morciano Di Romagna",
    "sg:city":"Morciano di Romagna",
    "sg:classifiers":[
        {
            "category":"Banks & Credit Unions",
            "subcategory":"Bank",
            "type":"Services"
        }
    ],
    "sg:phone":"+39 0541 859111",
    "sg:postcode":"47833",
    "sg:province":"Rimini",
    "sg:tags":[
        "banking",
        "institution"
    ],
    "wof:name":"Banca Popolare Valconca",
    "wof:placetype":"venue"
},
  "geometry": {"coordinates":[12.647498,43.912617],"type":"Point"}
}