{
  "type": "Feature",
  "properties": {
    "iso:country":"IT",
    "sg:address":"38068 Rovereto",
    "sg:city":"Rovereto",
    "sg:orig_category":"Cavi E Conduttori Elettrici E Telefonici",
    "sg:phone":"+39 0464 480897",
    "sg:postcode":"38068",
    "sg:province":"Trento",
    "wof:name":"Fabbrica Trentina Conduttori Srl",
    "wof:placetype":"venue"
},
  "geometry": {"coordinates":[11.007529,45.863983],"type":"Point"}
}