{
  "type": "Feature",
  "properties": {
    "iso:country":"IT",
    "sg:address":"Via Sila 40 59100 Prato",
    "sg:city":"Prato",
    "sg:classifiers":[
        {
            "category":"Home & Garden",
            "subcategory":"Furniture",
            "type":"Retail Goods"
        }
    ],
    "sg:phone":"+39 0574 815535",
    "sg:postcode":"59100",
    "sg:province":"Prato",
    "sg:tags":[
        "bathroom"
    ],
    "sg:website":"www.toscoquattro.it",
    "wof:name":"Toscoquattro Srl",
    "wof:placetype":"venue"
},
  "geometry": {"coordinates":[11.04403,43.882168],"type":"Point"}
}