{
  "type": "Feature",
  "properties": {
    "iso:country":"IT",
    "sg:address":"20123 Milano",
    "sg:city":"Milano",
    "sg:orig_category":"Professionisti - Studi E Servizi Ed Associazioni Di Interesse Aziendale. Associazioni Ed Organismi Di Interesse Pubblico",
    "sg:phone":"+39 02 806 9171",
    "sg:postcode":"20123",
    "sg:province":"Milano",
    "wof:name":"Certiquality Istituto Di Certificazione Della Qualita'",
    "wof:placetype":"venue"
},
  "geometry": {"coordinates":[9.188788414,45.4627342224],"type":"Point"}
}