{
  "type": "Feature",
  "properties": {
    "addr:full":"5, Via Stefani 33076 Pravisdomini Pravisdomini Pordenone 33076",
    "addr:postcode":"33076;33076",
    "addr:street":"Via Stefani",
    "iso:country":"IT",
    "sg:address":"5, Via Stefani 33076 Pravisdomini",
    "sg:city":"Pravisdomini",
    "sg:classifiers":[
        {
            "category":"Shopping",
            "type":"Retail Goods"
        }
    ],
    "sg:phone":"+39 0434 644810",
    "sg:postcode":"33076",
    "sg:province":"Pordenone",
    "sg:tags":[
        "finished",
        "-",
        "metallic"
    ],
    "wof:name":"Julia Stampi Di Lucchetta - Gaiardo & C. (s.n.c.)",
    "wof:placetype":"venue"
},
  "geometry": {"coordinates":[12.683795929,45.8093452454],"type":"Point"}
}