{
  "type": "Feature",
  "properties": {
    "addr:full":"95122 Catania Catania Catania 95122",
    "addr:postcode":"95122;95122",
    "iso:country":"IT",
    "sg:address":"95122 Catania",
    "sg:city":"Catania",
    "sg:orig_category":"Pescherie",
    "sg:phone":"+39 095 473852",
    "sg:postcode":"95122",
    "sg:province":"Catania",
    "wof:name":"Licata Loredana - Azzurra Distribuzione",
    "wof:placetype":"venue"
},
  "geometry": {"coordinates":[15.0398607254,37.5652389526],"type":"Point"}
}