{
  "type": "Feature",
  "properties": {
    "addr:full":"10024 Moncalieri Moncalieri Torino 10024",
    "addr:postcode":"10024;10024",
    "iso:country":"IT",
    "sg:address":"10024 Moncalieri",
    "sg:city":"Moncalieri",
    "sg:orig_category":"Buste E Sacchetti",
    "sg:phone":"+39 011 647 1002",
    "sg:postcode":"10024",
    "sg:province":"Torino",
    "wof:name":"F.t.c. Srl",
    "wof:placetype":"venue"
},
  "geometry": {"coordinates":[7.779292,44.641384],"type":"Point"}
}