{
  "type": "Feature",
  "properties": {
    "addr:full":"31020 San Vendemiano San Vendemiano Treviso 31020",
    "addr:housenumber":"31020;vendemiano",
    "addr:postcode":"vendemiano;31020",
    "addr:street":"San",
    "iso:country":"IT",
    "sg:address":"31020 San Vendemiano",
    "sg:city":"San Vendemiano",
    "sg:classifiers":[
        {
            "category":"Train Station",
            "subcategory":"Light Rail",
            "type":"Transportation"
        }
    ],
    "sg:phone":"+39 0438 400035",
    "sg:postcode":"31020",
    "sg:province":"Treviso",
    "sg:tags":[
        "plating",
        "treatments",
        "metals",
        "heat",
        "electroforming",
        "surface"
    ],
    "wof:name":"Lucarelli Florindo & Figli Snc",
    "wof:placetype":"venue"
},
  "geometry": {"coordinates":[12.327958107,45.9007148743],"type":"Point"}
}