{
  "type": "Feature",
  "properties": {
    "addr:full":"Via Provinciale Manduria, Km 1 72024 Oria Oria Brindisi 72024",
    "addr:postcode":"72024;72024",
    "addr:street":"Via Provinciale Manduria Km 1",
    "iso:country":"IT",
    "sg:address":"Via Provinciale Manduria, Km 1 72024 Oria",
    "sg:city":"Oria",
    "sg:classifiers":[
        {
            "category":"Manufacturing",
            "subcategory":"Lumber",
            "type":"Manufacturing & Wholesale Goods"
        }
    ],
    "sg:phone":"+39 0831 848319",
    "sg:postcode":"72024",
    "sg:province":"Brindisi",
    "sg:tags":[
        "hardwood",
        "sawmill"
    ],
    "wof:name":"Segheria Salentina Di Anne' Emanuele E Fratelli S.n.c.",
    "wof:placetype":"venue"
},
  "geometry": {"coordinates":[17.645449,40.501415],"type":"Point"}
}