{
  "type": "Feature",
  "properties": {
    "iso:country":"IT",
    "sg:address":"3, Via Dell' Industria 36036 Torrebelvicino",
    "sg:city":"Torrebelvicino",
    "sg:classifiers":[
        {
            "category":"Professional",
            "subcategory":"Engineering",
            "type":"Services"
        }
    ],
    "sg:phone":"+39 0445 661294",
    "sg:postcode":"36036",
    "sg:province":"Vicenza",
    "sg:tags":[
        "machine",
        "-",
        "mechanical"
    ],
    "wof:name":"S.i.m.a.l. (s.r.l.)",
    "wof:placetype":"venue"
},
  "geometry": {"coordinates":[11.323957,45.712246],"type":"Point"}
}