{
  "type": "Feature",
  "properties": {
    "iso:country":"IT",
    "sg:address":"25060 Cellatica",
    "sg:city":"Cellatica",
    "sg:orig_category":"Apparecchiature Pneumatiche Ed Idropneumatiche",
    "sg:phone":"+39 030 373 1904",
    "sg:postcode":"25060",
    "sg:province":"Brescia",
    "wof:name":"Vales Srl",
    "wof:placetype":"venue"
},
  "geometry": {"coordinates":[10.169778,45.5602],"type":"Point"}
}