{
  "type": "Feature",
  "properties": {
    "iso:country":"IT",
    "sg:address":"00198 Roma",
    "sg:city":"Roma",
    "sg:orig_category":"Ospedali E Servizi Sanitari. Servizi Sociali. Associazioni Ed Organismi Di Interesse Pubblico",
    "sg:phone":"+39 06 853748",
    "sg:postcode":"00198",
    "sg:province":"Roma",
    "wof:name":"Arco Iris Piccola Soc. Coop.",
    "wof:placetype":"venue"
},
  "geometry": {"coordinates":[12.603024,41.901905],"type":"Point"}
}