{
  "type": "Feature",
  "properties": {
    "iso:country":"IT",
    "sg:address":"51100 Pistoia",
    "sg:city":"Pistoia",
    "sg:classifiers":[
        {
            "category":"Military Area",
            "subcategory":"Coast Guard Base",
            "type":"Public Place"
        }
    ],
    "sg:phone":"+39 0573 545723",
    "sg:postcode":"51100",
    "sg:province":"Pistoia",
    "sg:tags":[
        "accessories",
        "linen",
        "furnishing",
        "bedroom",
        "blankets",
        "drapery"
    ],
    "wof:name":"Lady Laura Srl",
    "wof:placetype":"venue"
},
  "geometry": {"coordinates":[10.950642,43.89521],"type":"Point"}
}