{
  "type": "Feature",
  "properties": {
    "iso:country":"IT",
    "sg:address":"Via Del Commercio 4 27010 Cura Carpignano",
    "sg:city":"Cura Carpignano",
    "sg:classifiers":[
        {
            "category":"Food & Beverages",
            "subcategory":"Meat & Fish",
            "type":"Retail Goods"
        }
    ],
    "sg:phone":"+39 0382 474396",
    "sg:postcode":"27010",
    "sg:province":"Pavia",
    "sg:tags":[
        "slicer"
    ],
    "sg:website":"www.essedue.com",
    "wof:name":"Essedue Srl",
    "wof:placetype":"venue"
},
  "geometry": {"coordinates":[9.219943,45.206768],"type":"Point"}
}