{
  "type": "Feature",
  "properties": {
    "addr:full":"25135 Brescia Brescia Brescia 25135",
    "addr:postcode":"25135;25135",
    "iso:country":"IT",
    "sg:address":"25135 Brescia",
    "sg:city":"Brescia",
    "sg:orig_category":"Prodotti E Manufatti In Gomma. Servizi E Lavori Industria Della Gomma. Ricambi E Componenti Dei Mezzi Di Trasporto. Riparazione Dei Mezzi Di Trasporto",
    "sg:phone":"+39 030 336 5357",
    "sg:postcode":"25135",
    "sg:province":"Brescia",
    "sg:website":"http://www.gogpneus.it",
    "wof:name":"Gog Pneus Srl",
    "wof:placetype":"venue"
},
  "geometry": {"coordinates":[10.2803516388,45.5107460022],"type":"Point"}
}