{
  "type": "Feature",
  "properties": {
    "addr:full":"16, Via Pisani Vittor 20124 Milano Milano Milano 20124",
    "addr:postcode":"20124;20124",
    "addr:street":"Via Pisani Vittor",
    "iso:country":"IT",
    "sg:address":"16, Via Pisani Vittor 20124 Milano",
    "sg:city":"Milano",
    "sg:classifiers":[
        {
            "category":"Manufacturing",
            "subcategory":"Printing",
            "type":"Manufacturing & Wholesale Goods"
        }
    ],
    "sg:phone":"+39 02 6698 4851",
    "sg:postcode":"20124",
    "sg:province":"Milano",
    "sg:tags":[
        "publishing"
    ],
    "wof:name":"Dve Italia Spa",
    "wof:placetype":"venue"
},
  "geometry": {"coordinates":[9.201125145,45.4825210571],"type":"Point"}
}