{
  "type": "Feature",
  "properties": {
    "iso:country":"IT",
    "sg:address":"53036 Poggibonsi",
    "sg:city":"Poggibonsi",
    "sg:orig_category":"Arte Ed Artigianato Artistico",
    "sg:phone":"+39 0577 938192",
    "sg:postcode":"53036",
    "sg:province":"Siena",
    "sg:website":"http://www.paciniesaccardi.com",
    "wof:name":"Pacini & Saccardi Srl",
    "wof:placetype":"venue"
},
  "geometry": {"coordinates":[11.184389,43.452106],"type":"Point"}
}