{
  "type": "Feature",
  "properties": {
    "iso:country":"IT",
    "sg:address":"24020 Gorle",
    "sg:city":"Gorle",
    "sg:orig_category":"Legno E Semilavorati",
    "sg:phone":"+39 035 294568",
    "sg:postcode":"24020",
    "sg:province":"Bergamo",
    "wof:name":"Bizioli Legno Srl",
    "wof:placetype":"venue"
},
  "geometry": {"coordinates":[9.715767,45.694473],"type":"Point"}
}