{
  "type": "Feature",
  "properties": {
    "iso:country":"IT",
    "sg:address":"20059 Vimercate",
    "sg:city":"Vimercate",
    "sg:orig_category":"Macchine E Forniture Per Arredamento E Industria Del Legno. Colori, Vernici E Smalti",
    "sg:phone":"+39 039 667640",
    "sg:postcode":"20059",
    "sg:province":"Milano",
    "wof:name":"Industria Chimica Adriatica S.p.a.",
    "wof:placetype":"venue"
},
  "geometry": {"coordinates":[9.058305,45.532059],"type":"Point"}
}