{
  "type": "Feature",
  "properties": {
    "addr:full":"21046 Malnate Malnate Varese 21046",
    "addr:postcode":"21046;21046",
    "iso:country":"IT",
    "sg:address":"21046 Malnate",
    "sg:city":"Malnate",
    "sg:classifiers":[
        {
            "category":"Communications",
            "subcategory":"Film & Video Production",
            "type":"Services"
        }
    ],
    "sg:phone":"+39 0332 426660",
    "sg:postcode":"21046",
    "sg:province":"Varese",
    "sg:tags":[
        "semi-finished",
        "materials",
        "metal"
    ],
    "wof:name":"Car Mec Srl",
    "wof:placetype":"venue"
},
  "geometry": {"coordinates":[8.8795452118,45.7868537903],"type":"Point"}
}