{
  "type": "Feature",
  "properties": {
    "addr:full":"Via Aterno 66100 Chieti Chieti Chieti 66100",
    "addr:postcode":"66100;66100",
    "addr:street":"Via Aterno",
    "iso:country":"IT",
    "sg:address":"Via Aterno 66100 Chieti",
    "sg:city":"Chieti",
    "sg:classifiers":[
        {
            "category":"Shopping",
            "subcategory":"Computers & Home Electronics",
            "type":"Retail Goods"
        }
    ],
    "sg:phone":"+39 0871 564170",
    "sg:postcode":"66100",
    "sg:province":"Chieti",
    "sg:tags":[
        "electronic",
        "electrical",
        "equipment"
    ],
    "wof:name":"I.t.m. Srl",
    "wof:placetype":"venue"
},
  "geometry": {"coordinates":[14.130052,42.335903],"type":"Point"}
}