{
  "type": "Feature",
  "properties": {
    "addr:full":"00149 Roma Roma Roma 00149",
    "addr:postcode":"00149;00149",
    "iso:country":"IT",
    "sg:address":"00149 Roma",
    "sg:city":"Roma",
    "sg:orig_category":"Articoli Tecnici Industriali",
    "sg:phone":"+39 06 558 3715",
    "sg:postcode":"00149",
    "sg:province":"Roma",
    "wof:name":"B.b.c. Prodotti Per L'industria Srl",
    "wof:placetype":"venue"
},
  "geometry": {"coordinates":[12.456377,41.860851],"type":"Point"}
}