{
  "type": "Feature",
  "properties": {
    "iso:country":"IT",
    "sg:address":"Contrada Paterna 90049 Terrasini",
    "sg:city":"Terrasini",
    "sg:classifiers":[
        {
            "category":"Sports & Exercise",
            "subcategory":"Playing Field",
            "type":"Entertainment"
        }
    ],
    "sg:phone":"+39 091 869 5059",
    "sg:postcode":"90049",
    "sg:province":"Palermo",
    "sg:tags":[
        "game"
    ],
    "wof:name":"Trinacria Candles Di Li Cavoli Antonino",
    "wof:placetype":"venue"
},
  "geometry": {"coordinates":[13.361376,38.11562],"type":"Point"}
}