{
  "type": "Feature",
  "properties": {
    "addr:full":"00161 Roma Roma Roma 00161",
    "addr:postcode":"00161;00161",
    "iso:country":"IT",
    "sg:address":"00161 Roma",
    "sg:city":"Roma",
    "sg:orig_category":"Servizi Al Turismo. Ambasciate Ed Enti Internazionali",
    "sg:phone":"+39 06 440 2506",
    "sg:postcode":"00161",
    "sg:province":"Roma",
    "wof:name":"Ambasciata Presso Lo Stato Italiano Marocco",
    "wof:placetype":"venue"
},
  "geometry": {"coordinates":[12.510906,41.912319],"type":"Point"}
}