{
  "type": "Feature",
  "properties": {
    "addr:full":"82100 Benevento Benevento Benevento 82100",
    "addr:postcode":"82100;82100",
    "iso:country":"IT",
    "sg:address":"82100 Benevento",
    "sg:city":"Benevento",
    "sg:orig_category":"Agenzie D'affari E Servizi Commerciali. Servizi Per Aziende, Manifestazioni E Supporto Agli Scambi Commerciali",
    "sg:phone":"+39 0824 24623",
    "sg:postcode":"82100",
    "sg:province":"Benevento",
    "wof:name":"C.e.s.a.c. Angelo Villani Srl",
    "wof:placetype":"venue"
},
  "geometry": {"coordinates":[14.770932,41.135216],"type":"Point"}
}