{
  "type": "Feature",
  "properties": {
    "addr:full":"39012 Merano Merano Bolzano/Bozen 39012",
    "addr:postcode":"39012;39012",
    "iso:country":"IT",
    "sg:address":"39012 Merano",
    "sg:city":"Merano",
    "sg:orig_category":"Fotografia Apparecchi E Materiali - Produzione E Ingrosso",
    "sg:phone":"+39 0473 445277",
    "sg:postcode":"39012",
    "sg:province":"Bolzano/Bozen",
    "sg:website":"http://www.staschitz.com",
    "wof:name":"Foto Staschitz K.g. Sas",
    "wof:placetype":"venue"
},
  "geometry": {"coordinates":[11.35800457,46.4967155457],"type":"Point"}
}