{
  "type": "Feature",
  "properties": {
    "iso:country":"IT",
    "sg:address":"52037 Sansepolcro",
    "sg:city":"Sansepolcro",
    "sg:orig_category":"Servizi E Lavori Per Abbigliamento E Pelletterie. Scuole E Servizi Scolastici. Ricerca, Selezione E Formazione Del Personale",
    "sg:phone":"+39 0575 744057",
    "sg:postcode":"52037",
    "sg:province":"Arezzo",
    "wof:name":"Euroservizi Associati",
    "wof:placetype":"venue"
},
  "geometry": {"coordinates":[12.128971,43.592152],"type":"Point"}
}