{
  "type": "Feature",
  "properties": {
    "iso:country":"IT",
    "sg:address":"25064 Gussago",
    "sg:city":"Gussago",
    "sg:orig_category":"Apparecchiature Ed Attrezzature Meccaniche",
    "sg:phone":"+39 030 321556",
    "sg:postcode":"25064",
    "sg:province":"Brescia",
    "wof:name":"Ma Pi Di Fumagalli & C. Snc",
    "wof:placetype":"venue"
},
  "geometry": {"coordinates":[10.15023,45.551682],"type":"Point"}
}