{
  "type": "Feature",
  "properties": {
    "addr:full":"39030 Lutago Lutago Bolzano/Bozen 39030",
    "addr:postcode":"39030;39030",
    "addr:street":"Lutago",
    "iso:country":"IT",
    "sg:address":"39030 Lutago",
    "sg:city":"Lutago",
    "sg:orig_category":"Ospedali E Servizi Sanitari",
    "sg:phone":"+39 0474 671143",
    "sg:postcode":"39030",
    "sg:province":"Bolzano/Bozen",
    "wof:name":"Steger Rosa",
    "wof:placetype":"venue"
},
  "geometry": {"coordinates":[11.92017,46.950756],"type":"Point"}
}