{
  "type": "Feature",
  "properties": {
    "addr:full":"1, Via Longhi Roberto 40128 Bologna Bologna Bologna 40128",
    "addr:postcode":"40128;40128",
    "addr:street":"Via Longhi Roberto",
    "iso:country":"IT",
    "sg:address":"1, Via Longhi Roberto 40128 Bologna",
    "sg:city":"Bologna",
    "sg:classifiers":[
        {
            "category":"Utilities",
            "subcategory":"Telephone",
            "type":"Services"
        }
    ],
    "sg:phone":"+39 39051373513",
    "sg:postcode":"40128",
    "sg:province":"Bologna",
    "sg:tags":[
        "telecommunication"
    ],
    "wof:name":"Ondaelle S.r.l.",
    "wof:placetype":"venue"
},
  "geometry": {"coordinates":[11.346481,44.494221],"type":"Point"}
}