{
  "type": "Feature",
  "properties": {
    "iso:country":"IT",
    "sg:address":"70038 Terlizzi",
    "sg:city":"Terlizzi",
    "sg:orig_category":"Servizi E Lavori Per Industria Alimentare E Bevande",
    "sg:phone":"+39 080 351 8578",
    "sg:postcode":"70038",
    "sg:province":"Bari",
    "wof:name":"Da Pisa Domenico",
    "wof:placetype":"venue"
},
  "geometry": {"coordinates":[16.541691,41.126522],"type":"Point"}
}