{
  "type": "Feature",
  "properties": {
    "addr:full":"10121 Torino Torino Torino 10121",
    "addr:postcode":"10121;10121",
    "iso:country":"IT",
    "sg:address":"10121 Torino",
    "sg:city":"Torino",
    "sg:orig_category":"Ottica, Lenti A Contatto Ed Occhiali - Vendita Al Dettaglio",
    "sg:phone":"+39 011 547138",
    "sg:postcode":"10121",
    "sg:province":"Torino",
    "sg:website":"http://www.interlink.it/infovista",
    "wof:name":"Infovista Assistance",
    "wof:placetype":"venue"
},
  "geometry": {"coordinates":[7.570965,45.066242],"type":"Point"}
}