{
  "type": "Feature",
  "properties": {
    "iso:country":"IT",
    "sg:address":"63039 San Benedetto Del Tronto",
    "sg:city":"San Benedetto del Tronto",
    "sg:orig_category":"Servizi Ausiliari Per Il Trasporto",
    "sg:phone":"+39 0735 582185",
    "sg:postcode":"63039",
    "sg:province":"Ascoli Piceno",
    "wof:name":"F.a.ro.di Romani Antonio & C. - S.n.c.",
    "wof:placetype":"venue"
},
  "geometry": {"coordinates":[13.876759,42.959938],"type":"Point"}
}