{
  "type": "Feature",
  "properties": {
    "iso:country":"IT",
    "sg:address":"16, Via L. Da Vinci 28019 Suno",
    "sg:city":"Suno",
    "sg:classifiers":[
        {
            "category":"Shopping",
            "subcategory":"Crafts & Fabrics",
            "type":"Retail Goods"
        }
    ],
    "sg:phone":"+39 39032285191",
    "sg:postcode":"28019",
    "sg:province":"Novara",
    "wof:name":"Fi.te.s (s.p.a.)",
    "wof:placetype":"venue"
},
  "geometry": {"coordinates":[8.5574140549,45.6339759827],"type":"Point"}
}