{
  "type": "Feature",
  "properties": {
    "addr:full":"Via Alcide De Gasperi 128 38100 Trento Trento Trento 38100",
    "addr:housenumber":"128",
    "addr:postcode":"38100;38100",
    "addr:street":"Via Alcide De Gasperi",
    "iso:country":"IT",
    "sg:address":"Via Alcide De Gasperi 128 38100 Trento",
    "sg:city":"Trento",
    "sg:classifiers":[
        {
            "category":"Professional",
            "subcategory":"Printing & Photocopies",
            "type":"Services"
        }
    ],
    "sg:phone":"+39 0461 920043",
    "sg:postcode":"38100",
    "sg:province":"Trento",
    "sg:tags":[
        "dry",
        "offset"
    ],
    "sg:website":"www.stamparapida.it",
    "wof:name":"Tipografia Nuova Stampa Rapida Srl",
    "wof:placetype":"venue"
},
  "geometry": {"coordinates":[11.126989,46.048019],"type":"Point"}
}