{
  "type": "Feature",
  "properties": {
    "iso:country":"IT",
    "sg:address":"87036 Rende",
    "sg:city":"Rende",
    "sg:orig_category":"Ospedali E Servizi Sanitari. Servizi Ausiliari Di Analisi, Controllo E Ricerca",
    "sg:phone":"+39 0984 846425",
    "sg:postcode":"87036",
    "sg:province":"Cosenza",
    "wof:name":"Biogenet S.r.l.",
    "wof:placetype":"venue"
},
  "geometry": {"coordinates":[16.244097,39.327702],"type":"Point"}
}