{
  "type": "Feature",
  "properties": {
    "iso:country":"IT",
    "sg:address":"16031 Bogliasco",
    "sg:city":"Bogliasco",
    "sg:orig_category":"Bevande, Vini E Liquori. Agricoltura, Orticoltura E Floricoltura",
    "sg:phone":"+39 010 347 0103",
    "sg:postcode":"16031",
    "sg:province":"Genova",
    "wof:name":"Emporio Del Bere S.a.s.",
    "wof:placetype":"venue"
},
  "geometry": {"coordinates":[9.068001,44.379669],"type":"Point"}
}