{
  "type": "Feature",
  "properties": {
    "iso:country":"IT",
    "sg:address":"70121 Bari",
    "sg:city":"Bari",
    "sg:orig_category":"Arredi Sacri",
    "sg:phone":"+39 080 521 0132",
    "sg:postcode":"70121",
    "sg:province":"Bari",
    "wof:name":"Costantino Arredi Sacri Di Silvio Costantino & C. Sas",
    "wof:placetype":"venue"
},
  "geometry": {"coordinates":[16.86998,41.124027],"type":"Point"}
}