{
  "type": "Feature",
  "properties": {
    "iso:country":"IT",
    "sg:address":"70126 Bari",
    "sg:city":"Bari",
    "sg:orig_category":"Elettricita' Materiali - Ingrosso",
    "sg:phone":"+39 080 531 3030",
    "sg:postcode":"70126",
    "sg:province":"Bari",
    "sg:website":"http://www.intelettra.it",
    "wof:name":"Intelettra Sonepar Spa",
    "wof:placetype":"venue"
},
  "geometry": {"coordinates":[16.895887,41.114697],"type":"Point"}
}