{
  "type": "Feature",
  "properties": {
    "iso:country":"IT",
    "sg:address":"52100 Arezzo",
    "sg:city":"Arezzo",
    "sg:classifiers":[
        {
            "category":"Manufacturing",
            "subcategory":"Metals",
            "type":"Manufacturing & Wholesale Goods"
        }
    ],
    "sg:phone":"+39 0575 948045",
    "sg:postcode":"52100",
    "sg:province":"Arezzo",
    "sg:tags":[
        "watchmaker",
        "alloys",
        "jewelers",
        "gold",
        "silversmith"
    ],
    "sg:website":"http://www.cdinex.com",
    "wof:name":"C.d.i. In-ex Srl",
    "wof:placetype":"venue"
},
  "geometry": {"coordinates":[11.9348068237,43.4325447083],"type":"Point"}
}