{
  "type": "Feature",
  "properties": {
    "iso:country":"IT",
    "sg:address":"25, Via Rinascita 40064 Ozzano Dell'emilia",
    "sg:classifiers":[
        {
            "category":"Manufacturing",
            "subcategory":"Glass & Minerals",
            "type":"Manufacturing & Wholesale Goods"
        }
    ],
    "sg:phone":"+39 39051791611",
    "sg:postcode":"40064",
    "sg:province":"Bologna",
    "wof:name":"Aetna Group (s.p.a.)",
    "wof:placetype":"venue"
},
  "geometry": {"coordinates":[11.503451,44.465221],"type":"Point"}
}