{
  "type": "Feature",
  "properties": {
    "iso:country":"IT",
    "sg:address":"Corso Europa 14; Milano; 20122",
    "sg:city":"Milano",
    "sg:classifiers":[
        {
            "category":"Banks & Credit Unions",
            "subcategory":"Bank",
            "type":"Services"
        }
    ],
    "sg:phone":"+39 02 796999",
    "sg:postcode":"20122",
    "sg:province":"Milano",
    "wof:name":"Core States Bank Na",
    "wof:placetype":"venue"
},
  "geometry": {"coordinates":[9.196525,45.464382],"type":"Point"}
}