{
  "type": "Feature",
  "properties": {
    "addr:full":"37136 Verona Verona Verona 37136",
    "addr:postcode":"37136;37136",
    "iso:country":"IT",
    "sg:address":"37136 Verona",
    "sg:city":"Verona",
    "sg:orig_category":"Prodotti E Manufatti In Gomma. Servizi E Lavori Industria Della Gomma. Ricambi E Componenti Dei Mezzi Di Trasporto",
    "sg:phone":"+39 045 862 0023",
    "sg:postcode":"37136",
    "sg:province":"Verona",
    "wof:name":"Pedone Pneumatici",
    "wof:placetype":"venue"
},
  "geometry": {"coordinates":[10.9522647858,45.410282135],"type":"Point"}
}