{
  "type": "Feature",
  "properties": {
    "iso:country":"IT",
    "sg:address":"70051 Barletta",
    "sg:city":"Barletta",
    "sg:orig_category":"Servizi E Lavori Per Arredamento E Industria Del Legno. Vetro: Prodotti E Lavorazioni",
    "sg:phone":"+39 0883 517106",
    "sg:postcode":"70051",
    "sg:province":"Bari",
    "wof:name":"Cassatella Michele",
    "wof:placetype":"venue"
},
  "geometry": {"coordinates":[16.262827,41.3242],"type":"Point"}
}