{
  "type": "Feature",
  "properties": {
    "addr:full":"Piazza Della Repubblica 3, 34079 Staranzano, Go Staranzano Gorizia 34079",
    "addr:housenumber":"3",
    "addr:postcode":"34079;34079",
    "addr:street":"Piazza Della Repubblica",
    "iso:country":"IT",
    "sg:address":"Piazza Della Repubblica 3, 34079 Staranzano, Go",
    "sg:city":"Staranzano",
    "sg:classifiers":[
        {
            "category":"Banks & Credit Unions",
            "subcategory":"Bank",
            "type":"Services"
        }
    ],
    "sg:postcode":"34079",
    "sg:province":"Gorizia",
    "wof:name":"Banca Di Credito Cooperativo Di Staranzano Scrl",
    "wof:placetype":"venue"
},
  "geometry": {"coordinates":[13.50635,45.805748],"type":"Point"}
}