{
  "type": "Feature",
  "properties": {
    "addr:full":"00060 Riano Riano Roma 00060",
    "addr:postcode":"00060;00060",
    "iso:country":"IT",
    "sg:address":"00060 Riano",
    "sg:city":"Riano",
    "sg:orig_category":"Scuole E Servizi Scolastici. Servizi Per Lo Sport E Il Tempo Libero",
    "sg:phone":"+39 06 903 4352",
    "sg:postcode":"00060",
    "sg:province":"Roma",
    "wof:name":"Associazione Culturale Spazio Musica",
    "wof:placetype":"venue"
},
  "geometry": {"coordinates":[12.503922,42.100842],"type":"Point"}
}