{
  "type": "Feature",
  "properties": {
    "addr:full":"12, Via S. Pietro 31049 Valdobbiadene Valdobbiadene Treviso 31049",
    "addr:postcode":"31049;31049",
    "addr:street":"Via S. Pietro",
    "iso:country":"IT",
    "sg:address":"12, Via S. Pietro 31049 Valdobbiadene",
    "sg:city":"Valdobbiadene",
    "sg:classifiers":[
        {
            "category":"Shopping",
            "subcategory":"Clothing, Apparel, & Fashions",
            "type":"Retail Goods"
        }
    ],
    "sg:phone":"+39 0423 973265",
    "sg:postcode":"31049",
    "sg:province":"Treviso",
    "sg:tags":[
        "clothes"
    ],
    "wof:name":"K.w. Confezioni (s.r.l.)",
    "wof:placetype":"venue"
},
  "geometry": {"coordinates":[12.242072,45.666286],"type":"Point"}
}