{
  "type": "Feature",
  "properties": {
    "addr:full":"2, Via Delle Scienza 37139 Verona Verona Verona 37139",
    "addr:postcode":"37139;37139",
    "addr:street":"Via Delle Scienza",
    "iso:country":"IT",
    "sg:address":"2, Via Delle Scienza 37139 Verona",
    "sg:city":"Verona",
    "sg:classifiers":[
        {
            "category":"Manufacturing",
            "subcategory":"Rubber & Plastics",
            "type":"Manufacturing & Wholesale Goods"
        }
    ],
    "sg:phone":"+39 045 851 0230",
    "sg:postcode":"37139",
    "sg:province":"Verona",
    "wof:name":"Sallustio",
    "wof:placetype":"venue"
},
  "geometry": {"coordinates":[10.9917478561,45.4383659363],"type":"Point"}
}