{
  "type": "Feature",
  "properties": {
    "iso:country":"IT",
    "sg:address":"28017 S. Maurizio D'opaglio",
    "sg:orig_category":"Valvole E Apparecchiature Di Misura. Forniture Per Attivita' Industriali",
    "sg:phone":"+39 0322 915919",
    "sg:postcode":"28017",
    "sg:province":"Novara",
    "wof:name":"Tof Srl",
    "wof:placetype":"venue"
},
  "geometry": {"coordinates":[8.394937,45.767426],"type":"Point"}
}