{
  "type": "Feature",
  "properties": {
    "addr:full":"28021 Borgomanero Borgomanero Novara 28021",
    "addr:postcode":"28021;28021",
    "iso:country":"IT",
    "sg:address":"28021 Borgomanero",
    "sg:city":"Borgomanero",
    "sg:orig_category":"Trasporti E Spedizioni Merci",
    "sg:phone":"+39 0322 804217",
    "sg:postcode":"28021",
    "sg:province":"Novara",
    "wof:name":"Valloggia Autogru Srl",
    "wof:placetype":"venue"
},
  "geometry": {"coordinates":[8.486945,45.693062],"type":"Point"}
}