{
  "type": "Feature",
  "properties": {
    "addr:full":"Via Minima 1/r 50124 Firenze Firenze Firenze 50124",
    "addr:housenumber":"1 / r",
    "addr:postcode":"50124;50124",
    "addr:street":"Via Minima",
    "iso:country":"IT",
    "sg:address":"Via Minima 1/r 50124 Firenze",
    "sg:city":"Firenze",
    "sg:classifiers":[
        {
            "category":"Utilities",
            "subcategory":"Recycling",
            "type":"Services"
        }
    ],
    "sg:phone":"+39 055 229 8971",
    "sg:postcode":"50124",
    "sg:province":"Firenze",
    "sg:tags":[
        "machining",
        "plexiglas",
        "processing"
    ],
    "wof:name":"Mapa Snc",
    "wof:placetype":"venue"
},
  "geometry": {"coordinates":[11.256901741,43.7687339783],"type":"Point"}
}