{
  "type": "Feature",
  "properties": {
    "iso:country":"IT",
    "sg:address":"1, Via Settimo 37060 Buttapietra",
    "sg:city":"Buttapietra",
    "sg:classifiers":[
        {
            "category":"Manufacturing",
            "subcategory":"Metals",
            "type":"Manufacturing & Wholesale Goods"
        }
    ],
    "sg:phone":"+39 045 666 0976",
    "sg:postcode":"37060",
    "sg:province":"Verona",
    "sg:tags":[
        "processing"
    ],
    "wof:name":"Tecnocolor S.n.c.",
    "wof:placetype":"venue"
},
  "geometry": {"coordinates":[10.986697197,45.3290596008],"type":"Point"}
}