{
  "type": "Feature",
  "properties": {
    "iso:country":"IT",
    "sg:address":"33, Via S. Giuseppe La Rena 95121 Catania",
    "sg:city":"Catania",
    "sg:classifiers":[
        {
            "category":"Autos & Motor Vehicles",
            "subcategory":"Automobile Sales",
            "type":"Retail Goods"
        }
    ],
    "sg:phone":"+39 39095349793",
    "sg:postcode":"95121",
    "sg:province":"Catania",
    "sg:tags":[
        "industrial"
    ],
    "wof:name":"Pulvirenti & C. (s.p.a.)",
    "wof:placetype":"venue"
},
  "geometry": {"coordinates":[15.035744,37.470638],"type":"Point"}
}