{
  "type": "Feature",
  "properties": {
    "addr:full":"41100 Modena Modena Modena 41100",
    "addr:postcode":"41100;41100",
    "iso:country":"IT",
    "sg:address":"41100 Modena",
    "sg:city":"Modena",
    "sg:orig_category":"Prodotti E Manufatti In Gomma",
    "sg:phone":"+39 059 243166",
    "sg:postcode":"41100",
    "sg:province":"Modena",
    "wof:name":"Adani Avio",
    "wof:placetype":"venue"
},
  "geometry": {"coordinates":[10.9144287109,44.6639442444],"type":"Point"}
}