{
  "type": "Feature",
  "properties": {
    "iso:country":"IT",
    "sg:address":"35136 Padova",
    "sg:city":"Padova",
    "sg:orig_category":"Studi E Consulenze Amministrative, Commerciali E Aziendali. Consulenze Tecniche, Amministrative E Perizie",
    "sg:phone":"+39 049 897 9920",
    "sg:postcode":"35136",
    "sg:province":"Padova",
    "sg:website":"http://www.rmsagenti.com",
    "wof:name":"R.m.s. Di Rigon Alessandro & C. Sas",
    "wof:placetype":"venue"
},
  "geometry": {"coordinates":[11.839919,45.426163],"type":"Point"}
}