{
  "type": "Feature",
  "properties": {
    "iso:country":"IT",
    "sg:address":"25126 Brescia",
    "sg:city":"Brescia",
    "sg:orig_category":"Abbigliamento Esterno, Maglierie E Pelliccerie. Calzature, Pelletterie E Pelli. Shopping",
    "sg:phone":"+39 030 375 3359",
    "sg:postcode":"25126",
    "sg:province":"Brescia",
    "wof:name":"Casa Della Renna Di Ambrosini A. Maria Sas",
    "wof:placetype":"venue"
},
  "geometry": {"coordinates":[10.196121,45.54089],"type":"Point"}
}