{
  "type": "Feature",
  "properties": {
    "iso:country":"IT",
    "sg:address":"36061 Bassano Del Grappa",
    "sg:city":"Bassano del Grappa",
    "sg:classifiers":[
        {
            "category":"Professional",
            "subcategory":"Advertising",
            "type":"Services"
        }
    ],
    "sg:phone":"+39 0424 522200",
    "sg:postcode":"36061",
    "sg:province":"Vicenza",
    "sg:tags":[
        "marketing",
        "communication"
    ],
    "wof:name":"Adg Master Di Guazzo Dino & C. Snc",
    "wof:placetype":"venue"
},
  "geometry": {"coordinates":[11.740091,45.762066],"type":"Point"}
}