{
  "type": "Feature",
  "properties": {
    "iso:country":"IT",
    "sg:address":"66010 Tollo",
    "sg:city":"Ari",
    "sg:orig_category":"Bevande, Vini E Liquori. Ristorazione E Locali Pubblici Affini. Ristoranti Ed Esercizi Affini. Servizi Ausiliari Di Ristorazione E Di Intrattenimento",
    "sg:phone":"+39 0871 961810",
    "sg:postcode":"66010",
    "sg:province":"Chieti",
    "wof:name":"Ristorante Le Maschere",
    "wof:placetype":"venue"
},
  "geometry": {"coordinates":[14.304278,42.295998],"type":"Point"}
}