{
  "type": "Feature",
  "properties": {
    "addr:full":"39042 Bressanone Bressanone Bolzano/Bozen 39042",
    "addr:postcode":"39042;39042",
    "iso:country":"IT",
    "sg:address":"39042 Bressanone",
    "sg:city":"Bressanone",
    "sg:orig_category":"Serramenti Ed Infissi",
    "sg:phone":"+39 0472 834522",
    "sg:postcode":"39042",
    "sg:province":"Bolzano/Bozen",
    "sg:website":"http://www.mantinger-metallbau.com",
    "wof:name":"Mantinger Metallbau Sas",
    "wof:placetype":"venue"
},
  "geometry": {"coordinates":[11.664408,46.711765],"type":"Point"}
}