{
  "type": "Feature",
  "properties": {
    "iso:country":"IT",
    "sg:address":"41019 Soliera",
    "sg:city":"Soliera",
    "sg:classifiers":[
        {
            "category":"Building & Trades",
            "subcategory":"Equipment Rental",
            "type":"Services"
        }
    ],
    "sg:phone":"+39 059 561094",
    "sg:postcode":"41019",
    "sg:province":"Modena",
    "sg:tags":[
        "services",
        "refrigeration",
        "accommodation",
        "supply"
    ],
    "sg:website":"http://www.icam-inox.com",
    "wof:name":"Icam Inox Srl",
    "wof:placetype":"venue"
},
  "geometry": {"coordinates":[10.898629,44.744762],"type":"Point"}
}