{
  "type": "Feature",
  "properties": {
    "addr:full":"00147 Roma Roma Roma 00147",
    "addr:postcode":"00147;00147",
    "iso:country":"IT",
    "sg:address":"00147 Roma",
    "sg:city":"Roma",
    "sg:orig_category":"Caminetti, Forni Da Giardino E Barbecues",
    "sg:phone":"+39 06 5160 1407",
    "sg:postcode":"00147",
    "sg:province":"Roma",
    "wof:name":"Creazioni Fuoco",
    "wof:placetype":"venue"
},
  "geometry": {"coordinates":[12.501133,41.853874],"type":"Point"}
}