{
  "type": "Feature",
  "properties": {
    "iso:country":"IT",
    "sg:address":"00189 Roma",
    "sg:city":"Roma",
    "sg:orig_category":"Calzature, Pelletterie E Pelli. Servizi E Lavori Per Abbigliamento E Pelletterie",
    "sg:phone":"+39 06 335 1142",
    "sg:postcode":"00189",
    "sg:province":"Roma",
    "wof:name":"Lori Adolfo",
    "wof:placetype":"venue"
},
  "geometry": {"coordinates":[12.449522,41.980042],"type":"Point"}
}