{
  "type": "Feature",
  "properties": {
    "iso:country":"IT",
    "sg:address":"Via Folgaria 8 21100 Varese",
    "sg:city":"Varese",
    "sg:classifiers":[
        {
            "category":"Organizations",
            "subcategory":"Membership Organization",
            "type":"Services"
        }
    ],
    "sg:phone":"+39 0332 335010",
    "sg:postcode":"21100",
    "sg:province":"Varese",
    "sg:tags":[
        "beer",
        "tap",
        "system"
    ],
    "wof:name":"Ips Di Neri Alberto & C. Sas",
    "wof:placetype":"venue"
},
  "geometry": {"coordinates":[8.845823,45.815529],"type":"Point"}
}