{
  "type": "Feature",
  "properties": {
    "iso:country":"IT",
    "sg:address":"25047 Darfo Boario Terme",
    "sg:city":"Darfo",
    "sg:orig_category":"Elettrodomestici. Forniture Alle Strutture Ricettive",
    "sg:phone":"+39 036 453 4813",
    "sg:postcode":"25047",
    "sg:province":"Brescia",
    "wof:name":"Protec Sinergie Srl Di Pedersoli Gian Paolo",
    "wof:placetype":"venue"
},
  "geometry": {"coordinates":[10.212273,45.876549],"type":"Point"}
}