{
  "type": "Feature",
  "properties": {
    "addr:full":"40139 Bologna Bologna Bologna 40139",
    "addr:postcode":"40139;40139",
    "iso:country":"IT",
    "sg:address":"40139 Bologna",
    "sg:city":"Bologna",
    "sg:orig_category":"Telecomunicazioni E Telefonia, Impianti, Apparecchi E Servizi",
    "sg:phone":"+39 051 627 8668",
    "sg:postcode":"40139",
    "sg:province":"Bologna",
    "sg:website":"http://www.radiosystem.it",
    "wof:name":"Radio System Srl",
    "wof:placetype":"venue"
},
  "geometry": {"coordinates":[11.391461,44.474369],"type":"Point"}
}