{
  "type": "Feature",
  "properties": {
    "iso:country":"IT",
    "sg:address":"01035 Gallese",
    "sg:city":"Gallese",
    "sg:orig_category":"Legno E Semilavorati. Apparecchiature E Sistemi Per Magazzinaggio E Movimentazione",
    "sg:phone":"+39 0761 496727",
    "sg:postcode":"01035",
    "sg:province":"Viterbo",
    "wof:name":"Legnami & Imballaggi Gallese Srl",
    "wof:placetype":"venue"
},
  "geometry": {"coordinates":[12.439001,42.380333],"type":"Point"}
}