{
  "type": "Feature",
  "properties": {
    "addr:full":"24068 Seriate Seriate Bergamo 24068",
    "addr:postcode":"24068;24068",
    "iso:country":"IT",
    "sg:address":"24068 Seriate",
    "sg:city":"Seriate",
    "sg:orig_category":"Servizi E Lavori Per Ecologia E Smaltimento Rifiuti. Termotecnica E Riscaldamento, Apparecchiature E Servizi. Servizi Ausiliari Di Sorveglianza, Manutenzione E Pulizia",
    "sg:phone":"+39 035 297372",
    "sg:postcode":"24068",
    "sg:province":"Bergamo",
    "wof:name":"Cortinovis Isaia",
    "wof:placetype":"venue"
},
  "geometry": {"coordinates":[9.731078,45.678082],"type":"Point"}
}