{
  "type": "Feature",
  "properties": {
    "addr:full":"25030 Coccaglio Coccaglio Brescia 25030",
    "addr:postcode":"25030;25030",
    "iso:country":"IT",
    "sg:address":"25030 Coccaglio",
    "sg:city":"Coccaglio",
    "sg:classifiers":[
        {
            "category":"Manufacturing",
            "subcategory":"Metals",
            "type":"Manufacturing & Wholesale Goods"
        }
    ],
    "sg:phone":"+39 030 772 1850",
    "sg:postcode":"25030",
    "sg:province":"Brescia",
    "sg:tags":[
        "product",
        "various"
    ],
    "sg:website":"http://www.deantoni.it",
    "wof:name":"Dan Di De Antoni Srl",
    "wof:placetype":"venue"
},
  "geometry": {"coordinates":[9.975315,45.565647],"type":"Point"}
}