{
  "type": "Feature",
  "properties": {
    "iso:country":"IT",
    "sg:address":"Viale Giulio Cesare, 90; Roma",
    "sg:classifiers":[
        {
            "category":"Banks & Credit Unions",
            "subcategory":"Bank",
            "type":"Services"
        }
    ],
    "sg:phone":"+39 06 350275",
    "wof:name":"Banca Di Roma",
    "wof:placetype":"venue"
},
  "geometry": {"coordinates":[12.456773,41.9091],"type":"Point"}
}