{
  "type": "Feature",
  "properties": {
    "addr:full":"00135 Roma Roma Roma 00135",
    "addr:postcode":"00135;00135",
    "iso:country":"IT",
    "sg:address":"00135 Roma",
    "sg:city":"Roma",
    "sg:orig_category":"Prodotti Chimici Di Base",
    "sg:phone":"+39 06 338 5801",
    "sg:postcode":"00135",
    "sg:province":"Roma",
    "sg:website":"http://www.rotocut.it",
    "wof:name":"Rotocut Italiana",
    "wof:placetype":"venue"
},
  "geometry": {"coordinates":[12.4208641052,41.9490013123],"type":"Point"}
}