{
  "type": "Feature",
  "properties": {
    "iso:country":"IT",
    "sg:address":"46/a, Via Pellico Silvio 30010 Camponogara",
    "sg:city":"Camponogara",
    "sg:classifiers":[
        {
            "category":"Utilities",
            "subcategory":"Electric",
            "type":"Services"
        }
    ],
    "sg:phone":"+39 39041462471",
    "sg:postcode":"30010",
    "sg:province":"Venezia",
    "sg:tags":[
        "component",
        "electronic"
    ],
    "wof:name":"Simer (s.n.c.)",
    "wof:placetype":"venue"
},
  "geometry": {"coordinates":[12.338784,45.434338],"type":"Point"}
}