{
  "type": "Feature",
  "properties": {
    "iso:country":"IT",
    "sg:address":"Viale Della Costitutzione 9/a; Levata",
    "sg:classifiers":[
        {
            "category":"Banks & Credit Unions",
            "subcategory":"Bank",
            "type":"Services"
        }
    ],
    "sg:phone":"+39 0376 47710",
    "wof:name":"Banca Agricola Mantovana Scarl",
    "wof:placetype":"venue"
},
  "geometry": {"coordinates":[10.765775,45.124359],"type":"Point"}
}