{
  "type": "Feature",
  "properties": {
    "addr:full":"64, Via Felice Pusterla 22070 Grandate Grandate Como 22070",
    "addr:postcode":"22070;22070",
    "addr:street":"Via Felice Pusterla",
    "iso:country":"IT",
    "sg:address":"64, Via Felice Pusterla 22070 Grandate",
    "sg:city":"Grandate",
    "sg:classifiers":[
        {
            "category":"Shopping",
            "subcategory":"Clothing, Apparel, & Fashions",
            "type":"Retail Goods"
        }
    ],
    "sg:phone":"+39 39031398311",
    "sg:postcode":"22070",
    "sg:province":"Como",
    "sg:tags":[
        "clothes"
    ],
    "wof:name":"Union Spa-il Cavallo A Dondolo",
    "wof:placetype":"venue"
},
  "geometry": {"coordinates":[9.085456,45.811966],"type":"Point"}
}