{
  "type": "Feature",
  "properties": {
    "iso:country":"IT",
    "sg:address":"33080 Porcia",
    "sg:city":"Porcia",
    "sg:orig_category":"Serramenti Ed Infissi",
    "sg:phone":"+39 0434 361097",
    "sg:postcode":"33080",
    "sg:province":"Pordenone",
    "wof:name":"Falegnameria Valeri Rodolfo & Figli Snc",
    "wof:placetype":"venue"
},
  "geometry": {"coordinates":[12.629297,45.951836],"type":"Point"}
}