{
  "type": "Feature",
  "properties": {
    "iso:country":"IT",
    "sg:address":"20158 Milano",
    "sg:city":"Milano",
    "sg:orig_category":"Servizi Vari Di Interesse Pubblico",
    "sg:phone":"+39 02 376 0479",
    "sg:postcode":"20158",
    "sg:province":"Milano",
    "wof:name":"Sis Societa' Itali. Scommesse",
    "wof:placetype":"venue"
},
  "geometry": {"coordinates":[9.165641,45.497536],"type":"Point"}
}