{
  "type": "Feature",
  "properties": {
    "iso:country":"IT",
    "sg:address":"20040 Cambiago",
    "sg:city":"Cambiago",
    "sg:orig_category":"Attrezzature Meccaniche",
    "sg:phone":"+39 02 950 6382",
    "sg:postcode":"20040",
    "sg:province":"Milano",
    "wof:name":"Riva Antonio",
    "wof:placetype":"venue"
},
  "geometry": {"coordinates":[9.434307,45.579643],"type":"Point"}
}