{
  "type": "Feature",
  "properties": {
    "iso:country":"IT",
    "sg:address":"42019 Scandiano",
    "sg:orig_category":"Campeggio. Automobili E Mezzi Di Trasporto",
    "sg:phone":"+39 0522 857309",
    "sg:postcode":"42019",
    "sg:province":"Reggio Nell'Emilia",
    "wof:name":"Benassi Fratelli Snc",
    "wof:placetype":"venue"
},
  "geometry": {"coordinates":[10.689175,44.605984],"type":"Point"}
}