{
  "type": "Feature",
  "properties": {
    "iso:country":"IT",
    "sg:address":"Via Puccini 6a 42018 San Martino In Rio",
    "sg:classifiers":[
        {
            "category":"Manufacturing",
            "subcategory":"Tools & Machinery",
            "type":"Manufacturing & Wholesale Goods"
        }
    ],
    "sg:phone":"+39 0522 695890",
    "sg:postcode":"42018",
    "sg:province":"Reggio Nell'Emilia",
    "sg:tags":[
        "machine",
        "agriculture",
        "special"
    ],
    "sg:website":"www.rppaterlini.com",
    "wof:name":"Paterlini Remo Officina Meccanica",
    "wof:placetype":"venue"
},
  "geometry": {"coordinates":[10.775349,44.732738],"type":"Point"}
}