{
  "type": "Feature",
  "properties": {
    "iso:country":"IT",
    "sg:address":"20144 Milano",
    "sg:city":"Milano",
    "sg:orig_category":"Abbigliamento Intimo, Calze E Costumi Da Bagno",
    "sg:phone":"+39 02 4800 5443",
    "sg:postcode":"20144",
    "sg:province":"Milano",
    "wof:name":"Puia Srl",
    "wof:placetype":"venue"
},
  "geometry": {"coordinates":[9.163219,45.466244],"type":"Point"}
}