{
  "type": "Feature",
  "properties": {
    "addr:full":"Piazza Levi 11; Acqui Terme; 15011 Acqui Terme Alessandria 15011",
    "addr:housenumber":"11",
    "addr:postcode":"15011;15011",
    "addr:street":"Piazza Levi",
    "iso:country":"IT",
    "sg:address":"Piazza Levi 11; Acqui Terme; 15011",
    "sg:city":"Acqui Terme",
    "sg:classifiers":[
        {
            "category":"Banks & Credit Unions",
            "subcategory":"Bank",
            "type":"Services"
        }
    ],
    "sg:phone":"+39 0144 356090",
    "sg:postcode":"15011",
    "sg:province":"Alessandria",
    "wof:name":"Banca Nazionale Del Lavoro Spa",
    "wof:placetype":"venue"
},
  "geometry": {"coordinates":[8.469853,44.676319],"type":"Point"}
}