{
  "type": "Feature",
  "properties": {
    "addr:full":"51018 Pieve A Nievole Pieve a Nievole Pistoia 51018",
    "addr:postcode":"51018;51018",
    "addr:street":"A Nievole",
    "iso:country":"IT",
    "sg:address":"51018 Pieve A Nievole",
    "sg:city":"Pieve a Nievole",
    "sg:orig_category":"Scuole Di Ballo E Danza Classica E Moderna",
    "sg:phone":"+39 0572 952865",
    "sg:postcode":"51018",
    "sg:province":"Pistoia",
    "sg:website":"http://www.progetto-danza.com",
    "wof:name":"Progetto Danza",
    "wof:placetype":"venue"
},
  "geometry": {"coordinates":[10.794364,43.873917],"type":"Point"}
}