{
  "type": "Feature",
  "properties": {
    "iso:country":"IT",
    "sg:address":"33030 Campoformido",
    "sg:city":"Campoformido",
    "sg:orig_category":"Escavatori E Draghe",
    "sg:phone":"+39 0432 652584",
    "sg:postcode":"33030",
    "sg:province":"Udine",
    "wof:name":"Salomoni Srl",
    "wof:placetype":"venue"
},
  "geometry": {"coordinates":[13.229218,46.06638],"type":"Point"}
}