{
  "type": "Feature",
  "properties": {
    "iso:country":"IT",
    "sg:address":"38, Via Mucedola Monsignore 70014 Conversano",
    "sg:city":"Conversano",
    "sg:classifiers":[
        {
            "category":"Utilities",
            "subcategory":"Telephone",
            "type":"Services"
        }
    ],
    "sg:phone":"+39 080 495 9090",
    "sg:postcode":"70014",
    "sg:province":"Bari",
    "sg:tags":[
        "telecommunication"
    ],
    "wof:name":"Tecnovoice",
    "wof:placetype":"venue"
},
  "geometry": {"coordinates":[16.869291,41.126053],"type":"Point"}
}