{
  "type": "Feature",
  "properties": {
    "iso:country":"IT",
    "sg:address":"00149 Roma",
    "sg:city":"Roma",
    "sg:orig_category":"Elettrotecnica Industriale, Prodotti E Apparecchiature. Elettronica Industriale, Prodotti E Apparecchiature",
    "sg:phone":"+39 06 6574 7353",
    "sg:postcode":"00149",
    "sg:province":"Roma",
    "wof:name":"Lap Srl",
    "wof:placetype":"venue"
},
  "geometry": {"coordinates":[12.438282,41.84972],"type":"Point"}
}