{
  "type": "Feature",
  "properties": {
    "iso:country":"IT",
    "sg:address":"20060 Pessano Con Bornago",
    "sg:city":"Ornago",
    "sg:orig_category":"Macchine, Impianti Ed Attrezzature Per Abbigliamento E Pelletterie. Apparecchiature Ed Attrezzature Meccaniche. Elettrotecnica Industriale, Prodotti E Apparecchiature",
    "sg:phone":"+39 02 950 4961",
    "sg:postcode":"20060",
    "sg:province":"Milano",
    "wof:name":"N.s. Di Novara Sandro S.r.l.",
    "wof:placetype":"venue"
},
  "geometry": {"coordinates":[9.400857,45.543865],"type":"Point"}
}