{
  "type": "Feature",
  "properties": {
    "iso:country":"IT",
    "sg:address":"23900 Lecco",
    "sg:city":"Lecco",
    "sg:orig_category":"Associazioni Ed Organismi Di Interesse Pubblico",
    "sg:phone":"+39 0341 365555",
    "sg:postcode":"23900",
    "sg:province":"Lecco",
    "wof:name":"Movimento Consumatori",
    "wof:placetype":"venue"
},
  "geometry": {"coordinates":[9.415548,45.849552],"type":"Point"}
}