{
  "type": "Feature",
  "properties": {
    "iso:country":"IT",
    "sg:address":"41100 Modena",
    "sg:city":"Modena",
    "sg:orig_category":"Carpenterie Ferro",
    "sg:phone":"+39 059 283447",
    "sg:postcode":"41100",
    "sg:province":"Modena",
    "wof:name":"Ansaloni & Reami Srl",
    "wof:placetype":"venue"
},
  "geometry": {"coordinates":[10.976322,44.6404],"type":"Point"}
}