{
  "type": "Feature",
  "properties": {
    "iso:country":"IT",
    "sg:address":"Corso Canonico Allamano 46 10095 Grugliasco",
    "sg:city":"Grugliasco",
    "sg:classifiers":[
        {
            "category":"Autos & Motor Vehicles",
            "subcategory":"Automobile Sales",
            "type":"Retail Goods"
        }
    ],
    "sg:phone":"+39 011 40111",
    "sg:postcode":"10095",
    "sg:province":"Torino",
    "sg:tags":[
        "passenger",
        "car"
    ],
    "sg:website":"www.bertone.it",
    "wof:name":"Carrozzeria Bertone Spa",
    "wof:placetype":"venue"
},
  "geometry": {"coordinates":[7.6009635925,45.0516929626],"type":"Point"}
}