{
  "type": "Feature",
  "properties": {
    "iso:country":"IT",
    "sg:address":"Via Piana Di S. Marziale 53034 Colle Di Val D'elsa",
    "sg:classifiers":[
        {
            "category":"Shopping",
            "type":"Retail Goods"
        }
    ],
    "sg:phone":"+39 0577 929049",
    "sg:postcode":"53034",
    "sg:province":"Siena",
    "sg:tags":[
        "finished",
        "-",
        "metallic"
    ],
    "wof:name":"Officine S.l. (s.r.l.)",
    "wof:placetype":"venue"
},
  "geometry": {"coordinates":[11.3305139542,43.3186607361],"type":"Point"}
}