{
  "type": "Feature",
  "properties": {
    "iso:country":"IT",
    "sg:address":"50136 Firenze",
    "sg:city":"Firenze",
    "sg:orig_category":"Forniture Alle Strutture Ricettive. Macchine E Impianti Per Attivita' Commerciali Ed Artigianali",
    "sg:phone":"+39 055 650 3903",
    "sg:postcode":"50136",
    "sg:province":"Firenze",
    "wof:name":"Cherici Renato S.r.l.",
    "wof:placetype":"venue"
},
  "geometry": {"coordinates":[11.3015899658,43.7676010132],"type":"Point"}
}