{
  "type": "Feature",
  "properties": {
    "iso:country":"IT",
    "sg:address":"63, Via Treviso 30026 Portogruaro",
    "sg:city":"Portogruaro",
    "sg:classifiers":[
        {
            "category":"Professional",
            "subcategory":"Engineering",
            "type":"Services"
        }
    ],
    "sg:phone":"+39 0421 204560",
    "sg:postcode":"30026",
    "sg:province":"Venezia",
    "sg:tags":[
        "machine",
        "-",
        "mechanical"
    ],
    "wof:name":"Interpump Cleaning Spa",
    "wof:placetype":"venue"
},
  "geometry": {"coordinates":[12.780926,45.783558],"type":"Point"}
}