{
  "type": "Feature",
  "properties": {
    "addr:full":"00185 Roma Roma Roma 00185",
    "addr:postcode":"00185;00185",
    "iso:country":"IT",
    "sg:address":"00185 Roma",
    "sg:city":"Roma",
    "sg:orig_category":"Antenne Radio-televisione",
    "sg:phone":"+39 06 7049 5787",
    "sg:postcode":"00185",
    "sg:province":"Roma",
    "wof:name":"Sat Elettronica Snc",
    "wof:placetype":"venue"
},
  "geometry": {"coordinates":[12.502592,41.890789],"type":"Point"}
}