{
  "type": "Feature",
  "properties": {
    "iso:country":"IT",
    "sg:address":"00186 Roma",
    "sg:city":"Roma",
    "sg:orig_category":"Zootecnia E Pesca, Allevamento Piccoli Animali",
    "sg:phone":"+39 06 687 5184",
    "sg:postcode":"00186",
    "sg:province":"Roma",
    "wof:name":"C.i.r.s.pe. S.c.r.l.",
    "wof:placetype":"venue"
},
  "geometry": {"coordinates":[12.473204,41.901546],"type":"Point"}
}