{
  "type": "Feature",
  "properties": {
    "addr:full":"8/10, Viale Toselli Pietro 53100 Siena Siena Siena 53100",
    "addr:housenumber":"8 / 10",
    "addr:postcode":"53100;53100",
    "addr:street":"Viale Toselli Pietro",
    "iso:country":"IT",
    "sg:address":"8/10, Viale Toselli Pietro 53100 Siena",
    "sg:city":"Siena",
    "sg:classifiers":[
        {
            "category":"Farming",
            "subcategory":"Livestock Farm",
            "type":"Manufacturing & Wholesale Goods"
        }
    ],
    "sg:phone":"+39 39057744595",
    "sg:postcode":"53100",
    "sg:province":"Siena",
    "sg:tags":[
        "agriculture"
    ],
    "wof:name":"Lorenzini 2 S.r.l.",
    "wof:placetype":"venue"
},
  "geometry": {"coordinates":[11.343118,43.325333],"type":"Point"}
}