{
  "type": "Feature",
  "properties": {
    "addr:full":"140, Via Dell' Industriaa 61100 Pesaro Pesaro Pesaro E Urbino 61100",
    "addr:housenumber":"140",
    "addr:postcode":"61100;61100",
    "addr:street":"Via Dell ' Industriaa",
    "iso:country":"IT",
    "sg:address":"140, Via Dell' Industriaa 61100 Pesaro",
    "sg:city":"Pesaro",
    "sg:classifiers":[
        {
            "category":"Home & Garden",
            "subcategory":"Home Furnishings",
            "type":"Retail Goods"
        }
    ],
    "sg:phone":"+39 0721 481004",
    "sg:postcode":"61100",
    "sg:province":"Pesaro E Urbino",
    "sg:tags":[
        "household"
    ],
    "wof:name":"Bierre Di Broccoli F. & C. Snc",
    "wof:placetype":"venue"
},
  "geometry": {"coordinates":[12.529803,43.633556],"type":"Point"}
}