{
  "type": "Feature",
  "properties": {
    "addr:full":"41030 Bastiglia Bastiglia Modena 41030",
    "addr:postcode":"41030;41030",
    "addr:street":"Bastiglia Bastiglia Modena",
    "iso:country":"IT",
    "sg:address":"41030 Bastiglia",
    "sg:city":"Bastiglia",
    "sg:orig_category":"Macchine Utensili E Impianti",
    "sg:phone":"+39 059 904910",
    "sg:postcode":"41030",
    "sg:province":"Modena",
    "wof:name":"P Macchine S.r.l.",
    "wof:placetype":"venue"
},
  "geometry": {"coordinates":[11.002681,44.72718],"type":"Point"}
}