{
  "type": "Feature",
  "properties": {
    "iso:country":"IT",
    "sg:address":"Via Nazario Sauro, 2; Biella; 13051",
    "sg:classifiers":[
        {
            "category":"Banks & Credit Unions",
            "subcategory":"Bank",
            "type":"Services"
        }
    ],
    "sg:phone":"+39 015 355595",
    "wof:name":"Credito Varesino",
    "wof:placetype":"venue"
},
  "geometry": {"coordinates":[8.054112,45.562817],"type":"Point"}
}