{
  "type": "Feature",
  "properties": {
    "iso:country":"IT",
    "sg:address":"47900 Rimini",
    "sg:city":"Rimini",
    "sg:orig_category":"Automazione E Macchine Per Ufficio. Forniture Industriali Per Prevenzione, Controllo E Sicurezza",
    "sg:phone":"+39 0541 388582",
    "sg:postcode":"47900",
    "sg:province":"Rimini",
    "sg:website":"http://www.socos.it",
    "wof:name":"Socos Snc Di A. Borsetti & C.",
    "wof:placetype":"venue"
},
  "geometry": {"coordinates":[12.585273,44.024803],"type":"Point"}
}