{
  "type": "Feature",
  "properties": {
    "iso:country":"IT",
    "sg:address":"21052 Busto Arsizio",
    "sg:city":"Busto Arsizio",
    "sg:orig_category":"Servizi Ausiliari Di Sorveglianza, Manutenzione E Pulizia",
    "sg:phone":"+39 0331 323350",
    "sg:postcode":"21052",
    "sg:province":"Varese",
    "wof:name":"Nuova Prealpol Srl",
    "wof:placetype":"venue"
},
  "geometry": {"coordinates":[8.857913,45.6269],"type":"Point"}
}