{
  "type": "Feature",
  "properties": {
    "iso:country":"IT",
    "sg:address":"11, Via F. Romana 10083 Favria",
    "sg:city":"Favria",
    "sg:classifiers":[
        {
            "category":"Wholesale",
            "subcategory":"Drugs",
            "type":"Manufacturing & Wholesale Goods"
        }
    ],
    "sg:phone":"+39 39012434002",
    "sg:postcode":"10083",
    "sg:province":"Torino",
    "sg:tags":[
        "chemical",
        "pharmaceutical"
    ],
    "wof:name":"Costantino A. & C. (s.p.a.)",
    "wof:placetype":"venue"
},
  "geometry": {"coordinates":[7.686619,45.07056],"type":"Point"}
}