{
  "type": "Feature",
  "properties": {
    "iso:country":"IT",
    "sg:address":"50063 Figline Valdarno",
    "sg:city":"Figline Valdarno",
    "sg:orig_category":"Macchine E Forniture Per Arredamento E Industria Del Legno. Utensili Meccanici E Materiali",
    "sg:postcode":"50063",
    "sg:province":"Firenze",
    "wof:name":"Utensili International (s.r.l.)",
    "wof:placetype":"venue"
},
  "geometry": {"coordinates":[11.411205,43.619465],"type":"Point"}
}