{
  "type": "Feature",
  "properties": {
    "iso:country":"IT",
    "sg:address":"3, V. Nappi 83100 Avellino",
    "sg:city":"Avellino",
    "sg:classifiers":[
        {
            "category":"Professional",
            "subcategory":"Computer Services",
            "type":"Services"
        }
    ],
    "sg:phone":"+39 39082530544",
    "sg:postcode":"83100",
    "sg:province":"Avellino",
    "sg:tags":[
        "information",
        "technology"
    ],
    "sg:website":"http://www.notangle.com",
    "wof:name":"Notangle Srl",
    "wof:placetype":"venue"
},
  "geometry": {"coordinates":[14.794396,40.914902],"type":"Point"}
}