{
  "type": "Feature",
  "properties": {
    "iso:country":"IT",
    "sg:address":"73100 Lecce",
    "sg:city":"Lecce",
    "sg:orig_category":"Articoli Per Imballaggio E Confezionamento. Forniture Per Uffici. Forniture Per Attivita' Commerciali Ed Artigianali",
    "sg:phone":"+39 0832 349228",
    "sg:postcode":"73100",
    "sg:province":"Lecce",
    "wof:name":"Studiopack Srl",
    "wof:placetype":"venue"
},
  "geometry": {"coordinates":[18.178135,40.349041],"type":"Point"}
}