{
  "type": "Feature",
  "properties": {
    "iso:country":"IT",
    "sg:address":"20, Corso Genova 15050 Carbonara Scrivia",
    "sg:city":"Carbonara Scrivia",
    "sg:classifiers":[
        {
            "category":"Manufacturing",
            "subcategory":"Rubber & Plastics",
            "type":"Manufacturing & Wholesale Goods"
        }
    ],
    "sg:phone":"+39 0131 892584",
    "sg:postcode":"15050",
    "sg:province":"Alessandria",
    "wof:name":"Mopla (s.r.l.)",
    "wof:placetype":"venue"
},
  "geometry": {"coordinates":[8.8544082642,44.8548660278],"type":"Point"}
}