{
  "type": "Feature",
  "properties": {
    "iso:country":"IT",
    "sg:address":"7/9, Via Mantegna 13019 Varallo",
    "sg:city":"Varallo",
    "sg:classifiers":[
        {
            "category":"Manufacturing",
            "subcategory":"Wood Products",
            "type":"Manufacturing & Wholesale Goods"
        }
    ],
    "sg:phone":"+39 39016354488",
    "sg:postcode":"13019",
    "sg:province":"Vercelli",
    "sg:tags":[
        "furniture"
    ],
    "wof:name":"Eco Carpets S.a.s.",
    "wof:placetype":"venue"
},
  "geometry": {"coordinates":[8.265799,45.814663],"type":"Point"}
}