{
  "type": "Feature",
  "properties": {
    "addr:full":"37047 S.bonifacio Verona 37047",
    "addr:postcode":"37047;37047",
    "addr:street":"S.Bonifacio",
    "iso:country":"IT",
    "sg:address":"37047 S.bonifacio",
    "sg:orig_category":"Analisi Chimiche, Industriali E Merceologiche",
    "sg:phone":"+39 045 610 1643",
    "sg:postcode":"37047",
    "sg:province":"Verona",
    "sg:website":"http://www.pakelo.it",
    "wof:name":"Pakelo Motor Oil Srl",
    "wof:placetype":"venue"
},
  "geometry": {"coordinates":[10.9988470078,45.4470787048],"type":"Point"}
}