{
  "type": "Feature",
  "properties": {
    "iso:country":"IT",
    "sg:address":"1, Via Campagna Gello 56025 Pontedera",
    "sg:city":"Pontedera",
    "sg:classifiers":[
        {
            "category":"Food & Beverages",
            "subcategory":"Groceries & Convenience Stores",
            "type":"Retail Goods"
        }
    ],
    "sg:phone":"+39 0587 292900",
    "sg:postcode":"56025",
    "sg:province":"Pisa",
    "sg:tags":[
        "drink"
    ],
    "wof:name":"Castellani Spa",
    "wof:placetype":"venue"
},
  "geometry": {"coordinates":[10.396585,43.716137],"type":"Point"}
}