{
  "type": "Feature",
  "properties": {
    "addr:full":"11 Via Novelli Giovanni, 00166 Roma Roma Roma 00166",
    "addr:postcode":"00166;00166",
    "addr:street":"Via Novelli Giovanni",
    "iso:country":"IT",
    "sg:address":"11 Via Novelli Giovanni, 00166 Roma",
    "sg:city":"Roma",
    "sg:classifiers":[
        {
            "category":"Banks & Credit Unions",
            "subcategory":"Financial Services",
            "type":"Services"
        }
    ],
    "sg:phone":"+39 39066633508",
    "sg:postcode":"00166",
    "sg:province":"Roma",
    "sg:tags":[
        "banking",
        "finance",
        "insurance"
    ],
    "wof:name":"Tricofarma Srl",
    "wof:placetype":"venue"
},
  "geometry": {"coordinates":[12.4823246002,41.8954658508],"type":"Point"}
}