{
  "type": "Feature",
  "properties": {
    "iso:country":"IT",
    "sg:address":"Ss Valnerina 209 62034 Muccia",
    "sg:city":"Muccia",
    "sg:orig_category":"Herbal Liqueurs And Spice Liqueurs",
    "sg:phone":"+39 0737 647000",
    "sg:postcode":"62034",
    "sg:province":"Macerata",
    "sg:website":"www.varnelli.com",
    "wof:name":"Distilleria Varnelli Spa",
    "wof:placetype":"venue"
},
  "geometry": {"coordinates":[13.456262,43.300747],"type":"Point"}
}