{
  "type": "Feature",
  "properties": {
    "addr:full":"20121 Milano Milano Milano 20121",
    "addr:postcode":"20121;20121",
    "iso:country":"IT",
    "sg:address":"20121 Milano",
    "sg:city":"Milano",
    "sg:orig_category":"Imprese Pulizia",
    "sg:phone":"+39 02 867485",
    "sg:postcode":"20121",
    "sg:province":"Milano",
    "sg:website":"http://www.ambra91.com",
    "wof:name":"Ambra 91 Srl",
    "wof:placetype":"venue"
},
  "geometry": {"coordinates":[9.192039,45.47205],"type":"Point"}
}