{
  "type": "Feature",
  "properties": {
    "addr:full":"62100 Macerata Macerata Macerata 62100",
    "addr:postcode":"62100;62100",
    "iso:country":"IT",
    "sg:address":"62100 Macerata",
    "sg:city":"Macerata",
    "sg:orig_category":"Presse Eccentriche",
    "sg:phone":"+39 0733 202671",
    "sg:postcode":"62100",
    "sg:province":"Macerata",
    "wof:name":"O.m.e.t. Srl",
    "wof:placetype":"venue"
},
  "geometry": {"coordinates":[13.4352531433,43.2599372864],"type":"Point"}
}