{
  "type": "Feature",
  "properties": {
    "addr:full":"Via Pian Masino 96 16011 Arenzano Arenzano Genova 16011",
    "addr:housenumber":"96",
    "addr:postcode":"16011;16011",
    "addr:street":"Via Pian Masino",
    "iso:country":"IT",
    "sg:address":"Via Pian Masino 96 16011 Arenzano",
    "sg:city":"Arenzano",
    "sg:classifiers":[
        {
            "category":"Wholesale",
            "subcategory":"Chemicals & Plastics",
            "type":"Manufacturing & Wholesale Goods"
        }
    ],
    "sg:phone":"+39 010 913 0811",
    "sg:postcode":"16011",
    "sg:province":"Genova",
    "sg:tags":[
        "suitcase"
    ],
    "wof:name":"D & J Promotion S.r.l.",
    "wof:placetype":"venue"
},
  "geometry": {"coordinates":[8.6628551483,44.4047660828],"type":"Point"}
}