{
  "type": "Feature",
  "properties": {
    "addr:full":"50142 Firenze Firenze Firenze 50142",
    "addr:postcode":"50142;50142",
    "iso:country":"IT",
    "sg:address":"50142 Firenze",
    "sg:city":"Firenze",
    "sg:orig_category":"Fotolito",
    "sg:phone":"+39 055 733 1666",
    "sg:postcode":"50142",
    "sg:province":"Firenze",
    "wof:name":"Dardanelli Sas",
    "wof:placetype":"venue"
},
  "geometry": {"coordinates":[11.1900529861,43.7788238525],"type":"Point"}
}