{
  "type": "Feature",
  "properties": {
    "iso:country":"IT",
    "sg:address":"73100 Lecce",
    "sg:city":"Lecce",
    "sg:orig_category":"Macchine, Impianti Ed Attrezzature Industria Chimica. Macchine Ed Impianti Per Edilizia E Lavori Pubblici",
    "sg:phone":"+39 0832 351574",
    "sg:postcode":"73100",
    "sg:province":"Lecce",
    "wof:name":"Acquedotto Pugliese Spa",
    "wof:placetype":"venue"
},
  "geometry": {"coordinates":[18.144592,40.344139],"type":"Point"}
}