{
  "type": "Feature",
  "properties": {
    "iso:country":"IT",
    "sg:address":"00187 Roma",
    "sg:city":"Roma",
    "sg:orig_category":"Agenzie D'affari E Servizi Commerciali. Acqua, Luce, Gas E Societa' Di Esercizio Pubblico",
    "sg:phone":"+39 06 3600 4072",
    "sg:postcode":"00187",
    "sg:province":"Roma",
    "wof:name":"Semenzato Casa D'aste S.r.l.",
    "wof:placetype":"venue"
},
  "geometry": {"coordinates":[12.479304,41.908813],"type":"Point"}
}