{
  "type": "Feature",
  "properties": {
    "iso:country":"IT",
    "sg:address":"Via Mazzini 21-23; Scandiano; 42019",
    "sg:classifiers":[
        {
            "category":"Banks & Credit Unions",
            "subcategory":"Bank",
            "type":"Services"
        }
    ],
    "sg:phone":"+39 0522 982841",
    "sg:postcode":"42019",
    "sg:province":"Reggio Nell'Emilia",
    "wof:name":"Rolo Banca 1473 Spa",
    "wof:placetype":"venue"
},
  "geometry": {"coordinates":[10.686567,44.601486],"type":"Point"}
}