{
  "type": "Feature",
  "properties": {
    "iso:country":"IT",
    "sg:address":"12010 Vinadio",
    "sg:city":"Vinadio",
    "sg:orig_category":"Pubblica Amministrazione",
    "sg:phone":"+39 0171 959422",
    "sg:postcode":"12010",
    "sg:province":"Cuneo",
    "wof:name":"Guardia Di Finanza",
    "wof:placetype":"venue"
},
  "geometry": {"coordinates":[7.553730011,44.39503479],"type":"Point"}
}