{
  "type": "Feature",
  "properties": {
    "addr:full":"81100 Caserta Caserta Caserta 81100",
    "addr:postcode":"81100;81100",
    "iso:country":"IT",
    "sg:address":"81100 Caserta",
    "sg:city":"Caserta",
    "sg:classifiers":[
        {
            "category":"Bars & Pubs",
            "subcategory":"Biergarten",
            "type":"Food & Drink"
        }
    ],
    "sg:phone":"+39 0823 353473",
    "sg:postcode":"81100",
    "sg:province":"Caserta",
    "sg:tags":[
        "birrerie",
        "e"
    ],
    "sg:website":"http://www.casertanet.it/americapub",
    "wof:name":"C'era Una Volta L'america Srl",
    "wof:placetype":"venue"
},
  "geometry": {"coordinates":[14.322824,41.063507],"type":"Point"}
}