{
  "type": "Feature",
  "properties": {
    "iso:country":"IT",
    "sg:address":"41, Corso Europa 20020 Lainate",
    "sg:city":"Lainate",
    "sg:classifiers":[
        {
            "category":"Manufacturing",
            "subcategory":"Paper Products",
            "type":"Manufacturing & Wholesale Goods"
        }
    ],
    "sg:phone":"+39 39029375381",
    "sg:postcode":"20020",
    "sg:province":"Milano",
    "sg:tags":[
        "cardboard"
    ],
    "wof:name":"Itw Foils Srl",
    "wof:placetype":"venue"
},
  "geometry": {"coordinates":[9.0526199341,45.5257377625],"type":"Point"}
}