{
  "type": "Feature",
  "properties": {
    "iso:country":"IT",
    "sg:address":"51037 Montale",
    "sg:city":"Montale",
    "sg:orig_category":"Abbigliamento Esterno, Maglierie E Pelliccerie. Forniture Per Abbigliamento E Pelletterie",
    "sg:phone":"+39 0573 556972",
    "sg:postcode":"51037",
    "sg:province":"Pistoia",
    "wof:name":"Nerini Sauro",
    "wof:placetype":"venue"
},
  "geometry": {"coordinates":[11.026177,43.933525],"type":"Point"}
}