{
  "type": "Feature",
  "properties": {
    "addr:full":"60013 Corinaldo Corinaldo Ancona 60013",
    "addr:postcode":"60013;60013",
    "iso:country":"IT",
    "sg:address":"60013 Corinaldo",
    "sg:city":"Corinaldo",
    "sg:orig_category":"Prodotti E Manufatti In Materie Plastiche. Materiali Edili",
    "sg:phone":"+39 071 67665",
    "sg:postcode":"60013",
    "sg:province":"Ancona",
    "wof:name":"Isolcasa Di Bruciati R. & C. Snc",
    "wof:placetype":"venue"
},
  "geometry": {"coordinates":[13.5045080185,43.5972137451],"type":"Point"}
}