{
  "type": "Feature",
  "properties": {
    "addr:full":"27, Via Borsellino 25038 Rovato Rovato Brescia 25038",
    "addr:postcode":"25038;25038",
    "addr:street":"Via Borsellino",
    "iso:country":"IT",
    "sg:address":"27, Via Borsellino 25038 Rovato",
    "sg:city":"Rovato",
    "sg:classifiers":[
        {
            "category":"Professional",
            "subcategory":"Engineering",
            "type":"Services"
        }
    ],
    "sg:phone":"+39 030 772 1454",
    "sg:postcode":"25038",
    "sg:province":"Brescia",
    "sg:tags":[
        "machine",
        "-",
        "mechanical"
    ],
    "wof:name":"Immea Dosatrici (s.r.l.)",
    "wof:placetype":"venue"
},
  "geometry": {"coordinates":[10.009842,45.55751],"type":"Point"}
}