{
  "type": "Feature",
  "properties": {
    "addr:full":"12043 Canale Canale Cuneo 12043",
    "addr:postcode":"12043;12043",
    "iso:country":"IT",
    "sg:address":"12043 Canale",
    "sg:city":"Canale",
    "sg:orig_category":"Amplificazione Sonora",
    "sg:phone":"+39 0173 979638",
    "sg:postcode":"12043",
    "sg:province":"Cuneo",
    "sg:website":"http://www.paginegialle.it/oberaller",
    "wof:name":"Oberto & Allerino Snc",
    "wof:placetype":"venue"
},
  "geometry": {"coordinates":[8.015151,44.802776],"type":"Point"}
}