{
  "type": "Feature",
  "properties": {
    "addr:full":"58, Via Bruno Locatelli 24030 Brembate Di Sopra Brembate di Sopra Bergamo 24030",
    "addr:postcode":"24030;24030",
    "addr:street":"Via Bruno Locatelli",
    "iso:country":"IT",
    "sg:address":"58, Via Bruno Locatelli 24030 Brembate Di Sopra",
    "sg:city":"Brembate di Sopra",
    "sg:classifiers":[
        {
            "category":"Professional",
            "subcategory":"Engineering",
            "type":"Services"
        }
    ],
    "sg:phone":"+39 39035467411",
    "sg:postcode":"24030",
    "sg:province":"Bergamo",
    "sg:tags":[
        "machine",
        "-",
        "mechanical"
    ],
    "wof:name":"Alpla Brembate Srl",
    "wof:placetype":"venue"
},
  "geometry": {"coordinates":[9.582127,45.710972],"type":"Point"}
}