{
  "type": "Feature",
  "properties": {
    "iso:country":"IT",
    "sg:address":"43100 Parma",
    "sg:city":"Parma",
    "sg:orig_category":"Agenzie D'affari E Servizi Commerciali. Servizi Per Aziende, Manifestazioni E Supporto Agli Scambi Commerciali. Acqua, Luce, Gas E Societa' Di Esercizio Pubblico",
    "sg:phone":"+39 0521 21011",
    "sg:postcode":"43100",
    "sg:province":"Parma",
    "sg:website":"http://www.pr.camcom.it",
    "wof:name":"Camera Di Commercio Industria Artigianato E Agricoltura",
    "wof:placetype":"venue"
},
  "geometry": {"coordinates":[10.328317,44.807827],"type":"Point"}
}