{
  "type": "Feature",
  "properties": {
    "iso:country":"IT",
    "sg:address":"18, Via Alfredo Di Dio 21010 Besnate",
    "sg:city":"Besnate",
    "sg:classifiers":[
        {
            "category":"Manufacturing",
            "subcategory":"Metals",
            "type":"Manufacturing & Wholesale Goods"
        }
    ],
    "sg:phone":"+39 0331 274158",
    "sg:postcode":"21010",
    "sg:province":"Varese",
    "sg:tags":[
        "metallurgy",
        "metalworking"
    ],
    "wof:name":"Fonderia Leghe Leggere (s.r.l.)",
    "wof:placetype":"venue"
},
  "geometry": {"coordinates":[8.7654943466,45.7027587891],"type":"Point"}
}