{
  "type": "Feature",
  "properties": {
    "iso:country":"IT",
    "sg:address":"13855 Valdengo",
    "sg:city":"Valdengo",
    "sg:orig_category":"Macchine Utensili E Impianti",
    "sg:phone":"+39 015 881608",
    "sg:postcode":"13855",
    "sg:province":"Biella",
    "wof:name":"Officina Meccanica Cinti Paolo",
    "wof:placetype":"venue"
},
  "geometry": {"coordinates":[8.055999,45.564243],"type":"Point"}
}