{
  "type": "Feature",
  "properties": {
    "addr:full":"40, Via Rivana 36066 Sandrigo Sandrigo Vicenza 36066",
    "addr:postcode":"36066;36066",
    "addr:street":"Via Rivana",
    "iso:country":"IT",
    "sg:address":"40, Via Rivana 36066 Sandrigo",
    "sg:city":"Sandrigo",
    "sg:classifiers":[
        {
            "category":"Sports & Exercise",
            "subcategory":"Playing Field",
            "type":"Entertainment"
        }
    ],
    "sg:phone":"+39 0444 659525",
    "sg:postcode":"36066",
    "sg:province":"Vicenza",
    "sg:tags":[
        "game"
    ],
    "wof:name":"Ceramiche Arena (s.n.c.)",
    "wof:placetype":"venue"
},
  "geometry": {"coordinates":[11.607525,45.662304],"type":"Point"}
}