{
  "type": "Feature",
  "properties": {
    "iso:country":"IT",
    "sg:address":"1020, Via Cassia 00189 Roma",
    "sg:city":"Roma",
    "sg:classifiers":[
        {
            "category":"Professional",
            "subcategory":"Engineering",
            "type":"Services"
        }
    ],
    "sg:phone":"+39 06 3036 0348",
    "sg:postcode":"00189",
    "sg:province":"Roma",
    "sg:tags":[
        "machine",
        "-",
        "mechanical"
    ],
    "wof:name":"Solartec (s.p.a.)",
    "wof:placetype":"venue"
},
  "geometry": {"coordinates":[12.38226,42.035652],"type":"Point"}
}