{
  "type": "Feature",
  "properties": {
    "addr:full":"15, Via Stradone Del Dieci 45030 Villamarzana Villamarzana Rovigo 45030",
    "addr:postcode":"45030;45030",
    "addr:street":"Via Stradone Del Dieci",
    "iso:country":"IT",
    "sg:address":"15, Via Stradone Del Dieci 45030 Villamarzana",
    "sg:city":"Villamarzana",
    "sg:classifiers":[
        {
            "category":"Home & Garden",
            "subcategory":"Home Furnishings",
            "type":"Retail Goods"
        }
    ],
    "sg:phone":"+39 0425 438003",
    "sg:postcode":"45030",
    "sg:province":"Rovigo",
    "sg:tags":[
        "household"
    ],
    "wof:name":"Saga (s.r.l.)",
    "wof:placetype":"venue"
},
  "geometry": {"coordinates":[11.684006,45.016724],"type":"Point"}
}