{
  "type": "Feature",
  "properties": {
    "addr:full":"28100 Novara Novara Novara 28100",
    "addr:postcode":"28100;28100",
    "iso:country":"IT",
    "sg:address":"28100 Novara",
    "sg:city":"Novara",
    "sg:orig_category":"Termotecnica E Riscaldamento, Apparecchiature E Servizi",
    "sg:phone":"+39 0321 471751",
    "sg:postcode":"28100",
    "sg:province":"Novara",
    "wof:name":"Iser Spa",
    "wof:placetype":"venue"
},
  "geometry": {"coordinates":[8.624752,45.460396],"type":"Point"}
}