{
  "type": "Feature",
  "properties": {
    "addr:full":"22, Via Allende Salvador 26841 Casalpusterlengo Casalpusterlengo Lodi 26841",
    "addr:postcode":"26841;26841",
    "addr:street":"Via Allende",
    "iso:country":"IT",
    "sg:address":"22, Via Allende Salvador 26841 Casalpusterlengo",
    "sg:city":"Casalpusterlengo",
    "sg:classifiers":[
        {
            "category":"Manufacturing",
            "subcategory":"Metals",
            "type":"Manufacturing & Wholesale Goods"
        }
    ],
    "sg:phone":"+39 39037784953",
    "sg:postcode":"26841",
    "sg:province":"Lodi",
    "sg:tags":[
        "processing"
    ],
    "wof:name":"Bernasconi S.r.l.",
    "wof:placetype":"venue"
},
  "geometry": {"coordinates":[9.4978504181,45.312877655],"type":"Point"}
}