{
  "type": "Feature",
  "properties": {
    "addr:full":"35010 Limena Limena Padova 35010",
    "addr:postcode":"35010;35010",
    "iso:country":"IT",
    "sg:address":"35010 Limena",
    "sg:city":"Limena",
    "sg:orig_category":"Materiali E Componenti Elettrotecnici",
    "sg:phone":"+39 049 769188",
    "sg:postcode":"35010",
    "sg:province":"Padova",
    "wof:name":"Cet Eletric Srl",
    "wof:placetype":"venue"
},
  "geometry": {"coordinates":[11.856546,45.461246],"type":"Point"}
}