{
  "type": "Feature",
  "properties": {
    "iso:country":"IT",
    "sg:address":"70125 Bari",
    "sg:city":"Bari",
    "sg:classifiers":[
        {
            "category":"Health Services",
            "subcategory":"Nursing And Care Facility",
            "type":"Services"
        }
    ],
    "sg:phone":"+39 080 502 6714",
    "sg:postcode":"70125",
    "sg:province":"Bari",
    "sg:tags":[
        "case",
        "cura",
        "private",
        "di"
    ],
    "wof:name":"Sirafin Srl",
    "wof:placetype":"venue"
},
  "geometry": {"coordinates":[16.866692,41.087009],"type":"Point"}
}