{
  "type": "Feature",
  "properties": {
    "addr:full":"V Gb Fardella 371; Trapani; 91100 Trapani Trapani 91100",
    "addr:housenumber":"371",
    "addr:postcode":"91100;91100",
    "addr:street":"V;Fardella",
    "iso:country":"IT",
    "sg:address":"V Gb Fardella 371; Trapani; 91100",
    "sg:city":"Trapani",
    "sg:classifiers":[
        {
            "category":"Banks & Credit Unions",
            "subcategory":"Bank",
            "type":"Services"
        }
    ],
    "sg:phone":"+39 0923 20838",
    "sg:postcode":"91100",
    "sg:province":"Trapani",
    "wof:name":"Banca Sicula Spa",
    "wof:placetype":"venue"
},
  "geometry": {"coordinates":[12.552751,37.91608],"type":"Point"}
}