{
  "type": "Feature",
  "properties": {
    "addr:full":"35010 Borgoricco Borgoricco Padova 35010",
    "addr:postcode":"35010;35010",
    "iso:country":"IT",
    "sg:address":"35010 Borgoricco",
    "sg:city":"Borgoricco",
    "sg:orig_category":"Servizi E Lavori Per Arredamento E Industria Del Legno",
    "sg:phone":"+39 049 579 8138",
    "sg:postcode":"35010",
    "sg:province":"Padova",
    "sg:website":"http://www.vecchiato.it",
    "wof:name":"Vecchiato Di Vecchiato Siro E Diego Snc",
    "wof:placetype":"venue"
},
  "geometry": {"coordinates":[11.994308,45.534748],"type":"Point"}
}