{
  "type": "Feature",
  "properties": {
    "iso:country":"IT",
    "sg:address":"16129 Genova",
    "sg:city":"Genova",
    "sg:orig_category":"Agenzie D'affari E Servizi Commerciali",
    "sg:phone":"+39 010 586256",
    "sg:postcode":"16129",
    "sg:province":"Genova",
    "wof:name":"Centerphones",
    "wof:placetype":"venue"
},
  "geometry": {"coordinates":[8.950065,44.403214],"type":"Point"}
}