{
  "type": "Feature",
  "properties": {
    "iso:country":"IT",
    "sg:address":"13, Via Brioni 31030 Altivole",
    "sg:city":"Altivole",
    "sg:classifiers":[
        {
            "category":"Shopping",
            "subcategory":"Clothing, Apparel, & Fashions",
            "type":"Retail Goods"
        }
    ],
    "sg:phone":"+39 0423 940004",
    "sg:postcode":"31030",
    "sg:province":"Treviso",
    "sg:tags":[
        "clothes"
    ],
    "wof:name":"Efrem Sport Line Di Menegon E Bertolo S.n.c.",
    "wof:placetype":"venue"
},
  "geometry": {"coordinates":[11.915626,45.754902],"type":"Point"}
}