{
  "type": "Feature",
  "properties": {
    "addr:full":"15, Via Monte Grappa 20036 Meda Meda Milano 20036",
    "addr:postcode":"20036;20036",
    "addr:street":"Via Monte Grappa",
    "iso:country":"IT",
    "sg:address":"15, Via Monte Grappa 20036 Meda",
    "sg:city":"Meda",
    "sg:classifiers":[
        {
            "category":"Home & Garden",
            "subcategory":"Home Furnishings",
            "type":"Retail Goods"
        }
    ],
    "sg:phone":"+39 39036270509",
    "sg:postcode":"20036",
    "sg:province":"Milano",
    "sg:tags":[
        "household"
    ],
    "wof:name":"Simonetto S.r.l.",
    "wof:placetype":"venue"
},
  "geometry": {"coordinates":[9.156233,45.670353],"type":"Point"}
}