{
  "type": "Feature",
  "properties": {
    "iso:country":"IT",
    "sg:address":"6, Via Selva Casilina 03100 Frosinone",
    "sg:city":"Frosinone",
    "sg:classifiers":[
        {
            "category":"Banks & Credit Unions",
            "subcategory":"Bank",
            "type":"Services"
        }
    ],
    "sg:phone":"+39 0775 877025",
    "sg:postcode":"03100",
    "sg:province":"Frosinone",
    "sg:tags":[
        "banking",
        "institution"
    ],
    "wof:name":"Deltapol Sud Soc. Coop. Per Azioni A R. L.",
    "wof:placetype":"venue"
},
  "geometry": {"coordinates":[13.329042,41.651459],"type":"Point"}
}