{
  "type": "Feature",
  "properties": {
    "iso:country":"IT",
    "sg:address":"00122 Lido Di Ostia",
    "sg:orig_category":"Sport - Articoli E Forniture",
    "sg:phone":"+39 06 562 4309",
    "sg:postcode":"00122",
    "sg:province":"Roma",
    "wof:name":"Ennio Sport",
    "wof:placetype":"venue"
},
  "geometry": {"coordinates":[12.293578,41.726044],"type":"Point"}
}