{
  "type": "Feature",
  "properties": {
    "iso:country":"IT",
    "sg:address":"10139 Torino",
    "sg:city":"Torino",
    "sg:orig_category":"Prodotti Chimici Secondari. Macchine E Forniture Per Ecologia E Smaltimento Rifiuti. Forniture Per Attivita' Industriali",
    "sg:phone":"+39 011 382 8740",
    "sg:postcode":"10139",
    "sg:province":"Torino",
    "wof:name":"B&b Service Snc",
    "wof:placetype":"venue"
},
  "geometry": {"coordinates":[7.1200766563,45.1260185242],"type":"Point"}
}