{
  "type": "Feature",
  "properties": {
    "iso:country":"IT",
    "sg:address":"91025 Marsala",
    "sg:city":"Marsala",
    "sg:orig_category":"Arredamenti E Mobili Professionali. Complementi Di Arredamento",
    "sg:phone":"+39 0923 713871",
    "sg:postcode":"91025",
    "sg:province":"Trapani",
    "wof:name":"Fodale Pietro",
    "wof:placetype":"venue"
},
  "geometry": {"coordinates":[12.438224,37.794586],"type":"Point"}
}