{
  "type": "Feature",
  "properties": {
    "addr:full":"20131 Milano Milano Milano 20131",
    "addr:postcode":"20131;20131",
    "iso:country":"IT",
    "sg:address":"20131 Milano",
    "sg:city":"Milano",
    "sg:orig_category":"Tessuti E Stoffe",
    "sg:phone":"+39 02 284 6203",
    "sg:postcode":"20131",
    "sg:province":"Milano",
    "wof:name":"Dubini & Denti Ildegonda",
    "wof:placetype":"venue"
},
  "geometry": {"coordinates":[9.218427,45.486015],"type":"Point"}
}