{
  "type": "Feature",
  "properties": {
    "addr:full":"15, Via Dei Sabbioni 10094 Giaveno Giaveno Torino 10094",
    "addr:postcode":"10094;10094",
    "addr:street":"Via Dei Sabbioni",
    "iso:country":"IT",
    "sg:address":"15, Via Dei Sabbioni 10094 Giaveno",
    "sg:city":"Giaveno",
    "sg:classifiers":[
        {
            "category":"Professional",
            "subcategory":"Engineering",
            "type":"Services"
        }
    ],
    "sg:phone":"+39 011 936 4552",
    "sg:postcode":"10094",
    "sg:province":"Torino",
    "sg:tags":[
        "machine",
        "-",
        "mechanical"
    ],
    "wof:name":"Elto (s.p.a.)",
    "wof:placetype":"venue"
},
  "geometry": {"coordinates":[7.686619,45.07056],"type":"Point"}
}