{
  "type": "Feature",
  "properties": {
    "addr:full":"35010 Cadoneghe Cadoneghe Padova 35010",
    "addr:postcode":"35010;35010",
    "iso:country":"IT",
    "sg:address":"35010 Cadoneghe",
    "sg:city":"Cadoneghe",
    "sg:orig_category":"Termotecnica E Riscaldamento, Apparecchiature E Servizi",
    "sg:phone":"+39 049 700690",
    "sg:postcode":"35010",
    "sg:province":"Padova",
    "wof:name":"Zorzi Giorgio E Figlio",
    "wof:placetype":"venue"
},
  "geometry": {"coordinates":[11.90786,45.460503],"type":"Point"}
}