{
  "type": "Feature",
  "properties": {
    "iso:country":"IT",
    "sg:address":"20, Via Pirelli Giovanni Battista 20124 Milano",
    "sg:city":"Milano",
    "sg:classifiers":[
        {
            "category":"Professional",
            "subcategory":"Engineering",
            "type":"Services"
        }
    ],
    "sg:phone":"+39 39026787711",
    "sg:postcode":"20124",
    "sg:province":"Milano",
    "sg:tags":[
        "machine",
        "-",
        "mechanical"
    ],
    "wof:name":"Icn Biomedicals Srl",
    "wof:placetype":"venue"
},
  "geometry": {"coordinates":[9.198696,45.483936],"type":"Point"}
}