{
  "type": "Feature",
  "properties": {
    "iso:country":"IT",
    "sg:address":"00179 Roma",
    "sg:city":"Roma",
    "sg:orig_category":"Ricambi E Componenti Dei Mezzi Di Trasporto",
    "sg:phone":"+39 06 785 0958",
    "sg:postcode":"00179",
    "sg:province":"Roma",
    "wof:name":"Luisa Ferente Srl",
    "wof:placetype":"venue"
},
  "geometry": {"coordinates":[12.524619,41.869797],"type":"Point"}
}