{
  "type": "Feature",
  "properties": {
    "addr:full":"Km 41,400, V. Nazionale 84015 Nocera Superiore Nocera Superiore Salerno 84015",
    "addr:postcode":"84015;84015",
    "addr:street":"Nazionale",
    "iso:country":"IT",
    "sg:address":"Km 41,400, V. Nazionale 84015 Nocera Superiore",
    "sg:city":"Nocera Superiore",
    "sg:classifiers":[
        {
            "category":"Manufacturing",
            "subcategory":"Food",
            "type":"Manufacturing & Wholesale Goods"
        }
    ],
    "sg:phone":"+39 39081931096",
    "sg:postcode":"84015",
    "sg:province":"Salerno",
    "sg:tags":[
        "equipment",
        "processing",
        "-",
        "machinery"
    ],
    "sg:website":"http://www.officinesalzano.it",
    "wof:name":"Salzano Giovanni & C. Snc",
    "wof:placetype":"venue"
},
  "geometry": {"coordinates":[14.765912056,40.6779556274],"type":"Point"}
}