{
  "type": "Feature",
  "properties": {
    "addr:full":"Via Nazionale 12 33019 Tricesimo Tricesimo Udine 33019",
    "addr:housenumber":"12",
    "addr:postcode":"33019;33019",
    "addr:street":"Via Nazionale",
    "iso:country":"IT",
    "sg:address":"Via Nazionale 12 33019 Tricesimo",
    "sg:city":"Tricesimo",
    "sg:classifiers":[
        {
            "category":"Government",
            "subcategory":"Court House",
            "type":"Public Place"
        }
    ],
    "sg:phone":"+39 0432 851124",
    "sg:postcode":"33019",
    "sg:province":"Udine",
    "sg:tags":[
        "accommodation",
        "furniture"
    ],
    "wof:name":"Itas Di Cosani & C S.n.c.",
    "wof:placetype":"venue"
},
  "geometry": {"coordinates":[13.224566,46.126648],"type":"Point"}
}