{
  "type": "Feature",
  "properties": {
    "addr:full":"29, Via Per Castellanza 20025 Legnano Legnano Milano 20025",
    "addr:postcode":"20025;20025",
    "addr:street":"Via Per Castellanza",
    "iso:country":"IT",
    "sg:address":"29, Via Per Castellanza 20025 Legnano",
    "sg:city":"Legnano",
    "sg:classifiers":[
        {
            "category":"Shopping",
            "subcategory":"Crafts & Fabrics",
            "type":"Retail Goods"
        }
    ],
    "sg:phone":"+39 0331 546810",
    "sg:postcode":"20025",
    "sg:province":"Milano",
    "wof:name":"Ponson S.p.a.",
    "wof:placetype":"venue"
},
  "geometry": {"coordinates":[8.9088344574,45.6055297852],"type":"Point"}
}