{
  "type": "Feature",
  "properties": {
    "iso:country":"IT",
    "sg:address":"00171 Roma",
    "sg:city":"Roma",
    "sg:orig_category":"Pubblicita', Marketing E Comunicazione",
    "sg:phone":"+39 06 218 5518",
    "sg:postcode":"00171",
    "sg:province":"Roma",
    "wof:name":"De Renzis Pubblicit\u00c1 Snc",
    "wof:placetype":"venue"
},
  "geometry": {"coordinates":[12.5710420609,41.8920021057],"type":"Point"}
}