{
  "type": "Feature",
  "properties": {
    "addr:full":"121, Via Gorizia 34072 Gradisca D'isonzo Gorizia 34072",
    "addr:housenumber":"121",
    "addr:postcode":"34072;34072",
    "addr:street":"Via Gorizia",
    "iso:country":"IT",
    "sg:address":"121, Via Gorizia 34072 Gradisca D'isonzo",
    "sg:classifiers":[
        {
            "category":"Food & Beverages",
            "subcategory":"Groceries & Convenience Stores",
            "type":"Retail Goods"
        }
    ],
    "sg:phone":"+39 39048192237",
    "sg:postcode":"34072",
    "sg:province":"Gorizia",
    "sg:tags":[
        "drink"
    ],
    "wof:name":"Felluga Marco (s.r.l.)",
    "wof:placetype":"venue"
},
  "geometry": {"coordinates":[13.536602,45.904388],"type":"Point"}
}