{
  "type": "Feature",
  "properties": {
    "iso:country":"IT",
    "sg:address":"57121 Livorno",
    "sg:city":"Livorno",
    "sg:orig_category":"Elettrotecnica Industriale, Prodotti E Apparecchiature",
    "sg:phone":"+39 0586 426541",
    "sg:postcode":"57121",
    "sg:province":"Livorno",
    "wof:name":"Elettroinstallazioni Di Carlotti & Niccolai Snc",
    "wof:placetype":"venue"
},
  "geometry": {"coordinates":[10.344597,43.56752],"type":"Point"}
}