{
  "type": "Feature",
  "properties": {
    "iso:country":"IT",
    "sg:address":"20084 Lacchiarella",
    "sg:city":"Lacchiarella",
    "sg:orig_category":"Termotecnica E Riscaldamento, Apparecchiature E Servizi",
    "sg:phone":"+39 02 9003 3112",
    "sg:postcode":"20084",
    "sg:province":"Milano",
    "wof:name":"Gas Metano Tecnoassistenza S.n.c.",
    "wof:placetype":"venue"
},
  "geometry": {"coordinates":[9.136222,45.324997],"type":"Point"}
}