{
  "type": "Feature",
  "properties": {
    "addr:full":"Via Nazionale 55 Ponticino 52020 Laterina Laterina Arezzo 52020",
    "addr:housenumber":"55",
    "addr:postcode":"52020;52020",
    "addr:street":"Via Nazionale",
    "iso:country":"IT",
    "sg:address":"Via Nazionale 55 Ponticino 52020 Laterina",
    "sg:city":"Laterina",
    "sg:classifiers":[
        {
            "category":"Manufacturing",
            "subcategory":"Metals",
            "type":"Manufacturing & Wholesale Goods"
        }
    ],
    "sg:phone":"+39 0575 898736",
    "sg:postcode":"52020",
    "sg:province":"Arezzo",
    "sg:tags":[
        "metallurgy",
        "metalworking"
    ],
    "wof:name":"Monilia (s.n.c.)",
    "wof:placetype":"venue"
},
  "geometry": {"coordinates":[11.7169513702,43.4809989929],"type":"Point"}
}