{
  "type": "Feature",
  "properties": {
    "iso:country":"IT",
    "sg:address":"29, Via Brescia 20063 Cernusco Sul Naviglio",
    "sg:city":"Cernusco sul Naviglio",
    "sg:classifiers":[
        {
            "category":"Communications",
            "subcategory":"Television Station",
            "type":"Services"
        }
    ],
    "sg:phone":"+39 390 292 4401",
    "sg:postcode":"20063",
    "sg:province":"Milano",
    "sg:tags":[
        "audio-visual"
    ],
    "wof:name":"Logic Spa",
    "wof:placetype":"venue"
},
  "geometry": {"coordinates":[9.282716,45.532288],"type":"Point"}
}