{
  "type": "Feature",
  "properties": {
    "iso:country":"IT",
    "sg:address":"10148 Torino",
    "sg:city":"Torino",
    "sg:orig_category":"Cartotecnica E Servizi. Composizione, Stampa E Confezione. Servizi E Lavori Industria Delle Materie Plastiche. Servizi Per Imballaggio E Confezionamento",
    "sg:phone":"+39 011 220 1866",
    "sg:postcode":"10148",
    "sg:province":"Torino",
    "wof:name":"Teknoplast Di Cappellano G. & C. (s.a.s.)",
    "wof:placetype":"venue"
},
  "geometry": {"coordinates":[7.671482,45.113144],"type":"Point"}
}