{
  "type": "Feature",
  "properties": {
    "iso:country":"IT",
    "sg:address":"89029 Taurianova",
    "sg:city":"Taurianova",
    "sg:classifiers":[
        {
            "category":"Communications",
            "subcategory":"Film & Video Production",
            "type":"Services"
        }
    ],
    "sg:phone":"+39 0966 611770",
    "sg:postcode":"89029",
    "sg:province":"Reggio Di Calabria",
    "sg:tags":[
        "cracker",
        "e",
        "biscotti"
    ],
    "wof:name":"Murdolo Fratelli",
    "wof:placetype":"venue"
},
  "geometry": {"coordinates":[15.650137,38.114689],"type":"Point"}
}