{
  "type": "Feature",
  "properties": {
    "iso:country":"IT",
    "sg:address":"16139 Genova",
    "sg:city":"Genova",
    "sg:orig_category":"Ardesie",
    "sg:phone":"+39 010 838 0292",
    "sg:postcode":"16139",
    "sg:province":"Genova",
    "wof:name":"Fregosi Giuseppe Di Fregosi Bruna & C. Snc",
    "wof:placetype":"venue"
},
  "geometry": {"coordinates":[8.964007,44.434383],"type":"Point"}
}