{
  "type": "Feature",
  "properties": {
    "addr:full":"03100 Frosinone Frosinone Frosinone 03100",
    "addr:postcode":"03100;03100",
    "iso:country":"IT",
    "sg:address":"03100 Frosinone",
    "sg:city":"Frosinone",
    "sg:orig_category":"Costruzioni Meccaniche",
    "sg:phone":"+39 0775 291830",
    "sg:postcode":"03100",
    "sg:province":"Frosinone",
    "sg:website":"http://www.samem.com",
    "wof:name":"Samem Sas Di Lombardi M. Cristina & C.",
    "wof:placetype":"venue"
},
  "geometry": {"coordinates":[13.337976,41.621101],"type":"Point"}
}