{
  "type": "Feature",
  "properties": {
    "iso:country":"IT",
    "sg:address":"04010 Cori",
    "sg:city":"Cori",
    "sg:orig_category":"Sport - Articoli E Forniture",
    "sg:phone":"+39 06 967 8182",
    "sg:postcode":"04010",
    "sg:province":"Latina",
    "wof:name":"Carucci Antonio",
    "wof:placetype":"venue"
},
  "geometry": {"coordinates":[12.832435,41.593479],"type":"Point"}
}