{
  "type": "Feature",
  "properties": {
    "addr:full":"Via S. Alessandro 00131 Roma Roma Roma 00131",
    "addr:postcode":"00131;00131",
    "addr:street":"Via S. Alessandro",
    "iso:country":"IT",
    "sg:address":"Via S. Alessandro 00131 Roma",
    "sg:city":"Roma",
    "sg:classifiers":[
        {
            "category":"Travel",
            "subcategory":"Travel Agent",
            "type":"Entertainment"
        }
    ],
    "sg:phone":"+39 06 4140 9000",
    "sg:postcode":"00131",
    "sg:province":"Roma",
    "sg:tags":[
        "business"
    ],
    "wof:name":"Residence Torre Di Pratolungo",
    "wof:placetype":"venue"
},
  "geometry": {"coordinates":[12.484833,41.854401],"type":"Point"}
}