{
  "type": "Feature",
  "properties": {
    "addr:full":"10026 Santena Santena Torino 10026",
    "addr:housenumber":"10026",
    "addr:postcode":"10026",
    "addr:street":"Santena Santena",
    "iso:country":"IT",
    "sg:address":"10026 Santena",
    "sg:city":"Santena",
    "sg:orig_category":"Servizi E Lavori Per Abbigliamento E Pelletterie. Scuole E Servizi Scolastici. Ricerca, Selezione E Formazione Del Personale",
    "sg:phone":"+39 011 949 1625",
    "sg:postcode":"10026",
    "sg:province":"Torino",
    "wof:name":"Cani Anna",
    "wof:placetype":"venue"
},
  "geometry": {"coordinates":[7.779292,44.641384],"type":"Point"}
}