{
  "type": "Feature",
  "properties": {
    "iso:country":"IT",
    "sg:address":"40069 Zola Predosa",
    "sg:city":"Zola",
    "sg:orig_category":"Articoli Per Imballaggio E Confezionamento",
    "sg:phone":"+39 051 616 6764",
    "sg:postcode":"40069",
    "sg:province":"Bologna",
    "wof:name":"Ellebi Di Biagini Ledi",
    "wof:placetype":"venue"
},
  "geometry": {"coordinates":[11.225968,44.494858],"type":"Point"}
}