{
  "type": "Feature",
  "properties": {
    "addr:full":"Via Provinciale 5 23841 Annone Di Brianza Annone di Brianza Lecco 23841",
    "addr:housenumber":"5",
    "addr:postcode":"23841;di brianza;23841",
    "addr:street":"Via Provinciale",
    "iso:country":"IT",
    "sg:address":"Via Provinciale 5 23841 Annone Di Brianza",
    "sg:city":"Annone di Brianza",
    "sg:classifiers":[
        {
            "category":"Home & Garden",
            "subcategory":"Carpets & Floor Coverings",
            "type":"Retail Goods"
        }
    ],
    "sg:phone":"+39 0341 267011",
    "sg:postcode":"23841",
    "sg:province":"Lecco",
    "sg:tags":[
        "screed",
        "steel",
        "stainless",
        "grating"
    ],
    "wof:name":"Riva Acciaio Spa",
    "wof:placetype":"venue"
},
  "geometry": {"coordinates":[9.3598108292,45.8098106384],"type":"Point"}
}