{
  "type": "Feature",
  "properties": {
    "iso:country":"IT",
    "sg:address":"31051 Follina",
    "sg:city":"Follina",
    "sg:orig_category":"Traduttori Ed Interpreti",
    "sg:phone":"+39 0438 971794",
    "sg:postcode":"31051",
    "sg:province":"Treviso",
    "sg:website":"http://www.lstraduzioni.it",
    "wof:name":"Elle & Esse Traduzioni Di Fedato Luigino",
    "wof:placetype":"venue"
},
  "geometry": {"coordinates":[12.113674,45.950623],"type":"Point"}
}