{
  "type": "Feature",
  "properties": {
    "addr:full":"87046 Montalto Uffugo Montalto Uffugo Cosenza 87046",
    "addr:postcode":"87046;87046",
    "iso:country":"IT",
    "sg:address":"87046 Montalto Uffugo",
    "sg:city":"Montalto Uffugo",
    "sg:classifiers":[
        {
            "category":"Home & Garden",
            "subcategory":"Kitchen Supply",
            "type":"Retail Goods"
        }
    ],
    "sg:phone":"+39 0984 937041",
    "sg:postcode":"87046",
    "sg:province":"Cosenza",
    "sg:tags":[
        "houseware",
        "shopping",
        "utensil",
        "linen",
        "blankets",
        "drapery"
    ],
    "sg:website":"http://www.paginegialle.it/ricamart-cs",
    "wof:name":"Ricami Artigianali Calabresi Di Luigi Car\u00c0",
    "wof:placetype":"venue"
},
  "geometry": {"coordinates":[16.244337,39.392654],"type":"Point"}
}