{
  "type": "Feature",
  "properties": {
    "addr:full":"Loc. Imperatore 87043 Bisignano Bisignano Cosenza 87043",
    "addr:postcode":"87043;87043",
    "addr:street":"Imperatore",
    "iso:country":"IT",
    "sg:address":"Loc. Imperatore 87043 Bisignano",
    "sg:city":"Bisignano",
    "sg:classifiers":[
        {
            "category":"Food & Beverages",
            "subcategory":"Specialty",
            "type":"Retail Goods"
        }
    ],
    "sg:phone":"+39 0984 940381",
    "sg:postcode":"87043",
    "sg:province":"Cosenza",
    "sg:tags":[
        "olive-oil"
    ],
    "sg:website":"www.oliocolli.it",
    "wof:name":"Oliocolli Besidiae S.r.l.",
    "wof:placetype":"venue"
},
  "geometry": {"coordinates":[16.253809,39.298264],"type":"Point"}
}