{
  "type": "Feature",
  "properties": {
    "addr:full":"Via Piazzola 13/e 35010 Villafranca Padovana Villafranca Padovana Padova 35010",
    "addr:housenumber":"13 / e",
    "addr:postcode":"35010;35010",
    "addr:street":"Via Piazzola",
    "iso:country":"IT",
    "sg:address":"Via Piazzola 13/e 35010 Villafranca Padovana",
    "sg:city":"Villafranca Padovana",
    "sg:classifiers":[
        {
            "category":"Ice Cream",
            "type":"Food & Drink"
        }
    ],
    "sg:phone":"+39 049 905 0100",
    "sg:postcode":"35010",
    "sg:province":"Padova",
    "sg:tags":[
        "glass",
        "all-glass",
        "structures",
        "structure"
    ],
    "sg:website":"www.sunglass.it",
    "wof:name":"Sunglass Srl",
    "wof:placetype":"venue"
},
  "geometry": {"coordinates":[11.876589,45.409569],"type":"Point"}
}