{
  "type": "Feature",
  "properties": {
    "iso:country":"IT",
    "sg:address":"98121 Messina",
    "sg:city":"Messina",
    "sg:orig_category":"Estetiste",
    "sg:phone":"+39 090 573 1349",
    "sg:postcode":"98121",
    "sg:province":"Messina",
    "wof:name":"Associazione Body's Comfort",
    "wof:placetype":"venue"
},
  "geometry": {"coordinates":[15.557465,38.202286],"type":"Point"}
}