{
  "type": "Feature",
  "properties": {
    "iso:country":"IT",
    "sg:address":"21/23, V. Brig. Partigiane 15033 Casale Monferrato",
    "sg:city":"Casale Monferrato",
    "sg:classifiers":[
        {
            "category":"Shopping",
            "subcategory":"Computers & Home Electronics",
            "type":"Retail Goods"
        }
    ],
    "sg:phone":"+39 0142 464599",
    "sg:postcode":"15033",
    "sg:province":"Alessandria",
    "sg:tags":[
        "electronic",
        "electrical",
        "equipment"
    ],
    "sg:website":"http://www.paginegialle.it/",
    "wof:name":"Automation Systems Srl",
    "wof:placetype":"venue"
},
  "geometry": {"coordinates":[8.616951,44.913216],"type":"Point"}
}