{
  "type": "Feature",
  "properties": {
    "iso:country":"IT",
    "sg:address":"85050 Tito",
    "sg:city":"Tito",
    "sg:orig_category":"Apparecchiature E Sistemi Per Magazzinaggio E Movimentazione",
    "sg:phone":"+39 0971 651136",
    "sg:postcode":"85050",
    "sg:province":"Potenza",
    "sg:website":"http://potenza.pandora.it/somia",
    "wof:name":"Somia Srl",
    "wof:placetype":"venue"
},
  "geometry": {"coordinates":[15.67705,40.583752],"type":"Point"}
}