{
  "type": "Feature",
  "properties": {
    "iso:country":"IT",
    "sg:address":"48, Via S. Giovanni 36045 Lonigo",
    "sg:city":"Lonigo",
    "sg:classifiers":[
        {
            "category":"Professional",
            "subcategory":"Engineering",
            "type":"Services"
        }
    ],
    "sg:phone":"+39 0444 831205",
    "sg:postcode":"36045",
    "sg:province":"Vicenza",
    "sg:tags":[
        "machine",
        "-",
        "mechanical"
    ],
    "wof:name":"Cmv Sas Di Consolaro Giampaolo & C.",
    "wof:placetype":"venue"
},
  "geometry": {"coordinates":[11.540307,45.545906],"type":"Point"}
}