{
  "type": "Feature",
  "properties": {
    "addr:full":"42040 Calerno Reggio Nell'Emilia 42040",
    "addr:postcode":"42040;42040",
    "iso:country":"IT",
    "sg:address":"42040 Calerno",
    "sg:orig_category":"Manufacturers: Prefabbricati",
    "sg:phone":"+39 0522 679228",
    "sg:postcode":"42040",
    "sg:province":"Reggio Nell'Emilia",
    "wof:name":"Super Blok Piccinini (s.r.l.)",
    "wof:placetype":"venue"
},
  "geometry": {"coordinates":[10.481598,44.754875],"type":"Point"}
}