{
  "type": "Feature",
  "properties": {
    "iso:country":"IT",
    "sg:address":"27040 Borgo Priolo",
    "sg:city":"Borgo Priolo",
    "sg:orig_category":"Macchine Ed Impianti Per Edilizia E Lavori Pubblici",
    "sg:phone":"+39 0383 871080",
    "sg:postcode":"27040",
    "sg:province":"Pavia",
    "wof:name":"Officine Meccaniche Fasani",
    "wof:placetype":"venue"
},
  "geometry": {"coordinates":[9.14902,44.967445],"type":"Point"}
}