{
  "type": "Feature",
  "properties": {
    "iso:country":"IT",
    "sg:address":"Via Crocefisso 47 06059 Todi",
    "sg:city":"Todi",
    "sg:classifiers":[
        {
            "category":"Wholesale",
            "subcategory":"Fruits & Vegetables",
            "type":"Manufacturing & Wholesale Goods"
        }
    ],
    "sg:phone":"+39 075 894 2402",
    "sg:postcode":"06059",
    "sg:province":"Perugia",
    "sg:tags":[
        "product",
        "cereal"
    ],
    "wof:name":"Spazzoni Giuseppe Spa",
    "wof:placetype":"venue"
},
  "geometry": {"coordinates":[12.417245,42.78046],"type":"Point"}
}