{
  "type": "Feature",
  "properties": {
    "addr:full":"29013 Carpaneto Piacentino Carpaneto Piacentino Piacenza 29013",
    "addr:postcode":"29013;29013",
    "iso:country":"IT",
    "sg:address":"29013 Carpaneto Piacentino",
    "sg:city":"Carpaneto Piacentino",
    "sg:orig_category":"Cancelli, Porte E Portoni Automatici E Telecomandati",
    "sg:phone":"+39 0523 853263",
    "sg:postcode":"29013",
    "sg:province":"Piacenza",
    "wof:name":"Euroinfissi Di Paveri & Signaroldi",
    "wof:placetype":"venue"
},
  "geometry": {"coordinates":[9.799113,44.906525],"type":"Point"}
}