{
  "type": "Feature",
  "properties": {
    "iso:country":"IT",
    "sg:address":"27050 Retorbido",
    "sg:city":"Retorbido",
    "sg:orig_category":"Servizi E Lavori Per Edilizia E Lavori Pubblici",
    "sg:phone":"+39 0383 74027",
    "sg:postcode":"27050",
    "sg:province":"Pavia",
    "wof:name":"Gobbi Alberto Pavimenti In Legno",
    "wof:placetype":"venue"
},
  "geometry": {"coordinates":[9.042685,44.94458],"type":"Point"}
}