{
  "type": "Feature",
  "properties": {
    "iso:country":"IT",
    "sg:address":"30028 San Michele Tagliamento",
    "sg:orig_category":"Lavorazioni Meccaniche E Servizi",
    "sg:phone":"+39 0431 512155",
    "sg:postcode":"30028",
    "sg:province":"Venezia",
    "sg:website":"http://www.poolmeccanicalorenzon.it",
    "wof:name":"Poolmeccanica Lorenzon Snc",
    "wof:placetype":"venue"
},
  "geometry": {"coordinates":[12.978657,45.769444],"type":"Point"}
}