{
  "type": "Feature",
  "properties": {
    "addr:full":"5, Via Dante Alighieri 63014 Montegranaro Montegranaro Ascoli Piceno 63014",
    "addr:postcode":"63014;63014",
    "addr:street":"Via Dante Alighieri",
    "iso:country":"IT",
    "sg:address":"5, Via Dante Alighieri 63014 Montegranaro",
    "sg:city":"Montegranaro",
    "sg:classifiers":[
        {
            "category":"Personal",
            "subcategory":"Shoe Repair & Shine",
            "type":"Services"
        }
    ],
    "sg:phone":"+39 0734 890955",
    "sg:postcode":"63014",
    "sg:province":"Ascoli Piceno",
    "sg:tags":[
        "leather"
    ],
    "wof:name":"Formificio Veregra S.r.l.",
    "wof:placetype":"venue"
},
  "geometry": {"coordinates":[13.630151,43.231033],"type":"Point"}
}