{
  "type": "Feature",
  "properties": {
    "iso:country":"IT",
    "sg:address":"20154 Milano",
    "sg:city":"Milano",
    "sg:orig_category":"Hobbistica",
    "sg:phone":"+39 02 311317",
    "sg:postcode":"20154",
    "sg:province":"Milano",
    "wof:name":"Acchito Planetarium Srl",
    "wof:placetype":"venue"
},
  "geometry": {"coordinates":[9.177697,45.481541],"type":"Point"}
}