{
  "type": "Feature",
  "properties": {
    "iso:country":"IT",
    "sg:address":"Via Mameli Goffredo 124/d 37126 Verona",
    "sg:city":"Verona",
    "sg:classifiers":[
        {
            "category":"Transit Center",
            "subcategory":"Passenger",
            "type":"Transportation"
        }
    ],
    "sg:phone":"+39 045 916511",
    "sg:postcode":"37126",
    "sg:province":"Verona",
    "sg:tags":[
        "essence",
        "flavourings",
        "baking",
        "aromatic",
        "essences"
    ],
    "wof:name":"F. Zanardi E Figli S.r.l.",
    "wof:placetype":"venue"
},
  "geometry": {"coordinates":[10.991748,45.438366],"type":"Point"}
}