{
  "type": "Feature",
  "properties": {
    "iso:country":"IT",
    "sg:address":"21040 Jerago Con Orago",
    "sg:city":"Jerago con Orago",
    "sg:orig_category":"Servizi Di Magazzinaggio E Movimentazione",
    "sg:phone":"+39 0331 219366",
    "sg:postcode":"21040",
    "sg:province":"Varese",
    "sg:website":"http://www.bilance.com",
    "wof:name":"Futura Srl",
    "wof:placetype":"venue"
},
  "geometry": {"coordinates":[8.805638,45.704582],"type":"Point"}
}