{
  "type": "Feature",
  "properties": {
    "addr:full":"20060 Trezzano Rosa Trezzano Rosa Milano 20060",
    "addr:postcode":"20060;20060",
    "iso:country":"IT",
    "sg:address":"20060 Trezzano Rosa",
    "sg:city":"Trezzano Rosa",
    "sg:orig_category":"Medicinali E Prodotti Parafarmaceutici",
    "sg:phone":"+39 02 909 3131",
    "sg:postcode":"20060",
    "sg:province":"Milano",
    "wof:name":"Imo Istituto Di Medicina Omeopatica Spa",
    "wof:placetype":"venue"
},
  "geometry": {"coordinates":[9.4710092545,45.5882568359],"type":"Point"}
}