{
  "type": "Feature",
  "properties": {
    "iso:country":"IT",
    "sg:address":"27010 Cura Carpignano",
    "sg:city":"Cura Carpignano",
    "sg:orig_category":"Servizi E Lavori Per Ecologia E Smaltimento Rifiuti. Servizi Ausiliari Di Sorveglianza, Manutenzione E Pulizia",
    "sg:phone":"+39 0382 488729",
    "sg:postcode":"27010",
    "sg:province":"Pavia",
    "sg:website":"http://www.eco3.it",
    "wof:name":"Eco 3 Sas",
    "wof:placetype":"venue"
},
  "geometry": {"coordinates":[9.256694,45.21241],"type":"Point"}
}