{
  "type": "Feature",
  "properties": {
    "addr:full":"00165 Roma Roma Roma 00165",
    "addr:postcode":"00165;00165",
    "iso:country":"IT",
    "sg:address":"00165 Roma",
    "sg:city":"Roma",
    "sg:orig_category":"Abbigliamento Esterno, Maglierie E Pelliccerie. Calzature, Pelletterie E Pelli. Sport - Articoli E Forniture",
    "sg:phone":"+39 06 6601 8150",
    "sg:postcode":"00165",
    "sg:province":"Roma",
    "wof:name":"Blasio Enterprise Italia",
    "wof:placetype":"venue"
},
  "geometry": {"coordinates":[12.430734,41.900837],"type":"Point"}
}