{
  "type": "Feature",
  "properties": {
    "addr:full":"20084 Lacchiarella Lacchiarella Milano 20084",
    "addr:postcode":"20084;20084",
    "iso:country":"IT",
    "sg:address":"20084 Lacchiarella",
    "sg:city":"Lacchiarella",
    "sg:orig_category":"Arredo Bagno Ed Idrosanitari. Idrosanitari E Accessori. Minuterie Metalliche E Ferramenta",
    "sg:phone":"+39 02 900461",
    "sg:postcode":"20084",
    "sg:province":"Milano",
    "sg:website":"http://www.mamoli.it",
    "wof:name":"Mamoli Robinetteria Spa",
    "wof:placetype":"venue"
},
  "geometry": {"coordinates":[9.148467,45.319118],"type":"Point"}
}