{
  "type": "Feature",
  "properties": {
    "addr:full":"Via Don Mazzolari 5/7 42012 Campagnola Emilia Reggio Nell'Emilia 42012",
    "addr:housenumber":"5 / 7",
    "addr:postcode":"42012;42012",
    "addr:street":"Via Don Mazzolari",
    "iso:country":"IT",
    "sg:address":"Via Don Mazzolari 5/7 42012 Campagnola Emilia",
    "sg:classifiers":[
        {
            "category":"Structure",
            "subcategory":"Office Building",
            "type":"Public Place"
        }
    ],
    "sg:phone":"+39 0522 652814",
    "sg:postcode":"42012",
    "sg:province":"Reggio Nell'Emilia",
    "sg:tags":[
        "chair",
        "backrest"
    ],
    "wof:name":"V.r.b. Srl",
    "wof:placetype":"venue"
},
  "geometry": {"coordinates":[10.772559,44.836796],"type":"Point"}
}