{
  "type": "Feature",
  "properties": {
    "iso:country":"IT",
    "sg:address":"20090 Pieve Emanuele",
    "sg:city":"Pieve Emanuele",
    "sg:orig_category":"Macchine, Impianti Ed Attrezzature Per Agricoltura E Zootecnia. Macchine, Impianti Ed Attrezzature Industria Chimica. Macchine Utensili E Impianti",
    "sg:phone":"+39 02 9072 0647",
    "sg:postcode":"20090",
    "sg:province":"Milano",
    "wof:name":"Criotherm (s.r.l.)",
    "wof:placetype":"venue"
},
  "geometry": {"coordinates":[9.191497,45.373398],"type":"Point"}
}