{
  "type": "Feature",
  "properties": {
    "iso:country":"IT",
    "sg:address":"24048 Treviolo",
    "sg:city":"Treviolo",
    "sg:orig_category":"Fotoriproduttori E Fotocopiatrici",
    "sg:phone":"+39 035 204011",
    "sg:postcode":"24048",
    "sg:province":"Bergamo",
    "sg:website":"http://www.sitis.com",
    "wof:name":"S.i.t.i.s. Srl",
    "wof:placetype":"venue"
},
  "geometry": {"coordinates":[9.6268291473,45.6731796265],"type":"Point"}
}