{
  "type": "Feature",
  "properties": {
    "iso:country":"IT",
    "sg:address":"80014 Giugliano In Campania",
    "sg:city":"Giugliano in Campania",
    "sg:orig_category":"Avvocati - Studi",
    "sg:phone":"+39 081 420 2324",
    "sg:postcode":"80014",
    "sg:province":"Napoli",
    "wof:name":"Studio Legale Faiello Avv. Andrea",
    "wof:placetype":"venue"
},
  "geometry": {"coordinates":[14.247255,40.842644],"type":"Point"}
}