{
  "type": "Feature",
  "properties": {
    "addr:full":"56021 Cascina Cascina Pisa 56021",
    "addr:postcode":"56021;56021",
    "addr:street":"Cascina Pisa",
    "iso:country":"IT",
    "sg:address":"56021 Cascina",
    "sg:city":"Cascina",
    "sg:orig_category":"Antifurto",
    "sg:phone":"+39 050 775315",
    "sg:postcode":"56021",
    "sg:province":"Pisa",
    "wof:name":"Colombini Impianti Di Colombini Michele Snc",
    "wof:placetype":"venue"
},
  "geometry": {"coordinates":[10.4958677292,43.6605110168],"type":"Point"}
}