{
  "type": "Feature",
  "properties": {
    "iso:country":"IT",
    "sg:address":"2, Via Milite Ignoto 17021 Alassio",
    "sg:city":"Alassio",
    "sg:classifiers":[
        {
            "category":"Travel",
            "subcategory":"Travel Agent",
            "type":"Entertainment"
        }
    ],
    "sg:phone":"+39 39018266101",
    "sg:postcode":"17021",
    "sg:province":"Savona",
    "sg:tags":[
        "business"
    ],
    "wof:name":"Residence Europa Unita",
    "wof:placetype":"venue"
},
  "geometry": {"coordinates":[8.170949,44.005661],"type":"Point"}
}