{
  "type": "Feature",
  "properties": {
    "iso:country":"IT",
    "sg:address":"35, Via Archimede 20041 Agrate Brianza",
    "sg:city":"Agrate Brianza",
    "sg:classifiers":[
        {
            "category":"Professional",
            "subcategory":"Engineering",
            "type":"Services"
        }
    ],
    "sg:phone":"+39 039 605 7177",
    "sg:postcode":"20041",
    "sg:province":"Milano",
    "sg:tags":[
        "machine",
        "-",
        "mechanical"
    ],
    "wof:name":"Carpenterie Leggere Di Cerini E C. Snc",
    "wof:placetype":"venue"
},
  "geometry": {"coordinates":[9.33482,45.567482],"type":"Point"}
}