{
  "type": "Feature",
  "properties": {
    "addr:full":"25, Via Cesare Battisti 24035 Curno Curno Bergamo 24035",
    "addr:postcode":"24035;24035",
    "addr:street":"Via Cesare Battisti",
    "iso:country":"IT",
    "sg:address":"25, Via Cesare Battisti 24035 Curno",
    "sg:city":"Curno",
    "sg:classifiers":[
        {
            "category":"Wholesale",
            "subcategory":"Machinery & Supplies",
            "type":"Manufacturing & Wholesale Goods"
        }
    ],
    "sg:phone":"+39 39035618120",
    "sg:postcode":"24035",
    "sg:province":"Bergamo",
    "sg:tags":[
        "equipment",
        "-",
        "instrument",
        "measurement"
    ],
    "wof:name":"Burster Italia (s.r.l.)",
    "wof:placetype":"venue"
},
  "geometry": {"coordinates":[9.606808,45.691605],"type":"Point"}
}