{
  "type": "Feature",
  "properties": {
    "iso:country":"IT",
    "sg:address":"Via E. Mattei 20 50039 Vicchio",
    "sg:city":"Vicchio",
    "sg:classifiers":[
        {
            "category":"Shopping",
            "subcategory":"Jewelry",
            "type":"Retail Goods"
        }
    ],
    "sg:phone":"+39 055 844433",
    "sg:postcode":"50039",
    "sg:province":"Firenze",
    "sg:tags":[
        "item",
        "made",
        "silver",
        "gift"
    ],
    "wof:name":"Serena Argenti Srl",
    "wof:placetype":"venue"
},
  "geometry": {"coordinates":[11.324956,43.750034],"type":"Point"}
}