{
  "type": "Feature",
  "properties": {
    "iso:country":"IT",
    "sg:address":"25082 Botticino Sera",
    "sg:city":"Botticino",
    "sg:orig_category":"Prodotti Finiti Stampati. Forniture Per Attivita' Commerciali Ed Artigianali",
    "sg:phone":"+39 030 219 1056",
    "sg:postcode":"25082",
    "sg:province":"Brescia",
    "wof:name":"Decalco-plast Di Damoli A. & Taini M. Snc",
    "wof:placetype":"venue"
},
  "geometry": {"coordinates":[10.3094377518,45.5288200378],"type":"Point"}
}