{
  "type": "Feature",
  "properties": {
    "iso:country":"IT",
    "sg:address":"240, Via Del Lavoro 40014 Crevalcore",
    "sg:city":"Crevalcore",
    "sg:classifiers":[
        {
            "category":"Shopping",
            "subcategory":"Clothing, Apparel, & Fashions",
            "type":"Retail Goods"
        }
    ],
    "sg:phone":"+39 39051980506",
    "sg:postcode":"40014",
    "sg:province":"Bologna",
    "sg:tags":[
        "clothes"
    ],
    "wof:name":"Mondadori (s.r.l.)",
    "wof:placetype":"venue"
},
  "geometry": {"coordinates":[11.173011,44.717278],"type":"Point"}
}