{
  "type": "Feature",
  "properties": {
    "addr:full":"242, Via Maestra 33084 Cordenons Cordenons Pordenone 33084",
    "addr:housenumber":"242",
    "addr:postcode":"33084;33084",
    "addr:street":"Via Maestra",
    "iso:country":"IT",
    "sg:address":"242, Via Maestra 33084 Cordenons",
    "sg:city":"Cordenons",
    "sg:classifiers":[
        {
            "category":"Utilities",
            "subcategory":"Electric",
            "type":"Services"
        }
    ],
    "sg:phone":"+39 0434 542000",
    "sg:postcode":"33084",
    "sg:province":"Pordenone",
    "sg:tags":[
        "component",
        "electronic"
    ],
    "wof:name":"Mcperson (s.r.l.)",
    "wof:placetype":"venue"
},
  "geometry": {"coordinates":[12.67721,45.980682],"type":"Point"}
}