{
  "type": "Feature",
  "properties": {
    "iso:country":"IT",
    "sg:address":"Via Alle Cascine 24033 Calusco D'adda",
    "sg:classifiers":[
        {
            "category":"Manufacturing",
            "subcategory":"Rubber & Plastics",
            "type":"Manufacturing & Wholesale Goods"
        }
    ],
    "sg:phone":"+39 035 436 2301",
    "sg:postcode":"24033",
    "sg:province":"Bergamo",
    "sg:tags":[
        "ab",
        "styrene",
        "butadiene",
        "foil",
        "slab",
        "acrylonitrile"
    ],
    "wof:name":"Arcaprofil Spa",
    "wof:placetype":"venue"
},
  "geometry": {"coordinates":[9.498631,45.686939],"type":"Point"}
}