{
  "type": "Feature",
  "properties": {
    "addr:full":"4, Via Abetone Inferiore 41053 Maranello Maranello Modena 41053",
    "addr:postcode":"41053;41053",
    "addr:street":"Via Abetone Inferiore",
    "iso:country":"IT",
    "sg:address":"4, Via Abetone Inferiore 41053 Maranello",
    "sg:city":"Maranello",
    "sg:classifiers":[
        {
            "category":"Autos & Motor Vehicles",
            "subcategory":"Automobile Sales",
            "type":"Retail Goods"
        }
    ],
    "sg:phone":"+39 0536 949111",
    "sg:postcode":"41053",
    "sg:province":"Modena",
    "sg:tags":[
        "motor-cars"
    ],
    "wof:name":"Ferrari S.p.a.",
    "wof:placetype":"venue"
},
  "geometry": {"coordinates":[10.8641405106,44.5324478149],"type":"Point"}
}