{
  "type": "Feature",
  "properties": {
    "iso:country":"IT",
    "sg:address":"29100 Piacenza",
    "sg:city":"Piacenza",
    "sg:orig_category":"Trasporti E Spedizioni Merci",
    "sg:phone":"+39 0523 577511",
    "sg:postcode":"29100",
    "sg:province":"Piacenza",
    "wof:name":"I.t.c. Ageco Srl",
    "wof:placetype":"venue"
},
  "geometry": {"coordinates":[9.749794,45.039539],"type":"Point"}
}