{
  "type": "Feature",
  "properties": {
    "iso:country":"IT",
    "sg:address":"47, Via Virgilio 81030 Succivo",
    "sg:city":"Succivo",
    "sg:classifiers":[
        {
            "category":"Shopping",
            "subcategory":"Clothing, Apparel, & Fashions",
            "type":"Retail Goods"
        }
    ],
    "sg:phone":"+39 081 891 8222",
    "sg:postcode":"81030",
    "sg:province":"Caserta",
    "sg:tags":[
        "clothes"
    ],
    "wof:name":"Mo. Del Srl.",
    "wof:placetype":"venue"
},
  "geometry": {"coordinates":[14.254471,40.96397],"type":"Point"}
}