{
  "type": "Feature",
  "properties": {
    "iso:country":"IT",
    "sg:address":"20090 Pieve Emanuele",
    "sg:city":"Pieve Emanuele",
    "sg:orig_category":"Tubi Flessibili Per Pressioni",
    "sg:phone":"+39 02 9078 1932",
    "sg:postcode":"20090",
    "sg:province":"Milano",
    "wof:name":"Hydroflex Snc",
    "wof:placetype":"venue"
},
  "geometry": {"coordinates":[9.185198,45.37064],"type":"Point"}
}