{
  "type": "Feature",
  "properties": {
    "addr:full":"Via Enna 4 20142 Milano Milano Milano 20142",
    "addr:housenumber":"4",
    "addr:postcode":"20142;20142",
    "addr:street":"Via Enna",
    "iso:country":"IT",
    "sg:address":"Via Enna 4 20142 Milano",
    "sg:city":"Milano",
    "sg:classifiers":[
        {
            "category":"Retail",
            "subcategory":"Auto Rental",
            "type":"Services"
        }
    ],
    "sg:phone":"+39 02 891 0024",
    "sg:postcode":"20142",
    "sg:province":"Milano",
    "sg:tags":[
        "cranes",
        "automobile",
        "crane",
        "salvage",
        "wrecking"
    ],
    "wof:name":"Lige Fratelli Licenziato Srl",
    "wof:placetype":"venue"
},
  "geometry": {"coordinates":[9.128245,45.438156],"type":"Point"}
}