{
  "type": "Feature",
  "properties": {
    "addr:full":"118, Via Alimena F. 87100 Cosenza Cosenza Cosenza 87100",
    "addr:housenumber":"118",
    "addr:postcode":"87100;87100",
    "addr:street":"Via Alimena F.",
    "iso:country":"IT",
    "sg:address":"118, Via Alimena F. 87100 Cosenza",
    "sg:city":"Cosenza",
    "sg:classifiers":[
        {
            "category":"Travel",
            "subcategory":"Travel Agent",
            "type":"Entertainment"
        }
    ],
    "sg:phone":"+39 39098425874",
    "sg:postcode":"87100",
    "sg:province":"Cosenza",
    "sg:tags":[
        "business"
    ],
    "wof:name":"Centro Lingue E Congressi",
    "wof:placetype":"venue"
},
  "geometry": {"coordinates":[16.253809,39.298264],"type":"Point"}
}