{
  "type": "Feature",
  "properties": {
    "iso:country":"IT",
    "sg:address":"20040 Cavenago Di Brianza",
    "sg:city":"Cavenago di Brianza",
    "sg:classifiers":[
        {
            "category":"Banks & Credit Unions",
            "subcategory":"Financial Services",
            "type":"Services"
        }
    ],
    "sg:phone":"+39 02 9533 5141",
    "sg:postcode":"20040",
    "sg:province":"Milano",
    "sg:tags":[
        "articles",
        "product",
        "plastics",
        "industry",
        "work",
        "plastic"
    ],
    "wof:name":"Tesacom Di Fiammenghi Marcella & C. Snc",
    "wof:placetype":"venue"
},
  "geometry": {"coordinates":[9.4148349762,45.5795631409],"type":"Point"}
}