{
  "type": "Feature",
  "properties": {
    "addr:full":"Via Schizzalunga 1 36066 Sandrigo Sandrigo Vicenza 36066",
    "addr:housenumber":"1",
    "addr:postcode":"36066;36066",
    "addr:street":"Via Schizzalunga",
    "iso:country":"IT",
    "sg:address":"Via Schizzalunga 1 36066 Sandrigo",
    "sg:city":"Sandrigo",
    "sg:classifiers":[
        {
            "category":"Manufacturing",
            "subcategory":"Furniture",
            "type":"Manufacturing & Wholesale Goods"
        }
    ],
    "sg:phone":"+39 0444 659777",
    "sg:postcode":"36066",
    "sg:province":"Vicenza",
    "sg:tags":[
        "bedroom"
    ],
    "wof:name":"Cecchini Collection Srl",
    "wof:placetype":"venue"
},
  "geometry": {"coordinates":[11.540307,45.545906],"type":"Point"}
}