{
  "type": "Feature",
  "properties": {
    "addr:full":"Via Rossini 14 23873 Missaglia Missaglia Lecco 23873",
    "addr:housenumber":"14",
    "addr:postcode":"23873;23873",
    "addr:street":"Via Rossini",
    "iso:country":"IT",
    "sg:address":"Via Rossini 14 23873 Missaglia",
    "sg:city":"Missaglia",
    "sg:classifiers":[
        {
            "category":"Sports & Exercise",
            "subcategory":"Ski Resort",
            "type":"Entertainment"
        }
    ],
    "sg:phone":"+39 039 924 1116",
    "sg:postcode":"23873",
    "sg:province":"Lecco",
    "sg:tags":[
        "pipe",
        "fitting"
    ],
    "sg:website":"www.raccorfer.com",
    "wof:name":"Raccorfer Snc",
    "wof:placetype":"venue"
},
  "geometry": {"coordinates":[9.3900709152,45.8529815674],"type":"Point"}
}