{
  "type": "Feature",
  "properties": {
    "iso:country":"IT",
    "sg:address":"Via Archimede, 22/24 20041 Agrate Brianza",
    "sg:city":"Agrate Brianza",
    "sg:classifiers":[
        {
            "category":"Communications",
            "subcategory":"Radio Station",
            "type":"Services"
        }
    ],
    "sg:phone":"+39 039 60541",
    "sg:postcode":"20041",
    "sg:province":"Milano",
    "sg:tags":[
        "directional"
    ],
    "sg:website":"www.forem.it",
    "wof:name":"Forem Srl",
    "wof:placetype":"venue"
},
  "geometry": {"coordinates":[9.335768,45.567631],"type":"Point"}
}