{
  "type": "Feature",
  "properties": {
    "iso:country":"IT",
    "sg:address":"14, Via Bicocca 40026 Imola",
    "sg:city":"Imola",
    "sg:classifiers":[
        {
            "category":"Communications",
            "subcategory":"Television Station",
            "type":"Services"
        }
    ],
    "sg:phone":"+39 0542 643961",
    "sg:postcode":"40026",
    "sg:province":"Bologna",
    "sg:tags":[
        "audio-visual"
    ],
    "wof:name":"Elca Elettronica S R L",
    "wof:placetype":"venue"
},
  "geometry": {"coordinates":[11.746353,44.384251],"type":"Point"}
}