{
  "type": "Feature",
  "properties": {
    "iso:country":"IT",
    "sg:address":"8, Contrada Mandria Del Forno I 87064 Corigliano Calabro",
    "sg:city":"Corigliano Calabro",
    "sg:classifiers":[
        {
            "category":"Farming",
            "subcategory":"Livestock Farm",
            "type":"Manufacturing & Wholesale Goods"
        }
    ],
    "sg:phone":"+39 0983 808006",
    "sg:postcode":"87064",
    "sg:province":"Cosenza",
    "sg:tags":[
        "agriculture"
    ],
    "wof:name":"Gencarelli Egidio",
    "wof:placetype":"venue"
},
  "geometry": {"coordinates":[16.253809,39.298264],"type":"Point"}
}