{
  "type": "Feature",
  "properties": {
    "iso:country":"IT",
    "sg:address":"95047 Paterno'",
    "sg:orig_category":"Elettrotecnica Industriale, Prodotti E Apparecchiature",
    "sg:phone":"+39 095 854853",
    "sg:postcode":"95047",
    "sg:province":"Catania",
    "wof:name":"Cos.it.el Srl-costruzione Italiana Elettrica Srl",
    "wof:placetype":"venue"
},
  "geometry": {"coordinates":[14.904863,37.568695],"type":"Point"}
}