{
  "type": "Feature",
  "properties": {
    "iso:country":"IT",
    "sg:address":"39010 Sinigo",
    "sg:orig_category":"Macchine Ed Impianti Per Edilizia E Lavori Pubblici. Impianti E Attrezzature Per Lo Sport E Il Tempo Libero",
    "sg:phone":"+39 0473 247088",
    "sg:postcode":"39010",
    "sg:province":"Bolzano/Bozen",
    "wof:name":"Herbst S.r.l.",
    "wof:placetype":"venue"
},
  "geometry": {"coordinates":[11.330323,46.46991],"type":"Point"}
}