{
  "type": "Feature",
  "properties": {
    "iso:country":"IT",
    "sg:address":"33081 Aviano",
    "sg:city":"Aviano",
    "sg:orig_category":"Pubblica Amministrazione",
    "sg:phone":"+39 0434 651436",
    "sg:postcode":"33081",
    "sg:province":"Pordenone",
    "wof:name":"Stazione Forestale",
    "wof:placetype":"venue"
},
  "geometry": {"coordinates":[12.6022567749,45.9926605225],"type":"Point"}
}