{
  "type": "Feature",
  "properties": {
    "addr:full":"10122 Torino Torino Torino 10122",
    "addr:housenumber":"10122",
    "addr:postcode":"10122",
    "iso:country":"IT",
    "sg:address":"10122 Torino",
    "sg:city":"Torino",
    "sg:orig_category":"Scuole E Servizi Scolastici. Centri Di Estetica E Cosmesi E Servizi. Ricerca, Selezione E Formazione Del Personale",
    "sg:phone":"+39 011 517 5108",
    "sg:postcode":"10122",
    "sg:province":"Torino",
    "wof:name":"Clio (s.r.l.)",
    "wof:placetype":"venue"
},
  "geometry": {"coordinates":[7.67526,45.071148],"type":"Point"}
}