{
  "type": "Feature",
  "properties": {
    "iso:country":"IT",
    "sg:address":"Strada Comunale Per Bettola 1 20065 Inzago",
    "sg:city":"Inzago",
    "sg:classifiers":[
        {
            "category":"Manufacturing",
            "subcategory":"Glass & Minerals",
            "type":"Manufacturing & Wholesale Goods"
        }
    ],
    "sg:phone":"+39 02 954 7641",
    "sg:postcode":"20065",
    "sg:province":"Milano",
    "sg:tags":[
        "decorative",
        "artistic"
    ],
    "sg:website":"www.johnsonmatthey.com",
    "wof:name":"Johnson Matthey Spa",
    "wof:placetype":"venue"
},
  "geometry": {"coordinates":[9.188141,45.463688],"type":"Point"}
}