{
  "type": "Feature",
  "properties": {
    "addr:full":"16126 Genova Genova Genova 16126",
    "addr:postcode":"16126;16126",
    "iso:country":"IT",
    "sg:address":"16126 Genova",
    "sg:city":"Genova",
    "sg:orig_category":"Prodotti Chimici Secondari. Prodotti Cosmetici E Da Toeletta",
    "sg:phone":"+39 010 247 2158",
    "sg:postcode":"16126",
    "sg:province":"Genova",
    "wof:name":"Di Stefano - Articoli Medico Sanitari - Forniture",
    "wof:placetype":"venue"
},
  "geometry": {"coordinates":[8.8880691528,44.9679908752],"type":"Point"}
}