{
  "type": "Feature",
  "properties": {
    "iso:country":"IT",
    "sg:address":"14055 Boglietto",
    "sg:city":"Boglietto",
    "sg:orig_category":"Non-classified Establishments",
    "sg:phone":"+39 0141 968147",
    "sg:postcode":"14055",
    "sg:province":"Asti",
    "wof:name":"La Fonte Del Rustico Gestione Srl",
    "wof:placetype":"venue"
},
  "geometry": {"coordinates":[8.199055,44.764957],"type":"Point"}
}