{
  "type": "Feature",
  "properties": {
    "addr:full":"8, Via Medaglie D'argento 26012 Castelleone Castelleone Cremona 26012",
    "addr:postcode":"26012;26012",
    "addr:street":"Via Medaglie D'Argento",
    "iso:country":"IT",
    "sg:address":"8, Via Medaglie D'argento 26012 Castelleone",
    "sg:city":"Castelleone",
    "sg:classifiers":[
        {
            "category":"Professional",
            "subcategory":"Engineering",
            "type":"Services"
        }
    ],
    "sg:phone":"+39 39037457203",
    "sg:postcode":"26012",
    "sg:province":"Cremona",
    "sg:tags":[
        "machine",
        "-",
        "mechanical"
    ],
    "wof:name":"Bonetti M.antonio & C.(s.n.c.)",
    "wof:placetype":"venue"
},
  "geometry": {"coordinates":[9.750813,45.296921],"type":"Point"}
}