{
  "type": "Feature",
  "properties": {
    "iso:country":"IT",
    "sg:address":"20089 Rozzano",
    "sg:city":"Rozzano",
    "sg:orig_category":"Litografie",
    "sg:phone":"+39 02 5751 0930",
    "sg:postcode":"20089",
    "sg:province":"Milano",
    "wof:name":"Litosette Grafica E Comunicazione Srl",
    "wof:placetype":"venue"
},
  "geometry": {"coordinates":[9.169468,45.395924],"type":"Point"}
}