{
  "type": "Feature",
  "properties": {
    "iso:country":"IT",
    "sg:address":"08020 Budoni",
    "sg:orig_category":"Ricambi E Componenti Dei Mezzi Di Trasporto",
    "sg:phone":"+39 348 301 6840",
    "sg:postcode":"08020",
    "sg:province":"Nuoro",
    "wof:name":"Vancharter Srl",
    "wof:placetype":"venue"
},
  "geometry": {"coordinates":[9.699232,40.709496],"type":"Point"}
}