{
  "type": "Feature",
  "properties": {
    "iso:country":"IT",
    "sg:address":"Via Dell' Industria 8 31014 Colle Umberto",
    "sg:city":"Colle Umberto",
    "sg:classifiers":[
        {
            "category":"Autos & Motor Vehicles",
            "subcategory":"Motorcycle Sales",
            "type":"Retail Goods"
        }
    ],
    "sg:phone":"+39 0438 430459",
    "sg:postcode":"31014",
    "sg:province":"Treviso",
    "sg:tags":[
        "steel",
        "stainless",
        "grate"
    ],
    "sg:website":"www.prodinox.it",
    "wof:name":"Tecnofilo S.r.l.",
    "wof:placetype":"venue"
},
  "geometry": {"coordinates":[12.318446,45.889267],"type":"Point"}
}