{
  "type": "Feature",
  "properties": {
    "iso:country":"IT",
    "sg:address":"20035 Lissone",
    "sg:city":"Lissone",
    "sg:orig_category":"Climatizzazione E Condizionamento, Apparecchiature E Servizi",
    "sg:phone":"+39 039 484944",
    "sg:postcode":"20035",
    "sg:province":"Milano",
    "wof:name":"Primaria Sas Di Mauri E C.",
    "wof:placetype":"venue"
},
  "geometry": {"coordinates":[9.241694,45.607338],"type":"Point"}
}