{
  "type": "Feature",
  "properties": {
    "addr:full":"62, Via Di Vittorio Giuseppe 43044 Collecchio Collecchio Parma 43044",
    "addr:postcode":"43044;43044",
    "addr:street":"Via Di Vittorio Giuseppe",
    "iso:country":"IT",
    "sg:address":"62, Via Di Vittorio Giuseppe 43044 Collecchio",
    "sg:city":"Collecchio",
    "sg:classifiers":[
        {
            "category":"Manufacturing",
            "subcategory":"Rubber & Plastics",
            "type":"Manufacturing & Wholesale Goods"
        }
    ],
    "sg:phone":"+39 0521 804690",
    "sg:postcode":"43044",
    "sg:province":"Parma",
    "wof:name":"Gruppo Canali S.r.l.",
    "wof:placetype":"venue"
},
  "geometry": {"coordinates":[10.2622785568,44.7713775635],"type":"Point"}
}