{
  "type": "Feature",
  "properties": {
    "iso:country":"IT",
    "sg:address":"24033 Calusco D'adda",
    "sg:orig_category":"Macchine Ed Impianti Per Edilizia E Lavori Pubblici",
    "sg:phone":"+39 035 792142",
    "sg:postcode":"24033",
    "sg:province":"Bergamo",
    "wof:name":"Limonta Arturo",
    "wof:placetype":"venue"
},
  "geometry": {"coordinates":[9.473393,45.691189],"type":"Point"}
}