{
  "type": "Feature",
  "properties": {
    "iso:country":"IT",
    "sg:address":"9, Via Piave 22060 Cabiate",
    "sg:city":"Cabiate",
    "sg:classifiers":[
        {
            "category":"Home & Garden",
            "subcategory":"Home Furnishings",
            "type":"Retail Goods"
        }
    ],
    "sg:phone":"+39 39031756727",
    "sg:postcode":"22060",
    "sg:province":"Como",
    "sg:tags":[
        "household"
    ],
    "wof:name":"Martinis Design S.r.l.",
    "wof:placetype":"venue"
},
  "geometry": {"coordinates":[9.167307,45.68169],"type":"Point"}
}