{
  "type": "Feature",
  "properties": {
    "addr:full":"Corso Marconi 17; Seveso; 20030 Seveso Milano 20030",
    "addr:housenumber":"17",
    "addr:postcode":"20030;20030",
    "addr:street":"Corso Marconi",
    "iso:country":"IT",
    "sg:address":"Corso Marconi 17; Seveso; 20030",
    "sg:city":"Seveso",
    "sg:classifiers":[
        {
            "category":"Banks & Credit Unions",
            "subcategory":"Bank",
            "type":"Services"
        }
    ],
    "sg:phone":"+39 036 250 6135",
    "sg:postcode":"20030",
    "sg:province":"Milano",
    "wof:name":"Banco Ambrosiano Veneto Spa",
    "wof:placetype":"venue"
},
  "geometry": {"coordinates":[9.138636,45.646191],"type":"Point"}
}