{
  "type": "Feature",
  "properties": {
    "iso:country":"IT",
    "sg:address":"60126 Ancona",
    "sg:city":"Ancona",
    "sg:orig_category":"Servizi Di Magazzinaggio E Movimentazione. Servizi Ausiliari Di Sorveglianza, Manutenzione E Pulizia. Servizi Per Aziende, Manifestazioni E Supporto Agli Scambi Commerciali",
    "sg:phone":"+39 071 204735",
    "sg:postcode":"60126",
    "sg:province":"Ancona",
    "wof:name":"Cooperativa Portabagagli Stazione Soc. Coop. A R.l. - Cps",
    "wof:placetype":"venue"
},
  "geometry": {"coordinates":[13.445396,43.598934],"type":"Point"}
}