{
  "type": "Feature",
  "properties": {
    "addr:full":"13, Zona Artigianale Nord 39040 Ora Ora Bolzano/Bozen 39040",
    "addr:housenumber":"13",
    "addr:postcode":"39040;39040",
    "addr:street":"Zona Artigianale Nord",
    "iso:country":"IT",
    "sg:address":"13, Zona Artigianale Nord 39040 Ora",
    "sg:city":"Ora",
    "sg:classifiers":[
        {
            "category":"Home & Garden",
            "subcategory":"Home Furnishings",
            "type":"Retail Goods"
        }
    ],
    "sg:phone":"+39 0471 811236",
    "sg:postcode":"39040",
    "sg:province":"Bolzano/Bozen",
    "sg:tags":[
        "household"
    ],
    "wof:name":"Rossin S.r.l.",
    "wof:placetype":"venue"
},
  "geometry": {"coordinates":[11.317179,46.375698],"type":"Point"}
}