{
  "type": "Feature",
  "properties": {
    "iso:country":"IT",
    "sg:address":"7, V. Fossale San Rocco 13040 Alice Castello",
    "sg:city":"Alice Castello",
    "sg:classifiers":[
        {
            "category":"Real Estate",
            "subcategory":"Surveying",
            "type":"Services"
        }
    ],
    "sg:phone":"+39 39016190486",
    "sg:postcode":"13040",
    "sg:province":"Vercelli",
    "sg:tags":[
        "equipment",
        "material",
        "good",
        "-",
        "handling"
    ],
    "wof:name":"Tecnobelt Sas",
    "wof:placetype":"venue"
},
  "geometry": {"coordinates":[8.073247,45.364288],"type":"Point"}
}