{
  "type": "Feature",
  "properties": {
    "iso:country":"IT",
    "sg:address":"Via Negrelli 10 39100 Bolzano",
    "sg:city":"Bolzano",
    "sg:classifiers":[
        {
            "category":"Manufacturing",
            "subcategory":"Metals",
            "type":"Manufacturing & Wholesale Goods"
        }
    ],
    "sg:phone":"+39 0471 202994",
    "sg:postcode":"39100",
    "sg:province":"Bolzano/Bozen",
    "sg:tags":[
        "die",
        "aluminium",
        "casting"
    ],
    "sg:website":"www.engl.it",
    "wof:name":"Hanns Engl Snc",
    "wof:placetype":"venue"
},
  "geometry": {"coordinates":[11.328239,46.461643],"type":"Point"}
}