{
  "type": "Feature",
  "properties": {
    "addr:full":"20039 Varedo Varedo Milano 20039",
    "addr:postcode":"20039;20039",
    "iso:country":"IT",
    "sg:address":"20039 Varedo",
    "sg:city":"Varedo",
    "sg:orig_category":"Prodotti E Manufatti In Materie Plastiche",
    "sg:phone":"+39 036 258 0582",
    "sg:postcode":"20039",
    "sg:province":"Milano",
    "wof:name":"Bonetalli & Miranda Sas Di Bonetalli Renzo",
    "wof:placetype":"venue"
},
  "geometry": {"coordinates":[9.1810245514,45.4798240662],"type":"Point"}
}