{
  "type": "Feature",
  "properties": {
    "iso:country":"IT",
    "sg:address":"11, Via Ronchi Destra 35017 Piombino Dese",
    "sg:city":"Piombino Dese",
    "sg:classifiers":[
        {
            "category":"Building & Trades",
            "subcategory":"Construction",
            "type":"Services"
        }
    ],
    "sg:phone":"+39 049 936 5199",
    "sg:postcode":"35017",
    "sg:province":"Padova",
    "sg:tags":[
        "work",
        "public"
    ],
    "wof:name":"Cooperativa Persona A R.l.",
    "wof:placetype":"venue"
},
  "geometry": {"coordinates":[11.994317,45.594292],"type":"Point"}
}