{
  "type": "Feature",
  "properties": {
    "iso:country":"IT",
    "sg:address":"22, Via Diaz 25010 San Zeno Naviglio",
    "sg:city":"San Zeno Naviglio",
    "sg:classifiers":[
        {
            "category":"Shopping",
            "subcategory":"Crafts & Fabrics",
            "type":"Retail Goods"
        }
    ],
    "sg:phone":"+39 030 353 1688",
    "sg:postcode":"25010",
    "sg:province":"Brescia",
    "sg:tags":[
        "ceramic"
    ],
    "wof:name":"Valseriati Angelo & Bruni Zani Roberto (s.r.l.)",
    "wof:placetype":"venue"
},
  "geometry": {"coordinates":[10.217554,45.493595],"type":"Point"}
}