{
  "type": "Feature",
  "properties": {
    "iso:country":"IT",
    "sg:address":"00151 Roma",
    "sg:city":"Roma",
    "sg:orig_category":"Prodotti Alimentari",
    "sg:phone":"+39 06 582 7618",
    "sg:postcode":"00151",
    "sg:province":"Roma",
    "wof:name":"Viesto Gennaro",
    "wof:placetype":"venue"
},
  "geometry": {"coordinates":[12.4484558105,41.8688659668],"type":"Point"}
}