{
  "type": "Feature",
  "properties": {
    "iso:country":"IT",
    "sg:address":"20017 Rho",
    "sg:city":"Rho",
    "sg:orig_category":"Forniture Per Abbigliamento E Pelletterie",
    "sg:phone":"+39 02 9390 9170",
    "sg:postcode":"20017",
    "sg:province":"Milano",
    "wof:name":"Omar S.r.l.",
    "wof:placetype":"venue"
},
  "geometry": {"coordinates":[9.0615110397,45.5325584412],"type":"Point"}
}