{
  "type": "Feature",
  "properties": {
    "iso:country":"IT",
    "sg:address":"41018 San Cesario Sul Panaro",
    "sg:city":"San Cesario sul Panaro",
    "sg:orig_category":"Prodotti E Manufatti In Materie Plastiche",
    "sg:phone":"+39 059 923344",
    "sg:postcode":"41018",
    "sg:province":"Modena",
    "wof:name":"Modena Design S.r.l.",
    "wof:placetype":"venue"
},
  "geometry": {"coordinates":[11.029340744,44.5914726257],"type":"Point"}
}