{
  "type": "Feature",
  "properties": {
    "iso:country":"IT",
    "sg:address":"27, Via Melorie 56035 Lari",
    "sg:city":"Lari",
    "sg:classifiers":[
        {
            "category":"Parking",
            "subcategory":"Lot",
            "type":"Transportation"
        }
    ],
    "sg:phone":"+39 0587 617509",
    "sg:postcode":"56035",
    "sg:province":"Pisa",
    "sg:tags":[
        "transport",
        "road"
    ],
    "wof:name":"Meini Morando",
    "wof:placetype":"venue"
},
  "geometry": {"coordinates":[10.593736,43.611385],"type":"Point"}
}