{
  "type": "Feature",
  "properties": {
    "iso:country":"IT",
    "sg:address":"40050 Argelato",
    "sg:city":"Argelato",
    "sg:orig_category":"Banche E Servizi Finanziari",
    "sg:phone":"+39 051 663 5011",
    "sg:postcode":"40050",
    "sg:province":"Bologna",
    "sg:website":"http://www.emilbanca.it",
    "wof:name":"Emil Banca - Credito Cooperativo-bologna Scarl",
    "wof:placetype":"venue"
},
  "geometry": {"coordinates":[11.364972,44.488152],"type":"Point"}
}