{
  "type": "Feature",
  "properties": {
    "iso:country":"IT",
    "sg:address":"Corso Francia 141; Collegno",
    "sg:classifiers":[
        {
            "category":"Banks & Credit Unions",
            "subcategory":"Bank",
            "type":"Services"
        }
    ],
    "sg:phone":"+39 011 785284",
    "wof:name":"Banca Di Roma",
    "wof:placetype":"venue"
},
  "geometry": {"coordinates":[7.577783,45.072483],"type":"Point"}
}