{
  "type": "Feature",
  "properties": {
    "iso:country":"IT",
    "sg:address":"20019 Settimo Milanese",
    "sg:city":"Settimo Milanese",
    "sg:orig_category":"Prodotti Alimentari",
    "sg:phone":"+39 02 328 1478",
    "sg:postcode":"20019",
    "sg:province":"Milano",
    "wof:name":"Pravettoni Ermanno",
    "wof:placetype":"venue"
},
  "geometry": {"coordinates":[9.0072393417,45.4879760742],"type":"Point"}
}