{
  "type": "Feature",
  "properties": {
    "iso:country":"IT",
    "sg:address":"10154 Torino",
    "sg:city":"Torino",
    "sg:orig_category":"Termotecnica E Riscaldamento, Apparecchiature E Servizi",
    "sg:phone":"+39 011 242 6763",
    "sg:postcode":"10154",
    "sg:province":"Torino",
    "wof:name":"Dagna Giuseppe",
    "wof:placetype":"venue"
},
  "geometry": {"coordinates":[7.704576,45.092957],"type":"Point"}
}