{
  "type": "Feature",
  "properties": {
    "addr:full":"63017 Porto San Giorgio Porto San Giorgio Ascoli Piceno 63017",
    "addr:postcode":"63017;63017",
    "addr:street":"Piceno",
    "iso:country":"IT",
    "sg:address":"63017 Porto San Giorgio",
    "sg:city":"Porto San Giorgio",
    "sg:orig_category":"Musica",
    "sg:phone":"+39 0734 674849",
    "sg:postcode":"63017",
    "sg:province":"Ascoli Piceno",
    "wof:name":"Masciullo Lazzaro",
    "wof:placetype":"venue"
},
  "geometry": {"coordinates":[13.7929210663,43.1638298035],"type":"Point"}
}