{
  "type": "Feature",
  "properties": {
    "iso:country":"IT",
    "sg:address":"5, Via S. Caterina Da Siena 34122 Trieste",
    "sg:city":"Trieste",
    "sg:classifiers":[
        {
            "category":"Marine",
            "type":"Transportation"
        }
    ],
    "sg:phone":"+39 39040660076",
    "sg:postcode":"34122",
    "sg:province":"Trieste",
    "sg:tags":[
        "transport",
        "sea"
    ],
    "wof:name":"Gamap (s.r.l.)",
    "wof:placetype":"venue"
},
  "geometry": {"coordinates":[13.778407,45.653629],"type":"Point"}
}