{
  "type": "Feature",
  "properties": {
    "iso:country":"IT",
    "sg:address":"00040 Ariccia",
    "sg:city":"Ariccia",
    "sg:orig_category":"Frigotecnica, Apparecchiature E Servizi. Servizi Di Magazzinaggio E Movimentazione",
    "sg:phone":"+39 06 934 3771",
    "sg:postcode":"00040",
    "sg:province":"Roma",
    "wof:name":"Eurofrigo Srl",
    "wof:placetype":"venue"
},
  "geometry": {"coordinates":[12.6337223053,41.7127189636],"type":"Point"}
}