{
  "type": "Feature",
  "properties": {
    "iso:country":"IT",
    "sg:address":"Via Veneto 12 35020 Due Carrare",
    "sg:city":"Due Carrare",
    "sg:classifiers":[
        {
            "category":"Structure",
            "subcategory":"Factory",
            "type":"Public Place"
        }
    ],
    "sg:phone":"+39 049 529 0553",
    "sg:postcode":"35020",
    "sg:province":"Padova",
    "sg:tags":[
        "complete",
        "installations"
    ],
    "wof:name":"Comitec S.r.l.",
    "wof:placetype":"venue"
},
  "geometry": {"coordinates":[11.9121990204,45.3170623779],"type":"Point"}
}