{
  "type": "Feature",
  "properties": {
    "addr:full":"30, Via Panizzardo 24043 Caravaggio Caravaggio Bergamo 24043",
    "addr:postcode":"24043;24043",
    "addr:street":"Via Panizzardo",
    "iso:country":"IT",
    "sg:address":"30, Via Panizzardo 24043 Caravaggio",
    "sg:city":"Caravaggio",
    "sg:classifiers":[
        {
            "category":"Manufacturing",
            "subcategory":"Motor Vehicles & Parts",
            "type":"Manufacturing & Wholesale Goods"
        }
    ],
    "sg:phone":"+39 39036351591",
    "sg:postcode":"24043",
    "sg:province":"Bergamo",
    "sg:tags":[
        "engine"
    ],
    "wof:name":"Sorem Trasmissioni Meccaniche (s.p.a.)",
    "wof:placetype":"venue"
},
  "geometry": {"coordinates":[9.658179,45.47052],"type":"Point"}
}