{
  "type": "Feature",
  "properties": {
    "iso:country":"IT",
    "sg:address":"85/91, Corso Roma 20093 Cologno Monzese",
    "sg:city":"Cologno Monzese",
    "sg:classifiers":[
        {
            "category":"Professional",
            "subcategory":"Printing & Photocopies",
            "type":"Services"
        }
    ],
    "sg:phone":"+39 39022516511",
    "sg:postcode":"20093",
    "sg:province":"Milano",
    "wof:name":"Torriani & C Spa",
    "wof:placetype":"venue"
},
  "geometry": {"coordinates":[9.2815704346,45.5321807861],"type":"Point"}
}