{
  "type": "Feature",
  "properties": {
    "iso:country":"IT",
    "sg:address":"20128 Milano",
    "sg:city":"Milano",
    "sg:orig_category":"Cartotecnica E Servizi. Forniture Per Uffici",
    "sg:phone":"+39 02 259 0591",
    "sg:postcode":"20128",
    "sg:province":"Milano",
    "sg:website":"http://www.favorit.it",
    "wof:name":"Favorit Spa",
    "wof:placetype":"venue"
},
  "geometry": {"coordinates":[9.234201,45.507656],"type":"Point"}
}