{
  "type": "Feature",
  "properties": {
    "iso:country":"IT",
    "sg:address":"35010 Limena",
    "sg:city":"Limena",
    "sg:orig_category":"Forniture Per Edilizia E Lavori Pubblici",
    "sg:phone":"+39 049 884 0900",
    "sg:postcode":"35010",
    "sg:province":"Padova",
    "sg:website":"http://www.arcawood.it",
    "wof:name":"Arca Wood Srl",
    "wof:placetype":"venue"
},
  "geometry": {"coordinates":[11.8414945602,45.4720191956],"type":"Point"}
}