{
  "type": "Feature",
  "properties": {
    "iso:country":"IT",
    "sg:address":"28024 Gozzano",
    "sg:city":"Gozzano",
    "sg:orig_category":"Graniti",
    "sg:phone":"+39 0322 94284",
    "sg:postcode":"28024",
    "sg:province":"Novara",
    "wof:name":"Befo Graniti Di Bertona E Fornara Snc",
    "wof:placetype":"venue"
},
  "geometry": {"coordinates":[8.46473,45.696125],"type":"Point"}
}