{
  "type": "Feature",
  "properties": {
    "iso:country":"IT",
    "sg:address":"20, Via Caretti 24038 Sant'omobono Imagna",
    "sg:classifiers":[
        {
            "category":"Manufacturing",
            "subcategory":"Lumber",
            "type":"Manufacturing & Wholesale Goods"
        }
    ],
    "sg:phone":"+39 39035851275",
    "sg:postcode":"24038",
    "sg:province":"Bergamo",
    "sg:tags":[
        "wood"
    ],
    "wof:name":"Sacil",
    "wof:placetype":"venue"
},
  "geometry": {"coordinates":[9.534525,45.808647],"type":"Point"}
}