{
  "type": "Feature",
  "properties": {
    "addr:full":"4, Traversa Gesuiti 80045 Pompei Pompei Napoli 80045",
    "addr:housenumber":"4",
    "addr:postcode":"80045;80045",
    "addr:street":"Traversa Gesuiti",
    "iso:country":"IT",
    "sg:address":"4, Traversa Gesuiti 80045 Pompei",
    "sg:city":"Pompei",
    "sg:classifiers":[
        {
            "category":"Wholesale",
            "subcategory":"Medical Equipment & Supplies",
            "type":"Manufacturing & Wholesale Goods"
        }
    ],
    "sg:phone":"+39 081 850 7381",
    "sg:postcode":"80045",
    "sg:province":"Napoli",
    "sg:tags":[
        "-",
        "health",
        "instrument"
    ],
    "wof:name":"Cartaplast Di G.vitiello",
    "wof:placetype":"venue"
},
  "geometry": {"coordinates":[14.499516,40.726624],"type":"Point"}
}