{
  "type": "Feature",
  "properties": {
    "iso:country":"IT",
    "sg:address":"12061 San Giovanni",
    "sg:orig_category":"Macchine, Impianti Ed Attrezzature Per Agricoltura E Zootecnia",
    "sg:phone":"+39 0173 75503",
    "sg:postcode":"12061",
    "sg:province":"Cuneo",
    "wof:name":"Fea Renato",
    "wof:placetype":"venue"
},
  "geometry": {"coordinates":[7.848467,44.472946],"type":"Point"}
}