{
  "type": "Feature",
  "properties": {
    "addr:full":"95045 Misterbianco Misterbianco Catania 95045",
    "addr:postcode":"95045;95045",
    "iso:country":"IT",
    "sg:address":"95045 Misterbianco",
    "sg:city":"Misterbianco",
    "sg:orig_category":"Macchine, Impianti Ed Attrezzature Per Agricoltura E Zootecnia",
    "sg:phone":"+39 095 304457",
    "sg:postcode":"95045",
    "sg:province":"Catania",
    "wof:name":"Falco Giuseppe",
    "wof:placetype":"venue"
},
  "geometry": {"coordinates":[15.082842,37.49802],"type":"Point"}
}