{
  "type": "Feature",
  "properties": {
    "iso:country":"IT",
    "sg:address":"89125 Reggio Calabria",
    "sg:orig_category":"Scuole E Servizi Scolastici",
    "sg:phone":"+39 0965 373349",
    "sg:province":"RC",
    "wof:name":"Scuola Materna Pianeta Baby",
    "wof:placetype":"venue"
},
  "geometry": {"coordinates":[15.647851,38.110126],"type":"Point"}
}