{
  "type": "Feature",
  "properties": {
    "iso:country":"IT",
    "sg:address":"20145 Milano",
    "sg:city":"Milano",
    "sg:orig_category":"Apparecchi, Attrezzature E Forniture Per Centri Estetici",
    "sg:phone":"+39 02 498 7094",
    "sg:postcode":"20145",
    "sg:province":"Milano",
    "wof:name":"Enneci Di N. Ciampella & C. Sas.",
    "wof:placetype":"venue"
},
  "geometry": {"coordinates":[9.161996,45.474838],"type":"Point"}
}