{
  "type": "Feature",
  "properties": {
    "iso:country":"IT",
    "sg:address":"86025 Ripalimosani",
    "sg:city":"Ripalimosani",
    "sg:orig_category":"Prodotti Finiti Stampati. Forniture E Prodotti Informatici. Forniture Per Uffici",
    "sg:phone":"+39 0874 483224",
    "sg:postcode":"86025",
    "sg:province":"Campobasso",
    "wof:name":"Arti Grafiche La Regione Snc",
    "wof:placetype":"venue"
},
  "geometry": {"coordinates":[14.6471223831,41.6192092896],"type":"Point"}
}