{
  "type": "Feature",
  "properties": {
    "addr:full":"Via A. Sandroni 49 21040 Sumirago Sumirago Varese 21040",
    "addr:housenumber":"49",
    "addr:postcode":"21040;21040",
    "addr:street":"Via A. Sandroni",
    "iso:country":"IT",
    "sg:address":"Via A. Sandroni 49 21040 Sumirago",
    "sg:city":"Sumirago",
    "sg:classifiers":[
        {
            "category":"Structure",
            "subcategory":"Tunnel",
            "type":"Public Place"
        }
    ],
    "sg:phone":"+39 0331 909042",
    "sg:postcode":"21040",
    "sg:province":"Varese",
    "sg:tags":[
        "extrusion",
        "system",
        "extruders"
    ],
    "wof:name":"Leonard Snc Di Zgo Castelnovo & C",
    "wof:placetype":"venue"
},
  "geometry": {"coordinates":[8.826385,45.817604],"type":"Point"}
}