{
  "type": "Feature",
  "properties": {
    "iso:country":"IT",
    "sg:address":"35026 Conselve",
    "sg:city":"Conselve",
    "sg:orig_category":"Materiali E Componenti Elettrotecnici",
    "sg:phone":"+39 049 950 1290",
    "sg:postcode":"35026",
    "sg:province":"Padova",
    "wof:name":"Com.el. Srl Elet Plast",
    "wof:placetype":"venue"
},
  "geometry": {"coordinates":[11.887163,45.207012],"type":"Point"}
}