{
  "type": "Feature",
  "properties": {
    "iso:country":"IT",
    "sg:address":"10041 Carignano",
    "sg:city":"Carignano",
    "sg:classifiers":[
        {
            "category":"Health Services",
            "subcategory":"Health Practitioner",
            "type":"Services"
        }
    ],
    "sg:phone":"+39 011 969 2481",
    "sg:postcode":"10041",
    "sg:province":"Torino",
    "sg:tags":[
        "medici"
    ],
    "wof:name":"Vigada Guglielmo",
    "wof:placetype":"venue"
},
  "geometry": {"coordinates":[7.6702094078,44.9087677002],"type":"Point"}
}