{
  "type": "Feature",
  "properties": {
    "iso:country":"IT",
    "sg:address":"95129 Catania",
    "sg:city":"Catania",
    "sg:orig_category":"Motori Ed Organi Di Trasmissione. Ricambi E Componenti Dei Mezzi Di Trasporto",
    "sg:phone":"+39 095 536241",
    "sg:postcode":"95129",
    "sg:province":"Catania",
    "wof:name":"C.c.r.srl",
    "wof:placetype":"venue"
},
  "geometry": {"coordinates":[15.0986204147,37.5104866028],"type":"Point"}
}