{
  "type": "Feature",
  "properties": {
    "iso:country":"IT",
    "sg:address":"25031 Capriolo",
    "sg:city":"Capriolo",
    "sg:orig_category":"Forniture Per Attivita' Industriali",
    "sg:phone":"+39 030 746 0665",
    "sg:postcode":"25031",
    "sg:province":"Brescia",
    "wof:name":"Gitis Srl",
    "wof:placetype":"venue"
},
  "geometry": {"coordinates":[10.6109628677,45.3998527527],"type":"Point"}
}