{
  "type": "Feature",
  "properties": {
    "iso:country":"IT",
    "sg:address":"Piazza Roma, 11; Cortemilia; 12074",
    "sg:city":"Cortemilia",
    "sg:classifiers":[
        {
            "category":"Banks & Credit Unions",
            "subcategory":"Bank",
            "type":"Services"
        }
    ],
    "sg:phone":"+39 0173 81045",
    "sg:postcode":"12074",
    "sg:province":"Cuneo",
    "wof:name":"Banca Popolare Di Novara",
    "wof:placetype":"venue"
},
  "geometry": {"coordinates":[8.193379,44.57954],"type":"Point"}
}