{
  "type": "Feature",
  "properties": {
    "addr:full":"Via Marconi 33 25020 Azzano Mella Azzano Mella Brescia 25020",
    "addr:housenumber":"33",
    "addr:postcode":"25020;mella;25020",
    "addr:street":"Via Marconi",
    "iso:country":"IT",
    "sg:address":"Via Marconi 33 25020 Azzano Mella",
    "sg:city":"Azzano Mella",
    "sg:orig_category":"Ladies' Shoes",
    "sg:phone":"+39 030 974 8734",
    "sg:postcode":"25020",
    "sg:province":"Brescia",
    "wof:name":"Giunteria Giusy Di Conti Giuseppina Snc",
    "wof:placetype":"venue"
},
  "geometry": {"coordinates":[10.158539,45.527733],"type":"Point"}
}