{
  "type": "Feature",
  "properties": {
    "iso:country":"IT",
    "sg:address":"10, Via Panzeri Pietro 20123 Milano",
    "sg:city":"Milano",
    "sg:classifiers":[
        {
            "category":"Shopping",
            "subcategory":"Gifts & Souvenirs",
            "type":"Retail Goods"
        }
    ],
    "sg:phone":"+39 39023498498",
    "sg:postcode":"20123",
    "sg:province":"Milano",
    "wof:name":"Vega 3 (s.r.l.)",
    "wof:placetype":"venue"
},
  "geometry": {"coordinates":[9.17839,45.453129],"type":"Point"}
}