{
  "type": "Feature",
  "properties": {
    "addr:full":"90047 Partinico Partinico Palermo 90047",
    "addr:postcode":"90047;90047",
    "iso:country":"IT",
    "sg:address":"90047 Partinico",
    "sg:city":"Partinico",
    "sg:orig_category":"Prodotti Di Base E Forniture Per Industria Alimentare E Bevande",
    "sg:phone":"+39 091 890 6911",
    "sg:postcode":"90047",
    "sg:province":"Palermo",
    "wof:name":"Russo Rosario",
    "wof:placetype":"venue"
},
  "geometry": {"coordinates":[13.1186695099,38.0459823608],"type":"Point"}
}