{
  "type": "Feature",
  "properties": {
    "addr:full":"35123 Padova Padova Padova 35123",
    "addr:postcode":"35123;35123",
    "iso:country":"IT",
    "sg:address":"35123 Padova",
    "sg:city":"Padova",
    "sg:classifiers":[
        {
            "category":"Building & Trades",
            "subcategory":"Construction",
            "type":"Services"
        }
    ],
    "sg:phone":"+39 049 656790",
    "sg:postcode":"35123",
    "sg:province":"Padova",
    "sg:tags":[
        "art",
        "civil",
        "industry",
        "craft",
        "wood",
        "furnishing",
        "works",
        "artistic"
    ],
    "wof:name":"Morassutti Amistani Srl",
    "wof:placetype":"venue"
},
  "geometry": {"coordinates":[11.8807067871,45.401927948],"type":"Point"}
}