{
  "type": "Feature",
  "properties": {
    "iso:country":"IT",
    "sg:address":"62014 Corridonia",
    "sg:city":"Corridonia",
    "sg:orig_category":"Macchine, Impianti Ed Attrezzature Per Abbigliamento E Pelletterie",
    "sg:phone":"+39 0733 292903",
    "sg:postcode":"62014",
    "sg:province":"Macerata",
    "wof:name":"Studio Erre-gi Snc Di Ricci & Giustozzi",
    "wof:placetype":"venue"
},
  "geometry": {"coordinates":[13.493119,43.263538],"type":"Point"}
}