{
  "type": "Feature",
  "properties": {
    "iso:country":"IT",
    "sg:address":"71010 Lesina",
    "sg:city":"Lesina",
    "sg:orig_category":"Carni, Salumi E Pesci. Zootecnia E Pesca, Allevamento Piccoli Animali",
    "sg:phone":"+39 0882 92392",
    "sg:postcode":"71010",
    "sg:province":"Foggia",
    "wof:name":"Mediterranea Produzioni Srl",
    "wof:placetype":"venue"
},
  "geometry": {"coordinates":[15.353778,41.860481],"type":"Point"}
}