{
  "type": "Feature",
  "properties": {
    "addr:full":"13835 Trivero Trivero Biella 13835",
    "addr:housenumber":"13835",
    "addr:postcode":"13835",
    "iso:country":"IT",
    "sg:address":"13835 Trivero",
    "sg:city":"Trivero",
    "sg:orig_category":"Filati E Materie Prime Tessili",
    "sg:phone":"+39 015 737605",
    "sg:postcode":"13835",
    "sg:province":"Biella",
    "wof:name":"Filatura Pettinata Trabaldo Celestino",
    "wof:placetype":"venue"
},
  "geometry": {"coordinates":[8.1113796234,45.6160583496],"type":"Point"}
}