{
  "type": "Feature",
  "properties": {
    "iso:country":"IT",
    "sg:address":"20152 Milano",
    "sg:city":"Milano",
    "sg:orig_category":"Abbigliamento Esterno, Maglierie E Pelliccerie",
    "sg:phone":"+39 02 4830 4650",
    "sg:postcode":"20152",
    "sg:province":"Milano",
    "wof:name":"Gusella S.p.a.",
    "wof:placetype":"venue"
},
  "geometry": {"coordinates":[9.066766,45.444138],"type":"Point"}
}