{
  "type": "Feature",
  "properties": {
    "addr:full":"4, Via Scandilli S. 60022 Castelfidardo Castelfidardo Ancona 60022",
    "addr:postcode":"60022;60022",
    "addr:street":"Via Scandilli S.",
    "iso:country":"IT",
    "sg:address":"4, Via Scandilli S. 60022 Castelfidardo",
    "sg:city":"Castelfidardo",
    "sg:classifiers":[
        {
            "category":"Manufacturing",
            "subcategory":"Metals",
            "type":"Manufacturing & Wholesale Goods"
        }
    ],
    "sg:phone":"+39 071 721 4411",
    "sg:postcode":"60022",
    "sg:province":"Ancona",
    "sg:tags":[
        "metallurgy",
        "metalworking"
    ],
    "wof:name":"So.m.i.press Societa' Metalli Iniettati S.r.l.",
    "wof:placetype":"venue"
},
  "geometry": {"coordinates":[13.5187568665,43.6158561707],"type":"Point"}
}