{
  "type": "Feature",
  "properties": {
    "addr:full":"20146 Milano Milano Milano 20146",
    "addr:postcode":"20146;20146",
    "iso:country":"IT",
    "sg:address":"20146 Milano",
    "sg:city":"Milano",
    "sg:orig_category":"Servizi Editoriali. Servizi Per Aziende, Manifestazioni E Supporto Agli Scambi Commerciali",
    "sg:phone":"+39 02 4771 1017",
    "sg:postcode":"20146",
    "sg:province":"Milano",
    "wof:name":"Immagine Comunicazione Azienda Di Anna De Capitani & C. Sas",
    "wof:placetype":"venue"
},
  "geometry": {"coordinates":[9.146059,45.453121],"type":"Point"}
}