{
  "type": "Feature",
  "properties": {
    "addr:full":"Via Brandellero 23 36034 Malo Malo Vicenza 36034",
    "addr:housenumber":"23",
    "addr:postcode":"36034;36034",
    "addr:street":"Via Brandellero",
    "iso:country":"IT",
    "sg:address":"Via Brandellero 23 36034 Malo",
    "sg:city":"Malo",
    "sg:classifiers":[
        {
            "category":"Manufacturing",
            "subcategory":"Glass & Minerals",
            "type":"Manufacturing & Wholesale Goods"
        }
    ],
    "sg:phone":"+39 0445 602966",
    "sg:postcode":"36034",
    "sg:province":"Vicenza",
    "sg:tags":[
        "finishing"
    ],
    "wof:name":"Vetreria Romagna Srl",
    "wof:placetype":"venue"
},
  "geometry": {"coordinates":[11.40561,45.6642],"type":"Point"}
}