{
  "type": "Feature",
  "properties": {
    "iso:country":"IT",
    "sg:address":"47100 Forli'",
    "sg:orig_category":"Filati E Materie Prime Tessili",
    "sg:phone":"+39 0543 723566",
    "sg:postcode":"47100",
    "sg:province":"Forl\u00ec-Cesena",
    "wof:name":"Marzari Andrea",
    "wof:placetype":"venue"
},
  "geometry": {"coordinates":[12.0608177185,44.2343635559],"type":"Point"}
}