{
  "type": "Feature",
  "properties": {
    "iso:country":"IT",
    "sg:address":"15/int, Corso Roma 10024 Moncalieri",
    "sg:city":"Moncalieri",
    "sg:classifiers":[
        {
            "category":"Utilities",
            "subcategory":"Electric",
            "type":"Services"
        }
    ],
    "sg:phone":"+39 39011642019",
    "sg:postcode":"10024",
    "sg:province":"Torino",
    "sg:tags":[
        "component",
        "electronic"
    ],
    "wof:name":"Proces (s.n.c.)",
    "wof:placetype":"venue"
},
  "geometry": {"coordinates":[7.671916,45.004356],"type":"Point"}
}