{
  "type": "Feature",
  "properties": {
    "addr:full":"35024 Bovolenta Bovolenta Padova 35024",
    "addr:postcode":"35024;35024",
    "iso:country":"IT",
    "sg:address":"35024 Bovolenta",
    "sg:city":"Bovolenta",
    "sg:orig_category":"Prodotti Alimentari",
    "sg:phone":"+39 049 538 6056",
    "sg:postcode":"35024",
    "sg:province":"Padova",
    "wof:name":"La Medica Padana",
    "wof:placetype":"venue"
},
  "geometry": {"coordinates":[11.8892288208,45.280796051],"type":"Point"}
}