{
  "type": "Feature",
  "properties": {
    "iso:country":"IT",
    "sg:address":"64, Via Del Commercio 60131 Ancona",
    "sg:city":"Ancona",
    "sg:classifiers":[
        {
            "category":"Wholesale",
            "subcategory":"Medical Equipment & Supplies",
            "type":"Manufacturing & Wholesale Goods"
        }
    ],
    "sg:phone":"+39 071 280 2575",
    "sg:postcode":"60131",
    "sg:province":"Ancona",
    "sg:tags":[
        "-",
        "health",
        "instrument"
    ],
    "wof:name":"Itapak Srl",
    "wof:placetype":"venue"
},
  "geometry": {"coordinates":[13.507377,43.592834],"type":"Point"}
}