{
  "type": "Feature",
  "properties": {
    "addr:full":"00182 Roma Roma Roma 00182",
    "addr:postcode":"00182;00182",
    "iso:country":"IT",
    "sg:address":"00182 Roma",
    "sg:city":"Roma",
    "sg:orig_category":"Centri Di Estetica E Cosmesi E Servizi",
    "sg:phone":"+39 06 7049 3800",
    "sg:postcode":"00182",
    "sg:province":"Roma",
    "wof:name":"Da-ma",
    "wof:placetype":"venue"
},
  "geometry": {"coordinates":[12.513251,41.88311],"type":"Point"}
}