{
  "type": "Feature",
  "properties": {
    "addr:full":"25030 Barbariga Barbariga Brescia 25030",
    "addr:postcode":"25030;25030",
    "iso:country":"IT",
    "sg:address":"25030 Barbariga",
    "sg:city":"Barbariga",
    "sg:orig_category":"Forniture Per Abbigliamento E Pelletterie",
    "sg:phone":"+39 030 971 9402",
    "sg:postcode":"25030",
    "sg:province":"Brescia",
    "wof:name":"Studio Moda Effe",
    "wof:placetype":"venue"
},
  "geometry": {"coordinates":[10.183555603,45.5294914246],"type":"Point"}
}