{
  "type": "Feature",
  "properties": {
    "iso:country":"IT",
    "sg:address":"20052 Monza",
    "sg:city":"Monza",
    "sg:orig_category":"Psicologi - Studi",
    "sg:phone":"+39 039 202 1931",
    "sg:postcode":"20052",
    "sg:province":"Milano",
    "wof:name":"Fedeli Dott. Pierluigi",
    "wof:placetype":"venue"
},
  "geometry": {"coordinates":[9.2918701172,45.5774917603],"type":"Point"}
}