{
  "type": "Feature",
  "properties": {
    "addr:full":"12038 Savigliano Savigliano Cuneo 12038",
    "addr:postcode":"12038;12038",
    "iso:country":"IT",
    "sg:address":"12038 Savigliano",
    "sg:city":"Savigliano",
    "sg:classifiers":[
        {
            "category":"Health Services",
            "subcategory":"Health Practitioner",
            "type":"Services"
        }
    ],
    "sg:phone":"+39 0172 31661",
    "sg:postcode":"12038",
    "sg:province":"Cuneo",
    "sg:tags":[
        "medici"
    ],
    "wof:name":"Villa Marco",
    "wof:placetype":"venue"
},
  "geometry": {"coordinates":[7.652557373,44.6504211426],"type":"Point"}
}