{
  "type": "Feature",
  "properties": {
    "iso:country":"IT",
    "sg:address":"Piazza Nervi 1 15076 Ovada",
    "sg:city":"Ovada",
    "sg:classifiers":[
        {
            "category":"Banks & Credit Unions",
            "subcategory":"Bureau De Change",
            "type":"Services"
        }
    ],
    "sg:phone":"+39 0143 81844",
    "sg:postcode":"15076",
    "sg:province":"Alessandria",
    "sg:tags":[
        "press",
        "hydraulic"
    ],
    "sg:website":"www.immagine.com/vezzani",
    "wof:name":"Vezzani Spa",
    "wof:placetype":"venue"
},
  "geometry": {"coordinates":[8.645596,44.643528],"type":"Point"}
}