{
  "type": "Feature",
  "properties": {
    "iso:country":"IT",
    "sg:address":"98057 Milazzo",
    "sg:city":"Milazzo",
    "sg:orig_category":"Antiquariato",
    "sg:phone":"+39 090 922 2300",
    "sg:postcode":"98057",
    "sg:province":"Messina",
    "wof:name":"Mellina Antonia",
    "wof:placetype":"venue"
},
  "geometry": {"coordinates":[15.237034,38.200718],"type":"Point"}
}