{
  "type": "Feature",
  "properties": {
    "addr:full":"16, Via Gramsci Antonio 27049 Stradella Stradella Pavia 27049",
    "addr:postcode":"27049;27049",
    "addr:street":"Via Gramsci Antonio",
    "iso:country":"IT",
    "sg:address":"16, Via Gramsci Antonio 27049 Stradella",
    "sg:city":"Stradella",
    "sg:classifiers":[
        {
            "category":"Manufacturing",
            "subcategory":"Metals",
            "type":"Manufacturing & Wholesale Goods"
        }
    ],
    "sg:phone":"+39 39038548444",
    "sg:postcode":"27049",
    "sg:province":"Pavia",
    "sg:tags":[
        "metallurgy",
        "metalworking"
    ],
    "wof:name":"Pi.ro S.r.l.",
    "wof:placetype":"venue"
},
  "geometry": {"coordinates":[9.1565628052,45.1858863831],"type":"Point"}
}