{
  "type": "Feature",
  "properties": {
    "iso:country":"IT",
    "sg:address":"52037 Sansepolcro",
    "sg:city":"Sansepolcro",
    "sg:orig_category":"Giardinaggio - Macchine Ed Attrezzi",
    "sg:phone":"+39 0575 742010",
    "sg:postcode":"52037",
    "sg:province":"Arezzo",
    "wof:name":"Linea Verde Snc",
    "wof:placetype":"venue"
},
  "geometry": {"coordinates":[11.874938,43.458492],"type":"Point"}
}