{
  "type": "Feature",
  "properties": {
    "iso:country":"IT",
    "sg:address":"94018 Troina",
    "sg:city":"Troina",
    "sg:orig_category":"Materiali Semilavorati Metallici",
    "sg:phone":"+39 0935 657160",
    "sg:postcode":"94018",
    "sg:province":"Enna",
    "wof:name":"La.me.tro. Snc Di Carmeni & Di Franca",
    "wof:placetype":"venue"
},
  "geometry": {"coordinates":[14.635463,37.755424],"type":"Point"}
}