{
  "type": "Feature",
  "properties": {
    "addr:full":"89900 Vibo Valentia Vibo Valentia Vibo Valentia 89900",
    "addr:postcode":"89900;89900",
    "addr:street":"Vibo Valentia",
    "iso:country":"IT",
    "sg:address":"89900 Vibo Valentia",
    "sg:city":"Vibo Valentia",
    "sg:classifiers":[
        {
            "category":"Autos & Motor Vehicles",
            "subcategory":"Fuel & Gas Station",
            "type":"Retail Goods"
        }
    ],
    "sg:phone":"+39 0963 547636",
    "sg:postcode":"89900",
    "sg:province":"Vibo Valentia",
    "sg:tags":[
        "petroleum",
        "products"
    ],
    "wof:name":"Autoricambi Ceravolo E C. Srl",
    "wof:placetype":"venue"
},
  "geometry": {"coordinates":[16.1427574158,38.6945381165],"type":"Point"}
}