{
  "type": "Feature",
  "properties": {
    "addr:full":"31040 Mansue' Treviso 31040",
    "addr:postcode":"31040;31040",
    "addr:street":"Mansue ' Treviso",
    "iso:country":"IT",
    "sg:address":"31040 Mansue'",
    "sg:orig_category":"Arredo Bagno Ed Idrosanitari",
    "sg:phone":"+39 0422 711311",
    "sg:postcode":"31040",
    "sg:province":"Treviso",
    "sg:website":"http://www.santarossa.it",
    "wof:name":"Armony Spa",
    "wof:placetype":"venue"
},
  "geometry": {"coordinates":[12.561106,45.822857],"type":"Point"}
}