{
  "type": "Feature",
  "properties": {
    "iso:country":"IT",
    "sg:address":"12, Via Del Duca Lillo 20091 Bresso",
    "sg:city":"Bresso",
    "sg:classifiers":[
        {
            "category":"Wholesale",
            "subcategory":"Drugs",
            "type":"Manufacturing & Wholesale Goods"
        }
    ],
    "sg:phone":"+39 390 266 5241",
    "sg:postcode":"20091",
    "sg:province":"Milano",
    "sg:tags":[
        "chemical",
        "pharmaceutical"
    ],
    "wof:name":"Zambon Group S.p.a.",
    "wof:placetype":"venue"
},
  "geometry": {"coordinates":[9.189945,45.531143],"type":"Point"}
}