{
  "type": "Feature",
  "properties": {
    "iso:country":"IT",
    "sg:address":"95129 Catania",
    "sg:city":"Catania",
    "sg:orig_category":"Centri Di Estetica E Cosmesi E Servizi",
    "sg:phone":"+39 095 534842",
    "sg:postcode":"95129",
    "sg:province":"Catania",
    "wof:name":"Studio & Co.",
    "wof:placetype":"venue"
},
  "geometry": {"coordinates":[15.102899,37.512012],"type":"Point"}
}