{
  "type": "Feature",
  "properties": {
    "iso:country":"IT",
    "sg:address":"20134 Milano",
    "sg:city":"Milano",
    "sg:orig_category":"Traslochi",
    "sg:phone":"+39 02 264 0320",
    "sg:postcode":"20134",
    "sg:province":"Milano",
    "sg:website":"http://www.franzosini.it",
    "wof:name":"Casa Di Spedizioni Luciano Franzosini Spa",
    "wof:placetype":"venue"
},
  "geometry": {"coordinates":[9.246046,45.479149],"type":"Point"}
}