{
  "type": "Feature",
  "properties": {
    "iso:country":"IT",
    "sg:address":"68, Viale Europa 80059 Torre Del Greco",
    "sg:city":"Torre del Greco",
    "sg:classifiers":[
        {
            "category":"Home & Garden",
            "subcategory":"Home Furnishings",
            "type":"Retail Goods"
        }
    ],
    "sg:phone":"+39 081 847 2946",
    "sg:postcode":"80059",
    "sg:province":"Napoli",
    "sg:tags":[
        "household"
    ],
    "wof:name":"V.r.m. Srl",
    "wof:placetype":"venue"
},
  "geometry": {"coordinates":[14.357899,40.849873],"type":"Point"}
}