{
  "type": "Feature",
  "properties": {
    "iso:country":"IT",
    "sg:address":"655, Via Delle Ville 55012 Capannori",
    "sg:city":"Capannori",
    "sg:classifiers":[
        {
            "category":"Farming",
            "subcategory":"Livestock Farm",
            "type":"Manufacturing & Wholesale Goods"
        }
    ],
    "sg:phone":"+39 0583 929582",
    "sg:postcode":"55012",
    "sg:province":"Lucca",
    "sg:tags":[
        "agriculture"
    ],
    "wof:name":"Talini Antonio Srl",
    "wof:placetype":"venue"
},
  "geometry": {"coordinates":[10.540079,43.907936],"type":"Point"}
}