{
  "type": "Feature",
  "properties": {
    "addr:full":"55, Via Garibaldi 48024 Massa Lombarda Massa Lombarda Ravenna 48024",
    "addr:postcode":"48024;48024",
    "addr:street":"Via Garibaldi",
    "iso:country":"IT",
    "sg:address":"55, Via Garibaldi 48024 Massa Lombarda",
    "sg:city":"Massa Lombarda",
    "sg:classifiers":[
        {
            "category":"Manufacturing",
            "subcategory":"Printing",
            "type":"Manufacturing & Wholesale Goods"
        }
    ],
    "sg:phone":"+39 39054582105",
    "sg:postcode":"48024",
    "sg:province":"Ravenna",
    "sg:tags":[
        "publishing"
    ],
    "wof:name":"Giornale Di Massa",
    "wof:placetype":"venue"
},
  "geometry": {"coordinates":[11.8295755386,44.44688797],"type":"Point"}
}