{
  "type": "Feature",
  "properties": {
    "iso:country":"IT",
    "sg:address":"Via Restello 98 35010 Villa Del Conte",
    "sg:city":"Villa del Conte",
    "sg:classifiers":[
        {
            "category":"Home & Garden",
            "subcategory":"Building Materials",
            "type":"Retail Goods"
        }
    ],
    "sg:phone":"+39 049 932 5112",
    "sg:postcode":"35010",
    "sg:province":"Padova",
    "sg:tags":[
        "garage",
        "door"
    ],
    "sg:website":"www.ballan.com",
    "wof:name":"Ballan Spa",
    "wof:placetype":"venue"
},
  "geometry": {"coordinates":[11.845593,45.619343],"type":"Point"}
}