{
  "type": "Feature",
  "properties": {
    "addr:full":"27040 Casatisma Casatisma Pavia 27040",
    "addr:postcode":"27040;27040",
    "iso:country":"IT",
    "sg:address":"27040 Casatisma",
    "sg:city":"Casatisma",
    "sg:orig_category":"Lavorazioni Meccaniche E Servizi",
    "sg:phone":"+39 0383 84321",
    "sg:postcode":"27040",
    "sg:province":"Pavia",
    "wof:name":"Imcos Srl",
    "wof:placetype":"venue"
},
  "geometry": {"coordinates":[9.133694,45.048412],"type":"Point"}
}