{
  "type": "Feature",
  "properties": {
    "iso:country":"IT",
    "sg:address":"Via Alfonsine 18; S. Donato Milanese",
    "sg:classifiers":[
        {
            "category":"Banks & Credit Unions",
            "subcategory":"Bank",
            "type":"Services"
        }
    ],
    "sg:phone":"+39 02 527 9049",
    "wof:name":"Credito Italiano Spa",
    "wof:placetype":"venue"
},
  "geometry": {"coordinates":[9.266127,45.423252],"type":"Point"}
}