{
  "type": "Feature",
  "properties": {
    "iso:country":"IT",
    "sg:address":"Via Vespucci 16037 Riva Trigoso",
    "sg:classifiers":[
        {
            "category":"Autos & Motor Vehicles",
            "subcategory":"Boat Sales",
            "type":"Retail Goods"
        }
    ],
    "sg:phone":"+39 0185 44706",
    "sg:province":"GE",
    "sg:tags":[
        "construction",
        "environment-friendly",
        "orientated"
    ],
    "wof:name":"Cantiere Navale Diano Srl",
    "wof:placetype":"venue"
},
  "geometry": {"coordinates":[9.423565,44.259644],"type":"Point"}
}