{
  "type": "Feature",
  "properties": {
    "iso:country":"IT",
    "sg:address":"66020 San Giovanni Teatino",
    "sg:city":"Sambuceto",
    "sg:orig_category":"Elettrotecnica Industriale, Prodotti E Apparecchiature",
    "sg:phone":"+39 085 446 2641",
    "sg:postcode":"66020",
    "sg:province":"Chieti",
    "sg:website":"http://www.edimac.it",
    "wof:name":"Edimac Srl",
    "wof:placetype":"venue"
},
  "geometry": {"coordinates":[14.172642,42.417503],"type":"Point"}
}