{
  "type": "Feature",
  "properties": {
    "iso:country":"IT",
    "sg:address":"31015 Conegliano",
    "sg:city":"Conegliano",
    "sg:orig_category":"Tappeti",
    "sg:phone":"+39 0438 22313",
    "sg:postcode":"31015",
    "sg:province":"Treviso",
    "wof:name":"Dal Vera Giacomo & C. Sas",
    "wof:placetype":"venue"
},
  "geometry": {"coordinates":[12.299629,45.885502],"type":"Point"}
}