{
  "type": "Feature",
  "properties": {
    "addr:full":"53043 Chiusi Chiusi Siena 53043",
    "addr:postcode":"53043;53043",
    "iso:country":"IT",
    "sg:address":"53043 Chiusi",
    "sg:city":"Chiusi",
    "sg:orig_category":"Non-classified Establishments",
    "sg:phone":"+39 0578 274404",
    "sg:postcode":"53043",
    "sg:province":"Siena",
    "wof:name":"Ceramiche Barbetti Srl",
    "wof:placetype":"venue"
},
  "geometry": {"coordinates":[11.909537,43.017517],"type":"Point"}
}