{
  "type": "Feature",
  "properties": {
    "iso:country":"IT",
    "sg:address":"70010 Valenzano",
    "sg:city":"Valenzano",
    "sg:orig_category":"Scuole E Servizi Scolastici. Servizi Per Lo Sport E Il Tempo Libero",
    "sg:phone":"+39 080 467 6375",
    "sg:postcode":"70010",
    "sg:province":"Bari",
    "wof:name":"Centro Sportivo Green Finger (s.r.l.)",
    "wof:placetype":"venue"
},
  "geometry": {"coordinates":[16.878365,41.040565],"type":"Point"}
}