{
  "type": "Feature",
  "properties": {
    "iso:country":"IT",
    "sg:address":"80, Via Mazzini 37121 Verona",
    "sg:city":"Verona",
    "sg:classifiers":[
        {
            "category":"Personal",
            "subcategory":"Shoe Repair & Shine",
            "type":"Services"
        }
    ],
    "sg:phone":"+39 045 800 7165",
    "sg:postcode":"37121",
    "sg:province":"Verona",
    "sg:tags":[
        "leather"
    ],
    "wof:name":"Nuova Principe S.n.c.",
    "wof:placetype":"venue"
},
  "geometry": {"coordinates":[10.883698,45.347149],"type":"Point"}
}