{
  "type": "Feature",
  "properties": {
    "addr:full":"80046 San Giorgio A Cremano San Giorgio a Cremano Napoli 80046",
    "addr:housenumber":"80046",
    "addr:postcode":"80046",
    "addr:street":"San",
    "iso:country":"IT",
    "sg:address":"80046 San Giorgio A Cremano",
    "sg:city":"San Giorgio a Cremano",
    "sg:orig_category":"Servizi Culturali E Per Lo Spettacolo. Servizi Per Lo Sport E Il Tempo Libero. Servizi Per Aziende, Manifestazioni E Supporto Agli Scambi Commerciali",
    "sg:phone":"+39 081 574 4232",
    "sg:postcode":"80046",
    "sg:province":"Napoli",
    "wof:name":"Circolo Culturale Mediterraneo",
    "wof:placetype":"venue"
},
  "geometry": {"coordinates":[14.340637,40.831474],"type":"Point"}
}