{
  "type": "Feature",
  "properties": {
    "iso:country":"IT",
    "sg:address":"37036 San Martino Buon Albergo",
    "sg:city":"San Martino Buon Albergo",
    "sg:orig_category":"Contenitori - Produzione E Commercio",
    "sg:phone":"+39 045 990166",
    "sg:postcode":"37036",
    "sg:province":"Verona",
    "wof:name":"Legnimpex Srl",
    "wof:placetype":"venue"
},
  "geometry": {"coordinates":[11.084085,45.416168],"type":"Point"}
}