{
  "type": "Feature",
  "properties": {
    "addr:full":"06055 Marsciano Marsciano Perugia 06055",
    "addr:postcode":"06055;06055",
    "iso:country":"IT",
    "sg:address":"06055 Marsciano",
    "sg:city":"Marsciano",
    "sg:orig_category":"Prodotti Chimici Secondari. Tempo Libero - Articoli E Forniture. Servizi Per Lo Sport E Il Tempo Libero. Servizi Per Aziende, Manifestazioni E Supporto Agli Scambi Commerciali",
    "sg:phone":"+39 075 874 3888",
    "sg:postcode":"06055",
    "sg:province":"Perugia",
    "wof:name":"Marianeschi Fuochi D'artificio",
    "wof:placetype":"venue"
},
  "geometry": {"coordinates":[12.3371257782,42.9144744873],"type":"Point"}
}