{
  "type": "Feature",
  "properties": {
    "iso:country":"IT",
    "sg:address":"23807 Merate",
    "sg:city":"Merate",
    "sg:orig_category":"Sport - Articoli E Forniture",
    "sg:phone":"+39 039 990 6460",
    "sg:postcode":"23807",
    "sg:province":"Lecco",
    "wof:name":"L'armeria Di Merate (s.a.s.)",
    "wof:placetype":"venue"
},
  "geometry": {"coordinates":[9.419386,45.701015],"type":"Point"}
}