{
  "type": "Feature",
  "properties": {
    "iso:country":"IT",
    "sg:address":"10092 Beinasco",
    "sg:city":"Beinasco",
    "sg:orig_category":"Trattamenti Termici E Superficiali Metalli, Galvanotecnica",
    "sg:phone":"+39 011 397 2372",
    "sg:postcode":"10092",
    "sg:province":"Torino",
    "wof:name":"V.m.m. (s.r.l.)",
    "wof:placetype":"venue"
},
  "geometry": {"coordinates":[7.584508,45.027153],"type":"Point"}
}