{
  "type": "Feature",
  "properties": {
    "iso:country":"IT",
    "sg:address":"32, Via Piazzon 36051 Creazzo",
    "sg:city":"Creazzo",
    "sg:classifiers":[
        {
            "category":"Professional",
            "subcategory":"Engineering",
            "type":"Services"
        }
    ],
    "sg:phone":"+39 0444 520544",
    "sg:postcode":"36051",
    "sg:province":"Vicenza",
    "sg:tags":[
        "machine",
        "-",
        "mechanical"
    ],
    "wof:name":"Automatismi Brazzale S.r.l.",
    "wof:placetype":"venue"
},
  "geometry": {"coordinates":[11.496082,45.533241],"type":"Point"}
}