{
  "type": "Feature",
  "properties": {
    "iso:country":"IT",
    "sg:address":"22100 Como",
    "sg:city":"Como",
    "sg:orig_category":"Servizi Di Magazzinaggio E Movimentazione. Servizi Ausiliari Di Sorveglianza, Manutenzione E Pulizia. Servizi Per Aziende, Manifestazioni E Supporto Agli Scambi Commerciali",
    "sg:phone":"+39 031 525093",
    "sg:postcode":"22100",
    "sg:province":"Como",
    "sg:website":"http://www.clmitalia.it",
    "wof:name":"Clm Scarl",
    "wof:placetype":"venue"
},
  "geometry": {"coordinates":[9.092748,45.799282],"type":"Point"}
}