{
  "type": "Feature",
  "properties": {
    "iso:country":"IT",
    "sg:address":"20010 Vanzago",
    "sg:city":"Vanzago",
    "sg:orig_category":"Servizi E Lavori Per Arredamento E Industria Del Legno",
    "sg:phone":"+39 02 934 0516",
    "sg:postcode":"20010",
    "sg:province":"Milano",
    "wof:name":"L.a.c.i. Snc Di F. Rossoni E D. Galbagini",
    "wof:placetype":"venue"
},
  "geometry": {"coordinates":[8.983696,45.519077],"type":"Point"}
}