{
  "type": "Feature",
  "properties": {
    "addr:full":"33090 Sequals Sequals Pordenone 33090",
    "addr:postcode":"33090;33090",
    "iso:country":"IT",
    "sg:address":"33090 Sequals",
    "sg:city":"Sequals",
    "sg:orig_category":"Tipografie",
    "sg:phone":"+39 0427 93370",
    "sg:postcode":"33090",
    "sg:province":"Pordenone",
    "wof:name":"Grafiche Tielle Snc",
    "wof:placetype":"venue"
},
  "geometry": {"coordinates":[12.596619,45.893658],"type":"Point"}
}