{
  "type": "Feature",
  "properties": {
    "iso:country":"IT",
    "sg:address":"00193 Roma",
    "sg:city":"Roma",
    "sg:classifiers":[
        {
            "category":"Health Services",
            "subcategory":"Health Practitioner",
            "type":"Services"
        }
    ],
    "sg:phone":"+39 06 6813 6059",
    "sg:postcode":"00193",
    "sg:province":"Roma",
    "sg:tags":[
        "medici"
    ],
    "wof:name":"Rizzotto Antonio",
    "wof:placetype":"venue"
},
  "geometry": {"coordinates":[12.4950647354,41.8964385986],"type":"Point"}
}