{
  "type": "Feature",
  "properties": {
    "iso:country":"IT",
    "sg:address":"12042 Bra",
    "sg:city":"Bra",
    "sg:orig_category":"Banche E Servizi Finanziari",
    "sg:phone":"+39 0172 425644",
    "sg:postcode":"12042",
    "sg:province":"Cuneo",
    "wof:name":"Banca Fideuram Spa",
    "wof:placetype":"venue"
},
  "geometry": {"coordinates":[7.853923,44.69371],"type":"Point"}
}