{
  "type": "Feature",
  "properties": {
    "addr:full":"Via Manzoni 23 25041 Boario Terme Boario Terme Brescia 25041",
    "addr:housenumber":"23",
    "addr:postcode":"25041;25041",
    "addr:street":"Via Manzoni",
    "iso:country":"IT",
    "sg:address":"Via Manzoni 23 25041 Boario Terme",
    "sg:city":"Boario Terme",
    "sg:classifiers":[
        {
            "category":"Manufacturing",
            "subcategory":"Metals",
            "type":"Manufacturing & Wholesale Goods"
        }
    ],
    "sg:phone":"+39 036 453 4247",
    "sg:postcode":"25041",
    "sg:province":"Brescia",
    "sg:tags":[
        "profile"
    ],
    "sg:website":"www.siderval.it",
    "wof:name":"Siderval S.p.a.",
    "wof:placetype":"venue"
},
  "geometry": {"coordinates":[10.2229576111,45.5398292542],"type":"Point"}
}