{
  "type": "Feature",
  "properties": {
    "addr:full":"V.le Roma 205 47100 Forli' Forl\u00ec-Cesena 47100",
    "addr:housenumber":"205",
    "addr:postcode":"47100;47100",
    "addr:street":"V.Le Roma;' Forli\u0300-Cesena",
    "iso:country":"IT",
    "sg:address":"V.le Roma 205 47100 Forli'",
    "sg:classifiers":[
        {
            "category":"Home & Garden",
            "subcategory":"Building Materials",
            "type":"Retail Goods"
        }
    ],
    "sg:phone":"+39 0543 780189",
    "sg:postcode":"47100",
    "sg:province":"Forl\u00ec-Cesena",
    "sg:tags":[
        "finishing",
        "stucco"
    ],
    "sg:website":"www.novacolor.it",
    "wof:name":"Nova Color Di Ori Divonne & C. Sas",
    "wof:placetype":"venue"
},
  "geometry": {"coordinates":[12.0783967972,44.2064704895],"type":"Point"}
}