{
  "type": "Feature",
  "properties": {
    "addr:full":"65010 Spoltore Spoltore Pescara 65010",
    "addr:postcode":"65010;65010",
    "iso:country":"IT",
    "sg:address":"65010 Spoltore",
    "sg:city":"Spoltore",
    "sg:orig_category":"Impiantistica E Prodotti Tecnologici Per Edilizia. Elettronica Professionale E Di Consumo. Accessori Dei Mezzi Di Trasporto. Forniture Industriali Per Prevenzione, Controllo E Sicurezza",
    "sg:phone":"+39 085 497 1580",
    "sg:postcode":"65010",
    "sg:province":"Pescara",
    "wof:name":"Elettro Mg Di Giancola Mario",
    "wof:placetype":"venue"
},
  "geometry": {"coordinates":[14.144216,42.460678],"type":"Point"}
}