{
  "type": "Feature",
  "properties": {
    "iso:country":"IT",
    "sg:address":"22070 Casnate Con Bernate",
    "sg:city":"Casnate",
    "sg:orig_category":"Articoli Natalizi",
    "sg:phone":"+39 031 450322",
    "sg:postcode":"22070",
    "sg:province":"Como",
    "wof:name":"Comarco Sas",
    "wof:placetype":"venue"
},
  "geometry": {"coordinates":[9.072703,45.754562],"type":"Point"}
}