{
  "type": "Feature",
  "properties": {
    "iso:country":"IT",
    "sg:address":"57023 Cecina",
    "sg:city":"Cecina",
    "sg:orig_category":"Bevande, Vini E Liquori. Ristorazione E Locali Pubblici Affini. Ristoranti Ed Esercizi Affini. Servizi Ausiliari Di Ristorazione E Di Intrattenimento",
    "sg:phone":"+39 0586 680045",
    "sg:postcode":"57023",
    "sg:province":"Livorno",
    "wof:name":"Drugstore Pub Di Vanni & C Snc",
    "wof:placetype":"venue"
},
  "geometry": {"coordinates":[10.495868,43.317638],"type":"Point"}
}