{
  "type": "Feature",
  "properties": {
    "addr:full":"Via Fratte 7048 63019 Sant'elpidio A Mare Ascoli Piceno 63019",
    "addr:housenumber":"7048",
    "addr:postcode":"63019;63019",
    "addr:street":"Via Fratte",
    "iso:country":"IT",
    "sg:address":"Via Fratte 7048 63019 Sant'elpidio A Mare",
    "sg:orig_category":"Ladies' Shoes",
    "sg:phone":"+39 0734 860152",
    "sg:postcode":"63019",
    "sg:province":"Ascoli Piceno",
    "sg:website":"www.prevata.com",
    "wof:name":"Calzaturificio Azimut Srl",
    "wof:placetype":"venue"
},
  "geometry": {"coordinates":[13.735713,43.289677],"type":"Point"}
}