{
  "type": "Feature",
  "properties": {
    "iso:country":"IT",
    "sg:address":"20127 Milano",
    "sg:city":"Milano",
    "sg:orig_category":"Lavorazioni Meccaniche E Servizi. Riparazione Dei Mezzi Di Trasporto",
    "sg:phone":"+39 02 256 5501",
    "sg:postcode":"20127",
    "sg:province":"Milano",
    "wof:name":"L'autorettifica Di Mandelli I. & C. (s.a.s.)",
    "wof:placetype":"venue"
},
  "geometry": {"coordinates":[9.239511,45.50338],"type":"Point"}
}