{
  "type": "Feature",
  "properties": {
    "iso:country":"IT",
    "sg:address":"20154 Milano",
    "sg:city":"Milano",
    "sg:orig_category":"Abbigliamento Esterno, Maglierie E Pelliccerie. Shopping",
    "sg:phone":"+39 02 3360 3336",
    "sg:postcode":"20154",
    "sg:province":"Milano",
    "wof:name":"Dimensione Sposi Ofelia Srl",
    "wof:placetype":"venue"
},
  "geometry": {"coordinates":[9.176206,45.481388],"type":"Point"}
}