{
  "type": "Feature",
  "properties": {
    "addr:full":"20010 Canegrate Canegrate Milano 20010",
    "addr:postcode":"20010;20010",
    "iso:country":"IT",
    "sg:address":"20010 Canegrate",
    "sg:city":"Canegrate",
    "sg:orig_category":"Trattamenti Termici E Superficiali Metalli, Galvanotecnica",
    "sg:phone":"+39 0331 400430",
    "sg:postcode":"20010",
    "sg:province":"Milano",
    "sg:website":"http://www.toscasrl.com",
    "wof:name":"Tosca Srl",
    "wof:placetype":"venue"
},
  "geometry": {"coordinates":[8.928876,45.570087],"type":"Point"}
}