{
  "type": "Feature",
  "properties": {
    "iso:country":"IT",
    "sg:address":"43045 Fornovo Di Taro",
    "sg:city":"Fornovo di Taro",
    "sg:orig_category":"Servizi E Lavori Per Abbigliamento E Pelletterie",
    "sg:phone":"+39 0525 2474",
    "sg:postcode":"43045",
    "sg:province":"Parma",
    "wof:name":"Lavamil",
    "wof:placetype":"venue"
},
  "geometry": {"coordinates":[10.226377,44.716602],"type":"Point"}
}