{
  "type": "Feature",
  "properties": {
    "addr:full":"03013 Ferentino Ferentino Frosinone 03013",
    "addr:postcode":"03013;03013",
    "iso:country":"IT",
    "sg:address":"03013 Ferentino",
    "sg:city":"Ferentino",
    "sg:orig_category":"Macchine E Forniture Per Arredamento E Industria Del Legno. Macchine Utensili E Impianti",
    "sg:phone":"+39 0775 246789",
    "sg:postcode":"03013",
    "sg:province":"Frosinone",
    "wof:name":"Italutensili Srl Unipersonale",
    "wof:placetype":"venue"
},
  "geometry": {"coordinates":[13.243263,41.684708],"type":"Point"}
}