{
  "type": "Feature",
  "properties": {
    "addr:full":"30175 Marghera Marghera Venezia 30175",
    "addr:postcode":"30175;30175",
    "iso:country":"IT",
    "sg:address":"30175 Marghera",
    "sg:city":"Marghera",
    "sg:orig_category":"Servizi Ausiliari Di Analisi, Controllo E Ricerca",
    "sg:phone":"+39 041 930464",
    "sg:postcode":"30175",
    "sg:province":"Venezia",
    "wof:name":"Base (s.r.l.)",
    "wof:placetype":"venue"
},
  "geometry": {"coordinates":[12.224575,45.463936],"type":"Point"}
}