{
  "type": "Feature",
  "properties": {
    "iso:country":"IT",
    "sg:address":"16/f, Via Frattina 35011 Campodarsego",
    "sg:city":"Campodarsego",
    "sg:classifiers":[
        {
            "category":"Home & Garden",
            "subcategory":"Home Furnishings",
            "type":"Retail Goods"
        }
    ],
    "sg:phone":"+39 049 556 5655",
    "sg:postcode":"35011",
    "sg:province":"Padova",
    "sg:tags":[
        "household"
    ],
    "wof:name":"Maspi (s.r.l.)",
    "wof:placetype":"venue"
},
  "geometry": {"coordinates":[11.913717,45.468536],"type":"Point"}
}