{
  "type": "Feature",
  "properties": {
    "addr:full":"Via Isole Del; Roma",
    "addr:street":"Via Isole Del Roma",
    "iso:country":"IT",
    "sg:address":"Via Isole Del; Roma",
    "sg:classifiers":[
        {
            "category":"Banks & Credit Unions",
            "subcategory":"Bank",
            "type":"Services"
        }
    ],
    "sg:phone":"+39 06 564 0293",
    "wof:name":"Banca Di Roma",
    "wof:placetype":"venue"
},
  "geometry": {"coordinates":[12.509106,41.917568],"type":"Point"}
}