{
  "type": "Feature",
  "properties": {
    "addr:full":"73100 Lecce Lecce Lecce 73100",
    "addr:postcode":"73100;73100",
    "iso:country":"IT",
    "sg:address":"73100 Lecce",
    "sg:city":"Lecce",
    "sg:orig_category":"Gioielleria, Oreficeria E Argenteria. Shopping",
    "sg:phone":"+39 0832 331013",
    "sg:postcode":"73100",
    "sg:province":"Lecce",
    "sg:website":"http://www.lozaffiro.it",
    "wof:name":"Puglielli Massimiliano - Lo Zaffiro",
    "wof:placetype":"venue"
},
  "geometry": {"coordinates":[18.173986,40.350491],"type":"Point"}
}