{
  "type": "Feature",
  "properties": {
    "iso:country":"IT",
    "sg:address":"00015 Monterotondo",
    "sg:city":"Monterotondo",
    "sg:orig_category":"Manufacturers: Prefabbricati",
    "sg:phone":"+39 06 906 9907",
    "sg:postcode":"00015",
    "sg:province":"Roma",
    "wof:name":"I.ge.co. Snc",
    "wof:placetype":"venue"
},
  "geometry": {"coordinates":[12.594785,42.080284],"type":"Point"}
}