{
  "type": "Feature",
  "properties": {
    "addr:full":"60, Via Emilia Ovest 29010 Rottofreno Rottofreno Piacenza 29010",
    "addr:postcode":"29010;29010",
    "addr:street":"Via Emilia Ovest",
    "iso:country":"IT",
    "sg:address":"60, Via Emilia Ovest 29010 Rottofreno",
    "sg:city":"Rottofreno",
    "sg:classifiers":[
        {
            "category":"Professional",
            "subcategory":"Engineering",
            "type":"Services"
        }
    ],
    "sg:phone":"+39 0523 782811",
    "sg:postcode":"29010",
    "sg:province":"Piacenza",
    "sg:tags":[
        "machine",
        "-",
        "mechanical"
    ],
    "wof:name":"Linea (s.r.l.)",
    "wof:placetype":"venue"
},
  "geometry": {"coordinates":[9.602222,45.056221],"type":"Point"}
}