{
  "type": "Feature",
  "properties": {
    "iso:country":"IT",
    "sg:address":"16042 Carasco",
    "sg:city":"Carasco",
    "sg:orig_category":"Materie Plastiche - Produzione E Lavorazione",
    "sg:phone":"+39 0185 382320",
    "sg:postcode":"16042",
    "sg:province":"Genova",
    "wof:name":"Uniplast Snc",
    "wof:placetype":"venue"
},
  "geometry": {"coordinates":[9.355481,44.343758],"type":"Point"}
}