{
  "type": "Feature",
  "properties": {
    "iso:country":"IT",
    "sg:address":"70037 Ruvo Di Puglia",
    "sg:city":"Ruvo di Puglia",
    "sg:orig_category":"Articoli Da Regalo. Arte Ed Artigianato Artistico",
    "sg:phone":"+39 080 360 1001",
    "sg:postcode":"70037",
    "sg:province":"Bari",
    "sg:website":"http://www.gb-collezioni.it",
    "wof:name":"Gb. Collezioni Di Curci Maria & Cappelluti Michele Snc",
    "wof:placetype":"venue"
},
  "geometry": {"coordinates":[16.464146,41.064796],"type":"Point"}
}