{
  "type": "Feature",
  "properties": {
    "iso:country":"IT",
    "sg:address":"20060 Pozzuolo Martesana",
    "sg:city":"Pozzuolo Martesana",
    "sg:classifiers":[
        {
            "category":"Professional",
            "subcategory":"Engineering",
            "type":"Services"
        }
    ],
    "sg:phone":"+39 02 950031",
    "sg:postcode":"20060",
    "sg:province":"Milano",
    "sg:tags":[
        "equipment",
        "product",
        "industrial",
        "electrical"
    ],
    "sg:website":"http://www.elsist.com",
    "wof:name":"Elsist Srl",
    "wof:placetype":"venue"
},
  "geometry": {"coordinates":[9.479031,45.520031],"type":"Point"}
}