{
  "type": "Feature",
  "properties": {
    "addr:full":"28, Via Liguria 20068 Peschiera Borromeo Peschiera Borromeo Milano 20068",
    "addr:postcode":"20068;20068",
    "addr:street":"Via Liguria",
    "iso:country":"IT",
    "sg:address":"28, Via Liguria 20068 Peschiera Borromeo",
    "sg:city":"Peschiera Borromeo",
    "sg:classifiers":[
        {
            "category":"Wholesale",
            "subcategory":"Medical Equipment & Supplies",
            "type":"Manufacturing & Wholesale Goods"
        }
    ],
    "sg:phone":"+39 02 5165 0371",
    "sg:postcode":"20068",
    "sg:province":"Milano",
    "sg:tags":[
        "-",
        "health",
        "instrument"
    ],
    "wof:name":"Gruppo Bioimpianti Srl",
    "wof:placetype":"venue"
},
  "geometry": {"coordinates":[9.324155,45.429718],"type":"Point"}
}