{
  "type": "Feature",
  "properties": {
    "iso:country":"IT",
    "sg:address":"44042 Cento",
    "sg:city":"Cento",
    "sg:orig_category":"Macchine, Impianti Ed Attrezzature Per Industria Alimentare E Bevande",
    "sg:phone":"+39 051 684 2166",
    "sg:postcode":"44042",
    "sg:province":"Ferrara",
    "wof:name":"Axor (s.r.l.)",
    "wof:placetype":"venue"
},
  "geometry": {"coordinates":[11.295753,44.790031],"type":"Point"}
}