{
  "type": "Feature",
  "properties": {
    "iso:country":"IT",
    "sg:address":"41/e, V. Brescia 25065 Lumezzane",
    "sg:city":"Lumezzane",
    "sg:classifiers":[
        {
            "category":"Shopping",
            "type":"Retail Goods"
        }
    ],
    "sg:phone":"+39 030 897 0870",
    "sg:postcode":"25065",
    "sg:province":"Brescia",
    "sg:tags":[
        "finished",
        "-",
        "metallic"
    ],
    "sg:website":"http://www.labeg.it",
    "wof:name":"La B. E G. Di Bardini & C. Snc",
    "wof:placetype":"venue"
},
  "geometry": {"coordinates":[10.234246254,45.6522750854],"type":"Point"}
}