{
  "type": "Feature",
  "properties": {
    "iso:country":"IT",
    "sg:address":"Contrada Santissimo 91029 Santa Ninfa",
    "sg:city":"Santa Ninfa",
    "sg:classifiers":[
        {
            "category":"Communications",
            "subcategory":"Television Station",
            "type":"Services"
        }
    ],
    "sg:phone":"+39 39092462200",
    "sg:postcode":"91029",
    "sg:province":"Trapani",
    "sg:tags":[
        "audio-visual"
    ],
    "wof:name":"Sa.ni.co. Srl",
    "wof:placetype":"venue"
},
  "geometry": {"coordinates":[12.866247,37.768127],"type":"Point"}
}