{
  "type": "Feature",
  "properties": {
    "iso:country":"IT",
    "sg:address":"95045 Misterbianco",
    "sg:city":"Misterbianco",
    "sg:orig_category":"Abbigliamento Esterno, Maglierie E Pelliccerie. Forniture Per Il Settore Dello Spettacolo",
    "sg:phone":"+39 095 714 2490",
    "sg:postcode":"95045",
    "sg:province":"Catania",
    "wof:name":"Malilu' Moda Di Maria Nicolosi & C. (s.n.c.)",
    "wof:placetype":"venue"
},
  "geometry": {"coordinates":[15.057237,37.528393],"type":"Point"}
}