{
  "type": "Feature",
  "properties": {
    "addr:full":"56122 Pisa Pisa Pisa 56122",
    "addr:postcode":"56122;56122",
    "iso:country":"IT",
    "sg:address":"56122 Pisa",
    "sg:city":"Pisa",
    "sg:orig_category":"Pubblica Amministrazione",
    "sg:phone":"+39 050 838601",
    "sg:postcode":"56122",
    "sg:province":"Pisa",
    "wof:name":"Isp.centr.repressione Frodi",
    "wof:placetype":"venue"
},
  "geometry": {"coordinates":[10.3806877136,43.7161445618],"type":"Point"}
}