{
  "type": "Feature",
  "properties": {
    "iso:country":"IT",
    "sg:address":"15, Via Buonarroti Michelangelo 10095 Grugliasco",
    "sg:city":"Grugliasco",
    "sg:classifiers":[
        {
            "category":"Manufacturing",
            "subcategory":"Rubber & Plastics",
            "type":"Manufacturing & Wholesale Goods"
        }
    ],
    "sg:phone":"+39 39011781747",
    "sg:postcode":"10095",
    "sg:province":"Torino",
    "wof:name":"Elelys Spa",
    "wof:placetype":"venue"
},
  "geometry": {"coordinates":[7.6023359299,45.0764770508],"type":"Point"}
}