{
  "type": "Feature",
  "properties": {
    "iso:country":"IT",
    "sg:address":"Viale Lombardia 5/a 24050 Orio Al Serio",
    "sg:city":"Orio al Serio",
    "sg:orig_category":"Masks For Photolithography",
    "sg:phone":"+39 035 437 0411",
    "sg:postcode":"24050",
    "sg:province":"Bergamo",
    "wof:name":"Reproscan Srl",
    "wof:placetype":"venue"
},
  "geometry": {"coordinates":[9.684633,45.663696],"type":"Point"}
}