{
  "type": "Feature",
  "properties": {
    "addr:full":"98040 Torregrotta Torregrotta Messina 98040",
    "addr:postcode":"98040;98040",
    "iso:country":"IT",
    "sg:address":"98040 Torregrotta",
    "sg:city":"Torregrotta",
    "sg:orig_category":"Serramenti Ed Infissi",
    "sg:phone":"+39 090 991 0170",
    "sg:postcode":"98040",
    "sg:province":"Messina",
    "wof:name":"Cannistra' Andrea",
    "wof:placetype":"venue"
},
  "geometry": {"coordinates":[15.34808,38.211624],"type":"Point"}
}