{
  "type": "Feature",
  "properties": {
    "iso:country":"IT",
    "sg:address":"81050 Pastorano",
    "sg:city":"Pastorano",
    "sg:orig_category":"Non-classified Establishments",
    "sg:phone":"+39 0823 654989",
    "sg:postcode":"81050",
    "sg:province":"Caserta",
    "wof:name":"Catoplastic Srl",
    "wof:placetype":"venue"
},
  "geometry": {"coordinates":[14.199241,41.181889],"type":"Point"}
}