{
  "type": "Feature",
  "properties": {
    "iso:country":"IT",
    "sg:address":"00198 Roma",
    "sg:city":"Roma",
    "sg:orig_category":"Scuole E Servizi Scolastici. Ospedali E Servizi Sanitari",
    "sg:phone":"+39 06 4429 1049",
    "sg:postcode":"00198",
    "sg:province":"Roma",
    "wof:name":"Istituto Di Ortofonologia",
    "wof:placetype":"venue"
},
  "geometry": {"coordinates":[12.503461,41.912437],"type":"Point"}
}