{
  "type": "Feature",
  "properties": {
    "addr:full":"Via A. Grandi 7 40012 Calderara Di Reno Calderara di Reno Bologna 40012",
    "addr:housenumber":"7",
    "addr:postcode":"40012;40012",
    "addr:street":"Via A. Grandi",
    "iso:country":"IT",
    "sg:address":"Via A. Grandi 7 40012 Calderara Di Reno",
    "sg:city":"Calderara di Reno",
    "sg:classifiers":[
        {
            "category":"Shopping",
            "subcategory":"Computers & Home Electronics",
            "type":"Retail Goods"
        }
    ],
    "sg:phone":"+39 051 722310",
    "sg:postcode":"40012",
    "sg:province":"Bologna",
    "sg:tags":[
        "electronic",
        "module"
    ],
    "wof:name":"Urei Di Bianchi Dino & C. Snc",
    "wof:placetype":"venue"
},
  "geometry": {"coordinates":[11.346481,44.494221],"type":"Point"}
}