{
  "type": "Feature",
  "properties": {
    "addr:full":"20136 Milano Milano Milano 20136",
    "addr:postcode":"20136;20136",
    "iso:country":"IT",
    "sg:address":"20136 Milano",
    "sg:city":"Milano",
    "sg:classifiers":[
        {
            "category":"Professional",
            "subcategory":"Business Services",
            "type":"Services"
        }
    ],
    "sg:phone":"+39 02 5810 0241",
    "sg:postcode":"20136",
    "sg:province":"Milano",
    "sg:tags":[
        "auxiliary",
        "restaurant",
        "entertainment",
        "leisure",
        "catering",
        "services",
        "sport",
        "similar"
    ],
    "wof:name":"Tropicalia Srl",
    "wof:placetype":"venue"
},
  "geometry": {"coordinates":[9.177397,45.448673],"type":"Point"}
}