{
  "type": "Feature",
  "properties": {
    "iso:country":"IT",
    "sg:address":"10133 Torino",
    "sg:city":"Torino",
    "sg:orig_category":"Sport - Articoli E Forniture",
    "sg:phone":"+39 011 661 0422",
    "sg:postcode":"10133",
    "sg:province":"Torino",
    "wof:name":"New Line Amsei Sas",
    "wof:placetype":"venue"
},
  "geometry": {"coordinates":[7.685918,45.009018],"type":"Point"}
}