{
  "type": "Feature",
  "properties": {
    "addr:full":"52, Viale Borri Giuseppe 21053 Castellanza Castellanza Varese 21053",
    "addr:housenumber":"52",
    "addr:postcode":"21053;21053",
    "addr:street":"Viale Borri Giuseppe",
    "iso:country":"IT",
    "sg:address":"52, Viale Borri Giuseppe 21053 Castellanza",
    "sg:city":"Castellanza",
    "sg:classifiers":[
        {
            "category":"Utilities",
            "subcategory":"Electric",
            "type":"Services"
        }
    ],
    "sg:phone":"+39 0331 679680",
    "sg:postcode":"21053",
    "sg:province":"Varese",
    "sg:tags":[
        "component",
        "electronic"
    ],
    "wof:name":"Baldi Srl",
    "wof:placetype":"venue"
},
  "geometry": {"coordinates":[8.826385,45.817604],"type":"Point"}
}