{
  "type": "Feature",
  "properties": {
    "addr:full":"09124 Cagliari Cagliari Cagliari 09124",
    "addr:postcode":"09124;09124",
    "iso:country":"IT",
    "sg:address":"09124 Cagliari",
    "sg:city":"Cagliari",
    "sg:orig_category":"Climatizzazione E Condizionamento, Apparecchiature E Servizi",
    "sg:phone":"+39 070 669091",
    "sg:postcode":"09124",
    "sg:province":"Cagliari",
    "sg:website":"http://www.riva-sas.it",
    "wof:name":"R.i.v.a. Sas",
    "wof:placetype":"venue"
},
  "geometry": {"coordinates":[9.112147,39.212975],"type":"Point"}
}