{
  "type": "Feature",
  "properties": {
    "iso:country":"IT",
    "sg:address":"22, Via Benessea 17035 Cisano Sul Neva",
    "sg:city":"Cisano sul Neva",
    "sg:classifiers":[
        {
            "category":"Professional",
            "subcategory":"Engineering",
            "type":"Services"
        }
    ],
    "sg:phone":"+39 0182 595494",
    "sg:postcode":"17035",
    "sg:province":"Savona",
    "sg:tags":[
        "machine",
        "-",
        "mechanical"
    ],
    "wof:name":"Icomar Italia Srl",
    "wof:placetype":"venue"
},
  "geometry": {"coordinates":[8.160261,44.07526],"type":"Point"}
}