{
  "type": "Feature",
  "properties": {
    "iso:country":"IT",
    "sg:address":"20146 Milano",
    "sg:city":"Milano",
    "sg:orig_category":"Informatica - Consulenza E Servizi. Servizi Ausiliari Di Analisi, Controllo E Ricerca. Servizi Per Aziende, Manifestazioni E Supporto Agli Scambi Commerciali",
    "sg:phone":"+39 02 423 9449",
    "sg:postcode":"20146",
    "sg:province":"Milano",
    "wof:name":"D. S. Data Srl",
    "wof:placetype":"venue"
},
  "geometry": {"coordinates":[9.153077,45.452297],"type":"Point"}
}