{
  "type": "Feature",
  "properties": {
    "iso:country":"IT",
    "sg:address":"29100 Piacenza",
    "sg:city":"Piacenza",
    "sg:orig_category":"Cemento E Calcestruzzo - Manufatti",
    "sg:phone":"+39 0523 751128",
    "sg:postcode":"29100",
    "sg:province":"Piacenza",
    "wof:name":"M.f. Manstretta Francesco Laterizi Srl",
    "wof:placetype":"venue"
},
  "geometry": {"coordinates":[8.705935,44.923347],"type":"Point"}
}