{
  "type": "Feature",
  "properties": {
    "iso:country":"IT",
    "sg:address":"81025 Marcianise",
    "sg:city":"Marcianise",
    "sg:orig_category":"Arredo Cucina Ed Elettrodomestici",
    "sg:phone":"+39 0823 824678",
    "sg:postcode":"81025",
    "sg:province":"Caserta",
    "sg:website":"http://www.pierrearredi.it",
    "wof:name":"Pierre Srl",
    "wof:placetype":"venue"
},
  "geometry": {"coordinates":[14.297743,41.015236],"type":"Point"}
}