{
  "type": "Feature",
  "properties": {
    "iso:country":"IT",
    "sg:address":"Str. Statale Tiburtina Km 64 67063 Oricola",
    "sg:classifiers":[
        {
            "category":"Education",
            "subcategory":"University",
            "type":"Public Place"
        }
    ],
    "sg:phone":"+39 0863 900004",
    "sg:postcode":"67063",
    "sg:province":"L'Aquila",
    "sg:tags":[
        "training",
        "cad"
    ],
    "sg:website":"www.simadspa.it",
    "wof:name":"Simad Spa",
    "wof:placetype":"venue"
},
  "geometry": {"coordinates":[13.399934,42.350697],"type":"Point"}
}