{
  "type": "Feature",
  "properties": {
    "addr:full":"Via G. Marconi 3 40011 Anzola Dell'emilia Bologna 40011",
    "addr:housenumber":"3",
    "addr:postcode":"40011;40011",
    "addr:street":"Via G. Marconi",
    "iso:country":"IT",
    "sg:address":"Via G. Marconi 3 40011 Anzola Dell'emilia",
    "sg:orig_category":"Test Stands For Trucks And Utility Vehicles",
    "sg:phone":"+39 051 732652",
    "sg:postcode":"40011",
    "sg:province":"Bologna",
    "sg:website":"www.emanuel1899.com",
    "wof:name":"Emanuel Srl",
    "wof:placetype":"venue"
},
  "geometry": {"coordinates":[11.222641,44.490631],"type":"Point"}
}