{
  "type": "Feature",
  "properties": {
    "iso:country":"IT",
    "sg:address":"Via Bruno Pontecorvo 61/c 51015 Monsummano Terme",
    "sg:city":"Monsummano Terme",
    "sg:classifiers":[
        {
            "category":"Shopping",
            "subcategory":"Shoes",
            "type":"Retail Goods"
        }
    ],
    "sg:phone":"+39 0572 82861",
    "sg:postcode":"51015",
    "sg:province":"Pistoia",
    "sg:tags":[
        "men's",
        "boot"
    ],
    "wof:name":"Calzaturificio Zagor Di Bianco Antonio E Giuseppe S.n.c.",
    "wof:placetype":"venue"
},
  "geometry": {"coordinates":[10.8100442886,43.8591117859],"type":"Point"}
}