{
  "type": "Feature",
  "properties": {
    "addr:full":"86100 Campobasso Campobasso Campobasso 86100",
    "addr:postcode":"86100;86100",
    "iso:country":"IT",
    "sg:address":"86100 Campobasso",
    "sg:city":"Campobasso",
    "sg:orig_category":"Servizi Per Aziende, Manifestazioni E Supporto Agli Scambi Commerciali",
    "sg:phone":"+39 0874 61105",
    "sg:postcode":"86100",
    "sg:province":"Campobasso",
    "wof:name":"Mp Mirabilia Srl",
    "wof:placetype":"venue"
},
  "geometry": {"coordinates":[14.671653,41.566757],"type":"Point"}
}