{
  "type": "Feature",
  "properties": {
    "addr:full":"20080 Ozzero Ozzero Milano 20080",
    "addr:postcode":"20080;20080",
    "iso:country":"IT",
    "sg:address":"20080 Ozzero",
    "sg:city":"Ozzero",
    "sg:orig_category":"Prodotti E Manufatti In Materie Plastiche",
    "sg:phone":"+39 02 949 8181",
    "sg:postcode":"20080",
    "sg:province":"Milano",
    "wof:name":"Piad Prod. Ind.li Applicazioni D'arredamento Spa",
    "wof:placetype":"venue"
},
  "geometry": {"coordinates":[9.2262239456,45.4768600464],"type":"Point"}
}