{
  "type": "Feature",
  "properties": {
    "iso:country":"IT",
    "sg:address":"60035 Jesi",
    "sg:city":"Jesi",
    "sg:orig_category":"Petroli, Gas E Combustibili. Termotecnica E Riscaldamento, Apparecchiature E Servizi",
    "sg:phone":"+39 0731 209090",
    "sg:postcode":"60035",
    "sg:province":"Ancona",
    "wof:name":"Pirani Giuseppe Di Pirani Paolo & Oranognicoli",
    "wof:placetype":"venue"
},
  "geometry": {"coordinates":[13.2548046112,43.5223197937],"type":"Point"}
}