{
  "type": "Feature",
  "properties": {
    "iso:country":"IT",
    "sg:address":"Via Alveo Zennillo Sanseverino 80044 Ottaviano",
    "sg:city":"Ottaviano",
    "sg:classifiers":[
        {
            "category":"Shopping",
            "subcategory":"Department Store",
            "type":"Retail Goods"
        }
    ],
    "sg:phone":"+39 081 827 9422",
    "sg:postcode":"80044",
    "sg:province":"Napoli",
    "sg:tags":[
        "linen",
        "bed"
    ],
    "wof:name":"Linea C Di Carbone Vincenzo E C. Sas",
    "wof:placetype":"venue"
},
  "geometry": {"coordinates":[14.251636,40.840096],"type":"Point"}
}