{
  "type": "Feature",
  "properties": {
    "addr:full":"30035 Mirano Mirano Venezia 30035",
    "addr:postcode":"30035;30035",
    "iso:country":"IT",
    "sg:address":"30035 Mirano",
    "sg:city":"Mirano",
    "sg:orig_category":"Servizi E Lavori Per Arredamento E Industria Del Legno. Forniture Per Congressi, Fiere E Manifestazioni. Servizi Per Aziende, Manifestazioni E Supporto Agli Scambi Commerciali",
    "sg:phone":"+39 041 570 2178",
    "sg:postcode":"30035",
    "sg:province":"Venezia",
    "wof:name":"Fioreria Esmeralda Di Schwaiger Ingeborg",
    "wof:placetype":"venue"
},
  "geometry": {"coordinates":[12.148533,45.488865],"type":"Point"}
}