{
  "type": "Feature",
  "properties": {
    "iso:country":"IT",
    "sg:address":"13, Via Vignola 23848 Oggiono",
    "sg:city":"Oggiono",
    "sg:classifiers":[
        {
            "category":"Food & Beverages",
            "subcategory":"Groceries & Convenience Stores",
            "type":"Retail Goods"
        }
    ],
    "sg:phone":"+39 0341 576061",
    "sg:postcode":"23848",
    "sg:province":"Lecco",
    "sg:tags":[
        "product",
        "related"
    ],
    "wof:name":"Ripamonti Carni (s.r.l.)",
    "wof:placetype":"venue"
},
  "geometry": {"coordinates":[9.3902397156,45.8193855286],"type":"Point"}
}