{
  "type": "Feature",
  "properties": {
    "iso:country":"IT",
    "sg:address":"2, Piazza Duse Eleonora 20122 Milano",
    "sg:city":"Milano",
    "sg:classifiers":[
        {
            "category":"Communications",
            "subcategory":"Newspaper",
            "type":"Services"
        }
    ],
    "sg:phone":"+39 390 277 321",
    "sg:postcode":"20122",
    "sg:province":"Milano",
    "sg:tags":[
        "advertising"
    ],
    "wof:name":"Young & Rubicam Italia S.p.a.",
    "wof:placetype":"venue"
},
  "geometry": {"coordinates":[9.204206,45.471302],"type":"Point"}
}