{
  "type": "Feature",
  "properties": {
    "iso:country":"IT",
    "sg:address":"46020 Pegognaga",
    "sg:city":"Pegognaga",
    "sg:orig_category":"Assicurazioni",
    "sg:phone":"+39 0376 558241",
    "sg:postcode":"46020",
    "sg:province":"Mantova",
    "wof:name":"Veneri Barbara",
    "wof:placetype":"venue"
},
  "geometry": {"coordinates":[10.860796,44.993778],"type":"Point"}
}