{
  "type": "Feature",
  "properties": {
    "iso:country":"IT",
    "sg:address":"87010 Saracena",
    "sg:city":"Saracena",
    "sg:orig_category":"Calzature, Pelletterie E Pelli",
    "sg:phone":"+39 0981 34396",
    "sg:postcode":"87010",
    "sg:province":"Cosenza",
    "wof:name":"Centro Moda Pelle Di Cerbini S.",
    "wof:placetype":"venue"
},
  "geometry": {"coordinates":[16.157499,39.77985],"type":"Point"}
}