{
  "type": "Feature",
  "properties": {
    "iso:country":"IT",
    "sg:address":"Via Bottenigo 50 30175 Marghera",
    "sg:city":"Marghera",
    "sg:classifiers":[
        {
            "category":"Wholesale",
            "subcategory":"Vending Machines",
            "type":"Manufacturing & Wholesale Goods"
        }
    ],
    "sg:phone":"+39 041 922061",
    "sg:postcode":"30175",
    "sg:province":"Venezia",
    "sg:tags":[
        "carpentry"
    ],
    "wof:name":"Carraro Amedeo",
    "wof:placetype":"venue"
},
  "geometry": {"coordinates":[12.201219,45.475182],"type":"Point"}
}