{
  "type": "Feature",
  "properties": {
    "iso:country":"IT",
    "sg:address":"46027 San Benedetto Po",
    "sg:city":"San Benedetto Po",
    "sg:orig_category":"Elettrotecnica Industriale, Prodotti E Apparecchiature",
    "sg:phone":"+39 0376 615540",
    "sg:postcode":"46027",
    "sg:province":"Mantova",
    "wof:name":"Idro Po Snc",
    "wof:placetype":"venue"
},
  "geometry": {"coordinates":[10.933806,45.05127],"type":"Point"}
}