{
  "type": "Feature",
  "properties": {
    "iso:country":"IT",
    "sg:address":"19, Via Per Castelletto 20080 Albairate",
    "sg:city":"Albairate",
    "sg:classifiers":[
        {
            "category":"Manufacturing",
            "subcategory":"Rubber & Plastics",
            "type":"Manufacturing & Wholesale Goods"
        }
    ],
    "sg:phone":"+39 02 9406 1039",
    "sg:postcode":"20080",
    "sg:province":"Milano",
    "wof:name":"Domoplast S.r.l.",
    "wof:placetype":"venue"
},
  "geometry": {"coordinates":[8.9292478561,45.4147758484],"type":"Point"}
}