{
  "type": "Feature",
  "properties": {
    "addr:full":"32100 Belluno Belluno Belluno 32100",
    "addr:postcode":"32100;32100",
    "iso:country":"IT",
    "sg:address":"32100 Belluno",
    "sg:city":"Belluno",
    "sg:orig_category":"Lavorazioni Metalli, Stampaggio E Saldatura",
    "sg:phone":"+39 0437 9191",
    "sg:postcode":"32100",
    "sg:province":"Belluno",
    "sg:website":"http://www.silko.it",
    "wof:name":"Silko",
    "wof:placetype":"venue"
},
  "geometry": {"coordinates":[12.105525,46.110729],"type":"Point"}
}