{
  "type": "Feature",
  "properties": {
    "addr:full":"36015 Schio Schio Vicenza 36015",
    "addr:postcode":"36015;36015",
    "iso:country":"IT",
    "sg:address":"36015 Schio",
    "sg:city":"Schio",
    "sg:orig_category":"Cucine Per Comunita'",
    "sg:phone":"+39 0445 575232",
    "sg:postcode":"36015",
    "sg:province":"Vicenza",
    "wof:name":"Dbv Srl",
    "wof:placetype":"venue"
},
  "geometry": {"coordinates":[11.397454,45.72126],"type":"Point"}
}