{
  "type": "Feature",
  "properties": {
    "iso:country":"IT",
    "sg:address":"56/m, Viale Finali Gaspare 47023 Cesena",
    "sg:city":"Cesena",
    "sg:classifiers":[
        {
            "category":"Banks & Credit Unions",
            "subcategory":"Bank",
            "type":"Services"
        }
    ],
    "sg:phone":"+39 0547 613867",
    "sg:postcode":"47023",
    "sg:province":"Forl\u00ec-Cesena",
    "sg:tags":[
        "banking",
        "institution"
    ],
    "wof:name":"Banca Di Cesena Credito Cooperativo Di Cesena E Ronta Scrl",
    "wof:placetype":"venue"
},
  "geometry": {"coordinates":[11.980461,43.994766],"type":"Point"}
}