{
  "type": "Feature",
  "properties": {
    "iso:country":"IT",
    "sg:address":"9, Piazza S. Francesco 31100 Treviso",
    "sg:city":"Treviso",
    "sg:classifiers":[
        {
            "category":"Retail",
            "subcategory":"Animal Services",
            "type":"Services"
        }
    ],
    "sg:phone":"+39 0422 542837",
    "sg:postcode":"31100",
    "sg:province":"Treviso",
    "sg:tags":[
        "breeding"
    ],
    "wof:name":"Acquario Di Treviso",
    "wof:placetype":"venue"
},
  "geometry": {"coordinates":[12.219421,45.673531],"type":"Point"}
}