{
  "type": "Feature",
  "properties": {
    "iso:country":"IT",
    "sg:address":"25030 Coccaglio",
    "sg:city":"Coccaglio",
    "sg:orig_category":"Accessori Moda D'abbigliamento",
    "sg:phone":"+39 030 770 2570",
    "sg:postcode":"25030",
    "sg:province":"Brescia",
    "wof:name":"Vezzoli Fausto",
    "wof:placetype":"venue"
},
  "geometry": {"coordinates":[9.974807,45.55825],"type":"Point"}
}