{
  "type": "Feature",
  "properties": {
    "iso:country":"IT",
    "sg:address":"Via Delle Moie 56 25050 Rodengo Saiano",
    "sg:classifiers":[
        {
            "category":"Restaurant",
            "type":"Food & Drink"
        }
    ],
    "sg:phone":"+39 030 611858",
    "sg:postcode":"25050",
    "sg:province":"Brescia",
    "sg:tags":[
        "pasta"
    ],
    "wof:name":"Il Pastaio Srl",
    "wof:placetype":"venue"
},
  "geometry": {"coordinates":[10.1238660812,45.5779457092],"type":"Point"}
}