{
  "type": "Feature",
  "properties": {
    "addr:full":"19/c, Via Padova 31041 Cornuda Cornuda Treviso 31041",
    "addr:housenumber":"19 / c",
    "addr:postcode":"31041;31041",
    "addr:street":"Via Padova",
    "iso:country":"IT",
    "sg:address":"19/c, Via Padova 31041 Cornuda",
    "sg:city":"Cornuda",
    "sg:classifiers":[
        {
            "category":"Shopping",
            "subcategory":"Crafts & Fabrics",
            "type":"Retail Goods"
        }
    ],
    "sg:phone":"+39 0423 639109",
    "sg:postcode":"31041",
    "sg:province":"Treviso",
    "wof:name":"Siretessile (s.r.l.)",
    "wof:placetype":"venue"
},
  "geometry": {"coordinates":[12.2420721054,45.6662864685],"type":"Point"}
}