{
  "type": "Feature",
  "properties": {
    "iso:country":"IT",
    "sg:address":"09127 Cagliari",
    "sg:city":"Cagliari",
    "sg:orig_category":"Macchine E Forniture Per Industria Orafa E Per Orologeria",
    "sg:phone":"+39 070 654828",
    "sg:postcode":"09127",
    "sg:province":"Cagliari",
    "wof:name":"Saputo Salvatore",
    "wof:placetype":"venue"
},
  "geometry": {"coordinates":[9.122096,39.215393],"type":"Point"}
}