{
  "type": "Feature",
  "properties": {
    "addr:full":"168, Viale Leonardo Da Vinci 20090 Trezzano Sul Naviglio Trezzano sul Naviglio Milano 20090",
    "addr:postcode":"20090;20090",
    "addr:street":"Viale Leonardo Da Vinci",
    "iso:country":"IT",
    "sg:address":"168, Viale Leonardo Da Vinci 20090 Trezzano Sul Naviglio",
    "sg:city":"Trezzano sul Naviglio",
    "sg:orig_category":"Miscellaneous Products",
    "sg:phone":"+39 39024454057",
    "sg:postcode":"20090",
    "sg:province":"Milano",
    "wof:name":"San - O - Sub Italia S.r.l.",
    "wof:placetype":"venue"
},
  "geometry": {"coordinates":[9.056391716,45.4204368591],"type":"Point"}
}