{
  "type": "Feature",
  "properties": {
    "iso:country":"IT",
    "sg:address":"Via R. Colpi, 2/4/6 35010 Limena",
    "sg:city":"Limena",
    "sg:classifiers":[
        {
            "category":"Home & Garden",
            "subcategory":"Hardware",
            "type":"Retail Goods"
        }
    ],
    "sg:phone":"+39 049 769860",
    "sg:postcode":"35010",
    "sg:province":"Padova",
    "sg:tags":[
        "small",
        "ironware",
        "item"
    ],
    "sg:website":"www.viemme.net",
    "wof:name":"Viemme Srl",
    "wof:placetype":"venue"
},
  "geometry": {"coordinates":[11.85697,45.460537],"type":"Point"}
}