{
  "type": "Feature",
  "properties": {
    "iso:country":"IT",
    "sg:address":"15, Via C.battisti 22075 Lurate Caccivio",
    "sg:city":"Lurate Caccivio",
    "sg:classifiers":[
        {
            "category":"Shopping",
            "subcategory":"Crafts & Fabrics",
            "type":"Retail Goods"
        }
    ],
    "sg:phone":"+39 39031492944",
    "sg:postcode":"22075",
    "sg:province":"Como",
    "wof:name":"Macritex (s.p.a.)",
    "wof:placetype":"venue"
},
  "geometry": {"coordinates":[9.0025854111,45.7642402649],"type":"Point"}
}