{
  "type": "Feature",
  "properties": {
    "addr:full":"20031 Cesano Maderno Cesano Maderno Milano 20031",
    "addr:postcode":"20031;20031",
    "iso:country":"IT",
    "sg:address":"20031 Cesano Maderno",
    "sg:city":"Cesano Maderno",
    "sg:classifiers":[
        {
            "category":"Home & Garden",
            "subcategory":"Home Furnishings",
            "type":"Retail Goods"
        }
    ],
    "sg:phone":"+39 036 257 5020",
    "sg:postcode":"20031",
    "sg:province":"Milano",
    "sg:tags":[
        "varnish",
        "enamel",
        "paints",
        "industry",
        "wood",
        "machinery",
        "supplies"
    ],
    "wof:name":"Color Design Di Paolo Toppan",
    "wof:placetype":"venue"
},
  "geometry": {"coordinates":[9.1833992004,45.6399002075],"type":"Point"}
}