{
  "type": "Feature",
  "properties": {
    "iso:country":"IT",
    "sg:address":"25, Via Crocera Di Corva 33082 Azzano Decimo",
    "sg:city":"Azzano Decimo",
    "sg:classifiers":[
        {
            "category":"Home & Garden",
            "subcategory":"Home Furnishings",
            "type":"Retail Goods"
        }
    ],
    "sg:phone":"+39 0434 640733",
    "sg:postcode":"33082",
    "sg:province":"Pordenone",
    "sg:tags":[
        "household"
    ],
    "wof:name":"Horm Srl",
    "wof:placetype":"venue"
},
  "geometry": {"coordinates":[12.655044,45.96265],"type":"Point"}
}