{
  "type": "Feature",
  "properties": {
    "addr:full":"20144 Milano Milano Milano 20144",
    "addr:postcode":"20144;20144",
    "iso:country":"IT",
    "sg:address":"20144 Milano",
    "sg:city":"Milano",
    "sg:orig_category":"Servizi Per Lo Sport E Il Tempo Libero. Servizi Ausiliari Dei Mezzi Di Trasporto",
    "sg:phone":"+39 02 4771 9928",
    "sg:postcode":"20144",
    "sg:province":"Milano",
    "wof:name":"Blu Progetto Mare Srl",
    "wof:placetype":"venue"
},
  "geometry": {"coordinates":[9.157878,45.45689],"type":"Point"}
}