{
  "type": "Feature",
  "properties": {
    "iso:country":"IT",
    "sg:address":"C.so Novara 210 27029 Vigevano",
    "sg:city":"Vigevano",
    "sg:classifiers":[
        {
            "category":"Shopping",
            "subcategory":"Stationery & Office Supplies",
            "type":"Retail Goods"
        }
    ],
    "sg:phone":"+39 0381 329846",
    "sg:postcode":"27029",
    "sg:province":"Pavia",
    "sg:tags":[
        "packing",
        "cardboard",
        "cushioning",
        "purpose"
    ],
    "sg:website":"www.icsfirpo.it",
    "wof:name":"I.c.s. Firpo Spa",
    "wof:placetype":"venue"
},
  "geometry": {"coordinates":[9.156563,45.185886],"type":"Point"}
}