{
  "type": "Feature",
  "properties": {
    "addr:full":"Via Aquileia 43/a 20092 Cinisello Balsamo Cinisello Balsamo Milano 20092",
    "addr:housenumber":"43 / a",
    "addr:postcode":"20092;20092",
    "addr:street":"Via Aquileia",
    "iso:country":"IT",
    "sg:address":"Via Aquileia 43/a 20092 Cinisello Balsamo",
    "sg:city":"Cinisello Balsamo",
    "sg:classifiers":[
        {
            "category":"Utilities",
            "subcategory":"Mobile Phone",
            "type":"Services"
        }
    ],
    "sg:phone":"+39 02 6601 2372",
    "sg:postcode":"20092",
    "sg:province":"Milano",
    "sg:tags":[
        "speaker"
    ],
    "wof:name":"G.m.e. Srl",
    "wof:placetype":"venue"
},
  "geometry": {"coordinates":[9.207877,45.549648],"type":"Point"}
}