{
  "type": "Feature",
  "properties": {
    "iso:country":"IT",
    "sg:address":"69, Via Sturzo Don Luigi 22066 Mariano Comense",
    "sg:city":"Mariano Comense",
    "sg:classifiers":[
        {
            "category":"Shopping",
            "subcategory":"Crafts & Fabrics",
            "type":"Retail Goods"
        }
    ],
    "sg:phone":"+39 39031744966",
    "sg:postcode":"22066",
    "sg:province":"Como",
    "wof:name":"Tessitura Mauri (s.a.s.)",
    "wof:placetype":"venue"
},
  "geometry": {"coordinates":[9.0854558945,45.8119659424],"type":"Point"}
}