{
  "type": "Feature",
  "properties": {
    "iso:country":"IT",
    "sg:address":"97, V. Cesare Battisti 21040 Venegono Superiore",
    "sg:city":"Venegono Superiore",
    "sg:classifiers":[
        {
            "category":"Wholesale",
            "subcategory":"Medical Equipment & Supplies",
            "type":"Manufacturing & Wholesale Goods"
        }
    ],
    "sg:phone":"+39 0331 865304",
    "sg:postcode":"21040",
    "sg:province":"Varese",
    "sg:tags":[
        "-",
        "health",
        "instrument"
    ],
    "sg:website":"http://www.nomec92.com",
    "wof:name":"Nomec 92 Srl",
    "wof:placetype":"venue"
},
  "geometry": {"coordinates":[8.892426,45.752728],"type":"Point"}
}