{
  "type": "Feature",
  "properties": {
    "iso:country":"IT",
    "sg:address":"Via Zucchi 16; Monza; 20052",
    "sg:city":"Monza",
    "sg:classifiers":[
        {
            "category":"Banks & Credit Unions",
            "subcategory":"Bank",
            "type":"Services"
        }
    ],
    "sg:phone":"+39 039 23811",
    "sg:postcode":"20052",
    "sg:province":"Milano",
    "wof:name":"Credito Artigiano Spa",
    "wof:placetype":"venue"
},
  "geometry": {"coordinates":[9.273923,45.585873],"type":"Point"}
}