{
  "type": "Feature",
  "properties": {
    "addr:full":"Via Leonardo Da Vinci 24 20089 Rozzano Rozzano Milano 20089",
    "addr:housenumber":"24",
    "addr:postcode":"20089;20089",
    "addr:street":"Via Leonardo Da Vinci",
    "iso:country":"IT",
    "sg:address":"Via Leonardo Da Vinci 24 20089 Rozzano",
    "sg:city":"Rozzano",
    "sg:classifiers":[
        {
            "category":"Social Services",
            "subcategory":"Retirement Home",
            "type":"Services"
        }
    ],
    "sg:phone":"+39 02 5750 2104",
    "sg:postcode":"20089",
    "sg:province":"Milano",
    "sg:tags":[
        "closure",
        "safety"
    ],
    "wof:name":"Ziplast Srl",
    "wof:placetype":"venue"
},
  "geometry": {"coordinates":[9.16897,45.381317],"type":"Point"}
}