{
  "type": "Feature",
  "properties": {
    "iso:country":"IT",
    "sg:address":"13, V. Gorizia 22070 Luisago",
    "sg:city":"Luisago",
    "sg:classifiers":[
        {
            "category":"Shopping",
            "subcategory":"Crafts & Fabrics",
            "type":"Retail Goods"
        }
    ],
    "sg:phone":"+39 031 882 0111",
    "sg:postcode":"22070",
    "sg:province":"Como",
    "sg:website":"http://www.seride.it",
    "wof:name":"Seride Srl",
    "wof:placetype":"venue"
},
  "geometry": {"coordinates":[9.054643631,45.7584915161],"type":"Point"}
}