{
  "type": "Feature",
  "properties": {
    "addr:full":"20097 San Donato Milanese San Donato Milanese Milano 20097",
    "addr:housenumber":"20097",
    "addr:postcode":"20097",
    "addr:street":"San",
    "iso:country":"IT",
    "sg:address":"20097 San Donato Milanese",
    "sg:city":"San Donato Milanese",
    "sg:classifiers":[
        {
            "category":"Health Services",
            "subcategory":"Health Practitioner",
            "type":"Services"
        }
    ],
    "sg:phone":"+39 02 5560 6068",
    "sg:postcode":"20097",
    "sg:province":"Milano",
    "sg:tags":[
        "medici"
    ],
    "wof:name":"Pediglieri Maria Antonella",
    "wof:placetype":"venue"
},
  "geometry": {"coordinates":[9.2640991211,45.4090995789],"type":"Point"}
}