{
  "type": "Feature",
  "properties": {
    "iso:country":"IT",
    "sg:address":"00193 Roma",
    "sg:city":"Roma",
    "sg:orig_category":"Dolciumi E Gelati",
    "sg:phone":"+39 06 321 5405",
    "sg:postcode":"00193",
    "sg:province":"Roma",
    "wof:name":"Forno Pasticceria A. Colapicchioni",
    "wof:placetype":"venue"
},
  "geometry": {"coordinates":[12.46779,41.906452],"type":"Point"}
}