{
  "type": "Feature",
  "properties": {
    "iso:country":"IT",
    "sg:address":"20121 Milano",
    "sg:city":"Milano",
    "sg:orig_category":"Ospedali E Servizi Sanitari. Servizi Sociali",
    "sg:phone":"+39 02 861145",
    "sg:postcode":"20121",
    "sg:province":"Milano",
    "wof:name":"Consultorio Centro Problemi Donna",
    "wof:placetype":"venue"
},
  "geometry": {"coordinates":[9.189299,45.465508],"type":"Point"}
}