{
  "type": "Feature",
  "properties": {
    "addr:full":"38033 Cavalese Cavalese Trento 38033",
    "addr:postcode":"38033;38033",
    "iso:country":"IT",
    "sg:address":"38033 Cavalese",
    "sg:city":"Cavalese",
    "sg:classifiers":[
        {
            "category":"Sports & Exercise",
            "subcategory":"Tennis Court",
            "type":"Entertainment"
        }
    ],
    "sg:phone":"+39 0462 342423",
    "sg:postcode":"38033",
    "sg:province":"Trento",
    "sg:tags":[
        "e",
        "lo",
        "tempo",
        "libero",
        "per",
        "impianti",
        "il",
        "attrezzature"
    ],
    "wof:name":"Vinante Riccardo",
    "wof:placetype":"venue"
},
  "geometry": {"coordinates":[11.460531,46.290176],"type":"Point"}
}