{
  "type": "Feature",
  "properties": {
    "addr:full":"31025 Santa Lucia Di Piave Santa Lucia di Piave Treviso 31025",
    "addr:postcode":"31025;31025",
    "iso:country":"IT",
    "sg:address":"31025 Santa Lucia Di Piave",
    "sg:city":"Santa Lucia di Piave",
    "sg:orig_category":"Articoli Sportivi - Vendita Al Dettaglio",
    "sg:phone":"+39 0438 701880",
    "sg:postcode":"31025",
    "sg:province":"Treviso",
    "sg:website":"http://www.gammasportsas.com",
    "wof:name":"Gammasport Snc Di Zanardo Denis & C.",
    "wof:placetype":"venue"
},
  "geometry": {"coordinates":[12.288573,45.838375],"type":"Point"}
}