{
  "type": "Feature",
  "properties": {
    "iso:country":"IT",
    "sg:address":"20059 Vimercate",
    "sg:city":"Vimercate",
    "sg:classifiers":[
        {
            "category":"Manufacturing",
            "subcategory":"Motor Vehicles & Parts",
            "type":"Manufacturing & Wholesale Goods"
        }
    ],
    "sg:phone":"+39 039 667609",
    "sg:postcode":"20059",
    "sg:province":"Milano",
    "sg:tags":[
        "valve",
        "vehicles",
        "component",
        "equipment",
        "spare",
        "measurement"
    ],
    "sg:website":"http://www.c-effe.it",
    "wof:name":"C.effe International Srl",
    "wof:placetype":"venue"
},
  "geometry": {"coordinates":[9.368833,45.619343],"type":"Point"}
}