{
  "type": "Feature",
  "properties": {
    "addr:full":"59013 Montemurlo Montemurlo Prato 59013",
    "addr:postcode":"59013;59013",
    "iso:country":"IT",
    "sg:address":"59013 Montemurlo",
    "sg:city":"Montemurlo",
    "sg:orig_category":"Forniture Per Abbigliamento E Pelletterie",
    "sg:phone":"+39 0574 652412",
    "sg:postcode":"59013",
    "sg:province":"Prato",
    "wof:name":"Ganugi Guarducci & C. Snc",
    "wof:placetype":"venue"
},
  "geometry": {"coordinates":[11.0582523346,43.9118919373],"type":"Point"}
}