{
  "type": "Feature",
  "properties": {
    "iso:country":"IT",
    "sg:address":"87, Fr. Tre Rivi 12040 Monteu Roero",
    "sg:city":"Monteu Roero",
    "sg:classifiers":[
        {
            "category":"Food & Beverages",
            "subcategory":"Groceries & Convenience Stores",
            "type":"Retail Goods"
        }
    ],
    "sg:phone":"+39 39017390109",
    "sg:postcode":"12040",
    "sg:province":"Cuneo",
    "sg:tags":[
        "product",
        "related"
    ],
    "sg:website":"http://www.brezzo.it",
    "wof:name":"Brezzo",
    "wof:placetype":"venue"
},
  "geometry": {"coordinates":[7.9118847847,44.7610855103],"type":"Point"}
}