{
  "type": "Feature",
  "properties": {
    "iso:country":"IT",
    "sg:address":"Largo R Mattioli 1, 20121 Milan, Mi",
    "sg:classifiers":[
        {
            "category":"Banks & Credit Unions",
            "subcategory":"Bank",
            "type":"Services"
        }
    ],
    "sg:phone":"+39 0288501",
    "sg:postcode":"20121",
    "sg:province":"Milano",
    "wof:name":"Comit Service Srl",
    "wof:placetype":"venue"
},
  "geometry": {"coordinates":[9.191271,45.466953],"type":"Point"}
}