{
  "type": "Feature",
  "properties": {
    "addr:full":"180, Via Nazionale 55100 Lucca Lucca Lucca 55100",
    "addr:housenumber":"180",
    "addr:postcode":"55100;55100",
    "addr:street":"Via Nazionale",
    "iso:country":"IT",
    "sg:address":"180, Via Nazionale 55100 Lucca",
    "sg:city":"Lucca",
    "sg:classifiers":[
        {
            "category":"Manufacturing",
            "subcategory":"Rubber & Plastics",
            "type":"Manufacturing & Wholesale Goods"
        }
    ],
    "sg:phone":"+39 0583 579460",
    "sg:postcode":"55100",
    "sg:province":"Lucca",
    "wof:name":"Alfa Plast",
    "wof:placetype":"venue"
},
  "geometry": {"coordinates":[10.5336294174,43.905456543],"type":"Point"}
}