{
  "type": "Feature",
  "properties": {
    "iso:country":"IT",
    "sg:address":"27, Via Savonarola 44100 Ferrara",
    "sg:city":"Ferrara",
    "sg:classifiers":[
        {
            "category":"Shopping",
            "type":"Retail Goods"
        }
    ],
    "sg:phone":"+39 0532 207000",
    "sg:postcode":"44100",
    "sg:province":"Ferrara",
    "sg:tags":[
        "finished",
        "-",
        "metallic"
    ],
    "wof:name":"Saimi Spettoli Srl",
    "wof:placetype":"venue"
},
  "geometry": {"coordinates":[11.6280326843,44.8323326111],"type":"Point"}
}