{
  "type": "Feature",
  "properties": {
    "addr:full":"50018 Scandicci Scandicci Firenze 50018",
    "addr:postcode":"50018;50018",
    "iso:country":"IT",
    "sg:address":"50018 Scandicci",
    "sg:city":"Scandicci",
    "sg:orig_category":"Materiali Edili",
    "sg:phone":"+39 055 250176",
    "sg:postcode":"50018",
    "sg:province":"Firenze",
    "wof:name":"Fornaci Di S. Giusto (s.p.a.)",
    "wof:placetype":"venue"
},
  "geometry": {"coordinates":[11.193339,43.761909],"type":"Point"}
}