{
  "type": "Feature",
  "properties": {
    "iso:country":"IT",
    "sg:address":"31030 Dosson Di Casier",
    "sg:city":"Casier",
    "sg:orig_category":"Fotocomposizione",
    "sg:phone":"+39 0422 383303",
    "sg:postcode":"31030",
    "sg:province":"Treviso",
    "wof:name":"Trevicolor Srl",
    "wof:placetype":"venue"
},
  "geometry": {"coordinates":[12.2631616592,45.6339797974],"type":"Point"}
}