{
  "type": "Feature",
  "properties": {
    "iso:country":"IT",
    "sg:address":"24024 Cazzano Sant'andrea",
    "sg:orig_category":"Prodotti E Manufatti In Materie Plastiche",
    "sg:phone":"+39 035 741380",
    "sg:postcode":"24024",
    "sg:province":"Bergamo",
    "wof:name":"Martinelli Plast Di Martinelli Bruno & C. (s.n.c.)",
    "wof:placetype":"venue"
},
  "geometry": {"coordinates":[9.6465854645,45.6911354065],"type":"Point"}
}