{
  "type": "Feature",
  "properties": {
    "iso:country":"IT",
    "sg:address":"16158 Genova",
    "sg:city":"Genova",
    "sg:orig_category":"Alberghi E Strutture Extra Alberghiere. Ospedali E Servizi Sanitari",
    "sg:phone":"+39 010 613 6342",
    "sg:postcode":"16158",
    "sg:province":"Genova",
    "wof:name":"Casa Marina =s. Giuseppe= Piccole Figlie Del S. Cuore",
    "wof:placetype":"venue"
},
  "geometry": {"coordinates":[8.731628,44.421543],"type":"Point"}
}