{
  "type": "Feature",
  "properties": {
    "iso:country":"IT",
    "sg:address":"1/c, Via Petronio 34015 Muggia",
    "sg:city":"Muggia",
    "sg:classifiers":[
        {
            "category":"Shopping",
            "subcategory":"Computers & Home Electronics",
            "type":"Retail Goods"
        }
    ],
    "sg:phone":"+39 39040232653",
    "sg:postcode":"34015",
    "sg:province":"Trieste",
    "sg:tags":[
        "electronic",
        "electrical",
        "equipment"
    ],
    "wof:name":"Volpi Tecno Energia S.a.s.",
    "wof:placetype":"venue"
},
  "geometry": {"coordinates":[13.803159,45.592075],"type":"Point"}
}