{
  "type": "Feature",
  "properties": {
    "iso:country":"IT",
    "sg:address":"Via Molinetto 46 31054 Possagno",
    "sg:city":"Possagno",
    "sg:classifiers":[
        {
            "category":"Structure",
            "subcategory":"Historic Building",
            "type":"Public Place"
        }
    ],
    "sg:phone":"+39 0423 9205",
    "sg:postcode":"31054",
    "sg:province":"Treviso",
    "sg:tags":[
        "ceramic",
        "purpose"
    ],
    "sg:website":"www.cottopossagno.com",
    "wof:name":"Industrie Cotto Possagno S.p.a.",
    "wof:placetype":"venue"
},
  "geometry": {"coordinates":[11.833706,45.824512],"type":"Point"}
}