{
  "type": "Feature",
  "properties": {
    "iso:country":"IT",
    "sg:address":"85050 Marsicovetere",
    "sg:city":"Marsicovetere",
    "sg:orig_category":"Cine-foto-ottica",
    "sg:phone":"+39 0975 354234",
    "sg:postcode":"85050",
    "sg:province":"Potenza",
    "wof:name":"Gi.elle Video",
    "wof:placetype":"venue"
},
  "geometry": {"coordinates":[15.824876,40.357105],"type":"Point"}
}