{
  "type": "Feature",
  "properties": {
    "iso:country":"IT",
    "sg:address":"10010 Scarmagno",
    "sg:city":"Scarmagno",
    "sg:orig_category":"Elettrotecnica Industriale, Prodotti E Apparecchiature",
    "sg:phone":"+39 0125 637938",
    "sg:postcode":"10010",
    "sg:province":"Torino",
    "sg:website":"http://www.paginegialle.it/ghiggia-02",
    "wof:name":"Servizi Impianti Ghiggia Srl",
    "wof:placetype":"venue"
},
  "geometry": {"coordinates":[7.838505,45.367512],"type":"Point"}
}