{
  "type": "Feature",
  "properties": {
    "iso:country":"IT",
    "sg:address":"Via Pievano Rolando; Empoli; 50053",
    "sg:city":"Empoli",
    "sg:classifiers":[
        {
            "category":"Banks & Credit Unions",
            "subcategory":"Bank",
            "type":"Services"
        }
    ],
    "sg:phone":"+39 0571 74053",
    "sg:postcode":"50053",
    "sg:province":"Firenze",
    "wof:name":"Credito Italiano Spa",
    "wof:placetype":"venue"
},
  "geometry": {"coordinates":[10.948216,43.722095],"type":"Point"}
}