{
  "type": "Feature",
  "properties": {
    "iso:country":"IT",
    "sg:address":"C/o Banca Cassa Di Risparmio Di Tortona Spa, Piazza Duomo 13, 15057 Tortona, Al",
    "sg:city":"Tortona",
    "sg:classifiers":[
        {
            "category":"Banks & Credit Unions",
            "subcategory":"Bank",
            "type":"Services"
        }
    ],
    "sg:phone":"+39 0131 815781",
    "sg:postcode":"15057",
    "sg:province":"Alessandria",
    "wof:name":"Fondazione Cassa Di Risparmio Di Tortona",
    "wof:placetype":"venue"
},
  "geometry": {"coordinates":[8.616951,44.913216],"type":"Point"}
}