{
  "type": "Feature",
  "properties": {
    "iso:country":"IT",
    "sg:address":"14, Riva Cadamosto Alvise 34147 Trieste",
    "sg:city":"Trieste",
    "sg:classifiers":[
        {
            "category":"Autos & Motor Vehicles",
            "subcategory":"Boat Sales",
            "type":"Retail Goods"
        }
    ],
    "sg:phone":"+39 39040829206",
    "sg:postcode":"34147",
    "sg:province":"Trieste",
    "wof:name":"Fabbrica Tubi Mobilio - F.t.m. (s.p.a.)",
    "wof:placetype":"venue"
},
  "geometry": {"coordinates":[13.778407,45.653629],"type":"Point"}
}