{
  "type": "Feature",
  "properties": {
    "iso:country":"IT",
    "sg:address":"23861 Cesana Brianza",
    "sg:city":"Cesana Brianza",
    "sg:orig_category":"Macchine, Impianti Ed Attrezzature Industria Chimica. Attrezzature E Forniture Per Officine Riparazione E Servizi Ausiliari",
    "sg:phone":"+39 031 655727",
    "sg:postcode":"23861",
    "sg:province":"Lecco",
    "sg:website":"http://www.orbita.it",
    "wof:name":"Orbita Srl",
    "wof:placetype":"venue"
},
  "geometry": {"coordinates":[9.326819,45.808475],"type":"Point"}
}