{
  "type": "Feature",
  "properties": {
    "addr:full":"9, V. Aterno 66020 S. Giovanni Teatino Chieti 66020",
    "addr:housenumber":"9",
    "addr:postcode":"66020;66020",
    "addr:street":"V. Aterno",
    "iso:country":"IT",
    "sg:address":"9, V. Aterno 66020 S. Giovanni Teatino",
    "sg:classifiers":[
        {
            "category":"Shopping",
            "subcategory":"Stationery & Office Supplies",
            "type":"Retail Goods"
        }
    ],
    "sg:phone":"+39 085 446 0304",
    "sg:postcode":"66020",
    "sg:province":"Chieti",
    "sg:tags":[
        "professional"
    ],
    "sg:website":"http://www.braden.it",
    "wof:name":"Braden Srl",
    "wof:placetype":"venue"
},
  "geometry": {"coordinates":[14.1619062424,42.4136772156],"type":"Point"}
}