{
  "type": "Feature",
  "properties": {
    "iso:country":"IT",
    "sg:address":"63012 Cupra Marittima",
    "sg:city":"Cupra Marittima",
    "sg:orig_category":"Apparecchiature Ed Attrezzature Meccaniche",
    "sg:phone":"+39 0735 779068",
    "sg:postcode":"63012",
    "sg:province":"Ascoli Piceno",
    "sg:website":"http://www.dsmeccanica.com",
    "wof:name":"Ds Meccanica Di Di Carlo Sergio",
    "wof:placetype":"venue"
},
  "geometry": {"coordinates":[13.8390159607,43.0199165344],"type":"Point"}
}