{
  "type": "Feature",
  "properties": {
    "iso:country":"IT",
    "sg:address":"35020 Roncaglia",
    "sg:city":"Roncaglia",
    "sg:orig_category":"Arredamenti E Mobili Professionali. Impianti, Attrezzature E Forniture Sanitarie Ed Ospedaliere",
    "sg:phone":"+39 049 717212",
    "sg:postcode":"35020",
    "sg:province":"Padova",
    "wof:name":"Giraldin G. E C. (s.n.c.)",
    "wof:placetype":"venue"
},
  "geometry": {"coordinates":[11.923649,45.367565],"type":"Point"}
}