{
  "type": "Feature",
  "properties": {
    "iso:country":"IT",
    "sg:address":"20099 Sesto San Giovanni",
    "sg:city":"Sesto San Giovanni",
    "sg:orig_category":"Forniture Per Abbigliamento E Pelletterie",
    "sg:phone":"+39 02 2247 0563",
    "sg:postcode":"20099",
    "sg:province":"Milano",
    "wof:name":"Merceria Lella",
    "wof:placetype":"venue"
},
  "geometry": {"coordinates":[9.2276086807,45.5360412598],"type":"Point"}
}