{
  "type": "Feature",
  "properties": {
    "iso:country":"IT",
    "sg:address":"50124 Firenze",
    "sg:city":"Firenze",
    "sg:orig_category":"Servizi E Lavori Per Arredamento E Industria Del Legno. Servizi E Lavori Per Edilizia E Lavori Pubblici",
    "sg:phone":"+39 055 277 6209",
    "sg:postcode":"50124",
    "sg:province":"Firenze",
    "wof:name":"Gori Pierangelo",
    "wof:placetype":"venue"
},
  "geometry": {"coordinates":[11.224044,43.756546],"type":"Point"}
}