{
  "type": "Feature",
  "properties": {
    "iso:country":"IT",
    "sg:address":"10057 Sant'ambrogio Di Torino",
    "sg:classifiers":[
        {
            "category":"Parking",
            "subcategory":"Lot",
            "type":"Transportation"
        }
    ],
    "sg:phone":"+39 011 932 3084",
    "sg:postcode":"10057",
    "sg:province":"Torino",
    "sg:tags":[
        "good",
        "shipment",
        "transport"
    ],
    "wof:name":"A.w.s. Service Srl",
    "wof:placetype":"venue"
},
  "geometry": {"coordinates":[7.354903,45.10413],"type":"Point"}
}