{
  "type": "Feature",
  "properties": {
    "iso:country":"IT",
    "sg:address":"Vle Dell' Industrie 62 31030 Dosson",
    "sg:city":"Dosson",
    "sg:orig_category":"Ladies' Trousers Suits, Suits, Jackets, Skirts, And Trousers",
    "sg:phone":"+39 0422 490233",
    "sg:postcode":"31030",
    "sg:province":"Treviso",
    "sg:website":"www.agotex.com",
    "wof:name":"Agotex Carraretto Srl",
    "wof:placetype":"venue"
},
  "geometry": {"coordinates":[12.242072,45.666286],"type":"Point"}
}