{
  "type": "Feature",
  "properties": {
    "iso:country":"IT",
    "sg:address":"07010 Benetutti",
    "sg:city":"Benetutti",
    "sg:orig_category":"Legno E Semilavorati",
    "sg:phone":"+39 079 796493",
    "sg:postcode":"07010",
    "sg:province":"Sassari",
    "wof:name":"Begosin Di Sini Maria & C. S.a.s.",
    "wof:placetype":"venue"
},
  "geometry": {"coordinates":[8.56481,40.724392],"type":"Point"}
}