{
  "type": "Feature",
  "properties": {
    "iso:country":"IT",
    "sg:address":"84030 San Rufo",
    "sg:city":"San Rufo",
    "sg:orig_category":"Agriturismo",
    "sg:phone":"+39 0975 395348",
    "sg:postcode":"84030",
    "sg:province":"Salerno",
    "wof:name":"Erbanito Di Marmo Michele",
    "wof:placetype":"venue"
},
  "geometry": {"coordinates":[15.471817,40.418285],"type":"Point"}
}