{
  "type": "Feature",
  "properties": {
    "iso:country":"IT",
    "sg:address":"56040 Monteverdi Marittimo",
    "sg:city":"Monteverdi Marittimo",
    "sg:orig_category":"Alimentari - Produzione E Ingrosso",
    "sg:phone":"+39 0565 784217",
    "sg:postcode":"56040",
    "sg:province":"Pisa",
    "wof:name":"Specialit\u00c0 Mucci",
    "wof:placetype":"venue"
},
  "geometry": {"coordinates":[10.715639,43.178425],"type":"Point"}
}