{
  "type": "Feature",
  "properties": {
    "addr:full":"Via Antonelli E Tebaldi 62018 Potenza Picena Potenza Picena Macerata 62018",
    "addr:postcode":"62018;62018",
    "addr:street":"Via Antonelli E Tebaldi",
    "iso:country":"IT",
    "sg:address":"Via Antonelli E Tebaldi 62018 Potenza Picena",
    "sg:city":"Potenza Picena",
    "sg:classifiers":[
        {
            "category":"Manufacturing",
            "subcategory":"Rubber & Plastics",
            "type":"Manufacturing & Wholesale Goods"
        }
    ],
    "sg:phone":"+39 0733 880420",
    "sg:postcode":"62018",
    "sg:province":"Macerata",
    "wof:name":"Golden Plast S.p.a.",
    "wof:placetype":"venue"
},
  "geometry": {"coordinates":[13.6913108826,43.36277771],"type":"Point"}
}