{
  "type": "Feature",
  "properties": {
    "addr:full":"46030 Serravalle A Po Libiola Mantova 46030",
    "addr:housenumber":"a",
    "addr:postcode":"46030;46030",
    "addr:street":"Po Libiola",
    "iso:country":"IT",
    "sg:address":"46030 Serravalle A Po",
    "sg:city":"Libiola",
    "sg:orig_category":"Articoli Da Regalo. Arte Ed Artigianato Artistico. Shopping",
    "sg:phone":"+39 0386 40039",
    "sg:postcode":"46030",
    "sg:province":"Mantova",
    "wof:name":"Giunco Casa Di Carantini Alberto",
    "wof:placetype":"venue"
},
  "geometry": {"coordinates":[11.052296,45.06675],"type":"Point"}
}