{
  "type": "Feature",
  "properties": {
    "iso:country":"IT",
    "sg:address":"41100 Modena",
    "sg:city":"Modena",
    "sg:orig_category":"Ospedali E Servizi Sanitari",
    "sg:phone":"+39 059 238177",
    "sg:postcode":"41100",
    "sg:province":"Modena",
    "wof:name":"Iscra Istituto Modenese Di Psicoterapia Sistemica E Relazionale",
    "wof:placetype":"venue"
},
  "geometry": {"coordinates":[10.922978,44.649822],"type":"Point"}
}