{
  "type": "Feature",
  "properties": {
    "addr:full":"20041 Agrate Brianza Agrate Brianza Milano 20041",
    "addr:postcode":"20041;20041",
    "iso:country":"IT",
    "sg:address":"20041 Agrate Brianza",
    "sg:city":"Agrate Brianza",
    "sg:orig_category":"Pompe. Apparecchiature E Sistemi Per Imballaggio E Confezionamento",
    "sg:phone":"+39 039 605 6891",
    "sg:postcode":"20041",
    "sg:province":"Milano",
    "sg:website":"http://www.miltonroy.it",
    "wof:name":"Milton Roy (italia) Srl",
    "wof:placetype":"venue"
},
  "geometry": {"coordinates":[9.3378324509,45.5719985962],"type":"Point"}
}