{
  "type": "Feature",
  "properties": {
    "addr:full":"21040 Sumirago Sumirago Varese 21040",
    "addr:postcode":"21040;21040",
    "iso:country":"IT",
    "sg:address":"21040 Sumirago",
    "sg:city":"Sumirago",
    "sg:orig_category":"Apparecchiature E Sistemi Per Magazzinaggio E Movimentazione. Macchine E Impianti Per Attivita' Commerciali Ed Artigianali. Macchine, Strumenti Ed Apparecchi Per Attivita' Industriali",
    "sg:phone":"+39 0331 270148",
    "sg:postcode":"21040",
    "sg:province":"Varese",
    "sg:website":"http://www.tieffebilance.it",
    "wof:name":"Tieffe Snc",
    "wof:placetype":"venue"
},
  "geometry": {"coordinates":[8.831285,45.782505],"type":"Point"}
}