{
  "type": "Feature",
  "properties": {
    "iso:country":"IT",
    "sg:address":"20095 Cusano Milanino",
    "sg:city":"Cusano Milanino",
    "sg:orig_category":"Macchine Ed Impianti Per Edilizia E Lavori Pubblici. Apparecchiature Ed Attrezzature Meccaniche",
    "sg:phone":"+39 02 6640 1003",
    "sg:postcode":"20095",
    "sg:province":"Milano",
    "sg:website":"http://www.masterautomazione.com",
    "wof:name":"Master Automazione Srl",
    "wof:placetype":"venue"
},
  "geometry": {"coordinates":[9.175249,45.550007],"type":"Point"}
}