{
  "type": "Feature",
  "properties": {
    "addr:full":"64018 Tortoreto Tortoreto Teramo 64018",
    "addr:postcode":"64018;64018",
    "addr:street":"Tortoreto",
    "iso:country":"IT",
    "sg:address":"64018 Tortoreto",
    "sg:city":"Tortoreto",
    "sg:classifiers":[
        {
            "category":"Shopping",
            "subcategory":"Stationery & Office Supplies",
            "type":"Retail Goods"
        }
    ],
    "sg:phone":"+39 0861 7831",
    "sg:postcode":"64018",
    "sg:province":"Teramo",
    "sg:tags":[
        "equipment",
        "furniture",
        "furnishing",
        "professional"
    ],
    "sg:website":"http://www.las.it",
    "wof:name":"Las Mobili Srl",
    "wof:placetype":"venue"
},
  "geometry": {"coordinates":[13.8300762177,42.7067565918],"type":"Point"}
}