{
  "type": "Feature",
  "properties": {
    "iso:country":"IT",
    "sg:address":"13900 Biella",
    "sg:city":"Biella",
    "sg:orig_category":"Filati E Materie Prime Tessili",
    "sg:phone":"+39 015 28082",
    "sg:postcode":"13900",
    "sg:province":"Biella",
    "wof:name":"Paschetto Giorgio",
    "wof:placetype":"venue"
},
  "geometry": {"coordinates":[8.0365047455,45.5785598755],"type":"Point"}
}