{
  "type": "Feature",
  "properties": {
    "addr:full":"1, Via Di Meleto 50022 Greve In Chianti Greve in Chianti Firenze 50022",
    "addr:postcode":"50022;50022",
    "addr:street":"Via Di Meleto",
    "iso:country":"IT",
    "sg:address":"1, Via Di Meleto 50022 Greve In Chianti",
    "sg:city":"Greve in Chianti",
    "sg:classifiers":[
        {
            "category":"Personal",
            "subcategory":"Shoe Repair & Shine",
            "type":"Services"
        }
    ],
    "sg:phone":"+39 39055859241",
    "sg:postcode":"50022",
    "sg:province":"Firenze",
    "sg:tags":[
        "leather"
    ],
    "wof:name":"Celine Production Srl",
    "wof:placetype":"venue"
},
  "geometry": {"coordinates":[11.32204,43.665817],"type":"Point"}
}