{
  "type": "Feature",
  "properties": {
    "addr:full":"Viale Giordana 7/bis 10024 Moncalieri Moncalieri Torino 10024",
    "addr:housenumber":"7 / bis",
    "addr:postcode":"10024;10024",
    "addr:street":"Viale Giordana",
    "iso:country":"IT",
    "sg:address":"Viale Giordana 7/bis 10024 Moncalieri",
    "sg:city":"Moncalieri",
    "sg:orig_category":"Hangar Gates",
    "sg:phone":"+39 011 640 8452",
    "sg:postcode":"10024",
    "sg:province":"Torino",
    "sg:website":"www.luciano.it",
    "wof:name":"Luciano Srl",
    "wof:placetype":"venue"
},
  "geometry": {"coordinates":[7.668704,45.000031],"type":"Point"}
}