{
  "type": "Feature",
  "properties": {
    "iso:country":"IT",
    "sg:address":"50127 Firenze",
    "sg:city":"Firenze",
    "sg:classifiers":[
        {
            "category":"Retail",
            "subcategory":"Auto Repair",
            "type":"Services"
        }
    ],
    "sg:phone":"+39 055 422 2707",
    "sg:postcode":"50127",
    "sg:province":"Firenze",
    "sg:tags":[
        "articles",
        "product",
        "components",
        "industry",
        "vehicles",
        "rubber",
        "part",
        "spare",
        "motor",
        "works"
    ],
    "wof:name":"Motofficina Masini",
    "wof:placetype":"venue"
},
  "geometry": {"coordinates":[11.230584,43.79604],"type":"Point"}
}