{
  "type": "Feature",
  "properties": {
    "iso:country":"IT",
    "sg:address":"Via V. Veneto 30 Rubbiano 43040 Solignano",
    "sg:city":"Solignano",
    "sg:orig_category":"Light Expanded Clay Aggregate, Light Expanded Slate",
    "sg:phone":"+39 0525 4198",
    "sg:postcode":"43040",
    "sg:province":"Parma",
    "sg:website":"www.laterlite.it",
    "wof:name":"Laterlite Spa",
    "wof:placetype":"venue"
},
  "geometry": {"coordinates":[10.329548,44.807865],"type":"Point"}
}