{
  "type": "Feature",
  "properties": {
    "iso:country":"IT",
    "sg:address":"00134 Roma",
    "sg:city":"Roma",
    "sg:orig_category":"Agenzie D'affari E Servizi Commerciali",
    "sg:phone":"+39 06 7135 0641",
    "sg:postcode":"00134",
    "sg:province":"Roma",
    "wof:name":"Pastarito Spa",
    "wof:placetype":"venue"
},
  "geometry": {"coordinates":[12.526059,41.794472],"type":"Point"}
}