{
  "type": "Feature",
  "properties": {
    "addr:full":"Loc Aonedis 10 33038 San Daniele Del Friuli San Daniele del Friuli Udine 33038",
    "addr:housenumber":"10",
    "addr:postcode":"33038;33038",
    "addr:street":"Loc Aonedis",
    "iso:country":"IT",
    "sg:address":"Loc Aonedis 10 33038 San Daniele Del Friuli",
    "sg:city":"San Daniele del Friuli",
    "sg:classifiers":[
        {
            "category":"Recreation",
            "subcategory":"Fishing",
            "type":"Entertainment"
        }
    ],
    "sg:phone":"+39 0432 956560",
    "sg:postcode":"33038",
    "sg:province":"Udine",
    "sg:tags":[
        "fish-breeding"
    ],
    "sg:website":"www.friultrota.it",
    "wof:name":"Friultrota Di Pighin Srl",
    "wof:placetype":"venue"
},
  "geometry": {"coordinates":[13.2307243347,46.0649414062],"type":"Point"}
}