{
  "type": "Feature",
  "properties": {
    "addr:full":"59, Via Pagano Mario 20090 Trezzano Sul Naviglio Trezzano sul Naviglio Milano 20090",
    "addr:postcode":"20090;20090",
    "addr:street":"Via Pagano",
    "iso:country":"IT",
    "sg:address":"59, Via Pagano Mario 20090 Trezzano Sul Naviglio",
    "sg:city":"Trezzano sul Naviglio",
    "sg:orig_category":"Miscellaneous Products",
    "sg:phone":"+39 390 248 4431",
    "sg:postcode":"20090",
    "sg:province":"Milano",
    "wof:name":"Eurovetrocap S.r.l.",
    "wof:placetype":"venue"
},
  "geometry": {"coordinates":[9.0450935364,45.4288864136],"type":"Point"}
}