{
  "type": "Feature",
  "properties": {
    "iso:country":"IT",
    "sg:address":"04011 Aprilia",
    "sg:city":"Aprilia",
    "sg:orig_category":"Servizi Ausiliari Dei Mezzi Di Trasporto",
    "sg:phone":"+39 06 928 0300",
    "sg:postcode":"04011",
    "sg:province":"Latina",
    "wof:name":"Metano Aprilia",
    "wof:placetype":"venue"
},
  "geometry": {"coordinates":[12.670429,41.581421],"type":"Point"}
}