{
  "type": "Feature",
  "properties": {
    "iso:country":"IT",
    "sg:address":"29010 Rottofreno",
    "sg:city":"Rottofreno",
    "sg:orig_category":"Minuterie Metalliche E Ferramenta",
    "sg:phone":"+39 0523 768755",
    "sg:postcode":"29010",
    "sg:province":"Piacenza",
    "sg:website":"http://www.delfanti.it",
    "wof:name":"Delfanti Sandro & C. Snc",
    "wof:placetype":"venue"
},
  "geometry": {"coordinates":[9.6063747406,45.0521888733],"type":"Point"}
}