{
  "type": "Feature",
  "properties": {
    "iso:country":"IT",
    "sg:address":"73055 Racale",
    "sg:city":"Racale",
    "sg:orig_category":"Alimentari - Produzione E Ingrosso",
    "sg:phone":"+39 0833 585852",
    "sg:postcode":"73055",
    "sg:province":"Lecce",
    "wof:name":"Agenzia Italfood Di Nunziato Vitale & C. Sas",
    "wof:placetype":"venue"
},
  "geometry": {"coordinates":[18.022305,39.967709],"type":"Point"}
}