{
  "type": "Feature",
  "properties": {
    "addr:full":"Via Ferraris 26 31044 Montebelluna Montebelluna Treviso 31044",
    "addr:housenumber":"26",
    "addr:postcode":"31044;31044",
    "addr:street":"Via Ferraris",
    "iso:country":"IT",
    "sg:address":"Via Ferraris 26 31044 Montebelluna",
    "sg:city":"Montebelluna",
    "sg:orig_category":"Ladies' Trousers Suits, Suits, Jackets, Skirts, And Trousers",
    "sg:phone":"+39 0423 615616",
    "sg:postcode":"31044",
    "sg:province":"Treviso",
    "sg:website":"www.marikafashion.com",
    "wof:name":"Marika Fashion Di Gino Tonello Sas",
    "wof:placetype":"venue"
},
  "geometry": {"coordinates":[12.076934,45.767269],"type":"Point"}
}