{
  "type": "Feature",
  "properties": {
    "iso:country":"IT",
    "sg:address":"28, V. B. Cellini 15048 Valenza",
    "sg:city":"Valenza",
    "sg:classifiers":[
        {
            "category":"Shopping",
            "subcategory":"Jewelry",
            "type":"Retail Goods"
        }
    ],
    "sg:phone":"+39 0131 951903",
    "sg:postcode":"15048",
    "sg:province":"Alessandria",
    "sg:tags":[
        "jewellery"
    ],
    "sg:website":"http://www.dal-lago.it",
    "wof:name":"Dal Lago Srl",
    "wof:placetype":"venue"
},
  "geometry": {"coordinates":[8.64502,45.008018],"type":"Point"}
}