{
  "type": "Feature",
  "properties": {
    "addr:full":"Via Don Minzoni 10 22100 Como Como Como 22100",
    "addr:housenumber":"10",
    "addr:postcode":"22100;22100",
    "addr:street":"Via Don Minzoni",
    "iso:country":"IT",
    "sg:address":"Via Don Minzoni 10 22100 Como",
    "sg:city":"Como",
    "sg:orig_category":"Plastic Jointings",
    "sg:phone":"+39 031 301992",
    "sg:postcode":"22100",
    "sg:province":"Como",
    "sg:website":"www.solianiemc.com",
    "wof:name":"Soliani Emc Srl",
    "wof:placetype":"venue"
},
  "geometry": {"coordinates":[9.0854558945,45.8119659424],"type":"Point"}
}