{
  "type": "Feature",
  "properties": {
    "addr:full":"20020 Cogliate Cogliate Milano 20020",
    "addr:postcode":"20020;20020",
    "iso:country":"IT",
    "sg:address":"20020 Cogliate",
    "sg:city":"Cogliate",
    "sg:orig_category":"Porte",
    "sg:phone":"+39 02 966 1101",
    "sg:postcode":"20020",
    "sg:province":"Milano",
    "wof:name":"Df Sistemi Snc Di Damiani Vincenzo Antonio E Franco Gianluca",
    "wof:placetype":"venue"
},
  "geometry": {"coordinates":[9.1731100082,45.4691925049],"type":"Point"}
}