{
  "type": "Feature",
  "properties": {
    "addr:full":"34145 Trieste Trieste Trieste 34145",
    "addr:postcode":"34145;34145",
    "iso:country":"IT",
    "sg:address":"34145 Trieste",
    "sg:city":"Trieste",
    "sg:orig_category":"Manufacturers: Prefabbricati",
    "sg:phone":"+39 040 820884",
    "sg:postcode":"34145",
    "sg:province":"Trieste",
    "wof:name":"Razza Giuseppe",
    "wof:placetype":"venue"
},
  "geometry": {"coordinates":[13.784842,45.637939],"type":"Point"}
}