{
  "type": "Feature",
  "properties": {
    "iso:country":"IT",
    "sg:address":"42100 Reggio Emilia",
    "sg:orig_category":"Impianti, Attrezzature E Forniture Sanitarie Ed Ospedaliere",
    "sg:phone":"+39 0522 922521",
    "sg:postcode":"42100",
    "sg:province":"Reggio Nell'Emilia",
    "sg:website":"http://www.bidielle.com",
    "wof:name":"B.d.l. Snc Di Davoli Elio & C.",
    "wof:placetype":"venue"
},
  "geometry": {"coordinates":[10.618048,44.72324],"type":"Point"}
}