{
  "type": "Feature",
  "properties": {
    "addr:full":"395, Corso Alessandria 14100 Asti Asti Asti 14100",
    "addr:postcode":"14100;14100",
    "addr:street":"Corso Alessandria",
    "iso:country":"IT",
    "sg:address":"395, Corso Alessandria 14100 Asti",
    "sg:city":"Asti",
    "sg:classifiers":[
        {
            "category":"Shopping",
            "subcategory":"Computers & Home Electronics",
            "type":"Retail Goods"
        }
    ],
    "sg:phone":"+39 0141 444111",
    "sg:postcode":"14100",
    "sg:province":"Asti",
    "sg:tags":[
        "electronic",
        "electrical",
        "equipment"
    ],
    "wof:name":"Gate S.p.a.",
    "wof:placetype":"venue"
},
  "geometry": {"coordinates":[8.239221,44.905975],"type":"Point"}
}