{
  "type": "Feature",
  "properties": {
    "addr:full":"1/f, Via Setteponti 52029 Castiglion Fibocchi Castiglion Fibocchi Arezzo 52029",
    "addr:housenumber":"1 / f;fibocchi",
    "addr:postcode":"52029;52029",
    "addr:street":"Via Setteponti;Fibocchi",
    "iso:country":"IT",
    "sg:address":"1/f, Via Setteponti 52029 Castiglion Fibocchi",
    "sg:city":"Castiglion Fibocchi",
    "sg:classifiers":[
        {
            "category":"Shopping",
            "subcategory":"Jewelry",
            "type":"Retail Goods"
        }
    ],
    "sg:phone":"+39 0575 477741",
    "sg:postcode":"52029",
    "sg:province":"Arezzo",
    "sg:tags":[
        "jewellery"
    ],
    "wof:name":"Top Catene (s.r.l.)",
    "wof:placetype":"venue"
},
  "geometry": {"coordinates":[11.863062,43.471203],"type":"Point"}
}