{
  "type": "Feature",
  "properties": {
    "addr:full":"10, Via Veneto 25069 Villa Carcina Carcina Brescia 25069",
    "addr:postcode":"25069;carcina;25069",
    "addr:street":"Via Veneto",
    "iso:country":"IT",
    "sg:address":"10, Via Veneto 25069 Villa Carcina",
    "sg:city":"Carcina",
    "sg:classifiers":[
        {
            "category":"Manufacturing",
            "subcategory":"Rubber & Plastics",
            "type":"Manufacturing & Wholesale Goods"
        }
    ],
    "sg:phone":"+39 030 898 0009",
    "sg:postcode":"25069",
    "sg:province":"Brescia",
    "wof:name":"Scib Plastic Srl",
    "wof:placetype":"venue"
},
  "geometry": {"coordinates":[10.2250881195,45.6032066345],"type":"Point"}
}