{
  "type": "Feature",
  "properties": {
    "iso:country":"IT",
    "sg:address":"48100 Ravenna",
    "sg:city":"Ravenna",
    "sg:orig_category":"Cine-foto-ottica",
    "sg:phone":"+39 0544 453178",
    "sg:postcode":"48100",
    "sg:province":"Ravenna",
    "wof:name":"Rier Impianti Di Urbani Maurizio",
    "wof:placetype":"venue"
},
  "geometry": {"coordinates":[12.224458,44.380314],"type":"Point"}
}