{
  "type": "Feature",
  "properties": {
    "iso:country":"IT",
    "sg:address":"37131 Verona",
    "sg:city":"Verona",
    "sg:orig_category":"Macchine, Impianti E Forniture Per Industria Grafica, Cartaria E Cartotecnica",
    "sg:phone":"+39 045 522098",
    "sg:postcode":"37131",
    "sg:province":"Verona",
    "wof:name":"Ferrari Carlo",
    "wof:placetype":"venue"
},
  "geometry": {"coordinates":[11.023024,45.445755],"type":"Point"}
}