{
  "type": "Feature",
  "properties": {
    "addr:full":"20124 Milano Milano Milano 20124",
    "addr:postcode":"20124;20124",
    "iso:country":"IT",
    "sg:address":"20124 Milano",
    "sg:city":"Milano",
    "sg:orig_category":"Scuole E Servizi Scolastici. Ricerca, Selezione E Formazione Del Personale",
    "sg:phone":"+39 02 693361",
    "sg:postcode":"20124",
    "sg:province":"Milano",
    "sg:website":"http://www.interstudioviaggi.it",
    "wof:name":"Inter-studioviaggi Srl",
    "wof:placetype":"venue"
},
  "geometry": {"coordinates":[9.194973,45.491402],"type":"Point"}
}