{
  "type": "Feature",
  "properties": {
    "iso:country":"IT",
    "sg:address":"20133 Milano",
    "sg:city":"Milano",
    "sg:orig_category":"Carni, Salumi E Pesci",
    "sg:phone":"+39 02 236 3903",
    "sg:postcode":"20133",
    "sg:province":"Milano",
    "wof:name":"Necchi Gianfranco",
    "wof:placetype":"venue"
},
  "geometry": {"coordinates":[9.223203,45.478092],"type":"Point"}
}