{
  "type": "Feature",
  "properties": {
    "addr:full":"00179 Roma Roma Roma 00179",
    "addr:postcode":"00179;00179",
    "iso:country":"IT",
    "sg:address":"00179 Roma",
    "sg:city":"Roma",
    "sg:orig_category":"Termotecnica E Riscaldamento, Apparecchiature E Servizi",
    "sg:phone":"+39 06 782 4865",
    "sg:postcode":"00179",
    "sg:province":"Roma",
    "wof:name":"Arpinelli Idrotermica",
    "wof:placetype":"venue"
},
  "geometry": {"coordinates":[12.510616,41.872269],"type":"Point"}
}