{
  "type": "Feature",
  "properties": {
    "addr:full":"2, Via Artigiani 25030 Castelcovati Castelcovati Brescia 25030",
    "addr:postcode":"25030;25030",
    "addr:street":"Via Artigiani",
    "iso:country":"IT",
    "sg:address":"2, Via Artigiani 25030 Castelcovati",
    "sg:city":"Castelcovati",
    "sg:classifiers":[
        {
            "category":"Shopping",
            "subcategory":"Crafts & Fabrics",
            "type":"Retail Goods"
        }
    ],
    "sg:phone":"+39 030 708 0323",
    "sg:postcode":"25030",
    "sg:province":"Brescia",
    "wof:name":"Bulgari Filati (s.p.a.)",
    "wof:placetype":"venue"
},
  "geometry": {"coordinates":[9.9426813126,45.4762077332],"type":"Point"}
}