{
  "type": "Feature",
  "properties": {
    "iso:country":"IT",
    "sg:address":"20090 Cesano Boscone",
    "sg:city":"Cesano Boscone",
    "sg:classifiers":[
        {
            "category":"Health Services",
            "subcategory":"Health Practitioner",
            "type":"Services"
        }
    ],
    "sg:phone":"+39 02 4860 0442",
    "sg:postcode":"20090",
    "sg:province":"Milano",
    "sg:tags":[
        "medici"
    ],
    "wof:name":"Brunelli Gianfranco",
    "wof:placetype":"venue"
},
  "geometry": {"coordinates":[9.09944,45.443054],"type":"Point"}
}