{
  "type": "Feature",
  "properties": {
    "addr:full":"15, Via Piave 25015 Desenzano Del Garda Desenzano del Garda Brescia 25015",
    "addr:postcode":"25015;25015",
    "addr:street":"Via Piave",
    "iso:country":"IT",
    "sg:address":"15, Via Piave 25015 Desenzano Del Garda",
    "sg:city":"Desenzano del Garda",
    "sg:classifiers":[
        {
            "category":"Manufacturing",
            "subcategory":"Motor Vehicles & Parts",
            "type":"Manufacturing & Wholesale Goods"
        }
    ],
    "sg:phone":"+39 030 912 7052",
    "sg:postcode":"25015",
    "sg:province":"Brescia",
    "sg:tags":[
        "engine"
    ],
    "wof:name":"Scalvini Adriana",
    "wof:placetype":"venue"
},
  "geometry": {"coordinates":[10.522633,45.440655],"type":"Point"}
}