{
  "type": "Feature",
  "properties": {
    "iso:country":"IT",
    "sg:address":"22070 Cirimido",
    "sg:city":"Cirimido",
    "sg:orig_category":"Articoli Da Regalo. Arte Ed Artigianato Artistico. Shopping. Regalistica Aziendale",
    "sg:phone":"+39 031 937563",
    "sg:postcode":"22070",
    "sg:province":"Como",
    "sg:website":"http://www.rusconiarredamenti.it",
    "wof:name":"Arredamenti Rusconi Snc",
    "wof:placetype":"venue"
},
  "geometry": {"coordinates":[9.014972,45.701027],"type":"Point"}
}