{
  "type": "Feature",
  "properties": {
    "iso:country":"IT",
    "sg:address":"41015 Nonantola",
    "sg:city":"Bagazzano",
    "sg:orig_category":"Macchine Ed Impianti Per Edilizia E Lavori Pubblici",
    "sg:phone":"+39 059 546400",
    "sg:postcode":"41015",
    "sg:province":"Modena",
    "wof:name":"Carpanelli & C. Snc",
    "wof:placetype":"venue"
},
  "geometry": {"coordinates":[11.009823,44.662472],"type":"Point"}
}