{
  "type": "Feature",
  "properties": {
    "addr:full":"11, Via Camicie Rosse 20090 Opera Opera Milano 20090",
    "addr:postcode":"20090;20090",
    "addr:street":"Via Camicie Rosse",
    "iso:country":"IT",
    "sg:address":"11, Via Camicie Rosse 20090 Opera",
    "sg:city":"Opera",
    "sg:classifiers":[
        {
            "category":"Shopping",
            "type":"Retail Goods"
        }
    ],
    "sg:phone":"+39 02 5760 1845",
    "sg:postcode":"20090",
    "sg:province":"Milano",
    "sg:tags":[
        "finished",
        "-",
        "metallic"
    ],
    "wof:name":"Eurovalve (s.r.l.)",
    "wof:placetype":"venue"
},
  "geometry": {"coordinates":[9.2078857422,45.373085022],"type":"Point"}
}