{
  "type": "Feature",
  "properties": {
    "iso:country":"IT",
    "sg:address":"07047 Thiesi",
    "sg:city":"Thiesi",
    "sg:orig_category":"Pubblica Amministrazione",
    "sg:phone":"+39 079 886261",
    "sg:postcode":"07047",
    "sg:province":"Sassari",
    "wof:name":"Ispettorato Ripartimentale Foreste",
    "wof:placetype":"venue"
},
  "geometry": {"coordinates":[8.7204809189,40.5253982544],"type":"Point"}
}