{
  "type": "Feature",
  "properties": {
    "addr:full":"35010 Cadoneghe Cadoneghe Padova 35010",
    "addr:postcode":"35010;35010",
    "iso:country":"IT",
    "sg:address":"35010 Cadoneghe",
    "sg:city":"Cadoneghe",
    "sg:orig_category":"Manufacturers: Prefabbricati",
    "sg:phone":"+39 049 887 6015",
    "sg:postcode":"35010",
    "sg:province":"Padova",
    "wof:name":"Legno Plac Elementi Per Mobili S.r.l.",
    "wof:placetype":"venue"
},
  "geometry": {"coordinates":[11.889205,45.456459],"type":"Point"}
}