{
  "type": "Feature",
  "properties": {
    "iso:country":"IT",
    "sg:address":"90142 Palermo",
    "sg:city":"Palermo",
    "sg:orig_category":"Abbigliamento Esterno, Maglierie E Pelliccerie. Forniture Per Il Settore Dello Spettacolo",
    "sg:phone":"+39 091 545934",
    "sg:postcode":"90142",
    "sg:province":"Palermo",
    "wof:name":"Pipi Antonino",
    "wof:placetype":"venue"
},
  "geometry": {"coordinates":[13.359752,38.138493],"type":"Point"}
}