{
  "type": "Feature",
  "properties": {
    "addr:full":"25031 Capriolo Capriolo Brescia 25031",
    "addr:postcode":"25031;25031",
    "iso:country":"IT",
    "sg:address":"25031 Capriolo",
    "sg:city":"Capriolo",
    "sg:orig_category":"Forniture Per Abbigliamento E Pelletterie",
    "sg:phone":"+39 030 736 4971",
    "sg:postcode":"25031",
    "sg:province":"Brescia",
    "wof:name":"F.a.r. Di Agosti & C.",
    "wof:placetype":"venue"
},
  "geometry": {"coordinates":[10.212141037,45.5469970703],"type":"Point"}
}