{
  "type": "Feature",
  "properties": {
    "iso:country":"IT",
    "sg:address":"Via C. Colombo 44; Piacenza",
    "sg:classifiers":[
        {
            "category":"Banks & Credit Unions",
            "subcategory":"Bank",
            "type":"Services"
        }
    ],
    "sg:phone":"+39 0523 592510",
    "wof:name":"Banca Di Roma",
    "wof:placetype":"venue"
},
  "geometry": {"coordinates":[9.708658,45.045654],"type":"Point"}
}