{
  "type": "Feature",
  "properties": {
    "iso:country":"IT",
    "sg:address":"26, Via Borgo Tocchet 31010 Godega Di Sant'urbano",
    "sg:classifiers":[
        {
            "category":"Shopping",
            "type":"Retail Goods"
        }
    ],
    "sg:phone":"+39 39043838506",
    "sg:postcode":"31010",
    "sg:province":"Treviso",
    "sg:tags":[
        "finished",
        "-",
        "metallic"
    ],
    "wof:name":"S.c.m. Di Biasin Renato & C. S.n.c.",
    "wof:placetype":"venue"
},
  "geometry": {"coordinates":[12.3829145432,45.9296913147],"type":"Point"}
}