{
  "type": "Feature",
  "properties": {
    "addr:full":"20121 Milano Milano Milano 20121",
    "addr:postcode":"20121;20121",
    "iso:country":"IT",
    "sg:address":"20121 Milano",
    "sg:city":"Milano",
    "sg:orig_category":"Imprese Edili",
    "sg:phone":"+39 02 760671",
    "sg:postcode":"20121",
    "sg:province":"Milano",
    "sg:website":"http://www.marte.com/crea",
    "wof:name":"Crea Impresa Generale Di Costruzioni Spa",
    "wof:placetype":"venue"
},
  "geometry": {"coordinates":[9.198718,45.468189],"type":"Point"}
}