{
  "type": "Feature",
  "properties": {
    "iso:country":"IT",
    "sg:address":"9, Via Palazzina 47010 Galeata",
    "sg:city":"Galeata",
    "sg:classifiers":[
        {
            "category":"Farming",
            "subcategory":"Livestock Farm",
            "type":"Manufacturing & Wholesale Goods"
        }
    ],
    "sg:phone":"+39 0543 981764",
    "sg:postcode":"47010",
    "sg:province":"Forl\u00ec-Cesena",
    "sg:tags":[
        "agriculture"
    ],
    "wof:name":"Cooperativa Lavoratori Agricolo - Forestali Forlivese",
    "wof:placetype":"venue"
},
  "geometry": {"coordinates":[11.910235,43.996498],"type":"Point"}
}