{
  "type": "Feature",
  "properties": {
    "iso:country":"IT",
    "sg:address":"40069 Zola Predosa",
    "sg:city":"Zola",
    "sg:orig_category":"Detergenti Industriali",
    "sg:phone":"+39 051 752332",
    "sg:postcode":"40069",
    "sg:province":"Bologna",
    "wof:name":"Synt Srl",
    "wof:placetype":"venue"
},
  "geometry": {"coordinates":[11.244562,44.496849],"type":"Point"}
}