{
  "type": "Feature",
  "properties": {
    "addr:full":"13, Via U. Foscolo 20020 Vanzaghello Vanzaghello Milano 20020",
    "addr:postcode":"20020;20020",
    "addr:street":"Via U. Foscolo",
    "iso:country":"IT",
    "sg:address":"13, Via U. Foscolo 20020 Vanzaghello",
    "sg:city":"Vanzaghello",
    "sg:classifiers":[
        {
            "category":"Shopping",
            "subcategory":"Computers & Home Electronics",
            "type":"Retail Goods"
        }
    ],
    "sg:phone":"+39 0331 658066",
    "sg:postcode":"20020",
    "sg:province":"Milano",
    "sg:tags":[
        "electronic",
        "electrical",
        "equipment"
    ],
    "wof:name":"Brusatori S.p.a.",
    "wof:placetype":"venue"
},
  "geometry": {"coordinates":[9.188141,45.463688],"type":"Point"}
}