{
  "type": "Feature",
  "properties": {
    "iso:country":"IT",
    "sg:address":"40017 San Giovanni In Persiceto",
    "sg:city":"San Giovanni in Persiceto",
    "sg:orig_category":"Servizi Ausiliari Di Analisi, Controllo E Ricerca. Acqua, Luce, Gas E Societa' Di Esercizio Pubblico",
    "sg:phone":"+39 051 822108",
    "sg:postcode":"40017",
    "sg:province":"Bologna",
    "wof:name":"Corpo Guardie Ecologiche Giurate Volontarie",
    "wof:placetype":"venue"
},
  "geometry": {"coordinates":[11.209474,44.6632],"type":"Point"}
}