{
  "type": "Feature",
  "properties": {
    "addr:full":"3, Via Toniolo Giuseppe 95041 Caltagirone Caltagirone Catania 95041",
    "addr:postcode":"95041;95041",
    "addr:street":"Via Toniolo Giuseppe",
    "iso:country":"IT",
    "sg:address":"3, Via Toniolo Giuseppe 95041 Caltagirone",
    "sg:city":"Caltagirone",
    "sg:classifiers":[
        {
            "category":"Banks & Credit Unions",
            "subcategory":"Financial Services",
            "type":"Services"
        }
    ],
    "sg:phone":"+39 39093331240",
    "sg:postcode":"95041",
    "sg:province":"Catania",
    "sg:tags":[
        "banking",
        "finance",
        "insurance"
    ],
    "wof:name":"Assicurazioni Reale Mutua Ag.dr.messina Salvatore",
    "wof:placetype":"venue"
},
  "geometry": {"coordinates":[14.511271,37.238541],"type":"Point"}
}