{
  "type": "Feature",
  "properties": {
    "iso:country":"IT",
    "sg:address":"8, Via Ponte Nuovo 36034 Malo",
    "sg:city":"Malo",
    "sg:classifiers":[
        {
            "category":"Farming",
            "subcategory":"Livestock Farm",
            "type":"Manufacturing & Wholesale Goods"
        }
    ],
    "sg:phone":"+39 0445 602702",
    "sg:postcode":"36034",
    "sg:province":"Vicenza",
    "sg:tags":[
        "agriculture"
    ],
    "wof:name":"Coriele Luigi & Severino (s.n.c.)",
    "wof:placetype":"venue"
},
  "geometry": {"coordinates":[11.417742,45.653496],"type":"Point"}
}