{
  "type": "Feature",
  "properties": {
    "iso:country":"IT",
    "sg:address":"20040 Cornate D'adda",
    "sg:classifiers":[
        {
            "category":"Train Station",
            "subcategory":"Light Rail",
            "type":"Transportation"
        }
    ],
    "sg:phone":"+39 039 692345",
    "sg:postcode":"20040",
    "sg:province":"Milano",
    "sg:tags":[
        "plating",
        "treatments",
        "metals",
        "heat",
        "electroforming",
        "surface"
    ],
    "wof:name":"La Nuova Galvanica Srl",
    "wof:placetype":"venue"
},
  "geometry": {"coordinates":[9.4623632431,45.6499137878],"type":"Point"}
}