{
  "type": "Feature",
  "properties": {
    "addr:full":"46, Str. Poggio Dei Pini 09012 Capoterra Capoterra Cagliari 09012",
    "addr:postcode":"09012;09012",
    "addr:street":"Str. Poggio Dei Pini",
    "iso:country":"IT",
    "sg:address":"46, Str. Poggio Dei Pini 09012 Capoterra",
    "sg:city":"Capoterra",
    "sg:classifiers":[
        {
            "category":"Manufacturing",
            "subcategory":"Metals",
            "type":"Manufacturing & Wholesale Goods"
        }
    ],
    "sg:phone":"+39 39070725732",
    "sg:postcode":"09012",
    "sg:province":"Cagliari",
    "sg:tags":[
        "metallurgy",
        "metalworking"
    ],
    "sg:website":"http://www.samet.it",
    "wof:name":"Sa.met",
    "wof:placetype":"venue"
},
  "geometry": {"coordinates":[9.1092281342,39.2154579163],"type":"Point"}
}