{
  "type": "Feature",
  "properties": {
    "addr:full":"Via Elorina 131b 96100 Siracusa Siracusa Siracusa 96100",
    "addr:housenumber":"131b",
    "addr:postcode":"96100;96100",
    "addr:street":"Via Elorina",
    "iso:country":"IT",
    "sg:address":"Via Elorina 131b 96100 Siracusa",
    "sg:city":"Siracusa",
    "sg:classifiers":[
        {
            "category":"Food & Beverages",
            "subcategory":"Fruits & Vegetables",
            "type":"Retail Goods"
        }
    ],
    "sg:phone":"+39 0931 722376",
    "sg:postcode":"96100",
    "sg:province":"Siracusa",
    "wof:name":"Azienda Agricola Archimede",
    "wof:placetype":"venue"
},
  "geometry": {"coordinates":[15.2390146255,37.0028038025],"type":"Point"}
}