{
  "type": "Feature",
  "properties": {
    "addr:full":"12, Via Po 00198 Roma Roma Roma 00198",
    "addr:postcode":"00198;00198",
    "addr:street":"Via Po",
    "iso:country":"IT",
    "sg:address":"12, Via Po 00198 Roma",
    "sg:city":"Roma",
    "sg:classifiers":[
        {
            "category":"Manufacturing",
            "subcategory":"Printing",
            "type":"Manufacturing & Wholesale Goods"
        }
    ],
    "sg:phone":"+39 390 684 781",
    "sg:postcode":"00198",
    "sg:province":"Roma",
    "sg:tags":[
        "publishing"
    ],
    "wof:name":"Giornale L'espresso",
    "wof:placetype":"venue"
},
  "geometry": {"coordinates":[12.2782058716,42.1454734802],"type":"Point"}
}