{
  "type": "Feature",
  "properties": {
    "iso:country":"IT",
    "sg:address":"80131 Napoli",
    "sg:city":"Napoli",
    "sg:classifiers":[
        {
            "category":"Shopping",
            "subcategory":"Crafts & Fabrics",
            "type":"Retail Goods"
        }
    ],
    "sg:phone":"+39 081 545 6056",
    "sg:postcode":"80131",
    "sg:province":"Napoli",
    "sg:tags":[
        "art",
        "gifts",
        "finished",
        "products",
        "printed",
        "crafts",
        "artistic"
    ],
    "wof:name":"Maresol Sas",
    "wof:placetype":"venue"
},
  "geometry": {"coordinates":[14.2184553146,40.8646240234],"type":"Point"}
}