{
  "type": "Feature",
  "properties": {
    "iso:country":"IT",
    "sg:address":"32 Via Libeccio, 09126 Cagliari",
    "sg:city":"Cagliari",
    "sg:classifiers":[
        {
            "category":"Banks & Credit Unions",
            "subcategory":"Financial Services",
            "type":"Services"
        }
    ],
    "sg:phone":"+39 39070373232",
    "sg:postcode":"09126",
    "sg:province":"Cagliari",
    "sg:tags":[
        "banking",
        "finance",
        "insurance"
    ],
    "wof:name":"Nuova Sicurvis Srl",
    "wof:placetype":"venue"
},
  "geometry": {"coordinates":[9.1463088989,39.2020835876],"type":"Point"}
}