{
  "type": "Feature",
  "properties": {
    "addr:full":"43, Via Pantiera 31057 Silea Silea Treviso 31057",
    "addr:postcode":"31057;31057",
    "addr:street":"Via Pantiera",
    "iso:country":"IT",
    "sg:address":"43, Via Pantiera 31057 Silea",
    "sg:city":"Silea",
    "sg:classifiers":[
        {
            "category":"Farming",
            "subcategory":"Livestock Farm",
            "type":"Manufacturing & Wholesale Goods"
        }
    ],
    "sg:phone":"+39 0422 683003",
    "sg:postcode":"31057",
    "sg:province":"Treviso",
    "sg:tags":[
        "agriculture"
    ],
    "wof:name":"Bellio Fratelli (s.r.l.)",
    "wof:placetype":"venue"
},
  "geometry": {"coordinates":[12.389608,45.628082],"type":"Point"}
}