{
  "type": "Feature",
  "properties": {
    "addr:full":"37124 Verona Verona Verona 37124",
    "addr:postcode":"37124;37124",
    "iso:country":"IT",
    "sg:address":"37124 Verona",
    "sg:city":"Verona",
    "sg:orig_category":"Medici. Assicurazioni E Servizi Assicurativi. Avvocati, Notai E Servizi Legali. Professionisti - Studi E Servizi Ed Associazioni Di Interesse Aziendale",
    "sg:phone":"+39 045 834 2721",
    "sg:postcode":"37124",
    "sg:province":"Verona",
    "wof:name":"Zuppichini Franco",
    "wof:placetype":"venue"
},
  "geometry": {"coordinates":[10.9800243378,45.4594688416],"type":"Point"}
}