{
  "type": "Feature",
  "properties": {
    "iso:country":"IT",
    "sg:address":"40128 Bologna",
    "sg:city":"Bologna",
    "sg:orig_category":"Antifurto",
    "sg:phone":"+39 051 250408",
    "sg:postcode":"40128",
    "sg:province":"Bologna",
    "wof:name":"Teleoffice Srl",
    "wof:placetype":"venue"
},
  "geometry": {"coordinates":[11.354772,44.505596],"type":"Point"}
}