{
  "type": "Feature",
  "properties": {
    "iso:country":"IT",
    "sg:address":"50141 Firenze",
    "sg:city":"Firenze",
    "sg:orig_category":"Macchine, Strumenti Ed Apparecchi Per Attivita' Industriali",
    "sg:phone":"+39 055 451085",
    "sg:postcode":"50141",
    "sg:province":"Firenze",
    "sg:website":"http://www.falconinstruments.it",
    "wof:name":"Falcon Instruments Srl",
    "wof:placetype":"venue"
},
  "geometry": {"coordinates":[11.243877,43.818378],"type":"Point"}
}