{
  "type": "Feature",
  "properties": {
    "iso:country":"IT",
    "sg:address":"12030 Cavallermaggiore",
    "sg:city":"Cavallermaggiore",
    "sg:classifiers":[
        {
            "category":"Communications",
            "subcategory":"Film & Video Production",
            "type":"Services"
        }
    ],
    "sg:phone":"+39 0172 382660",
    "sg:postcode":"12030",
    "sg:province":"Cuneo",
    "sg:tags":[
        "cracker",
        "e",
        "biscotti"
    ],
    "wof:name":"Campiello Srl",
    "wof:placetype":"venue"
},
  "geometry": {"coordinates":[7.691669,44.708824],"type":"Point"}
}