{
  "type": "Feature",
  "properties": {
    "iso:country":"IT",
    "sg:address":"Via Belvedere 20 21020 Galliate Lombardo",
    "sg:city":"Galliate Lombardo",
    "sg:classifiers":[
        {
            "category":"Manufacturing",
            "subcategory":"Tools & Machinery",
            "type":"Manufacturing & Wholesale Goods"
        }
    ],
    "sg:phone":"+39 0332 949091",
    "sg:postcode":"21020",
    "sg:province":"Varese",
    "sg:tags":[
        "extrusion"
    ],
    "sg:website":"www.lampdief.com",
    "wof:name":"Lamp Srl",
    "wof:placetype":"venue"
},
  "geometry": {"coordinates":[8.774658,45.781567],"type":"Point"}
}