{
  "type": "Feature",
  "properties": {
    "iso:country":"IT",
    "sg:address":"12, Via Roveglia 14030 Montemagno",
    "sg:city":"Montemagno",
    "sg:classifiers":[
        {
            "category":"Shopping",
            "subcategory":"Crafts & Fabrics",
            "type":"Retail Goods"
        }
    ],
    "sg:phone":"+39 0141 653901",
    "sg:postcode":"14030",
    "sg:province":"Asti",
    "wof:name":"Conf S.r.l.",
    "wof:placetype":"venue"
},
  "geometry": {"coordinates":[8.3230953217,44.9770126343],"type":"Point"}
}