{
  "type": "Feature",
  "properties": {
    "addr:full":"84070 Silvi Marina Salerno 84070",
    "addr:postcode":"84070;84070",
    "iso:country":"IT",
    "sg:address":"84070 Silvi Marina",
    "sg:orig_category":"Impiantistica E Prodotti Tecnologici Per Edilizia. Elettrotecnica Industriale, Prodotti E Apparecchiature. Elettrotecnica Professionale E Di Consumo",
    "sg:phone":"+39 085 930340",
    "sg:postcode":"84070",
    "sg:province":"Salerno",
    "sg:website":"http://www.pac.it",
    "wof:name":"Pac Elettromeccanica Di Pacchione Claudio",
    "wof:placetype":"venue"
},
  "geometry": {"coordinates":[14.765912,40.677956],"type":"Point"}
}