{
  "type": "Feature",
  "properties": {
    "addr:full":"37121 Verona Verona Verona 37121",
    "addr:postcode":"37121;37121",
    "iso:country":"IT",
    "sg:address":"37121 Verona",
    "sg:city":"Verona",
    "sg:orig_category":"Arredo Cucina Ed Elettrodomestici. Elettrodomestici. Apparecchi, Attrezzature E Forniture Per Centri Estetici",
    "sg:phone":"+39 045 800 4635",
    "sg:postcode":"37121",
    "sg:province":"Verona",
    "wof:name":"Casa Del Rasoio Marini R.",
    "wof:placetype":"venue"
},
  "geometry": {"coordinates":[10.996305,45.44241],"type":"Point"}
}