{
  "type": "Feature",
  "properties": {
    "iso:country":"IT",
    "sg:address":"16/18, Via Del Lavoro 41018 San Cesario Sul Panaro",
    "sg:city":"San Cesario sul Panaro",
    "sg:classifiers":[
        {
            "category":"Autos & Motor Vehicles",
            "subcategory":"Automobile Sales",
            "type":"Retail Goods"
        }
    ],
    "sg:phone":"+39 39059926190",
    "sg:postcode":"41018",
    "sg:province":"Modena",
    "sg:tags":[
        "equipment",
        "transport"
    ],
    "wof:name":"Santunione (s.r.l.)",
    "wof:placetype":"venue"
},
  "geometry": {"coordinates":[11.026747,44.594646],"type":"Point"}
}