{
  "type": "Feature",
  "properties": {
    "iso:country":"IT",
    "sg:address":"20123 Milano",
    "sg:city":"Milano",
    "sg:orig_category":"Prodotti Chimici Di Base. Forniture Per Attivita' Industriali",
    "sg:phone":"+39 02 4800 6577",
    "sg:postcode":"20123",
    "sg:province":"Milano",
    "wof:name":"La Robbia Srl",
    "wof:placetype":"venue"
},
  "geometry": {"coordinates":[9.1711521149,45.4645080566],"type":"Point"}
}