{
  "type": "Feature",
  "properties": {
    "addr:full":"21, Viale Caduti Della Polveriera 10051 Avigliana Avigliana Torino 10051",
    "addr:housenumber":"21",
    "addr:postcode":"10051;10051",
    "addr:street":"Viale Caduti Della Polveriera",
    "iso:country":"IT",
    "sg:address":"21, Viale Caduti Della Polveriera 10051 Avigliana",
    "sg:city":"Avigliana",
    "sg:classifiers":[
        {
            "category":"Professional",
            "subcategory":"Engineering",
            "type":"Services"
        }
    ],
    "sg:phone":"+39 011 936 9488",
    "sg:postcode":"10051",
    "sg:province":"Torino",
    "sg:tags":[
        "machine",
        "-",
        "mechanical"
    ],
    "wof:name":"Miv Insulating Systems Srl",
    "wof:placetype":"venue"
},
  "geometry": {"coordinates":[7.378547,45.079781],"type":"Point"}
}