{
  "type": "Feature",
  "properties": {
    "iso:country":"IT",
    "sg:address":"20142 Milano",
    "sg:city":"Milano",
    "sg:orig_category":"Servizi Ausiliari Di Certificati, Riproduzioni, Disegni E Foto",
    "sg:phone":"+39 02 8954 6105",
    "sg:postcode":"20142",
    "sg:province":"Milano",
    "wof:name":"Laref Srl",
    "wof:placetype":"venue"
},
  "geometry": {"coordinates":[9.171592,45.441902],"type":"Point"}
}