{
  "type": "Feature",
  "properties": {
    "iso:country":"IT",
    "sg:address":"16121 Genova",
    "sg:city":"Genova",
    "sg:orig_category":"Gioielleria, Oreficeria E Argenteria. Shopping",
    "sg:phone":"+39 010 589070",
    "sg:postcode":"16121",
    "sg:province":"Genova",
    "wof:name":"Thals",
    "wof:placetype":"venue"
},
  "geometry": {"coordinates":[8.936098,44.405987],"type":"Point"}
}