{
  "type": "Feature",
  "properties": {
    "addr:full":"35010 Cadoneghe Cadoneghe Padova 35010",
    "addr:postcode":"35010;35010",
    "iso:country":"IT",
    "sg:address":"35010 Cadoneghe",
    "sg:city":"Cadoneghe",
    "sg:classifiers":[
        {
            "category":"Manufacturing",
            "subcategory":"Chemicals & Compounds",
            "type":"Manufacturing & Wholesale Goods"
        }
    ],
    "sg:phone":"+39 049 865 5411",
    "sg:postcode":"35010",
    "sg:province":"Padova",
    "sg:tags":[
        "activities",
        "industrial",
        "supply",
        "chemicals",
        "products",
        "basic"
    ],
    "sg:website":"http://www.chimar.com",
    "wof:name":"Chimar Srl",
    "wof:placetype":"venue"
},
  "geometry": {"coordinates":[11.901711,45.470646],"type":"Point"}
}