{
  "type": "Feature",
  "properties": {
    "iso:country":"IT",
    "sg:address":"20159 Milano",
    "sg:city":"Milano",
    "sg:orig_category":"Professionisti - Studi E Servizi Ed Associazioni Di Interesse Aziendale. Associazioni Ed Organismi Di Interesse Pubblico",
    "sg:phone":"+39 02 688 7026",
    "sg:postcode":"20159",
    "sg:province":"Milano",
    "wof:name":"S.i.bio.c.",
    "wof:placetype":"venue"
},
  "geometry": {"coordinates":[9.1858930588,45.495929718],"type":"Point"}
}