{
  "type": "Feature",
  "properties": {
    "iso:country":"IT",
    "sg:address":"41100 Modena",
    "sg:city":"Modena",
    "sg:orig_category":"Arredi Ed Attrezzature Per Uffici",
    "sg:phone":"+39 059 374703",
    "sg:postcode":"41100",
    "sg:province":"Modena",
    "wof:name":"Martinelli Modena Srl",
    "wof:placetype":"venue"
},
  "geometry": {"coordinates":[10.91668,44.638634],"type":"Point"}
}