{
  "type": "Feature",
  "properties": {
    "addr:full":"35122 Padova Padova Padova 35122",
    "addr:postcode":"35122;35122",
    "iso:country":"IT",
    "sg:address":"35122 Padova",
    "sg:city":"Padova",
    "sg:orig_category":"Agenzie Ed Enti Turistici. Consulenze Tecniche, Amministrative E Perizie",
    "sg:phone":"+39 049 875 1877",
    "sg:postcode":"35122",
    "sg:province":"Padova",
    "wof:name":"Ufficio Viaggi Cobianchi",
    "wof:placetype":"venue"
},
  "geometry": {"coordinates":[11.831532,45.344246],"type":"Point"}
}