{
  "type": "Feature",
  "properties": {
    "iso:country":"IT",
    "sg:address":"Viale S Modestino 36; Mercogliano",
    "sg:classifiers":[
        {
            "category":"Banks & Credit Unions",
            "subcategory":"Bank",
            "type":"Services"
        }
    ],
    "sg:phone":"+39 0825 788783",
    "wof:name":"Banca Popolare Dell'irpinia Scarl",
    "wof:placetype":"venue"
},
  "geometry": {"coordinates":[14.744456,40.9226],"type":"Point"}
}