{
  "type": "Feature",
  "properties": {
    "iso:country":"IT",
    "sg:address":"27027 Gropello Cairoli",
    "sg:city":"Gropello Cairoli",
    "sg:orig_category":"Materiali E Componenti Elettrotecnici",
    "sg:phone":"+39 0382 815522",
    "sg:postcode":"27027",
    "sg:province":"Pavia",
    "sg:website":"http://www.sogeac.it",
    "wof:name":"Sogeac Srl",
    "wof:placetype":"venue"
},
  "geometry": {"coordinates":[8.988814,45.180653],"type":"Point"}
}