{
  "type": "Feature",
  "properties": {
    "iso:country":"IT",
    "sg:address":"Via G. Camozzi 124; Bergamo; 24121",
    "sg:city":"Bergamo",
    "sg:classifiers":[
        {
            "category":"Industrial Area",
            "type":"Public Place"
        }
    ],
    "sg:phone":"+39 39035396111",
    "sg:postcode":"24121",
    "sg:province":"Bergamo",
    "sg:tags":[
        "large",
        "private"
    ],
    "sg:website":"www.italcementi-group.com",
    "wof:name":"Italcementi S.p.a.",
    "wof:placetype":"venue"
},
  "geometry": {"coordinates":[9.6746473312,45.6961936951],"type":"Point"}
}