{
  "type": "Feature",
  "properties": {
    "addr:full":"11024 Chatillon Chatillon Aosta 11024",
    "addr:postcode":"11024;11024",
    "iso:country":"IT",
    "sg:address":"11024 Chatillon",
    "sg:city":"Chatillon",
    "sg:orig_category":"Forniture Per Edilizia E Lavori Pubblici",
    "sg:phone":"+39 0166 62159",
    "sg:postcode":"11024",
    "sg:province":"Aosta",
    "wof:name":"Machet Igino",
    "wof:placetype":"venue"
},
  "geometry": {"coordinates":[7.6113219261,45.7531318665],"type":"Point"}
}