{
  "type": "Feature",
  "properties": {
    "iso:country":"IT",
    "sg:address":"84085 Pandola",
    "sg:city":"Pandola",
    "sg:orig_category":"Prodotti Di Base E Forniture Per Industria Alimentare E Bevande. Forniture E Materiali Per Imballaggio E Confezionamento",
    "sg:phone":"+39 089 879512",
    "sg:postcode":"84085",
    "sg:province":"Salerno",
    "wof:name":"Sugher Tap S.r.l.",
    "wof:placetype":"venue"
},
  "geometry": {"coordinates":[14.7597055435,40.794883728],"type":"Point"}
}