{
  "type": "Feature",
  "properties": {
    "iso:country":"IT",
    "sg:address":"4, Via Portogallo 46042 Castel Goffredo",
    "sg:city":"Castel Goffredo",
    "sg:classifiers":[
        {
            "category":"Shopping",
            "subcategory":"Computers & Home Electronics",
            "type":"Retail Goods"
        }
    ],
    "sg:phone":"+39 0376 770869",
    "sg:postcode":"46042",
    "sg:province":"Mantova",
    "sg:tags":[
        "electronic",
        "electrical",
        "equipment"
    ],
    "wof:name":"Proiettori Lampo (s.r.l.)",
    "wof:placetype":"venue"
},
  "geometry": {"coordinates":[10.46556,45.284435],"type":"Point"}
}