{
  "type": "Feature",
  "properties": {
    "iso:country":"IT",
    "sg:address":"87043 Bisignano",
    "sg:city":"Bisignano",
    "sg:orig_category":"Arredo Cucina Ed Elettrodomestici. Elettrodomestici",
    "sg:phone":"+39 0984 918181",
    "sg:postcode":"87043",
    "sg:province":"Cosenza",
    "wof:name":"Formosa Antonello",
    "wof:placetype":"venue"
},
  "geometry": {"coordinates":[16.263983,39.512356],"type":"Point"}
}