{
  "type": "Feature",
  "properties": {
    "addr:full":"Via Fiume Abbandonato 235; Ravenna; 48100 Ravenna Ravenna 48100",
    "addr:housenumber":"235",
    "addr:postcode":"48100;48100",
    "addr:street":"Via Fiume Abbandonato",
    "iso:country":"IT",
    "sg:address":"Via Fiume Abbandonato 235; Ravenna; 48100",
    "sg:city":"Ravenna",
    "sg:classifiers":[
        {
            "category":"Banks & Credit Unions",
            "subcategory":"Bank",
            "type":"Services"
        }
    ],
    "sg:phone":"+39 0544 35715",
    "sg:postcode":"48100",
    "sg:province":"Ravenna",
    "wof:name":"Banca Del Monte",
    "wof:placetype":"venue"
},
  "geometry": {"coordinates":[12.188721,44.415482],"type":"Point"}
}