{
  "type": "Feature",
  "properties": {
    "iso:country":"IT",
    "sg:address":"19038 Sarzana",
    "sg:city":"Sarzana",
    "sg:orig_category":"Abbigliamento Esterno, Maglierie E Pelliccerie. Shopping",
    "sg:phone":"+39 0187 620144",
    "sg:postcode":"19038",
    "sg:province":"La Spezia",
    "wof:name":"Gerardo",
    "wof:placetype":"venue"
},
  "geometry": {"coordinates":[9.962835,44.104794],"type":"Point"}
}