{
  "type": "Feature",
  "properties": {
    "addr:full":"Centro Marco Polo; Sora",
    "iso:country":"IT",
    "sg:address":"Centro Marco Polo; Sora",
    "sg:classifiers":[
        {
            "category":"Banks & Credit Unions",
            "subcategory":"Bank",
            "type":"Services"
        }
    ],
    "sg:phone":"+39 0776 814741",
    "wof:name":"Banca Del Fucino Spa",
    "wof:placetype":"venue"
},
  "geometry": {"coordinates":[13.614745,41.719055],"type":"Point"}
}