{
  "type": "Feature",
  "properties": {
    "addr:full":"15, Via Verri Pietro 20090 Trezzano Sul Naviglio Trezzano sul Naviglio Milano 20090",
    "addr:postcode":"20090;20090",
    "addr:street":"Via Verri Pietro",
    "iso:country":"IT",
    "sg:address":"15, Via Verri Pietro 20090 Trezzano Sul Naviglio",
    "sg:city":"Trezzano sul Naviglio",
    "sg:classifiers":[
        {
            "category":"Autos & Motor Vehicles",
            "subcategory":"Automobile Sales",
            "type":"Retail Goods"
        }
    ],
    "sg:phone":"+39 02 4840 3771",
    "sg:postcode":"20090",
    "sg:province":"Milano",
    "sg:tags":[
        "motor-cars"
    ],
    "wof:name":"Autosystem Climatronic S.r.l.",
    "wof:placetype":"venue"
},
  "geometry": {"coordinates":[9.0490531921,45.4279975891],"type":"Point"}
}