{
  "type": "Feature",
  "properties": {
    "addr:full":"25, Corso Cirie' 10152 Torino Torino Torino 10152",
    "addr:postcode":"10152;10152",
    "addr:street":"Corso Cirie '",
    "iso:country":"IT",
    "sg:address":"25, Corso Cirie' 10152 Torino",
    "sg:city":"Torino",
    "sg:classifiers":[
        {
            "category":"Professional",
            "subcategory":"Engineering",
            "type":"Services"
        }
    ],
    "sg:phone":"+39 011 436 3073",
    "sg:postcode":"10152",
    "sg:province":"Torino",
    "sg:tags":[
        "machine",
        "-",
        "mechanical"
    ],
    "wof:name":"S.w.f. S.r.l.",
    "wof:placetype":"venue"
},
  "geometry": {"coordinates":[7.677411,45.083454],"type":"Point"}
}