{
  "type": "Feature",
  "properties": {
    "addr:full":"Via Fiume, 17/19 20017 Rho Rho Milano 20017",
    "addr:housenumber":"17 / 19",
    "addr:postcode":"20017;20017",
    "addr:street":"Via Fiume",
    "iso:country":"IT",
    "sg:address":"Via Fiume, 17/19 20017 Rho",
    "sg:city":"Rho",
    "sg:classifiers":[
        {
            "category":"Home & Garden",
            "subcategory":"Hardware",
            "type":"Retail Goods"
        }
    ],
    "sg:phone":"+39 02 931 4156",
    "sg:postcode":"20017",
    "sg:province":"Milano",
    "sg:tags":[
        "small",
        "ironware",
        "item"
    ],
    "wof:name":"Magi Spa",
    "wof:placetype":"venue"
},
  "geometry": {"coordinates":[9.048476,45.523808],"type":"Point"}
}