{
  "type": "Feature",
  "properties": {
    "iso:country":"IT",
    "sg:address":"46044 Goito",
    "sg:city":"Goito",
    "sg:orig_category":"Servizi Di Magazzinaggio E Movimentazione",
    "sg:phone":"+39 0376 60111",
    "sg:postcode":"46044",
    "sg:province":"Mantova",
    "wof:name":"Veronesi Bruno",
    "wof:placetype":"venue"
},
  "geometry": {"coordinates":[10.791306,45.158642],"type":"Point"}
}