{
  "type": "Feature",
  "properties": {
    "iso:country":"IT",
    "sg:address":"36016 Thiene",
    "sg:city":"Thiene",
    "sg:orig_category":"Telecomunicazioni E Telefonia, Impianti, Apparecchi E Servizi",
    "sg:phone":"+39 0445 800700",
    "sg:postcode":"36016",
    "sg:province":"Vicenza",
    "wof:name":"Reti S.r.l.",
    "wof:placetype":"venue"
},
  "geometry": {"coordinates":[11.466891,45.690178],"type":"Point"}
}