{
  "type": "Feature",
  "properties": {
    "iso:country":"IT",
    "sg:address":"41100 Lesignana",
    "sg:city":"Lesignana",
    "sg:orig_category":"Macchine Ed Impianti Per Edilizia E Lavori Pubblici",
    "sg:phone":"+39 059 849296",
    "sg:postcode":"41100",
    "sg:province":"Modena",
    "wof:name":"Sti.mar. (s.a.s.)",
    "wof:placetype":"venue"
},
  "geometry": {"coordinates":[10.882243,44.682503],"type":"Point"}
}