{
  "type": "Feature",
  "properties": {
    "iso:country":"IT",
    "sg:address":"00041 Albano Laziale",
    "sg:city":"Albano Laziale",
    "sg:orig_category":"Macchine, Impianti Ed Attrezzature Per Industria Alimentare E Bevande. Elettrodomestici. Macchine E Impianti Per Attivita' Commerciali Ed Artigianali",
    "sg:phone":"+39 06 932 0699",
    "sg:postcode":"00041",
    "sg:province":"Roma",
    "wof:name":"Facciponte Giovanna",
    "wof:placetype":"venue"
},
  "geometry": {"coordinates":[12.627362,41.691238],"type":"Point"}
}