{
  "type": "Feature",
  "properties": {
    "iso:country":"IT",
    "sg:address":"27, Viale Monza 20127 Milano",
    "sg:city":"Milano",
    "sg:classifiers":[
        {
            "category":"Wholesale",
            "subcategory":"Medical Equipment & Supplies",
            "type":"Manufacturing & Wholesale Goods"
        }
    ],
    "sg:phone":"+39 39022847030",
    "sg:postcode":"20127",
    "sg:province":"Milano",
    "sg:tags":[
        "-",
        "health",
        "instrument"
    ],
    "wof:name":"Di Bernardo S.r.l.",
    "wof:placetype":"venue"
},
  "geometry": {"coordinates":[9.21748,45.489044],"type":"Point"}
}