{
  "type": "Feature",
  "properties": {
    "iso:country":"IT",
    "sg:address":"V. Galileo Galilei 46020 Motteggiana",
    "sg:city":"Motteggiana",
    "sg:classifiers":[
        {
            "category":"Professional",
            "subcategory":"Engineering",
            "type":"Services"
        }
    ],
    "sg:phone":"+39 0376 510065",
    "sg:postcode":"46020",
    "sg:province":"Mantova",
    "sg:tags":[
        "machine",
        "-",
        "mechanical"
    ],
    "sg:website":"http://www.alberti-international.it",
    "wof:name":"Alberti International",
    "wof:placetype":"venue"
},
  "geometry": {"coordinates":[10.768932,45.029858],"type":"Point"}
}