{
  "type": "Feature",
  "properties": {
    "iso:country":"IT",
    "sg:address":"13, Via Provinciale 24024 Gandino",
    "sg:city":"Gandino",
    "sg:orig_category":"Miscellaneous Products",
    "sg:phone":"+39 39035732549",
    "sg:postcode":"24024",
    "sg:province":"Bergamo",
    "wof:name":"Confezioni Paulato E Radici Di Graziella Radici E",
    "wof:placetype":"venue"
},
  "geometry": {"coordinates":[9.8926115036,45.8053131104],"type":"Point"}
}