{
  "type": "Feature",
  "properties": {
    "iso:country":"IT",
    "sg:address":"46010 Marcaria",
    "sg:city":"Campitello",
    "sg:orig_category":"Arredo Camera Letto E Complementi",
    "sg:phone":"+39 0376 96464",
    "sg:postcode":"46010",
    "sg:province":"Mantova",
    "wof:name":"Casanova Ercolina Casanova",
    "wof:placetype":"venue"
},
  "geometry": {"coordinates":[10.605981,45.090488],"type":"Point"}
}