{
  "type": "Feature",
  "properties": {
    "iso:country":"IT",
    "sg:address":"20122 Milano",
    "sg:city":"Milano",
    "sg:orig_category":"Servizi Editoriali. Servizi Ausiliari Per Il Trasporto",
    "sg:phone":"+39 02 874524",
    "sg:postcode":"20122",
    "sg:province":"Milano",
    "wof:name":"Associazione Distributori Nazionali - A.d.n.",
    "wof:placetype":"venue"
},
  "geometry": {"coordinates":[9.186895,45.456997],"type":"Point"}
}