{
  "type": "Feature",
  "properties": {
    "iso:country":"IT",
    "sg:address":"Via Moscuso 81049 Mignano Monte Lungo",
    "sg:city":"Mignano Monte Lungo",
    "sg:classifiers":[
        {
            "category":"Utilities",
            "subcategory":"Electric",
            "type":"Services"
        }
    ],
    "sg:phone":"+39 0823 903797",
    "sg:postcode":"81049",
    "sg:province":"Caserta",
    "sg:tags":[
        "component",
        "electronic"
    ],
    "wof:name":"Megarad S.r.l.",
    "wof:placetype":"venue"
},
  "geometry": {"coordinates":[13.956614,41.414173],"type":"Point"}
}