{
  "type": "Feature",
  "properties": {
    "addr:full":"Via Brasil 33028 Tolmezzo Tolmezzo Udine 33028",
    "addr:postcode":"33028;33028",
    "addr:street":"Via Brasil",
    "iso:country":"IT",
    "sg:address":"Via Brasil 33028 Tolmezzo",
    "sg:city":"Tolmezzo",
    "sg:classifiers":[
        {
            "category":"Professional",
            "subcategory":"Engineering",
            "type":"Services"
        }
    ],
    "sg:phone":"+39 39043340049",
    "sg:postcode":"33028",
    "sg:province":"Udine",
    "sg:tags":[
        "machine",
        "-",
        "mechanical"
    ],
    "wof:name":"Nassimbeni Stefano & C. (s.n.c.)",
    "wof:placetype":"venue"
},
  "geometry": {"coordinates":[13.033138,46.389572],"type":"Point"}
}