{
  "type": "Feature",
  "properties": {
    "addr:full":"21, Via Marzeno 48013 Brisighella Brisighella Ravenna 48013",
    "addr:postcode":"48013;48013",
    "addr:street":"Via Marzeno",
    "iso:country":"IT",
    "sg:address":"21, Via Marzeno 48013 Brisighella",
    "sg:city":"Brisighella",
    "sg:classifiers":[
        {
            "category":"Manufacturing",
            "subcategory":"Rubber & Plastics",
            "type":"Manufacturing & Wholesale Goods"
        }
    ],
    "sg:phone":"+39 39054640002",
    "sg:postcode":"48013",
    "sg:province":"Ravenna",
    "wof:name":"Molino Naldoni S.r.l.",
    "wof:placetype":"venue"
},
  "geometry": {"coordinates":[11.8602514267,44.2270202637],"type":"Point"}
}