{
  "type": "Feature",
  "properties": {
    "addr:full":"44015 Portomaggiore Portomaggiore Ferrara 44015",
    "addr:postcode":"44015;44015",
    "iso:country":"IT",
    "sg:address":"44015 Portomaggiore",
    "sg:city":"Portomaggiore",
    "sg:orig_category":"Minuterie Metalliche E Ferramenta",
    "sg:phone":"+39 0532 811178",
    "sg:postcode":"44015",
    "sg:province":"Ferrara",
    "sg:website":"http://www.vernicizamagni.com",
    "wof:name":"Vernici Zamagni Snc",
    "wof:placetype":"venue"
},
  "geometry": {"coordinates":[11.8109016418,44.7051429749],"type":"Point"}
}