{
  "type": "Feature",
  "properties": {
    "iso:country":"IT",
    "sg:address":"43029 Traversetolo",
    "sg:city":"Traversetolo",
    "sg:orig_category":"Tessuti Arredamento, Tende E Tappeti. Forniture Per Edilizia E Lavori Pubblici",
    "sg:phone":"+39 0521 842660",
    "sg:postcode":"43029",
    "sg:province":"Parma",
    "wof:name":"Arredamenti Tiberini Snc",
    "wof:placetype":"venue"
},
  "geometry": {"coordinates":[10.358364,44.620434],"type":"Point"}
}