{
  "type": "Feature",
  "properties": {
    "addr:full":"25026 Pontevico Pontevico Brescia 25026",
    "addr:postcode":"25026;25026",
    "iso:country":"IT",
    "sg:address":"25026 Pontevico",
    "sg:city":"Pontevico",
    "sg:orig_category":"Macchine E Forniture Per Ecologia E Smaltimento Rifiuti",
    "sg:phone":"+39 030 993 0597",
    "sg:postcode":"25026",
    "sg:province":"Brescia",
    "wof:name":"Scaglia Luciano",
    "wof:placetype":"venue"
},
  "geometry": {"coordinates":[10.121168,45.247398],"type":"Point"}
}