{
  "type": "Feature",
  "properties": {
    "iso:country":"IT",
    "sg:address":"24, Via Etnea 95131 Catania",
    "sg:city":"Catania",
    "sg:classifiers":[
        {
            "category":"Shopping",
            "subcategory":"Clothing, Apparel, & Fashions",
            "type":"Retail Goods"
        }
    ],
    "sg:phone":"+39 39095325224",
    "sg:postcode":"95131",
    "sg:province":"Catania",
    "sg:tags":[
        "clothes"
    ],
    "wof:name":"Azzurro Market",
    "wof:placetype":"venue"
},
  "geometry": {"coordinates":[15.083743,37.517929],"type":"Point"}
}