{
  "type": "Feature",
  "properties": {
    "iso:country":"IT",
    "sg:address":"167, Via Trani 70051 Barletta",
    "sg:city":"Barletta",
    "sg:classifiers":[
        {
            "category":"Personal",
            "subcategory":"Shoe Repair & Shine",
            "type":"Services"
        }
    ],
    "sg:phone":"+39 0883 349104",
    "sg:postcode":"70051",
    "sg:province":"Bari",
    "sg:tags":[
        "leather"
    ],
    "wof:name":"Pezzol (s.r.l.)",
    "wof:placetype":"venue"
},
  "geometry": {"coordinates":[16.316193,41.306427],"type":"Point"}
}