{
  "type": "Feature",
  "properties": {
    "iso:country":"IT",
    "sg:address":"25063 Gardone Val Trompia",
    "sg:city":"Gardone Val Trompia",
    "sg:orig_category":"Acciaierie E Fonderie",
    "sg:phone":"+39 030 831437",
    "sg:postcode":"25063",
    "sg:province":"Brescia",
    "sg:website":"http://www.metrocast.it",
    "wof:name":"Metrocast Italiana Spa",
    "wof:placetype":"venue"
},
  "geometry": {"coordinates":[10.168765,45.688896],"type":"Point"}
}