{
  "type": "Feature",
  "properties": {
    "addr:full":"20144 Milano Milano Milano 20144",
    "addr:postcode":"20144;20144",
    "iso:country":"IT",
    "sg:address":"20144 Milano",
    "sg:city":"Milano",
    "sg:orig_category":"Arte Ed Artigianato Artistico",
    "sg:phone":"+39 02 832 3098",
    "sg:postcode":"20144",
    "sg:province":"Milano",
    "wof:name":"D.a.l.f. (s.r.l.)",
    "wof:placetype":"venue"
},
  "geometry": {"coordinates":[9.170551,45.453796],"type":"Point"}
}