{
  "type": "Feature",
  "properties": {
    "iso:country":"IT",
    "sg:address":"Via Gentile Da Fabriano; Ancona; 60100",
    "sg:classifiers":[
        {
            "category":"Travel",
            "subcategory":"Travel Agent",
            "type":"Entertainment"
        }
    ],
    "sg:website":"le-marche.com",
    "wof:name":"Marche Region",
    "wof:placetype":"venue"
},
  "geometry": {"coordinates":[13.508392,43.610165],"type":"Point"}
}