{
  "type": "Feature",
  "properties": {
    "iso:country":"IT",
    "sg:address":"25064 Gussago",
    "sg:city":"Gussago",
    "sg:orig_category":"Chiese Ed Associazioni Religiose",
    "sg:phone":"+39 030 318797",
    "sg:postcode":"25064",
    "sg:province":"Brescia",
    "wof:name":"Christ Peace And Love",
    "wof:placetype":"venue"
},
  "geometry": {"coordinates":[10.155327,45.559109],"type":"Point"}
}