{
  "type": "Feature",
  "properties": {
    "addr:full":"Via Tolomei 61 35010 Loreggia Loreggia Padova 35010",
    "addr:housenumber":"61",
    "addr:postcode":"35010;35010",
    "addr:street":"Via Tolomei",
    "iso:country":"IT",
    "sg:address":"Via Tolomei 61 35010 Loreggia",
    "sg:city":"Loreggia",
    "sg:classifiers":[
        {
            "category":"Landmark",
            "subcategory":"Square",
            "type":"Public Place"
        }
    ],
    "sg:phone":"+39 049 930 0312",
    "sg:postcode":"35010",
    "sg:province":"Padova",
    "sg:tags":[
        "brick",
        "plane"
    ],
    "sg:website":"www.santanselmo.com",
    "wof:name":"Sant'anselmo Fornace Spa",
    "wof:placetype":"venue"
},
  "geometry": {"coordinates":[11.9566488266,45.5879669189],"type":"Point"}
}