{
  "type": "Feature",
  "properties": {
    "iso:country":"IT",
    "sg:address":"95131 Catania",
    "sg:city":"Catania",
    "sg:orig_category":"Alberghi E Strutture Extra Alberghiere. Ospedali E Servizi Sanitari",
    "sg:phone":"+39 095 447358",
    "sg:postcode":"95131",
    "sg:province":"Catania",
    "wof:name":"Associazione Monteverdi",
    "wof:placetype":"venue"
},
  "geometry": {"coordinates":[15.095753,37.508911],"type":"Point"}
}