{
  "type": "Feature",
  "properties": {
    "iso:country":"IT",
    "sg:address":"Contrada Porticello 98055 Lipari",
    "sg:city":"Lipari",
    "sg:classifiers":[
        {
            "category":"Marine",
            "type":"Transportation"
        }
    ],
    "sg:phone":"+39 090 982 1033",
    "sg:postcode":"98055",
    "sg:province":"Messina",
    "sg:tags":[
        "transport",
        "sea"
    ],
    "wof:name":"Nolmar (s.r.l.)",
    "wof:placetype":"venue"
},
  "geometry": {"coordinates":[15.555523,38.192333],"type":"Point"}
}