{
  "type": "Feature",
  "properties": {
    "addr:full":"Via Virgilio 204 55049 Viareggio Viareggio Lucca 55049",
    "addr:housenumber":"204",
    "addr:postcode":"55049;55049",
    "addr:street":"Via Virgilio",
    "iso:country":"IT",
    "sg:address":"Via Virgilio 204 55049 Viareggio",
    "sg:city":"Viareggio",
    "sg:orig_category":"Joinery Supraregional",
    "sg:phone":"+39 0584 383900",
    "sg:postcode":"55049",
    "sg:province":"Lucca",
    "wof:name":"R.a.p. Arredamenti Impresa Individuale",
    "wof:placetype":"venue"
},
  "geometry": {"coordinates":[10.244987,43.861458],"type":"Point"}
}