{
  "type": "Feature",
  "properties": {
    "iso:country":"IT",
    "sg:address":"01032 Caprarola",
    "sg:city":"Caprarola",
    "sg:orig_category":"Prodotti Alimentari",
    "sg:phone":"+39 0761 646591",
    "sg:postcode":"01032",
    "sg:province":"Viterbo",
    "wof:name":"Assofrutti - Associazione Produttori Frutta A Guscio",
    "wof:placetype":"venue"
},
  "geometry": {"coordinates":[12.1975831985,42.3383750916],"type":"Point"}
}