{
  "type": "Feature",
  "properties": {
    "addr:full":"73010 Lequile Lequile Lecce 73010",
    "addr:postcode":"73010;73010",
    "iso:country":"IT",
    "sg:address":"73010 Lequile",
    "sg:city":"Lequile",
    "sg:orig_category":"Analisi Cliniche - Centri E Laboratori",
    "sg:phone":"+39 0832 633584",
    "sg:postcode":"73010",
    "sg:province":"Lecce",
    "wof:name":"Artini M. Adele",
    "wof:placetype":"venue"
},
  "geometry": {"coordinates":[18.148027,40.305443],"type":"Point"}
}