{
  "type": "Feature",
  "properties": {
    "addr:full":"00144 Roma Roma Roma 00144",
    "addr:postcode":"00144;00144",
    "iso:country":"IT",
    "sg:address":"00144 Roma",
    "sg:city":"Roma",
    "sg:orig_category":"Servizi Al Turismo. Servizi Ausiliari Dei Mezzi Di Trasporto. Servizi Ausiliari Per Il Trasporto. Acqua, Luce, Gas E Societa' Di Esercizio Pubblico",
    "sg:phone":"+39 06 5439 3502",
    "sg:postcode":"00144",
    "sg:province":"Roma",
    "wof:name":"Registro Aeronautico Italiano",
    "wof:placetype":"venue"
},
  "geometry": {"coordinates":[12.463721,41.838215],"type":"Point"}
}