{
  "type": "Feature",
  "properties": {
    "iso:country":"IT",
    "sg:address":"50131 Firenze",
    "sg:city":"Firenze",
    "sg:orig_category":"Analisi Cliniche - Centri E Laboratori",
    "sg:phone":"+39 055 588294",
    "sg:postcode":"50131",
    "sg:province":"Firenze",
    "wof:name":"Diagnostica Pacinotti Srl",
    "wof:placetype":"venue"
},
  "geometry": {"coordinates":[11.190739,43.834579],"type":"Point"}
}