{
  "type": "Feature",
  "properties": {
    "addr:full":"Via Dell' Industria 36070 Castelgomberto Castelgomberto Vicenza 36070",
    "addr:postcode":"36070;36070",
    "addr:street":"Via Dell ' Industria",
    "iso:country":"IT",
    "sg:address":"Via Dell' Industria 36070 Castelgomberto",
    "sg:city":"Castelgomberto",
    "sg:classifiers":[
        {
            "category":"Wholesale",
            "subcategory":"Drugs",
            "type":"Manufacturing & Wholesale Goods"
        }
    ],
    "sg:phone":"+39 0445 941166",
    "sg:postcode":"36070",
    "sg:province":"Vicenza",
    "sg:tags":[
        "chemical",
        "pharmaceutical"
    ],
    "wof:name":"Unichem S.r.l.",
    "wof:placetype":"venue"
},
  "geometry": {"coordinates":[11.379334,45.556015],"type":"Point"}
}