{
  "type": "Feature",
  "properties": {
    "addr:full":"10122 Torino Torino Torino 10122",
    "addr:housenumber":"10122",
    "addr:postcode":"10122",
    "iso:country":"IT",
    "sg:address":"10122 Torino",
    "sg:city":"Torino",
    "sg:orig_category":"Centri Di Estetica E Cosmesi E Servizi",
    "sg:phone":"+39 011 436 1391",
    "sg:postcode":"10122",
    "sg:province":"Torino",
    "wof:name":"A.s.e.m. Di Astolfi Luciana",
    "wof:placetype":"venue"
},
  "geometry": {"coordinates":[7.410153,45.447395],"type":"Point"}
}