{
  "type": "Feature",
  "properties": {
    "iso:country":"IT",
    "sg:address":"10090 Romano Canavese",
    "sg:city":"Romano Canavese",
    "sg:orig_category":"Servizi Ausiliari Di Certificati, Riproduzioni, Disegni E Foto",
    "sg:phone":"+39 0125 637770",
    "sg:postcode":"10090",
    "sg:province":"Torino",
    "wof:name":"Formica Art - Studio",
    "wof:placetype":"venue"
},
  "geometry": {"coordinates":[7.706978,45.151657],"type":"Point"}
}