{
  "type": "Feature",
  "properties": {
    "iso:country":"IT",
    "sg:address":"11/13, Via Pordenone 31045 Motta Di Livenza",
    "sg:city":"Motta di Livenza",
    "sg:classifiers":[
        {
            "category":"Manufacturing",
            "subcategory":"Lumber",
            "type":"Manufacturing & Wholesale Goods"
        }
    ],
    "sg:phone":"+39 0422 861415",
    "sg:postcode":"31045",
    "sg:province":"Treviso",
    "sg:tags":[
        "wood"
    ],
    "wof:name":"Trio Legno S.r.l.",
    "wof:placetype":"venue"
},
  "geometry": {"coordinates":[12.611326,45.798164],"type":"Point"}
}