{
  "type": "Feature",
  "properties": {
    "iso:country":"IT",
    "sg:address":"24123 Bergamo",
    "sg:city":"Bergamo",
    "sg:orig_category":"Arredamenti E Mobili Professionali. Apparecchi, Attrezzature E Forniture Per Centri Estetici. Arredi Ed Attrezzature Per Attivita' Commerciali Ed Artigianali",
    "sg:phone":"+39 035 417 5376",
    "sg:postcode":"24123",
    "sg:province":"Bergamo",
    "sg:website":"http://www.freesun.it",
    "wof:name":"Free Sun Sas Di Goisis Giulio & C.",
    "wof:placetype":"venue"
},
  "geometry": {"coordinates":[9.696491,45.713978],"type":"Point"}
}