{
  "type": "Feature",
  "properties": {
    "addr:full":"Via Caduti Lavoro 26020 Casalmorano Casalmorano Cremona 26020",
    "addr:postcode":"26020;26020",
    "addr:street":"Via Caduti Lavoro",
    "iso:country":"IT",
    "sg:address":"Via Caduti Lavoro 26020 Casalmorano",
    "sg:city":"Casalmorano",
    "sg:classifiers":[
        {
            "category":"Shopping",
            "type":"Retail Goods"
        }
    ],
    "sg:phone":"+39 39037474176",
    "sg:postcode":"26020",
    "sg:province":"Cremona",
    "sg:tags":[
        "finished",
        "-",
        "metallic"
    ],
    "wof:name":"Carpam (s.n.c.)",
    "wof:placetype":"venue"
},
  "geometry": {"coordinates":[9.8957710266,45.2930908203],"type":"Point"}
}