{
  "type": "Feature",
  "properties": {
    "iso:country":"IT",
    "sg:address":"714, V. Bologna 44100 Ferrara",
    "sg:city":"Ferrara",
    "sg:classifiers":[
        {
            "category":"Farming",
            "subcategory":"Livestock Farm",
            "type":"Manufacturing & Wholesale Goods"
        }
    ],
    "sg:phone":"+39 0532 785511",
    "sg:postcode":"44100",
    "sg:province":"Ferrara",
    "sg:tags":[
        "agriculture"
    ],
    "sg:website":"http://www.paginegialle.it/unacoa",
    "wof:name":"Unacoa Spa - Salvi",
    "wof:placetype":"venue"
},
  "geometry": {"coordinates":[11.575353,44.782646],"type":"Point"}
}