{
  "type": "Feature",
  "properties": {
    "iso:country":"IT",
    "sg:address":"34170 Gorizia",
    "sg:city":"Gorizia",
    "sg:orig_category":"Elettronica Professionale E Di Consumo. Automazione E Macchine Per Ufficio",
    "sg:phone":"+39 0481 33330",
    "sg:postcode":"34170",
    "sg:province":"Gorizia",
    "wof:name":"Cronomarket (s.n.c.)",
    "wof:placetype":"venue"
},
  "geometry": {"coordinates":[13.616554,45.940708],"type":"Point"}
}