{
  "type": "Feature",
  "properties": {
    "addr:full":"48014 Castel Bolognese Castel Bolognese Ravenna 48014",
    "addr:postcode":"48014;48014",
    "iso:country":"IT",
    "sg:address":"48014 Castel Bolognese",
    "sg:city":"Castel Bolognese",
    "sg:orig_category":"Condizionamento Aria Impianti - Installazione E Manutenzione",
    "sg:phone":"+39 0546 54880",
    "sg:postcode":"48014",
    "sg:province":"Ravenna",
    "sg:website":"http://www.montimpianti.it",
    "wof:name":"Monti Impianti Snc",
    "wof:placetype":"venue"
},
  "geometry": {"coordinates":[11.786566,44.324245],"type":"Point"}
}