{
  "type": "Feature",
  "properties": {
    "addr:full":"100/106, Via Dante Alighieri 24058 Romano Di Lombardia Romano di Lombardia Bergamo 24058",
    "addr:housenumber":"100 / 106",
    "addr:postcode":"24058;24058",
    "addr:street":"Via Dante Alighieri",
    "iso:country":"IT",
    "sg:address":"100/106, Via Dante Alighieri 24058 Romano Di Lombardia",
    "sg:city":"Romano di Lombardia",
    "sg:classifiers":[
        {
            "category":"Shopping",
            "subcategory":"Computers & Home Electronics",
            "type":"Retail Goods"
        }
    ],
    "sg:phone":"+39 390 363 9991",
    "sg:postcode":"24058",
    "sg:province":"Bergamo",
    "sg:tags":[
        "electronic",
        "electrical",
        "equipment"
    ],
    "wof:name":"Exide Italia S.p.a.",
    "wof:placetype":"venue"
},
  "geometry": {"coordinates":[9.746255,45.52771],"type":"Point"}
}