{
  "type": "Feature",
  "properties": {
    "iso:country":"IT",
    "sg:address":"8, Corso Europa Unita 24030 Valbrembo",
    "sg:city":"Valbrembo",
    "sg:classifiers":[
        {
            "category":"Real Estate",
            "subcategory":"Surveying",
            "type":"Services"
        }
    ],
    "sg:phone":"+39 39035527663",
    "sg:postcode":"24030",
    "sg:province":"Bergamo",
    "sg:tags":[
        "equipment",
        "material",
        "good",
        "-",
        "handling"
    ],
    "wof:name":"P.l.m. Impianti S.p.a.",
    "wof:placetype":"venue"
},
  "geometry": {"coordinates":[9.6011333466,45.7162742615],"type":"Point"}
}