{
  "type": "Feature",
  "properties": {
    "iso:country":"IT",
    "sg:address":"19122 La Spezia",
    "sg:classifiers":[
        {
            "category":"Government",
            "subcategory":"Office",
            "type":"Public Place"
        }
    ],
    "sg:phone":"+39 0187 78502",
    "sg:province":"SP",
    "sg:tags":[
        "administration"
    ],
    "wof:name":"Marina Militare - Maritele La Spezia",
    "wof:placetype":"venue"
},
  "geometry": {"coordinates":[9.8097038269,44.1118812561],"type":"Point"}
}