{
  "type": "Feature",
  "properties": {
    "iso:country":"IT",
    "sg:address":"20017 Rho",
    "sg:city":"Rho",
    "sg:orig_category":"Elettrodomestici. Elettronica Professionale E Di Consumo. Arredi Ed Attrezzature Per Attivita' Commerciali Ed Artigianali. Macchine, Strumenti Ed Apparecchi Per Attivita' Industriali",
    "sg:phone":"+39 02 9390 3941",
    "sg:postcode":"20017",
    "sg:province":"Milano",
    "sg:website":"http://www.milanobilance.it",
    "wof:name":"Milano Bilance Srl",
    "wof:placetype":"venue"
},
  "geometry": {"coordinates":[9.084982,45.525616],"type":"Point"}
}