{
  "type": "Feature",
  "properties": {
    "addr:full":"Via Liguria 29017 Fiorenzuola D'arda Piacenza 29017",
    "addr:postcode":"29017;29017",
    "addr:street":"Via Liguria",
    "iso:country":"IT",
    "sg:address":"Via Liguria 29017 Fiorenzuola D'arda",
    "sg:classifiers":[
        {
            "category":"Manufacturing",
            "subcategory":"Rubber & Plastics",
            "type":"Manufacturing & Wholesale Goods"
        }
    ],
    "sg:phone":"+39 0523 983729",
    "sg:postcode":"29017",
    "sg:province":"Piacenza",
    "wof:name":"Lagoplast (s.r.l.)",
    "wof:placetype":"venue"
},
  "geometry": {"coordinates":[9.9039049149,44.9347839355],"type":"Point"}
}