{
  "type": "Feature",
  "properties": {
    "iso:country":"IT",
    "sg:address":"36075 Montecchio Maggiore",
    "sg:city":"Montecchio Maggiore",
    "sg:orig_category":"Arredamenti E Mobili Professionali. Impianti, Attrezzature E Forniture Sanitarie Ed Ospedaliere",
    "sg:phone":"+39 0444 696690",
    "sg:postcode":"36075",
    "sg:province":"Vicenza",
    "wof:name":"Giraldo Rosino E Figlio Snc Di Giraldo Rosino &. C.",
    "wof:placetype":"venue"
},
  "geometry": {"coordinates":[11.405453,45.513783],"type":"Point"}
}