{
  "type": "Feature",
  "properties": {
    "iso:country":"IT",
    "sg:address":"Viale Iv Novembre 60019 Senigallia",
    "sg:city":"Senigallia",
    "sg:classifiers":[
        {
            "category":"Professional",
            "subcategory":"Business Services",
            "type":"Services"
        }
    ],
    "sg:phone":"+39 390 716 5343",
    "sg:postcode":"60019",
    "sg:province":"Ancona",
    "sg:tags":[
        "advice"
    ],
    "wof:name":"Associazione Albergatori Alberghi E Turismo Senigallia Soc.coop. A.r.l.",
    "wof:placetype":"venue"
},
  "geometry": {"coordinates":[13.518757,43.615856],"type":"Point"}
}