{
  "type": "Feature",
  "properties": {
    "addr:full":"20, Via A.stoppani 22032 Albese Con Cassano Albese con Cassano Como 22032",
    "addr:postcode":"22032;22032",
    "addr:street":"Via A.Stoppani",
    "iso:country":"IT",
    "sg:address":"20, Via A.stoppani 22032 Albese Con Cassano",
    "sg:city":"Albese con Cassano",
    "sg:classifiers":[
        {
            "category":"Shopping",
            "type":"Retail Goods"
        }
    ],
    "sg:phone":"+39 39031421035",
    "sg:postcode":"22032",
    "sg:province":"Como",
    "sg:tags":[
        "finished",
        "-",
        "metallic"
    ],
    "wof:name":"Cosmos (s.r.l.)",
    "wof:placetype":"venue"
},
  "geometry": {"coordinates":[9.1739721298,45.7928695679],"type":"Point"}
}