{
  "type": "Feature",
  "properties": {
    "iso:country":"IT",
    "sg:address":"00141 Roma",
    "sg:city":"Roma",
    "sg:classifiers":[
        {
            "category":"Restaurant",
            "type":"Food & Drink"
        }
    ],
    "sg:phone":"+39 06 860 4333",
    "sg:postcode":"00141",
    "sg:province":"Roma",
    "sg:tags":[
        "auxiliary",
        "entertainment",
        "premises",
        "related",
        "catering",
        "similar",
        "public",
        "restaurants"
    ],
    "wof:name":"Grazia Deledda Snc",
    "wof:placetype":"venue"
},
  "geometry": {"coordinates":[12.52744,41.933907],"type":"Point"}
}