{
  "type": "Feature",
  "properties": {
    "addr:full":"21052 Busto Arsizio Busto Arsizio Varese 21052",
    "addr:postcode":"21052;21052",
    "iso:country":"IT",
    "sg:address":"21052 Busto Arsizio",
    "sg:city":"Busto Arsizio",
    "sg:orig_category":"Sport And Leisure, Services. Tourism, Services. Motor Vehicles, Auxiliary Services. Transport, Auxiliary Services",
    "sg:phone":"+39 0331 322190",
    "sg:postcode":"21052",
    "sg:province":"Varese",
    "wof:name":"Covitur",
    "wof:placetype":"venue"
},
  "geometry": {"coordinates":[8.840526,45.609806],"type":"Point"}
}