{
  "type": "Feature",
  "properties": {
    "iso:country":"IT",
    "sg:address":"25124 Brescia",
    "sg:city":"Brescia",
    "sg:orig_category":"Telefonia - Impianti Ed Apparecchi",
    "sg:phone":"+39 030 353 3335",
    "sg:postcode":"25124",
    "sg:province":"Brescia",
    "sg:website":"http://www.netcomsystems.it",
    "wof:name":"Netcom Network",
    "wof:placetype":"venue"
},
  "geometry": {"coordinates":[10.214762,45.526661],"type":"Point"}
}