{
  "type": "Feature",
  "properties": {
    "addr:full":"55010 Zone Lucca 55010",
    "addr:housenumber":"55010",
    "addr:postcode":"55010",
    "addr:street":"Zone Lucca",
    "iso:country":"IT",
    "sg:address":"55010 Zone",
    "sg:orig_category":"Macchine, Impianti E Forniture Per Industria Grafica, Cartaria E Cartotecnica",
    "sg:phone":"+39 0583 920550",
    "sg:postcode":"55010",
    "sg:province":"Lucca",
    "wof:name":"Mondial Converting Machinery Srl",
    "wof:placetype":"venue"
},
  "geometry": {"coordinates":[10.57267,43.849514],"type":"Point"}
}