{
  "type": "Feature",
  "properties": {
    "iso:country":"IT",
    "sg:address":"20157 Milano",
    "sg:city":"Milano",
    "sg:orig_category":"Trattamenti Termici E Superficiali Metalli, Galvanotecnica",
    "sg:phone":"+39 02 355 1855",
    "sg:postcode":"20157",
    "sg:province":"Milano",
    "wof:name":"Nuova Nicrom",
    "wof:placetype":"venue"
},
  "geometry": {"coordinates":[9.157147,45.466782],"type":"Point"}
}