{
  "type": "Feature",
  "properties": {
    "iso:country":"IT",
    "sg:address":"80147 Napoli",
    "sg:city":"Napoli",
    "sg:orig_category":"Servizi Culturali E Per Lo Spettacolo. Servizi Per Lo Sport E Il Tempo Libero. Servizi Per Aziende, Manifestazioni E Supporto Agli Scambi Commerciali",
    "sg:phone":"+39 081 577 0321",
    "sg:postcode":"80147",
    "sg:province":"Napoli",
    "wof:name":"Animania",
    "wof:placetype":"venue"
},
  "geometry": {"coordinates":[14.338573,40.863091],"type":"Point"}
}