{
  "type": "Feature",
  "properties": {
    "iso:country":"IT",
    "sg:address":"21100 Varese",
    "sg:city":"Varese",
    "sg:orig_category":"Tessuti Arredamento, Tende E Tappeti",
    "sg:phone":"+39 0332 831323",
    "sg:postcode":"21100",
    "sg:province":"Varese",
    "wof:name":"Parola Elena",
    "wof:placetype":"venue"
},
  "geometry": {"coordinates":[8.814065,45.90757],"type":"Point"}
}