{
  "type": "Feature",
  "properties": {
    "iso:country":"IT",
    "sg:address":"12020 Villar San Costanzo",
    "sg:city":"Villar",
    "sg:classifiers":[
        {
            "category":"Communications",
            "subcategory":"Film & Video Production",
            "type":"Services"
        }
    ],
    "sg:phone":"+39 0171 902186",
    "sg:postcode":"12020",
    "sg:province":"Cuneo",
    "sg:tags":[
        "cracker",
        "e",
        "biscotti"
    ],
    "wof:name":"Forneria Artigiana Cavanna",
    "wof:placetype":"venue"
},
  "geometry": {"coordinates":[7.39597,44.475163],"type":"Point"}
}