{
  "type": "Feature",
  "properties": {
    "addr:full":"10127 Torino Torino Torino 10127",
    "addr:postcode":"10127;10127",
    "iso:country":"IT",
    "sg:address":"10127 Torino",
    "sg:city":"Torino",
    "sg:orig_category":"Apparecchiature E Sistemi Per Imballaggio E Confezionamento",
    "sg:phone":"+39 011 667 7523",
    "sg:postcode":"10127",
    "sg:province":"Torino",
    "wof:name":"Professione Lavoro S.c.a.r.l.",
    "wof:placetype":"venue"
},
  "geometry": {"coordinates":[7.654738,45.021843],"type":"Point"}
}