{
  "type": "Feature",
  "properties": {
    "iso:country":"IT",
    "sg:address":"06081 Assisi",
    "sg:city":"Assisi",
    "sg:orig_category":"Alberghi E Strutture Extra Alberghiere",
    "sg:phone":"+39 075 815 5124",
    "sg:postcode":"06081",
    "sg:province":"Perugia",
    "wof:name":"Residenza D'epoca 'san Crispino'",
    "wof:placetype":"venue"
},
  "geometry": {"coordinates":[12.644587,43.069424],"type":"Point"}
}