{
  "type": "Feature",
  "properties": {
    "addr:full":"80125 Napoli Napoli Napoli 80125",
    "addr:housenumber":"80125",
    "addr:postcode":"80125",
    "iso:country":"IT",
    "sg:address":"80125 Napoli",
    "sg:city":"Napoli",
    "sg:orig_category":"Tessuti Arredamento, Tende E Tappeti. Forniture Per Edilizia E Lavori Pubblici",
    "sg:phone":"+39 081 593 9901",
    "sg:postcode":"80125",
    "sg:province":"Napoli",
    "wof:name":"Linoleum System 2000",
    "wof:placetype":"venue"
},
  "geometry": {"coordinates":[14.131795,40.868317],"type":"Point"}
}