{
  "type": "Feature",
  "properties": {
    "iso:country":"IT",
    "sg:address":"261/b, V. S. Giovanni Battista 60011 Arcevia",
    "sg:city":"Arcevia",
    "sg:classifiers":[
        {
            "category":"Personal",
            "subcategory":"Shoe Repair & Shine",
            "type":"Services"
        }
    ],
    "sg:phone":"+39 0731 984011",
    "sg:postcode":"60011",
    "sg:province":"Ancona",
    "sg:tags":[
        "leather"
    ],
    "sg:website":"http://www.paginegialle.it/contifulvio",
    "wof:name":"Stringhificio Fa-las Di Conti Fulvio",
    "wof:placetype":"venue"
},
  "geometry": {"coordinates":[12.834788,43.552856],"type":"Point"}
}