{
  "type": "Feature",
  "properties": {
    "iso:country":"IT",
    "sg:address":"42100 Reggio Emilia",
    "sg:orig_category":"Centri Di Estetica E Cosmesi E Servizi",
    "sg:phone":"+39 0522 322122",
    "sg:postcode":"42100",
    "sg:province":"Reggio Nell'Emilia",
    "wof:name":"Centro Capelli Srl",
    "wof:placetype":"venue"
},
  "geometry": {"coordinates":[10.61414,44.680389],"type":"Point"}
}