{
  "type": "Feature",
  "properties": {
    "iso:country":"IT",
    "sg:address":"80131 Napoli",
    "sg:city":"Napoli",
    "sg:orig_category":"Riparazione Dei Mezzi Di Trasporto",
    "sg:phone":"+39 081 743 5782",
    "sg:postcode":"80131",
    "sg:province":"Napoli",
    "sg:website":"http://silverstone.fortunecity.com/mansell/326/",
    "wof:name":"Bruognolo Mariano",
    "wof:placetype":"venue"
},
  "geometry": {"coordinates":[14.237479,40.867504],"type":"Point"}
}