{
  "type": "Feature",
  "properties": {
    "addr:full":"10024 Moncalieri Moncalieri Torino 10024",
    "addr:postcode":"10024;10024",
    "iso:country":"IT",
    "sg:address":"10024 Moncalieri",
    "sg:city":"Moncalieri",
    "sg:orig_category":"Pompe. Ricambi E Componenti Dei Mezzi Di Trasporto",
    "sg:phone":"+39 011 641878",
    "sg:postcode":"10024",
    "sg:province":"Torino",
    "wof:name":"L'elettrodiesel Di Chetto Michele E C. (s.n.c.)",
    "wof:placetype":"venue"
},
  "geometry": {"coordinates":[7.6919484138,44.9967422485],"type":"Point"}
}