{
  "type": "Feature",
  "properties": {
    "iso:country":"IT",
    "sg:address":"73, Via Ala Di Stura 10148 Torino",
    "sg:city":"Torino",
    "sg:classifiers":[
        {
            "category":"Shopping",
            "type":"Retail Goods"
        }
    ],
    "sg:phone":"+39 011 220 2444",
    "sg:postcode":"10148",
    "sg:province":"Torino",
    "sg:tags":[
        "finished",
        "-",
        "metallic"
    ],
    "wof:name":"Mollificio Dellepiane S.r.l.",
    "wof:placetype":"venue"
},
  "geometry": {"coordinates":[7.6849541664,45.1067504883],"type":"Point"}
}