{
  "type": "Feature",
  "properties": {
    "addr:full":"Via Diaz, 12; Rapallo; 16035 Rapallo Genova 16035",
    "addr:housenumber":"12",
    "addr:postcode":"16035;16035",
    "addr:street":"Via Diaz",
    "iso:country":"IT",
    "sg:address":"Via Diaz, 12; Rapallo; 16035",
    "sg:city":"Rapallo",
    "sg:classifiers":[
        {
            "category":"Banks & Credit Unions",
            "subcategory":"Bank",
            "type":"Services"
        }
    ],
    "sg:phone":"+39 0185 273943",
    "sg:postcode":"16035",
    "sg:province":"Genova",
    "wof:name":"Banco Ambrosiano Veneto Spa",
    "wof:placetype":"venue"
},
  "geometry": {"coordinates":[9.228112,44.347557],"type":"Point"}
}