{
  "type": "Feature",
  "properties": {
    "iso:country":"IT",
    "sg:address":"42011 Bagnolo In Piano",
    "sg:orig_category":"Macchine, Impianti Ed Attrezzature Per Agricoltura E Zootecnia. Macchine E Forniture Per Arredamento E Industria Del Legno",
    "sg:phone":"+39 0522 953131",
    "sg:postcode":"42011",
    "sg:province":"Reggio Nell'Emilia",
    "wof:name":"Comer (s.p.a.)",
    "wof:placetype":"venue"
},
  "geometry": {"coordinates":[10.621368,44.678082],"type":"Point"}
}