{
  "type": "Feature",
  "properties": {
    "addr:full":"31040 Trevignano Musano Treviso 31040",
    "addr:postcode":"31040;31040",
    "iso:country":"IT",
    "sg:address":"31040 Trevignano",
    "sg:city":"Musano",
    "sg:orig_category":"Campane",
    "sg:phone":"+39 0423 81771",
    "sg:postcode":"31040",
    "sg:province":"Treviso",
    "wof:name":"B.b. Di Borsato & Bordignon",
    "wof:placetype":"venue"
},
  "geometry": {"coordinates":[12.104692,45.734657],"type":"Point"}
}