{
  "type": "Feature",
  "properties": {
    "addr:full":"60027 Osimo Osimo Ancona 60027",
    "addr:postcode":"60027;60027",
    "iso:country":"IT",
    "sg:address":"60027 Osimo",
    "sg:city":"Osimo",
    "sg:orig_category":"Minuterie Metalliche E Ferramenta",
    "sg:phone":"+39 071 723 2496",
    "sg:postcode":"60027",
    "sg:province":"Ancona",
    "sg:website":"http://www.pirani.it",
    "wof:name":"Pirani Francesco Mollificio",
    "wof:placetype":"venue"
},
  "geometry": {"coordinates":[13.4733953476,43.4781227112],"type":"Point"}
}