{
  "type": "Feature",
  "properties": {
    "addr:full":"00192 Roma Roma Roma 00192",
    "addr:postcode":"00192;00192",
    "iso:country":"IT",
    "sg:address":"00192 Roma",
    "sg:city":"Roma",
    "sg:orig_category":"Accessori Moda D'abbigliamento",
    "sg:phone":"+39 06 3972 0659",
    "sg:postcode":"00192",
    "sg:province":"Roma",
    "wof:name":"Roots Sas Di Tomassi Paola E C.",
    "wof:placetype":"venue"
},
  "geometry": {"coordinates":[12.4499721527,41.9073867798],"type":"Point"}
}