{
  "type": "Feature",
  "properties": {
    "addr:full":"25062 San Vigilio San Vigilio Brescia 25062",
    "addr:housenumber":"25062",
    "addr:postcode":"25062",
    "addr:street":"San Vigilio San Vigilio Brescia",
    "iso:country":"IT",
    "sg:address":"25062 San Vigilio",
    "sg:city":"San Vigilio",
    "sg:orig_category":"Sport - Articoli E Forniture",
    "sg:phone":"+39 030 275 1449",
    "sg:postcode":"25062",
    "sg:province":"Brescia",
    "wof:name":"Sandro Gatti & C. S.n.c.",
    "wof:placetype":"venue"
},
  "geometry": {"coordinates":[10.200238,45.606518],"type":"Point"}
}