{
  "type": "Feature",
  "properties": {
    "iso:country":"IT",
    "sg:address":"60122 Ancona",
    "sg:city":"Ancona",
    "sg:orig_category":"Arte Ed Artigianato Artistico. Scuole E Servizi Scolastici. Servizi Ausiliari Di Analisi, Controllo E Ricerca",
    "sg:phone":"+39 071 205070",
    "sg:postcode":"60122",
    "sg:province":"Ancona",
    "wof:name":"Accademia Psicobiogena Coordinamento Ricerca E Studi",
    "wof:placetype":"venue"
},
  "geometry": {"coordinates":[13.513769,43.616932],"type":"Point"}
}