{
  "type": "Feature",
  "properties": {
    "iso:country":"IT",
    "sg:address":"30131 Venezia",
    "sg:classifiers":[
        {
            "category":"Building & Trades",
            "subcategory":"Construction",
            "type":"Services"
        }
    ],
    "sg:phone":"+39 041 521 0019",
    "sg:province":"VE",
    "sg:tags":[
        "art",
        "civil",
        "industry",
        "craft",
        "wood",
        "furnishing",
        "works",
        "artistic"
    ],
    "wof:name":"Marina De Grandis Legatrice E Restauratrice",
    "wof:placetype":"venue"
},
  "geometry": {"coordinates":[12.3184947968,45.4382553101],"type":"Point"}
}