{
  "type": "Feature",
  "properties": {
    "addr:full":"15033 Casale Monferrato Casale Monferrato Alessandria 15033",
    "addr:postcode":"15033;15033",
    "iso:country":"IT",
    "sg:address":"15033 Casale Monferrato",
    "sg:city":"Casale Monferrato",
    "sg:orig_category":"Autofficine E Centri Assistenza",
    "sg:phone":"+39 0142 561677",
    "sg:postcode":"15033",
    "sg:province":"Alessandria",
    "wof:name":"Nuova Imca Di Cantarelli E C. Snc",
    "wof:placetype":"venue"
},
  "geometry": {"coordinates":[8.439952,45.148983],"type":"Point"}
}