{
  "type": "Feature",
  "properties": {
    "iso:country":"IT",
    "sg:address":"Via 1 Maggio 51035 Lamporecchio",
    "sg:city":"Lamporecchio",
    "sg:classifiers":[
        {
            "category":"Manufacturing",
            "subcategory":"Metals",
            "type":"Manufacturing & Wholesale Goods"
        }
    ],
    "sg:phone":"+39 39057382678",
    "sg:postcode":"51035",
    "sg:province":"Pistoia",
    "sg:tags":[
        "processing"
    ],
    "wof:name":"Semico S.r.l.",
    "wof:placetype":"venue"
},
  "geometry": {"coordinates":[10.9185237885,43.9321556091],"type":"Point"}
}